Workbook
Name lst_CostCentre: Lists!$A$5:$A$10
Name lst_InvoiceType: Lists!$B$5:$B$14
Name lst_TaxCode: Lists!$C$5:$C$8
Name lst_Status: Lists!$D$5:$D$13
Name lst_YN: Lists!$E$5:$E$7
Name lst_Ariba: Lists!$F$5:$F$10
Name lst_WIPType: Lists!$G$5:$G$10
Name lst_WIPGL: Lists!$H$5:$H$7
Name lst_Team: Lists!$I$5:$I$8
Name set_GSTRate: Lists!$U$8
Name set_QwilrBase: Lists!$U$5
Name set_RMSBase: Lists!$U$6
Name lst_RevGL: Lists!$K$5:$K$39
Name lst_Months: Lists!$N$5:$N$100
Name lst_Jobs: Lists!$P$5:$P$1500
Name lst_JobName: Lists!$Q$5:$Q$1500
Name lst_JobCC: Lists!$R$5:$R$1500

Sheet Read Me
B2: FY27 Revenue Tracker
B4: Corporate Technology Services Pty Ltd - replaces FY27_Revenue_Tracker_v2.xlsm
B6: WHO TYPES WHERE
C7: Finance types on the Finance sheet. Nowhere else. Every invoice line, every month.
C8: Each department types on its own sheet. Nowhere else. One row per job number.
C9: The two meet on Job Number, which is a real Xero tracking category and is checked against the live job list as you type. Nothing has to be kept lined up by hand.
B11: HOW IT FITS TOGETHER
B12: Finance | C12: The invoice register, and the only source of revenue. One row per invoice LINE, coded to one cost centre, exactly as Xero holds it. Filter the Issue column to see everything that needs fixing.
B13: Onsite / Production / Consulting | C13: One row per job. Client, invoice count and revenue come from Finance automatically; the department fills in its own costs, hours and references.
B14: WIP Movements | C14: Manual journals between the P&L and GL 11300 Work in Progress. Anything with a defer start and end on Finance does not belong here - it is handled automatically.
B15: Deferred Revenue | C15: The workings behind the automatic deferrals. Nothing is typed here; it mirrors the Finance lines that carry a defer start and end.
B16: Month-End | C16: The close: revenue by cost centre against Xero, the WIP reconciliation, fifteen data checks and a sign-off box.
B17: WIP Summary | C17: WIP opening / movement / closing for every job, to tie job by job back to the WIP Schedule file.
B18: Lists | C18: Every dropdown. Cost centres, job numbers and revenue GL codes came straight out of your Xero organisation, so they already match.
B20: DEFERRED REVENUE - it releases itself
C21: Put a Defer Start and a Defer End on a Finance line and the revenue spreads evenly across those months instead of landing all in the month you invoiced. Leave both blank for an ordinary one-off invoice.
C22: In the month invoiced: one month is recognised, the rest goes to WIP.
C23: Every month after: one more month is released, automatically.
C24: Worked example - $12,000 invoiced 15 Sep 2025 for Sep 2025 to Aug 2026. September recognises $1,000 and defers $11,000. Each month after releases $1,000. By August 2026 the balance is nil. Nothing is typed each month and no journal is needed.
C25: The Deferred Revenue sheet shows the workings line by line, and Month-End and WIP Summary already include it. One warning: a deferred line must not ALSO have a manual row on WIP Movements or it counts twice - Month-End checks for that.
B27: VIDEO REVENUE
C28: There is no video split column any more, and nothing to keep honest. In Xero a cost centre sits on the invoice LINE, so a job invoiced part production and part video is simply two lines on the Finance sheet - one coded PRODUCTION, one coded VIDEO. The VIDEO figure at month-end is then a plain sum of the lines coded VIDEO, and it ties to the Xero VIDEO cost centre without any adjustment.
C29: The 26 migrated invoices that carried a video amount were split into two lines each on the way across. Ex GST in total is unchanged.
C30: The Production sheet carries a Video Revenue column beside the expenses, and Video % of Revenue next to it. Both read the Finance lines coded VIDEO, so nothing is typed. Job by job they reproduce the old Video Total column to the cent - 38,484.75 in total across 28 jobs.
B32: WHY THIS VERSION IS NOT SLOW, AND WHY IT OPENS
C33: The v2 file was slow because of its macro: every keystroke copied 26 columns by 200 rows into hidden storage, and it was capped at 200 rows per department. There are no macros here at all, and it is a .xlsx, so no macro warning and nothing blocked on SharePoint.
C34: There are also no dynamic array formulas - no VSTACK, FILTER, SORT, UNIQUE or XLOOKUP. Every sheet is a real Excel Table or a plain SUMIFS grid, which means the filter buttons, sorting and PivotTables all work normally, and every formula runs in any version of Excel.
B36: MONTH-END, IN ORDER
C37: 1. Chase the departments until every invoice for the month is on the Finance sheet and Posted to Xero is Y.
C38: 2. Open Month-End and set the month.
C39: 3. Work section 3 first. Every count must be zero. Fix on the Finance sheet, or filter the Issue column there, which lists the same problems row by row.
C40: 4. Section 1: run the Xero P&L for the month by Cost Centre and type the revenue into the yellow column. Each line should read Reconciled.
C41: 5. Section 2: type the WIP Schedule closing balance and the Xero GL 11300 balance.
C42: 6. Breaks in section 2 - open WIP Summary, paste the WIP Schedule balances into column G and the variance column shows which job is out.
C43: 7. Sign off in section 4.
B45: THE WIP SIGN RULE
C46: One signed Amount column does both jobs, because GL 11300 nets accrued and deferred revenue. Positive = revenue recognised this month (work done but not yet invoiced, or a deferral released). Negative = revenue pushed out of this month (invoiced in advance). So revenue recognised = invoiced Ex GST + WIP movement, and the running total of the Amount column is the GL 11300 balance.
B48: LOCKED CELLS, LINKS AND TOTALS
C49: Every sheet is protected with no password. Only the cells you are meant to fill are open; the grey calculated ones are locked so a stray keystroke cannot wipe a formula. To turn it off: Review, Unprotect Sheet. Sorting and filtering still work.
C50: Qwilr quotes and Current RMS numbers are clickable. Paste a full web address and it is used as it stands; type a bare number and it is added to the base address on the Lists sheet. The Qwilr base is already set, and Current RMS on the Production sheet now works exactly the same way - paste the whole Current RMS address into the Current RMS No cell and it links straight away. Only fill in Lists column U row 6 if you would rather type the bare opportunity number.
C51: Each sheet shows its total ex-GST at the top, and it follows the filter - filter to one client or one month and the total follows. Finance shows Ex GST, GST and Inc GST.
C52: The GST rate is no longer buried in the formula. It sits on the Lists sheet, column U row 8, and every GST cell reads it from there.
B54: RULES THAT KEEP IT FAST
C55: Never insert or delete rows above the header row.
C56: Add rows by typing in the next blank row of the table, or press Tab at the end of the last row and the table grows with the formulas.
C57: Paste values only, never whole columns.
C58: Leave calculation on Automatic. Nothing here is volatile - no OFFSET, no INDIRECT, no TODAY in bulk.
C59: Keep it as .xlsx. The moment someone saves it as .xlsm and adds a macro you are back where you started.
B61: WHAT CAME ACROSS FROM v2
C62: Finance: 175 invoice lines from the 149 v2 records, the difference being the 26 video splits now carried as their own line.
C63: Department sheets: one row per job - Onsite 27, Production 58, Consulting 28.
C64: WIP Movements: 126 rows.
C65: Totals tie to the cent: Onsite 512,023.81, Production 460,883.46, Consulting 857,950.27, WIP 17,537.91.
C66: Revenue GL codes were assigned by rule (Onsite 41100, Production 42100, Video 42150, Consulting 42800, Integration 42300). Spot-check them.
C67: The 126 WIP rows were given a Type from the sign of the amount. Confirm before relying on them.
C68: Production keeps its v2 columns. Client Email came across (57 of 58 jobs). Company, Event Grouping, Conf. Call Costs and Transcription Costs are there but empty - v2 showed them on screen and its macro never saved them, so there is nothing to bring. Conf. Call and Transcription now feed Total Expense, which v2 never did.
C69: Job Type is gone - Cost Centres says the same thing and fills itself. Net Total and Discount as % of Net Total are gone for the reason under STILL TO CONFIRM.
B71: STILL TO CONFIRM
C72: Discounts. Checked against Xero: for all 17 August production invoices carrying a discount, the ex-GST total on the Xero invoice equals Ex GST here exactly, and not one matched Ex GST minus the discount. So the discount comes off before the invoice is raised and Ex GST is what reconciles. The old "Net Total" is gone; Discounts Given now sits on the Production sheet at job level with Value Before Discount beside it. ASSUMPTION: it records what was given away off standard rates.
C73: 23 migrated records have no invoice number and 21 have no date - $93,346.99 of revenue that belongs to no month. They are on the Finance sheet with the Issue column filled in. Filter that column and work the list to nothing.
B75: Bigger text, shorter lines, one sentence per line: open the Read Me (Easy Read) tab. Same words, easier on the eye.

Sheet Read Me (Easy Read)
B2: FY27 Revenue Tracker
B3: Corporate Technology Services Pty Ltd - replaces FY27_Revenue_Tracker_v2.xlsm
B5: Who types where
C6: Finance types on the Finance sheet.
C7: Nowhere else.
C8: Every invoice line, every month.
C10: Each department types on its own sheet.
C11: Nowhere else.
C12: One row per job number.
C14: The two meet on Job Number, which is a real Xero tracking category and is checked against the live job list as you type.
C15: Nothing has to be kept lined up by hand.
B18: How it fits together
B19: Finance | C19: The invoice register, and the only source of revenue. One row per invoice line, coded to one cost centre, exactly as Xero holds it. Filter the Issue column to see everything that needs fixing.
B20: Onsite / Production / Consulting | C20: One row per job. Client, invoice count and revenue come from Finance automatically; the department fills in its own costs, hours and references.
B21: WIP Movements | C21: Manual journals between the P&L and GL 11300 Work in Progress. Anything with a defer start and end on Finance does not belong here - it is handled automatically.
B22: Deferred Revenue | C22: The workings behind the automatic deferrals. Nothing is typed here; it mirrors the Finance lines that carry a defer start and end.
B23: Month-End | C23: The close: revenue by cost centre against Xero, the WIP reconciliation, fifteen data checks and a sign-off box.
B24: WIP Summary | C24: WIP opening / movement / closing for every job, to tie job by job back to the WIP Schedule file.
B25: Lists | C25: Every dropdown. Cost centres, job numbers and revenue GL codes came straight out of your Xero organisation, so they already match.
B27: Deferred revenue - it releases itself
C28: Put a Defer Start and a Defer End on a Finance line and the revenue spreads evenly across those months instead of landing all in the month you invoiced.
C29: Leave both blank for an ordinary one-off invoice.
C31: In the month invoiced: one month is recognised, the rest goes to WIP.
C33: Every month after: one more month is released, automatically.
C35: Worked example - $12,000 invoiced 15 Sep 2025 for Sep 2025 to Aug 2026.
C36: September recognises $1,000 and defers $11,000.
C37: Each month after releases $1,000.
C38: By August 2026 the balance is nil.
C39: Nothing is typed each month and no journal is needed.
C41: The Deferred Revenue sheet shows the workings line by line, and Month-End and WIP Summary already include it.
C42: One warning: a deferred line must not also have a manual row on WIP Movements or it counts twice - Month-End checks for that.
B45: Video revenue
C46: There is no video split column any more, and nothing to keep honest.
C47: In Xero a cost centre sits on the invoice line, so a job invoiced part production and part video is simply two lines on the Finance sheet - one coded PRODUCTION, one coded VIDEO.
C48: The VIDEO figure at month-end is then a plain sum of the lines coded VIDEO, and it ties to the Xero VIDEO cost centre without any adjustment.
C50: The 26 migrated invoices that carried a video amount were split into two lines each on the way across.
C51: Ex GST in total is unchanged.
C53: The Production sheet carries a Video Revenue column beside the expenses, and Video % of Revenue next to it.
C54: Both read the Finance lines coded VIDEO, so nothing is typed.
C55: Job by job they reproduce the old Video Total column to the cent - 38,484.75 in total across 28 jobs.
B58: Why this version is not slow, and why it opens
C59: The v2 file was slow because of its macro: every keystroke copied 26 columns by 200 rows into hidden storage, and it was capped at 200 rows per department.
C60: There are no macros here at all, and it is a .xlsx, so no macro warning and nothing blocked on SharePoint.
C62: There are also no dynamic array formulas - no VSTACK, FILTER, SORT, UNIQUE or XLOOKUP.
C63: Every sheet is a real Excel Table or a plain SUMIFS grid, which means the filter buttons, sorting and PivotTables all work normally, and every formula runs in any version of Excel.
B66: Month-end, in order
C67: 1. Chase the departments until every invoice for the month is on the Finance sheet and Posted to Xero is Y.
C69: 2. Open Month-End and set the month.
C71: 3. Work section 3 first.
C72: Every count must be zero.
C73: Fix on the Finance sheet, or filter the Issue column there, which lists the same problems row by row.
C75: 4. Section 1: run the Xero P&L for the month by Cost Centre and type the revenue into the yellow column.
C76: Each line should read Reconciled.
C78: 5. Section 2: type the WIP Schedule closing balance and the Xero GL 11300 balance.
C80: 6. Breaks in section 2 - open WIP Summary, paste the WIP Schedule balances into column G and the variance column shows which job is out.
C82: 7. Sign off in section 4.
B85: The WIP sign rule
C86: One signed Amount column does both jobs, because GL 11300 nets accrued and deferred revenue.
C87: Positive = revenue recognised this month (work done but not yet invoiced, or a deferral released).
C88: Negative = revenue pushed out of this month (invoiced in advance).
C89: So revenue recognised = invoiced Ex GST + WIP movement, and the running total of the Amount column is the GL 11300 balance.
B92: Locked cells, links and totals
C93: Every sheet is protected with no password.
C94: Only the cells you are meant to fill are open; the grey calculated ones are locked so a stray keystroke cannot wipe a formula.
C95: To turn it off: Review, Unprotect Sheet.
C96: Sorting and filtering still work.
C98: Qwilr quotes and Current RMS numbers are clickable.
C99: Paste a full web address and it is used as it stands; type a bare number and it is added to the base address on the Lists sheet.
C100: The Qwilr base is already set, and Current RMS on the Production sheet now works exactly the same way - paste the whole Current RMS address into the Current RMS No cell and it links straight away.
C101: Only fill in Lists column U row 6 if you would rather type the bare opportunity number.
C103: Each sheet shows its total ex-GST at the top, and it follows the filter - filter to one client or one month and the total follows.
C104: Finance shows Ex GST, GST and Inc GST.
C106: The GST rate is no longer buried in the formula.
C107: It sits on the Lists sheet, column U row 8, and every GST cell reads it from there.
B110: Rules that keep it fast
C111: Never insert or delete rows above the header row.
C113: Add rows by typing in the next blank row of the table, or press Tab at the end of the last row and the table grows with the formulas.
C115: Paste values only, never whole columns.
C117: Leave calculation on Automatic.
C118: Nothing here is volatile - no OFFSET, no INDIRECT, no TODAY in bulk.
C120: Keep it as .xlsx.
C121: The moment someone saves it as .xlsm and adds a macro you are back where you started.
B124: What came across from v2
C125: Finance: 175 invoice lines from the 149 v2 records, the difference being the 26 video splits now carried as their own line.
C127: Department sheets: one row per job - Onsite 27, Production 58, Consulting 28.
C129: WIP Movements: 126 rows.
C131: Totals tie to the cent: Onsite 512,023.81, Production 460,883.46, Consulting 857,950.27, WIP 17,537.91.
C133: Revenue GL codes were assigned by rule (Onsite 41100, Production 42100, Video 42150, Consulting 42800, Integration 42300).
C134: Spot-check them.
C136: The 126 WIP rows were given a Type from the sign of the amount.
C137: Confirm before relying on them.
C139: Production keeps its v2 columns.
C140: Client Email came across (57 of 58 jobs).
C141: Company, Event Grouping, Conf.
C142: Call Costs and Transcription Costs are there but empty - v2 showed them on screen and its macro never saved them, so there is nothing to bring.
... C147: Net Total and Discount as % of Net Total are gone for the reason under STILL TO CONFIRM.
B150: Still to confirm
C151: Discounts.
C152: Checked against Xero: for all 17 August production invoices carrying a discount, the ex-GST total on the Xero invoice equals Ex GST here exactly, and not one matched Ex GST minus the discount.
C153: So the discount comes off before the invoice is raised and Ex GST is what reconciles.
...

Sheet Finance
A1: Finance - Invoice Register
A2: One row per invoice line, coded to one cost centre, the same way Xero holds it. Finance types here and nowhere else. A job invoiced part production and part video is two lines. Filter the Issue column to see what needs fixing.
A3: ="Ex GST "&TEXT(SUBTOTAL(109,tbl_Finance[Ex GST]),"$#,##0.00")&" "&"GST "&TEXT(SUBTOTAL(109,tbl_Finance[GST]),"$#,##0.00")&" "&"Inc GST "&TEXT(SUBTOTAL(109,tbl_Finance[Inc GST]),"$#,##0.00")
A4: Date | B4: Month | C4: Xero Invoice No | D4: Client | E4: Job Number | F4: Job in Xero? | G4: Description | H4: Team | I4: Cost Centre | J4: Invoice Type | K4: Tax Code | L4: Ex GST | M4: GST | N4: Inc GST | O4: Revenue GL | P4: Posted to Xero | Q4: To WIP | R4: Defer Start | S4: Defer End | T4: Status | U4: Notes | V4: Issue | W4: Job Name (Xero) | X4: Lines on this Job | Y4: Job Total Ex GST | Z4: Job Invoiced | AA4: Job To Invoice | AB4: Job Quote / Ref | AC4: Open Quote | AD4: Job Expense | AE4: Job Margin | AF4: Job Margin % | AG4: Dept Notes
A5: 46234 | B5: =IF(A5="","",EOMONTH(A5,0)) | C5: INV-10525 | D5: CBA | E5: 1350 | F5: =IF(E5="","",IF(COUNTIF(lst_Jobs,E5&"")>0,"OK","CHECK")) | G5: CBA BNE July 2026 | H5: Onsite | I5: ONSITE | J5: Contract | K5: GST 10% | L5: 8588.45 | M5: =IF(L5="","",IF(K5="GST 10%",ROUND(L5*set_GSTRate,2),0)) | N5: =IF(L5="","",L5+M5) | O5: 41100 | P5: Y | Q5: N | T5: Invoiced | U5: 174.05 hours | V5: =IF(COUNTA(A5,D5,C5,L5)=0,"",IF(A5="","No date - sits outside every month",IF(E5="","No job number",IF(F5="CHECK","Job number is not in the Xero job list",IF(I5="","No cost centre",IF(AND(P5="Y",C5=""),"Marked posted to Xero but has no invoice number",IF(AND(L5<>"",K5=""),"No tax code",IF(AND(L5<>"",O5=""),"No revenue GL code","")))))))) | W5: =IF(E5="","",IFERROR(INDEX(lst_JobName,MATCH(E5&"",lst_Jobs,0)),"")) | X5: =IF(E5="","",COUNTIFS(tbl_Finance[Job Number],E5&"",tbl_Finance[Ex GST],"<>")) | Y5: =IF(E5="","",SUMIFS(tbl_Finance[Ex GST],tbl_Finance[Job Number],E5&"")) | Z5: =IF(E5="","",SUMIFS(tbl_Finance[Ex GST],tbl_Finance[Job Number],E5&"",tbl_Finance[Xero Invoice No],"<>")) | AA5: =IF(E5="","",Y5-Z5) | AB5: =IF(E5="","",IF(H5="Onsite",IFERROR(INDEX(tbl_Onsite[Qwilr Quote],MATCH(E5&"",tbl_Onsite[Job Number],0)),""),IF(H5="Production",IFERROR(IF(INDEX(tbl_Production[Current RMS No],MATCH(E5&"",tbl_Production[Job Number],0))="",INDEX(tbl_Production[Qwilr Quote],MATCH(E5&"",tbl_Production[Job Number],0)),INDEX(tbl_Production[Current RMS No],MATCH(E5&"",tbl_Production[Job Number],0))),""),IF(H5="Consulting",IFERROR(INDEX(tbl_Consulting[Qwilr Quote],MATCH(E5&"",tbl_Consulting[Job Number],0)),""),"")))) | AC5: =IF(AB5="","",IF(AND(LEFT(AB5,4)<>"http",IF(H5="Production",set_RMSBase,set_QwilrBase)=""),"",HYPERLINK(IF(LEFT(AB5,4)="http",AB5,IF(H5="Production",set_RMSBase,set_QwilrBase)&AB5),"Open"))) | AD5: =IF(E5="","",IF(H5="Production",IFERROR(INDEX(tbl_Production[Total Expense],MATCH(E5&"",tbl_Production[Job Number],0)),0),IF(H5="Consulting",IFERROR(INDEX(tbl_Consulting[Total Expense],MATCH(E5&"",tbl_Consulting[Job Number],0)),0),0))) | AE5: =IF(E5="","",Y5-N(AD5)) | AF5: =IFERROR(AE5/Y5,"") | AG5: =IF(E5="","",IF(H5="Onsite",IFERROR(INDEX(tbl_Onsite[Notes],MATCH(E5&"",tbl_Onsite[Job Number],0)),""),IF(H5="Production",IFERROR(INDEX(tbl_Production[Notes],MATCH(E5&"",tbl_Production[Job Number],0)),""),IF(H5="Consulting",IFERROR(INDEX(tbl_Consulting[Notes],MATCH(E5&"",tbl_Consulting[Job Number],0)),""),""))))
A6: 46234 | B6: =IF(A6="","",EOMONTH(A6,0)) | C6: INV-10526 | D6: CBA | E6: 585/586/1755 | F6: =IF(E6="","",IF(COUNTIF(lst_Jobs,E6&"")>0,"OK","CHECK")) | G6: CBP July 2026 | H6: Onsite | I6: ONSITE | J6: Contract | K6: GST 10% | L6: 22120.57 | M6: =IF(L6="","",IF(K6="GST 10%",ROUND(L6*set_GSTRate,2),0)) | N6: =IF(L6="","",L6+M6) | O6: 41100 | P6: Y | Q6: N | T6: Invoiced | U6: Deduct 3hrs for TN 01/07 & 6hrs for NP 14/07 | V6: =IF(COUNTA(A6,D6,C6,L6)=0,"",IF(A6="","No date - sits outside every month",IF(E6="","No job number",IF(F6="CHECK","Job number is not in the Xero job list",IF(I6="","No cost centre",IF(AND(P6="Y",C6=""),"Marked posted to Xero but has no invoice number",IF(AND(L6<>"",K6=""),"No tax code",IF(AND(L6<>"",O6=""),"No revenue GL code","")))))))) | W6: =IF(E6="","",IFERROR(INDEX(lst_JobName,MATCH(E6&"",lst_Jobs,0)),"")) | X6: =IF(E6="","",COUNTIFS(tbl_Finance[Job Number],E6&"",tbl_Finance[Ex GST],"<>")) | Y6: =IF(E6="","",SUMIFS(tbl_Finance[Ex GST],tbl_Finance[Job Number],E6&"")) | Z6: =IF(E6="","",SUMIFS(tbl_Finance[Ex GST],tbl_Finance[Job Number],E6&"",tbl_Finance[Xero Invoice No],"<>")) | AA6: =IF(E6="","",Y6-Z6) | AB6: =IF(E6="","",IF(H6="Onsite",IFERROR(INDEX(tbl_Onsite[Qwilr Quote],MATCH(E6&"",tbl_Onsite[Job Number],0)),""),IF(H6="Production",IFERROR(IF(INDEX(tbl_Production[Current RMS No],MATCH(E6&"",tbl_Production[Job Number],0))="",INDEX(tbl_Production[Qwilr Quote],MATCH(E6&"",tbl_Production[Job Number],0)),INDEX(tbl_Production[Current RMS No],MATCH(E6&"",tbl_Production[Job Number],0))),""),IF(H6="Consulting",IFERROR(INDEX(tbl_Consulting[Qwilr Quote],MATCH(E6&"",tbl_Consulting[Job Number],0)),""),"")))) | AC6: =IF(AB6="","",IF(AND(LEFT(AB6,4)<>"http",IF(H6="Production",set_RMSBase,set_QwilrBase)=""),"",HYPERLINK(IF(LEFT(AB6,4)="http",AB6,IF(H6="Production",set_RMSBase,set_QwilrBase)&AB6),"Open"))) | AD6: =IF(E6="","",IF(H6="Production",IFERROR(INDEX(tbl_Production[Total Expense],MATCH(E6&"",tbl_Production[Job Number],0)),0),IF(H6="Consulting",IFERROR(INDEX(tbl_Consulting[Total Expense],MATCH(E6&"",tbl_Consulting[Job Number],0)),0),0))) | AE6: =IF(E6="","",Y6-N(AD6)) | AF6: =IFERROR(AE6/Y6,"") | AG6: =IF(E6="","",IF(H6="Onsite",IFERROR(INDEX(tbl_Onsite[Notes],MATCH(E6&"",tbl_Onsite[Job Number],0)),""),IF(H6="Production",IFERROR(INDEX(tbl_Production[Notes],MATCH(E6&"",tbl_Production[Job Number],0)),""),IF(H6="Consulting",IFERROR(INDEX(tbl_Consulting[Notes],MATCH(E6&"",tbl_Consulting[Job Number],0)),""),""))))
A7: 46234 | B7: =IF(A7="","",EOMONTH(A7,0)) | C7: INV-10527 | D7: CBA | E7: 587 | F7: =IF(E7="","",IF(COUNTIF(lst_Jobs,E7&"")>0,"OK","CHECK")) | G7: CBS July 2026 | H7: Onsite | I7: ONSITE | J7: Contract | K7: GST 10% | L7: 10720 | M7: =IF(L7="","",IF(K7="GST 10%",ROUND(L7*set_GSTRate,2),0)) | N7: =IF(L7="","",L7+M7) | O7: 41100 | P7: Y | Q7: N | T7: Invoiced | V7: =IF(COUNTA(A7,D7,C7,L7)=0,"",IF(A7="","No date - sits outside every month",IF(E7="","No job number",IF(F7="CHECK","Job number is not in the Xero job list",IF(I7="","No cost centre",IF(AND(P7="Y",C7=""),"Marked posted to Xero but has no invoice number",IF(AND(L7<>"",K7=""),"No tax code",IF(AND(L7<>"",O7=""),"No revenue GL code","")))))))) | W7: =IF(E7="","",IFERROR(INDEX(lst_JobName,MATCH(E7&"",lst_Jobs,0)),"")) | X7: =IF(E7="","",COUNTIFS(tbl_Finance[Job Number],E7&"",tbl_Finance[Ex GST],"<>")) | Y7: =IF(E7="","",SUMIFS(tbl_Finance[Ex GST],tbl_Finance[Job Number],E7&"")) | Z7: =IF(E7="","",SUMIFS(tbl_Finance[Ex GST],tbl_Finance[Job Number],E7&"",tbl_Finance[Xero Invoice No],"<>")) | AA7: =IF(E7="","",Y7-Z7) | AB7: =IF(E7="","",IF(H7="Onsite",IFERROR(INDEX(tbl_Onsite[Qwilr Quote],MATCH(E7&"",tbl_Onsite[Job Number],0)),""),IF(H7="Production",IFERROR(IF(INDEX(tbl_Production[Current RMS No],MATCH(E7&"",tbl_Production[Job Number],0))="",INDEX(tbl_Production[Qwilr Quote],MATCH(E7&"",tbl_Production[Job Number],0)),INDEX(tbl_Production[Current RMS No],MATCH(E7&"",tbl_Production[Job Number],0))),""),IF(H7="Consulting",IFERROR(INDEX(tbl_Consulting[Qwilr Quote],MATCH(E7&"",tbl_Consulting[Job Number],0)),""),"")))) | AC7: =IF(AB7="","",IF(AND(LEFT(AB7,4)<>"http",IF(H7="Production",set_RMSBase,set_QwilrBase)=""),"",HYPERLINK(IF(LEFT(AB7,4)="http",AB7,IF(H7="Production",set_RMSBase,set_QwilrBase)&AB7),"Open"))) | AD7: =IF(E7="","",IF(H7="Production",IFERROR(INDEX(tbl_Production[Total Expense],MATCH(E7&"",tbl_Production[Job Number],0)),0),IF(H7="Consulting",IFERROR(INDEX(tbl_Consulting[Total Expense],MATCH(E7&"",tbl_Consulting[Job Number],0)),0),0))) | AE7: =IF(E7="","",Y7-N(AD7)) | AF7: =IFERROR(AE7/Y7,"") | AG7: =IF(E7="","",IF(H7="Onsite",IFERROR(INDEX(tbl_Onsite[Notes],MATCH(E7&"",tbl_Onsite[Job Number],0)),""),IF(H7="Production",IFERROR(INDEX(tbl_Production[Notes],MATCH(E7&"",tbl_Production[Job Number],0)),""),IF(H7="Consulting",IFERROR(INDEX(tbl_Consulting[Notes],MATCH(E7&"",tbl_Consulting[Job Number],0)),""),""))))
A8: 46234 | B8: =IF(A8="","",EOMONTH(A8,0)) | C8: INV-10528 | D8: DTTL | E8: 2846/1401/725/1400/1530/1862/2402/2849/974 | F8: =IF(E8="","",IF(COUNTIF(lst_Jobs,E8&"")>0,"OK","CHECK")) | G8: DTTL Contract July 2026 | H8: Onsite | I8: ONSITE | J8: Contract | K8: GST 10% | L8: 103625.44 | M8: =IF(L8="","",IF(K8="GST 10%",ROUND(L8*set_GSTRate,2),0)) | N8: =IF(L8="","",L8+M8) | O8: 41100 | P8: Y | Q8: N | T8: Invoiced | V8: =IF(COUNTA(A8,D8,C8,L8)=0,"",IF(A8="","No date - sits outside every month",IF(E8="","No job number",IF(F8="CHECK","Job number is not in the Xero job list",IF(I8="","No cost centre",IF(AND(P8="Y",C8=""),"Marked posted to Xero but has no invoice number",IF(AND(L8<>"",K8=""),"No tax code",IF(AND(L8<>"",O8=""),"No revenue GL code","")))))))) | W8: =IF(E8="","",IFERROR(INDEX(lst_JobName,MATCH(E8&"",lst_Jobs,0)),"")) | X8: =IF(E8="","",COUNTIFS(tbl_Finance[Job Number],E8&"",tbl_Finance[Ex GST],"<>")) | Y8: =IF(E8="","",SUMIFS(tbl_Finance[Ex GST],tbl_Finance[Job Number],E8&"")) | Z8: =IF(E8="","",SUMIFS(tbl_Finance[Ex GST],tbl_Finance[Job Number],E8&"",tbl_Finance[Xero Invoice No],"<>")) | AA8: =IF(E8="","",Y8-Z8) | AB8: =IF(E8="","",IF(H8="Onsite",IFERROR(INDEX(tbl_Onsite[Qwilr Quote],MATCH(E8&"",tbl_Onsite[Job Number],0)),""),IF(H8="Production",IFERROR(IF(INDEX(tbl_Production[Current RMS No],MATCH(E8&"",tbl_Production[Job Number],0))="",INDEX(tbl_Production[Qwilr Quote],MATCH(E8&"",tbl_Production[Job Number],0)),INDEX(tbl_Production[Current RMS No],MATCH(E8&"",tbl_Production[Job Number],0))),""),IF(H8="Consulting",IFERROR(INDEX(tbl_Consulting[Qwilr Quote],MATCH(E8&"",tbl_Consulting[Job Number],0)),""),"")))) | AC8: =IF(AB8="","",IF(AND(LEFT(AB8,4)<>"http",IF(H8="Production",set_RMSBase,set_QwilrBase)=""),"",HYPERLINK(IF(LEFT(AB8,4)="http",AB8,IF(H8="Production",set_RMSBase,set_QwilrBase)&AB8),"Open"))) | AD8: =IF(E8="","",IF(H8="Production",IFERROR(INDEX(tbl_Production[Total Expense],MATCH(E8&"",tbl_Production[Job Number],0)),0),IF(H8="Consulting",IFERROR(INDEX(tbl_Consulting[Total Expense],MATCH(E8&"",tbl_Consulting[Job Number],0)),0),0))) | AE8: =IF(E8="","",Y8-N(AD8)) | AF8: =IFERROR(AE8/Y8,"") | AG8: =IF(E8="","",IF(H8="Onsite",IFERROR(INDEX(tbl_Onsite[Notes],MATCH(E8&"",tbl_Onsite[Job Number],0)),""),IF(H8="Production",IFERROR(INDEX(tbl_Production[Notes],MATCH(E8&"",tbl_Production[Job Number],0)),""),IF(H8="Consulting",IFERROR(INDEX(tbl_Consulting[Notes],MATCH(E8&"",tbl_Consulting[Job Number],0)),""),""))))
A9: 46234 | B9: =IF(A9="","",EOMONTH(A9,0)) | C9: INV-10529 | D9: BW | E9: 732/1144 | F9: =IF(E9="","",IF(COUNTIF(lst_Jobs,E9&"")>0,"OK","CHECK")) | G9: BW Contract July 2026 | H9: Onsite | I9: ONSITE | J9: Contract | K9: GST 10% | L9: 19427.5 | M9: =IF(L9="","",IF(K9="GST 10%",ROUND(L9*set_GSTRate,2),0)) | N9: =IF(L9="","",L9+M9) | O9: 41100 | P9: Y | Q9: N | T9: Invoiced | V9: =IF(COUNTA(A9,D9,C9,L9)=0,"",IF(A9="","No date - sits outside every month",IF(E9="","No job number",IF(F9="CHECK","Job number is not in the Xero job list",IF(I9="","No cost centre",IF(AND(P9="Y",C9=""),"Marked posted to Xero but has no invoice number",IF(AND(L9<>"",K9=""),"No tax code",IF(AND(L9<>"",O9=""),"No revenue GL code","")))))))) | W9: =IF(E9="","",IFERROR(INDEX(lst_JobName,MATCH(E9&"",lst_Jobs,0)),"")) | X9: =IF(E9="","",COUNTIFS(tbl_Finance[Job Number],E9&"",tbl_Finance[Ex GST],"<>")) | Y9: =IF(E9="","",SUMIFS(tbl_Finance[Ex GST],tbl_Finance[Job Number],E9&"")) | Z9: =IF(E9="","",SUMIFS(tbl_Finance[Ex GST],tbl_Finance[Job Number],E9&"",tbl_Finance[Xero Invoice No],"<>")) | AA9: =IF(E9="","",Y9-Z9) | AB9: =IF(E9="","",IF(H9="Onsite",IFERROR(INDEX(tbl_Onsite[Qwilr Quote],MATCH(E9&"",tbl_Onsite[Job Number],0)),""),IF(H9="Production",IFERROR(IF(INDEX(tbl_Production[Current RMS No],MATCH(E9&"",tbl_Production[Job Number],0))="",INDEX(tbl_Production[Qwilr Quote],MATCH(E9&"",tbl_Production[Job Number],0)),INDEX(tbl_Production[Current RMS No],MATCH(E9&"",tbl_Production[Job Number],0))),""),IF(H9="Consulting",IFERROR(INDEX(tbl_Consulting[Qwilr Quote],MATCH(E9&"",tbl_Consulting[Job Number],0)),""),"")))) | AC9: =IF(AB9="","",IF(AND(LEFT(AB9,4)<>"http",IF(H9="Production",set_RMSBase,set_QwilrBase)=""),"",HYPERLINK(IF(LEFT(AB9,4)="http",AB9,IF(H9="Production",set_RMSBase,set_QwilrBase)&AB9),"Open"))) | AD9: =IF(E9="","",IF(H9="Production",IFERROR(INDEX(tbl_Production[Total Expense],MATCH(E9&"",tbl_Production[Job Number],0)),0),IF(H9="Consulting",IFERROR(INDEX(tbl_Consulting[Total Expense],MATCH(E9&"",tbl_Consulting[Job Number],0)),0),0))) | AE9: =IF(E9="","",Y9-N(AD9)) | AF9: =IFERROR(AE9/Y9,"") | AG9: =IF(E9="","",IF(H9="Onsite",IFERROR(INDEX(tbl_Onsite[Notes],MATCH(E9&"",tbl_Onsite[Job Number],0)),""),IF(H9="Production",IFERROR(INDEX(tbl_Production[Notes],MATCH(E9&"",tbl_Production[Job Number],0)),""),IF(H9="Consulting",IFERROR(INDEX(tbl_Consulting[Notes],MATCH(E9&"",tbl_Consulting[Job Number],0)),""),""))))
A10: 46234 | B10: =IF(A10="","",EOMONTH(A10,0)) | C10: INV-10530 | D10: BW | E10: 2192 | F10: =IF(E10="","",IF(COUNTIF(lst_Jobs,E10&"")>0,"OK","CHECK")) | G10: BW Additionals July 2026 | H10: Onsite | I10: ONSITE | J10: Contract | K10: GST 10% | L10: 1120 | M10: =IF(L10="","",IF(K10="GST 10%",ROUND(L10*set_GSTRate,2),0)) | N10: =IF(L10="","",L10+M10) | O10: 41100 | P10: Y | Q10: N | T10: Invoiced | V10: =IF(COUNTA(A10,D10,C10,L10)=0,"",IF(A10="","No date - sits outside every month",IF(E10="","No job number",IF(F10="CHECK","Job number is not in the Xero job list",IF(I10="","No cost centre",IF(AND(P10="Y",C10=""),"Marked posted to Xero but has no invoice number",IF(AND(L10<>"",K10=""),"No tax code",IF(AND(L10<>"",O10=""),"No revenue GL code","")))))))) | W10: =IF(E10="","",IFERROR(INDEX(lst_JobName,MATCH(E10&"",lst_Jobs,0)),"")) | X10: =IF(E10="","",COUNTIFS(tbl_Finance[Job Number],E10&"",tbl_Finance[Ex GST],"<>")) | Y10: =IF(E10="","",SUMIFS(tbl_Finance[Ex GST],tbl_Finance[Job Number],E10&"")) | Z10: =IF(E10="","",SUMIFS(tbl_Finance[Ex GST],tbl_Finance[Job Number],E10&"",tbl_Finance[Xero Invoice No],"<>")) | AA10: =IF(E10="","",Y10-Z10) | AB10: =IF(E10="","",IF(H10="Onsite",IFERROR(INDEX(tbl_Onsite[Qwilr Quote],MATCH(E10&"",tbl_Onsite[Job Number],0)),""),IF(H10="Production",IFERROR(IF(INDEX(tbl_Production[Current RMS No],MATCH(E10&"",tbl_Production[Job Number],0))="",INDEX(tbl_Production[Qwilr Quote],MATCH(E10&"",tbl_Production[Job Number],0)),INDEX(tbl_Production[Current RMS No],MATCH(E10&"",tbl_Production[Job Number],0))),""),IF(H10="Consulting",IFERROR(INDEX(tbl_Consulting[Qwilr Quote],MATCH(E10&"",tbl_Consulting[Job Number],0)),""),"")))) | AC10: =IF(AB10="","",IF(AND(LEFT(AB10,4)<>"http",IF(H10="Production",set_RMSBase,set_QwilrBase)=""),"",HYPERLINK(IF(LEFT(AB10,4)="http",AB10,IF(H10="Production",set_RMSBase,set_QwilrBase)&AB10),"Open"))) | AD10: =IF(E10="","",IF(H10="Production",IFERROR(INDEX(tbl_Production[Total Expense],MATCH(E10&"",tbl_Production[Job Number],0)),0),IF(H10="Consulting",IFERROR(INDEX(tbl_Consulting[Total Expense],MATCH(E10&"",tbl_Consulting[Job Number],0)),0),0))) | AE10: =IF(E10="","",Y10-N(AD10)) | AF10: =IFERROR(AE10/Y10,"") | AG10: =IF(E10="","",IF(H10="Onsite",IFERROR(INDEX(tbl_Onsite[Notes],MATCH(E10&"",tbl_Onsite[Job Number],0)),""),IF(H10="Production",IFERROR(INDEX(tbl_Production[Notes],MATCH(E10&"",tbl_Production[Job Number],0)),""),IF(H10="Consulting",IFERROR(INDEX(tbl_Consulting[Notes],MATCH(E10&"",tbl_Consulting[Job Number],0)),""),""))))
A11: 46234 | B11: =IF(A11="","",EOMONTH(A11,0)) | C11: INV-10531 | D11: PWC | E11: 2488 | F11: =IF(E11="","",IF(COUNTIF(lst_Jobs,E11&"")>0,"OK","CHECK")) | G11: PWC Brisbane July 2026 | H11: Onsite | I11: ONSITE | J11: Contract | K11: GST 10% | L11: 7150 | M11: =IF(L11="","",IF(K11="GST 10%",ROUND(L11*set_GSTRate,2),0)) | N11: =IF(L11="","",L11+M11) | O11: 41100 | P11: Y | Q11: N | T11: Invoiced | V11: =IF(COUNTA(A11,D11,C11,L11)=0,"",IF(A11="","No date - sits outside every month",IF(E11="","No job number",IF(F11="CHECK","Job number is not in the Xero job list",IF(I11="","No cost centre",IF(AND(P11="Y",C11=""),"Marked posted to Xero but has no invoice number",IF(AND(L11<>"",K11=""),"No tax code",IF(AND(L11<>"",O11=""),"No revenue GL code","")))))))) | W11: =IF(E11="","",IFERROR(INDEX(lst_JobName,MATCH(E11&"",lst_Jobs,0)),"")) | X11: =IF(E11="","",COUNTIFS(tbl_Finance[Job Number],E11&"",tbl_Finance[Ex GST],"<>")) | Y11: =IF(E11="","",SUMIFS(tbl_Finance[Ex GST],tbl_Finance[Job Number],E11&"")) | Z11: =IF(E11="","",SUMIFS(tbl_Finance[Ex GST],tbl_Finance[Job Number],E11&"",tbl_Finance[Xero Invoice No],"<>")) | AA11: =IF(E11="","",Y11-Z11) | AB11: =IF(E11="","",IF(H11="Onsite",IFERROR(INDEX(tbl_Onsite[Qwilr Quote],MATCH(E11&"",tbl_Onsite[Job Number],0)),""),IF(H11="Production",IFERROR(IF(INDEX(tbl_Production[Current RMS No],MATCH(E11&"",tbl_Production[Job Number],0))="",INDEX(tbl_Production[Qwilr Quote],MATCH(E11&"",tbl_Production[Job Number],0)),INDEX(tbl_Production[Current RMS No],MATCH(E11&"",tbl_Production[Job Number],0))),""),IF(H11="Consulting",IFERROR(INDEX(tbl_Consulting[Qwilr Quote],MATCH(E11&"",tbl_Consulting[Job Number],0)),""),"")))) | AC11: =IF(AB11="","",IF(AND(LEFT(AB11,4)<>"http",IF(H11="Production",set_RMSBase,set_QwilrBase)=""),"",HYPERLINK(IF(LEFT(AB11,4)="http",AB11,IF(H11="Production",set_RMSBase,set_QwilrBase)&AB11),"Open"))) | AD11: =IF(E11="","",IF(H11="Production",IFERROR(INDEX(tbl_Production[Total Expense],MATCH(E11&"",tbl_Production[Job Number],0)),0),IF(H11="Consulting",IFERROR(INDEX(tbl_Consulting[Total Expense],MATCH(E11&"",tbl_Consulting[Job Number],0)),0),0))) | AE11: =IF(E11="","",Y11-N(AD11)) | AF11: =IFERROR(AE11/Y11,"") | AG11: =IF(E11="","",IF(H11="Onsite",IFERROR(INDEX(tbl_Onsite[Notes],MATCH(E11&"",tbl_Onsite[Job Number],0)),""),IF(H11="Production",IFERROR(INDEX(tbl_Production[Notes],MATCH(E11&"",tbl_Production[Job Number],0)),""),IF(H11="Consulting",IFERROR(INDEX(tbl_Consulting[Notes],MATCH(E11&"",tbl_Consulting[Job Number],0)),""),""))))
A12: 46234 | B12: =IF(A12="","",EOMONTH(A12,0)) | C12: INV-10532 | D12: Gen-E | E12: 26021602 | F12: =IF(E12="","",IF(COUNTIF(lst_Jobs,E12&"")>0,"OK","CHECK")) | G12: Gen-E ABS July 2026 | H12: Onsite | I12: ONSITE | J12: Contract | K12: GST 10% | L12: 12388.8 | M12: =IF(L12="","",IF(K12="GST 10%",ROUND(L12*set_GSTRate,2),0)) | N12: =IF(L12="","",L12+M12) | O12: 41100 | P12: Y | Q12: N | T12: Invoiced | V12: =IF(COUNTA(A12,D12,C12,L12)=0,"",IF(A12="","No date - sits outside every month",IF(E12="","No job number",IF(F12="CHECK","Job number is not in the Xero job list",IF(I12="","No cost centre",IF(AND(P12="Y",C12=""),"Marked posted to Xero but has no invoice number",IF(AND(L12<>"",K12=""),"No tax code",IF(AND(L12<>"",O12=""),"No revenue GL code","")))))))) | W12: =IF(E12="","",IFERROR(INDEX(lst_JobName,MATCH(E12&"",lst_Jobs,0)),"")) | X12: =IF(E12="","",COUNTIFS(tbl_Finance[Job Number],E12&"",tbl_Finance[Ex GST],"<>")) | Y12: =IF(E12="","",SUMIFS(tbl_Finance[Ex GST],tbl_Finance[Job Number],E12&"")) | Z12: =IF(E12="","",SUMIFS(tbl_Finance[Ex GST],tbl_Finance[Job Number],E12&"",tbl_Finance[Xero Invoice No],"<>")) | AA12: =IF(E12="","",Y12-Z12) | AB12: =IF(E12="","",IF(H12="Onsite",IFERROR(INDEX(tbl_Onsite[Qwilr Quote],MATCH(E12&"",tbl_Onsite[Job Number],0)),""),IF(H12="Production",IFERROR(IF(INDEX(tbl_Production[Current RMS No],MATCH(E12&"",tbl_Production[Job Number],0))="",INDEX(tbl_Production[Qwilr Quote],MATCH(E12&"",tbl_Production[Job Number],0)),INDEX(tbl_Production[Current RMS No],MATCH(E12&"",tbl_Production[Job Number],0))),""),IF(H12="Consulting",IFERROR(INDEX(tbl_Consulting[Qwilr Quote],MATCH(E12&"",tbl_Consulting[Job Number],0)),""),"")))) | AC12: =IF(AB12="","",IF(AND(LEFT(AB12,4)<>"http",IF(H12="Production",set_RMSBase,set_QwilrBase)=""),"",HYPERLINK(IF(LEFT(AB12,4)="http",AB12,IF(H12="Production",set_RMSBase,set_QwilrBase)&AB12),"Open"))) | AD12: =IF(E12="","",IF(H12="Production",IFERROR(INDEX(tbl_Production[Total Expense],MATCH(E12&"",tbl_Production[Job Number],0)),0),IF(H12="Consulting",IFERROR(INDEX(tbl_Consulting[Total Expense],MATCH(E12&"",tbl_Consulting[Job Number],0)),0),0))) | AE12: =IF(E12="","",Y12-N(AD12)) | AF12: =IFERROR(AE12/Y12,"") | AG12: =IF(E12="","",IF(H12="Onsite",IFERROR(INDEX(tbl_Onsite[Notes],MATCH(E12&"",tbl_Onsite[Job Number],0)),""),IF(H12="Production",IFERROR(INDEX(tbl_Production[Notes],MATCH(E12&"",tbl_Production[Job Number],0)),""),IF(H12="Consulting",IFERROR(INDEX(tbl_Consulting[Notes],MATCH(E12&"",tbl_Consulting[Job Number],0)),""),""))))
A13: 46234 | B13: =IF(A13="","",EOMONTH(A13,0)) | C13: INV-10534 | D13: CBA | E13: 26043001 | F13: =IF(E13="","",IF(COUNTIF(lst_Jobs,E13&"")>0,"OK","CHECK")) | G13: CBA Mel July 2026 | H13: Onsite | I13: ONSITE | J13: Contract | K13: GST 10% | L13: 11377.12 | M13: =IF(L13="","",IF(K13="GST 10%",ROUND(L13*set_GSTRate,2),0)) | N13: =IF(L13="","",L13+M13) | O13: 41100 | P13: Y | Q13: N | T13: Invoiced | U13: Deduct 8hrs CN for 03/07 | V13: =IF(COUNTA(A13,D13,C13,L13)=0,"",IF(A13="","No date - sits outside every month",IF(E13="","No job number",IF(F13="CHECK","Job number is not in the Xero job list",IF(I13="","No cost centre",IF(AND(P13="Y",C13=""),"Marked posted to Xero but has no invoice number",IF(AND(L13<>"",K13=""),"No tax code",IF(AND(L13<>"",O13=""),"No revenue GL code","")))))))) | W13: =IF(E13="","",IFERROR(INDEX(lst_JobName,MATCH(E13&"",lst_Jobs,0)),"")) | X13: =IF(E13="","",COUNTIFS(tbl_Finance[Job Number],E13&"",tbl_Finance[Ex GST],"<>")) | Y13: =IF(E13="","",SUMIFS(tbl_Finance[Ex GST],tbl_Finance[Job Number],E13&"")) | Z13: =IF(E13="","",SUMIFS(tbl_Finance[Ex GST],tbl_Finance[Job Number],E13&"",tbl_Finance[Xero Invoice No],"<>")) | AA13: =IF(E13="","",Y13-Z13) | AB13: =IF(E13="","",IF(H13="Onsite",IFERROR(INDEX(tbl_Onsite[Qwilr Quote],MATCH(E13&"",tbl_Onsite[Job Number],0)),""),IF(H13="Production",IFERROR(IF(INDEX(tbl_Production[Current RMS No],MATCH(E13&"",tbl_Production[Job Number],0))="",INDEX(tbl_Production[Qwilr Quote],MATCH(E13&"",tbl_Production[Job Number],0)),INDEX(tbl_Production[Current RMS No],MATCH(E13&"",tbl_Production[Job Number],0))),""),IF(H13="Consulting",IFERROR(INDEX(tbl_Consulting[Qwilr Quote],MATCH(E13&"",tbl_Consulting[Job Number],0)),""),"")))) | AC13: =IF(AB13="","",IF(AND(LEFT(AB13,4)<>"http",IF(H13="Production",set_RMSBase,set_QwilrBase)=""),"",HYPERLINK(IF(LEFT(AB13,4)="http",AB13,IF(H13="Production",set_RMSBase,set_QwilrBase)&AB13),"Open"))) | AD13: =IF(E13="","",IF(H13="Production",IFERROR(INDEX(tbl_Production[Total Expense],MATCH(E13&"",tbl_Production[Job Number],0)),0),IF(H13="Consulting",IFERROR(INDEX(tbl_Consulting[Total Expense],MATCH(E13&"",tbl_Consulting[Job Number],0)),0),0))) | AE13: =IF(E13="","",Y13-N(AD13)) | AF13: =IFERROR(AE13/Y13,"") | AG13: =IF(E13="","",IF(H13="Onsite",IFERROR(INDEX(tbl_Onsite[Notes],MATCH(E13&"",tbl_Onsite[Job Number],0)),""),IF(H13="Production",IFERROR(INDEX(tbl_Production[Notes],MATCH(E13&"",tbl_Production[Job Number],0)),""),IF(H13="Consulting",IFERROR(INDEX(tbl_Consulting[Notes],MATCH(E13&"",tbl_Consulting[Job Number],0)),""),""))))
A14: 46234 | B14: =IF(A14="","",EOMONTH(A14,0)) | C14: INV-10535 | D14: PWC | E14: 25101301B | F14: =IF(E14="","",IF(COUNTIF(lst_Jobs,E14&"")>0,"OK","CHECK")) | G14: PWC Sydney IT July 2026 | H14: Onsite | I14: ONSITE | J14: Contract | K14: GST 10% | L14: 11907 | M14: =IF(L14="","",IF(K14="GST 10%",ROUND(L14*set_GSTRate,2),0)) | N14: =IF(L14="","",L14+M14) | O14: 41100 | P14: Y | Q14: N | T14: Invoiced | V14: =IF(COUNTA(A14,D14,C14,L14)=0,"",IF(A14="","No date - sits outside every month",IF(E14="","No job number",IF(F14="CHECK","Job number is not in the Xero job list",IF(I14="","No cost centre",IF(AND(P14="Y",C14=""),"Marked posted to Xero but has no invoice number",IF(AND(L14<>"",K14=""),"No tax code",IF(AND(L14<>"",O14=""),"No revenue GL code","")))))))) | W14: =IF(E14="","",IFERROR(INDEX(lst_JobName,MATCH(E14&"",lst_Jobs,0)),"")) | X14: =IF(E14="","",COUNTIFS(tbl_Finance[Job Number],E14&"",tbl_Finance[Ex GST],"<>")) | Y14: =IF(E14="","",SUMIFS(tbl_Finance[Ex GST],tbl_Finance[Job Number],E14&"")) | Z14: =IF(E14="","",SUMIFS(tbl_Finance[Ex GST],tbl_Finance[Job Number],E14&"",tbl_Finance[Xero Invoice No],"<>")) | AA14: =IF(E14="","",Y14-Z14) | AB14: =IF(E14="","",IF(H14="Onsite",IFERROR(INDEX(tbl_Onsite[Qwilr Quote],MATCH(E14&"",tbl_Onsite[Job Number],0)),""),IF(H14="Production",IFERROR(IF(INDEX(tbl_Production[Current RMS No],MATCH(E14&"",tbl_Production[Job Number],0))="",INDEX(tbl_Production[Qwilr Quote],MATCH(E14&"",tbl_Production[Job Number],0)),INDEX(tbl_Production[Current RMS No],MATCH(E14&"",tbl_Production[Job Number],0))),""),IF(H14="Consulting",IFERROR(INDEX(tbl_Consulting[Qwilr Quote],MATCH(E14&"",tbl_Consulting[Job Number],0)),""),"")))) | AC14: =IF(AB14="","",IF(AND(LEFT(AB14,4)<>"http",IF(H14="Production",set_RMSBase,set_QwilrBase)=""),"",HYPERLINK(IF(LEFT(AB14,4)="http",AB14,IF(H14="Production",set_RMSBase,set_QwilrBase)&AB14),"Open"))) | AD14: =IF(E14="","",IF(H14="Production",IFERROR(INDEX(tbl_Production[Total Expense],MATCH(E14&"",tbl_Production[Job Number],0)),0),IF(H14="Consulting",IFERROR(INDEX(tbl_Consulting[Total Expense],MATCH(E14&"",tbl_Consulting[Job Number],0)),0),0))) | AE14: =IF(E14="","",Y14-N(AD14)) | AF14: =IFERROR(AE14/Y14,"") | AG14: =IF(E14="","",IF(H14="Onsite",IFERROR(INDEX(tbl_Onsite[Notes],MATCH(E14&"",tbl_Onsite[Job Number],0)),""),IF(H14="Production",IFERROR(INDEX(tbl_Production[Notes],MATCH(E14&"",tbl_Production[Job Number],0)),""),IF(H14="Consulting",IFERROR(INDEX(tbl_Consulting[Notes],MATCH(E14&"",tbl_Consulting[Job Number],0)),""),""))))
A15: 46234 | B15: =IF(A15="","",EOMONTH(A15,0)) | C15: INV-10536 | D15: RICOH | E15: 2880 | F15: =IF(E15="","",IF(COUNTIF(lst_Jobs,E15&"")>0,"OK","CHECK")) | G15: Ricoh Contract July 2026 | H15: Onsite | I15: ONSITE | J15: Contract | K15: GST 10% | L15: 11860.5 | M15: =IF(L15="","",IF(K15="GST 10%",ROUND(L15*set_GSTRate,2),0)) | N15: =IF(L15="","",L15+M15) | O15: 41100 | P15: Y | Q15: N | T15: Invoiced | U15: 2 months extension | V15: =IF(COUNTA(A15,D15,C15,L15)=0,"",IF(A15="","No date - sits outside every month",IF(E15="","No job number",IF(F15="CHECK","Job number is not in the Xero job list",IF(I15="","No cost centre",IF(AND(P15="Y",C15=""),"Marked posted to Xero but has no invoice number",IF(AND(L15<>"",K15=""),"No tax code",IF(AND(L15<>"",O15=""),"No revenue GL code","")))))))) | W15: =IF(E15="","",IFERROR(INDEX(lst_JobName,MATCH(E15&"",lst_Jobs,0)),"")) | X15: =IF(E15="","",COUNTIFS(tbl_Finance[Job Number],E15&"",tbl_Finance[Ex GST],"<>")) | Y15: =IF(E15="","",SUMIFS(tbl_Finance[Ex GST],tbl_Finance[Job Number],E15&"")) | Z15: =IF(E15="","",SUMIFS(tbl_Finance[Ex GST],tbl_Finance[Job Number],E15&"",tbl_Finance[Xero Invoice No],"<>")) | AA15: =IF(E15="","",Y15-Z15) | AB15: =IF(E15="","",IF(H15="Onsite",IFERROR(INDEX(tbl_Onsite[Qwilr Quote],MATCH(E15&"",tbl_Onsite[Job Number],0)),""),IF(H15="Production",IFERROR(IF(INDEX(tbl_Production[Current RMS No],MATCH(E15&"",tbl_Production[Job Number],0))="",INDEX(tbl_Production[Qwilr Quote],MATCH(E15&"",tbl_Production[Job Number],0)),INDEX(tbl_Production[Current RMS No],MATCH(E15&"",tbl_Production[Job Number],0))),""),IF(H15="Consulting",IFERROR(INDEX(tbl_Consulting[Qwilr Quote],MATCH(E15&"",tbl_Consulting[Job Number],0)),""),"")))) | AC15: =IF(AB15="","",IF(AND(LEFT(AB15,4)<>"http",IF(H15="Production",set_RMSBase,set_QwilrBase)=""),"",HYPERLINK(IF(LEFT(AB15,4)="http",AB15,IF(H15="Production",set_RMSBase,set_QwilrBase)&AB15),"Open"))) | AD15: =IF(E15="","",IF(H15="Production",IFERROR(INDEX(tbl_Production[Total Expense],MATCH(E15&"",tbl_Production[Job Number],0)),0),IF(H15="Consulting",IFERROR(INDEX(tbl_Consulting[Total Expense],MATCH(E15&"",tbl_Consulting[Job Number],0)),0),0))) | AE15: =IF(E15="","",Y15-N(AD15)) | AF15: =IFERROR(AE15/Y15,"") | AG15: =IF(E15="","",IF(H15="Onsite",IFERROR(INDEX(tbl_Onsite[Notes],MATCH(E15&"",tbl_Onsite[Job Number],0)),""),IF(H15="Production",IFERROR(INDEX(tbl_Production[Notes],MATCH(E15&"",tbl_Production[Job Number],0)),""),IF(H15="Consulting",IFERROR(INDEX(tbl_Consulting[Notes],MATCH(E15&"",tbl_Consulting[Job Number],0)),""),""))))
A16: 46234 | B16: =IF(A16="","",EOMONTH(A16,0)) | C16: INV-10537 | D16: PWC | F16: =IF(E16="","",IF(COUNTIF(lst_Jobs,E16&"")>0,"OK","CHECK")) | G16: PWC Dedicated Tech 29/07/2026 | H16: Onsite | I16: ONSITE | J16: Contract | K16: GST 10% | L16: 340 | M16: =IF(L16="","",IF(K16="GST 10%",ROUND(L16*set_GSTRate,2),0)) | N16: =IF(L16="","",L16+M16) | O16: 41100 | P16: Y | Q16: N | T16: Invoiced | U16: 29/07/2026 4hours | V16: =IF(COUNTA(A16,D16,C16,L16)=0,"",IF(A16="","No date - sits outside every month",IF(E16="","No job number",IF(F16="CHECK","Job number is not in the Xero job list",IF(I16="","No cost centre",IF(AND(P16="Y",C16=""),"Marked posted to Xero but has no invoice number",IF(AND(L16<>"",K16=""),"No tax code",IF(AND(L16<>"",O16=""),"No revenue GL code","")))))))) | W16: =IF(E16="","",IFERROR(INDEX(lst_JobName,MATCH(E16&"",lst_Jobs,0)),"")) | X16: =IF(E16="","",COUNTIFS(tbl_Finance[Job Number],E16&"",tbl_Finance[Ex GST],"<>")) | Y16: =IF(E16="","",SUMIFS(tbl_Finance[Ex GST],tbl_Finance[Job Number],E16&"")) | Z16: =IF(E16="","",SUMIFS(tbl_Finance[Ex GST],tbl_Finance[Job Number],E16&"",tbl_Finance[Xero Invoice No],"<>")) | AA16: =IF(E16="","",Y16-Z16) | AB16: =IF(E16="","",IF(H16="Onsite",IFERROR(INDEX(tbl_Onsite[Qwilr Quote],MATCH(E16&"",tbl_Onsite[Job Number],0)),""),IF(H16="Production",IFERROR(IF(INDEX(tbl_Production[Current RMS No],MATCH(E16&"",tbl_Production[Job Number],0))="",INDEX(tbl_Production[Qwilr Quote],MATCH(E16&"",tbl_Production[Job Number],0)),INDEX(tbl_Production[Current RMS No],MATCH(E16&"",tbl_Production[Job Number],0))),""),IF(H16="Consulting",IFERROR(INDEX(tbl_Consulting[Qwilr Quote],MATCH(E16&"",tbl_Consulting[Job Number],0)),""),"")))) | AC16: =IF(AB16="","",IF(AND(LEFT(AB16,4)<>"http",IF(H16="Production",set_RMSBase,set_QwilrBase)=""),"",HYPERLINK(IF(LEFT(AB16,4)="http",AB16,IF(H16="Production",set_RMSBase,set_QwilrBase)&AB16),"Open"))) | AD16: =IF(E16="","",IF(H16="Production",IFERROR(INDEX(tbl_Production[Total Expense],MATCH(E16&"",tbl_Production[Job Number],0)),0),IF(H16="Consulting",IFERROR(INDEX(tbl_Consulting[Total Expense],MATCH(E16&"",tbl_Consulting[Job Number],0)),0),0))) | AE16: =IF(E16="","",Y16-N(AD16)) | AF16: =IFERROR(AE16/Y16,"") | AG16: =IF(E16="","",IF(H16="Onsite",IFERROR(INDEX(tbl_Onsite[Notes],MATCH(E16&"",tbl_Onsite[Job Number],0)),""),IF(H16="Production",IFERROR(INDEX(tbl_Production[Notes],MATCH(E16&"",tbl_Production[Job Number],0)),""),IF(H16="Consulting",IFERROR(INDEX(tbl_Consulting[Notes],MATCH(E16&"",tbl_Consulting[Job Number],0)),""),""))))
A17: 46234 | B17: =IF(A17="","",EOMONTH(A17,0)) | C17: INV-10541 | D17: APN | E17: 3056 | F17: =IF(E17="","",IF(COUNTIF(lst_Jobs,E17&"")>0,"OK","CHECK")) | G17: APN Tech Support July 22 & 24 | H17: Onsite | I17: ONSITE | J17: Contract | K17: GST 10% | L17: 680 | M17: =IF(L17="","",IF(K17="GST 10%",ROUND(L17*set_GSTRate,2),0)) | N17: =IF(L17="","",L17+M17) | O17: 41100 | P17: Y | Q17: N | T17: Invoiced | V17: =IF(COUNTA(A17,D17,C17,L17)=0,"",IF(A17="","No date - sits outside every month",IF(E17="","No job number",IF(F17="CHECK","Job number is not in the Xero job list",IF(I17="","No cost centre",IF(AND(P17="Y",C17=""),"Marked posted to Xero but has no invoice number",IF(AND(L17<>"",K17=""),"No tax code",IF(AND(L17<>"",O17=""),"No revenue GL code","")))))))) | W17: =IF(E17="","",IFERROR(INDEX(lst_JobName,MATCH(E17&"",lst_Jobs,0)),"")) | X17: =IF(E17="","",COUNTIFS(tbl_Finance[Job Number],E17&"",tbl_Finance[Ex GST],"<>")) | Y17: =IF(E17="","",SUMIFS(tbl_Finance[Ex GST],tbl_Finance[Job Number],E17&"")) | Z17: =IF(E17="","",SUMIFS(tbl_Finance[Ex GST],tbl_Finance[Job Number],E17&"",tbl_Finance[Xero Invoice No],"<>")) | AA17: =IF(E17="","",Y17-Z17) | AB17: =IF(E17="","",IF(H17="Onsite",IFERROR(INDEX(tbl_Onsite[Qwilr Quote],MATCH(E17&"",tbl_Onsite[Job Number],0)),""),IF(H17="Production",IFERROR(IF(INDEX(tbl_Production[Current RMS No],MATCH(E17&"",tbl_Production[Job Number],0))="",INDEX(tbl_Production[Qwilr Quote],MATCH(E17&"",tbl_Production[Job Number],0)),INDEX(tbl_Production[Current RMS No],MATCH(E17&"",tbl_Production[Job Number],0))),""),IF(H17="Consulting",IFERROR(INDEX(tbl_Consulting[Qwilr Quote],MATCH(E17&"",tbl_Consulting[Job Number],0)),""),"")))) | AC17: =IF(AB17="","",IF(AND(LEFT(AB17,4)<>"http",IF(H17="Production",set_RMSBase,set_QwilrBase)=""),"",HYPERLINK(IF(LEFT(AB17,4)="http",AB17,IF(H17="Production",set_RMSBase,set_QwilrBase)&AB17),"Open"))) | AD17: =IF(E17="","",IF(H17="Production",IFERROR(INDEX(tbl_Production[Total Expense],MATCH(E17&"",tbl_Production[Job Number],0)),0),IF(H17="Consulting",IFERROR(INDEX(tbl_Consulting[Total Expense],MATCH(E17&"",tbl_Consulting[Job Number],0)),0),0))) | AE17: =IF(E17="","",Y17-N(AD17)) | AF17: =IFERROR(AE17/Y17,"") | AG17: =IF(E17="","",IF(H17="Onsite",IFERROR(INDEX(tbl_Onsite[Notes],MATCH(E17&"",tbl_Onsite[Job Number],0)),""),IF(H17="Production",IFERROR(INDEX(tbl_Production[Notes],MATCH(E17&"",tbl_Production[Job Number],0)),""),IF(H17="Consulting",IFERROR(INDEX(tbl_Consulting[Notes],MATCH(E17&"",tbl_Consulting[Job Number],0)),""),""))))
A18: 46234 | B18: =IF(A18="","",EOMONTH(A18,0)) | C18: INV-10539 | D18: PWC | E18: 20250731 | F18: =IF(E18="","",IF(COUNTIF(lst_Jobs,E18&"")>0,"OK","CHECK")) | G18: PWC Pool of Hours (50 hours) | H18: Onsite | I18: ONSITE | J18: Contract | K18: GST 10% | L18: 4250 | M18: =IF(L18="","",IF(K18="GST 10%",ROUND(L18*set_GSTRate,2),0)) | N18: =IF(L18="","",L18+M18) | O18: 41100 | P18: Y | Q18: N | T18: Invoiced | U18: PO2601703215 | V18: =IF(COUNTA(A18,D18,C18,L18)=0,"",IF(A18="","No date - sits outside every month",IF(E18="","No job number",IF(F18="CHECK","Job number is not in the Xero job list",IF(I18="","No cost centre",IF(AND(P18="Y",C18=""),"Marked posted to Xero but has no invoice number",IF(AND(L18<>"",K18=""),"No tax code",IF(AND(L18<>"",O18=""),"No revenue GL code","")))))))) | W18: =IF(E18="","",IFERROR(INDEX(lst_JobName,MATCH(E18&"",lst_Jobs,0)),"")) | X18: =IF(E18="","",COUNTIFS(tbl_Finance[Job Number],E18&"",tbl_Finance[Ex GST],"<>")) | Y18: =IF(E18="","",SUMIFS(tbl_Finance[Ex GST],tbl_Finance[Job Number],E18&"")) | Z18: =IF(E18="","",SUMIFS(tbl_Finance[Ex GST],tbl_Finance[Job Number],E18&"",tbl_Finance[Xero Invoice No],"<>")) | AA18: =IF(E18="","",Y18-Z18) | AB18: =IF(E18="","",IF(H18="Onsite",IFERROR(INDEX(tbl_Onsite[Qwilr Quote],MATCH(E18&"",tbl_Onsite[Job Number],0)),""),IF(H18="Production",IFERROR(IF(INDEX(tbl_Production[Current RMS No],MATCH(E18&"",tbl_Production[Job Number],0))="",INDEX(tbl_Production[Qwilr Quote],MATCH(E18&"",tbl_Production[Job Number],0)),INDEX(tbl_Production[Current RMS No],MATCH(E18&"",tbl_Production[Job Number],0))),""),IF(H18="Consulting",IFERROR(INDEX(tbl_Consulting[Qwilr Quote],MATCH(E18&"",tbl_Consulting[Job Number],0)),""),"")))) | AC18: =IF(AB18="","",IF(AND(LEFT(AB18,4)<>"http",IF(H18="Production",set_RMSBase,set_QwilrBase)=""),"",HYPERLINK(IF(LEFT(AB18,4)="http",AB18,IF(H18="Production",set_RMSBase,set_QwilrBase)&AB18),"Open"))) | AD18: =IF(E18="","",IF(H18="Production",IFERROR(INDEX(tbl_Production[Total Expense],MATCH(E18&"",tbl_Production[Job Number],0)),0),IF(H18="Consulting",IFERROR(INDEX(tbl_Consulting[Total Expense],MATCH(E18&"",tbl_Consulting[Job Number],0)),0),0))) | AE18: =IF(E18="","",Y18-N(AD18)) | AF18: =IFERROR(AE18/Y18,"") | AG18: =IF(E18="","",IF(H18="Onsite",IFERROR(INDEX(tbl_Onsite[Notes],MATCH(E18&"",tbl_Onsite[Job Number],0)),""),IF(H18="Production",IFERROR(INDEX(tbl_Production[Notes],MATCH(E18&"",tbl_Production[Job Number],0)),""),IF(H18="Consulting",IFERROR(INDEX(tbl_Consulting[Notes],MATCH(E18&"",tbl_Consulting[Job Number],0)),""),""))))
A19: 46234 | B19: =IF(A19="","",EOMONTH(A19,0)) | C19: INV-10542 | D19: CBA | E19: 1668 | F19: =IF(E19="","",IF(COUNTIF(lst_Jobs,E19&"")>0,"OK","CHECK")) | G19: AH Support 02/07/2026 | H19: Onsite | I19: ONSITE | J19: Contract | K19: GST 10% | L19: 180 | M19: =IF(L19="","",IF(K19="GST 10%",ROUND(L19*set_GSTRate,2),0)) | N19: =IF(L19="","",L19+M19) | O19: 41100 | P19: Y | Q19: N | T19: Invoiced | V19: =IF(COUNTA(A19,D19,C19,L19)=0,"",IF(A19="","No date - sits outside every month",IF(E19="","No job number",IF(F19="CHECK","Job number is not in the Xero job list",IF(I19="","No cost centre",IF(AND(P19="Y",C19=""),"Marked posted to Xero but has no invoice number",IF(AND(L19<>"",K19=""),"No tax code",IF(AND(L19<>"",O19=""),"No revenue GL code","")))))))) | W19: =IF(E19="","",IFERROR(INDEX(lst_JobName,MATCH(E19&"",lst_Jobs,0)),"")) | X19: =IF(E19="","",COUNTIFS(tbl_Finance[Job Number],E19&"",tbl_Finance[Ex GST],"<>")) | Y19: =IF(E19="","",SUMIFS(tbl_Finance[Ex GST],tbl_Finance[Job Number],E19&"")) | Z19: =IF(E19="","",SUMIFS(tbl_Finance[Ex GST],tbl_Finance[Job Number],E19&"",tbl_Finance[Xero Invoice No],"<>")) | AA19: =IF(E19="","",Y19-Z19) | AB19: =IF(E19="","",IF(H19="Onsite",IFERROR(INDEX(tbl_Onsite[Qwilr Quote],MATCH(E19&"",tbl_Onsite[Job Number],0)),""),IF(H19="Production",IFERROR(IF(INDEX(tbl_Production[Current RMS No],MATCH(E19&"",tbl_Production[Job Number],0))="",INDEX(tbl_Production[Qwilr Quote],MATCH(E19&"",tbl_Production[Job Number],0)),INDEX(tbl_Production[Current RMS No],MATCH(E19&"",tbl_Production[Job Number],0))),""),IF(H19="Consulting",IFERROR(INDEX(tbl_Consulting[Qwilr Quote],MATCH(E19&"",tbl_Consulting[Job Number],0)),""),"")))) | AC19: =IF(AB19="","",IF(AND(LEFT(AB19,4)<>"http",IF(H19="Production",set_RMSBase,set_QwilrBase)=""),"",HYPERLINK(IF(LEFT(AB19,4)="http",AB19,IF(H19="Production",set_RMSBase,set_QwilrBase)&AB19),"Open"))) | AD19: =IF(E19="","",IF(H19="Production",IFERROR(INDEX(tbl_Production[Total Expense],MATCH(E19&"",tbl_Production[Job Number],0)),0),IF(H19="Consulting",IFERROR(INDEX(tbl_Consulting[Total Expense],MATCH(E19&"",tbl_Consulting[Job Number],0)),0),0))) | AE19: =IF(E19="","",Y19-N(AD19)) | AF19: =IFERROR(AE19/Y19,"") | AG19: =IF(E19="","",IF(H19="Onsite",IFERROR(INDEX(tbl_Onsite[Notes],MATCH(E19&"",tbl_Onsite[Job Number],0)),""),IF(H19="Production",IFERROR(INDEX(tbl_Production[Notes],MATCH(E19&"",tbl_Production[Job Number],0)),""),IF(H19="Consulting",IFERROR(INDEX(tbl_Consulting[Notes],MATCH(E19&"",tbl_Consulting[Job Number],0)),""),""))))
A20: 46234 | B20: =IF(A20="","",EOMONTH(A20,0)) | C20: INV-10543 | D20: CBA | E20: 1668 | F20: =IF(E20="","",IF(COUNTIF(lst_Jobs,E20&"")>0,"OK","CHECK")) | G20: DT Support 02/07/2026 | H20: Onsite | I20: ONSITE | J20: Contract | K20: GST 10% | L20: 425 | M20: =IF(L20="","",IF(K20="GST 10%",ROUND(L20*set_GSTRate,2),0)) | N20: =IF(L20="","",L20+M20) | O20: 41100 | P20: Y | Q20: N | T20: Invoiced | V20: =IF(COUNTA(A20,D20,C20,L20)=0,"",IF(A20="","No date - sits outside every month",IF(E20="","No job number",IF(F20="CHECK","Job number is not in the Xero job list",IF(I20="","No cost centre",IF(AND(P20="Y",C20=""),"Marked posted to Xero but has no invoice number",IF(AND(L20<>"",K20=""),"No tax code",IF(AND(L20<>"",O20=""),"No revenue GL code","")))))))) | W20: =IF(E20="","",IFERROR(INDEX(lst_JobName,MATCH(E20&"",lst_Jobs,0)),"")) | X20: =IF(E20="","",COUNTIFS(tbl_Finance[Job Number],E20&"",tbl_Finance[Ex GST],"<>")) | Y20: =IF(E20="","",SUMIFS(tbl_Finance[Ex GST],tbl_Finance[Job Number],E20&"")) | Z20: =IF(E20="","",SUMIFS(tbl_Finance[Ex GST],tbl_Finance[Job Number],E20&"",tbl_Finance[Xero Invoice No],"<>")) | AA20: =IF(E20="","",Y20-Z20) | AB20: =IF(E20="","",IF(H20="Onsite",IFERROR(INDEX(tbl_Onsite[Qwilr Quote],MATCH(E20&"",tbl_Onsite[Job Number],0)),""),IF(H20="Production",IFERROR(IF(INDEX(tbl_Production[Current RMS No],MATCH(E20&"",tbl_Production[Job Number],0))="",INDEX(tbl_Production[Qwilr Quote],MATCH(E20&"",tbl_Production[Job Number],0)),INDEX(tbl_Production[Current RMS No],MATCH(E20&"",tbl_Production[Job Number],0))),""),IF(H20="Consulting",IFERROR(INDEX(tbl_Consulting[Qwilr Quote],MATCH(E20&"",tbl_Consulting[Job Number],0)),""),"")))) | AC20: =IF(AB20="","",IF(AND(LEFT(AB20,4)<>"http",IF(H20="Production",set_RMSBase,set_QwilrBase)=""),"",HYPERLINK(IF(LEFT(AB20,4)="http",AB20,IF(H20="Production",set_RMSBase,set_QwilrBase)&AB20),"Open"))) | AD20: =IF(E20="","",IF(H20="Production",IFERROR(INDEX(tbl_Production[Total Expense],MATCH(E20&"",tbl_Production[Job Number],0)),0),IF(H20="Consulting",IFERROR(INDEX(tbl_Consulting[Total Expense],MATCH(E20&"",tbl_Consulting[Job Number],0)),0),0))) | AE20: =IF(E20="","",Y20-N(AD20)) | AF20: =IFERROR(AE20/Y20,"") | AG20: =IF(E20="","",IF(H20="Onsite",IFERROR(INDEX(tbl_Onsite[Notes],MATCH(E20&"",tbl_Onsite[Job Number],0)),""),IF(H20="Production",IFERROR(INDEX(tbl_Production[Notes],MATCH(E20&"",tbl_Production[Job Number],0)),""),IF(H20="Consulting",IFERROR(INDEX(tbl_Consulting[Notes],MATCH(E20&"",tbl_Consulting[Job Number],0)),""),""))))
A21: 46234 | B21: =IF(A21="","",EOMONTH(A21,0)) | C21: INV-10544 | D21: CBA | E21: 1668 | F21: =IF(E21="","",IF(COUNTIF(lst_Jobs,E21&"")>0,"OK","CHECK")) | G21: DT Support 23/07/2026 | H21: Onsite | I21: ONSITE | J21: Contract | K21: GST 10% | L21: 510 | M21: =IF(L21="","",IF(K21="GST 10%",ROUND(L21*set_GSTRate,2),0)) | N21: =IF(L21="","",L21+M21) | O21: 41100 | P21: Y | Q21: N | T21: Invoiced | V21: =IF(COUNTA(A21,D21,C21,L21)=0,"",IF(A21="","No date - sits outside every month",IF(E21="","No job number",IF(F21="CHECK","Job number is not in the Xero job list",IF(I21="","No cost centre",IF(AND(P21="Y",C21=""),"Marked posted to Xero but has no invoice number",IF(AND(L21<>"",K21=""),"No tax code",IF(AND(L21<>"",O21=""),"No revenue GL code","")))))))) | W21: =IF(E21="","",IFERROR(INDEX(lst_JobName,MATCH(E21&"",lst_Jobs,0)),"")) | X21: =IF(E21="","",COUNTIFS(tbl_Finance[Job Number],E21&"",tbl_Finance[Ex GST],"<>")) | Y21: =IF(E21="","",SUMIFS(tbl_Finance[Ex GST],tbl_Finance[Job Number],E21&"")) | Z21: =IF(E21="","",SUMIFS(tbl_Finance[Ex GST],tbl_Finance[Job Number],E21&"",tbl_Finance[Xero Invoice No],"<>")) | AA21: =IF(E21="","",Y21-Z21) | AB21: =IF(E21="","",IF(H21="Onsite",IFERROR(INDEX(tbl_Onsite[Qwilr Quote],MATCH(E21&"",tbl_Onsite[Job Number],0)),""),IF(H21="Production",IFERROR(IF(INDEX(tbl_Production[Current RMS No],MATCH(E21&"",tbl_Production[Job Number],0))="",INDEX(tbl_Production[Qwilr Quote],MATCH(E21&"",tbl_Production[Job Number],0)),INDEX(tbl_Production[Current RMS No],MATCH(E21&"",tbl_Production[Job Number],0))),""),IF(H21="Consulting",IFERROR(INDEX(tbl_Consulting[Qwilr Quote],MATCH(E21&"",tbl_Consulting[Job Number],0)),""),"")))) | AC21: =IF(AB21="","",IF(AND(LEFT(AB21,4)<>"http",IF(H21="Production",set_RMSBase,set_QwilrBase)=""),"",HYPERLINK(IF(LEFT(AB21,4)="http",AB21,IF(H21="Production",set_RMSBase,set_QwilrBase)&AB21),"Open"))) | AD21: =IF(E21="","",IF(H21="Production",IFERROR(INDEX(tbl_Production[Total Expense],MATCH(E21&"",tbl_Production[Job Number],0)),0),IF(H21="Consulting",IFERROR(INDEX(tbl_Consulting[Total Expense],MATCH(E21&"",tbl_Consulting[Job Number],0)),0),0))) | AE21: =IF(E21="","",Y21-N(AD21)) | AF21: =IFERROR(AE21/Y21,"") | AG21: =IF(E21="","",IF(H21="Onsite",IFERROR(INDEX(tbl_Onsite[Notes],MATCH(E21&"",tbl_Onsite[Job Number],0)),""),IF(H21="Production",IFERROR(INDEX(tbl_Production[Notes],MATCH(E21&"",tbl_Production[Job Number],0)),""),IF(H21="Consulting",IFERROR(INDEX(tbl_Consulting[Notes],MATCH(E21&"",tbl_Consulting[Job Number],0)),""),""))))
A22: 46233 | B22: =IF(A22="","",EOMONTH(A22,0)) | C22: INV-10545 | D22: PWC | E22: 2540 | F22: =IF(E22="","",IF(COUNTIF(lst_Jobs,E22&"")>0,"OK","CHECK")) | G22: PWC Dedicated Tech 30/07/2026 | H22: Onsite | I22: ONSITE | J22: Contract | K22: GST 10% | L22: 340 | M22: =IF(L22="","",IF(K22="GST 10%",ROUND(L22*set_GSTRate,2),0)) | N22: =IF(L22="","",L22+M22) | O22: 41100 | P22: Y | Q22: N | T22: Invoiced | U22: PO2601703274 | V22: =IF(COUNTA(A22,D22,C22,L22)=0,"",IF(A22="","No date - sits outside every month",IF(E22="","No job number",IF(F22="CHECK","Job number is not in the Xero job list",IF(I22="","No cost centre",IF(AND(P22="Y",C22=""),"Marked posted to Xero but has no invoice number",IF(AND(L22<>"",K22=""),"No tax code",IF(AND(L22<>"",O22=""),"No revenue GL code","")))))))) | W22: =IF(E22="","",IFERROR(INDEX(lst_JobName,MATCH(E22&"",lst_Jobs,0)),"")) | X22: =IF(E22="","",COUNTIFS(tbl_Finance[Job Number],E22&"",tbl_Finance[Ex GST],"<>")) | Y22: =IF(E22="","",SUMIFS(tbl_Finance[Ex GST],tbl_Finance[Job Number],E22&"")) | Z22: =IF(E22="","",SUMIFS(tbl_Finance[Ex GST],tbl_Finance[Job Number],E22&"",tbl_Finance[Xero Invoice No],"<>")) | AA22: =IF(E22="","",Y22-Z22) | AB22: =IF(E22="","",IF(H22="Onsite",IFERROR(INDEX(tbl_Onsite[Qwilr Quote],MATCH(E22&"",tbl_Onsite[Job Number],0)),""),IF(H22="Production",IFERROR(IF(INDEX(tbl_Production[Current RMS No],MATCH(E22&"",tbl_Production[Job Number],0))="",INDEX(tbl_Production[Qwilr Quote],MATCH(E22&"",tbl_Production[Job Number],0)),INDEX(tbl_Production[Current RMS No],MATCH(E22&"",tbl_Production[Job Number],0))),""),IF(H22="Consulting",IFERROR(INDEX(tbl_Consulting[Qwilr Quote],MATCH(E22&"",tbl_Consulting[Job Number],0)),""),"")))) | AC22: =IF(AB22="","",IF(AND(LEFT(AB22,4)<>"http",IF(H22="Production",set_RMSBase,set_QwilrBase)=""),"",HYPERLINK(IF(LEFT(AB22,4)="http",AB22,IF(H22="Production",set_RMSBase,set_QwilrBase)&AB22),"Open"))) | AD22: =IF(E22="","",IF(H22="Production",IFERROR(INDEX(tbl_Production[Total Expense],MATCH(E22&"",tbl_Production[Job Number],0)),0),IF(H22="Consulting",IFERROR(INDEX(tbl_Consulting[Total Expense],MATCH(E22&"",tbl_Consulting[Job Number],0)),0),0))) | AE22: =IF(E22="","",Y22-N(AD22)) | AF22: =IFERROR(AE22/Y22,"") | AG22: =IF(E22="","",IF(H22="Onsite",IFERROR(INDEX(tbl_Onsite[Notes],MATCH(E22&"",tbl_Onsite[Job Number],0)),""),IF(H22="Production",IFERROR(INDEX(tbl_Production[Notes],MATCH(E22&"",tbl_Production[Job Number],0)),""),IF(H22="Consulting",IFERROR(INDEX(tbl_Consulting[Notes],MATCH(E22&"",tbl_Consulting[Job Number],0)),""),""))))
A23: 46233 | B23: =IF(A23="","",EOMONTH(A23,0)) | C23: INV-10546 | D23: DTTL | E23: 26062501/2347 | F23: =IF(E23="","",IF(COUNTIF(lst_Jobs,E23&"")>0,"OK","CHECK")) | G23: DH Travel 06-07/07 & Ad-hoc Tech Support 30/07 & Market Shapers | H23: Onsite | I23: ONSITE | J23: Contract | K23: GST 10% | L23: 1672.5 | M23: =IF(L23="","",IF(K23="GST 10%",ROUND(L23*set_GSTRate,2),0)) | N23: =IF(L23="","",L23+M23) | O23: 41100 | P23: Y | Q23: N | T23: Invoiced | V23: =IF(COUNTA(A23,D23,C23,L23)=0,"",IF(A23="","No date - sits outside every month",IF(E23="","No job number",IF(F23="CHECK","Job number is not in the Xero job list",IF(I23="","No cost centre",IF(AND(P23="Y",C23=""),"Marked posted to Xero but has no invoice number",IF(AND(L23<>"",K23=""),"No tax code",IF(AND(L23<>"",O23=""),"No revenue GL code","")))))))) | W23: =IF(E23="","",IFERROR(INDEX(lst_JobName,MATCH(E23&"",lst_Jobs,0)),"")) | X23: =IF(E23="","",COUNTIFS(tbl_Finance[Job Number],E23&"",tbl_Finance[Ex GST],"<>")) | Y23: =IF(E23="","",SUMIFS(tbl_Finance[Ex GST],tbl_Finance[Job Number],E23&"")) | Z23: =IF(E23="","",SUMIFS(tbl_Finance[Ex GST],tbl_Finance[Job Number],E23&"",tbl_Finance[Xero Invoice No],"<>")) | AA23: =IF(E23="","",Y23-Z23) | AB23: =IF(E23="","",IF(H23="Onsite",IFERROR(INDEX(tbl_Onsite[Qwilr Quote],MATCH(E23&"",tbl_Onsite[Job Number],0)),""),IF(H23="Production",IFERROR(IF(INDEX(tbl_Production[Current RMS No],MATCH(E23&"",tbl_Production[Job Number],0))="",INDEX(tbl_Production[Qwilr Quote],MATCH(E23&"",tbl_Production[Job Number],0)),INDEX(tbl_Production[Current RMS No],MATCH(E23&"",tbl_Production[Job Number],0))),""),IF(H23="Consulting",IFERROR(INDEX(tbl_Consulting[Qwilr Quote],MATCH(E23&"",tbl_Consulting[Job Number],0)),""),"")))) | AC23: =IF(AB23="","",IF(AND(LEFT(AB23,4)<>"http",IF(H23="Production",set_RMSBase,set_QwilrBase)=""),"",HYPERLINK(IF(LEFT(AB23,4)="http",AB23,IF(H23="Production",set_RMSBase,set_QwilrBase)&AB23),"Open"))) | AD23: =IF(E23="","",IF(H23="Production",IFERROR(INDEX(tbl_Production[Total Expense],MATCH(E23&"",tbl_Production[Job Number],0)),0),IF(H23="Consulting",IFERROR(INDEX(tbl_Consulting[Total Expense],MATCH(E23&"",tbl_Consulting[Job Number],0)),0),0))) | AE23: =IF(E23="","",Y23-N(AD23)) | AF23: =IFERROR(AE23/Y23,"") | AG23: =IF(E23="","",IF(H23="Onsite",IFERROR(INDEX(tbl_Onsite[Notes],MATCH(E23&"",tbl_Onsite[Job Number],0)),""),IF(H23="Production",IFERROR(INDEX(tbl_Production[Notes],MATCH(E23&"",tbl_Production[Job Number],0)),""),IF(H23="Consulting",IFERROR(INDEX(tbl_Consulting[Notes],MATCH(E23&"",tbl_Consulting[Job Number],0)),""),""))))
A24: 46233 | B24: =IF(A24="","",EOMONTH(A24,0)) | C24: INV-10550 | D24: APN | E24: 2026021101 | F24: =IF(E24="","",IF(COUNTIF(lst_Jobs,E24&"")>0,"OK","CHECK")) | G24: APN Quarterly AV Support | H24: Onsite | I24: ONSITE | J24: Contract | K24: GST 10% | L24: 1670 | M24: =IF(L24="","",IF(K24="GST 10%",ROUND(L24*set_GSTRate,2),0)) | N24: =IF(L24="","",L24+M24) | O24: 41100 | P24: Y | Q24: N | T24: Invoiced | U24: Invoice 1/2 | V24: =IF(COUNTA(A24,D24,C24,L24)=0,"",IF(A24="","No date - sits outside every month",IF(E24="","No job number",IF(F24="CHECK","Job number is not in the Xero job list",IF(I24="","No cost centre",IF(AND(P24="Y",C24=""),"Marked posted to Xero but has no invoice number",IF(AND(L24<>"",K24=""),"No tax code",IF(AND(L24<>"",O24=""),"No revenue GL code","")))))))) | W24: =IF(E24="","",IFERROR(INDEX(lst_JobName,MATCH(E24&"",lst_Jobs,0)),"")) | X24: =IF(E24="","",COUNTIFS(tbl_Finance[Job Number],E24&"",tbl_Finance[Ex GST],"<>")) | Y24: =IF(E24="","",SUMIFS(tbl_Finance[Ex GST],tbl_Finance[Job Number],E24&"")) | Z24: =IF(E24="","",SUMIFS(tbl_Finance[Ex GST],tbl_Finance[Job Number],E24&"",tbl_Finance[Xero Invoice No],"<>")) | AA24: =IF(E24="","",Y24-Z24) | AB24: =IF(E24="","",IF(H24="Onsite",IFERROR(INDEX(tbl_Onsite[Qwilr Quote],MATCH(E24&"",tbl_Onsite[Job Number],0)),""),IF(H24="Production",IFERROR(IF(INDEX(tbl_Production[Current RMS No],MATCH(E24&"",tbl_Production[Job Number],0))="",INDEX(tbl_Production[Qwilr Quote],MATCH(E24&"",tbl_Production[Job Number],0)),INDEX(tbl_Production[Current RMS No],MATCH(E24&"",tbl_Production[Job Number],0))),""),IF(H24="Consulting",IFERROR(INDEX(tbl_Consulting[Qwilr Quote],MATCH(E24&"",tbl_Consulting[Job Number],0)),""),"")))) | AC24: =IF(AB24="","",IF(AND(LEFT(AB24,4)<>"http",IF(H24="Production",set_RMSBase,set_QwilrBase)=""),"",HYPERLINK(IF(LEFT(AB24,4)="http",AB24,IF(H24="Production",set_RMSBase,set_QwilrBase)&AB24),"Open"))) | AD24: =IF(E24="","",IF(H24="Production",IFERROR(INDEX(tbl_Production[Total Expense],MATCH(E24&"",tbl_Production[Job Number],0)),0),IF(H24="Consulting",IFERROR(INDEX(tbl_Consulting[Total Expense],MATCH(E24&"",tbl_Consulting[Job Number],0)),0),0))) | AE24: =IF(E24="","",Y24-N(AD24)) | AF24: =IFERROR(AE24/Y24,"") | AG24: =IF(E24="","",IF(H24="Onsite",IFERROR(INDEX(tbl_Onsite[Notes],MATCH(E24&"",tbl_Onsite[Job Number],0)),""),IF(H24="Production",IFERROR(INDEX(tbl_Production[Notes],MATCH(E24&"",tbl_Production[Job Number],0)),""),IF(H24="Consulting",IFERROR(INDEX(tbl_Consulting[Notes],MATCH(E24&"",tbl_Consulting[Job Number],0)),""),""))))
A25: 46234 | B25: =IF(A25="","",EOMONTH(A25,0)) | C25: INV-10551 | D25: Aware Super | E25: 26022301 | F25: =IF(E25="","",IF(COUNTIF(lst_Jobs,E25&"")>0,"OK","CHECK")) | G25: Aware Super Contract July 2026 | H25: Onsite | I25: ONSITE | J25: Contract | K25: GST 10% | L25: 11000 | M25: =IF(L25="","",IF(K25="GST 10%",ROUND(L25*set_GSTRate,2),0)) | N25: =IF(L25="","",L25+M25) | O25: 41100 | P25: Y | Q25: N | T25: Invoiced | V25: =IF(COUNTA(A25,D25,C25,L25)=0,"",IF(A25="","No date - sits outside every month",IF(E25="","No job number",IF(F25="CHECK","Job number is not in the Xero job list",IF(I25="","No cost centre",IF(AND(P25="Y",C25=""),"Marked posted to Xero but has no invoice number",IF(AND(L25<>"",K25=""),"No tax code",IF(AND(L25<>"",O25=""),"No revenue GL code","")))))))) | W25: =IF(E25="","",IFERROR(INDEX(lst_JobName,MATCH(E25&"",lst_Jobs,0)),"")) | X25: =IF(E25="","",COUNTIFS(tbl_Finance[Job Number],E25&"",tbl_Finance[Ex GST],"<>")) | Y25: =IF(E25="","",SUMIFS(tbl_Finance[Ex GST],tbl_Finance[Job Number],E25&"")) | Z25: =IF(E25="","",SUMIFS(tbl_Finance[Ex GST],tbl_Finance[Job Number],E25&"",tbl_Finance[Xero Invoice No],"<>")) | AA25: =IF(E25="","",Y25-Z25) | AB25: =IF(E25="","",IF(H25="Onsite",IFERROR(INDEX(tbl_Onsite[Qwilr Quote],MATCH(E25&"",tbl_Onsite[Job Number],0)),""),IF(H25="Production",IFERROR(IF(INDEX(tbl_Production[Current RMS No],MATCH(E25&"",tbl_Production[Job Number],0))="",INDEX(tbl_Production[Qwilr Quote],MATCH(E25&"",tbl_Production[Job Number],0)),INDEX(tbl_Production[Current RMS No],MATCH(E25&"",tbl_Production[Job Number],0))),""),IF(H25="Consulting",IFERROR(INDEX(tbl_Consulting[Qwilr Quote],MATCH(E25&"",tbl_Consulting[Job Number],0)),""),"")))) | AC25: =IF(AB25="","",IF(AND(LEFT(AB25,4)<>"http",IF(H25="Production",set_RMSBase,set_QwilrBase)=""),"",HYPERLINK(IF(LEFT(AB25,4)="http",AB25,IF(H25="Production",set_RMSBase,set_QwilrBase)&AB25),"Open"))) | AD25: =IF(E25="","",IF(H25="Production",IFERROR(INDEX(tbl_Production[Total Expense],MATCH(E25&"",tbl_Production[Job Number],0)),0),IF(H25="Consulting",IFERROR(INDEX(tbl_Consulting[Total Expense],MATCH(E25&"",tbl_Consulting[Job Number],0)),0),0))) | AE25: =IF(E25="","",Y25-N(AD25)) | AF25: =IFERROR(AE25/Y25,"") | AG25: =IF(E25="","",IF(H25="Onsite",IFERROR(INDEX(tbl_Onsite[Notes],MATCH(E25&"",tbl_Onsite[Job Number],0)),""),IF(H25="Production",IFERROR(INDEX(tbl_Production[Notes],MATCH(E25&"",tbl_Production[Job Number],0)),""),IF(H25="Consulting",IFERROR(INDEX(tbl_Consulting[Notes],MATCH(E25&"",tbl_Consulting[Job Number],0)),""),""))))
A26: 46265 | B26: =IF(A26="","",EOMONTH(A26,0)) | C26: INV-10597 | D26: DTTL | E26: 2608502 | F26: =IF(E26="","",IF(COUNTIF(lst_Jobs,E26&"")>0,"OK","CHECK")) | G26: DTTL Additionals August 2026 | H26: Onsite | I26: ONSITE | J26: Contract | K26: GST 10% | L26: 1275 | M26: =IF(L26="","",IF(K26="GST 10%",ROUND(L26*set_GSTRate,2),0)) | N26: =IF(L26="","",L26+M26) | O26: 41100 | P26: Y | Q26: N | T26: Invoiced | U26: 8419.62 differe from invoice amount | V26: =IF(COUNTA(A26,D26,C26,L26)=0,"",IF(A26="","No date - sits outside every month",IF(E26="","No job number",IF(F26="CHECK","Job number is not in the Xero job list",IF(I26="","No cost centre",IF(AND(P26="Y",C26=""),"Marked posted to Xero but has no invoice number",IF(AND(L26<>"",K26=""),"No tax code",IF(AND(L26<>"",O26=""),"No revenue GL code","")))))))) | W26: =IF(E26="","",IFERROR(INDEX(lst_JobName,MATCH(E26&"",lst_Jobs,0)),"")) | X26: =IF(E26="","",COUNTIFS(tbl_Finance[Job Number],E26&"",tbl_Finance[Ex GST],"<>")) | Y26: =IF(E26="","",SUMIFS(tbl_Finance[Ex GST],tbl_Finance[Job Number],E26&"")) | Z26: =IF(E26="","",SUMIFS(tbl_Finance[Ex GST],tbl_Finance[Job Number],E26&"",tbl_Finance[Xero Invoice No],"<>")) | AA26: =IF(E26="","",Y26-Z26) | AB26: =IF(E26="","",IF(H26="Onsite",IFERROR(INDEX(tbl_Onsite[Qwilr Quote],MATCH(E26&"",tbl_Onsite[Job Number],0)),""),IF(H26="Production",IFERROR(IF(INDEX(tbl_Production[Current RMS No],MATCH(E26&"",tbl_Production[Job Number],0))="",INDEX(tbl_Production[Qwilr Quote],MATCH(E26&"",tbl_Production[Job Number],0)),INDEX(tbl_Production[Current RMS No],MATCH(E26&"",tbl_Production[Job Number],0))),""),IF(H26="Consulting",IFERROR(INDEX(tbl_Consulting[Qwilr Quote],MATCH(E26&"",tbl_Consulting[Job Number],0)),""),"")))) | AC26: =IF(AB26="","",IF(AND(LEFT(AB26,4)<>"http",IF(H26="Production",set_RMSBase,set_QwilrBase)=""),"",HYPERLINK(IF(LEFT(AB26,4)="http",AB26,IF(H26="Production",set_RMSBase,set_QwilrBase)&AB26),"Open"))) | AD26: =IF(E26="","",IF(H26="Production",IFERROR(INDEX(tbl_Production[Total Expense],MATCH(E26&"",tbl_Production[Job Number],0)),0),IF(H26="Consulting",IFERROR(INDEX(tbl_Consulting[Total Expense],MATCH(E26&"",tbl_Consulting[Job Number],0)),0),0))) | AE26: =IF(E26="","",Y26-N(AD26)) | AF26: =IFERROR(AE26/Y26,"") | AG26: =IF(E26="","",IF(H26="Onsite",IFERROR(INDEX(tbl_Onsite[Notes],MATCH(E26&"",tbl_Onsite[Job Number],0)),""),IF(H26="Production",IFERROR(INDEX(tbl_Production[Notes],MATCH(E26&"",tbl_Production[Job Number],0)),""),IF(H26="Consulting",IFERROR(INDEX(tbl_Consulting[Notes],MATCH(E26&"",tbl_Consulting[Job Number],0)),""),""))))
A27: 46265 | B27: =IF(A27="","",EOMONTH(A27,0)) | C27: INV-10598 | D27: PWC | E27: 26073102 | F27: =IF(E27="","",IF(COUNTIF(lst_Jobs,E27&"")>0,"OK","CHECK")) | G27: Pool of Hours - National AV/IT Support | H27: Onsite | I27: ONSITE | J27: Contract | K27: GST 10% | L27: 8500 | M27: =IF(L27="","",IF(K27="GST 10%",ROUND(L27*set_GSTRate,2),0)) | N27: =IF(L27="","",L27+M27) | O27: 41100 | P27: Y | Q27: N | T27: Invoiced | V27: =IF(COUNTA(A27,D27,C27,L27)=0,"",IF(A27="","No date - sits outside every month",IF(E27="","No job number",IF(F27="CHECK","Job number is not in the Xero job list",IF(I27="","No cost centre",IF(AND(P27="Y",C27=""),"Marked posted to Xero but has no invoice number",IF(AND(L27<>"",K27=""),"No tax code",IF(AND(L27<>"",O27=""),"No revenue GL code","")))))))) | W27: =IF(E27="","",IFERROR(INDEX(lst_JobName,MATCH(E27&"",lst_Jobs,0)),"")) | X27: =IF(E27="","",COUNTIFS(tbl_Finance[Job Number],E27&"",tbl_Finance[Ex GST],"<>")) | Y27: =IF(E27="","",SUMIFS(tbl_Finance[Ex GST],tbl_Finance[Job Number],E27&"")) | Z27: =IF(E27="","",SUMIFS(tbl_Finance[Ex GST],tbl_Finance[Job Number],E27&"",tbl_Finance[Xero Invoice No],"<>")) | AA27: =IF(E27="","",Y27-Z27) | AB27: =IF(E27="","",IF(H27="Onsite",IFERROR(INDEX(tbl_Onsite[Qwilr Quote],MATCH(E27&"",tbl_Onsite[Job Number],0)),""),IF(H27="Production",IFERROR(IF(INDEX(tbl_Production[Current RMS No],MATCH(E27&"",tbl_Production[Job Number],0))="",INDEX(tbl_Production[Qwilr Quote],MATCH(E27&"",tbl_Production[Job Number],0)),INDEX(tbl_Production[Current RMS No],MATCH(E27&"",tbl_Production[Job Number],0))),""),IF(H27="Consulting",IFERROR(INDEX(tbl_Consulting[Qwilr Quote],MATCH(E27&"",tbl_Consulting[Job Number],0)),""),"")))) | AC27: =IF(AB27="","",IF(AND(LEFT(AB27,4)<>"http",IF(H27="Production",set_RMSBase,set_QwilrBase)=""),"",HYPERLINK(IF(LEFT(AB27,4)="http",AB27,IF(H27="Production",set_RMSBase,set_QwilrBase)&AB27),"Open"))) | AD27: =IF(E27="","",IF(H27="Production",IFERROR(INDEX(tbl_Production[Total Expense],MATCH(E27&"",tbl_Production[Job Number],0)),0),IF(H27="Consulting",IFERROR(INDEX(tbl_Consulting[Total Expense],MATCH(E27&"",tbl_Consulting[Job Number],0)),0),0))) | AE27: =IF(E27="","",Y27-N(AD27)) | AF27: =IFERROR(AE27/Y27,"") | AG27: =IF(E27="","",IF(H27="Onsite",IFERROR(INDEX(tbl_Onsite[Notes],MATCH(E27&"",tbl_Onsite[Job Number],0)),""),IF(H27="Production",IFERROR(INDEX(tbl_Production[Notes],MATCH(E27&"",tbl_Production[Job Number],0)),""),IF(H27="Consulting",IFERROR(INDEX(tbl_Consulting[Notes],MATCH(E27&"",tbl_Consulting[Job Number],0)),""),""))))
A28: 46265 | B28: =IF(A28="","",EOMONTH(A28,0)) | C28: INV-10565 | D28: CBA | E28: 1350 | F28: =IF(E28="","",IF(COUNTIF(lst_Jobs,E28&"")>0,"OK","CHECK")) | G28: CBA BNE August 2026 | H28: Onsite | I28: ONSITE | J28: Contract | K28: GST 10% | L28: 8022.5 | M28: =IF(L28="","",IF(K28="GST 10%",ROUND(L28*set_GSTRate,2),0)) | N28: =IF(L28="","",L28+M28) | O28: 41100 | P28: Y | Q28: N | T28: Invoiced | V28: =IF(COUNTA(A28,D28,C28,L28)=0,"",IF(A28="","No date - sits outside every month",IF(E28="","No job number",IF(F28="CHECK","Job number is not in the Xero job list",IF(I28="","No cost centre",IF(AND(P28="Y",C28=""),"Marked posted to Xero but has no invoice number",IF(AND(L28<>"",K28=""),"No tax code",IF(AND(L28<>"",O28=""),"No revenue GL code","")))))))) | W28: =IF(E28="","",IFERROR(INDEX(lst_JobName,MATCH(E28&"",lst_Jobs,0)),"")) | X28: =IF(E28="","",COUNTIFS(tbl_Finance[Job Number],E28&"",tbl_Finance[Ex GST],"<>")) | Y28: =IF(E28="","",SUMIFS(tbl_Finance[Ex GST],tbl_Finance[Job Number],E28&"")) | Z28: =IF(E28="","",SUMIFS(tbl_Finance[Ex GST],tbl_Finance[Job Number],E28&"",tbl_Finance[Xero Invoice No],"<>")) | AA28: =IF(E28="","",Y28-Z28) | AB28: =IF(E28="","",IF(H28="Onsite",IFERROR(INDEX(tbl_Onsite[Qwilr Quote],MATCH(E28&"",tbl_Onsite[Job Number],0)),""),IF(H28="Production",IFERROR(IF(INDEX(tbl_Production[Current RMS No],MATCH(E28&"",tbl_Production[Job Number],0))="",INDEX(tbl_Production[Qwilr Quote],MATCH(E28&"",tbl_Production[Job Number],0)),INDEX(tbl_Production[Current RMS No],MATCH(E28&"",tbl_Production[Job Number],0))),""),IF(H28="Consulting",IFERROR(INDEX(tbl_Consulting[Qwilr Quote],MATCH(E28&"",tbl_Consulting[Job Number],0)),""),"")))) | AC28: =IF(AB28="","",IF(AND(LEFT(AB28,4)<>"http",IF(H28="Production",set_RMSBase,set_QwilrBase)=""),"",HYPERLINK(IF(LEFT(AB28,4)="http",AB28,IF(H28="Production",set_RMSBase,set_QwilrBase)&AB28),"Open"))) | AD28: =IF(E28="","",IF(H28="Production",IFERROR(INDEX(tbl_Production[Total Expense],MATCH(E28&"",tbl_Production[Job Number],0)),0),IF(H28="Consulting",IFERROR(INDEX(tbl_Consulting[Total Expense],MATCH(E28&"",tbl_Consulting[Job Number],0)),0),0))) | AE28: =IF(E28="","",Y28-N(AD28)) | AF28: =IFERROR(AE28/Y28,"") | AG28: =IF(E28="","",IF(H28="Onsite",IFERROR(INDEX(tbl_Onsite[Notes],MATCH(E28&"",tbl_Onsite[Job Number],0)),""),IF(H28="Production",IFERROR(INDEX(tbl_Production[Notes],MATCH(E28&"",tbl_Production[Job Number],0)),""),IF(H28="Consulting",IFERROR(INDEX(tbl_Consulting[Notes],MATCH(E28&"",tbl_Consulting[Job Number],0)),""),""))))
B29: =IF(A29="","",EOMONTH(A29,0)) | D29: CBA | E29: 585/586/1755 | F29: =IF(E29="","",IF(COUNTIF(lst_Jobs,E29&"")>0,"OK","CHECK")) | G29: CBP August 2026 | H29: Onsite | I29: ONSITE | J29: Contract | K29: GST 10% | M29: =IF(L29="","",IF(K29="GST 10%",ROUND(L29*set_GSTRate,2),0)) | N29: =IF(L29="","",L29+M29) | O29: 41100 | P29: N | Q29: N | T29: To Invoice | V29: =IF(COUNTA(A29,D29,C29,L29)=0,"",IF(A29="","No date - sits outside every month",IF(E29="","No job number",IF(F29="CHECK","Job number is not in the Xero job list",IF(I29="","No cost centre",IF(AND(P29="Y",C29=""),"Marked posted to Xero but has no invoice number",IF(AND(L29<>"",K29=""),"No tax code",IF(AND(L29<>"",O29=""),"No revenue GL code","")))))))) | W29: =IF(E29="","",IFERROR(INDEX(lst_JobName,MATCH(E29&"",lst_Jobs,0)),"")) | X29: =IF(E29="","",COUNTIFS(tbl_Finance[Job Number],E29&"",tbl_Finance[Ex GST],"<>")) | Y29: =IF(E29="","",SUMIFS(tbl_Finance[Ex GST],tbl_Finance[Job Number],E29&"")) | Z29: =IF(E29="","",SUMIFS(tbl_Finance[Ex GST],tbl_Finance[Job Number],E29&"",tbl_Finance[Xero Invoice No],"<>")) | AA29: =IF(E29="","",Y29-Z29) | AB29: =IF(E29="","",IF(H29="Onsite",IFERROR(INDEX(tbl_Onsite[Qwilr Quote],MATCH(E29&"",tbl_Onsite[Job Number],0)),""),IF(H29="Production",IFERROR(IF(INDEX(tbl_Production[Current RMS No],MATCH(E29&"",tbl_Production[Job Number],0))="",INDEX(tbl_Production[Qwilr Quote],MATCH(E29&"",tbl_Production[Job Number],0)),INDEX(tbl_Production[Current RMS No],MATCH(E29&"",tbl_Production[Job Number],0))),""),IF(H29="Consulting",IFERROR(INDEX(tbl_Consulting[Qwilr Quote],MATCH(E29&"",tbl_Consulting[Job Number],0)),""),"")))) | AC29: =IF(AB29="","",IF(AND(LEFT(AB29,4)<>"http",IF(H29="Production",set_RMSBase,set_QwilrBase)=""),"",HYPERLINK(IF(LEFT(AB29,4)="http",AB29,IF(H29="Production",set_RMSBase,set_QwilrBase)&AB29),"Open"))) | AD29: =IF(E29="","",IF(H29="Production",IFERROR(INDEX(tbl_Production[Total Expense],MATCH(E29&"",tbl_Production[Job Number],0)),0),IF(H29="Consulting",IFERROR(INDEX(tbl_Consulting[Total Expense],MATCH(E29&"",tbl_Consulting[Job Number],0)),0),0))) | AE29: =IF(E29="","",Y29-N(AD29)) | AF29: =IFERROR(AE29/Y29,"") | AG29: =IF(E29="","",IF(H29="Onsite",IFERROR(INDEX(tbl_Onsite[Notes],MATCH(E29&"",tbl_Onsite[Job Number],0)),""),IF(H29="Production",IFERROR(INDEX(tbl_Production[Notes],MATCH(E29&"",tbl_Production[Job Number],0)),""),IF(H29="Consulting",IFERROR(INDEX(tbl_Consulting[Notes],MATCH(E29&"",tbl_Consulting[Job Number],0)),""),""))))
B30: =IF(A30="","",EOMONTH(A30,0)) | D30: CBA | E30: 587 | F30: =IF(E30="","",IF(COUNTIF(lst_Jobs,E30&"")>0,"OK","CHECK")) | G30: CBS August 2026 | H30: Onsite | I30: ONSITE | J30: Contract | K30: GST 10% | M30: =IF(L30="","",IF(K30="GST 10%",ROUND(L30*set_GSTRate,2),0)) | N30: =IF(L30="","",L30+M30) | O30: 41100 | P30: N | Q30: N | T30: To Invoice | V30: =IF(COUNTA(A30,D30,C30,L30)=0,"",IF(A30="","No date - sits outside every month",IF(E30="","No job number",IF(F30="CHECK","Job number is not in the Xero job list",IF(I30="","No cost centre",IF(AND(P30="Y",C30=""),"Marked posted to Xero but has no invoice number",IF(AND(L30<>"",K30=""),"No tax code",IF(AND(L30<>"",O30=""),"No revenue GL code","")))))))) | W30: =IF(E30="","",IFERROR(INDEX(lst_JobName,MATCH(E30&"",lst_Jobs,0)),"")) | X30: =IF(E30="","",COUNTIFS(tbl_Finance[Job Number],E30&"",tbl_Finance[Ex GST],"<>")) | Y30: =IF(E30="","",SUMIFS(tbl_Finance[Ex GST],tbl_Finance[Job Number],E30&"")) | Z30: =IF(E30="","",SUMIFS(tbl_Finance[Ex GST],tbl_Finance[Job Number],E30&"",tbl_Finance[Xero Invoice No],"<>")) | AA30: =IF(E30="","",Y30-Z30) | AB30: =IF(E30="","",IF(H30="Onsite",IFERROR(INDEX(tbl_Onsite[Qwilr Quote],MATCH(E30&"",tbl_Onsite[Job Number],0)),""),IF(H30="Production",IFERROR(IF(INDEX(tbl_Production[Current RMS No],MATCH(E30&"",tbl_Production[Job Number],0))="",INDEX(tbl_Production[Qwilr Quote],MATCH(E30&"",tbl_Production[Job Number],0)),INDEX(tbl_Production[Current RMS No],MATCH(E30&"",tbl_Production[Job Number],0))),""),IF(H30="Consulting",IFERROR(INDEX(tbl_Consulting[Qwilr Quote],MATCH(E30&"",tbl_Consulting[Job Number],0)),""),"")))) | AC30: =IF(AB30="","",IF(AND(LEFT(AB30,4)<>"http",IF(H30="Production",set_RMSBase,set_QwilrBase)=""),"",HYPERLINK(IF(LEFT(AB30,4)="http",AB30,IF(H30="Production",set_RMSBase,set_QwilrBase)&AB30),"Open"))) | AD30: =IF(E30="","",IF(H30="Production",IFERROR(INDEX(tbl_Production[Total Expense],MATCH(E30&"",tbl_Production[Job Number],0)),0),IF(H30="Consulting",IFERROR(INDEX(tbl_Consulting[Total Expense],MATCH(E30&"",tbl_Consulting[Job Number],0)),0),0))) | AE30: =IF(E30="","",Y30-N(AD30)) | AF30: =IFERROR(AE30/Y30,"") | AG30: =IF(E30="","",IF(H30="Onsite",IFERROR(INDEX(tbl_Onsite[Notes],MATCH(E30&"",tbl_Onsite[Job Number],0)),""),IF(H30="Production",IFERROR(INDEX(tbl_Production[Notes],MATCH(E30&"",tbl_Production[Job Number],0)),""),IF(H30="Consulting",IFERROR(INDEX(tbl_Consulting[Notes],MATCH(E30&"",tbl_Consulting[Job Number],0)),""),""))))
A31: 46265 | B31: =IF(A31="","",EOMONTH(A31,0)) | C31: INV-10569 | D31: DTTL | E31: 2846/1401/725/1400/1530/1862/2402/2849/974 | F31: =IF(E31="","",IF(COUNTIF(lst_Jobs,E31&"")>0,"OK","CHECK")) | G31: DTTL Contract August 2026 | H31: Onsite | I31: ONSITE | J31: Contract | K31: GST 10% | L31: 103625.44 | M31: =IF(L31="","",IF(K31="GST 10%",ROUND(L31*set_GSTRate,2),0)) | N31: =IF(L31="","",L31+M31) | O31: 41100 | P31: Y | Q31: N | T31: Invoiced | V31: =IF(COUNTA(A31,D31,C31,L31)=0,"",IF(A31="","No date - sits outside every month",IF(E31="","No job number",IF(F31="CHECK","Job number is not in the Xero job list",IF(I31="","No cost centre",IF(AND(P31="Y",C31=""),"Marked posted to Xero but has no invoice number",IF(AND(L31<>"",K31=""),"No tax code",IF(AND(L31<>"",O31=""),"No revenue GL code","")))))))) | W31: =IF(E31="","",IFERROR(INDEX(lst_JobName,MATCH(E31&"",lst_Jobs,0)),"")) | X31: =IF(E31="","",COUNTIFS(tbl_Finance[Job Number],E31&"",tbl_Finance[Ex GST],"<>")) | Y31: =IF(E31="","",SUMIFS(tbl_Finance[Ex GST],tbl_Finance[Job Number],E31&"")) | Z31: =IF(E31="","",SUMIFS(tbl_Finance[Ex GST],tbl_Finance[Job Number],E31&"",tbl_Finance[Xero Invoice No],"<>")) | AA31: =IF(E31="","",Y31-Z31) | AB31: =IF(E31="","",IF(H31="Onsite",IFERROR(INDEX(tbl_Onsite[Qwilr Quote],MATCH(E31&"",tbl_Onsite[Job Number],0)),""),IF(H31="Production",IFERROR(IF(INDEX(tbl_Production[Current RMS No],MATCH(E31&"",tbl_Production[Job Number],0))="",INDEX(tbl_Production[Qwilr Quote],MATCH(E31&"",tbl_Production[Job Number],0)),INDEX(tbl_Production[Current RMS No],MATCH(E31&"",tbl_Production[Job Number],0))),""),IF(H31="Consulting",IFERROR(INDEX(tbl_Consulting[Qwilr Quote],MATCH(E31&"",tbl_Consulting[Job Number],0)),""),"")))) | AC31: =IF(AB31="","",IF(AND(LEFT(AB31,4)<>"http",IF(H31="Production",set_RMSBase,set_QwilrBase)=""),"",HYPERLINK(IF(LEFT(AB31,4)="http",AB31,IF(H31="Production",set_RMSBase,set_QwilrBase)&AB31),"Open"))) | AD31: =IF(E31="","",IF(H31="Production",IFERROR(INDEX(tbl_Production[Total Expense],MATCH(E31&"",tbl_Production[Job Number],0)),0),IF(H31="Consulting",IFERROR(INDEX(tbl_Consulting[Total Expense],MATCH(E31&"",tbl_Consulting[Job Number],0)),0),0))) | AE31: =IF(E31="","",Y31-N(AD31)) | AF31: =IFERROR(AE31/Y31,"") | AG31: =IF(E31="","",IF(H31="Onsite",IFERROR(INDEX(tbl_Onsite[Notes],MATCH(E31&"",tbl_Onsite[Job Number],0)),""),IF(H31="Production",IFERROR(INDEX(tbl_Production[Notes],MATCH(E31&"",tbl_Production[Job Number],0)),""),IF(H31="Consulting",IFERROR(INDEX(tbl_Consulting[Notes],MATCH(E31&"",tbl_Consulting[Job Number],0)),""),""))))
A32: 46265 | B32: =IF(A32="","",EOMONTH(A32,0)) | C32: INV-10570 | D32: BW | E32: 732/1144 | F32: =IF(E32="","",IF(COUNTIF(lst_Jobs,E32&"")>0,"OK","CHECK")) | G32: BW Contract August 2026 | H32: Onsite | I32: ONSITE | J32: Contract | K32: GST 10% | L32: 15113.75 | M32: =IF(L32="","",IF(K32="GST 10%",ROUND(L32*set_GSTRate,2),0)) | N32: =IF(L32="","",L32+M32) | O32: 41100 | P32: Y | Q32: N | T32: Invoiced | V32: =IF(COUNTA(A32,D32,C32,L32)=0,"",IF(A32="","No date - sits outside every month",IF(E32="","No job number",IF(F32="CHECK","Job number is not in the Xero job list",IF(I32="","No cost centre",IF(AND(P32="Y",C32=""),"Marked posted to Xero but has no invoice number",IF(AND(L32<>"",K32=""),"No tax code",IF(AND(L32<>"",O32=""),"No revenue GL code","")))))))) | W32: =IF(E32="","",IFERROR(INDEX(lst_JobName,MATCH(E32&"",lst_Jobs,0)),"")) | X32: =IF(E32="","",COUNTIFS(tbl_Finance[Job Number],E32&"",tbl_Finance[Ex GST],"<>")) | Y32: =IF(E32="","",SUMIFS(tbl_Finance[Ex GST],tbl_Finance[Job Number],E32&"")) | Z32: =IF(E32="","",SUMIFS(tbl_Finance[Ex GST],tbl_Finance[Job Number],E32&"",tbl_Finance[Xero Invoice No],"<>")) | AA32: =IF(E32="","",Y32-Z32) | AB32: =IF(E32="","",IF(H32="Onsite",IFERROR(INDEX(tbl_Onsite[Qwilr Quote],MATCH(E32&"",tbl_Onsite[Job Number],0)),""),IF(H32="Production",IFERROR(IF(INDEX(tbl_Production[Current RMS No],MATCH(E32&"",tbl_Production[Job Number],0))="",INDEX(tbl_Production[Qwilr Quote],MATCH(E32&"",tbl_Production[Job Number],0)),INDEX(tbl_Production[Current RMS No],MATCH(E32&"",tbl_Production[Job Number],0))),""),IF(H32="Consulting",IFERROR(INDEX(tbl_Consulting[Qwilr Quote],MATCH(E32&"",tbl_Consulting[Job Number],0)),""),"")))) | AC32: =IF(AB32="","",IF(AND(LEFT(AB32,4)<>"http",IF(H32="Production",set_RMSBase,set_QwilrBase)=""),"",HYPERLINK(IF(LEFT(AB32,4)="http",AB32,IF(H32="Production",set_RMSBase,set_QwilrBase)&AB32),"Open"))) | AD32: =IF(E32="","",IF(H32="Production",IFERROR(INDEX(tbl_Production[Total Expense],MATCH(E32&"",tbl_Production[Job Number],0)),0),IF(H32="Consulting",IFERROR(INDEX(tbl_Consulting[Total Expense],MATCH(E32&"",tbl_Consulting[Job Number],0)),0),0))) | AE32: =IF(E32="","",Y32-N(AD32)) | AF32: =IFERROR(AE32/Y32,"") | AG32: =IF(E32="","",IF(H32="Onsite",IFERROR(INDEX(tbl_Onsite[Notes],MATCH(E32&"",tbl_Onsite[Job Number],0)),""),IF(H32="Production",IFERROR(INDEX(tbl_Production[Notes],MATCH(E32&"",tbl_Production[Job Number],0)),""),IF(H32="Consulting",IFERROR(INDEX(tbl_Consulting[Notes],MATCH(E32&"",tbl_Consulting[Job Number],0)),""),""))))
A33: 46265 | B33: =IF(A33="","",EOMONTH(A33,0)) | C33: INV-10571 | D33: BW | E33: 2192 | F33: =IF(E33="","",IF(COUNTIF(lst_Jobs,E33&"")>0,"OK","CHECK")) | G33: BW Additionals August 2026 | H33: Onsite | I33: ONSITE | J33: Contract | K33: GST 10% | L33: 2080 | M33: =IF(L33="","",IF(K33="GST 10%",ROUND(L33*set_GSTRate,2),0)) | N33: =IF(L33="","",L33+M33) | O33: 41100 | P33: Y | Q33: N | T33: Invoiced | V33: =IF(COUNTA(A33,D33,C33,L33)=0,"",IF(A33="","No date - sits outside every month",IF(E33="","No job number",IF(F33="CHECK","Job number is not in the Xero job list",IF(I33="","No cost centre",IF(AND(P33="Y",C33=""),"Marked posted to Xero but has no invoice number",IF(AND(L33<>"",K33=""),"No tax code",IF(AND(L33<>"",O33=""),"No revenue GL code","")))))))) | W33: =IF(E33="","",IFERROR(INDEX(lst_JobName,MATCH(E33&"",lst_Jobs,0)),"")) | X33: =IF(E33="","",COUNTIFS(tbl_Finance[Job Number],E33&"",tbl_Finance[Ex GST],"<>")) | Y33: =IF(E33="","",SUMIFS(tbl_Finance[Ex GST],tbl_Finance[Job Number],E33&"")) | Z33: =IF(E33="","",SUMIFS(tbl_Finance[Ex GST],tbl_Finance[Job Number],E33&"",tbl_Finance[Xero Invoice No],"<>")) | AA33: =IF(E33="","",Y33-Z33) | AB33: =IF(E33="","",IF(H33="Onsite",IFERROR(INDEX(tbl_Onsite[Qwilr Quote],MATCH(E33&"",tbl_Onsite[Job Number],0)),""),IF(H33="Production",IFERROR(IF(INDEX(tbl_Production[Current RMS No],MATCH(E33&"",tbl_Production[Job Number],0))="",INDEX(tbl_Production[Qwilr Quote],MATCH(E33&"",tbl_Production[Job Number],0)),INDEX(tbl_Production[Current RMS No],MATCH(E33&"",tbl_Production[Job Number],0))),""),IF(H33="Consulting",IFERROR(INDEX(tbl_Consulting[Qwilr Quote],MATCH(E33&"",tbl_Consulting[Job Number],0)),""),"")))) | AC33: =IF(AB33="","",IF(AND(LEFT(AB33,4)<>"http",IF(H33="Production",set_RMSBase,set_QwilrBase)=""),"",HYPERLINK(IF(LEFT(AB33,4)="http",AB33,IF(H33="Production",set_RMSBase,set_QwilrBase)&AB33),"Open"))) | AD33: =IF(E33="","",IF(H33="Production",IFERROR(INDEX(tbl_Production[Total Expense],MATCH(E33&"",tbl_Production[Job Number],0)),0),IF(H33="Consulting",IFERROR(INDEX(tbl_Consulting[Total Expense],MATCH(E33&"",tbl_Consulting[Job Number],0)),0),0))) | AE33: =IF(E33="","",Y33-N(AD33)) | AF33: =IFERROR(AE33/Y33,"") | AG33: =IF(E33="","",IF(H33="Onsite",IFERROR(INDEX(tbl_Onsite[Notes],MATCH(E33&"",tbl_Onsite[Job Number],0)),""),IF(H33="Production",IFERROR(INDEX(tbl_Production[Notes],MATCH(E33&"",tbl_Production[Job Number],0)),""),IF(H33="Consulting",IFERROR(INDEX(tbl_Consulting[Notes],MATCH(E33&"",tbl_Consulting[Job Number],0)),""),""))))
A34: 46265 | B34: =IF(A34="","",EOMONTH(A34,0)) | C34: INV-10572 | D34: PWC | E34: 2488 | F34: =IF(E34="","",IF(COUNTIF(lst_Jobs,E34&"")>0,"OK","CHECK")) | G34: PWC Brisbane August 2026 | H34: Onsite | I34: ONSITE | J34: Contract | K34: GST 10% | L34: 7150 | M34: =IF(L34="","",IF(K34="GST 10%",ROUND(L34*set_GSTRate,2),0)) | N34: =IF(L34="","",L34+M34) | O34: 41100 | P34: Y | Q34: N | T34: Invoiced | V34: =IF(COUNTA(A34,D34,C34,L34)=0,"",IF(A34="","No date - sits outside every month",IF(E34="","No job number",IF(F34="CHECK","Job number is not in the Xero job list",IF(I34="","No cost centre",IF(AND(P34="Y",C34=""),"Marked posted to Xero but has no invoice number",IF(AND(L34<>"",K34=""),"No tax code",IF(AND(L34<>"",O34=""),"No revenue GL code","")))))))) | W34: =IF(E34="","",IFERROR(INDEX(lst_JobName,MATCH(E34&"",lst_Jobs,0)),"")) | X34: =IF(E34="","",COUNTIFS(tbl_Finance[Job Number],E34&"",tbl_Finance[Ex GST],"<>")) | Y34: =IF(E34="","",SUMIFS(tbl_Finance[Ex GST],tbl_Finance[Job Number],E34&"")) | Z34: =IF(E34="","",SUMIFS(tbl_Finance[Ex GST],tbl_Finance[Job Number],E34&"",tbl_Finance[Xero Invoice No],"<>")) | AA34: =IF(E34="","",Y34-Z34) | AB34: =IF(E34="","",IF(H34="Onsite",IFERROR(INDEX(tbl_Onsite[Qwilr Quote],MATCH(E34&"",tbl_Onsite[Job Number],0)),""),IF(H34="Production",IFERROR(IF(INDEX(tbl_Production[Current RMS No],MATCH(E34&"",tbl_Production[Job Number],0))="",INDEX(tbl_Production[Qwilr Quote],MATCH(E34&"",tbl_Production[Job Number],0)),INDEX(tbl_Production[Current RMS No],MATCH(E34&"",tbl_Production[Job Number],0))),""),IF(H34="Consulting",IFERROR(INDEX(tbl_Consulting[Qwilr Quote],MATCH(E34&"",tbl_Consulting[Job Number],0)),""),"")))) | AC34: =IF(AB34="","",IF(AND(LEFT(AB34,4)<>"http",IF(H34="Production",set_RMSBase,set_QwilrBase)=""),"",HYPERLINK(IF(LEFT(AB34,4)="http",AB34,IF(H34="Production",set_RMSBase,set_QwilrBase)&AB34),"Open"))) | AD34: =IF(E34="","",IF(H34="Production",IFERROR(INDEX(tbl_Production[Total Expense],MATCH(E34&"",tbl_Production[Job Number],0)),0),IF(H34="Consulting",IFERROR(INDEX(tbl_Consulting[Total Expense],MATCH(E34&"",tbl_Consulting[Job Number],0)),0),0))) | AE34: =IF(E34="","",Y34-N(AD34)) | AF34: =IFERROR(AE34/Y34,"") | AG34: =IF(E34="","",IF(H34="Onsite",IFERROR(INDEX(tbl_Onsite[Notes],MATCH(E34&"",tbl_Onsite[Job Number],0)),""),IF(H34="Production",IFERROR(INDEX(tbl_Production[Notes],MATCH(E34&"",tbl_Production[Job Number],0)),""),IF(H34="Consulting",IFERROR(INDEX(tbl_Consulting[Notes],MATCH(E34&"",tbl_Consulting[Job Number],0)),""),""))))
A35: 46265 | B35: =IF(A35="","",EOMONTH(A35,0)) | C35: INV-10573 | D35: Gen-E | E35: 26021602 | F35: =IF(E35="","",IF(COUNTIF(lst_Jobs,E35&"")>0,"OK","CHECK")) | G35: Gen-E ABS August 2026 | H35: Onsite | I35: ONSITE | J35: Contract | K35: GST 10% | L35: 12388.8 | M35: =IF(L35="","",IF(K35="GST 10%",ROUND(L35*set_GSTRate,2),0)) | N35: =IF(L35="","",L35+M35) | O35: 41100 | P35: Y | Q35: N | T35: Invoiced | V35: =IF(COUNTA(A35,D35,C35,L35)=0,"",IF(A35="","No date - sits outside every month",IF(E35="","No job number",IF(F35="CHECK","Job number is not in the Xero job list",IF(I35="","No cost centre",IF(AND(P35="Y",C35=""),"Marked posted to Xero but has no invoice number",IF(AND(L35<>"",K35=""),"No tax code",IF(AND(L35<>"",O35=""),"No revenue GL code","")))))))) | W35: =IF(E35="","",IFERROR(INDEX(lst_JobName,MATCH(E35&"",lst_Jobs,0)),"")) | X35: =IF(E35="","",COUNTIFS(tbl_Finance[Job Number],E35&"",tbl_Finance[Ex GST],"<>")) | Y35: =IF(E35="","",SUMIFS(tbl_Finance[Ex GST],tbl_Finance[Job Number],E35&"")) | Z35: =IF(E35="","",SUMIFS(tbl_Finance[Ex GST],tbl_Finance[Job Number],E35&"",tbl_Finance[Xero Invoice No],"<>")) | AA35: =IF(E35="","",Y35-Z35) | AB35: =IF(E35="","",IF(H35="Onsite",IFERROR(INDEX(tbl_Onsite[Qwilr Quote],MATCH(E35&"",tbl_Onsite[Job Number],0)),""),IF(H35="Production",IFERROR(IF(INDEX(tbl_Production[Current RMS No],MATCH(E35&"",tbl_Production[Job Number],0))="",INDEX(tbl_Production[Qwilr Quote],MATCH(E35&"",tbl_Production[Job Number],0)),INDEX(tbl_Production[Current RMS No],MATCH(E35&"",tbl_Production[Job Number],0))),""),IF(H35="Consulting",IFERROR(INDEX(tbl_Consulting[Qwilr Quote],MATCH(E35&"",tbl_Consulting[Job Number],0)),""),"")))) | AC35: =IF(AB35="","",IF(AND(LEFT(AB35,4)<>"http",IF(H35="Production",set_RMSBase,set_QwilrBase)=""),"",HYPERLINK(IF(LEFT(AB35,4)="http",AB35,IF(H35="Production",set_RMSBase,set_QwilrBase)&AB35),"Open"))) | AD35: =IF(E35="","",IF(H35="Production",IFERROR(INDEX(tbl_Production[Total Expense],MATCH(E35&"",tbl_Production[Job Number],0)),0),IF(H35="Consulting",IFERROR(INDEX(tbl_Consulting[Total Expense],MATCH(E35&"",tbl_Consulting[Job Number],0)),0),0))) | AE35: =IF(E35="","",Y35-N(AD35)) | AF35: =IFERROR(AE35/Y35,"") | AG35: =IF(E35="","",IF(H35="Onsite",IFERROR(INDEX(tbl_Onsite[Notes],MATCH(E35&"",tbl_Onsite[Job Number],0)),""),IF(H35="Production",IFERROR(INDEX(tbl_Production[Notes],MATCH(E35&"",tbl_Production[Job Number],0)),""),IF(H35="Consulting",IFERROR(INDEX(tbl_Consulting[Notes],MATCH(E35&"",tbl_Consulting[Job Number],0)),""),""))))
A36: 46265 | B36: =IF(A36="","",EOMONTH(A36,0)) | C36: INV-10582 | D36: CBA | E36: 26043001 | F36: =IF(E36="","",IF(COUNTIF(lst_Jobs,E36&"")>0,"OK","CHECK")) | G36: CBA Mel August 2026 | H36: Onsite | I36: ONSITE | J36: Contract | K36: GST 10% | L36: 11960 | M36: =IF(L36="","",IF(K36="GST 10%",ROUND(L36*set_GSTRate,2),0)) | N36: =IF(L36="","",L36+M36) | O36: 41100 | P36: Y | Q36: N | T36: Invoiced | V36: =IF(COUNTA(A36,D36,C36,L36)=0,"",IF(A36="","No date - sits outside every month",IF(E36="","No job number",IF(F36="CHECK","Job number is not in the Xero job list",IF(I36="","No cost centre",IF(AND(P36="Y",C36=""),"Marked posted to Xero but has no invoice number",IF(AND(L36<>"",K36=""),"No tax code",IF(AND(L36<>"",O36=""),"No revenue GL code","")))))))) | W36: =IF(E36="","",IFERROR(INDEX(lst_JobName,MATCH(E36&"",lst_Jobs,0)),"")) | X36: =IF(E36="","",COUNTIFS(tbl_Finance[Job Number],E36&"",tbl_Finance[Ex GST],"<>")) | Y36: =IF(E36="","",SUMIFS(tbl_Finance[Ex GST],tbl_Finance[Job Number],E36&"")) | Z36: =IF(E36="","",SUMIFS(tbl_Finance[Ex GST],tbl_Finance[Job Number],E36&"",tbl_Finance[Xero Invoice No],"<>")) | AA36: =IF(E36="","",Y36-Z36) | AB36: =IF(E36="","",IF(H36="Onsite",IFERROR(INDEX(tbl_Onsite[Qwilr Quote],MATCH(E36&"",tbl_Onsite[Job Number],0)),""),IF(H36="Production",IFERROR(IF(INDEX(tbl_Production[Current RMS No],MATCH(E36&"",tbl_Production[Job Number],0))="",INDEX(tbl_Production[Qwilr Quote],MATCH(E36&"",tbl_Production[Job Number],0)),INDEX(tbl_Production[Current RMS No],MATCH(E36&"",tbl_Production[Job Number],0))),""),IF(H36="Consulting",IFERROR(INDEX(tbl_Consulting[Qwilr Quote],MATCH(E36&"",tbl_Consulting[Job Number],0)),""),"")))) | AC36: =IF(AB36="","",IF(AND(LEFT(AB36,4)<>"http",IF(H36="Production",set_RMSBase,set_QwilrBase)=""),"",HYPERLINK(IF(LEFT(AB36,4)="http",AB36,IF(H36="Production",set_RMSBase,set_QwilrBase)&AB36),"Open"))) | AD36: =IF(E36="","",IF(H36="Production",IFERROR(INDEX(tbl_Production[Total Expense],MATCH(E36&"",tbl_Production[Job Number],0)),0),IF(H36="Consulting",IFERROR(INDEX(tbl_Consulting[Total Expense],MATCH(E36&"",tbl_Consulting[Job Number],0)),0),0))) | AE36: =IF(E36="","",Y36-N(AD36)) | AF36: =IFERROR(AE36/Y36,"") | AG36: =IF(E36="","",IF(H36="Onsite",IFERROR(INDEX(tbl_Onsite[Notes],MATCH(E36&"",tbl_Onsite[Job Number],0)),""),IF(H36="Production",IFERROR(INDEX(tbl_Production[Notes],MATCH(E36&"",tbl_Production[Job Number],0)),""),IF(H36="Consulting",IFERROR(INDEX(tbl_Consulting[Notes],MATCH(E36&"",tbl_Consulting[Job Number],0)),""),""))))
A37: 46265 | B37: =IF(A37="","",EOMONTH(A37,0)) | C37: INV-10615 | D37: Aware Super | E37: 26022301 | F37: =IF(E37="","",IF(COUNTIF(lst_Jobs,E37&"")>0,"OK","CHECK")) | G37: Aware Super Contract August 2026 | H37: Onsite | I37: ONSITE | J37: Contract | K37: GST 10% | L37: 11000 | M37: =IF(L37="","",IF(K37="GST 10%",ROUND(L37*set_GSTRate,2),0)) | N37: =IF(L37="","",L37+M37) | O37: 41100 | P37: Y | Q37: N | T37: Invoiced | U37: Split TBC - Xero split this with production ($850) | V37: =IF(COUNTA(A37,D37,C37,L37)=0,"",IF(A37="","No date - sits outside every month",IF(E37="","No job number",IF(F37="CHECK","Job number is not in the Xero job list",IF(I37="","No cost centre",IF(AND(P37="Y",C37=""),"Marked posted to Xero but has no invoice number",IF(AND(L37<>"",K37=""),"No tax code",IF(AND(L37<>"",O37=""),"No revenue GL code","")))))))) | W37: =IF(E37="","",IFERROR(INDEX(lst_JobName,MATCH(E37&"",lst_Jobs,0)),"")) | X37: =IF(E37="","",COUNTIFS(tbl_Finance[Job Number],E37&"",tbl_Finance[Ex GST],"<>")) | Y37: =IF(E37="","",SUMIFS(tbl_Finance[Ex GST],tbl_Finance[Job Number],E37&"")) | Z37: =IF(E37="","",SUMIFS(tbl_Finance[Ex GST],tbl_Finance[Job Number],E37&"",tbl_Finance[Xero Invoice No],"<>")) | AA37: =IF(E37="","",Y37-Z37) | AB37: =IF(E37="","",IF(H37="Onsite",IFERROR(INDEX(tbl_Onsite[Qwilr Quote],MATCH(E37&"",tbl_Onsite[Job Number],0)),""),IF(H37="Production",IFERROR(IF(INDEX(tbl_Production[Current RMS No],MATCH(E37&"",tbl_Production[Job Number],0))="",INDEX(tbl_Production[Qwilr Quote],MATCH(E37&"",tbl_Production[Job Number],0)),INDEX(tbl_Production[Current RMS No],MATCH(E37&"",tbl_Production[Job Number],0))),""),IF(H37="Consulting",IFERROR(INDEX(tbl_Consulting[Qwilr Quote],MATCH(E37&"",tbl_Consulting[Job Number],0)),""),"")))) | AC37: =IF(AB37="","",IF(AND(LEFT(AB37,4)<>"http",IF(H37="Production",set_RMSBase,set_QwilrBase)=""),"",HYPERLINK(IF(LEFT(AB37,4)="http",AB37,IF(H37="Production",set_RMSBase,set_QwilrBase)&AB37),"Open"))) | AD37: =IF(E37="","",IF(H37="Production",IFERROR(INDEX(tbl_Production[Total Expense],MATCH(E37&"",tbl_Production[Job Number],0)),0),IF(H37="Consulting",IFERROR(INDEX(tbl_Consulting[Total Expense],MATCH(E37&"",tbl_Consulting[Job Number],0)),0),0))) | AE37: =IF(E37="","",Y37-N(AD37)) | AF37: =IFERROR(AE37/Y37,"") | AG37: =IF(E37="","",IF(H37="Onsite",IFERROR(INDEX(tbl_Onsite[Notes],MATCH(E37&"",tbl_Onsite[Job Number],0)),""),IF(H37="Production",IFERROR(INDEX(tbl_Production[Notes],MATCH(E37&"",tbl_Production[Job Number],0)),""),IF(H37="Consulting",IFERROR(INDEX(tbl_Consulting[Notes],MATCH(E37&"",tbl_Consulting[Job Number],0)),""),""))))
A38: 46265 | B38: =IF(A38="","",EOMONTH(A38,0)) | C38: INV-10585 | D38: PWC | E38: 25101301B | F38: =IF(E38="","",IF(COUNTIF(lst_Jobs,E38&"")>0,"OK","CHECK")) | G38: PWC Sydney IT August 2026 | H38: Onsite | I38: ONSITE | J38: Contract | K38: GST 10% | L38: 11907 | M38: =IF(L38="","",IF(K38="GST 10%",ROUND(L38*set_GSTRate,2),0)) | N38: =IF(L38="","",L38+M38) | O38: 41100 | P38: Y | Q38: N | T38: Invoiced | V38: =IF(COUNTA(A38,D38,C38,L38)=0,"",IF(A38="","No date - sits outside every month",IF(E38="","No job number",IF(F38="CHECK","Job number is not in the Xero job list",IF(I38="","No cost centre",IF(AND(P38="Y",C38=""),"Marked posted to Xero but has no invoice number",IF(AND(L38<>"",K38=""),"No tax code",IF(AND(L38<>"",O38=""),"No revenue GL code","")))))))) | W38: =IF(E38="","",IFERROR(INDEX(lst_JobName,MATCH(E38&"",lst_Jobs,0)),"")) | X38: =IF(E38="","",COUNTIFS(tbl_Finance[Job Number],E38&"",tbl_Finance[Ex GST],"<>")) | Y38: =IF(E38="","",SUMIFS(tbl_Finance[Ex GST],tbl_Finance[Job Number],E38&"")) | Z38: =IF(E38="","",SUMIFS(tbl_Finance[Ex GST],tbl_Finance[Job Number],E38&"",tbl_Finance[Xero Invoice No],"<>")) | AA38: =IF(E38="","",Y38-Z38) | AB38: =IF(E38="","",IF(H38="Onsite",IFERROR(INDEX(tbl_Onsite[Qwilr Quote],MATCH(E38&"",tbl_Onsite[Job Number],0)),""),IF(H38="Production",IFERROR(IF(INDEX(tbl_Production[Current RMS No],MATCH(E38&"",tbl_Production[Job Number],0))="",INDEX(tbl_Production[Qwilr Quote],MATCH(E38&"",tbl_Production[Job Number],0)),INDEX(tbl_Production[Current RMS No],MATCH(E38&"",tbl_Production[Job Number],0))),""),IF(H38="Consulting",IFERROR(INDEX(tbl_Consulting[Qwilr Quote],MATCH(E38&"",tbl_Consulting[Job Number],0)),""),"")))) | AC38: =IF(AB38="","",IF(AND(LEFT(AB38,4)<>"http",IF(H38="Production",set_RMSBase,set_QwilrBase)=""),"",HYPERLINK(IF(LEFT(AB38,4)="http",AB38,IF(H38="Production",set_RMSBase,set_QwilrBase)&AB38),"Open"))) | AD38: =IF(E38="","",IF(H38="Production",IFERROR(INDEX(tbl_Production[Total Expense],MATCH(E38&"",tbl_Production[Job Number],0)),0),IF(H38="Consulting",IFERROR(INDEX(tbl_Consulting[Total Expense],MATCH(E38&"",tbl_Consulting[Job Number],0)),0),0))) | AE38: =IF(E38="","",Y38-N(AD38)) | AF38: =IFERROR(AE38/Y38,"") | AG38: =IF(E38="","",IF(H38="Onsite",IFERROR(INDEX(tbl_Onsite[Notes],MATCH(E38&"",tbl_Onsite[Job Number],0)),""),IF(H38="Production",IFERROR(INDEX(tbl_Production[Notes],MATCH(E38&"",tbl_Production[Job Number],0)),""),IF(H38="Consulting",IFERROR(INDEX(tbl_Consulting[Notes],MATCH(E38&"",tbl_Consulting[Job Number],0)),""),""))))
B39: =IF(A39="","",EOMONTH(A39,0)) | D39: TWG | E39: 26081301 | F39: =IF(E39="","",IF(COUNTIF(lst_Jobs,E39&"")>0,"OK","CHECK")) | G39: EY Support Technician BNE | H39: Onsite | I39: ONSITE | J39: Contract | K39: GST 10% | L39: 3740 | M39: =IF(L39="","",IF(K39="GST 10%",ROUND(L39*set_GSTRate,2),0)) | N39: =IF(L39="","",L39+M39) | O39: 41100 | P39: N | Q39: N | T39: To Invoice | U39: November | V39: =IF(COUNTA(A39,D39,C39,L39)=0,"",IF(A39="","No date - sits outside every month",IF(E39="","No job number",IF(F39="CHECK","Job number is not in the Xero job list",IF(I39="","No cost centre",IF(AND(P39="Y",C39=""),"Marked posted to Xero but has no invoice number",IF(AND(L39<>"",K39=""),"No tax code",IF(AND(L39<>"",O39=""),"No revenue GL code","")))))))) | W39: =IF(E39="","",IFERROR(INDEX(lst_JobName,MATCH(E39&"",lst_Jobs,0)),"")) | X39: =IF(E39="","",COUNTIFS(tbl_Finance[Job Number],E39&"",tbl_Finance[Ex GST],"<>")) | Y39: =IF(E39="","",SUMIFS(tbl_Finance[Ex GST],tbl_Finance[Job Number],E39&"")) | Z39: =IF(E39="","",SUMIFS(tbl_Finance[Ex GST],tbl_Finance[Job Number],E39&"",tbl_Finance[Xero Invoice No],"<>")) | AA39: =IF(E39="","",Y39-Z39) | AB39: =IF(E39="","",IF(H39="Onsite",IFERROR(INDEX(tbl_Onsite[Qwilr Quote],MATCH(E39&"",tbl_Onsite[Job Number],0)),""),IF(H39="Production",IFERROR(IF(INDEX(tbl_Production[Current RMS No],MATCH(E39&"",tbl_Production[Job Number],0))="",INDEX(tbl_Production[Qwilr Quote],MATCH(E39&"",tbl_Production[Job Number],0)),INDEX(tbl_Production[Current RMS No],MATCH(E39&"",tbl_Production[Job Number],0))),""),IF(H39="Consulting",IFERROR(INDEX(tbl_Consulting[Qwilr Quote],MATCH(E39&"",tbl_Consulting[Job Number],0)),""),"")))) | AC39: =IF(AB39="","",IF(AND(LEFT(AB39,4)<>"http",IF(H39="Production",set_RMSBase,set_QwilrBase)=""),"",HYPERLINK(IF(LEFT(AB39,4)="http",AB39,IF(H39="Production",set_RMSBase,set_QwilrBase)&AB39),"Open"))) | AD39: =IF(E39="","",IF(H39="Production",IFERROR(INDEX(tbl_Production[Total Expense],MATCH(E39&"",tbl_Production[Job Number],0)),0),IF(H39="Consulting",IFERROR(INDEX(tbl_Consulting[Total Expense],MATCH(E39&"",tbl_Consulting[Job Number],0)),0),0))) | AE39: =IF(E39="","",Y39-N(AD39)) | AF39: =IFERROR(AE39/Y39,"") | AG39: =IF(E39="","",IF(H39="Onsite",IFERROR(INDEX(tbl_Onsite[Notes],MATCH(E39&"",tbl_Onsite[Job Number],0)),""),IF(H39="Production",IFERROR(INDEX(tbl_Production[Notes],MATCH(E39&"",tbl_Production[Job Number],0)),""),IF(H39="Consulting",IFERROR(INDEX(tbl_Consulting[Notes],MATCH(E39&"",tbl_Consulting[Job Number],0)),""),""))))
A40: 46265 | B40: =IF(A40="","",EOMONTH(A40,0)) | C40: INV-10603 | D40: CBA | E40: 1668 | F40: =IF(E40="","",IF(COUNTIF(lst_Jobs,E40&"")>0,"OK","CHECK")) | G40: 85720001CBPSCSJUN27 AFTERHOUR | H40: Onsite | I40: ONSITE | J40: Contract | K40: GST 10% | L40: 775 | M40: =IF(L40="","",IF(K40="GST 10%",ROUND(L40*set_GSTRate,2),0)) | N40: =IF(L40="","",L40+M40) | O40: 41100 | P40: Y | Q40: N | T40: Invoiced | V40: =IF(COUNTA(A40,D40,C40,L40)=0,"",IF(A40="","No date - sits outside every month",IF(E40="","No job number",IF(F40="CHECK","Job number is not in the Xero job list",IF(I40="","No cost centre",IF(AND(P40="Y",C40=""),"Marked posted to Xero but has no invoice number",IF(AND(L40<>"",K40=""),"No tax code",IF(AND(L40<>"",O40=""),"No revenue GL code","")))))))) | W40: =IF(E40="","",IFERROR(INDEX(lst_JobName,MATCH(E40&"",lst_Jobs,0)),"")) | X40: =IF(E40="","",COUNTIFS(tbl_Finance[Job Number],E40&"",tbl_Finance[Ex GST],"<>")) | Y40: =IF(E40="","",SUMIFS(tbl_Finance[Ex GST],tbl_Finance[Job Number],E40&"")) | Z40: =IF(E40="","",SUMIFS(tbl_Finance[Ex GST],tbl_Finance[Job Number],E40&"",tbl_Finance[Xero Invoice No],"<>")) | AA40: =IF(E40="","",Y40-Z40) | AB40: =IF(E40="","",IF(H40="Onsite",IFERROR(INDEX(tbl_Onsite[Qwilr Quote],MATCH(E40&"",tbl_Onsite[Job Number],0)),""),IF(H40="Production",IFERROR(IF(INDEX(tbl_Production[Current RMS No],MATCH(E40&"",tbl_Production[Job Number],0))="",INDEX(tbl_Production[Qwilr Quote],MATCH(E40&"",tbl_Production[Job Number],0)),INDEX(tbl_Production[Current RMS No],MATCH(E40&"",tbl_Production[Job Number],0))),""),IF(H40="Consulting",IFERROR(INDEX(tbl_Consulting[Qwilr Quote],MATCH(E40&"",tbl_Consulting[Job Number],0)),""),"")))) | AC40: =IF(AB40="","",IF(AND(LEFT(AB40,4)<>"http",IF(H40="Production",set_RMSBase,set_QwilrBase)=""),"",HYPERLINK(IF(LEFT(AB40,4)="http",AB40,IF(H40="Production",set_RMSBase,set_QwilrBase)&AB40),"Open"))) | AD40: =IF(E40="","",IF(H40="Production",IFERROR(INDEX(tbl_Production[Total Expense],MATCH(E40&"",tbl_Production[Job Number],0)),0),IF(H40="Consulting",IFERROR(INDEX(tbl_Consulting[Total Expense],MATCH(E40&"",tbl_Consulting[Job Number],0)),0),0))) | AE40: =IF(E40="","",Y40-N(AD40)) | AF40: =IFERROR(AE40/Y40,"") | AG40: =IF(E40="","",IF(H40="Onsite",IFERROR(INDEX(tbl_Onsite[Notes],MATCH(E40&"",tbl_Onsite[Job Number],0)),""),IF(H40="Production",IFERROR(INDEX(tbl_Production[Notes],MATCH(E40&"",tbl_Production[Job Number],0)),""),IF(H40="Consulting",IFERROR(INDEX(tbl_Consulting[Notes],MATCH(E40&"",tbl_Consulting[Job Number],0)),""),""))))
A41: 46265 | B41: =IF(A41="","",EOMONTH(A41,0)) | C41: INV-10604 | D41: CBA | E41: 1668 | F41: =IF(E41="","",IF(COUNTIF(lst_Jobs,E41&"")>0,"OK","CHECK")) | G41: 85720001CBPSCSJUN27 DEDICATED TECH | H41: Onsite | I41: ONSITE | J41: Contract | K41: GST 10% | L41: 510 | M41: =IF(L41="","",IF(K41="GST 10%",ROUND(L41*set_GSTRate,2),0)) | N41: =IF(L41="","",L41+M41) | O41: 41100 | P41: Y | Q41: N | T41: Invoiced | V41: =IF(COUNTA(A41,D41,C41,L41)=0,"",IF(A41="","No date - sits outside every month",IF(E41="","No job number",IF(F41="CHECK","Job number is not in the Xero job list",IF(I41="","No cost centre",IF(AND(P41="Y",C41=""),"Marked posted to Xero but has no invoice number",IF(AND(L41<>"",K41=""),"No tax code",IF(AND(L41<>"",O41=""),"No revenue GL code","")))))))) | W41: =IF(E41="","",IFERROR(INDEX(lst_JobName,MATCH(E41&"",lst_Jobs,0)),"")) | X41: =IF(E41="","",COUNTIFS(tbl_Finance[Job Number],E41&"",tbl_Finance[Ex GST],"<>")) | Y41: =IF(E41="","",SUMIFS(tbl_Finance[Ex GST],tbl_Finance[Job Number],E41&"")) | Z41: =IF(E41="","",SUMIFS(tbl_Finance[Ex GST],tbl_Finance[Job Number],E41&"",tbl_Finance[Xero Invoice No],"<>")) | AA41: =IF(E41="","",Y41-Z41) | AB41: =IF(E41="","",IF(H41="Onsite",IFERROR(INDEX(tbl_Onsite[Qwilr Quote],MATCH(E41&"",tbl_Onsite[Job Number],0)),""),IF(H41="Production",IFERROR(IF(INDEX(tbl_Production[Current RMS No],MATCH(E41&"",tbl_Production[Job Number],0))="",INDEX(tbl_Production[Qwilr Quote],MATCH(E41&"",tbl_Production[Job Number],0)),INDEX(tbl_Production[Current RMS No],MATCH(E41&"",tbl_Production[Job Number],0))),""),IF(H41="Consulting",IFERROR(INDEX(tbl_Consulting[Qwilr Quote],MATCH(E41&"",tbl_Consulting[Job Number],0)),""),"")))) | AC41: =IF(AB41="","",IF(AND(LEFT(AB41,4)<>"http",IF(H41="Production",set_RMSBase,set_QwilrBase)=""),"",HYPERLINK(IF(LEFT(AB41,4)="http",AB41,IF(H41="Production",set_RMSBase,set_QwilrBase)&AB41),"Open"))) | AD41: =IF(E41="","",IF(H41="Production",IFERROR(INDEX(tbl_Production[Total Expense],MATCH(E41&"",tbl_Production[Job Number],0)),0),IF(H41="Consulting",IFERROR(INDEX(tbl_Consulting[Total Expense],MATCH(E41&"",tbl_Consulting[Job Number],0)),0),0))) | AE41: =IF(E41="","",Y41-N(AD41)) | AF41: =IFERROR(AE41/Y41,"") | AG41: =IF(E41="","",IF(H41="Onsite",IFERROR(INDEX(tbl_Onsite[Notes],MATCH(E41&"",tbl_Onsite[Job Number],0)),""),IF(H41="Production",IFERROR(INDEX(tbl_Production[Notes],MATCH(E41&"",tbl_Production[Job Number],0)),""),IF(H41="Consulting",IFERROR(INDEX(tbl_Consulting[Notes],MATCH(E41&"",tbl_Consulting[Job Number],0)),""),""))))
A42: 46265 | B42: =IF(A42="","",EOMONTH(A42,0)) | C42: INV-10605 | D42: CBA | E42: 1668 | F42: =IF(E42="","",IF(COUNTIF(lst_Jobs,E42&"")>0,"OK","CHECK")) | G42: 85720001CBPSCSJUN27 DEDICATED TECH | H42: Onsite | I42: ONSITE | J42: Contract | K42: GST 10% | L42: 340 | M42: =IF(L42="","",IF(K42="GST 10%",ROUND(L42*set_GSTRate,2),0)) | N42: =IF(L42="","",L42+M42) | O42: 41100 | P42: Y | Q42: N | T42: Invoiced | V42: =IF(COUNTA(A42,D42,C42,L42)=0,"",IF(A42="","No date - sits outside every month",IF(E42="","No job number",IF(F42="CHECK","Job number is not in the Xero job list",IF(I42="","No cost centre",IF(AND(P42="Y",C42=""),"Marked posted to Xero but has no invoice number",IF(AND(L42<>"",K42=""),"No tax code",IF(AND(L42<>"",O42=""),"No revenue GL code","")))))))) | W42: =IF(E42="","",IFERROR(INDEX(lst_JobName,MATCH(E42&"",lst_Jobs,0)),"")) | X42: =IF(E42="","",COUNTIFS(tbl_Finance[Job Number],E42&"",tbl_Finance[Ex GST],"<>")) | Y42: =IF(E42="","",SUMIFS(tbl_Finance[Ex GST],tbl_Finance[Job Number],E42&"")) | Z42: =IF(E42="","",SUMIFS(tbl_Finance[Ex GST],tbl_Finance[Job Number],E42&"",tbl_Finance[Xero Invoice No],"<>")) | AA42: =IF(E42="","",Y42-Z42) | AB42: =IF(E42="","",IF(H42="Onsite",IFERROR(INDEX(tbl_Onsite[Qwilr Quote],MATCH(E42&"",tbl_Onsite[Job Number],0)),""),IF(H42="Production",IFERROR(IF(INDEX(tbl_Production[Current RMS No],MATCH(E42&"",tbl_Production[Job Number],0))="",INDEX(tbl_Production[Qwilr Quote],MATCH(E42&"",tbl_Production[Job Number],0)),INDEX(tbl_Production[Current RMS No],MATCH(E42&"",tbl_Production[Job Number],0))),""),IF(H42="Consulting",IFERROR(INDEX(tbl_Consulting[Qwilr Quote],MATCH(E42&"",tbl_Consulting[Job Number],0)),""),"")))) | AC42: =IF(AB42="","",IF(AND(LEFT(AB42,4)<>"http",IF(H42="Production",set_RMSBase,set_QwilrBase)=""),"",HYPERLINK(IF(LEFT(AB42,4)="http",AB42,IF(H42="Production",set_RMSBase,set_QwilrBase)&AB42),"Open"))) | AD42: =IF(E42="","",IF(H42="Production",IFERROR(INDEX(tbl_Production[Total Expense],MATCH(E42&"",tbl_Production[Job Number],0)),0),IF(H42="Consulting",IFERROR(INDEX(tbl_Consulting[Total Expense],MATCH(E42&"",tbl_Consulting[Job Number],0)),0),0))) | AE42: =IF(E42="","",Y42-N(AD42)) | AF42: =IFERROR(AE42/Y42,"") | AG42: =IF(E42="","",IF(H42="Onsite",IFERROR(INDEX(tbl_Onsite[Notes],MATCH(E42&"",tbl_Onsite[Job Number],0)),""),IF(H42="Production",IFERROR(INDEX(tbl_Production[Notes],MATCH(E42&"",tbl_Production[Job Number],0)),""),IF(H42="Consulting",IFERROR(INDEX(tbl_Consulting[Notes],MATCH(E42&"",tbl_Consulting[Job Number],0)),""),""))))
A43: 46265 | B43: =IF(A43="","",EOMONTH(A43,0)) | C43: INV-10606 | D43: CBA | E43: 1668 | F43: =IF(E43="","",IF(COUNTIF(lst_Jobs,E43&"")>0,"OK","CHECK")) | G43: 85720001CBPSCSJUN27 DEDICATED TECH | H43: Onsite | I43: ONSITE | J43: Contract | K43: GST 10% | L43: 510 | M43: =IF(L43="","",IF(K43="GST 10%",ROUND(L43*set_GSTRate,2),0)) | N43: =IF(L43="","",L43+M43) | O43: 41100 | P43: Y | Q43: N | T43: Invoiced | V43: =IF(COUNTA(A43,D43,C43,L43)=0,"",IF(A43="","No date - sits outside every month",IF(E43="","No job number",IF(F43="CHECK","Job number is not in the Xero job list",IF(I43="","No cost centre",IF(AND(P43="Y",C43=""),"Marked posted to Xero but has no invoice number",IF(AND(L43<>"",K43=""),"No tax code",IF(AND(L43<>"",O43=""),"No revenue GL code","")))))))) | W43: =IF(E43="","",IFERROR(INDEX(lst_JobName,MATCH(E43&"",lst_Jobs,0)),"")) | X43: =IF(E43="","",COUNTIFS(tbl_Finance[Job Number],E43&"",tbl_Finance[Ex GST],"<>")) | Y43: =IF(E43="","",SUMIFS(tbl_Finance[Ex GST],tbl_Finance[Job Number],E43&"")) | Z43: =IF(E43="","",SUMIFS(tbl_Finance[Ex GST],tbl_Finance[Job Number],E43&"",tbl_Finance[Xero Invoice No],"<>")) | AA43: =IF(E43="","",Y43-Z43) | AB43: =IF(E43="","",IF(H43="Onsite",IFERROR(INDEX(tbl_Onsite[Qwilr Quote],MATCH(E43&"",tbl_Onsite[Job Number],0)),""),IF(H43="Production",IFERROR(IF(INDEX(tbl_Production[Current RMS No],MATCH(E43&"",tbl_Production[Job Number],0))="",INDEX(tbl_Production[Qwilr Quote],MATCH(E43&"",tbl_Production[Job Number],0)),INDEX(tbl_Production[Current RMS No],MATCH(E43&"",tbl_Production[Job Number],0))),""),IF(H43="Consulting",IFERROR(INDEX(tbl_Consulting[Qwilr Quote],MATCH(E43&"",tbl_Consulting[Job Number],0)),""),"")))) | AC43: =IF(AB43="","",IF(AND(LEFT(AB43,4)<>"http",IF(H43="Production",set_RMSBase,set_QwilrBase)=""),"",HYPERLINK(IF(LEFT(AB43,4)="http",AB43,IF(H43="Production",set_RMSBase,set_QwilrBase)&AB43),"Open"))) | AD43: =IF(E43="","",IF(H43="Production",IFERROR(INDEX(tbl_Production[Total Expense],MATCH(E43&"",tbl_Production[Job Number],0)),0),IF(H43="Consulting",IFERROR(INDEX(tbl_Consulting[Total Expense],MATCH(E43&"",tbl_Consulting[Job Number],0)),0),0))) | AE43: =IF(E43="","",Y43-N(AD43)) | AF43: =IFERROR(AE43/Y43,"") | AG43: =IF(E43="","",IF(H43="Onsite",IFERROR(INDEX(tbl_Onsite[Notes],MATCH(E43&"",tbl_Onsite[Job Number],0)),""),IF(H43="Production",IFERROR(INDEX(tbl_Production[Notes],MATCH(E43&"",tbl_Production[Job Number],0)),""),IF(H43="Consulting",IFERROR(INDEX(tbl_Consulting[Notes],MATCH(E43&"",tbl_Consulting[Job Number],0)),""),""))))
A44: 46265 | B44: =IF(A44="","",EOMONTH(A44,0)) | C44: INV-10607 | D44: CBA | E44: 1668 | F44: =IF(E44="","",IF(COUNTIF(lst_Jobs,E44&"")>0,"OK","CHECK")) | G44: 85720001CBPSCSJUN27 DEDICATED TECH | H44: Onsite | I44: ONSITE | J44: Contract | K44: GST 10% | L44: 510 | M44: =IF(L44="","",IF(K44="GST 10%",ROUND(L44*set_GSTRate,2),0)) | N44: =IF(L44="","",L44+M44) | O44: 41100 | P44: Y | Q44: N | T44: Invoiced | V44: =IF(COUNTA(A44,D44,C44,L44)=0,"",IF(A44="","No date - sits outside every month",IF(E44="","No job number",IF(F44="CHECK","Job number is not in the Xero job list",IF(I44="","No cost centre",IF(AND(P44="Y",C44=""),"Marked posted to Xero but has no invoice number",IF(AND(L44<>"",K44=""),"No tax code",IF(AND(L44<>"",O44=""),"No revenue GL code","")))))))) | W44: =IF(E44="","",IFERROR(INDEX(lst_JobName,MATCH(E44&"",lst_Jobs,0)),"")) | X44: =IF(E44="","",COUNTIFS(tbl_Finance[Job Number],E44&"",tbl_Finance[Ex GST],"<>")) | Y44: =IF(E44="","",SUMIFS(tbl_Finance[Ex GST],tbl_Finance[Job Number],E44&"")) | Z44: =IF(E44="","",SUMIFS(tbl_Finance[Ex GST],tbl_Finance[Job Number],E44&"",tbl_Finance[Xero Invoice No],"<>")) | AA44: =IF(E44="","",Y44-Z44) | AB44: =IF(E44="","",IF(H44="Onsite",IFERROR(INDEX(tbl_Onsite[Qwilr Quote],MATCH(E44&"",tbl_Onsite[Job Number],0)),""),IF(H44="Production",IFERROR(IF(INDEX(tbl_Production[Current RMS No],MATCH(E44&"",tbl_Production[Job Number],0))="",INDEX(tbl_Production[Qwilr Quote],MATCH(E44&"",tbl_Production[Job Number],0)),INDEX(tbl_Production[Current RMS No],MATCH(E44&"",tbl_Production[Job Number],0))),""),IF(H44="Consulting",IFERROR(INDEX(tbl_Consulting[Qwilr Quote],MATCH(E44&"",tbl_Consulting[Job Number],0)),""),"")))) | AC44: =IF(AB44="","",IF(AND(LEFT(AB44,4)<>"http",IF(H44="Production",set_RMSBase,set_QwilrBase)=""),"",HYPERLINK(IF(LEFT(AB44,4)="http",AB44,IF(H44="Production",set_RMSBase,set_QwilrBase)&AB44),"Open"))) | AD44: =IF(E44="","",IF(H44="Production",IFERROR(INDEX(tbl_Production[Total Expense],MATCH(E44&"",tbl_Production[Job Number],0)),0),IF(H44="Consulting",IFERROR(INDEX(tbl_Consulting[Total Expense],MATCH(E44&"",tbl_Consulting[Job Number],0)),0),0))) | AE44: =IF(E44="","",Y44-N(AD44)) | AF44: =IFERROR(AE44/Y44,"") | AG44: =IF(E44="","",IF(H44="Onsite",IFERROR(INDEX(tbl_Onsite[Notes],MATCH(E44&"",tbl_Onsite[Job Number],0)),""),IF(H44="Production",IFERROR(INDEX(tbl_Production[Notes],MATCH(E44&"",tbl_Production[Job Number],0)),""),IF(H44="Consulting",IFERROR(INDEX(tbl_Consulting[Notes],MATCH(E44&"",tbl_Consulting[Job Number],0)),""),""))))
A45: 46265 | B45: =IF(A45="","",EOMONTH(A45,0)) | C45: INV-10608 | D45: CBA | E45: 1668 | F45: =IF(E45="","",IF(COUNTIF(lst_Jobs,E45&"")>0,"OK","CHECK")) | G45: 85720001CBPSCSJUN27 DEDICATED TECH | H45: Onsite | I45: ONSITE | J45: Contract | K45: GST 10% | L45: 340 | M45: =IF(L45="","",IF(K45="GST 10%",ROUND(L45*set_GSTRate,2),0)) | N45: =IF(L45="","",L45+M45) | O45: 41100 | P45: Y | Q45: N | T45: Invoiced | V45: =IF(COUNTA(A45,D45,C45,L45)=0,"",IF(A45="","No date - sits outside every month",IF(E45="","No job number",IF(F45="CHECK","Job number is not in the Xero job list",IF(I45="","No cost centre",IF(AND(P45="Y",C45=""),"Marked posted to Xero but has no invoice number",IF(AND(L45<>"",K45=""),"No tax code",IF(AND(L45<>"",O45=""),"No revenue GL code","")))))))) | W45: =IF(E45="","",IFERROR(INDEX(lst_JobName,MATCH(E45&"",lst_Jobs,0)),"")) | X45: =IF(E45="","",COUNTIFS(tbl_Finance[Job Number],E45&"",tbl_Finance[Ex GST],"<>")) | Y45: =IF(E45="","",SUMIFS(tbl_Finance[Ex GST],tbl_Finance[Job Number],E45&"")) | Z45: =IF(E45="","",SUMIFS(tbl_Finance[Ex GST],tbl_Finance[Job Number],E45&"",tbl_Finance[Xero Invoice No],"<>")) | AA45: =IF(E45="","",Y45-Z45) | AB45: =IF(E45="","",IF(H45="Onsite",IFERROR(INDEX(tbl_Onsite[Qwilr Quote],MATCH(E45&"",tbl_Onsite[Job Number],0)),""),IF(H45="Production",IFERROR(IF(INDEX(tbl_Production[Current RMS No],MATCH(E45&"",tbl_Production[Job Number],0))="",INDEX(tbl_Production[Qwilr Quote],MATCH(E45&"",tbl_Production[Job Number],0)),INDEX(tbl_Production[Current RMS No],MATCH(E45&"",tbl_Production[Job Number],0))),""),IF(H45="Consulting",IFERROR(INDEX(tbl_Consulting[Qwilr Quote],MATCH(E45&"",tbl_Consulting[Job Number],0)),""),"")))) | AC45: =IF(AB45="","",IF(AND(LEFT(AB45,4)<>"http",IF(H45="Production",set_RMSBase,set_QwilrBase)=""),"",HYPERLINK(IF(LEFT(AB45,4)="http",AB45,IF(H45="Production",set_RMSBase,set_QwilrBase)&AB45),"Open"))) | AD45: =IF(E45="","",IF(H45="Production",IFERROR(INDEX(tbl_Production[Total Expense],MATCH(E45&"",tbl_Production[Job Number],0)),0),IF(H45="Consulting",IFERROR(INDEX(tbl_Consulting[Total Expense],MATCH(E45&"",tbl_Consulting[Job Number],0)),0),0))) | AE45: =IF(E45="","",Y45-N(AD45)) | AF45: =IFERROR(AE45/Y45,"") | AG45: =IF(E45="","",IF(H45="Onsite",IFERROR(INDEX(tbl_Onsite[Notes],MATCH(E45&"",tbl_Onsite[Job Number],0)),""),IF(H45="Production",IFERROR(INDEX(tbl_Production[Notes],MATCH(E45&"",tbl_Production[Job Number],0)),""),IF(H45="Consulting",IFERROR(INDEX(tbl_Consulting[Notes],MATCH(E45&"",tbl_Consulting[Job Number],0)),""),""))))
A46: 46265 | B46: =IF(A46="","",EOMONTH(A46,0)) | C46: INV-10609 | D46: CBA | E46: 1668 | F46: =IF(E46="","",IF(COUNTIF(lst_Jobs,E46&"")>0,"OK","CHECK")) | G46: 85720001CBPSCSJUN27 DEDICATED TECH | H46: Onsite | I46: ONSITE | J46: Contract | K46: GST 10% | L46: 425 | M46: =IF(L46="","",IF(K46="GST 10%",ROUND(L46*set_GSTRate,2),0)) | N46: =IF(L46="","",L46+M46) | O46: 41100 | P46: Y | Q46: N | T46: Invoiced | V46: =IF(COUNTA(A46,D46,C46,L46)=0,"",IF(A46="","No date - sits outside every month",IF(E46="","No job number",IF(F46="CHECK","Job number is not in the Xero job list",IF(I46="","No cost centre",IF(AND(P46="Y",C46=""),"Marked posted to Xero but has no invoice number",IF(AND(L46<>"",K46=""),"No tax code",IF(AND(L46<>"",O46=""),"No revenue GL code","")))))))) | W46: =IF(E46="","",IFERROR(INDEX(lst_JobName,MATCH(E46&"",lst_Jobs,0)),"")) | X46: =IF(E46="","",COUNTIFS(tbl_Finance[Job Number],E46&"",tbl_Finance[Ex GST],"<>")) | Y46: =IF(E46="","",SUMIFS(tbl_Finance[Ex GST],tbl_Finance[Job Number],E46&"")) | Z46: =IF(E46="","",SUMIFS(tbl_Finance[Ex GST],tbl_Finance[Job Number],E46&"",tbl_Finance[Xero Invoice No],"<>")) | AA46: =IF(E46="","",Y46-Z46) | AB46: =IF(E46="","",IF(H46="Onsite",IFERROR(INDEX(tbl_Onsite[Qwilr Quote],MATCH(E46&"",tbl_Onsite[Job Number],0)),""),IF(H46="Production",IFERROR(IF(INDEX(tbl_Production[Current RMS No],MATCH(E46&"",tbl_Production[Job Number],0))="",INDEX(tbl_Production[Qwilr Quote],MATCH(E46&"",tbl_Production[Job Number],0)),INDEX(tbl_Production[Current RMS No],MATCH(E46&"",tbl_Production[Job Number],0))),""),IF(H46="Consulting",IFERROR(INDEX(tbl_Consulting[Qwilr Quote],MATCH(E46&"",tbl_Consulting[Job Number],0)),""),"")))) | AC46: =IF(AB46="","",IF(AND(LEFT(AB46,4)<>"http",IF(H46="Production",set_RMSBase,set_QwilrBase)=""),"",HYPERLINK(IF(LEFT(AB46,4)="http",AB46,IF(H46="Production",set_RMSBase,set_QwilrBase)&AB46),"Open"))) | AD46: =IF(E46="","",IF(H46="Production",IFERROR(INDEX(tbl_Production[Total Expense],MATCH(E46&"",tbl_Production[Job Number],0)),0),IF(H46="Consulting",IFERROR(INDEX(tbl_Consulting[Total Expense],MATCH(E46&"",tbl_Consulting[Job Number],0)),0),0))) | AE46: =IF(E46="","",Y46-N(AD46)) | AF46: =IFERROR(AE46/Y46,"") | AG46: =IF(E46="","",IF(H46="Onsite",IFERROR(INDEX(tbl_Onsite[Notes],MATCH(E46&"",tbl_Onsite[Job Number],0)),""),IF(H46="Production",IFERROR(INDEX(tbl_Production[Notes],MATCH(E46&"",tbl_Production[Job Number],0)),""),IF(H46="Consulting",IFERROR(INDEX(tbl_Consulting[Notes],MATCH(E46&"",tbl_Consulting[Job Number],0)),""),""))))
A47: 46265 | B47: =IF(A47="","",EOMONTH(A47,0)) | C47: INV-10610 | D47: CBA | E47: 1668 | F47: =IF(E47="","",IF(COUNTIF(lst_Jobs,E47&"")>0,"OK","CHECK")) | G47: 85720001CBPSCSJUN27 DEDICATED TECH | H47: Onsite | I47: ONSITE | J47: Contract | K47: GST 10% | L47: 595 | M47: =IF(L47="","",IF(K47="GST 10%",ROUND(L47*set_GSTRate,2),0)) | N47: =IF(L47="","",L47+M47) | O47: 41100 | P47: Y | Q47: N | T47: Invoiced | V47: =IF(COUNTA(A47,D47,C47,L47)=0,"",IF(A47="","No date - sits outside every month",IF(E47="","No job number",IF(F47="CHECK","Job number is not in the Xero job list",IF(I47="","No cost centre",IF(AND(P47="Y",C47=""),"Marked posted to Xero but has no invoice number",IF(AND(L47<>"",K47=""),"No tax code",IF(AND(L47<>"",O47=""),"No revenue GL code","")))))))) | W47: =IF(E47="","",IFERROR(INDEX(lst_JobName,MATCH(E47&"",lst_Jobs,0)),"")) | X47: =IF(E47="","",COUNTIFS(tbl_Finance[Job Number],E47&"",tbl_Finance[Ex GST],"<>")) | Y47: =IF(E47="","",SUMIFS(tbl_Finance[Ex GST],tbl_Finance[Job Number],E47&"")) | Z47: =IF(E47="","",SUMIFS(tbl_Finance[Ex GST],tbl_Finance[Job Number],E47&"",tbl_Finance[Xero Invoice No],"<>")) | AA47: =IF(E47="","",Y47-Z47) | AB47: =IF(E47="","",IF(H47="Onsite",IFERROR(INDEX(tbl_Onsite[Qwilr Quote],MATCH(E47&"",tbl_Onsite[Job Number],0)),""),IF(H47="Production",IFERROR(IF(INDEX(tbl_Production[Current RMS No],MATCH(E47&"",tbl_Production[Job Number],0))="",INDEX(tbl_Production[Qwilr Quote],MATCH(E47&"",tbl_Production[Job Number],0)),INDEX(tbl_Production[Current RMS No],MATCH(E47&"",tbl_Production[Job Number],0))),""),IF(H47="Consulting",IFERROR(INDEX(tbl_Consulting[Qwilr Quote],MATCH(E47&"",tbl_Consulting[Job Number],0)),""),"")))) | AC47: =IF(AB47="","",IF(AND(LEFT(AB47,4)<>"http",IF(H47="Production",set_RMSBase,set_QwilrBase)=""),"",HYPERLINK(IF(LEFT(AB47,4)="http",AB47,IF(H47="Production",set_RMSBase,set_QwilrBase)&AB47),"Open"))) | AD47: =IF(E47="","",IF(H47="Production",IFERROR(INDEX(tbl_Production[Total Expense],MATCH(E47&"",tbl_Production[Job Number],0)),0),IF(H47="Consulting",IFERROR(INDEX(tbl_Consulting[Total Expense],MATCH(E47&"",tbl_Consulting[Job Number],0)),0),0))) | AE47: =IF(E47="","",Y47-N(AD47)) | AF47: =IFERROR(AE47/Y47,"") | AG47: =IF(E47="","",IF(H47="Onsite",IFERROR(INDEX(tbl_Onsite[Notes],MATCH(E47&"",tbl_Onsite[Job Number],0)),""),IF(H47="Production",IFERROR(INDEX(tbl_Production[Notes],MATCH(E47&"",tbl_Production[Job Number],0)),""),IF(H47="Consulting",IFERROR(INDEX(tbl_Consulting[Notes],MATCH(E47&"",tbl_Consulting[Job Number],0)),""),""))))
A48: 46265 | B48: =IF(A48="","",EOMONTH(A48,0)) | C48: INV-10614 | D48: CBA | E48: 585, 586 | F48: =IF(E48="","",IF(COUNTIF(lst_Jobs,E48&"")>0,"OK","CHECK")) | G48: 85720001CBPSCSJUN27 | H48: Onsite | I48: ONSITE | J48: Contract | K48: GST 10% | L48: 22680 | M48: =IF(L48="","",IF(K48="GST 10%",ROUND(L48*set_GSTRate,2),0)) | N48: =IF(L48="","",L48+M48) | O48: 41100 | P48: Y | Q48: N | T48: Invoiced | V48: =IF(COUNTA(A48,D48,C48,L48)=0,"",IF(A48="","No date - sits outside every month",IF(E48="","No job number",IF(F48="CHECK","Job number is not in the Xero job list",IF(I48="","No cost centre",IF(AND(P48="Y",C48=""),"Marked posted to Xero but has no invoice number",IF(AND(L48<>"",K48=""),"No tax code",IF(AND(L48<>"",O48=""),"No revenue GL code","")))))))) | W48: =IF(E48="","",IFERROR(INDEX(lst_JobName,MATCH(E48&"",lst_Jobs,0)),"")) | X48: =IF(E48="","",COUNTIFS(tbl_Finance[Job Number],E48&"",tbl_Finance[Ex GST],"<>")) | Y48: =IF(E48="","",SUMIFS(tbl_Finance[Ex GST],tbl_Finance[Job Number],E48&"")) | Z48: =IF(E48="","",SUMIFS(tbl_Finance[Ex GST],tbl_Finance[Job Number],E48&"",tbl_Finance[Xero Invoice No],"<>")) | AA48: =IF(E48="","",Y48-Z48) | AB48: =IF(E48="","",IF(H48="Onsite",IFERROR(INDEX(tbl_Onsite[Qwilr Quote],MATCH(E48&"",tbl_Onsite[Job Number],0)),""),IF(H48="Production",IFERROR(IF(INDEX(tbl_Production[Current RMS No],MATCH(E48&"",tbl_Production[Job Number],0))="",INDEX(tbl_Production[Qwilr Quote],MATCH(E48&"",tbl_Production[Job Number],0)),INDEX(tbl_Production[Current RMS No],MATCH(E48&"",tbl_Production[Job Number],0))),""),IF(H48="Consulting",IFERROR(INDEX(tbl_Consulting[Qwilr Quote],MATCH(E48&"",tbl_Consulting[Job Number],0)),""),"")))) | AC48: =IF(AB48="","",IF(AND(LEFT(AB48,4)<>"http",IF(H48="Production",set_RMSBase,set_QwilrBase)=""),"",HYPERLINK(IF(LEFT(AB48,4)="http",AB48,IF(H48="Production",set_RMSBase,set_QwilrBase)&AB48),"Open"))) | AD48: =IF(E48="","",IF(H48="Production",IFERROR(INDEX(tbl_Production[Total Expense],MATCH(E48&"",tbl_Production[Job Number],0)),0),IF(H48="Consulting",IFERROR(INDEX(tbl_Consulting[Total Expense],MATCH(E48&"",tbl_Consulting[Job Number],0)),0),0))) | AE48: =IF(E48="","",Y48-N(AD48)) | AF48: =IFERROR(AE48/Y48,"") | AG48: =IF(E48="","",IF(H48="Onsite",IFERROR(INDEX(tbl_Onsite[Notes],MATCH(E48&"",tbl_Onsite[Job Number],0)),""),IF(H48="Production",IFERROR(INDEX(tbl_Production[Notes],MATCH(E48&"",tbl_Production[Job Number],0)),""),IF(H48="Consulting",IFERROR(INDEX(tbl_Consulting[Notes],MATCH(E48&"",tbl_Consulting[Job Number],0)),""),""))))
A49: 46265 | B49: =IF(A49="","",EOMONTH(A49,0)) | C49: INV-10613 | D49: CBA | E49: 587 | F49: =IF(E49="","",IF(COUNTIF(lst_Jobs,E49&"")>0,"OK","CHECK")) | G49: 85720001CBSCSJUN27 | H49: Onsite | I49: ONSITE | J49: Contract | K49: GST 10% | L49: 10197.88 | M49: =IF(L49="","",IF(K49="GST 10%",ROUND(L49*set_GSTRate,2),0)) | N49: =IF(L49="","",L49+M49) | O49: 41100 | P49: Y | Q49: N | T49: Invoiced | V49: =IF(COUNTA(A49,D49,C49,L49)=0,"",IF(A49="","No date - sits outside every month",IF(E49="","No job number",IF(F49="CHECK","Job number is not in the Xero job list",IF(I49="","No cost centre",IF(AND(P49="Y",C49=""),"Marked posted to Xero but has no invoice number",IF(AND(L49<>"",K49=""),"No tax code",IF(AND(L49<>"",O49=""),"No revenue GL code","")))))))) | W49: =IF(E49="","",IFERROR(INDEX(lst_JobName,MATCH(E49&"",lst_Jobs,0)),"")) | X49: =IF(E49="","",COUNTIFS(tbl_Finance[Job Number],E49&"",tbl_Finance[Ex GST],"<>")) | Y49: =IF(E49="","",SUMIFS(tbl_Finance[Ex GST],tbl_Finance[Job Number],E49&"")) | Z49: =IF(E49="","",SUMIFS(tbl_Finance[Ex GST],tbl_Finance[Job Number],E49&"",tbl_Finance[Xero Invoice No],"<>")) | AA49: =IF(E49="","",Y49-Z49) | AB49: =IF(E49="","",IF(H49="Onsite",IFERROR(INDEX(tbl_Onsite[Qwilr Quote],MATCH(E49&"",tbl_Onsite[Job Number],0)),""),IF(H49="Production",IFERROR(IF(INDEX(tbl_Production[Current RMS No],MATCH(E49&"",tbl_Production[Job Number],0))="",INDEX(tbl_Production[Qwilr Quote],MATCH(E49&"",tbl_Production[Job Number],0)),INDEX(tbl_Production[Current RMS No],MATCH(E49&"",tbl_Production[Job Number],0))),""),IF(H49="Consulting",IFERROR(INDEX(tbl_Consulting[Qwilr Quote],MATCH(E49&"",tbl_Consulting[Job Number],0)),""),"")))) | AC49: =IF(AB49="","",IF(AND(LEFT(AB49,4)<>"http",IF(H49="Production",set_RMSBase,set_QwilrBase)=""),"",HYPERLINK(IF(LEFT(AB49,4)="http",AB49,IF(H49="Production",set_RMSBase,set_QwilrBase)&AB49),"Open"))) | AD49: =IF(E49="","",IF(H49="Production",IFERROR(INDEX(tbl_Production[Total Expense],MATCH(E49&"",tbl_Production[Job Number],0)),0),IF(H49="Consulting",IFERROR(INDEX(tbl_Consulting[Total Expense],MATCH(E49&"",tbl_Consulting[Job Number],0)),0),0))) | AE49: =IF(E49="","",Y49-N(AD49)) | AF49: =IFERROR(AE49/Y49,"") | AG49: =IF(E49="","",IF(H49="Onsite",IFERROR(INDEX(tbl_Onsite[Notes],MATCH(E49&"",tbl_Onsite[Job Number],0)),""),IF(H49="Production",IFERROR(INDEX(tbl_Production[Notes],MATCH(E49&"",tbl_Production[Job Number],0)),""),IF(H49="Consulting",IFERROR(INDEX(tbl_Consulting[Notes],MATCH(E49&"",tbl_Consulting[Job Number],0)),""),""))))
A50: 46265 | B50: =IF(A50="","",EOMONTH(A50,0)) | C50: INV-10602 | D50: CBA | E50: 1668 | F50: =IF(E50="","",IF(COUNTIF(lst_Jobs,E50&"")>0,"OK","CHECK")) | G50: 85720001CBPSCSJUN27 DEDICATED TECH | H50: Onsite | I50: ONSITE | J50: Contract | K50: GST 10% | L50: 170 | M50: =IF(L50="","",IF(K50="GST 10%",ROUND(L50*set_GSTRate,2),0)) | N50: =IF(L50="","",L50+M50) | O50: 41100 | P50: Y | Q50: N | T50: Invoiced | V50: =IF(COUNTA(A50,D50,C50,L50)=0,"",IF(A50="","No date - sits outside every month",IF(E50="","No job number",IF(F50="CHECK","Job number is not in the Xero job list",IF(I50="","No cost centre",IF(AND(P50="Y",C50=""),"Marked posted to Xero but has no invoice number",IF(AND(L50<>"",K50=""),"No tax code",IF(AND(L50<>"",O50=""),"No revenue GL code","")))))))) | W50: =IF(E50="","",IFERROR(INDEX(lst_JobName,MATCH(E50&"",lst_Jobs,0)),"")) | X50: =IF(E50="","",COUNTIFS(tbl_Finance[Job Number],E50&"",tbl_Finance[Ex GST],"<>")) | Y50: =IF(E50="","",SUMIFS(tbl_Finance[Ex GST],tbl_Finance[Job Number],E50&"")) | Z50: =IF(E50="","",SUMIFS(tbl_Finance[Ex GST],tbl_Finance[Job Number],E50&"",tbl_Finance[Xero Invoice No],"<>")) | AA50: =IF(E50="","",Y50-Z50) | AB50: =IF(E50="","",IF(H50="Onsite",IFERROR(INDEX(tbl_Onsite[Qwilr Quote],MATCH(E50&"",tbl_Onsite[Job Number],0)),""),IF(H50="Production",IFERROR(IF(INDEX(tbl_Production[Current RMS No],MATCH(E50&"",tbl_Production[Job Number],0))="",INDEX(tbl_Production[Qwilr Quote],MATCH(E50&"",tbl_Production[Job Number],0)),INDEX(tbl_Production[Current RMS No],MATCH(E50&"",tbl_Production[Job Number],0))),""),IF(H50="Consulting",IFERROR(INDEX(tbl_Consulting[Qwilr Quote],MATCH(E50&"",tbl_Consulting[Job Number],0)),""),"")))) | AC50: =IF(AB50="","",IF(AND(LEFT(AB50,4)<>"http",IF(H50="Production",set_RMSBase,set_QwilrBase)=""),"",HYPERLINK(IF(LEFT(AB50,4)="http",AB50,IF(H50="Production",set_RMSBase,set_QwilrBase)&AB50),"Open"))) | AD50: =IF(E50="","",IF(H50="Production",IFERROR(INDEX(tbl_Production[Total Expense],MATCH(E50&"",tbl_Production[Job Number],0)),0),IF(H50="Consulting",IFERROR(INDEX(tbl_Consulting[Total Expense],MATCH(E50&"",tbl_Consulting[Job Number],0)),0),0))) | AE50: =IF(E50="","",Y50-N(AD50)) | AF50: =IFERROR(AE50/Y50,"") | AG50: =IF(E50="","",IF(H50="Onsite",IFERROR(INDEX(tbl_Onsite[Notes],MATCH(E50&"",tbl_Onsite[Job Number],0)),""),IF(H50="Production",IFERROR(INDEX(tbl_Production[Notes],MATCH(E50&"",tbl_Production[Job Number],0)),""),IF(H50="Consulting",IFERROR(INDEX(tbl_Consulting[Notes],MATCH(E50&"",tbl_Consulting[Job Number],0)),""),""))))
A51: 46265 | B51: =IF(A51="","",EOMONTH(A51,0)) | C51: INV-10618 | D51: Ricoh Australia Pty Ltd | E51: 2880 | F51: =IF(E51="","",IF(COUNTIF(lst_Jobs,E51&"")>0,"OK","CHECK")) | G51: CONTRACT | H51: Onsite | I51: ONSITE | J51: Contract | K51: GST 10% | L51: 11860.56 | M51: =IF(L51="","",IF(K51="GST 10%",ROUND(L51*set_GSTRate,2),0)) | N51: =IF(L51="","",L51+M51) | O51: 41100 | P51: Y | Q51: N | T51: Invoiced | V51: =IF(COUNTA(A51,D51,C51,L51)=0,"",IF(A51="","No date - sits outside every month",IF(E51="","No job number",IF(F51="CHECK","Job number is not in the Xero job list",IF(I51="","No cost centre",IF(AND(P51="Y",C51=""),"Marked posted to Xero but has no invoice number",IF(AND(L51<>"",K51=""),"No tax code",IF(AND(L51<>"",O51=""),"No revenue GL code","")))))))) | W51: =IF(E51="","",IFERROR(INDEX(lst_JobName,MATCH(E51&"",lst_Jobs,0)),"")) | X51: =IF(E51="","",COUNTIFS(tbl_Finance[Job Number],E51&"",tbl_Finance[Ex GST],"<>")) | Y51: =IF(E51="","",SUMIFS(tbl_Finance[Ex GST],tbl_Finance[Job Number],E51&"")) | Z51: =IF(E51="","",SUMIFS(tbl_Finance[Ex GST],tbl_Finance[Job Number],E51&"",tbl_Finance[Xero Invoice No],"<>")) | AA51: =IF(E51="","",Y51-Z51) | AB51: =IF(E51="","",IF(H51="Onsite",IFERROR(INDEX(tbl_Onsite[Qwilr Quote],MATCH(E51&"",tbl_Onsite[Job Number],0)),""),IF(H51="Production",IFERROR(IF(INDEX(tbl_Production[Current RMS No],MATCH(E51&"",tbl_Production[Job Number],0))="",INDEX(tbl_Production[Qwilr Quote],MATCH(E51&"",tbl_Production[Job Number],0)),INDEX(tbl_Production[Current RMS No],MATCH(E51&"",tbl_Production[Job Number],0))),""),IF(H51="Consulting",IFERROR(INDEX(tbl_Consulting[Qwilr Quote],MATCH(E51&"",tbl_Consulting[Job Number],0)),""),"")))) | AC51: =IF(AB51="","",IF(AND(LEFT(AB51,4)<>"http",IF(H51="Production",set_RMSBase,set_QwilrBase)=""),"",HYPERLINK(IF(LEFT(AB51,4)="http",AB51,IF(H51="Production",set_RMSBase,set_QwilrBase)&AB51),"Open"))) | AD51: =IF(E51="","",IF(H51="Production",IFERROR(INDEX(tbl_Production[Total Expense],MATCH(E51&"",tbl_Production[Job Number],0)),0),IF(H51="Consulting",IFERROR(INDEX(tbl_Consulting[Total Expense],MATCH(E51&"",tbl_Consulting[Job Number],0)),0),0))) | AE51: =IF(E51="","",Y51-N(AD51)) | AF51: =IFERROR(AE51/Y51,"") | AG51: =IF(E51="","",IF(H51="Onsite",IFERROR(INDEX(tbl_Onsite[Notes],MATCH(E51&"",tbl_Onsite[Job Number],0)),""),IF(H51="Production",IFERROR(INDEX(tbl_Production[Notes],MATCH(E51&"",tbl_Production[Job Number],0)),""),IF(H51="Consulting",IFERROR(INDEX(tbl_Consulting[Notes],MATCH(E51&"",tbl_Consulting[Job Number],0)),""),""))))
B52: =IF(A52="","",EOMONTH(A52,0)) | D52: DTTL | E52: 26073103 | F52: =IF(E52="","",IF(COUNTIF(lst_Jobs,E52&"")>0,"OK","CHECK")) | G52: Perth AV & Hospitality Technician (SEP26-FEB27) | H52: Onsite | I52: ONSITE | J52: Contract | K52: GST 10% | M52: =IF(L52="","",IF(K52="GST 10%",ROUND(L52*set_GSTRate,2),0)) | N52: =IF(L52="","",L52+M52) | O52: 41100 | P52: N | Q52: N | T52: To Invoice | U52: https://protect.checkpoint.com/v2/r04/___https://app.qwilr.com/%23/page/6a6fe5279de8ab6be4a65917___.Y3A0YTpjb3Jwb3JhdGV0ZWNobm9sb2d5c2VydmljZXNwdHlsdGQ6YzpvOmI1YjBhMWJiMjVjM2UxZGViYmNmN2MyYzg2MGMwOGIwOjc6YjdkZDo5NzUxYWEwYjZkNTAxZWIyMGNiNmQ4OWExM2E0MmQ4OWQ0YjVkZmFkYjk0Y2UxYjUzODI4ODM5ODhhNzE3MTM4OnQ6VDpG | V52: =IF(COUNTA(A52,D52,C52,L52)=0,"",IF(A52="","No date - sits outside every month",IF(E52="","No job number",IF(F52="CHECK","Job number is not in the Xero job list",IF(I52="","No cost centre",IF(AND(P52="Y",C52=""),"Marked posted to Xero but has no invoice number",IF(AND(L52<>"",K52=""),"No tax code",IF(AND(L52<>"",O52=""),"No revenue GL code","")))))))) | W52: =IF(E52="","",IFERROR(INDEX(lst_JobName,MATCH(E52&"",lst_Jobs,0)),"")) | X52: =IF(E52="","",COUNTIFS(tbl_Finance[Job Number],E52&"",tbl_Finance[Ex GST],"<>")) | Y52: =IF(E52="","",SUMIFS(tbl_Finance[Ex GST],tbl_Finance[Job Number],E52&"")) | Z52: =IF(E52="","",SUMIFS(tbl_Finance[Ex GST],tbl_Finance[Job Number],E52&"",tbl_Finance[Xero Invoice No],"<>")) | AA52: =IF(E52="","",Y52-Z52) | AB52: =IF(E52="","",IF(H52="Onsite",IFERROR(INDEX(tbl_Onsite[Qwilr Quote],MATCH(E52&"",tbl_Onsite[Job Number],0)),""),IF(H52="Production",IFERROR(IF(INDEX(tbl_Production[Current RMS No],MATCH(E52&"",tbl_Production[Job Number],0))="",INDEX(tbl_Production[Qwilr Quote],MATCH(E52&"",tbl_Production[Job Number],0)),INDEX(tbl_Production[Current RMS No],MATCH(E52&"",tbl_Production[Job Number],0))),""),IF(H52="Consulting",IFERROR(INDEX(tbl_Consulting[Qwilr Quote],MATCH(E52&"",tbl_Consulting[Job Number],0)),""),"")))) | AC52: =IF(AB52="","",IF(AND(LEFT(AB52,4)<>"http",IF(H52="Production",set_RMSBase,set_QwilrBase)=""),"",HYPERLINK(IF(LEFT(AB52,4)="http",AB52,IF(H52="Production",set_RMSBase,set_QwilrBase)&AB52),"Open"))) | AD52: =IF(E52="","",IF(H52="Production",IFERROR(INDEX(tbl_Production[Total Expense],MATCH(E52&"",tbl_Production[Job Number],0)),0),IF(H52="Consulting",IFERROR(INDEX(tbl_Consulting[Total Expense],MATCH(E52&"",tbl_Consulting[Job Number],0)),0),0))) | AE52: =IF(E52="","",Y52-N(AD52)) | AF52: =IFERROR(AE52/Y52,"") | AG52: =IF(E52="","",IF(H52="Onsite",IFERROR(INDEX(tbl_Onsite[Notes],MATCH(E52&"",tbl_Onsite[Job Number],0)),""),IF(H52="Production",IFERROR(INDEX(tbl_Production[Notes],MATCH(E52&"",tbl_Production[Job Number],0)),""),IF(H52="Consulting",IFERROR(INDEX(tbl_Consulting[Notes],MATCH(E52&"",tbl_Consulting[Job Number],0)),""),""))))
A53: 46268 | B53: =IF(A53="","",EOMONTH(A53,0)) | C53: INV-10620 | D53: Ricoh Australia Pty Ltd | E53: 26082801 | F53: =IF(E53="","",IF(COUNTIF(lst_Jobs,E53&"")>0,"OK","CHECK")) | G53: Ricoh Australia - SHELL AV Support | H53: Onsite | I53: ONSITE | J53: Contract | K53: GST 10% | L53: 340 | M53: =IF(L53="","",IF(K53="GST 10%",ROUND(L53*set_GSTRate,2),0)) | N53: =IF(L53="","",L53+M53) | O53: 41100 | P53: Y | Q53: N | T53: Invoiced | U53: This was not actually for Shell - error in quote. End client was Wotton Kearney. | V53: =IF(COUNTA(A53,D53,C53,L53)=0,"",IF(A53="","No date - sits outside every month",IF(E53="","No job number",IF(F53="CHECK","Job number is not in the Xero job list",IF(I53="","No cost centre",IF(AND(P53="Y",C53=""),"Marked posted to Xero but has no invoice number",IF(AND(L53<>"",K53=""),"No tax code",IF(AND(L53<>"",O53=""),"No revenue GL code","")))))))) | W53: =IF(E53="","",IFERROR(INDEX(lst_JobName,MATCH(E53&"",lst_Jobs,0)),"")) | X53: =IF(E53="","",COUNTIFS(tbl_Finance[Job Number],E53&"",tbl_Finance[Ex GST],"<>")) | Y53: =IF(E53="","",SUMIFS(tbl_Finance[Ex GST],tbl_Finance[Job Number],E53&"")) | Z53: =IF(E53="","",SUMIFS(tbl_Finance[Ex GST],tbl_Finance[Job Number],E53&"",tbl_Finance[Xero Invoice No],"<>")) | AA53: =IF(E53="","",Y53-Z53) | AB53: =IF(E53="","",IF(H53="Onsite",IFERROR(INDEX(tbl_Onsite[Qwilr Quote],MATCH(E53&"",tbl_Onsite[Job Number],0)),""),IF(H53="Production",IFERROR(IF(INDEX(tbl_Production[Current RMS No],MATCH(E53&"",tbl_Production[Job Number],0))="",INDEX(tbl_Production[Qwilr Quote],MATCH(E53&"",tbl_Production[Job Number],0)),INDEX(tbl_Production[Current RMS No],MATCH(E53&"",tbl_Production[Job Number],0))),""),IF(H53="Consulting",IFERROR(INDEX(tbl_Consulting[Qwilr Quote],MATCH(E53&"",tbl_Consulting[Job Number],0)),""),"")))) | AC53: =IF(AB53="","",IF(AND(LEFT(AB53,4)<>"http",IF(H53="Production",set_RMSBase,set_QwilrBase)=""),"",HYPERLINK(IF(LEFT(AB53,4)="http",AB53,IF(H53="Production",set_RMSBase,set_QwilrBase)&AB53),"Open"))) | AD53: =IF(E53="","",IF(H53="Production",IFERROR(INDEX(tbl_Production[Total Expense],MATCH(E53&"",tbl_Production[Job Number],0)),0),IF(H53="Consulting",IFERROR(INDEX(tbl_Consulting[Total Expense],MATCH(E53&"",tbl_Consulting[Job Number],0)),0),0))) | AE53: =IF(E53="","",Y53-N(AD53)) | AF53: =IFERROR(AE53/Y53,"") | AG53: =IF(E53="","",IF(H53="Onsite",IFERROR(INDEX(tbl_Onsite[Notes],MATCH(E53&"",tbl_Onsite[Job Number],0)),""),IF(H53="Production",IFERROR(INDEX(tbl_Production[Notes],MATCH(E53&"",tbl_Production[Job Number],0)),""),IF(H53="Consulting",IFERROR(INDEX(tbl_Consulting[Notes],MATCH(E53&"",tbl_Consulting[Job Number],0)),""),""))))
B54: =IF(A54="","",EOMONTH(A54,0)) | D54: PWC | E54: 2608603 | F54: =IF(E54="","",IF(COUNTIF(lst_Jobs,E54&"")>0,"OK","CHECK")) | G54: Pool of Hours - National AV / IT Support | H54: Onsite | I54: ONSITE | J54: Contract | K54: GST 10% | L54: 8500 | M54: =IF(L54="","",IF(K54="GST 10%",ROUND(L54*set_GSTRate,2),0)) | N54: =IF(L54="","",L54+M54) | O54: 41100 | P54: N | Q54: N | T54: To Invoice | V54: =IF(COUNTA(A54,D54,C54,L54)=0,"",IF(A54="","No date - sits outside every month",IF(E54="","No job number",IF(F54="CHECK","Job number is not in the Xero job list",IF(I54="","No cost centre",IF(AND(P54="Y",C54=""),"Marked posted to Xero but has no invoice number",IF(AND(L54<>"",K54=""),"No tax code",IF(AND(L54<>"",O54=""),"No revenue GL code","")))))))) | W54: =IF(E54="","",IFERROR(INDEX(lst_JobName,MATCH(E54&"",lst_Jobs,0)),"")) | X54: =IF(E54="","",COUNTIFS(tbl_Finance[Job Number],E54&"",tbl_Finance[Ex GST],"<>")) | Y54: =IF(E54="","",SUMIFS(tbl_Finance[Ex GST],tbl_Finance[Job Number],E54&"")) | Z54: =IF(E54="","",SUMIFS(tbl_Finance[Ex GST],tbl_Finance[Job Number],E54&"",tbl_Finance[Xero Invoice No],"<>")) | AA54: =IF(E54="","",Y54-Z54) | AB54: =IF(E54="","",IF(H54="Onsite",IFERROR(INDEX(tbl_Onsite[Qwilr Quote],MATCH(E54&"",tbl_Onsite[Job Number],0)),""),IF(H54="Production",IFERROR(IF(INDEX(tbl_Production[Current RMS No],MATCH(E54&"",tbl_Production[Job Number],0))="",INDEX(tbl_Production[Qwilr Quote],MATCH(E54&"",tbl_Production[Job Number],0)),INDEX(tbl_Production[Current RMS No],MATCH(E54&"",tbl_Production[Job Number],0))),""),IF(H54="Consulting",IFERROR(INDEX(tbl_Consulting[Qwilr Quote],MATCH(E54&"",tbl_Consulting[Job Number],0)),""),"")))) | AC54: =IF(AB54="","",IF(AND(LEFT(AB54,4)<>"http",IF(H54="Production",set_RMSBase,set_QwilrBase)=""),"",HYPERLINK(IF(LEFT(AB54,4)="http",AB54,IF(H54="Production",set_RMSBase,set_QwilrBase)&AB54),"Open"))) | AD54: =IF(E54="","",IF(H54="Production",IFERROR(INDEX(tbl_Production[Total Expense],MATCH(E54&"",tbl_Production[Job Number],0)),0),IF(H54="Consulting",IFERROR(INDEX(tbl_Consulting[Total Expense],MATCH(E54&"",tbl_Consulting[Job Number],0)),0),0))) | AE54: =IF(E54="","",Y54-N(AD54)) | AF54: =IFERROR(AE54/Y54,"") | AG54: =IF(E54="","",IF(H54="Onsite",IFERROR(INDEX(tbl_Onsite[Notes],MATCH(E54&"",tbl_Onsite[Job Number],0)),""),IF(H54="Production",IFERROR(INDEX(tbl_Production[Notes],MATCH(E54&"",tbl_Production[Job Number],0)),""),IF(H54="Consulting",IFERROR(INDEX(tbl_Consulting[Notes],MATCH(E54&"",tbl_Consulting[Job Number],0)),""),""))))
B55: =IF(A55="","",EOMONTH(A55,0)) | D55: DTTL | E55: 26073107 | F55: =IF(E55="","",IF(COUNTIF(lst_Jobs,E55&"")>0,"OK","CHECK")) | G55: Technician Travel (ADL-HOB Return) | H55: Onsite | I55: ONSITE | J55: Contract | K55: GST 10% | L55: 7145 | M55: =IF(L55="","",IF(K55="GST 10%",ROUND(L55*set_GSTRate,2),0)) | N55: =IF(L55="","",L55+M55) | O55: 41100 | P55: N | Q55: N | T55: To Invoice | V55: =IF(COUNTA(A55,D55,C55,L55)=0,"",IF(A55="","No date - sits outside every month",IF(E55="","No job number",IF(F55="CHECK","Job number is not in the Xero job list",IF(I55="","No cost centre",IF(AND(P55="Y",C55=""),"Marked posted to Xero but has no invoice number",IF(AND(L55<>"",K55=""),"No tax code",IF(AND(L55<>"",O55=""),"No revenue GL code","")))))))) | W55: =IF(E55="","",IFERROR(INDEX(lst_JobName,MATCH(E55&"",lst_Jobs,0)),"")) | X55: =IF(E55="","",COUNTIFS(tbl_Finance[Job Number],E55&"",tbl_Finance[Ex GST],"<>")) | Y55: =IF(E55="","",SUMIFS(tbl_Finance[Ex GST],tbl_Finance[Job Number],E55&"")) | Z55: =IF(E55="","",SUMIFS(tbl_Finance[Ex GST],tbl_Finance[Job Number],E55&"",tbl_Finance[Xero Invoice No],"<>")) | AA55: =IF(E55="","",Y55-Z55) | AB55: =IF(E55="","",IF(H55="Onsite",IFERROR(INDEX(tbl_Onsite[Qwilr Quote],MATCH(E55&"",tbl_Onsite[Job Number],0)),""),IF(H55="Production",IFERROR(IF(INDEX(tbl_Production[Current RMS No],MATCH(E55&"",tbl_Production[Job Number],0))="",INDEX(tbl_Production[Qwilr Quote],MATCH(E55&"",tbl_Production[Job Number],0)),INDEX(tbl_Production[Current RMS No],MATCH(E55&"",tbl_Production[Job Number],0))),""),IF(H55="Consulting",IFERROR(INDEX(tbl_Consulting[Qwilr Quote],MATCH(E55&"",tbl_Consulting[Job Number],0)),""),"")))) | AC55: =IF(AB55="","",IF(AND(LEFT(AB55,4)<>"http",IF(H55="Production",set_RMSBase,set_QwilrBase)=""),"",HYPERLINK(IF(LEFT(AB55,4)="http",AB55,IF(H55="Production",set_RMSBase,set_QwilrBase)&AB55),"Open"))) | AD55: =IF(E55="","",IF(H55="Production",IFERROR(INDEX(tbl_Production[Total Expense],MATCH(E55&"",tbl_Production[Job Number],0)),0),IF(H55="Consulting",IFERROR(INDEX(tbl_Consulting[Total Expense],MATCH(E55&"",tbl_Consulting[Job Number],0)),0),0))) | AE55: =IF(E55="","",Y55-N(AD55)) | AF55: =IFERROR(AE55/Y55,"") | AG55: =IF(E55="","",IF(H55="Onsite",IFERROR(INDEX(tbl_Onsite[Notes],MATCH(E55&"",tbl_Onsite[Job Number],0)),""),IF(H55="Production",IFERROR(INDEX(tbl_Production[Notes],MATCH(E55&"",tbl_Production[Job Number],0)),""),IF(H55="Consulting",IFERROR(INDEX(tbl_Consulting[Notes],MATCH(E55&"",tbl_Consulting[Job Number],0)),""),""))))
B56: =IF(A56="","",EOMONTH(A56,0)) | D56: DTTL | E56: 2608502 | F56: =IF(E56="","",IF(COUNTIF(lst_Jobs,E56&"")>0,"OK","CHECK")) | G56: Change Maker | H56: Onsite | I56: ONSITE | J56: Contract | K56: GST 10% | L56: 1275 | M56: =IF(L56="","",IF(K56="GST 10%",ROUND(L56*set_GSTRate,2),0)) | N56: =IF(L56="","",L56+M56) | O56: 41100 | P56: N | Q56: N | T56: To Invoice | V56: =IF(COUNTA(A56,D56,C56,L56)=0,"",IF(A56="","No date - sits outside every month",IF(E56="","No job number",IF(F56="CHECK","Job number is not in the Xero job list",IF(I56="","No cost centre",IF(AND(P56="Y",C56=""),"Marked posted to Xero but has no invoice number",IF(AND(L56<>"",K56=""),"No tax code",IF(AND(L56<>"",O56=""),"No revenue GL code","")))))))) | W56: =IF(E56="","",IFERROR(INDEX(lst_JobName,MATCH(E56&"",lst_Jobs,0)),"")) | X56: =IF(E56="","",COUNTIFS(tbl_Finance[Job Number],E56&"",tbl_Finance[Ex GST],"<>")) | Y56: =IF(E56="","",SUMIFS(tbl_Finance[Ex GST],tbl_Finance[Job Number],E56&"")) | Z56: =IF(E56="","",SUMIFS(tbl_Finance[Ex GST],tbl_Finance[Job Number],E56&"",tbl_Finance[Xero Invoice No],"<>")) | AA56: =IF(E56="","",Y56-Z56) | AB56: =IF(E56="","",IF(H56="Onsite",IFERROR(INDEX(tbl_Onsite[Qwilr Quote],MATCH(E56&"",tbl_Onsite[Job Number],0)),""),IF(H56="Production",IFERROR(IF(INDEX(tbl_Production[Current RMS No],MATCH(E56&"",tbl_Production[Job Number],0))="",INDEX(tbl_Production[Qwilr Quote],MATCH(E56&"",tbl_Production[Job Number],0)),INDEX(tbl_Production[Current RMS No],MATCH(E56&"",tbl_Production[Job Number],0))),""),IF(H56="Consulting",IFERROR(INDEX(tbl_Consulting[Qwilr Quote],MATCH(E56&"",tbl_Consulting[Job Number],0)),""),"")))) | AC56: =IF(AB56="","",IF(AND(LEFT(AB56,4)<>"http",IF(H56="Production",set_RMSBase,set_QwilrBase)=""),"",HYPERLINK(IF(LEFT(AB56,4)="http",AB56,IF(H56="Production",set_RMSBase,set_QwilrBase)&AB56),"Open"))) | AD56: =IF(E56="","",IF(H56="Production",IFERROR(INDEX(tbl_Production[Total Expense],MATCH(E56&"",tbl_Production[Job Number],0)),0),IF(H56="Consulting",IFERROR(INDEX(tbl_Consulting[Total Expense],MATCH(E56&"",tbl_Consulting[Job Number],0)),0),0))) | AE56: =IF(E56="","",Y56-N(AD56)) | AF56: =IFERROR(AE56/Y56,"") | AG56: =IF(E56="","",IF(H56="Onsite",IFERROR(INDEX(tbl_Onsite[Notes],MATCH(E56&"",tbl_Onsite[Job Number],0)),""),IF(H56="Production",IFERROR(INDEX(tbl_Production[Notes],MATCH(E56&"",tbl_Production[Job Number],0)),""),IF(H56="Consulting",IFERROR(INDEX(tbl_Consulting[Notes],MATCH(E56&"",tbl_Consulting[Job Number],0)),""),""))))
B57: =IF(A57="","",EOMONTH(A57,0)) | D57: DTTL | E57: 26082704 | F57: =IF(E57="","",IF(COUNTIF(lst_Jobs,E57&"")>0,"OK","CHECK")) | G57: STL Travel (SYD-PER) | H57: Onsite | I57: ONSITE | J57: Contract | K57: GST 10% | L57: 7735 | M57: =IF(L57="","",IF(K57="GST 10%",ROUND(L57*set_GSTRate,2),0)) | N57: =IF(L57="","",L57+M57) | O57: 41100 | P57: N | Q57: N | T57: To Invoice | V57: =IF(COUNTA(A57,D57,C57,L57)=0,"",IF(A57="","No date - sits outside every month",IF(E57="","No job number",IF(F57="CHECK","Job number is not in the Xero job list",IF(I57="","No cost centre",IF(AND(P57="Y",C57=""),"Marked posted to Xero but has no invoice number",IF(AND(L57<>"",K57=""),"No tax code",IF(AND(L57<>"",O57=""),"No revenue GL code","")))))))) | W57: =IF(E57="","",IFERROR(INDEX(lst_JobName,MATCH(E57&"",lst_Jobs,0)),"")) | X57: =IF(E57="","",COUNTIFS(tbl_Finance[Job Number],E57&"",tbl_Finance[Ex GST],"<>")) | Y57: =IF(E57="","",SUMIFS(tbl_Finance[Ex GST],tbl_Finance[Job Number],E57&"")) | Z57: =IF(E57="","",SUMIFS(tbl_Finance[Ex GST],tbl_Finance[Job Number],E57&"",tbl_Finance[Xero Invoice No],"<>")) | AA57: =IF(E57="","",Y57-Z57) | AB57: =IF(E57="","",IF(H57="Onsite",IFERROR(INDEX(tbl_Onsite[Qwilr Quote],MATCH(E57&"",tbl_Onsite[Job Number],0)),""),IF(H57="Production",IFERROR(IF(INDEX(tbl_Production[Current RMS No],MATCH(E57&"",tbl_Production[Job Number],0))="",INDEX(tbl_Production[Qwilr Quote],MATCH(E57&"",tbl_Production[Job Number],0)),INDEX(tbl_Production[Current RMS No],MATCH(E57&"",tbl_Production[Job Number],0))),""),IF(H57="Consulting",IFERROR(INDEX(tbl_Consulting[Qwilr Quote],MATCH(E57&"",tbl_Consulting[Job Number],0)),""),"")))) | AC57: =IF(AB57="","",IF(AND(LEFT(AB57,4)<>"http",IF(H57="Production",set_RMSBase,set_QwilrBase)=""),"",HYPERLINK(IF(LEFT(AB57,4)="http",AB57,IF(H57="Production",set_RMSBase,set_QwilrBase)&AB57),"Open"))) | AD57: =IF(E57="","",IF(H57="Production",IFERROR(INDEX(tbl_Production[Total Expense],MATCH(E57&"",tbl_Production[Job Number],0)),0),IF(H57="Consulting",IFERROR(INDEX(tbl_Consulting[Total Expense],MATCH(E57&"",tbl_Consulting[Job Number],0)),0),0))) | AE57: =IF(E57="","",Y57-N(AD57)) | AF57: =IFERROR(AE57/Y57,"") | AG57: =IF(E57="","",IF(H57="Onsite",IFERROR(INDEX(tbl_Onsite[Notes],MATCH(E57&"",tbl_Onsite[Job Number],0)),""),IF(H57="Production",IFERROR(INDEX(tbl_Production[Notes],MATCH(E57&"",tbl_Production[Job Number],0)),""),IF(H57="Consulting",IFERROR(INDEX(tbl_Consulting[Notes],MATCH(E57&"",tbl_Consulting[Job Number],0)),""),""))))
B58: =IF(A58="","",EOMONTH(A58,0)) | D58: CBA | E58: 26043001 | F58: =IF(E58="","",IF(COUNTIF(lst_Jobs,E58&"")>0,"OK","CHECK")) | H58: Onsite | I58: ONSITE | J58: Contract | K58: GST 10% | M58: =IF(L58="","",IF(K58="GST 10%",ROUND(L58*set_GSTRate,2),0)) | N58: =IF(L58="","",L58+M58) | O58: 41100 | P58: N | Q58: N | T58: To Invoice | V58: =IF(COUNTA(A58,D58,C58,L58)=0,"",IF(A58="","No date - sits outside every month",IF(E58="","No job number",IF(F58="CHECK","Job number is not in the Xero job list",IF(I58="","No cost centre",IF(AND(P58="Y",C58=""),"Marked posted to Xero but has no invoice number",IF(AND(L58<>"",K58=""),"No tax code",IF(AND(L58<>"",O58=""),"No revenue GL code","")))))))) | W58: =IF(E58="","",IFERROR(INDEX(lst_JobName,MATCH(E58&"",lst_Jobs,0)),"")) | X58: =IF(E58="","",COUNTIFS(tbl_Finance[Job Number],E58&"",tbl_Finance[Ex GST],"<>")) | Y58: =IF(E58="","",SUMIFS(tbl_Finance[Ex GST],tbl_Finance[Job Number],E58&"")) | Z58: =IF(E58="","",SUMIFS(tbl_Finance[Ex GST],tbl_Finance[Job Number],E58&"",tbl_Finance[Xero Invoice No],"<>")) | AA58: =IF(E58="","",Y58-Z58) | AB58: =IF(E58="","",IF(H58="Onsite",IFERROR(INDEX(tbl_Onsite[Qwilr Quote],MATCH(E58&"",tbl_Onsite[Job Number],0)),""),IF(H58="Production",IFERROR(IF(INDEX(tbl_Production[Current RMS No],MATCH(E58&"",tbl_Production[Job Number],0))="",INDEX(tbl_Production[Qwilr Quote],MATCH(E58&"",tbl_Production[Job Number],0)),INDEX(tbl_Production[Current RMS No],MATCH(E58&"",tbl_Production[Job Number],0))),""),IF(H58="Consulting",IFERROR(INDEX(tbl_Consulting[Qwilr Quote],MATCH(E58&"",tbl_Consulting[Job Number],0)),""),"")))) | AC58: =IF(AB58="","",IF(AND(LEFT(AB58,4)<>"http",IF(H58="Production",set_RMSBase,set_QwilrBase)=""),"",HYPERLINK(IF(LEFT(AB58,4)="http",AB58,IF(H58="Production",set_RMSBase,set_QwilrBase)&AB58),"Open"))) | AD58: =IF(E58="","",IF(H58="Production",IFERROR(INDEX(tbl_Production[Total Expense],MATCH(E58&"",tbl_Production[Job Number],0)),0),IF(H58="Consulting",IFERROR(INDEX(tbl_Consulting[Total Expense],MATCH(E58&"",tbl_Consulting[Job Number],0)),0),0))) | AE58: =IF(E58="","",Y58-N(AD58)) | AF58: =IFERROR(AE58/Y58,"") | AG58: =IF(E58="","",IF(H58="Onsite",IFERROR(INDEX(tbl_Onsite[Notes],MATCH(E58&"",tbl_Onsite[Job Number],0)),""),IF(H58="Production",IFERROR(INDEX(tbl_Production[Notes],MATCH(E58&"",tbl_Production[Job Number],0)),""),IF(H58="Consulting",IFERROR(INDEX(tbl_Consulting[Notes],MATCH(E58&"",tbl_Consulting[Job Number],0)),""),""))))
A59: 46205 | B59: =IF(A59="","",EOMONTH(A59,0)) | C59: INV-10513 | D59: Elkiem | E59: 2602309 | F59: =IF(E59="","",IF(COUNTIF(lst_Jobs,E59&"")>0,"OK","CHECK")) | G59: Studio Support | 1.7.26 | H59: Production | I59: PRODUCTION | J59: Project | K59: GST 10% | L59: 380 | M59: =IF(L59="","",IF(K59="GST 10%",ROUND(L59*set_GSTRate,2),0)) | N59: =IF(L59="","",L59+M59) | O59: 42100 | P59: Y | Q59: N | T59: Invoiced | V59: =IF(COUNTA(A59,D59,C59,L59)=0,"",IF(A59="","No date - sits outside every month",IF(E59="","No job number",IF(F59="CHECK","Job number is not in the Xero job list",IF(I59="","No cost centre",IF(AND(P59="Y",C59=""),"Marked posted to Xero but has no invoice number",IF(AND(L59<>"",K59=""),"No tax code",IF(AND(L59<>"",O59=""),"No revenue GL code","")))))))) | W59: =IF(E59="","",IFERROR(INDEX(lst_JobName,MATCH(E59&"",lst_Jobs,0)),"")) | X59: =IF(E59="","",COUNTIFS(tbl_Finance[Job Number],E59&"",tbl_Finance[Ex GST],"<>")) | Y59: =IF(E59="","",SUMIFS(tbl_Finance[Ex GST],tbl_Finance[Job Number],E59&"")) | Z59: =IF(E59="","",SUMIFS(tbl_Finance[Ex GST],tbl_Finance[Job Number],E59&"",tbl_Finance[Xero Invoice No],"<>")) | AA59: =IF(E59="","",Y59-Z59) | AB59: =IF(E59="","",IF(H59="Onsite",IFERROR(INDEX(tbl_Onsite[Qwilr Quote],MATCH(E59&"",tbl_Onsite[Job Number],0)),""),IF(H59="Production",IFERROR(IF(INDEX(tbl_Production[Current RMS No],MATCH(E59&"",tbl_Production[Job Number],0))="",INDEX(tbl_Production[Qwilr Quote],MATCH(E59&"",tbl_Production[Job Number],0)),INDEX(tbl_Production[Current RMS No],MATCH(E59&"",tbl_Production[Job Number],0))),""),IF(H59="Consulting",IFERROR(INDEX(tbl_Consulting[Qwilr Quote],MATCH(E59&"",tbl_Consulting[Job Number],0)),""),"")))) | AC59: =IF(AB59="","",IF(AND(LEFT(AB59,4)<>"http",IF(H59="Production",set_RMSBase,set_QwilrBase)=""),"",HYPERLINK(IF(LEFT(AB59,4)="http",AB59,IF(H59="Production",set_RMSBase,set_QwilrBase)&AB59),"Open"))) | AD59: =IF(E59="","",IF(H59="Production",IFERROR(INDEX(tbl_Production[Total Expense],MATCH(E59&"",tbl_Production[Job Number],0)),0),IF(H59="Consulting",IFERROR(INDEX(tbl_Consulting[Total Expense],MATCH(E59&"",tbl_Consulting[Job Number],0)),0),0))) | AE59: =IF(E59="","",Y59-N(AD59)) | AF59: =IFERROR(AE59/Y59,"") | AG59: =IF(E59="","",IF(H59="Onsite",IFERROR(INDEX(tbl_Onsite[Notes],MATCH(E59&"",tbl_Onsite[Job Number],0)),""),IF(H59="Production",IFERROR(INDEX(tbl_Production[Notes],MATCH(E59&"",tbl_Production[Job Number],0)),""),IF(H59="Consulting",IFERROR(INDEX(tbl_Consulting[Notes],MATCH(E59&"",tbl_Consulting[Job Number],0)),""),""))))
A60: 46210 | B60: =IF(A60="","",EOMONTH(A60,0)) | C60: INV-10519 | D60: RSNSW | E60: 26032301 | F60: =IF(E60="","",IF(COUNTIF(lst_Jobs,E60&"")>0,"OK","CHECK")) | G60: Ordinary General Meeting | 1.7.26 | H60: Production | I60: PRODUCTION | J60: Project | K60: GST 10% | L60: 2042 | M60: =IF(L60="","",IF(K60="GST 10%",ROUND(L60*set_GSTRate,2),0)) | N60: =IF(L60="","",L60+M60) | O60: 42100 | P60: Y | Q60: N | T60: Invoiced | U60: Production portion of this invoice | V60: =IF(COUNTA(A60,D60,C60,L60)=0,"",IF(A60="","No date - sits outside every month",IF(E60="","No job number",IF(F60="CHECK","Job number is not in the Xero job list",IF(I60="","No cost centre",IF(AND(P60="Y",C60=""),"Marked posted to Xero but has no invoice number",IF(AND(L60<>"",K60=""),"No tax code",IF(AND(L60<>"",O60=""),"No revenue GL code","")))))))) | W60: =IF(E60="","",IFERROR(INDEX(lst_JobName,MATCH(E60&"",lst_Jobs,0)),"")) | X60: =IF(E60="","",COUNTIFS(tbl_Finance[Job Number],E60&"",tbl_Finance[Ex GST],"<>")) | Y60: =IF(E60="","",SUMIFS(tbl_Finance[Ex GST],tbl_Finance[Job Number],E60&"")) | Z60: =IF(E60="","",SUMIFS(tbl_Finance[Ex GST],tbl_Finance[Job Number],E60&"",tbl_Finance[Xero Invoice No],"<>")) | AA60: =IF(E60="","",Y60-Z60) | AB60: =IF(E60="","",IF(H60="Onsite",IFERROR(INDEX(tbl_Onsite[Qwilr Quote],MATCH(E60&"",tbl_Onsite[Job Number],0)),""),IF(H60="Production",IFERROR(IF(INDEX(tbl_Production[Current RMS No],MATCH(E60&"",tbl_Production[Job Number],0))="",INDEX(tbl_Production[Qwilr Quote],MATCH(E60&"",tbl_Production[Job Number],0)),INDEX(tbl_Production[Current RMS No],MATCH(E60&"",tbl_Production[Job Number],0))),""),IF(H60="Consulting",IFERROR(INDEX(tbl_Consulting[Qwilr Quote],MATCH(E60&"",tbl_Consulting[Job Number],0)),""),"")))) | AC60: =IF(AB60="","",IF(AND(LEFT(AB60,4)<>"http",IF(H60="Production",set_RMSBase,set_QwilrBase)=""),"",HYPERLINK(IF(LEFT(AB60,4)="http",AB60,IF(H60="Production",set_RMSBase,set_QwilrBase)&AB60),"Open"))) | AD60: =IF(E60="","",IF(H60="Production",IFERROR(INDEX(tbl_Production[Total Expense],MATCH(E60&"",tbl_Production[Job Number],0)),0),IF(H60="Consulting",IFERROR(INDEX(tbl_Consulting[Total Expense],MATCH(E60&"",tbl_Consulting[Job Number],0)),0),0))) | AE60: =IF(E60="","",Y60-N(AD60)) | AF60: =IFERROR(AE60/Y60,"") | AG60: =IF(E60="","",IF(H60="Onsite",IFERROR(INDEX(tbl_Onsite[Notes],MATCH(E60&"",tbl_Onsite[Job Number],0)),""),IF(H60="Production",IFERROR(INDEX(tbl_Production[Notes],MATCH(E60&"",tbl_Production[Job Number],0)),""),IF(H60="Consulting",IFERROR(INDEX(tbl_Consulting[Notes],MATCH(E60&"",tbl_Consulting[Job Number],0)),""),""))))
A61: 46210 | B61: =IF(A61="","",EOMONTH(A61,0)) | C61: INV-10519 | D61: RSNSW | E61: 26032301 | F61: =IF(E61="","",IF(COUNTIF(lst_Jobs,E61&"")>0,"OK","CHECK")) | G61: Ordinary General Meeting | 1.7.26 | H61: Production | I61: VIDEO | J61: Project | K61: GST 10% | L61: 1029 | M61: =IF(L61="","",IF(K61="GST 10%",ROUND(L61*set_GSTRate,2),0)) | N61: =IF(L61="","",L61+M61) | O61: 42150 | P61: Y | Q61: N | T61: Invoiced | U61: Video portion of this invoice | V61: =IF(COUNTA(A61,D61,C61,L61)=0,"",IF(A61="","No date - sits outside every month",IF(E61="","No job number",IF(F61="CHECK","Job number is not in the Xero job list",IF(I61="","No cost centre",IF(AND(P61="Y",C61=""),"Marked posted to Xero but has no invoice number",IF(AND(L61<>"",K61=""),"No tax code",IF(AND(L61<>"",O61=""),"No revenue GL code","")))))))) | W61: =IF(E61="","",IFERROR(INDEX(lst_JobName,MATCH(E61&"",lst_Jobs,0)),"")) | X61: =IF(E61="","",COUNTIFS(tbl_Finance[Job Number],E61&"",tbl_Finance[Ex GST],"<>")) | Y61: =IF(E61="","",SUMIFS(tbl_Finance[Ex GST],tbl_Finance[Job Number],E61&"")) | Z61: =IF(E61="","",SUMIFS(tbl_Finance[Ex GST],tbl_Finance[Job Number],E61&"",tbl_Finance[Xero Invoice No],"<>")) | AA61: =IF(E61="","",Y61-Z61) | AB61: =IF(E61="","",IF(H61="Onsite",IFERROR(INDEX(tbl_Onsite[Qwilr Quote],MATCH(E61&"",tbl_Onsite[Job Number],0)),""),IF(H61="Production",IFERROR(IF(INDEX(tbl_Production[Current RMS No],MATCH(E61&"",tbl_Production[Job Number],0))="",INDEX(tbl_Production[Qwilr Quote],MATCH(E61&"",tbl_Production[Job Number],0)),INDEX(tbl_Production[Current RMS No],MATCH(E61&"",tbl_Production[Job Number],0))),""),IF(H61="Consulting",IFERROR(INDEX(tbl_Consulting[Qwilr Quote],MATCH(E61&"",tbl_Consulting[Job Number],0)),""),"")))) | AC61: =IF(AB61="","",IF(AND(LEFT(AB61,4)<>"http",IF(H61="Production",set_RMSBase,set_QwilrBase)=""),"",HYPERLINK(IF(LEFT(AB61,4)="http",AB61,IF(H61="Production",set_RMSBase,set_QwilrBase)&AB61),"Open"))) | AD61: =IF(E61="","",IF(H61="Production",IFERROR(INDEX(tbl_Production[Total Expense],MATCH(E61&"",tbl_Production[Job Number],0)),0),IF(H61="Consulting",IFERROR(INDEX(tbl_Consulting[Total Expense],MATCH(E61&"",tbl_Consulting[Job Number],0)),0),0))) | AE61: =IF(E61="","",Y61-N(AD61)) | AF61: =IFERROR(AE61/Y61,"") | AG61: =IF(E61="","",IF(H61="Onsite",IFERROR(INDEX(tbl_Onsite[Notes],MATCH(E61&"",tbl_Onsite[Job Number],0)),""),IF(H61="Production",IFERROR(INDEX(tbl_Production[Notes],MATCH(E61&"",tbl_Production[Job Number],0)),""),IF(H61="Consulting",IFERROR(INDEX(tbl_Consulting[Notes],MATCH(E61&"",tbl_Consulting[Job Number],0)),""),""))))
A62: 46210 | B62: =IF(A62="","",EOMONTH(A62,0)) | C62: INV-10515 | D62: PWC | E62: 26062201 | F62: =IF(E62="","",IF(COUNTIF(lst_Jobs,E62&"")>0,"OK","CHECK")) | G62: Tax and Legal Webcast 2.7.26 | H62: Production | I62: PRODUCTION | J62: Project | K62: GST 10% | L62: 955 | M62: =IF(L62="","",IF(K62="GST 10%",ROUND(L62*set_GSTRate,2),0)) | N62: =IF(L62="","",L62+M62) | O62: 42100 | P62: Y | Q62: N | T62: Invoiced | U62: Production portion of this invoice | V62: =IF(COUNTA(A62,D62,C62,L62)=0,"",IF(A62="","No date - sits outside every month",IF(E62="","No job number",IF(F62="CHECK","Job number is not in the Xero job list",IF(I62="","No cost centre",IF(AND(P62="Y",C62=""),"Marked posted to Xero but has no invoice number",IF(AND(L62<>"",K62=""),"No tax code",IF(AND(L62<>"",O62=""),"No revenue GL code","")))))))) | W62: =IF(E62="","",IFERROR(INDEX(lst_JobName,MATCH(E62&"",lst_Jobs,0)),"")) | X62: =IF(E62="","",COUNTIFS(tbl_Finance[Job Number],E62&"",tbl_Finance[Ex GST],"<>")) | Y62: =IF(E62="","",SUMIFS(tbl_Finance[Ex GST],tbl_Finance[Job Number],E62&"")) | Z62: =IF(E62="","",SUMIFS(tbl_Finance[Ex GST],tbl_Finance[Job Number],E62&"",tbl_Finance[Xero Invoice No],"<>")) | AA62: =IF(E62="","",Y62-Z62) | AB62: =IF(E62="","",IF(H62="Onsite",IFERROR(INDEX(tbl_Onsite[Qwilr Quote],MATCH(E62&"",tbl_Onsite[Job Number],0)),""),IF(H62="Production",IFERROR(IF(INDEX(tbl_Production[Current RMS No],MATCH(E62&"",tbl_Production[Job Number],0))="",INDEX(tbl_Production[Qwilr Quote],MATCH(E62&"",tbl_Production[Job Number],0)),INDEX(tbl_Production[Current RMS No],MATCH(E62&"",tbl_Production[Job Number],0))),""),IF(H62="Consulting",IFERROR(INDEX(tbl_Consulting[Qwilr Quote],MATCH(E62&"",tbl_Consulting[Job Number],0)),""),"")))) | AC62: =IF(AB62="","",IF(AND(LEFT(AB62,4)<>"http",IF(H62="Production",set_RMSBase,set_QwilrBase)=""),"",HYPERLINK(IF(LEFT(AB62,4)="http",AB62,IF(H62="Production",set_RMSBase,set_QwilrBase)&AB62),"Open"))) | AD62: =IF(E62="","",IF(H62="Production",IFERROR(INDEX(tbl_Production[Total Expense],MATCH(E62&"",tbl_Production[Job Number],0)),0),IF(H62="Consulting",IFERROR(INDEX(tbl_Consulting[Total Expense],MATCH(E62&"",tbl_Consulting[Job Number],0)),0),0))) | AE62: =IF(E62="","",Y62-N(AD62)) | AF62: =IFERROR(AE62/Y62,"") | AG62: =IF(E62="","",IF(H62="Onsite",IFERROR(INDEX(tbl_Onsite[Notes],MATCH(E62&"",tbl_Onsite[Job Number],0)),""),IF(H62="Production",IFERROR(INDEX(tbl_Production[Notes],MATCH(E62&"",tbl_Production[Job Number],0)),""),IF(H62="Consulting",IFERROR(INDEX(tbl_Consulting[Notes],MATCH(E62&"",tbl_Consulting[Job Number],0)),""),""))))
A63: 46210 | B63: =IF(A63="","",EOMONTH(A63,0)) | C63: INV-10515 | D63: PWC | E63: 26062201 | F63: =IF(E63="","",IF(COUNTIF(lst_Jobs,E63&"")>0,"OK","CHECK")) | G63: Tax and Legal Webcast 2.7.26 | H63: Production | I63: VIDEO | J63: Project | K63: GST 10% | L63: 970 | M63: =IF(L63="","",IF(K63="GST 10%",ROUND(L63*set_GSTRate,2),0)) | N63: =IF(L63="","",L63+M63) | O63: 42150 | P63: Y | Q63: N | T63: Invoiced | U63: Video portion of this invoice | V63: =IF(COUNTA(A63,D63,C63,L63)=0,"",IF(A63="","No date - sits outside every month",IF(E63="","No job number",IF(F63="CHECK","Job number is not in the Xero job list",IF(I63="","No cost centre",IF(AND(P63="Y",C63=""),"Marked posted to Xero but has no invoice number",IF(AND(L63<>"",K63=""),"No tax code",IF(AND(L63<>"",O63=""),"No revenue GL code","")))))))) | W63: =IF(E63="","",IFERROR(INDEX(lst_JobName,MATCH(E63&"",lst_Jobs,0)),"")) | X63: =IF(E63="","",COUNTIFS(tbl_Finance[Job Number],E63&"",tbl_Finance[Ex GST],"<>")) | Y63: =IF(E63="","",SUMIFS(tbl_Finance[Ex GST],tbl_Finance[Job Number],E63&"")) | Z63: =IF(E63="","",SUMIFS(tbl_Finance[Ex GST],tbl_Finance[Job Number],E63&"",tbl_Finance[Xero Invoice No],"<>")) | AA63: =IF(E63="","",Y63-Z63) | AB63: =IF(E63="","",IF(H63="Onsite",IFERROR(INDEX(tbl_Onsite[Qwilr Quote],MATCH(E63&"",tbl_Onsite[Job Number],0)),""),IF(H63="Production",IFERROR(IF(INDEX(tbl_Production[Current RMS No],MATCH(E63&"",tbl_Production[Job Number],0))="",INDEX(tbl_Production[Qwilr Quote],MATCH(E63&"",tbl_Production[Job Number],0)),INDEX(tbl_Production[Current RMS No],MATCH(E63&"",tbl_Production[Job Number],0))),""),IF(H63="Consulting",IFERROR(INDEX(tbl_Consulting[Qwilr Quote],MATCH(E63&"",tbl_Consulting[Job Number],0)),""),"")))) | AC63: =IF(AB63="","",IF(AND(LEFT(AB63,4)<>"http",IF(H63="Production",set_RMSBase,set_QwilrBase)=""),"",HYPERLINK(IF(LEFT(AB63,4)="http",AB63,IF(H63="Production",set_RMSBase,set_QwilrBase)&AB63),"Open"))) | AD63: =IF(E63="","",IF(H63="Production",IFERROR(INDEX(tbl_Production[Total Expense],MATCH(E63&"",tbl_Production[Job Number],0)),0),IF(H63="Consulting",IFERROR(INDEX(tbl_Consulting[Total Expense],MATCH(E63&"",tbl_Consulting[Job Number],0)),0),0))) | AE63: =IF(E63="","",Y63-N(AD63)) | AF63: =IFERROR(AE63/Y63,"") | AG63: =IF(E63="","",IF(H63="Onsite",IFERROR(INDEX(tbl_Onsite[Notes],MATCH(E63&"",tbl_Onsite[Job Number],0)),""),IF(H63="Production",IFERROR(INDEX(tbl_Production[Notes],MATCH(E63&"",tbl_Production[Job Number],0)),""),IF(H63="Consulting",IFERROR(INDEX(tbl_Consulting[Notes],MATCH(E63&"",tbl_Consulting[Job Number],0)),""),""))))
A64: 46219 | B64: =IF(A64="","",EOMONTH(A64,0)) | C64: INV-10524 | D64: Elkiem - PM** Cancelled | E64: 2605802 | F64: =IF(E64="","",IF(COUNTIF(lst_Jobs,E64&"")>0,"OK","CHECK")) | G64: Elkiem Studio Support | 15.7.26 | H64: Production | I64: PRODUCTION | J64: Project | K64: GST 10% | L64: 261.25 | M64: =IF(L64="","",IF(K64="GST 10%",ROUND(L64*set_GSTRate,2),0)) | N64: =IF(L64="","",L64+M64) | O64: 42100 | P64: Y | Q64: N | T64: Invoiced | V64: =IF(COUNTA(A64,D64,C64,L64)=0,"",IF(A64="","No date - sits outside every month",IF(E64="","No job number",IF(F64="CHECK","Job number is not in the Xero job list",IF(I64="","No cost centre",IF(AND(P64="Y",C64=""),"Marked posted to Xero but has no invoice number",IF(AND(L64<>"",K64=""),"No tax code",IF(AND(L64<>"",O64=""),"No revenue GL code","")))))))) | W64: =IF(E64="","",IFERROR(INDEX(lst_JobName,MATCH(E64&"",lst_Jobs,0)),"")) | X64: =IF(E64="","",COUNTIFS(tbl_Finance[Job Number],E64&"",tbl_Finance[Ex GST],"<>")) | Y64: =IF(E64="","",SUMIFS(tbl_Finance[Ex GST],tbl_Finance[Job Number],E64&"")) | Z64: =IF(E64="","",SUMIFS(tbl_Finance[Ex GST],tbl_Finance[Job Number],E64&"",tbl_Finance[Xero Invoice No],"<>")) | AA64: =IF(E64="","",Y64-Z64) | AB64: =IF(E64="","",IF(H64="Onsite",IFERROR(INDEX(tbl_Onsite[Qwilr Quote],MATCH(E64&"",tbl_Onsite[Job Number],0)),""),IF(H64="Production",IFERROR(IF(INDEX(tbl_Production[Current RMS No],MATCH(E64&"",tbl_Production[Job Number],0))="",INDEX(tbl_Production[Qwilr Quote],MATCH(E64&"",tbl_Production[Job Number],0)),INDEX(tbl_Production[Current RMS No],MATCH(E64&"",tbl_Production[Job Number],0))),""),IF(H64="Consulting",IFERROR(INDEX(tbl_Consulting[Qwilr Quote],MATCH(E64&"",tbl_Consulting[Job Number],0)),""),"")))) | AC64: =IF(AB64="","",IF(AND(LEFT(AB64,4)<>"http",IF(H64="Production",set_RMSBase,set_QwilrBase)=""),"",HYPERLINK(IF(LEFT(AB64,4)="http",AB64,IF(H64="Production",set_RMSBase,set_QwilrBase)&AB64),"Open"))) | AD64: =IF(E64="","",IF(H64="Production",IFERROR(INDEX(tbl_Production[Total Expense],MATCH(E64&"",tbl_Production[Job Number],0)),0),IF(H64="Consulting",IFERROR(INDEX(tbl_Consulting[Total Expense],MATCH(E64&"",tbl_Consulting[Job Number],0)),0),0))) | AE64: =IF(E64="","",Y64-N(AD64)) | AF64: =IFERROR(AE64/Y64,"") | AG64: =IF(E64="","",IF(H64="Onsite",IFERROR(INDEX(tbl_Onsite[Notes],MATCH(E64&"",tbl_Onsite[Job Number],0)),""),IF(H64="Production",IFERROR(INDEX(tbl_Production[Notes],MATCH(E64&"",tbl_Production[Job Number],0)),""),IF(H64="Consulting",IFERROR(INDEX(tbl_Consulting[Notes],MATCH(E64&"",tbl_Consulting[Job Number],0)),""),""))))
A65: 46210 | B65: =IF(A65="","",EOMONTH(A65,0)) | C65: INV-10518 | D65: Litecard | E65: 2607701 | F65: =IF(E65="","",IF(COUNTIF(lst_Jobs,E65&"")>0,"OK","CHECK")) | G65: Screen & Mic Hire 16.7.26 | H65: Production | I65: PRODUCTION | J65: Project | K65: GST 10% | L65: 500 | M65: =IF(L65="","",IF(K65="GST 10%",ROUND(L65*set_GSTRate,2),0)) | N65: =IF(L65="","",L65+M65) | O65: 42100 | P65: Y | Q65: N | T65: Invoiced | V65: =IF(COUNTA(A65,D65,C65,L65)=0,"",IF(A65="","No date - sits outside every month",IF(E65="","No job number",IF(F65="CHECK","Job number is not in the Xero job list",IF(I65="","No cost centre",IF(AND(P65="Y",C65=""),"Marked posted to Xero but has no invoice number",IF(AND(L65<>"",K65=""),"No tax code",IF(AND(L65<>"",O65=""),"No revenue GL code","")))))))) | W65: =IF(E65="","",IFERROR(INDEX(lst_JobName,MATCH(E65&"",lst_Jobs,0)),"")) | X65: =IF(E65="","",COUNTIFS(tbl_Finance[Job Number],E65&"",tbl_Finance[Ex GST],"<>")) | Y65: =IF(E65="","",SUMIFS(tbl_Finance[Ex GST],tbl_Finance[Job Number],E65&"")) | Z65: =IF(E65="","",SUMIFS(tbl_Finance[Ex GST],tbl_Finance[Job Number],E65&"",tbl_Finance[Xero Invoice No],"<>")) | AA65: =IF(E65="","",Y65-Z65) | AB65: =IF(E65="","",IF(H65="Onsite",IFERROR(INDEX(tbl_Onsite[Qwilr Quote],MATCH(E65&"",tbl_Onsite[Job Number],0)),""),IF(H65="Production",IFERROR(IF(INDEX(tbl_Production[Current RMS No],MATCH(E65&"",tbl_Production[Job Number],0))="",INDEX(tbl_Production[Qwilr Quote],MATCH(E65&"",tbl_Production[Job Number],0)),INDEX(tbl_Production[Current RMS No],MATCH(E65&"",tbl_Production[Job Number],0))),""),IF(H65="Consulting",IFERROR(INDEX(tbl_Consulting[Qwilr Quote],MATCH(E65&"",tbl_Consulting[Job Number],0)),""),"")))) | AC65: =IF(AB65="","",IF(AND(LEFT(AB65,4)<>"http",IF(H65="Production",set_RMSBase,set_QwilrBase)=""),"",HYPERLINK(IF(LEFT(AB65,4)="http",AB65,IF(H65="Production",set_RMSBase,set_QwilrBase)&AB65),"Open"))) | AD65: =IF(E65="","",IF(H65="Production",IFERROR(INDEX(tbl_Production[Total Expense],MATCH(E65&"",tbl_Production[Job Number],0)),0),IF(H65="Consulting",IFERROR(INDEX(tbl_Consulting[Total Expense],MATCH(E65&"",tbl_Consulting[Job Number],0)),0),0))) | AE65: =IF(E65="","",Y65-N(AD65)) | AF65: =IFERROR(AE65/Y65,"") | AG65: =IF(E65="","",IF(H65="Onsite",IFERROR(INDEX(tbl_Onsite[Notes],MATCH(E65&"",tbl_Onsite[Job Number],0)),""),IF(H65="Production",IFERROR(INDEX(tbl_Production[Notes],MATCH(E65&"",tbl_Production[Job Number],0)),""),IF(H65="Consulting",IFERROR(INDEX(tbl_Consulting[Notes],MATCH(E65&"",tbl_Consulting[Job Number],0)),""),""))))
A66: 46216 | B66: =IF(A66="","",EOMONTH(A66,0)) | C66: INV-10522 | D66: Litecard | E66: 2607701 | F66: =IF(E66="","",IF(COUNTIF(lst_Jobs,E66&"")>0,"OK","CHECK")) | G66: Litecard - Event Photographer - 16.7.26 | H66: Production | I66: VIDEO | J66: Project | K66: GST 10% | L66: 550 | M66: =IF(L66="","",IF(K66="GST 10%",ROUND(L66*set_GSTRate,2),0)) | N66: =IF(L66="","",L66+M66) | O66: 42150 | P66: Y | Q66: N | T66: Invoiced | V66: =IF(COUNTA(A66,D66,C66,L66)=0,"",IF(A66="","No date - sits outside every month",IF(E66="","No job number",IF(F66="CHECK","Job number is not in the Xero job list",IF(I66="","No cost centre",IF(AND(P66="Y",C66=""),"Marked posted to Xero but has no invoice number",IF(AND(L66<>"",K66=""),"No tax code",IF(AND(L66<>"",O66=""),"No revenue GL code","")))))))) | W66: =IF(E66="","",IFERROR(INDEX(lst_JobName,MATCH(E66&"",lst_Jobs,0)),"")) | X66: =IF(E66="","",COUNTIFS(tbl_Finance[Job Number],E66&"",tbl_Finance[Ex GST],"<>")) | Y66: =IF(E66="","",SUMIFS(tbl_Finance[Ex GST],tbl_Finance[Job Number],E66&"")) | Z66: =IF(E66="","",SUMIFS(tbl_Finance[Ex GST],tbl_Finance[Job Number],E66&"",tbl_Finance[Xero Invoice No],"<>")) | AA66: =IF(E66="","",Y66-Z66) | AB66: =IF(E66="","",IF(H66="Onsite",IFERROR(INDEX(tbl_Onsite[Qwilr Quote],MATCH(E66&"",tbl_Onsite[Job Number],0)),""),IF(H66="Production",IFERROR(IF(INDEX(tbl_Production[Current RMS No],MATCH(E66&"",tbl_Production[Job Number],0))="",INDEX(tbl_Production[Qwilr Quote],MATCH(E66&"",tbl_Production[Job Number],0)),INDEX(tbl_Production[Current RMS No],MATCH(E66&"",tbl_Production[Job Number],0))),""),IF(H66="Consulting",IFERROR(INDEX(tbl_Consulting[Qwilr Quote],MATCH(E66&"",tbl_Consulting[Job Number],0)),""),"")))) | AC66: =IF(AB66="","",IF(AND(LEFT(AB66,4)<>"http",IF(H66="Production",set_RMSBase,set_QwilrBase)=""),"",HYPERLINK(IF(LEFT(AB66,4)="http",AB66,IF(H66="Production",set_RMSBase,set_QwilrBase)&AB66),"Open"))) | AD66: =IF(E66="","",IF(H66="Production",IFERROR(INDEX(tbl_Production[Total Expense],MATCH(E66&"",tbl_Production[Job Number],0)),0),IF(H66="Consulting",IFERROR(INDEX(tbl_Consulting[Total Expense],MATCH(E66&"",tbl_Consulting[Job Number],0)),0),0))) | AE66: =IF(E66="","",Y66-N(AD66)) | AF66: =IFERROR(AE66/Y66,"") | AG66: =IF(E66="","",IF(H66="Onsite",IFERROR(INDEX(tbl_Onsite[Notes],MATCH(E66&"",tbl_Onsite[Job Number],0)),""),IF(H66="Production",IFERROR(INDEX(tbl_Production[Notes],MATCH(E66&"",tbl_Production[Job Number],0)),""),IF(H66="Consulting",IFERROR(INDEX(tbl_Consulting[Notes],MATCH(E66&"",tbl_Consulting[Job Number],0)),""),""))))
A67: 46234 | B67: =IF(A67="","",EOMONTH(A67,0)) | C67: INV-10554 | D67: Microsoft | E67: 26052703 | F67: =IF(E67="","",IF(COUNTIF(lst_Jobs,E67&"")>0,"OK","CHECK")) | G67: Microsoft Town Hall 21.7.26 | H67: Production | I67: PRODUCTION | J67: Project | K67: GST 10% | L67: 10885 | M67: =IF(L67="","",IF(K67="GST 10%",ROUND(L67*set_GSTRate,2),0)) | N67: =IF(L67="","",L67+M67) | O67: 42100 | P67: Y | Q67: N | T67: Invoiced | U67: Production portion of this invoice | V67: =IF(COUNTA(A67,D67,C67,L67)=0,"",IF(A67="","No date - sits outside every month",IF(E67="","No job number",IF(F67="CHECK","Job number is not in the Xero job list",IF(I67="","No cost centre",IF(AND(P67="Y",C67=""),"Marked posted to Xero but has no invoice number",IF(AND(L67<>"",K67=""),"No tax code",IF(AND(L67<>"",O67=""),"No revenue GL code","")))))))) | W67: =IF(E67="","",IFERROR(INDEX(lst_JobName,MATCH(E67&"",lst_Jobs,0)),"")) | X67: =IF(E67="","",COUNTIFS(tbl_Finance[Job Number],E67&"",tbl_Finance[Ex GST],"<>")) | Y67: =IF(E67="","",SUMIFS(tbl_Finance[Ex GST],tbl_Finance[Job Number],E67&"")) | Z67: =IF(E67="","",SUMIFS(tbl_Finance[Ex GST],tbl_Finance[Job Number],E67&"",tbl_Finance[Xero Invoice No],"<>")) | AA67: =IF(E67="","",Y67-Z67) | AB67: =IF(E67="","",IF(H67="Onsite",IFERROR(INDEX(tbl_Onsite[Qwilr Quote],MATCH(E67&"",tbl_Onsite[Job Number],0)),""),IF(H67="Production",IFERROR(IF(INDEX(tbl_Production[Current RMS No],MATCH(E67&"",tbl_Production[Job Number],0))="",INDEX(tbl_Production[Qwilr Quote],MATCH(E67&"",tbl_Production[Job Number],0)),INDEX(tbl_Production[Current RMS No],MATCH(E67&"",tbl_Production[Job Number],0))),""),IF(H67="Consulting",IFERROR(INDEX(tbl_Consulting[Qwilr Quote],MATCH(E67&"",tbl_Consulting[Job Number],0)),""),"")))) | AC67: =IF(AB67="","",IF(AND(LEFT(AB67,4)<>"http",IF(H67="Production",set_RMSBase,set_QwilrBase)=""),"",HYPERLINK(IF(LEFT(AB67,4)="http",AB67,IF(H67="Production",set_RMSBase,set_QwilrBase)&AB67),"Open"))) | AD67: =IF(E67="","",IF(H67="Production",IFERROR(INDEX(tbl_Production[Total Expense],MATCH(E67&"",tbl_Production[Job Number],0)),0),IF(H67="Consulting",IFERROR(INDEX(tbl_Consulting[Total Expense],MATCH(E67&"",tbl_Consulting[Job Number],0)),0),0))) | AE67: =IF(E67="","",Y67-N(AD67)) | AF67: =IFERROR(AE67/Y67,"") | AG67: =IF(E67="","",IF(H67="Onsite",IFERROR(INDEX(tbl_Onsite[Notes],MATCH(E67&"",tbl_Onsite[Job Number],0)),""),IF(H67="Production",IFERROR(INDEX(tbl_Production[Notes],MATCH(E67&"",tbl_Production[Job Number],0)),""),IF(H67="Consulting",IFERROR(INDEX(tbl_Consulting[Notes],MATCH(E67&"",tbl_Consulting[Job Number],0)),""),""))))
A68: 46234 | B68: =IF(A68="","",EOMONTH(A68,0)) | C68: INV-10554 | D68: Microsoft | E68: 26052703 | F68: =IF(E68="","",IF(COUNTIF(lst_Jobs,E68&"")>0,"OK","CHECK")) | G68: Microsoft Town Hall 21.7.26 | H68: Production | I68: VIDEO | J68: Project | K68: GST 10% | L68: 1702 | M68: =IF(L68="","",IF(K68="GST 10%",ROUND(L68*set_GSTRate,2),0)) | N68: =IF(L68="","",L68+M68) | O68: 42150 | P68: Y | Q68: N | T68: Invoiced | U68: Video portion of this invoice | V68: =IF(COUNTA(A68,D68,C68,L68)=0,"",IF(A68="","No date - sits outside every month",IF(E68="","No job number",IF(F68="CHECK","Job number is not in the Xero job list",IF(I68="","No cost centre",IF(AND(P68="Y",C68=""),"Marked posted to Xero but has no invoice number",IF(AND(L68<>"",K68=""),"No tax code",IF(AND(L68<>"",O68=""),"No revenue GL code","")))))))) | W68: =IF(E68="","",IFERROR(INDEX(lst_JobName,MATCH(E68&"",lst_Jobs,0)),"")) | X68: =IF(E68="","",COUNTIFS(tbl_Finance[Job Number],E68&"",tbl_Finance[Ex GST],"<>")) | Y68: =IF(E68="","",SUMIFS(tbl_Finance[Ex GST],tbl_Finance[Job Number],E68&"")) | Z68: =IF(E68="","",SUMIFS(tbl_Finance[Ex GST],tbl_Finance[Job Number],E68&"",tbl_Finance[Xero Invoice No],"<>")) | AA68: =IF(E68="","",Y68-Z68) | AB68: =IF(E68="","",IF(H68="Onsite",IFERROR(INDEX(tbl_Onsite[Qwilr Quote],MATCH(E68&"",tbl_Onsite[Job Number],0)),""),IF(H68="Production",IFERROR(IF(INDEX(tbl_Production[Current RMS No],MATCH(E68&"",tbl_Production[Job Number],0))="",INDEX(tbl_Production[Qwilr Quote],MATCH(E68&"",tbl_Production[Job Number],0)),INDEX(tbl_Production[Current RMS No],MATCH(E68&"",tbl_Production[Job Number],0))),""),IF(H68="Consulting",IFERROR(INDEX(tbl_Consulting[Qwilr Quote],MATCH(E68&"",tbl_Consulting[Job Number],0)),""),"")))) | AC68: =IF(AB68="","",IF(AND(LEFT(AB68,4)<>"http",IF(H68="Production",set_RMSBase,set_QwilrBase)=""),"",HYPERLINK(IF(LEFT(AB68,4)="http",AB68,IF(H68="Production",set_RMSBase,set_QwilrBase)&AB68),"Open"))) | AD68: =IF(E68="","",IF(H68="Production",IFERROR(INDEX(tbl_Production[Total Expense],MATCH(E68&"",tbl_Production[Job Number],0)),0),IF(H68="Consulting",IFERROR(INDEX(tbl_Consulting[Total Expense],MATCH(E68&"",tbl_Consulting[Job Number],0)),0),0))) | AE68: =IF(E68="","",Y68-N(AD68)) | AF68: =IFERROR(AE68/Y68,"") | AG68: =IF(E68="","",IF(H68="Onsite",IFERROR(INDEX(tbl_Onsite[Notes],MATCH(E68&"",tbl_Onsite[Job Number],0)),""),IF(H68="Production",IFERROR(INDEX(tbl_Production[Notes],MATCH(E68&"",tbl_Production[Job Number],0)),""),IF(H68="Consulting",IFERROR(INDEX(tbl_Consulting[Notes],MATCH(E68&"",tbl_Consulting[Job Number],0)),""),""))))
A69: 46232 | B69: =IF(A69="","",EOMONTH(A69,0)) | C69: INV-10538 | D69: Optiver | E69: 26041603 | F69: =IF(E69="","",IF(COUNTIF(lst_Jobs,E69&"")>0,"OK","CHECK")) | G69: Mid-Year Town Hall 23.7.26 | H69: Production | I69: PRODUCTION | J69: Project | K69: GST 10% | L69: 745 | M69: =IF(L69="","",IF(K69="GST 10%",ROUND(L69*set_GSTRate,2),0)) | N69: =IF(L69="","",L69+M69) | O69: 42100 | P69: Y | Q69: N | T69: Invoiced | V69: =IF(COUNTA(A69,D69,C69,L69)=0,"",IF(A69="","No date - sits outside every month",IF(E69="","No job number",IF(F69="CHECK","Job number is not in the Xero job list",IF(I69="","No cost centre",IF(AND(P69="Y",C69=""),"Marked posted to Xero but has no invoice number",IF(AND(L69<>"",K69=""),"No tax code",IF(AND(L69<>"",O69=""),"No revenue GL code","")))))))) | W69: =IF(E69="","",IFERROR(INDEX(lst_JobName,MATCH(E69&"",lst_Jobs,0)),"")) | X69: =IF(E69="","",COUNTIFS(tbl_Finance[Job Number],E69&"",tbl_Finance[Ex GST],"<>")) | Y69: =IF(E69="","",SUMIFS(tbl_Finance[Ex GST],tbl_Finance[Job Number],E69&"")) | Z69: =IF(E69="","",SUMIFS(tbl_Finance[Ex GST],tbl_Finance[Job Number],E69&"",tbl_Finance[Xero Invoice No],"<>")) | AA69: =IF(E69="","",Y69-Z69) | AB69: =IF(E69="","",IF(H69="Onsite",IFERROR(INDEX(tbl_Onsite[Qwilr Quote],MATCH(E69&"",tbl_Onsite[Job Number],0)),""),IF(H69="Production",IFERROR(IF(INDEX(tbl_Production[Current RMS No],MATCH(E69&"",tbl_Production[Job Number],0))="",INDEX(tbl_Production[Qwilr Quote],MATCH(E69&"",tbl_Production[Job Number],0)),INDEX(tbl_Production[Current RMS No],MATCH(E69&"",tbl_Production[Job Number],0))),""),IF(H69="Consulting",IFERROR(INDEX(tbl_Consulting[Qwilr Quote],MATCH(E69&"",tbl_Consulting[Job Number],0)),""),"")))) | AC69: =IF(AB69="","",IF(AND(LEFT(AB69,4)<>"http",IF(H69="Production",set_RMSBase,set_QwilrBase)=""),"",HYPERLINK(IF(LEFT(AB69,4)="http",AB69,IF(H69="Production",set_RMSBase,set_QwilrBase)&AB69),"Open"))) | AD69: =IF(E69="","",IF(H69="Production",IFERROR(INDEX(tbl_Production[Total Expense],MATCH(E69&"",tbl_Production[Job Number],0)),0),IF(H69="Consulting",IFERROR(INDEX(tbl_Consulting[Total Expense],MATCH(E69&"",tbl_Consulting[Job Number],0)),0),0))) | AE69: =IF(E69="","",Y69-N(AD69)) | AF69: =IFERROR(AE69/Y69,"") | AG69: =IF(E69="","",IF(H69="Onsite",IFERROR(INDEX(tbl_Onsite[Notes],MATCH(E69&"",tbl_Onsite[Job Number],0)),""),IF(H69="Production",IFERROR(INDEX(tbl_Production[Notes],MATCH(E69&"",tbl_Production[Job Number],0)),""),IF(H69="Consulting",IFERROR(INDEX(tbl_Consulting[Notes],MATCH(E69&"",tbl_Consulting[Job Number],0)),""),""))))
A70: 46234 | B70: =IF(A70="","",EOMONTH(A70,0)) | C70: INV-10540 | D70: Arup | E70: 2605403 | F70: =IF(E70="","",IF(COUNTIF(lst_Jobs,E70&"")>0,"OK","CHECK")) | G70: Oves Awards Night 23.7.26 | H70: Production | I70: PRODUCTION | J70: Project | K70: GST 10% | L70: 5460 | M70: =IF(L70="","",IF(K70="GST 10%",ROUND(L70*set_GSTRate,2),0)) | N70: =IF(L70="","",L70+M70) | O70: 42100 | P70: Y | Q70: N | T70: Invoiced | U70: Production portion of this invoice | V70: =IF(COUNTA(A70,D70,C70,L70)=0,"",IF(A70="","No date - sits outside every month",IF(E70="","No job number",IF(F70="CHECK","Job number is not in the Xero job list",IF(I70="","No cost centre",IF(AND(P70="Y",C70=""),"Marked posted to Xero but has no invoice number",IF(AND(L70<>"",K70=""),"No tax code",IF(AND(L70<>"",O70=""),"No revenue GL code","")))))))) | W70: =IF(E70="","",IFERROR(INDEX(lst_JobName,MATCH(E70&"",lst_Jobs,0)),"")) | X70: =IF(E70="","",COUNTIFS(tbl_Finance[Job Number],E70&"",tbl_Finance[Ex GST],"<>")) | Y70: =IF(E70="","",SUMIFS(tbl_Finance[Ex GST],tbl_Finance[Job Number],E70&"")) | Z70: =IF(E70="","",SUMIFS(tbl_Finance[Ex GST],tbl_Finance[Job Number],E70&"",tbl_Finance[Xero Invoice No],"<>")) | AA70: =IF(E70="","",Y70-Z70) | AB70: =IF(E70="","",IF(H70="Onsite",IFERROR(INDEX(tbl_Onsite[Qwilr Quote],MATCH(E70&"",tbl_Onsite[Job Number],0)),""),IF(H70="Production",IFERROR(IF(INDEX(tbl_Production[Current RMS No],MATCH(E70&"",tbl_Production[Job Number],0))="",INDEX(tbl_Production[Qwilr Quote],MATCH(E70&"",tbl_Production[Job Number],0)),INDEX(tbl_Production[Current RMS No],MATCH(E70&"",tbl_Production[Job Number],0))),""),IF(H70="Consulting",IFERROR(INDEX(tbl_Consulting[Qwilr Quote],MATCH(E70&"",tbl_Consulting[Job Number],0)),""),"")))) | AC70: =IF(AB70="","",IF(AND(LEFT(AB70,4)<>"http",IF(H70="Production",set_RMSBase,set_QwilrBase)=""),"",HYPERLINK(IF(LEFT(AB70,4)="http",AB70,IF(H70="Production",set_RMSBase,set_QwilrBase)&AB70),"Open"))) | AD70: =IF(E70="","",IF(H70="Production",IFERROR(INDEX(tbl_Production[Total Expense],MATCH(E70&"",tbl_Production[Job Number],0)),0),IF(H70="Consulting",IFERROR(INDEX(tbl_Consulting[Total Expense],MATCH(E70&"",tbl_Consulting[Job Number],0)),0),0))) | AE70: =IF(E70="","",Y70-N(AD70)) | AF70: =IFERROR(AE70/Y70,"") | AG70: =IF(E70="","",IF(H70="Onsite",IFERROR(INDEX(tbl_Onsite[Notes],MATCH(E70&"",tbl_Onsite[Job Number],0)),""),IF(H70="Production",IFERROR(INDEX(tbl_Production[Notes],MATCH(E70&"",tbl_Production[Job Number],0)),""),IF(H70="Consulting",IFERROR(INDEX(tbl_Consulting[Notes],MATCH(E70&"",tbl_Consulting[Job Number],0)),""),""))))
A71: 46234 | B71: =IF(A71="","",EOMONTH(A71,0)) | C71: INV-10540 | D71: Arup | E71: 2605403 | F71: =IF(E71="","",IF(COUNTIF(lst_Jobs,E71&"")>0,"OK","CHECK")) | G71: Oves Awards Night 23.7.26 | H71: Production | I71: VIDEO | J71: Project | K71: GST 10% | L71: 176 | M71: =IF(L71="","",IF(K71="GST 10%",ROUND(L71*set_GSTRate,2),0)) | N71: =IF(L71="","",L71+M71) | O71: 42150 | P71: Y | Q71: N | T71: Invoiced | U71: Video portion of this invoice | V71: =IF(COUNTA(A71,D71,C71,L71)=0,"",IF(A71="","No date - sits outside every month",IF(E71="","No job number",IF(F71="CHECK","Job number is not in the Xero job list",IF(I71="","No cost centre",IF(AND(P71="Y",C71=""),"Marked posted to Xero but has no invoice number",IF(AND(L71<>"",K71=""),"No tax code",IF(AND(L71<>"",O71=""),"No revenue GL code","")))))))) | W71: =IF(E71="","",IFERROR(INDEX(lst_JobName,MATCH(E71&"",lst_Jobs,0)),"")) | X71: =IF(E71="","",COUNTIFS(tbl_Finance[Job Number],E71&"",tbl_Finance[Ex GST],"<>")) | Y71: =IF(E71="","",SUMIFS(tbl_Finance[Ex GST],tbl_Finance[Job Number],E71&"")) | Z71: =IF(E71="","",SUMIFS(tbl_Finance[Ex GST],tbl_Finance[Job Number],E71&"",tbl_Finance[Xero Invoice No],"<>")) | AA71: =IF(E71="","",Y71-Z71) | AB71: =IF(E71="","",IF(H71="Onsite",IFERROR(INDEX(tbl_Onsite[Qwilr Quote],MATCH(E71&"",tbl_Onsite[Job Number],0)),""),IF(H71="Production",IFERROR(IF(INDEX(tbl_Production[Current RMS No],MATCH(E71&"",tbl_Production[Job Number],0))="",INDEX(tbl_Production[Qwilr Quote],MATCH(E71&"",tbl_Production[Job Number],0)),INDEX(tbl_Production[Current RMS No],MATCH(E71&"",tbl_Production[Job Number],0))),""),IF(H71="Consulting",IFERROR(INDEX(tbl_Consulting[Qwilr Quote],MATCH(E71&"",tbl_Consulting[Job Number],0)),""),"")))) | AC71: =IF(AB71="","",IF(AND(LEFT(AB71,4)<>"http",IF(H71="Production",set_RMSBase,set_QwilrBase)=""),"",HYPERLINK(IF(LEFT(AB71,4)="http",AB71,IF(H71="Production",set_RMSBase,set_QwilrBase)&AB71),"Open"))) | AD71: =IF(E71="","",IF(H71="Production",IFERROR(INDEX(tbl_Production[Total Expense],MATCH(E71&"",tbl_Production[Job Number],0)),0),IF(H71="Consulting",IFERROR(INDEX(tbl_Consulting[Total Expense],MATCH(E71&"",tbl_Consulting[Job Number],0)),0),0))) | AE71: =IF(E71="","",Y71-N(AD71)) | AF71: =IFERROR(AE71/Y71,"") | AG71: =IF(E71="","",IF(H71="Onsite",IFERROR(INDEX(tbl_Onsite[Notes],MATCH(E71&"",tbl_Onsite[Job Number],0)),""),IF(H71="Production",IFERROR(INDEX(tbl_Production[Notes],MATCH(E71&"",tbl_Production[Job Number],0)),""),IF(H71="Consulting",IFERROR(INDEX(tbl_Consulting[Notes],MATCH(E71&"",tbl_Consulting[Job Number],0)),""),""))))
A72: 46234 | B72: =IF(A72="","",EOMONTH(A72,0)) | C72: INV-10552 | D72: On24 | E72: 2607901 | F72: =IF(E72="","",IF(COUNTIF(lst_Jobs,E72&"")>0,"OK","CHECK")) | G72: KWM Event 23.7.26 (PO #25962) | H72: Production | I72: PRODUCTION | J72: Project | K72: GST 10% | L72: 2575 | M72: =IF(L72="","",IF(K72="GST 10%",ROUND(L72*set_GSTRate,2),0)) | N72: =IF(L72="","",L72+M72) | O72: 42100 | P72: Y | Q72: N | T72: Invoiced | V72: =IF(COUNTA(A72,D72,C72,L72)=0,"",IF(A72="","No date - sits outside every month",IF(E72="","No job number",IF(F72="CHECK","Job number is not in the Xero job list",IF(I72="","No cost centre",IF(AND(P72="Y",C72=""),"Marked posted to Xero but has no invoice number",IF(AND(L72<>"",K72=""),"No tax code",IF(AND(L72<>"",O72=""),"No revenue GL code","")))))))) | W72: =IF(E72="","",IFERROR(INDEX(lst_JobName,MATCH(E72&"",lst_Jobs,0)),"")) | X72: =IF(E72="","",COUNTIFS(tbl_Finance[Job Number],E72&"",tbl_Finance[Ex GST],"<>")) | Y72: =IF(E72="","",SUMIFS(tbl_Finance[Ex GST],tbl_Finance[Job Number],E72&"")) | Z72: =IF(E72="","",SUMIFS(tbl_Finance[Ex GST],tbl_Finance[Job Number],E72&"",tbl_Finance[Xero Invoice No],"<>")) | AA72: =IF(E72="","",Y72-Z72) | AB72: =IF(E72="","",IF(H72="Onsite",IFERROR(INDEX(tbl_Onsite[Qwilr Quote],MATCH(E72&"",tbl_Onsite[Job Number],0)),""),IF(H72="Production",IFERROR(IF(INDEX(tbl_Production[Current RMS No],MATCH(E72&"",tbl_Production[Job Number],0))="",INDEX(tbl_Production[Qwilr Quote],MATCH(E72&"",tbl_Production[Job Number],0)),INDEX(tbl_Production[Current RMS No],MATCH(E72&"",tbl_Production[Job Number],0))),""),IF(H72="Consulting",IFERROR(INDEX(tbl_Consulting[Qwilr Quote],MATCH(E72&"",tbl_Consulting[Job Number],0)),""),"")))) | AC72: =IF(AB72="","",IF(AND(LEFT(AB72,4)<>"http",IF(H72="Production",set_RMSBase,set_QwilrBase)=""),"",HYPERLINK(IF(LEFT(AB72,4)="http",AB72,IF(H72="Production",set_RMSBase,set_QwilrBase)&AB72),"Open"))) | AD72: =IF(E72="","",IF(H72="Production",IFERROR(INDEX(tbl_Production[Total Expense],MATCH(E72&"",tbl_Production[Job Number],0)),0),IF(H72="Consulting",IFERROR(INDEX(tbl_Consulting[Total Expense],MATCH(E72&"",tbl_Consulting[Job Number],0)),0),0))) | AE72: =IF(E72="","",Y72-N(AD72)) | AF72: =IFERROR(AE72/Y72,"") | AG72: =IF(E72="","",IF(H72="Onsite",IFERROR(INDEX(tbl_Onsite[Notes],MATCH(E72&"",tbl_Onsite[Job Number],0)),""),IF(H72="Production",IFERROR(INDEX(tbl_Production[Notes],MATCH(E72&"",tbl_Production[Job Number],0)),""),IF(H72="Consulting",IFERROR(INDEX(tbl_Consulting[Notes],MATCH(E72&"",tbl_Consulting[Job Number],0)),""),""))))
A73: 46223 | B73: =IF(A73="","",EOMONTH(A73,0)) | C73: INV-10533 | D73: Skykick Ranger | E73: 26063001 | F73: =IF(E73="","",IF(COUNTIF(lst_Jobs,E73&"")>0,"OK","CHECK")) | G73: Sydney Performance Dry Hire 26.7.26 | H73: Production | I73: PRODUCTION | J73: Project | K73: GST 10% | L73: 975 | M73: =IF(L73="","",IF(K73="GST 10%",ROUND(L73*set_GSTRate,2),0)) | N73: =IF(L73="","",L73+M73) | O73: 42100 | P73: Y | Q73: N | T73: Invoiced | V73: =IF(COUNTA(A73,D73,C73,L73)=0,"",IF(A73="","No date - sits outside every month",IF(E73="","No job number",IF(F73="CHECK","Job number is not in the Xero job list",IF(I73="","No cost centre",IF(AND(P73="Y",C73=""),"Marked posted to Xero but has no invoice number",IF(AND(L73<>"",K73=""),"No tax code",IF(AND(L73<>"",O73=""),"No revenue GL code","")))))))) | W73: =IF(E73="","",IFERROR(INDEX(lst_JobName,MATCH(E73&"",lst_Jobs,0)),"")) | X73: =IF(E73="","",COUNTIFS(tbl_Finance[Job Number],E73&"",tbl_Finance[Ex GST],"<>")) | Y73: =IF(E73="","",SUMIFS(tbl_Finance[Ex GST],tbl_Finance[Job Number],E73&"")) | Z73: =IF(E73="","",SUMIFS(tbl_Finance[Ex GST],tbl_Finance[Job Number],E73&"",tbl_Finance[Xero Invoice No],"<>")) | AA73: =IF(E73="","",Y73-Z73) | AB73: =IF(E73="","",IF(H73="Onsite",IFERROR(INDEX(tbl_Onsite[Qwilr Quote],MATCH(E73&"",tbl_Onsite[Job Number],0)),""),IF(H73="Production",IFERROR(IF(INDEX(tbl_Production[Current RMS No],MATCH(E73&"",tbl_Production[Job Number],0))="",INDEX(tbl_Production[Qwilr Quote],MATCH(E73&"",tbl_Production[Job Number],0)),INDEX(tbl_Production[Current RMS No],MATCH(E73&"",tbl_Production[Job Number],0))),""),IF(H73="Consulting",IFERROR(INDEX(tbl_Consulting[Qwilr Quote],MATCH(E73&"",tbl_Consulting[Job Number],0)),""),"")))) | AC73: =IF(AB73="","",IF(AND(LEFT(AB73,4)<>"http",IF(H73="Production",set_RMSBase,set_QwilrBase)=""),"",HYPERLINK(IF(LEFT(AB73,4)="http",AB73,IF(H73="Production",set_RMSBase,set_QwilrBase)&AB73),"Open"))) | AD73: =IF(E73="","",IF(H73="Production",IFERROR(INDEX(tbl_Production[Total Expense],MATCH(E73&"",tbl_Production[Job Number],0)),0),IF(H73="Consulting",IFERROR(INDEX(tbl_Consulting[Total Expense],MATCH(E73&"",tbl_Consulting[Job Number],0)),0),0))) | AE73: =IF(E73="","",Y73-N(AD73)) | AF73: =IFERROR(AE73/Y73,"") | AG73: =IF(E73="","",IF(H73="Onsite",IFERROR(INDEX(tbl_Onsite[Notes],MATCH(E73&"",tbl_Onsite[Job Number],0)),""),IF(H73="Production",IFERROR(INDEX(tbl_Production[Notes],MATCH(E73&"",tbl_Production[Job Number],0)),""),IF(H73="Consulting",IFERROR(INDEX(tbl_Consulting[Notes],MATCH(E73&"",tbl_Consulting[Job Number],0)),""),""))))
A74: 46234 | B74: =IF(A74="","",EOMONTH(A74,0)) | C74: INV-10557 | D74: Ventia | E74: 2604202 | F74: =IF(E74="","",IF(COUNTIF(lst_Jobs,E74&"")>0,"OK","CHECK")) | G74: Ventia Awards 28 & 30.7.26 (PO 4701355678) | H74: Production | I74: PRODUCTION | J74: Project | K74: GST 10% | L74: 52749.78 | M74: =IF(L74="","",IF(K74="GST 10%",ROUND(L74*set_GSTRate,2),0)) | N74: =IF(L74="","",L74+M74) | O74: 42100 | P74: Y | Q74: N | T74: Invoiced | V74: =IF(COUNTA(A74,D74,C74,L74)=0,"",IF(A74="","No date - sits outside every month",IF(E74="","No job number",IF(F74="CHECK","Job number is not in the Xero job list",IF(I74="","No cost centre",IF(AND(P74="Y",C74=""),"Marked posted to Xero but has no invoice number",IF(AND(L74<>"",K74=""),"No tax code",IF(AND(L74<>"",O74=""),"No revenue GL code","")))))))) | W74: =IF(E74="","",IFERROR(INDEX(lst_JobName,MATCH(E74&"",lst_Jobs,0)),"")) | X74: =IF(E74="","",COUNTIFS(tbl_Finance[Job Number],E74&"",tbl_Finance[Ex GST],"<>")) | Y74: =IF(E74="","",SUMIFS(tbl_Finance[Ex GST],tbl_Finance[Job Number],E74&"")) | Z74: =IF(E74="","",SUMIFS(tbl_Finance[Ex GST],tbl_Finance[Job Number],E74&"",tbl_Finance[Xero Invoice No],"<>")) | AA74: =IF(E74="","",Y74-Z74) | AB74: =IF(E74="","",IF(H74="Onsite",IFERROR(INDEX(tbl_Onsite[Qwilr Quote],MATCH(E74&"",tbl_Onsite[Job Number],0)),""),IF(H74="Production",IFERROR(IF(INDEX(tbl_Production[Current RMS No],MATCH(E74&"",tbl_Production[Job Number],0))="",INDEX(tbl_Production[Qwilr Quote],MATCH(E74&"",tbl_Production[Job Number],0)),INDEX(tbl_Production[Current RMS No],MATCH(E74&"",tbl_Production[Job Number],0))),""),IF(H74="Consulting",IFERROR(INDEX(tbl_Consulting[Qwilr Quote],MATCH(E74&"",tbl_Consulting[Job Number],0)),""),"")))) | AC74: =IF(AB74="","",IF(AND(LEFT(AB74,4)<>"http",IF(H74="Production",set_RMSBase,set_QwilrBase)=""),"",HYPERLINK(IF(LEFT(AB74,4)="http",AB74,IF(H74="Production",set_RMSBase,set_QwilrBase)&AB74),"Open"))) | AD74: =IF(E74="","",IF(H74="Production",IFERROR(INDEX(tbl_Production[Total Expense],MATCH(E74&"",tbl_Production[Job Number],0)),0),IF(H74="Consulting",IFERROR(INDEX(tbl_Consulting[Total Expense],MATCH(E74&"",tbl_Consulting[Job Number],0)),0),0))) | AE74: =IF(E74="","",Y74-N(AD74)) | AF74: =IFERROR(AE74/Y74,"") | AG74: =IF(E74="","",IF(H74="Onsite",IFERROR(INDEX(tbl_Onsite[Notes],MATCH(E74&"",tbl_Onsite[Job Number],0)),""),IF(H74="Production",IFERROR(INDEX(tbl_Production[Notes],MATCH(E74&"",tbl_Production[Job Number],0)),""),IF(H74="Consulting",IFERROR(INDEX(tbl_Consulting[Notes],MATCH(E74&"",tbl_Consulting[Job Number],0)),""),""))))
A75: 46234 | B75: =IF(A75="","",EOMONTH(A75,0)) | C75: INV-10555 | D75: PWC | E75: 26062202 | F75: =IF(E75="","",IF(COUNTIF(lst_Jobs,E75&"")>0,"OK","CHECK")) | G75: Early Careers Webcast 29.7.26 | H75: Production | I75: PRODUCTION | J75: Project | K75: GST 10% | L75: 1925 | M75: =IF(L75="","",IF(K75="GST 10%",ROUND(L75*set_GSTRate,2),0)) | N75: =IF(L75="","",L75+M75) | O75: 42100 | P75: Y | Q75: N | T75: Invoiced | V75: =IF(COUNTA(A75,D75,C75,L75)=0,"",IF(A75="","No date - sits outside every month",IF(E75="","No job number",IF(F75="CHECK","Job number is not in the Xero job list",IF(I75="","No cost centre",IF(AND(P75="Y",C75=""),"Marked posted to Xero but has no invoice number",IF(AND(L75<>"",K75=""),"No tax code",IF(AND(L75<>"",O75=""),"No revenue GL code","")))))))) | W75: =IF(E75="","",IFERROR(INDEX(lst_JobName,MATCH(E75&"",lst_Jobs,0)),"")) | X75: =IF(E75="","",COUNTIFS(tbl_Finance[Job Number],E75&"",tbl_Finance[Ex GST],"<>")) | Y75: =IF(E75="","",SUMIFS(tbl_Finance[Ex GST],tbl_Finance[Job Number],E75&"")) | Z75: =IF(E75="","",SUMIFS(tbl_Finance[Ex GST],tbl_Finance[Job Number],E75&"",tbl_Finance[Xero Invoice No],"<>")) | AA75: =IF(E75="","",Y75-Z75) | AB75: =IF(E75="","",IF(H75="Onsite",IFERROR(INDEX(tbl_Onsite[Qwilr Quote],MATCH(E75&"",tbl_Onsite[Job Number],0)),""),IF(H75="Production",IFERROR(IF(INDEX(tbl_Production[Current RMS No],MATCH(E75&"",tbl_Production[Job Number],0))="",INDEX(tbl_Production[Qwilr Quote],MATCH(E75&"",tbl_Production[Job Number],0)),INDEX(tbl_Production[Current RMS No],MATCH(E75&"",tbl_Production[Job Number],0))),""),IF(H75="Consulting",IFERROR(INDEX(tbl_Consulting[Qwilr Quote],MATCH(E75&"",tbl_Consulting[Job Number],0)),""),"")))) | AC75: =IF(AB75="","",IF(AND(LEFT(AB75,4)<>"http",IF(H75="Production",set_RMSBase,set_QwilrBase)=""),"",HYPERLINK(IF(LEFT(AB75,4)="http",AB75,IF(H75="Production",set_RMSBase,set_QwilrBase)&AB75),"Open"))) | AD75: =IF(E75="","",IF(H75="Production",IFERROR(INDEX(tbl_Production[Total Expense],MATCH(E75&"",tbl_Production[Job Number],0)),0),IF(H75="Consulting",IFERROR(INDEX(tbl_Consulting[Total Expense],MATCH(E75&"",tbl_Consulting[Job Number],0)),0),0))) | AE75: =IF(E75="","",Y75-N(AD75)) | AF75: =IFERROR(AE75/Y75,"") | AG75: =IF(E75="","",IF(H75="Onsite",IFERROR(INDEX(tbl_Onsite[Notes],MATCH(E75&"",tbl_Onsite[Job Number],0)),""),IF(H75="Production",IFERROR(INDEX(tbl_Production[Notes],MATCH(E75&"",tbl_Production[Job Number],0)),""),IF(H75="Consulting",IFERROR(INDEX(tbl_Consulting[Notes],MATCH(E75&"",tbl_Consulting[Job Number],0)),""),""))))
