Workbook
Name lst_CostCentre: Lists!$A$5:$A$10
Name lst_InvoiceType: Lists!$B$5:$B$14
Name lst_TaxCode: Lists!$C$5:$C$8
Name lst_Status: Lists!$D$5:$D$13
Name lst_YN: Lists!$E$5:$E$7
Name lst_Ariba: Lists!$F$5:$F$10
Name lst_WIPType: Lists!$G$5:$G$13
Name lst_WIPGL: Lists!$H$5:$H$7
Name lst_Team: Lists!$I$5:$I$8
Name lst_RevCost: Lists!$J$5:$J$6
Name lst_WonSource: Lists!$M$5:$M$8
Name lst_WonStatus: Lists!$O$5:$O$8
Name set_GSTRate: Lists!$U$8
Name set_QwilrBase: Lists!$U$5
Name set_RMSBase: Lists!$U$6
Name set_WIPAsset: Lists!$U$9
Name set_WIPIncome: Lists!$U$10
Name lst_RevGL: Lists!$K$5:$K$39
Name lst_Months: Lists!$N$5:$N$100
Name lst_Jobs: Lists!$P$5:$P$1500
Name lst_JobName: Lists!$Q$5:$Q$1500
Name lst_JobCC: Lists!$R$5:$R$1500

Sheet Read Me
B2: FY27 Revenue Tracker
B4: Corporate Technology Services Pty Ltd - replaces FY27_Revenue_Tracker_v2.xlsm
B6: WHO TYPES WHERE
C7: Finance types on the Finance sheet. Nowhere else. Every invoice line, every month.
C8: Each department types on its own sheet. Nowhere else. One row per job number.
C9: The two meet on Job Number, which is a real Xero tracking category and is checked against the live job list as you type. Nothing has to be kept lined up by hand.
B11: HOW IT FITS TOGETHER
B12: Finance | C12: The invoice register, and the only source of revenue. One row per invoice LINE, coded to one cost centre, exactly as Xero holds it. Filter the Issue column to see everything that needs fixing.
B13: Onsite / Production / Consulting | C13: One row per job. Client, invoice count and revenue come from Finance automatically; the department fills in its own costs, hours and references.
B14: WIP Movements | C14: Manual journals between the P&L and GL 11300 Work in Progress. Anything with a defer start and end on Finance does not belong here - it is handled automatically.
B15: Deferred Revenue | C15: The workings behind the automatic deferrals. Nothing is typed here; it mirrors the Finance lines that carry a defer start and end.
B16: Month-End | C16: The close: revenue by cost centre against Xero, the WIP reconciliation, fifteen data checks and a sign-off box.
B17: WIP Summary | C17: WIP opening / movement / closing for every job, to tie job by job back to the WIP Schedule file.
B18: Lists | C18: Every dropdown. Cost centres, job numbers and revenue GL codes came straight out of your Xero organisation, so they already match.
B20: DEFERRED REVENUE - it releases itself
C21: Put a Defer Start and a Defer End on a Finance line and the revenue spreads evenly across those months instead of landing all in the month you invoiced. Leave both blank for an ordinary one-off invoice.
C22: In the month invoiced: one month is recognised, the rest goes to WIP.
C23: Every month after: one more month is released, automatically.
C24: Worked example - $12,000 invoiced 15 Sep 2025 for Sep 2025 to Aug 2026. September recognises $1,000 and defers $11,000. Each month after releases $1,000. By August 2026 the balance is nil. Nothing is typed each month and no journal is needed.
C25: The Deferred Revenue sheet shows the workings line by line, and Month-End and WIP Summary already include it. One warning: a deferred line must not ALSO have a manual row on WIP Movements or it counts twice - Month-End checks for that.
C26: A cost can be deferred the same way, and it belongs on WIP Movements rather than Finance because it comes off a supplier bill, not an invoice. Type the bill amount as a positive, set Revenue or Cost to Cost, fill the two defer dates and put the expense account in P&L Account. It then spreads by month in the second block of the Deferred Revenue sheet exactly like revenue does.
C27: GL 11300 nets the two against each other, so Xero shows one figure and cannot tell you what it is made of. Month-End section 2 splits it: Total, Deferred / accrued revenue, Deferred / accrued cost. Compare only the Total column to Xero. Deferred cost never counts as revenue - section 1 leaves it out.
B29: VIDEO REVENUE
C30: There is no video split column any more, and nothing to keep honest. In Xero a cost centre sits on the invoice LINE, so a job invoiced part production and part video is simply two lines on the Finance sheet - one coded PRODUCTION, one coded VIDEO. The VIDEO figure at month-end is then a plain sum of the lines coded VIDEO, and it ties to the Xero VIDEO cost centre without any adjustment.
C31: The 26 migrated invoices that carried a video amount were split into two lines each on the way across. Ex GST in total is unchanged.
C32: The Production sheet carries a Video Revenue column beside the expenses, and Video % of Revenue next to it. Both read the Finance lines coded VIDEO, so nothing is typed. Job by job they reproduce the old Video Total column to the cent - 38,484.75 in total across 28 jobs.
B34: WHY THIS VERSION IS NOT SLOW, AND WHY IT OPENS
C35: The v2 file was slow because of its macro: every keystroke copied 26 columns by 200 rows into hidden storage, and it was capped at 200 rows per department. There are no macros here at all, and it is a .xlsx, so no macro warning and nothing blocked on SharePoint.
C36: There are also no dynamic array formulas - no VSTACK, FILTER, SORT, UNIQUE or XLOOKUP. Every sheet is a real Excel Table or a plain SUMIFS grid, which means the filter buttons, sorting and PivotTables all work normally, and every formula runs in any version of Excel.
B38: WORK WON - ZOHO, CURRENT RMS AND QWILR
C39: Paste the month's won opportunities onto the Work Won sheet, one row each, with the source, the value and the job number where you have it. Month-End section 5 totals them by source and puts them next to what was actually invoiced.
C40: It is a sense check and nothing else. No revenue ever comes off this sheet. What it catches is work won and never invoiced, and invoicing with no opportunity behind it. Put a job number on a row and it also tells you what has been raised against that job so far.
C41: Month-End section 6 turns the same sheet into the forecast. It adds two things that have no invoice against them: a Finance line carrying a value but no invoice number, and work marked Won less everything Finance already holds against that job. Subtracting all of it is what stops the same work being counted twice. Open opportunities and deferred revenue still to release sit underneath as memos, deliberately outside the total.
B43: MONTH-END, IN ORDER
C44: 1. Chase the departments until every invoice for the month is on the Finance sheet and Posted to Xero is Y.
C45: 2. Open Month-End and set the month.
C46: 3. Work section 3 first. Every count must be zero. Fix on the Finance sheet, or filter the Issue column there, which lists the same problems row by row.
C47: 4. Section 1: run the Xero P&L for the month by Cost Centre and type the revenue into the yellow column. Each line should read Reconciled.
C48: 5. Section 2: type the WIP Schedule closing balance and the Xero GL 11300 balance.
C49: 6. Breaks in section 2 - open WIP Summary, paste the WIP Schedule balances into column G and the variance column shows which job is out.
C50: 7. Section 4 is the journal. It names the account to debit, the account to credit and the amount, split by cost centre. Key it into Xero as one manual journal, then put the journal reference back on the WIP Movements rows.
C51: 8. Section 5 is the Work Won sense check against ZOHO, Current RMS and Qwilr.
B53: THE WIP SIGN RULE
C54: One signed Amount column does both jobs, because GL 11300 nets accrued and deferred revenue. Positive = revenue recognised this month (work done but not yet invoiced, or a deferral released). Negative = revenue pushed out of this month (invoiced in advance). So revenue recognised = invoiced Ex GST + WIP movement, and the running total of the Amount column is the GL 11300 balance.
C55: Every row on WIP Movements now says which account to debit, which to credit and for how much, and gives you a narration to paste. A positive amount puts revenue back into the month, so WIP goes up: debit 11300 Work in Progress, credit 44200 Closing Work in Progress. A negative amount is the other way round. The old GL Code column is gone - it said 11300 on every row and these two columns replace it.
C56: Month-End section 4 adds those rows up with the automatic deferrals and gives you the whole month as one journal, split by cost centre so it can carry tracking in Xero. Debit and credit must agree and the sheet says Balanced when they do. Nothing posts itself - you key it in and put the reference back on the rows.
C57: The two accounts are set on the Lists sheet, column U rows 9 and 10. Change them there and every Debit / Credit follows.
B59: LOCKED CELLS, LINKS AND TOTALS
C60: Every sheet is protected with the password CTS1234. Only the cells you are meant to fill are open; the grey calculated ones are locked so a stray keystroke cannot wipe a formula. To edit a locked cell: Review, Unprotect Sheet, type CTS1234. Sorting and filtering work without unprotecting anything. The workbook structure uses the same password, so sheets cannot be renamed, reordered or deleted by accident either.
C61: Qwilr quotes and Current RMS numbers are clickable. Paste a full web address and it is used as it stands; type a bare number and it is added to the base address on the Lists sheet. The Qwilr base is already set, and Current RMS on the Production sheet now works exactly the same way - paste the whole Current RMS address into the Current RMS No cell and it links straight away. Only fill in Lists column U row 6 if you would rather type the bare opportunity number.
C62: Each sheet shows its total ex-GST at the top, and it follows the filter - filter to one client or one month and the total follows. Finance shows Ex GST, GST and Inc GST.
C63: The GST rate is no longer buried in the formula. It sits on the Lists sheet, column U row 8, and every GST cell reads it from there.
B65: RULES THAT KEEP IT FAST
C66: Never insert or delete rows above the header row.
C67: Add rows by typing in the next blank row of the table, or press Tab at the end of the last row and the table grows with the formulas.
C68: Paste values only, never whole columns.
C69: Leave calculation on Automatic. Nothing here is volatile - no OFFSET, no INDIRECT, no TODAY in bulk.
C70: Keep it as .xlsx. The moment someone saves it as .xlsm and adds a macro you are back where you started.
B72: THIS IS THE EMPTY TEST COPY
C73: Nothing has been migrated into this file. Every sheet is empty and ready to type into, and every formula, dropdown, lock, hyperlink and month-end check is exactly the same as the live workbook.
C74: What is still here is reference data, because the dropdowns and the job checks need it: the Xero job list, the cost centres, the revenue GL codes and the month list on the Lists sheet.
C75: To test it end to end: type an invoice line on the Finance sheet, then type the same job number on the matching department sheet, then open Month-End, set the month and work down. Section 3 should go to nil and section 1 should add up to what you typed.
B77: STILL TO CONFIRM
C78: Discounts. Checked against Xero: for all 17 August production invoices carrying a discount, the ex-GST total on the Xero invoice equals Ex GST here exactly, and not one matched Ex GST minus the discount. So the discount comes off before the invoice is raised and Ex GST is what reconciles. The old "Net Total" is gone; Discounts Given now sits on the Production sheet at job level with Value Before Discount beside it. ASSUMPTION: it records what was given away off standard rates.
B80: Bigger text, shorter lines, one sentence per line: open the Read Me (Easy Read) tab. Same words, easier on the eye.

Sheet Read Me (Easy Read)
B2: FY27 Revenue Tracker
B3: Corporate Technology Services Pty Ltd - replaces FY27_Revenue_Tracker_v2.xlsm
B5: Who types where
C6: Finance types on the Finance sheet.
C7: Nowhere else.
C8: Every invoice line, every month.
C10: Each department types on its own sheet.
C11: Nowhere else.
C12: One row per job number.
C14: The two meet on Job Number, which is a real Xero tracking category and is checked against the live job list as you type.
C15: Nothing has to be kept lined up by hand.
B18: How it fits together
B19: Finance | C19: The invoice register, and the only source of revenue. One row per invoice line, coded to one cost centre, exactly as Xero holds it. Filter the Issue column to see everything that needs fixing.
B20: Onsite / Production / Consulting | C20: One row per job. Client, invoice count and revenue come from Finance automatically; the department fills in its own costs, hours and references.
B21: WIP Movements | C21: Manual journals between the P&L and GL 11300 Work in Progress. Anything with a defer start and end on Finance does not belong here - it is handled automatically.
B22: Deferred Revenue | C22: The workings behind the automatic deferrals. Nothing is typed here; it mirrors the Finance lines that carry a defer start and end.
B23: Month-End | C23: The close: revenue by cost centre against Xero, the WIP reconciliation, fifteen data checks and a sign-off box.
B24: WIP Summary | C24: WIP opening / movement / closing for every job, to tie job by job back to the WIP Schedule file.
B25: Lists | C25: Every dropdown. Cost centres, job numbers and revenue GL codes came straight out of your Xero organisation, so they already match.
B27: Deferred revenue - it releases itself
C28: Put a Defer Start and a Defer End on a Finance line and the revenue spreads evenly across those months instead of landing all in the month you invoiced.
C29: Leave both blank for an ordinary one-off invoice.
C31: In the month invoiced: one month is recognised, the rest goes to WIP.
C33: Every month after: one more month is released, automatically.
C35: Worked example - $12,000 invoiced 15 Sep 2025 for Sep 2025 to Aug 2026.
C36: September recognises $1,000 and defers $11,000.
C37: Each month after releases $1,000.
C38: By August 2026 the balance is nil.
C39: Nothing is typed each month and no journal is needed.
C41: The Deferred Revenue sheet shows the workings line by line, and Month-End and WIP Summary already include it.
C42: One warning: a deferred line must not also have a manual row on WIP Movements or it counts twice - Month-End checks for that.
C44: A cost can be deferred the same way, and it belongs on WIP Movements rather than Finance because it comes off a supplier bill, not an invoice.
... C51: Deferred cost never counts as revenue - section 1 leaves it out.
B54: Video revenue
C55: There is no video split column any more, and nothing to keep honest.
C56: In Xero a cost centre sits on the invoice line, so a job invoiced part production and part video is simply two lines on the Finance sheet - one coded PRODUCTION, one coded VIDEO.
C57: The VIDEO figure at month-end is then a plain sum of the lines coded VIDEO, and it ties to the Xero VIDEO cost centre without any adjustment.
C59: The 26 migrated invoices that carried a video amount were split into two lines each on the way across.
C60: Ex GST in total is unchanged.
C62: The Production sheet carries a Video Revenue column beside the expenses, and Video % of Revenue next to it.
C63: Both read the Finance lines coded VIDEO, so nothing is typed.
C64: Job by job they reproduce the old Video Total column to the cent - 38,484.75 in total across 28 jobs.
B67: Why this version is not slow, and why it opens
C68: The v2 file was slow because of its macro: every keystroke copied 26 columns by 200 rows into hidden storage, and it was capped at 200 rows per department.
C69: There are no macros here at all, and it is a .xlsx, so no macro warning and nothing blocked on SharePoint.
C71: There are also no dynamic array formulas - no VSTACK, FILTER, SORT, UNIQUE or XLOOKUP.
C72: Every sheet is a real Excel Table or a plain SUMIFS grid, which means the filter buttons, sorting and PivotTables all work normally, and every formula runs in any version of Excel.
B75: Work won - zoho, current rms and qwilr
C76: Paste the month's won opportunities onto the Work Won sheet, one row each, with the source, the value and the job number where you have it.
C77: Month-End section 5 totals them by source and puts them next to what was actually invoiced.
C79: It is a sense check and nothing else.
C80: No revenue ever comes off this sheet.
C81: What it catches is work won and never invoiced, and invoicing with no opportunity behind it.
C82: Put a job number on a row and it also tells you what has been raised against that job so far.
C84: Month-End section 6 turns the same sheet into the forecast.
C85: It adds two things that have no invoice against them: a Finance line carrying a value but no invoice number, and work marked Won less everything Finance already holds against that job.
C86: Subtracting all of it is what stops the same work being counted twice.
C87: Open opportunities and deferred revenue still to release sit underneath as memos, deliberately outside the total.
B90: Month-end, in order
C91: 1. Chase the departments until every invoice for the month is on the Finance sheet and Posted to Xero is Y.
C93: 2. Open Month-End and set the month.
C95: 3. Work section 3 first.
C96: Every count must be zero.
C97: Fix on the Finance sheet, or filter the Issue column there, which lists the same problems row by row.
C99: 4. Section 1: run the Xero P&L for the month by Cost Centre and type the revenue into the yellow column.
C100: Each line should read Reconciled.
C102: 5. Section 2: type the WIP Schedule closing balance and the Xero GL 11300 balance.
C104: 6. Breaks in section 2 - open WIP Summary, paste the WIP Schedule balances into column G and the variance column shows which job is out.
C106: 7. Section 4 is the journal.
C107: It names the account to debit, the account to credit and the amount, split by cost centre.
C108: Key it into Xero as one manual journal, then put the journal reference back on the WIP Movements rows.
C110: 8. Section 5 is the Work Won sense check against ZOHO, Current RMS and Qwilr.
B113: The WIP sign rule
C114: One signed Amount column does both jobs, because GL 11300 nets accrued and deferred revenue.
C115: Positive = revenue recognised this month (work done but not yet invoiced, or a deferral released).
C116: Negative = revenue pushed out of this month (invoiced in advance).
C117: So revenue recognised = invoiced Ex GST + WIP movement, and the running total of the Amount column is the GL 11300 balance.
C119: Every row on WIP Movements now says which account to debit, which to credit and for how much, and gives you a narration to paste.
C120: A positive amount puts revenue back into the month, so WIP goes up: debit 11300 Work in Progress, credit 44200 Closing Work in Progress.
C121: A negative amount is the other way round.
C122: The old GL Code column is gone - it said 11300 on every row and these two columns replace it.
C124: Month-End section 4 adds those rows up with the automatic deferrals and gives you the whole month as one journal, split by cost centre so it can carry tracking in Xero.
C125: Debit and credit must agree and the sheet says Balanced when they do.
C126: Nothing posts itself - you key it in and put the reference back on the rows.
C128: The two accounts are set on the Lists sheet, column U rows 9 and 10.
C129: Change them there and every Debit / Credit follows.
B132: Locked cells, links and totals
C133: Every sheet is protected with the password CTS1234.
C134: Only the cells you are meant to fill are open; the grey calculated ones are locked so a stray keystroke cannot wipe a formula.
C135: To edit a locked cell: Review, Unprotect Sheet, type CTS1234.
C136: Sorting and filtering work without unprotecting anything.
C137: The workbook structure uses the same password, so sheets cannot be renamed, reordered or deleted by accident either.
C139: Qwilr quotes and Current RMS numbers are clickable.
C140: Paste a full web address and it is used as it stands; type a bare number and it is added to the base address on the Lists sheet.
C141: The Qwilr base is already set, and Current RMS on the Production sheet now works exactly the same way - paste the whole Current RMS address into the Current RMS No cell and it links straight away.
C142: Only fill in Lists column U row 6 if you would rather type the bare opportunity number.
C144: Each sheet shows its total ex-GST at the top, and it follows the filter - filter to one client or one month and the total follows.
C145: Finance shows Ex GST, GST and Inc GST.
C147: The GST rate is no longer buried in the formula.
C148: It sits on the Lists sheet, column U row 8, and every GST cell reads it from there.
...

Sheet Finance
A1: Finance - Invoice Register
A2: One row per invoice line, coded to one cost centre, the same way Xero holds it. Finance types here and nowhere else. A job invoiced part production and part video is two lines. Filter the Issue column to see what needs fixing.
A3: ="Ex GST "&TEXT(SUBTOTAL(109,tbl_Finance[Ex GST]),"$#,##0.00")&" "&"GST "&TEXT(SUBTOTAL(109,tbl_Finance[GST]),"$#,##0.00")&" "&"Inc GST "&TEXT(SUBTOTAL(109,tbl_Finance[Inc GST]),"$#,##0.00")
A4: Date | B4: Month | C4: Xero Invoice No | D4: Client | E4: Job Number | F4: Job in Xero? | G4: Description | H4: Team | I4: Cost Centre | J4: Invoice Type | K4: Tax Code | L4: Ex GST | M4: GST | N4: Inc GST | O4: Revenue GL | P4: Posted to Xero | Q4: To WIP | R4: Defer Start | S4: Defer End | T4: Status | U4: Notes | V4: Issue | W4: On Dept Sheet | X4: Job Name (Xero) | Y4: Lines on this Job | Z4: Job Total Ex GST | AA4: Job Invoiced | AB4: Job To Invoice | AC4: Job Quote / Ref | AD4: Open Quote | AE4: Job Expense | AF4: Job Margin | AG4: Job Margin % | AH4: Dept Notes
B5: =IF(A5="","",EOMONTH(A5,0)) | F5: =IF(E5="","",IF(COUNTIF(lst_Jobs,E5&"")>0,"OK","CHECK")) | M5: =IF(L5="","",IF(K5="GST 10%",ROUND(L5*set_GSTRate,2),0)) | N5: =IF(L5="","",L5+M5) | V5: =IF(COUNTA(A5,D5,C5,L5)=0,"",IF(A5="","No date - sits outside every month",IF(E5="","No job number",IF(F5="CHECK","Job number is not in the Xero job list",IF(I5="","No cost centre",IF(AND(P5="Y",C5=""),"Marked posted to Xero but has no invoice number",IF(AND(L5<>"",K5=""),"No tax code",IF(AND(L5<>"",O5=""),"No revenue GL code","")))))))) | W5: =IF(E5="","",IF(COUNTIF(tbl_Onsite[Job Number],E5&"")>0,"Onsite",IF(COUNTIF(tbl_Production[Job Number],E5&"")>0,"Production",IF(COUNTIF(tbl_Consulting[Job Number],E5&"")>0,"Consulting","not set up yet")))) | X5: =IF(E5="","",IFERROR(INDEX(lst_JobName,MATCH(E5&"",lst_Jobs,0)),"")) | Y5: =IF(E5="","",COUNTIFS(tbl_Finance[Job Number],E5&"",tbl_Finance[Ex GST],"<>")) | Z5: =IF(E5="","",SUMIFS(tbl_Finance[Ex GST],tbl_Finance[Job Number],E5&"")) | AA5: =IF(E5="","",SUMIFS(tbl_Finance[Ex GST],tbl_Finance[Job Number],E5&"",tbl_Finance[Xero Invoice No],"<>")) | AB5: =IF(E5="","",Z5-AA5) | AC5: =IF(E5="","",IFERROR(IF(INDEX(tbl_Onsite[Qwilr Quote],MATCH(E5&"",tbl_Onsite[Job Number],0))="","",INDEX(tbl_Onsite[Qwilr Quote],MATCH(E5&"",tbl_Onsite[Job Number],0))),IFERROR(IF(IF(INDEX(tbl_Production[Current RMS No],MATCH(E5&"",tbl_Production[Job Number],0))="",INDEX(tbl_Production[Qwilr Quote],MATCH(E5&"",tbl_Production[Job Number],0)),INDEX(tbl_Production[Current RMS No],MATCH(E5&"",tbl_Production[Job Number],0)))="","",IF(INDEX(tbl_Production[Current RMS No],MATCH(E5&"",tbl_Production[Job Number],0))="",INDEX(tbl_Production[Qwilr Quote],MATCH(E5&"",tbl_Production[Job Number],0)),INDEX(tbl_Production[Current RMS No],MATCH(E5&"",tbl_Production[Job Number],0)))),IFERROR(IF(INDEX(tbl_Consulting[Qwilr Quote],MATCH(E5&"",tbl_Consulting[Job Number],0))="","",INDEX(tbl_Consulting[Qwilr Quote],MATCH(E5&"",tbl_Consulting[Job Number],0))),"")))) | AD5: =IF(AC5="","",IF(AND(LEFT(AC5,4)<>"http",IF(H5="Production",set_RMSBase,set_QwilrBase)=""),"",HYPERLINK(IF(LEFT(AC5,4)="http",AC5,IF(H5="Production",set_RMSBase,set_QwilrBase)&AC5),"Open"))) | AE5: =IF(E5="","",IFERROR(INDEX(tbl_Production[Total Expense],MATCH(E5&"",tbl_Production[Job Number],0)),IFERROR(INDEX(tbl_Consulting[Total Expense],MATCH(E5&"",tbl_Consulting[Job Number],0)),0))) | AF5: =IF(E5="","",Z5-N(AE5)) | AG5: =IFERROR(AF5/Z5,"") | AH5: =IF(E5="","",IFERROR(IF(INDEX(tbl_Onsite[Notes],MATCH(E5&"",tbl_Onsite[Job Number],0))="","",INDEX(tbl_Onsite[Notes],MATCH(E5&"",tbl_Onsite[Job Number],0))),IFERROR(IF(INDEX(tbl_Production[Notes],MATCH(E5&"",tbl_Production[Job Number],0))="","",INDEX(tbl_Production[Notes],MATCH(E5&"",tbl_Production[Job Number],0))),IFERROR(IF(INDEX(tbl_Consulting[Notes],MATCH(E5&"",tbl_Consulting[Job Number],0))="","",INDEX(tbl_Consulting[Notes],MATCH(E5&"",tbl_Consulting[Job Number],0))),""))))
B6: =IF(A6="","",EOMONTH(A6,0)) | F6: =IF(E6="","",IF(COUNTIF(lst_Jobs,E6&"")>0,"OK","CHECK")) | M6: =IF(L6="","",IF(K6="GST 10%",ROUND(L6*set_GSTRate,2),0)) | N6: =IF(L6="","",L6+M6) | V6: =IF(COUNTA(A6,D6,C6,L6)=0,"",IF(A6="","No date - sits outside every month",IF(E6="","No job number",IF(F6="CHECK","Job number is not in the Xero job list",IF(I6="","No cost centre",IF(AND(P6="Y",C6=""),"Marked posted to Xero but has no invoice number",IF(AND(L6<>"",K6=""),"No tax code",IF(AND(L6<>"",O6=""),"No revenue GL code","")))))))) | W6: =IF(E6="","",IF(COUNTIF(tbl_Onsite[Job Number],E6&"")>0,"Onsite",IF(COUNTIF(tbl_Production[Job Number],E6&"")>0,"Production",IF(COUNTIF(tbl_Consulting[Job Number],E6&"")>0,"Consulting","not set up yet")))) | X6: =IF(E6="","",IFERROR(INDEX(lst_JobName,MATCH(E6&"",lst_Jobs,0)),"")) | Y6: =IF(E6="","",COUNTIFS(tbl_Finance[Job Number],E6&"",tbl_Finance[Ex GST],"<>")) | Z6: =IF(E6="","",SUMIFS(tbl_Finance[Ex GST],tbl_Finance[Job Number],E6&"")) | AA6: =IF(E6="","",SUMIFS(tbl_Finance[Ex GST],tbl_Finance[Job Number],E6&"",tbl_Finance[Xero Invoice No],"<>")) | AB6: =IF(E6="","",Z6-AA6) | AC6: =IF(E6="","",IFERROR(IF(INDEX(tbl_Onsite[Qwilr Quote],MATCH(E6&"",tbl_Onsite[Job Number],0))="","",INDEX(tbl_Onsite[Qwilr Quote],MATCH(E6&"",tbl_Onsite[Job Number],0))),IFERROR(IF(IF(INDEX(tbl_Production[Current RMS No],MATCH(E6&"",tbl_Production[Job Number],0))="",INDEX(tbl_Production[Qwilr Quote],MATCH(E6&"",tbl_Production[Job Number],0)),INDEX(tbl_Production[Current RMS No],MATCH(E6&"",tbl_Production[Job Number],0)))="","",IF(INDEX(tbl_Production[Current RMS No],MATCH(E6&"",tbl_Production[Job Number],0))="",INDEX(tbl_Production[Qwilr Quote],MATCH(E6&"",tbl_Production[Job Number],0)),INDEX(tbl_Production[Current RMS No],MATCH(E6&"",tbl_Production[Job Number],0)))),IFERROR(IF(INDEX(tbl_Consulting[Qwilr Quote],MATCH(E6&"",tbl_Consulting[Job Number],0))="","",INDEX(tbl_Consulting[Qwilr Quote],MATCH(E6&"",tbl_Consulting[Job Number],0))),"")))) | AD6: =IF(AC6="","",IF(AND(LEFT(AC6,4)<>"http",IF(H6="Production",set_RMSBase,set_QwilrBase)=""),"",HYPERLINK(IF(LEFT(AC6,4)="http",AC6,IF(H6="Production",set_RMSBase,set_QwilrBase)&AC6),"Open"))) | AE6: =IF(E6="","",IFERROR(INDEX(tbl_Production[Total Expense],MATCH(E6&"",tbl_Production[Job Number],0)),IFERROR(INDEX(tbl_Consulting[Total Expense],MATCH(E6&"",tbl_Consulting[Job Number],0)),0))) | AF6: =IF(E6="","",Z6-N(AE6)) | AG6: =IFERROR(AF6/Z6,"") | AH6: =IF(E6="","",IFERROR(IF(INDEX(tbl_Onsite[Notes],MATCH(E6&"",tbl_Onsite[Job Number],0))="","",INDEX(tbl_Onsite[Notes],MATCH(E6&"",tbl_Onsite[Job Number],0))),IFERROR(IF(INDEX(tbl_Production[Notes],MATCH(E6&"",tbl_Production[Job Number],0))="","",INDEX(tbl_Production[Notes],MATCH(E6&"",tbl_Production[Job Number],0))),IFERROR(IF(INDEX(tbl_Consulting[Notes],MATCH(E6&"",tbl_Consulting[Job Number],0))="","",INDEX(tbl_Consulting[Notes],MATCH(E6&"",tbl_Consulting[Job Number],0))),""))))
B7: =IF(A7="","",EOMONTH(A7,0)) | F7: =IF(E7="","",IF(COUNTIF(lst_Jobs,E7&"")>0,"OK","CHECK")) | M7: =IF(L7="","",IF(K7="GST 10%",ROUND(L7*set_GSTRate,2),0)) | N7: =IF(L7="","",L7+M7) | V7: =IF(COUNTA(A7,D7,C7,L7)=0,"",IF(A7="","No date - sits outside every month",IF(E7="","No job number",IF(F7="CHECK","Job number is not in the Xero job list",IF(I7="","No cost centre",IF(AND(P7="Y",C7=""),"Marked posted to Xero but has no invoice number",IF(AND(L7<>"",K7=""),"No tax code",IF(AND(L7<>"",O7=""),"No revenue GL code","")))))))) | W7: =IF(E7="","",IF(COUNTIF(tbl_Onsite[Job Number],E7&"")>0,"Onsite",IF(COUNTIF(tbl_Production[Job Number],E7&"")>0,"Production",IF(COUNTIF(tbl_Consulting[Job Number],E7&"")>0,"Consulting","not set up yet")))) | X7: =IF(E7="","",IFERROR(INDEX(lst_JobName,MATCH(E7&"",lst_Jobs,0)),"")) | Y7: =IF(E7="","",COUNTIFS(tbl_Finance[Job Number],E7&"",tbl_Finance[Ex GST],"<>")) | Z7: =IF(E7="","",SUMIFS(tbl_Finance[Ex GST],tbl_Finance[Job Number],E7&"")) | AA7: =IF(E7="","",SUMIFS(tbl_Finance[Ex GST],tbl_Finance[Job Number],E7&"",tbl_Finance[Xero Invoice No],"<>")) | AB7: =IF(E7="","",Z7-AA7) | AC7: =IF(E7="","",IFERROR(IF(INDEX(tbl_Onsite[Qwilr Quote],MATCH(E7&"",tbl_Onsite[Job Number],0))="","",INDEX(tbl_Onsite[Qwilr Quote],MATCH(E7&"",tbl_Onsite[Job Number],0))),IFERROR(IF(IF(INDEX(tbl_Production[Current RMS No],MATCH(E7&"",tbl_Production[Job Number],0))="",INDEX(tbl_Production[Qwilr Quote],MATCH(E7&"",tbl_Production[Job Number],0)),INDEX(tbl_Production[Current RMS No],MATCH(E7&"",tbl_Production[Job Number],0)))="","",IF(INDEX(tbl_Production[Current RMS No],MATCH(E7&"",tbl_Production[Job Number],0))="",INDEX(tbl_Production[Qwilr Quote],MATCH(E7&"",tbl_Production[Job Number],0)),INDEX(tbl_Production[Current RMS No],MATCH(E7&"",tbl_Production[Job Number],0)))),IFERROR(IF(INDEX(tbl_Consulting[Qwilr Quote],MATCH(E7&"",tbl_Consulting[Job Number],0))="","",INDEX(tbl_Consulting[Qwilr Quote],MATCH(E7&"",tbl_Consulting[Job Number],0))),"")))) | AD7: =IF(AC7="","",IF(AND(LEFT(AC7,4)<>"http",IF(H7="Production",set_RMSBase,set_QwilrBase)=""),"",HYPERLINK(IF(LEFT(AC7,4)="http",AC7,IF(H7="Production",set_RMSBase,set_QwilrBase)&AC7),"Open"))) | AE7: =IF(E7="","",IFERROR(INDEX(tbl_Production[Total Expense],MATCH(E7&"",tbl_Production[Job Number],0)),IFERROR(INDEX(tbl_Consulting[Total Expense],MATCH(E7&"",tbl_Consulting[Job Number],0)),0))) | AF7: =IF(E7="","",Z7-N(AE7)) | AG7: =IFERROR(AF7/Z7,"") | AH7: =IF(E7="","",IFERROR(IF(INDEX(tbl_Onsite[Notes],MATCH(E7&"",tbl_Onsite[Job Number],0))="","",INDEX(tbl_Onsite[Notes],MATCH(E7&"",tbl_Onsite[Job Number],0))),IFERROR(IF(INDEX(tbl_Production[Notes],MATCH(E7&"",tbl_Production[Job Number],0))="","",INDEX(tbl_Production[Notes],MATCH(E7&"",tbl_Production[Job Number],0))),IFERROR(IF(INDEX(tbl_Consulting[Notes],MATCH(E7&"",tbl_Consulting[Job Number],0))="","",INDEX(tbl_Consulting[Notes],MATCH(E7&"",tbl_Consulting[Job Number],0))),""))))
B8: =IF(A8="","",EOMONTH(A8,0)) | F8: =IF(E8="","",IF(COUNTIF(lst_Jobs,E8&"")>0,"OK","CHECK")) | M8: =IF(L8="","",IF(K8="GST 10%",ROUND(L8*set_GSTRate,2),0)) | N8: =IF(L8="","",L8+M8) | V8: =IF(COUNTA(A8,D8,C8,L8)=0,"",IF(A8="","No date - sits outside every month",IF(E8="","No job number",IF(F8="CHECK","Job number is not in the Xero job list",IF(I8="","No cost centre",IF(AND(P8="Y",C8=""),"Marked posted to Xero but has no invoice number",IF(AND(L8<>"",K8=""),"No tax code",IF(AND(L8<>"",O8=""),"No revenue GL code","")))))))) | W8: =IF(E8="","",IF(COUNTIF(tbl_Onsite[Job Number],E8&"")>0,"Onsite",IF(COUNTIF(tbl_Production[Job Number],E8&"")>0,"Production",IF(COUNTIF(tbl_Consulting[Job Number],E8&"")>0,"Consulting","not set up yet")))) | X8: =IF(E8="","",IFERROR(INDEX(lst_JobName,MATCH(E8&"",lst_Jobs,0)),"")) | Y8: =IF(E8="","",COUNTIFS(tbl_Finance[Job Number],E8&"",tbl_Finance[Ex GST],"<>")) | Z8: =IF(E8="","",SUMIFS(tbl_Finance[Ex GST],tbl_Finance[Job Number],E8&"")) | AA8: =IF(E8="","",SUMIFS(tbl_Finance[Ex GST],tbl_Finance[Job Number],E8&"",tbl_Finance[Xero Invoice No],"<>")) | AB8: =IF(E8="","",Z8-AA8) | AC8: =IF(E8="","",IFERROR(IF(INDEX(tbl_Onsite[Qwilr Quote],MATCH(E8&"",tbl_Onsite[Job Number],0))="","",INDEX(tbl_Onsite[Qwilr Quote],MATCH(E8&"",tbl_Onsite[Job Number],0))),IFERROR(IF(IF(INDEX(tbl_Production[Current RMS No],MATCH(E8&"",tbl_Production[Job Number],0))="",INDEX(tbl_Production[Qwilr Quote],MATCH(E8&"",tbl_Production[Job Number],0)),INDEX(tbl_Production[Current RMS No],MATCH(E8&"",tbl_Production[Job Number],0)))="","",IF(INDEX(tbl_Production[Current RMS No],MATCH(E8&"",tbl_Production[Job Number],0))="",INDEX(tbl_Production[Qwilr Quote],MATCH(E8&"",tbl_Production[Job Number],0)),INDEX(tbl_Production[Current RMS No],MATCH(E8&"",tbl_Production[Job Number],0)))),IFERROR(IF(INDEX(tbl_Consulting[Qwilr Quote],MATCH(E8&"",tbl_Consulting[Job Number],0))="","",INDEX(tbl_Consulting[Qwilr Quote],MATCH(E8&"",tbl_Consulting[Job Number],0))),"")))) | AD8: =IF(AC8="","",IF(AND(LEFT(AC8,4)<>"http",IF(H8="Production",set_RMSBase,set_QwilrBase)=""),"",HYPERLINK(IF(LEFT(AC8,4)="http",AC8,IF(H8="Production",set_RMSBase,set_QwilrBase)&AC8),"Open"))) | AE8: =IF(E8="","",IFERROR(INDEX(tbl_Production[Total Expense],MATCH(E8&"",tbl_Production[Job Number],0)),IFERROR(INDEX(tbl_Consulting[Total Expense],MATCH(E8&"",tbl_Consulting[Job Number],0)),0))) | AF8: =IF(E8="","",Z8-N(AE8)) | AG8: =IFERROR(AF8/Z8,"") | AH8: =IF(E8="","",IFERROR(IF(INDEX(tbl_Onsite[Notes],MATCH(E8&"",tbl_Onsite[Job Number],0))="","",INDEX(tbl_Onsite[Notes],MATCH(E8&"",tbl_Onsite[Job Number],0))),IFERROR(IF(INDEX(tbl_Production[Notes],MATCH(E8&"",tbl_Production[Job Number],0))="","",INDEX(tbl_Production[Notes],MATCH(E8&"",tbl_Production[Job Number],0))),IFERROR(IF(INDEX(tbl_Consulting[Notes],MATCH(E8&"",tbl_Consulting[Job Number],0))="","",INDEX(tbl_Consulting[Notes],MATCH(E8&"",tbl_Consulting[Job Number],0))),""))))
B9: =IF(A9="","",EOMONTH(A9,0)) | F9: =IF(E9="","",IF(COUNTIF(lst_Jobs,E9&"")>0,"OK","CHECK")) | M9: =IF(L9="","",IF(K9="GST 10%",ROUND(L9*set_GSTRate,2),0)) | N9: =IF(L9="","",L9+M9) | V9: =IF(COUNTA(A9,D9,C9,L9)=0,"",IF(A9="","No date - sits outside every month",IF(E9="","No job number",IF(F9="CHECK","Job number is not in the Xero job list",IF(I9="","No cost centre",IF(AND(P9="Y",C9=""),"Marked posted to Xero but has no invoice number",IF(AND(L9<>"",K9=""),"No tax code",IF(AND(L9<>"",O9=""),"No revenue GL code","")))))))) | W9: =IF(E9="","",IF(COUNTIF(tbl_Onsite[Job Number],E9&"")>0,"Onsite",IF(COUNTIF(tbl_Production[Job Number],E9&"")>0,"Production",IF(COUNTIF(tbl_Consulting[Job Number],E9&"")>0,"Consulting","not set up yet")))) | X9: =IF(E9="","",IFERROR(INDEX(lst_JobName,MATCH(E9&"",lst_Jobs,0)),"")) | Y9: =IF(E9="","",COUNTIFS(tbl_Finance[Job Number],E9&"",tbl_Finance[Ex GST],"<>")) | Z9: =IF(E9="","",SUMIFS(tbl_Finance[Ex GST],tbl_Finance[Job Number],E9&"")) | AA9: =IF(E9="","",SUMIFS(tbl_Finance[Ex GST],tbl_Finance[Job Number],E9&"",tbl_Finance[Xero Invoice No],"<>")) | AB9: =IF(E9="","",Z9-AA9) | AC9: =IF(E9="","",IFERROR(IF(INDEX(tbl_Onsite[Qwilr Quote],MATCH(E9&"",tbl_Onsite[Job Number],0))="","",INDEX(tbl_Onsite[Qwilr Quote],MATCH(E9&"",tbl_Onsite[Job Number],0))),IFERROR(IF(IF(INDEX(tbl_Production[Current RMS No],MATCH(E9&"",tbl_Production[Job Number],0))="",INDEX(tbl_Production[Qwilr Quote],MATCH(E9&"",tbl_Production[Job Number],0)),INDEX(tbl_Production[Current RMS No],MATCH(E9&"",tbl_Production[Job Number],0)))="","",IF(INDEX(tbl_Production[Current RMS No],MATCH(E9&"",tbl_Production[Job Number],0))="",INDEX(tbl_Production[Qwilr Quote],MATCH(E9&"",tbl_Production[Job Number],0)),INDEX(tbl_Production[Current RMS No],MATCH(E9&"",tbl_Production[Job Number],0)))),IFERROR(IF(INDEX(tbl_Consulting[Qwilr Quote],MATCH(E9&"",tbl_Consulting[Job Number],0))="","",INDEX(tbl_Consulting[Qwilr Quote],MATCH(E9&"",tbl_Consulting[Job Number],0))),"")))) | AD9: =IF(AC9="","",IF(AND(LEFT(AC9,4)<>"http",IF(H9="Production",set_RMSBase,set_QwilrBase)=""),"",HYPERLINK(IF(LEFT(AC9,4)="http",AC9,IF(H9="Production",set_RMSBase,set_QwilrBase)&AC9),"Open"))) | AE9: =IF(E9="","",IFERROR(INDEX(tbl_Production[Total Expense],MATCH(E9&"",tbl_Production[Job Number],0)),IFERROR(INDEX(tbl_Consulting[Total Expense],MATCH(E9&"",tbl_Consulting[Job Number],0)),0))) | AF9: =IF(E9="","",Z9-N(AE9)) | AG9: =IFERROR(AF9/Z9,"") | AH9: =IF(E9="","",IFERROR(IF(INDEX(tbl_Onsite[Notes],MATCH(E9&"",tbl_Onsite[Job Number],0))="","",INDEX(tbl_Onsite[Notes],MATCH(E9&"",tbl_Onsite[Job Number],0))),IFERROR(IF(INDEX(tbl_Production[Notes],MATCH(E9&"",tbl_Production[Job Number],0))="","",INDEX(tbl_Production[Notes],MATCH(E9&"",tbl_Production[Job Number],0))),IFERROR(IF(INDEX(tbl_Consulting[Notes],MATCH(E9&"",tbl_Consulting[Job Number],0))="","",INDEX(tbl_Consulting[Notes],MATCH(E9&"",tbl_Consulting[Job Number],0))),""))))
B10: =IF(A10="","",EOMONTH(A10,0)) | F10: =IF(E10="","",IF(COUNTIF(lst_Jobs,E10&"")>0,"OK","CHECK")) | M10: =IF(L10="","",IF(K10="GST 10%",ROUND(L10*set_GSTRate,2),0)) | N10: =IF(L10="","",L10+M10) | V10: =IF(COUNTA(A10,D10,C10,L10)=0,"",IF(A10="","No date - sits outside every month",IF(E10="","No job number",IF(F10="CHECK","Job number is not in the Xero job list",IF(I10="","No cost centre",IF(AND(P10="Y",C10=""),"Marked posted to Xero but has no invoice number",IF(AND(L10<>"",K10=""),"No tax code",IF(AND(L10<>"",O10=""),"No revenue GL code","")))))))) | W10: =IF(E10="","",IF(COUNTIF(tbl_Onsite[Job Number],E10&"")>0,"Onsite",IF(COUNTIF(tbl_Production[Job Number],E10&"")>0,"Production",IF(COUNTIF(tbl_Consulting[Job Number],E10&"")>0,"Consulting","not set up yet")))) | X10: =IF(E10="","",IFERROR(INDEX(lst_JobName,MATCH(E10&"",lst_Jobs,0)),"")) | Y10: =IF(E10="","",COUNTIFS(tbl_Finance[Job Number],E10&"",tbl_Finance[Ex GST],"<>")) | Z10: =IF(E10="","",SUMIFS(tbl_Finance[Ex GST],tbl_Finance[Job Number],E10&"")) | AA10: =IF(E10="","",SUMIFS(tbl_Finance[Ex GST],tbl_Finance[Job Number],E10&"",tbl_Finance[Xero Invoice No],"<>")) | AB10: =IF(E10="","",Z10-AA10) | AC10: =IF(E10="","",IFERROR(IF(INDEX(tbl_Onsite[Qwilr Quote],MATCH(E10&"",tbl_Onsite[Job Number],0))="","",INDEX(tbl_Onsite[Qwilr Quote],MATCH(E10&"",tbl_Onsite[Job Number],0))),IFERROR(IF(IF(INDEX(tbl_Production[Current RMS No],MATCH(E10&"",tbl_Production[Job Number],0))="",INDEX(tbl_Production[Qwilr Quote],MATCH(E10&"",tbl_Production[Job Number],0)),INDEX(tbl_Production[Current RMS No],MATCH(E10&"",tbl_Production[Job Number],0)))="","",IF(INDEX(tbl_Production[Current RMS No],MATCH(E10&"",tbl_Production[Job Number],0))="",INDEX(tbl_Production[Qwilr Quote],MATCH(E10&"",tbl_Production[Job Number],0)),INDEX(tbl_Production[Current RMS No],MATCH(E10&"",tbl_Production[Job Number],0)))),IFERROR(IF(INDEX(tbl_Consulting[Qwilr Quote],MATCH(E10&"",tbl_Consulting[Job Number],0))="","",INDEX(tbl_Consulting[Qwilr Quote],MATCH(E10&"",tbl_Consulting[Job Number],0))),"")))) | AD10: =IF(AC10="","",IF(AND(LEFT(AC10,4)<>"http",IF(H10="Production",set_RMSBase,set_QwilrBase)=""),"",HYPERLINK(IF(LEFT(AC10,4)="http",AC10,IF(H10="Production",set_RMSBase,set_QwilrBase)&AC10),"Open"))) | AE10: =IF(E10="","",IFERROR(INDEX(tbl_Production[Total Expense],MATCH(E10&"",tbl_Production[Job Number],0)),IFERROR(INDEX(tbl_Consulting[Total Expense],MATCH(E10&"",tbl_Consulting[Job Number],0)),0))) | AF10: =IF(E10="","",Z10-N(AE10)) | AG10: =IFERROR(AF10/Z10,"") | AH10: =IF(E10="","",IFERROR(IF(INDEX(tbl_Onsite[Notes],MATCH(E10&"",tbl_Onsite[Job Number],0))="","",INDEX(tbl_Onsite[Notes],MATCH(E10&"",tbl_Onsite[Job Number],0))),IFERROR(IF(INDEX(tbl_Production[Notes],MATCH(E10&"",tbl_Production[Job Number],0))="","",INDEX(tbl_Production[Notes],MATCH(E10&"",tbl_Production[Job Number],0))),IFERROR(IF(INDEX(tbl_Consulting[Notes],MATCH(E10&"",tbl_Consulting[Job Number],0))="","",INDEX(tbl_Consulting[Notes],MATCH(E10&"",tbl_Consulting[Job Number],0))),""))))
B11: =IF(A11="","",EOMONTH(A11,0)) | F11: =IF(E11="","",IF(COUNTIF(lst_Jobs,E11&"")>0,"OK","CHECK")) | M11: =IF(L11="","",IF(K11="GST 10%",ROUND(L11*set_GSTRate,2),0)) | N11: =IF(L11="","",L11+M11) | V11: =IF(COUNTA(A11,D11,C11,L11)=0,"",IF(A11="","No date - sits outside every month",IF(E11="","No job number",IF(F11="CHECK","Job number is not in the Xero job list",IF(I11="","No cost centre",IF(AND(P11="Y",C11=""),"Marked posted to Xero but has no invoice number",IF(AND(L11<>"",K11=""),"No tax code",IF(AND(L11<>"",O11=""),"No revenue GL code","")))))))) | W11: =IF(E11="","",IF(COUNTIF(tbl_Onsite[Job Number],E11&"")>0,"Onsite",IF(COUNTIF(tbl_Production[Job Number],E11&"")>0,"Production",IF(COUNTIF(tbl_Consulting[Job Number],E11&"")>0,"Consulting","not set up yet")))) | X11: =IF(E11="","",IFERROR(INDEX(lst_JobName,MATCH(E11&"",lst_Jobs,0)),"")) | Y11: =IF(E11="","",COUNTIFS(tbl_Finance[Job Number],E11&"",tbl_Finance[Ex GST],"<>")) | Z11: =IF(E11="","",SUMIFS(tbl_Finance[Ex GST],tbl_Finance[Job Number],E11&"")) | AA11: =IF(E11="","",SUMIFS(tbl_Finance[Ex GST],tbl_Finance[Job Number],E11&"",tbl_Finance[Xero Invoice No],"<>")) | AB11: =IF(E11="","",Z11-AA11) | AC11: =IF(E11="","",IFERROR(IF(INDEX(tbl_Onsite[Qwilr Quote],MATCH(E11&"",tbl_Onsite[Job Number],0))="","",INDEX(tbl_Onsite[Qwilr Quote],MATCH(E11&"",tbl_Onsite[Job Number],0))),IFERROR(IF(IF(INDEX(tbl_Production[Current RMS No],MATCH(E11&"",tbl_Production[Job Number],0))="",INDEX(tbl_Production[Qwilr Quote],MATCH(E11&"",tbl_Production[Job Number],0)),INDEX(tbl_Production[Current RMS No],MATCH(E11&"",tbl_Production[Job Number],0)))="","",IF(INDEX(tbl_Production[Current RMS No],MATCH(E11&"",tbl_Production[Job Number],0))="",INDEX(tbl_Production[Qwilr Quote],MATCH(E11&"",tbl_Production[Job Number],0)),INDEX(tbl_Production[Current RMS No],MATCH(E11&"",tbl_Production[Job Number],0)))),IFERROR(IF(INDEX(tbl_Consulting[Qwilr Quote],MATCH(E11&"",tbl_Consulting[Job Number],0))="","",INDEX(tbl_Consulting[Qwilr Quote],MATCH(E11&"",tbl_Consulting[Job Number],0))),"")))) | AD11: =IF(AC11="","",IF(AND(LEFT(AC11,4)<>"http",IF(H11="Production",set_RMSBase,set_QwilrBase)=""),"",HYPERLINK(IF(LEFT(AC11,4)="http",AC11,IF(H11="Production",set_RMSBase,set_QwilrBase)&AC11),"Open"))) | AE11: =IF(E11="","",IFERROR(INDEX(tbl_Production[Total Expense],MATCH(E11&"",tbl_Production[Job Number],0)),IFERROR(INDEX(tbl_Consulting[Total Expense],MATCH(E11&"",tbl_Consulting[Job Number],0)),0))) | AF11: =IF(E11="","",Z11-N(AE11)) | AG11: =IFERROR(AF11/Z11,"") | AH11: =IF(E11="","",IFERROR(IF(INDEX(tbl_Onsite[Notes],MATCH(E11&"",tbl_Onsite[Job Number],0))="","",INDEX(tbl_Onsite[Notes],MATCH(E11&"",tbl_Onsite[Job Number],0))),IFERROR(IF(INDEX(tbl_Production[Notes],MATCH(E11&"",tbl_Production[Job Number],0))="","",INDEX(tbl_Production[Notes],MATCH(E11&"",tbl_Production[Job Number],0))),IFERROR(IF(INDEX(tbl_Consulting[Notes],MATCH(E11&"",tbl_Consulting[Job Number],0))="","",INDEX(tbl_Consulting[Notes],MATCH(E11&"",tbl_Consulting[Job Number],0))),""))))
B12: =IF(A12="","",EOMONTH(A12,0)) | F12: =IF(E12="","",IF(COUNTIF(lst_Jobs,E12&"")>0,"OK","CHECK")) | M12: =IF(L12="","",IF(K12="GST 10%",ROUND(L12*set_GSTRate,2),0)) | N12: =IF(L12="","",L12+M12) | V12: =IF(COUNTA(A12,D12,C12,L12)=0,"",IF(A12="","No date - sits outside every month",IF(E12="","No job number",IF(F12="CHECK","Job number is not in the Xero job list",IF(I12="","No cost centre",IF(AND(P12="Y",C12=""),"Marked posted to Xero but has no invoice number",IF(AND(L12<>"",K12=""),"No tax code",IF(AND(L12<>"",O12=""),"No revenue GL code","")))))))) | W12: =IF(E12="","",IF(COUNTIF(tbl_Onsite[Job Number],E12&"")>0,"Onsite",IF(COUNTIF(tbl_Production[Job Number],E12&"")>0,"Production",IF(COUNTIF(tbl_Consulting[Job Number],E12&"")>0,"Consulting","not set up yet")))) | X12: =IF(E12="","",IFERROR(INDEX(lst_JobName,MATCH(E12&"",lst_Jobs,0)),"")) | Y12: =IF(E12="","",COUNTIFS(tbl_Finance[Job Number],E12&"",tbl_Finance[Ex GST],"<>")) | Z12: =IF(E12="","",SUMIFS(tbl_Finance[Ex GST],tbl_Finance[Job Number],E12&"")) | AA12: =IF(E12="","",SUMIFS(tbl_Finance[Ex GST],tbl_Finance[Job Number],E12&"",tbl_Finance[Xero Invoice No],"<>")) | AB12: =IF(E12="","",Z12-AA12) | AC12: =IF(E12="","",IFERROR(IF(INDEX(tbl_Onsite[Qwilr Quote],MATCH(E12&"",tbl_Onsite[Job Number],0))="","",INDEX(tbl_Onsite[Qwilr Quote],MATCH(E12&"",tbl_Onsite[Job Number],0))),IFERROR(IF(IF(INDEX(tbl_Production[Current RMS No],MATCH(E12&"",tbl_Production[Job Number],0))="",INDEX(tbl_Production[Qwilr Quote],MATCH(E12&"",tbl_Production[Job Number],0)),INDEX(tbl_Production[Current RMS No],MATCH(E12&"",tbl_Production[Job Number],0)))="","",IF(INDEX(tbl_Production[Current RMS No],MATCH(E12&"",tbl_Production[Job Number],0))="",INDEX(tbl_Production[Qwilr Quote],MATCH(E12&"",tbl_Production[Job Number],0)),INDEX(tbl_Production[Current RMS No],MATCH(E12&"",tbl_Production[Job Number],0)))),IFERROR(IF(INDEX(tbl_Consulting[Qwilr Quote],MATCH(E12&"",tbl_Consulting[Job Number],0))="","",INDEX(tbl_Consulting[Qwilr Quote],MATCH(E12&"",tbl_Consulting[Job Number],0))),"")))) | AD12: =IF(AC12="","",IF(AND(LEFT(AC12,4)<>"http",IF(H12="Production",set_RMSBase,set_QwilrBase)=""),"",HYPERLINK(IF(LEFT(AC12,4)="http",AC12,IF(H12="Production",set_RMSBase,set_QwilrBase)&AC12),"Open"))) | AE12: =IF(E12="","",IFERROR(INDEX(tbl_Production[Total Expense],MATCH(E12&"",tbl_Production[Job Number],0)),IFERROR(INDEX(tbl_Consulting[Total Expense],MATCH(E12&"",tbl_Consulting[Job Number],0)),0))) | AF12: =IF(E12="","",Z12-N(AE12)) | AG12: =IFERROR(AF12/Z12,"") | AH12: =IF(E12="","",IFERROR(IF(INDEX(tbl_Onsite[Notes],MATCH(E12&"",tbl_Onsite[Job Number],0))="","",INDEX(tbl_Onsite[Notes],MATCH(E12&"",tbl_Onsite[Job Number],0))),IFERROR(IF(INDEX(tbl_Production[Notes],MATCH(E12&"",tbl_Production[Job Number],0))="","",INDEX(tbl_Production[Notes],MATCH(E12&"",tbl_Production[Job Number],0))),IFERROR(IF(INDEX(tbl_Consulting[Notes],MATCH(E12&"",tbl_Consulting[Job Number],0))="","",INDEX(tbl_Consulting[Notes],MATCH(E12&"",tbl_Consulting[Job Number],0))),""))))
B13: =IF(A13="","",EOMONTH(A13,0)) | F13: =IF(E13="","",IF(COUNTIF(lst_Jobs,E13&"")>0,"OK","CHECK")) | M13: =IF(L13="","",IF(K13="GST 10%",ROUND(L13*set_GSTRate,2),0)) | N13: =IF(L13="","",L13+M13) | V13: =IF(COUNTA(A13,D13,C13,L13)=0,"",IF(A13="","No date - sits outside every month",IF(E13="","No job number",IF(F13="CHECK","Job number is not in the Xero job list",IF(I13="","No cost centre",IF(AND(P13="Y",C13=""),"Marked posted to Xero but has no invoice number",IF(AND(L13<>"",K13=""),"No tax code",IF(AND(L13<>"",O13=""),"No revenue GL code","")))))))) | W13: =IF(E13="","",IF(COUNTIF(tbl_Onsite[Job Number],E13&"")>0,"Onsite",IF(COUNTIF(tbl_Production[Job Number],E13&"")>0,"Production",IF(COUNTIF(tbl_Consulting[Job Number],E13&"")>0,"Consulting","not set up yet")))) | X13: =IF(E13="","",IFERROR(INDEX(lst_JobName,MATCH(E13&"",lst_Jobs,0)),"")) | Y13: =IF(E13="","",COUNTIFS(tbl_Finance[Job Number],E13&"",tbl_Finance[Ex GST],"<>")) | Z13: =IF(E13="","",SUMIFS(tbl_Finance[Ex GST],tbl_Finance[Job Number],E13&"")) | AA13: =IF(E13="","",SUMIFS(tbl_Finance[Ex GST],tbl_Finance[Job Number],E13&"",tbl_Finance[Xero Invoice No],"<>")) | AB13: =IF(E13="","",Z13-AA13) | AC13: =IF(E13="","",IFERROR(IF(INDEX(tbl_Onsite[Qwilr Quote],MATCH(E13&"",tbl_Onsite[Job Number],0))="","",INDEX(tbl_Onsite[Qwilr Quote],MATCH(E13&"",tbl_Onsite[Job Number],0))),IFERROR(IF(IF(INDEX(tbl_Production[Current RMS No],MATCH(E13&"",tbl_Production[Job Number],0))="",INDEX(tbl_Production[Qwilr Quote],MATCH(E13&"",tbl_Production[Job Number],0)),INDEX(tbl_Production[Current RMS No],MATCH(E13&"",tbl_Production[Job Number],0)))="","",IF(INDEX(tbl_Production[Current RMS No],MATCH(E13&"",tbl_Production[Job Number],0))="",INDEX(tbl_Production[Qwilr Quote],MATCH(E13&"",tbl_Production[Job Number],0)),INDEX(tbl_Production[Current RMS No],MATCH(E13&"",tbl_Production[Job Number],0)))),IFERROR(IF(INDEX(tbl_Consulting[Qwilr Quote],MATCH(E13&"",tbl_Consulting[Job Number],0))="","",INDEX(tbl_Consulting[Qwilr Quote],MATCH(E13&"",tbl_Consulting[Job Number],0))),"")))) | AD13: =IF(AC13="","",IF(AND(LEFT(AC13,4)<>"http",IF(H13="Production",set_RMSBase,set_QwilrBase)=""),"",HYPERLINK(IF(LEFT(AC13,4)="http",AC13,IF(H13="Production",set_RMSBase,set_QwilrBase)&AC13),"Open"))) | AE13: =IF(E13="","",IFERROR(INDEX(tbl_Production[Total Expense],MATCH(E13&"",tbl_Production[Job Number],0)),IFERROR(INDEX(tbl_Consulting[Total Expense],MATCH(E13&"",tbl_Consulting[Job Number],0)),0))) | AF13: =IF(E13="","",Z13-N(AE13)) | AG13: =IFERROR(AF13/Z13,"") | AH13: =IF(E13="","",IFERROR(IF(INDEX(tbl_Onsite[Notes],MATCH(E13&"",tbl_Onsite[Job Number],0))="","",INDEX(tbl_Onsite[Notes],MATCH(E13&"",tbl_Onsite[Job Number],0))),IFERROR(IF(INDEX(tbl_Production[Notes],MATCH(E13&"",tbl_Production[Job Number],0))="","",INDEX(tbl_Production[Notes],MATCH(E13&"",tbl_Production[Job Number],0))),IFERROR(IF(INDEX(tbl_Consulting[Notes],MATCH(E13&"",tbl_Consulting[Job Number],0))="","",INDEX(tbl_Consulting[Notes],MATCH(E13&"",tbl_Consulting[Job Number],0))),""))))
B14: =IF(A14="","",EOMONTH(A14,0)) | F14: =IF(E14="","",IF(COUNTIF(lst_Jobs,E14&"")>0,"OK","CHECK")) | M14: =IF(L14="","",IF(K14="GST 10%",ROUND(L14*set_GSTRate,2),0)) | N14: =IF(L14="","",L14+M14) | V14: =IF(COUNTA(A14,D14,C14,L14)=0,"",IF(A14="","No date - sits outside every month",IF(E14="","No job number",IF(F14="CHECK","Job number is not in the Xero job list",IF(I14="","No cost centre",IF(AND(P14="Y",C14=""),"Marked posted to Xero but has no invoice number",IF(AND(L14<>"",K14=""),"No tax code",IF(AND(L14<>"",O14=""),"No revenue GL code","")))))))) | W14: =IF(E14="","",IF(COUNTIF(tbl_Onsite[Job Number],E14&"")>0,"Onsite",IF(COUNTIF(tbl_Production[Job Number],E14&"")>0,"Production",IF(COUNTIF(tbl_Consulting[Job Number],E14&"")>0,"Consulting","not set up yet")))) | X14: =IF(E14="","",IFERROR(INDEX(lst_JobName,MATCH(E14&"",lst_Jobs,0)),"")) | Y14: =IF(E14="","",COUNTIFS(tbl_Finance[Job Number],E14&"",tbl_Finance[Ex GST],"<>")) | Z14: =IF(E14="","",SUMIFS(tbl_Finance[Ex GST],tbl_Finance[Job Number],E14&"")) | AA14: =IF(E14="","",SUMIFS(tbl_Finance[Ex GST],tbl_Finance[Job Number],E14&"",tbl_Finance[Xero Invoice No],"<>")) | AB14: =IF(E14="","",Z14-AA14) | AC14: =IF(E14="","",IFERROR(IF(INDEX(tbl_Onsite[Qwilr Quote],MATCH(E14&"",tbl_Onsite[Job Number],0))="","",INDEX(tbl_Onsite[Qwilr Quote],MATCH(E14&"",tbl_Onsite[Job Number],0))),IFERROR(IF(IF(INDEX(tbl_Production[Current RMS No],MATCH(E14&"",tbl_Production[Job Number],0))="",INDEX(tbl_Production[Qwilr Quote],MATCH(E14&"",tbl_Production[Job Number],0)),INDEX(tbl_Production[Current RMS No],MATCH(E14&"",tbl_Production[Job Number],0)))="","",IF(INDEX(tbl_Production[Current RMS No],MATCH(E14&"",tbl_Production[Job Number],0))="",INDEX(tbl_Production[Qwilr Quote],MATCH(E14&"",tbl_Production[Job Number],0)),INDEX(tbl_Production[Current RMS No],MATCH(E14&"",tbl_Production[Job Number],0)))),IFERROR(IF(INDEX(tbl_Consulting[Qwilr Quote],MATCH(E14&"",tbl_Consulting[Job Number],0))="","",INDEX(tbl_Consulting[Qwilr Quote],MATCH(E14&"",tbl_Consulting[Job Number],0))),"")))) | AD14: =IF(AC14="","",IF(AND(LEFT(AC14,4)<>"http",IF(H14="Production",set_RMSBase,set_QwilrBase)=""),"",HYPERLINK(IF(LEFT(AC14,4)="http",AC14,IF(H14="Production",set_RMSBase,set_QwilrBase)&AC14),"Open"))) | AE14: =IF(E14="","",IFERROR(INDEX(tbl_Production[Total Expense],MATCH(E14&"",tbl_Production[Job Number],0)),IFERROR(INDEX(tbl_Consulting[Total Expense],MATCH(E14&"",tbl_Consulting[Job Number],0)),0))) | AF14: =IF(E14="","",Z14-N(AE14)) | AG14: =IFERROR(AF14/Z14,"") | AH14: =IF(E14="","",IFERROR(IF(INDEX(tbl_Onsite[Notes],MATCH(E14&"",tbl_Onsite[Job Number],0))="","",INDEX(tbl_Onsite[Notes],MATCH(E14&"",tbl_Onsite[Job Number],0))),IFERROR(IF(INDEX(tbl_Production[Notes],MATCH(E14&"",tbl_Production[Job Number],0))="","",INDEX(tbl_Production[Notes],MATCH(E14&"",tbl_Production[Job Number],0))),IFERROR(IF(INDEX(tbl_Consulting[Notes],MATCH(E14&"",tbl_Consulting[Job Number],0))="","",INDEX(tbl_Consulting[Notes],MATCH(E14&"",tbl_Consulting[Job Number],0))),""))))
B15: =IF(A15="","",EOMONTH(A15,0)) | F15: =IF(E15="","",IF(COUNTIF(lst_Jobs,E15&"")>0,"OK","CHECK")) | M15: =IF(L15="","",IF(K15="GST 10%",ROUND(L15*set_GSTRate,2),0)) | N15: =IF(L15="","",L15+M15) | V15: =IF(COUNTA(A15,D15,C15,L15)=0,"",IF(A15="","No date - sits outside every month",IF(E15="","No job number",IF(F15="CHECK","Job number is not in the Xero job list",IF(I15="","No cost centre",IF(AND(P15="Y",C15=""),"Marked posted to Xero but has no invoice number",IF(AND(L15<>"",K15=""),"No tax code",IF(AND(L15<>"",O15=""),"No revenue GL code","")))))))) | W15: =IF(E15="","",IF(COUNTIF(tbl_Onsite[Job Number],E15&"")>0,"Onsite",IF(COUNTIF(tbl_Production[Job Number],E15&"")>0,"Production",IF(COUNTIF(tbl_Consulting[Job Number],E15&"")>0,"Consulting","not set up yet")))) | X15: =IF(E15="","",IFERROR(INDEX(lst_JobName,MATCH(E15&"",lst_Jobs,0)),"")) | Y15: =IF(E15="","",COUNTIFS(tbl_Finance[Job Number],E15&"",tbl_Finance[Ex GST],"<>")) | Z15: =IF(E15="","",SUMIFS(tbl_Finance[Ex GST],tbl_Finance[Job Number],E15&"")) | AA15: =IF(E15="","",SUMIFS(tbl_Finance[Ex GST],tbl_Finance[Job Number],E15&"",tbl_Finance[Xero Invoice No],"<>")) | AB15: =IF(E15="","",Z15-AA15) | AC15: =IF(E15="","",IFERROR(IF(INDEX(tbl_Onsite[Qwilr Quote],MATCH(E15&"",tbl_Onsite[Job Number],0))="","",INDEX(tbl_Onsite[Qwilr Quote],MATCH(E15&"",tbl_Onsite[Job Number],0))),IFERROR(IF(IF(INDEX(tbl_Production[Current RMS No],MATCH(E15&"",tbl_Production[Job Number],0))="",INDEX(tbl_Production[Qwilr Quote],MATCH(E15&"",tbl_Production[Job Number],0)),INDEX(tbl_Production[Current RMS No],MATCH(E15&"",tbl_Production[Job Number],0)))="","",IF(INDEX(tbl_Production[Current RMS No],MATCH(E15&"",tbl_Production[Job Number],0))="",INDEX(tbl_Production[Qwilr Quote],MATCH(E15&"",tbl_Production[Job Number],0)),INDEX(tbl_Production[Current RMS No],MATCH(E15&"",tbl_Production[Job Number],0)))),IFERROR(IF(INDEX(tbl_Consulting[Qwilr Quote],MATCH(E15&"",tbl_Consulting[Job Number],0))="","",INDEX(tbl_Consulting[Qwilr Quote],MATCH(E15&"",tbl_Consulting[Job Number],0))),"")))) | AD15: =IF(AC15="","",IF(AND(LEFT(AC15,4)<>"http",IF(H15="Production",set_RMSBase,set_QwilrBase)=""),"",HYPERLINK(IF(LEFT(AC15,4)="http",AC15,IF(H15="Production",set_RMSBase,set_QwilrBase)&AC15),"Open"))) | AE15: =IF(E15="","",IFERROR(INDEX(tbl_Production[Total Expense],MATCH(E15&"",tbl_Production[Job Number],0)),IFERROR(INDEX(tbl_Consulting[Total Expense],MATCH(E15&"",tbl_Consulting[Job Number],0)),0))) | AF15: =IF(E15="","",Z15-N(AE15)) | AG15: =IFERROR(AF15/Z15,"") | AH15: =IF(E15="","",IFERROR(IF(INDEX(tbl_Onsite[Notes],MATCH(E15&"",tbl_Onsite[Job Number],0))="","",INDEX(tbl_Onsite[Notes],MATCH(E15&"",tbl_Onsite[Job Number],0))),IFERROR(IF(INDEX(tbl_Production[Notes],MATCH(E15&"",tbl_Production[Job Number],0))="","",INDEX(tbl_Production[Notes],MATCH(E15&"",tbl_Production[Job Number],0))),IFERROR(IF(INDEX(tbl_Consulting[Notes],MATCH(E15&"",tbl_Consulting[Job Number],0))="","",INDEX(tbl_Consulting[Notes],MATCH(E15&"",tbl_Consulting[Job Number],0))),""))))
B16: =IF(A16="","",EOMONTH(A16,0)) | F16: =IF(E16="","",IF(COUNTIF(lst_Jobs,E16&"")>0,"OK","CHECK")) | M16: =IF(L16="","",IF(K16="GST 10%",ROUND(L16*set_GSTRate,2),0)) | N16: =IF(L16="","",L16+M16) | V16: =IF(COUNTA(A16,D16,C16,L16)=0,"",IF(A16="","No date - sits outside every month",IF(E16="","No job number",IF(F16="CHECK","Job number is not in the Xero job list",IF(I16="","No cost centre",IF(AND(P16="Y",C16=""),"Marked posted to Xero but has no invoice number",IF(AND(L16<>"",K16=""),"No tax code",IF(AND(L16<>"",O16=""),"No revenue GL code","")))))))) | W16: =IF(E16="","",IF(COUNTIF(tbl_Onsite[Job Number],E16&"")>0,"Onsite",IF(COUNTIF(tbl_Production[Job Number],E16&"")>0,"Production",IF(COUNTIF(tbl_Consulting[Job Number],E16&"")>0,"Consulting","not set up yet")))) | X16: =IF(E16="","",IFERROR(INDEX(lst_JobName,MATCH(E16&"",lst_Jobs,0)),"")) | Y16: =IF(E16="","",COUNTIFS(tbl_Finance[Job Number],E16&"",tbl_Finance[Ex GST],"<>")) | Z16: =IF(E16="","",SUMIFS(tbl_Finance[Ex GST],tbl_Finance[Job Number],E16&"")) | AA16: =IF(E16="","",SUMIFS(tbl_Finance[Ex GST],tbl_Finance[Job Number],E16&"",tbl_Finance[Xero Invoice No],"<>")) | AB16: =IF(E16="","",Z16-AA16) | AC16: =IF(E16="","",IFERROR(IF(INDEX(tbl_Onsite[Qwilr Quote],MATCH(E16&"",tbl_Onsite[Job Number],0))="","",INDEX(tbl_Onsite[Qwilr Quote],MATCH(E16&"",tbl_Onsite[Job Number],0))),IFERROR(IF(IF(INDEX(tbl_Production[Current RMS No],MATCH(E16&"",tbl_Production[Job Number],0))="",INDEX(tbl_Production[Qwilr Quote],MATCH(E16&"",tbl_Production[Job Number],0)),INDEX(tbl_Production[Current RMS No],MATCH(E16&"",tbl_Production[Job Number],0)))="","",IF(INDEX(tbl_Production[Current RMS No],MATCH(E16&"",tbl_Production[Job Number],0))="",INDEX(tbl_Production[Qwilr Quote],MATCH(E16&"",tbl_Production[Job Number],0)),INDEX(tbl_Production[Current RMS No],MATCH(E16&"",tbl_Production[Job Number],0)))),IFERROR(IF(INDEX(tbl_Consulting[Qwilr Quote],MATCH(E16&"",tbl_Consulting[Job Number],0))="","",INDEX(tbl_Consulting[Qwilr Quote],MATCH(E16&"",tbl_Consulting[Job Number],0))),"")))) | AD16: =IF(AC16="","",IF(AND(LEFT(AC16,4)<>"http",IF(H16="Production",set_RMSBase,set_QwilrBase)=""),"",HYPERLINK(IF(LEFT(AC16,4)="http",AC16,IF(H16="Production",set_RMSBase,set_QwilrBase)&AC16),"Open"))) | AE16: =IF(E16="","",IFERROR(INDEX(tbl_Production[Total Expense],MATCH(E16&"",tbl_Production[Job Number],0)),IFERROR(INDEX(tbl_Consulting[Total Expense],MATCH(E16&"",tbl_Consulting[Job Number],0)),0))) | AF16: =IF(E16="","",Z16-N(AE16)) | AG16: =IFERROR(AF16/Z16,"") | AH16: =IF(E16="","",IFERROR(IF(INDEX(tbl_Onsite[Notes],MATCH(E16&"",tbl_Onsite[Job Number],0))="","",INDEX(tbl_Onsite[Notes],MATCH(E16&"",tbl_Onsite[Job Number],0))),IFERROR(IF(INDEX(tbl_Production[Notes],MATCH(E16&"",tbl_Production[Job Number],0))="","",INDEX(tbl_Production[Notes],MATCH(E16&"",tbl_Production[Job Number],0))),IFERROR(IF(INDEX(tbl_Consulting[Notes],MATCH(E16&"",tbl_Consulting[Job Number],0))="","",INDEX(tbl_Consulting[Notes],MATCH(E16&"",tbl_Consulting[Job Number],0))),""))))
... B404: =IF(A404="","",EOMONTH(A404,0)) | F404: =IF(E404="","",IF(COUNTIF(lst_Jobs,E404&"")>0,"OK","CHECK")) | M404: =IF(L404="","",IF(K404="GST 10%",ROUND(L404*set_GSTRate,2),0)) | N404: =IF(L404="","",L404+M404) | V404: =IF(COUNTA(A404,D404,C404,L404)=0,"",IF(A404="","No date - sits outside every month",IF(E404="","No job number",IF(F404="CHECK","Job number is not in the Xero job list",IF(I404="","No cost centre",IF(AND(P404="Y",C404=""),"Marked posted to Xero but has no invoice number",IF(AND(L404<>"",K404=""),"No tax code",IF(AND(L404<>"",O404=""),"No revenue GL code","")))))))) | W404: =IF(E404="","",IF(COUNTIF(tbl_Onsite[Job Number],E404&"")>0,"Onsite",IF(COUNTIF(tbl_Production[Job Number],E404&"")>0,"Production",IF(COUNTIF(tbl_Consulting[Job Number],E404&"")>0,"Consulting","not set up yet")))) | X404: =IF(E404="","",IFERROR(INDEX(lst_JobName,MATCH(E404&"",lst_Jobs,0)),"")) | Y404: =IF(E404="","",COUNTIFS(tbl_Finance[Job Number],E404&"",tbl_Finance[Ex GST],"<>")) | Z404: =IF(E404="","",SUMIFS(tbl_Finance[Ex GST],tbl_Finance[Job Number],E404&"")) | AA404: =IF(E404="","",SUMIFS(tbl_Finance[Ex GST],tbl_Finance[Job Number],E404&"",tbl_Finance[Xero Invoice No],"<>")) | AB404: =IF(E404="","",Z404-AA404) | AC404: =IF(E404="","",IFERROR(IF(INDEX(tbl_Onsite[Qwilr Quote],MATCH(E404&"",tbl_Onsite[Job Number],0))="","",INDEX(tbl_Onsite[Qwilr Quote],MATCH(E404&"",tbl_Onsite[Job Number],0))),IFERROR(IF(IF(INDEX(tbl_Production[Current RMS No],MATCH(E404&"",tbl_Production[Job Number],0))="",INDEX(tbl_Production[Qwilr Quote],MATCH(E404&"",tbl_Production[Job Number],0)),INDEX(tbl_Production[Current RMS No],MATCH(E404&"",tbl_Production[Job Number],0)))="","",IF(INDEX(tbl_Production[Current RMS No],MATCH(E404&"",tbl_Production[Job Number],0))="",INDEX(tbl_Production[Qwilr Quote],MATCH(E404&"",tbl_Production[Job Number],0)),INDEX(tbl_Production[Current RMS No],MATCH(E404&"",tbl_Production[Job Number],0)))),IFERROR(IF(INDEX(tbl_Consulting[Qwilr Quote],MATCH(E404&"",tbl_Consulting[Job Number],0))="","",INDEX(tbl_Consulting[Qwilr Quote],MATCH(E404&"",tbl_Consulting[Job Number],0))),"")))) | AD404: =IF(AC404="","",IF(AND(LEFT(AC404,4)<>"http",IF(H404="Production",set_RMSBase,set_QwilrBase)=""),"",HYPERLINK(IF(LEFT(AC404,4)="http",AC404,IF(H404="Production",set_RMSBase,set_QwilrBase)&AC404),"Open"))) | AE404: =IF(E404="","",IFERROR(INDEX(tbl_Production[Total Expense],MATCH(E404&"",tbl_Production[Job Number],0)),IFERROR(INDEX(tbl_Consulting[Total Expense],MATCH(E404&"",tbl_Consulting[Job Number],0)),0))) | AF404: =IF(E404="","",Z404-N(AE404)) | AG404: =IFERROR(AF404/Z404,"") | AH404: =IF(E404="","",IFERROR(IF(INDEX(tbl_Onsite[Notes],MATCH(E404&"",tbl_Onsite[Job Number],0))="","",INDEX(tbl_Onsite[Notes],MATCH(E404&"",tbl_Onsite[Job Number],0))),IFERROR(IF(INDEX(tbl_Production[Notes],MATCH(E404&"",tbl_Production[Job Number],0))="","",INDEX(tbl_Production[Notes],MATCH(E404&"",tbl_Production[Job Number],0))),IFERROR(IF(INDEX(tbl_Consulting[Notes],MATCH(E404&"",tbl_Consulting[Job Number],0))="","",INDEX(tbl_Consulting[Notes],MATCH(E404&"",tbl_Consulting[Job Number],0))),""))))

Sheet Month-End
A1: Month-End Revenue Close
A2: Pick the month, type the Xero figures into the yellow cells, and work down. Everything white or grey calculates itself.
A4: Month being closed | C4: 46265 | D4: <- month end date
A6: 1. REVENUE BY COST CENTRE - tracker vs Xero
A7: Cost Centre | B7: Invoiced Ex GST | C7: GST | D7: Inc GST | E7: WIP Movement | F7: Revenue Recognised | G7: Xero Revenue (type in) | H7: Variance | I7: Check
A8: ONSITE | B8: =SUMIFS(tbl_Finance[Ex GST],tbl_Finance[Month],$C$4,tbl_Finance[Cost Centre],$A8) | C8: =SUMIFS(tbl_Finance[GST],tbl_Finance[Month],$C$4,tbl_Finance[Cost Centre],$A8) | D8: =B8+C8 | E8: =SUMIFS(tbl_WIP[Amount],tbl_WIP[Month],$C$4,tbl_WIP[Cost Centre],$A8,tbl_WIP[Revenue or Cost],"<>Cost",tbl_WIP[Defer Start],"")+SUMIFS('Deferred Revenue'!$Q$6:$Q$607,'Deferred Revenue'!$F$6:$F$607,$A8,'Deferred Revenue'!$T$6:$T$607,"<>Cost") | F8: =B8+E8 | H8: =IF($G8="","",$F8-$G8) | I8: =IF($G8="","Enter Xero figure",IF(ROUND($H8,2)=0,"Reconciled","CHECK - "&TEXT($H8,"$#,##0.00")))
A9: PRODUCTION | B9: =SUMIFS(tbl_Finance[Ex GST],tbl_Finance[Month],$C$4,tbl_Finance[Cost Centre],$A9) | C9: =SUMIFS(tbl_Finance[GST],tbl_Finance[Month],$C$4,tbl_Finance[Cost Centre],$A9) | D9: =B9+C9 | E9: =SUMIFS(tbl_WIP[Amount],tbl_WIP[Month],$C$4,tbl_WIP[Cost Centre],$A9,tbl_WIP[Revenue or Cost],"<>Cost",tbl_WIP[Defer Start],"")+SUMIFS('Deferred Revenue'!$Q$6:$Q$607,'Deferred Revenue'!$F$6:$F$607,$A9,'Deferred Revenue'!$T$6:$T$607,"<>Cost") | F9: =B9+E9 | H9: =IF($G9="","",$F9-$G9) | I9: =IF($G9="","Enter Xero figure",IF(ROUND($H9,2)=0,"Reconciled","CHECK - "&TEXT($H9,"$#,##0.00")))
A10: VIDEO | B10: =SUMIFS(tbl_Finance[Ex GST],tbl_Finance[Month],$C$4,tbl_Finance[Cost Centre],$A10) | C10: =SUMIFS(tbl_Finance[GST],tbl_Finance[Month],$C$4,tbl_Finance[Cost Centre],$A10) | D10: =B10+C10 | E10: =SUMIFS(tbl_WIP[Amount],tbl_WIP[Month],$C$4,tbl_WIP[Cost Centre],$A10,tbl_WIP[Revenue or Cost],"<>Cost",tbl_WIP[Defer Start],"")+SUMIFS('Deferred Revenue'!$Q$6:$Q$607,'Deferred Revenue'!$F$6:$F$607,$A10,'Deferred Revenue'!$T$6:$T$607,"<>Cost") | F10: =B10+E10 | H10: =IF($G10="","",$F10-$G10) | I10: =IF($G10="","Enter Xero figure",IF(ROUND($H10,2)=0,"Reconciled","CHECK - "&TEXT($H10,"$#,##0.00")))
A11: INTEGRATION | B11: =SUMIFS(tbl_Finance[Ex GST],tbl_Finance[Month],$C$4,tbl_Finance[Cost Centre],$A11) | C11: =SUMIFS(tbl_Finance[GST],tbl_Finance[Month],$C$4,tbl_Finance[Cost Centre],$A11) | D11: =B11+C11 | E11: =SUMIFS(tbl_WIP[Amount],tbl_WIP[Month],$C$4,tbl_WIP[Cost Centre],$A11,tbl_WIP[Revenue or Cost],"<>Cost",tbl_WIP[Defer Start],"")+SUMIFS('Deferred Revenue'!$Q$6:$Q$607,'Deferred Revenue'!$F$6:$F$607,$A11,'Deferred Revenue'!$T$6:$T$607,"<>Cost") | F11: =B11+E11 | H11: =IF($G11="","",$F11-$G11) | I11: =IF($G11="","Enter Xero figure",IF(ROUND($H11,2)=0,"Reconciled","CHECK - "&TEXT($H11,"$#,##0.00")))
A12: CONSULTING | B12: =SUMIFS(tbl_Finance[Ex GST],tbl_Finance[Month],$C$4,tbl_Finance[Cost Centre],$A12) | C12: =SUMIFS(tbl_Finance[GST],tbl_Finance[Month],$C$4,tbl_Finance[Cost Centre],$A12) | D12: =B12+C12 | E12: =SUMIFS(tbl_WIP[Amount],tbl_WIP[Month],$C$4,tbl_WIP[Cost Centre],$A12,tbl_WIP[Revenue or Cost],"<>Cost",tbl_WIP[Defer Start],"")+SUMIFS('Deferred Revenue'!$Q$6:$Q$607,'Deferred Revenue'!$F$6:$F$607,$A12,'Deferred Revenue'!$T$6:$T$607,"<>Cost") | F12: =B12+E12 | H12: =IF($G12="","",$F12-$G12) | I12: =IF($G12="","Enter Xero figure",IF(ROUND($H12,2)=0,"Reconciled","CHECK - "&TEXT($H12,"$#,##0.00")))
A13: CTS | B13: =SUMIFS(tbl_Finance[Ex GST],tbl_Finance[Month],$C$4,tbl_Finance[Cost Centre],$A13) | C13: =SUMIFS(tbl_Finance[GST],tbl_Finance[Month],$C$4,tbl_Finance[Cost Centre],$A13) | D13: =B13+C13 | E13: =SUMIFS(tbl_WIP[Amount],tbl_WIP[Month],$C$4,tbl_WIP[Cost Centre],$A13,tbl_WIP[Revenue or Cost],"<>Cost",tbl_WIP[Defer Start],"")+SUMIFS('Deferred Revenue'!$Q$6:$Q$607,'Deferred Revenue'!$F$6:$F$607,$A13,'Deferred Revenue'!$T$6:$T$607,"<>Cost") | F13: =B13+E13 | H13: =IF($G13="","",$F13-$G13) | I13: =IF($G13="","Enter Xero figure",IF(ROUND($H13,2)=0,"Reconciled","CHECK - "&TEXT($H13,"$#,##0.00")))
A14: TOTAL | B14: =SUM(B8:B13) | C14: =SUM(C8:C13) | D14: =SUM(D8:D13) | E14: =SUM(E8:E13) | F14: =SUM(F8:F13) | G14: =SUM(G8:G13) | H14: =SUM(H8:H13) | I14: =IF(COUNT($G8:$G13)=0,"Enter Xero figures",IF(ROUND($H14,2)=0,"Reconciled","CHECK - "&TEXT($H14,"$#,##0.00")))
A15: Every line on the Finance sheet carries one cost centre, so these add to the month's invoicing exactly.
A17: 2. WORK IN PROGRESS - GL 11300
B18: Total | C18: Deferred / accrued revenue | D18: Deferred / accrued cost | I18: Check
A19: Opening WIP balance (all months before this one) | B19: =C19+D19 | C19: =SUMIFS(tbl_WIP[Amount],tbl_WIP[Month],"<>",tbl_WIP[Month],"<"&$C$4,tbl_WIP[Revenue or Cost],"<>Cost",tbl_WIP[Defer Start],"")+SUMIFS('Deferred Revenue'!$P$6:$P$607,'Deferred Revenue'!$T$6:$T$607,"<>Cost") | D19: =SUMIFS(tbl_WIP[Amount],tbl_WIP[Month],"<>",tbl_WIP[Month],"<"&$C$4,tbl_WIP[Revenue or Cost],"Cost",tbl_WIP[Defer Start],"")+SUMIFS('Deferred Revenue'!$P$6:$P$607,'Deferred Revenue'!$T$6:$T$607,"Cost")
A20: Movement this month | B20: =C20+D20 | C20: =SUMIFS(tbl_WIP[Amount],tbl_WIP[Month],$C$4,tbl_WIP[Revenue or Cost],"<>Cost",tbl_WIP[Defer Start],"")+SUMIFS('Deferred Revenue'!$Q$6:$Q$607,'Deferred Revenue'!$T$6:$T$607,"<>Cost") | D20: =SUMIFS(tbl_WIP[Amount],tbl_WIP[Month],$C$4,tbl_WIP[Revenue or Cost],"Cost",tbl_WIP[Defer Start],"")+SUMIFS('Deferred Revenue'!$Q$6:$Q$607,'Deferred Revenue'!$T$6:$T$607,"Cost")
A21: Closing WIP balance per this tracker | B21: =B19+B20 | C21: =C19+C20 | D21: =D19+D20
A22: Closing balance per the WIP Schedule file
A23: Variance - tracker vs WIP Schedule | B23: =IF(B22="","",B21-B22) | I23: =IF(B22="","Enter WIP Schedule figure",IF(ROUND(B23,2)=0,"Reconciled","CHECK"))
A24: Closing balance per Xero GL 11300
A25: Variance - tracker vs Xero | B25: =IF(B24="","",B21-B24) | I25: =IF(B24="","Enter Xero 11300 balance",IF(ROUND(B25,2)=0,"Reconciled","CHECK"))
A26: GL 11300 nets deferred revenue against deferred cost, so Xero shows one figure and cannot split it. The Revenue or Cost column on WIP Movements splits it here. Only the Total column should be compared to Xero.
A28: 3. DATA CHECKS - every count should be zero before you close
A29: Check | B29: Count | I29: Status
A30: Invoice lines with an amount but no date | B30: =SUMPRODUCT(--(tbl_Finance[Date]=""),--(tbl_Finance[Ex GST]<>"")) | I30: =IF(B30=0,"Clear","REVIEW")
A31: Invoice lines with an amount but no job number | B31: =COUNTIFS(tbl_Finance[Ex GST],"<>",tbl_Finance[Job Number],"") | I31: =IF(B31=0,"Clear","REVIEW")
A32: Job numbers not found in the Xero job list | B32: =COUNTIF(tbl_Finance[Job in Xero?],"CHECK") | I32: =IF(B32=0,"Clear","REVIEW")
A33: Marked posted to Xero but no invoice number | B33: =COUNTIFS(tbl_Finance[Posted to Xero],"Y",tbl_Finance[Xero Invoice No],"") | I33: =IF(B33=0,"Clear","REVIEW")
A34: Invoice lines with an amount but no cost centre | B34: =COUNTIFS(tbl_Finance[Ex GST],"<>",tbl_Finance[Cost Centre],"") | I34: =IF(B34=0,"Clear","REVIEW")
A35: Invoice lines with an amount but no tax code | B35: =COUNTIFS(tbl_Finance[Ex GST],"<>",tbl_Finance[Tax Code],"") | I35: =IF(B35=0,"Clear","REVIEW")
A36: Invoice lines with an amount but no revenue GL code | B36: =COUNTIFS(tbl_Finance[Ex GST],"<>",tbl_Finance[Revenue GL],"") | I36: =IF(B36=0,"Clear","REVIEW")
A37: Anything flagged in the Issue column | B37: =COUNTIF(tbl_Finance[Issue],"?*") | I37: =IF(B37=0,"Clear","REVIEW")
A38: Flagged "To WIP = Y" but no matching WIP movement | B38: =SUMPRODUCT(--(tbl_Finance[To WIP]="Y"),--(tbl_Finance[Xero Invoice No]<>""),--(COUNTIF(tbl_WIP[Xero Invoice No],tbl_Finance[Xero Invoice No]&"")=0)) | I38: =IF(B38=0,"Clear","REVIEW")
A39: WIP movements with an amount but no month or no job | B39: =COUNTIFS(tbl_WIP[Month],"",tbl_WIP[Amount],"<>")+COUNTIFS(tbl_WIP[Job Number],"",tbl_WIP[Amount],"<>") | I39: =IF(B39=0,"Clear","REVIEW")
A40: WIP job numbers not found in the Xero job list | B40: =COUNTIF(tbl_WIP[Job in Xero?],"CHECK") | I40: =IF(B40=0,"Clear","REVIEW")
A41: Consulting revenue split does not equal the job revenue | B41: =COUNTIF(tbl_Consulting[Revenue Split Check],"MISMATCH") | I41: =IF(B41=0,"Clear","REVIEW")
A42: Invoiced jobs not set up on any department sheet | B42: =COUNTIF(tbl_Finance[On Dept Sheet],"not set up yet") | I42: =IF(B42=0,"Clear","REVIEW")
A43: Job numbers sitting on more than one department sheet | B43: =SUMPRODUCT(--(tbl_Onsite[Job Number]<>""),--(COUNTIF(tbl_Production[Job Number],tbl_Onsite[Job Number]&"")>0))+SUMPRODUCT(--(tbl_Onsite[Job Number]<>""),--(COUNTIF(tbl_Consulting[Job Number],tbl_Onsite[Job Number]&"")>0))+SUMPRODUCT(--(tbl_Production[Job Number]<>""),--(COUNTIF(tbl_Consulting[Job Number],tbl_Production[Job Number]&"")>0)) | I43: =IF(B43=0,"Clear","REVIEW")
A44: Jobs on a department sheet with no invoice yet | B44: =COUNTIFS(tbl_Onsite[Job Number],"<>",tbl_Onsite[Lines on Job],0)+COUNTIFS(tbl_Production[Job Number],"<>",tbl_Production[Lines on Job],0)+COUNTIFS(tbl_Consulting[Job Number],"<>",tbl_Consulting[Lines on Job],0) | I44: =IF(B44=0,"Clear","REVIEW")
A45: Deferred lines that also have a manual WIP journal (would double count) | B45: =SUMPRODUCT(--(tbl_Finance[Defer Start]<>""),--(tbl_Finance[Xero Invoice No]<>""),--(COUNTIF(tbl_WIP[Xero Invoice No],tbl_Finance[Xero Invoice No]&"")>0)) | I45: =IF(B45=0,"Clear","REVIEW")
A46: Deferred lines missing an end date | B46: =SUMPRODUCT(--(tbl_Finance[Defer Start]<>""),--(tbl_Finance[Defer End]=""))+SUMPRODUCT(--(tbl_WIP[Defer Start]<>""),--(tbl_WIP[Defer End]="")) | I46: =IF(B46=0,"Clear","REVIEW")
A47: WIP rows with an amount but Revenue or Cost not set | B47: =SUMPRODUCT(--(tbl_WIP[Amount]<>""),--(tbl_WIP[Revenue or Cost]="")) | I47: =IF(B47=0,"Clear","REVIEW")
A48: Deferred cost rows with no P&L Account to credit | B48: =COUNTIFS(tbl_WIP[Revenue or Cost],"Cost",tbl_WIP[P&L Account],"",tbl_WIP[Amount],"<>") | I48: =IF(B48=0,"Clear","REVIEW")
A49: Still sitting at "To Invoice" for the selected month | B49: =COUNTIFS(tbl_Finance[Month],$C$4,tbl_Finance[Status],"To Invoice") | I49: =IF(B49=0,"Clear","REVIEW")
A50: Revenue dated this month with no invoice number - it is in the forecast | B50: =COUNTIFS(tbl_Finance[Month],$C$4,tbl_Finance[Xero Invoice No],"",tbl_Finance[Ex GST],"<>") | I50: =IF(B50=0,"Clear","REVIEW")
A51: Value of invoice lines with no date (excluded from every month) | B51: =SUMPRODUCT(--(tbl_Finance[Date]=""),IFERROR(tbl_Finance[Ex GST]*1,0)) | I51: =IF(ROUND(B51,2)=0,"Clear","REVIEW")
A53: 4. WIP JOURNAL FOR THE MONTH - post this one journal in Xero
A54: Account | B54: Cost Centre | C54: Debit | D54: Credit
A55: =set_WIPAsset | B55: ="(no tracking)" | C55: =IF(ROUND((SUMIFS(tbl_WIP[Amount],tbl_WIP[Month],$C$4,tbl_WIP[Defer Start],"",tbl_WIP[Revenue or Cost],"<>Cost")+SUMIFS('Deferred Revenue'!$Q$6:$Q$607,'Deferred Revenue'!$T$6:$T$607,"<>Cost")),2)>0,(SUMIFS(tbl_WIP[Amount],tbl_WIP[Month],$C$4,tbl_WIP[Defer Start],"",tbl_WIP[Revenue or Cost],"<>Cost")+SUMIFS('Deferred Revenue'!$Q$6:$Q$607,'Deferred Revenue'!$T$6:$T$607,"<>Cost")),"") | D55: =IF(ROUND((SUMIFS(tbl_WIP[Amount],tbl_WIP[Month],$C$4,tbl_WIP[Defer Start],"",tbl_WIP[Revenue or Cost],"<>Cost")+SUMIFS('Deferred Revenue'!$Q$6:$Q$607,'Deferred Revenue'!$T$6:$T$607,"<>Cost")),2)<0,-(SUMIFS(tbl_WIP[Amount],tbl_WIP[Month],$C$4,tbl_WIP[Defer Start],"",tbl_WIP[Revenue or Cost],"<>Cost")+SUMIFS('Deferred Revenue'!$Q$6:$Q$607,'Deferred Revenue'!$T$6:$T$607,"<>Cost")),"")
A56: =set_WIPIncome | B56: =$A$8 | C56: =IF(ROUND($E$8,2)<0,-$E$8,"") | D56: =IF(ROUND($E$8,2)>0,$E$8,"")
A57: =set_WIPIncome | B57: =$A$9 | C57: =IF(ROUND($E$9,2)<0,-$E$9,"") | D57: =IF(ROUND($E$9,2)>0,$E$9,"")
A58: =set_WIPIncome | B58: =$A$10 | C58: =IF(ROUND($E$10,2)<0,-$E$10,"") | D58: =IF(ROUND($E$10,2)>0,$E$10,"")
A59: =set_WIPIncome | B59: =$A$11 | C59: =IF(ROUND($E$11,2)<0,-$E$11,"") | D59: =IF(ROUND($E$11,2)>0,$E$11,"")
A60: =set_WIPIncome | B60: =$A$12 | C60: =IF(ROUND($E$12,2)<0,-$E$12,"") | D60: =IF(ROUND($E$12,2)>0,$E$12,"")
A61: =set_WIPIncome | B61: =$A$13 | C61: =IF(ROUND($E$13,2)<0,-$E$13,"") | D61: =IF(ROUND($E$13,2)>0,$E$13,"")
A62: =set_WIPIncome | B62: ="(cost centre not set - fix it)" | C62: =IF(ROUND(((SUMIFS(tbl_WIP[Amount],tbl_WIP[Month],$C$4,tbl_WIP[Defer Start],"",tbl_WIP[Revenue or Cost],"<>Cost")+SUMIFS('Deferred Revenue'!$Q$6:$Q$607,'Deferred Revenue'!$T$6:$T$607,"<>Cost"))-$E$14),2)<0,-((SUMIFS(tbl_WIP[Amount],tbl_WIP[Month],$C$4,tbl_WIP[Defer Start],"",tbl_WIP[Revenue or Cost],"<>Cost")+SUMIFS('Deferred Revenue'!$Q$6:$Q$607,'Deferred Revenue'!$T$6:$T$607,"<>Cost"))-$E$14),"") | D62: =IF(ROUND(((SUMIFS(tbl_WIP[Amount],tbl_WIP[Month],$C$4,tbl_WIP[Defer Start],"",tbl_WIP[Revenue or Cost],"<>Cost")+SUMIFS('Deferred Revenue'!$Q$6:$Q$607,'Deferred Revenue'!$T$6:$T$607,"<>Cost"))-$E$14),2)>0,((SUMIFS(tbl_WIP[Amount],tbl_WIP[Month],$C$4,tbl_WIP[Defer Start],"",tbl_WIP[Revenue or Cost],"<>Cost")+SUMIFS('Deferred Revenue'!$Q$6:$Q$607,'Deferred Revenue'!$T$6:$T$607,"<>Cost"))-$E$14),"")
A63: TOTAL | C63: =SUM(C55:C62) | D63: =SUM(D55:D62) | E63: =IF(ROUND($C$63,2)=ROUND($D$63,2),"Balanced","CHECK - does not balance")
A64: Narration to use | C64: ="WIP movement "&TEXT($C$4,"mmmm yyyy")
A65: Made up of - manual revenue rows on WIP Movements | C65: =SUMIFS(tbl_WIP[Amount],tbl_WIP[Month],$C$4,tbl_WIP[Defer Start],"",tbl_WIP[Revenue or Cost],"<>Cost")
A66: Made up of - revenue that spreads (Deferred Revenue sheet) | C66: =SUMIFS('Deferred Revenue'!$Q$6:$Q$607,'Deferred Revenue'!$T$6:$T$607,"<>Cost")
A67: Total revenue movement - section 2, revenue column | C67: =(SUMIFS(tbl_WIP[Amount],tbl_WIP[Month],$C$4,tbl_WIP[Defer Start],"",tbl_WIP[Revenue or Cost],"<>Cost")+SUMIFS('Deferred Revenue'!$Q$6:$Q$607,'Deferred Revenue'!$T$6:$T$607,"<>Cost"))
A68: Deferred / accrued cost movement - post these line by line | C68: =(SUMIFS(tbl_WIP[Amount],tbl_WIP[Month],$C$4,tbl_WIP[Defer Start],"",tbl_WIP[Revenue or Cost],"Cost")+SUMIFS('Deferred Revenue'!$Q$6:$Q$607,'Deferred Revenue'!$T$6:$T$607,"Cost"))
A69: Nothing here posts itself. The tracker works the movement out; you key this journal into Xero and put the reference back on the WIP Movements rows. The cost line above is not in this journal: every deferred cost credits the expense account its bill came from, so post those from WIP Movements with Revenue or Cost filtered to Cost.
A71: 5. WORK WON - ZOHO / Current RMS / Qwilr vs what was invoiced
A72: Source | B72: Opportunities | C72: Value Ex GST | I72: Check
A73: ZOHO | B73: =COUNTIFS(tbl_Won[Month],$C$4,tbl_Won[Source],$A73,tbl_Won[Status],"Won") | C73: =SUMIFS(tbl_Won[Value Ex GST],tbl_Won[Month],$C$4,tbl_Won[Source],$A73,tbl_Won[Status],"Won")
A74: Current RMS | B74: =COUNTIFS(tbl_Won[Month],$C$4,tbl_Won[Source],$A74,tbl_Won[Status],"Won") | C74: =SUMIFS(tbl_Won[Value Ex GST],tbl_Won[Month],$C$4,tbl_Won[Source],$A74,tbl_Won[Status],"Won")
A75: Qwilr | B75: =COUNTIFS(tbl_Won[Month],$C$4,tbl_Won[Source],$A75,tbl_Won[Status],"Won") | C75: =SUMIFS(tbl_Won[Value Ex GST],tbl_Won[Month],$C$4,tbl_Won[Source],$A75,tbl_Won[Status],"Won")
A76: Other | B76: =COUNTIFS(tbl_Won[Month],$C$4,tbl_Won[Source],$A76,tbl_Won[Status],"Won") | C76: =SUMIFS(tbl_Won[Value Ex GST],tbl_Won[Month],$C$4,tbl_Won[Source],$A76,tbl_Won[Status],"Won")
A77: TOTAL WON THIS MONTH | B77: =SUM(B73:B76) | C77: =SUM(C73:C76)
A78: Invoiced this month (Finance, Ex GST) | C78: =$B$14
A79: Won less invoiced | C79: =$C$77-$C$78
A80: Won this month, still not invoiced against the job | C80: =SUMIFS(tbl_Won[Still to Invoice],tbl_Won[Month],$C$4,tbl_Won[Status],"Won")
A81: Won with a job number Xero does not have | C81: =COUNTIFS(tbl_Won[Month],$C$4,tbl_Won[Status],"Won",tbl_Won[Job in Xero?],"CHECK")
A82: A sense check, not a source. Revenue only ever comes off the Finance sheet. A big gap either way is worth a look: work won and never invoiced, or invoiced with no opportunity behind it.
A84: 6. FORECAST - work with no invoice against it
A85: Cost Centre | B85: Finance: to invoice | C85: Won, not invoiced | D85: Total forecast
A86: ONSITE | B86: =SUMIFS(tbl_Finance[Ex GST],tbl_Finance[Cost Centre],$A86,tbl_Finance[Xero Invoice No],"") | C86: =SUMIFS(tbl_Won[Still to Invoice],tbl_Won[Cost Centre],$A86,tbl_Won[Status],"Won") | D86: =B86+C86
A87: PRODUCTION | B87: =SUMIFS(tbl_Finance[Ex GST],tbl_Finance[Cost Centre],$A87,tbl_Finance[Xero Invoice No],"") | C87: =SUMIFS(tbl_Won[Still to Invoice],tbl_Won[Cost Centre],$A87,tbl_Won[Status],"Won") | D87: =B87+C87
A88: VIDEO | B88: =SUMIFS(tbl_Finance[Ex GST],tbl_Finance[Cost Centre],$A88,tbl_Finance[Xero Invoice No],"") | C88: =SUMIFS(tbl_Won[Still to Invoice],tbl_Won[Cost Centre],$A88,tbl_Won[Status],"Won") | D88: =B88+C88
A89: INTEGRATION | B89: =SUMIFS(tbl_Finance[Ex GST],tbl_Finance[Cost Centre],$A89,tbl_Finance[Xero Invoice No],"") | C89: =SUMIFS(tbl_Won[Still to Invoice],tbl_Won[Cost Centre],$A89,tbl_Won[Status],"Won") | D89: =B89+C89
A90: CONSULTING | B90: =SUMIFS(tbl_Finance[Ex GST],tbl_Finance[Cost Centre],$A90,tbl_Finance[Xero Invoice No],"") | C90: =SUMIFS(tbl_Won[Still to Invoice],tbl_Won[Cost Centre],$A90,tbl_Won[Status],"Won") | D90: =B90+C90
A91: CTS | B91: =SUMIFS(tbl_Finance[Ex GST],tbl_Finance[Cost Centre],$A91,tbl_Finance[Xero Invoice No],"") | C91: =SUMIFS(tbl_Won[Still to Invoice],tbl_Won[Cost Centre],$A91,tbl_Won[Status],"Won") | D91: =B91+C91
A92: TOTAL FORECAST | B92: =SUM(B86:B91) | C92: =SUM(C86:C91) | D92: =SUM(D86:D91)
A93: Not in the forecast above - open opportunities, not yet won | D93: =SUMIFS(tbl_Won[Value Ex GST],tbl_Won[Status],"Open")
A94: Not in the forecast above - deferred revenue still to release (already invoiced) | D94: =-SUMIFS('Deferred Revenue'!$R$6:$R$607,'Deferred Revenue'!$T$6:$T$607,"<>Cost")
A95: Jobs on a department sheet with no invoice line at all (count) | D95: =COUNTIFS(tbl_Onsite[Job Number],"<>",tbl_Onsite[Lines on Job],0)+COUNTIFS(tbl_Production[Job Number],"<>",tbl_Production[Lines on Job],0)+COUNTIFS(tbl_Consulting[Job Number],"<>",tbl_Consulting[Lines on Job],0)
A96: Nothing here is revenue yet. Finance: to invoice is a line already on the Finance sheet with no invoice number on it. Won, not invoiced is the value won less everything Finance already holds against that job, so the two columns add up without counting the same work twice.
A98: 7. SIGN-OFF
A99: Prepared by | E99: Accounts Assistant
A100: Reviewed by | E100: Finance Operations Manager
A101: Date closed
A102: Notes / carried forward items

Sheet WIP Summary
A1: WIP Balance by Job
A2: Job-level WIP for the month selected on the Month-End sheet. Paste the matching balance from the WIP Schedule file into column G and the variance column finds the breaks. Filter column F to hide the nil rows.
A4: Month | C4: ='Month-End'!C4 | D4: <- set this on the Month-End sheet
A6: Opening total | B6: =SUMIFS(tbl_WIP[Amount],tbl_WIP[Month],"<>",tbl_WIP[Month],"<"&$C$4,tbl_WIP[Defer Start],"")+SUM('Deferred Revenue'!$P$6:$P$607)
A7: Movement this month | B7: =SUMIFS(tbl_WIP[Amount],tbl_WIP[Month],$C$4,tbl_WIP[Defer Start],"")+SUM('Deferred Revenue'!$Q$6:$Q$607)
A8: Closing total | B8: =B6+B7
A9: Of which is on a job Xero does not have - fix these | B9: =SUMIFS(tbl_WIP[Amount],tbl_WIP[Job in Xero?],"CHECK",tbl_WIP[Month],"<="&$C$4,tbl_WIP[Defer Start],"")
A10: Closing listed below, job by job | B10: =B8-B9 | D10: =COUNTIF($F$12:$F$434,"yes")&" jobs carry a balance - filter column F to 'yes' to see only those"
A11: Job Number | B11: Job Name (Xero) | C11: Opening | D11: Movement | E11: Closing | F11: Any balance? | G11: Per WIP Schedule (paste in) | H11: Variance
A12: 1144 | B12: Bankwest PER Half Tech | C12: =SUMIFS(tbl_WIP[Amount],tbl_WIP[Job Number],$A12,tbl_WIP[Month],"<>",tbl_WIP[Month],"<"&$C$4,tbl_WIP[Defer Start],"")+SUMIF('Deferred Revenue'!$E$6:$E$607,$A12,'Deferred Revenue'!$P$6:$P$607) | D12: =SUMIFS(tbl_WIP[Amount],tbl_WIP[Job Number],$A12,tbl_WIP[Month],$C$4,tbl_WIP[Defer Start],"")+SUMIF('Deferred Revenue'!$E$6:$E$607,$A12,'Deferred Revenue'!$Q$6:$Q$607) | E12: =C12+D12 | F12: =IF(ROUND(C12,2)+ROUND(D12,2)=0,"","yes") | H12: =IF($G12="","",$E12-$G12)
A13: 1350 | B13: CBA Brisbane ONS | C13: =SUMIFS(tbl_WIP[Amount],tbl_WIP[Job Number],$A13,tbl_WIP[Month],"<>",tbl_WIP[Month],"<"&$C$4,tbl_WIP[Defer Start],"")+SUMIF('Deferred Revenue'!$E$6:$E$607,$A13,'Deferred Revenue'!$P$6:$P$607) | D13: =SUMIFS(tbl_WIP[Amount],tbl_WIP[Job Number],$A13,tbl_WIP[Month],$C$4,tbl_WIP[Defer Start],"")+SUMIF('Deferred Revenue'!$E$6:$E$607,$A13,'Deferred Revenue'!$Q$6:$Q$607) | E13: =C13+D13 | F13: =IF(ROUND(C13,2)+ROUND(D13,2)=0,"","yes") | H13: =IF($G13="","",$E13-$G13)
A14: 1400 | B14: DTTL Mel Tech FT 2 | C14: =SUMIFS(tbl_WIP[Amount],tbl_WIP[Job Number],$A14,tbl_WIP[Month],"<>",tbl_WIP[Month],"<"&$C$4,tbl_WIP[Defer Start],"")+SUMIF('Deferred Revenue'!$E$6:$E$607,$A14,'Deferred Revenue'!$P$6:$P$607) | D14: =SUMIFS(tbl_WIP[Amount],tbl_WIP[Job Number],$A14,tbl_WIP[Month],$C$4,tbl_WIP[Defer Start],"")+SUMIF('Deferred Revenue'!$E$6:$E$607,$A14,'Deferred Revenue'!$Q$6:$Q$607) | E14: =C14+D14 | F14: =IF(ROUND(C14,2)+ROUND(D14,2)=0,"","yes") | H14: =IF($G14="","",$E14-$G14)
A15: 1401 | B15: DTTL SYD FT Tech 2 | C15: =SUMIFS(tbl_WIP[Amount],tbl_WIP[Job Number],$A15,tbl_WIP[Month],"<>",tbl_WIP[Month],"<"&$C$4,tbl_WIP[Defer Start],"")+SUMIF('Deferred Revenue'!$E$6:$E$607,$A15,'Deferred Revenue'!$P$6:$P$607) | D15: =SUMIFS(tbl_WIP[Amount],tbl_WIP[Job Number],$A15,tbl_WIP[Month],$C$4,tbl_WIP[Defer Start],"")+SUMIF('Deferred Revenue'!$E$6:$E$607,$A15,'Deferred Revenue'!$Q$6:$Q$607) | E15: =C15+D15 | F15: =IF(ROUND(C15,2)+ROUND(D15,2)=0,"","yes") | H15: =IF($G15="","",$E15-$G15)
A16: 1530 | B16: DTTL BNE Onsite | C16: =SUMIFS(tbl_WIP[Amount],tbl_WIP[Job Number],$A16,tbl_WIP[Month],"<>",tbl_WIP[Month],"<"&$C$4,tbl_WIP[Defer Start],"")+SUMIF('Deferred Revenue'!$E$6:$E$607,$A16,'Deferred Revenue'!$P$6:$P$607) | D16: =SUMIFS(tbl_WIP[Amount],tbl_WIP[Job Number],$A16,tbl_WIP[Month],$C$4,tbl_WIP[Defer Start],"")+SUMIF('Deferred Revenue'!$E$6:$E$607,$A16,'Deferred Revenue'!$Q$6:$Q$607) | E16: =C16+D16 | F16: =IF(ROUND(C16,2)+ROUND(D16,2)=0,"","yes") | H16: =IF($G16="","",$E16-$G16)
A17: 1668 | B17: CBA Dedicated Tech | C17: =SUMIFS(tbl_WIP[Amount],tbl_WIP[Job Number],$A17,tbl_WIP[Month],"<>",tbl_WIP[Month],"<"&$C$4,tbl_WIP[Defer Start],"")+SUMIF('Deferred Revenue'!$E$6:$E$607,$A17,'Deferred Revenue'!$P$6:$P$607) | D17: =SUMIFS(tbl_WIP[Amount],tbl_WIP[Job Number],$A17,tbl_WIP[Month],$C$4,tbl_WIP[Defer Start],"")+SUMIF('Deferred Revenue'!$E$6:$E$607,$A17,'Deferred Revenue'!$Q$6:$Q$607) | E17: =C17+D17 | F17: =IF(ROUND(C17,2)+ROUND(D17,2)=0,"","yes") | H17: =IF($G17="","",$E17-$G17)
A18: 1750 | B18: Bankwest Spotify | C18: =SUMIFS(tbl_WIP[Amount],tbl_WIP[Job Number],$A18,tbl_WIP[Month],"<>",tbl_WIP[Month],"<"&$C$4,tbl_WIP[Defer Start],"")+SUMIF('Deferred Revenue'!$E$6:$E$607,$A18,'Deferred Revenue'!$P$6:$P$607) | D18: =SUMIFS(tbl_WIP[Amount],tbl_WIP[Job Number],$A18,tbl_WIP[Month],$C$4,tbl_WIP[Defer Start],"")+SUMIF('Deferred Revenue'!$E$6:$E$607,$A18,'Deferred Revenue'!$Q$6:$Q$607) | E18: =C18+D18 | F18: =IF(ROUND(C18,2)+ROUND(D18,2)=0,"","yes") | H18: =IF($G18="","",$E18-$G18)
A19: 1755 | B19: CBA Spotify | C19: =SUMIFS(tbl_WIP[Amount],tbl_WIP[Job Number],$A19,tbl_WIP[Month],"<>",tbl_WIP[Month],"<"&$C$4,tbl_WIP[Defer Start],"")+SUMIF('Deferred Revenue'!$E$6:$E$607,$A19,'Deferred Revenue'!$P$6:$P$607) | D19: =SUMIFS(tbl_WIP[Amount],tbl_WIP[Job Number],$A19,tbl_WIP[Month],$C$4,tbl_WIP[Defer Start],"")+SUMIF('Deferred Revenue'!$E$6:$E$607,$A19,'Deferred Revenue'!$Q$6:$Q$607) | E19: =C19+D19 | F19: =IF(ROUND(C19,2)+ROUND(D19,2)=0,"","yes") | H19: =IF($G19="","",$E19-$G19)
A20: 1771 | B20: Integration - Training | C20: =SUMIFS(tbl_WIP[Amount],tbl_WIP[Job Number],$A20,tbl_WIP[Month],"<>",tbl_WIP[Month],"<"&$C$4,tbl_WIP[Defer Start],"")+SUMIF('Deferred Revenue'!$E$6:$E$607,$A20,'Deferred Revenue'!$P$6:$P$607) | D20: =SUMIFS(tbl_WIP[Amount],tbl_WIP[Job Number],$A20,tbl_WIP[Month],$C$4,tbl_WIP[Defer Start],"")+SUMIF('Deferred Revenue'!$E$6:$E$607,$A20,'Deferred Revenue'!$Q$6:$Q$607) | E20: =C20+D20 | F20: =IF(ROUND(C20,2)+ROUND(D20,2)=0,"","yes") | H20: =IF($G20="","",$E20-$G20)
A21: 1862 | B21: DTTL ADL Onsite | C21: =SUMIFS(tbl_WIP[Amount],tbl_WIP[Job Number],$A21,tbl_WIP[Month],"<>",tbl_WIP[Month],"<"&$C$4,tbl_WIP[Defer Start],"")+SUMIF('Deferred Revenue'!$E$6:$E$607,$A21,'Deferred Revenue'!$P$6:$P$607) | D21: =SUMIFS(tbl_WIP[Amount],tbl_WIP[Job Number],$A21,tbl_WIP[Month],$C$4,tbl_WIP[Defer Start],"")+SUMIF('Deferred Revenue'!$E$6:$E$607,$A21,'Deferred Revenue'!$Q$6:$Q$607) | E21: =C21+D21 | F21: =IF(ROUND(C21,2)+ROUND(D21,2)=0,"","yes") | H21: =IF($G21="","",$E21-$G21)
A22: 20250731 | B22: PWC National Pool of Hours | C22: =SUMIFS(tbl_WIP[Amount],tbl_WIP[Job Number],$A22,tbl_WIP[Month],"<>",tbl_WIP[Month],"<"&$C$4,tbl_WIP[Defer Start],"")+SUMIF('Deferred Revenue'!$E$6:$E$607,$A22,'Deferred Revenue'!$P$6:$P$607) | D22: =SUMIFS(tbl_WIP[Amount],tbl_WIP[Job Number],$A22,tbl_WIP[Month],$C$4,tbl_WIP[Defer Start],"")+SUMIF('Deferred Revenue'!$E$6:$E$607,$A22,'Deferred Revenue'!$Q$6:$Q$607) | E22: =C22+D22 | F22: =IF(ROUND(C22,2)+ROUND(D22,2)=0,"","yes") | H22: =IF($G22="","",$E22-$G22)
A23: 2026021101 | B23: AusPayNet Quarterly AV Support & Maintenance 2026 | C23: =SUMIFS(tbl_WIP[Amount],tbl_WIP[Job Number],$A23,tbl_WIP[Month],"<>",tbl_WIP[Month],"<"&$C$4,tbl_WIP[Defer Start],"")+SUMIF('Deferred Revenue'!$E$6:$E$607,$A23,'Deferred Revenue'!$P$6:$P$607) | D23: =SUMIFS(tbl_WIP[Amount],tbl_WIP[Job Number],$A23,tbl_WIP[Month],$C$4,tbl_WIP[Defer Start],"")+SUMIF('Deferred Revenue'!$E$6:$E$607,$A23,'Deferred Revenue'!$Q$6:$Q$607) | E23: =C23+D23 | F23: =IF(ROUND(C23,2)+ROUND(D23,2)=0,"","yes") | H23: =IF($G23="","",$E23-$G23)
... A434: 974 | B434: DTTL 1300 Number | C434: =SUMIFS(tbl_WIP[Amount],tbl_WIP[Job Number],$A434,tbl_WIP[Month],"<>",tbl_WIP[Month],"<"&$C$4,tbl_WIP[Defer Start],"")+SUMIF('Deferred Revenue'!$E$6:$E$607,$A434,'Deferred Revenue'!$P$6:$P$607) | D434: =SUMIFS(tbl_WIP[Amount],tbl_WIP[Job Number],$A434,tbl_WIP[Month],$C$4,tbl_WIP[Defer Start],"")+SUMIF('Deferred Revenue'!$E$6:$E$607,$A434,'Deferred Revenue'!$Q$6:$Q$607) | E434: =C434+D434 | F434: =IF(ROUND(C434,2)+ROUND(D434,2)=0,"","yes") | H434: =IF($G434="","",$E434-$G434)

Sheet Deferred Revenue
A1: Deferrals - revenue and cost, released automatically
A2: Every line that carries a Defer Start and a Defer End - Finance invoices in the top block, WIP Movements rows in the block below it. The amount spreads evenly across those months and the WIP movement works itself out. Nothing is typed here.
A3: Month | C3: ='Month-End'!C4 | D3: <- set on the Month-End sheet
A5: Line | B5: Date | C5: Xero Invoice No | D5: Client | E5: Job Number | F5: Cost Centre | G5: Ex GST | H5: Defer Start | I5: Defer End | J5: Months | K5: Per Month | L5: Recognised to date | M5: Recognised to prior | N5: Invoiced to date | O5: Invoiced to prior | P5: Opening WIP | Q5: Movement | R5: Closing WIP | S5: Source | T5: Rev/Cost
A6: =ROW()-5 | B6: =IFERROR(INDEX(tbl_Finance[Date],$A6),"") | C6: =IFERROR(INDEX(tbl_Finance[Xero Invoice No],$A6),"") | D6: =IFERROR(INDEX(tbl_Finance[Client],$A6),"") | E6: =IFERROR(INDEX(tbl_Finance[Job Number],$A6),"") | F6: =IFERROR(INDEX(tbl_Finance[Cost Centre],$A6),"") | G6: =IFERROR(INDEX(tbl_Finance[Ex GST],$A6),"") | H6: =IFERROR(INDEX(tbl_Finance[Defer Start],$A6),"") | I6: =IFERROR(INDEX(tbl_Finance[Defer End],$A6),"") | J6: =IF(OR($H6="",$I6="",$G6=""),"",MAX(1,(YEAR($I6)-YEAR($H6))*12+MONTH($I6)-MONTH($H6)+1)) | K6: =IF($J6="","",$G6/$J6) | L6: =IF($J6="",0,$K6*MAX(0,MIN(YEAR($C$3)*12+MONTH($C$3),YEAR($I6)*12+MONTH($I6))-(YEAR($H6)*12+MONTH($H6))+1)) | M6: =IF($J6="",0,$K6*MAX(0,MIN(YEAR($C$3)*12+MONTH($C$3)-1,YEAR($I6)*12+MONTH($I6))-(YEAR($H6)*12+MONTH($H6))+1)) | N6: =IF(OR($J6="",$B6=""),0,IF(YEAR($B6)*12+MONTH($B6)<=YEAR($C$3)*12+MONTH($C$3),$G6,0)) | O6: =IF(OR($J6="",$B6=""),0,IF(YEAR($B6)*12+MONTH($B6)<=YEAR($C$3)*12+MONTH($C$3)-1,$G6,0)) | P6: =$M6-$O6 | Q6: =($L6-$M6)-($N6-$O6) | R6: =$L6-$N6 | S6: ="Finance invoice" | T6: ="Revenue"
A7: =ROW()-5 | B7: =IFERROR(INDEX(tbl_Finance[Date],$A7),"") | C7: =IFERROR(INDEX(tbl_Finance[Xero Invoice No],$A7),"") | D7: =IFERROR(INDEX(tbl_Finance[Client],$A7),"") | E7: =IFERROR(INDEX(tbl_Finance[Job Number],$A7),"") | F7: =IFERROR(INDEX(tbl_Finance[Cost Centre],$A7),"") | G7: =IFERROR(INDEX(tbl_Finance[Ex GST],$A7),"") | H7: =IFERROR(INDEX(tbl_Finance[Defer Start],$A7),"") | I7: =IFERROR(INDEX(tbl_Finance[Defer End],$A7),"") | J7: =IF(OR($H7="",$I7="",$G7=""),"",MAX(1,(YEAR($I7)-YEAR($H7))*12+MONTH($I7)-MONTH($H7)+1)) | K7: =IF($J7="","",$G7/$J7) | L7: =IF($J7="",0,$K7*MAX(0,MIN(YEAR($C$3)*12+MONTH($C$3),YEAR($I7)*12+MONTH($I7))-(YEAR($H7)*12+MONTH($H7))+1)) | M7: =IF($J7="",0,$K7*MAX(0,MIN(YEAR($C$3)*12+MONTH($C$3)-1,YEAR($I7)*12+MONTH($I7))-(YEAR($H7)*12+MONTH($H7))+1)) | N7: =IF(OR($J7="",$B7=""),0,IF(YEAR($B7)*12+MONTH($B7)<=YEAR($C$3)*12+MONTH($C$3),$G7,0)) | O7: =IF(OR($J7="",$B7=""),0,IF(YEAR($B7)*12+MONTH($B7)<=YEAR($C$3)*12+MONTH($C$3)-1,$G7,0)) | P7: =$M7-$O7 | Q7: =($L7-$M7)-($N7-$O7) | R7: =$L7-$N7 | S7: ="Finance invoice" | T7: ="Revenue"
A8: =ROW()-5 | B8: =IFERROR(INDEX(tbl_Finance[Date],$A8),"") | C8: =IFERROR(INDEX(tbl_Finance[Xero Invoice No],$A8),"") | D8: =IFERROR(INDEX(tbl_Finance[Client],$A8),"") | E8: =IFERROR(INDEX(tbl_Finance[Job Number],$A8),"") | F8: =IFERROR(INDEX(tbl_Finance[Cost Centre],$A8),"") | G8: =IFERROR(INDEX(tbl_Finance[Ex GST],$A8),"") | H8: =IFERROR(INDEX(tbl_Finance[Defer Start],$A8),"") | I8: =IFERROR(INDEX(tbl_Finance[Defer End],$A8),"") | J8: =IF(OR($H8="",$I8="",$G8=""),"",MAX(1,(YEAR($I8)-YEAR($H8))*12+MONTH($I8)-MONTH($H8)+1)) | K8: =IF($J8="","",$G8/$J8) | L8: =IF($J8="",0,$K8*MAX(0,MIN(YEAR($C$3)*12+MONTH($C$3),YEAR($I8)*12+MONTH($I8))-(YEAR($H8)*12+MONTH($H8))+1)) | M8: =IF($J8="",0,$K8*MAX(0,MIN(YEAR($C$3)*12+MONTH($C$3)-1,YEAR($I8)*12+MONTH($I8))-(YEAR($H8)*12+MONTH($H8))+1)) | N8: =IF(OR($J8="",$B8=""),0,IF(YEAR($B8)*12+MONTH($B8)<=YEAR($C$3)*12+MONTH($C$3),$G8,0)) | O8: =IF(OR($J8="",$B8=""),0,IF(YEAR($B8)*12+MONTH($B8)<=YEAR($C$3)*12+MONTH($C$3)-1,$G8,0)) | P8: =$M8-$O8 | Q8: =($L8-$M8)-($N8-$O8) | R8: =$L8-$N8 | S8: ="Finance invoice" | T8: ="Revenue"
A9: =ROW()-5 | B9: =IFERROR(INDEX(tbl_Finance[Date],$A9),"") | C9: =IFERROR(INDEX(tbl_Finance[Xero Invoice No],$A9),"") | D9: =IFERROR(INDEX(tbl_Finance[Client],$A9),"") | E9: =IFERROR(INDEX(tbl_Finance[Job Number],$A9),"") | F9: =IFERROR(INDEX(tbl_Finance[Cost Centre],$A9),"") | G9: =IFERROR(INDEX(tbl_Finance[Ex GST],$A9),"") | H9: =IFERROR(INDEX(tbl_Finance[Defer Start],$A9),"") | I9: =IFERROR(INDEX(tbl_Finance[Defer End],$A9),"") | J9: =IF(OR($H9="",$I9="",$G9=""),"",MAX(1,(YEAR($I9)-YEAR($H9))*12+MONTH($I9)-MONTH($H9)+1)) | K9: =IF($J9="","",$G9/$J9) | L9: =IF($J9="",0,$K9*MAX(0,MIN(YEAR($C$3)*12+MONTH($C$3),YEAR($I9)*12+MONTH($I9))-(YEAR($H9)*12+MONTH($H9))+1)) | M9: =IF($J9="",0,$K9*MAX(0,MIN(YEAR($C$3)*12+MONTH($C$3)-1,YEAR($I9)*12+MONTH($I9))-(YEAR($H9)*12+MONTH($H9))+1)) | N9: =IF(OR($J9="",$B9=""),0,IF(YEAR($B9)*12+MONTH($B9)<=YEAR($C$3)*12+MONTH($C$3),$G9,0)) | O9: =IF(OR($J9="",$B9=""),0,IF(YEAR($B9)*12+MONTH($B9)<=YEAR($C$3)*12+MONTH($C$3)-1,$G9,0)) | P9: =$M9-$O9 | Q9: =($L9-$M9)-($N9-$O9) | R9: =$L9-$N9 | S9: ="Finance invoice" | T9: ="Revenue"
A10: =ROW()-5 | B10: =IFERROR(INDEX(tbl_Finance[Date],$A10),"") | C10: =IFERROR(INDEX(tbl_Finance[Xero Invoice No],$A10),"") | D10: =IFERROR(INDEX(tbl_Finance[Client],$A10),"") | E10: =IFERROR(INDEX(tbl_Finance[Job Number],$A10),"") | F10: =IFERROR(INDEX(tbl_Finance[Cost Centre],$A10),"") | G10: =IFERROR(INDEX(tbl_Finance[Ex GST],$A10),"") | H10: =IFERROR(INDEX(tbl_Finance[Defer Start],$A10),"") | I10: =IFERROR(INDEX(tbl_Finance[Defer End],$A10),"") | J10: =IF(OR($H10="",$I10="",$G10=""),"",MAX(1,(YEAR($I10)-YEAR($H10))*12+MONTH($I10)-MONTH($H10)+1)) | K10: =IF($J10="","",$G10/$J10) | L10: =IF($J10="",0,$K10*MAX(0,MIN(YEAR($C$3)*12+MONTH($C$3),YEAR($I10)*12+MONTH($I10))-(YEAR($H10)*12+MONTH($H10))+1)) | M10: =IF($J10="",0,$K10*MAX(0,MIN(YEAR($C$3)*12+MONTH($C$3)-1,YEAR($I10)*12+MONTH($I10))-(YEAR($H10)*12+MONTH($H10))+1)) | N10: =IF(OR($J10="",$B10=""),0,IF(YEAR($B10)*12+MONTH($B10)<=YEAR($C$3)*12+MONTH($C$3),$G10,0)) | O10: =IF(OR($J10="",$B10=""),0,IF(YEAR($B10)*12+MONTH($B10)<=YEAR($C$3)*12+MONTH($C$3)-1,$G10,0)) | P10: =$M10-$O10 | Q10: =($L10-$M10)-($N10-$O10) | R10: =$L10-$N10 | S10: ="Finance invoice" | T10: ="Revenue"
A11: =ROW()-5 | B11: =IFERROR(INDEX(tbl_Finance[Date],$A11),"") | C11: =IFERROR(INDEX(tbl_Finance[Xero Invoice No],$A11),"") | D11: =IFERROR(INDEX(tbl_Finance[Client],$A11),"") | E11: =IFERROR(INDEX(tbl_Finance[Job Number],$A11),"") | F11: =IFERROR(INDEX(tbl_Finance[Cost Centre],$A11),"") | G11: =IFERROR(INDEX(tbl_Finance[Ex GST],$A11),"") | H11: =IFERROR(INDEX(tbl_Finance[Defer Start],$A11),"") | I11: =IFERROR(INDEX(tbl_Finance[Defer End],$A11),"") | J11: =IF(OR($H11="",$I11="",$G11=""),"",MAX(1,(YEAR($I11)-YEAR($H11))*12+MONTH($I11)-MONTH($H11)+1)) | K11: =IF($J11="","",$G11/$J11) | L11: =IF($J11="",0,$K11*MAX(0,MIN(YEAR($C$3)*12+MONTH($C$3),YEAR($I11)*12+MONTH($I11))-(YEAR($H11)*12+MONTH($H11))+1)) | M11: =IF($J11="",0,$K11*MAX(0,MIN(YEAR($C$3)*12+MONTH($C$3)-1,YEAR($I11)*12+MONTH($I11))-(YEAR($H11)*12+MONTH($H11))+1)) | N11: =IF(OR($J11="",$B11=""),0,IF(YEAR($B11)*12+MONTH($B11)<=YEAR($C$3)*12+MONTH($C$3),$G11,0)) | O11: =IF(OR($J11="",$B11=""),0,IF(YEAR($B11)*12+MONTH($B11)<=YEAR($C$3)*12+MONTH($C$3)-1,$G11,0)) | P11: =$M11-$O11 | Q11: =($L11-$M11)-($N11-$O11) | R11: =$L11-$N11 | S11: ="Finance invoice" | T11: ="Revenue"
A12: =ROW()-5 | B12: =IFERROR(INDEX(tbl_Finance[Date],$A12),"") | C12: =IFERROR(INDEX(tbl_Finance[Xero Invoice No],$A12),"") | D12: =IFERROR(INDEX(tbl_Finance[Client],$A12),"") | E12: =IFERROR(INDEX(tbl_Finance[Job Number],$A12),"") | F12: =IFERROR(INDEX(tbl_Finance[Cost Centre],$A12),"") | G12: =IFERROR(INDEX(tbl_Finance[Ex GST],$A12),"") | H12: =IFERROR(INDEX(tbl_Finance[Defer Start],$A12),"") | I12: =IFERROR(INDEX(tbl_Finance[Defer End],$A12),"") | J12: =IF(OR($H12="",$I12="",$G12=""),"",MAX(1,(YEAR($I12)-YEAR($H12))*12+MONTH($I12)-MONTH($H12)+1)) | K12: =IF($J12="","",$G12/$J12) | L12: =IF($J12="",0,$K12*MAX(0,MIN(YEAR($C$3)*12+MONTH($C$3),YEAR($I12)*12+MONTH($I12))-(YEAR($H12)*12+MONTH($H12))+1)) | M12: =IF($J12="",0,$K12*MAX(0,MIN(YEAR($C$3)*12+MONTH($C$3)-1,YEAR($I12)*12+MONTH($I12))-(YEAR($H12)*12+MONTH($H12))+1)) | N12: =IF(OR($J12="",$B12=""),0,IF(YEAR($B12)*12+MONTH($B12)<=YEAR($C$3)*12+MONTH($C$3),$G12,0)) | O12: =IF(OR($J12="",$B12=""),0,IF(YEAR($B12)*12+MONTH($B12)<=YEAR($C$3)*12+MONTH($C$3)-1,$G12,0)) | P12: =$M12-$O12 | Q12: =($L12-$M12)-($N12-$O12) | R12: =$L12-$N12 | S12: ="Finance invoice" | T12: ="Revenue"
A13: =ROW()-5 | B13: =IFERROR(INDEX(tbl_Finance[Date],$A13),"") | C13: =IFERROR(INDEX(tbl_Finance[Xero Invoice No],$A13),"") | D13: =IFERROR(INDEX(tbl_Finance[Client],$A13),"") | E13: =IFERROR(INDEX(tbl_Finance[Job Number],$A13),"") | F13: =IFERROR(INDEX(tbl_Finance[Cost Centre],$A13),"") | G13: =IFERROR(INDEX(tbl_Finance[Ex GST],$A13),"") | H13: =IFERROR(INDEX(tbl_Finance[Defer Start],$A13),"") | I13: =IFERROR(INDEX(tbl_Finance[Defer End],$A13),"") | J13: =IF(OR($H13="",$I13="",$G13=""),"",MAX(1,(YEAR($I13)-YEAR($H13))*12+MONTH($I13)-MONTH($H13)+1)) | K13: =IF($J13="","",$G13/$J13) | L13: =IF($J13="",0,$K13*MAX(0,MIN(YEAR($C$3)*12+MONTH($C$3),YEAR($I13)*12+MONTH($I13))-(YEAR($H13)*12+MONTH($H13))+1)) | M13: =IF($J13="",0,$K13*MAX(0,MIN(YEAR($C$3)*12+MONTH($C$3)-1,YEAR($I13)*12+MONTH($I13))-(YEAR($H13)*12+MONTH($H13))+1)) | N13: =IF(OR($J13="",$B13=""),0,IF(YEAR($B13)*12+MONTH($B13)<=YEAR($C$3)*12+MONTH($C$3),$G13,0)) | O13: =IF(OR($J13="",$B13=""),0,IF(YEAR($B13)*12+MONTH($B13)<=YEAR($C$3)*12+MONTH($C$3)-1,$G13,0)) | P13: =$M13-$O13 | Q13: =($L13-$M13)-($N13-$O13) | R13: =$L13-$N13 | S13: ="Finance invoice" | T13: ="Revenue"
A14: =ROW()-5 | B14: =IFERROR(INDEX(tbl_Finance[Date],$A14),"") | C14: =IFERROR(INDEX(tbl_Finance[Xero Invoice No],$A14),"") | D14: =IFERROR(INDEX(tbl_Finance[Client],$A14),"") | E14: =IFERROR(INDEX(tbl_Finance[Job Number],$A14),"") | F14: =IFERROR(INDEX(tbl_Finance[Cost Centre],$A14),"") | G14: =IFERROR(INDEX(tbl_Finance[Ex GST],$A14),"") | H14: =IFERROR(INDEX(tbl_Finance[Defer Start],$A14),"") | I14: =IFERROR(INDEX(tbl_Finance[Defer End],$A14),"") | J14: =IF(OR($H14="",$I14="",$G14=""),"",MAX(1,(YEAR($I14)-YEAR($H14))*12+MONTH($I14)-MONTH($H14)+1)) | K14: =IF($J14="","",$G14/$J14) | L14: =IF($J14="",0,$K14*MAX(0,MIN(YEAR($C$3)*12+MONTH($C$3),YEAR($I14)*12+MONTH($I14))-(YEAR($H14)*12+MONTH($H14))+1)) | M14: =IF($J14="",0,$K14*MAX(0,MIN(YEAR($C$3)*12+MONTH($C$3)-1,YEAR($I14)*12+MONTH($I14))-(YEAR($H14)*12+MONTH($H14))+1)) | N14: =IF(OR($J14="",$B14=""),0,IF(YEAR($B14)*12+MONTH($B14)<=YEAR($C$3)*12+MONTH($C$3),$G14,0)) | O14: =IF(OR($J14="",$B14=""),0,IF(YEAR($B14)*12+MONTH($B14)<=YEAR($C$3)*12+MONTH($C$3)-1,$G14,0)) | P14: =$M14-$O14 | Q14: =($L14-$M14)-($N14-$O14) | R14: =$L14-$N14 | S14: ="Finance invoice" | T14: ="Revenue"
A15: =ROW()-5 | B15: =IFERROR(INDEX(tbl_Finance[Date],$A15),"") | C15: =IFERROR(INDEX(tbl_Finance[Xero Invoice No],$A15),"") | D15: =IFERROR(INDEX(tbl_Finance[Client],$A15),"") | E15: =IFERROR(INDEX(tbl_Finance[Job Number],$A15),"") | F15: =IFERROR(INDEX(tbl_Finance[Cost Centre],$A15),"") | G15: =IFERROR(INDEX(tbl_Finance[Ex GST],$A15),"") | H15: =IFERROR(INDEX(tbl_Finance[Defer Start],$A15),"") | I15: =IFERROR(INDEX(tbl_Finance[Defer End],$A15),"") | J15: =IF(OR($H15="",$I15="",$G15=""),"",MAX(1,(YEAR($I15)-YEAR($H15))*12+MONTH($I15)-MONTH($H15)+1)) | K15: =IF($J15="","",$G15/$J15) | L15: =IF($J15="",0,$K15*MAX(0,MIN(YEAR($C$3)*12+MONTH($C$3),YEAR($I15)*12+MONTH($I15))-(YEAR($H15)*12+MONTH($H15))+1)) | M15: =IF($J15="",0,$K15*MAX(0,MIN(YEAR($C$3)*12+MONTH($C$3)-1,YEAR($I15)*12+MONTH($I15))-(YEAR($H15)*12+MONTH($H15))+1)) | N15: =IF(OR($J15="",$B15=""),0,IF(YEAR($B15)*12+MONTH($B15)<=YEAR($C$3)*12+MONTH($C$3),$G15,0)) | O15: =IF(OR($J15="",$B15=""),0,IF(YEAR($B15)*12+MONTH($B15)<=YEAR($C$3)*12+MONTH($C$3)-1,$G15,0)) | P15: =$M15-$O15 | Q15: =($L15-$M15)-($N15-$O15) | R15: =$L15-$N15 | S15: ="Finance invoice" | T15: ="Revenue"
A16: =ROW()-5 | B16: =IFERROR(INDEX(tbl_Finance[Date],$A16),"") | C16: =IFERROR(INDEX(tbl_Finance[Xero Invoice No],$A16),"") | D16: =IFERROR(INDEX(tbl_Finance[Client],$A16),"") | E16: =IFERROR(INDEX(tbl_Finance[Job Number],$A16),"") | F16: =IFERROR(INDEX(tbl_Finance[Cost Centre],$A16),"") | G16: =IFERROR(INDEX(tbl_Finance[Ex GST],$A16),"") | H16: =IFERROR(INDEX(tbl_Finance[Defer Start],$A16),"") | I16: =IFERROR(INDEX(tbl_Finance[Defer End],$A16),"") | J16: =IF(OR($H16="",$I16="",$G16=""),"",MAX(1,(YEAR($I16)-YEAR($H16))*12+MONTH($I16)-MONTH($H16)+1)) | K16: =IF($J16="","",$G16/$J16) | L16: =IF($J16="",0,$K16*MAX(0,MIN(YEAR($C$3)*12+MONTH($C$3),YEAR($I16)*12+MONTH($I16))-(YEAR($H16)*12+MONTH($H16))+1)) | M16: =IF($J16="",0,$K16*MAX(0,MIN(YEAR($C$3)*12+MONTH($C$3)-1,YEAR($I16)*12+MONTH($I16))-(YEAR($H16)*12+MONTH($H16))+1)) | N16: =IF(OR($J16="",$B16=""),0,IF(YEAR($B16)*12+MONTH($B16)<=YEAR($C$3)*12+MONTH($C$3),$G16,0)) | O16: =IF(OR($J16="",$B16=""),0,IF(YEAR($B16)*12+MONTH($B16)<=YEAR($C$3)*12+MONTH($C$3)-1,$G16,0)) | P16: =$M16-$O16 | Q16: =($L16-$M16)-($N16-$O16) | R16: =$L16-$N16 | S16: ="Finance invoice" | T16: ="Revenue"
A17: =ROW()-5 | B17: =IFERROR(INDEX(tbl_Finance[Date],$A17),"") | C17: =IFERROR(INDEX(tbl_Finance[Xero Invoice No],$A17),"") | D17: =IFERROR(INDEX(tbl_Finance[Client],$A17),"") | E17: =IFERROR(INDEX(tbl_Finance[Job Number],$A17),"") | F17: =IFERROR(INDEX(tbl_Finance[Cost Centre],$A17),"") | G17: =IFERROR(INDEX(tbl_Finance[Ex GST],$A17),"") | H17: =IFERROR(INDEX(tbl_Finance[Defer Start],$A17),"") | I17: =IFERROR(INDEX(tbl_Finance[Defer End],$A17),"") | J17: =IF(OR($H17="",$I17="",$G17=""),"",MAX(1,(YEAR($I17)-YEAR($H17))*12+MONTH($I17)-MONTH($H17)+1)) | K17: =IF($J17="","",$G17/$J17) | L17: =IF($J17="",0,$K17*MAX(0,MIN(YEAR($C$3)*12+MONTH($C$3),YEAR($I17)*12+MONTH($I17))-(YEAR($H17)*12+MONTH($H17))+1)) | M17: =IF($J17="",0,$K17*MAX(0,MIN(YEAR($C$3)*12+MONTH($C$3)-1,YEAR($I17)*12+MONTH($I17))-(YEAR($H17)*12+MONTH($H17))+1)) | N17: =IF(OR($J17="",$B17=""),0,IF(YEAR($B17)*12+MONTH($B17)<=YEAR($C$3)*12+MONTH($C$3),$G17,0)) | O17: =IF(OR($J17="",$B17=""),0,IF(YEAR($B17)*12+MONTH($B17)<=YEAR($C$3)*12+MONTH($C$3)-1,$G17,0)) | P17: =$M17-$O17 | Q17: =($L17-$M17)-($N17-$O17) | R17: =$L17-$N17 | S17: ="Finance invoice" | T17: ="Revenue"
... A405: =ROW()-5 | B405: =IFERROR(INDEX(tbl_Finance[Date],$A405),"") | C405: =IFERROR(INDEX(tbl_Finance[Xero Invoice No],$A405),"") | D405: =IFERROR(INDEX(tbl_Finance[Client],$A405),"") | E405: =IFERROR(INDEX(tbl_Finance[Job Number],$A405),"") | F405: =IFERROR(INDEX(tbl_Finance[Cost Centre],$A405),"") | G405: =IFERROR(INDEX(tbl_Finance[Ex GST],$A405),"") | H405: =IFERROR(INDEX(tbl_Finance[Defer Start],$A405),"") | I405: =IFERROR(INDEX(tbl_Finance[Defer End],$A405),"") | J405: =IF(OR($H405="",$I405="",$G405=""),"",MAX(1,(YEAR($I405)-YEAR($H405))*12+MONTH($I405)-MONTH($H405)+1)) | K405: =IF($J405="","",$G405/$J405) | L405: =IF($J405="",0,$K405*MAX(0,MIN(YEAR($C$3)*12+MONTH($C$3),YEAR($I405)*12+MONTH($I405))-(YEAR($H405)*12+MONTH($H405))+1)) | M405: =IF($J405="",0,$K405*MAX(0,MIN(YEAR($C$3)*12+MONTH($C$3)-1,YEAR($I405)*12+MONTH($I405))-(YEAR($H405)*12+MONTH($H405))+1)) | N405: =IF(OR($J405="",$B405=""),0,IF(YEAR($B405)*12+MONTH($B405)<=YEAR($C$3)*12+MONTH($C$3),$G405,0)) | O405: =IF(OR($J405="",$B405=""),0,IF(YEAR($B405)*12+MONTH($B405)<=YEAR($C$3)*12+MONTH($C$3)-1,$G405,0)) | P405: =$M405-$O405 | Q405: =($L405-$M405)-($N405-$O405) | R405: =$L405-$N405 | S405: ="Finance invoice" | T405: ="Revenue"
A407: WIP Movements rows that spread over months - deferred cost and manual deferred revenue
A408: =ROW()-407 | B408: =IFERROR(INDEX(tbl_WIP[Month],$A408),"") | C408: =IFERROR(INDEX(tbl_WIP[Xero Invoice No],$A408),"") | D408: =IFERROR(INDEX(tbl_WIP[Client],$A408),"") | E408: =IFERROR(INDEX(tbl_WIP[Job Number],$A408),"") | F408: =IFERROR(INDEX(tbl_WIP[Cost Centre],$A408),"") | G408: =IFERROR(IF(INDEX(tbl_WIP[Defer Start],$A408)="","",IF(INDEX(tbl_WIP[Revenue or Cost],$A408)="Cost",-1,1)*INDEX(tbl_WIP[Amount],$A408)),"") | H408: =IFERROR(INDEX(tbl_WIP[Defer Start],$A408),"") | I408: =IFERROR(INDEX(tbl_WIP[Defer End],$A408),"") | J408: =IF(OR($H408="",$I408="",$G408=""),"",MAX(1,(YEAR($I408)-YEAR($H408))*12+MONTH($I408)-MONTH($H408)+1)) | K408: =IF($J408="","",$G408/$J408) | L408: =IF($J408="",0,$K408*MAX(0,MIN(YEAR($C$3)*12+MONTH($C$3),YEAR($I408)*12+MONTH($I408))-(YEAR($H408)*12+MONTH($H408))+1)) | M408: =IF($J408="",0,$K408*MAX(0,MIN(YEAR($C$3)*12+MONTH($C$3)-1,YEAR($I408)*12+MONTH($I408))-(YEAR($H408)*12+MONTH($H408))+1)) | N408: =IF(OR($J408="",$B408=""),0,IF(YEAR($B408)*12+MONTH($B408)<=YEAR($C$3)*12+MONTH($C$3),$G408,0)) | O408: =IF(OR($J408="",$B408=""),0,IF(YEAR($B408)*12+MONTH($B408)<=YEAR($C$3)*12+MONTH($C$3)-1,$G408,0)) | P408: =$M408-$O408 | Q408: =($L408-$M408)-($N408-$O408) | R408: =$L408-$N408 | S408: ="WIP journal" | T408: =IFERROR(INDEX(tbl_WIP[Revenue or Cost],$A408),"")
A409: =ROW()-407 | B409: =IFERROR(INDEX(tbl_WIP[Month],$A409),"") | C409: =IFERROR(INDEX(tbl_WIP[Xero Invoice No],$A409),"") | D409: =IFERROR(INDEX(tbl_WIP[Client],$A409),"") | E409: =IFERROR(INDEX(tbl_WIP[Job Number],$A409),"") | F409: =IFERROR(INDEX(tbl_WIP[Cost Centre],$A409),"") | G409: =IFERROR(IF(INDEX(tbl_WIP[Defer Start],$A409)="","",IF(INDEX(tbl_WIP[Revenue or Cost],$A409)="Cost",-1,1)*INDEX(tbl_WIP[Amount],$A409)),"") | H409: =IFERROR(INDEX(tbl_WIP[Defer Start],$A409),"") | I409: =IFERROR(INDEX(tbl_WIP[Defer End],$A409),"") | J409: =IF(OR($H409="",$I409="",$G409=""),"",MAX(1,(YEAR($I409)-YEAR($H409))*12+MONTH($I409)-MONTH($H409)+1)) | K409: =IF($J409="","",$G409/$J409) | L409: =IF($J409="",0,$K409*MAX(0,MIN(YEAR($C$3)*12+MONTH($C$3),YEAR($I409)*12+MONTH($I409))-(YEAR($H409)*12+MONTH($H409))+1)) | M409: =IF($J409="",0,$K409*MAX(0,MIN(YEAR($C$3)*12+MONTH($C$3)-1,YEAR($I409)*12+MONTH($I409))-(YEAR($H409)*12+MONTH($H409))+1)) | N409: =IF(OR($J409="",$B409=""),0,IF(YEAR($B409)*12+MONTH($B409)<=YEAR($C$3)*12+MONTH($C$3),$G409,0)) | O409: =IF(OR($J409="",$B409=""),0,IF(YEAR($B409)*12+MONTH($B409)<=YEAR($C$3)*12+MONTH($C$3)-1,$G409,0)) | P409: =$M409-$O409 | Q409: =($L409-$M409)-($N409-$O409) | R409: =$L409-$N409 | S409: ="WIP journal" | T409: =IFERROR(INDEX(tbl_WIP[Revenue or Cost],$A409),"")
A410: =ROW()-407 | B410: =IFERROR(INDEX(tbl_WIP[Month],$A410),"") | C410: =IFERROR(INDEX(tbl_WIP[Xero Invoice No],$A410),"") | D410: =IFERROR(INDEX(tbl_WIP[Client],$A410),"") | E410: =IFERROR(INDEX(tbl_WIP[Job Number],$A410),"") | F410: =IFERROR(INDEX(tbl_WIP[Cost Centre],$A410),"") | G410: =IFERROR(IF(INDEX(tbl_WIP[Defer Start],$A410)="","",IF(INDEX(tbl_WIP[Revenue or Cost],$A410)="Cost",-1,1)*INDEX(tbl_WIP[Amount],$A410)),"") | H410: =IFERROR(INDEX(tbl_WIP[Defer Start],$A410),"") | I410: =IFERROR(INDEX(tbl_WIP[Defer End],$A410),"") | J410: =IF(OR($H410="",$I410="",$G410=""),"",MAX(1,(YEAR($I410)-YEAR($H410))*12+MONTH($I410)-MONTH($H410)+1)) | K410: =IF($J410="","",$G410/$J410) | L410: =IF($J410="",0,$K410*MAX(0,MIN(YEAR($C$3)*12+MONTH($C$3),YEAR($I410)*12+MONTH($I410))-(YEAR($H410)*12+MONTH($H410))+1)) | M410: =IF($J410="",0,$K410*MAX(0,MIN(YEAR($C$3)*12+MONTH($C$3)-1,YEAR($I410)*12+MONTH($I410))-(YEAR($H410)*12+MONTH($H410))+1)) | N410: =IF(OR($J410="",$B410=""),0,IF(YEAR($B410)*12+MONTH($B410)<=YEAR($C$3)*12+MONTH($C$3),$G410,0)) | O410: =IF(OR($J410="",$B410=""),0,IF(YEAR($B410)*12+MONTH($B410)<=YEAR($C$3)*12+MONTH($C$3)-1,$G410,0)) | P410: =$M410-$O410 | Q410: =($L410-$M410)-($N410-$O410) | R410: =$L410-$N410 | S410: ="WIP journal" | T410: =IFERROR(INDEX(tbl_WIP[Revenue or Cost],$A410),"")
A411: =ROW()-407 | B411: =IFERROR(INDEX(tbl_WIP[Month],$A411),"") | C411: =IFERROR(INDEX(tbl_WIP[Xero Invoice No],$A411),"") | D411: =IFERROR(INDEX(tbl_WIP[Client],$A411),"") | E411: =IFERROR(INDEX(tbl_WIP[Job Number],$A411),"") | F411: =IFERROR(INDEX(tbl_WIP[Cost Centre],$A411),"") | G411: =IFERROR(IF(INDEX(tbl_WIP[Defer Start],$A411)="","",IF(INDEX(tbl_WIP[Revenue or Cost],$A411)="Cost",-1,1)*INDEX(tbl_WIP[Amount],$A411)),"") | H411: =IFERROR(INDEX(tbl_WIP[Defer Start],$A411),"") | I411: =IFERROR(INDEX(tbl_WIP[Defer End],$A411),"") | J411: =IF(OR($H411="",$I411="",$G411=""),"",MAX(1,(YEAR($I411)-YEAR($H411))*12+MONTH($I411)-MONTH($H411)+1)) | K411: =IF($J411="","",$G411/$J411) | L411: =IF($J411="",0,$K411*MAX(0,MIN(YEAR($C$3)*12+MONTH($C$3),YEAR($I411)*12+MONTH($I411))-(YEAR($H411)*12+MONTH($H411))+1)) | M411: =IF($J411="",0,$K411*MAX(0,MIN(YEAR($C$3)*12+MONTH($C$3)-1,YEAR($I411)*12+MONTH($I411))-(YEAR($H411)*12+MONTH($H411))+1)) | N411: =IF(OR($J411="",$B411=""),0,IF(YEAR($B411)*12+MONTH($B411)<=YEAR($C$3)*12+MONTH($C$3),$G411,0)) | O411: =IF(OR($J411="",$B411=""),0,IF(YEAR($B411)*12+MONTH($B411)<=YEAR($C$3)*12+MONTH($C$3)-1,$G411,0)) | P411: =$M411-$O411 | Q411: =($L411-$M411)-($N411-$O411) | R411: =$L411-$N411 | S411: ="WIP journal" | T411: =IFERROR(INDEX(tbl_WIP[Revenue or Cost],$A411),"")
A412: =ROW()-407 | B412: =IFERROR(INDEX(tbl_WIP[Month],$A412),"") | C412: =IFERROR(INDEX(tbl_WIP[Xero Invoice No],$A412),"") | D412: =IFERROR(INDEX(tbl_WIP[Client],$A412),"") | E412: =IFERROR(INDEX(tbl_WIP[Job Number],$A412),"") | F412: =IFERROR(INDEX(tbl_WIP[Cost Centre],$A412),"") | G412: =IFERROR(IF(INDEX(tbl_WIP[Defer Start],$A412)="","",IF(INDEX(tbl_WIP[Revenue or Cost],$A412)="Cost",-1,1)*INDEX(tbl_WIP[Amount],$A412)),"") | H412: =IFERROR(INDEX(tbl_WIP[Defer Start],$A412),"") | I412: =IFERROR(INDEX(tbl_WIP[Defer End],$A412),"") | J412: =IF(OR($H412="",$I412="",$G412=""),"",MAX(1,(YEAR($I412)-YEAR($H412))*12+MONTH($I412)-MONTH($H412)+1)) | K412: =IF($J412="","",$G412/$J412) | L412: =IF($J412="",0,$K412*MAX(0,MIN(YEAR($C$3)*12+MONTH($C$3),YEAR($I412)*12+MONTH($I412))-(YEAR($H412)*12+MONTH($H412))+1)) | M412: =IF($J412="",0,$K412*MAX(0,MIN(YEAR($C$3)*12+MONTH($C$3)-1,YEAR($I412)*12+MONTH($I412))-(YEAR($H412)*12+MONTH($H412))+1)) | N412: =IF(OR($J412="",$B412=""),0,IF(YEAR($B412)*12+MONTH($B412)<=YEAR($C$3)*12+MONTH($C$3),$G412,0)) | O412: =IF(OR($J412="",$B412=""),0,IF(YEAR($B412)*12+MONTH($B412)<=YEAR($C$3)*12+MONTH($C$3)-1,$G412,0)) | P412: =$M412-$O412 | Q412: =($L412-$M412)-($N412-$O412) | R412: =$L412-$N412 | S412: ="WIP journal" | T412: =IFERROR(INDEX(tbl_WIP[Revenue or Cost],$A412),"")
A413: =ROW()-407 | B413: =IFERROR(INDEX(tbl_WIP[Month],$A413),"") | C413: =IFERROR(INDEX(tbl_WIP[Xero Invoice No],$A413),"") | D413: =IFERROR(INDEX(tbl_WIP[Client],$A413),"") | E413: =IFERROR(INDEX(tbl_WIP[Job Number],$A413),"") | F413: =IFERROR(INDEX(tbl_WIP[Cost Centre],$A413),"") | G413: =IFERROR(IF(INDEX(tbl_WIP[Defer Start],$A413)="","",IF(INDEX(tbl_WIP[Revenue or Cost],$A413)="Cost",-1,1)*INDEX(tbl_WIP[Amount],$A413)),"") | H413: =IFERROR(INDEX(tbl_WIP[Defer Start],$A413),"") | I413: =IFERROR(INDEX(tbl_WIP[Defer End],$A413),"") | J413: =IF(OR($H413="",$I413="",$G413=""),"",MAX(1,(YEAR($I413)-YEAR($H413))*12+MONTH($I413)-MONTH($H413)+1)) | K413: =IF($J413="","",$G413/$J413) | L413: =IF($J413="",0,$K413*MAX(0,MIN(YEAR($C$3)*12+MONTH($C$3),YEAR($I413)*12+MONTH($I413))-(YEAR($H413)*12+MONTH($H413))+1)) | M413: =IF($J413="",0,$K413*MAX(0,MIN(YEAR($C$3)*12+MONTH($C$3)-1,YEAR($I413)*12+MONTH($I413))-(YEAR($H413)*12+MONTH($H413))+1)) | N413: =IF(OR($J413="",$B413=""),0,IF(YEAR($B413)*12+MONTH($B413)<=YEAR($C$3)*12+MONTH($C$3),$G413,0)) | O413: =IF(OR($J413="",$B413=""),0,IF(YEAR($B413)*12+MONTH($B413)<=YEAR($C$3)*12+MONTH($C$3)-1,$G413,0)) | P413: =$M413-$O413 | Q413: =($L413-$M413)-($N413-$O413) | R413: =$L413-$N413 | S413: ="WIP journal" | T413: =IFERROR(INDEX(tbl_WIP[Revenue or Cost],$A413),"")
A414: =ROW()-407 | B414: =IFERROR(INDEX(tbl_WIP[Month],$A414),"") | C414: =IFERROR(INDEX(tbl_WIP[Xero Invoice No],$A414),"") | D414: =IFERROR(INDEX(tbl_WIP[Client],$A414),"") | E414: =IFERROR(INDEX(tbl_WIP[Job Number],$A414),"") | F414: =IFERROR(INDEX(tbl_WIP[Cost Centre],$A414),"") | G414: =IFERROR(IF(INDEX(tbl_WIP[Defer Start],$A414)="","",IF(INDEX(tbl_WIP[Revenue or Cost],$A414)="Cost",-1,1)*INDEX(tbl_WIP[Amount],$A414)),"") | H414: =IFERROR(INDEX(tbl_WIP[Defer Start],$A414),"") | I414: =IFERROR(INDEX(tbl_WIP[Defer End],$A414),"") | J414: =IF(OR($H414="",$I414="",$G414=""),"",MAX(1,(YEAR($I414)-YEAR($H414))*12+MONTH($I414)-MONTH($H414)+1)) | K414: =IF($J414="","",$G414/$J414) | L414: =IF($J414="",0,$K414*MAX(0,MIN(YEAR($C$3)*12+MONTH($C$3),YEAR($I414)*12+MONTH($I414))-(YEAR($H414)*12+MONTH($H414))+1)) | M414: =IF($J414="",0,$K414*MAX(0,MIN(YEAR($C$3)*12+MONTH($C$3)-1,YEAR($I414)*12+MONTH($I414))-(YEAR($H414)*12+MONTH($H414))+1)) | N414: =IF(OR($J414="",$B414=""),0,IF(YEAR($B414)*12+MONTH($B414)<=YEAR($C$3)*12+MONTH($C$3),$G414,0)) | O414: =IF(OR($J414="",$B414=""),0,IF(YEAR($B414)*12+MONTH($B414)<=YEAR($C$3)*12+MONTH($C$3)-1,$G414,0)) | P414: =$M414-$O414 | Q414: =($L414-$M414)-($N414-$O414) | R414: =$L414-$N414 | S414: ="WIP journal" | T414: =IFERROR(INDEX(tbl_WIP[Revenue or Cost],$A414),"")
A415: =ROW()-407 | B415: =IFERROR(INDEX(tbl_WIP[Month],$A415),"") | C415: =IFERROR(INDEX(tbl_WIP[Xero Invoice No],$A415),"") | D415: =IFERROR(INDEX(tbl_WIP[Client],$A415),"") | E415: =IFERROR(INDEX(tbl_WIP[Job Number],$A415),"") | F415: =IFERROR(INDEX(tbl_WIP[Cost Centre],$A415),"") | G415: =IFERROR(IF(INDEX(tbl_WIP[Defer Start],$A415)="","",IF(INDEX(tbl_WIP[Revenue or Cost],$A415)="Cost",-1,1)*INDEX(tbl_WIP[Amount],$A415)),"") | H415: =IFERROR(INDEX(tbl_WIP[Defer Start],$A415),"") | I415: =IFERROR(INDEX(tbl_WIP[Defer End],$A415),"") | J415: =IF(OR($H415="",$I415="",$G415=""),"",MAX(1,(YEAR($I415)-YEAR($H415))*12+MONTH($I415)-MONTH($H415)+1)) | K415: =IF($J415="","",$G415/$J415) | L415: =IF($J415="",0,$K415*MAX(0,MIN(YEAR($C$3)*12+MONTH($C$3),YEAR($I415)*12+MONTH($I415))-(YEAR($H415)*12+MONTH($H415))+1)) | M415: =IF($J415="",0,$K415*MAX(0,MIN(YEAR($C$3)*12+MONTH($C$3)-1,YEAR($I415)*12+MONTH($I415))-(YEAR($H415)*12+MONTH($H415))+1)) | N415: =IF(OR($J415="",$B415=""),0,IF(YEAR($B415)*12+MONTH($B415)<=YEAR($C$3)*12+MONTH($C$3),$G415,0)) | O415: =IF(OR($J415="",$B415=""),0,IF(YEAR($B415)*12+MONTH($B415)<=YEAR($C$3)*12+MONTH($C$3)-1,$G415,0)) | P415: =$M415-$O415 | Q415: =($L415-$M415)-($N415-$O415) | R415: =$L415-$N415 | S415: ="WIP journal" | T415: =IFERROR(INDEX(tbl_WIP[Revenue or Cost],$A415),"")
A416: =ROW()-407 | B416: =IFERROR(INDEX(tbl_WIP[Month],$A416),"") | C416: =IFERROR(INDEX(tbl_WIP[Xero Invoice No],$A416),"") | D416: =IFERROR(INDEX(tbl_WIP[Client],$A416),"") | E416: =IFERROR(INDEX(tbl_WIP[Job Number],$A416),"") | F416: =IFERROR(INDEX(tbl_WIP[Cost Centre],$A416),"") | G416: =IFERROR(IF(INDEX(tbl_WIP[Defer Start],$A416)="","",IF(INDEX(tbl_WIP[Revenue or Cost],$A416)="Cost",-1,1)*INDEX(tbl_WIP[Amount],$A416)),"") | H416: =IFERROR(INDEX(tbl_WIP[Defer Start],$A416),"") | I416: =IFERROR(INDEX(tbl_WIP[Defer End],$A416),"") | J416: =IF(OR($H416="",$I416="",$G416=""),"",MAX(1,(YEAR($I416)-YEAR($H416))*12+MONTH($I416)-MONTH($H416)+1)) | K416: =IF($J416="","",$G416/$J416) | L416: =IF($J416="",0,$K416*MAX(0,MIN(YEAR($C$3)*12+MONTH($C$3),YEAR($I416)*12+MONTH($I416))-(YEAR($H416)*12+MONTH($H416))+1)) | M416: =IF($J416="",0,$K416*MAX(0,MIN(YEAR($C$3)*12+MONTH($C$3)-1,YEAR($I416)*12+MONTH($I416))-(YEAR($H416)*12+MONTH($H416))+1)) | N416: =IF(OR($J416="",$B416=""),0,IF(YEAR($B416)*12+MONTH($B416)<=YEAR($C$3)*12+MONTH($C$3),$G416,0)) | O416: =IF(OR($J416="",$B416=""),0,IF(YEAR($B416)*12+MONTH($B416)<=YEAR($C$3)*12+MONTH($C$3)-1,$G416,0)) | P416: =$M416-$O416 | Q416: =($L416-$M416)-($N416-$O416) | R416: =$L416-$N416 | S416: ="WIP journal" | T416: =IFERROR(INDEX(tbl_WIP[Revenue or Cost],$A416),"")
A417: =ROW()-407 | B417: =IFERROR(INDEX(tbl_WIP[Month],$A417),"") | C417: =IFERROR(INDEX(tbl_WIP[Xero Invoice No],$A417),"") | D417: =IFERROR(INDEX(tbl_WIP[Client],$A417),"") | E417: =IFERROR(INDEX(tbl_WIP[Job Number],$A417),"") | F417: =IFERROR(INDEX(tbl_WIP[Cost Centre],$A417),"") | G417: =IFERROR(IF(INDEX(tbl_WIP[Defer Start],$A417)="","",IF(INDEX(tbl_WIP[Revenue or Cost],$A417)="Cost",-1,1)*INDEX(tbl_WIP[Amount],$A417)),"") | H417: =IFERROR(INDEX(tbl_WIP[Defer Start],$A417),"") | I417: =IFERROR(INDEX(tbl_WIP[Defer End],$A417),"") | J417: =IF(OR($H417="",$I417="",$G417=""),"",MAX(1,(YEAR($I417)-YEAR($H417))*12+MONTH($I417)-MONTH($H417)+1)) | K417: =IF($J417="","",$G417/$J417) | L417: =IF($J417="",0,$K417*MAX(0,MIN(YEAR($C$3)*12+MONTH($C$3),YEAR($I417)*12+MONTH($I417))-(YEAR($H417)*12+MONTH($H417))+1)) | M417: =IF($J417="",0,$K417*MAX(0,MIN(YEAR($C$3)*12+MONTH($C$3)-1,YEAR($I417)*12+MONTH($I417))-(YEAR($H417)*12+MONTH($H417))+1)) | N417: =IF(OR($J417="",$B417=""),0,IF(YEAR($B417)*12+MONTH($B417)<=YEAR($C$3)*12+MONTH($C$3),$G417,0)) | O417: =IF(OR($J417="",$B417=""),0,IF(YEAR($B417)*12+MONTH($B417)<=YEAR($C$3)*12+MONTH($C$3)-1,$G417,0)) | P417: =$M417-$O417 | Q417: =($L417-$M417)-($N417-$O417) | R417: =$L417-$N417 | S417: ="WIP journal" | T417: =IFERROR(INDEX(tbl_WIP[Revenue or Cost],$A417),"")
A418: =ROW()-407 | B418: =IFERROR(INDEX(tbl_WIP[Month],$A418),"") | C418: =IFERROR(INDEX(tbl_WIP[Xero Invoice No],$A418),"") | D418: =IFERROR(INDEX(tbl_WIP[Client],$A418),"") | E418: =IFERROR(INDEX(tbl_WIP[Job Number],$A418),"") | F418: =IFERROR(INDEX(tbl_WIP[Cost Centre],$A418),"") | G418: =IFERROR(IF(INDEX(tbl_WIP[Defer Start],$A418)="","",IF(INDEX(tbl_WIP[Revenue or Cost],$A418)="Cost",-1,1)*INDEX(tbl_WIP[Amount],$A418)),"") | H418: =IFERROR(INDEX(tbl_WIP[Defer Start],$A418),"") | I418: =IFERROR(INDEX(tbl_WIP[Defer End],$A418),"") | J418: =IF(OR($H418="",$I418="",$G418=""),"",MAX(1,(YEAR($I418)-YEAR($H418))*12+MONTH($I418)-MONTH($H418)+1)) | K418: =IF($J418="","",$G418/$J418) | L418: =IF($J418="",0,$K418*MAX(0,MIN(YEAR($C$3)*12+MONTH($C$3),YEAR($I418)*12+MONTH($I418))-(YEAR($H418)*12+MONTH($H418))+1)) | M418: =IF($J418="",0,$K418*MAX(0,MIN(YEAR($C$3)*12+MONTH($C$3)-1,YEAR($I418)*12+MONTH($I418))-(YEAR($H418)*12+MONTH($H418))+1)) | N418: =IF(OR($J418="",$B418=""),0,IF(YEAR($B418)*12+MONTH($B418)<=YEAR($C$3)*12+MONTH($C$3),$G418,0)) | O418: =IF(OR($J418="",$B418=""),0,IF(YEAR($B418)*12+MONTH($B418)<=YEAR($C$3)*12+MONTH($C$3)-1,$G418,0)) | P418: =$M418-$O418 | Q418: =($L418-$M418)-($N418-$O418) | R418: =$L418-$N418 | S418: ="WIP journal" | T418: =IFERROR(INDEX(tbl_WIP[Revenue or Cost],$A418),"")
A419: =ROW()-407 | B419: =IFERROR(INDEX(tbl_WIP[Month],$A419),"") | C419: =IFERROR(INDEX(tbl_WIP[Xero Invoice No],$A419),"") | D419: =IFERROR(INDEX(tbl_WIP[Client],$A419),"") | E419: =IFERROR(INDEX(tbl_WIP[Job Number],$A419),"") | F419: =IFERROR(INDEX(tbl_WIP[Cost Centre],$A419),"") | G419: =IFERROR(IF(INDEX(tbl_WIP[Defer Start],$A419)="","",IF(INDEX(tbl_WIP[Revenue or Cost],$A419)="Cost",-1,1)*INDEX(tbl_WIP[Amount],$A419)),"") | H419: =IFERROR(INDEX(tbl_WIP[Defer Start],$A419),"") | I419: =IFERROR(INDEX(tbl_WIP[Defer End],$A419),"") | J419: =IF(OR($H419="",$I419="",$G419=""),"",MAX(1,(YEAR($I419)-YEAR($H419))*12+MONTH($I419)-MONTH($H419)+1)) | K419: =IF($J419="","",$G419/$J419) | L419: =IF($J419="",0,$K419*MAX(0,MIN(YEAR($C$3)*12+MONTH($C$3),YEAR($I419)*12+MONTH($I419))-(YEAR($H419)*12+MONTH($H419))+1)) | M419: =IF($J419="",0,$K419*MAX(0,MIN(YEAR($C$3)*12+MONTH($C$3)-1,YEAR($I419)*12+MONTH($I419))-(YEAR($H419)*12+MONTH($H419))+1)) | N419: =IF(OR($J419="",$B419=""),0,IF(YEAR($B419)*12+MONTH($B419)<=YEAR($C$3)*12+MONTH($C$3),$G419,0)) | O419: =IF(OR($J419="",$B419=""),0,IF(YEAR($B419)*12+MONTH($B419)<=YEAR($C$3)*12+MONTH($C$3)-1,$G419,0)) | P419: =$M419-$O419 | Q419: =($L419-$M419)-($N419-$O419) | R419: =$L419-$N419 | S419: ="WIP journal" | T419: =IFERROR(INDEX(tbl_WIP[Revenue or Cost],$A419),"")
... A607: =ROW()-407 | B607: =IFERROR(INDEX(tbl_WIP[Month],$A607),"") | C607: =IFERROR(INDEX(tbl_WIP[Xero Invoice No],$A607),"") | D607: =IFERROR(INDEX(tbl_WIP[Client],$A607),"") | E607: =IFERROR(INDEX(tbl_WIP[Job Number],$A607),"") | F607: =IFERROR(INDEX(tbl_WIP[Cost Centre],$A607),"") | G607: =IFERROR(IF(INDEX(tbl_WIP[Defer Start],$A607)="","",IF(INDEX(tbl_WIP[Revenue or Cost],$A607)="Cost",-1,1)*INDEX(tbl_WIP[Amount],$A607)),"") | H607: =IFERROR(INDEX(tbl_WIP[Defer Start],$A607),"") | I607: =IFERROR(INDEX(tbl_WIP[Defer End],$A607),"") | J607: =IF(OR($H607="",$I607="",$G607=""),"",MAX(1,(YEAR($I607)-YEAR($H607))*12+MONTH($I607)-MONTH($H607)+1)) | K607: =IF($J607="","",$G607/$J607) | L607: =IF($J607="",0,$K607*MAX(0,MIN(YEAR($C$3)*12+MONTH($C$3),YEAR($I607)*12+MONTH($I607))-(YEAR($H607)*12+MONTH($H607))+1)) | M607: =IF($J607="",0,$K607*MAX(0,MIN(YEAR($C$3)*12+MONTH($C$3)-1,YEAR($I607)*12+MONTH($I607))-(YEAR($H607)*12+MONTH($H607))+1)) | N607: =IF(OR($J607="",$B607=""),0,IF(YEAR($B607)*12+MONTH($B607)<=YEAR($C$3)*12+MONTH($C$3),$G607,0)) | O607: =IF(OR($J607="",$B607=""),0,IF(YEAR($B607)*12+MONTH($B607)<=YEAR($C$3)*12+MONTH($C$3)-1,$G607,0)) | P607: =$M607-$O607 | Q607: =($L607-$M607)-($N607-$O607) | R607: =$L607-$N607 | S607: ="WIP journal" | T607: =IFERROR(INDEX(tbl_WIP[Revenue or Cost],$A607),"")

Sheet Onsite
A1: Onsite - Job Detail
A2: Onsite / Support jobs. One row per job number. Client, invoice count and revenue come from the Finance sheet - fill in the columns from PO / Reference onwards.
A3: ="Revenue Ex GST "&TEXT(SUBTOTAL(109,tbl_Onsite[Revenue Ex GST]),"$#,##0.00")
A4: Invoice Date | B4: Invoice No | C4: Job Number | D4: Job in Xero? | E4: Job Name (Xero) | F4: Client | G4: Lines on Job | H4: Revenue Ex GST | I4: Invoiced | J4: To Invoice | K4: Cost Centres | L4: PO / Reference | M4: Qwilr Quote | N4: Open Qwilr | O4: Billable Hours | P4: Approved By | Q4: Notes
A5: =IF(C5="","",IFERROR(IF(SUMPRODUCT(MAX((tbl_Finance[Job Number]=C5&"")*(tbl_Finance[Xero Invoice No]<>"")*tbl_Finance[Date]))=0,"",SUMPRODUCT(MAX((tbl_Finance[Job Number]=C5&"")*(tbl_Finance[Xero Invoice No]<>"")*tbl_Finance[Date]))),"")) | B5: =IF(C5="","",IF(COUNTIFS(tbl_Finance[Job Number],C5&"",tbl_Finance[Xero Invoice No],"<>")=0,"",IFERROR(IF(COUNTIFS(tbl_Finance[Job Number],C5&"",tbl_Finance[Xero Invoice No],LOOKUP(2,1/((tbl_Finance[Job Number]=C5&"")*(tbl_Finance[Xero Invoice No]<>"")),tbl_Finance[Xero Invoice No]))=COUNTIFS(tbl_Finance[Job Number],C5&"",tbl_Finance[Xero Invoice No],"<>"),LOOKUP(2,1/((tbl_Finance[Job Number]=C5&"")*(tbl_Finance[Xero Invoice No]<>"")),tbl_Finance[Xero Invoice No]),LOOKUP(2,1/((tbl_Finance[Job Number]=C5&"")*(tbl_Finance[Xero Invoice No]<>"")),tbl_Finance[Xero Invoice No])&" +more"),""))) | D5: =IF(C5="","",IF(COUNTIF(lst_Jobs,C5&"")>0,"OK","CHECK")) | E5: =IF(C5="","",IFERROR(INDEX(lst_JobName,MATCH(C5&"",lst_Jobs,0)),"")) | F5: =IF(C5="","",IFERROR(INDEX(tbl_Finance[Client],MATCH(C5&"",tbl_Finance[Job Number],0)),"")) | G5: =IF(C5="","",COUNTIFS(tbl_Finance[Job Number],C5&"",tbl_Finance[Ex GST],"<>")) | H5: =IF(C5="","",SUMIFS(tbl_Finance[Ex GST],tbl_Finance[Job Number],C5&"")) | I5: =IF(C5="","",SUMIFS(tbl_Finance[Ex GST],tbl_Finance[Job Number],C5&"",tbl_Finance[Xero Invoice No],"<>")) | J5: =IF(C5="","",H5-I5) | K5: =IF(C5="","",IF(G5=0,"not invoiced yet",SUBSTITUTE(TRIM(IF(COUNTIFS(tbl_Finance[Job Number],C5&"",tbl_Finance[Cost Centre],"ONSITE")>0,"ONSITE ","")&IF(COUNTIFS(tbl_Finance[Job Number],C5&"",tbl_Finance[Cost Centre],"PRODUCTION")>0,"PRODUCTION ","")&IF(COUNTIFS(tbl_Finance[Job Number],C5&"",tbl_Finance[Cost Centre],"VIDEO")>0,"VIDEO ","")&IF(COUNTIFS(tbl_Finance[Job Number],C5&"",tbl_Finance[Cost Centre],"INTEGRATION")>0,"INTEGRATION ","")&IF(COUNTIFS(tbl_Finance[Job Number],C5&"",tbl_Finance[Cost Centre],"CONSULTING")>0,"CONSULTING ","")&IF(COUNTIFS(tbl_Finance[Job Number],C5&"",tbl_Finance[Cost Centre],"CTS")>0,"CTS ",""))," ",", "))) | N5: =IF(M5="","",HYPERLINK(IF(LEFT(M5,4)="http",M5,set_QwilrBase&M5),"Open quote"))
A6: =IF(C6="","",IFERROR(IF(SUMPRODUCT(MAX((tbl_Finance[Job Number]=C6&"")*(tbl_Finance[Xero Invoice No]<>"")*tbl_Finance[Date]))=0,"",SUMPRODUCT(MAX((tbl_Finance[Job Number]=C6&"")*(tbl_Finance[Xero Invoice No]<>"")*tbl_Finance[Date]))),"")) | B6: =IF(C6="","",IF(COUNTIFS(tbl_Finance[Job Number],C6&"",tbl_Finance[Xero Invoice No],"<>")=0,"",IFERROR(IF(COUNTIFS(tbl_Finance[Job Number],C6&"",tbl_Finance[Xero Invoice No],LOOKUP(2,1/((tbl_Finance[Job Number]=C6&"")*(tbl_Finance[Xero Invoice No]<>"")),tbl_Finance[Xero Invoice No]))=COUNTIFS(tbl_Finance[Job Number],C6&"",tbl_Finance[Xero Invoice No],"<>"),LOOKUP(2,1/((tbl_Finance[Job Number]=C6&"")*(tbl_Finance[Xero Invoice No]<>"")),tbl_Finance[Xero Invoice No]),LOOKUP(2,1/((tbl_Finance[Job Number]=C6&"")*(tbl_Finance[Xero Invoice No]<>"")),tbl_Finance[Xero Invoice No])&" +more"),""))) | D6: =IF(C6="","",IF(COUNTIF(lst_Jobs,C6&"")>0,"OK","CHECK")) | E6: =IF(C6="","",IFERROR(INDEX(lst_JobName,MATCH(C6&"",lst_Jobs,0)),"")) | F6: =IF(C6="","",IFERROR(INDEX(tbl_Finance[Client],MATCH(C6&"",tbl_Finance[Job Number],0)),"")) | G6: =IF(C6="","",COUNTIFS(tbl_Finance[Job Number],C6&"",tbl_Finance[Ex GST],"<>")) | H6: =IF(C6="","",SUMIFS(tbl_Finance[Ex GST],tbl_Finance[Job Number],C6&"")) | I6: =IF(C6="","",SUMIFS(tbl_Finance[Ex GST],tbl_Finance[Job Number],C6&"",tbl_Finance[Xero Invoice No],"<>")) | J6: =IF(C6="","",H6-I6) | K6: =IF(C6="","",IF(G6=0,"not invoiced yet",SUBSTITUTE(TRIM(IF(COUNTIFS(tbl_Finance[Job Number],C6&"",tbl_Finance[Cost Centre],"ONSITE")>0,"ONSITE ","")&IF(COUNTIFS(tbl_Finance[Job Number],C6&"",tbl_Finance[Cost Centre],"PRODUCTION")>0,"PRODUCTION ","")&IF(COUNTIFS(tbl_Finance[Job Number],C6&"",tbl_Finance[Cost Centre],"VIDEO")>0,"VIDEO ","")&IF(COUNTIFS(tbl_Finance[Job Number],C6&"",tbl_Finance[Cost Centre],"INTEGRATION")>0,"INTEGRATION ","")&IF(COUNTIFS(tbl_Finance[Job Number],C6&"",tbl_Finance[Cost Centre],"CONSULTING")>0,"CONSULTING ","")&IF(COUNTIFS(tbl_Finance[Job Number],C6&"",tbl_Finance[Cost Centre],"CTS")>0,"CTS ",""))," ",", "))) | N6: =IF(M6="","",HYPERLINK(IF(LEFT(M6,4)="http",M6,set_QwilrBase&M6),"Open quote"))
A7: =IF(C7="","",IFERROR(IF(SUMPRODUCT(MAX((tbl_Finance[Job Number]=C7&"")*(tbl_Finance[Xero Invoice No]<>"")*tbl_Finance[Date]))=0,"",SUMPRODUCT(MAX((tbl_Finance[Job Number]=C7&"")*(tbl_Finance[Xero Invoice No]<>"")*tbl_Finance[Date]))),"")) | B7: =IF(C7="","",IF(COUNTIFS(tbl_Finance[Job Number],C7&"",tbl_Finance[Xero Invoice No],"<>")=0,"",IFERROR(IF(COUNTIFS(tbl_Finance[Job Number],C7&"",tbl_Finance[Xero Invoice No],LOOKUP(2,1/((tbl_Finance[Job Number]=C7&"")*(tbl_Finance[Xero Invoice No]<>"")),tbl_Finance[Xero Invoice No]))=COUNTIFS(tbl_Finance[Job Number],C7&"",tbl_Finance[Xero Invoice No],"<>"),LOOKUP(2,1/((tbl_Finance[Job Number]=C7&"")*(tbl_Finance[Xero Invoice No]<>"")),tbl_Finance[Xero Invoice No]),LOOKUP(2,1/((tbl_Finance[Job Number]=C7&"")*(tbl_Finance[Xero Invoice No]<>"")),tbl_Finance[Xero Invoice No])&" +more"),""))) | D7: =IF(C7="","",IF(COUNTIF(lst_Jobs,C7&"")>0,"OK","CHECK")) | E7: =IF(C7="","",IFERROR(INDEX(lst_JobName,MATCH(C7&"",lst_Jobs,0)),"")) | F7: =IF(C7="","",IFERROR(INDEX(tbl_Finance[Client],MATCH(C7&"",tbl_Finance[Job Number],0)),"")) | G7: =IF(C7="","",COUNTIFS(tbl_Finance[Job Number],C7&"",tbl_Finance[Ex GST],"<>")) | H7: =IF(C7="","",SUMIFS(tbl_Finance[Ex GST],tbl_Finance[Job Number],C7&"")) | I7: =IF(C7="","",SUMIFS(tbl_Finance[Ex GST],tbl_Finance[Job Number],C7&"",tbl_Finance[Xero Invoice No],"<>")) | J7: =IF(C7="","",H7-I7) | K7: =IF(C7="","",IF(G7=0,"not invoiced yet",SUBSTITUTE(TRIM(IF(COUNTIFS(tbl_Finance[Job Number],C7&"",tbl_Finance[Cost Centre],"ONSITE")>0,"ONSITE ","")&IF(COUNTIFS(tbl_Finance[Job Number],C7&"",tbl_Finance[Cost Centre],"PRODUCTION")>0,"PRODUCTION ","")&IF(COUNTIFS(tbl_Finance[Job Number],C7&"",tbl_Finance[Cost Centre],"VIDEO")>0,"VIDEO ","")&IF(COUNTIFS(tbl_Finance[Job Number],C7&"",tbl_Finance[Cost Centre],"INTEGRATION")>0,"INTEGRATION ","")&IF(COUNTIFS(tbl_Finance[Job Number],C7&"",tbl_Finance[Cost Centre],"CONSULTING")>0,"CONSULTING ","")&IF(COUNTIFS(tbl_Finance[Job Number],C7&"",tbl_Finance[Cost Centre],"CTS")>0,"CTS ",""))," ",", "))) | N7: =IF(M7="","",HYPERLINK(IF(LEFT(M7,4)="http",M7,set_QwilrBase&M7),"Open quote"))
A8: =IF(C8="","",IFERROR(IF(SUMPRODUCT(MAX((tbl_Finance[Job Number]=C8&"")*(tbl_Finance[Xero Invoice No]<>"")*tbl_Finance[Date]))=0,"",SUMPRODUCT(MAX((tbl_Finance[Job Number]=C8&"")*(tbl_Finance[Xero Invoice No]<>"")*tbl_Finance[Date]))),"")) | B8: =IF(C8="","",IF(COUNTIFS(tbl_Finance[Job Number],C8&"",tbl_Finance[Xero Invoice No],"<>")=0,"",IFERROR(IF(COUNTIFS(tbl_Finance[Job Number],C8&"",tbl_Finance[Xero Invoice No],LOOKUP(2,1/((tbl_Finance[Job Number]=C8&"")*(tbl_Finance[Xero Invoice No]<>"")),tbl_Finance[Xero Invoice No]))=COUNTIFS(tbl_Finance[Job Number],C8&"",tbl_Finance[Xero Invoice No],"<>"),LOOKUP(2,1/((tbl_Finance[Job Number]=C8&"")*(tbl_Finance[Xero Invoice No]<>"")),tbl_Finance[Xero Invoice No]),LOOKUP(2,1/((tbl_Finance[Job Number]=C8&"")*(tbl_Finance[Xero Invoice No]<>"")),tbl_Finance[Xero Invoice No])&" +more"),""))) | D8: =IF(C8="","",IF(COUNTIF(lst_Jobs,C8&"")>0,"OK","CHECK")) | E8: =IF(C8="","",IFERROR(INDEX(lst_JobName,MATCH(C8&"",lst_Jobs,0)),"")) | F8: =IF(C8="","",IFERROR(INDEX(tbl_Finance[Client],MATCH(C8&"",tbl_Finance[Job Number],0)),"")) | G8: =IF(C8="","",COUNTIFS(tbl_Finance[Job Number],C8&"",tbl_Finance[Ex GST],"<>")) | H8: =IF(C8="","",SUMIFS(tbl_Finance[Ex GST],tbl_Finance[Job Number],C8&"")) | I8: =IF(C8="","",SUMIFS(tbl_Finance[Ex GST],tbl_Finance[Job Number],C8&"",tbl_Finance[Xero Invoice No],"<>")) | J8: =IF(C8="","",H8-I8) | K8: =IF(C8="","",IF(G8=0,"not invoiced yet",SUBSTITUTE(TRIM(IF(COUNTIFS(tbl_Finance[Job Number],C8&"",tbl_Finance[Cost Centre],"ONSITE")>0,"ONSITE ","")&IF(COUNTIFS(tbl_Finance[Job Number],C8&"",tbl_Finance[Cost Centre],"PRODUCTION")>0,"PRODUCTION ","")&IF(COUNTIFS(tbl_Finance[Job Number],C8&"",tbl_Finance[Cost Centre],"VIDEO")>0,"VIDEO ","")&IF(COUNTIFS(tbl_Finance[Job Number],C8&"",tbl_Finance[Cost Centre],"INTEGRATION")>0,"INTEGRATION ","")&IF(COUNTIFS(tbl_Finance[Job Number],C8&"",tbl_Finance[Cost Centre],"CONSULTING")>0,"CONSULTING ","")&IF(COUNTIFS(tbl_Finance[Job Number],C8&"",tbl_Finance[Cost Centre],"CTS")>0,"CTS ",""))," ",", "))) | N8: =IF(M8="","",HYPERLINK(IF(LEFT(M8,4)="http",M8,set_QwilrBase&M8),"Open quote"))
A9: =IF(C9="","",IFERROR(IF(SUMPRODUCT(MAX((tbl_Finance[Job Number]=C9&"")*(tbl_Finance[Xero Invoice No]<>"")*tbl_Finance[Date]))=0,"",SUMPRODUCT(MAX((tbl_Finance[Job Number]=C9&"")*(tbl_Finance[Xero Invoice No]<>"")*tbl_Finance[Date]))),"")) | B9: =IF(C9="","",IF(COUNTIFS(tbl_Finance[Job Number],C9&"",tbl_Finance[Xero Invoice No],"<>")=0,"",IFERROR(IF(COUNTIFS(tbl_Finance[Job Number],C9&"",tbl_Finance[Xero Invoice No],LOOKUP(2,1/((tbl_Finance[Job Number]=C9&"")*(tbl_Finance[Xero Invoice No]<>"")),tbl_Finance[Xero Invoice No]))=COUNTIFS(tbl_Finance[Job Number],C9&"",tbl_Finance[Xero Invoice No],"<>"),LOOKUP(2,1/((tbl_Finance[Job Number]=C9&"")*(tbl_Finance[Xero Invoice No]<>"")),tbl_Finance[Xero Invoice No]),LOOKUP(2,1/((tbl_Finance[Job Number]=C9&"")*(tbl_Finance[Xero Invoice No]<>"")),tbl_Finance[Xero Invoice No])&" +more"),""))) | D9: =IF(C9="","",IF(COUNTIF(lst_Jobs,C9&"")>0,"OK","CHECK")) | E9: =IF(C9="","",IFERROR(INDEX(lst_JobName,MATCH(C9&"",lst_Jobs,0)),"")) | F9: =IF(C9="","",IFERROR(INDEX(tbl_Finance[Client],MATCH(C9&"",tbl_Finance[Job Number],0)),"")) | G9: =IF(C9="","",COUNTIFS(tbl_Finance[Job Number],C9&"",tbl_Finance[Ex GST],"<>")) | H9: =IF(C9="","",SUMIFS(tbl_Finance[Ex GST],tbl_Finance[Job Number],C9&"")) | I9: =IF(C9="","",SUMIFS(tbl_Finance[Ex GST],tbl_Finance[Job Number],C9&"",tbl_Finance[Xero Invoice No],"<>")) | J9: =IF(C9="","",H9-I9) | K9: =IF(C9="","",IF(G9=0,"not invoiced yet",SUBSTITUTE(TRIM(IF(COUNTIFS(tbl_Finance[Job Number],C9&"",tbl_Finance[Cost Centre],"ONSITE")>0,"ONSITE ","")&IF(COUNTIFS(tbl_Finance[Job Number],C9&"",tbl_Finance[Cost Centre],"PRODUCTION")>0,"PRODUCTION ","")&IF(COUNTIFS(tbl_Finance[Job Number],C9&"",tbl_Finance[Cost Centre],"VIDEO")>0,"VIDEO ","")&IF(COUNTIFS(tbl_Finance[Job Number],C9&"",tbl_Finance[Cost Centre],"INTEGRATION")>0,"INTEGRATION ","")&IF(COUNTIFS(tbl_Finance[Job Number],C9&"",tbl_Finance[Cost Centre],"CONSULTING")>0,"CONSULTING ","")&IF(COUNTIFS(tbl_Finance[Job Number],C9&"",tbl_Finance[Cost Centre],"CTS")>0,"CTS ",""))," ",", "))) | N9: =IF(M9="","",HYPERLINK(IF(LEFT(M9,4)="http",M9,set_QwilrBase&M9),"Open quote"))
A10: =IF(C10="","",IFERROR(IF(SUMPRODUCT(MAX((tbl_Finance[Job Number]=C10&"")*(tbl_Finance[Xero Invoice No]<>"")*tbl_Finance[Date]))=0,"",SUMPRODUCT(MAX((tbl_Finance[Job Number]=C10&"")*(tbl_Finance[Xero Invoice No]<>"")*tbl_Finance[Date]))),"")) | B10: =IF(C10="","",IF(COUNTIFS(tbl_Finance[Job Number],C10&"",tbl_Finance[Xero Invoice No],"<>")=0,"",IFERROR(IF(COUNTIFS(tbl_Finance[Job Number],C10&"",tbl_Finance[Xero Invoice No],LOOKUP(2,1/((tbl_Finance[Job Number]=C10&"")*(tbl_Finance[Xero Invoice No]<>"")),tbl_Finance[Xero Invoice No]))=COUNTIFS(tbl_Finance[Job Number],C10&"",tbl_Finance[Xero Invoice No],"<>"),LOOKUP(2,1/((tbl_Finance[Job Number]=C10&"")*(tbl_Finance[Xero Invoice No]<>"")),tbl_Finance[Xero Invoice No]),LOOKUP(2,1/((tbl_Finance[Job Number]=C10&"")*(tbl_Finance[Xero Invoice No]<>"")),tbl_Finance[Xero Invoice No])&" +more"),""))) | D10: =IF(C10="","",IF(COUNTIF(lst_Jobs,C10&"")>0,"OK","CHECK")) | E10: =IF(C10="","",IFERROR(INDEX(lst_JobName,MATCH(C10&"",lst_Jobs,0)),"")) | F10: =IF(C10="","",IFERROR(INDEX(tbl_Finance[Client],MATCH(C10&"",tbl_Finance[Job Number],0)),"")) | G10: =IF(C10="","",COUNTIFS(tbl_Finance[Job Number],C10&"",tbl_Finance[Ex GST],"<>")) | H10: =IF(C10="","",SUMIFS(tbl_Finance[Ex GST],tbl_Finance[Job Number],C10&"")) | I10: =IF(C10="","",SUMIFS(tbl_Finance[Ex GST],tbl_Finance[Job Number],C10&"",tbl_Finance[Xero Invoice No],"<>")) | J10: =IF(C10="","",H10-I10) | K10: =IF(C10="","",IF(G10=0,"not invoiced yet",SUBSTITUTE(TRIM(IF(COUNTIFS(tbl_Finance[Job Number],C10&"",tbl_Finance[Cost Centre],"ONSITE")>0,"ONSITE ","")&IF(COUNTIFS(tbl_Finance[Job Number],C10&"",tbl_Finance[Cost Centre],"PRODUCTION")>0,"PRODUCTION ","")&IF(COUNTIFS(tbl_Finance[Job Number],C10&"",tbl_Finance[Cost Centre],"VIDEO")>0,"VIDEO ","")&IF(COUNTIFS(tbl_Finance[Job Number],C10&"",tbl_Finance[Cost Centre],"INTEGRATION")>0,"INTEGRATION ","")&IF(COUNTIFS(tbl_Finance[Job Number],C10&"",tbl_Finance[Cost Centre],"CONSULTING")>0,"CONSULTING ","")&IF(COUNTIFS(tbl_Finance[Job Number],C10&"",tbl_Finance[Cost Centre],"CTS")>0,"CTS ",""))," ",", "))) | N10: =IF(M10="","",HYPERLINK(IF(LEFT(M10,4)="http",M10,set_QwilrBase&M10),"Open quote"))
A11: =IF(C11="","",IFERROR(IF(SUMPRODUCT(MAX((tbl_Finance[Job Number]=C11&"")*(tbl_Finance[Xero Invoice No]<>"")*tbl_Finance[Date]))=0,"",SUMPRODUCT(MAX((tbl_Finance[Job Number]=C11&"")*(tbl_Finance[Xero Invoice No]<>"")*tbl_Finance[Date]))),"")) | B11: =IF(C11="","",IF(COUNTIFS(tbl_Finance[Job Number],C11&"",tbl_Finance[Xero Invoice No],"<>")=0,"",IFERROR(IF(COUNTIFS(tbl_Finance[Job Number],C11&"",tbl_Finance[Xero Invoice No],LOOKUP(2,1/((tbl_Finance[Job Number]=C11&"")*(tbl_Finance[Xero Invoice No]<>"")),tbl_Finance[Xero Invoice No]))=COUNTIFS(tbl_Finance[Job Number],C11&"",tbl_Finance[Xero Invoice No],"<>"),LOOKUP(2,1/((tbl_Finance[Job Number]=C11&"")*(tbl_Finance[Xero Invoice No]<>"")),tbl_Finance[Xero Invoice No]),LOOKUP(2,1/((tbl_Finance[Job Number]=C11&"")*(tbl_Finance[Xero Invoice No]<>"")),tbl_Finance[Xero Invoice No])&" +more"),""))) | D11: =IF(C11="","",IF(COUNTIF(lst_Jobs,C11&"")>0,"OK","CHECK")) | E11: =IF(C11="","",IFERROR(INDEX(lst_JobName,MATCH(C11&"",lst_Jobs,0)),"")) | F11: =IF(C11="","",IFERROR(INDEX(tbl_Finance[Client],MATCH(C11&"",tbl_Finance[Job Number],0)),"")) | G11: =IF(C11="","",COUNTIFS(tbl_Finance[Job Number],C11&"",tbl_Finance[Ex GST],"<>")) | H11: =IF(C11="","",SUMIFS(tbl_Finance[Ex GST],tbl_Finance[Job Number],C11&"")) | I11: =IF(C11="","",SUMIFS(tbl_Finance[Ex GST],tbl_Finance[Job Number],C11&"",tbl_Finance[Xero Invoice No],"<>")) | J11: =IF(C11="","",H11-I11) | K11: =IF(C11="","",IF(G11=0,"not invoiced yet",SUBSTITUTE(TRIM(IF(COUNTIFS(tbl_Finance[Job Number],C11&"",tbl_Finance[Cost Centre],"ONSITE")>0,"ONSITE ","")&IF(COUNTIFS(tbl_Finance[Job Number],C11&"",tbl_Finance[Cost Centre],"PRODUCTION")>0,"PRODUCTION ","")&IF(COUNTIFS(tbl_Finance[Job Number],C11&"",tbl_Finance[Cost Centre],"VIDEO")>0,"VIDEO ","")&IF(COUNTIFS(tbl_Finance[Job Number],C11&"",tbl_Finance[Cost Centre],"INTEGRATION")>0,"INTEGRATION ","")&IF(COUNTIFS(tbl_Finance[Job Number],C11&"",tbl_Finance[Cost Centre],"CONSULTING")>0,"CONSULTING ","")&IF(COUNTIFS(tbl_Finance[Job Number],C11&"",tbl_Finance[Cost Centre],"CTS")>0,"CTS ",""))," ",", "))) | N11: =IF(M11="","",HYPERLINK(IF(LEFT(M11,4)="http",M11,set_QwilrBase&M11),"Open quote"))
A12: =IF(C12="","",IFERROR(IF(SUMPRODUCT(MAX((tbl_Finance[Job Number]=C12&"")*(tbl_Finance[Xero Invoice No]<>"")*tbl_Finance[Date]))=0,"",SUMPRODUCT(MAX((tbl_Finance[Job Number]=C12&"")*(tbl_Finance[Xero Invoice No]<>"")*tbl_Finance[Date]))),"")) | B12: =IF(C12="","",IF(COUNTIFS(tbl_Finance[Job Number],C12&"",tbl_Finance[Xero Invoice No],"<>")=0,"",IFERROR(IF(COUNTIFS(tbl_Finance[Job Number],C12&"",tbl_Finance[Xero Invoice No],LOOKUP(2,1/((tbl_Finance[Job Number]=C12&"")*(tbl_Finance[Xero Invoice No]<>"")),tbl_Finance[Xero Invoice No]))=COUNTIFS(tbl_Finance[Job Number],C12&"",tbl_Finance[Xero Invoice No],"<>"),LOOKUP(2,1/((tbl_Finance[Job Number]=C12&"")*(tbl_Finance[Xero Invoice No]<>"")),tbl_Finance[Xero Invoice No]),LOOKUP(2,1/((tbl_Finance[Job Number]=C12&"")*(tbl_Finance[Xero Invoice No]<>"")),tbl_Finance[Xero Invoice No])&" +more"),""))) | D12: =IF(C12="","",IF(COUNTIF(lst_Jobs,C12&"")>0,"OK","CHECK")) | E12: =IF(C12="","",IFERROR(INDEX(lst_JobName,MATCH(C12&"",lst_Jobs,0)),"")) | F12: =IF(C12="","",IFERROR(INDEX(tbl_Finance[Client],MATCH(C12&"",tbl_Finance[Job Number],0)),"")) | G12: =IF(C12="","",COUNTIFS(tbl_Finance[Job Number],C12&"",tbl_Finance[Ex GST],"<>")) | H12: =IF(C12="","",SUMIFS(tbl_Finance[Ex GST],tbl_Finance[Job Number],C12&"")) | I12: =IF(C12="","",SUMIFS(tbl_Finance[Ex GST],tbl_Finance[Job Number],C12&"",tbl_Finance[Xero Invoice No],"<>")) | J12: =IF(C12="","",H12-I12) | K12: =IF(C12="","",IF(G12=0,"not invoiced yet",SUBSTITUTE(TRIM(IF(COUNTIFS(tbl_Finance[Job Number],C12&"",tbl_Finance[Cost Centre],"ONSITE")>0,"ONSITE ","")&IF(COUNTIFS(tbl_Finance[Job Number],C12&"",tbl_Finance[Cost Centre],"PRODUCTION")>0,"PRODUCTION ","")&IF(COUNTIFS(tbl_Finance[Job Number],C12&"",tbl_Finance[Cost Centre],"VIDEO")>0,"VIDEO ","")&IF(COUNTIFS(tbl_Finance[Job Number],C12&"",tbl_Finance[Cost Centre],"INTEGRATION")>0,"INTEGRATION ","")&IF(COUNTIFS(tbl_Finance[Job Number],C12&"",tbl_Finance[Cost Centre],"CONSULTING")>0,"CONSULTING ","")&IF(COUNTIFS(tbl_Finance[Job Number],C12&"",tbl_Finance[Cost Centre],"CTS")>0,"CTS ",""))," ",", "))) | N12: =IF(M12="","",HYPERLINK(IF(LEFT(M12,4)="http",M12,set_QwilrBase&M12),"Open quote"))
A13: =IF(C13="","",IFERROR(IF(SUMPRODUCT(MAX((tbl_Finance[Job Number]=C13&"")*(tbl_Finance[Xero Invoice No]<>"")*tbl_Finance[Date]))=0,"",SUMPRODUCT(MAX((tbl_Finance[Job Number]=C13&"")*(tbl_Finance[Xero Invoice No]<>"")*tbl_Finance[Date]))),"")) | B13: =IF(C13="","",IF(COUNTIFS(tbl_Finance[Job Number],C13&"",tbl_Finance[Xero Invoice No],"<>")=0,"",IFERROR(IF(COUNTIFS(tbl_Finance[Job Number],C13&"",tbl_Finance[Xero Invoice No],LOOKUP(2,1/((tbl_Finance[Job Number]=C13&"")*(tbl_Finance[Xero Invoice No]<>"")),tbl_Finance[Xero Invoice No]))=COUNTIFS(tbl_Finance[Job Number],C13&"",tbl_Finance[Xero Invoice No],"<>"),LOOKUP(2,1/((tbl_Finance[Job Number]=C13&"")*(tbl_Finance[Xero Invoice No]<>"")),tbl_Finance[Xero Invoice No]),LOOKUP(2,1/((tbl_Finance[Job Number]=C13&"")*(tbl_Finance[Xero Invoice No]<>"")),tbl_Finance[Xero Invoice No])&" +more"),""))) | D13: =IF(C13="","",IF(COUNTIF(lst_Jobs,C13&"")>0,"OK","CHECK")) | E13: =IF(C13="","",IFERROR(INDEX(lst_JobName,MATCH(C13&"",lst_Jobs,0)),"")) | F13: =IF(C13="","",IFERROR(INDEX(tbl_Finance[Client],MATCH(C13&"",tbl_Finance[Job Number],0)),"")) | G13: =IF(C13="","",COUNTIFS(tbl_Finance[Job Number],C13&"",tbl_Finance[Ex GST],"<>")) | H13: =IF(C13="","",SUMIFS(tbl_Finance[Ex GST],tbl_Finance[Job Number],C13&"")) | I13: =IF(C13="","",SUMIFS(tbl_Finance[Ex GST],tbl_Finance[Job Number],C13&"",tbl_Finance[Xero Invoice No],"<>")) | J13: =IF(C13="","",H13-I13) | K13: =IF(C13="","",IF(G13=0,"not invoiced yet",SUBSTITUTE(TRIM(IF(COUNTIFS(tbl_Finance[Job Number],C13&"",tbl_Finance[Cost Centre],"ONSITE")>0,"ONSITE ","")&IF(COUNTIFS(tbl_Finance[Job Number],C13&"",tbl_Finance[Cost Centre],"PRODUCTION")>0,"PRODUCTION ","")&IF(COUNTIFS(tbl_Finance[Job Number],C13&"",tbl_Finance[Cost Centre],"VIDEO")>0,"VIDEO ","")&IF(COUNTIFS(tbl_Finance[Job Number],C13&"",tbl_Finance[Cost Centre],"INTEGRATION")>0,"INTEGRATION ","")&IF(COUNTIFS(tbl_Finance[Job Number],C13&"",tbl_Finance[Cost Centre],"CONSULTING")>0,"CONSULTING ","")&IF(COUNTIFS(tbl_Finance[Job Number],C13&"",tbl_Finance[Cost Centre],"CTS")>0,"CTS ",""))," ",", "))) | N13: =IF(M13="","",HYPERLINK(IF(LEFT(M13,4)="http",M13,set_QwilrBase&M13),"Open quote"))
A14: =IF(C14="","",IFERROR(IF(SUMPRODUCT(MAX((tbl_Finance[Job Number]=C14&"")*(tbl_Finance[Xero Invoice No]<>"")*tbl_Finance[Date]))=0,"",SUMPRODUCT(MAX((tbl_Finance[Job Number]=C14&"")*(tbl_Finance[Xero Invoice No]<>"")*tbl_Finance[Date]))),"")) | B14: =IF(C14="","",IF(COUNTIFS(tbl_Finance[Job Number],C14&"",tbl_Finance[Xero Invoice No],"<>")=0,"",IFERROR(IF(COUNTIFS(tbl_Finance[Job Number],C14&"",tbl_Finance[Xero Invoice No],LOOKUP(2,1/((tbl_Finance[Job Number]=C14&"")*(tbl_Finance[Xero Invoice No]<>"")),tbl_Finance[Xero Invoice No]))=COUNTIFS(tbl_Finance[Job Number],C14&"",tbl_Finance[Xero Invoice No],"<>"),LOOKUP(2,1/((tbl_Finance[Job Number]=C14&"")*(tbl_Finance[Xero Invoice No]<>"")),tbl_Finance[Xero Invoice No]),LOOKUP(2,1/((tbl_Finance[Job Number]=C14&"")*(tbl_Finance[Xero Invoice No]<>"")),tbl_Finance[Xero Invoice No])&" +more"),""))) | D14: =IF(C14="","",IF(COUNTIF(lst_Jobs,C14&"")>0,"OK","CHECK")) | E14: =IF(C14="","",IFERROR(INDEX(lst_JobName,MATCH(C14&"",lst_Jobs,0)),"")) | F14: =IF(C14="","",IFERROR(INDEX(tbl_Finance[Client],MATCH(C14&"",tbl_Finance[Job Number],0)),"")) | G14: =IF(C14="","",COUNTIFS(tbl_Finance[Job Number],C14&"",tbl_Finance[Ex GST],"<>")) | H14: =IF(C14="","",SUMIFS(tbl_Finance[Ex GST],tbl_Finance[Job Number],C14&"")) | I14: =IF(C14="","",SUMIFS(tbl_Finance[Ex GST],tbl_Finance[Job Number],C14&"",tbl_Finance[Xero Invoice No],"<>")) | J14: =IF(C14="","",H14-I14) | K14: =IF(C14="","",IF(G14=0,"not invoiced yet",SUBSTITUTE(TRIM(IF(COUNTIFS(tbl_Finance[Job Number],C14&"",tbl_Finance[Cost Centre],"ONSITE")>0,"ONSITE ","")&IF(COUNTIFS(tbl_Finance[Job Number],C14&"",tbl_Finance[Cost Centre],"PRODUCTION")>0,"PRODUCTION ","")&IF(COUNTIFS(tbl_Finance[Job Number],C14&"",tbl_Finance[Cost Centre],"VIDEO")>0,"VIDEO ","")&IF(COUNTIFS(tbl_Finance[Job Number],C14&"",tbl_Finance[Cost Centre],"INTEGRATION")>0,"INTEGRATION ","")&IF(COUNTIFS(tbl_Finance[Job Number],C14&"",tbl_Finance[Cost Centre],"CONSULTING")>0,"CONSULTING ","")&IF(COUNTIFS(tbl_Finance[Job Number],C14&"",tbl_Finance[Cost Centre],"CTS")>0,"CTS ",""))," ",", "))) | N14: =IF(M14="","",HYPERLINK(IF(LEFT(M14,4)="http",M14,set_QwilrBase&M14),"Open quote"))
A15: =IF(C15="","",IFERROR(IF(SUMPRODUCT(MAX((tbl_Finance[Job Number]=C15&"")*(tbl_Finance[Xero Invoice No]<>"")*tbl_Finance[Date]))=0,"",SUMPRODUCT(MAX((tbl_Finance[Job Number]=C15&"")*(tbl_Finance[Xero Invoice No]<>"")*tbl_Finance[Date]))),"")) | B15: =IF(C15="","",IF(COUNTIFS(tbl_Finance[Job Number],C15&"",tbl_Finance[Xero Invoice No],"<>")=0,"",IFERROR(IF(COUNTIFS(tbl_Finance[Job Number],C15&"",tbl_Finance[Xero Invoice No],LOOKUP(2,1/((tbl_Finance[Job Number]=C15&"")*(tbl_Finance[Xero Invoice No]<>"")),tbl_Finance[Xero Invoice No]))=COUNTIFS(tbl_Finance[Job Number],C15&"",tbl_Finance[Xero Invoice No],"<>"),LOOKUP(2,1/((tbl_Finance[Job Number]=C15&"")*(tbl_Finance[Xero Invoice No]<>"")),tbl_Finance[Xero Invoice No]),LOOKUP(2,1/((tbl_Finance[Job Number]=C15&"")*(tbl_Finance[Xero Invoice No]<>"")),tbl_Finance[Xero Invoice No])&" +more"),""))) | D15: =IF(C15="","",IF(COUNTIF(lst_Jobs,C15&"")>0,"OK","CHECK")) | E15: =IF(C15="","",IFERROR(INDEX(lst_JobName,MATCH(C15&"",lst_Jobs,0)),"")) | F15: =IF(C15="","",IFERROR(INDEX(tbl_Finance[Client],MATCH(C15&"",tbl_Finance[Job Number],0)),"")) | G15: =IF(C15="","",COUNTIFS(tbl_Finance[Job Number],C15&"",tbl_Finance[Ex GST],"<>")) | H15: =IF(C15="","",SUMIFS(tbl_Finance[Ex GST],tbl_Finance[Job Number],C15&"")) | I15: =IF(C15="","",SUMIFS(tbl_Finance[Ex GST],tbl_Finance[Job Number],C15&"",tbl_Finance[Xero Invoice No],"<>")) | J15: =IF(C15="","",H15-I15) | K15: =IF(C15="","",IF(G15=0,"not invoiced yet",SUBSTITUTE(TRIM(IF(COUNTIFS(tbl_Finance[Job Number],C15&"",tbl_Finance[Cost Centre],"ONSITE")>0,"ONSITE ","")&IF(COUNTIFS(tbl_Finance[Job Number],C15&"",tbl_Finance[Cost Centre],"PRODUCTION")>0,"PRODUCTION ","")&IF(COUNTIFS(tbl_Finance[Job Number],C15&"",tbl_Finance[Cost Centre],"VIDEO")>0,"VIDEO ","")&IF(COUNTIFS(tbl_Finance[Job Number],C15&"",tbl_Finance[Cost Centre],"INTEGRATION")>0,"INTEGRATION ","")&IF(COUNTIFS(tbl_Finance[Job Number],C15&"",tbl_Finance[Cost Centre],"CONSULTING")>0,"CONSULTING ","")&IF(COUNTIFS(tbl_Finance[Job Number],C15&"",tbl_Finance[Cost Centre],"CTS")>0,"CTS ",""))," ",", "))) | N15: =IF(M15="","",HYPERLINK(IF(LEFT(M15,4)="http",M15,set_QwilrBase&M15),"Open quote"))
A16: =IF(C16="","",IFERROR(IF(SUMPRODUCT(MAX((tbl_Finance[Job Number]=C16&"")*(tbl_Finance[Xero Invoice No]<>"")*tbl_Finance[Date]))=0,"",SUMPRODUCT(MAX((tbl_Finance[Job Number]=C16&"")*(tbl_Finance[Xero Invoice No]<>"")*tbl_Finance[Date]))),"")) | B16: =IF(C16="","",IF(COUNTIFS(tbl_Finance[Job Number],C16&"",tbl_Finance[Xero Invoice No],"<>")=0,"",IFERROR(IF(COUNTIFS(tbl_Finance[Job Number],C16&"",tbl_Finance[Xero Invoice No],LOOKUP(2,1/((tbl_Finance[Job Number]=C16&"")*(tbl_Finance[Xero Invoice No]<>"")),tbl_Finance[Xero Invoice No]))=COUNTIFS(tbl_Finance[Job Number],C16&"",tbl_Finance[Xero Invoice No],"<>"),LOOKUP(2,1/((tbl_Finance[Job Number]=C16&"")*(tbl_Finance[Xero Invoice No]<>"")),tbl_Finance[Xero Invoice No]),LOOKUP(2,1/((tbl_Finance[Job Number]=C16&"")*(tbl_Finance[Xero Invoice No]<>"")),tbl_Finance[Xero Invoice No])&" +more"),""))) | D16: =IF(C16="","",IF(COUNTIF(lst_Jobs,C16&"")>0,"OK","CHECK")) | E16: =IF(C16="","",IFERROR(INDEX(lst_JobName,MATCH(C16&"",lst_Jobs,0)),"")) | F16: =IF(C16="","",IFERROR(INDEX(tbl_Finance[Client],MATCH(C16&"",tbl_Finance[Job Number],0)),"")) | G16: =IF(C16="","",COUNTIFS(tbl_Finance[Job Number],C16&"",tbl_Finance[Ex GST],"<>")) | H16: =IF(C16="","",SUMIFS(tbl_Finance[Ex GST],tbl_Finance[Job Number],C16&"")) | I16: =IF(C16="","",SUMIFS(tbl_Finance[Ex GST],tbl_Finance[Job Number],C16&"",tbl_Finance[Xero Invoice No],"<>")) | J16: =IF(C16="","",H16-I16) | K16: =IF(C16="","",IF(G16=0,"not invoiced yet",SUBSTITUTE(TRIM(IF(COUNTIFS(tbl_Finance[Job Number],C16&"",tbl_Finance[Cost Centre],"ONSITE")>0,"ONSITE ","")&IF(COUNTIFS(tbl_Finance[Job Number],C16&"",tbl_Finance[Cost Centre],"PRODUCTION")>0,"PRODUCTION ","")&IF(COUNTIFS(tbl_Finance[Job Number],C16&"",tbl_Finance[Cost Centre],"VIDEO")>0,"VIDEO ","")&IF(COUNTIFS(tbl_Finance[Job Number],C16&"",tbl_Finance[Cost Centre],"INTEGRATION")>0,"INTEGRATION ","")&IF(COUNTIFS(tbl_Finance[Job Number],C16&"",tbl_Finance[Cost Centre],"CONSULTING")>0,"CONSULTING ","")&IF(COUNTIFS(tbl_Finance[Job Number],C16&"",tbl_Finance[Cost Centre],"CTS")>0,"CTS ",""))," ",", "))) | N16: =IF(M16="","",HYPERLINK(IF(LEFT(M16,4)="http",M16,set_QwilrBase&M16),"Open quote"))
... A404: =IF(C404="","",IFERROR(IF(SUMPRODUCT(MAX((tbl_Finance[Job Number]=C404&"")*(tbl_Finance[Xero Invoice No]<>"")*tbl_Finance[Date]))=0,"",SUMPRODUCT(MAX((tbl_Finance[Job Number]=C404&"")*(tbl_Finance[Xero Invoice No]<>"")*tbl_Finance[Date]))),"")) | B404: =IF(C404="","",IF(COUNTIFS(tbl_Finance[Job Number],C404&"",tbl_Finance[Xero Invoice No],"<>")=0,"",IFERROR(IF(COUNTIFS(tbl_Finance[Job Number],C404&"",tbl_Finance[Xero Invoice No],LOOKUP(2,1/((tbl_Finance[Job Number]=C404&"")*(tbl_Finance[Xero Invoice No]<>"")),tbl_Finance[Xero Invoice No]))=COUNTIFS(tbl_Finance[Job Number],C404&"",tbl_Finance[Xero Invoice No],"<>"),LOOKUP(2,1/((tbl_Finance[Job Number]=C404&"")*(tbl_Finance[Xero Invoice No]<>"")),tbl_Finance[Xero Invoice No]),LOOKUP(2,1/((tbl_Finance[Job Number]=C404&"")*(tbl_Finance[Xero Invoice No]<>"")),tbl_Finance[Xero Invoice No])&" +more"),""))) | D404: =IF(C404="","",IF(COUNTIF(lst_Jobs,C404&"")>0,"OK","CHECK")) | E404: =IF(C404="","",IFERROR(INDEX(lst_JobName,MATCH(C404&"",lst_Jobs,0)),"")) | F404: =IF(C404="","",IFERROR(INDEX(tbl_Finance[Client],MATCH(C404&"",tbl_Finance[Job Number],0)),"")) | G404: =IF(C404="","",COUNTIFS(tbl_Finance[Job Number],C404&"",tbl_Finance[Ex GST],"<>")) | H404: =IF(C404="","",SUMIFS(tbl_Finance[Ex GST],tbl_Finance[Job Number],C404&"")) | I404: =IF(C404="","",SUMIFS(tbl_Finance[Ex GST],tbl_Finance[Job Number],C404&"",tbl_Finance[Xero Invoice No],"<>")) | J404: =IF(C404="","",H404-I404) | K404: =IF(C404="","",IF(G404=0,"not invoiced yet",SUBSTITUTE(TRIM(IF(COUNTIFS(tbl_Finance[Job Number],C404&"",tbl_Finance[Cost Centre],"ONSITE")>0,"ONSITE ","")&IF(COUNTIFS(tbl_Finance[Job Number],C404&"",tbl_Finance[Cost Centre],"PRODUCTION")>0,"PRODUCTION ","")&IF(COUNTIFS(tbl_Finance[Job Number],C404&"",tbl_Finance[Cost Centre],"VIDEO")>0,"VIDEO ","")&IF(COUNTIFS(tbl_Finance[Job Number],C404&"",tbl_Finance[Cost Centre],"INTEGRATION")>0,"INTEGRATION ","")&IF(COUNTIFS(tbl_Finance[Job Number],C404&"",tbl_Finance[Cost Centre],"CONSULTING")>0,"CONSULTING ","")&IF(COUNTIFS(tbl_Finance[Job Number],C404&"",tbl_Finance[Cost Centre],"CTS")>0,"CTS ",""))," ",", "))) | N404: =IF(M404="","",HYPERLINK(IF(LEFT(M404,4)="http",M404,set_QwilrBase&M404),"Open quote"))

Sheet Production
A1: Production - Job Detail
A2: Production and Video jobs. One row per job number. Revenue comes from the Finance sheet, so margin is the whole job: every invoice against it less the costs you enter here.
A3: ="Revenue Ex GST "&TEXT(SUBTOTAL(109,tbl_Production[Revenue Ex GST]),"$#,##0.00")
A4: Invoice Date | B4: Invoice No | C4: Job Number | D4: Job in Xero? | E4: Job Name (Xero) | F4: Client | G4: Lines on Job | H4: Revenue Ex GST | I4: Invoiced | J4: To Invoice | K4: Cost Centres | L4: Total Inc GST | M4: Company | N4: Event Name | O4: Client Email | P4: Event Grouping | Q4: Event Date | R4: Current RMS No | S4: Open in Current RMS | T4: Qwilr Quote | U4: Open Qwilr | V4: Zoho Number | W4: Job Closed | X4: Discounts Given | Y4: Value Before Discount | Z4: Discount % | AA4: Cross Hire Expense | AB4: Conf. Call Costs | AC4: Transcription Costs | AD4: Labour Expense (Internal) | AE4: Video Revenue | AF4: Video % of Revenue | AG4: Total Expense | AH4: Margin | AI4: Margin % | AJ4: Video Filming Hrs | AK4: Video Editing Hrs | AL4: Project Mgmt Hrs | AM4: Video Project Mgmt Hrs | AN4: Production Labour Hrs | AO4: Notes
A5: =IF(C5="","",IFERROR(IF(SUMPRODUCT(MAX((tbl_Finance[Job Number]=C5&"")*(tbl_Finance[Xero Invoice No]<>"")*tbl_Finance[Date]))=0,"",SUMPRODUCT(MAX((tbl_Finance[Job Number]=C5&"")*(tbl_Finance[Xero Invoice No]<>"")*tbl_Finance[Date]))),"")) | B5: =IF(C5="","",IF(COUNTIFS(tbl_Finance[Job Number],C5&"",tbl_Finance[Xero Invoice No],"<>")=0,"",IFERROR(IF(COUNTIFS(tbl_Finance[Job Number],C5&"",tbl_Finance[Xero Invoice No],LOOKUP(2,1/((tbl_Finance[Job Number]=C5&"")*(tbl_Finance[Xero Invoice No]<>"")),tbl_Finance[Xero Invoice No]))=COUNTIFS(tbl_Finance[Job Number],C5&"",tbl_Finance[Xero Invoice No],"<>"),LOOKUP(2,1/((tbl_Finance[Job Number]=C5&"")*(tbl_Finance[Xero Invoice No]<>"")),tbl_Finance[Xero Invoice No]),LOOKUP(2,1/((tbl_Finance[Job Number]=C5&"")*(tbl_Finance[Xero Invoice No]<>"")),tbl_Finance[Xero Invoice No])&" +more"),""))) | D5: =IF(C5="","",IF(COUNTIF(lst_Jobs,C5&"")>0,"OK","CHECK")) | E5: =IF(C5="","",IFERROR(INDEX(lst_JobName,MATCH(C5&"",lst_Jobs,0)),"")) | F5: =IF(C5="","",IFERROR(INDEX(tbl_Finance[Client],MATCH(C5&"",tbl_Finance[Job Number],0)),"")) | G5: =IF(C5="","",COUNTIFS(tbl_Finance[Job Number],C5&"",tbl_Finance[Ex GST],"<>")) | H5: =IF(C5="","",SUMIFS(tbl_Finance[Ex GST],tbl_Finance[Job Number],C5&"")) | I5: =IF(C5="","",SUMIFS(tbl_Finance[Ex GST],tbl_Finance[Job Number],C5&"",tbl_Finance[Xero Invoice No],"<>")) | J5: =IF(C5="","",H5-I5) | K5: =IF(C5="","",IF(G5=0,"not invoiced yet",SUBSTITUTE(TRIM(IF(COUNTIFS(tbl_Finance[Job Number],C5&"",tbl_Finance[Cost Centre],"ONSITE")>0,"ONSITE ","")&IF(COUNTIFS(tbl_Finance[Job Number],C5&"",tbl_Finance[Cost Centre],"PRODUCTION")>0,"PRODUCTION ","")&IF(COUNTIFS(tbl_Finance[Job Number],C5&"",tbl_Finance[Cost Centre],"VIDEO")>0,"VIDEO ","")&IF(COUNTIFS(tbl_Finance[Job Number],C5&"",tbl_Finance[Cost Centre],"INTEGRATION")>0,"INTEGRATION ","")&IF(COUNTIFS(tbl_Finance[Job Number],C5&"",tbl_Finance[Cost Centre],"CONSULTING")>0,"CONSULTING ","")&IF(COUNTIFS(tbl_Finance[Job Number],C5&"",tbl_Finance[Cost Centre],"CTS")>0,"CTS ",""))," ",", "))) | L5: =IF(C5="","",SUMIFS(tbl_Finance[Inc GST],tbl_Finance[Job Number],C5&"")) | N5: =IF(C5="","",IFERROR(INDEX(tbl_Finance[Description],MATCH(C5&"",tbl_Finance[Job Number],0)),"")) | S5: =IF(R5="","",IF(AND(LEFT(R5,4)<>"http",set_RMSBase=""),"",HYPERLINK(IF(LEFT(R5,4)="http",R5,set_RMSBase&R5),"Open opportunity"))) | U5: =IF(T5="","",HYPERLINK(IF(LEFT(T5,4)="http",T5,set_QwilrBase&T5),"Open quote")) | V5: =IF(C5="","",C5) | Y5: =IF(C5="","",H5+N(X5)) | Z5: =IFERROR(X5/Y5,"") | AE5: =IF(C5="","",SUMIFS(tbl_Finance[Ex GST],tbl_Finance[Job Number],C5&"",tbl_Finance[Cost Centre],"VIDEO")) | AF5: =IFERROR(AE5/H5,"") | AG5: =IF(C5="","",N(AA5)+N(AB5)+N(AC5)+N(AD5)) | AH5: =IF(C5="","",H5-AG5) | AI5: =IFERROR(AH5/H5,"")
A6: =IF(C6="","",IFERROR(IF(SUMPRODUCT(MAX((tbl_Finance[Job Number]=C6&"")*(tbl_Finance[Xero Invoice No]<>"")*tbl_Finance[Date]))=0,"",SUMPRODUCT(MAX((tbl_Finance[Job Number]=C6&"")*(tbl_Finance[Xero Invoice No]<>"")*tbl_Finance[Date]))),"")) | B6: =IF(C6="","",IF(COUNTIFS(tbl_Finance[Job Number],C6&"",tbl_Finance[Xero Invoice No],"<>")=0,"",IFERROR(IF(COUNTIFS(tbl_Finance[Job Number],C6&"",tbl_Finance[Xero Invoice No],LOOKUP(2,1/((tbl_Finance[Job Number]=C6&"")*(tbl_Finance[Xero Invoice No]<>"")),tbl_Finance[Xero Invoice No]))=COUNTIFS(tbl_Finance[Job Number],C6&"",tbl_Finance[Xero Invoice No],"<>"),LOOKUP(2,1/((tbl_Finance[Job Number]=C6&"")*(tbl_Finance[Xero Invoice No]<>"")),tbl_Finance[Xero Invoice No]),LOOKUP(2,1/((tbl_Finance[Job Number]=C6&"")*(tbl_Finance[Xero Invoice No]<>"")),tbl_Finance[Xero Invoice No])&" +more"),""))) | D6: =IF(C6="","",IF(COUNTIF(lst_Jobs,C6&"")>0,"OK","CHECK")) | E6: =IF(C6="","",IFERROR(INDEX(lst_JobName,MATCH(C6&"",lst_Jobs,0)),"")) | F6: =IF(C6="","",IFERROR(INDEX(tbl_Finance[Client],MATCH(C6&"",tbl_Finance[Job Number],0)),"")) | G6: =IF(C6="","",COUNTIFS(tbl_Finance[Job Number],C6&"",tbl_Finance[Ex GST],"<>")) | H6: =IF(C6="","",SUMIFS(tbl_Finance[Ex GST],tbl_Finance[Job Number],C6&"")) | I6: =IF(C6="","",SUMIFS(tbl_Finance[Ex GST],tbl_Finance[Job Number],C6&"",tbl_Finance[Xero Invoice No],"<>")) | J6: =IF(C6="","",H6-I6) | K6: =IF(C6="","",IF(G6=0,"not invoiced yet",SUBSTITUTE(TRIM(IF(COUNTIFS(tbl_Finance[Job Number],C6&"",tbl_Finance[Cost Centre],"ONSITE")>0,"ONSITE ","")&IF(COUNTIFS(tbl_Finance[Job Number],C6&"",tbl_Finance[Cost Centre],"PRODUCTION")>0,"PRODUCTION ","")&IF(COUNTIFS(tbl_Finance[Job Number],C6&"",tbl_Finance[Cost Centre],"VIDEO")>0,"VIDEO ","")&IF(COUNTIFS(tbl_Finance[Job Number],C6&"",tbl_Finance[Cost Centre],"INTEGRATION")>0,"INTEGRATION ","")&IF(COUNTIFS(tbl_Finance[Job Number],C6&"",tbl_Finance[Cost Centre],"CONSULTING")>0,"CONSULTING ","")&IF(COUNTIFS(tbl_Finance[Job Number],C6&"",tbl_Finance[Cost Centre],"CTS")>0,"CTS ",""))," ",", "))) | L6: =IF(C6="","",SUMIFS(tbl_Finance[Inc GST],tbl_Finance[Job Number],C6&"")) | N6: =IF(C6="","",IFERROR(INDEX(tbl_Finance[Description],MATCH(C6&"",tbl_Finance[Job Number],0)),"")) | S6: =IF(R6="","",IF(AND(LEFT(R6,4)<>"http",set_RMSBase=""),"",HYPERLINK(IF(LEFT(R6,4)="http",R6,set_RMSBase&R6),"Open opportunity"))) | U6: =IF(T6="","",HYPERLINK(IF(LEFT(T6,4)="http",T6,set_QwilrBase&T6),"Open quote")) | V6: =IF(C6="","",C6) | Y6: =IF(C6="","",H6+N(X6)) | Z6: =IFERROR(X6/Y6,"") | AE6: =IF(C6="","",SUMIFS(tbl_Finance[Ex GST],tbl_Finance[Job Number],C6&"",tbl_Finance[Cost Centre],"VIDEO")) | AF6: =IFERROR(AE6/H6,"") | AG6: =IF(C6="","",N(AA6)+N(AB6)+N(AC6)+N(AD6)) | AH6: =IF(C6="","",H6-AG6) | AI6: =IFERROR(AH6/H6,"")
A7: =IF(C7="","",IFERROR(IF(SUMPRODUCT(MAX((tbl_Finance[Job Number]=C7&"")*(tbl_Finance[Xero Invoice No]<>"")*tbl_Finance[Date]))=0,"",SUMPRODUCT(MAX((tbl_Finance[Job Number]=C7&"")*(tbl_Finance[Xero Invoice No]<>"")*tbl_Finance[Date]))),"")) | B7: =IF(C7="","",IF(COUNTIFS(tbl_Finance[Job Number],C7&"",tbl_Finance[Xero Invoice No],"<>")=0,"",IFERROR(IF(COUNTIFS(tbl_Finance[Job Number],C7&"",tbl_Finance[Xero Invoice No],LOOKUP(2,1/((tbl_Finance[Job Number]=C7&"")*(tbl_Finance[Xero Invoice No]<>"")),tbl_Finance[Xero Invoice No]))=COUNTIFS(tbl_Finance[Job Number],C7&"",tbl_Finance[Xero Invoice No],"<>"),LOOKUP(2,1/((tbl_Finance[Job Number]=C7&"")*(tbl_Finance[Xero Invoice No]<>"")),tbl_Finance[Xero Invoice No]),LOOKUP(2,1/((tbl_Finance[Job Number]=C7&"")*(tbl_Finance[Xero Invoice No]<>"")),tbl_Finance[Xero Invoice No])&" +more"),""))) | D7: =IF(C7="","",IF(COUNTIF(lst_Jobs,C7&"")>0,"OK","CHECK")) | E7: =IF(C7="","",IFERROR(INDEX(lst_JobName,MATCH(C7&"",lst_Jobs,0)),"")) | F7: =IF(C7="","",IFERROR(INDEX(tbl_Finance[Client],MATCH(C7&"",tbl_Finance[Job Number],0)),"")) | G7: =IF(C7="","",COUNTIFS(tbl_Finance[Job Number],C7&"",tbl_Finance[Ex GST],"<>")) | H7: =IF(C7="","",SUMIFS(tbl_Finance[Ex GST],tbl_Finance[Job Number],C7&"")) | I7: =IF(C7="","",SUMIFS(tbl_Finance[Ex GST],tbl_Finance[Job Number],C7&"",tbl_Finance[Xero Invoice No],"<>")) | J7: =IF(C7="","",H7-I7) | K7: =IF(C7="","",IF(G7=0,"not invoiced yet",SUBSTITUTE(TRIM(IF(COUNTIFS(tbl_Finance[Job Number],C7&"",tbl_Finance[Cost Centre],"ONSITE")>0,"ONSITE ","")&IF(COUNTIFS(tbl_Finance[Job Number],C7&"",tbl_Finance[Cost Centre],"PRODUCTION")>0,"PRODUCTION ","")&IF(COUNTIFS(tbl_Finance[Job Number],C7&"",tbl_Finance[Cost Centre],"VIDEO")>0,"VIDEO ","")&IF(COUNTIFS(tbl_Finance[Job Number],C7&"",tbl_Finance[Cost Centre],"INTEGRATION")>0,"INTEGRATION ","")&IF(COUNTIFS(tbl_Finance[Job Number],C7&"",tbl_Finance[Cost Centre],"CONSULTING")>0,"CONSULTING ","")&IF(COUNTIFS(tbl_Finance[Job Number],C7&"",tbl_Finance[Cost Centre],"CTS")>0,"CTS ",""))," ",", "))) | L7: =IF(C7="","",SUMIFS(tbl_Finance[Inc GST],tbl_Finance[Job Number],C7&"")) | N7: =IF(C7="","",IFERROR(INDEX(tbl_Finance[Description],MATCH(C7&"",tbl_Finance[Job Number],0)),"")) | S7: =IF(R7="","",IF(AND(LEFT(R7,4)<>"http",set_RMSBase=""),"",HYPERLINK(IF(LEFT(R7,4)="http",R7,set_RMSBase&R7),"Open opportunity"))) | U7: =IF(T7="","",HYPERLINK(IF(LEFT(T7,4)="http",T7,set_QwilrBase&T7),"Open quote")) | V7: =IF(C7="","",C7) | Y7: =IF(C7="","",H7+N(X7)) | Z7: =IFERROR(X7/Y7,"") | AE7: =IF(C7="","",SUMIFS(tbl_Finance[Ex GST],tbl_Finance[Job Number],C7&"",tbl_Finance[Cost Centre],"VIDEO")) | AF7: =IFERROR(AE7/H7,"") | AG7: =IF(C7="","",N(AA7)+N(AB7)+N(AC7)+N(AD7)) | AH7: =IF(C7="","",H7-AG7) | AI7: =IFERROR(AH7/H7,"")
A8: =IF(C8="","",IFERROR(IF(SUMPRODUCT(MAX((tbl_Finance[Job Number]=C8&"")*(tbl_Finance[Xero Invoice No]<>"")*tbl_Finance[Date]))=0,"",SUMPRODUCT(MAX((tbl_Finance[Job Number]=C8&"")*(tbl_Finance[Xero Invoice No]<>"")*tbl_Finance[Date]))),"")) | B8: =IF(C8="","",IF(COUNTIFS(tbl_Finance[Job Number],C8&"",tbl_Finance[Xero Invoice No],"<>")=0,"",IFERROR(IF(COUNTIFS(tbl_Finance[Job Number],C8&"",tbl_Finance[Xero Invoice No],LOOKUP(2,1/((tbl_Finance[Job Number]=C8&"")*(tbl_Finance[Xero Invoice No]<>"")),tbl_Finance[Xero Invoice No]))=COUNTIFS(tbl_Finance[Job Number],C8&"",tbl_Finance[Xero Invoice No],"<>"),LOOKUP(2,1/((tbl_Finance[Job Number]=C8&"")*(tbl_Finance[Xero Invoice No]<>"")),tbl_Finance[Xero Invoice No]),LOOKUP(2,1/((tbl_Finance[Job Number]=C8&"")*(tbl_Finance[Xero Invoice No]<>"")),tbl_Finance[Xero Invoice No])&" +more"),""))) | D8: =IF(C8="","",IF(COUNTIF(lst_Jobs,C8&"")>0,"OK","CHECK")) | E8: =IF(C8="","",IFERROR(INDEX(lst_JobName,MATCH(C8&"",lst_Jobs,0)),"")) | F8: =IF(C8="","",IFERROR(INDEX(tbl_Finance[Client],MATCH(C8&"",tbl_Finance[Job Number],0)),"")) | G8: =IF(C8="","",COUNTIFS(tbl_Finance[Job Number],C8&"",tbl_Finance[Ex GST],"<>")) | H8: =IF(C8="","",SUMIFS(tbl_Finance[Ex GST],tbl_Finance[Job Number],C8&"")) | I8: =IF(C8="","",SUMIFS(tbl_Finance[Ex GST],tbl_Finance[Job Number],C8&"",tbl_Finance[Xero Invoice No],"<>")) | J8: =IF(C8="","",H8-I8) | K8: =IF(C8="","",IF(G8=0,"not invoiced yet",SUBSTITUTE(TRIM(IF(COUNTIFS(tbl_Finance[Job Number],C8&"",tbl_Finance[Cost Centre],"ONSITE")>0,"ONSITE ","")&IF(COUNTIFS(tbl_Finance[Job Number],C8&"",tbl_Finance[Cost Centre],"PRODUCTION")>0,"PRODUCTION ","")&IF(COUNTIFS(tbl_Finance[Job Number],C8&"",tbl_Finance[Cost Centre],"VIDEO")>0,"VIDEO ","")&IF(COUNTIFS(tbl_Finance[Job Number],C8&"",tbl_Finance[Cost Centre],"INTEGRATION")>0,"INTEGRATION ","")&IF(COUNTIFS(tbl_Finance[Job Number],C8&"",tbl_Finance[Cost Centre],"CONSULTING")>0,"CONSULTING ","")&IF(COUNTIFS(tbl_Finance[Job Number],C8&"",tbl_Finance[Cost Centre],"CTS")>0,"CTS ",""))," ",", "))) | L8: =IF(C8="","",SUMIFS(tbl_Finance[Inc GST],tbl_Finance[Job Number],C8&"")) | N8: =IF(C8="","",IFERROR(INDEX(tbl_Finance[Description],MATCH(C8&"",tbl_Finance[Job Number],0)),"")) | S8: =IF(R8="","",IF(AND(LEFT(R8,4)<>"http",set_RMSBase=""),"",HYPERLINK(IF(LEFT(R8,4)="http",R8,set_RMSBase&R8),"Open opportunity"))) | U8: =IF(T8="","",HYPERLINK(IF(LEFT(T8,4)="http",T8,set_QwilrBase&T8),"Open quote")) | V8: =IF(C8="","",C8) | Y8: =IF(C8="","",H8+N(X8)) | Z8: =IFERROR(X8/Y8,"") | AE8: =IF(C8="","",SUMIFS(tbl_Finance[Ex GST],tbl_Finance[Job Number],C8&"",tbl_Finance[Cost Centre],"VIDEO")) | AF8: =IFERROR(AE8/H8,"") | AG8: =IF(C8="","",N(AA8)+N(AB8)+N(AC8)+N(AD8)) | AH8: =IF(C8="","",H8-AG8) | AI8: =IFERROR(AH8/H8,"")
A9: =IF(C9="","",IFERROR(IF(SUMPRODUCT(MAX((tbl_Finance[Job Number]=C9&"")*(tbl_Finance[Xero Invoice No]<>"")*tbl_Finance[Date]))=0,"",SUMPRODUCT(MAX((tbl_Finance[Job Number]=C9&"")*(tbl_Finance[Xero Invoice No]<>"")*tbl_Finance[Date]))),"")) | B9: =IF(C9="","",IF(COUNTIFS(tbl_Finance[Job Number],C9&"",tbl_Finance[Xero Invoice No],"<>")=0,"",IFERROR(IF(COUNTIFS(tbl_Finance[Job Number],C9&"",tbl_Finance[Xero Invoice No],LOOKUP(2,1/((tbl_Finance[Job Number]=C9&"")*(tbl_Finance[Xero Invoice No]<>"")),tbl_Finance[Xero Invoice No]))=COUNTIFS(tbl_Finance[Job Number],C9&"",tbl_Finance[Xero Invoice No],"<>"),LOOKUP(2,1/((tbl_Finance[Job Number]=C9&"")*(tbl_Finance[Xero Invoice No]<>"")),tbl_Finance[Xero Invoice No]),LOOKUP(2,1/((tbl_Finance[Job Number]=C9&"")*(tbl_Finance[Xero Invoice No]<>"")),tbl_Finance[Xero Invoice No])&" +more"),""))) | D9: =IF(C9="","",IF(COUNTIF(lst_Jobs,C9&"")>0,"OK","CHECK")) | E9: =IF(C9="","",IFERROR(INDEX(lst_JobName,MATCH(C9&"",lst_Jobs,0)),"")) | F9: =IF(C9="","",IFERROR(INDEX(tbl_Finance[Client],MATCH(C9&"",tbl_Finance[Job Number],0)),"")) | G9: =IF(C9="","",COUNTIFS(tbl_Finance[Job Number],C9&"",tbl_Finance[Ex GST],"<>")) | H9: =IF(C9="","",SUMIFS(tbl_Finance[Ex GST],tbl_Finance[Job Number],C9&"")) | I9: =IF(C9="","",SUMIFS(tbl_Finance[Ex GST],tbl_Finance[Job Number],C9&"",tbl_Finance[Xero Invoice No],"<>")) | J9: =IF(C9="","",H9-I9) | K9: =IF(C9="","",IF(G9=0,"not invoiced yet",SUBSTITUTE(TRIM(IF(COUNTIFS(tbl_Finance[Job Number],C9&"",tbl_Finance[Cost Centre],"ONSITE")>0,"ONSITE ","")&IF(COUNTIFS(tbl_Finance[Job Number],C9&"",tbl_Finance[Cost Centre],"PRODUCTION")>0,"PRODUCTION ","")&IF(COUNTIFS(tbl_Finance[Job Number],C9&"",tbl_Finance[Cost Centre],"VIDEO")>0,"VIDEO ","")&IF(COUNTIFS(tbl_Finance[Job Number],C9&"",tbl_Finance[Cost Centre],"INTEGRATION")>0,"INTEGRATION ","")&IF(COUNTIFS(tbl_Finance[Job Number],C9&"",tbl_Finance[Cost Centre],"CONSULTING")>0,"CONSULTING ","")&IF(COUNTIFS(tbl_Finance[Job Number],C9&"",tbl_Finance[Cost Centre],"CTS")>0,"CTS ",""))," ",", "))) | L9: =IF(C9="","",SUMIFS(tbl_Finance[Inc GST],tbl_Finance[Job Number],C9&"")) | N9: =IF(C9="","",IFERROR(INDEX(tbl_Finance[Description],MATCH(C9&"",tbl_Finance[Job Number],0)),"")) | S9: =IF(R9="","",IF(AND(LEFT(R9,4)<>"http",set_RMSBase=""),"",HYPERLINK(IF(LEFT(R9,4)="http",R9,set_RMSBase&R9),"Open opportunity"))) | U9: =IF(T9="","",HYPERLINK(IF(LEFT(T9,4)="http",T9,set_QwilrBase&T9),"Open quote")) | V9: =IF(C9="","",C9) | Y9: =IF(C9="","",H9+N(X9)) | Z9: =IFERROR(X9/Y9,"") | AE9: =IF(C9="","",SUMIFS(tbl_Finance[Ex GST],tbl_Finance[Job Number],C9&"",tbl_Finance[Cost Centre],"VIDEO")) | AF9: =IFERROR(AE9/H9,"") | AG9: =IF(C9="","",N(AA9)+N(AB9)+N(AC9)+N(AD9)) | AH9: =IF(C9="","",H9-AG9) | AI9: =IFERROR(AH9/H9,"")
A10: =IF(C10="","",IFERROR(IF(SUMPRODUCT(MAX((tbl_Finance[Job Number]=C10&"")*(tbl_Finance[Xero Invoice No]<>"")*tbl_Finance[Date]))=0,"",SUMPRODUCT(MAX((tbl_Finance[Job Number]=C10&"")*(tbl_Finance[Xero Invoice No]<>"")*tbl_Finance[Date]))),"")) | B10: =IF(C10="","",IF(COUNTIFS(tbl_Finance[Job Number],C10&"",tbl_Finance[Xero Invoice No],"<>")=0,"",IFERROR(IF(COUNTIFS(tbl_Finance[Job Number],C10&"",tbl_Finance[Xero Invoice No],LOOKUP(2,1/((tbl_Finance[Job Number]=C10&"")*(tbl_Finance[Xero Invoice No]<>"")),tbl_Finance[Xero Invoice No]))=COUNTIFS(tbl_Finance[Job Number],C10&"",tbl_Finance[Xero Invoice No],"<>"),LOOKUP(2,1/((tbl_Finance[Job Number]=C10&"")*(tbl_Finance[Xero Invoice No]<>"")),tbl_Finance[Xero Invoice No]),LOOKUP(2,1/((tbl_Finance[Job Number]=C10&"")*(tbl_Finance[Xero Invoice No]<>"")),tbl_Finance[Xero Invoice No])&" +more"),""))) | D10: =IF(C10="","",IF(COUNTIF(lst_Jobs,C10&"")>0,"OK","CHECK")) | E10: =IF(C10="","",IFERROR(INDEX(lst_JobName,MATCH(C10&"",lst_Jobs,0)),"")) | F10: =IF(C10="","",IFERROR(INDEX(tbl_Finance[Client],MATCH(C10&"",tbl_Finance[Job Number],0)),"")) | G10: =IF(C10="","",COUNTIFS(tbl_Finance[Job Number],C10&"",tbl_Finance[Ex GST],"<>")) | H10: =IF(C10="","",SUMIFS(tbl_Finance[Ex GST],tbl_Finance[Job Number],C10&"")) | I10: =IF(C10="","",SUMIFS(tbl_Finance[Ex GST],tbl_Finance[Job Number],C10&"",tbl_Finance[Xero Invoice No],"<>")) | J10: =IF(C10="","",H10-I10) | K10: =IF(C10="","",IF(G10=0,"not invoiced yet",SUBSTITUTE(TRIM(IF(COUNTIFS(tbl_Finance[Job Number],C10&"",tbl_Finance[Cost Centre],"ONSITE")>0,"ONSITE ","")&IF(COUNTIFS(tbl_Finance[Job Number],C10&"",tbl_Finance[Cost Centre],"PRODUCTION")>0,"PRODUCTION ","")&IF(COUNTIFS(tbl_Finance[Job Number],C10&"",tbl_Finance[Cost Centre],"VIDEO")>0,"VIDEO ","")&IF(COUNTIFS(tbl_Finance[Job Number],C10&"",tbl_Finance[Cost Centre],"INTEGRATION")>0,"INTEGRATION ","")&IF(COUNTIFS(tbl_Finance[Job Number],C10&"",tbl_Finance[Cost Centre],"CONSULTING")>0,"CONSULTING ","")&IF(COUNTIFS(tbl_Finance[Job Number],C10&"",tbl_Finance[Cost Centre],"CTS")>0,"CTS ",""))," ",", "))) | L10: =IF(C10="","",SUMIFS(tbl_Finance[Inc GST],tbl_Finance[Job Number],C10&"")) | N10: =IF(C10="","",IFERROR(INDEX(tbl_Finance[Description],MATCH(C10&"",tbl_Finance[Job Number],0)),"")) | S10: =IF(R10="","",IF(AND(LEFT(R10,4)<>"http",set_RMSBase=""),"",HYPERLINK(IF(LEFT(R10,4)="http",R10,set_RMSBase&R10),"Open opportunity"))) | U10: =IF(T10="","",HYPERLINK(IF(LEFT(T10,4)="http",T10,set_QwilrBase&T10),"Open quote")) | V10: =IF(C10="","",C10) | Y10: =IF(C10="","",H10+N(X10)) | Z10: =IFERROR(X10/Y10,"") | AE10: =IF(C10="","",SUMIFS(tbl_Finance[Ex GST],tbl_Finance[Job Number],C10&"",tbl_Finance[Cost Centre],"VIDEO")) | AF10: =IFERROR(AE10/H10,"") | AG10: =IF(C10="","",N(AA10)+N(AB10)+N(AC10)+N(AD10)) | AH10: =IF(C10="","",H10-AG10) | AI10: =IFERROR(AH10/H10,"")
A11: =IF(C11="","",IFERROR(IF(SUMPRODUCT(MAX((tbl_Finance[Job Number]=C11&"")*(tbl_Finance[Xero Invoice No]<>"")*tbl_Finance[Date]))=0,"",SUMPRODUCT(MAX((tbl_Finance[Job Number]=C11&"")*(tbl_Finance[Xero Invoice No]<>"")*tbl_Finance[Date]))),"")) | B11: =IF(C11="","",IF(COUNTIFS(tbl_Finance[Job Number],C11&"",tbl_Finance[Xero Invoice No],"<>")=0,"",IFERROR(IF(COUNTIFS(tbl_Finance[Job Number],C11&"",tbl_Finance[Xero Invoice No],LOOKUP(2,1/((tbl_Finance[Job Number]=C11&"")*(tbl_Finance[Xero Invoice No]<>"")),tbl_Finance[Xero Invoice No]))=COUNTIFS(tbl_Finance[Job Number],C11&"",tbl_Finance[Xero Invoice No],"<>"),LOOKUP(2,1/((tbl_Finance[Job Number]=C11&"")*(tbl_Finance[Xero Invoice No]<>"")),tbl_Finance[Xero Invoice No]),LOOKUP(2,1/((tbl_Finance[Job Number]=C11&"")*(tbl_Finance[Xero Invoice No]<>"")),tbl_Finance[Xero Invoice No])&" +more"),""))) | D11: =IF(C11="","",IF(COUNTIF(lst_Jobs,C11&"")>0,"OK","CHECK")) | E11: =IF(C11="","",IFERROR(INDEX(lst_JobName,MATCH(C11&"",lst_Jobs,0)),"")) | F11: =IF(C11="","",IFERROR(INDEX(tbl_Finance[Client],MATCH(C11&"",tbl_Finance[Job Number],0)),"")) | G11: =IF(C11="","",COUNTIFS(tbl_Finance[Job Number],C11&"",tbl_Finance[Ex GST],"<>")) | H11: =IF(C11="","",SUMIFS(tbl_Finance[Ex GST],tbl_Finance[Job Number],C11&"")) | I11: =IF(C11="","",SUMIFS(tbl_Finance[Ex GST],tbl_Finance[Job Number],C11&"",tbl_Finance[Xero Invoice No],"<>")) | J11: =IF(C11="","",H11-I11) | K11: =IF(C11="","",IF(G11=0,"not invoiced yet",SUBSTITUTE(TRIM(IF(COUNTIFS(tbl_Finance[Job Number],C11&"",tbl_Finance[Cost Centre],"ONSITE")>0,"ONSITE ","")&IF(COUNTIFS(tbl_Finance[Job Number],C11&"",tbl_Finance[Cost Centre],"PRODUCTION")>0,"PRODUCTION ","")&IF(COUNTIFS(tbl_Finance[Job Number],C11&"",tbl_Finance[Cost Centre],"VIDEO")>0,"VIDEO ","")&IF(COUNTIFS(tbl_Finance[Job Number],C11&"",tbl_Finance[Cost Centre],"INTEGRATION")>0,"INTEGRATION ","")&IF(COUNTIFS(tbl_Finance[Job Number],C11&"",tbl_Finance[Cost Centre],"CONSULTING")>0,"CONSULTING ","")&IF(COUNTIFS(tbl_Finance[Job Number],C11&"",tbl_Finance[Cost Centre],"CTS")>0,"CTS ",""))," ",", "))) | L11: =IF(C11="","",SUMIFS(tbl_Finance[Inc GST],tbl_Finance[Job Number],C11&"")) | N11: =IF(C11="","",IFERROR(INDEX(tbl_Finance[Description],MATCH(C11&"",tbl_Finance[Job Number],0)),"")) | S11: =IF(R11="","",IF(AND(LEFT(R11,4)<>"http",set_RMSBase=""),"",HYPERLINK(IF(LEFT(R11,4)="http",R11,set_RMSBase&R11),"Open opportunity"))) | U11: =IF(T11="","",HYPERLINK(IF(LEFT(T11,4)="http",T11,set_QwilrBase&T11),"Open quote")) | V11: =IF(C11="","",C11) | Y11: =IF(C11="","",H11+N(X11)) | Z11: =IFERROR(X11/Y11,"") | AE11: =IF(C11="","",SUMIFS(tbl_Finance[Ex GST],tbl_Finance[Job Number],C11&"",tbl_Finance[Cost Centre],"VIDEO")) | AF11: =IFERROR(AE11/H11,"") | AG11: =IF(C11="","",N(AA11)+N(AB11)+N(AC11)+N(AD11)) | AH11: =IF(C11="","",H11-AG11) | AI11: =IFERROR(AH11/H11,"")
A12: =IF(C12="","",IFERROR(IF(SUMPRODUCT(MAX((tbl_Finance[Job Number]=C12&"")*(tbl_Finance[Xero Invoice No]<>"")*tbl_Finance[Date]))=0,"",SUMPRODUCT(MAX((tbl_Finance[Job Number]=C12&"")*(tbl_Finance[Xero Invoice No]<>"")*tbl_Finance[Date]))),"")) | B12: =IF(C12="","",IF(COUNTIFS(tbl_Finance[Job Number],C12&"",tbl_Finance[Xero Invoice No],"<>")=0,"",IFERROR(IF(COUNTIFS(tbl_Finance[Job Number],C12&"",tbl_Finance[Xero Invoice No],LOOKUP(2,1/((tbl_Finance[Job Number]=C12&"")*(tbl_Finance[Xero Invoice No]<>"")),tbl_Finance[Xero Invoice No]))=COUNTIFS(tbl_Finance[Job Number],C12&"",tbl_Finance[Xero Invoice No],"<>"),LOOKUP(2,1/((tbl_Finance[Job Number]=C12&"")*(tbl_Finance[Xero Invoice No]<>"")),tbl_Finance[Xero Invoice No]),LOOKUP(2,1/((tbl_Finance[Job Number]=C12&"")*(tbl_Finance[Xero Invoice No]<>"")),tbl_Finance[Xero Invoice No])&" +more"),""))) | D12: =IF(C12="","",IF(COUNTIF(lst_Jobs,C12&"")>0,"OK","CHECK")) | E12: =IF(C12="","",IFERROR(INDEX(lst_JobName,MATCH(C12&"",lst_Jobs,0)),"")) | F12: =IF(C12="","",IFERROR(INDEX(tbl_Finance[Client],MATCH(C12&"",tbl_Finance[Job Number],0)),"")) | G12: =IF(C12="","",COUNTIFS(tbl_Finance[Job Number],C12&"",tbl_Finance[Ex GST],"<>")) | H12: =IF(C12="","",SUMIFS(tbl_Finance[Ex GST],tbl_Finance[Job Number],C12&"")) | I12: =IF(C12="","",SUMIFS(tbl_Finance[Ex GST],tbl_Finance[Job Number],C12&"",tbl_Finance[Xero Invoice No],"<>")) | J12: =IF(C12="","",H12-I12) | K12: =IF(C12="","",IF(G12=0,"not invoiced yet",SUBSTITUTE(TRIM(IF(COUNTIFS(tbl_Finance[Job Number],C12&"",tbl_Finance[Cost Centre],"ONSITE")>0,"ONSITE ","")&IF(COUNTIFS(tbl_Finance[Job Number],C12&"",tbl_Finance[Cost Centre],"PRODUCTION")>0,"PRODUCTION ","")&IF(COUNTIFS(tbl_Finance[Job Number],C12&"",tbl_Finance[Cost Centre],"VIDEO")>0,"VIDEO ","")&IF(COUNTIFS(tbl_Finance[Job Number],C12&"",tbl_Finance[Cost Centre],"INTEGRATION")>0,"INTEGRATION ","")&IF(COUNTIFS(tbl_Finance[Job Number],C12&"",tbl_Finance[Cost Centre],"CONSULTING")>0,"CONSULTING ","")&IF(COUNTIFS(tbl_Finance[Job Number],C12&"",tbl_Finance[Cost Centre],"CTS")>0,"CTS ",""))," ",", "))) | L12: =IF(C12="","",SUMIFS(tbl_Finance[Inc GST],tbl_Finance[Job Number],C12&"")) | N12: =IF(C12="","",IFERROR(INDEX(tbl_Finance[Description],MATCH(C12&"",tbl_Finance[Job Number],0)),"")) | S12: =IF(R12="","",IF(AND(LEFT(R12,4)<>"http",set_RMSBase=""),"",HYPERLINK(IF(LEFT(R12,4)="http",R12,set_RMSBase&R12),"Open opportunity"))) | U12: =IF(T12="","",HYPERLINK(IF(LEFT(T12,4)="http",T12,set_QwilrBase&T12),"Open quote")) | V12: =IF(C12="","",C12) | Y12: =IF(C12="","",H12+N(X12)) | Z12: =IFERROR(X12/Y12,"") | AE12: =IF(C12="","",SUMIFS(tbl_Finance[Ex GST],tbl_Finance[Job Number],C12&"",tbl_Finance[Cost Centre],"VIDEO")) | AF12: =IFERROR(AE12/H12,"") | AG12: =IF(C12="","",N(AA12)+N(AB12)+N(AC12)+N(AD12)) | AH12: =IF(C12="","",H12-AG12) | AI12: =IFERROR(AH12/H12,"")
A13: =IF(C13="","",IFERROR(IF(SUMPRODUCT(MAX((tbl_Finance[Job Number]=C13&"")*(tbl_Finance[Xero Invoice No]<>"")*tbl_Finance[Date]))=0,"",SUMPRODUCT(MAX((tbl_Finance[Job Number]=C13&"")*(tbl_Finance[Xero Invoice No]<>"")*tbl_Finance[Date]))),"")) | B13: =IF(C13="","",IF(COUNTIFS(tbl_Finance[Job Number],C13&"",tbl_Finance[Xero Invoice No],"<>")=0,"",IFERROR(IF(COUNTIFS(tbl_Finance[Job Number],C13&"",tbl_Finance[Xero Invoice No],LOOKUP(2,1/((tbl_Finance[Job Number]=C13&"")*(tbl_Finance[Xero Invoice No]<>"")),tbl_Finance[Xero Invoice No]))=COUNTIFS(tbl_Finance[Job Number],C13&"",tbl_Finance[Xero Invoice No],"<>"),LOOKUP(2,1/((tbl_Finance[Job Number]=C13&"")*(tbl_Finance[Xero Invoice No]<>"")),tbl_Finance[Xero Invoice No]),LOOKUP(2,1/((tbl_Finance[Job Number]=C13&"")*(tbl_Finance[Xero Invoice No]<>"")),tbl_Finance[Xero Invoice No])&" +more"),""))) | D13: =IF(C13="","",IF(COUNTIF(lst_Jobs,C13&"")>0,"OK","CHECK")) | E13: =IF(C13="","",IFERROR(INDEX(lst_JobName,MATCH(C13&"",lst_Jobs,0)),"")) | F13: =IF(C13="","",IFERROR(INDEX(tbl_Finance[Client],MATCH(C13&"",tbl_Finance[Job Number],0)),"")) | G13: =IF(C13="","",COUNTIFS(tbl_Finance[Job Number],C13&"",tbl_Finance[Ex GST],"<>")) | H13: =IF(C13="","",SUMIFS(tbl_Finance[Ex GST],tbl_Finance[Job Number],C13&"")) | I13: =IF(C13="","",SUMIFS(tbl_Finance[Ex GST],tbl_Finance[Job Number],C13&"",tbl_Finance[Xero Invoice No],"<>")) | J13: =IF(C13="","",H13-I13) | K13: =IF(C13="","",IF(G13=0,"not invoiced yet",SUBSTITUTE(TRIM(IF(COUNTIFS(tbl_Finance[Job Number],C13&"",tbl_Finance[Cost Centre],"ONSITE")>0,"ONSITE ","")&IF(COUNTIFS(tbl_Finance[Job Number],C13&"",tbl_Finance[Cost Centre],"PRODUCTION")>0,"PRODUCTION ","")&IF(COUNTIFS(tbl_Finance[Job Number],C13&"",tbl_Finance[Cost Centre],"VIDEO")>0,"VIDEO ","")&IF(COUNTIFS(tbl_Finance[Job Number],C13&"",tbl_Finance[Cost Centre],"INTEGRATION")>0,"INTEGRATION ","")&IF(COUNTIFS(tbl_Finance[Job Number],C13&"",tbl_Finance[Cost Centre],"CONSULTING")>0,"CONSULTING ","")&IF(COUNTIFS(tbl_Finance[Job Number],C13&"",tbl_Finance[Cost Centre],"CTS")>0,"CTS ",""))," ",", "))) | L13: =IF(C13="","",SUMIFS(tbl_Finance[Inc GST],tbl_Finance[Job Number],C13&"")) | N13: =IF(C13="","",IFERROR(INDEX(tbl_Finance[Description],MATCH(C13&"",tbl_Finance[Job Number],0)),"")) | S13: =IF(R13="","",IF(AND(LEFT(R13,4)<>"http",set_RMSBase=""),"",HYPERLINK(IF(LEFT(R13,4)="http",R13,set_RMSBase&R13),"Open opportunity"))) | U13: =IF(T13="","",HYPERLINK(IF(LEFT(T13,4)="http",T13,set_QwilrBase&T13),"Open quote")) | V13: =IF(C13="","",C13) | Y13: =IF(C13="","",H13+N(X13)) | Z13: =IFERROR(X13/Y13,"") | AE13: =IF(C13="","",SUMIFS(tbl_Finance[Ex GST],tbl_Finance[Job Number],C13&"",tbl_Finance[Cost Centre],"VIDEO")) | AF13: =IFERROR(AE13/H13,"") | AG13: =IF(C13="","",N(AA13)+N(AB13)+N(AC13)+N(AD13)) | AH13: =IF(C13="","",H13-AG13) | AI13: =IFERROR(AH13/H13,"")
A14: =IF(C14="","",IFERROR(IF(SUMPRODUCT(MAX((tbl_Finance[Job Number]=C14&"")*(tbl_Finance[Xero Invoice No]<>"")*tbl_Finance[Date]))=0,"",SUMPRODUCT(MAX((tbl_Finance[Job Number]=C14&"")*(tbl_Finance[Xero Invoice No]<>"")*tbl_Finance[Date]))),"")) | B14: =IF(C14="","",IF(COUNTIFS(tbl_Finance[Job Number],C14&"",tbl_Finance[Xero Invoice No],"<>")=0,"",IFERROR(IF(COUNTIFS(tbl_Finance[Job Number],C14&"",tbl_Finance[Xero Invoice No],LOOKUP(2,1/((tbl_Finance[Job Number]=C14&"")*(tbl_Finance[Xero Invoice No]<>"")),tbl_Finance[Xero Invoice No]))=COUNTIFS(tbl_Finance[Job Number],C14&"",tbl_Finance[Xero Invoice No],"<>"),LOOKUP(2,1/((tbl_Finance[Job Number]=C14&"")*(tbl_Finance[Xero Invoice No]<>"")),tbl_Finance[Xero Invoice No]),LOOKUP(2,1/((tbl_Finance[Job Number]=C14&"")*(tbl_Finance[Xero Invoice No]<>"")),tbl_Finance[Xero Invoice No])&" +more"),""))) | D14: =IF(C14="","",IF(COUNTIF(lst_Jobs,C14&"")>0,"OK","CHECK")) | E14: =IF(C14="","",IFERROR(INDEX(lst_JobName,MATCH(C14&"",lst_Jobs,0)),"")) | F14: =IF(C14="","",IFERROR(INDEX(tbl_Finance[Client],MATCH(C14&"",tbl_Finance[Job Number],0)),"")) | G14: =IF(C14="","",COUNTIFS(tbl_Finance[Job Number],C14&"",tbl_Finance[Ex GST],"<>")) | H14: =IF(C14="","",SUMIFS(tbl_Finance[Ex GST],tbl_Finance[Job Number],C14&"")) | I14: =IF(C14="","",SUMIFS(tbl_Finance[Ex GST],tbl_Finance[Job Number],C14&"",tbl_Finance[Xero Invoice No],"<>")) | J14: =IF(C14="","",H14-I14) | K14: =IF(C14="","",IF(G14=0,"not invoiced yet",SUBSTITUTE(TRIM(IF(COUNTIFS(tbl_Finance[Job Number],C14&"",tbl_Finance[Cost Centre],"ONSITE")>0,"ONSITE ","")&IF(COUNTIFS(tbl_Finance[Job Number],C14&"",tbl_Finance[Cost Centre],"PRODUCTION")>0,"PRODUCTION ","")&IF(COUNTIFS(tbl_Finance[Job Number],C14&"",tbl_Finance[Cost Centre],"VIDEO")>0,"VIDEO ","")&IF(COUNTIFS(tbl_Finance[Job Number],C14&"",tbl_Finance[Cost Centre],"INTEGRATION")>0,"INTEGRATION ","")&IF(COUNTIFS(tbl_Finance[Job Number],C14&"",tbl_Finance[Cost Centre],"CONSULTING")>0,"CONSULTING ","")&IF(COUNTIFS(tbl_Finance[Job Number],C14&"",tbl_Finance[Cost Centre],"CTS")>0,"CTS ",""))," ",", "))) | L14: =IF(C14="","",SUMIFS(tbl_Finance[Inc GST],tbl_Finance[Job Number],C14&"")) | N14: =IF(C14="","",IFERROR(INDEX(tbl_Finance[Description],MATCH(C14&"",tbl_Finance[Job Number],0)),"")) | S14: =IF(R14="","",IF(AND(LEFT(R14,4)<>"http",set_RMSBase=""),"",HYPERLINK(IF(LEFT(R14,4)="http",R14,set_RMSBase&R14),"Open opportunity"))) | U14: =IF(T14="","",HYPERLINK(IF(LEFT(T14,4)="http",T14,set_QwilrBase&T14),"Open quote")) | V14: =IF(C14="","",C14) | Y14: =IF(C14="","",H14+N(X14)) | Z14: =IFERROR(X14/Y14,"") | AE14: =IF(C14="","",SUMIFS(tbl_Finance[Ex GST],tbl_Finance[Job Number],C14&"",tbl_Finance[Cost Centre],"VIDEO")) | AF14: =IFERROR(AE14/H14,"") | AG14: =IF(C14="","",N(AA14)+N(AB14)+N(AC14)+N(AD14)) | AH14: =IF(C14="","",H14-AG14) | AI14: =IFERROR(AH14/H14,"")
A15: =IF(C15="","",IFERROR(IF(SUMPRODUCT(MAX((tbl_Finance[Job Number]=C15&"")*(tbl_Finance[Xero Invoice No]<>"")*tbl_Finance[Date]))=0,"",SUMPRODUCT(MAX((tbl_Finance[Job Number]=C15&"")*(tbl_Finance[Xero Invoice No]<>"")*tbl_Finance[Date]))),"")) | B15: =IF(C15="","",IF(COUNTIFS(tbl_Finance[Job Number],C15&"",tbl_Finance[Xero Invoice No],"<>")=0,"",IFERROR(IF(COUNTIFS(tbl_Finance[Job Number],C15&"",tbl_Finance[Xero Invoice No],LOOKUP(2,1/((tbl_Finance[Job Number]=C15&"")*(tbl_Finance[Xero Invoice No]<>"")),tbl_Finance[Xero Invoice No]))=COUNTIFS(tbl_Finance[Job Number],C15&"",tbl_Finance[Xero Invoice No],"<>"),LOOKUP(2,1/((tbl_Finance[Job Number]=C15&"")*(tbl_Finance[Xero Invoice No]<>"")),tbl_Finance[Xero Invoice No]),LOOKUP(2,1/((tbl_Finance[Job Number]=C15&"")*(tbl_Finance[Xero Invoice No]<>"")),tbl_Finance[Xero Invoice No])&" +more"),""))) | D15: =IF(C15="","",IF(COUNTIF(lst_Jobs,C15&"")>0,"OK","CHECK")) | E15: =IF(C15="","",IFERROR(INDEX(lst_JobName,MATCH(C15&"",lst_Jobs,0)),"")) | F15: =IF(C15="","",IFERROR(INDEX(tbl_Finance[Client],MATCH(C15&"",tbl_Finance[Job Number],0)),"")) | G15: =IF(C15="","",COUNTIFS(tbl_Finance[Job Number],C15&"",tbl_Finance[Ex GST],"<>")) | H15: =IF(C15="","",SUMIFS(tbl_Finance[Ex GST],tbl_Finance[Job Number],C15&"")) | I15: =IF(C15="","",SUMIFS(tbl_Finance[Ex GST],tbl_Finance[Job Number],C15&"",tbl_Finance[Xero Invoice No],"<>")) | J15: =IF(C15="","",H15-I15) | K15: =IF(C15="","",IF(G15=0,"not invoiced yet",SUBSTITUTE(TRIM(IF(COUNTIFS(tbl_Finance[Job Number],C15&"",tbl_Finance[Cost Centre],"ONSITE")>0,"ONSITE ","")&IF(COUNTIFS(tbl_Finance[Job Number],C15&"",tbl_Finance[Cost Centre],"PRODUCTION")>0,"PRODUCTION ","")&IF(COUNTIFS(tbl_Finance[Job Number],C15&"",tbl_Finance[Cost Centre],"VIDEO")>0,"VIDEO ","")&IF(COUNTIFS(tbl_Finance[Job Number],C15&"",tbl_Finance[Cost Centre],"INTEGRATION")>0,"INTEGRATION ","")&IF(COUNTIFS(tbl_Finance[Job Number],C15&"",tbl_Finance[Cost Centre],"CONSULTING")>0,"CONSULTING ","")&IF(COUNTIFS(tbl_Finance[Job Number],C15&"",tbl_Finance[Cost Centre],"CTS")>0,"CTS ",""))," ",", "))) | L15: =IF(C15="","",SUMIFS(tbl_Finance[Inc GST],tbl_Finance[Job Number],C15&"")) | N15: =IF(C15="","",IFERROR(INDEX(tbl_Finance[Description],MATCH(C15&"",tbl_Finance[Job Number],0)),"")) | S15: =IF(R15="","",IF(AND(LEFT(R15,4)<>"http",set_RMSBase=""),"",HYPERLINK(IF(LEFT(R15,4)="http",R15,set_RMSBase&R15),"Open opportunity"))) | U15: =IF(T15="","",HYPERLINK(IF(LEFT(T15,4)="http",T15,set_QwilrBase&T15),"Open quote")) | V15: =IF(C15="","",C15) | Y15: =IF(C15="","",H15+N(X15)) | Z15: =IFERROR(X15/Y15,"") | AE15: =IF(C15="","",SUMIFS(tbl_Finance[Ex GST],tbl_Finance[Job Number],C15&"",tbl_Finance[Cost Centre],"VIDEO")) | AF15: =IFERROR(AE15/H15,"") | AG15: =IF(C15="","",N(AA15)+N(AB15)+N(AC15)+N(AD15)) | AH15: =IF(C15="","",H15-AG15) | AI15: =IFERROR(AH15/H15,"")
A16: =IF(C16="","",IFERROR(IF(SUMPRODUCT(MAX((tbl_Finance[Job Number]=C16&"")*(tbl_Finance[Xero Invoice No]<>"")*tbl_Finance[Date]))=0,"",SUMPRODUCT(MAX((tbl_Finance[Job Number]=C16&"")*(tbl_Finance[Xero Invoice No]<>"")*tbl_Finance[Date]))),"")) | B16: =IF(C16="","",IF(COUNTIFS(tbl_Finance[Job Number],C16&"",tbl_Finance[Xero Invoice No],"<>")=0,"",IFERROR(IF(COUNTIFS(tbl_Finance[Job Number],C16&"",tbl_Finance[Xero Invoice No],LOOKUP(2,1/((tbl_Finance[Job Number]=C16&"")*(tbl_Finance[Xero Invoice No]<>"")),tbl_Finance[Xero Invoice No]))=COUNTIFS(tbl_Finance[Job Number],C16&"",tbl_Finance[Xero Invoice No],"<>"),LOOKUP(2,1/((tbl_Finance[Job Number]=C16&"")*(tbl_Finance[Xero Invoice No]<>"")),tbl_Finance[Xero Invoice No]),LOOKUP(2,1/((tbl_Finance[Job Number]=C16&"")*(tbl_Finance[Xero Invoice No]<>"")),tbl_Finance[Xero Invoice No])&" +more"),""))) | D16: =IF(C16="","",IF(COUNTIF(lst_Jobs,C16&"")>0,"OK","CHECK")) | E16: =IF(C16="","",IFERROR(INDEX(lst_JobName,MATCH(C16&"",lst_Jobs,0)),"")) | F16: =IF(C16="","",IFERROR(INDEX(tbl_Finance[Client],MATCH(C16&"",tbl_Finance[Job Number],0)),"")) | G16: =IF(C16="","",COUNTIFS(tbl_Finance[Job Number],C16&"",tbl_Finance[Ex GST],"<>")) | H16: =IF(C16="","",SUMIFS(tbl_Finance[Ex GST],tbl_Finance[Job Number],C16&"")) | I16: =IF(C16="","",SUMIFS(tbl_Finance[Ex GST],tbl_Finance[Job Number],C16&"",tbl_Finance[Xero Invoice No],"<>")) | J16: =IF(C16="","",H16-I16) | K16: =IF(C16="","",IF(G16=0,"not invoiced yet",SUBSTITUTE(TRIM(IF(COUNTIFS(tbl_Finance[Job Number],C16&"",tbl_Finance[Cost Centre],"ONSITE")>0,"ONSITE ","")&IF(COUNTIFS(tbl_Finance[Job Number],C16&"",tbl_Finance[Cost Centre],"PRODUCTION")>0,"PRODUCTION ","")&IF(COUNTIFS(tbl_Finance[Job Number],C16&"",tbl_Finance[Cost Centre],"VIDEO")>0,"VIDEO ","")&IF(COUNTIFS(tbl_Finance[Job Number],C16&"",tbl_Finance[Cost Centre],"INTEGRATION")>0,"INTEGRATION ","")&IF(COUNTIFS(tbl_Finance[Job Number],C16&"",tbl_Finance[Cost Centre],"CONSULTING")>0,"CONSULTING ","")&IF(COUNTIFS(tbl_Finance[Job Number],C16&"",tbl_Finance[Cost Centre],"CTS")>0,"CTS ",""))," ",", "))) | L16: =IF(C16="","",SUMIFS(tbl_Finance[Inc GST],tbl_Finance[Job Number],C16&"")) | N16: =IF(C16="","",IFERROR(INDEX(tbl_Finance[Description],MATCH(C16&"",tbl_Finance[Job Number],0)),"")) | S16: =IF(R16="","",IF(AND(LEFT(R16,4)<>"http",set_RMSBase=""),"",HYPERLINK(IF(LEFT(R16,4)="http",R16,set_RMSBase&R16),"Open opportunity"))) | U16: =IF(T16="","",HYPERLINK(IF(LEFT(T16,4)="http",T16,set_QwilrBase&T16),"Open quote")) | V16: =IF(C16="","",C16) | Y16: =IF(C16="","",H16+N(X16)) | Z16: =IFERROR(X16/Y16,"") | AE16: =IF(C16="","",SUMIFS(tbl_Finance[Ex GST],tbl_Finance[Job Number],C16&"",tbl_Finance[Cost Centre],"VIDEO")) | AF16: =IFERROR(AE16/H16,"") | AG16: =IF(C16="","",N(AA16)+N(AB16)+N(AC16)+N(AD16)) | AH16: =IF(C16="","",H16-AG16) | AI16: =IFERROR(AH16/H16,"")
... A404: =IF(C404="","",IFERROR(IF(SUMPRODUCT(MAX((tbl_Finance[Job Number]=C404&"")*(tbl_Finance[Xero Invoice No]<>"")*tbl_Finance[Date]))=0,"",SUMPRODUCT(MAX((tbl_Finance[Job Number]=C404&"")*(tbl_Finance[Xero Invoice No]<>"")*tbl_Finance[Date]))),"")) | B404: =IF(C404="","",IF(COUNTIFS(tbl_Finance[Job Number],C404&"",tbl_Finance[Xero Invoice No],"<>")=0,"",IFERROR(IF(COUNTIFS(tbl_Finance[Job Number],C404&"",tbl_Finance[Xero Invoice No],LOOKUP(2,1/((tbl_Finance[Job Number]=C404&"")*(tbl_Finance[Xero Invoice No]<>"")),tbl_Finance[Xero Invoice No]))=COUNTIFS(tbl_Finance[Job Number],C404&"",tbl_Finance[Xero Invoice No],"<>"),LOOKUP(2,1/((tbl_Finance[Job Number]=C404&"")*(tbl_Finance[Xero Invoice No]<>"")),tbl_Finance[Xero Invoice No]),LOOKUP(2,1/((tbl_Finance[Job Number]=C404&"")*(tbl_Finance[Xero Invoice No]<>"")),tbl_Finance[Xero Invoice No])&" +more"),""))) | D404: =IF(C404="","",IF(COUNTIF(lst_Jobs,C404&"")>0,"OK","CHECK")) | E404: =IF(C404="","",IFERROR(INDEX(lst_JobName,MATCH(C404&"",lst_Jobs,0)),"")) | F404: =IF(C404="","",IFERROR(INDEX(tbl_Finance[Client],MATCH(C404&"",tbl_Finance[Job Number],0)),"")) | G404: =IF(C404="","",COUNTIFS(tbl_Finance[Job Number],C404&"",tbl_Finance[Ex GST],"<>")) | H404: =IF(C404="","",SUMIFS(tbl_Finance[Ex GST],tbl_Finance[Job Number],C404&"")) | I404: =IF(C404="","",SUMIFS(tbl_Finance[Ex GST],tbl_Finance[Job Number],C404&"",tbl_Finance[Xero Invoice No],"<>")) | J404: =IF(C404="","",H404-I404) | K404: =IF(C404="","",IF(G404=0,"not invoiced yet",SUBSTITUTE(TRIM(IF(COUNTIFS(tbl_Finance[Job Number],C404&"",tbl_Finance[Cost Centre],"ONSITE")>0,"ONSITE ","")&IF(COUNTIFS(tbl_Finance[Job Number],C404&"",tbl_Finance[Cost Centre],"PRODUCTION")>0,"PRODUCTION ","")&IF(COUNTIFS(tbl_Finance[Job Number],C404&"",tbl_Finance[Cost Centre],"VIDEO")>0,"VIDEO ","")&IF(COUNTIFS(tbl_Finance[Job Number],C404&"",tbl_Finance[Cost Centre],"INTEGRATION")>0,"INTEGRATION ","")&IF(COUNTIFS(tbl_Finance[Job Number],C404&"",tbl_Finance[Cost Centre],"CONSULTING")>0,"CONSULTING ","")&IF(COUNTIFS(tbl_Finance[Job Number],C404&"",tbl_Finance[Cost Centre],"CTS")>0,"CTS ",""))," ",", "))) | L404: =IF(C404="","",SUMIFS(tbl_Finance[Inc GST],tbl_Finance[Job Number],C404&"")) | N404: =IF(C404="","",IFERROR(INDEX(tbl_Finance[Description],MATCH(C404&"",tbl_Finance[Job Number],0)),"")) | S404: =IF(R404="","",IF(AND(LEFT(R404,4)<>"http",set_RMSBase=""),"",HYPERLINK(IF(LEFT(R404,4)="http",R404,set_RMSBase&R404),"Open opportunity"))) | U404: =IF(T404="","",HYPERLINK(IF(LEFT(T404,4)="http",T404,set_QwilrBase&T404),"Open quote")) | V404: =IF(C404="","",C404) | Y404: =IF(C404="","",H404+N(X404)) | Z404: =IFERROR(X404/Y404,"") | AE404: =IF(C404="","",SUMIFS(tbl_Finance[Ex GST],tbl_Finance[Job Number],C404&"",tbl_Finance[Cost Centre],"VIDEO")) | AF404: =IFERROR(AE404/H404,"") | AG404: =IF(C404="","",N(AA404)+N(AB404)+N(AC404)+N(AD404)) | AH404: =IF(C404="","",H404-AG404) | AI404: =IFERROR(AH404/H404,"")

Sheet Consulting
A1: Consulting - Job Detail
A2: Consulting and Integration jobs. One row per job number. Revenue comes from the Finance sheet; split it across Labour / Equipment / Subscription and the check column flags any mismatch.
A3: ="Revenue Ex GST "&TEXT(SUBTOTAL(109,tbl_Consulting[Revenue Ex GST]),"$#,##0.00")
A4: Invoice Date | B4: Invoice No | C4: Job Number | D4: Job in Xero? | E4: Job Name (Xero) | F4: Client | G4: Lines on Job | H4: Revenue Ex GST | I4: Invoiced | J4: To Invoice | K4: Cost Centres | L4: Qwilr Quote | M4: Open Qwilr | N4: Labour Revenue | O4: Equipment Revenue | P4: Subscription Revenue | Q4: Revenue Split Check | R4: Labour Expense (External) | S4: Equipment Expense (Internal) | T4: Subscription & Licences Expense | U4: Total Expense | V4: Margin | W4: Margin % | X4: Notes
A5: =IF(C5="","",IFERROR(IF(SUMPRODUCT(MAX((tbl_Finance[Job Number]=C5&"")*(tbl_Finance[Xero Invoice No]<>"")*tbl_Finance[Date]))=0,"",SUMPRODUCT(MAX((tbl_Finance[Job Number]=C5&"")*(tbl_Finance[Xero Invoice No]<>"")*tbl_Finance[Date]))),"")) | B5: =IF(C5="","",IF(COUNTIFS(tbl_Finance[Job Number],C5&"",tbl_Finance[Xero Invoice No],"<>")=0,"",IFERROR(IF(COUNTIFS(tbl_Finance[Job Number],C5&"",tbl_Finance[Xero Invoice No],LOOKUP(2,1/((tbl_Finance[Job Number]=C5&"")*(tbl_Finance[Xero Invoice No]<>"")),tbl_Finance[Xero Invoice No]))=COUNTIFS(tbl_Finance[Job Number],C5&"",tbl_Finance[Xero Invoice No],"<>"),LOOKUP(2,1/((tbl_Finance[Job Number]=C5&"")*(tbl_Finance[Xero Invoice No]<>"")),tbl_Finance[Xero Invoice No]),LOOKUP(2,1/((tbl_Finance[Job Number]=C5&"")*(tbl_Finance[Xero Invoice No]<>"")),tbl_Finance[Xero Invoice No])&" +more"),""))) | D5: =IF(C5="","",IF(COUNTIF(lst_Jobs,C5&"")>0,"OK","CHECK")) | E5: =IF(C5="","",IFERROR(INDEX(lst_JobName,MATCH(C5&"",lst_Jobs,0)),"")) | F5: =IF(C5="","",IFERROR(INDEX(tbl_Finance[Client],MATCH(C5&"",tbl_Finance[Job Number],0)),"")) | G5: =IF(C5="","",COUNTIFS(tbl_Finance[Job Number],C5&"",tbl_Finance[Ex GST],"<>")) | H5: =IF(C5="","",SUMIFS(tbl_Finance[Ex GST],tbl_Finance[Job Number],C5&"")) | I5: =IF(C5="","",SUMIFS(tbl_Finance[Ex GST],tbl_Finance[Job Number],C5&"",tbl_Finance[Xero Invoice No],"<>")) | J5: =IF(C5="","",H5-I5) | K5: =IF(C5="","",IF(G5=0,"not invoiced yet",SUBSTITUTE(TRIM(IF(COUNTIFS(tbl_Finance[Job Number],C5&"",tbl_Finance[Cost Centre],"ONSITE")>0,"ONSITE ","")&IF(COUNTIFS(tbl_Finance[Job Number],C5&"",tbl_Finance[Cost Centre],"PRODUCTION")>0,"PRODUCTION ","")&IF(COUNTIFS(tbl_Finance[Job Number],C5&"",tbl_Finance[Cost Centre],"VIDEO")>0,"VIDEO ","")&IF(COUNTIFS(tbl_Finance[Job Number],C5&"",tbl_Finance[Cost Centre],"INTEGRATION")>0,"INTEGRATION ","")&IF(COUNTIFS(tbl_Finance[Job Number],C5&"",tbl_Finance[Cost Centre],"CONSULTING")>0,"CONSULTING ","")&IF(COUNTIFS(tbl_Finance[Job Number],C5&"",tbl_Finance[Cost Centre],"CTS")>0,"CTS ",""))," ",", "))) | M5: =IF(L5="","",HYPERLINK(IF(LEFT(L5,4)="http",L5,set_QwilrBase&L5),"Open quote")) | Q5: =IF(C5="","",IF(N(N5)+N(O5)+N(P5)=0,"Not split",IF(ROUND(N(N5)+N(O5)+N(P5),2)=ROUND(H5,2),"OK","MISMATCH"))) | U5: =IF(C5="","",N(R5)+N(S5)+N(T5)) | V5: =IF(C5="","",H5-U5) | W5: =IFERROR(V5/H5,"")
A6: =IF(C6="","",IFERROR(IF(SUMPRODUCT(MAX((tbl_Finance[Job Number]=C6&"")*(tbl_Finance[Xero Invoice No]<>"")*tbl_Finance[Date]))=0,"",SUMPRODUCT(MAX((tbl_Finance[Job Number]=C6&"")*(tbl_Finance[Xero Invoice No]<>"")*tbl_Finance[Date]))),"")) | B6: =IF(C6="","",IF(COUNTIFS(tbl_Finance[Job Number],C6&"",tbl_Finance[Xero Invoice No],"<>")=0,"",IFERROR(IF(COUNTIFS(tbl_Finance[Job Number],C6&"",tbl_Finance[Xero Invoice No],LOOKUP(2,1/((tbl_Finance[Job Number]=C6&"")*(tbl_Finance[Xero Invoice No]<>"")),tbl_Finance[Xero Invoice No]))=COUNTIFS(tbl_Finance[Job Number],C6&"",tbl_Finance[Xero Invoice No],"<>"),LOOKUP(2,1/((tbl_Finance[Job Number]=C6&"")*(tbl_Finance[Xero Invoice No]<>"")),tbl_Finance[Xero Invoice No]),LOOKUP(2,1/((tbl_Finance[Job Number]=C6&"")*(tbl_Finance[Xero Invoice No]<>"")),tbl_Finance[Xero Invoice No])&" +more"),""))) | D6: =IF(C6="","",IF(COUNTIF(lst_Jobs,C6&"")>0,"OK","CHECK")) | E6: =IF(C6="","",IFERROR(INDEX(lst_JobName,MATCH(C6&"",lst_Jobs,0)),"")) | F6: =IF(C6="","",IFERROR(INDEX(tbl_Finance[Client],MATCH(C6&"",tbl_Finance[Job Number],0)),"")) | G6: =IF(C6="","",COUNTIFS(tbl_Finance[Job Number],C6&"",tbl_Finance[Ex GST],"<>")) | H6: =IF(C6="","",SUMIFS(tbl_Finance[Ex GST],tbl_Finance[Job Number],C6&"")) | I6: =IF(C6="","",SUMIFS(tbl_Finance[Ex GST],tbl_Finance[Job Number],C6&"",tbl_Finance[Xero Invoice No],"<>")) | J6: =IF(C6="","",H6-I6) | K6: =IF(C6="","",IF(G6=0,"not invoiced yet",SUBSTITUTE(TRIM(IF(COUNTIFS(tbl_Finance[Job Number],C6&"",tbl_Finance[Cost Centre],"ONSITE")>0,"ONSITE ","")&IF(COUNTIFS(tbl_Finance[Job Number],C6&"",tbl_Finance[Cost Centre],"PRODUCTION")>0,"PRODUCTION ","")&IF(COUNTIFS(tbl_Finance[Job Number],C6&"",tbl_Finance[Cost Centre],"VIDEO")>0,"VIDEO ","")&IF(COUNTIFS(tbl_Finance[Job Number],C6&"",tbl_Finance[Cost Centre],"INTEGRATION")>0,"INTEGRATION ","")&IF(COUNTIFS(tbl_Finance[Job Number],C6&"",tbl_Finance[Cost Centre],"CONSULTING")>0,"CONSULTING ","")&IF(COUNTIFS(tbl_Finance[Job Number],C6&"",tbl_Finance[Cost Centre],"CTS")>0,"CTS ",""))," ",", "))) | M6: =IF(L6="","",HYPERLINK(IF(LEFT(L6,4)="http",L6,set_QwilrBase&L6),"Open quote")) | Q6: =IF(C6="","",IF(N(N6)+N(O6)+N(P6)=0,"Not split",IF(ROUND(N(N6)+N(O6)+N(P6),2)=ROUND(H6,2),"OK","MISMATCH"))) | U6: =IF(C6="","",N(R6)+N(S6)+N(T6)) | V6: =IF(C6="","",H6-U6) | W6: =IFERROR(V6/H6,"")
A7: =IF(C7="","",IFERROR(IF(SUMPRODUCT(MAX((tbl_Finance[Job Number]=C7&"")*(tbl_Finance[Xero Invoice No]<>"")*tbl_Finance[Date]))=0,"",SUMPRODUCT(MAX((tbl_Finance[Job Number]=C7&"")*(tbl_Finance[Xero Invoice No]<>"")*tbl_Finance[Date]))),"")) | B7: =IF(C7="","",IF(COUNTIFS(tbl_Finance[Job Number],C7&"",tbl_Finance[Xero Invoice No],"<>")=0,"",IFERROR(IF(COUNTIFS(tbl_Finance[Job Number],C7&"",tbl_Finance[Xero Invoice No],LOOKUP(2,1/((tbl_Finance[Job Number]=C7&"")*(tbl_Finance[Xero Invoice No]<>"")),tbl_Finance[Xero Invoice No]))=COUNTIFS(tbl_Finance[Job Number],C7&"",tbl_Finance[Xero Invoice No],"<>"),LOOKUP(2,1/((tbl_Finance[Job Number]=C7&"")*(tbl_Finance[Xero Invoice No]<>"")),tbl_Finance[Xero Invoice No]),LOOKUP(2,1/((tbl_Finance[Job Number]=C7&"")*(tbl_Finance[Xero Invoice No]<>"")),tbl_Finance[Xero Invoice No])&" +more"),""))) | D7: =IF(C7="","",IF(COUNTIF(lst_Jobs,C7&"")>0,"OK","CHECK")) | E7: =IF(C7="","",IFERROR(INDEX(lst_JobName,MATCH(C7&"",lst_Jobs,0)),"")) | F7: =IF(C7="","",IFERROR(INDEX(tbl_Finance[Client],MATCH(C7&"",tbl_Finance[Job Number],0)),"")) | G7: =IF(C7="","",COUNTIFS(tbl_Finance[Job Number],C7&"",tbl_Finance[Ex GST],"<>")) | H7: =IF(C7="","",SUMIFS(tbl_Finance[Ex GST],tbl_Finance[Job Number],C7&"")) | I7: =IF(C7="","",SUMIFS(tbl_Finance[Ex GST],tbl_Finance[Job Number],C7&"",tbl_Finance[Xero Invoice No],"<>")) | J7: =IF(C7="","",H7-I7) | K7: =IF(C7="","",IF(G7=0,"not invoiced yet",SUBSTITUTE(TRIM(IF(COUNTIFS(tbl_Finance[Job Number],C7&"",tbl_Finance[Cost Centre],"ONSITE")>0,"ONSITE ","")&IF(COUNTIFS(tbl_Finance[Job Number],C7&"",tbl_Finance[Cost Centre],"PRODUCTION")>0,"PRODUCTION ","")&IF(COUNTIFS(tbl_Finance[Job Number],C7&"",tbl_Finance[Cost Centre],"VIDEO")>0,"VIDEO ","")&IF(COUNTIFS(tbl_Finance[Job Number],C7&"",tbl_Finance[Cost Centre],"INTEGRATION")>0,"INTEGRATION ","")&IF(COUNTIFS(tbl_Finance[Job Number],C7&"",tbl_Finance[Cost Centre],"CONSULTING")>0,"CONSULTING ","")&IF(COUNTIFS(tbl_Finance[Job Number],C7&"",tbl_Finance[Cost Centre],"CTS")>0,"CTS ",""))," ",", "))) | M7: =IF(L7="","",HYPERLINK(IF(LEFT(L7,4)="http",L7,set_QwilrBase&L7),"Open quote")) | Q7: =IF(C7="","",IF(N(N7)+N(O7)+N(P7)=0,"Not split",IF(ROUND(N(N7)+N(O7)+N(P7),2)=ROUND(H7,2),"OK","MISMATCH"))) | U7: =IF(C7="","",N(R7)+N(S7)+N(T7)) | V7: =IF(C7="","",H7-U7) | W7: =IFERROR(V7/H7,"")
A8: =IF(C8="","",IFERROR(IF(SUMPRODUCT(MAX((tbl_Finance[Job Number]=C8&"")*(tbl_Finance[Xero Invoice No]<>"")*tbl_Finance[Date]))=0,"",SUMPRODUCT(MAX((tbl_Finance[Job Number]=C8&"")*(tbl_Finance[Xero Invoice No]<>"")*tbl_Finance[Date]))),"")) | B8: =IF(C8="","",IF(COUNTIFS(tbl_Finance[Job Number],C8&"",tbl_Finance[Xero Invoice No],"<>")=0,"",IFERROR(IF(COUNTIFS(tbl_Finance[Job Number],C8&"",tbl_Finance[Xero Invoice No],LOOKUP(2,1/((tbl_Finance[Job Number]=C8&"")*(tbl_Finance[Xero Invoice No]<>"")),tbl_Finance[Xero Invoice No]))=COUNTIFS(tbl_Finance[Job Number],C8&"",tbl_Finance[Xero Invoice No],"<>"),LOOKUP(2,1/((tbl_Finance[Job Number]=C8&"")*(tbl_Finance[Xero Invoice No]<>"")),tbl_Finance[Xero Invoice No]),LOOKUP(2,1/((tbl_Finance[Job Number]=C8&"")*(tbl_Finance[Xero Invoice No]<>"")),tbl_Finance[Xero Invoice No])&" +more"),""))) | D8: =IF(C8="","",IF(COUNTIF(lst_Jobs,C8&"")>0,"OK","CHECK")) | E8: =IF(C8="","",IFERROR(INDEX(lst_JobName,MATCH(C8&"",lst_Jobs,0)),"")) | F8: =IF(C8="","",IFERROR(INDEX(tbl_Finance[Client],MATCH(C8&"",tbl_Finance[Job Number],0)),"")) | G8: =IF(C8="","",COUNTIFS(tbl_Finance[Job Number],C8&"",tbl_Finance[Ex GST],"<>")) | H8: =IF(C8="","",SUMIFS(tbl_Finance[Ex GST],tbl_Finance[Job Number],C8&"")) | I8: =IF(C8="","",SUMIFS(tbl_Finance[Ex GST],tbl_Finance[Job Number],C8&"",tbl_Finance[Xero Invoice No],"<>")) | J8: =IF(C8="","",H8-I8) | K8: =IF(C8="","",IF(G8=0,"not invoiced yet",SUBSTITUTE(TRIM(IF(COUNTIFS(tbl_Finance[Job Number],C8&"",tbl_Finance[Cost Centre],"ONSITE")>0,"ONSITE ","")&IF(COUNTIFS(tbl_Finance[Job Number],C8&"",tbl_Finance[Cost Centre],"PRODUCTION")>0,"PRODUCTION ","")&IF(COUNTIFS(tbl_Finance[Job Number],C8&"",tbl_Finance[Cost Centre],"VIDEO")>0,"VIDEO ","")&IF(COUNTIFS(tbl_Finance[Job Number],C8&"",tbl_Finance[Cost Centre],"INTEGRATION")>0,"INTEGRATION ","")&IF(COUNTIFS(tbl_Finance[Job Number],C8&"",tbl_Finance[Cost Centre],"CONSULTING")>0,"CONSULTING ","")&IF(COUNTIFS(tbl_Finance[Job Number],C8&"",tbl_Finance[Cost Centre],"CTS")>0,"CTS ",""))," ",", "))) | M8: =IF(L8="","",HYPERLINK(IF(LEFT(L8,4)="http",L8,set_QwilrBase&L8),"Open quote")) | Q8: =IF(C8="","",IF(N(N8)+N(O8)+N(P8)=0,"Not split",IF(ROUND(N(N8)+N(O8)+N(P8),2)=ROUND(H8,2),"OK","MISMATCH"))) | U8: =IF(C8="","",N(R8)+N(S8)+N(T8)) | V8: =IF(C8="","",H8-U8) | W8: =IFERROR(V8/H8,"")
A9: =IF(C9="","",IFERROR(IF(SUMPRODUCT(MAX((tbl_Finance[Job Number]=C9&"")*(tbl_Finance[Xero Invoice No]<>"")*tbl_Finance[Date]))=0,"",SUMPRODUCT(MAX((tbl_Finance[Job Number]=C9&"")*(tbl_Finance[Xero Invoice No]<>"")*tbl_Finance[Date]))),"")) | B9: =IF(C9="","",IF(COUNTIFS(tbl_Finance[Job Number],C9&"",tbl_Finance[Xero Invoice No],"<>")=0,"",IFERROR(IF(COUNTIFS(tbl_Finance[Job Number],C9&"",tbl_Finance[Xero Invoice No],LOOKUP(2,1/((tbl_Finance[Job Number]=C9&"")*(tbl_Finance[Xero Invoice No]<>"")),tbl_Finance[Xero Invoice No]))=COUNTIFS(tbl_Finance[Job Number],C9&"",tbl_Finance[Xero Invoice No],"<>"),LOOKUP(2,1/((tbl_Finance[Job Number]=C9&"")*(tbl_Finance[Xero Invoice No]<>"")),tbl_Finance[Xero Invoice No]),LOOKUP(2,1/((tbl_Finance[Job Number]=C9&"")*(tbl_Finance[Xero Invoice No]<>"")),tbl_Finance[Xero Invoice No])&" +more"),""))) | D9: =IF(C9="","",IF(COUNTIF(lst_Jobs,C9&"")>0,"OK","CHECK")) | E9: =IF(C9="","",IFERROR(INDEX(lst_JobName,MATCH(C9&"",lst_Jobs,0)),"")) | F9: =IF(C9="","",IFERROR(INDEX(tbl_Finance[Client],MATCH(C9&"",tbl_Finance[Job Number],0)),"")) | G9: =IF(C9="","",COUNTIFS(tbl_Finance[Job Number],C9&"",tbl_Finance[Ex GST],"<>")) | H9: =IF(C9="","",SUMIFS(tbl_Finance[Ex GST],tbl_Finance[Job Number],C9&"")) | I9: =IF(C9="","",SUMIFS(tbl_Finance[Ex GST],tbl_Finance[Job Number],C9&"",tbl_Finance[Xero Invoice No],"<>")) | J9: =IF(C9="","",H9-I9) | K9: =IF(C9="","",IF(G9=0,"not invoiced yet",SUBSTITUTE(TRIM(IF(COUNTIFS(tbl_Finance[Job Number],C9&"",tbl_Finance[Cost Centre],"ONSITE")>0,"ONSITE ","")&IF(COUNTIFS(tbl_Finance[Job Number],C9&"",tbl_Finance[Cost Centre],"PRODUCTION")>0,"PRODUCTION ","")&IF(COUNTIFS(tbl_Finance[Job Number],C9&"",tbl_Finance[Cost Centre],"VIDEO")>0,"VIDEO ","")&IF(COUNTIFS(tbl_Finance[Job Number],C9&"",tbl_Finance[Cost Centre],"INTEGRATION")>0,"INTEGRATION ","")&IF(COUNTIFS(tbl_Finance[Job Number],C9&"",tbl_Finance[Cost Centre],"CONSULTING")>0,"CONSULTING ","")&IF(COUNTIFS(tbl_Finance[Job Number],C9&"",tbl_Finance[Cost Centre],"CTS")>0,"CTS ",""))," ",", "))) | M9: =IF(L9="","",HYPERLINK(IF(LEFT(L9,4)="http",L9,set_QwilrBase&L9),"Open quote")) | Q9: =IF(C9="","",IF(N(N9)+N(O9)+N(P9)=0,"Not split",IF(ROUND(N(N9)+N(O9)+N(P9),2)=ROUND(H9,2),"OK","MISMATCH"))) | U9: =IF(C9="","",N(R9)+N(S9)+N(T9)) | V9: =IF(C9="","",H9-U9) | W9: =IFERROR(V9/H9,"")
