Workbook

Sheet Read Me
B2: FY 2026-27 Revenue Tracker
B3: Rebuilt from FY27_Revenue_Tracker_v2.xlsm. Your original file has not been changed.
B5: How a record works
B6: Every record needs two things: a Type and a Department. Between them they decide which Dashboard
B7: column the money lands in.
B9: Type Invoice or WIP. Pick WIP for a work-in-progress movement, Invoice for everything else.
B10: Department Consulting, Integration, Onsite, Other, Production, Support or Video.
B11: Amount One column, always. For a WIP record this is the movement, and it can be negative.
B13: "Reports as" is calculated for you and shows which Dashboard column the record feeds. Type WIP always
B14: reports as WIP whatever the department. Otherwise the department decides: Support goes to Support,
B15: Consulting and Integration go to Consulting, and Production, Video, Other and Onsite go to Production.
B16: That mapping is on the Lists tab if you ever need to change it.
... B53: Everything here is calculated fresh, so July and August Production read lower. The lower ones are correct.

Sheet Lists
A1: Control values — edit here and every dropdown, check and report line follows
A3: Financial year start | B3: 46204 | D3: Type | F3: Department | G3: Reports as | I3: Status | K3: Yes / No
A4: Financial year end (excl.) | B4: 46569 | D4: Invoice | F4: Consulting | G4: Consulting | I4: In Progress | K4: Y
D5: WIP | F5: Integration | G5: Consulting | I5: Completed | K5: N
F6: Onsite | G6: Production | I6: Cancelled
F7: Other | G7: Production | I7: Closed
F8: Production | G8: Production
F9: Support | G9: Support
F10: Video | G10: Production
F12: A record whose Type is WIP always reports as WIP, whatever its department.

Sheet Data
A1: No. | B1: Type | C1: Date | D1: Department | E1: Reports as | F1: Status | G1: Client | H1: Job Number | I1: Description | J1: Invoice Number | K1: Amount | L1: Net Revenue | M1: Margin | N1: Margin % | O1: Date Check | P1: Duplicate Check | Q1: Notes | R1: Client Email | S1: Event Date | T1: Zoho Number | U1: Current Number | V1: Closed | W1: Invoice Posted to Xero | X1: Video Filming | Y1: Video Editing | Z1: Project Management | AA1: Video Project Management | AB1: Production Labour Hours | AC1: Video Total | AD1: Discounts Included | AE1: Discounts as % of Net | AF1: Cross Hire Expense | AG1: Labour Expense (Internal) | AH1: Qwilr Link | AI1: Labour Revenue | AJ1: Equipment Revenue | AK1: Subscription Revenue | AL1: Labour Expense (External) | AM1: Equipment Expense (Internal) | AN1: Subscription & Licences Expense
A2: =IF(COUNTA($B2:$K2)=0,"",ROW()-1) | B2: Invoice | C2: 46234 | D2: Support | E2: =IF($B2="","",IF($B2="WIP","WIP",IFERROR(INDEX(Lists!$G$4:$G$10,MATCH($D2,Lists!$F$4:$F$10,0)),"Unmapped"))) | G2: CBA | H2: 1350 | I2: CBA BNE July 2026 | J2: INV-10525 | K2: 8588.45 | L2: =IF($K2="","",IF($E2="Production",$K2-N($AD2),$K2)) | M2: =IF($E2="Production",IF($K2="","",$K2-(N($AF2)+N($AG2))),IF($E2="Consulting",IF($K2="","",$K2-(N($AL2)+N($AM2)+N($AN2))),"")) | N2: =IFERROR($M2/$K2,"") | O2: =IF(COUNTA($B2:$K2)=0,"",IF($C2="","No date",IF(AND($C2>=Lists!$B$3,$C2<Lists!$B$4),"In FY27","Outside FY27"))) | P2: =IF($E2<>"WIP","",IF($H2="","",IF(COUNTIFS($E$2:$E$20000,"<>WIP",$H$2:$H$20000,$H2)>0,"Job already invoiced",""))) | Q2: 174.05 hours | AE2: =IF($E2<>"Production","",IFERROR($AD2/$L2,""))
A3: =IF(COUNTA($B3:$K3)=0,"",ROW()-1) | B3: Invoice | C3: 46234 | D3: Support | E3: =IF($B3="","",IF($B3="WIP","WIP",IFERROR(INDEX(Lists!$G$4:$G$10,MATCH($D3,Lists!$F$4:$F$10,0)),"Unmapped"))) | G3: CBA | H3: 585/586/1755 | I3: CBP July 2026 | J3: INV-10526 | K3: 22120.57 | L3: =IF($K3="","",IF($E3="Production",$K3-N($AD3),$K3)) | M3: =IF($E3="Production",IF($K3="","",$K3-(N($AF3)+N($AG3))),IF($E3="Consulting",IF($K3="","",$K3-(N($AL3)+N($AM3)+N($AN3))),"")) | N3: =IFERROR($M3/$K3,"") | O3: =IF(COUNTA($B3:$K3)=0,"",IF($C3="","No date",IF(AND($C3>=Lists!$B$3,$C3<Lists!$B$4),"In FY27","Outside FY27"))) | P3: =IF($E3<>"WIP","",IF($H3="","",IF(COUNTIFS($E$2:$E$20000,"<>WIP",$H$2:$H$20000,$H3)>0,"Job already invoiced",""))) | Q3: Deduct 3hrs for TN 01/07 & 6hrs for NP 14/07 | AE3: =IF($E3<>"Production","",IFERROR($AD3/$L3,""))
A4: =IF(COUNTA($B4:$K4)=0,"",ROW()-1) | B4: Invoice | C4: 46234 | D4: Support | E4: =IF($B4="","",IF($B4="WIP","WIP",IFERROR(INDEX(Lists!$G$4:$G$10,MATCH($D4,Lists!$F$4:$F$10,0)),"Unmapped"))) | G4: CBA | H4: 587 | I4: CBS July 2026 | J4: INV-10527 | K4: 10720 | L4: =IF($K4="","",IF($E4="Production",$K4-N($AD4),$K4)) | M4: =IF($E4="Production",IF($K4="","",$K4-(N($AF4)+N($AG4))),IF($E4="Consulting",IF($K4="","",$K4-(N($AL4)+N($AM4)+N($AN4))),"")) | N4: =IFERROR($M4/$K4,"") | O4: =IF(COUNTA($B4:$K4)=0,"",IF($C4="","No date",IF(AND($C4>=Lists!$B$3,$C4<Lists!$B$4),"In FY27","Outside FY27"))) | P4: =IF($E4<>"WIP","",IF($H4="","",IF(COUNTIFS($E$2:$E$20000,"<>WIP",$H$2:$H$20000,$H4)>0,"Job already invoiced",""))) | AE4: =IF($E4<>"Production","",IFERROR($AD4/$L4,""))
A5: =IF(COUNTA($B5:$K5)=0,"",ROW()-1) | B5: Invoice | C5: 46234 | D5: Support | E5: =IF($B5="","",IF($B5="WIP","WIP",IFERROR(INDEX(Lists!$G$4:$G$10,MATCH($D5,Lists!$F$4:$F$10,0)),"Unmapped"))) | G5: DTTL | H5: 2846/1401/725/1400/1530/1862/2402/2849/974 | I5: DTTL Contract July 2026 | J5: INV-10528 | K5: 103625.44 | L5: =IF($K5="","",IF($E5="Production",$K5-N($AD5),$K5)) | M5: =IF($E5="Production",IF($K5="","",$K5-(N($AF5)+N($AG5))),IF($E5="Consulting",IF($K5="","",$K5-(N($AL5)+N($AM5)+N($AN5))),"")) | N5: =IFERROR($M5/$K5,"") | O5: =IF(COUNTA($B5:$K5)=0,"",IF($C5="","No date",IF(AND($C5>=Lists!$B$3,$C5<Lists!$B$4),"In FY27","Outside FY27"))) | P5: =IF($E5<>"WIP","",IF($H5="","",IF(COUNTIFS($E$2:$E$20000,"<>WIP",$H$2:$H$20000,$H5)>0,"Job already invoiced",""))) | AE5: =IF($E5<>"Production","",IFERROR($AD5/$L5,""))
A6: =IF(COUNTA($B6:$K6)=0,"",ROW()-1) | B6: Invoice | C6: 46234 | D6: Support | E6: =IF($B6="","",IF($B6="WIP","WIP",IFERROR(INDEX(Lists!$G$4:$G$10,MATCH($D6,Lists!$F$4:$F$10,0)),"Unmapped"))) | G6: BW | H6: 732/1144 | I6: BW Contract July 2026 | J6: INV-10529 | K6: 19427.5 | L6: =IF($K6="","",IF($E6="Production",$K6-N($AD6),$K6)) | M6: =IF($E6="Production",IF($K6="","",$K6-(N($AF6)+N($AG6))),IF($E6="Consulting",IF($K6="","",$K6-(N($AL6)+N($AM6)+N($AN6))),"")) | N6: =IFERROR($M6/$K6,"") | O6: =IF(COUNTA($B6:$K6)=0,"",IF($C6="","No date",IF(AND($C6>=Lists!$B$3,$C6<Lists!$B$4),"In FY27","Outside FY27"))) | P6: =IF($E6<>"WIP","",IF($H6="","",IF(COUNTIFS($E$2:$E$20000,"<>WIP",$H$2:$H$20000,$H6)>0,"Job already invoiced",""))) | AE6: =IF($E6<>"Production","",IFERROR($AD6/$L6,""))
A7: =IF(COUNTA($B7:$K7)=0,"",ROW()-1) | B7: Invoice | C7: 46234 | D7: Support | E7: =IF($B7="","",IF($B7="WIP","WIP",IFERROR(INDEX(Lists!$G$4:$G$10,MATCH($D7,Lists!$F$4:$F$10,0)),"Unmapped"))) | G7: BW | H7: 2192 | I7: BW Additionals July 2026 | J7: INV-10530 | K7: 1120 | L7: =IF($K7="","",IF($E7="Production",$K7-N($AD7),$K7)) | M7: =IF($E7="Production",IF($K7="","",$K7-(N($AF7)+N($AG7))),IF($E7="Consulting",IF($K7="","",$K7-(N($AL7)+N($AM7)+N($AN7))),"")) | N7: =IFERROR($M7/$K7,"") | O7: =IF(COUNTA($B7:$K7)=0,"",IF($C7="","No date",IF(AND($C7>=Lists!$B$3,$C7<Lists!$B$4),"In FY27","Outside FY27"))) | P7: =IF($E7<>"WIP","",IF($H7="","",IF(COUNTIFS($E$2:$E$20000,"<>WIP",$H$2:$H$20000,$H7)>0,"Job already invoiced",""))) | AE7: =IF($E7<>"Production","",IFERROR($AD7/$L7,""))
A8: =IF(COUNTA($B8:$K8)=0,"",ROW()-1) | B8: Invoice | C8: 46234 | D8: Support | E8: =IF($B8="","",IF($B8="WIP","WIP",IFERROR(INDEX(Lists!$G$4:$G$10,MATCH($D8,Lists!$F$4:$F$10,0)),"Unmapped"))) | G8: PWC | H8: 2488 | I8: PWC Brisbane July 2026 | J8: INV-10531 | K8: 7150 | L8: =IF($K8="","",IF($E8="Production",$K8-N($AD8),$K8)) | M8: =IF($E8="Production",IF($K8="","",$K8-(N($AF8)+N($AG8))),IF($E8="Consulting",IF($K8="","",$K8-(N($AL8)+N($AM8)+N($AN8))),"")) | N8: =IFERROR($M8/$K8,"") | O8: =IF(COUNTA($B8:$K8)=0,"",IF($C8="","No date",IF(AND($C8>=Lists!$B$3,$C8<Lists!$B$4),"In FY27","Outside FY27"))) | P8: =IF($E8<>"WIP","",IF($H8="","",IF(COUNTIFS($E$2:$E$20000,"<>WIP",$H$2:$H$20000,$H8)>0,"Job already invoiced",""))) | AE8: =IF($E8<>"Production","",IFERROR($AD8/$L8,""))
A9: =IF(COUNTA($B9:$K9)=0,"",ROW()-1) | B9: Invoice | C9: 46234 | D9: Support | E9: =IF($B9="","",IF($B9="WIP","WIP",IFERROR(INDEX(Lists!$G$4:$G$10,MATCH($D9,Lists!$F$4:$F$10,0)),"Unmapped"))) | G9: Gen-E | H9: 26021602 | I9: Gen-E ABS July 2026 | J9: INV-10532 | K9: 12388.8 | L9: =IF($K9="","",IF($E9="Production",$K9-N($AD9),$K9)) | M9: =IF($E9="Production",IF($K9="","",$K9-(N($AF9)+N($AG9))),IF($E9="Consulting",IF($K9="","",$K9-(N($AL9)+N($AM9)+N($AN9))),"")) | N9: =IFERROR($M9/$K9,"") | O9: =IF(COUNTA($B9:$K9)=0,"",IF($C9="","No date",IF(AND($C9>=Lists!$B$3,$C9<Lists!$B$4),"In FY27","Outside FY27"))) | P9: =IF($E9<>"WIP","",IF($H9="","",IF(COUNTIFS($E$2:$E$20000,"<>WIP",$H$2:$H$20000,$H9)>0,"Job already invoiced",""))) | AE9: =IF($E9<>"Production","",IFERROR($AD9/$L9,""))
A10: =IF(COUNTA($B10:$K10)=0,"",ROW()-1) | B10: Invoice | C10: 46234 | D10: Support | E10: =IF($B10="","",IF($B10="WIP","WIP",IFERROR(INDEX(Lists!$G$4:$G$10,MATCH($D10,Lists!$F$4:$F$10,0)),"Unmapped"))) | G10: CBA | H10: 26043001 | I10: CBA Mel July 2026 | J10: INV-10534 | K10: 11377.12 | L10: =IF($K10="","",IF($E10="Production",$K10-N($AD10),$K10)) | M10: =IF($E10="Production",IF($K10="","",$K10-(N($AF10)+N($AG10))),IF($E10="Consulting",IF($K10="","",$K10-(N($AL10)+N($AM10)+N($AN10))),"")) | N10: =IFERROR($M10/$K10,"") | O10: =IF(COUNTA($B10:$K10)=0,"",IF($C10="","No date",IF(AND($C10>=Lists!$B$3,$C10<Lists!$B$4),"In FY27","Outside FY27"))) | P10: =IF($E10<>"WIP","",IF($H10="","",IF(COUNTIFS($E$2:$E$20000,"<>WIP",$H$2:$H$20000,$H10)>0,"Job already invoiced",""))) | Q10: Deduct 8hrs CN for 03/07 | AE10: =IF($E10<>"Production","",IFERROR($AD10/$L10,""))
A11: =IF(COUNTA($B11:$K11)=0,"",ROW()-1) | B11: Invoice | C11: 46234 | D11: Support | E11: =IF($B11="","",IF($B11="WIP","WIP",IFERROR(INDEX(Lists!$G$4:$G$10,MATCH($D11,Lists!$F$4:$F$10,0)),"Unmapped"))) | G11: PWC | H11: 25101301B | I11: PWC Sydney IT July 2026 | J11: INV-10535 | K11: 11907 | L11: =IF($K11="","",IF($E11="Production",$K11-N($AD11),$K11)) | M11: =IF($E11="Production",IF($K11="","",$K11-(N($AF11)+N($AG11))),IF($E11="Consulting",IF($K11="","",$K11-(N($AL11)+N($AM11)+N($AN11))),"")) | N11: =IFERROR($M11/$K11,"") | O11: =IF(COUNTA($B11:$K11)=0,"",IF($C11="","No date",IF(AND($C11>=Lists!$B$3,$C11<Lists!$B$4),"In FY27","Outside FY27"))) | P11: =IF($E11<>"WIP","",IF($H11="","",IF(COUNTIFS($E$2:$E$20000,"<>WIP",$H$2:$H$20000,$H11)>0,"Job already invoiced",""))) | AE11: =IF($E11<>"Production","",IFERROR($AD11/$L11,""))
A12: =IF(COUNTA($B12:$K12)=0,"",ROW()-1) | B12: Invoice | C12: 46234 | D12: Support | E12: =IF($B12="","",IF($B12="WIP","WIP",IFERROR(INDEX(Lists!$G$4:$G$10,MATCH($D12,Lists!$F$4:$F$10,0)),"Unmapped"))) | G12: RICOH | H12: 2880 | I12: Ricoh Contract July 2026 | J12: INV-10536 | K12: 11860.5 | L12: =IF($K12="","",IF($E12="Production",$K12-N($AD12),$K12)) | M12: =IF($E12="Production",IF($K12="","",$K12-(N($AF12)+N($AG12))),IF($E12="Consulting",IF($K12="","",$K12-(N($AL12)+N($AM12)+N($AN12))),"")) | N12: =IFERROR($M12/$K12,"") | O12: =IF(COUNTA($B12:$K12)=0,"",IF($C12="","No date",IF(AND($C12>=Lists!$B$3,$C12<Lists!$B$4),"In FY27","Outside FY27"))) | P12: =IF($E12<>"WIP","",IF($H12="","",IF(COUNTIFS($E$2:$E$20000,"<>WIP",$H$2:$H$20000,$H12)>0,"Job already invoiced",""))) | Q12: 2 months extension | AE12: =IF($E12<>"Production","",IFERROR($AD12/$L12,""))
A13: =IF(COUNTA($B13:$K13)=0,"",ROW()-1) | B13: Invoice | C13: 46234 | D13: Support | E13: =IF($B13="","",IF($B13="WIP","WIP",IFERROR(INDEX(Lists!$G$4:$G$10,MATCH($D13,Lists!$F$4:$F$10,0)),"Unmapped"))) | G13: PWC | I13: PWC Dedicated Tech 29/07/2026 | J13: INV-10537 | K13: 340 | L13: =IF($K13="","",IF($E13="Production",$K13-N($AD13),$K13)) | M13: =IF($E13="Production",IF($K13="","",$K13-(N($AF13)+N($AG13))),IF($E13="Consulting",IF($K13="","",$K13-(N($AL13)+N($AM13)+N($AN13))),"")) | N13: =IFERROR($M13/$K13,"") | O13: =IF(COUNTA($B13:$K13)=0,"",IF($C13="","No date",IF(AND($C13>=Lists!$B$3,$C13<Lists!$B$4),"In FY27","Outside FY27"))) | P13: =IF($E13<>"WIP","",IF($H13="","",IF(COUNTIFS($E$2:$E$20000,"<>WIP",$H$2:$H$20000,$H13)>0,"Job already invoiced",""))) | Q13: 29/07/2026 4hours | AE13: =IF($E13<>"Production","",IFERROR($AD13/$L13,""))
A14: =IF(COUNTA($B14:$K14)=0,"",ROW()-1) | B14: Invoice | C14: 46234 | D14: Support | E14: =IF($B14="","",IF($B14="WIP","WIP",IFERROR(INDEX(Lists!$G$4:$G$10,MATCH($D14,Lists!$F$4:$F$10,0)),"Unmapped"))) | G14: APN | H14: 3056 | I14: APN Tech Support July 22 & 24 | J14: INV-10541 | K14: 680 | L14: =IF($K14="","",IF($E14="Production",$K14-N($AD14),$K14)) | M14: =IF($E14="Production",IF($K14="","",$K14-(N($AF14)+N($AG14))),IF($E14="Consulting",IF($K14="","",$K14-(N($AL14)+N($AM14)+N($AN14))),"")) | N14: =IFERROR($M14/$K14,"") | O14: =IF(COUNTA($B14:$K14)=0,"",IF($C14="","No date",IF(AND($C14>=Lists!$B$3,$C14<Lists!$B$4),"In FY27","Outside FY27"))) | P14: =IF($E14<>"WIP","",IF($H14="","",IF(COUNTIFS($E$2:$E$20000,"<>WIP",$H$2:$H$20000,$H14)>0,"Job already invoiced",""))) | AE14: =IF($E14<>"Production","",IFERROR($AD14/$L14,""))
A15: =IF(COUNTA($B15:$K15)=0,"",ROW()-1) | B15: Invoice | C15: 46234 | D15: Support | E15: =IF($B15="","",IF($B15="WIP","WIP",IFERROR(INDEX(Lists!$G$4:$G$10,MATCH($D15,Lists!$F$4:$F$10,0)),"Unmapped"))) | G15: PWC | H15: 20250731 | I15: PWC Pool of Hours (50 hours) | J15: INV-10539 | K15: 4250 | L15: =IF($K15="","",IF($E15="Production",$K15-N($AD15),$K15)) | M15: =IF($E15="Production",IF($K15="","",$K15-(N($AF15)+N($AG15))),IF($E15="Consulting",IF($K15="","",$K15-(N($AL15)+N($AM15)+N($AN15))),"")) | N15: =IFERROR($M15/$K15,"") | O15: =IF(COUNTA($B15:$K15)=0,"",IF($C15="","No date",IF(AND($C15>=Lists!$B$3,$C15<Lists!$B$4),"In FY27","Outside FY27"))) | P15: =IF($E15<>"WIP","",IF($H15="","",IF(COUNTIFS($E$2:$E$20000,"<>WIP",$H$2:$H$20000,$H15)>0,"Job already invoiced",""))) | Q15: PO2601703215 | AE15: =IF($E15<>"Production","",IFERROR($AD15/$L15,""))
A16: =IF(COUNTA($B16:$K16)=0,"",ROW()-1) | B16: Invoice | C16: 46234 | D16: Support | E16: =IF($B16="","",IF($B16="WIP","WIP",IFERROR(INDEX(Lists!$G$4:$G$10,MATCH($D16,Lists!$F$4:$F$10,0)),"Unmapped"))) | G16: CBA | H16: 1668 | I16: AH Support 02/07/2026 | J16: INV-10542 | K16: 180 | L16: =IF($K16="","",IF($E16="Production",$K16-N($AD16),$K16)) | M16: =IF($E16="Production",IF($K16="","",$K16-(N($AF16)+N($AG16))),IF($E16="Consulting",IF($K16="","",$K16-(N($AL16)+N($AM16)+N($AN16))),"")) | N16: =IFERROR($M16/$K16,"") | O16: =IF(COUNTA($B16:$K16)=0,"",IF($C16="","No date",IF(AND($C16>=Lists!$B$3,$C16<Lists!$B$4),"In FY27","Outside FY27"))) | P16: =IF($E16<>"WIP","",IF($H16="","",IF(COUNTIFS($E$2:$E$20000,"<>WIP",$H$2:$H$20000,$H16)>0,"Job already invoiced",""))) | AE16: =IF($E16<>"Production","",IFERROR($AD16/$L16,""))
A17: =IF(COUNTA($B17:$K17)=0,"",ROW()-1) | B17: Invoice | C17: 46234 | D17: Support | E17: =IF($B17="","",IF($B17="WIP","WIP",IFERROR(INDEX(Lists!$G$4:$G$10,MATCH($D17,Lists!$F$4:$F$10,0)),"Unmapped"))) | G17: CBA | H17: 1668 | I17: DT Support 02/07/2026 | J17: INV-10543 | K17: 425 | L17: =IF($K17="","",IF($E17="Production",$K17-N($AD17),$K17)) | M17: =IF($E17="Production",IF($K17="","",$K17-(N($AF17)+N($AG17))),IF($E17="Consulting",IF($K17="","",$K17-(N($AL17)+N($AM17)+N($AN17))),"")) | N17: =IFERROR($M17/$K17,"") | O17: =IF(COUNTA($B17:$K17)=0,"",IF($C17="","No date",IF(AND($C17>=Lists!$B$3,$C17<Lists!$B$4),"In FY27","Outside FY27"))) | P17: =IF($E17<>"WIP","",IF($H17="","",IF(COUNTIFS($E$2:$E$20000,"<>WIP",$H$2:$H$20000,$H17)>0,"Job already invoiced",""))) | AE17: =IF($E17<>"Production","",IFERROR($AD17/$L17,""))
A18: =IF(COUNTA($B18:$K18)=0,"",ROW()-1) | B18: Invoice | C18: 46234 | D18: Support | E18: =IF($B18="","",IF($B18="WIP","WIP",IFERROR(INDEX(Lists!$G$4:$G$10,MATCH($D18,Lists!$F$4:$F$10,0)),"Unmapped"))) | G18: CBA | H18: 1668 | I18: DT Support 23/07/2026 | J18: INV-10544 | K18: 510 | L18: =IF($K18="","",IF($E18="Production",$K18-N($AD18),$K18)) | M18: =IF($E18="Production",IF($K18="","",$K18-(N($AF18)+N($AG18))),IF($E18="Consulting",IF($K18="","",$K18-(N($AL18)+N($AM18)+N($AN18))),"")) | N18: =IFERROR($M18/$K18,"") | O18: =IF(COUNTA($B18:$K18)=0,"",IF($C18="","No date",IF(AND($C18>=Lists!$B$3,$C18<Lists!$B$4),"In FY27","Outside FY27"))) | P18: =IF($E18<>"WIP","",IF($H18="","",IF(COUNTIFS($E$2:$E$20000,"<>WIP",$H$2:$H$20000,$H18)>0,"Job already invoiced",""))) | AE18: =IF($E18<>"Production","",IFERROR($AD18/$L18,""))
A19: =IF(COUNTA($B19:$K19)=0,"",ROW()-1) | B19: Invoice | C19: 46233 | D19: Support | E19: =IF($B19="","",IF($B19="WIP","WIP",IFERROR(INDEX(Lists!$G$4:$G$10,MATCH($D19,Lists!$F$4:$F$10,0)),"Unmapped"))) | G19: PWC | H19: 2540 | I19: PWC Dedicated Tech 30/07/2026 | J19: INV-10545 | K19: 340 | L19: =IF($K19="","",IF($E19="Production",$K19-N($AD19),$K19)) | M19: =IF($E19="Production",IF($K19="","",$K19-(N($AF19)+N($AG19))),IF($E19="Consulting",IF($K19="","",$K19-(N($AL19)+N($AM19)+N($AN19))),"")) | N19: =IFERROR($M19/$K19,"") | O19: =IF(COUNTA($B19:$K19)=0,"",IF($C19="","No date",IF(AND($C19>=Lists!$B$3,$C19<Lists!$B$4),"In FY27","Outside FY27"))) | P19: =IF($E19<>"WIP","",IF($H19="","",IF(COUNTIFS($E$2:$E$20000,"<>WIP",$H$2:$H$20000,$H19)>0,"Job already invoiced",""))) | Q19: PO2601703274 | AE19: =IF($E19<>"Production","",IFERROR($AD19/$L19,""))
A20: =IF(COUNTA($B20:$K20)=0,"",ROW()-1) | B20: Invoice | C20: 46233 | D20: Support | E20: =IF($B20="","",IF($B20="WIP","WIP",IFERROR(INDEX(Lists!$G$4:$G$10,MATCH($D20,Lists!$F$4:$F$10,0)),"Unmapped"))) | G20: DTTL | H20: 26062501/2347 | I20: DH Travel 06-07/07 & Ad-hoc Tech Support 30/07 & Market Shapers | J20: INV-10546 | K20: 1672.5 | L20: =IF($K20="","",IF($E20="Production",$K20-N($AD20),$K20)) | M20: =IF($E20="Production",IF($K20="","",$K20-(N($AF20)+N($AG20))),IF($E20="Consulting",IF($K20="","",$K20-(N($AL20)+N($AM20)+N($AN20))),"")) | N20: =IFERROR($M20/$K20,"") | O20: =IF(COUNTA($B20:$K20)=0,"",IF($C20="","No date",IF(AND($C20>=Lists!$B$3,$C20<Lists!$B$4),"In FY27","Outside FY27"))) | P20: =IF($E20<>"WIP","",IF($H20="","",IF(COUNTIFS($E$2:$E$20000,"<>WIP",$H$2:$H$20000,$H20)>0,"Job already invoiced",""))) | AE20: =IF($E20<>"Production","",IFERROR($AD20/$L20,""))
A21: =IF(COUNTA($B21:$K21)=0,"",ROW()-1) | B21: Invoice | C21: 46233 | D21: Support | E21: =IF($B21="","",IF($B21="WIP","WIP",IFERROR(INDEX(Lists!$G$4:$G$10,MATCH($D21,Lists!$F$4:$F$10,0)),"Unmapped"))) | G21: APN | H21: 2026021101 | I21: APN Quarterly AV Support | J21: INV-10550 | K21: 1670 | L21: =IF($K21="","",IF($E21="Production",$K21-N($AD21),$K21)) | M21: =IF($E21="Production",IF($K21="","",$K21-(N($AF21)+N($AG21))),IF($E21="Consulting",IF($K21="","",$K21-(N($AL21)+N($AM21)+N($AN21))),"")) | N21: =IFERROR($M21/$K21,"") | O21: =IF(COUNTA($B21:$K21)=0,"",IF($C21="","No date",IF(AND($C21>=Lists!$B$3,$C21<Lists!$B$4),"In FY27","Outside FY27"))) | P21: =IF($E21<>"WIP","",IF($H21="","",IF(COUNTIFS($E$2:$E$20000,"<>WIP",$H$2:$H$20000,$H21)>0,"Job already invoiced",""))) | Q21: Invoice 1/2 | AE21: =IF($E21<>"Production","",IFERROR($AD21/$L21,""))
A22: =IF(COUNTA($B22:$K22)=0,"",ROW()-1) | B22: Invoice | C22: 46234 | D22: Support | E22: =IF($B22="","",IF($B22="WIP","WIP",IFERROR(INDEX(Lists!$G$4:$G$10,MATCH($D22,Lists!$F$4:$F$10,0)),"Unmapped"))) | G22: Aware Super | H22: 26022301 | I22: Aware Super Contract July 2026 | J22: INV-10551 | K22: 11000 | L22: =IF($K22="","",IF($E22="Production",$K22-N($AD22),$K22)) | M22: =IF($E22="Production",IF($K22="","",$K22-(N($AF22)+N($AG22))),IF($E22="Consulting",IF($K22="","",$K22-(N($AL22)+N($AM22)+N($AN22))),"")) | N22: =IFERROR($M22/$K22,"") | O22: =IF(COUNTA($B22:$K22)=0,"",IF($C22="","No date",IF(AND($C22>=Lists!$B$3,$C22<Lists!$B$4),"In FY27","Outside FY27"))) | P22: =IF($E22<>"WIP","",IF($H22="","",IF(COUNTIFS($E$2:$E$20000,"<>WIP",$H$2:$H$20000,$H22)>0,"Job already invoiced",""))) | AE22: =IF($E22<>"Production","",IFERROR($AD22/$L22,""))
A23: =IF(COUNTA($B23:$K23)=0,"",ROW()-1) | B23: Invoice | C23: 46265 | D23: Support | E23: =IF($B23="","",IF($B23="WIP","WIP",IFERROR(INDEX(Lists!$G$4:$G$10,MATCH($D23,Lists!$F$4:$F$10,0)),"Unmapped"))) | G23: DTTL | H23: 2608502 | I23: DTTL Additionals August 2026 | J23: INV-10597 | K23: 8419.62 | L23: =IF($K23="","",IF($E23="Production",$K23-N($AD23),$K23)) | M23: =IF($E23="Production",IF($K23="","",$K23-(N($AF23)+N($AG23))),IF($E23="Consulting",IF($K23="","",$K23-(N($AL23)+N($AM23)+N($AN23))),"")) | N23: =IFERROR($M23/$K23,"") | O23: =IF(COUNTA($B23:$K23)=0,"",IF($C23="","No date",IF(AND($C23>=Lists!$B$3,$C23<Lists!$B$4),"In FY27","Outside FY27"))) | P23: =IF($E23<>"WIP","",IF($H23="","",IF(COUNTIFS($E$2:$E$20000,"<>WIP",$H$2:$H$20000,$H23)>0,"Job already invoiced",""))) | AE23: =IF($E23<>"Production","",IFERROR($AD23/$L23,""))
A24: =IF(COUNTA($B24:$K24)=0,"",ROW()-1) | B24: Invoice | D24: Support | E24: =IF($B24="","",IF($B24="WIP","WIP",IFERROR(INDEX(Lists!$G$4:$G$10,MATCH($D24,Lists!$F$4:$F$10,0)),"Unmapped"))) | G24: PWC | H24: 26073102 | I24: Pool of Hours - National AV/IT Support | J24: INV-10598 | K24: 8500 | L24: =IF($K24="","",IF($E24="Production",$K24-N($AD24),$K24)) | M24: =IF($E24="Production",IF($K24="","",$K24-(N($AF24)+N($AG24))),IF($E24="Consulting",IF($K24="","",$K24-(N($AL24)+N($AM24)+N($AN24))),"")) | N24: =IFERROR($M24/$K24,"") | O24: =IF(COUNTA($B24:$K24)=0,"",IF($C24="","No date",IF(AND($C24>=Lists!$B$3,$C24<Lists!$B$4),"In FY27","Outside FY27"))) | P24: =IF($E24<>"WIP","",IF($H24="","",IF(COUNTIFS($E$2:$E$20000,"<>WIP",$H$2:$H$20000,$H24)>0,"Job already invoiced",""))) | Q24: PO2601703509 | AE24: =IF($E24<>"Production","",IFERROR($AD24/$L24,""))
A25: =IF(COUNTA($B25:$K25)=0,"",ROW()-1) | B25: Invoice | D25: Support | E25: =IF($B25="","",IF($B25="WIP","WIP",IFERROR(INDEX(Lists!$G$4:$G$10,MATCH($D25,Lists!$F$4:$F$10,0)),"Unmapped"))) | G25: CBA | H25: 1350 | I25: CBA BNE August 2026 | J25: INV-10565 | K25: 5940 | L25: =IF($K25="","",IF($E25="Production",$K25-N($AD25),$K25)) | M25: =IF($E25="Production",IF($K25="","",$K25-(N($AF25)+N($AG25))),IF($E25="Consulting",IF($K25="","",$K25-(N($AL25)+N($AM25)+N($AN25))),"")) | N25: =IFERROR($M25/$K25,"") | O25: =IF(COUNTA($B25:$K25)=0,"",IF($C25="","No date",IF(AND($C25>=Lists!$B$3,$C25<Lists!$B$4),"In FY27","Outside FY27"))) | P25: =IF($E25<>"WIP","",IF($H25="","",IF(COUNTIFS($E$2:$E$20000,"<>WIP",$H$2:$H$20000,$H25)>0,"Job already invoiced",""))) | AE25: =IF($E25<>"Production","",IFERROR($AD25/$L25,""))
A26: =IF(COUNTA($B26:$K26)=0,"",ROW()-1) | B26: Invoice | D26: Support | E26: =IF($B26="","",IF($B26="WIP","WIP",IFERROR(INDEX(Lists!$G$4:$G$10,MATCH($D26,Lists!$F$4:$F$10,0)),"Unmapped"))) | G26: CBA | H26: 585/586/1755 | I26: CBP August 2026 | J26: INV-10566 | K26: 22708 | L26: =IF($K26="","",IF($E26="Production",$K26-N($AD26),$K26)) | M26: =IF($E26="Production",IF($K26="","",$K26-(N($AF26)+N($AG26))),IF($E26="Consulting",IF($K26="","",$K26-(N($AL26)+N($AM26)+N($AN26))),"")) | N26: =IFERROR($M26/$K26,"") | O26: =IF(COUNTA($B26:$K26)=0,"",IF($C26="","No date",IF(AND($C26>=Lists!$B$3,$C26<Lists!$B$4),"In FY27","Outside FY27"))) | P26: =IF($E26<>"WIP","",IF($H26="","",IF(COUNTIFS($E$2:$E$20000,"<>WIP",$H$2:$H$20000,$H26)>0,"Job already invoiced",""))) | AE26: =IF($E26<>"Production","",IFERROR($AD26/$L26,""))
A27: =IF(COUNTA($B27:$K27)=0,"",ROW()-1) | B27: Invoice | D27: Support | E27: =IF($B27="","",IF($B27="WIP","WIP",IFERROR(INDEX(Lists!$G$4:$G$10,MATCH($D27,Lists!$F$4:$F$10,0)),"Unmapped"))) | G27: CBA | H27: 587 | I27: CBS August 2026 | J27: INV-10568 | K27: 10720 | L27: =IF($K27="","",IF($E27="Production",$K27-N($AD27),$K27)) | M27: =IF($E27="Production",IF($K27="","",$K27-(N($AF27)+N($AG27))),IF($E27="Consulting",IF($K27="","",$K27-(N($AL27)+N($AM27)+N($AN27))),"")) | N27: =IFERROR($M27/$K27,"") | O27: =IF(COUNTA($B27:$K27)=0,"",IF($C27="","No date",IF(AND($C27>=Lists!$B$3,$C27<Lists!$B$4),"In FY27","Outside FY27"))) | P27: =IF($E27<>"WIP","",IF($H27="","",IF(COUNTIFS($E$2:$E$20000,"<>WIP",$H$2:$H$20000,$H27)>0,"Job already invoiced",""))) | AE27: =IF($E27<>"Production","",IFERROR($AD27/$L27,""))
A28: =IF(COUNTA($B28:$K28)=0,"",ROW()-1) | B28: Invoice | C28: 46265 | D28: Support | E28: =IF($B28="","",IF($B28="WIP","WIP",IFERROR(INDEX(Lists!$G$4:$G$10,MATCH($D28,Lists!$F$4:$F$10,0)),"Unmapped"))) | G28: DTTL | H28: 2846/1401/725/1400/1530/1862/2402/2849/974 | I28: DTTL Contract August 2026 | J28: INV-10569 | K28: 103625.44 | L28: =IF($K28="","",IF($E28="Production",$K28-N($AD28),$K28)) | M28: =IF($E28="Production",IF($K28="","",$K28-(N($AF28)+N($AG28))),IF($E28="Consulting",IF($K28="","",$K28-(N($AL28)+N($AM28)+N($AN28))),"")) | N28: =IFERROR($M28/$K28,"") | O28: =IF(COUNTA($B28:$K28)=0,"",IF($C28="","No date",IF(AND($C28>=Lists!$B$3,$C28<Lists!$B$4),"In FY27","Outside FY27"))) | P28: =IF($E28<>"WIP","",IF($H28="","",IF(COUNTIFS($E$2:$E$20000,"<>WIP",$H$2:$H$20000,$H28)>0,"Job already invoiced",""))) | AE28: =IF($E28<>"Production","",IFERROR($AD28/$L28,""))
A29: =IF(COUNTA($B29:$K29)=0,"",ROW()-1) | B29: Invoice | D29: Support | E29: =IF($B29="","",IF($B29="WIP","WIP",IFERROR(INDEX(Lists!$G$4:$G$10,MATCH($D29,Lists!$F$4:$F$10,0)),"Unmapped"))) | G29: BW | H29: 732/1144 | I29: BW Contract August 2026 | J29: INV-10570 | K29: 15113.75 | L29: =IF($K29="","",IF($E29="Production",$K29-N($AD29),$K29)) | M29: =IF($E29="Production",IF($K29="","",$K29-(N($AF29)+N($AG29))),IF($E29="Consulting",IF($K29="","",$K29-(N($AL29)+N($AM29)+N($AN29))),"")) | N29: =IFERROR($M29/$K29,"") | O29: =IF(COUNTA($B29:$K29)=0,"",IF($C29="","No date",IF(AND($C29>=Lists!$B$3,$C29<Lists!$B$4),"In FY27","Outside FY27"))) | P29: =IF($E29<>"WIP","",IF($H29="","",IF(COUNTIFS($E$2:$E$20000,"<>WIP",$H$2:$H$20000,$H29)>0,"Job already invoiced",""))) | AE29: =IF($E29<>"Production","",IFERROR($AD29/$L29,""))
A30: =IF(COUNTA($B30:$K30)=0,"",ROW()-1) | B30: Invoice | D30: Support | E30: =IF($B30="","",IF($B30="WIP","WIP",IFERROR(INDEX(Lists!$G$4:$G$10,MATCH($D30,Lists!$F$4:$F$10,0)),"Unmapped"))) | G30: BW | H30: 2192 | I30: BW Additionals August 2026 | J30: INV-10571 | K30: 2080 | L30: =IF($K30="","",IF($E30="Production",$K30-N($AD30),$K30)) | M30: =IF($E30="Production",IF($K30="","",$K30-(N($AF30)+N($AG30))),IF($E30="Consulting",IF($K30="","",$K30-(N($AL30)+N($AM30)+N($AN30))),"")) | N30: =IFERROR($M30/$K30,"") | O30: =IF(COUNTA($B30:$K30)=0,"",IF($C30="","No date",IF(AND($C30>=Lists!$B$3,$C30<Lists!$B$4),"In FY27","Outside FY27"))) | P30: =IF($E30<>"WIP","",IF($H30="","",IF(COUNTIFS($E$2:$E$20000,"<>WIP",$H$2:$H$20000,$H30)>0,"Job already invoiced",""))) | AE30: =IF($E30<>"Production","",IFERROR($AD30/$L30,""))
A31: =IF(COUNTA($B31:$K31)=0,"",ROW()-1) | B31: Invoice | D31: Support | E31: =IF($B31="","",IF($B31="WIP","WIP",IFERROR(INDEX(Lists!$G$4:$G$10,MATCH($D31,Lists!$F$4:$F$10,0)),"Unmapped"))) | G31: PWC | H31: 2488 | I31: PWC Brisbane August 2026 | J31: INV-10572 | K31: 7150 | L31: =IF($K31="","",IF($E31="Production",$K31-N($AD31),$K31)) | M31: =IF($E31="Production",IF($K31="","",$K31-(N($AF31)+N($AG31))),IF($E31="Consulting",IF($K31="","",$K31-(N($AL31)+N($AM31)+N($AN31))),"")) | N31: =IFERROR($M31/$K31,"") | O31: =IF(COUNTA($B31:$K31)=0,"",IF($C31="","No date",IF(AND($C31>=Lists!$B$3,$C31<Lists!$B$4),"In FY27","Outside FY27"))) | P31: =IF($E31<>"WIP","",IF($H31="","",IF(COUNTIFS($E$2:$E$20000,"<>WIP",$H$2:$H$20000,$H31)>0,"Job already invoiced",""))) | AE31: =IF($E31<>"Production","",IFERROR($AD31/$L31,""))
A32: =IF(COUNTA($B32:$K32)=0,"",ROW()-1) | B32: Invoice | D32: Support | E32: =IF($B32="","",IF($B32="WIP","WIP",IFERROR(INDEX(Lists!$G$4:$G$10,MATCH($D32,Lists!$F$4:$F$10,0)),"Unmapped"))) | G32: Gen-E | H32: 26021602 | I32: Gen-E ABS August 2026 | J32: INV-10573 | K32: 12388.8 | L32: =IF($K32="","",IF($E32="Production",$K32-N($AD32),$K32)) | M32: =IF($E32="Production",IF($K32="","",$K32-(N($AF32)+N($AG32))),IF($E32="Consulting",IF($K32="","",$K32-(N($AL32)+N($AM32)+N($AN32))),"")) | N32: =IFERROR($M32/$K32,"") | O32: =IF(COUNTA($B32:$K32)=0,"",IF($C32="","No date",IF(AND($C32>=Lists!$B$3,$C32<Lists!$B$4),"In FY27","Outside FY27"))) | P32: =IF($E32<>"WIP","",IF($H32="","",IF(COUNTIFS($E$2:$E$20000,"<>WIP",$H$2:$H$20000,$H32)>0,"Job already invoiced",""))) | AE32: =IF($E32<>"Production","",IFERROR($AD32/$L32,""))
A33: =IF(COUNTA($B33:$K33)=0,"",ROW()-1) | B33: Invoice | D33: Support | E33: =IF($B33="","",IF($B33="WIP","WIP",IFERROR(INDEX(Lists!$G$4:$G$10,MATCH($D33,Lists!$F$4:$F$10,0)),"Unmapped"))) | G33: CBA | H33: 26043001 | I33: CBA Mel August 2026 | J33: INV-10582 | K33: 11377.12 | L33: =IF($K33="","",IF($E33="Production",$K33-N($AD33),$K33)) | M33: =IF($E33="Production",IF($K33="","",$K33-(N($AF33)+N($AG33))),IF($E33="Consulting",IF($K33="","",$K33-(N($AL33)+N($AM33)+N($AN33))),"")) | N33: =IFERROR($M33/$K33,"") | O33: =IF(COUNTA($B33:$K33)=0,"",IF($C33="","No date",IF(AND($C33>=Lists!$B$3,$C33<Lists!$B$4),"In FY27","Outside FY27"))) | P33: =IF($E33<>"WIP","",IF($H33="","",IF(COUNTIFS($E$2:$E$20000,"<>WIP",$H$2:$H$20000,$H33)>0,"Job already invoiced",""))) | AE33: =IF($E33<>"Production","",IFERROR($AD33/$L33,""))
A34: =IF(COUNTA($B34:$K34)=0,"",ROW()-1) | B34: Invoice | C34: 46265 | D34: Support | E34: =IF($B34="","",IF($B34="WIP","WIP",IFERROR(INDEX(Lists!$G$4:$G$10,MATCH($D34,Lists!$F$4:$F$10,0)),"Unmapped"))) | G34: Aware Super | H34: 26022301 | I34: Aware Super Contract August 2026 | J34: INV-10583 | K34: 11000 | L34: =IF($K34="","",IF($E34="Production",$K34-N($AD34),$K34)) | M34: =IF($E34="Production",IF($K34="","",$K34-(N($AF34)+N($AG34))),IF($E34="Consulting",IF($K34="","",$K34-(N($AL34)+N($AM34)+N($AN34))),"")) | N34: =IFERROR($M34/$K34,"") | O34: =IF(COUNTA($B34:$K34)=0,"",IF($C34="","No date",IF(AND($C34>=Lists!$B$3,$C34<Lists!$B$4),"In FY27","Outside FY27"))) | P34: =IF($E34<>"WIP","",IF($H34="","",IF(COUNTIFS($E$2:$E$20000,"<>WIP",$H$2:$H$20000,$H34)>0,"Job already invoiced",""))) | Q34: Split TBC | AE34: =IF($E34<>"Production","",IFERROR($AD34/$L34,""))
A35: =IF(COUNTA($B35:$K35)=0,"",ROW()-1) | B35: Invoice | D35: Support | E35: =IF($B35="","",IF($B35="WIP","WIP",IFERROR(INDEX(Lists!$G$4:$G$10,MATCH($D35,Lists!$F$4:$F$10,0)),"Unmapped"))) | G35: PWC | H35: 25101301B | I35: PWC Sydney IT August 2026 | J35: INV-10585 | K35: 11907 | L35: =IF($K35="","",IF($E35="Production",$K35-N($AD35),$K35)) | M35: =IF($E35="Production",IF($K35="","",$K35-(N($AF35)+N($AG35))),IF($E35="Consulting",IF($K35="","",$K35-(N($AL35)+N($AM35)+N($AN35))),"")) | N35: =IFERROR($M35/$K35,"") | O35: =IF(COUNTA($B35:$K35)=0,"",IF($C35="","No date",IF(AND($C35>=Lists!$B$3,$C35<Lists!$B$4),"In FY27","Outside FY27"))) | P35: =IF($E35<>"WIP","",IF($H35="","",IF(COUNTIFS($E$2:$E$20000,"<>WIP",$H$2:$H$20000,$H35)>0,"Job already invoiced",""))) | AE35: =IF($E35<>"Production","",IFERROR($AD35/$L35,""))
A36: =IF(COUNTA($B36:$K36)=0,"",ROW()-1) | B36: Invoice | D36: Support | E36: =IF($B36="","",IF($B36="WIP","WIP",IFERROR(INDEX(Lists!$G$4:$G$10,MATCH($D36,Lists!$F$4:$F$10,0)),"Unmapped"))) | G36: TWG | H36: 26081301 | I36: EY Support Technician BNE | K36: 3740 | L36: =IF($K36="","",IF($E36="Production",$K36-N($AD36),$K36)) | M36: =IF($E36="Production",IF($K36="","",$K36-(N($AF36)+N($AG36))),IF($E36="Consulting",IF($K36="","",$K36-(N($AL36)+N($AM36)+N($AN36))),"")) | N36: =IFERROR($M36/$K36,"") | O36: =IF(COUNTA($B36:$K36)=0,"",IF($C36="","No date",IF(AND($C36>=Lists!$B$3,$C36<Lists!$B$4),"In FY27","Outside FY27"))) | P36: =IF($E36<>"WIP","",IF($H36="","",IF(COUNTIFS($E$2:$E$20000,"<>WIP",$H$2:$H$20000,$H36)>0,"Job already invoiced",""))) | Q36: November | AE36: =IF($E36<>"Production","",IFERROR($AD36/$L36,""))
A37: =IF(COUNTA($B37:$K37)=0,"",ROW()-1) | B37: Invoice | C37: 46205 | D37: Production | E37: =IF($B37="","",IF($B37="WIP","WIP",IFERROR(INDEX(Lists!$G$4:$G$10,MATCH($D37,Lists!$F$4:$F$10,0)),"Unmapped"))) | G37: Elkiem | H37: 2602309 | I37: Studio Support | 1.7.26 | J37: INV-10513 | K37: 380 | L37: =IF($K37="","",IF($E37="Production",$K37-N($AD37),$K37)) | M37: =IF($E37="Production",IF($K37="","",$K37-(N($AF37)+N($AG37))),IF($E37="Consulting",IF($K37="","",$K37-(N($AL37)+N($AM37)+N($AN37))),"")) | N37: =IFERROR($M37/$K37,"") | O37: =IF(COUNTA($B37:$K37)=0,"",IF($C37="","No date",IF(AND($C37>=Lists!$B$3,$C37<Lists!$B$4),"In FY27","Outside FY27"))) | P37: =IF($E37<>"WIP","",IF($H37="","",IF(COUNTIFS($E$2:$E$20000,"<>WIP",$H$2:$H$20000,$H37)>0,"Job already invoiced",""))) | R37: Ben.woodlock@elkiem.com | S37: 7/1/2026 | T37: 2602309 | U37: 5879 | V37: Y | W37: Y | AB37: 4 | AE37: =IF($E37<>"Production","",IFERROR($AD37/$L37,""))
A38: =IF(COUNTA($B38:$K38)=0,"",ROW()-1) | B38: Invoice | C38: 46210 | D38: Production | E38: =IF($B38="","",IF($B38="WIP","WIP",IFERROR(INDEX(Lists!$G$4:$G$10,MATCH($D38,Lists!$F$4:$F$10,0)),"Unmapped"))) | G38: RSNSW | H38: 26032301 | I38: Ordinary General Meeting | 1.7.26 | J38: INV-10519 | K38: 3071 | L38: =IF($K38="","",IF($E38="Production",$K38-N($AD38),$K38)) | M38: =IF($E38="Production",IF($K38="","",$K38-(N($AF38)+N($AG38))),IF($E38="Consulting",IF($K38="","",$K38-(N($AL38)+N($AM38)+N($AN38))),"")) | N38: =IFERROR($M38/$K38,"") | O38: =IF(COUNTA($B38:$K38)=0,"",IF($C38="","No date",IF(AND($C38>=Lists!$B$3,$C38<Lists!$B$4),"In FY27","Outside FY27"))) | P38: =IF($E38<>"WIP","",IF($H38="","",IF(COUNTIFS($E$2:$E$20000,"<>WIP",$H$2:$H$20000,$H38)>0,"Job already invoiced",""))) | R38: lindsay.botten@outlook.com | S38: 7/1/2026 | T38: 26032301 | U38: 5924 | V38: Y | W38: Y | X38: 4 | AB38: 10 | AC38: 1029 | AD38: 334 | AE38: =IF($E38<>"Production","",IFERROR($AD38/$L38,""))
A39: =IF(COUNTA($B39:$K39)=0,"",ROW()-1) | B39: Invoice | C39: 46210 | D39: Production | E39: =IF($B39="","",IF($B39="WIP","WIP",IFERROR(INDEX(Lists!$G$4:$G$10,MATCH($D39,Lists!$F$4:$F$10,0)),"Unmapped"))) | G39: PWC | H39: 26062201 | I39: Tax and Legal Webcast 2.7.26 | J39: INV-10515 | K39: 1925 | L39: =IF($K39="","",IF($E39="Production",$K39-N($AD39),$K39)) | M39: =IF($E39="Production",IF($K39="","",$K39-(N($AF39)+N($AG39))),IF($E39="Consulting",IF($K39="","",$K39-(N($AL39)+N($AM39)+N($AN39))),"")) | N39: =IFERROR($M39/$K39,"") | O39: =IF(COUNTA($B39:$K39)=0,"",IF($C39="","No date",IF(AND($C39>=Lists!$B$3,$C39<Lists!$B$4),"In FY27","Outside FY27"))) | P39: =IF($E39<>"WIP","",IF($H39="","",IF(COUNTIFS($E$2:$E$20000,"<>WIP",$H$2:$H$20000,$H39)>0,"Job already invoiced",""))) | R39: libby.kovac@au.pwc.com | S39: 7/2/2026 | T39: 26062201 | U39: 6076 | V39: Y | W39: Y | X39: 8 | Z39: 1 | AB39: 8 | AC39: 970 | AE39: =IF($E39<>"Production","",IFERROR($AD39/$L39,""))
A40: =IF(COUNTA($B40:$K40)=0,"",ROW()-1) | B40: Invoice | C40: 46219 | D40: Production | E40: =IF($B40="","",IF($B40="WIP","WIP",IFERROR(INDEX(Lists!$G$4:$G$10,MATCH($D40,Lists!$F$4:$F$10,0)),"Unmapped"))) | G40: Elkiem - PM** Cancelled | H40: 2605802 | I40: Elkiem Studio Support | 15.7.26 | J40: INV-10524 | K40: 261.25 | L40: =IF($K40="","",IF($E40="Production",$K40-N($AD40),$K40)) | M40: =IF($E40="Production",IF($K40="","",$K40-(N($AF40)+N($AG40))),IF($E40="Consulting",IF($K40="","",$K40-(N($AL40)+N($AM40)+N($AN40))),"")) | N40: =IFERROR($M40/$K40,"") | O40: =IF(COUNTA($B40:$K40)=0,"",IF($C40="","No date",IF(AND($C40>=Lists!$B$3,$C40<Lists!$B$4),"In FY27","Outside FY27"))) | P40: =IF($E40<>"WIP","",IF($H40="","",IF(COUNTIFS($E$2:$E$20000,"<>WIP",$H$2:$H$20000,$H40)>0,"Job already invoiced",""))) | R40: Ben.woodlock@elkiem.com | S40: 7/15/2026 | T40: 2605802 | U40: 6013 | V40: Y | W40: Y | Z40: 2 | AB40: 4 | AE40: =IF($E40<>"Production","",IFERROR($AD40/$L40,""))
A41: =IF(COUNTA($B41:$K41)=0,"",ROW()-1) | B41: Invoice | C41: 46210 | D41: Production | E41: =IF($B41="","",IF($B41="WIP","WIP",IFERROR(INDEX(Lists!$G$4:$G$10,MATCH($D41,Lists!$F$4:$F$10,0)),"Unmapped"))) | G41: Litecard | H41: 2607701 | I41: Screen & Mic Hire 16.7.26 | J41: INV-10518 | K41: 500 | L41: =IF($K41="","",IF($E41="Production",$K41-N($AD41),$K41)) | M41: =IF($E41="Production",IF($K41="","",$K41-(N($AF41)+N($AG41))),IF($E41="Consulting",IF($K41="","",$K41-(N($AL41)+N($AM41)+N($AN41))),"")) | N41: =IFERROR($M41/$K41,"") | O41: =IF(COUNTA($B41:$K41)=0,"",IF($C41="","No date",IF(AND($C41>=Lists!$B$3,$C41<Lists!$B$4),"In FY27","Outside FY27"))) | P41: =IF($E41<>"WIP","",IF($H41="","",IF(COUNTIFS($E$2:$E$20000,"<>WIP",$H$2:$H$20000,$H41)>0,"Job already invoiced",""))) | R41: brian@litecard.com.au | S41: 7/16/2026 | T41: 2607701 | U41: 6089 | V41: Y | W41: Y | AB41: 2 | AD41: 465 | AE41: =IF($E41<>"Production","",IFERROR($AD41/$L41,""))
A42: =IF(COUNTA($B42:$K42)=0,"",ROW()-1) | B42: Invoice | C42: 46216 | D42: Video | E42: =IF($B42="","",IF($B42="WIP","WIP",IFERROR(INDEX(Lists!$G$4:$G$10,MATCH($D42,Lists!$F$4:$F$10,0)),"Unmapped"))) | G42: Litecard | H42: 2607701 | I42: Litecard - Event Photographer - 16.7.26 | J42: INV-10522 | K42: 550 | L42: =IF($K42="","",IF($E42="Production",$K42-N($AD42),$K42)) | M42: =IF($E42="Production",IF($K42="","",$K42-(N($AF42)+N($AG42))),IF($E42="Consulting",IF($K42="","",$K42-(N($AL42)+N($AM42)+N($AN42))),"")) | N42: =IFERROR($M42/$K42,"") | O42: =IF(COUNTA($B42:$K42)=0,"",IF($C42="","No date",IF(AND($C42>=Lists!$B$3,$C42<Lists!$B$4),"In FY27","Outside FY27"))) | P42: =IF($E42<>"WIP","",IF($H42="","",IF(COUNTIFS($E$2:$E$20000,"<>WIP",$H$2:$H$20000,$H42)>0,"Job already invoiced",""))) | R42: brian@litecard.com.au | S42: 46219 | T42: 2607701 | U42: 6102 | V42: Y | W42: Y | X42: 4 | AC42: 550 | AE42: =IF($E42<>"Production","",IFERROR($AD42/$L42,""))
A43: =IF(COUNTA($B43:$K43)=0,"",ROW()-1) | B43: Invoice | C43: 46234 | D43: Production | E43: =IF($B43="","",IF($B43="WIP","WIP",IFERROR(INDEX(Lists!$G$4:$G$10,MATCH($D43,Lists!$F$4:$F$10,0)),"Unmapped"))) | G43: Microsoft | H43: 26052703 | I43: Microsoft Town Hall 21.7.26 | J43: INV-10554 | K43: 12587 | L43: =IF($K43="","",IF($E43="Production",$K43-N($AD43),$K43)) | M43: =IF($E43="Production",IF($K43="","",$K43-(N($AF43)+N($AG43))),IF($E43="Consulting",IF($K43="","",$K43-(N($AL43)+N($AM43)+N($AN43))),"")) | N43: =IFERROR($M43/$K43,"") | O43: =IF(COUNTA($B43:$K43)=0,"",IF($C43="","No date",IF(AND($C43>=Lists!$B$3,$C43<Lists!$B$4),"In FY27","Outside FY27"))) | P43: =IF($E43<>"WIP","",IF($H43="","",IF(COUNTIFS($E$2:$E$20000,"<>WIP",$H$2:$H$20000,$H43)>0,"Job already invoiced",""))) | R43: helenkingham@microsoft.com | S43: 46224 | T43: 26052703 | U43: 6034 | V43: Y | W43: Y | X43: 4 | AB43: 44 | AC43: 1702 | AD43: 580 | AE43: =IF($E43<>"Production","",IFERROR($AD43/$L43,"")) | AF43: 631.5
A44: =IF(COUNTA($B44:$K44)=0,"",ROW()-1) | B44: Invoice | C44: 46232 | D44: Production | E44: =IF($B44="","",IF($B44="WIP","WIP",IFERROR(INDEX(Lists!$G$4:$G$10,MATCH($D44,Lists!$F$4:$F$10,0)),"Unmapped"))) | G44: Optiver | H44: 26041603 | I44: Mid-Year Town Hall 23.7.26 | J44: INV-10538 | K44: 745 | L44: =IF($K44="","",IF($E44="Production",$K44-N($AD44),$K44)) | M44: =IF($E44="Production",IF($K44="","",$K44-(N($AF44)+N($AG44))),IF($E44="Consulting",IF($K44="","",$K44-(N($AL44)+N($AM44)+N($AN44))),"")) | N44: =IFERROR($M44/$K44,"") | O44: =IF(COUNTA($B44:$K44)=0,"",IF($C44="","No date",IF(AND($C44>=Lists!$B$3,$C44<Lists!$B$4),"In FY27","Outside FY27"))) | P44: =IF($E44<>"WIP","",IF($H44="","",IF(COUNTIFS($E$2:$E$20000,"<>WIP",$H$2:$H$20000,$H44)>0,"Job already invoiced",""))) | R44: jo.rosewarne@optiver.com.au | S44: 46226 | T44: 26041603 | U44: 6085 | V44: Y | W44: Y | AB44: 4 | AE44: =IF($E44<>"Production","",IFERROR($AD44/$L44,""))
A45: =IF(COUNTA($B45:$K45)=0,"",ROW()-1) | B45: Invoice | C45: 46234 | D45: Production | E45: =IF($B45="","",IF($B45="WIP","WIP",IFERROR(INDEX(Lists!$G$4:$G$10,MATCH($D45,Lists!$F$4:$F$10,0)),"Unmapped"))) | G45: Arup | H45: 2605403 | I45: Oves Awards Night 23.7.26 | J45: INV-10540 | K45: 5636 | L45: =IF($K45="","",IF($E45="Production",$K45-N($AD45),$K45)) | M45: =IF($E45="Production",IF($K45="","",$K45-(N($AF45)+N($AG45))),IF($E45="Consulting",IF($K45="","",$K45-(N($AL45)+N($AM45)+N($AN45))),"")) | N45: =IFERROR($M45/$K45,"") | O45: =IF(COUNTA($B45:$K45)=0,"",IF($C45="","No date",IF(AND($C45>=Lists!$B$3,$C45<Lists!$B$4),"In FY27","Outside FY27"))) | P45: =IF($E45<>"WIP","",IF($H45="","",IF(COUNTIFS($E$2:$E$20000,"<>WIP",$H$2:$H$20000,$H45)>0,"Job already invoiced",""))) | R45: Timothy.Hicks@arup.com | S45: 46226 | T45: 2605403 | U45: 5956 | V45: Y | W45: Y | AB45: 16 | AC45: 176 | AD45: 839 | AE45: =IF($E45<>"Production","",IFERROR($AD45/$L45,""))
A46: =IF(COUNTA($B46:$K46)=0,"",ROW()-1) | B46: Invoice | C46: 46234 | D46: Production | E46: =IF($B46="","",IF($B46="WIP","WIP",IFERROR(INDEX(Lists!$G$4:$G$10,MATCH($D46,Lists!$F$4:$F$10,0)),"Unmapped"))) | G46: On24 | H46: 2607901 | I46: KWM Event 23.7.26 (PO #25962) | J46: INV-10552 | K46: 2575 | L46: =IF($K46="","",IF($E46="Production",$K46-N($AD46),$K46)) | M46: =IF($E46="Production",IF($K46="","",$K46-(N($AF46)+N($AG46))),IF($E46="Consulting",IF($K46="","",$K46-(N($AL46)+N($AM46)+N($AN46))),"")) | N46: =IFERROR($M46/$K46,"") | O46: =IF(COUNTA($B46:$K46)=0,"",IF($C46="","No date",IF(AND($C46>=Lists!$B$3,$C46<Lists!$B$4),"In FY27","Outside FY27"))) | P46: =IF($E46<>"WIP","",IF($H46="","",IF(COUNTIFS($E$2:$E$20000,"<>WIP",$H$2:$H$20000,$H46)>0,"Job already invoiced",""))) | R46: lisa.caraccio@on24.com | S46: 46226 | T46: 2607901 | U46: 6097 | V46: Y | W46: Y | AB46: 6 | AD46: 95 | AE46: =IF($E46<>"Production","",IFERROR($AD46/$L46,""))
A47: =IF(COUNTA($B47:$K47)=0,"",ROW()-1) | B47: Invoice | C47: 46223 | D47: Production | E47: =IF($B47="","",IF($B47="WIP","WIP",IFERROR(INDEX(Lists!$G$4:$G$10,MATCH($D47,Lists!$F$4:$F$10,0)),"Unmapped"))) | G47: Skykick Ranger | H47: 26063001 | I47: Sydney Performance Dry Hire 26.7.26 | J47: INV-10533 | K47: 975 | L47: =IF($K47="","",IF($E47="Production",$K47-N($AD47),$K47)) | M47: =IF($E47="Production",IF($K47="","",$K47-(N($AF47)+N($AG47))),IF($E47="Consulting",IF($K47="","",$K47-(N($AL47)+N($AM47)+N($AN47))),"")) | N47: =IFERROR($M47/$K47,"") | O47: =IF(COUNTA($B47:$K47)=0,"",IF($C47="","No date",IF(AND($C47>=Lists!$B$3,$C47<Lists!$B$4),"In FY27","Outside FY27"))) | P47: =IF($E47<>"WIP","",IF($H47="","",IF(COUNTIFS($E$2:$E$20000,"<>WIP",$H$2:$H$20000,$H47)>0,"Job already invoiced",""))) | R47: park_za_888@hotmail.com | S47: 46229 | T47: 26063001 | U47: 6114 | V47: Y | W47: Y | AB47: 0 | AE47: =IF($E47<>"Production","",IFERROR($AD47/$L47,"")) | AF47: 850
A48: =IF(COUNTA($B48:$K48)=0,"",ROW()-1) | B48: Invoice | C48: 46234 | D48: Production | E48: =IF($B48="","",IF($B48="WIP","WIP",IFERROR(INDEX(Lists!$G$4:$G$10,MATCH($D48,Lists!$F$4:$F$10,0)),"Unmapped"))) | G48: Ventia | H48: 2604202 | I48: Ventia Awards 28 & 30.7.26 (PO 4701355678) | J48: INV-10557 | K48: 52749.78 | L48: =IF($K48="","",IF($E48="Production",$K48-N($AD48),$K48)) | M48: =IF($E48="Production",IF($K48="","",$K48-(N($AF48)+N($AG48))),IF($E48="Consulting",IF($K48="","",$K48-(N($AL48)+N($AM48)+N($AN48))),"")) | N48: =IFERROR($M48/$K48,"") | O48: =IF(COUNTA($B48:$K48)=0,"",IF($C48="","No date",IF(AND($C48>=Lists!$B$3,$C48<Lists!$B$4),"In FY27","Outside FY27"))) | P48: =IF($E48<>"WIP","",IF($H48="","",IF(COUNTIFS($E$2:$E$20000,"<>WIP",$H$2:$H$20000,$H48)>0,"Job already invoiced",""))) | R48: amy.johnson@ventia.com | S48: 46231 | T48: 2604202 | U48: 6099 | V48: Y | W48: Y | Z48: 8 | AB48: 142 | AC48: 970 | AE48: =IF($E48<>"Production","",IFERROR($AD48/$L48,""))
A49: =IF(COUNTA($B49:$K49)=0,"",ROW()-1) | B49: Invoice | C49: 46234 | D49: Production | E49: =IF($B49="","",IF($B49="WIP","WIP",IFERROR(INDEX(Lists!$G$4:$G$10,MATCH($D49,Lists!$F$4:$F$10,0)),"Unmapped"))) | G49: PWC | H49: 26062202 | I49: Early Careers Webcast 29.7.26 | J49: INV-10555 | K49: 1925 | L49: =IF($K49="","",IF($E49="Production",$K49-N($AD49),$K49)) | M49: =IF($E49="Production",IF($K49="","",$K49-(N($AF49)+N($AG49))),IF($E49="Consulting",IF($K49="","",$K49-(N($AL49)+N($AM49)+N($AN49))),"")) | N49: =IFERROR($M49/$K49,"") | O49: =IF(COUNTA($B49:$K49)=0,"",IF($C49="","No date",IF(AND($C49>=Lists!$B$3,$C49<Lists!$B$4),"In FY27","Outside FY27"))) | P49: =IF($E49<>"WIP","",IF($H49="","",IF(COUNTIFS($E$2:$E$20000,"<>WIP",$H$2:$H$20000,$H49)>0,"Job already invoiced",""))) | R49: libby.kovac@au.pwc.com | S49: 46232 | T49: 26062202 | U49: 6075 | V49: Y | W49: Y | X49: 8 | Z49: 1 | AB49: 8 | AD49: 4452.72 | AE49: =IF($E49<>"Production","",IFERROR($AD49/$L49,"")) | AF49: 19155.02
A50: =IF(COUNTA($B50:$K50)=0,"",ROW()-1) | B50: Invoice | C50: 46234 | D50: Production | E50: =IF($B50="","",IF($B50="WIP","WIP",IFERROR(INDEX(Lists!$G$4:$G$10,MATCH($D50,Lists!$F$4:$F$10,0)),"Unmapped"))) | G50: Ventia (Melbourne) | H50: 26071303 | I50: Melbourne Office Event 30&31.7.26 | J50: INV-10558 | K50: 11570 | L50: =IF($K50="","",IF($E50="Production",$K50-N($AD50),$K50)) | M50: =IF($E50="Production",IF($K50="","",$K50-(N($AF50)+N($AG50))),IF($E50="Consulting",IF($K50="","",$K50-(N($AL50)+N($AM50)+N($AN50))),"")) | N50: =IFERROR($M50/$K50,"") | O50: =IF(COUNTA($B50:$K50)=0,"",IF($C50="","No date",IF(AND($C50>=Lists!$B$3,$C50<Lists!$B$4),"In FY27","Outside FY27"))) | P50: =IF($E50<>"WIP","",IF($H50="","",IF(COUNTIFS($E$2:$E$20000,"<>WIP",$H$2:$H$20000,$H50)>0,"Job already invoiced",""))) | R50: Lauren.Quinn@ventia.com | S50: 46233 | T50: 26071303 | U50: 6125 | V50: Y | W50: Y | AB50: 40 | AE50: =IF($E50<>"Production","",IFERROR($AD50/$L50,"")) | AF50: 9487
A51: =IF(COUNTA($B51:$K51)=0,"",ROW()-1) | B51: Invoice | C51: 46234 | D51: Production | E51: =IF($B51="","",IF($B51="WIP","WIP",IFERROR(INDEX(Lists!$G$4:$G$10,MATCH($D51,Lists!$F$4:$F$10,0)),"Unmapped"))) | G51: Garvan | H51: 26061702 | I51: Morning Tea Event 31.7.26 (PO-58817) | J51: INV-10556 | K51: 1120 | L51: =IF($K51="","",IF($E51="Production",$K51-N($AD51),$K51)) | M51: =IF($E51="Production",IF($K51="","",$K51-(N($AF51)+N($AG51))),IF($E51="Consulting",IF($K51="","",$K51-(N($AL51)+N($AM51)+N($AN51))),"")) | N51: =IFERROR($M51/$K51,"") | O51: =IF(COUNTA($B51:$K51)=0,"",IF($C51="","No date",IF(AND($C51>=Lists!$B$3,$C51<Lists!$B$4),"In FY27","Outside FY27"))) | P51: =IF($E51<>"WIP","",IF($H51="","",IF(COUNTIFS($E$2:$E$20000,"<>WIP",$H$2:$H$20000,$H51)>0,"Job already invoiced",""))) | R51: l.cordt@garvan.org.au | S51: 46234 | T51: 26061702 | U51: 6066 | V51: Y | W51: Y | AB51: 10 | AE51: =IF($E51<>"Production","",IFERROR($AD51/$L51,""))
A52: =IF(COUNTA($B52:$K52)=0,"",ROW()-1) | B52: Invoice | C52: 46234 | D52: Production | E52: =IF($B52="","",IF($B52="WIP","WIP",IFERROR(INDEX(Lists!$G$4:$G$10,MATCH($D52,Lists!$F$4:$F$10,0)),"Unmapped"))) | G52: CBA | H52: 26061701 | I52: CBA LES July 2026 | J52: INV-10559 | K52: 8882.5 | L52: =IF($K52="","",IF($E52="Production",$K52-N($AD52),$K52)) | M52: =IF($E52="Production",IF($K52="","",$K52-(N($AF52)+N($AG52))),IF($E52="Consulting",IF($K52="","",$K52-(N($AL52)+N($AM52)+N($AN52))),"")) | N52: =IFERROR($M52/$K52,"") | O52: =IF(COUNTA($B52:$K52)=0,"",IF($C52="","No date",IF(AND($C52>=Lists!$B$3,$C52<Lists!$B$4),"In FY27","Outside FY27"))) | P52: =IF($E52<>"WIP","",IF($H52="","",IF(COUNTIFS($E$2:$E$20000,"<>WIP",$H$2:$H$20000,$H52)>0,"Job already invoiced",""))) | R52: steve.chezzi@cba.com.au | S52: 46234 | T52: 26061701 | U52: 6145 | V52: Y | W52: Y | AE52: =IF($E52<>"Production","",IFERROR($AD52/$L52,""))
A53: =IF(COUNTA($B53:$K53)=0,"",ROW()-1) | B53: Invoice | C53: 46247 | D53: Production | E53: =IF($B53="","",IF($B53="WIP","WIP",IFERROR(INDEX(Lists!$G$4:$G$10,MATCH($D53,Lists!$F$4:$F$10,0)),"Unmapped"))) | G53: CBA | H53: 26061701 | I53: CBA LES July 2026 Loading Reversal | J53: CN-10563 | K53: -332.5 | L53: =IF($K53="","",IF($E53="Production",$K53-N($AD53),$K53)) | M53: =IF($E53="Production",IF($K53="","",$K53-(N($AF53)+N($AG53))),IF($E53="Consulting",IF($K53="","",$K53-(N($AL53)+N($AM53)+N($AN53))),"")) | N53: =IFERROR($M53/$K53,"") | O53: =IF(COUNTA($B53:$K53)=0,"",IF($C53="","No date",IF(AND($C53>=Lists!$B$3,$C53<Lists!$B$4),"In FY27","Outside FY27"))) | P53: =IF($E53<>"WIP","",IF($H53="","",IF(COUNTIFS($E$2:$E$20000,"<>WIP",$H$2:$H$20000,$H53)>0,"Job already invoiced",""))) | R53: steve.chezzi@cba.com.au | S53: 46234 | T53: 26061701 | U53: 6145 | V53: Y | W53: Y | AE53: =IF($E53<>"Production","",IFERROR($AD53/$L53,""))
A54: =IF(COUNTA($B54:$K54)=0,"",ROW()-1) | B54: Invoice | C54: 46247 | D54: Production | E54: =IF($B54="","",IF($B54="WIP","WIP",IFERROR(INDEX(Lists!$G$4:$G$10,MATCH($D54,Lists!$F$4:$F$10,0)),"Unmapped"))) | G54: RSNSW | H54: 2512804 | I54: Ordinary General Meeting 5.8.26 | K54: 3261 | L54: =IF($K54="","",IF($E54="Production",$K54-N($AD54),$K54)) | M54: =IF($E54="Production",IF($K54="","",$K54-(N($AF54)+N($AG54))),IF($E54="Consulting",IF($K54="","",$K54-(N($AL54)+N($AM54)+N($AN54))),"")) | N54: =IFERROR($M54/$K54,"") | O54: =IF(COUNTA($B54:$K54)=0,"",IF($C54="","No date",IF(AND($C54>=Lists!$B$3,$C54<Lists!$B$4),"In FY27","Outside FY27"))) | P54: =IF($E54<>"WIP","",IF($H54="","",IF(COUNTIFS($E$2:$E$20000,"<>WIP",$H$2:$H$20000,$H54)>0,"Job already invoiced",""))) | R54: lindsay.botten@outlook.com | S54: 46239 | T54: 2512804 | U54: 5826 | V54: Y | W54: Y | X54: 4 | AB54: 12 | AC54: 1029 | AD54: 334 | AE54: =IF($E54<>"Production","",IFERROR($AD54/$L54,""))
A55: =IF(COUNTA($B55:$K55)=0,"",ROW()-1) | B55: Invoice | C55: 46247 | D55: Production | E55: =IF($B55="","",IF($B55="WIP","WIP",IFERROR(INDEX(Lists!$G$4:$G$10,MATCH($D55,Lists!$F$4:$F$10,0)),"Unmapped"))) | G55: Garvan | H55: 2607703 | I55: YPO Event 6.8.26 (PO-58493) | K55: 2152.5 | L55: =IF($K55="","",IF($E55="Production",$K55-N($AD55),$K55)) | M55: =IF($E55="Production",IF($K55="","",$K55-(N($AF55)+N($AG55))),IF($E55="Consulting",IF($K55="","",$K55-(N($AL55)+N($AM55)+N($AN55))),"")) | N55: =IFERROR($M55/$K55,"") | O55: =IF(COUNTA($B55:$K55)=0,"",IF($C55="","No date",IF(AND($C55>=Lists!$B$3,$C55<Lists!$B$4),"In FY27","Outside FY27"))) | P55: =IF($E55<>"WIP","",IF($H55="","",IF(COUNTIFS($E$2:$E$20000,"<>WIP",$H$2:$H$20000,$H55)>0,"Job already invoiced",""))) | R55: m.gonzalezhuerta@garvan.org.au | S55: 46240 | T55: 2607703 | U55: 6088 | V55: Y | W55: Y | AB55: 11 | AD55: 0 | AE55: =IF($E55<>"Production","",IFERROR($AD55/$L55,""))
A56: =IF(COUNTA($B56:$K56)=0,"",ROW()-1) | B56: Invoice | C56: 46247 | D56: Production | E56: =IF($B56="","",IF($B56="WIP","WIP",IFERROR(INDEX(Lists!$G$4:$G$10,MATCH($D56,Lists!$F$4:$F$10,0)),"Unmapped"))) | G56: PwC | H56: 26072902 | I56: AI Townhall 6.8.26 (PO2601703328) | K56: 1650 | L56: =IF($K56="","",IF($E56="Production",$K56-N($AD56),$K56)) | M56: =IF($E56="Production",IF($K56="","",$K56-(N($AF56)+N($AG56))),IF($E56="Consulting",IF($K56="","",$K56-(N($AL56)+N($AM56)+N($AN56))),"")) | N56: =IFERROR($M56/$K56,"") | O56: =IF(COUNTA($B56:$K56)=0,"",IF($C56="","No date",IF(AND($C56>=Lists!$B$3,$C56<Lists!$B$4),"In FY27","Outside FY27"))) | P56: =IF($E56<>"WIP","",IF($H56="","",IF(COUNTIFS($E$2:$E$20000,"<>WIP",$H$2:$H$20000,$H56)>0,"Job already invoiced",""))) | R56: libby.kovac@au.pwc.com | S56: 46240 | T56: 26072902 | U56: 6128 | V56: Y | W56: Y | X56: 4 | Z56: 1 | AB56: 10 | AC56: 485 | AE56: =IF($E56<>"Production","",IFERROR($AD56/$L56,"")) | AF56: 1092.36
A57: =IF(COUNTA($B57:$K57)=0,"",ROW()-1) | B57: Invoice | C57: 46255 | D57: Production | E57: =IF($B57="","",IF($B57="WIP","WIP",IFERROR(INDEX(Lists!$G$4:$G$10,MATCH($D57,Lists!$F$4:$F$10,0)),"Unmapped"))) | G57: Elkiem | H57: 26071901 | I57: Studio Support 11.8.26 | J57: INV-10580 | K57: 380 | L57: =IF($K57="","",IF($E57="Production",$K57-N($AD57),$K57)) | M57: =IF($E57="Production",IF($K57="","",$K57-(N($AF57)+N($AG57))),IF($E57="Consulting",IF($K57="","",$K57-(N($AL57)+N($AM57)+N($AN57))),"")) | N57: =IFERROR($M57/$K57,"") | O57: =IF(COUNTA($B57:$K57)=0,"",IF($C57="","No date",IF(AND($C57>=Lists!$B$3,$C57<Lists!$B$4),"In FY27","Outside FY27"))) | P57: =IF($E57<>"WIP","",IF($H57="","",IF(COUNTIFS($E$2:$E$20000,"<>WIP",$H$2:$H$20000,$H57)>0,"Job already invoiced",""))) | R57: ben.woodlock@elkiem.com | S57: 46245 | T57: 26071901 | U57: 6127 | V57: Y | W57: Y | AB57: 4 | AE57: =IF($E57<>"Production","",IFERROR($AD57/$L57,""))
A58: =IF(COUNTA($B58:$K58)=0,"",ROW()-1) | B58: Invoice | C58: 46255 | D58: Production | E58: =IF($B58="","",IF($B58="WIP","WIP",IFERROR(INDEX(Lists!$G$4:$G$10,MATCH($D58,Lists!$F$4:$F$10,0)),"Unmapped"))) | G58: CEO Institute | H58: 26063002 | I58: CEO Connect 11.8.26 | J58: INV-10581 | K58: 8260.35 | L58: =IF($K58="","",IF($E58="Production",$K58-N($AD58),$K58)) | M58: =IF($E58="Production",IF($K58="","",$K58-(N($AF58)+N($AG58))),IF($E58="Consulting",IF($K58="","",$K58-(N($AL58)+N($AM58)+N($AN58))),"")) | N58: =IFERROR($M58/$K58,"") | O58: =IF(COUNTA($B58:$K58)=0,"",IF($C58="","No date",IF(AND($C58>=Lists!$B$3,$C58<Lists!$B$4),"In FY27","Outside FY27"))) | P58: =IF($E58<>"WIP","",IF($H58="","",IF(COUNTIFS($E$2:$E$20000,"<>WIP",$H$2:$H$20000,$H58)>0,"Job already invoiced",""))) | R58: taniaa@ceoinstitute.com | S58: 46245 | T58: 26063002 | U58: 6084 | V58: Y | W58: Y | X58: 7 | Z58: 2 | AB58: 37 | AD58: 2104.4 | AE58: =IF($E58<>"Production","",IFERROR($AD58/$L58,""))
A59: =IF(COUNTA($B59:$K59)=0,"",ROW()-1) | B59: Invoice | C59: 46259 | D59: Production | E59: =IF($B59="","",IF($B59="WIP","WIP",IFERROR(INDEX(Lists!$G$4:$G$10,MATCH($D59,Lists!$F$4:$F$10,0)),"Unmapped"))) | G59: PwC | H59: 26072903 | I59: GB Webcast 11.8.26 | J59: INV-10577 | K59: 4300 | L59: =IF($K59="","",IF($E59="Production",$K59-N($AD59),$K59)) | M59: =IF($E59="Production",IF($K59="","",$K59-(N($AF59)+N($AG59))),IF($E59="Consulting",IF($K59="","",$K59-(N($AL59)+N($AM59)+N($AN59))),"")) | N59: =IFERROR($M59/$K59,"") | O59: =IF(COUNTA($B59:$K59)=0,"",IF($C59="","No date",IF(AND($C59>=Lists!$B$3,$C59<Lists!$B$4),"In FY27","Outside FY27"))) | P59: =IF($E59<>"WIP","",IF($H59="","",IF(COUNTIFS($E$2:$E$20000,"<>WIP",$H$2:$H$20000,$H59)>0,"Job already invoiced",""))) | R59: libby.kovac@au.pwc.com | S59: 46245 | T59: 26072903 | U59: 6134 | V59: Y | W59: Y | X59: 9 | AB59: 9 | AC59: 3270 | AE59: =IF($E59<>"Production","",IFERROR($AD59/$L59,"")) | AF59: 1092.36
A60: =IF(COUNTA($B60:$K60)=0,"",ROW()-1) | B60: Invoice | C60: 46259 | D60: Production | E60: =IF($B60="","",IF($B60="WIP","WIP",IFERROR(INDEX(Lists!$G$4:$G$10,MATCH($D60,Lists!$F$4:$F$10,0)),"Unmapped"))) | G60: MUFG | H60: 26061104 | I60: MUFG - Suncorp FYR | J60: INV - 10584 INV - 10585 | K60: 28652.25 | L60: =IF($K60="","",IF($E60="Production",$K60-N($AD60),$K60)) | M60: =IF($E60="Production",IF($K60="","",$K60-(N($AF60)+N($AG60))),IF($E60="Consulting",IF($K60="","",$K60-(N($AL60)+N($AM60)+N($AN60))),"")) | N60: =IFERROR($M60/$K60,"") | O60: =IF(COUNTA($B60:$K60)=0,"",IF($C60="","No date",IF(AND($C60>=Lists!$B$3,$C60<Lists!$B$4),"In FY27","Outside FY27"))) | P60: =IF($E60<>"WIP","",IF($H60="","",IF(COUNTIFS($E$2:$E$20000,"<>WIP",$H$2:$H$20000,$H60)>0,"Job already invoiced",""))) | R60: events@cm.mpms.mufg.com | S60: 46246 | T60: 26061104 | U60: Proj: 0016 | V60: Y | W60: Y | X60: 8 | Z60: 12 | AB60: 104 | AC60: 3017 | AD60: 5271.5 | AE60: =IF($E60<>"Production","",IFERROR($AD60/$L60,"")) | AF60: 980.16
A61: =IF(COUNTA($B61:$K61)=0,"",ROW()-1) | B61: Invoice | C61: 46247 | D61: Production | E61: =IF($B61="","",IF($B61="WIP","WIP",IFERROR(INDEX(Lists!$G$4:$G$10,MATCH($D61,Lists!$F$4:$F$10,0)),"Unmapped"))) | G61: CBA | H61: 26061105 | I61: CBA FYR 2026 (Order PO3308779) | K61: 12170 | L61: =IF($K61="","",IF($E61="Production",$K61-N($AD61),$K61)) | M61: =IF($E61="Production",IF($K61="","",$K61-(N($AF61)+N($AG61))),IF($E61="Consulting",IF($K61="","",$K61-(N($AL61)+N($AM61)+N($AN61))),"")) | N61: =IFERROR($M61/$K61,"") | O61: =IF(COUNTA($B61:$K61)=0,"",IF($C61="","No date",IF(AND($C61>=Lists!$B$3,$C61<Lists!$B$4),"In FY27","Outside FY27"))) | P61: =IF($E61<>"WIP","",IF($H61="","",IF(COUNTIFS($E$2:$E$20000,"<>WIP",$H$2:$H$20000,$H61)>0,"Job already invoiced",""))) | R61: Rebecca.Rodger@cba.com.au | S61: 46246 | T61: 26061105 | U61: 6093 | V61: Y | W61: Y | AB61: 16 | AD61: 1680 | AE61: =IF($E61<>"Production","",IFERROR($AD61/$L61,"")) | AF61: 2436.2
A62: =IF(COUNTA($B62:$K62)=0,"",ROW()-1) | B62: Invoice | C62: 46255 | D62: Production | E62: =IF($B62="","",IF($B62="WIP","WIP",IFERROR(INDEX(Lists!$G$4:$G$10,MATCH($D62,Lists!$F$4:$F$10,0)),"Unmapped"))) | G62: AGL | H62: 2605401 | I62: AGL FYR - Investor Briefing | J62: INV-10579 | K62: 14271.5 | L62: =IF($K62="","",IF($E62="Production",$K62-N($AD62),$K62)) | M62: =IF($E62="Production",IF($K62="","",$K62-(N($AF62)+N($AG62))),IF($E62="Consulting",IF($K62="","",$K62-(N($AL62)+N($AM62)+N($AN62))),"")) | N62: =IFERROR($M62/$K62,"") | O62: =IF(COUNTA($B62:$K62)=0,"",IF($C62="","No date",IF(AND($C62>=Lists!$B$3,$C62<Lists!$B$4),"In FY27","Outside FY27"))) | P62: =IF($E62<>"WIP","",IF($H62="","",IF(COUNTIFS($E$2:$E$20000,"<>WIP",$H$2:$H$20000,$H62)>0,"Job already invoiced",""))) | R62: KDraisey@agl.com.au | S62: 46246 | T62: 2605401 | U62: Proj: 0019 | V62: Y | W62: Y | Y62: 8 | AB62: 18 | AC62: 1806 | AD62: 2351.5 | AE62: =IF($E62<>"Production","",IFERROR($AD62/$L62,"")) | AF62: 3520.25
A63: =IF(COUNTA($B63:$K63)=0,"",ROW()-1) | B63: Invoice | C63: 46255 | D63: Production | E63: =IF($B63="","",IF($B63="WIP","WIP",IFERROR(INDEX(Lists!$G$4:$G$10,MATCH($D63,Lists!$F$4:$F$10,0)),"Unmapped"))) | G63: AGL | H63: 2605402 | I63: AGL FYR - Employee Town Hall | J63: INV-10578 | K63: 7144.75 | L63: =IF($K63="","",IF($E63="Production",$K63-N($AD63),$K63)) | M63: =IF($E63="Production",IF($K63="","",$K63-(N($AF63)+N($AG63))),IF($E63="Consulting",IF($K63="","",$K63-(N($AL63)+N($AM63)+N($AN63))),"")) | N63: =IFERROR($M63/$K63,"") | O63: =IF(COUNTA($B63:$K63)=0,"",IF($C63="","No date",IF(AND($C63>=Lists!$B$3,$C63<Lists!$B$4),"In FY27","Outside FY27"))) | P63: =IF($E63<>"WIP","",IF($H63="","",IF(COUNTIFS($E$2:$E$20000,"<>WIP",$H$2:$H$20000,$H63)>0,"Job already invoiced",""))) | R63: KDraisey@agl.com.au | S63: 46246 | T63: 2605402 | U63: Proj: 0019 | V63: Y | W63: Y | X63: 4 | AB63: 31 | AC63: 845.75 | AD63: 1309.25 | AE63: =IF($E63<>"Production","",IFERROR($AD63/$L63,"")) | AF63: 706.67
A64: =IF(COUNTA($B64:$K64)=0,"",ROW()-1) | B64: Invoice | C64: 46255 | D64: Production | E64: =IF($B64="","",IF($B64="WIP","WIP",IFERROR(INDEX(Lists!$G$4:$G$10,MATCH($D64,Lists!$F$4:$F$10,0)),"Unmapped"))) | G64: ASX | H64: 2608604 | I64: ASX Employee Townhall 13.8.26 | J64: INV-10599 | K64: 1510 | L64: =IF($K64="","",IF($E64="Production",$K64-N($AD64),$K64)) | M64: =IF($E64="Production",IF($K64="","",$K64-(N($AF64)+N($AG64))),IF($E64="Consulting",IF($K64="","",$K64-(N($AL64)+N($AM64)+N($AN64))),"")) | N64: =IFERROR($M64/$K64,"") | O64: =IF(COUNTA($B64:$K64)=0,"",IF($C64="","No date",IF(AND($C64>=Lists!$B$3,$C64<Lists!$B$4),"In FY27","Outside FY27"))) | P64: =IF($E64<>"WIP","",IF($H64="","",IF(COUNTIFS($E$2:$E$20000,"<>WIP",$H$2:$H$20000,$H64)>0,"Job already invoiced",""))) | R64: Aimee.Kuipers@asx.com.au | S64: 46247 | T64: 2608604 | U64: 6138 | V64: Y | W64: Y | X64: 4 | Z64: 2 | AB64: 6 | AC64: 3357 | AD64: 25 | AE64: =IF($E64<>"Production","",IFERROR($AD64/$L64,""))
A65: =IF(COUNTA($B65:$K65)=0,"",ROW()-1) | B65: Invoice | D65: Production | E65: =IF($B65="","",IF($B65="WIP","WIP",IFERROR(INDEX(Lists!$G$4:$G$10,MATCH($D65,Lists!$F$4:$F$10,0)),"Unmapped"))) | G65: ASX | H65: 26052702 | I65: ASX FYR Briefing 13.8.26 | J65: INV-10576 | K65: 37579 | L65: =IF($K65="","",IF($E65="Production",$K65-N($AD65),$K65)) | M65: =IF($E65="Production",IF($K65="","",$K65-(N($AF65)+N($AG65))),IF($E65="Consulting",IF($K65="","",$K65-(N($AL65)+N($AM65)+N($AN65))),"")) | N65: =IFERROR($M65/$K65,"") | O65: =IF(COUNTA($B65:$K65)=0,"",IF($C65="","No date",IF(AND($C65>=Lists!$B$3,$C65<Lists!$B$4),"In FY27","Outside FY27"))) | P65: =IF($E65<>"WIP","",IF($H65="","",IF(COUNTIFS($E$2:$E$20000,"<>WIP",$H$2:$H$20000,$H65)>0,"Job already invoiced",""))) | R65: simon.starr@asx.com.au | S65: 46247 | T65: 26052702 | U65: 6045 | V65: Y | W65: Y | Z65: 6 | AB65: 78 | AD65: 2181 | AE65: =IF($E65<>"Production","",IFERROR($AD65/$L65,"")) | AF65: 5005.78
A66: =IF(COUNTA($B66:$K66)=0,"",ROW()-1) | B66: Invoice | D66: Video | E66: =IF($B66="","",IF($B66="WIP","WIP",IFERROR(INDEX(Lists!$G$4:$G$10,MATCH($D66,Lists!$F$4:$F$10,0)),"Unmapped"))) | G66: ASX | H66: 26072906 | I66: ASX Advisory Group on Corporate Governance | K66: 4601.7 | L66: =IF($K66="","",IF($E66="Production",$K66-N($AD66),$K66)) | M66: =IF($E66="Production",IF($K66="","",$K66-(N($AF66)+N($AG66))),IF($E66="Consulting",IF($K66="","",$K66-(N($AL66)+N($AM66)+N($AN66))),"")) | N66: =IFERROR($M66/$K66,"") | O66: =IF(COUNTA($B66:$K66)=0,"",IF($C66="","No date",IF(AND($C66>=Lists!$B$3,$C66<Lists!$B$4),"In FY27","Outside FY27"))) | P66: =IF($E66<>"WIP","",IF($H66="","",IF(COUNTIFS($E$2:$E$20000,"<>WIP",$H$2:$H$20000,$H66)>0,"Job already invoiced",""))) | R66: vicky.duan@asx.com.au | S66: 46252 | T66: 26072906 | U66: 6130 | V66: Y | W66: Y | X66: 8 | Y66: 8 | AB66: 8 | AC66: 4221.7 | AD66: 148.8 | AE66: =IF($E66<>"Production","",IFERROR($AD66/$L66,""))
A67: =IF(COUNTA($B67:$K67)=0,"",ROW()-1) | B67: Invoice | D67: Production | E67: =IF($B67="","",IF($B67="WIP","WIP",IFERROR(INDEX(Lists!$G$4:$G$10,MATCH($D67,Lists!$F$4:$F$10,0)),"Unmapped"))) | G67: Cochlear | H67: 2603104 | I67: Cochlear FY26 Results 18.8.26 | J67: INV-10590 | K67: 10540.5 | L67: =IF($K67="","",IF($E67="Production",$K67-N($AD67),$K67)) | M67: =IF($E67="Production",IF($K67="","",$K67-(N($AF67)+N($AG67))),IF($E67="Consulting",IF($K67="","",$K67-(N($AL67)+N($AM67)+N($AN67))),"")) | N67: =IFERROR($M67/$K67,"") | O67: =IF(COUNTA($B67:$K67)=0,"",IF($C67="","No date",IF(AND($C67>=Lists!$B$3,$C67<Lists!$B$4),"In FY27","Outside FY27"))) | P67: =IF($E67<>"WIP","",IF($H67="","",IF(COUNTIFS($E$2:$E$20000,"<>WIP",$H$2:$H$20000,$H67)>0,"Job already invoiced",""))) | R67: jbarrish@cochlear.com | S67: 46252 | T67: 2603104 | U67: 6091 | V67: Y | W67: Y | X67: 8 | AB67: 18 | AD67: 2984.5 | AE67: =IF($E67<>"Production","",IFERROR($AD67/$L67,"")) | AF67: 2166.76
A68: =IF(COUNTA($B68:$K68)=0,"",ROW()-1) | B68: Invoice | D68: Production | E68: =IF($B68="","",IF($B68="WIP","WIP",IFERROR(INDEX(Lists!$G$4:$G$10,MATCH($D68,Lists!$F$4:$F$10,0)),"Unmapped"))) | G68: ON24 | H68: 26072802 | I68: KWM Sydney Event 18.8.26 (PO25962) | J68: INV-10589 | K68: 2732.5 | L68: =IF($K68="","",IF($E68="Production",$K68-N($AD68),$K68)) | M68: =IF($E68="Production",IF($K68="","",$K68-(N($AF68)+N($AG68))),IF($E68="Consulting",IF($K68="","",$K68-(N($AL68)+N($AM68)+N($AN68))),"")) | N68: =IFERROR($M68/$K68,"") | O68: =IF(COUNTA($B68:$K68)=0,"",IF($C68="","No date",IF(AND($C68>=Lists!$B$3,$C68<Lists!$B$4),"In FY27","Outside FY27"))) | P68: =IF($E68<>"WIP","",IF($H68="","",IF(COUNTIFS($E$2:$E$20000,"<>WIP",$H$2:$H$20000,$H68)>0,"Job already invoiced",""))) | R68: lisa.caraccio@on24.com | S68: 46252 | T68: 26072802 | U68: 6131 | V68: Y | W68: Y | AB68: 6.5 | AD68: 95 | AE68: =IF($E68<>"Production","",IFERROR($AD68/$L68,""))
A69: =IF(COUNTA($B69:$K69)=0,"",ROW()-1) | B69: Invoice | D69: Production | E69: =IF($B69="","",IF($B69="WIP","WIP",IFERROR(INDEX(Lists!$G$4:$G$10,MATCH($D69,Lists!$F$4:$F$10,0)),"Unmapped"))) | G69: Dimensional | H69: 26081402 | I69: AV Support 19.8.26 | J69: INV-10588 | K69: 460 | L69: =IF($K69="","",IF($E69="Production",$K69-N($AD69),$K69)) | M69: =IF($E69="Production",IF($K69="","",$K69-(N($AF69)+N($AG69))),IF($E69="Consulting",IF($K69="","",$K69-(N($AL69)+N($AM69)+N($AN69))),"")) | N69: =IFERROR($M69/$K69,"") | O69: =IF(COUNTA($B69:$K69)=0,"",IF($C69="","No date",IF(AND($C69>=Lists!$B$3,$C69<Lists!$B$4),"In FY27","Outside FY27"))) | P69: =IF($E69<>"WIP","",IF($H69="","",IF(COUNTIFS($E$2:$E$20000,"<>WIP",$H$2:$H$20000,$H69)>0,"Job already invoiced",""))) | R69: Mahan.Noori@dimensional.com.au | S69: 46253 | T69: 26081402 | U69: 6153 | V69: Y | W69: Y | AB69: 4 | AE69: =IF($E69<>"Production","",IFERROR($AD69/$L69,""))
A70: =IF(COUNTA($B70:$K70)=0,"",ROW()-1) | B70: Invoice | C70: 46259 | D70: Production | E70: =IF($B70="","",IF($B70="WIP","WIP",IFERROR(INDEX(Lists!$G$4:$G$10,MATCH($D70,Lists!$F$4:$F$10,0)),"Unmapped"))) | G70: TLC - Melbourne | H70: 26061106 | I70: TLC Full Year Results | J70: INV-10591 | K70: 13661 | L70: =IF($K70="","",IF($E70="Production",$K70-N($AD70),$K70)) | M70: =IF($E70="Production",IF($K70="","",$K70-(N($AF70)+N($AG70))),IF($E70="Consulting",IF($K70="","",$K70-(N($AL70)+N($AM70)+N($AN70))),"")) | N70: =IFERROR($M70/$K70,"") | O70: =IF(COUNTA($B70:$K70)=0,"",IF($C70="","No date",IF(AND($C70>=Lists!$B$3,$C70<Lists!$B$4),"In FY27","Outside FY27"))) | P70: =IF($E70<>"WIP","",IF($H70="","",IF(COUNTIFS($E$2:$E$20000,"<>WIP",$H$2:$H$20000,$H70)>0,"Job already invoiced",""))) | R70: sharne.flanagan@thelotterycorporation.com | S70: 46253 | T70: 26061106 | U70: 5853 | V70: Y | W70: Y | Y70: 4 | Z70: 2 | AB70: 25 | AC70: 674 | AD70: 611.5 | AE70: =IF($E70<>"Production","",IFERROR($AD70/$L70,"")) | AF70: 4272.26
A71: =IF(COUNTA($B71:$K71)=0,"",ROW()-1) | B71: Invoice | D71: Production | E71: =IF($B71="","",IF($B71="WIP","WIP",IFERROR(INDEX(Lists!$G$4:$G$10,MATCH($D71,Lists!$F$4:$F$10,0)),"Unmapped"))) | G71: Downer | H71: 26061107 | I71: Downer FYR26 20.8.26 | J71: INV-10587 | K71: 11644.25 | L71: =IF($K71="","",IF($E71="Production",$K71-N($AD71),$K71)) | M71: =IF($E71="Production",IF($K71="","",$K71-(N($AF71)+N($AG71))),IF($E71="Consulting",IF($K71="","",$K71-(N($AL71)+N($AM71)+N($AN71))),"")) | N71: =IFERROR($M71/$K71,"") | O71: =IF(COUNTA($B71:$K71)=0,"",IF($C71="","No date",IF(AND($C71>=Lists!$B$3,$C71<Lists!$B$4),"In FY27","Outside FY27"))) | P71: =IF($E71<>"WIP","",IF($H71="","",IF(COUNTIFS($E$2:$E$20000,"<>WIP",$H$2:$H$20000,$H71)>0,"Job already invoiced",""))) | R71: mitchell.dale@downergroup.com | S71: 46254 | T71: 26061107 | U71: 6092 | V71: Y | W71: Y | Z71: 3 | AB71: 18 | AC71: 263.5 | AD71: 885.75 | AE71: =IF($E71<>"Production","",IFERROR($AD71/$L71,"")) | AF71: 1221.04
A72: =IF(COUNTA($B72:$K72)=0,"",ROW()-1) | B72: Invoice | D72: Production | E72: =IF($B72="","",IF($B72="WIP","WIP",IFERROR(INDEX(Lists!$G$4:$G$10,MATCH($D72,Lists!$F$4:$F$10,0)),"Unmapped"))) | G72: Garvan | H72: 26073110 | I72: Garvan - Weizmann Dinner Event | J72: INV-10586 | K72: 1055 | L72: =IF($K72="","",IF($E72="Production",$K72-N($AD72),$K72)) | M72: =IF($E72="Production",IF($K72="","",$K72-(N($AF72)+N($AG72))),IF($E72="Consulting",IF($K72="","",$K72-(N($AL72)+N($AM72)+N($AN72))),"")) | N72: =IFERROR($M72/$K72,"") | O72: =IF(COUNTA($B72:$K72)=0,"",IF($C72="","No date",IF(AND($C72>=Lists!$B$3,$C72<Lists!$B$4),"In FY27","Outside FY27"))) | P72: =IF($E72<>"WIP","",IF($H72="","",IF(COUNTIFS($E$2:$E$20000,"<>WIP",$H$2:$H$20000,$H72)>0,"Job already invoiced",""))) | R72: m.gonzalezhuerta@garvan.org.au | S72: 46254 | T72: 26073110 | U72: 6117 | V72: Y | W72: Y | Z72: 1 | AB72: 8 | AE72: =IF($E72<>"Production","",IFERROR($AD72/$L72,""))
A73: =IF(COUNTA($B73:$K73)=0,"",ROW()-1) | B73: Invoice | D73: Production | E73: =IF($B73="","",IF($B73="WIP","WIP",IFERROR(INDEX(Lists!$G$4:$G$10,MATCH($D73,Lists!$F$4:$F$10,0)),"Unmapped"))) | G73: APA | H73: 25121208 | I73: APA FYR Investor Briefing 20.8.26 | J73: Package | K73: 8472.5 | L73: =IF($K73="","",IF($E73="Production",$K73-N($AD73),$K73)) | M73: =IF($E73="Production",IF($K73="","",$K73-(N($AF73)+N($AG73))),IF($E73="Consulting",IF($K73="","",$K73-(N($AL73)+N($AM73)+N($AN73))),"")) | N73: =IFERROR($M73/$K73,"") | O73: =IF(COUNTA($B73:$K73)=0,"",IF($C73="","No date",IF(AND($C73>=Lists!$B$3,$C73<Lists!$B$4),"In FY27","Outside FY27"))) | P73: =IF($E73<>"WIP","",IF($H73="","",IF(COUNTIFS($E$2:$E$20000,"<>WIP",$H$2:$H$20000,$H73)>0,"Job already invoiced",""))) | R73: anna.sampson@apa.com.au | S73: 46254 | T73: 25121208 | U73: 5821 | V73: Y | W73: Y | Z73: 2 | AB73: 20 | AD73: 3652.5 | AE73: =IF($E73<>"Production","",IFERROR($AD73/$L73,"")) | AF73: 1805.72
A74: =IF(COUNTA($B74:$K74)=0,"",ROW()-1) | B74: Invoice | D74: Production | E74: =IF($B74="","",IF($B74="WIP","WIP",IFERROR(INDEX(Lists!$G$4:$G$10,MATCH($D74,Lists!$F$4:$F$10,0)),"Unmapped"))) | G74: APA | H74: 2608702 | I74: APA FYR Town Hall Screen Hire 20.8.26 | J74: INV-10592 | K74: 830 | L74: =IF($K74="","",IF($E74="Production",$K74-N($AD74),$K74)) | M74: =IF($E74="Production",IF($K74="","",$K74-(N($AF74)+N($AG74))),IF($E74="Consulting",IF($K74="","",$K74-(N($AL74)+N($AM74)+N($AN74))),"")) | N74: =IFERROR($M74/$K74,"") | O74: =IF(COUNTA($B74:$K74)=0,"",IF($C74="","No date",IF(AND($C74>=Lists!$B$3,$C74<Lists!$B$4),"In FY27","Outside FY27"))) | P74: =IF($E74<>"WIP","",IF($H74="","",IF(COUNTIFS($E$2:$E$20000,"<>WIP",$H$2:$H$20000,$H74)>0,"Job already invoiced",""))) | R74: anna.sampson@apa.com.au | S74: 46254 | T74: 2608702 | U74: 6149 | V74: Y | W74: Y | AE74: =IF($E74<>"Production","",IFERROR($AD74/$L74,"")) | AF74: 784.5
A75: =IF(COUNTA($B75:$K75)=0,"",ROW()-1) | B75: Invoice | D75: Production | E75: =IF($B75="","",IF($B75="WIP","WIP",IFERROR(INDEX(Lists!$G$4:$G$10,MATCH($D75,Lists!$F$4:$F$10,0)),"Unmapped"))) | G75: APA | H75: 26061108 | I75: APA FYR Town Hall 20.8.26 | J75: Package | K75: 12600.6 | L75: =IF($K75="","",IF($E75="Production",$K75-N($AD75),$K75)) | M75: =IF($E75="Production",IF($K75="","",$K75-(N($AF75)+N($AG75))),IF($E75="Consulting",IF($K75="","",$K75-(N($AL75)+N($AM75)+N($AN75))),"")) | N75: =IFERROR($M75/$K75,"") | O75: =IF(COUNTA($B75:$K75)=0,"",IF($C75="","No date",IF(AND($C75>=Lists!$B$3,$C75<Lists!$B$4),"In FY27","Outside FY27"))) | P75: =IF($E75<>"WIP","",IF($H75="","",IF(COUNTIFS($E$2:$E$20000,"<>WIP",$H$2:$H$20000,$H75)>0,"Job already invoiced",""))) | R75: steph.bennett@apa.com.au | S75: 46254 | T75: 26061108 | U75: 6073 | V75: Y | W75: Y | X75: 5 | Z75: 6 | AB75: 45 | AC75: 1261.6 | AD75: 1651.4 | AE75: =IF($E75<>"Production","",IFERROR($AD75/$L75,""))
A76: =IF(COUNTA($B76:$K76)=0,"",ROW()-1) | B76: Invoice | D76: Production | E76: =IF($B76="","",IF($B76="WIP","WIP",IFERROR(INDEX(Lists!$G$4:$G$10,MATCH($D76,Lists!$F$4:$F$10,0)),"Unmapped"))) | G76: Ventia | H76: 26061109 | I76: Ventia HYR Employee Town Hall 24.8.26 (PO 4701366307) | J76: INV-10593 | K76: 13401.5 | L76: =IF($K76="","",IF($E76="Production",$K76-N($AD76),$K76)) | M76: =IF($E76="Production",IF($K76="","",$K76-(N($AF76)+N($AG76))),IF($E76="Consulting",IF($K76="","",$K76-(N($AL76)+N($AM76)+N($AN76))),"")) | N76: =IFERROR($M76/$K76,"") | O76: =IF(COUNTA($B76:$K76)=0,"",IF($C76="","No date",IF(AND($C76>=Lists!$B$3,$C76<Lists!$B$4),"In FY27","Outside FY27"))) | P76: =IF($E76<>"WIP","",IF($H76="","",IF(COUNTIFS($E$2:$E$20000,"<>WIP",$H$2:$H$20000,$H76)>0,"Job already invoiced",""))) | R76: amy.johnson@ventia.com | S76: 46258 | T76: 26061109 | U76: 6095 | V76: Y | W76: Y | X76: 4 | AB76: 41 | AC76: 1771 | AD76: 524.5 | AE76: =IF($E76<>"Production","",IFERROR($AD76/$L76,"")) | AF76: 1350
A77: =IF(COUNTA($B77:$K77)=0,"",ROW()-1) | B77: Invoice | C77: 46265 | D77: Production | E77: =IF($B77="","",IF($B77="WIP","WIP",IFERROR(INDEX(Lists!$G$4:$G$10,MATCH($D77,Lists!$F$4:$F$10,0)),"Unmapped"))) | G77: Ventia | H77: 26071501 | I77: Ventia Half Year Results Briefing | J77: INV-10612 | K77: 10835.49 | L77: =IF($K77="","",IF($E77="Production",$K77-N($AD77),$K77)) | M77: =IF($E77="Production",IF($K77="","",$K77-(N($AF77)+N($AG77))),IF($E77="Consulting",IF($K77="","",$K77-(N($AL77)+N($AM77)+N($AN77))),"")) | N77: =IFERROR($M77/$K77,"") | O77: =IF(COUNTA($B77:$K77)=0,"",IF($C77="","No date",IF(AND($C77>=Lists!$B$3,$C77<Lists!$B$4),"In FY27","Outside FY27"))) | P77: =IF($E77<>"WIP","",IF($H77="","",IF(COUNTIFS($E$2:$E$20000,"<>WIP",$H$2:$H$20000,$H77)>0,"Job already invoiced",""))) | R77: chantal.travers@ventia.com | S77: 46258 | T77: 26071501 | U77: 6094 | V77: Y | W77: Y | AB77: 11 | AD77: 495 | AE77: =IF($E77<>"Production","",IFERROR($AD77/$L77,"")) | AF77: 2303.09
A78: =IF(COUNTA($B78:$K78)=0,"",ROW()-1) | B78: Invoice | C78: 46265 | D78: Production | E78: =IF($B78="","",IF($B78="WIP","WIP",IFERROR(INDEX(Lists!$G$4:$G$10,MATCH($D78,Lists!$F$4:$F$10,0)),"Unmapped"))) | G78: Downer - Melbourne | H78: 26073111 | I78: Employee Results Briefing | J78: INV-10611 | K78: 24413.75 | L78: =IF($K78="","",IF($E78="Production",$K78-N($AD78),$K78)) | M78: =IF($E78="Production",IF($K78="","",$K78-(N($AF78)+N($AG78))),IF($E78="Consulting",IF($K78="","",$K78-(N($AL78)+N($AM78)+N($AN78))),"")) | N78: =IFERROR($M78/$K78,"") | O78: =IF(COUNTA($B78:$K78)=0,"",IF($C78="","No date",IF(AND($C78>=Lists!$B$3,$C78<Lists!$B$4),"In FY27","Outside FY27"))) | P78: =IF($E78<>"WIP","",IF($H78="","",IF(COUNTIFS($E$2:$E$20000,"<>WIP",$H$2:$H$20000,$H78)>0,"Job already invoiced",""))) | R78: mitchell.dale@downergroup.com | S78: 46259 | T78: 26073111 | U78: 6144 | V78: Y | W78: Y | X78: 5 | Z78: 3 | AB78: 37 | AC78: 1785 | AD78: 2281.25 | AE78: =IF($E78<>"Production","",IFERROR($AD78/$L78,"")) | AF78: 14754.3
A79: =IF(COUNTA($B79:$K79)=0,"",ROW()-1) | B79: Invoice | C79: 46259 | D79: Production | E79: =IF($B79="","",IF($B79="WIP","WIP",IFERROR(INDEX(Lists!$G$4:$G$10,MATCH($D79,Lists!$F$4:$F$10,0)),"Unmapped"))) | G79: Symal - Melbourne | H79: 2606904 | I79: Symal FYR 2026 | K79: 13347 | L79: =IF($K79="","",IF($E79="Production",$K79-N($AD79),$K79)) | M79: =IF($E79="Production",IF($K79="","",$K79-(N($AF79)+N($AG79))),IF($E79="Consulting",IF($K79="","",$K79-(N($AL79)+N($AM79)+N($AN79))),"")) | N79: =IFERROR($M79/$K79,"") | O79: =IF(COUNTA($B79:$K79)=0,"",IF($C79="","No date",IF(AND($C79>=Lists!$B$3,$C79<Lists!$B$4),"In FY27","Outside FY27"))) | P79: =IF($E79<>"WIP","",IF($H79="","",IF(COUNTIFS($E$2:$E$20000,"<>WIP",$H$2:$H$20000,$H79)>0,"Job already invoiced",""))) | R79: pia.witt@symal.com.au | S79: 46259 | T79: 2606904 | U79: 6044 | V79: Y | W79: Y | Z79: 2 | AB79: 22 | AC79: 86.5 | AD79: 3563 | AE79: =IF($E79<>"Production","",IFERROR($AD79/$L79,"")) | AF79: 1874
A80: =IF(COUNTA($B80:$K80)=0,"",ROW()-1) | B80: Invoice | D80: Production | E80: =IF($B80="","",IF($B80="WIP","WIP",IFERROR(INDEX(Lists!$G$4:$G$10,MATCH($D80,Lists!$F$4:$F$10,0)),"Unmapped"))) | G80: Garvan | H80: 26061001 | I80: Garvan August All Clear Event 25.8.26 | J80: INV-10595 | K80: 770 | L80: =IF($K80="","",IF($E80="Production",$K80-N($AD80),$K80)) | M80: =IF($E80="Production",IF($K80="","",$K80-(N($AF80)+N($AG80))),IF($E80="Consulting",IF($K80="","",$K80-(N($AL80)+N($AM80)+N($AN80))),"")) | N80: =IFERROR($M80/$K80,"") | O80: =IF(COUNTA($B80:$K80)=0,"",IF($C80="","No date",IF(AND($C80>=Lists!$B$3,$C80<Lists!$B$4),"In FY27","Outside FY27"))) | P80: =IF($E80<>"WIP","",IF($H80="","",IF(COUNTIFS($E$2:$E$20000,"<>WIP",$H$2:$H$20000,$H80)>0,"Job already invoiced",""))) | R80: t.choi@garvan.org.au | S80: 46259 | T80: 26061001 | U80: 6055 | V80: Y | W80: Y | Z80: 1 | AB80: 4 | AD80: 90 | AE80: =IF($E80<>"Production","",IFERROR($AD80/$L80,""))
A81: =IF(COUNTA($B81:$K81)=0,"",ROW()-1) | B81: Invoice | D81: Production | E81: =IF($B81="","",IF($B81="WIP","WIP",IFERROR(INDEX(Lists!$G$4:$G$10,MATCH($D81,Lists!$F$4:$F$10,0)),"Unmapped"))) | G81: Elkiem | H81: 26073105 | I81: Studio Support 25.8.26 | J81: INV-10594 | K81: 380 | L81: =IF($K81="","",IF($E81="Production",$K81-N($AD81),$K81)) | M81: =IF($E81="Production",IF($K81="","",$K81-(N($AF81)+N($AG81))),IF($E81="Consulting",IF($K81="","",$K81-(N($AL81)+N($AM81)+N($AN81))),"")) | N81: =IFERROR($M81/$K81,"") | O81: =IF(COUNTA($B81:$K81)=0,"",IF($C81="","No date",IF(AND($C81>=Lists!$B$3,$C81<Lists!$B$4),"In FY27","Outside FY27"))) | P81: =IF($E81<>"WIP","",IF($H81="","",IF(COUNTIFS($E$2:$E$20000,"<>WIP",$H$2:$H$20000,$H81)>0,"Job already invoiced",""))) | R81: ben.woodlock@elkiem.com | S81: 46259 | T81: 26073105 | U81: 6129 | V81: Y | W81: Y | AB81: 4 | AE81: =IF($E81<>"Production","",IFERROR($AD81/$L81,""))
A82: =IF(COUNTA($B82:$K82)=0,"",ROW()-1) | B82: Invoice | D82: Production | E82: =IF($B82="","",IF($B82="WIP","WIP",IFERROR(INDEX(Lists!$G$4:$G$10,MATCH($D82,Lists!$F$4:$F$10,0)),"Unmapped"))) | G82: Virgin - BNE | H82: 2606903 | I82: FY26 Results - 28.8.26 | K82: 13389.5 | L82: =IF($K82="","",IF($E82="Production",$K82-N($AD82),$K82)) | M82: =IF($E82="Production",IF($K82="","",$K82-(N($AF82)+N($AG82))),IF($E82="Consulting",IF($K82="","",$K82-(N($AL82)+N($AM82)+N($AN82))),"")) | N82: =IFERROR($M82/$K82,"") | O82: =IF(COUNTA($B82:$K82)=0,"",IF($C82="","No date",IF(AND($C82>=Lists!$B$3,$C82<Lists!$B$4),"In FY27","Outside FY27"))) | P82: =IF($E82<>"WIP","",IF($H82="","",IF(COUNTIFS($E$2:$E$20000,"<>WIP",$H$2:$H$20000,$H82)>0,"Job already invoiced",""))) | R82: Saranya.Nagpal@virginaustralia.com | S82: 46262 | T82: 2606903 | U82: 6024 | V82: Y | W82: Y | Z82: 4 | AB82: 23 | AD82: 3530.5 | AE82: =IF($E82<>"Production","",IFERROR($AD82/$L82,"")) | AF82: 4749.88
A83: =IF(COUNTA($B83:$K83)=0,"",ROW()-1) | B83: Invoice | D83: Production | E83: =IF($B83="","",IF($B83="WIP","WIP",IFERROR(INDEX(Lists!$G$4:$G$10,MATCH($D83,Lists!$F$4:$F$10,0)),"Unmapped"))) | G83: CBA | H83: 26072003 | I83: CBA - Live Event Support - August | J83: INV-10616 | K83: 3990 | L83: =IF($K83="","",IF($E83="Production",$K83-N($AD83),$K83)) | M83: =IF($E83="Production",IF($K83="","",$K83-(N($AF83)+N($AG83))),IF($E83="Consulting",IF($K83="","",$K83-(N($AL83)+N($AM83)+N($AN83))),"")) | N83: =IFERROR($M83/$K83,"") | O83: =IF(COUNTA($B83:$K83)=0,"",IF($C83="","No date",IF(AND($C83>=Lists!$B$3,$C83<Lists!$B$4),"In FY27","Outside FY27"))) | P83: =IF($E83<>"WIP","",IF($H83="","",IF(COUNTIFS($E$2:$E$20000,"<>WIP",$H$2:$H$20000,$H83)>0,"Job already invoiced",""))) | R83: Steve.chezzi@cba.com.au | S83: 46265 | T83: 26072003 | U83: 6169 | V83: Y | W83: Y | AB83: 56 | AE83: =IF($E83<>"Production","",IFERROR($AD83/$L83,""))
A84: =IF(COUNTA($B84:$K84)=0,"",ROW()-1) | B84: Invoice | C84: 46218 | D84: Production | E84: =IF($B84="","",IF($B84="WIP","WIP",IFERROR(INDEX(Lists!$G$4:$G$10,MATCH($D84,Lists!$F$4:$F$10,0)),"Unmapped"))) | G84: APA | H84: 26061609/26061608/26061607/26061108 | I84: APA - All Hands Package FY27 (PO-00030766) | J84: INV-10521 | K84: 54051.4 | L84: =IF($K84="","",IF($E84="Production",$K84-N($AD84),$K84)) | M84: =IF($E84="Production",IF($K84="","",$K84-(N($AF84)+N($AG84))),IF($E84="Consulting",IF($K84="","",$K84-(N($AL84)+N($AM84)+N($AN84))),"")) | N84: =IFERROR($M84/$K84,"") | O84: =IF(COUNTA($B84:$K84)=0,"",IF($C84="","No date",IF(AND($C84>=Lists!$B$3,$C84<Lists!$B$4),"In FY27","Outside FY27"))) | P84: =IF($E84<>"WIP","",IF($H84="","",IF(COUNTIFS($E$2:$E$20000,"<>WIP",$H$2:$H$20000,$H84)>0,"Job already invoiced",""))) | S84: N/A | T84: 26061609 | U84: Proj: 0017 | V84: Y | W84: Y | AC84: 4308 | AE84: =IF($E84<>"Production","",IFERROR($AD84/$L84,""))
A85: =IF(COUNTA($B85:$K85)=0,"",ROW()-1) | B85: Invoice | C85: 46216 | D85: Other | E85: =IF($B85="","",IF($B85="WIP","WIP",IFERROR(INDEX(Lists!$G$4:$G$10,MATCH($D85,Lists!$F$4:$F$10,0)),"Unmapped"))) | G85: Jaaz Salanoa | H85: 9100 | I85: Jaaz - Goget Hire | J85: INV-10523 | L85: =IF($K85="","",IF($E85="Production",$K85-N($AD85),$K85)) | M85: =IF($E85="Production",IF($K85="","",$K85-(N($AF85)+N($AG85))),IF($E85="Consulting",IF($K85="","",$K85-(N($AL85)+N($AM85)+N($AN85))),"")) | N85: =IFERROR($M85/$K85,"") | O85: =IF(COUNTA($B85:$K85)=0,"",IF($C85="","No date",IF(AND($C85>=Lists!$B$3,$C85<Lists!$B$4),"In FY27","Outside FY27"))) | P85: =IF($E85<>"WIP","",IF($H85="","",IF(COUNTIFS($E$2:$E$20000,"<>WIP",$H$2:$H$20000,$H85)>0,"Job already invoiced",""))) | R85: jaaz.salanoa@ctsav.com.au | S85: N/A | T85: N/A | V85: Y | W85: Y | AE85: =IF($E85<>"Production","",IFERROR($AD85/$L85,""))
A86: =IF(COUNTA($B86:$K86)=0,"",ROW()-1) | B86: Invoice | C86: 45805 | D86: Consulting | E86: =IF($B86="","",IF($B86="WIP","WIP",IFERROR(INDEX(Lists!$G$4:$G$10,MATCH($D86,Lists!$F$4:$F$10,0)),"Unmapped"))) | F86: Completed | G86: DAFF | H86: 25021901 | I86: Technology Standards Evaluation | J86: INV-9860 | K86: 9875 | L86: =IF($K86="","",IF($E86="Production",$K86-N($AD86),$K86)) | M86: =IF($E86="Production",IF($K86="","",$K86-(N($AF86)+N($AG86))),IF($E86="Consulting",IF($K86="","",$K86-(N($AL86)+N($AM86)+N($AN86))),"")) | N86: =IFERROR($M86/$K86,"") | O86: =IF(COUNTA($B86:$K86)=0,"",IF($C86="","No date",IF(AND($C86>=Lists!$B$3,$C86<Lists!$B$4),"In FY27","Outside FY27"))) | P86: =IF($E86<>"WIP","",IF($H86="","",IF(COUNTIFS($E$2:$E$20000,"<>WIP",$H$2:$H$20000,$H86)>0,"Job already invoiced",""))) | Q86: Revenue still in WIP | AE86: =IF($E86<>"Production","",IFERROR($AD86/$L86,"")) | AH86: https://cts.qwilr.com/25021901-DAFF-Technology-Standards-Evaluation-A7PRmNNwQ5Wn | AI86: 9875
A87: =IF(COUNTA($B87:$K87)=0,"",ROW()-1) | B87: Invoice | C87: 46101 | D87: Consulting | E87: =IF($B87="","",IF($B87="WIP","WIP",IFERROR(INDEX(Lists!$G$4:$G$10,MATCH($D87,Lists!$F$4:$F$10,0)),"Unmapped"))) | F87: In Progress | G87: DEWR | H87: 25102701 | I87: DEWR Studio Upgrade | J87: INV-10319 | K87: 23050 | L87: =IF($K87="","",IF($E87="Production",$K87-N($AD87),$K87)) | M87: =IF($E87="Production",IF($K87="","",$K87-(N($AF87)+N($AG87))),IF($E87="Consulting",IF($K87="","",$K87-(N($AL87)+N($AM87)+N($AN87))),"")) | N87: =IFERROR($M87/$K87,"") | O87: =IF(COUNTA($B87:$K87)=0,"",IF($C87="","No date",IF(AND($C87>=Lists!$B$3,$C87<Lists!$B$4),"In FY27","Outside FY27"))) | P87: =IF($E87<>"WIP","",IF($H87="","",IF(COUNTIFS($E$2:$E$20000,"<>WIP",$H$2:$H$20000,$H87)>0,"Job already invoiced",""))) | Q87: Progress Claim 01 | AE87: =IF($E87<>"Production","",IFERROR($AD87/$L87,"")) | AH87: https://cts.qwilr.com/25102701-DEWR-Studio-Upgrade-ESE25-143997-Rev-4-KTqWXx2QQz6f | AI87: 23050
A88: =IF(COUNTA($B88:$K88)=0,"",ROW()-1) | B88: Invoice | C88: 46104 | D88: Consulting | E88: =IF($B88="","",IF($B88="WIP","WIP",IFERROR(INDEX(Lists!$G$4:$G$10,MATCH($D88,Lists!$F$4:$F$10,0)),"Unmapped"))) | F88: In Progress | G88: DEWR | H88: 25102701 | I88: DEWR Studio Upgrade | J88: INV-10320 | K88: 13250 | L88: =IF($K88="","",IF($E88="Production",$K88-N($AD88),$K88)) | M88: =IF($E88="Production",IF($K88="","",$K88-(N($AF88)+N($AG88))),IF($E88="Consulting",IF($K88="","",$K88-(N($AL88)+N($AM88)+N($AN88))),"")) | N88: =IFERROR($M88/$K88,"") | O88: =IF(COUNTA($B88:$K88)=0,"",IF($C88="","No date",IF(AND($C88>=Lists!$B$3,$C88<Lists!$B$4),"In FY27","Outside FY27"))) | P88: =IF($E88<>"WIP","",IF($H88="","",IF(COUNTIFS($E$2:$E$20000,"<>WIP",$H$2:$H$20000,$H88)>0,"Job already invoiced",""))) | Q88: Progress Claim 02 | AE88: =IF($E88<>"Production","",IFERROR($AD88/$L88,"")) | AH88: https://cts.qwilr.com/25102701-DEWR-Studio-Upgrade-ESE25-143997-Rev-4-KTqWXx2QQz6f | AI88: 13250
A89: =IF(COUNTA($B89:$K89)=0,"",ROW()-1) | B89: Invoice | C89: 46128 | D89: Consulting | E89: =IF($B89="","",IF($B89="WIP","WIP",IFERROR(INDEX(Lists!$G$4:$G$10,MATCH($D89,Lists!$F$4:$F$10,0)),"Unmapped"))) | F89: In Progress | G89: DEWR | H89: 25102701 | I89: DEWR Studio Upgrade | J89: INV-10353 | K89: 24410 | L89: =IF($K89="","",IF($E89="Production",$K89-N($AD89),$K89)) | M89: =IF($E89="Production",IF($K89="","",$K89-(N($AF89)+N($AG89))),IF($E89="Consulting",IF($K89="","",$K89-(N($AL89)+N($AM89)+N($AN89))),"")) | N89: =IFERROR($M89/$K89,"") | O89: =IF(COUNTA($B89:$K89)=0,"",IF($C89="","No date",IF(AND($C89>=Lists!$B$3,$C89<Lists!$B$4),"In FY27","Outside FY27"))) | P89: =IF($E89<>"WIP","",IF($H89="","",IF(COUNTIFS($E$2:$E$20000,"<>WIP",$H$2:$H$20000,$H89)>0,"Job already invoiced",""))) | Q89: Progress Claim 03 | AE89: =IF($E89<>"Production","",IFERROR($AD89/$L89,"")) | AH89: https://cts.qwilr.com/25102701-DEWR-Studio-Upgrade-ESE25-143997-Rev-4-KTqWXx2QQz6f | AI89: 24410
A90: =IF(COUNTA($B90:$K90)=0,"",ROW()-1) | B90: Invoice | C90: 46162 | D90: Integration | E90: =IF($B90="","",IF($B90="WIP","WIP",IFERROR(INDEX(Lists!$G$4:$G$10,MATCH($D90,Lists!$F$4:$F$10,0)),"Unmapped"))) | F90: In Progress | G90: DTTL | H90: 26052002 | I90: BNE ​L23 Training Rooms Upgrade | J90: INV-10425 | K90: 57706 | L90: =IF($K90="","",IF($E90="Production",$K90-N($AD90),$K90)) | M90: =IF($E90="Production",IF($K90="","",$K90-(N($AF90)+N($AG90))),IF($E90="Consulting",IF($K90="","",$K90-(N($AL90)+N($AM90)+N($AN90))),"")) | N90: =IFERROR($M90/$K90,"") | O90: =IF(COUNTA($B90:$K90)=0,"",IF($C90="","No date",IF(AND($C90>=Lists!$B$3,$C90<Lists!$B$4),"In FY27","Outside FY27"))) | P90: =IF($E90<>"WIP","",IF($H90="","",IF(COUNTIFS($E$2:$E$20000,"<>WIP",$H$2:$H$20000,$H90)>0,"Job already invoiced",""))) | AE90: =IF($E90<>"Production","",IFERROR($AD90/$L90,"")) | AH90: https://cts.qwilr.com/26052002-DeloitteBNE-Proposal-v1-0-Agx8wV5qTcax | AI90: 18262 | AJ90: 39444 | AL90: 15600 | AM90: 36400
A91: =IF(COUNTA($B91:$K91)=0,"",ROW()-1) | B91: Invoice | C91: 46163 | D91: Integration | E91: =IF($B91="","",IF($B91="WIP","WIP",IFERROR(INDEX(Lists!$G$4:$G$10,MATCH($D91,Lists!$F$4:$F$10,0)),"Unmapped"))) | F91: Closed | G91: DTTL | H91: 26052003 | I91: SYD Mobile Display Supply | J91: INV-10426 | K91: 26234 | L91: =IF($K91="","",IF($E91="Production",$K91-N($AD91),$K91)) | M91: =IF($E91="Production",IF($K91="","",$K91-(N($AF91)+N($AG91))),IF($E91="Consulting",IF($K91="","",$K91-(N($AL91)+N($AM91)+N($AN91))),"")) | N91: =IFERROR($M91/$K91,"") | O91: =IF(COUNTA($B91:$K91)=0,"",IF($C91="","No date",IF(AND($C91>=Lists!$B$3,$C91<Lists!$B$4),"In FY27","Outside FY27"))) | P91: =IF($E91<>"WIP","",IF($H91="","",IF(COUNTIFS($E$2:$E$20000,"<>WIP",$H$2:$H$20000,$H91)>0,"Job already invoiced",""))) | AE91: =IF($E91<>"Production","",IFERROR($AD91/$L91,"")) | AH91: https://cts.qwilr.com/26052003-DTTL-Costing-v1-0-0mJlWQroQJWo | AI91: 2984 | AJ91: 23250 | AL91: 602 | AM91: 19094.31
A92: =IF(COUNTA($B92:$K92)=0,"",ROW()-1) | B92: Invoice | C92: 46171 | D92: Consulting | E92: =IF($B92="","",IF($B92="WIP","WIP",IFERROR(INDEX(Lists!$G$4:$G$10,MATCH($D92,Lists!$F$4:$F$10,0)),"Unmapped"))) | F92: In Progress | G92: DEWR | H92: 25102701 | I92: DEWR Studio Upgrade | J92: INV-10442 | K92: 7563 | L92: =IF($K92="","",IF($E92="Production",$K92-N($AD92),$K92)) | M92: =IF($E92="Production",IF($K92="","",$K92-(N($AF92)+N($AG92))),IF($E92="Consulting",IF($K92="","",$K92-(N($AL92)+N($AM92)+N($AN92))),"")) | N92: =IFERROR($M92/$K92,"") | O92: =IF(COUNTA($B92:$K92)=0,"",IF($C92="","No date",IF(AND($C92>=Lists!$B$3,$C92<Lists!$B$4),"In FY27","Outside FY27"))) | P92: =IF($E92<>"WIP","",IF($H92="","",IF(COUNTIFS($E$2:$E$20000,"<>WIP",$H$2:$H$20000,$H92)>0,"Job already invoiced",""))) | Q92: Progress Claim 04 | AE92: =IF($E92<>"Production","",IFERROR($AD92/$L92,"")) | AH92: https://cts.qwilr.com/25102701-DEWR-Studio-Upgrade-ESE25-143997-Rev-4-KTqWXx2QQz6f | AI92: 7563 | AM92: 149604.26
A93: =IF(COUNTA($B93:$K93)=0,"",ROW()-1) | B93: Invoice | C93: 46190 | D93: Integration | E93: =IF($B93="","",IF($B93="WIP","WIP",IFERROR(INDEX(Lists!$G$4:$G$10,MATCH($D93,Lists!$F$4:$F$10,0)),"Unmapped"))) | F93: Completed | G93: PwC | H93: 26051801 | I93: Mel Studio Equipment | J93: INV-10462 | K93: 12039 | L93: =IF($K93="","",IF($E93="Production",$K93-N($AD93),$K93)) | M93: =IF($E93="Production",IF($K93="","",$K93-(N($AF93)+N($AG93))),IF($E93="Consulting",IF($K93="","",$K93-(N($AL93)+N($AM93)+N($AN93))),"")) | N93: =IFERROR($M93/$K93,"") | O93: =IF(COUNTA($B93:$K93)=0,"",IF($C93="","No date",IF(AND($C93>=Lists!$B$3,$C93<Lists!$B$4),"In FY27","Outside FY27"))) | P93: =IF($E93<>"WIP","",IF($H93="","",IF(COUNTIFS($E$2:$E$20000,"<>WIP",$H$2:$H$20000,$H93)>0,"Job already invoiced",""))) | AE93: =IF($E93<>"Production","",IFERROR($AD93/$L93,"")) | AH93: https://cts.qwilr.com/26051801-PwC-Costing-v3-0-HUL2JaYQCO39 | AI93: 289 | AJ93: 11750 | AL93: 237 | AM93: 8810
A94: =IF(COUNTA($B94:$K94)=0,"",ROW()-1) | B94: Invoice | C94: 46190 | D94: Integration | E94: =IF($B94="","",IF($B94="WIP","WIP",IFERROR(INDEX(Lists!$G$4:$G$10,MATCH($D94,Lists!$F$4:$F$10,0)),"Unmapped"))) | F94: Closed | G94: PwC | H94: 26043003 | I94: Screen Replacements (SYD/MEL) | J94: INV-10461 | K94: 96068 | L94: =IF($K94="","",IF($E94="Production",$K94-N($AD94),$K94)) | M94: =IF($E94="Production",IF($K94="","",$K94-(N($AF94)+N($AG94))),IF($E94="Consulting",IF($K94="","",$K94-(N($AL94)+N($AM94)+N($AN94))),"")) | N94: =IFERROR($M94/$K94,"") | O94: =IF(COUNTA($B94:$K94)=0,"",IF($C94="","No date",IF(AND($C94>=Lists!$B$3,$C94<Lists!$B$4),"In FY27","Outside FY27"))) | P94: =IF($E94<>"WIP","",IF($H94="","",IF(COUNTIFS($E$2:$E$20000,"<>WIP",$H$2:$H$20000,$H94)>0,"Job already invoiced",""))) | AE94: =IF($E94<>"Production","",IFERROR($AD94/$L94,"")) | AH94: https://cts.qwilr.com/26043003-PwC-Costing-v1-0-LoPgcYilSIWh | AI94: 17766 | AJ94: 78301 | AL94: 13439 | AM94: 74537
A95: =IF(COUNTA($B95:$K95)=0,"",ROW()-1) | B95: Invoice | C95: 46198 | D95: Integration | E95: =IF($B95="","",IF($B95="WIP","WIP",IFERROR(INDEX(Lists!$G$4:$G$10,MATCH($D95,Lists!$F$4:$F$10,0)),"Unmapped"))) | F95: Closed | G95: PwC | H95: 2606901 | I95: Sydney Office box drop | J95: INV-10500 | K95: 561 | L95: =IF($K95="","",IF($E95="Production",$K95-N($AD95),$K95)) | M95: =IF($E95="Production",IF($K95="","",$K95-(N($AF95)+N($AG95))),IF($E95="Consulting",IF($K95="","",$K95-(N($AL95)+N($AM95)+N($AN95))),"")) | N95: =IFERROR($M95/$K95,"") | O95: =IF(COUNTA($B95:$K95)=0,"",IF($C95="","No date",IF(AND($C95>=Lists!$B$3,$C95<Lists!$B$4),"In FY27","Outside FY27"))) | P95: =IF($E95<>"WIP","",IF($H95="","",IF(COUNTIFS($E$2:$E$20000,"<>WIP",$H$2:$H$20000,$H95)>0,"Job already invoiced",""))) | AE95: =IF($E95<>"Production","",IFERROR($AD95/$L95,"")) | AH95: https://app.qwilr.com/#/page-view/6a336995d5bfec1e1c7a08ed | AI95: 41 | AJ95: 520 | AL95: 30.98 | AM95: 389
A96: =IF(COUNTA($B96:$K96)=0,"",ROW()-1) | B96: Invoice | C96: 46198 | D96: Consulting | E96: =IF($B96="","",IF($B96="WIP","WIP",IFERROR(INDEX(Lists!$G$4:$G$10,MATCH($D96,Lists!$F$4:$F$10,0)),"Unmapped"))) | F96: In Progress | G96: YSG Studio | H96: 2602203 | I96: Orange Room Upgrade CONS | J96: INV-10499 | K96: 2247.5 | L96: =IF($K96="","",IF($E96="Production",$K96-N($AD96),$K96)) | M96: =IF($E96="Production",IF($K96="","",$K96-(N($AF96)+N($AG96))),IF($E96="Consulting",IF($K96="","",$K96-(N($AL96)+N($AM96)+N($AN96))),"")) | N96: =IFERROR($M96/$K96,"") | O96: =IF(COUNTA($B96:$K96)=0,"",IF($C96="","No date",IF(AND($C96>=Lists!$B$3,$C96<Lists!$B$4),"In FY27","Outside FY27"))) | P96: =IF($E96<>"WIP","",IF($H96="","",IF(COUNTIFS($E$2:$E$20000,"<>WIP",$H$2:$H$20000,$H96)>0,"Job already invoiced",""))) | Q96: Progress Claim 03 | AE96: =IF($E96<>"Production","",IFERROR($AD96/$L96,"")) | AH96: https://cts.qwilr.com/2602203-YSGStudio-Proposal-A-Yw8447MlTUK7 | AI96: 2247.5 | AL96: 4840.96 | AM96: 17621.33
A97: =IF(COUNTA($B97:$K97)=0,"",ROW()-1) | B97: Invoice | C97: 46203 | D97: Integration | E97: =IF($B97="","",IF($B97="WIP","WIP",IFERROR(INDEX(Lists!$G$4:$G$10,MATCH($D97,Lists!$F$4:$F$10,0)),"Unmapped"))) | F97: Closed | G97: CoS | H97: 25111203 | I97: Barco E3 Sale | J97: INV-10510 | K97: 159150 | L97: =IF($K97="","",IF($E97="Production",$K97-N($AD97),$K97)) | M97: =IF($E97="Production",IF($K97="","",$K97-(N($AF97)+N($AG97))),IF($E97="Consulting",IF($K97="","",$K97-(N($AL97)+N($AM97)+N($AN97))),"")) | N97: =IFERROR($M97/$K97,"") | O97: =IF(COUNTA($B97:$K97)=0,"",IF($C97="","No date",IF(AND($C97>=Lists!$B$3,$C97<Lists!$B$4),"In FY27","Outside FY27"))) | P97: =IF($E97<>"WIP","",IF($H97="","",IF(COUNTIFS($E$2:$E$20000,"<>WIP",$H$2:$H$20000,$H97)>0,"Job already invoiced",""))) | AE97: =IF($E97<>"Production","",IFERROR($AD97/$L97,"")) | AH97: https://cts.qwilr.com/25111203-CoS-Proposal-v3-0-SyP1MwQ2TcKi | AJ97: 159150 | AM97: 149604.26
A98: =IF(COUNTA($B98:$K98)=0,"",ROW()-1) | B98: Invoice | C98: 46203 | D98: Integration | E98: =IF($B98="","",IF($B98="WIP","WIP",IFERROR(INDEX(Lists!$G$4:$G$10,MATCH($D98,Lists!$F$4:$F$10,0)),"Unmapped"))) | F98: Closed | G98: DTTL | H98: 26033003 | I98: 8PSQ-Dream-Big-Microphones | J98: INV-10355 | K98: 27408 | L98: =IF($K98="","",IF($E98="Production",$K98-N($AD98),$K98)) | M98: =IF($E98="Production",IF($K98="","",$K98-(N($AF98)+N($AG98))),IF($E98="Consulting",IF($K98="","",$K98-(N($AL98)+N($AM98)+N($AN98))),"")) | N98: =IFERROR($M98/$K98,"") | O98: =IF(COUNTA($B98:$K98)=0,"",IF($C98="","No date",IF(AND($C98>=Lists!$B$3,$C98<Lists!$B$4),"In FY27","Outside FY27"))) | P98: =IF($E98<>"WIP","",IF($H98="","",IF(COUNTIFS($E$2:$E$20000,"<>WIP",$H$2:$H$20000,$H98)>0,"Job already invoiced",""))) | Q98: Invoiced in DTTL Additionals | AE98: =IF($E98<>"Production","",IFERROR($AD98/$L98,"")) | AH98: 26033003-Deloitte-8PSQ-Dream-Big-Microphones-v1-0-E9jd4w9T62Y1 | AI98: 5904 | AJ98: 21504 | AL98: 4840.8 | AM98: 17621.2
A99: =IF(COUNTA($B99:$K99)=0,"",ROW()-1) | B99: Invoice | C99: 46203 | D99: Integration | E99: =IF($B99="","",IF($B99="WIP","WIP",IFERROR(INDEX(Lists!$G$4:$G$10,MATCH($D99,Lists!$F$4:$F$10,0)),"Unmapped"))) | F99: In Progress | G99: DTTL | H99: 26033005 | I99: QQT & 8PSQ_Crestron Connect Adaptor | J99: INV-10355 | K99: 20128 | L99: =IF($K99="","",IF($E99="Production",$K99-N($AD99),$K99)) | M99: =IF($E99="Production",IF($K99="","",$K99-(N($AF99)+N($AG99))),IF($E99="Consulting",IF($K99="","",$K99-(N($AL99)+N($AM99)+N($AN99))),"")) | N99: =IFERROR($M99/$K99,"") | O99: =IF(COUNTA($B99:$K99)=0,"",IF($C99="","No date",IF(AND($C99>=Lists!$B$3,$C99<Lists!$B$4),"In FY27","Outside FY27"))) | P99: =IF($E99<>"WIP","",IF($H99="","",IF(COUNTIFS($E$2:$E$20000,"<>WIP",$H$2:$H$20000,$H99)>0,"Job already invoiced",""))) | AE99: =IF($E99<>"Production","",IFERROR($AD99/$L99,"")) | AH99: 26033005_Deloitte QQT & 8PSQ_Crestron Connect Adaptor_v1.0 | AI99: 4105 | AJ99: 16023 | AL99: 3013.72 | AM99: 13493.15
A100: =IF(COUNTA($B100:$K100)=0,"",ROW()-1) | B100: Invoice | C100: 46203 | D100: Integration | E100: =IF($B100="","",IF($B100="WIP","WIP",IFERROR(INDEX(Lists!$G$4:$G$10,MATCH($D100,Lists!$F$4:$F$10,0)),"Unmapped"))) | F100: In Progress | G100: DTTL | H100: 26033006 | I100: 8PSQ_Bluetooth Audio | J100: INV-10355 | K100: 5065 | L100: =IF($K100="","",IF($E100="Production",$K100-N($AD100),$K100)) | M100: =IF($E100="Production",IF($K100="","",$K100-(N($AF100)+N($AG100))),IF($E100="Consulting",IF($K100="","",$K100-(N($AL100)+N($AM100)+N($AN100))),"")) | N100: =IFERROR($M100/$K100,"") | O100: =IF(COUNTA($B100:$K100)=0,"",IF($C100="","No date",IF(AND($C100>=Lists!$B$3,$C100<Lists!$B$4),"In FY27","Outside FY27"))) | P100: =IF($E100<>"WIP","",IF($H100="","",IF(COUNTIFS($E$2:$E$20000,"<>WIP",$H$2:$H$20000,$H100)>0,"Job already invoiced",""))) | AE100: =IF($E100<>"Production","",IFERROR($AD100/$L100,"")) | AH100: 26033006_Deloitte 8PSQ_Bluetooth Audio_v1.0 | AI100: 2578 | AJ100: 2487 | AL100: 2114 | AM100: 2110
...

Sheet Dashboard
A1: FY 2026-27 — Monthly revenue by report line
A2: Month | B2: Support | C2: Production | D2: Consulting | E2: WIP | F2: Total Revenue | G2: P&L Total | H2: Variance
A3: 46204 | B3: =SUMIFS(Data!$L$2:$L$20000,Data!$E$2:$E$20000,B$2,Data!$C$2:$C$20000,">="&$A3,Data!$C$2:$C$20000,"<"&EDATE($A3,1)) | C3: =SUMIFS(Data!$L$2:$L$20000,Data!$E$2:$E$20000,C$2,Data!$C$2:$C$20000,">="&$A3,Data!$C$2:$C$20000,"<"&EDATE($A3,1)) | D3: =SUMIFS(Data!$L$2:$L$20000,Data!$E$2:$E$20000,D$2,Data!$C$2:$C$20000,">="&$A3,Data!$C$2:$C$20000,"<"&EDATE($A3,1)) | E3: =SUMIFS(Data!$L$2:$L$20000,Data!$E$2:$E$20000,E$2,Data!$C$2:$C$20000,">="&$A3,Data!$C$2:$C$20000,"<"&EDATE($A3,1)) | F3: =SUM($B3:$E3) | H3: =IF($G3="","",IF(ABS($F3-$G3)<0.99,"Reconciled",$F3-$G3))
A4: 46235 | B4: =SUMIFS(Data!$L$2:$L$20000,Data!$E$2:$E$20000,B$2,Data!$C$2:$C$20000,">="&$A4,Data!$C$2:$C$20000,"<"&EDATE($A4,1)) | C4: =SUMIFS(Data!$L$2:$L$20000,Data!$E$2:$E$20000,C$2,Data!$C$2:$C$20000,">="&$A4,Data!$C$2:$C$20000,"<"&EDATE($A4,1)) | D4: =SUMIFS(Data!$L$2:$L$20000,Data!$E$2:$E$20000,D$2,Data!$C$2:$C$20000,">="&$A4,Data!$C$2:$C$20000,"<"&EDATE($A4,1)) | E4: =SUMIFS(Data!$L$2:$L$20000,Data!$E$2:$E$20000,E$2,Data!$C$2:$C$20000,">="&$A4,Data!$C$2:$C$20000,"<"&EDATE($A4,1)) | F4: =SUM($B4:$E4) | H4: =IF($G4="","",IF(ABS($F4-$G4)<0.99,"Reconciled",$F4-$G4))
A5: 46266 | B5: =SUMIFS(Data!$L$2:$L$20000,Data!$E$2:$E$20000,B$2,Data!$C$2:$C$20000,">="&$A5,Data!$C$2:$C$20000,"<"&EDATE($A5,1)) | C5: =SUMIFS(Data!$L$2:$L$20000,Data!$E$2:$E$20000,C$2,Data!$C$2:$C$20000,">="&$A5,Data!$C$2:$C$20000,"<"&EDATE($A5,1)) | D5: =SUMIFS(Data!$L$2:$L$20000,Data!$E$2:$E$20000,D$2,Data!$C$2:$C$20000,">="&$A5,Data!$C$2:$C$20000,"<"&EDATE($A5,1)) | E5: =SUMIFS(Data!$L$2:$L$20000,Data!$E$2:$E$20000,E$2,Data!$C$2:$C$20000,">="&$A5,Data!$C$2:$C$20000,"<"&EDATE($A5,1)) | F5: =SUM($B5:$E5) | H5: =IF($G5="","",IF(ABS($F5-$G5)<0.99,"Reconciled",$F5-$G5))
A6: 46296 | B6: =SUMIFS(Data!$L$2:$L$20000,Data!$E$2:$E$20000,B$2,Data!$C$2:$C$20000,">="&$A6,Data!$C$2:$C$20000,"<"&EDATE($A6,1)) | C6: =SUMIFS(Data!$L$2:$L$20000,Data!$E$2:$E$20000,C$2,Data!$C$2:$C$20000,">="&$A6,Data!$C$2:$C$20000,"<"&EDATE($A6,1)) | D6: =SUMIFS(Data!$L$2:$L$20000,Data!$E$2:$E$20000,D$2,Data!$C$2:$C$20000,">="&$A6,Data!$C$2:$C$20000,"<"&EDATE($A6,1)) | E6: =SUMIFS(Data!$L$2:$L$20000,Data!$E$2:$E$20000,E$2,Data!$C$2:$C$20000,">="&$A6,Data!$C$2:$C$20000,"<"&EDATE($A6,1)) | F6: =SUM($B6:$E6) | H6: =IF($G6="","",IF(ABS($F6-$G6)<0.99,"Reconciled",$F6-$G6))
A7: 46327 | B7: =SUMIFS(Data!$L$2:$L$20000,Data!$E$2:$E$20000,B$2,Data!$C$2:$C$20000,">="&$A7,Data!$C$2:$C$20000,"<"&EDATE($A7,1)) | C7: =SUMIFS(Data!$L$2:$L$20000,Data!$E$2:$E$20000,C$2,Data!$C$2:$C$20000,">="&$A7,Data!$C$2:$C$20000,"<"&EDATE($A7,1)) | D7: =SUMIFS(Data!$L$2:$L$20000,Data!$E$2:$E$20000,D$2,Data!$C$2:$C$20000,">="&$A7,Data!$C$2:$C$20000,"<"&EDATE($A7,1)) | E7: =SUMIFS(Data!$L$2:$L$20000,Data!$E$2:$E$20000,E$2,Data!$C$2:$C$20000,">="&$A7,Data!$C$2:$C$20000,"<"&EDATE($A7,1)) | F7: =SUM($B7:$E7) | H7: =IF($G7="","",IF(ABS($F7-$G7)<0.99,"Reconciled",$F7-$G7))
A8: 46357 | B8: =SUMIFS(Data!$L$2:$L$20000,Data!$E$2:$E$20000,B$2,Data!$C$2:$C$20000,">="&$A8,Data!$C$2:$C$20000,"<"&EDATE($A8,1)) | C8: =SUMIFS(Data!$L$2:$L$20000,Data!$E$2:$E$20000,C$2,Data!$C$2:$C$20000,">="&$A8,Data!$C$2:$C$20000,"<"&EDATE($A8,1)) | D8: =SUMIFS(Data!$L$2:$L$20000,Data!$E$2:$E$20000,D$2,Data!$C$2:$C$20000,">="&$A8,Data!$C$2:$C$20000,"<"&EDATE($A8,1)) | E8: =SUMIFS(Data!$L$2:$L$20000,Data!$E$2:$E$20000,E$2,Data!$C$2:$C$20000,">="&$A8,Data!$C$2:$C$20000,"<"&EDATE($A8,1)) | F8: =SUM($B8:$E8) | H8: =IF($G8="","",IF(ABS($F8-$G8)<0.99,"Reconciled",$F8-$G8))
A9: 46388 | B9: =SUMIFS(Data!$L$2:$L$20000,Data!$E$2:$E$20000,B$2,Data!$C$2:$C$20000,">="&$A9,Data!$C$2:$C$20000,"<"&EDATE($A9,1)) | C9: =SUMIFS(Data!$L$2:$L$20000,Data!$E$2:$E$20000,C$2,Data!$C$2:$C$20000,">="&$A9,Data!$C$2:$C$20000,"<"&EDATE($A9,1)) | D9: =SUMIFS(Data!$L$2:$L$20000,Data!$E$2:$E$20000,D$2,Data!$C$2:$C$20000,">="&$A9,Data!$C$2:$C$20000,"<"&EDATE($A9,1)) | E9: =SUMIFS(Data!$L$2:$L$20000,Data!$E$2:$E$20000,E$2,Data!$C$2:$C$20000,">="&$A9,Data!$C$2:$C$20000,"<"&EDATE($A9,1)) | F9: =SUM($B9:$E9) | H9: =IF($G9="","",IF(ABS($F9-$G9)<0.99,"Reconciled",$F9-$G9))
A10: 46419 | B10: =SUMIFS(Data!$L$2:$L$20000,Data!$E$2:$E$20000,B$2,Data!$C$2:$C$20000,">="&$A10,Data!$C$2:$C$20000,"<"&EDATE($A10,1)) | C10: =SUMIFS(Data!$L$2:$L$20000,Data!$E$2:$E$20000,C$2,Data!$C$2:$C$20000,">="&$A10,Data!$C$2:$C$20000,"<"&EDATE($A10,1)) | D10: =SUMIFS(Data!$L$2:$L$20000,Data!$E$2:$E$20000,D$2,Data!$C$2:$C$20000,">="&$A10,Data!$C$2:$C$20000,"<"&EDATE($A10,1)) | E10: =SUMIFS(Data!$L$2:$L$20000,Data!$E$2:$E$20000,E$2,Data!$C$2:$C$20000,">="&$A10,Data!$C$2:$C$20000,"<"&EDATE($A10,1)) | F10: =SUM($B10:$E10) | H10: =IF($G10="","",IF(ABS($F10-$G10)<0.99,"Reconciled",$F10-$G10))
A11: 46447 | B11: =SUMIFS(Data!$L$2:$L$20000,Data!$E$2:$E$20000,B$2,Data!$C$2:$C$20000,">="&$A11,Data!$C$2:$C$20000,"<"&EDATE($A11,1)) | C11: =SUMIFS(Data!$L$2:$L$20000,Data!$E$2:$E$20000,C$2,Data!$C$2:$C$20000,">="&$A11,Data!$C$2:$C$20000,"<"&EDATE($A11,1)) | D11: =SUMIFS(Data!$L$2:$L$20000,Data!$E$2:$E$20000,D$2,Data!$C$2:$C$20000,">="&$A11,Data!$C$2:$C$20000,"<"&EDATE($A11,1)) | E11: =SUMIFS(Data!$L$2:$L$20000,Data!$E$2:$E$20000,E$2,Data!$C$2:$C$20000,">="&$A11,Data!$C$2:$C$20000,"<"&EDATE($A11,1)) | F11: =SUM($B11:$E11) | H11: =IF($G11="","",IF(ABS($F11-$G11)<0.99,"Reconciled",$F11-$G11))
A12: 46478 | B12: =SUMIFS(Data!$L$2:$L$20000,Data!$E$2:$E$20000,B$2,Data!$C$2:$C$20000,">="&$A12,Data!$C$2:$C$20000,"<"&EDATE($A12,1)) | C12: =SUMIFS(Data!$L$2:$L$20000,Data!$E$2:$E$20000,C$2,Data!$C$2:$C$20000,">="&$A12,Data!$C$2:$C$20000,"<"&EDATE($A12,1)) | D12: =SUMIFS(Data!$L$2:$L$20000,Data!$E$2:$E$20000,D$2,Data!$C$2:$C$20000,">="&$A12,Data!$C$2:$C$20000,"<"&EDATE($A12,1)) | E12: =SUMIFS(Data!$L$2:$L$20000,Data!$E$2:$E$20000,E$2,Data!$C$2:$C$20000,">="&$A12,Data!$C$2:$C$20000,"<"&EDATE($A12,1)) | F12: =SUM($B12:$E12) | H12: =IF($G12="","",IF(ABS($F12-$G12)<0.99,"Reconciled",$F12-$G12))
A13: 46508 | B13: =SUMIFS(Data!$L$2:$L$20000,Data!$E$2:$E$20000,B$2,Data!$C$2:$C$20000,">="&$A13,Data!$C$2:$C$20000,"<"&EDATE($A13,1)) | C13: =SUMIFS(Data!$L$2:$L$20000,Data!$E$2:$E$20000,C$2,Data!$C$2:$C$20000,">="&$A13,Data!$C$2:$C$20000,"<"&EDATE($A13,1)) | D13: =SUMIFS(Data!$L$2:$L$20000,Data!$E$2:$E$20000,D$2,Data!$C$2:$C$20000,">="&$A13,Data!$C$2:$C$20000,"<"&EDATE($A13,1)) | E13: =SUMIFS(Data!$L$2:$L$20000,Data!$E$2:$E$20000,E$2,Data!$C$2:$C$20000,">="&$A13,Data!$C$2:$C$20000,"<"&EDATE($A13,1)) | F13: =SUM($B13:$E13) | H13: =IF($G13="","",IF(ABS($F13-$G13)<0.99,"Reconciled",$F13-$G13))
A14: 46539 | B14: =SUMIFS(Data!$L$2:$L$20000,Data!$E$2:$E$20000,B$2,Data!$C$2:$C$20000,">="&$A14,Data!$C$2:$C$20000,"<"&EDATE($A14,1)) | C14: =SUMIFS(Data!$L$2:$L$20000,Data!$E$2:$E$20000,C$2,Data!$C$2:$C$20000,">="&$A14,Data!$C$2:$C$20000,"<"&EDATE($A14,1)) | D14: =SUMIFS(Data!$L$2:$L$20000,Data!$E$2:$E$20000,D$2,Data!$C$2:$C$20000,">="&$A14,Data!$C$2:$C$20000,"<"&EDATE($A14,1)) | E14: =SUMIFS(Data!$L$2:$L$20000,Data!$E$2:$E$20000,E$2,Data!$C$2:$C$20000,">="&$A14,Data!$C$2:$C$20000,"<"&EDATE($A14,1)) | F14: =SUM($B14:$E14) | H14: =IF($G14="","",IF(ABS($F14-$G14)<0.99,"Reconciled",$F14-$G14))
A15: Total | B15: =SUM(B3:B14) | C15: =SUM(C3:C14) | D15: =SUM(D3:D14) | E15: =SUM(E3:E14) | F15: =SUM(F3:F14) | G15: =SUM(G3:G14) | H15: =IF(COUNT($G$3:$G$14)=0,"",IF(ABS(SUMPRODUCT(($G$3:$G$14<>"")*$F$3:$F$14)-SUM($G$3:$G$14))<0.99,"Reconciled",SUMPRODUCT(($G$3:$G$14<>"")*$F$3:$F$14)-SUM($G$3:$G$14)))
A17: P&L Total (yellow) is the only figure you type here. Variance reads "Reconciled" under $0.99.
A18: The Total row measures only the months where a P&L Total has been entered, so a part-year shows no false gap.
A21: Reconciliation — is every record reaching the monthly view?
A22: Report line | B22: Total in tracker | C22: In FY27 months | D22: No date | E22: Dated outside FY27 | F22: Adds up?
A23: Support | B23: =SUMIF(Data!$E$2:$E$20000,$A23,Data!$L$2:$L$20000) | C23: =SUMIFS(Data!$L$2:$L$20000,Data!$E$2:$E$20000,$A23,Data!$O$2:$O$20000,"In FY27") | D23: =SUMIFS(Data!$L$2:$L$20000,Data!$E$2:$E$20000,$A23,Data!$O$2:$O$20000,"No date") | E23: =SUMIFS(Data!$L$2:$L$20000,Data!$E$2:$E$20000,$A23,Data!$O$2:$O$20000,"Outside FY27") | F23: =IF(ABS($B23-SUM($C23:$E23))<0.01,"OK","Check")
A24: Production | B24: =SUMIF(Data!$E$2:$E$20000,$A24,Data!$L$2:$L$20000) | C24: =SUMIFS(Data!$L$2:$L$20000,Data!$E$2:$E$20000,$A24,Data!$O$2:$O$20000,"In FY27") | D24: =SUMIFS(Data!$L$2:$L$20000,Data!$E$2:$E$20000,$A24,Data!$O$2:$O$20000,"No date") | E24: =SUMIFS(Data!$L$2:$L$20000,Data!$E$2:$E$20000,$A24,Data!$O$2:$O$20000,"Outside FY27") | F24: =IF(ABS($B24-SUM($C24:$E24))<0.01,"OK","Check")
A25: Consulting | B25: =SUMIF(Data!$E$2:$E$20000,$A25,Data!$L$2:$L$20000) | C25: =SUMIFS(Data!$L$2:$L$20000,Data!$E$2:$E$20000,$A25,Data!$O$2:$O$20000,"In FY27") | D25: =SUMIFS(Data!$L$2:$L$20000,Data!$E$2:$E$20000,$A25,Data!$O$2:$O$20000,"No date") | E25: =SUMIFS(Data!$L$2:$L$20000,Data!$E$2:$E$20000,$A25,Data!$O$2:$O$20000,"Outside FY27") | F25: =IF(ABS($B25-SUM($C25:$E25))<0.01,"OK","Check")
A26: WIP | B26: =SUMIF(Data!$E$2:$E$20000,$A26,Data!$L$2:$L$20000) | C26: =SUMIFS(Data!$L$2:$L$20000,Data!$E$2:$E$20000,$A26,Data!$O$2:$O$20000,"In FY27") | D26: =SUMIFS(Data!$L$2:$L$20000,Data!$E$2:$E$20000,$A26,Data!$O$2:$O$20000,"No date") | E26: =SUMIFS(Data!$L$2:$L$20000,Data!$E$2:$E$20000,$A26,Data!$O$2:$O$20000,"Outside FY27") | F26: =IF(ABS($B26-SUM($C26:$E26))<0.01,"OK","Check")
A27: Total | B27: =SUM(B23:B26) | C27: =SUM(C23:C26) | D27: =SUM(D23:D26) | E27: =SUM(E23:E26) | F27: =IF(ABS($C$27-$F$15)<0.01,"Matches monthly grid","Does not match monthly grid")
A29: "No date" and "Dated outside FY27" are different problems. A blank date needs filling in. A date outside FY27 is a real date from another financial year.

Sheet Checks
A1: Data quality checks
A2: Live formulas — they update the moment you change anything on the Data tab.
A4: # | B4: What is being checked | C4: Records | D4: Value | E4: Status | F4: What to do
A5: 1 | B5: Records with no date | C5: =COUNTIF(Data!$O$2:$O$20000,"No date") | D5: =SUMIF(Data!$O$2:$O$20000,"No date",Data!$L$2:$L$20000) | E5: =IF(AND(N($C5)=0,ROUND(N($D5),2)=0),"OK","Review") | F5: Filter Date Check to "No date" on the Data tab and fill them in. This money is in no month until you do.
A6: 2 | B6: Records dated outside FY 2026-27 | C6: =COUNTIF(Data!$O$2:$O$20000,"Outside FY27") | D6: =SUMIF(Data!$O$2:$O$20000,"Outside FY27",Data!$L$2:$L$20000) | E6: =IF(AND(N($C6)=0,ROUND(N($D6),2)=0),"OK","Review") | F6: Real dates from another financial year. Decide whether they belong in this tracker at all.
A7: 3 | B7: WIP jobs that have also been invoiced | C7: =COUNTIF(Data!$P$2:$P$20000,"Job already invoiced") | D7: =SUMIF(Data!$P$2:$P$20000,"Job already invoiced",Data!$L$2:$L$20000) | E7: =IF(AND(N($C7)=0,ROUND(N($D7),2)=0),"OK","Review") | F7: Filter Duplicate Check on the Data tab. Each needs a reversing WIP entry or it is double counted.
A8: 4 | B8: Departments that do not map to a report line | C8: =COUNTIF(Data!$E$2:$E$20000,"Unmapped") | E8: =IF(AND(N($C8)=0,ROUND(N($D8),2)=0),"OK","Review") | F8: The department is not on the Lists tab. Correct the record, or add the department and its report line.
A9: 5 | B9: Records with a Type but no Department | C9: =SUMPRODUCT((Data!$B$2:$B$20000<>"")*(Data!$D$2:$D$20000="")) | E9: =IF(AND(N($C9)=0,ROUND(N($D9),2)=0),"OK","Review") | F9: Every record needs a department so it lands on the right report line.
A10: 6 | B10: Records with money but no client | C10: =SUMPRODUCT((Data!$K$2:$K$20000<>0)*(Data!$K$2:$K$20000<>"")*(Data!$G$2:$G$20000="")) | E10: =IF(AND(N($C10)=0,ROUND(N($D10),2)=0),"OK","Review") | F10: A revenue line with no client cannot be traced back to anything.
A11: 7 | B11: Records with money but no job number | C11: =SUMPRODUCT((Data!$K$2:$K$20000<>0)*(Data!$K$2:$K$20000<>"")*(Data!$H$2:$H$20000="")) | E11: =IF(AND(N($C11)=0,ROUND(N($D11),2)=0),"OK","Review") | F11: Without a job number the WIP duplicate check cannot see this record.
A12: 8 | B12: Monthly grid vs total in tracker | D12: =Dashboard!$F$15-Dashboard!$C$27 | E12: =IF(AND(N($C12)=0,ROUND(N($D12),2)=0),"OK","Review") | F12: Should be zero. Anything else means the Dashboard and the Data tab disagree.
A15: WIP jobs that already appear on an invoiced record
A16: Snapshot from the rebuild. The live version is the Duplicate Check column on the Data tab.
A17: Job Number | B17: Client | C17: WIP Amount | D17: Invoiced dept | E17: Invoiced Amount
A18: 26043001 | B18: CBA | C18: -5950 | D18: Support | E18: 11377.12
A19: 26043001 | B19: CBA | C19: -5950 | D19: Support | E19: 11377.12
A20: 2604704 | B20: Aware Super | C20: 1821.25 | D20: Integration | E20: 202647
A21: 2606101 | B21: APA | C21: -4205 | D21: Integration | E21: 4205
A22: 26061108 | B22: APA | C22: -600 | D22: Production | E22: 12600.6
A23: 26061108 | B23: APA | C23: -237.5 | D23: Production | E23: 12600.6
A24: 26061108 | B24: APA | C24: -5413.6 | D24: Production | E24: 12600.6
A25: 26061108 | B25: APA | C25: -4520 | D25: Production | E25: 12600.6
A26: 26061108 | B26: APA | C26: -300 | D26: Production | E26: 12600.6
A27: 26061108 | B27: APA | C27: -690 | D27: Production | E27: 12600.6
A28: 2603104 | B28: Cochlear | C28: 172.5 | D28: Production | E28: 10540.5
A29: 2512804 | B29: RSNSW | C29: 115 | D29: Production | E29: 3261
A30: 26061108 | B30: APA | C30: 172.5 | D30: Production | E30: 12600.6

Sheet Legacy Notes
A1: Notes and comments recovered from the old workbook
A2: In the old file these were Excel comments stuck to cell positions, not to jobs. The macro swapped the data
A3: underneath them every time you changed department, so they had already drifted off the records they describe.
A4: They are listed here with their original cell reference. Paste each into the Notes column on the Data tab
A5: against the right record. Nothing has been guessed — no note has been assigned to a record for you.
A7: Original cell | B7: Type | C7: Author | D7: Date | E7: Note text
A8: U17 | B8: Note | C8: tc={64CAFEA6-7403-473A-A07F-D5B46206835A} | E8: <t xml:space="preserve">[Threaded comment] Your version of Excel allows you to read this threaded comment; however, any edits to it will get removed if the file is opened in a newer version of Excel. Learn more: https://go.microsoft.com/fwlink/?linkid=870924 Comment: PO: BlueChip PO-00016878 Accrued (Y/N & Date): Invoice #: SOR-1395622
A9: V17 | B9: Note | C9: tc={EE0E9B4C-B60C-49C0-8F08-349C412BAFC8} | E9: <t xml:space="preserve">[Threaded comment] Your version of Excel allows you to read this threaded comment; however, any edits to it will get removed if the file is opened in a newer version of Excel. Learn more: https://go.microsoft.com/fwlink/?linkid=870924 Comment: PO: BlueChip PO-00016878 Accrued (Y/N & Date): Invoice #: SOR-1395622
A10: V18 | B10: Threaded | C10: Gianmaria Gonzales-Yao | D10: 2026-08-04 | E10: PO: Barco PO-00016890 Accrued (Y/N & Date): Y & June 2026 Invoice #:
A11: V18 | B11: Note | C11: tc={7E633869-2C05-4011-93DA-CE274E40F652} | E11: <t>[Threaded comment] Your version of Excel allows you to read this threaded comment; however, any edits to it will get removed if the file is opened in a newer version of Excel. Learn more: https://go.microsoft.com/fwlink/?linkid=870924 Comment: PO: Barco PO-00016890 Accrued (Y/N & Date): Y & June 2026 Invoice #:
A12: U19 | B12: Note | C12: tc={C3AFA031-D315-42CB-955F-559A0953C2F6} | E12: <t xml:space="preserve">[Threaded comment] Your version of Excel allows you to read this threaded comment; however, any edits to it will get removed if the file is opened in a newer version of Excel. Learn more: https://go.microsoft.com/fwlink/?linkid=870924 Comment: PO: The Avit Group PO-00016884 The Avit Group PO-00016883 Accrued (Y/N & Date): Y & 30/06/2026 Invoice #:
A13: V19 | B13: Note | C13: tc={B1A6549A-741E-48A0-93A8-3D72C4F6B6CD} | E13: <t xml:space="preserve">[Threaded comment] Your version of Excel allows you to read this threaded comment; however, any edits to it will get removed if the file is opened in a newer version of Excel. Learn more: https://go.microsoft.com/fwlink/?linkid=870924 Comment: PO: The Avit Group PO-00016884 The Avit Group PO-00016883 Accrued (Y/N & Date): Y & 30/06/2026 Invoice #:
A14: U20 | B14: Threaded | C14: Gianmaria Gonzales-Yao | D14: 2026-08-04 | E14: PO: PO-00016891 Accrued (Y/N & Date): Y & June 2026 Invoice #: Videoguys SVG-18021
A15: U20 | B15: Note | C15: tc={432278A5-4123-4995-88E4-681666009693} | E15: <t>[Threaded comment] Your version of Excel allows you to read this threaded comment; however, any edits to it will get removed if the file is opened in a newer version of Excel. Learn more: https://go.microsoft.com/fwlink/?linkid=870924 Comment: PO: PO-00016891 Accrued (Y/N & Date): Y & June 2026 Invoice #: Videoguys SVG-18021
A16: V20 | B16: Threaded | C16: Gianmaria Gonzales-Yao | D16: 2026-08-04 | E16: PO: PO-00016891 Accrued (Y/N & Date): Y & June 2026 Invoice #: Videoguys SVG-18021
A17: V20 | B17: Note | C17: tc={C95DCE37-33FF-4A28-8E75-6667F197CCE1} | E17: <t>[Threaded comment] Your version of Excel allows you to read this threaded comment; however, any edits to it will get removed if the file is opened in a newer version of Excel. Learn more: https://go.microsoft.com/fwlink/?linkid=870924 Comment: PO: PO-00016891 Accrued (Y/N & Date): Y & June 2026 Invoice #: Videoguys SVG-18021
A18: U21 | B18: Note | C18: tc={D5B423E1-891A-42E0-AB10-E5B34B26421D} | E18: <t xml:space="preserve">[Threaded comment] Your version of Excel allows you to read this threaded comment; however, any edits to it will get removed if the file is opened in a newer version of Excel. Learn more: https://go.microsoft.com/fwlink/?linkid=870924 Comment: Videoguys invoice SVG-18021
A19: V21 | B19: Note | C19: tc={E5112070-2700-4FA6-A16E-E69A2CC631FC} | E19: <t xml:space="preserve">[Threaded comment] Your version of Excel allows you to read this threaded comment; however, any edits to it will get removed if the file is opened in a newer version of Excel. Learn more: https://go.microsoft.com/fwlink/?linkid=870924 Comment: Videoguys invoice SVG-18021
A20: U22 | B20: Note | C20: tc={F645B815-BC54-4739-8F08-E26362FA348E} | E20: <t xml:space="preserve">[Threaded comment] Your version of Excel allows you to read this threaded comment; however, any edits to it will get removed if the file is opened in a newer version of Excel. Learn more: https://go.microsoft.com/fwlink/?linkid=870924 Comment: PO: Fredon PO-00016852 Accrued (Y/N & Date): Y & April 2026 Invoice #:
A21: V22 | B21: Note | C21: tc={464F0CEA-A369-43EC-8D87-09E13085EAF9} | E21: <t xml:space="preserve">[Threaded comment] Your version of Excel allows you to read this threaded comment; however, any edits to it will get removed if the file is opened in a newer version of Excel. Learn more: https://go.microsoft.com/fwlink/?linkid=870924 Comment: PO: Fredon PO-00016852 Accrued (Y/N & Date): Y & April 2026 Invoice #:
A22: U23 | B22: Note | C22: tc={88B86C69-7FD4-4F41-92D1-98518D7CBDC0} | E22: <t xml:space="preserve">[Threaded comment] Your version of Excel allows you to read this threaded comment; however, any edits to it will get removed if the file is opened in a newer version of Excel. Learn more: https://go.microsoft.com/fwlink/?linkid=870924 Comment: PO: Fredon Fredon - PO-00016855 Accrued (Y/N & Date): Y & 30/06/2026 Invoice #:
A23: V23 | B23: Threaded | C23: Gianmaria Gonzales-Yao | D23: 2026-08-19 | E23: Bill received on 14/08/2026 Inv 198300267
A24: V23 | B24: Note | C24: tc={580A4F97-8784-4209-89E5-D2BEA6549D1C} | E24: <t>[Threaded comment] Your version of Excel allows you to read this threaded comment; however, any edits to it will get removed if the file is opened in a newer version of Excel. Learn more: https://go.microsoft.com/fwlink/?linkid=870924 Comment: PO: Fredon Fredon - PO-00016855 Accrued (Y/N & Date): Y & 30/06/2026 Invoice #: Reply: Bill received on 14/08/2026 Inv 198300267
A25: U24 | B25: Note | C25: tc={6ECBC017-4130-435D-BF00-5BE2F45103A6} | E25: <t xml:space="preserve">[Threaded comment] Your version of Excel allows you to read this threaded comment; however, any edits to it will get removed if the file is opened in a newer version of Excel. Learn more: https://go.microsoft.com/fwlink/?linkid=870924 Comment: PO: Fredon Fredon - PO-00016855 Accrued (Y/N & Date): Y & 30/06/2026 Invoice #: Reply: Fredon INV11S-26080021
A26: V24 | B26: Note | C26: tc={A15634CA-358E-4BDB-8CDC-5487C2A57F2E} | E26: <t xml:space="preserve">[Threaded comment] Your version of Excel allows you to read this threaded comment; however, any edits to it will get removed if the file is opened in a newer version of Excel. Learn more: https://go.microsoft.com/fwlink/?linkid=870924 Comment: PO: Fredon - PO-00016856 Accrued (Y/N & Date): Y & 30/06/2026 Invoice #: INV11S-26080021
A27: U25 | B27: Note | C27: tc={E8AFBB0D-66C7-43D8-AC34-ADEAC8B82E3A} | E27: <t xml:space="preserve">[Threaded comment] Your version of Excel allows you to read this threaded comment; however, any edits to it will get removed if the file is opened in a newer version of Excel. Learn more: https://go.microsoft.com/fwlink/?linkid=870924 Comment: PO: Fredon - PO-00016857 Accrued (Y/N & Date): Y & 30/06/2026 Invoice #:
A28: V25 | B28: Note | C28: tc={12399B37-19EB-49AC-9FC8-419497837192} | E28: <t xml:space="preserve">[Threaded comment] Your version of Excel allows you to read this threaded comment; however, any edits to it will get removed if the file is opened in a newer version of Excel. Learn more: https://go.microsoft.com/fwlink/?linkid=870924 Comment: PO: Fredon - PO-00016857 Accrued (Y/N & Date): Y & 30/06/2026 Invoice #:
A29: U26 | B29: Threaded | C29: Emelda Waiya | D29: 2026-08-04 | E29: Fredon INV11S-26080019 WIP: Reverse
A30: U26 | B30: Note | C30: tc={3C7D3A40-B297-4077-BD0A-F71143DF873E} | E30: <t>[Threaded comment] Your version of Excel allows you to read this threaded comment; however, any edits to it will get removed if the file is opened in a newer version of Excel. Learn more: https://go.microsoft.com/fwlink/?linkid=870924 Comment: Fredon INV11S-26080019 WIP: Reverse
A31: V26 | B31: Threaded | C31: Emelda Waiya | D31: 2026-08-04 | E31: Fredon INV11S-26080019 WIP: Reverse
A32: V26 | B32: Note | C32: tc={D8C53BB3-AEDA-4676-9B21-8B249A5025E3} | E32: <t>[Threaded comment] Your version of Excel allows you to read this threaded comment; however, any edits to it will get removed if the file is opened in a newer version of Excel. Learn more: https://go.microsoft.com/fwlink/?linkid=870924 Comment: Fredon INV11S-26080019 WIP: Reverse
A33: V27 | B33: Note | C33: tc={F9AAE1E7-E84D-4BCB-863D-5B44FA57F6DD} | E33: <t xml:space="preserve">[Threaded comment] Your version of Excel allows you to read this threaded comment; however, any edits to it will get removed if the file is opened in a newer version of Excel. Learn more: https://go.microsoft.com/fwlink/?linkid=870924 Comment: PO: Fredon PO-00016897 Accrued (Y/N & Date): Invoice #:
A34: U29 | B34: Note | C34: tc={7905AD5A-56E7-4172-BD87-D176F2E31C49} | E34: <t xml:space="preserve">[Threaded comment] Your version of Excel allows you to read this threaded comment; however, any edits to it will get removed if the file is opened in a newer version of Excel. Learn more: https://go.microsoft.com/fwlink/?linkid=870924 Comment: PO: no PO yet Accrued (Y/N & Date): Y & July 2026 Invoice #:
A35: V29 | B35: Note | C35: tc={9E2FFBE7-3071-479A-A6E8-09A0840A6836} | E35: <t xml:space="preserve">[Threaded comment] Your version of Excel allows you to read this threaded comment; however, any edits to it will get removed if the file is opened in a newer version of Excel. Learn more: https://go.microsoft.com/fwlink/?linkid=870924 Comment: Invoice: Harvey Norman INV31004114902 - $5,529.10 PO: Crestron PO-00016909 $20,678.00 Reply: Dicker Data INV7697713 $1,403.28
A36: V30 | B36: Threaded | C36: Emelda Waiya | D36: 2026-08-04 | E36: Invoice SOR-1404815 Full invoice recieved
A37: V30 | B37: Note | C37: tc={BB87ACD6-893B-495E-B563-7829733592A3} | E37: <t>[Threaded comment] Your version of Excel allows you to read this threaded comment; however, any edits to it will get removed if the file is opened in a newer version of Excel. Learn more: https://go.microsoft.com/fwlink/?linkid=870924 Comment: Invoice SOR-1404815 Full invoice recieved
A38: AH31 | B38: Note | C38: tc={B00BBD23-4E8F-414D-A202-A9DC0CE6AEB0} | E38: <t xml:space="preserve">[Threaded comment] Your version of Excel allows you to read this threaded comment; however, any edits to it will get removed if the file is opened in a newer version of Excel. Learn more: https://go.microsoft.com/fwlink/?linkid=870924 Comment: Suzy Cue - Invoice No. 10590 ($2184.72) Split between this event and PWC GB Webcast on 11.8.26
A39: U31 | B39: Threaded | C39: Emelda Waiya | D39: 2026-08-24 | E39: AVIT INV016005230 WIP: Reverse
A40: U31 | B40: Note | C40: tc={C23A94B4-0DFB-44CB-BCA5-60EBF5420128} | E40: <t>[Threaded comment] Your version of Excel allows you to read this threaded comment; however, any edits to it will get removed if the file is opened in a newer version of Excel. Learn more: https://go.microsoft.com/fwlink/?linkid=870924 Comment: AVIT INV016005230 WIP: Reverse
A41: V31 | B41: Note | C41: tc={5DFA6BBF-FA44-4112-91A3-8C485BAA780C} | E41: <t xml:space="preserve">[Threaded comment] Your version of Excel allows you to read this threaded comment; however, any edits to it will get removed if the file is opened in a newer version of Excel. Learn more: https://go.microsoft.com/fwlink/?linkid=870924 Comment: TAG INV360930
A42: W32 | B42: Threaded | C42: Gianmaria Gonzales-Yao | D42: 2026-08-07 | E42: INV-86016 received in full
A43: W32 | B43: Note | C43: tc={EB43A1B5-EAE3-47BB-9676-0D23A0BE733C} | E43: <t>[Threaded comment] Your version of Excel allows you to read this threaded comment; however, any edits to it will get removed if the file is opened in a newer version of Excel. Learn more: https://go.microsoft.com/fwlink/?linkid=870924 Comment: PO: PO-00016904 Accrued (Y/N & Date): Y & 31/07/2026 Invoice #: Reply: INV-86016 received in full
A44: V33 | B44: Note | C44: tc={0D0FBC52-D318-4A42-ABA8-ABCABC7BB662} | E44: <t xml:space="preserve">[Threaded comment] Your version of Excel allows you to read this threaded comment; however, any edits to it will get removed if the file is opened in a newer version of Excel. Learn more: https://go.microsoft.com/fwlink/?linkid=870924 Comment: Dicker Data invoice INV7647226
A45: AH34 | B45: Note | C45: tc={10CDAE97-637B-490F-8488-E90CF32FE6F3} | E45: <t xml:space="preserve">[Threaded comment] Your version of Excel allows you to read this threaded comment; however, any edits to it will get removed if the file is opened in a newer version of Excel. Learn more: https://go.microsoft.com/fwlink/?linkid=870924 Comment: Suzy Cue - Invoice No. 10590 ($2184.72)
A46: V34 | B46: Note | C46: tc={D7B7D7FF-FA79-453C-A13A-4F147DD756B1} | E46: <t xml:space="preserve">[Threaded comment] Your version of Excel allows you to read this threaded comment; however, any edits to it will get removed if the file is opened in a newer version of Excel. Learn more: https://go.microsoft.com/fwlink/?linkid=870924 Comment: PO: Complete AV PO-00016902 Accrued (Y/N & Date): N Invoice #: 31407
A47: AF35 | B47: Note | C47: tc={AED2653A-DF10-4A30-9F91-ECA455B08BCC} | E47: <t xml:space="preserve">[Threaded comment] Your version of Excel allows you to read this threaded comment; however, any edits to it will get removed if the file is opened in a newer version of Excel. Learn more: https://go.microsoft.com/fwlink/?linkid=870924 [Tasks] There is a task anchored to this comment that cannot be viewed in your client. Comment: @Gianmaria Gonzales-Yao - could you just check the Vid allocations as the other Tracker has an amount of $3047 and we have $1600- maybe my allocations are incorrect?
A48: AH35 | B48: Threaded | C48: Mitchell Healey | D48: 2026-08-31 | E48: Riedel INVOICE # : 00010213 ($980.16)
A49: AH35 | B49: Note | C49: tc={E6A7C08C-C05A-428C-965B-51FB53D9A92D} | E49: <t>[Threaded comment] Your version of Excel allows you to read this threaded comment; however, any edits to it will get removed if the file is opened in a newer version of Excel. Learn more: https://go.microsoft.com/fwlink/?linkid=870924 Comment: Riedel INVOICE # : 00010213 ($980.16)
A50: U35 | B50: Note | C50: tc={3136511E-86B4-4EC6-A835-AFA87448BA0E} | E50: <t xml:space="preserve">[Threaded comment] Your version of Excel allows you to read this threaded comment; however, any edits to it will get removed if the file is opened in a newer version of Excel. Learn more: https://go.microsoft.com/fwlink/?linkid=870924 Comment: PO: Dicker Data PO-00016928 Accrued (Y/N & Date): Y & 21/08/2026 Invoice #:
A51: V35 | B51: Note | C51: tc={02513043-4B30-4682-AFBB-8C49A4358188} | E51: <t xml:space="preserve">[Threaded comment] Your version of Excel allows you to read this threaded comment; however, any edits to it will get removed if the file is opened in a newer version of Excel. Learn more: https://go.microsoft.com/fwlink/?linkid=870924 Comment: PO: Dicker Data PO-00016927 Accrued (Y/N & Date): y & 21/08/2026 Invoice #:
A52: AH36 | B52: Threaded | C52: Mitchell Healey | D52: 2026-08-31 | E52: AI Media Captioning Tax Invoice No. 21970 ($850)
A53: AH36 | B53: Note | C53: tc={654956BE-59AB-4928-B21D-552879291475} | E53: <t xml:space="preserve">[Threaded comment] Your version of Excel allows you to read this threaded comment; however, any edits to it will get removed if the file is opened in a newer version of Excel. Learn more: https://go.microsoft.com/fwlink/?linkid=870924 Comment: AI Media Captioning Tax Invoice No. 21970 ($850) Reply: Chorus Call Invoice 02-82168 ($87.84) & Invoice 02-82169 ($1398.36)
A54: U36 | B54: Note | C54: tc={40400985-DC8F-420D-84FE-A2A087290B7C} | E54: <t xml:space="preserve">[Threaded comment] Your version of Excel allows you to read this threaded comment; however, any edits to it will get removed if the file is opened in a newer version of Excel. Learn more: https://go.microsoft.com/fwlink/?linkid=870924 Comment: PO: Dicker Data PO-00016928 Accrued (Y/N & Date): Y & 19/08/2026 Invoice #:
A55: V36 | B55: Note | C55: tc={E5D927D0-DF6C-4697-BB5C-4C052B5CC2D0} | E55: <t xml:space="preserve">[Threaded comment] Your version of Excel allows you to read this threaded comment; however, any edits to it will get removed if the file is opened in a newer version of Excel. Learn more: https://go.microsoft.com/fwlink/?linkid=870924 Comment: PO: Dicker Data PO-00016927 Accrued (Y/N & Date): Y & 19/08/2026 Invoice #:
A56: AA37 | B56: Note | C56: tc={0A2845B9-525D-44DF-A137-CA940C1379EC} | E56: <t xml:space="preserve">[Threaded comment] Your version of Excel allows you to read this threaded comment; however, any edits to it will get removed if the file is opened in a newer version of Excel. Learn more: https://go.microsoft.com/fwlink/?linkid=870924 Comment: Webcast Operator 9 Hours PROD
A57: AH37 | B57: Note | C57: tc={0C1579BE-A923-4C6D-83F6-72EB1781AC3D} | E57: <t xml:space="preserve">[Threaded comment] Your version of Excel allows you to read this threaded comment; however, any edits to it will get removed if the file is opened in a newer version of Excel. Learn more: https://go.microsoft.com/fwlink/?linkid=870924 Comment: Hire Intelligence Invoice No: CS166507 (66% of $2120) Reply: Chorus Call Invoice 02-82170 ($1737.72) Reply: TypeTranscripts Invoice - 6032 (Total $608.40 but included ASX) - $369.20 being AGL
A58: U37 | B58: Note | C58: tc={F738CB12-40B5-479D-A6AD-5FD1009E72B1} | E58: <t xml:space="preserve">[Threaded comment] Your version of Excel allows you to read this threaded comment; however, any edits to it will get removed if the file is opened in a newer version of Excel. Learn more: https://go.microsoft.com/fwlink/?linkid=870924 Comment: PO: Complete AV PO-00016905 Accrued (Y/N & Date): N Invoice #: Reply: PO: Complete AV PO-00016905 Accrued (Y/N & Date): Y & 19/08/2026 Invoice #:
A59: V37 | B59: Note | C59: tc={CEF1B43F-600E-48CB-B70D-2A5868A0F46F} | E59: <t xml:space="preserve">[Threaded comment] Your version of Excel allows you to read this threaded comment; however, any edits to it will get removed if the file is opened in a newer version of Excel. Learn more: https://go.microsoft.com/fwlink/?linkid=870924 Comment: PO: Crestron PO-00016916 $6,993.00 Accrued (Y/N & Date): Y & 18/08/2026 Invoice #: PO: Midwich PO-00016919 $1322 Accrued (Y/N & Date): Y & 18/08/2026 Invoice #: PO: Leading Solutions PO-00016918 $166.45 Accrued (Y/N & Date): Y & 18/08/2026 Invoice #: PO: Dicker Data PO-00016917 $151.95 Accrued (Y/N & Date): Y & 18/08/2026 Invoice #: PO: Midwich PO-00016919 $1322 Accrued (Y/N & Date): Y & 18/08/2026 Invoice #: SO-MWAU11187
A60: AA38 | B60: Note | C60: tc={3F64684F-A100-40C7-AD96-67E61BA9C235} | E60: <t xml:space="preserve">[Threaded comment] Your version of Excel allows you to read this threaded comment; however, any edits to it will get removed if the file is opened in a newer version of Excel. Learn more: https://go.microsoft.com/fwlink/?linkid=870924 Comment: Webcast Operator 9 Hours PROD
A61: AH38 | B61: Note | C61: tc={2BF254E8-3C48-4DCE-90D0-5411E5EFDA0E} | E61: <t xml:space="preserve">[Threaded comment] Your version of Excel allows you to read this threaded comment; however, any edits to it will get removed if the file is opened in a newer version of Excel. Learn more: https://go.microsoft.com/fwlink/?linkid=870924 Comment: Hire Intelligence Invoice No: CS166507 (33% of $2120)
A62: V38 | B62: Threaded | C62: Emelda Waiya | D62: 2026-08-27 | E62: Crestron invoice INV950917698 $2500
A63: V38 | B63: Threaded | C63: Emelda Waiya | D63: 2026-08-27 | E63: @Daniel Sobkowski Hi Dan, could you please advise if we are purchasing any other items apart from Crestron as it seems you have put $2647 but the Crestron invoice is only $2500?
A64: V38 | B64: Note | C64: tc={1EB4EDE9-79C0-4E9D-8F61-F18EF3A03599} | E64: <t>[Threaded comment] Your version of Excel allows you to read this threaded comment; however, any edits to it will get removed if the file is opened in a newer version of Excel. Learn more: https://go.microsoft.com/fwlink/?linkid=870924 [Tasks] There is a task anchored to this comment that cannot be viewed in your client. Comment: PO: Crestron PO-00016922 Accrued (Y/N & Date): Y & 19/08/2026 Invoice #: Reply: Crestron invoice INV950917698 $2500 Reply: @Daniel Sobkowski Hi Dan, could you please advise if we are purchasing any other items apart from Crestron as it seems you have put $2647 but the Crestron invoice is only $2500?
A65: AH40 | B65: Threaded | C65: Mitchell Healey | D65: 2026-08-31 | E65: Hire Intelligence - Invoice CS166508 ($1465.60) Wordbirds Autocue - Invoice 1971 ($2359.54)
A66: AH40 | B66: Note | C66: tc={A0ABC931-20FF-4CD9-9ADB-473B42326840} | E66: <t xml:space="preserve">[Threaded comment] Your version of Excel allows you to read this threaded comment; however, any edits to it will get removed if the file is opened in a newer version of Excel. Learn more: https://go.microsoft.com/fwlink/?linkid=870924 Comment: Hire Intelligence - Invoice CS166508 ($1465.60) Wordbirds Autocue - Invoice 1971 ($2359.54) Reply: Chorus Call - Invoice Invoice Number: 02-82171 ($941.44) We are also adding the previous $250 cancellation fee to this one from earlier in the year. Reply: TypeTranscripts Invoice - 6032 (Total $608.40 but included AGL) - $239.20 being ASX
A67: U41 | B67: Threaded | C67: Emelda Waiya | D67: 2026-08-19 | E67: PO: Complete AV PO-00016913 Accrued (Y/N & Date): Y & 19/08/2026 Invoice #:
A68: U41 | B68: Note | C68: tc={6244562F-3DAB-4D07-BC53-067A783EC98D} | E68: <t>[Threaded comment] Your version of Excel allows you to read this threaded comment; however, any edits to it will get removed if the file is opened in a newer version of Excel. Learn more: https://go.microsoft.com/fwlink/?linkid=870924 Comment: PO: Complete AV PO-00016913 Accrued (Y/N & Date): Y & 19/08/2026 Invoice #:
A69: AH42 | B69: Note | C69: tc={9ACB1C3E-3CB7-4347-BFB2-D716DDA8CF71} | E69: <t xml:space="preserve">[Threaded comment] Your version of Excel allows you to read this threaded comment; however, any edits to it will get removed if the file is opened in a newer version of Excel. Learn more: https://go.microsoft.com/fwlink/?linkid=870924 Comment: Chorus Call - Invoice Number: 02-82202 ($1,813.16) Reply: Type Transcrips - Invoice 6036 $353.60
A70: V42 | B70: Threaded | C70: Emelda Waiya | D70: 2026-08-20 | E70: PO: Dicker Data PO-00016924 Accrued (Y/N & Date): Y & 20/08/2026 Invoice #:
A71: V42 | B71: Note | C71: tc={D8992ED2-5B5D-4331-BD5C-7B20B4C889B8} | E71: <t xml:space="preserve">[Threaded comment] Your version of Excel allows you to read this threaded comment; however, any edits to it will get removed if the file is opened in a newer version of Excel. Learn more: https://go.microsoft.com/fwlink/?linkid=870924 Comment: PO: Dicker Data PO-00016924 Accrued (Y/N & Date): Y & 20/08/2026 Invoice #: Reply: Invoice INV7697058
A72: V43 | B72: Note | C72: tc={AD87BDBB-D3B6-48F7-A511-44CD3960CF3D} | E72: <t xml:space="preserve">[Threaded comment] Your version of Excel allows you to read this threaded comment; however, any edits to it will get removed if the file is opened in a newer version of Excel. Learn more: https://go.microsoft.com/fwlink/?linkid=870924 Comment: PO: Concept AV PO-00016929 Accrued (Y/N & Date): N Invoice #:
A73: AA45 | B73: Note | C73: tc={7C44114B-99D0-4C56-BD7A-183319910702} | E73: <t xml:space="preserve">[Threaded comment] Your version of Excel allows you to read this threaded comment; however, any edits to it will get removed if the file is opened in a newer version of Excel. Learn more: https://go.microsoft.com/fwlink/?linkid=870924 Comment: Plus webcasting Delivery quotation
A74: AH45 | B74: Threaded | C74: Mitchell Healey | D74: 2026-08-31 | E74: Headroom AV Invoice Number INV-0017 ($2822.50)
A75: AH45 | B75: Note | C75: tc={BB22B8A5-56C3-428B-A108-FCFDBC34E75B} | E75: <t xml:space="preserve">[Threaded comment] Your version of Excel allows you to read this threaded comment; however, any edits to it will get removed if the file is opened in a newer version of Excel. Learn more: https://go.microsoft.com/fwlink/?linkid=870924 Comment: Headroom AV Invoice Number INV-0017 ($2822.50) Reply: Chorus Call Teleconference Invoice 02-82207 ($1,179.36) Reply: Type Transcrips - Invoice 6036 $270.40
A76: AH46 | B76: Note | C76: tc={4BD19B7E-0A3E-4990-ADED-3CAC22D3E985} | E76: <t xml:space="preserve">[Threaded comment] Your version of Excel allows you to read this threaded comment; however, any edits to it will get removed if the file is opened in a newer version of Excel. Learn more: https://go.microsoft.com/fwlink/?linkid=870924 Comment: Chorus Call Invoice - Invoice Number: 02-82223 ($976.64) Reply: Type Transcripts INVOICE NO. 6039 ($244.40)
A77: AH48 | B77: Note | C77: tc={CB481D73-FC17-4A8A-950C-0047F8518B98} | E77: <t xml:space="preserve">[Threaded comment] Your version of Excel allows you to read this threaded comment; however, any edits to it will get removed if the file is opened in a newer version of Excel. Learn more: https://go.microsoft.com/fwlink/?linkid=870924 Comment: Chorus Call - Invoice Number: 02-82224 ($1,342.92) Reply: Type Transcripts INVOICE NO. 6039 ($462.80)
A78: K48 | B78: Note | C78: tc={2CEC4323-F5C9-4D66-B2BE-F8256FA7A3BA} | E78: <t xml:space="preserve">[Threaded comment] Your version of Excel allows you to read this threaded comment; however, any edits to it will get removed if the file is opened in a newer version of Excel. Learn more: https://go.microsoft.com/fwlink/?linkid=870924 Comment: Previously invoiced package
A79: AH49 | B79: Threaded | C79: Mitchell Healey | D79: 2026-08-31 | E79: Hire Intelligence - Invoice CS166600 ($784.50)
A80: AH49 | B80: Note | C80: tc={6429DDF6-8C32-406D-B076-0F72F2D4E071} | E80: <t>[Threaded comment] Your version of Excel allows you to read this threaded comment; however, any edits to it will get removed if the file is opened in a newer version of Excel. Learn more: https://go.microsoft.com/fwlink/?linkid=870924 Comment: Hire Intelligence - Invoice CS166600 ($784.50)
A81: K50 | B81: Note | C81: tc={81AD2B60-1894-4C46-8BE8-3D00C49F8AE8} | E81: <t xml:space="preserve">[Threaded comment] Your version of Excel allows you to read this threaded comment; however, any edits to it will get removed if the file is opened in a newer version of Excel. Learn more: https://go.microsoft.com/fwlink/?linkid=870924 Comment: Previously invoiced package
A82: AH51 | B82: Threaded | C82: Mitchell Healey | D82: 2026-08-31 | E82: Hire Intel Tax Invoice CS166632 ($1350)
A83: AH51 | B83: Note | C83: tc={80977456-C2DA-4B9F-8530-B80CF4EFB1EF} | E83: <t>[Threaded comment] Your version of Excel allows you to read this threaded comment; however, any edits to it will get removed if the file is opened in a newer version of Excel. Learn more: https://go.microsoft.com/fwlink/?linkid=870924 Comment: Hire Intel Tax Invoice CS166632 ($1350)
A84: AH52 | B84: Threaded | C84: Mitchell Healey | D84: 2026-08-31 | E84: WordBirds Invoice - INV-1978 ($831.25)
A85: AH52 | B85: Threaded | C85: Mitchell Healey | D85: 2026-08-31 | E85: Type Transcripts - INVOICE NO. 6041 ($800.80) but Divided: Ventia - $275.60 Symal - $234 Virgin - $275.60
A86: AH52 | B86: Note | C86: tc={049EB4F5-48B9-43D0-8B41-F4D97E4993BB} | E86: <t>[Threaded comment] Your version of Excel allows you to read this threaded comment; however, any edits to it will get removed if the file is opened in a newer version of Excel. Learn more: https://go.microsoft.com/fwlink/?linkid=870924 Comment: WordBirds Invoice - INV-1978 ($831.25) Reply: Chorus Call Invoice Number: 02-82243 ($1196.24) Reply: Type Transcripts - INVOICE NO. 6041 ($800.80) but Divided: Ventia - $275.60 Symal - $234 Virgin - $275.60
A87: AF53 | B87: Threaded | C87: Emelda Waiya | D87: 2026-08-31 | E87: @Mitchell Healey my video total is $1,785 including the Camera Director revenue
A88: AF53 | B88: Threaded | C88: Mitchell Healey | D88: 2026-08-31 | E88: @Emelda Waiya, Let's go with that then. The camera director is actually a vision switcher but for this month, video revenue is low so we can include in Video labour.
A89: AF53 | B89: Note | C89: tc={725B7A31-FB9C-40DB-8705-4FD29ED17AC9} | E89: <t>[Threaded comment] Your version of Excel allows you to read this threaded comment; however, any edits to it will get removed if the file is opened in a newer version of Excel. Learn more: https://go.microsoft.com/fwlink/?linkid=870924 [Tasks] There is a task anchored to this comment that cannot be viewed in your client. Comment: @Mitchell Healey my video total is $1,785 including the Camera Director revenue Reply: @Emelda Waiya, Let's go with that then. The camera director is actually a vision switcher but for this month, video revenue is low so we can include in Video labour.
A90: AH53 | B90: Threaded | C90: Mitchell Healey | D90: 2026-08-31 | E90: AusStage Quote CORTECSE00167 $14745.30
A91: AH53 | B91: Note | C91: tc={DCBB289E-22AB-4CD0-AC51-BA080E8251C0} | E91: <t>[Threaded comment] Your version of Excel allows you to read this threaded comment; however, any edits to it will get removed if the file is opened in a newer version of Excel. Learn more: https://go.microsoft.com/fwlink/?linkid=870924 Comment: AusStage Quote CORTECSE00167 $14745.30
A92: AH54 | B92: Threaded | C92: Mitchell Healey | D92: 2026-08-31 | E92: Headroom AV - Invoice 0024 ($1640.00)
A93: AH54 | B93: Threaded | C93: Mitchell Healey | D93: 2026-08-31 | E93: Type Transcripts - INVOICE NO. 6041 ($800.80) but Divided: Ventia - $275.60 Symal - $234 Virgin - $275.60
A94: AH54 | B94: Note | C94: tc={61F0DDC6-FB43-4E9C-BBF5-671D67EAAD41} | E94: <t>[Threaded comment] Your version of Excel allows you to read this threaded comment; however, any edits to it will get removed if the file is opened in a newer version of Excel. Learn more: https://go.microsoft.com/fwlink/?linkid=870924 Comment: Headroom AV - Invoice 0024 ($1640.00) Reply: Type Transcripts - INVOICE NO. 6041 ($800.80) but Divided: Ventia - $275.60 Symal - $234 Virgin - $275.60
A95: AH57 | B95: Threaded | C95: Mitchell Healey | D95: 2026-08-31 | E95: VAST AV Order Number QU01788 ($2955)
A96: AH57 | B96: Note | C96: tc={CE561B30-9DCE-4A33-B592-9802BF84385D} | E96: <t xml:space="preserve">[Threaded comment] Your version of Excel allows you to read this threaded comment; however, any edits to it will get removed if the file is opened in a newer version of Excel. Learn more: https://go.microsoft.com/fwlink/?linkid=870924 Comment: VAST AV Order Number QU01788 ($2955) Reply: Chorus Call Invoices: Invoice Number: 02-82299 - ($902.96) Invoice Number: 02-82300 ($600.72) Reply: Type Transcripts - INVOICE NO. 6041 ($800.80) but Divided: Ventia - $275.60 Symal - $234 Virgin - $275.60
A97: U59 | B97: Note | C97: tc={8341720E-0468-4E19-A3C2-19424F79EA74} | E97: <t xml:space="preserve">[Threaded comment] Your version of Excel allows you to read this threaded comment; however, any edits to it will get removed if the file is opened in a newer version of Excel. Learn more: https://go.microsoft.com/fwlink/?linkid=870924 Comment: Dicker Data INV7620669
A98: V59 | B98: Threaded | C98: Gianmaria Gonzales-Yao | D98: 2026-08-14 | E98: Dicker Data INV7620669AA
A99: V59 | B99: Note | C99: tc={C85D9825-B6BD-4AEB-878A-B78F57090EE1} | E99: <t>[Threaded comment] Your version of Excel allows you to read this threaded comment; however, any edits to it will get removed if the file is opened in a newer version of Excel. Learn more: https://go.microsoft.com/fwlink/?linkid=870924 Comment: Dicker Data INV7620669AA
A100: U60 | B100: Note | C100: tc={55C110FE-281D-47B5-B524-431DBEE8A7DE} | E100: <t xml:space="preserve">[Threaded comment] Your version of Excel allows you to read this threaded comment; however, any edits to it will get removed if the file is opened in a newer version of Excel. Learn more: https://go.microsoft.com/fwlink/?linkid=870924 Comment: PO: Fredon PO-00016897 Accrued (Y/N & Date): Y & July 2026 Invoice #:
A101: V60 | B101: Note | C101: tc={6C4533A8-87C6-40CA-8783-F639AF3F4F8B} | E101: <t xml:space="preserve">[Threaded comment] Your version of Excel allows you to read this threaded comment; however, any edits to it will get removed if the file is opened in a newer version of Excel. Learn more: https://go.microsoft.com/fwlink/?linkid=870924 Comment: PO: Fredon PO-00016897 Accrued (Y/N & Date): Y & July 2026 Invoice #:
