Workbook

Sheet Cash Flow
A1: Corporate Technology Services Pty Ltd
A2: Weekly Cash Flow Forecast vs Actual - 29 October to 2 December 2026
A3: How this works: the Forecast columns are formulas off the Receivables, Payables, Payroll and Assumptions tabs. Each week, put the actual movements in the yellow Actual column, type in the closing bank balance from CommBiz, and set 'Actuals entered' to 1. The next week then starts from the real bank balance and the difference row shows anything that's been missed. The Creditors run row comes off the Creditors Run tab - paste the Xero aged payables detail in there each month.
B5: Week 1 | D5: Week 2 | F5: Week 3 | H5: Week 4 | J5: Week 5 | L5: Total | N5: Variance | O5: Notes
B6: =TEXT(Assumptions!$B$44,"d mmm")&" - "&TEXT(Assumptions!$C$44,"d mmm") -> 29 Oct - 4 Nov | D6: =TEXT(Assumptions!$B$45,"d mmm")&" - "&TEXT(Assumptions!$C$45,"d mmm") -> 5 Nov - 11 Nov | F6: =TEXT(Assumptions!$B$46,"d mmm")&" - "&TEXT(Assumptions!$C$46,"d mmm") -> 12 Nov - 18 Nov | H6: =TEXT(Assumptions!$B$47,"d mmm")&" - "&TEXT(Assumptions!$C$47,"d mmm") -> 19 Nov - 25 Nov | J6: =TEXT(Assumptions!$B$48,"d mmm")&" - "&TEXT(Assumptions!$C$48,"d mmm") -> 26 Nov - 2 Dec | N6: (weeks with
A7: $ AUD (GST inclusive) | B7: Forecast | C7: Actual | D7: Forecast | E7: Actual | F7: Forecast | G7: Actual | H7: Forecast | I7: Actual | J7: Forecast | K7: Actual | L7: Forecast | M7: Actual | N7: actuals)
A8: Actuals entered for this week? (1 = yes) | C8: 0 | E8: 0 | G8: 0 | I8: 0 | K8: 0 | O8: Set to 1 once the week is done and the CommBiz balance is in. Then the next week opens from the real number.
A10: OPENING BANK BALANCE | B10: =Assumptions!$B$6 -> 439930.68 | C10: =B10 -> 439930.68 | D10: =IF(C$8=1,C59,B58) -> 198149.53 | E10: =D10 -> 198149.53 | F10: =IF(E$8=1,E59,D58) -> 416895.7 | G10: =F10 -> 416895.7 | H10: =IF(G$8=1,G59,F58) -> 576615.91 | I10: =H10 -> 576615.91 | J10: =IF(I$8=1,I59,H58) -> 437719.9 | K10: =J10 -> 437719.9 | L10: =B10 -> 439930.68 | M10: =C10 -> 439930.68
A12: INCOME
A13: Trading income - customer receipts (invoices) | B13: =SUMIFS(Receivables!$F$5:$F$65,Receivables!$H$5:$H$65,">="&Assumptions!$B$44,Receivables!$H$5:$H$65,"<="&Assumptions!$C$44) -> 43966.46 | D13: =SUMIFS(Receivables!$F$5:$F$65,Receivables!$H$5:$H$65,">="&Assumptions!$B$45,Receivables!$H$5:$H$65,"<="&Assumptions!$C$45) -> 273382.65 | F13: =SUMIFS(Receivables!$F$5:$F$65,Receivables!$H$5:$H$65,">="&Assumptions!$B$46,Receivables!$H$5:$H$65,"<="&Assumptions!$C$46)+Assumptions!$B$39/3 -> 159720.21 | H13: =SUMIFS(Receivables!$F$5:$F$65,Receivables!$H$5:$H$65,">="&Assumptions!$B$47,Receivables!$H$5:$H$65,"<="&Assumptions!$C$47)+Assumptions!$B$39/3 -> 36402.277 | J13: =SUMIFS(Receivables!$F$5:$F$65,Receivables!$H$5:$H$65,">="&Assumptions!$B$48,Receivables!$H$5:$H$65,"<="&Assumptions!$C$48)+Assumptions!$B$39/3 -> 197088.52 | L13: =SUM(B13,D13,F13,H13,J13) -> 710560.11 | M13: =SUM(C13,E13,G13,I13,K13) -> 0 | N13: =(C13-B13)*C$8+(E13-D13)*E$8+(G13-F13)*G$8+(I13-H13)*I$8+(K13-J13)*K$8 -> 0 | O13: Receivables tab. Week 1 is PwC, ICC and ASX on the due date (30 Oct) plus the Bankwest Oct contract. Week 2 is the CBA production kit ($118k) and the Deloitte Oct invoices. Week 5 is the ASX AGM, TLC and April 5.
A14: Other income - interest received | B14: =Assumptions!$B$40 -> 600 | D14: =0 -> 0 | F14: =0 -> 0 | H14: =0 -> 0 | J14: =Assumptions!$B$40 -> 600 | L14: =SUM(B14,D14,F14,H14,J14) -> 1200 | M14: =SUM(C14,E14,G14,I14,K14) -> 0 | N14: =(C14-B14)*C$8+(E14-D14)*E$8+(G14-F14)*G$8+(I14-H14)*I$8+(K14-J14)*K$8 -> 0 | O14: Savings interest at month end - 30 Oct and 30 Nov.
A15: TOTAL INCOME | B15: =B13+B14 -> 44566.46 | C15: =C13+C14 -> 0 | D15: =D13+D14 -> 273382.65 | E15: =E13+E14 -> 0 | F15: =F13+F14 -> 159720.21 | G15: =G13+G14 -> 0 | H15: =H13+H14 -> 36402.277 | I15: =I13+I14 -> 0 | ... N15: =N13+N14 -> 0
A17: OPERATING EXPENSES
A18: Employment
A19: Salaries & wages (net pay) | B19: =SUMIFS(Payroll!$E$5:$E$7,Payroll!$C$5:$C$7,">="&Assumptions!$B$44,Payroll!$C$5:$C$7,"<="&Assumptions!$C$44) -> 84710 | D19: =SUMIFS(Payroll!$E$5:$E$7,Payroll!$C$5:$C$7,">="&Assumptions!$B$45,Payroll!$C$5:$C$7,"<="&Assumptions!$C$45) -> 0 | F19: =SUMIFS(Payroll!$E$5:$E$7,Payroll!$C$5:$C$7,">="&Assumptions!$B$46,Payroll!$C$5:$C$7,"<="&Assumptions!$C$46) -> 84710 | H19: =SUMIFS(Payroll!$E$5:$E$7,Payroll!$C$5:$C$7,">="&Assumptions!$B$47,Payroll!$C$5:$C$7,"<="&Assumptions!$C$47) -> 0 | J19: =SUMIFS(Payroll!$E$5:$E$7,Payroll!$C$5:$C$7,">="&Assumptions!$B$48,Payroll!$C$5:$C$7,"<="&Assumptions!$C$48) -> 84710 | L19: =SUM(B19,D19,F19,H19,J19) -> 254130 | M19: =SUM(C19,E19,G19,I19,K19) -> 0 | N19: =(C19-B19)*C$8+(E19-D19)*E$8+(G19-F19)*G$8+(I19-H19)*I$8+(K19-J19)*K$8 -> 0 | O19: Payroll tab - gross x net %. Fortnight is Sat to Fri and the money goes out the Tuesday after: Tue 3 Nov (week 1), Tue 17 Nov (week 3) and Tue 1 Dec (week 5).
A20: Superannuation | B20: =SUMIFS(Payroll!$G$5:$G$7,Payroll!$C$5:$C$7,">="&Assumptions!$B$44,Payroll!$C$5:$C$7,"<="&Assumptions!$C$44) -> 12900 | D20: =SUMIFS(Payroll!$G$5:$G$7,Payroll!$C$5:$C$7,">="&Assumptions!$B$45,Payroll!$C$5:$C$7,"<="&Assumptions!$C$45) -> 0 | F20: =SUMIFS(Payroll!$G$5:$G$7,Payroll!$C$5:$C$7,">="&Assumptions!$B$46,Payroll!$C$5:$C$7,"<="&Assumptions!$C$46) -> 12900 | H20: =SUMIFS(Payroll!$G$5:$G$7,Payroll!$C$5:$C$7,">="&Assumptions!$B$47,Payroll!$C$5:$C$7,"<="&Assumptions!$C$47) -> 0 | J20: =SUMIFS(Payroll!$G$5:$G$7,Payroll!$C$5:$C$7,">="&Assumptions!$B$48,Payroll!$C$5:$C$7,"<="&Assumptions!$C$48) -> 12900 | L20: =SUM(B20,D20,F20,H20,J20) -> 38700 | M20: =SUM(C20,E20,G20,I20,K20) -> 0 | N20: =(C20-B20)*C$8+(E20-D20)*E$8+(G20-F20)*G$8+(I20-H20)*I$8+(K20-J20)*K$8 -> 0 | O20: Gross x 12%. Direct debits the day after pay day.
A21: PAYG withholding - monthly IAS | B21: =IF(AND(Assumptions!$B$51>=Assumptions!$B$44,Assumptions!$B$51<=Assumptions!$C$44),Assumptions!$B$50,0) -> 0 | D21: =IF(AND(Assumptions!$B$51>=Assumptions!$B$45,Assumptions!$B$51<=Assumptions!$C$45),Assumptions!$B$50,0) -> 0 | F21: =IF(AND(Assumptions!$B$51>=Assumptions!$B$46,Assumptions!$B$51<=Assumptions!$C$46),Assumptions!$B$50,0) -> 0 | H21: =IF(AND(Assumptions!$B$51>=Assumptions!$B$47,Assumptions!$B$51<=Assumptions!$C$47),Assumptions!$B$50,0) -> 45145.415 | J21: =IF(AND(Assumptions!$B$51>=Assumptions!$B$48,Assumptions!$B$51<=Assumptions!$C$48),Assumptions!$B$50,0) -> 0 | L21: =SUM(B21,D21,F21,H21,J21) -> 45145.415 | M21: =SUM(C21,E21,G21,I21,K21) -> 0 | N21: =(C21-B21)*C$8+(E21-D21)*E$8+(G21-F21)*G$8+(I21-H21)*I$8+(K21-J21)*K$8 -> 0 | O21: Oct PAYG on the monthly IAS, due 21 Nov - paid Fri 20 Nov (week 4). Assumptions B50.
A22: Payroll tax (NSW + other states) | B22: =IF(AND(Assumptions!$B$19>=Assumptions!$B$44,Assumptions!$B$19<=Assumptions!$C$44),Assumptions!$B$17+Assumptions!$B$18,0) -> 0 | D22: =IF(AND(Assumptions!$B$19>=Assumptions!$B$45,Assumptions!$B$19<=Assumptions!$C$45),Assumptions!$B$17+Assumptions!$B$18,0) -> 8602.75 | F22: =IF(AND(Assumptions!$B$19>=Assumptions!$B$46,Assumptions!$B$19<=Assumptions!$C$46),Assumptions!$B$17+Assumptions!$B$18,0) -> 0 | H22: =IF(AND(Assumptions!$B$19>=Assumptions!$B$47,Assumptions!$B$19<=Assumptions!$C$47),Assumptions!$B$17+Assumptions!$B$18,0) -> 0 | J22: =IF(AND(Assumptions!$B$19>=Assumptions!$B$48,Assumptions!$B$19<=Assumptions!$C$48),Assumptions!$B$17+Assumptions!$B$18,0) -> 0 | L22: =SUM(B22,D22,F22,H22,J22) -> 8602.75 | M22: =SUM(C22,E22,G22,I22,K22) -> 0 | N22: =(C22-B22)*C$8+(E22-D22)*E$8+(G22-F22)*G$8+(I22-H22)*I$8+(K22-J22)*K$8 -> 0 | O22: Oct wages, due 7 Nov - a Saturday, so Fri 6 Nov (week 2). Sep was $8,602.75 all up, same total used.
A23: Employee reimbursements (expense claims) | B23: =SUMIFS(Payroll!$H$5:$H$7,Payroll!$C$5:$C$7,">="&Assumptions!$B$44,Payroll!$C$5:$C$7,"<="&Assumptions!$C$44) -> 1000 | D23: =SUMIFS(Payroll!$H$5:$H$7,Payroll!$C$5:$C$7,">="&Assumptions!$B$45,Payroll!$C$5:$C$7,"<="&Assumptions!$C$45) -> 0 | F23: =SUMIFS(Payroll!$H$5:$H$7,Payroll!$C$5:$C$7,">="&Assumptions!$B$46,Payroll!$C$5:$C$7,"<="&Assumptions!$C$46) -> 1000 | H23: =SUMIFS(Payroll!$H$5:$H$7,Payroll!$C$5:$C$7,">="&Assumptions!$B$47,Payroll!$C$5:$C$7,"<="&Assumptions!$C$47) -> 0 | J23: =SUMIFS(Payroll!$H$5:$H$7,Payroll!$C$5:$C$7,">="&Assumptions!$B$48,Payroll!$C$5:$C$7,"<="&Assumptions!$C$48) -> 1000 | L23: =SUM(B23,D23,F23,H23,J23) -> 3000 | M23: =SUM(C23,E23,G23,I23,K23) -> 0 | N23: =(C23-B23)*C$8+(E23-D23)*E$8+(G23-F23)*G$8+(I23-H23)*I$8+(K23-J23)*K$8 -> 0 | O23: Placeholder - goes out with the ABA.
A24: Subtotal employment | B24: =B19+B20+B21+B22+B23 -> 98610 | C24: =C19+C20+C21+C22+C23 -> 0 | D24: =D19+D20+D21+D22+D23 -> 8602.75 | E24: =E19+E20+E21+E22+E23 -> 0 | F24: =F19+F20+F21+F22+F23 -> 98610 | G24: =G19+G20+G21+G22+G23 -> 0 | H24: =H19+H20+H21+H22+H23 -> 45145.415 | I24: =I19+I20+I21+I22+I23 -> 0 | ... N24: =N19+N20+N21+N22+N23 -> 0
A26: Cost of sales (client jobs)
A27: Project equipment & installation | B27: =SUMIFS(Payables!$D$19:$D$95,Payables!$K$19:$K$95,"Yes",Payables!$G$19:$G$95,">="&Assumptions!$B$44,Payables!$G$19:$G$95,"<="&Assumptions!$C$44,Payables!$E$19:$E$95,"<>Card",Payables!$F$19:$F$95,"Equipment purchases")+Assumptions!$B$29/5 -> 4000 | D27: =SUMIFS(Payables!$D$19:$D$95,Payables!$K$19:$K$95,"Yes",Payables!$G$19:$G$95,">="&Assumptions!$B$45,Payables!$G$19:$G$95,"<="&Assumptions!$C$45,Payables!$E$19:$E$95,"<>Card",Payables!$F$19:$F$95,"Equipment purchases")+Assumptions!$B$29/5 -> 4000 | F27: =SUMIFS(Payables!$D$19:$D$95,Payables!$K$19:$K$95,"Yes",Payables!$G$19:$G$95,">="&Assumptions!$B$46,Payables!$G$19:$G$95,"<="&Assumptions!$C$46,Payables!$E$19:$E$95,"<>Card",Payables!$F$19:$F$95,"Equipment purchases")+Assumptions!$B$29/5 -> 4000 | H27: =SUMIFS(Payables!$D$19:$D$95,Payables!$K$19:$K$95,"Yes",Payables!$G$19:$G$95,">="&Assumptions!$B$47,Payables!$G$19:$G$95,"<="&Assumptions!$C$47,Payables!$E$19:$E$95,"<>Card",Payables!$F$19:$F$95,"Equipment purchases")+Assumptions!$B$29/5 -> 4000 | J27: =SUMIFS(Payables!$D$19:$D$95,Payables!$K$19:$K$95,"Yes",Payables!$G$19:$G$95,">="&Assumptions!$B$48,Payables!$G$19:$G$95,"<="&Assumptions!$C$48,Payables!$E$19:$E$95,"<>Card",Payables!$F$19:$F$95,"Equipment purchases")+Assumptions!$B$29/5 -> 4000 | L27: =SUM(B27,D27,F27,H27,J27) -> 20000 | M27: =SUM(C27,E27,G27,I27,K27) -> 0 | N27: =(C27-B27)*C$8+(E27-D27)*E$8+(G27-F27)*G$8+(I27-H27)*I$8+(K27-J27)*K$8 -> 0 | O27: Contact Group Hobart fitout is in the creditors run. This line is just the unbilled estimate now.
A28: Sub-contract labour | B28: =Assumptions!$B$27/5 -> 8000 | D28: =Assumptions!$B$27/5 -> 8000 | F28: =Assumptions!$B$27/5 -> 8000 | H28: =Assumptions!$B$27/5 -> 8000 | J28: =Assumptions!$B$27/5 -> 8000 | L28: =SUM(B28,D28,F28,H28,J28) -> 40000 | M28: =SUM(C28,E28,G28,I28,K28) -> 0 | N28: =(C28-B28)*C$8+(E28-D28)*E$8+(G28-F28)*G$8+(I28-H28)*I$8+(K28-J28)*K$8 -> 0 | O28: Estimate (Sep was ~$39k, Oct ~$18k so far), spread evenly.
A29: Equipment & service hires | B29: =Assumptions!$B$28/5 -> 6000 | D29: =Assumptions!$B$28/5 -> 6000 | F29: =Assumptions!$B$28/5 -> 6000 | H29: =Assumptions!$B$28/5 -> 6000 | J29: =Assumptions!$B$28/5 -> 6000 | L29: =SUM(B29,D29,F29,H29,J29) -> 30000 | M29: =SUM(C29,E29,G29,I29,K29) -> 0 | N29: =(C29-B29)*C$8+(E29-D29)*E$8+(G29-F29)*G$8+(I29-H29)*I$8+(K29-J29)*K$8 -> 0 | O29: Estimate, spread evenly. The hire bills already in Xero (WordBirds, Riedel, 2020 Events, Start Webcast) are in the creditors run.
A30: Subscriptions & licences (client) | B30: =SUMIFS(Payables!$D$19:$D$95,Payables!$K$19:$K$95,"Yes",Payables!$G$19:$G$95,">="&Assumptions!$B$44,Payables!$G$19:$G$95,"<="&Assumptions!$C$44,Payables!$E$19:$E$95,"<>Card",Payables!$F$19:$F$95,"Client subscriptions")+Assumptions!$B$31/5 -> 600 | D30: =SUMIFS(Payables!$D$19:$D$95,Payables!$K$19:$K$95,"Yes",Payables!$G$19:$G$95,">="&Assumptions!$B$45,Payables!$G$19:$G$95,"<="&Assumptions!$C$45,Payables!$E$19:$E$95,"<>Card",Payables!$F$19:$F$95,"Client subscriptions")+Assumptions!$B$31/5 -> 600 | F30: =SUMIFS(Payables!$D$19:$D$95,Payables!$K$19:$K$95,"Yes",Payables!$G$19:$G$95,">="&Assumptions!$B$46,Payables!$G$19:$G$95,"<="&Assumptions!$C$46,Payables!$E$19:$E$95,"<>Card",Payables!$F$19:$F$95,"Client subscriptions")+Assumptions!$B$31/5 -> 2085 | H30: =SUMIFS(Payables!$D$19:$D$95,Payables!$K$19:$K$95,"Yes",Payables!$G$19:$G$95,">="&Assumptions!$B$47,Payables!$G$19:$G$95,"<="&Assumptions!$C$47,Payables!$E$19:$E$95,"<>Card",Payables!$F$19:$F$95,"Client subscriptions")+Assumptions!$B$31/5 -> 600 | J30: =SUMIFS(Payables!$D$19:$D$95,Payables!$K$19:$K$95,"Yes",Payables!$G$19:$G$95,">="&Assumptions!$B$48,Payables!$G$19:$G$95,"<="&Assumptions!$C$48,Payables!$E$19:$E$95,"<>Card",Payables!$F$19:$F$95,"Client subscriptions")+Assumptions!$B$31/5 -> 6328.8 | L30: =SUM(B30,D30,F30,H30,J30) -> 10213.8 | M30: =SUM(C30,E30,G30,I30,K30) -> 0 | N30: =(C30-B30)*C$8+(E30-D30)*E$8+(G30-F30)*G$8+(I30-H30)*I$8+(K30-J30)*K$8 -> 0 | O30: LiveU and Spacera Nov templates plus the unbilled estimate. Appspace and Spacera Oct are in the creditors run.
A31: Direct travel & freight | B31: =SUMIFS(Payables!$D$19:$D$95,Payables!$K$19:$K$95,"Yes",Payables!$G$19:$G$95,">="&Assumptions!$B$44,Payables!$G$19:$G$95,"<="&Assumptions!$C$44,Payables!$E$19:$E$95,"<>Card",Payables!$F$19:$F$95,"Direct travel & freight")+Assumptions!$B$30/5 -> 1400 | D31: =SUMIFS(Payables!$D$19:$D$95,Payables!$K$19:$K$95,"Yes",Payables!$G$19:$G$95,">="&Assumptions!$B$45,Payables!$G$19:$G$95,"<="&Assumptions!$C$45,Payables!$E$19:$E$95,"<>Card",Payables!$F$19:$F$95,"Direct travel & freight")+Assumptions!$B$30/5 -> 1400 | F31: =SUMIFS(Payables!$D$19:$D$95,Payables!$K$19:$K$95,"Yes",Payables!$G$19:$G$95,">="&Assumptions!$B$46,Payables!$G$19:$G$95,"<="&Assumptions!$C$46,Payables!$E$19:$E$95,"<>Card",Payables!$F$19:$F$95,"Direct travel & freight")+Assumptions!$B$30/5 -> 1400 | H31: =SUMIFS(Payables!$D$19:$D$95,Payables!$K$19:$K$95,"Yes",Payables!$G$19:$G$95,">="&Assumptions!$B$47,Payables!$G$19:$G$95,"<="&Assumptions!$C$47,Payables!$E$19:$E$95,"<>Card",Payables!$F$19:$F$95,"Direct travel & freight")+Assumptions!$B$30/5 -> 1400 | J31: =SUMIFS(Payables!$D$19:$D$95,Payables!$K$19:$K$95,"Yes",Payables!$G$19:$G$95,">="&Assumptions!$B$48,Payables!$G$19:$G$95,"<="&Assumptions!$C$48,Payables!$E$19:$E$95,"<>Card",Payables!$F$19:$F$95,"Direct travel & freight")+Assumptions!$B$30/5 -> 1400 | L31: =SUM(B31,D31,F31,H31,J31) -> 7000 | M31: =SUM(C31,E31,G31,I31,K31) -> 0 | N31: =(C31-B31)*C$8+(E31-D31)*E$8+(G31-F31)*G$8+(I31-H31)*I$8+(K31-J31)*K$8 -> 0 | O31: Estimate plus the Goget template (card).
A32: Subtotal cost of sales | B32: =B27+B28+B29+B30+B31 -> 20000 | C32: =C27+C28+C29+C30+C31 -> 0 | D32: =D27+D28+D29+D30+D31 -> 20000 | E32: =E27+E28+E29+E30+E31 -> 0 | F32: =F27+F28+F29+F30+F31 -> 21485 | G32: =G27+G28+G29+G30+G31 -> 0 | H32: =H27+H28+H29+H30+H31 -> 20000 | I32: =I27+I28+I29+I30+I31 -> 0 | ... N32: =N27+N28+N29+N30+N31 -> 0
A34: Overheads
A35: Rent & outgoings | B35: =SUMIFS(Payables!$D$19:$D$95,Payables!$K$19:$K$95,"Yes",Payables!$G$19:$G$95,">="&Assumptions!$B$44,Payables!$G$19:$G$95,"<="&Assumptions!$C$44,Payables!$E$19:$E$95,"<>Card",Payables!$F$19:$F$95,"Rent") -> 28895.72 | D35: =SUMIFS(Payables!$D$19:$D$95,Payables!$K$19:$K$95,"Yes",Payables!$G$19:$G$95,">="&Assumptions!$B$45,Payables!$G$19:$G$95,"<="&Assumptions!$C$45,Payables!$E$19:$E$95,"<>Card",Payables!$F$19:$F$95,"Rent") -> 0 | F35: =SUMIFS(Payables!$D$19:$D$95,Payables!$K$19:$K$95,"Yes",Payables!$G$19:$G$95,">="&Assumptions!$B$46,Payables!$G$19:$G$95,"<="&Assumptions!$C$46,Payables!$E$19:$E$95,"<>Card",Payables!$F$19:$F$95,"Rent") -> 0 | H35: =SUMIFS(Payables!$D$19:$D$95,Payables!$K$19:$K$95,"Yes",Payables!$G$19:$G$95,">="&Assumptions!$B$47,Payables!$G$19:$G$95,"<="&Assumptions!$C$47,Payables!$E$19:$E$95,"<>Card",Payables!$F$19:$F$95,"Rent") -> 0 | J35: =SUMIFS(Payables!$D$19:$D$95,Payables!$K$19:$K$95,"Yes",Payables!$G$19:$G$95,">="&Assumptions!$B$48,Payables!$G$19:$G$95,"<="&Assumptions!$C$48,Payables!$E$19:$E$95,"<>Card",Payables!$F$19:$F$95,"Rent") -> 28895.72 | L35: =SUM(B35,D35,F35,H35,J35) -> 57791.44 | M35: =SUM(C35,E35,G35,I35,K35) -> 0 | N35: =(C35-B35)*C$8+(E35-D35)*E$8+(G35-F35)*G$8+(I35-H35)*I$8+(K35-J35)*K$8 -> 0 | O35: Investa Nov rent ~$28,896 billed 1 Nov, paid with the 2 Nov run (week 1). Dec rent lands Tue 1 Dec (week 5) if they bill on the day again.
A36: IT network service & support | B36: =SUMIFS(Payables!$D$19:$D$95,Payables!$K$19:$K$95,"Yes",Payables!$G$19:$G$95,">="&Assumptions!$B$44,Payables!$G$19:$G$95,"<="&Assumptions!$C$44,Payables!$E$19:$E$95,"<>Card",Payables!$F$19:$F$95,"IT support") -> 0 | D36: =SUMIFS(Payables!$D$19:$D$95,Payables!$K$19:$K$95,"Yes",Payables!$G$19:$G$95,">="&Assumptions!$B$45,Payables!$G$19:$G$95,"<="&Assumptions!$C$45,Payables!$E$19:$E$95,"<>Card",Payables!$F$19:$F$95,"IT support") -> 0 | F36: =SUMIFS(Payables!$D$19:$D$95,Payables!$K$19:$K$95,"Yes",Payables!$G$19:$G$95,">="&Assumptions!$B$46,Payables!$G$19:$G$95,"<="&Assumptions!$C$46,Payables!$E$19:$E$95,"<>Card",Payables!$F$19:$F$95,"IT support") -> 14466.27 | H36: =SUMIFS(Payables!$D$19:$D$95,Payables!$K$19:$K$95,"Yes",Payables!$G$19:$G$95,">="&Assumptions!$B$47,Payables!$G$19:$G$95,"<="&Assumptions!$C$47,Payables!$E$19:$E$95,"<>Card",Payables!$F$19:$F$95,"IT support") -> 0 | J36: =SUMIFS(Payables!$D$19:$D$95,Payables!$K$19:$K$95,"Yes",Payables!$G$19:$G$95,">="&Assumptions!$B$48,Payables!$G$19:$G$95,"<="&Assumptions!$C$48,Payables!$E$19:$E$95,"<>Card",Payables!$F$19:$F$95,"IT support") -> 0 | L36: =SUM(B36,D36,F36,H36,J36) -> 14466.27 | M36: =SUM(C36,E36,G36,I36,K36) -> 0 | N36: =(C36-B36)*C$8+(E36-D36)*E$8+(G36-F36)*G$8+(I36-H36)*I$8+(K36-J36)*K$8 -> 0 | O36: First Focus CORE + Azure, DD 16 Nov (week 3).
A37: Advertising & marketing | B37: =SUMIFS(Payables!$D$19:$D$95,Payables!$K$19:$K$95,"Yes",Payables!$G$19:$G$95,">="&Assumptions!$B$44,Payables!$G$19:$G$95,"<="&Assumptions!$C$44,Payables!$E$19:$E$95,"<>Card",Payables!$F$19:$F$95,"Advertising") -> 0 | D37: =SUMIFS(Payables!$D$19:$D$95,Payables!$K$19:$K$95,"Yes",Payables!$G$19:$G$95,">="&Assumptions!$B$45,Payables!$G$19:$G$95,"<="&Assumptions!$C$45,Payables!$E$19:$E$95,"<>Card",Payables!$F$19:$F$95,"Advertising") -> 0 | F37: =SUMIFS(Payables!$D$19:$D$95,Payables!$K$19:$K$95,"Yes",Payables!$G$19:$G$95,">="&Assumptions!$B$46,Payables!$G$19:$G$95,"<="&Assumptions!$C$46,Payables!$E$19:$E$95,"<>Card",Payables!$F$19:$F$95,"Advertising") -> 0 | H37: =SUMIFS(Payables!$D$19:$D$95,Payables!$K$19:$K$95,"Yes",Payables!$G$19:$G$95,">="&Assumptions!$B$47,Payables!$G$19:$G$95,"<="&Assumptions!$C$47,Payables!$E$19:$E$95,"<>Card",Payables!$F$19:$F$95,"Advertising") -> 4675 | J37: =SUMIFS(Payables!$D$19:$D$95,Payables!$K$19:$K$95,"Yes",Payables!$G$19:$G$95,">="&Assumptions!$B$48,Payables!$G$19:$G$95,"<="&Assumptions!$C$48,Payables!$E$19:$E$95,"<>Card",Payables!$F$19:$F$95,"Advertising") -> 0 | L37: =SUM(B37,D37,F37,H37,J37) -> 4675 | M37: =SUM(C37,E37,G37,I37,K37) -> 0 | N37: =(C37-B37)*C$8+(E37-D37)*E$8+(G37-F37)*G$8+(I37-H37)*I$8+(K37-J37)*K$8 -> 0 | O37: RJW digital marketing Nov $4,675, due 21 Nov.
A38: Accounting, legal & advisory | B38: =SUMIFS(Payables!$D$19:$D$95,Payables!$K$19:$K$95,"Yes",Payables!$G$19:$G$95,">="&Assumptions!$B$44,Payables!$G$19:$G$95,"<="&Assumptions!$C$44,Payables!$E$19:$E$95,"<>Card",Payables!$F$19:$F$95,"Professional fees")+Assumptions!$B$33/5 -> 4650 | D38: =SUMIFS(Payables!$D$19:$D$95,Payables!$K$19:$K$95,"Yes",Payables!$G$19:$G$95,">="&Assumptions!$B$45,Payables!$G$19:$G$95,"<="&Assumptions!$C$45,Payables!$E$19:$E$95,"<>Card",Payables!$F$19:$F$95,"Professional fees")+Assumptions!$B$33/5 -> 1680 | F38: =SUMIFS(Payables!$D$19:$D$95,Payables!$K$19:$K$95,"Yes",Payables!$G$19:$G$95,">="&Assumptions!$B$46,Payables!$G$19:$G$95,"<="&Assumptions!$C$46,Payables!$E$19:$E$95,"<>Card",Payables!$F$19:$F$95,"Professional fees")+Assumptions!$B$33/5 -> 800 | H38: =SUMIFS(Payables!$D$19:$D$95,Payables!$K$19:$K$95,"Yes",Payables!$G$19:$G$95,">="&Assumptions!$B$47,Payables!$G$19:$G$95,"<="&Assumptions!$C$47,Payables!$E$19:$E$95,"<>Card",Payables!$F$19:$F$95,"Professional fees")+Assumptions!$B$33/5 -> 800 | J38: =SUMIFS(Payables!$D$19:$D$95,Payables!$K$19:$K$95,"Yes",Payables!$G$19:$G$95,">="&Assumptions!$B$48,Payables!$G$19:$G$95,"<="&Assumptions!$C$48,Payables!$E$19:$E$95,"<>Card",Payables!$F$19:$F$95,"Professional fees")+Assumptions!$B$33/5 -> 800 | L38: =SUM(B38,D38,F38,H38,J38) -> 8730 | M38: =SUM(C38,E38,G38,I38,K38) -> 0 | N38: =(C38-B38)*C$8+(E38-D38)*E$8+(G38-F38)*G$8+(I38-H38)*I$8+(K38-J38)*K$8 -> 0 | O38: 8020 Advisors $3,850 and Employsure $880 templates, plus the estimate. Easton Belle legal is in the creditors run.
A39: Dues & subscriptions | B39: =SUMIFS(Payables!$D$19:$D$95,Payables!$K$19:$K$95,"Yes",Payables!$G$19:$G$95,">="&Assumptions!$B$44,Payables!$G$19:$G$95,"<="&Assumptions!$C$44,Payables!$E$19:$E$95,"<>Card",Payables!$F$19:$F$95,"Dues & subscriptions") -> 0 | D39: =SUMIFS(Payables!$D$19:$D$95,Payables!$K$19:$K$95,"Yes",Payables!$G$19:$G$95,">="&Assumptions!$B$45,Payables!$G$19:$G$95,"<="&Assumptions!$C$45,Payables!$E$19:$E$95,"<>Card",Payables!$F$19:$F$95,"Dues & subscriptions") -> 0 | F39: =SUMIFS(Payables!$D$19:$D$95,Payables!$K$19:$K$95,"Yes",Payables!$G$19:$G$95,">="&Assumptions!$B$46,Payables!$G$19:$G$95,"<="&Assumptions!$C$46,Payables!$E$19:$E$95,"<>Card",Payables!$F$19:$F$95,"Dues & subscriptions") -> 0 | H39: =SUMIFS(Payables!$D$19:$D$95,Payables!$K$19:$K$95,"Yes",Payables!$G$19:$G$95,">="&Assumptions!$B$47,Payables!$G$19:$G$95,"<="&Assumptions!$C$47,Payables!$E$19:$E$95,"<>Card",Payables!$F$19:$F$95,"Dues & subscriptions") -> 0 | J39: =SUMIFS(Payables!$D$19:$D$95,Payables!$K$19:$K$95,"Yes",Payables!$G$19:$G$95,">="&Assumptions!$B$48,Payables!$G$19:$G$95,"<="&Assumptions!$C$48,Payables!$E$19:$E$95,"<>Card",Payables!$F$19:$F$95,"Dues & subscriptions") -> 0 | L39: =SUM(B39,D39,F39,H39,J39) -> 0 | M39: =SUM(C39,E39,G39,I39,K39) -> 0 | N39: =(C39-B39)*C$8+(E39-D39)*E$8+(G39-F39)*G$8+(I39-H39)*I$8+(K39-J39)*K$8 -> 0 | O39: Card subscriptions sit in the card line. CEO Institute and AVIXA fall after 2 Dec.
A40: Telephone & internet | B40: =SUMIFS(Payables!$D$19:$D$95,Payables!$K$19:$K$95,"Yes",Payables!$G$19:$G$95,">="&Assumptions!$B$44,Payables!$G$19:$G$95,"<="&Assumptions!$C$44,Payables!$E$19:$E$95,"<>Card",Payables!$F$19:$F$95,"Telephone & internet") -> 0 | D40: =SUMIFS(Payables!$D$19:$D$95,Payables!$K$19:$K$95,"Yes",Payables!$G$19:$G$95,">="&Assumptions!$B$45,Payables!$G$19:$G$95,"<="&Assumptions!$C$45,Payables!$E$19:$E$95,"<>Card",Payables!$F$19:$F$95,"Telephone & internet") -> 0 | F40: =SUMIFS(Payables!$D$19:$D$95,Payables!$K$19:$K$95,"Yes",Payables!$G$19:$G$95,">="&Assumptions!$B$46,Payables!$G$19:$G$95,"<="&Assumptions!$C$46,Payables!$E$19:$E$95,"<>Card",Payables!$F$19:$F$95,"Telephone & internet") -> 0 | H40: =SUMIFS(Payables!$D$19:$D$95,Payables!$K$19:$K$95,"Yes",Payables!$G$19:$G$95,">="&Assumptions!$B$47,Payables!$G$19:$G$95,"<="&Assumptions!$C$47,Payables!$E$19:$E$95,"<>Card",Payables!$F$19:$F$95,"Telephone & internet") -> 231.2 | J40: =SUMIFS(Payables!$D$19:$D$95,Payables!$K$19:$K$95,"Yes",Payables!$G$19:$G$95,">="&Assumptions!$B$48,Payables!$G$19:$G$95,"<="&Assumptions!$C$48,Payables!$E$19:$E$95,"<>Card",Payables!$F$19:$F$95,"Telephone & internet") -> 0 | L40: =SUM(B40,D40,F40,H40,J40) -> 231.2 | M40: =SUM(C40,E40,G40,I40,K40) -> 0 | N40: =(C40-B40)*C$8+(E40-D40)*E$8+(G40-F40)*G$8+(I40-H40)*I$8+(K40-J40)*K$8 -> 0 | O40: Optus Lugstein BPAY, Telstra Nighthawk Nov. Optus mobiles Oct is in the creditors run, Nov falls after 2 Dec.
A41: Recruitment | B41: =SUMIFS(Payables!$D$19:$D$95,Payables!$K$19:$K$95,"Yes",Payables!$G$19:$G$95,">="&Assumptions!$B$44,Payables!$G$19:$G$95,"<="&Assumptions!$C$44,Payables!$E$19:$E$95,"<>Card",Payables!$F$19:$F$95,"Recruitment")+Assumptions!$B$32/5 -> 1000 | D41: =SUMIFS(Payables!$D$19:$D$95,Payables!$K$19:$K$95,"Yes",Payables!$G$19:$G$95,">="&Assumptions!$B$45,Payables!$G$19:$G$95,"<="&Assumptions!$C$45,Payables!$E$19:$E$95,"<>Card",Payables!$F$19:$F$95,"Recruitment")+Assumptions!$B$32/5 -> 1000 | F41: =SUMIFS(Payables!$D$19:$D$95,Payables!$K$19:$K$95,"Yes",Payables!$G$19:$G$95,">="&Assumptions!$B$46,Payables!$G$19:$G$95,"<="&Assumptions!$C$46,Payables!$E$19:$E$95,"<>Card",Payables!$F$19:$F$95,"Recruitment")+Assumptions!$B$32/5 -> 1000 | H41: =SUMIFS(Payables!$D$19:$D$95,Payables!$K$19:$K$95,"Yes",Payables!$G$19:$G$95,">="&Assumptions!$B$47,Payables!$G$19:$G$95,"<="&Assumptions!$C$47,Payables!$E$19:$E$95,"<>Card",Payables!$F$19:$F$95,"Recruitment")+Assumptions!$B$32/5 -> 1000 | J41: =SUMIFS(Payables!$D$19:$D$95,Payables!$K$19:$K$95,"Yes",Payables!$G$19:$G$95,">="&Assumptions!$B$48,Payables!$G$19:$G$95,"<="&Assumptions!$C$48,Payables!$E$19:$E$95,"<>Card",Payables!$F$19:$F$95,"Recruitment")+Assumptions!$B$32/5 -> 1000 | L41: =SUM(B41,D41,F41,H41,J41) -> 5000 | M41: =SUM(C41,E41,G41,I41,K41) -> 0 | N41: =(C41-B41)*C$8+(E41-D41)*E$8+(G41-F41)*G$8+(I41-H41)*I$8+(K41-J41)*K$8 -> 0 | O41: Estimate. Seek ads go on the card.
A42: Insurance | B42: =SUMIFS(Payables!$D$19:$D$95,Payables!$K$19:$K$95,"Yes",Payables!$G$19:$G$95,">="&Assumptions!$B$44,Payables!$G$19:$G$95,"<="&Assumptions!$C$44,Payables!$E$19:$E$95,"<>Card",Payables!$F$19:$F$95,"Insurance")+Assumptions!$B$34/5 -> 0 | D42: =SUMIFS(Payables!$D$19:$D$95,Payables!$K$19:$K$95,"Yes",Payables!$G$19:$G$95,">="&Assumptions!$B$45,Payables!$G$19:$G$95,"<="&Assumptions!$C$45,Payables!$E$19:$E$95,"<>Card",Payables!$F$19:$F$95,"Insurance")+Assumptions!$B$34/5 -> 0 | F42: =SUMIFS(Payables!$D$19:$D$95,Payables!$K$19:$K$95,"Yes",Payables!$G$19:$G$95,">="&Assumptions!$B$46,Payables!$G$19:$G$95,"<="&Assumptions!$C$46,Payables!$E$19:$E$95,"<>Card",Payables!$F$19:$F$95,"Insurance")+Assumptions!$B$34/5 -> 0 | H42: =SUMIFS(Payables!$D$19:$D$95,Payables!$K$19:$K$95,"Yes",Payables!$G$19:$G$95,">="&Assumptions!$B$47,Payables!$G$19:$G$95,"<="&Assumptions!$C$47,Payables!$E$19:$E$95,"<>Card",Payables!$F$19:$F$95,"Insurance")+Assumptions!$B$34/5 -> 0 | J42: =SUMIFS(Payables!$D$19:$D$95,Payables!$K$19:$K$95,"Yes",Payables!$G$19:$G$95,">="&Assumptions!$B$48,Payables!$G$19:$G$95,"<="&Assumptions!$C$48,Payables!$E$19:$E$95,"<>Card",Payables!$F$19:$F$95,"Insurance")+Assumptions!$B$34/5 -> 0 | L42: =SUM(B42,D42,F42,H42,J42) -> 0 | M42: =SUM(C42,E42,G42,I42,K42) -> 0 | N42: =(C42-B42)*C$8+(E42-D42)*E$8+(G42-F42)*G$8+(I42-H42)*I$8+(K42-J42)*K$8 -> 0 | O42: Brookvale $66,239 is in the creditors run (2 Nov). Nothing else expected - estimate is nil.
A43: Office, printing & amenities | B43: =SUMIFS(Payables!$D$19:$D$95,Payables!$K$19:$K$95,"Yes",Payables!$G$19:$G$95,">="&Assumptions!$B$44,Payables!$G$19:$G$95,"<="&Assumptions!$C$44,Payables!$E$19:$E$95,"<>Card",Payables!$F$19:$F$95,"Office")+Assumptions!$B$35/5 -> 400 | D43: =SUMIFS(Payables!$D$19:$D$95,Payables!$K$19:$K$95,"Yes",Payables!$G$19:$G$95,">="&Assumptions!$B$45,Payables!$G$19:$G$95,"<="&Assumptions!$C$45,Payables!$E$19:$E$95,"<>Card",Payables!$F$19:$F$95,"Office")+Assumptions!$B$35/5 -> 400 | F43: =SUMIFS(Payables!$D$19:$D$95,Payables!$K$19:$K$95,"Yes",Payables!$G$19:$G$95,">="&Assumptions!$B$46,Payables!$G$19:$G$95,"<="&Assumptions!$C$46,Payables!$E$19:$E$95,"<>Card",Payables!$F$19:$F$95,"Office")+Assumptions!$B$35/5 -> 400 | H43: =SUMIFS(Payables!$D$19:$D$95,Payables!$K$19:$K$95,"Yes",Payables!$G$19:$G$95,">="&Assumptions!$B$47,Payables!$G$19:$G$95,"<="&Assumptions!$C$47,Payables!$E$19:$E$95,"<>Card",Payables!$F$19:$F$95,"Office")+Assumptions!$B$35/5 -> 400 | J43: =SUMIFS(Payables!$D$19:$D$95,Payables!$K$19:$K$95,"Yes",Payables!$G$19:$G$95,">="&Assumptions!$B$48,Payables!$G$19:$G$95,"<="&Assumptions!$C$48,Payables!$E$19:$E$95,"<>Card",Payables!$F$19:$F$95,"Office")+Assumptions!$B$35/5 -> 400 | L43: =SUM(B43,D43,F43,H43,J43) -> 2000 | M43: =SUM(C43,E43,G43,I43,K43) -> 0 | N43: =(C43-B43)*C$8+(E43-D43)*E$8+(G43-F43)*G$8+(I43-H43)*I$8+(K43-J43)*K$8 -> 0 | O43: Ricoh DD and Posh are in the creditors run, plus the estimate.
A44: Electricity | B44: =SUMIFS(Payables!$D$19:$D$95,Payables!$K$19:$K$95,"Yes",Payables!$G$19:$G$95,">="&Assumptions!$B$44,Payables!$G$19:$G$95,"<="&Assumptions!$C$44,Payables!$E$19:$E$95,"<>Card",Payables!$F$19:$F$95,"Electricity") -> 0 | D44: =SUMIFS(Payables!$D$19:$D$95,Payables!$K$19:$K$95,"Yes",Payables!$G$19:$G$95,">="&Assumptions!$B$45,Payables!$G$19:$G$95,"<="&Assumptions!$C$45,Payables!$E$19:$E$95,"<>Card",Payables!$F$19:$F$95,"Electricity") -> 0 | F44: =SUMIFS(Payables!$D$19:$D$95,Payables!$K$19:$K$95,"Yes",Payables!$G$19:$G$95,">="&Assumptions!$B$46,Payables!$G$19:$G$95,"<="&Assumptions!$C$46,Payables!$E$19:$E$95,"<>Card",Payables!$F$19:$F$95,"Electricity") -> 0 | H44: =SUMIFS(Payables!$D$19:$D$95,Payables!$K$19:$K$95,"Yes",Payables!$G$19:$G$95,">="&Assumptions!$B$47,Payables!$G$19:$G$95,"<="&Assumptions!$C$47,Payables!$E$19:$E$95,"<>Card",Payables!$F$19:$F$95,"Electricity") -> 0 | J44: =SUMIFS(Payables!$D$19:$D$95,Payables!$K$19:$K$95,"Yes",Payables!$G$19:$G$95,">="&Assumptions!$B$48,Payables!$G$19:$G$95,"<="&Assumptions!$C$48,Payables!$E$19:$E$95,"<>Card",Payables!$F$19:$F$95,"Electricity") -> 0 | L44: =SUM(B44,D44,F44,H44,J44) -> 0 | M44: =SUM(C44,E44,G44,I44,K44) -> 0 | N44: =(C44-B44)*C$8+(E44-D44)*E$8+(G44-F44)*G$8+(I44-H44)*I$8+(K44-J44)*K$8 -> 0 | O44: Energy Australia DDs the PL card so it shows in the credit card line, not here.
A45: Bank & merchant fees | B45: =Assumptions!$B$36/5 -> 200 | D45: =Assumptions!$B$36/5 -> 200 | F45: =Assumptions!$B$36/5 -> 200 | H45: =Assumptions!$B$36/5 -> 200 | J45: =Assumptions!$B$36/5 -> 200 | L45: =SUM(B45,D45,F45,H45,J45) -> 1000 | M45: =SUM(C45,E45,G45,I45,K45) -> 0 | N45: =(C45-B45)*C$8+(E45-D45)*E$8+(G45-F45)*G$8+(I45-H45)*I$8+(K45-J45)*K$8 -> 0 | O45: Estimate - bank charges and Stripe.
A46: Credit card settlements (card spend, all categories) | B46: =Assumptions!$B$37/5 -> 5000 | D46: =Assumptions!$B$37/5 -> 5000 | F46: =Assumptions!$B$37/5 -> 5000 | H46: =Assumptions!$B$37/5 -> 5000 | J46: =Assumptions!$B$37/5 -> 5000 | L46: =SUM(B46,D46,F46,H46,J46) -> 25000 | M46: =SUM(C46,E46,G46,I46,K46) -> 0 | N46: =(C46-B46)*C$8+(E46-D46)*E$8+(G46-F46)*G$8+(I46-H46)*I$8+(K46-J46)*K$8 -> 0 | O46: ~$25k a month transferred to the PL and DL cards. Covers every Card row on the Payables tab.
A47: Other expenses | B47: =SUMIFS(Payables!$D$19:$D$95,Payables!$K$19:$K$95,"Yes",Payables!$G$19:$G$95,">="&Assumptions!$B$44,Payables!$G$19:$G$95,"<="&Assumptions!$C$44,Payables!$E$19:$E$95,"<>Card",Payables!$F$19:$F$95,"Other") -> 0 | D47: =SUMIFS(Payables!$D$19:$D$95,Payables!$K$19:$K$95,"Yes",Payables!$G$19:$G$95,">="&Assumptions!$B$45,Payables!$G$19:$G$95,"<="&Assumptions!$C$45,Payables!$E$19:$E$95,"<>Card",Payables!$F$19:$F$95,"Other") -> 0 | F47: =SUMIFS(Payables!$D$19:$D$95,Payables!$K$19:$K$95,"Yes",Payables!$G$19:$G$95,">="&Assumptions!$B$46,Payables!$G$19:$G$95,"<="&Assumptions!$C$46,Payables!$E$19:$E$95,"<>Card",Payables!$F$19:$F$95,"Other") -> 0 | H47: =SUMIFS(Payables!$D$19:$D$95,Payables!$K$19:$K$95,"Yes",Payables!$G$19:$G$95,">="&Assumptions!$B$47,Payables!$G$19:$G$95,"<="&Assumptions!$C$47,Payables!$E$19:$E$95,"<>Card",Payables!$F$19:$F$95,"Other") -> 0 | J47: =SUMIFS(Payables!$D$19:$D$95,Payables!$K$19:$K$95,"Yes",Payables!$G$19:$G$95,">="&Assumptions!$B$48,Payables!$G$19:$G$95,"<="&Assumptions!$C$48,Payables!$E$19:$E$95,"<>Card",Payables!$F$19:$F$95,"Other") -> 0 | L47: =SUM(B47,D47,F47,H47,J47) -> 0 | M47: =SUM(C47,E47,G47,I47,K47) -> 0 | N47: =(C47-B47)*C$8+(E47-D47)*E$8+(G47-F47)*G$8+(I47-H47)*I$8+(K47-J47)*K$8 -> 0 | O47: Nothing listed.
A48: Creditors run (Xero aged payables paste - run Mon 2 Nov) | B48: =IF('Creditors Run'!$B$5=1,SUMPRODUCT(('Creditors Run'!$A$11:$A$510<>"")*ISNUMBER('Creditors Run'!$I$11:$I$510)*('Creditors Run'!$M$11:$M$510="")*('Creditors Run'!$N$11:$N$510>=Assumptions!$B$44)*('Creditors Run'!$N$11:$N$510<=Assumptions!$C$44),'Creditors Run'!$I$11:$I$510),0) -> 127591.89 | D48: =IF('Creditors Run'!$B$5=1,SUMPRODUCT(('Creditors Run'!$A$11:$A$510<>"")*ISNUMBER('Creditors Run'!$I$11:$I$510)*('Creditors Run'!$M$11:$M$510="")*('Creditors Run'!$N$11:$N$510>=Assumptions!$B$45)*('Creditors Run'!$N$11:$N$510<=Assumptions!$C$45),'Creditors Run'!$I$11:$I$510),0) -> 17753.73 | F48: =IF('Creditors Run'!$B$5=1,SUMPRODUCT(('Creditors Run'!$A$11:$A$510<>"")*ISNUMBER('Creditors Run'!$I$11:$I$510)*('Creditors Run'!$M$11:$M$510="")*('Creditors Run'!$N$11:$N$510>=Assumptions!$B$46)*('Creditors Run'!$N$11:$N$510<=Assumptions!$C$46),'Creditors Run'!$I$11:$I$510),0) -> 2920.06 | H48: =IF('Creditors Run'!$B$5=1,SUMPRODUCT(('Creditors Run'!$A$11:$A$510<>"")*ISNUMBER('Creditors Run'!$I$11:$I$510)*('Creditors Run'!$M$11:$M$510="")*('Creditors Run'!$N$11:$N$510>=Assumptions!$B$47)*('Creditors Run'!$N$11:$N$510<=Assumptions!$C$47),'Creditors Run'!$I$11:$I$510),0) -> 1829.52 | J48: =IF('Creditors Run'!$B$5=1,SUMPRODUCT(('Creditors Run'!$A$11:$A$510<>"")*ISNUMBER('Creditors Run'!$I$11:$I$510)*('Creditors Run'!$M$11:$M$510="")*('Creditors Run'!$N$11:$N$510>=Assumptions!$B$48)*('Creditors Run'!$N$11:$N$510<=Assumptions!$C$48),'Creditors Run'!$I$11:$I$510),0) -> 4157.58 | L48: =SUM(B48,D48,F48,H48,J48) -> 154252.78 | M48: =SUM(C48,E48,G48,I48,K48) -> 0 | N48: =(C48-B48)*C$8+(E48-D48)*E$8+(G48-F48)*G$8+(I48-H48)*I$8+(K48-J48)*K$8 -> 0 | O48: Creditors Run tab - the 46 open bills at 29 Oct ($158k). Everything due by 2 Nov goes in the Mon 2 Nov run ($131k incl. Brookvale $66k and Appspace $19k). The rest lands on its due date. Start Webcast $12.8k is in the run but DL / TW still need to approve it.
A49: Subtotal overheads | B49: =B35+B36+B37+B38+B39+B40+B41+B42+B43+B44+B45+B46+B47+B48 -> 167737.61 | C49: =C35+C36+C37+C38+C39+C40+C41+C42+C43+C44+C45+C46+C47+C48 -> 0 | D49: =D35+D36+D37+D38+D39+D40+D41+D42+D43+D44+D45+D46+D47+D48 -> 26033.73 | E49: =E35+E36+E37+E38+E39+E40+E41+E42+E43+E44+E45+E46+E47+E48 -> 0 | F49: =F35+F36+F37+F38+F39+F40+F41+F42+F43+F44+F45+F46+F47+F48 -> 24786.33 | G49: =G35+G36+G37+G38+G39+G40+G41+G42+G43+G44+G45+G46+G47+G48 -> 0 | H49: =H35+H36+H37+H38+H39+H40+H41+H42+H43+H44+H45+H46+H47+H48 -> 14135.72 | I49: =I35+I36+I37+I38+I39+I40+I41+I42+I43+I44+I45+I46+I47+I48 -> 0 | ... N49: =N35+N36+N37+N38+N39+N40+N41+N42+N43+N44+N45+N46+N47+N48 -> 0
A51: Tax
A52: BAS - GST, PAYG withholding & instalment (Q1) | B52: =IF(AND(Assumptions!$B$25>=Assumptions!$B$44,Assumptions!$B$25<=Assumptions!$C$44),Assumptions!$B$21*(Assumptions!$B$22+Assumptions!$B$23+Assumptions!$B$24),0) -> 0 | D52: =IF(AND(Assumptions!$B$25>=Assumptions!$B$45,Assumptions!$B$25<=Assumptions!$C$45),Assumptions!$B$21*(Assumptions!$B$22+Assumptions!$B$23+Assumptions!$B$24),0) -> 0 | F52: =IF(AND(Assumptions!$B$25>=Assumptions!$B$46,Assumptions!$B$25<=Assumptions!$C$46),Assumptions!$B$21*(Assumptions!$B$22+Assumptions!$B$23+Assumptions!$B$24),0) -> 0 | H52: =IF(AND(Assumptions!$B$25>=Assumptions!$B$47,Assumptions!$B$25<=Assumptions!$C$47),Assumptions!$B$21*(Assumptions!$B$22+Assumptions!$B$23+Assumptions!$B$24),0) -> 96017.144 | J52: =IF(AND(Assumptions!$B$25>=Assumptions!$B$48,Assumptions!$B$25<=Assumptions!$C$48),Assumptions!$B$21*(Assumptions!$B$22+Assumptions!$B$23+Assumptions!$B$24),0) -> 0 | L52: =SUM(B52,D52,F52,H52,J52) -> 96017.144 | M52: =SUM(C52,E52,G52,I52,K52) -> 0 | N52: =(C52-B52)*C$8+(E52-D52)*E$8+(G52-F52)*G$8+(I52-H52)*I$8+(K52-J52)*K$8 -> 0 | O52: ="Q1 BAS est. "&TEXT(Assumptions!$B$22+Assumptions!$B$23+Assumptions!$B$24,"$#,##0")&" (Sep PAYG + GST estimate). Did not go 28 Oct, so assumed 25 Nov through the agent (week 4). Swap the GST estimate for the activity statement figure." -> Q1 BAS est. $96,017 (Sep PAYG + GST estimate). Did not go 28 Oct, so assumed 25 Nov through the agent (week 4). Swap the GST estimate for the activity statement figure.
A53: Subtotal tax | B53: =B52 -> 0 | C53: =C52 -> 0 | D53: =D52 -> 0 | E53: =E52 -> 0 | F53: =F52 -> 0 | G53: =G52 -> 0 | H53: =H52 -> 96017.144 | I53: =I52 -> 0 | ... N53: =N52 -> 0
A55: TOTAL OPERATING EXPENSES | B55: =B24+B32+B49+B53 -> 286347.61 | C55: =C24+C32+C49+C53 -> 0 | D55: =D24+D32+D49+D53 -> 54636.48 | E55: =E24+E32+E49+E53 -> 0 | F55: =F24+F32+F49+F66 -> 144881.33 | G55: =G24+G32+G49+G53 -> 0 | H55: =H24+H32+H49+H53 -> 175298.28 | I55: =I24+I32+I49+I53 -> 0 | J55: =J24+J32+J49+J53 -> 164792.1 | K55: =K24+K32+K49+K53 -> 0 | L55: =L24+L32+L49+L53 -> 825955.8 | M55: =M24+M32+M49+M53 -> 0 | N55: =N24+N32+N49+N53 -> 0
A57: NET CASH FLOW | B57: =B15-B55 -> -241781.15 | C57: =C15-C55 -> 0 | D57: =D15-D55 -> 218746.17 | E57: =E15-E55 -> 0 | F57: =F15-F68 -> 159720.21 | G57: =G15-G55 -> 0 | H57: =H15-H55 -> -138896 | I57: =I15-I55 -> 0 | J57: =J15-J55 -> 32896.417 | K57: =K15-K55 -> 0 | L57: =L15-L55 -> -114195.69 | M57: =M15-M55 -> 0 | N57: =N15-N55 -> 0
A58: CLOSING BANK BALANCE | B58: =B10+B57 -> 198149.53 | C58: =C10+C57 -> 439930.68 | D58: =D10+D57 -> 416895.7 | E58: =IF(E$8=1,E10+E57,"") | F58: =F10+F57 -> 576615.91 | G58: =IF(G$8=1,G10+G57,"") | H58: =H10+H57 -> 437719.9 | I58: =IF(I$8=1,I10+I57,"") | J58: =J10+J57 -> 470616.32 | K58: =IF(K$8=1,K10+K57,"") | L58: =J58 -> 470616.32 | M58: =IF(K$8=1,K58,IF(I$8=1,I58,IF(G$8=1,G58,IF(E$8=1,E58,IF(C$8=1,C58,""))))) | O58: Opening + net. The Actual column fills in once the week's flag is 1, and the total column shows the latest completed week.
A59: Actual bank balance per CommBiz (enter) | O59: Type the real closing balance (cheque + savings) in at the end of each week. The opening balance on the Assumptions tab is an estimate off Xero - replace it with the 28 Oct CommBiz figure first.
A60: Unexplained difference (actual closing less bank) | C60: =C58-C59 -> 439930.68 | E60: =IF(E$8=1,E58-E59,"") | G60: =IF(G$8=1,G58-G59,"") | I60: =IF(I$8=1,I58-I59,"") | K60: =IF(K$8=1,K58-K59,"") | O60: Should be nil once everything's in. This is a sense check.
A62: MEMO
A63: Cash needed in the cheque account on pay day (net + super + reimb.) | B63: =B19+B20+B23 -> 98610 | D63: =D19+D20+D23 -> 0 | F63: =F19+F20+F23 -> 98610 | H63: =H19+H20+H23 -> 0 | J63: =J19+J20+J23 -> 98610
A64: Closing balance as weeks of payroll cover | B64: =IF(Payroll!$I$5=0,0,B58/(Payroll!$I$5/2)) -> 4.0188527 | D64: =IF(Payroll!$I$5=0,0,D58/(Payroll!$I$5/2)) -> 8.4554447 | F64: =IF(Payroll!$I$5=0,0,F58/(Payroll!$I$5/2)) -> 11.694877 | H64: =IF(Payroll!$I$5=0,0,H58/(Payroll!$I$5/2)) -> 8.8777995 | J64: =IF(Payroll!$I$5=0,0,J58/(Payroll!$I$5/2)) -> 9.545002
A65: Receipts expected after 2 Dec (not in this forecast) | L65: =SUMIFS(Receivables!$F$5:$F$65,Receivables!$H$5:$H$65,">"&Assumptions!$C$48) -> 5141.71 | O65: Nov contract invoices (raised 30 Nov, paid Dec), Meet Magic, Jaaz.
A66: Payments held past 2 Dec (not in this forecast) | L66: =SUMIFS(Payables!$D$19:$D$95,Payables!$K$19:$K$95,"Yes",Payables!$E$19:$E$95,"<>Card",Payables!$G$19:$G$95,">"&Assumptions!$C$48) -> 6209.06 | O66: Posh Nov, Optus mobiles Nov, CEO Institute, AVIXA.
A68: KEY RISKS & THINGS TO CONFIRM
A69: 1. Tax is the big block this month - Oct payroll tax $8.6k on 6 Nov, the Oct IAS ~$45k on 20 Nov and the Q1 BAS ~$96k on 25 Nov. That is ~$150k out in weeks 2 to 4. The BAS did not go on 28 Oct, so confirm when it is actually due and the GST figure off the activity statement.
A70: 2. CBA Place South $118,250 (INV-10677, production kit, due 15 Nov) is the biggest receipt. CBA have been paying in about 15 days, so I have it Fri 6 Nov. If it slips to the due date it moves to week 3 - still in the forecast, but week 2 would dip.
A71: 3. Overdue debtors: Downer $39,664, Ventia $36,677, Microsoft $13,846, Gen-e $11,850 and ON24 $3,006 - about $105k, all a month or more old. I have them landing in weeks 3 and 4. If none of it comes, closing is ~$105k lower. Chase this week.
A72: 4. Creditors run Mon 2 Nov is ~$131k including Brookvale $66k and Appspace $19k, plus Nov rent $29k and the 3 Nov pay run ~$98k in the same week. Week 1 is the tightest week - make sure the CBA / Deloitte money is in before the run if the balance looks thin.

Sheet Assumptions
A1: CTS Cash Flow Forecast - Assumptions & Inputs
A2: Blue = change it if you need to. Black = formula, leave it alone. Bright yellow = the ones I still want to double check. Everything is GST inclusive because that's what actually hits the bank.
A4: TIMING & OPENING POSITION
A5: Forecast start | B5: 46324 | C5: Thu 29 Oct. Five weeks of Thu to Wed, running on from the last forecast (its week 5 is this week 1). Week table is at the bottom of this tab.
A6: Opening bank balance - cheque + savings | B6: =896676.95-456746.27 -> 439930.68 | C6: Estimate - Xero total cash at Wed 28 Oct ($896,677) less the other accounts ($456,746, the gap on 5 Oct when cheque + savings was $358,696). Replace with the CommBiz cheque + savings balance at 28 Oct.
A7: Number of weeks | B7: 5 | C7: Each week has a Forecast and an Actual column on the Cash Flow tab.
A8: PAYROLL (fortnightly, Sat to Fri, paid the Tuesday after the fortnight ends)
A9: Gross wages per fortnight | B9: 107500 | C9: Average of the last four fortnights: the two Sep runs $217,062, 6 Oct $101,246 and 20 Oct $111,704 (Xero cash P&L). Detail on the Payroll tab.
A10: Net pay as % of gross | B10: 0.788 | C10: 6 Oct run: $101,246 gross, about $79,736 left the bank = 78.8%. Was 76.8% on the 25 Aug ABA. Swap in the ABA figure when you have it.
A11: PAYG withheld as % of gross | B11: =1-B10 -> 0.212 | C11: 1 less net %. Goes to the ATO with the IAS/BAS, not on pay day.
A12: Superannuation as % of gross | B12: 0.12 | C12: SG is 12%. 25 Aug: $13,677 SG on $115,340 gross. Sal sac super (~$1k a run) goes out in the same super batch but comes off gross, so it's not added on here.
A13: Employee reimbursements per pay run (expense claims) | B13: 1000 | C13: Placeholder - I can't see expense claims in Xero. Per diems ($75 a night) go through payroll so they're already in net pay. Put the usual expense claim amount in here.
A14: Pay date - run 1 (fortnight Sat 17 Oct to Fri 30 Oct) | B14: 46329 | C14: Tue 3 Nov (week 1). Super direct debits the day after.
A15: Pay date - run 2 (fortnight Sat 31 Oct to Fri 13 Nov) | B15: 46343 | C15: Tue 17 Nov (week 3).
A16: Pay date - run 3 (fortnight Sat 14 Nov to Fri 27 Nov) | B16: 46357 | C16: Tue 1 Dec (week 5).
A17: Payroll tax NSW - October return (due 7 Nov) | B17: 5902.75 | C17: Sep return was $8,602.75 all up, paid 7 Oct. I've used the same total. The NSW / other split is assumed - I can't see it in Xero.
A18: Payroll tax other states - October (due 7 Nov) | B18: 2700 | C18: Assumed, see above.
A19: Payroll tax payment date | B19: 46332 | C19: 7 Nov is a Saturday, so Fri 6 Nov (week 2).
A20: BAS / PAYG WITHHOLDING
A21: Q1 BAS paid inside this forecast? (1 = yes, 0 = no) | B21: 1 | C21: It did not go out on 28 Oct (Xero bank is flat 28 to 29 Oct), so I've assumed it goes through the agent and is paid 25 Nov (week 4). Change the date in B25 if it goes earlier, or set this to 0.
A22: Sep PAYG withholding (goes on the Q1 BAS) | B22: =B11*217062 -> 46017.144 | C22: PAYG % x Sep gross $217,062 (Xero cash P&L). Jul and Aug went on the IAS, Sep goes on the Q1 BAS.
A23: Net GST payable for Sep quarter - ESTIMATE | B23: 50000 | C23: Rough guess - GST on ~$1.5m in, less GST on ~$1.0m out. Replace with the activity statement figure from Xero.
A24: PAYG income-tax instalment for Sep quarter | B24: 0 | C24: Can't see this in Xero. Put the ATO instalment in here if there is one.
A25: BAS payment date | B25: 46351 | C25: Wed 25 Nov - agent lodgement date.
A26: COSTS NOT BILLED YET - MONTHLY ESTIMATES (spread over the 5 weeks)
A27: Sub-contract labour | B27: 40000 | C27: Sep cash P&L: Integration $31,990 + PRD $7,154. Oct work that gets billed and paid inside the month.
A28: Equipment & service hires | B28: 30000 | C28: Sep cash P&L: service hires $17,344 + equipment hires $11,427.
A29: Project equipment purchases (not yet billed) | B29: 20000 | C29: On top of the Complete AV / Crestron / Fredon bills already listed. Oct is a big Production month in the budget ($587k income) so this could easily be higher.
A30: Direct travel & freight (client jobs) | B30: 7000 | C30: Sep: ONS travel $4,120 + PRD $1,572 + ~$1,300 freight.
A31: Client subscriptions & licences (not yet billed) | B31: 3000 | C31: Sep: $3,573 outside the Appspace / Spacera / Eptura bills.
A32: Recruitment (Seek, LinkedIn, agency) | B32: 5000 | C32: Sep was $11,742 with the casual concierge campaign. I've assumed half that.
A33: Accounting, legal & advisory (beyond the 8020 retainer) | B33: 4000 | C33: Jun-Aug: accounting $7,733 + legal $2,900 over 3 months.
A34: Insurance | B34: 0 | C34: Was $3k a month as an estimate. The annual Brookvale renewals ($66,239, due 14 Oct) are now on the Payables tab under Insurance, so this is nil - put a number back in if something else comes up (icare, Asteron is quarterly and was paid 25 Sep).
A35: Office, amenities & entertainment | B35: 2000 | C35: Jun-Aug ran ~$4k a month across amenities, supplies and staff entertainment. Sep was lower.
A36: Bank & merchant fees | B36: 1000 | C36: Sep: bank charges $2,311 + Stripe $271, but Sep had a one-off in it.
A37: Credit card settlements per month (PL + DL cards) | B37: 25000 | C37: Sep transfers to the cards: $15,000 + $4,224.75 (PL) + $5,718.88 (DL) = $24,944. Covers every bill marked paid via CC - those are left out of the Payables totals so nothing gets counted twice.
A38: RECEIPTS - ESTIMATES
A39: Invoices raised and collected inside the 5 weeks (not listed) | B39: 20000 | C39: Not used in the formulas - the Receivables tab lists everything. Left for reference.
A40: Interest received on savings | B40: 600 | C40: Sep was $648.92, Oct $430.17. Lands at month end - 30 Oct (week 1) and 30 Nov (week 5).
A42: WEEK TABLE (calculated)
A43: Week | B43: Start | C43: End
A44: 1 | B44: =Assumptions!$B$5 -> 46324 | C44: =B44+6 -> 46330
A45: 2 | B45: =C44+1 -> 46331 | C45: =B45+6 -> 46337
A46: 3 | B46: =C45+1 -> 46338 | C46: =B46+6 -> 46344
A47: 4 | B47: =C46+1 -> 46345 | C47: =B47+6 -> 46351
A48: 5 | B48: =C47+1 -> 46352 | C48: =B48+6 -> 46358
A50: October PAYG withholding - monthly IAS | B50: =B11*(101245.94+111704.13) -> 45145.415 | C50: PAYG % x the two Oct runs ($212,950 gross, Xero cash P&L). Jul and Aug were paid 21 Aug and 21 Sep on the IAS.
A51: IAS payment date | B51: 46346 | C51: 21 Nov is a Saturday, so Fri 20 Nov (week 4).

Sheet Payroll
A1: Payroll schedule - October 2026
A2: Fortnightly, Saturday to Friday. The money only goes out of the bank on the Tuesday after the fortnight ends. Super direct debits the same week. PAYG goes later with the IAS/BAS.
A4: Pay run | B4: Fortnight ending (Fri) | C4: Pay date | D4: Gross wages | E4: Net pay (ABA file) | F4: PAYG withheld | G4: Super (direct debit) | H4: Reimbursements | I4: Cash out on payday (net + super + reimb.) | J4: Notes
A5: Run 1 - Sat 17 Oct to Fri 30 Oct | B5: 46325 | C5: =Assumptions!$B$14 -> 46329 | D5: =Assumptions!$B$9 -> 107500 | E5: =D5*Assumptions!$B$10 -> 84710 | F5: =D5*Assumptions!$B$11 -> 22790 | G5: =D5*Assumptions!$B$12 -> 12900 | H5: =Assumptions!$B$13 -> 1000 | I5: =E5+G5+H5 -> 98610 | J5: Timesheets close Fri 30 Oct, processed Mon 2 Nov, out of the bank Tue 3 Nov. Last run of the month - accrue bonus leave (Checklist step 48).
A6: Run 2 - Sat 31 Oct to Fri 13 Nov | B6: 46339 | C6: =Assumptions!$B$15 -> 46343 | D6: =Assumptions!$B$9 -> 107500 | E6: =D6*Assumptions!$B$10 -> 84710 | F6: =D6*Assumptions!$B$11 -> 22790 | G6: =D6*Assumptions!$B$12 -> 12900 | H6: =Assumptions!$B$13 -> 1000 | I6: =E6+G6+H6 -> 98610 | J6: Paid Tue 17 Nov.
A7: Run 3 - Sat 14 Nov to Fri 27 Nov | B7: 46353 | C7: =Assumptions!$B$16 -> 46357 | D7: =Assumptions!$B$9 -> 107500 | E7: =D7*Assumptions!$B$10 -> 84710 | F7: =D7*Assumptions!$B$11 -> 22790 | G7: =D7*Assumptions!$B$12 -> 12900 | H7: =Assumptions!$B$13 -> 1000 | I7: =E7+G7+H7 -> 98610 | J7: Paid Tue 1 Dec. Last run of November - accrue bonus leave again.
A8: Total pay runs listed | D8: =SUM(D5:D7) -> 322500 | E8: =SUM(E5:E7) -> 254130 | F8: =SUM(F5:F7) -> 68370 | G8: =SUM(G5:G7) -> 38700 | H8: =SUM(H5:H7) -> 3000 | I8: =SUM(I5:I7) -> 295830
A9: Payroll tax for October wages (paid November)
A10: NSW - due 7 Nov (paid Fri 6 Nov) | B10: =Assumptions!$B$17 -> 5902.75 | C10: =Assumptions!$B$19 -> 46332
A11: Other states - due 7 Nov (paid Fri 6 Nov) | B11: =Assumptions!$B$18 -> 2700 | C11: =Assumptions!$B$19 -> 46332
A12: Total payroll tax | B12: =B10+B11 -> 8602.75
A13: Payroll tax on Nov wages is due 7 Dec - after this forecast.
A15: Reference - actual pay runs this financial year
A16: Pay run | B16: Journal date | C16: Gross wages | D16: Super batch (SG + salary sacrifice) | E16: Batch % of gross | F16: Source
A17: FE 10 Jul | B17: 46217 | C17: 104335.03 | D17: 13289.41 | E17: =IF(C17=0,0,D17/C17) -> 0.12737247 | F17: Controller Pack GL_Paste journals #69527 / #69434
A18: FE 24 Jul | B18: 46231 | C18: 101030.18 | D18: 13068.87 | E18: =IF(C18=0,0,D18/C18) -> 0.1293561 | F18: GL journals #68743 / #68744
A19: FE 7 Aug | B19: 46245 | C19: 108324.58 | D19: 13783.25 | E19: =IF(C19=0,0,D19/C19) -> 0.12724028 | F19: GL journals #69396 / #69397
A20: FE 21 Aug | B20: 46259 | C20: 115339.8 | D20: 14677.93 | E20: =IF(C20=0,0,D20/C20) -> 0.12725815 | F20: GL journals #69669 / #69663 (the run in the training videos)
A21: FE 4 Sep + FE 18 Sep (two runs) | B21: 46287 | C21: 217061.76 | D21: 27815.63 | E21: =IF(C21=0,0,D21/C21) -> 0.12814616 | F21: Xero cash P&L 1-28 Sep: all salaries & wages accounts; direct + indirect super
A22: FE 2 Oct (paid Tue 6 Oct) | B22: 46304 | C22: 101245.94 | D22: 13083.54 | E22: =IF(C22=0,0,D22/C22) -> 0.12922533 | F22: Xero cash P&L, journal dated 8-9 Oct. Bank shows about $79.7k net leaving 6 Oct, super + payroll tax 7 Oct.
A23: FE 16 Oct (paid Tue 20 Oct) | B23: 46315 | C23: 111704.13 | D23: 14214.47 | E23: =IF(C23=0,0,D23/C23) -> 0.12725107 | F23: Xero cash P&L 13-28 Oct: all salaries & wages accounts; direct + indirect super.
A24: Average gross per fortnight (last 4 fortnights) | B24: =(C21+C22+C23)/4 -> 107502.96 | C24: The two Sep runs plus the two Oct runs, over four fortnights.
A25: SG is 12%. The batch % above is higher because the GL super accounts include sal sac super (25 Aug: $13,677 SG + $1,052 sal sac). Forecast uses 12% - the sal sac part comes off gross so it isn't counted twice.
A27: Reference - payroll tax accruals this financial year
A28: Month | B28: NSW | C28: Other states | D28: Total | E28: Source
A29: July 2026 | B29: 5170.8 | C29: 3000 | D29: =B29+C29 -> 8170.8 | E29: GL journals #68926 (NSW) and #68927 (other states)
A30: August 2026 | B30: 6295.07 | C30: 2700 | D30: =B30+C30 -> 8995.07 | E30: GL journals #69671 + #70351 (NSW) and #69670 (other states)
A31: Sep return paid 7 Oct was $8,602.75 all up (Xero cash P&L). Split by state not visible, so the Nov payment uses that total with the Aug split.

Sheet Receivables
A1: Receivables - every open invoice and when the cash is expected
A2: Xero aged receivables at 29 Oct ($445,570.46, 35 invoices) plus the Oct contract invoices still to be raised (from the repeating templates, Sep actuals used where the amount varies). Expected date (blue) is my call based on how each customer has been paying - change it and the forecast moves. Aware Super paid everything in October, including the $225,887.
A4: Customer | B4: Invoice | C4: Reference | D4: Invoice date | E4: Due date | F4: Amount (incl GST) | G4: Status | H4: Expected receipt date | I4: Days after due | J4: Week | K4: Why that date
A5: ASX Operations | B5: INV-10668 | C5: External listing test days 29.9.26 | D5: 46295 | E5: 46325 | F5: 5747.5 | G5: Current | H5: 46325 | I5: =H5-E5 -> 0 | J5: =IF(H5<Assumptions!$B$5,"Before",IF(H5>Assumptions!$C$48,"After",INT((H5-Assumptions!$B$5)/7)+1)) -> 1 | K5: ASX pay on the due date - the 15 Oct ones landed 15 Oct.
A6: ASX Operations | B6: INV-10705 | C6: ASX AGM 22.10.2026 | D6: 46324 | E6: 46354 | F6: 70644.76 | G6: Current | H6: 46356 | I6: =H6-E6 -> 2 | J6: =IF(H6<Assumptions!$B$5,"Before",IF(H6>Assumptions!$C$48,"After",INT((H6-Assumptions!$B$5)/7)+1)) -> 5 | K6: Due Sat 28 Nov, call it Mon 30 Nov. The big one for ASX.
A7: ASX Operations | B7: INV-10704 | C7: CEO Connect series 27.10.2026 | D7: 46324 | E7: 46354 | F7: 4041.4 | G7: Current | H7: 46356 | I7: =H7-E7 -> 2 | J7: =IF(H7<Assumptions!$B$5,"Before",IF(H7>Assumptions!$C$48,"After",INT((H7-Assumptions!$B$5)/7)+1)) -> 5 | K7: With the AGM one.
A8: ASX Operations | B8: INV-10703 | C8: Listing event lighting 14.10.26 | D8: 46324 | E8: 46354 | F8: 1903 | G8: Current | H8: 46356 | I8: =H8-E8 -> 2 | J8: =IF(H8<Assumptions!$B$5,"Before",IF(H8>Assumptions!$C$48,"After",INT((H8-Assumptions!$B$5)/7)+1)) -> 5 | K8: With the AGM one.
A9: April 5 | B9: INV-10706 | C9: Microsoft SME&C event 14.10.2026 (PO016066) | D9: 46324 | E9: 46354 | F9: 32452.77 | G9: Current | H9: 46356 | I9: =H9-E9 -> 2 | J9: =IF(H9<Assumptions!$B$5,"Before",IF(H9>Assumptions!$C$48,"After",INT((H9-Assumptions!$B$5)/7)+1)) -> 5 | K9: New customer - on the due date, Mon 30 Nov.
A10: Chorus Call Australia | B10: INV-10678 | C10: Redox AGM 07.10.2026 | D10: 46311 | E10: 46341 | F10: 5326.2 | G10: Current | H10: 46342 | I10: =H10-E10 -> 1 | J10: =IF(H10<Assumptions!$B$5,"Before",IF(H10>Assumptions!$C$48,"After",INT((H10-Assumptions!$B$5)/7)+1)) -> 3 | K10: Due Sun 15 Nov so Mon 16 Nov.
A11: Commonwealth Bank (CBA Place South) | B11: INV-10677 | C11: Bankwest production kit (PO3311640) | D11: 46311 | E11: 46341 | F11: 118250 | G11: Current | H11: 46332 | I11: =H11-E11 -> -9 | J11: =IF(H11<Assumptions!$B$5,"Before",IF(H11>Assumptions!$C$48,"After",INT((H11-Assumptions!$B$5)/7)+1)) -> 2 | K11: Biggest one in the forecast. CBA paid the Sep contract invoices 15 days after we sent them, so Fri 6 Nov. If they take the full 30 days it is Mon 16 Nov - still inside the forecast.
A12: Commonwealth Bank (CBA Place South) | B12: INV-10707 | C12: Foldback monitor hire 22.10.2026 | D12: 46324 | E12: 46354 | F12: 3498 | G12: Current | H12: 46339 | I12: =H12-E12 -> -15 | J12: =IF(H12<Assumptions!$B$5,"Before",IF(H12>Assumptions!$C$48,"After",INT((H12-Assumptions!$B$5)/7)+1)) -> 3 | K12: 15 days after invoice.
A13: Dimensional Fund Advisors | B13: INV-10692 | C13: AV audio support 15.10.26 | D13: 46315 | E13: 46345 | F13: 418 | G13: Current | H13: 46332 | I13: =H13-E13 -> -13 | J13: =IF(H13<Assumptions!$B$5,"Before",IF(H13>Assumptions!$C$48,"After",INT((H13-Assumptions!$B$5)/7)+1)) -> 2 | K13: Paid the last one 9 days after invoice.
A14: Downer EDI | B14: INV-10587 | C14: Full year results briefing 20.08.2026 | D14: 46259 | E14: 46289 | F14: 12808.69 | G14: Overdue 1 month | H14: 46339 | I14: =H14-E14 -> 50 | J14: =IF(H14<Assumptions!$B$5,"Before",IF(H14>Assumptions!$C$48,"After",INT((H14-Assumptions!$B$5)/7)+1)) -> 3 | K14: Five weeks overdue at 29 Oct and nothing in yet. Chase. Fri 13 Nov.
A15: Downer EDI | B15: INV-10611 | C15: Full year employee briefing 25.08.2026 | D15: 46265 | E15: 46295 | F15: 26855.13 | G15: Overdue | H15: 46339 | I15: =H15-E15 -> 44 | J15: =IF(H15<Assumptions!$B$5,"Before",IF(H15>Assumptions!$C$48,"After",INT((H15-Assumptions!$B$5)/7)+1)) -> 3 | K15: A month overdue. Chase with the other one.
A16: Garvan Research Foundation | B16: INV-10679 | C16: Breast cancer public lecture 01.10.2026 | D16: 46310 | E16: 46340 | F16: 418 | G16: Current | H16: 46342 | I16: =H16-E16 -> 2 | J16: =IF(H16<Assumptions!$B$5,"Before",IF(H16>Assumptions!$C$48,"After",INT((H16-Assumptions!$B$5)/7)+1)) -> 3 | K16: Due Sat 14 Nov so Mon 16 Nov.
... A52: Aware Super | B52: TBR | C52: Annual National Maintenance - October | D52: 46325 | E52: 46355 | F52: 12100 | G52: To be raised | H52: 46353 | I52: =H52-E52 -> -2 | J52: =IF(H52<Assumptions!$B$5,"Before",IF(H52>Assumptions!$C$48,"After",INT((H52-Assumptions!$B$5)/7)+1)) -> 5 | K52: Aware paid the Sep one 27 Oct, three days before due.
A66: TOTAL | F66: =SUM(F5:F65) -> 695701.82
A67: of which open in Xero at 29 Oct (should be $445,570.46) | F67: =SUMIFS(F5:F65,G5:G65,"<>To be raised") -> 445570.46
A68: of which expected inside the forecast (29 Oct to 2 Dec) | F68: =SUMIFS(F5:F65,H5:H65,">="&Assumptions!$B$5,H5:H65,"<="&Assumptions!$C$48) -> 690560.11
A69: of which pushed past the forecast (Meet Magic, Jaaz, the Nov contract invoices are not listed) | F69: =F66-F68 -> 5141.71

Sheet Payables
A1: Payables - every open bill, plus October's recurring bills not yet in Xero
A2: Xero aged payables at 29 Oct ($158,464.01, 46 bills) plus the repeating bill templates for November. Card rows get paid on the PL/DL cards and sit in the credit card line on the Cash Flow tab, so they're left out of the category totals. With the Creditors Run tab switched on, the open Xero bills come through the Creditors run row and the templates come through the category lines.
A4: PAYMENTS THIS WEEK (29 Oct - 4 Nov) - creditors run Mon 2 Nov
A5: Supplier | B5: Bill / reference | C5: Due date | D5: Amount (incl GST) | E5: Method | F5: Status | G5: Pay on | J5: Notes
A6: Brookvale Insurance Brokers | B6: Six annual renewals - INV1918462, 1918336, 1918436, 1920058, 1920113, 1914759 | C6: 46325 | D6: =SUM(D19:D24) -> 66238.98 | E6: EFT | F6: AGREED - PAY | G6: 46328 | J6: GC approved all six. One payment in the Mon 2 Nov run - $66,238.98.
A7: =A25 -> Appspace | B7: =B25 -> INV00133660 - Appspace licensing for Aware Super (balance) | C7: =C25 -> 46319 | D7: =D25 -> 19077.66 | E7: =E25 -> EFT | F7: Due this week | G7: =G25 -> 46328 | J7: Appspace - Aware paid us for it 20 Oct. Overdue, pay in the run.
A8: =A26 -> Start Webcast | B8: =B26 -> INV-202222 - CBA AGM 2026 equipment & services | C8: =C26 -> 46324 | D8: =D26 -> 12787.06 | E8: =E26 -> EFT | F8: AWAITING DL / TW | G8: =G26 -> 46328 | J8: Start Webcast - DL / TW still to approve. Hold until they do. | O8: ='Complete AV'!K19 -> 139086.23
A9: Contact Group | B9: INV457215 + INV457214 - DTTL Hobart fitout | C9: 46327 | D9: =D27+D28 -> 10555.92 | E9: EFT | F9: Due this week | G9: 46328 | J9: Due Sun 1 Nov - in the run. | O9: =25155-5155 -> 20000
A10: =A29 -> SPACERA | B10: =B29 -> INV-0060 - Aware Super national support October | C10: =C29 -> 46326 | D10: =D29 -> 5728.8 | E10: =E29 -> EFT | F10: Due this week | G10: =G29 -> 46328 | J10: Spacera Oct - in the run. | O10: =O8-O9 -> 119086.23
A11: =A30 -> Easton Belle | B11: =B30 -> INV00004009 - legal fees, general commercial file | C11: =C30 -> 46325 | D11: =D30 -> 3932.5 | E11: =E30 -> EFT | F11: Due this week | G11: =G30 -> 46328 | J11: Easton Belle - DL approved, in the run.
A12: Headroom / Hire Intelligence / 2020 Events / Employsure / Type Transcripts / Ricoh | B12: Small ones due by 4 Nov | C12: 46330 | D12: =SUM(D31:D36) -> 9270.97 | E12: EFT | F12: Due this week | G12: 46328 | J12: All MH approved except Employsure (overdue) and Ricoh (DD). | O12: =O10+25155 -> 144241.23
A13: =A65 -> Investa Asset Management | B13: =B65 -> Rent November 2026 (Oct was $28,895.72) | C13: =C65 -> 46327 | D13: =D65 -> 28895.72 | E13: =E65 -> EFT | F13: Due this week | G13: =G65 -> 46328 | J13: Investa Nov rent - template, pay with the run like last month.
A14: =A66 -> Cleveland Partners (8020 Advisors) | B14: =B66 -> Monthly advisory fees - November | C14: =C66 -> 46328 | D14: =D66 -> 3850 | E14: =E66 -> EFT | F14: Due this week | G14: =G66 -> 46328 | J14: 8020 Advisors - template, check the Nov invoice has come in.
A15: Total this week | D15: =SUM(D6:D14) -> 160337.61
A16: of which agreed / due this week (excludes Start Webcast until DL / TW approve) | D16: =SUMIFS(D6:D14,F6:F14,"AGREED - PAY")+SUMIFS(D6:D14,F6:F14,"Due this week") -> 147550.55
A17: ALL OPEN BILLS AND OCTOBER TEMPLATES
A18: Supplier | B18: Bill / reference | C18: Due date | D18: Amount (incl GST) | E18: Method | F18: P&L category | G18: Planned payment date | H18: Week | I18: Source | J18: Notes | K18: Counted in the category lines? (open Xero bills move to the creditors run)
A19: Brookvale Insurance Brokers | B19: INV1918462 - IT liability insurance (annual) | C19: 46325 | D19: 35304.46 | E19: EFT | F19: Insurance | G19: 46328 | H19: =IF(G19<Assumptions!$B$5,"Before",IF(G19>Assumptions!$C$48,"After",INT((G19-Assumptions!$B$5)/7)+1)) -> 1 | I19: Xero bill | J19: GC approved. In the 2 Nov run. | K19: =IF(AND('Creditors Run'!$B$5=1,I19="Xero bill",LEFT(J19,4)<>"PAID"),"No - in the creditors run","Yes") -> No - in the creditors run
A20: Brookvale Insurance Brokers | B20: INV1918336 - removable / electronic equipment insurance (annual) | C20: 46325 | D20: 11283.16 | E20: EFT | F20: Insurance | G20: 46328 | H20: =IF(G20<Assumptions!$B$5,"Before",IF(G20>Assumptions!$C$48,"After",INT((G20-Assumptions!$B$5)/7)+1)) -> 1 | I20: Xero bill | J20: GC approved. In the 2 Nov run. | K20: =IF(AND('Creditors Run'!$B$5=1,I20="Xero bill",LEFT(J20,4)<>"PAID"),"No - in the creditors run","Yes") -> No - in the creditors run
A21: Brookvale Insurance Brokers | B21: INV1918436 - Mecon contract works insurance (annual) | C21: 46325 | D21: 8020.39 | E21: EFT | F21: Insurance | G21: 46328 | H21: =IF(G21<Assumptions!$B$5,"Before",IF(G21>Assumptions!$C$48,"After",INT((G21-Assumptions!$B$5)/7)+1)) -> 1 | I21: Xero bill | J21: GC approved. In the 2 Nov run. | K21: =IF(AND('Creditors Run'!$B$5=1,I21="Xero bill",LEFT(J21,4)<>"PAID"),"No - in the creditors run","Yes") -> No - in the creditors run
A22: Brookvale Insurance Brokers | B22: INV1920058 - management liability insurance (annual) | C22: 46325 | D22: 6778.21 | E22: EFT | F22: Insurance | G22: 46328 | H22: =IF(G22<Assumptions!$B$5,"Before",IF(G22>Assumptions!$C$48,"After",INT((G22-Assumptions!$B$5)/7)+1)) -> 1 | I22: Xero bill | J22: GC approved. In the 2 Nov run. | K22: =IF(AND('Creditors Run'!$B$5=1,I22="Xero bill",LEFT(J22,4)<>"PAID"),"No - in the creditors run","Yes") -> No - in the creditors run
A23: Brookvale Insurance Brokers | B23: INV1920113 - business pack insurance (annual) | C23: 46325 | D23: 3510.52 | E23: EFT | F23: Insurance | G23: 46328 | H23: =IF(G23<Assumptions!$B$5,"Before",IF(G23>Assumptions!$C$48,"After",INT((G23-Assumptions!$B$5)/7)+1)) -> 1 | I23: Xero bill | J23: GC approved. In the 2 Nov run. | K23: =IF(AND('Creditors Run'!$B$5=1,I23="Xero bill",LEFT(J23,4)<>"PAID"),"No - in the creditors run","Yes") -> No - in the creditors run
A24: Brookvale Insurance Brokers | B24: INV1914759 - corporate travel insurance (annual) | C24: 46325 | D24: 1342.24 | E24: EFT | F24: Insurance | G24: 46328 | H24: =IF(G24<Assumptions!$B$5,"Before",IF(G24>Assumptions!$C$48,"After",INT((G24-Assumptions!$B$5)/7)+1)) -> 1 | I24: Xero bill | J24: GC approved. In the 2 Nov run. | K24: =IF(AND('Creditors Run'!$B$5=1,I24="Xero bill",LEFT(J24,4)<>"PAID"),"No - in the creditors run","Yes") -> No - in the creditors run
A25: Appspace | B25: INV00133660 - Appspace licensing for Aware Super (balance) | C25: 46319 | D25: 19077.66 | E25: EFT | F25: Client subscriptions | G25: 46328 | H25: =IF(G25<Assumptions!$B$5,"Before",IF(G25>Assumptions!$C$48,"After",INT((G25-Assumptions!$B$5)/7)+1)) -> 1 | I25: Xero bill | J25: Overdue - Aware paid us for it 20 Oct. $19,077.66 left on it in Xero. In the 2 Nov run. | K25: =IF(AND('Creditors Run'!$B$5=1,I25="Xero bill",LEFT(J25,4)<>"PAID"),"No - in the creditors run","Yes") -> No - in the creditors run
A26: Start Webcast | B26: INV-202222 - CBA AGM 2026 equipment & services | C26: 46324 | D26: 12787.06 | E26: EFT | F26: Equipment & service hires | G26: 46328 | H26: =IF(G26<Assumptions!$B$5,"Before",IF(G26>Assumptions!$C$48,"After",INT((G26-Assumptions!$B$5)/7)+1)) -> 1 | I26: Xero bill | J26: DL / TW still to approve. In the 2 Nov run once approved. | K26: =IF(AND('Creditors Run'!$B$5=1,I26="Xero bill",LEFT(J26,4)<>"PAID"),"No - in the creditors run","Yes") -> No - in the creditors run
A27: Contact Group | B27: INV457215 - DTTL Hobart AV fitout equipment & labour | C27: 46327 | D27: 9652.54 | E27: EFT | F27: Equipment purchases | G27: 46328 | H27: =IF(G27<Assumptions!$B$5,"Before",IF(G27>Assumptions!$C$48,"After",INT((G27-Assumptions!$B$5)/7)+1)) -> 1 | I27: Xero bill | J27: In the 2 Nov run. | K27: =IF(AND('Creditors Run'!$B$5=1,I27="Xero bill",LEFT(J27,4)<>"PAID"),"No - in the creditors run","Yes") -> No - in the creditors run
A28: Contact Group | B28: INV457214 - DTTL Hobart AV fitout equipment | C28: 46327 | D28: 903.38 | E28: EFT | F28: Equipment purchases | G28: 46328 | H28: =IF(G28<Assumptions!$B$5,"Before",IF(G28>Assumptions!$C$48,"After",INT((G28-Assumptions!$B$5)/7)+1)) -> 1 | I28: Xero bill | J28: In the 2 Nov run. | K28: =IF(AND('Creditors Run'!$B$5=1,I28="Xero bill",LEFT(J28,4)<>"PAID"),"No - in the creditors run","Yes") -> No - in the creditors run
A29: SPACERA | B29: INV-0060 - Aware Super national support October | C29: 46326 | D29: 5728.8 | E29: EFT | F29: Client subscriptions | G29: 46328 | H29: =IF(G29<Assumptions!$B$5,"Before",IF(G29>Assumptions!$C$48,"After",INT((G29-Assumptions!$B$5)/7)+1)) -> 1 | I29: Xero bill | J29: In the 2 Nov run. | K29: =IF(AND('Creditors Run'!$B$5=1,I29="Xero bill",LEFT(J29,4)<>"PAID"),"No - in the creditors run","Yes") -> No - in the creditors run
A30: Easton Belle | B30: INV00004009 - legal fees, general commercial file | C30: 46325 | D30: 3932.5 | E30: EFT | F30: Professional fees | G30: 46328 | H30: =IF(G30<Assumptions!$B$5,"Before",IF(G30>Assumptions!$C$48,"After",INT((G30-Assumptions!$B$5)/7)+1)) -> 1 | I30: Xero bill | J30: DL approved. In the 2 Nov run. | K30: =IF(AND('Creditors Run'!$B$5=1,I30="Xero bill",LEFT(J30,4)<>"PAID"),"No - in the creditors run","Yes") -> No - in the creditors run
... A87: AVIXA | B87: DL annual silver membership | C87: 46367 | D87: 2850 | E87: EFT | F87: Dues & subscriptions | G87: 46367 | H87: =IF(G87<Assumptions!$B$5,"Before",IF(G87>Assumptions!$C$48,"After",INT((G87-Assumptions!$B$5)/7)+1)) -> After | I87: Repeating template | J87: After this forecast. | K87: =IF(AND('Creditors Run'!$B$5=1,I87="Xero bill",LEFT(J87,4)<>"PAID"),"No - in the creditors run","Yes") -> Yes
H88: =IF(G88<Assumptions!$B$5,"Before",IF(G88>Assumptions!$C$48,"After",INT((G88-Assumptions!$B$5)/7)+1)) -> Before | K88: =IF(AND('Creditors Run'!$B$5=1,I88="Xero bill",LEFT(J88,4)<>"PAID"),"No - in the creditors run","Yes") -> Yes
H89: =IF(G89<Assumptions!$B$5,"Before",IF(G89>Assumptions!$C$48,"After",INT((G89-Assumptions!$B$5)/7)+1)) -> Before | K89: =IF(AND('Creditors Run'!$B$5=1,I89="Xero bill",LEFT(J89,4)<>"PAID"),"No - in the creditors run","Yes") -> Yes
H90: =IF(G90<Assumptions!$B$5,"Before",IF(G90>Assumptions!$C$48,"After",INT((G90-Assumptions!$B$5)/7)+1)) -> Before | K90: =IF(AND('Creditors Run'!$B$5=1,I90="Xero bill",LEFT(J90,4)<>"PAID"),"No - in the creditors run","Yes") -> Yes
H91: =IF(G91<Assumptions!$B$5,"Before",IF(G91>Assumptions!$C$48,"After",INT((G91-Assumptions!$B$5)/7)+1)) -> Before | K91: =IF(AND('Creditors Run'!$B$5=1,I91="Xero bill",LEFT(J91,4)<>"PAID"),"No - in the creditors run","Yes") -> Yes
H92: =IF(G92<Assumptions!$B$5,"Before",IF(G92>Assumptions!$C$48,"After",INT((G92-Assumptions!$B$5)/7)+1)) -> Before | K92: =IF(AND('Creditors Run'!$B$5=1,I92="Xero bill",LEFT(J92,4)<>"PAID"),"No - in the creditors run","Yes") -> Yes
H93: =IF(G93<Assumptions!$B$5,"Before",IF(G93>Assumptions!$C$48,"After",INT((G93-Assumptions!$B$5)/7)+1)) -> Before | K93: =IF(AND('Creditors Run'!$B$5=1,I93="Xero bill",LEFT(J93,4)<>"PAID"),"No - in the creditors run","Yes") -> Yes
H94: =IF(G94<Assumptions!$B$5,"Before",IF(G94>Assumptions!$C$48,"After",INT((G94-Assumptions!$B$5)/7)+1)) -> Before | K94: =IF(AND('Creditors Run'!$B$5=1,I94="Xero bill",LEFT(J94,4)<>"PAID"),"No - in the creditors run","Yes") -> Yes
H95: =IF(G95<Assumptions!$B$5,"Before",IF(G95>Assumptions!$C$48,"After",INT((G95-Assumptions!$B$5)/7)+1)) -> Before | K95: =IF(AND('Creditors Run'!$B$5=1,I95="Xero bill",LEFT(J95,4)<>"PAID"),"No - in the creditors run","Yes") -> Yes
A97: TOTAL bills listed from Xero (aged payables at 29 Oct, should be $158,464.01) | D97: =SUMIFS(D19:D95,I19:I95,"Xero bill") -> 158464.01
A98: of which paid by card (left out - see the credit card line) | D98: =SUMIFS(D19:D95,E19:E95,"Card",I19:I95,"Xero bill") -> 4211.23
A99: Templates (non-card) inside the forecast | D99: =SUMIFS(D19:D95,I19:I95,"Repeating template",E19:E95,"<>Card",G19:G95,">="&Assumptions!$B$5,G19:G95,"<="&Assumptions!$C$48) -> 89107.71
A100: Non-card bills dated past the forecast (Oct rent, Oct mobiles) | D100: =SUMIFS(D19:D95,E19:E95,"<>Card",G19:G95,">"&Assumptions!$C$48) -> 6209.06

Sheet Creditors Run
A1: Creditors run - paste the Xero aged payables detail straight in
A2: How it works: run the aged payables detail in Xero, export it, and paste the lines in from row 11 (columns A to K, same order as the report). Anything with a date in column A and a number in Gross gets counted - the contact and total lines the report adds are ignored. Every bill goes out on the run date in B4 unless you type a date in L, and an x in M leaves a line out (card bills - they sit in the card line). With B5 at 1 the Cash Flow Creditors run row takes these numbers and the Payables tab stops counting its Xero bill rows, so nothing is counted twice.
A4: Creditors run pay date | B4: 46328 | C4: Mon 2 Nov (1 Nov is a Sunday). Change it each month. Anything with its own date in column L ignores this.
A5: Use this paste for the forecast? (1 = yes, 0 = use the Payables tab rows instead) | B5: 1
A6: Total open per the paste (what the forecast uses, before any x) | B6: =SUMPRODUCT((A11:A510<>"")*ISNUMBER(I11:I510),I11:I510) -> 158464.01
A7: Report total per Xero (type it from the bottom of the report) | B7: 158464.01
A8: Difference - should be nil | B8: =IF(B7="","",B6-B7) -> 0
A10: Invoice Date | B10: Source | C10: Reference | D10: Item Code | E10: Description | F10: Quantity | G10: Unit Price (ex) | H10: GST | I10: Gross | J10: Invoice Total | K10: Status | L10: Pay on (optional) | M10: Exclude (x) | N10: Pay date used
A11: 46295 | B11: Bill | C11: INV1918462 | E11: Brookvale Insurance Brokers - IT liability insurance (annual) | G11: 32254.45 | H11: 3050.02 | I11: 35304.46 | J11: 35304.46 | K11: Awaiting Payment | N11: =IF(L11="",$B$4,L11) -> 46328
A12: 46295 | B12: Bill | C12: INV1918336 | E12: Brookvale Insurance Brokers - removable / electronic equipment insurance (annual) | G12: 10300.62 | H12: 982.54 | I12: 11283.16 | J12: 11283.16 | K12: Awaiting Payment | N12: =IF(L12="",$B$4,L12) -> 46328
A13: 46295 | B13: Bill | C13: INV1918436 | E13: Brookvale Insurance Brokers - Mecon contract works insurance (annual) | G13: 7338.73 | H13: 681.66 | I13: 8020.39 | J13: 8020.39 | K13: Awaiting Payment | N13: =IF(L13="",$B$4,L13) -> 46328
A14: 46295 | B14: Bill | C14: INV1920058 | E14: Brookvale Insurance Brokers - management liability insurance (annual) | G14: 6195.64 | H14: 582.57 | I14: 6778.21 | J14: 6778.21 | K14: Awaiting Payment | N14: =IF(L14="",$B$4,L14) -> 46328
A15: 46295 | B15: Bill | C15: INV1920113 | E15: Brookvale Insurance Brokers - business pack insurance (annual) | G15: 3211.96 | H15: 298.57 | I15: 3510.52 | J15: 3510.52 | K15: Awaiting Payment | N15: =IF(L15="",$B$4,L15) -> 46328
A16: 46295 | B16: Bill | C16: INV1914759 | E16: Brookvale Insurance Brokers - corporate travel insurance (annual) | G16: 1246.49 | H16: 95.75 | I16: 1342.24 | J16: 1342.24 | K16: Awaiting Payment | N16: =IF(L16="",$B$4,L16) -> 46328
A17: 46289 | B17: Bill | C17: INV00133660 | E17: Appspace - Appspace licensing for Aware Super (balance) | G17: 17343.33 | H17: 1734.33 | I17: 19077.66 | J17: 19077.66 | K17: Awaiting Payment | N17: =IF(L17="",$B$4,L17) -> 46328
A18: 46309 | B18: Bill | C18: INV-202222 | E18: Start Webcast - CBA AGM 2026 equipment & services | G18: 11624.6 | H18: 1162.46 | I18: 12787.06 | J18: 12787.06 | K18: Awaiting Payment | N18: =IF(L18="",$B$4,L18) -> 46328
A19: 46295 | B19: Bill | C19: INV457215 | E19: Contact Group - DTTL Hobart AV fitout equipment & labour | G19: 8775 | H19: 877.54 | I19: 9652.54 | J19: 9652.54 | K19: Awaiting Payment | N19: =IF(L19="",$B$4,L19) -> 46328
A20: 46295 | B20: Bill | C20: INV457214 | E20: Contact Group - DTTL Hobart AV fitout equipment | G20: 821.25 | H20: 82.13 | I20: 903.38 | J20: 903.38 | K20: Awaiting Payment | N20: =IF(L20="",$B$4,L20) -> 46328
A21: 46296 | B21: Bill | C21: INV-0060 | E21: SPACERA - Aware Super national support October | G21: 5208 | H21: 520.8 | I21: 5728.8 | J21: 5728.8 | K21: Awaiting Payment | N21: =IF(L21="",$B$4,L21) -> 46328
A22: 46295 | B22: Bill | C22: INV00004009 | E22: Easton Belle - legal fees, general commercial file | G22: 3575 | H22: 357.5 | I22: 3932.5 | J22: 3932.5 | K22: Awaiting Payment | N22: =IF(L22="",$B$4,L22) -> 46328
... A24: 46324 | B24: Bill | C24: CS167608 | E24: Hire Intelligence - SUN investor day 29.10.26 equipment hire | G24: 2350 | H24: 235 | I24: 2585 | J24: 2585 | K24: Awaiting Payment | N24: =IF(L24="",$B$4,L24) -> 46328
A25: 46316 | B25: Bill | C25: INV-1611 | E25: 2020 Events - Microsoft SME&C townhall 14.10.26 hire | G25: 2133.06 | H25: 213.31 | I25: 2346.37 | J25: 2346.37 | K25: Awaiting Payment | L25: 46330 | N25: =IF(L25="",$B$4,L25) -> 46330
A26: 46300 | B26: Bill | C26: 42 of 60 | E26: Employsure - October | G26: 800 | H26: 80 | I26: 880 | J26: 880 | K26: Awaiting Payment | N26: =IF(L26="",$B$4,L26) -> 46328
A27: 46310 | B27: Bill | C27: INV6062 | E27: Type Transcripts - TLC AGM transcription 14.10.2026 | G27: 234 | H27: 23.4 | I27: 257.4 | J27: 257.4 | K27: Awaiting Payment | N27: =IF(L27="",$B$4,L27) -> 46328
A28: 46290 | B28: Bill | C28: INV15775235 | E28: Ricoh Australia - printing Sep | G28: 191.09 | H28: 19.11 | I28: 210.2 | J28: 210.2 | K28: Awaiting Payment | N28: =IF(L28="",$B$4,L28) -> 46328
A29: 46321 | B29: Bill | C29: INV-1618 | E29: 2020 Events - Cochlear AGM 26.10.26 hire | G29: 5150 | H29: 515 | I29: 5665 | J29: 5665 | K29: Awaiting Payment | L29: 46335 | N29: =IF(L29="",$B$4,L29) -> 46335
A30: 46321 | B30: Bill | C30: INV-2016 | E30: WordBirds - ASX AGM 22.10.26 services | G30: 4603.18 | H30: 460.32 | I30: 5063.5 | J30: 5063.5 | K30: Awaiting Payment | L30: 46335 | N30: =IF(L30="",$B$4,L30) -> 46335
A31: 46322 | B31: Bill | C31: INV-2019 | E31: WordBirds - Cochlear AGM 26.10.26 services | G31: 2970 | H31: 297 | I31: 3267 | J31: 3267 | K31: Awaiting Payment | L31: 46336 | N31: =IF(L31="",$B$4,L31) -> 46336
A32: 46321 | B32: Bill | C32: INV26-12398 | E32: Dubology Studios - Microsoft SME&C and CBA LES Oct services | G32: 1925 | H32: 192.5 | I32: 2117.5 | J32: 2117.5 | K32: Awaiting Payment | L32: 46335 | N32: =IF(L32="",$B$4,L32) -> 46335
A33: 46321 | B33: Bill | C33: INV409016 | E33: Deaf Services - CBA AGM 2026 services | G33: 282.5 | H33: 28.25 | I33: 310.75 | J33: 310.75 | K33: Awaiting Payment | L33: 46335 | N33: =IF(L33="",$B$4,L33) -> 46335
A34: 46305 | B34: Bill | C34: INV000600307641 | E34: Optus - staff mobiles Oct | G34: 764.53 | H34: 76.41 | I34: 840.98 | J34: 840.98 | K34: Awaiting Payment | L34: 46335 | N34: =IF(L34="",$B$4,L34) -> 46335
A35: 46304 | B35: Bill | C35: INV21742621 | E35: Posh Services (Ambius) - indoor plants Oct | G35: 222.73 | H35: 22.27 | I35: 245 | J35: 245 | K35: Awaiting Payment | L35: 46335 | N35: =IF(L35="",$B$4,L35) -> 46335
A36: 46320 | B36: Bill | C36: TTI20233644300 | E36: Telstra - Nighthawk Oct | G36: 123.64 | H36: 12.36 | I36: 136 | J36: 136 | K36: Awaiting Payment | L36: 46332 | N36: =IF(L36="",$B$4,L36) -> 46332
A37: 46302 | B37: Bill | C37: INV632570641 | E37: Officeworks - keyboard & mouse for CBA AGM | G37: 98.18 | H37: 9.82 | I37: 108 | J37: 108 | K37: Awaiting Payment | L37: 46332 | N37: =IF(L37="",$B$4,L37) -> 46332
A38: 46310 | B38: Bill | C38: INV00010410 | E38: Riedel Communications - Microsoft SME&C townhall 14.10.26 hire | G38: 804.6 | H38: 80.46 | I38: 885.06 | J38: 885.06 | K38: Awaiting Payment | L38: 46342 | N38: =IF(L38="",$B$4,L38) -> 46342
A39: 46314 | B39: Bill | C39: INV22273 | E39: Access Innovation Media - CBA AGM 2026 services | G39: 840 | H39: 84 | I39: 924 | J39: 924 | K39: Awaiting Payment | L39: 46344 | N39: =IF(L39="",$B$4,L39) -> 46344
A40: 46314 | B40: Bill | C40: INV22274 | E40: Access Innovation Media - CBA AGM 2026 services | G40: 620 | H40: 62 | I40: 682 | J40: 682 | K40: Awaiting Payment | L40: 46344 | N40: =IF(L40="",$B$4,L40) -> 46344
... A46: 46321 | B46: Bill | C46: INV15788514 | E46: Ricoh Australia - printing Oct | G46: 234.06 | H46: 23.41 | I46: 257.47 | J46: 257.47 | K46: Awaiting Payment | L46: 46356 | N46: =IF(L46="",$B$4,L46) -> 46356
A47: 46318 | B47: Bill | C47: INV02434590 | E47: Avetta - worker management annual licence 2026-27 | G47: 892 | H47: 0 | I47: 892 | J47: 892 | K47: Awaiting Payment | M47: x | N47: =IF(L47="",$B$4,L47) -> 46328
A48: 46322 | B48: Bill | C48: WLVRMZBY0012 | E48: Australian Tenders - WA core subscription Oct | G48: 90 | H48: 9 | I48: 99 | J48: 99 | K48: Awaiting Payment | M48: x | N48: =IF(L48="",$B$4,L48) -> 46328
A49: 46289 | B49: Bill | C49: INV260412412804 | E49: Energy Australia - electricity 23 Aug to 21 Sep | G49: 632.95 | H49: 63.3 | I49: 696.25 | J49: 696.25 | K49: Awaiting Payment | M49: x | N49: =IF(L49="",$B$4,L49) -> 46328
A50: 46315 | B50: Bill | C50: IT73569434492806 | E50: Expedia - accommodation J Salanoa, Ventia townhall | G50: 212.57 | H50: 21.26 | I50: 233.83 | J50: 233.83 | K50: Awaiting Payment | M50: x | N50: =IF(L50="",$B$4,L50) -> 46328
A51: 46315 | B51: Bill | C51: JGTOZQ | E51: Virgin Australia - return flight J Salanoa, Ventia townhall | G51: 650.91 | H51: 65.09 | I51: 716 | J51: 716 | K51: Awaiting Payment | M51: x | N51: =IF(L51="",$B$4,L51) -> 46328
A52: 46323 | B52: Bill | C52: INV1115.7 | E52: Google - YouTube Premium Oct | G52: 15.45 | H52: 1.54 | I52: 16.99 | J52: 16.99 | K52: Awaiting Payment | M52: x | N52: =IF(L52="",$B$4,L52) -> 46328
A53: 46313 | B53: Bill | C53: MC27578191 | E53: Mailchimp - October | G53: 38.54 | H53: 0 | I53: 38.54 | J53: 38.54 | K53: Awaiting Payment | M53: x | N53: =IF(L53="",$B$4,L53) -> 46328
A54: 46302 | B54: Bill | C54: INV000599871925 | E54: Optus - office internet & landline Oct | G54: 581.04 | H54: 58.11 | I54: 639.15 | J54: 639.15 | K54: Awaiting Payment | M54: x | N54: =IF(L54="",$B$4,L54) -> 46328
A55: 46316 | B55: Bill | C55: INV702171405 | E55: Seek - accounts assistant job ad | G55: 505 | H55: 50.5 | I55: 555.5 | J55: 555.5 | K55: Awaiting Payment | M55: x | N55: =IF(L55="",$B$4,L55) -> 46328
A56: 46323 | B56: Bill | C56: INV375651107 | E56: Zoom - Oct subscription | G56: 323.97 | H56: 0 | I56: 323.97 | J56: 323.97 | K56: Awaiting Payment | M56: x | N56: =IF(L56="",$B$4,L56) -> 46328
N57: =IF(L57="",$B$4,L57) -> 46328
A58: Rows 11 to 56 are the 46 open bills in Xero at 29 Oct ($158,464.01) typed in the report layout. Next month, clear them and paste the new report over the top. | N58: =IF(L58="",$B$4,L58) -> 46328
N59: =IF(L59="",$B$4,L59) -> 46328
N60: =IF(L60="",$B$4,L60) -> 46328
N61: =IF(L61="",$B$4,L61) -> 46328
N62: =IF(L62="",$B$4,L62) -> 46328
N63: =IF(L63="",$B$4,L63) -> 46328
N64: =IF(L64="",$B$4,L64) -> 46328
N65: =IF(L65="",$B$4,L65) -> 46328
N66: =IF(L66="",$B$4,L66) -> 46328
N67: =IF(L67="",$B$4,L67) -> 46328
N68: =IF(L68="",$B$4,L68) -> 46328
N69: =IF(L69="",$B$4,L69) -> 46328
N70: =IF(L70="",$B$4,L70) -> 46328
... N510: =IF(L510="",$B$4,L510) -> 46328

Sheet Complete AV
A1: Complete AV Solutions - INV41565 - what we paid and when
A2: Aware Super seminar room audio upgrade (Q-12140v1, PO-00016902). Bill total $178,119.25 inc GST, dated 1 Sep, due 26 Sep. Agreed 28 Sep (Graham / Jordan): pay the materials now, hold labour and programming until Aware sign off and we get the handover docs. Line items are straight off the bill in Xero. Update 12 Oct: the labour and programming that was held ($39,033.02) was released and paid Thu 8 Oct, so the whole bill is now paid. | G2: GC amounts Per Email received on the 29/09/2026
A4: Line on the bill | B4: Qty | C4: Unit (ex GST) | D4: Amount (ex GST) | E4: Notes | G4: Line | H4: Description | I4: CAV cost ex GST | J4: Claim 1 claimed | K4: GC verified | L4: Balance held
A5: Hardware | G5: CTS PO PO-00016902 | H5: Main PO 1 of 2 - seminar room audio upgrade | I5: 177457.98 | J5: 177457.98 | K5: 140320.33 | L5: 37137.65
A6: Crestron DM-NVX-E30 4K network AV encoder | B6: 6 | C6: 1345.56 | D6: =B6*C6 -> 8073.36 | G6: CTS PO PO-00016899 | H6: PO 2 of 2 - camera upgrade, not yet billed | I6: 17700.52 | J6: 0 | K6: 0 | L6: 0
A7: Crestron DM-NVX-385 AV-over-IP switcher | B7: 2 | C7: 3390.25 | D7: =B7*C7 -> 6780.5 | G7: CAV Vary 1.1 | H7: Removed Panasonic cameras & licences | I7: -7281.07 | J7: -7281.07 | K7: -7281.07 | L7: 0
A8: Crestron DM-NVX-360 encoder/decoder | B8: 8 | C8: 2144.14 | D8: =B8*C8 -> 17153.12 | G8: CAV Vary 1.2 | H8: RMB hardware added (mount kit) | I8: 321.5 | J8: 321.5 | K8: 321.5 | L8: 0
A9: Panasonic AW-UE40 4K integrated camera | B9: 4 | C9: 4063.96 | D9: =B9*C9 -> 16255.84 | G9: CAV Vary 1.3 | H9: Removed control processor (Crestron CP4N) | I9: -3032.23 | J9: -3032.23 | K9: -3032.23 | L9: 0
A10: Crestron UC-C100-T Teams Rooms integrator kit | B10: 2 | C10: 5350.41 | D10: =B10*C10 -> 10700.82 | G10: CAV Vary 1.4 | H10: Removed camera Crestron decoder | I10: -4600.2 | J10: -4600.2 | K10: -4600.2 | L10: 0
A11: Q-SYS Core 24f DSP | B11: 2 | C11: 8295.67 | D11: =B11*C11 -> 16591.34 | G11: CAV Vary 1.5 | H11: Rack cabling | I11: 691.6 | J11: 691.6 | K11: 0 | L11: 691.6
A12: Crestron DM-NAX Bluetooth audio wall plate | B12: 2 | C12: 815.49 | D12: =B12*C12 -> 1630.98 | G12: CAV Vary 1.6 | H12: Graphics card (card only verified) | I12: 2153.7 | J12: 2153.7 | K12: 713.7 | L12: 1440
A13: Crestron FP-G1-B-T face plate | B13: 2 | C13: 21 | D13: =B13*C13 -> 42 | G13: CAV Vary 1.7 | H13: Lighting integration programming | I13: 1064 | J13: 1064 | K13: 0 | L13: 1064
A14: Crestron TSS-880 room scheduling touch screen | B14: 2 | C14: 1223.23 | D14: =B14*C14 -> 2446.46 | G14: Total | I14: =SUM(I5:I13) -> 184475.8 | J14: =SUM(J5:J13) -> 166775.28 | K14: =SUM(K5:K13) -> 126442.03 | L14: =SUM(L5:L13) -> 40333.25
A15: Crestron TSW-1080 wall mount touch screen | B15: 2 | C15: 3186.38 | D15: =B15*C15 -> 6372.76 | K15: =K14-126442.03 -> -1.4551915e-11
A16: Crestron CP4N control system | B16: 1 | C16: 3032.23 | D16: =B16*C16 -> 3032.23
A17: Netgear M4250 PoE+ managed switch | B17: 2 | C17: 3179.58 | D17: =B17*C17 -> 6359.16 | K17: Amount to Pay | L17: Amount to Hold
A18: Netgear AXC761 SFP+ transceiver | B18: 2 | C18: 121.46 | D18: =B18*C18 -> 242.92 | G18: GST 10% | K18: =ROUND(K14*0.1,2) -> 12644.2 | L18: =ROUND(L14*0.1,2) -> 4033.33
A19: Crestron DM-NVX-E30 encoder (second batch) | B19: 2 | C19: 1517.06 | D19: =B19*C19 -> 3034.12 | G19: PAYING NOW (incl GST) | K19: =K14+K18 -> 139086.23 | L19: =L14+L18 -> 44366.58
A20: Panasonic AW-SF200Z auto tracking software | B20: 1 | C20: 2541.01 | D20: =B20*C20 -> 2541.01
A21: Panasonic AW-SF300Z visual preset software | B21: 1 | C21: 1921.47 | D21: =B21*C21 -> 1921.47 | G21: Xero Supplier Invoice Amount INV41565 ( Complete AV Solutions) | L21: =D59 -> 178119.25
A22: Panasonic AW-SF501Z auto framing software | B22: 1 | C22: 5309.33 | D22: =B22*C22 -> 5309.33 | G22: NOT YET BILLED - $4,848.68 ex GST / $5,333.55 inc GST. Complete AV's own "remaining claim balance to be invoiced" line on INV41565. Not in Xero yet, so not in the forecast. Will come as a new bill; add it to Payables when it lands. | L22: =SUM(K19:L19)-L21 -> 5333.56
A23: Precision Computers 4U rack-mount PC | B23: 1 | C23: 3883.95 | D23: =B23*C23 -> 3883.95
A24: Sennheiser TeamConnect Ceiling 2 mic | B24: 4 | C24: 5946.65 | D24: =B24*C24 -> 23786.6
A25: Q-SYS Dante 16x16 licence | B25: 1 | C25: 743.84 | D25: =B25*C25 -> 743.84
A26: Graphics card | B26: 1 | C26: 2153.7 | D26: =B26*C26 -> 2153.7
A27: RMB hardware added | B27: 1 | C27: 321.5 | D27: =B27*C27 -> 321.5
A28: Less: removed Panasonic cameras & licences | B28: 1 | C28: -7281.07 | D28: =B28*C28 -> -7281.07
A29: Less: removed control processor | B29: 1 | C29: -3032.23 | D29: =B29*C29 -> -3032.23
A30: Less: removed camera Crestron decoder | B30: 1 | C30: -4600.2 | D30: =B30*C30 -> -4600.2
A31: Hardware subtotal | D31: =SUM(D6:D30) -> 124463.51
A32: Consumables and delivery
A33: Cables, fixings and hardware (4 lines: $1,515.30 + $696.24 + $934.08 + $691.60) | D33: 3837.22
A34: Freight & handling (3 lines: $100.00 + $53.20 + $59.85) | D34: 213.05
A35: E-waste / waste management (3 lines: $59.85 + $39.90 + $19.95) | D35: 119.7
A36: Consumables subtotal | D36: =SUM(D33:D35) -> 4169.97
A40: Materials subtotal (ex GST) | D40: =D31+D36 -> 128633.48
A41: Less: Complete AV's own line 'Remaining claim balance $4,848.68 to be invoiced' | D41: -4848.68 | E41: Their reduction, not allocated to anything. Taken off the part we're paying now - conservative. If you'd rather take it off the held labour, pay $141,496.83 and hold $36,622.43.
A42: Materials net (ex GST) | D42: =D40+D41 -> 123784.8
A43: GST 10% | D43: =ROUND(D42*0.1,2) -> 12378.48
A44: PAYING NOW (incl GST) | D44: =D42+D43 -> 136163.28
A46: Pay on | D46: 46295
A48: LABOUR AND PROGRAMMING - was held, released and PAID Thu 8 Oct
A49: Labour & programming | D49: 23320
A50: Labour | D50: 7196
A51: Labour | D51: 6561.8
A52: Lighting integration programming (coded to equipment in Xero, but it's programming) | D52: 1064
A53: Held (ex GST) | D53: =SUM(D49:D52) -> 38141.8
A54: GST 10% | D54: =ROUND(D53*0.1,2) -> 3814.18
A55: HELD (incl GST) | D55: =D53+D54 -> 41955.98
A57: Check
A58: Paying now + held | D58: =D44+D55 -> 178119.26
A59: Bill total per Xero | D59: 178119.25
A60: Difference (rounding) | D60: =D58-D59 -> 0.01
