Workbook

Sheet Basis of Preparation
A1: Corporate Technology Services Pty Ltd
A2: Basis of Preparation
A3: Discretionary technology spend - FY2027 year to date (1 July 2026 to 31 August 2026)
A5: Entity | B5: Corporate Technology Services Pty Ltd.
A6: Reporting period | B6: 1 July 2026 to 31 August 2026. This is 2 months of the FY2027 financial year (1 July 2026 to 30 June 2027). Actual amounts in this report are for those 2 months only and are not annual figures.
A7: Source of actuals | B7: General ledger transaction export from Xero, being the same export used for the entity's monthly management reporting. The export covers 3,771 ledger lines for the period, of which 247 lines relate to the accounts within the scope of this report.
A8: Accounting basis | B8: Accrual. Amounts are exclusive of GST, consistent with the general ledger.
A9: Scope | B9: Seven general ledger accounts identified by management as discretionary technology spend, listed on the Summary schedule. No other accounts have been included, and no allocation, apportionment or estimate has been applied.
A10: Presentation of amounts | B10: The general ledger records amounts as credit less debit. Costs are therefore negative in the ledger and have been presented here as positive expenditure. Debit and credit as recorded are shown unchanged on the Transaction Listing so that each line can be agreed back to the ledger.
A11: Budget figures | B11: Budget amounts are management's FY2027 annual budget for each account, as provided. They are unaudited and are included for comparison only. The year-to-date budget shown is the annual budget apportioned evenly across twelve months and multiplied by 2; no seasonality has been applied.
A12: Completeness | B12: Every ledger line coded to the seven accounts in the period is listed on the Transaction Listing. No line has been excluded, summarised or netted. The Reconciliation schedule agrees the listing to the summary and to the ledger.
A13: Matters noted | B13: Two matters are disclosed on the Summary schedule: an arithmetic overstatement in the budget total as originally presented to us, and expenditure recorded without a supplier name. Both are described where they arise.
A14: Prepared | B14: Prepared from the general ledger export by the finance function. Figures are unaudited.

Sheet Summary
A1: Corporate Technology Services Pty Ltd
A2: Summary by account
A3: Discretionary technology spend - FY2027 year to date (1 July 2026 to 31 August 2026)
A5: Grouping | B5: General ledger account | C5: Annual budget FY2027 | D5: Budget 2 months | E5: Actual 2 months | F5: Variance | G5: Lines | H5: Annualised run rate | I5: Run rate vs budget
A6: Core technology | B6: IT Network Service & Support | C6: 149160 | D6: 24860 | E6: 30218.74 | F6: =E6-D6 -> 5358.74 | G6: 20 | H6: =E6/2*12 -> 181312.44 | I6: =IF(C6=0,"n/a",H6/C6-1) -> 0.21555672
A7: Core technology | B7: Dues & Subscriptions | C7: 86544 | D7: 14424 | E7: 20672.16 | F7: =E7-D7 -> 6248.16 | G7: 139 | H7: =E7/2*12 -> 124032.96 | I7: =IF(C7=0,"n/a",H7/C7-1) -> 0.43317804
A8: Core technology | B8: Instant Asset Write Off | C8: 60000 | D8: 10000 | E8: 5000 | F8: =E8-D8 -> -5000 | G8: 22 | H8: =E8/2*12 -> 30000 | I8: =IF(C8=0,"n/a",H8/C8-1) -> -0.5
A9: Telecommunications | B9: Internet | C9: 4814 | D9: 802.33 | E9: 727.64 | F9: =E9-D9 -> -74.69 | G9: 4 | H9: =E9/2*12 -> 4365.84 | I9: =IF(C9=0,"n/a",H9/C9-1) -> -0.093095139
A10: Telecommunications | B10: Mobile Phones | C10: 3300 | D10: 550 | E10: 1286.29 | F10: =E10-D10 -> 736.29 | G10: 53 | H10: =E10/2*12 -> 7717.74 | I10: =IF(C10=0,"n/a",H10/C10-1) -> 1.3387091
A11: Telecommunications | B11: Office Phones | C11: 2400 | D11: 400 | E11: 343.42 | F11: =E11-D11 -> -56.58 | G11: 3 | H11: =E11/2*12 -> 2060.52 | I11: =IF(C11=0,"n/a",H11/C11-1) -> -0.14145
A12: Telecommunications | B12: 1300 Number | C12: 780 | D12: 130 | E12: 171.33 | F12: =E12-D12 -> 41.33 | G12: 6 | H12: =E12/2*12 -> 1027.98 | I12: =IF(C12=0,"n/a",H12/C12-1) -> 0.31792308
B13: Subtotal - core technology | C13: =C6+C7+C8 -> 295704 | D13: =D6+D7+D8 -> 49284 | E13: =E6+E7+E8 -> 55890.9 | F13: =F6+F7+F8 -> 6606.9 | G13: =G6+G7+G8 -> 181 | H13: =H6+H7+H8 -> 335345.4 | I13: =IF(C13=0,"n/a",H13/C13-1) -> 0.13405771
B14: Subtotal - telecommunications | C14: =C9+C10+C11+C12 -> 11294 | D14: =D9+D10+D11+D12 -> 1882.33 | E14: =E9+E10+E11+E12 -> 2528.68 | F14: =F9+F10+F11+F12 -> 646.35 | G14: =G9+G10+G11+G12 -> 66 | H14: =H9+H10+H11+H12 -> 15172.08 | I14: =IF(C14=0,"n/a",H14/C14-1) -> 0.34337524
B15: Total discretionary technology spend | C15: =C13+C14 -> 306998 | D15: =D13+D14 -> 51166.33 | E15: =E13+E14 -> 58419.58 | F15: =F13+F14 -> 7253.25 | G15: =G13+G14 -> 247 | H15: =H13+H14 -> 350517.48 | I15: =IF(C15=0,"n/a",H15/C15-1) -> 0.14175819
A17: Note 1 - budget total | B17: The budget schedule provided to us showed a total of $602,702. That figure adds a 'standard' subtotal of $295,704 (the three core technology accounts) to a 'broad' subtotal of $306,998, where the broad subtotal already contains the standard subtotal. The three core accounts are therefore counted twice and the total is overstated by $295,704. The annual budget for the seven accounts, each counted once, is $306,998 as shown above.
A18: Note 2 - expenditure with no supplier recorded | B18: $9,568.78 of the expenditure in the period, being 16.4% of the total, is recorded on ledger lines that carry no contact or supplier name. These lines are listed in full on the Transaction Listing and are shown as a separate line on the Supplier Analysis schedule.
A19: Note 3 - supplier concentration | B19: One supplier, First Focus IT Pty Ltd, accounts for $37,799.82 of expenditure in the period, being 64.7% of the total. That expenditure is recorded across two accounts, IT Network Service & Support and Dues & Subscriptions. See the Supplier Analysis schedule.
A20: Note 4 - period covered | B20: These figures cover July and August only, which is 2 months of a twelve month year. The annualised run rate column takes what has been spent so far, divides it by 2 and multiplies by twelve, so it assumes the rest of the year looks like the first 2 months. It makes no allowance for quieter or busier periods, for annual renewals that fall due later in the year, or for spending already committed but not yet incurred. Treat it as a rough indicator, not a forecast.

Sheet Supplier Analysis
A1: Corporate Technology Services Pty Ltd
A2: Supplier analysis
A3: Discretionary technology spend - FY2027 year to date (1 July 2026 to 31 August 2026) - use the + and - buttons in the left margin to open a supplier down to its ledger lines
A5: Supplier / account / transaction date | B5: Amount | C5: % of total | D5: Lines | E5: Description | F5: Invoice no. | G5: Reference | H5: Job number | I5: Cost centre | J5: Source
A6: First Focus IT Pty Ltd | B6: =B7+B28 -> 37799.82 | C6: =B6/$B$326 -> 0.64704026 | D6: 43
A7: IT Network Service & Support | B7: =B8+B9+B10+B11+B12+B13+B14+B15+B16+B17+B18+B19+B20+B21+B22+B23+B24+B25+B26+B27 -> 30218.74 | D7: 20
A8: 46204 | B8: 9953 | E8: First Focus IT Pty Ltd - CORE Intelligent Managed Services | F8: INV167160 - MSA: CORE Intelligent Managed Services: CORE Intelligent Managed Services July 2026 [paid via DD] To recieve credits for the interest charged | G8: INV167160 - MSA: CORE Intelligent Managed Services: CORE Intelligent Managed Services July 2026 [paid via DD] To recieve credits for the interest charged | H8: 9000 - OFFICE / ADMIN [CTS] | I8: CTS | J8: Payable Invoice
A9: 46204 | B9: 403.5 | E9: First Focus IT Pty Ltd - CORE Intelligent Managed Services Email Only User 75% discount | F9: INV167160 - MSA: CORE Intelligent Managed Services: CORE Intelligent Managed Services July 2026 [paid via DD] To recieve credits for the interest charged | G9: INV167160 - MSA: CORE Intelligent Managed Services: CORE Intelligent Managed Services July 2026 [paid via DD] To recieve credits for the interest charged | H9: 9000 - OFFICE / ADMIN [CTS] | I9: CTS | J9: Payable Invoice
A10: 46204 | B10: 1247 | E10: First Focus IT Pty Ltd - CORE - Hatz AI Multi-LLM Platform | F10: INV167160 - MSA: CORE Intelligent Managed Services: CORE Intelligent Managed Services July 2026 [paid via DD] To recieve credits for the interest charged | G10: INV167160 - MSA: CORE Intelligent Managed Services: CORE Intelligent Managed Services July 2026 [paid via DD] To recieve credits for the interest charged | H10: 9000 - OFFICE / ADMIN [CTS] | I10: CTS | J10: Payable Invoice
A11: 46204 | B11: -430 | E11: First Focus IT Pty Ltd - CORE Early Sign Up Discount Hatz (12 month) | F11: INV167160 - MSA: CORE Intelligent Managed Services: CORE Intelligent Managed Services July 2026 [paid via DD] To recieve credits for the interest charged | G11: INV167160 - MSA: CORE Intelligent Managed Services: CORE Intelligent Managed Services July 2026 [paid via DD] To recieve credits for the interest charged | H11: 9000 - OFFICE / ADMIN [CTS] | I11: CTS | J11: Payable Invoice
A12: 46204 | B12: 100 | E12: First Focus IT Pty Ltd - DMARC Email Security Management: Per Domain | F12: INV167160 - MSA: CORE Intelligent Managed Services: CORE Intelligent Managed Services July 2026 [paid via DD] To recieve credits for the interest charged | G12: INV167160 - MSA: CORE Intelligent Managed Services: CORE Intelligent Managed Services July 2026 [paid via DD] To recieve credits for the interest charged | H12: 9000 - OFFICE / ADMIN [CTS] | I12: CTS | J12: Payable Invoice
A13: 46204 | B13: 325 | E13: First Focus IT Pty Ltd - Managed SD-WAN Firewall (1Gbps max) | F13: INV167160 - MSA: CORE Intelligent Managed Services: CORE Intelligent Managed Services July 2026 [paid via DD] To recieve credits for the interest charged | G13: INV167160 - MSA: CORE Intelligent Managed Services: CORE Intelligent Managed Services July 2026 [paid via DD] To recieve credits for the interest charged | H13: 9000 - OFFICE / ADMIN [CTS] | I13: CTS | J13: Payable Invoice
A14: 46204 | B14: 28.8 | E14: First Focus IT Pty Ltd - Exchange Online (Plan 1) (NCE COM 1MTH) Serial Number(s): S365L | F14: INV167160 - MSA: CORE Intelligent Managed Services: CORE Intelligent Managed Services July 2026 [paid via DD] To recieve credits for the interest charged | G14: INV167160 - MSA: CORE Intelligent Managed Services: CORE Intelligent Managed Services July 2026 [paid via DD] To recieve credits for the interest charged | H14: 9000 - OFFICE / ADMIN [CTS] | I14: CTS | J14: Payable Invoice
A15: 46204 | B15: 198.58 | E15: First Focus IT Pty Ltd - Interest on late payments 162027 164522 162627 (To be credited) | F15: INV167160 - MSA: CORE Intelligent Managed Services: CORE Intelligent Managed Services July 2026 [paid via DD] To recieve credits for the interest charged | G15: INV167160 - MSA: CORE Intelligent Managed Services: CORE Intelligent Managed Services July 2026 [paid via DD] To recieve credits for the interest charged | H15: 9000 - OFFICE / ADMIN [CTS] | I15: CTS | J15: Payable Invoice
A16: 46219 | B16: -198.58 | E16: First Focus IT Pty Ltd - Interest on late payments 162027 164522 162627 | F16: INV168824 - Interest Charges on INV167160 for May 2026 invoices (to apply in August invoice) | G16: INV168824 - Interest Charges on INV167160 for May 2026 invoices (to apply in August invoice) | H16: 9000 - OFFICE / ADMIN [CTS] | I16: CTS | J16: Payable Credit Note
A17: 46234 | B17: 18325.73 | E17: First Focus IT Pty Ltd - Fixed Fee Project | F17: INV171598 - Completion of CORE Intelligent Managed Services One-Time Project - Balance Fee [PO-00016880] pay via EFT | G17: INV171598 - Completion of CORE Intelligent Managed Services One-Time Project - Balance Fee [PO-00016880] pay via EFT | H17: 9000 - OFFICE / ADMIN [CTS] | I17: CTS | J17: Payable Invoice
A18: 46234 | B18: -7330.29 | E18: First Focus IT Pty Ltd - CORE Early Sign Up Discount At cost transitions project Offer valid for agreements signed prior to 15/04 | F18: INV171598 - Completion of CORE Intelligent Managed Services One-Time Project - Balance Fee [PO-00016880] pay via EFT | G18: INV171598 - Completion of CORE Intelligent Managed Services One-Time Project - Balance Fee [PO-00016880] pay via EFT | H18: 9000 - OFFICE / ADMIN [CTS] | I18: CTS | J18: Payable Invoice
A19: 46234 | B19: -2451 | E19: First Focus IT Pty Ltd - CORE Early Sign Up Discount Hatz | F19: INV171598 - Completion of CORE Intelligent Managed Services One-Time Project - Balance Fee [PO-00016880] pay via EFT | G19: INV171598 - Completion of CORE Intelligent Managed Services One-Time Project - Balance Fee [PO-00016880] pay via EFT | H19: 9000 - OFFICE / ADMIN [CTS] | I19: CTS | J19: Payable Invoice
... A27: 46237 | B27: 609.7 | E27: First Focus IT Pty Ltd - Replacement for NAS Hard Drive Seagate IronWolf 8 TB Hard Drive - 3.5" Internal - SATA (SATA/600) - 7200rpm 256 MB Buffer - 3 Year Warranty | F27: INV170542 - Replacement for NAS Hard Drive [Q-034252v1 - PO-00016911] GC App (Pay by EFT) | G27: INV170542 - Replacement for NAS Hard Drive [Q-034252v1 - PO-00016911] GC App (Pay by EFT) | H27: 9000 - OFFICE / ADMIN [CTS] | I27: CTS | J27: Payable Invoice
A28: Dues & Subscriptions | B28: =B29+B30+B31+B32+B33+B34+B35+B36+B37+B38+B39+B40+B41+B42+B43+B44+B45+B46+B47+B48+B49+B50+B51 -> 7581.08 | D28: 23
A29: 46204 | B29: 616.89 | E29: First Focus IT Pty Ltd - Microsoft Azure Consumption | F29: INV168585: MSA: Managed Services: Managed Services - Azure July 2026 [paid via DD] | G29: INV168585: MSA: Managed Services: Managed Services - Azure July 2026 [paid via DD] | H29: 9000 - OFFICE / ADMIN [CTS] | I29: CTS | J29: Payable Invoice
A30: 46204 | B30: 79.92 | E30: First Focus IT Pty Ltd - Exchange Online (Plan 2) (NCE COM 1MTH) Serial Number(s): S365L | F30: INV167160 - MSA: CORE Intelligent Managed Services: CORE Intelligent Managed Services July 2026 [paid via DD] To recieve credits for the interest charged | G30: INV167160 - MSA: CORE Intelligent Managed Services: CORE Intelligent Managed Services July 2026 [paid via DD] To recieve credits for the interest charged | H30: 9000 - OFFICE / ADMIN [CTS] | I30: CTS | J30: Payable Invoice
A31: 46204 | B31: 57.6 | E31: First Focus IT Pty Ltd - Microsoft Defender for Office 365 (Plan 1) (NCE COM 1MTH) | F31: INV167160 - MSA: CORE Intelligent Managed Services: CORE Intelligent Managed Services July 2026 [paid via DD] To recieve credits for the interest charged | G31: INV167160 - MSA: CORE Intelligent Managed Services: CORE Intelligent Managed Services July 2026 [paid via DD] To recieve credits for the interest charged | H31: 9000 - OFFICE / ADMIN [CTS] | I31: CTS | J31: Payable Invoice
A32: 46204 | B32: 9 | E32: First Focus IT Pty Ltd - Microsoft Defender for Office 365 (Plan 2) (NCE COM 1MTH) | F32: INV167160 - MSA: CORE Intelligent Managed Services: CORE Intelligent Managed Services July 2026 [paid via DD] To recieve credits for the interest charged | G32: INV167160 - MSA: CORE Intelligent Managed Services: CORE Intelligent Managed Services July 2026 [paid via DD] To recieve credits for the interest charged | H32: 9000 - OFFICE / ADMIN [CTS] | I32: CTS | J32: Payable Invoice
A33: 46204 | B33: 917.28 | E33: First Focus IT Pty Ltd - Office 365 Extra File Storage (NCE Product) (NCE COM 1MTH | F33: INV167160 - MSA: CORE Intelligent Managed Services: CORE Intelligent Managed Services July 2026 [paid via DD] To recieve credits for the interest charged | G33: INV167160 - MSA: CORE Intelligent Managed Services: CORE Intelligent Managed Services July 2026 [paid via DD] To recieve credits for the interest charged | H33: 9000 - OFFICE / ADMIN [CTS] | I33: CTS | J33: Payable Invoice
A34: 46204 | B34: 104.1 | E34: First Focus IT Pty Ltd - Planner and Project Plan 3 (NCE COM 1MTH) Serial Number(s): S365L | F34: INV167160 - MSA: CORE Intelligent Managed Services: CORE Intelligent Managed Services July 2026 [paid via DD] To recieve credits for the interest charged | G34: INV167160 - MSA: CORE Intelligent Managed Services: CORE Intelligent Managed Services July 2026 [paid via DD] To recieve credits for the interest charged | H34: 9000 - OFFICE / ADMIN [CTS] | I34: CTS | J34: Payable Invoice
A35: 46204 | B35: 215.04 | E35: First Focus IT Pty Ltd - Visio Plan 2 (NCE COM 1MTH) Serial Number(s): S365L | F35: INV167160 - MSA: CORE Intelligent Managed Services: CORE Intelligent Managed Services July 2026 [paid via DD] To recieve credits for the interest charged | G35: INV167160 - MSA: CORE Intelligent Managed Services: CORE Intelligent Managed Services July 2026 [paid via DD] To recieve credits for the interest charged | H35: 9000 - OFFICE / ADMIN [CTS] | I35: CTS | J35: Payable Invoice
A36: 46204 | B36: 157.12 | E36: First Focus IT Pty Ltd - Microsoft 365 Business Standard (NCE COM 1YR MTH) Serial Number(s): S365L | F36: INV167160 - MSA: CORE Intelligent Managed Services: CORE Intelligent Managed Services July 2026 [paid via DD] To recieve credits for the interest charged | G36: INV167160 - MSA: CORE Intelligent Managed Services: CORE Intelligent Managed Services July 2026 [paid via DD] To recieve credits for the interest charged | H36: 9000 - OFFICE / ADMIN [CTS] | I36: CTS | J36: Payable Invoice
A37: 46204 | B37: 274.05 | E37: First Focus IT Pty Ltd - Microsoft 365 Business Basic (NCE COM 1YR MTH) Serial Number(s): S365L | F37: INV167160 - MSA: CORE Intelligent Managed Services: CORE Intelligent Managed Services July 2026 [paid via DD] To recieve credits for the interest charged | G37: INV167160 - MSA: CORE Intelligent Managed Services: CORE Intelligent Managed Services July 2026 [paid via DD] To recieve credits for the interest charged | H37: 9000 - OFFICE / ADMIN [CTS] | I37: CTS | J37: Payable Invoice
A38: 46204 | B38: 1071.05 | E38: First Focus IT Pty Ltd - Microsoft 365 Business Premium (NCE COM 1YR MTH) Serial Number(s): S365L | F38: INV167160 - MSA: CORE Intelligent Managed Services: CORE Intelligent Managed Services July 2026 [paid via DD] To recieve credits for the interest charged | G38: INV167160 - MSA: CORE Intelligent Managed Services: CORE Intelligent Managed Services July 2026 [paid via DD] To recieve credits for the interest charged | H38: 9000 - OFFICE / ADMIN [CTS] | I38: CTS | J38: Payable Invoice
A39: 46204 | B39: 15.76 | E39: First Focus IT Pty Ltd - Microsoft 365 Business Basic (NCE COM 1YR MTH) This item has been prorated with a start date of: 06/06/2026 | F39: INV167160 - MSA: CORE Intelligent Managed Services: CORE Intelligent Managed Services July 2026 [paid via DD] To recieve credits for the interest charged | G39: INV167160 - MSA: CORE Intelligent Managed Services: CORE Intelligent Managed Services July 2026 [paid via DD] To recieve credits for the interest charged | H39: 9000 - OFFICE / ADMIN [CTS] | I39: CTS | J39: Payable Invoice
A40: 46204 | B40: 265.36 | E40: First Focus IT Pty Ltd - Datto SAAS Protection for Microsoft 365 (CSP COM 3YR MTH) | F40: INV167160 - MSA: CORE Intelligent Managed Services: CORE Intelligent Managed Services July 2026 [paid via DD] To recieve credits for the interest charged | G40: INV167160 - MSA: CORE Intelligent Managed Services: CORE Intelligent Managed Services July 2026 [paid via DD] To recieve credits for the interest charged | H40: 9000 - OFFICE / ADMIN [CTS] | I40: CTS | J40: Payable Invoice
... A51: 46235 | B51: 265.36 | E51: First Focus IT Pty Ltd - Datto SAAS Protection for Microsoft 365 (CSP COM 3YR MTH) | F51: INV170755 - MSA: CORE Intelligent Managed Services: CORE Intelligent Managed Services August 2026 [paid via DD] | G51: INV170755 - MSA: CORE Intelligent Managed Services: CORE Intelligent Managed Services August 2026 [paid via DD] | H51: 9000 - OFFICE / ADMIN [CTS] | I51: CTS | J51: Payable Invoice
A52: (no supplier name recorded on the ledger line) | B52: =B53+B108 -> 9568.78 | C52: =B52/$B$326 -> 0.16379406 | D52: 56
A53: Dues & Subscriptions | B53: =B54+B55+B56+B57+B58+B59+B60+B61+B62+B63+B64+B65+B66+B67+B68+B69+B70+B71+B72+B73+B74+B75+B76+B77+B78+B79+B80+B81+B82+B83+B84+B85+B86+B87+B88+B89+B90+B91+B92+B93+B94+B95+B96+B97+B98+B99+B100+B101+B102+B103+B104+B105+B106+B107 -> 9876.52 | D53: 54
A54: 46234 | B54: 38.75 | E54: Prepayments July 2026 - Inv6115846AA|27/03|Dicker Data| | G54: #69222 | H54: 2910 - Office Move 2024 [CTS] | I54: CTS | J54: Manual Journal
A55: 46234 | B55: 12.5 | E55: Prepayments July 2026 - Inv58586033|10/02|Crazy Domains (website renewal)| | G55: #69222 | H55: 9350 - MARKETING (external) [CTS] | I55: CTS | J55: Manual Journal
A56: 46234 | B56: 35.36 | E56: Prepayments July 2026 - Inv1753767723|29/07|Webflow.com| | G56: #69222 | H56: 9350 - MARKETING (external) [CTS] | I56: CTS | J56: Manual Journal
A57: 46234 | B57: 348.89 | E57: Prepayments July 2026 - Inv415083|06/08|PigeonLab Pte Ltd| | G57: #69222 | H57: 9100 - PRODUCTION [PRD] | I57: PRODUCTION | J57: Manual Journal
A58: 46234 | B58: 38.59 | E58: Prepayments July 2026 - Inv88AD1D8F-0004|15/08|Plumsail Inc| | G58: #69222 | H58: 9100 - PRODUCTION [PRD] | I58: PRODUCTION | J58: Manual Journal
A59: 46234 | B59: 530 | E59: Prepayments July 2026 - Inv51110652883|01/09|Linkedin Singapore| | G59: #69222 | H59: 9300 - HUMAN RESOURCES [CTS] | I59: CTS | J59: Manual Journal
A60: 46234 | B60: 44.28 | E60: Prepayments July 2026 - Inv721699|22/09|Qantas Airways Limited| | G60: #69222 | H60: 3059 - CBA AGM 2025 [PRD] | I60: PRODUCTION | J60: Manual Journal
A61: 46234 | B61: 44.33 | E61: Prepayments July 2026 - Inv356325|08/09|AddEvent Inc| | G61: #69222 | H61: 9100 - PRODUCTION [PRD] | I61: PRODUCTION | J61: Manual Journal
A62: 46234 | B62: 79.75 | E62: Prepayments July 2026 - Inv50BB48DA-0011|06/10|Qwilr Pty Ltd| | G62: #69222 | H62: 9105 - ONSITE (including PROD backup) | I62: ONSITE | J62: Manual Journal
A63: 46234 | B63: 39.88 | E63: Prepayments July 2026 - Inv50BB48DA-0011|06/10|Qwilr Pty Ltd| | G63: #69222 | H63: 9200 - INTEGRATION [INT] | I63: INTEGRATION | J63: Manual Journal
A64: 46234 | B64: 39.88 | E64: Prepayments July 2026 - Inv50BB48DA-0011|06/10|Qwilr Pty Ltd| | G64: #69222 | H64: 9400 - CONSULTING [CONS] | I64: CONSULTING | J64: Manual Journal
A65: 46234 | B65: 237.5 | E65: Prepayments July 2026 - Inv3435939|11/11|AVIXA (Formerly InfoComm International)| | G65: #69222 | H65: 9000 - OFFICE / ADMIN [CTS] | I65: CTS | J65: Manual Journal
... A106: 46265 | B106: 700 | E106: Prepayments August 2026 - InvINV137220 |01/08|The CEO Institute (JS)| | G106: #70417 | H106: 9000 - OFFICE / ADMIN [CTS] | I106: CTS | J106: Manual Journal
A107: 46265 | B107: 0.9 | E107: Expense Plumsail residual - net position under the $300 prepayment threshold - Rounding Variance - Expense Plumsail residual - net position under the $300 prepayment threshold | G107: #70435 | I107: PRODUCTION | J107: Manual Journal
A108: Instant Asset Write Off | B108: =B109+B110 -> -307.74 | D108: 2
A109: 46234 | B109: 3910.91 | E109: Expense Accrual July 2026 - Instant Asset Write Off | G109: #69405 | H109: 9000 - OFFICE / ADMIN [CTS] | I109: CTS | J109: Manual Journal
A110: 46265 | B110: -4218.65 | E110: Expense Accrual August 2026 - Instant Asset Write Off | G110: #70416 | H110: 9000 - OFFICE / ADMIN [CTS] | I110: CTS | J110: Manual Journal
A111: Optus Billing Services Pty Ltd | B111: =B112+B158+B163+B167 -> 2208.68 | C111: =B111/$B$326 -> 0.037807187 | D111: 58
A112: Mobile Phones | B112: =B113+B114+B115+B116+B117+B118+B119+B120+B121+B122+B123+B124+B125+B126+B127+B128+B129+B130+B131+B132+B133+B134+B135+B136+B137+B138+B139+B140+B141+B142+B143+B144+B145+B146+B147+B148+B149+B150+B151+B152+B153+B154+B155+B156+B157 -> 966.29 | D112: 45
A113: 46210 | B113: 31.35 | E113: Optus Billing Services Pty Ltd - 0488287111 - Mitchell Healey (PRD Manager) | F113: INV000583847765 - Office Internet and Phone Service Charges July 2026 [paid via PL CC] | G113: INV000583847765 - Office Internet and Phone Service Charges July 2026 [paid via PL CC] | H113: 9100 - PRODUCTION [PRD] | I113: PRODUCTION | J113: Payable Invoice
A114: 46210 | B114: 31.35 | E114: Optus Billing Services Pty Ltd - 0417669001 - Duncan Lugstein (MD) | F114: INV000583847765 - Office Internet and Phone Service Charges July 2026 [paid via PL CC] | G114: INV000583847765 - Office Internet and Phone Service Charges July 2026 [paid via PL CC] | H114: 9000 - OFFICE / ADMIN [CTS] | I114: CTS | J114: Payable Invoice
A115: 46210 | B115: 31.35 | E115: Optus Billing Services Pty Ltd - 0488287000 - Tyler Wood (Events Op Manager) | F115: INV000583847765 - Office Internet and Phone Service Charges July 2026 [paid via PL CC] | G115: INV000583847765 - Office Internet and Phone Service Charges July 2026 [paid via PL CC] | H115: 9100 - PRODUCTION [PRD] | I115: PRODUCTION | J115: Payable Invoice
A116: 46210 | B116: 31.35 | E116: Optus Billing Services Pty Ltd - 0488287777 - Graham Cherry | F116: INV000583847765 - Office Internet and Phone Service Charges July 2026 [paid via PL CC] | G116: INV000583847765 - Office Internet and Phone Service Charges July 2026 [paid via PL CC] | H116: 9000 - OFFICE / ADMIN [CTS] | I116: CTS | J116: Payable Invoice
A117: 46210 | B117: 31.35 | E117: Optus Billing Services Pty Ltd - 0488287092 - Rob Mahood (Gen-E Onsite) | F117: INV000583847765 - Office Internet and Phone Service Charges July 2026 [paid via PL CC] | G117: INV000583847765 - Office Internet and Phone Service Charges July 2026 [paid via PL CC] | H117: 26021602 - Gen E ABS AV Support (Canberra) [ONS] | I117: ONSITE | J117: Payable Invoice
A118: 46210 | B118: 31.35 | E118: Optus Billing Services Pty Ltd - 0488688446 - Available but Locked Handset (HR Manager) | F118: INV000583847765 - Office Internet and Phone Service Charges July 2026 [paid via PL CC] | G118: INV000583847765 - Office Internet and Phone Service Charges July 2026 [paid via PL CC] | H118: 9300 - HUMAN RESOURCES [CTS] | I118: CTS | J118: Payable Invoice
A119: 46210 | B119: 31.35 | E119: Optus Billing Services Pty Ltd - 0488287280 - Daniel Sobkowski (CONS) | F119: INV000583847765 - Office Internet and Phone Service Charges July 2026 [paid via PL CC] | G119: INV000583847765 - Office Internet and Phone Service Charges July 2026 [paid via PL CC] | H119: 9200 - INTEGRATION [INT] | I119: INTEGRATION | J119: Payable Invoice
A120: 46210 | B120: 31.35 | E120: Optus Billing Services Pty Ltd - 0401365435 - CTS Tech 1 (In Bluekeeper Kit 2) | F120: INV000583847765 - Office Internet and Phone Service Charges July 2026 [paid via PL CC] | G120: INV000583847765 - Office Internet and Phone Service Charges July 2026 [paid via PL CC] | H120: 9100 - PRODUCTION [PRD] | I120: PRODUCTION | J120: Payable Invoice
A121: 46210 | B121: 31.35 | E121: Optus Billing Services Pty Ltd - 0401851589 - Jordan Sexty (GM) | F121: INV000583847765 - Office Internet and Phone Service Charges July 2026 [paid via PL CC] | G121: INV000583847765 - Office Internet and Phone Service Charges July 2026 [paid via PL CC] | H121: 9000 - OFFICE / ADMIN [CTS] | I121: CTS | J121: Payable Invoice
A122: 46210 | B122: 31.35 | E122: Optus Billing Services Pty Ltd - 0411840340 - (CONS Manager) | F122: INV000583847765 - Office Internet and Phone Service Charges July 2026 [paid via PL CC] | G122: INV000583847765 - Office Internet and Phone Service Charges July 2026 [paid via PL CC] | H122: 9400 - CONSULTING [CONS] | I122: CONSULTING | J122: Payable Invoice
A123: 46210 | B123: 140.44 | E123: Optus Billing Services Pty Ltd - 0402849950 - Premila Lugstein (ACC) | F123: INV000583847765 - Office Internet and Phone Service Charges July 2026 [paid via PL CC] | G123: INV000583847765 - Office Internet and Phone Service Charges July 2026 [paid via PL CC] | H123: 9000 - OFFICE / ADMIN [CTS] | I123: CTS | J123: Payable Invoice
A124: 46210 | B124: 31.35 | E124: Optus Billing Services Pty Ltd - 0481100557 - CTS Tech 2 (In Bluekeeper Kit 1) | F124: INV000583847765 - Office Internet and Phone Service Charges July 2026 [paid via PL CC] | G124: INV000583847765 - Office Internet and Phone Service Charges July 2026 [paid via PL CC] | H124: 9000 - OFFICE / ADMIN [CTS] | I124: CTS | J124: Payable Invoice
... A157: 46245 | B157: 0.3 | E157: Optus Billing Services Pty Ltd - Usage Charges | F157: INV000589831435 - Office Internet and Phone Service Charges August 2026 [paid via PL CC] | G157: INV000589831435 - Office Internet and Phone Service Charges August 2026 [paid via PL CC] | H157: 9100 - PRODUCTION [PRD] | I157: PRODUCTION | J157: Payable Invoice
A158: Internet | B158: =B159+B160+B161+B162 -> 727.64 | D158: 4
A159: 46209 | B159: 92 | E159: Optus Billing Services Pty Ltd - Lugstein on Internet Everyday Fast | F159: INV000583618957 - Lugstein Home Internet July 2026 | G159: INV000583618957 - Lugstein Home Internet July 2026 | H159: 9000 - OFFICE / ADMIN [CTS] | I159: CTS | J159: Payable Invoice
A160: 46210 | B160: 271.82 | E160: Optus Billing Services Pty Ltd - Evolve Internet RC - Unlimited | F160: INV000583847765 - Office Internet and Phone Service Charges July 2026 [paid via PL CC] | G160: INV000583847765 - Office Internet and Phone Service Charges July 2026 [paid via PL CC] | H160: 9000 - OFFICE / ADMIN [CTS] | I160: CTS | J160: Payable Invoice
A161: 46240 | B161: 92 | E161: Optus Billing Services Pty Ltd - Lugstein on Internet Everyday Fast | F161: INV000589011323 - Lugstein Home Internet August 2026 [BPAY] | G161: INV000589011323 - Lugstein Home Internet August 2026 [BPAY] | H161: 9000 - OFFICE / ADMIN [CTS] | I161: CTS | J161: Payable Invoice
A162: 46241 | B162: 271.82 | E162: Optus Billing Services Pty Ltd - Evolve Internet RC - Unlimited | F162: INV000589213447 - Office Internet and Phone Service Charges August 2026 [paid via PL CC] | G162: INV000589213447 - Office Internet and Phone Service Charges August 2026 [paid via PL CC] | H162: 9000 - OFFICE / ADMIN [CTS] | I162: CTS | J162: Payable Invoice
A163: Office Phones | B163: =B164+B165+B166 -> 343.42 | D163: 3
A164: 46210 | B164: 1.31 | E164: Optus Billing Services Pty Ltd - Evolve Voice Number Extensions - PAYG | F164: INV000583847765 - Office Internet and Phone Service Charges July 2026 [paid via PL CC] | G164: INV000583847765 - Office Internet and Phone Service Charges July 2026 [paid via PL CC] | H164: 9000 - OFFICE / ADMIN [CTS] | I164: CTS | J164: Payable Invoice
A165: 46210 | B165: 170.4 | E165: Optus Billing Services Pty Ltd - Evolve Voice | F165: INV000583847765 - Office Internet and Phone Service Charges July 2026 [paid via PL CC] | G165: INV000583847765 - Office Internet and Phone Service Charges July 2026 [paid via PL CC] | H165: 9000 - OFFICE / ADMIN [CTS] | I165: CTS | J165: Payable Invoice
A166: 46241 | B166: 171.71 | E166: Optus Billing Services Pty Ltd - Evolve Voice | F166: INV000589213447 - Office Internet and Phone Service Charges August 2026 [paid via PL CC] | G166: INV000589213447 - Office Internet and Phone Service Charges August 2026 [paid via PL CC] | H166: 9000 - OFFICE / ADMIN [CTS] | I166: CTS | J166: Payable Invoice
A167: 1300 Number | B167: =B168+B169+B170+B171+B172+B173 -> 171.33 | D167: 6
A168: 46210 | B168: 26.29 | E168: Optus Billing Services Pty Ltd - 1300 283 247 | F168: INV000583847765 - Office Internet and Phone Service Charges July 2026 [paid via PL CC] | G168: INV000583847765 - Office Internet and Phone Service Charges July 2026 [paid via PL CC] | H168: 9000 - OFFICE / ADMIN [CTS] | I168: CTS | J168: Payable Invoice
A169: 46210 | B169: 25.85 | E169: Optus Billing Services Pty Ltd - 1300 388 528 (DTTL Phone) | F169: INV000583847765 - Office Internet and Phone Service Charges July 2026 [paid via PL CC] | G169: INV000583847765 - Office Internet and Phone Service Charges July 2026 [paid via PL CC] | H169: 974 - DTTL 1300 Number [ONS] | I169: ONSITE | J169: Payable Invoice
A170: 46210 | B170: 28.95 | E170: Optus Billing Services Pty Ltd - 1800 225 528 | F170: INV000583847765 - Office Internet and Phone Service Charges July 2026 [paid via PL CC] | G170: INV000583847765 - Office Internet and Phone Service Charges July 2026 [paid via PL CC] | H170: 9000 - OFFICE / ADMIN [CTS] | I170: CTS | J170: Payable Invoice
A171: 46241 | B171: 26.31 | E171: Optus Billing Services Pty Ltd - 1300 283 247 | F171: INV000589213447 - Office Internet and Phone Service Charges August 2026 [paid via PL CC] | G171: INV000589213447 - Office Internet and Phone Service Charges August 2026 [paid via PL CC] | H171: 9000 - OFFICE / ADMIN [CTS] | I171: CTS | J171: Payable Invoice
A172: 46241 | B172: 25.71 | E172: Optus Billing Services Pty Ltd - 1300 388 528 (DTTL Phone) | F172: INV000589213447 - Office Internet and Phone Service Charges August 2026 [paid via PL CC] | G172: INV000589213447 - Office Internet and Phone Service Charges August 2026 [paid via PL CC] | H172: 974 - DTTL 1300 Number [ONS] | I172: ONSITE | J172: Payable Invoice
A173: 46241 | B173: 38.22 | E173: Optus Billing Services Pty Ltd - 1800 225 528 | F173: INV000589213447 - Office Internet and Phone Service Charges August 2026 [paid via PL CC] | G173: INV000589213447 - Office Internet and Phone Service Charges August 2026 [paid via PL CC] | H173: 9000 - OFFICE / ADMIN [CTS] | I173: CTS | J173: Payable Invoice
A174: Officeworks Superstores Pty Ltd | B174: =B175 -> 1256.36 | C174: =B174/$B$326 -> 0.021505803 | D174: 2
A175: Instant Asset Write Off | B175: =B176+B177 -> 1256.36 | D175: 2
A176: 46234 | B176: 1089.09 | E176: Officeworks Superstores Pty Ltd - SAMSUNG 2TB T7 SSD GY | F176: INV631151334 - Graham Cherry SAMSUNG 2TB hard drive [paid via PL CC] | G176: INV631151334 - Graham Cherry SAMSUNG 2TB hard drive [paid via PL CC] | H176: 9000 - OFFICE / ADMIN [CTS] | I176: CTS | J176: Payable Invoice
A177: 46239 | B177: 167.27 | E177: Officeworks Superstores Pty Ltd - CYGNETT 12W DUAL USB-A WL CHRG | F177: INV631256092 - PRD Asset purchase [JS App] | G177: INV631256092 - PRD Asset purchase [JS App] | H177: 9100 - PRODUCTION [PRD] | I177: PRODUCTION | J177: Payable Invoice
A178: Techbox Australia Pty Ltd | B178: =B179 -> 889.08 | C178: =B178/$B$326 -> 0.01521887 | D178: 1
A179: Instant Asset Write Off | B179: =B180 -> 889.08 | D179: 1
A180: 46239 | B180: 889.08 | E180: Techbox Australia Pty Ltd - DSAN PerfectCue Four Button Transmitter SKU: TBVISDSANPC4BUTREM_ | F180: TB008297 - PRD Asset purchase [JS App] | G180: TB008297 - PRD Asset purchase [JS App] | H180: 9100 - PRODUCTION [PRD] | I180: PRODUCTION | J180: Payable Invoice
A181: Insphire Ltd. (Current) | B181: =B182 -> 862 | C181: =B181/$B$326 -> 0.014755327 | D181: 4
A182: Dues & Subscriptions | B182: =B183+B184+B185+B186 -> 862 | D182: 4
A183: 46219 | B183: 110 | E183: Insphire Ltd. (Current) - Current RMS | F183: CAU-21862 - Current RMS Monthly July 2026 | G183: CAU-21862 - Current RMS Monthly July 2026 | H183: 9100 - PRODUCTION [PRD] | I183: PRODUCTION | J183: Payable Invoice
A184: 46219 | B184: 321 | E184: Insphire Ltd. (Current) - Additional User | F184: CAU-21862 - Current RMS Monthly July 2026 | G184: CAU-21862 - Current RMS Monthly July 2026 | H184: 9100 - PRODUCTION [PRD] | I184: PRODUCTION | J184: Payable Invoice
A185: 46250 | B185: 110 | E185: Insphire Ltd. (Current) - Current RMS | F185: CAU-22062 - Current RMS Monthly August 2026 [paid via PL CC] | G185: CAU-22062 - Current RMS Monthly August 2026 [paid via PL CC] | H185: 9100 - PRODUCTION [PRD] | I185: PRODUCTION | J185: Payable Invoice
A186: 46250 | B186: 321 | E186: Insphire Ltd. (Current) - Additional User | F186: CAU-22062 - Current RMS Monthly August 2026 [paid via PL CC] | G186: CAU-22062 - Current RMS Monthly August 2026 [paid via PL CC] | H186: 9100 - PRODUCTION [PRD] | I186: PRODUCTION | J186: Payable Invoice
A187: DJ City | B187: =B188 -> 780 | C187: =B187/$B$326 -> 0.013351688 | D187: 1
A188: Instant Asset Write Off | B188: =B189 -> 780 | D188: 1
A189: 46239 | B189: 780 | E189: DJ City - Zoom H6essential 32-Bit Float Portable Field Recorder SKU:ZOOM-H6EBackorder product | F189: INV1265316 - PRD Asset purchases [JS App] | G189: INV1265316 - PRD Asset purchases [JS App] | H189: 9000 - OFFICE / ADMIN [CTS] | I189: PRODUCTION | J189: Payable Invoice
A190: Zoom Video Communications Inc. | B190: =B191 -> 647.94 | C190: =B190/$B$326 -> 0.011091144 | D190: 6
...

Sheet Monthly Analysis
A1: Corporate Technology Services Pty Ltd
A2: Monthly analysis by account
A3: Discretionary technology spend - FY2027 year to date (1 July 2026 to 31 August 2026)
A5: General ledger account | B5: Jul 2026 | C5: Aug 2026 | D5: Total
A6: IT Network Service & Support | B6: 20171.74 | C6: 10047 | D6: =SUM(B6:C6) -> 30218.74
A7: Dues & Subscriptions | B7: 10445.04 | C7: 10227.12 | D7: =SUM(B7:C7) -> 20672.16
A8: Instant Asset Write Off | B8: 5000 | C8: 0 | D8: =SUM(B8:C8) -> 5000
A9: Internet | B9: 363.82 | C9: 363.82 | D9: =SUM(B9:C9) -> 727.64
A10: Mobile Phones | B10: 695.29 | C10: 591 | D10: =SUM(B10:C10) -> 1286.29
A11: Office Phones | B11: 171.71 | C11: 171.71 | D11: =SUM(B11:C11) -> 343.42
A12: 1300 Number | B12: 81.09 | C12: 90.24 | D12: =SUM(B12:C12) -> 171.33
A13: Total | B13: =SUM(B6:B12) -> 36928.69 | C13: =SUM(C6:C12) -> 21490.89 | D13: =SUM(D6:D12) -> 58419.58

Sheet Transaction Listing
A1: Corporate Technology Services Pty Ltd
A2: Transaction listing
A3: Discretionary technology spend - FY2027 year to date (1 July 2026 to 31 August 2026) - every ledger line coded to the seven accounts, 247 lines
A5: Date | B5: Acct code | C5: General ledger account | D5: Source | E5: Supplier / contact | F5: Description | G5: Invoice no. | H5: Reference | I5: Job number | J5: Cost centre | K5: Debit | L5: Credit | M5: Expenditure
A6: 46210 | B6: 64510 | C6: 1300 Number | D6: Payable Invoice | E6: Optus Billing Services Pty Ltd | F6: Optus Billing Services Pty Ltd - 1300 283 247 | G6: INV000583847765 - Office Internet and Phone Service Charges July 2026 [paid via PL CC] | H6: INV000583847765 - Office Internet and Phone Service Charges July 2026 [paid via PL CC] | I6: 9000 - OFFICE / ADMIN [CTS] | J6: CTS | K6: 26.29 | L6: 0 | M6: 26.29
A7: 46210 | B7: 64510 | C7: 1300 Number | D7: Payable Invoice | E7: Optus Billing Services Pty Ltd | F7: Optus Billing Services Pty Ltd - 1300 388 528 (DTTL Phone) | G7: INV000583847765 - Office Internet and Phone Service Charges July 2026 [paid via PL CC] | H7: INV000583847765 - Office Internet and Phone Service Charges July 2026 [paid via PL CC] | I7: 974 - DTTL 1300 Number [ONS] | J7: ONSITE | K7: 25.85 | L7: 0 | M7: 25.85
A8: 46210 | B8: 64510 | C8: 1300 Number | D8: Payable Invoice | E8: Optus Billing Services Pty Ltd | F8: Optus Billing Services Pty Ltd - 1800 225 528 | G8: INV000583847765 - Office Internet and Phone Service Charges July 2026 [paid via PL CC] | H8: INV000583847765 - Office Internet and Phone Service Charges July 2026 [paid via PL CC] | I8: 9000 - OFFICE / ADMIN [CTS] | J8: CTS | K8: 28.95 | L8: 0 | M8: 28.95
A9: 46241 | B9: 64510 | C9: 1300 Number | D9: Payable Invoice | E9: Optus Billing Services Pty Ltd | F9: Optus Billing Services Pty Ltd - 1300 283 247 | G9: INV000589213447 - Office Internet and Phone Service Charges August 2026 [paid via PL CC] | H9: INV000589213447 - Office Internet and Phone Service Charges August 2026 [paid via PL CC] | I9: 9000 - OFFICE / ADMIN [CTS] | J9: CTS | K9: 26.31 | L9: 0 | M9: 26.31
A10: 46241 | B10: 64510 | C10: 1300 Number | D10: Payable Invoice | E10: Optus Billing Services Pty Ltd | F10: Optus Billing Services Pty Ltd - 1300 388 528 (DTTL Phone) | G10: INV000589213447 - Office Internet and Phone Service Charges August 2026 [paid via PL CC] | H10: INV000589213447 - Office Internet and Phone Service Charges August 2026 [paid via PL CC] | I10: 974 - DTTL 1300 Number [ONS] | J10: ONSITE | K10: 25.71 | L10: 0 | M10: 25.71
A11: 46241 | B11: 64510 | C11: 1300 Number | D11: Payable Invoice | E11: Optus Billing Services Pty Ltd | F11: Optus Billing Services Pty Ltd - 1800 225 528 | G11: INV000589213447 - Office Internet and Phone Service Charges August 2026 [paid via PL CC] | H11: INV000589213447 - Office Internet and Phone Service Charges August 2026 [paid via PL CC] | I11: 9000 - OFFICE / ADMIN [CTS] | J11: CTS | K11: 38.22 | L11: 0 | M11: 38.22
A12: 46204 | B12: 61400 | C12: Dues & Subscriptions | D12: Payable Invoice | E12: First Focus IT Pty Ltd | F12: First Focus IT Pty Ltd - Microsoft Azure Consumption | G12: INV168585: MSA: Managed Services: Managed Services - Azure July 2026 [paid via DD] | H12: INV168585: MSA: Managed Services: Managed Services - Azure July 2026 [paid via DD] | I12: 9000 - OFFICE / ADMIN [CTS] | J12: CTS | K12: 616.89 | L12: 0 | M12: 616.89
A13: 46204 | B13: 61400 | C13: Dues & Subscriptions | D13: Payable Invoice | E13: First Focus IT Pty Ltd | F13: First Focus IT Pty Ltd - Exchange Online (Plan 2) (NCE COM 1MTH) Serial Number(s): S365L | G13: INV167160 - MSA: CORE Intelligent Managed Services: CORE Intelligent Managed Services July 2026 [paid via DD] To recieve credits for the interest charged | H13: INV167160 - MSA: CORE Intelligent Managed Services: CORE Intelligent Managed Services July 2026 [paid via DD] To recieve credits for the interest charged | I13: 9000 - OFFICE / ADMIN [CTS] | J13: CTS | K13: 79.92 | L13: 0 | M13: 79.92
A14: 46204 | B14: 61400 | C14: Dues & Subscriptions | D14: Payable Invoice | E14: First Focus IT Pty Ltd | F14: First Focus IT Pty Ltd - Microsoft Defender for Office 365 (Plan 1) (NCE COM 1MTH) | G14: INV167160 - MSA: CORE Intelligent Managed Services: CORE Intelligent Managed Services July 2026 [paid via DD] To recieve credits for the interest charged | H14: INV167160 - MSA: CORE Intelligent Managed Services: CORE Intelligent Managed Services July 2026 [paid via DD] To recieve credits for the interest charged | I14: 9000 - OFFICE / ADMIN [CTS] | J14: CTS | K14: 57.6 | L14: 0 | M14: 57.6
A15: 46204 | B15: 61400 | C15: Dues & Subscriptions | D15: Payable Invoice | E15: First Focus IT Pty Ltd | F15: First Focus IT Pty Ltd - Microsoft Defender for Office 365 (Plan 2) (NCE COM 1MTH) | G15: INV167160 - MSA: CORE Intelligent Managed Services: CORE Intelligent Managed Services July 2026 [paid via DD] To recieve credits for the interest charged | H15: INV167160 - MSA: CORE Intelligent Managed Services: CORE Intelligent Managed Services July 2026 [paid via DD] To recieve credits for the interest charged | I15: 9000 - OFFICE / ADMIN [CTS] | J15: CTS | K15: 9 | L15: 0 | M15: 9
A16: 46204 | B16: 61400 | C16: Dues & Subscriptions | D16: Payable Invoice | E16: First Focus IT Pty Ltd | F16: First Focus IT Pty Ltd - Office 365 Extra File Storage (NCE Product) (NCE COM 1MTH | G16: INV167160 - MSA: CORE Intelligent Managed Services: CORE Intelligent Managed Services July 2026 [paid via DD] To recieve credits for the interest charged | H16: INV167160 - MSA: CORE Intelligent Managed Services: CORE Intelligent Managed Services July 2026 [paid via DD] To recieve credits for the interest charged | I16: 9000 - OFFICE / ADMIN [CTS] | J16: CTS | K16: 917.28 | L16: 0 | M16: 917.28
A17: 46204 | B17: 61400 | C17: Dues & Subscriptions | D17: Payable Invoice | E17: First Focus IT Pty Ltd | F17: First Focus IT Pty Ltd - Planner and Project Plan 3 (NCE COM 1MTH) Serial Number(s): S365L | G17: INV167160 - MSA: CORE Intelligent Managed Services: CORE Intelligent Managed Services July 2026 [paid via DD] To recieve credits for the interest charged | H17: INV167160 - MSA: CORE Intelligent Managed Services: CORE Intelligent Managed Services July 2026 [paid via DD] To recieve credits for the interest charged | I17: 9000 - OFFICE / ADMIN [CTS] | J17: CTS | K17: 104.1 | L17: 0 | M17: 104.1
... A61: 46233 | B61: 61400 | C61: Dues & Subscriptions | D61: Payable Invoice | E61: LIVEU INC - US & INTERNATIONAL | F61: LIVEU INC - US & INTERNATIONAL - 1 × Monthly (at $45.00 US Dollars / month) July 31, 2026 to August 31, 2026 Serial number: 202120-23123 | G61: AF983502-0245 - LiveU Monthly Plan for 202120-23123 | H61: AF983502-0245 - LiveU Monthly Plan for 202120-23123 | I61: 9100 - PRODUCTION [PRD] | J61: PRODUCTION | K61: 65.03 | L61: 0 | M61: 65.03
A62: 46234 | B62: 61400 | C62: Dues & Subscriptions | D62: Manual Journal | E62: (no supplier name recorded) | F62: Prepayments July 2026 - Inv6115846AA|27/03|Dicker Data| | H62: #69222 | I62: 2910 - Office Move 2024 [CTS] | J62: CTS | K62: 38.75 | L62: 0 | M62: 38.75
A63: 46234 | B63: 61400 | C63: Dues & Subscriptions | D63: Manual Journal | E63: (no supplier name recorded) | F63: Prepayments July 2026 - Inv58586033|10/02|Crazy Domains (website renewal)| | H63: #69222 | I63: 9350 - MARKETING (external) [CTS] | J63: CTS | K63: 12.5 | L63: 0 | M63: 12.5
A64: 46234 | B64: 61400 | C64: Dues & Subscriptions | D64: Manual Journal | E64: (no supplier name recorded) | F64: Prepayments July 2026 - Inv1753767723|29/07|Webflow.com| | H64: #69222 | I64: 9350 - MARKETING (external) [CTS] | J64: CTS | K64: 35.36 | L64: 0 | M64: 35.36
A65: 46234 | B65: 61400 | C65: Dues & Subscriptions | D65: Manual Journal | E65: (no supplier name recorded) | F65: Prepayments July 2026 - Inv415083|06/08|PigeonLab Pte Ltd| | H65: #69222 | I65: 9100 - PRODUCTION [PRD] | J65: PRODUCTION | K65: 348.89 | L65: 0 | M65: 348.89
A66: 46234 | B66: 61400 | C66: Dues & Subscriptions | D66: Manual Journal | E66: (no supplier name recorded) | F66: Prepayments July 2026 - Inv88AD1D8F-0004|15/08|Plumsail Inc| | H66: #69222 | I66: 9100 - PRODUCTION [PRD] | J66: PRODUCTION | K66: 38.59 | L66: 0 | M66: 38.59
A67: 46234 | B67: 61400 | C67: Dues & Subscriptions | D67: Manual Journal | E67: (no supplier name recorded) | F67: Prepayments July 2026 - Inv51110652883|01/09|Linkedin Singapore| | H67: #69222 | I67: 9300 - HUMAN RESOURCES [CTS] | J67: CTS | K67: 530 | L67: 0 | M67: 530
A68: 46234 | B68: 61400 | C68: Dues & Subscriptions | D68: Manual Journal | E68: (no supplier name recorded) | F68: Prepayments July 2026 - Inv721699|22/09|Qantas Airways Limited| | H68: #69222 | I68: 3059 - CBA AGM 2025 [PRD] | J68: PRODUCTION | K68: 44.28 | L68: 0 | M68: 44.28
A69: 46234 | B69: 61400 | C69: Dues & Subscriptions | D69: Manual Journal | E69: (no supplier name recorded) | F69: Prepayments July 2026 - Inv356325|08/09|AddEvent Inc| | H69: #69222 | I69: 9100 - PRODUCTION [PRD] | J69: PRODUCTION | K69: 44.33 | L69: 0 | M69: 44.33
A70: 46234 | B70: 61400 | C70: Dues & Subscriptions | D70: Manual Journal | E70: (no supplier name recorded) | F70: Prepayments July 2026 - Inv50BB48DA-0011|06/10|Qwilr Pty Ltd| | H70: #69222 | I70: 9105 - ONSITE (including PROD backup) | J70: ONSITE | K70: 79.75 | L70: 0 | M70: 79.75
A71: 46234 | B71: 61400 | C71: Dues & Subscriptions | D71: Manual Journal | E71: (no supplier name recorded) | F71: Prepayments July 2026 - Inv50BB48DA-0011|06/10|Qwilr Pty Ltd| | H71: #69222 | I71: 9200 - INTEGRATION [INT] | J71: INTEGRATION | K71: 39.88 | L71: 0 | M71: 39.88
A72: 46234 | B72: 61400 | C72: Dues & Subscriptions | D72: Manual Journal | E72: (no supplier name recorded) | F72: Prepayments July 2026 - Inv50BB48DA-0011|06/10|Qwilr Pty Ltd| | H72: #69222 | I72: 9400 - CONSULTING [CONS] | J72: CONSULTING | K72: 39.88 | L72: 0 | M72: 39.88
A73: 46234 | B73: 61400 | C73: Dues & Subscriptions | D73: Manual Journal | E73: (no supplier name recorded) | F73: Prepayments July 2026 - Inv3435939|11/11|AVIXA (Formerly InfoComm International)| | H73: #69222 | I73: 9000 - OFFICE / ADMIN [CTS] | J73: CTS | K73: 237.5 | L73: 0 | M73: 237.5
... A87: 46234 | B87: 61400 | C87: Dues & Subscriptions | D87: Manual Journal | E87: (no supplier name recorded) | F87: Prepayments July 2026 - InvINV20611845 |06/07|Lucid| | H87: #69222 | I87: 9000 - OFFICE / ADMIN [CTS] | J87: CTS | K87: 43.36 | L87: 0 | M87: 43.36
A88: 46234 | B88: 61400 | C88: Dues & Subscriptions | D88: Payable Invoice | E88: LIVEU INC - US & INTERNATIONAL | F88: LIVEU INC - US & INTERNATIONAL - 1 × Monthly (at $45.00 US Dollars / month) August 1, 2026 to September 1, 2026 Serial number: 202120-23120 | G88: AF983502-0246 - LiveU Monthly Plan for 202120-23120 | H88: AF983502-0246 - LiveU Monthly Plan for 202120-23120 | I88: 9100 - PRODUCTION [PRD] | J88: PRODUCTION | K88: 64.39 | L88: 0 | M88: 64.39
A89: 46235 | B89: 61400 | C89: Dues & Subscriptions | D89: Payable Invoice | E89: First Focus IT Pty Ltd | F89: First Focus IT Pty Ltd - Microsoft Azure Consumption | G89: INV173381: MSA: Managed Services: Managed Services - Azure August 2026 [paid via DD] | H89: INV173381: MSA: Managed Services: Managed Services - Azure August 2026 [paid via DD] | I89: 9000 - OFFICE / ADMIN [CTS] | J89: CTS | K89: 643.73 | L89: 0 | M89: 643.73
A90: 46235 | B90: 61400 | C90: Dues & Subscriptions | D90: Payable Invoice | E90: First Focus IT Pty Ltd | F90: First Focus IT Pty Ltd - Exchange Online (Plan 2) (NCE COM 1MTH) Serial Number(s): S365L | G90: INV170755 - MSA: CORE Intelligent Managed Services: CORE Intelligent Managed Services August 2026 [paid via DD] | H90: INV170755 - MSA: CORE Intelligent Managed Services: CORE Intelligent Managed Services August 2026 [paid via DD] | I90: 9000 - OFFICE / ADMIN [CTS] | J90: CTS | K90: 79.92 | L90: 0 | M90: 79.92
A91: 46235 | B91: 61400 | C91: Dues & Subscriptions | D91: Payable Invoice | E91: First Focus IT Pty Ltd | F91: First Focus IT Pty Ltd - Microsoft Defender for Office 365 (Plan 1) (NCE COM 1MTH) | G91: INV170755 - MSA: CORE Intelligent Managed Services: CORE Intelligent Managed Services August 2026 [paid via DD] | H91: INV170755 - MSA: CORE Intelligent Managed Services: CORE Intelligent Managed Services August 2026 [paid via DD] | I91: 9000 - OFFICE / ADMIN [CTS] | J91: CTS | K91: 57.6 | L91: 0 | M91: 57.6
A92: 46235 | B92: 61400 | C92: Dues & Subscriptions | D92: Payable Invoice | E92: First Focus IT Pty Ltd | F92: First Focus IT Pty Ltd - Microsoft Defender for Office 365 (Plan 2) (NCE COM 1MTH) | G92: INV170755 - MSA: CORE Intelligent Managed Services: CORE Intelligent Managed Services August 2026 [paid via DD] | H92: INV170755 - MSA: CORE Intelligent Managed Services: CORE Intelligent Managed Services August 2026 [paid via DD] | I92: 9000 - OFFICE / ADMIN [CTS] | J92: CTS | K92: 9 | L92: 0 | M92: 9
A93: 46235 | B93: 61400 | C93: Dues & Subscriptions | D93: Payable Invoice | E93: First Focus IT Pty Ltd | F93: First Focus IT Pty Ltd - Office 365 Extra File Storage (NCE Product) (NCE COM 1MTH | G93: INV170755 - MSA: CORE Intelligent Managed Services: CORE Intelligent Managed Services August 2026 [paid via DD] | H93: INV170755 - MSA: CORE Intelligent Managed Services: CORE Intelligent Managed Services August 2026 [paid via DD] | I93: 9000 - OFFICE / ADMIN [CTS] | J93: CTS | K93: 917.28 | L93: 0 | M93: 917.28
A94: 46235 | B94: 61400 | C94: Dues & Subscriptions | D94: Payable Invoice | E94: First Focus IT Pty Ltd | F94: First Focus IT Pty Ltd - Planner and Project Plan 3 (NCE COM 1MTH) Serial Number(s): S365L | G94: INV170755 - MSA: CORE Intelligent Managed Services: CORE Intelligent Managed Services August 2026 [paid via DD] | H94: INV170755 - MSA: CORE Intelligent Managed Services: CORE Intelligent Managed Services August 2026 [paid via DD] | I94: 9000 - OFFICE / ADMIN [CTS] | J94: CTS | K94: 107.76 | L94: 0 | M94: 107.76
A95: 46235 | B95: 61400 | C95: Dues & Subscriptions | D95: Payable Invoice | E95: First Focus IT Pty Ltd | F95: First Focus IT Pty Ltd - Visio Plan 2 (NCE COM 1MTH) Serial Number(s): S365L | G95: INV170755 - MSA: CORE Intelligent Managed Services: CORE Intelligent Managed Services August 2026 [paid via DD] | H95: INV170755 - MSA: CORE Intelligent Managed Services: CORE Intelligent Managed Services August 2026 [paid via DD] | I95: 9000 - OFFICE / ADMIN [CTS] | J95: CTS | K95: 215.04 | L95: 0 | M95: 215.04
A96: 46235 | B96: 61400 | C96: Dues & Subscriptions | D96: Payable Invoice | E96: First Focus IT Pty Ltd | F96: First Focus IT Pty Ltd - Microsoft 365 Business Standard (NCE COM 1YR MTH) Serial Number(s): S365L | G96: INV170755 - MSA: CORE Intelligent Managed Services: CORE Intelligent Managed Services August 2026 [paid via DD] | H96: INV170755 - MSA: CORE Intelligent Managed Services: CORE Intelligent Managed Services August 2026 [paid via DD] | I96: 9000 - OFFICE / ADMIN [CTS] | J96: CTS | K96: 157.12 | L96: 0 | M96: 157.12
A97: 46235 | B97: 61400 | C97: Dues & Subscriptions | D97: Payable Invoice | E97: First Focus IT Pty Ltd | F97: First Focus IT Pty Ltd - Microsoft 365 Business Basic (NCE COM 1YR MTH) Serial Number(s): S365L | G97: INV170755 - MSA: CORE Intelligent Managed Services: CORE Intelligent Managed Services August 2026 [paid via DD] | H97: INV170755 - MSA: CORE Intelligent Managed Services: CORE Intelligent Managed Services August 2026 [paid via DD] | I97: 9000 - OFFICE / ADMIN [CTS] | J97: CTS | K97: 274.05 | L97: 0 | M97: 274.05
A98: 46235 | B98: 61400 | C98: Dues & Subscriptions | D98: Payable Invoice | E98: First Focus IT Pty Ltd | F98: First Focus IT Pty Ltd - Microsoft 365 Business Premium (NCE COM 1YR MTH) Serial Number(s): S365L | G98: INV170755 - MSA: CORE Intelligent Managed Services: CORE Intelligent Managed Services August 2026 [paid via DD] | H98: INV170755 - MSA: CORE Intelligent Managed Services: CORE Intelligent Managed Services August 2026 [paid via DD] | I98: 9000 - OFFICE / ADMIN [CTS] | J98: CTS | K98: 1071.05 | L98: 0 | M98: 1071.05
A99: 46235 | B99: 61400 | C99: Dues & Subscriptions | D99: Payable Invoice | E99: First Focus IT Pty Ltd | F99: First Focus IT Pty Ltd - Datto SAAS Protection for Microsoft 365 (CSP COM 3YR MTH) | G99: INV170755 - MSA: CORE Intelligent Managed Services: CORE Intelligent Managed Services August 2026 [paid via DD] | H99: INV170755 - MSA: CORE Intelligent Managed Services: CORE Intelligent Managed Services August 2026 [paid via DD] | I99: 9000 - OFFICE / ADMIN [CTS] | J99: CTS | K99: 265.36 | L99: 0 | M99: 265.36
... A121: 46264 | B121: 61400 | C121: Dues & Subscriptions | D121: Payable Invoice | E121: LIVEU INC - US & INTERNATIONAL | F121: LIVEU INC - US & INTERNATIONAL - 1 × Monthly (at $45.00 US Dollars / month) August 31, 2026 to October 1, 2026 Serial number: 201706-23902 | G121: AF983502-0249 - LiveU Monthly Plan for 202120-23123 | H121: AF983502-0249 - LiveU Monthly Plan for 202120-23123 | I121: 9100 - PRODUCTION [PRD] | J121: PRODUCTION | K121: 62.83 | L121: 0 | M121: 62.83
A122: 46265 | B122: 61400 | C122: Dues & Subscriptions | D122: Manual Journal | E122: (no supplier name recorded) | F122: Expense Accrual August 2026 - LiveU June 2025 & July 2026 | H122: #70416 | I122: 9000 - OFFICE / ADMIN [CTS] | J122: CTS | K122: 208.09 | L122: 0 | M122: 208.09
A123: 46265 | B123: 61400 | C123: Dues & Subscriptions | D123: Manual Journal | E123: (no supplier name recorded) | F123: Prepayments August 2026 - Inv6115846AA|27/03|Dicker Data| | H123: #70417 | I123: 2910 - Office Move 2024 [CTS] | J123: CTS | K123: 38.75 | L123: 0 | M123: 38.75
A124: 46265 | B124: 61400 | C124: Dues & Subscriptions | D124: Manual Journal | E124: (no supplier name recorded) | F124: Prepayments August 2026 - Inv58586033|10/02|Crazy Domains (website renewal)| | H124: #70417 | I124: 9350 - MARKETING (external) [CTS] | J124: CTS | K124: 12.5 | L124: 0 | M124: 12.5
A125: 46265 | B125: 61400 | C125: Dues & Subscriptions | D125: Manual Journal | E125: (no supplier name recorded) | F125: Prepayments August 2026 - Inv51110652883|01/09|Linkedin Singapore| | H125: #70417 | I125: 9300 - HUMAN RESOURCES [CTS] | J125: CTS | K125: 530 | L125: 0 | M125: 530
A126: 46265 | B126: 61400 | C126: Dues & Subscriptions | D126: Manual Journal | E126: (no supplier name recorded) | F126: Prepayments August 2026 - Inv721699|22/09|Qantas Airways Limited| | H126: #70417 | I126: 3059 - CBA AGM 2025 [PRD] | J126: PRODUCTION | K126: 44.28 | L126: 0 | M126: 44.28
A127: 46265 | B127: 61400 | C127: Dues & Subscriptions | D127: Manual Journal | E127: (no supplier name recorded) | F127: Prepayments August 2026 - Inv1847146|29/09|Brookvale Insurance Brokers Pty Ltd (Bus Com)| | H127: #70417 | I127: 9000 - OFFICE / ADMIN [CTS] | J127: CTS | K127: 175.03 | L127: 0 | M127: 175.03
A128: 46265 | B128: 61400 | C128: Dues & Subscriptions | D128: Manual Journal | E128: (no supplier name recorded) | F128: Prepayments August 2026 - Inv1847148|29/09|Brookvale Insurance Brokers Pty Ltd (Mecon)| | H128: #70417 | I128: 9200 - INTEGRATION [INT] | J128: INTEGRATION | K128: 343.27 | L128: 0 | M128: 343.27
A129: 46265 | B129: 61400 | C129: Dues & Subscriptions | D129: Manual Journal | E129: (no supplier name recorded) | F129: Prepayments August 2026 - Inv1847147|29/09|Brookvale Insurance Brokers Pty Ltd (Removeable Equip)| | H129: #70417 | I129: 9100 - PRODUCTION [PRD] | J129: PRODUCTION | K129: 528.18 | L129: 0 | M129: 528.18
A130: 46265 | B130: 61400 | C130: Dues & Subscriptions | D130: Manual Journal | E130: (no supplier name recorded) | F130: Prepayments August 2026 - Inv3435939|11/11|AVIXA (Formerly InfoComm International)| | H130: #70417 | I130: 9000 - OFFICE / ADMIN [CTS] | J130: CTS | K130: 237.5 | L130: 0 | M130: 237.5
A131: 46265 | B131: 61400 | C131: Dues & Subscriptions | D131: Manual Journal | E131: (no supplier name recorded) | F131: Prepayments August 2026 - Inv12112025|12/11|Linkedin Singapore| | H131: #70417 | I131: 9000 - OFFICE / ADMIN [CTS] | J131: CTS | K131: 49.99 | L131: 0 | M131: 49.99
A132: 46265 | B132: 61400 | C132: Dues & Subscriptions | D132: Manual Journal | E132: (no supplier name recorded) | F132: Prepayments August 2026 - InvINV-18112025|18/11|Labour Hire Licence VIC| | H132: #70417 | I132: 9105 - ONSITE (including PROD backup) | J132: ONSITE | K132: 280.17 | L132: 0 | M132: 280.17
A133: 46265 | B133: 61400 | C133: Dues & Subscriptions | D133: Manual Journal | E133: (no supplier name recorded) | F133: Prepayments August 2026 - InvINV02191196|11/11|Avetta| | H133: #70417 | I133: 585 - CBA Team Leader [ONS] | J133: ONSITE | K133: 24.78 | L133: 0 | M133: 24.78
... A148: 46265 | B148: 61400 | C148: Dues & Subscriptions | D148: Manual Journal | E148: (no supplier name recorded) | F148: Prepayments August 2026 - InvINV137220 |01/08|The CEO Institute (JS)| | H148: #70417 | I148: 9000 - OFFICE / ADMIN [CTS] | J148: CTS | K148: 700 | L148: 0 | M148: 700
A149: 46265 | B149: 61400 | C149: Dues & Subscriptions | D149: Manual Journal | E149: (no supplier name recorded) | F149: Expense Plumsail residual - net position under the $300 prepayment threshold - Rounding Variance - Expense Plumsail residual - net position under the $300 prepayment threshold | H149: #70435 | J149: PRODUCTION | K149: 0.9 | L149: 0 | M149: 0.9
A150: 46265 | B150: 61400 | C150: Dues & Subscriptions | D150: Payable Invoice | E150: LIVEU INC - US & INTERNATIONAL | F150: LIVEU INC - US & INTERNATIONAL - 1 × Monthly (at $45.00 US Dollars / month) September 1, 2026 to October 1, 2026 Serial number: 202120-23120 | G150: AF983502-0250 - LiveU Monthly Plan for 202120-23120 | H150: AF983502-0250 - LiveU Monthly Plan for 202120-23120 | I150: 9100 - PRODUCTION [PRD] | J150: PRODUCTION | K150: 62.95 | L150: 0 | M150: 62.95
A151: 46204 | B151: 64700 | C151: IT Network Service & Support | D151: Payable Invoice | E151: First Focus IT Pty Ltd | F151: First Focus IT Pty Ltd - CORE Intelligent Managed Services | G151: INV167160 - MSA: CORE Intelligent Managed Services: CORE Intelligent Managed Services July 2026 [paid via DD] To recieve credits for the interest charged | H151: INV167160 - MSA: CORE Intelligent Managed Services: CORE Intelligent Managed Services July 2026 [paid via DD] To recieve credits for the interest charged | I151: 9000 - OFFICE / ADMIN [CTS] | J151: CTS | K151: 9953 | L151: 0 | M151: 9953
A152: 46204 | B152: 64700 | C152: IT Network Service & Support | D152: Payable Invoice | E152: First Focus IT Pty Ltd | F152: First Focus IT Pty Ltd - CORE Intelligent Managed Services Email Only User 75% discount | G152: INV167160 - MSA: CORE Intelligent Managed Services: CORE Intelligent Managed Services July 2026 [paid via DD] To recieve credits for the interest charged | H152: INV167160 - MSA: CORE Intelligent Managed Services: CORE Intelligent Managed Services July 2026 [paid via DD] To recieve credits for the interest charged | I152: 9000 - OFFICE / ADMIN [CTS] | J152: CTS | K152: 403.5 | L152: 0 | M152: 403.5
A153: 46204 | B153: 64700 | C153: IT Network Service & Support | D153: Payable Invoice | E153: First Focus IT Pty Ltd | F153: First Focus IT Pty Ltd - CORE - Hatz AI Multi-LLM Platform | G153: INV167160 - MSA: CORE Intelligent Managed Services: CORE Intelligent Managed Services July 2026 [paid via DD] To recieve credits for the interest charged | H153: INV167160 - MSA: CORE Intelligent Managed Services: CORE Intelligent Managed Services July 2026 [paid via DD] To recieve credits for the interest charged | I153: 9000 - OFFICE / ADMIN [CTS] | J153: CTS | K153: 1247 | L153: 0 | M153: 1247
A154: 46204 | B154: 64700 | C154: IT Network Service & Support | D154: Payable Invoice | E154: First Focus IT Pty Ltd | F154: First Focus IT Pty Ltd - CORE Early Sign Up Discount Hatz (12 month) | G154: INV167160 - MSA: CORE Intelligent Managed Services: CORE Intelligent Managed Services July 2026 [paid via DD] To recieve credits for the interest charged | H154: INV167160 - MSA: CORE Intelligent Managed Services: CORE Intelligent Managed Services July 2026 [paid via DD] To recieve credits for the interest charged | I154: 9000 - OFFICE / ADMIN [CTS] | J154: CTS | K154: 0 | L154: 430 | M154: -430
A155: 46204 | B155: 64700 | C155: IT Network Service & Support | D155: Payable Invoice | E155: First Focus IT Pty Ltd | F155: First Focus IT Pty Ltd - DMARC Email Security Management: Per Domain | G155: INV167160 - MSA: CORE Intelligent Managed Services: CORE Intelligent Managed Services July 2026 [paid via DD] To recieve credits for the interest charged | H155: INV167160 - MSA: CORE Intelligent Managed Services: CORE Intelligent Managed Services July 2026 [paid via DD] To recieve credits for the interest charged | I155: 9000 - OFFICE / ADMIN [CTS] | J155: CTS | K155: 100 | L155: 0 | M155: 100
A156: 46204 | B156: 64700 | C156: IT Network Service & Support | D156: Payable Invoice | E156: First Focus IT Pty Ltd | F156: First Focus IT Pty Ltd - Managed SD-WAN Firewall (1Gbps max) | G156: INV167160 - MSA: CORE Intelligent Managed Services: CORE Intelligent Managed Services July 2026 [paid via DD] To recieve credits for the interest charged | H156: INV167160 - MSA: CORE Intelligent Managed Services: CORE Intelligent Managed Services July 2026 [paid via DD] To recieve credits for the interest charged | I156: 9000 - OFFICE / ADMIN [CTS] | J156: CTS | K156: 325 | L156: 0 | M156: 325
A157: 46204 | B157: 64700 | C157: IT Network Service & Support | D157: Payable Invoice | E157: First Focus IT Pty Ltd | F157: First Focus IT Pty Ltd - Exchange Online (Plan 1) (NCE COM 1MTH) Serial Number(s): S365L | G157: INV167160 - MSA: CORE Intelligent Managed Services: CORE Intelligent Managed Services July 2026 [paid via DD] To recieve credits for the interest charged | H157: INV167160 - MSA: CORE Intelligent Managed Services: CORE Intelligent Managed Services July 2026 [paid via DD] To recieve credits for the interest charged | I157: 9000 - OFFICE / ADMIN [CTS] | J157: CTS | K157: 28.8 | L157: 0 | M157: 28.8
A158: 46204 | B158: 64700 | C158: IT Network Service & Support | D158: Payable Invoice | E158: First Focus IT Pty Ltd | F158: First Focus IT Pty Ltd - Interest on late payments 162027 164522 162627 (To be credited) | G158: INV167160 - MSA: CORE Intelligent Managed Services: CORE Intelligent Managed Services July 2026 [paid via DD] To recieve credits for the interest charged | H158: INV167160 - MSA: CORE Intelligent Managed Services: CORE Intelligent Managed Services July 2026 [paid via DD] To recieve credits for the interest charged | I158: 9000 - OFFICE / ADMIN [CTS] | J158: CTS | K158: 198.58 | L158: 0 | M158: 198.58
A159: 46219 | B159: 64700 | C159: IT Network Service & Support | D159: Payable Credit Note | E159: First Focus IT Pty Ltd | F159: First Focus IT Pty Ltd - Interest on late payments 162027 164522 162627 | G159: INV168824 - Interest Charges on INV167160 for May 2026 invoices (to apply in August invoice) | H159: INV168824 - Interest Charges on INV167160 for May 2026 invoices (to apply in August invoice) | I159: 9000 - OFFICE / ADMIN [CTS] | J159: CTS | K159: 0 | L159: 198.58 | M159: -198.58
A160: 46234 | B160: 64700 | C160: IT Network Service & Support | D160: Payable Invoice | E160: First Focus IT Pty Ltd | F160: First Focus IT Pty Ltd - Fixed Fee Project | G160: INV171598 - Completion of CORE Intelligent Managed Services One-Time Project - Balance Fee [PO-00016880] pay via EFT | H160: INV171598 - Completion of CORE Intelligent Managed Services One-Time Project - Balance Fee [PO-00016880] pay via EFT | I160: 9000 - OFFICE / ADMIN [CTS] | J160: CTS | K160: 18325.73 | L160: 0 | M160: 18325.73
A161: 46234 | B161: 64700 | C161: IT Network Service & Support | D161: Payable Invoice | E161: First Focus IT Pty Ltd | F161: First Focus IT Pty Ltd - CORE Early Sign Up Discount At cost transitions project Offer valid for agreements signed prior to 15/04 | G161: INV171598 - Completion of CORE Intelligent Managed Services One-Time Project - Balance Fee [PO-00016880] pay via EFT | H161: INV171598 - Completion of CORE Intelligent Managed Services One-Time Project - Balance Fee [PO-00016880] pay via EFT | I161: 9000 - OFFICE / ADMIN [CTS] | J161: CTS | K161: 0 | L161: 7330.29 | M161: -7330.29
... A170: 46237 | B170: 64700 | C170: IT Network Service & Support | D170: Payable Invoice | E170: First Focus IT Pty Ltd | F170: First Focus IT Pty Ltd - Replacement for NAS Hard Drive Seagate IronWolf 8 TB Hard Drive - 3.5" Internal - SATA (SATA/600) - 7200rpm 256 MB Buffer - 3 Year Warranty | G170: INV170542 - Replacement for NAS Hard Drive [Q-034252v1 - PO-00016911] GC App (Pay by EFT) | H170: INV170542 - Replacement for NAS Hard Drive [Q-034252v1 - PO-00016911] GC App (Pay by EFT) | I170: 9000 - OFFICE / ADMIN [CTS] | J170: CTS | K170: 609.7 | L170: 0 | M170: 609.7
A171: 46234 | B171: 61730 | C171: Instant Asset Write Off | D171: Manual Journal | E171: (no supplier name recorded) | F171: Expense Accrual July 2026 - Instant Asset Write Off | H171: #69405 | I171: 9000 - OFFICE / ADMIN [CTS] | J171: CTS | K171: 3910.91 | L171: 0 | M171: 3910.91
A172: 46234 | B172: 61730 | C172: Instant Asset Write Off | D172: Payable Invoice | E172: Officeworks Superstores Pty Ltd | F172: Officeworks Superstores Pty Ltd - SAMSUNG 2TB T7 SSD GY | G172: INV631151334 - Graham Cherry SAMSUNG 2TB hard drive [paid via PL CC] | H172: INV631151334 - Graham Cherry SAMSUNG 2TB hard drive [paid via PL CC] | I172: 9000 - OFFICE / ADMIN [CTS] | J172: CTS | K172: 1089.09 | L172: 0 | M172: 1089.09
A173: 46238 | B173: 61730 | C173: Instant Asset Write Off | D173: Payable Invoice | E173: Amazon.com, Inc. | F173: Amazon.com, Inc. - Bingfu HD/3G-SDI RG179 BNC Cable 30cm 75 Ohm for Camera Monitor | G173: INV249-8412052 - PRD Asset purchase [JS App] | H173: INV249-8412052 - PRD Asset purchase [JS App] | I173: 9100 - PRODUCTION [PRD] | J173: PRODUCTION | K173: 34.58 | L173: 0 | M173: 34.58
A174: 46238 | B174: 61730 | C174: Instant Asset Write Off | D174: Payable Invoice | E174: K&F Concept Australia | F174: K&F Concept Australia - Camera Tripod Quick Release Mounting Plate KF31.030 | G174: INV15-403950 - PRD Asset purchase [JS App] | H174: INV15-403950 - PRD Asset purchase [JS App] | I174: 9100 - PRODUCTION [PRD] | J174: PRODUCTION | K174: 29.99 | L174: 0 | M174: 29.99
A175: 46238 | B175: 61730 | C175: Instant Asset Write Off | D175: Payable Invoice | E175: Scorptec Computers | F175: Scorptec Computers - Samsung S32GF 24inch 120Hz FHD IPS Monitor, 1920x1080, 16:9, 5ms GTG, 1000:1 Contrast, 250 Nits, 2x HDMI 1.4, Super Slim Design, Tilt, VESA 100x100mm (WTY - 3 year) Model: LS24F320GAEXXY (WTY - 3 year) 1 x SN: 0YR7HNAL500571 | G175: INV3924027 - PRD Asset purchase [JS App] | H175: INV3924027 - PRD Asset purchase [JS App] | I175: 9100 - PRODUCTION [PRD] | J175: PRODUCTION | K175: 113.64 | L175: 0 | M175: 113.64
A176: 46239 | B176: 61730 | C176: Instant Asset Write Off | D176: Payable Invoice | E176: Core Electronics | F176: Core Electronics - Mini HDMI to HDMI Cable | G176: INV1000704401 - PRD Asset purchase [JS App] | H176: INV1000704401 - PRD Asset purchase [JS App] | I176: 9100 - PRODUCTION [PRD] | J176: PRODUCTION | K176: 130.35 | L176: 0 | M176: 130.35
A177: 46239 | B177: 61730 | C177: Instant Asset Write Off | D177: Payable Invoice | E177: DJ City | F177: DJ City - Zoom H6essential 32-Bit Float Portable Field Recorder SKU:ZOOM-H6EBackorder product | G177: INV1265316 - PRD Asset purchases [JS App] | H177: INV1265316 - PRD Asset purchases [JS App] | I177: 9000 - OFFICE / ADMIN [CTS] | J177: PRODUCTION | K177: 780 | L177: 0 | M177: 780
A178: 46239 | B178: 61730 | C178: Instant Asset Write Off | D178: Payable Invoice | E178: JB Hi-Fi Pty Ltd Group | F178: JB Hi-Fi Pty Ltd Group - Samsung 45W Power Adapter with USB-C Cable | G178: JB-26704587 - PRD Asset purchase [JS App] | H178: JB-26704587 - PRD Asset purchase [JS App] | I178: 9100 - PRODUCTION [PRD] | J178: PRODUCTION | K178: 76.36 | L178: 0 | M178: 76.36
A179: 46239 | B179: 61730 | C179: Instant Asset Write Off | D179: Payable Invoice | E179: MEXI TRADING PTY LTD (T/A LG Spare Part) | F179: MEXI TRADING PTY LTD (T/A LG Spare Part) - LG GENUINE PART -EAY62990908 LG TV AC POWER ADAPTER 19V 3.42A 65W | G179: LGSP107722 - PRD Asset purchases [JS App] | H179: LGSP107722 - PRD Asset purchases [JS App] | I179: 9100 - PRODUCTION [PRD] | J179: PRODUCTION | K179: 66.23 | L179: 0 | M179: 66.23
A180: 46239 | B180: 61730 | C180: Instant Asset Write Off | D180: Payable Invoice | E180: Mouser Electronics Inc. | F180: Mouser Electronics Inc. - 490-SDI18-5-U-P5 MFG Part No: SDI18-5-U-P5 CUI Inc. 15W 5V 3A C14 2.1 ce / Desktop AC Adapters US HTS:8504409510 ECCN:EAR99 COO:CN ACO:-- COD: | G180: INV91792378 - PRD Asset purchase [JS App] | H180: INV91792378 - PRD Asset purchase [JS App] | I180: 9100 - PRODUCTION [PRD] | J180: PRODUCTION | K180: 120.6 | L180: 0 | M180: 120.6
A181: 46239 | B181: 61730 | C181: Instant Asset Write Off | D181: Payable Invoice | E181: Officeworks Superstores Pty Ltd | F181: Officeworks Superstores Pty Ltd - CYGNETT 12W DUAL USB-A WL CHRG | G181: INV631256092 - PRD Asset purchase [JS App] | H181: INV631256092 - PRD Asset purchase [JS App] | I181: 9100 - PRODUCTION [PRD] | J181: PRODUCTION | K181: 167.27 | L181: 0 | M181: 167.27
A182: 46239 | B182: 61730 | C182: Instant Asset Write Off | D182: Payable Invoice | E182: Rubber Monkey Sales | F182: Rubber Monkey Sales - Atomos Locking AC Power Adaptor | G182: RMS-470854 - PRD Asset purchases [JS App] | H182: RMS-470854 - PRD Asset purchases [JS App] | I182: 9100 - PRODUCTION [PRD] | J182: PRODUCTION | K182: 75.41 | L182: 0 | M182: 75.41
A183: 46239 | B183: 61730 | C183: Instant Asset Write Off | D183: Payable Invoice | E183: Techbox Australia Pty Ltd | F183: Techbox Australia Pty Ltd - DSAN PerfectCue Four Button Transmitter SKU: TBVISDSANPC4BUTREM_ | G183: TB008297 - PRD Asset purchase [JS App] | H183: TB008297 - PRD Asset purchase [JS App] | I183: 9100 - PRODUCTION [PRD] | J183: PRODUCTION | K183: 889.08 | L183: 0 | M183: 889.08
... A191: 46253 | B191: 61730 | C191: Instant Asset Write Off | D191: Payable Invoice | E191: digiDirect Sydney | F191: digiDirect Sydney - Atomos AtomX Battery Eliminator | G191: INV563536 - PRD Asset purchase [JS App] | H191: INV563536 - PRD Asset purchase [JS App] | I191: 9100 - PRODUCTION [PRD] | J191: PRODUCTION | K191: 33.68 | L191: 0 | M191: 33.68
A192: 46265 | B192: 61730 | C192: Instant Asset Write Off | D192: Manual Journal | E192: (no supplier name recorded) | F192: Expense Accrual August 2026 - Instant Asset Write Off | H192: #70416 | I192: 9000 - OFFICE / ADMIN [CTS] | J192: CTS | K192: 0 | L192: 4218.65 | M192: -4218.65
A193: 46209 | B193: 64560 | C193: Internet | D193: Payable Invoice | E193: Optus Billing Services Pty Ltd | F193: Optus Billing Services Pty Ltd - Lugstein on Internet Everyday Fast | G193: INV000583618957 - Lugstein Home Internet July 2026 | H193: INV000583618957 - Lugstein Home Internet July 2026 | I193: 9000 - OFFICE / ADMIN [CTS] | J193: CTS | K193: 92 | L193: 0 | M193: 92
A194: 46210 | B194: 64560 | C194: Internet | D194: Payable Invoice | E194: Optus Billing Services Pty Ltd | F194: Optus Billing Services Pty Ltd - Evolve Internet RC - Unlimited | G194: INV000583847765 - Office Internet and Phone Service Charges July 2026 [paid via PL CC] | H194: INV000583847765 - Office Internet and Phone Service Charges July 2026 [paid via PL CC] | I194: 9000 - OFFICE / ADMIN [CTS] | J194: CTS | K194: 271.82 | L194: 0 | M194: 271.82
A195: 46240 | B195: 64560 | C195: Internet | D195: Payable Invoice | E195: Optus Billing Services Pty Ltd | F195: Optus Billing Services Pty Ltd - Lugstein on Internet Everyday Fast | G195: INV000589011323 - Lugstein Home Internet August 2026 [BPAY] | H195: INV000589011323 - Lugstein Home Internet August 2026 [BPAY] | I195: 9000 - OFFICE / ADMIN [CTS] | J195: CTS | K195: 92 | L195: 0 | M195: 92
A196: 46241 | B196: 64560 | C196: Internet | D196: Payable Invoice | E196: Optus Billing Services Pty Ltd | F196: Optus Billing Services Pty Ltd - Evolve Internet RC - Unlimited | G196: INV000589213447 - Office Internet and Phone Service Charges August 2026 [paid via PL CC] | H196: INV000589213447 - Office Internet and Phone Service Charges August 2026 [paid via PL CC] | I196: 9000 - OFFICE / ADMIN [CTS] | J196: CTS | K196: 271.82 | L196: 0 | M196: 271.82
A197: 46210 | B197: 64530 | C197: Mobile Phones | D197: Payable Invoice | E197: Optus Billing Services Pty Ltd | F197: Optus Billing Services Pty Ltd - 0488287111 - Mitchell Healey (PRD Manager) | G197: INV000583847765 - Office Internet and Phone Service Charges July 2026 [paid via PL CC] | H197: INV000583847765 - Office Internet and Phone Service Charges July 2026 [paid via PL CC] | I197: 9100 - PRODUCTION [PRD] | J197: PRODUCTION | K197: 31.35 | L197: 0 | M197: 31.35
A198: 46210 | B198: 64530 | C198: Mobile Phones | D198: Payable Invoice | E198: Optus Billing Services Pty Ltd | F198: Optus Billing Services Pty Ltd - 0417669001 - Duncan Lugstein (MD) | G198: INV000583847765 - Office Internet and Phone Service Charges July 2026 [paid via PL CC] | H198: INV000583847765 - Office Internet and Phone Service Charges July 2026 [paid via PL CC] | I198: 9000 - OFFICE / ADMIN [CTS] | J198: CTS | K198: 31.35 | L198: 0 | M198: 31.35
A199: 46210 | B199: 64530 | C199: Mobile Phones | D199: Payable Invoice | E199: Optus Billing Services Pty Ltd | F199: Optus Billing Services Pty Ltd - 0488287000 - Tyler Wood (Events Op Manager) | G199: INV000583847765 - Office Internet and Phone Service Charges July 2026 [paid via PL CC] | H199: INV000583847765 - Office Internet and Phone Service Charges July 2026 [paid via PL CC] | I199: 9100 - PRODUCTION [PRD] | J199: PRODUCTION | K199: 31.35 | L199: 0 | M199: 31.35
A200: 46210 | B200: 64530 | C200: Mobile Phones | D200: Payable Invoice | E200: Optus Billing Services Pty Ltd | F200: Optus Billing Services Pty Ltd - 0488287777 - Graham Cherry | G200: INV000583847765 - Office Internet and Phone Service Charges July 2026 [paid via PL CC] | H200: INV000583847765 - Office Internet and Phone Service Charges July 2026 [paid via PL CC] | I200: 9000 - OFFICE / ADMIN [CTS] | J200: CTS | K200: 31.35 | L200: 0 | M200: 31.35
A201: 46210 | B201: 64530 | C201: Mobile Phones | D201: Payable Invoice | E201: Optus Billing Services Pty Ltd | F201: Optus Billing Services Pty Ltd - 0488287092 - Rob Mahood (Gen-E Onsite) | G201: INV000583847765 - Office Internet and Phone Service Charges July 2026 [paid via PL CC] | H201: INV000583847765 - Office Internet and Phone Service Charges July 2026 [paid via PL CC] | I201: 26021602 - Gen E ABS AV Support (Canberra) [ONS] | J201: ONSITE | K201: 31.35 | L201: 0 | M201: 31.35
A202: 46210 | B202: 64530 | C202: Mobile Phones | D202: Payable Invoice | E202: Optus Billing Services Pty Ltd | F202: Optus Billing Services Pty Ltd - 0488688446 - Available but Locked Handset (HR Manager) | G202: INV000583847765 - Office Internet and Phone Service Charges July 2026 [paid via PL CC] | H202: INV000583847765 - Office Internet and Phone Service Charges July 2026 [paid via PL CC] | I202: 9300 - HUMAN RESOURCES [CTS] | J202: CTS | K202: 31.35 | L202: 0 | M202: 31.35
A203: 46210 | B203: 64530 | C203: Mobile Phones | D203: Payable Invoice | E203: Optus Billing Services Pty Ltd | F203: Optus Billing Services Pty Ltd - 0488287280 - Daniel Sobkowski (CONS) | G203: INV000583847765 - Office Internet and Phone Service Charges July 2026 [paid via PL CC] | H203: INV000583847765 - Office Internet and Phone Service Charges July 2026 [paid via PL CC] | I203: 9200 - INTEGRATION [INT] | J203: INTEGRATION | K203: 31.35 | L203: 0 | M203: 31.35
A204: 46210 | B204: 64530 | C204: Mobile Phones | D204: Payable Invoice | E204: Optus Billing Services Pty Ltd | F204: Optus Billing Services Pty Ltd - 0401365435 - CTS Tech 1 (In Bluekeeper Kit 2) | G204: INV000583847765 - Office Internet and Phone Service Charges July 2026 [paid via PL CC] | H204: INV000583847765 - Office Internet and Phone Service Charges July 2026 [paid via PL CC] | I204: 9100 - PRODUCTION [PRD] | J204: PRODUCTION | K204: 31.35 | L204: 0 | M204: 31.35
... A252: 46241 | B252: 64520 | C252: Office Phones | D252: Payable Invoice | E252: Optus Billing Services Pty Ltd | F252: Optus Billing Services Pty Ltd - Evolve Voice | G252: INV000589213447 - Office Internet and Phone Service Charges August 2026 [paid via PL CC] | H252: INV000589213447 - Office Internet and Phone Service Charges August 2026 [paid via PL CC] | I252: 9000 - OFFICE / ADMIN [CTS] | J252: CTS | K252: 171.71 | L252: 0 | M252: 171.71
A253: Total | K253: =SUM(K6:K252) -> 73882.86 | L253: =SUM(L6:L252) -> 15463.28 | M253: =SUM(M6:M252) -> 58419.58

Sheet Reconciliation
A1: Corporate Technology Services Pty Ltd
A2: Reconciliation
A3: Discretionary technology spend - FY2027 year to date (1 July 2026 to 31 August 2026)
A5: Ref | B5: Reconciling item | C5: Amount | D5: Agrees | E5: Basis
A6: R1 | B6: Total expenditure per the Transaction Listing | C6: ='Transaction Listing'!M253 -> 58419.58 | E6: Sum of 247 ledger lines.
A7: R2 | B7: Total expenditure per the Summary schedule | C7: =Summary!E15 -> 58419.58 | E7: Sum of the seven accounts.
A8: R3 | B8: Difference, R1 less R2 | C8: =C6-C7 -> 0 | D8: =IF(ROUND(C8,2)=0,"Yes","NO") -> Yes | E8: Must be nil. The two schedules are built from the same lines.
A9: R4 | B9: Total expenditure per the Supplier Analysis schedule | C9: ='Supplier Analysis'!B326 -> 58419.58 | E9: Sum of all suppliers, including lines with no supplier recorded.
A10: R5 | B10: Difference, R1 less R4 | C10: =C6-C9 -> 0 | D10: =IF(ROUND(C10,2)=0,"Yes","NO") -> Yes | E10: Must be nil.
A11: R6 | B11: Total expenditure per the Monthly Analysis schedule | C11: ='Monthly Analysis'!D13 -> 58419.58 | E11: Sum of all months.
A12: R7 | B12: Difference, R1 less R6 | C12: =C6-C11 -> 0 | D12: =IF(ROUND(C12,2)=0,"Yes","NO") -> Yes | E12: Must be nil.
A13: R8 | B13: Line count per the Transaction Listing | C13: 247 | E13: Against 3,771 lines in the full ledger export for the period.
A14: R9 | B14: Debits less credits per the Transaction Listing | C14: ='Transaction Listing'!K253-'Transaction Listing'!L253 -> 58419.58 | E14: Equals total expenditure, confirming these are expense lines with no credits netted off.
A15: R10 | B15: Difference, R9 less R1 | C15: =C14-C6 -> 0 | D15: =IF(ROUND(C15,2)=0,"Yes","NO") -> Yes | E15: Must be nil.
