Workbook
Name set_AsAt: Settings!$B$5
Name set_FYStart: Settings!$B$6
Name set_DealShare: Settings!$B$7
Name set_BigValue: Settings!$B$8
Name set_EarlyProb: Settings!$B$9
Name set_ClientHigh: Settings!$B$10
Name set_Top5High: Settings!$B$11
Name set_ScoreHigh: Settings!$B$12
Name set_ScoreMed: Settings!$B$13
Name rev_Amt: 'Data - Revenue'!$AD$2:$AD$4501
Name rev_Date: 'Data - Revenue'!$AE$2:$AE$4501
Name rev_Cnt: 'Data - Revenue'!$AF$2:$AF$4501
Name rev_Month: 'Data - Revenue'!$AG$2:$AG$4501
Name rev_Client: 'Data - Revenue'!$AH$2:$AH$4501
Name rev_CC: 'Data - Revenue'!$AI$2:$AI$4501
Name rev_FY: 'Data - Revenue'!$AJ$2:$AJ$4501
Name rev_New: 'Data - Revenue'!$AK$2:$AK$4501
Name p_Status: 'Data - Pipeline'!$T$2:$T$601
Name p_Value: 'Data - Pipeline'!$U$2:$U$601
Name p_Has: 'Data - Pipeline'!$V$2:$V$601
Name p_Prob: 'Data - Pipeline'!$W$2:$W$601
Name p_Weighted: 'Data - Pipeline'!$X$2:$X$601
Name p_Still: 'Data - Pipeline'!$Y$2:$Y$601
Name p_Month: 'Data - Pipeline'!$Z$2:$Z$601
Name p_CC: 'Data - Pipeline'!$AA$2:$AA$601
Name p_Stage: 'Data - Pipeline'!$AB$2:$AB$601
Name p_Client: 'Data - Pipeline'!$AC$2:$AC$601
Name p_Deal: 'Data - Pipeline'!$AD$2:$AD$601
Name p_Job: 'Data - Pipeline'!$AE$2:$AE$601
Name p_Score: 'Data - Pipeline'!$AL$2:$AL$601
Name p_Rating: 'Data - Pipeline'!$AM$2:$AM$601
Name p_Reg: 'Data - Pipeline'!$AN$2:$AN$601
Name p_Risk: 'Data - Pipeline'!$AO$2:$AO$601
Name p_Key: 'Data - Pipeline'!$AP$2:$AP$601
Name p_Flags: 'Data - Pipeline'!$AQ$2:$AQ$601

Sheet Dashboard
A1: Revenue Risk Profile - FY27
A2: ="Corporate Technology Services - data as at "&TEXT(set_AsAt,"d mmmm yyyy")&". Actual revenue from Xero via the revenue tracker; won, lost and pipeline from Zoho."
B4: Invoiced FYTD | E4: Won - still to invoice | H4: Weighted open pipeline | K4: Full-year forecast | N4: Win rate (value) | Q4: Largest client share
B5: =Departments!B13 | E5: =Departments!G13 | H5: =Departments!I13 | K5: =Monthly!E17 | N5: =Departments!F13 | Q5: ='Client Concentration'!C32
B7: RISK REGISTER SUMMARY | C7: Items | D7: Revenue at risk | G7: Rating | H7: Deal | N7: Revenue at risk | P7: Why
B8: High | C8: =COUNTIFS(p_Reg,1,p_Rating,B8) | D8: =SUMIFS(p_Risk,p_Reg,1,p_Rating,B8) | G8: ='Risk Register'!B5 | H8: ='Risk Register'!E5&" - "&'Risk Register'!F5 | N8: ='Risk Register'!L5 | P8: ='Risk Register'!N5
B9: Medium | C9: =COUNTIFS(p_Reg,1,p_Rating,B9) | D9: =SUMIFS(p_Risk,p_Reg,1,p_Rating,B9) | G9: ='Risk Register'!B6 | H9: ='Risk Register'!E6&" - "&'Risk Register'!F6 | N9: ='Risk Register'!L6 | P9: ='Risk Register'!N6
B10: Low | C10: =COUNTIFS(p_Reg,1,p_Rating,B10) | D10: =SUMIFS(p_Risk,p_Reg,1,p_Rating,B10) | G10: ='Risk Register'!B7 | H10: ='Risk Register'!E7&" - "&'Risk Register'!F7 | N10: ='Risk Register'!L7 | P10: ='Risk Register'!N7
G11: ='Risk Register'!B8 | H11: ='Risk Register'!E8&" - "&'Risk Register'!F8 | N11: ='Risk Register'!L8 | P11: ='Risk Register'!N8
G12: ='Risk Register'!B9 | H12: ='Risk Register'!E9&" - "&'Risk Register'!F9 | N12: ='Risk Register'!L9 | P12: ='Risk Register'!N9
B13: Weighted pipeline uses assumed stage probabilities. Forecast = invoiced + won still to invoice + weighted pipeline. See Risk Register for every item and Settings for thresholds.

Sheet Read Me
A1: How this workbook works
A2: Revenue Risk Profile - built from the FY27 Revenue Tracker.
B4: WHAT IT SHOWS
B5: Dashboard - the headline numbers, the risk summary, the five biggest risks and five charts.
B6: Monthly - actual invoiced revenue by month, plus won work still to invoice and weighted pipeline by expected invoice month, and the full-year forecast.
B7: Departments - invoiced, won, lost, win rate, still to invoice and pipeline by cost centre, and the open pipeline by stage.
B8: Client Concentration - top 20 clients by invoiced revenue, their share and cumulative share, and three concentration measures with a High/Medium/Low rating.
B9: Risk Register - every open deal and every won deal not fully invoiced, scored and sorted worst first, with the reason.
B10: Settings - the thresholds behind every rating. Change them there.
B12: REFRESH IT EACH MONTH (two copy / paste-values)
B13: 1. In the revenue tracker, do the Zoho dump and make sure it has recalculated (open it in Excel and save).
B14: 2. Tracker Finance sheet: select A6:AB4506, Ctrl+C. Here: Data - Revenue, click A1, Paste Special - Values.
B15: 3. Tracker Work Won sheet: select A4:R604, Ctrl+C. Here: Data - Pipeline, click A1, Paste Special - Values.
B16: 4. Settings: change 'Data as at' to the date the tracker data is as at. Everything else, charts included, updates by itself.
... B23: Open deals dated outside this financial year are in the Risk Register but not in the monthly grid.

Sheet Monthly
A1: Monthly Revenue and Forecast
A2: Actual invoiced (Xero via Finance) plus won work still to invoice and the weighted open pipeline, by expected invoice month.
A4: Month | B4: Invoiced (actual) | C4: Won - still to invoice | D4: Open pipeline - weighted | E4: Forecast | F4: Open pipeline - full | G4: Cumulative actual | H4: Cumulative forecast
A5: =EOMONTH(set_FYStart,0) | B5: =SUMIFS(rev_Amt,rev_Cnt,1,rev_Month,$A5) | C5: =SUMIFS(p_Still,p_Status,"Won",p_Month,$A5,p_Still,">0") | D5: =SUMIFS(p_Weighted,p_Status,"Open",p_Month,$A5) | E5: =B5+C5+D5 | F5: =SUMIFS(p_Value,p_Status,"Open",p_Month,$A5) | G5: =IF($A5<=EOMONTH(set_AsAt,0),SUM($B$5:B5),) | H5: =SUM($E$5:E5)
A6: =EOMONTH(set_FYStart,1) | B6: =SUMIFS(rev_Amt,rev_Cnt,1,rev_Month,$A6) | C6: =SUMIFS(p_Still,p_Status,"Won",p_Month,$A6,p_Still,">0") | D6: =SUMIFS(p_Weighted,p_Status,"Open",p_Month,$A6) | E6: =B6+C6+D6 | F6: =SUMIFS(p_Value,p_Status,"Open",p_Month,$A6) | G6: =IF($A6<=EOMONTH(set_AsAt,0),SUM($B$5:B6),) | H6: =SUM($E$5:E6)
A7: =EOMONTH(set_FYStart,2) | B7: =SUMIFS(rev_Amt,rev_Cnt,1,rev_Month,$A7) | C7: =SUMIFS(p_Still,p_Status,"Won",p_Month,$A7,p_Still,">0") | D7: =SUMIFS(p_Weighted,p_Status,"Open",p_Month,$A7) | E7: =B7+C7+D7 | F7: =SUMIFS(p_Value,p_Status,"Open",p_Month,$A7) | G7: =IF($A7<=EOMONTH(set_AsAt,0),SUM($B$5:B7),) | H7: =SUM($E$5:E7)
A8: =EOMONTH(set_FYStart,3) | B8: =SUMIFS(rev_Amt,rev_Cnt,1,rev_Month,$A8) | C8: =SUMIFS(p_Still,p_Status,"Won",p_Month,$A8,p_Still,">0") | D8: =SUMIFS(p_Weighted,p_Status,"Open",p_Month,$A8) | E8: =B8+C8+D8 | F8: =SUMIFS(p_Value,p_Status,"Open",p_Month,$A8) | G8: =IF($A8<=EOMONTH(set_AsAt,0),SUM($B$5:B8),) | H8: =SUM($E$5:E8)
A9: =EOMONTH(set_FYStart,4) | B9: =SUMIFS(rev_Amt,rev_Cnt,1,rev_Month,$A9) | C9: =SUMIFS(p_Still,p_Status,"Won",p_Month,$A9,p_Still,">0") | D9: =SUMIFS(p_Weighted,p_Status,"Open",p_Month,$A9) | E9: =B9+C9+D9 | F9: =SUMIFS(p_Value,p_Status,"Open",p_Month,$A9) | G9: =IF($A9<=EOMONTH(set_AsAt,0),SUM($B$5:B9),) | H9: =SUM($E$5:E9)
A10: =EOMONTH(set_FYStart,5) | B10: =SUMIFS(rev_Amt,rev_Cnt,1,rev_Month,$A10) | C10: =SUMIFS(p_Still,p_Status,"Won",p_Month,$A10,p_Still,">0") | D10: =SUMIFS(p_Weighted,p_Status,"Open",p_Month,$A10) | E10: =B10+C10+D10 | F10: =SUMIFS(p_Value,p_Status,"Open",p_Month,$A10) | G10: =IF($A10<=EOMONTH(set_AsAt,0),SUM($B$5:B10),) | H10: =SUM($E$5:E10)
A11: =EOMONTH(set_FYStart,6) | B11: =SUMIFS(rev_Amt,rev_Cnt,1,rev_Month,$A11) | C11: =SUMIFS(p_Still,p_Status,"Won",p_Month,$A11,p_Still,">0") | D11: =SUMIFS(p_Weighted,p_Status,"Open",p_Month,$A11) | E11: =B11+C11+D11 | F11: =SUMIFS(p_Value,p_Status,"Open",p_Month,$A11) | G11: =IF($A11<=EOMONTH(set_AsAt,0),SUM($B$5:B11),) | H11: =SUM($E$5:E11)
A12: =EOMONTH(set_FYStart,7) | B12: =SUMIFS(rev_Amt,rev_Cnt,1,rev_Month,$A12) | C12: =SUMIFS(p_Still,p_Status,"Won",p_Month,$A12,p_Still,">0") | D12: =SUMIFS(p_Weighted,p_Status,"Open",p_Month,$A12) | E12: =B12+C12+D12 | F12: =SUMIFS(p_Value,p_Status,"Open",p_Month,$A12) | G12: =IF($A12<=EOMONTH(set_AsAt,0),SUM($B$5:B12),) | H12: =SUM($E$5:E12)
A13: =EOMONTH(set_FYStart,8) | B13: =SUMIFS(rev_Amt,rev_Cnt,1,rev_Month,$A13) | C13: =SUMIFS(p_Still,p_Status,"Won",p_Month,$A13,p_Still,">0") | D13: =SUMIFS(p_Weighted,p_Status,"Open",p_Month,$A13) | E13: =B13+C13+D13 | F13: =SUMIFS(p_Value,p_Status,"Open",p_Month,$A13) | G13: =IF($A13<=EOMONTH(set_AsAt,0),SUM($B$5:B13),) | H13: =SUM($E$5:E13)
A14: =EOMONTH(set_FYStart,9) | B14: =SUMIFS(rev_Amt,rev_Cnt,1,rev_Month,$A14) | C14: =SUMIFS(p_Still,p_Status,"Won",p_Month,$A14,p_Still,">0") | D14: =SUMIFS(p_Weighted,p_Status,"Open",p_Month,$A14) | E14: =B14+C14+D14 | F14: =SUMIFS(p_Value,p_Status,"Open",p_Month,$A14) | G14: =IF($A14<=EOMONTH(set_AsAt,0),SUM($B$5:B14),) | H14: =SUM($E$5:E14)
A15: =EOMONTH(set_FYStart,10) | B15: =SUMIFS(rev_Amt,rev_Cnt,1,rev_Month,$A15) | C15: =SUMIFS(p_Still,p_Status,"Won",p_Month,$A15,p_Still,">0") | D15: =SUMIFS(p_Weighted,p_Status,"Open",p_Month,$A15) | E15: =B15+C15+D15 | F15: =SUMIFS(p_Value,p_Status,"Open",p_Month,$A15) | G15: =IF($A15<=EOMONTH(set_AsAt,0),SUM($B$5:B15),) | H15: =SUM($E$5:E15)
A16: =EOMONTH(set_FYStart,11) | B16: =SUMIFS(rev_Amt,rev_Cnt,1,rev_Month,$A16) | C16: =SUMIFS(p_Still,p_Status,"Won",p_Month,$A16,p_Still,">0") | D16: =SUMIFS(p_Weighted,p_Status,"Open",p_Month,$A16) | E16: =B16+C16+D16 | F16: =SUMIFS(p_Value,p_Status,"Open",p_Month,$A16) | G16: =IF($A16<=EOMONTH(set_AsAt,0),SUM($B$5:B16),) | H16: =SUM($E$5:E16)
A17: TOTAL | B17: =SUM(B5:B16) | C17: =SUM(C5:C16) | D17: =SUM(D5:D16) | E17: =SUM(E5:E16) | F17: =SUM(F5:F16)
A19: Won - still to invoice counts only positive balances. In months already gone it is billing to chase, not future revenue. Weighted = deal value x stage probability (tracker Lists AA:AB - assumptions). Open deals dated outside this FY are not in the grid.

Sheet Departments
A1: By Cost Centre and Pipeline Stage
A2: Where the revenue comes from and where the pipeline sits.
A4: 1. BY COST CENTRE - financial year to date
A5: Cost Centre | B5: Invoiced FYTD | C5: Share | D5: Won (FY) | E5: Lost (FY) | F5: Win rate (value) | G5: Won - still to invoice | H5: Open pipeline | I5: Weighted pipeline | J5: Rest-of-year forecast
A6: ONSITE | B6: =SUMIFS(rev_Amt,rev_FY,1,rev_CC,$A6) | C6: =IFERROR(B6/$B$13,0) | D6: =SUMIFS(p_Value,p_Status,"Won",p_CC,$A6) | E6: =SUMIFS(p_Value,p_Status,"Lost",p_CC,$A6) | F6: =IFERROR(D6/(D6+E6),"") | G6: =SUMIFS(p_Still,p_Status,"Won",p_Still,">0",p_CC,$A6) | H6: =SUMIFS(p_Value,p_Status,"Open",p_CC,$A6) | I6: =SUMIFS(p_Weighted,p_Status,"Open",p_CC,$A6) | J6: =G6+I6
A7: PRODUCTION | B7: =SUMIFS(rev_Amt,rev_FY,1,rev_CC,$A7) | C7: =IFERROR(B7/$B$13,0) | D7: =SUMIFS(p_Value,p_Status,"Won",p_CC,$A7) | E7: =SUMIFS(p_Value,p_Status,"Lost",p_CC,$A7) | F7: =IFERROR(D7/(D7+E7),"") | G7: =SUMIFS(p_Still,p_Status,"Won",p_Still,">0",p_CC,$A7) | H7: =SUMIFS(p_Value,p_Status,"Open",p_CC,$A7) | I7: =SUMIFS(p_Weighted,p_Status,"Open",p_CC,$A7) | J7: =G7+I7
A8: VIDEO | B8: =SUMIFS(rev_Amt,rev_FY,1,rev_CC,$A8) | C8: =IFERROR(B8/$B$13,0) | D8: =SUMIFS(p_Value,p_Status,"Won",p_CC,$A8) | E8: =SUMIFS(p_Value,p_Status,"Lost",p_CC,$A8) | F8: =IFERROR(D8/(D8+E8),"") | G8: =SUMIFS(p_Still,p_Status,"Won",p_Still,">0",p_CC,$A8) | H8: =SUMIFS(p_Value,p_Status,"Open",p_CC,$A8) | I8: =SUMIFS(p_Weighted,p_Status,"Open",p_CC,$A8) | J8: =G8+I8
A9: INTEGRATION | B9: =SUMIFS(rev_Amt,rev_FY,1,rev_CC,$A9) | C9: =IFERROR(B9/$B$13,0) | D9: =SUMIFS(p_Value,p_Status,"Won",p_CC,$A9) | E9: =SUMIFS(p_Value,p_Status,"Lost",p_CC,$A9) | F9: =IFERROR(D9/(D9+E9),"") | G9: =SUMIFS(p_Still,p_Status,"Won",p_Still,">0",p_CC,$A9) | H9: =SUMIFS(p_Value,p_Status,"Open",p_CC,$A9) | I9: =SUMIFS(p_Weighted,p_Status,"Open",p_CC,$A9) | J9: =G9+I9
A10: CONSULTING | B10: =SUMIFS(rev_Amt,rev_FY,1,rev_CC,$A10) | C10: =IFERROR(B10/$B$13,0) | D10: =SUMIFS(p_Value,p_Status,"Won",p_CC,$A10) | E10: =SUMIFS(p_Value,p_Status,"Lost",p_CC,$A10) | F10: =IFERROR(D10/(D10+E10),"") | G10: =SUMIFS(p_Still,p_Status,"Won",p_Still,">0",p_CC,$A10) | H10: =SUMIFS(p_Value,p_Status,"Open",p_CC,$A10) | I10: =SUMIFS(p_Weighted,p_Status,"Open",p_CC,$A10) | J10: =G10+I10
A11: CTS | B11: =SUMIFS(rev_Amt,rev_FY,1,rev_CC,$A11) | C11: =IFERROR(B11/$B$13,0) | D11: =SUMIFS(p_Value,p_Status,"Won",p_CC,$A11) | E11: =SUMIFS(p_Value,p_Status,"Lost",p_CC,$A11) | F11: =IFERROR(D11/(D11+E11),"") | G11: =SUMIFS(p_Still,p_Status,"Won",p_Still,">0",p_CC,$A11) | H11: =SUMIFS(p_Value,p_Status,"Open",p_CC,$A11) | I11: =SUMIFS(p_Weighted,p_Status,"Open",p_CC,$A11) | J11: =G11+I11
A12: Other / not set | B12: =SUMIFS(rev_Amt,rev_FY,1)-SUM(B6:B11) | C12: =IFERROR(B12/$B$13,0) | D12: =SUMIFS(p_Value,p_Status,"Won")-SUM(D6:D11) | E12: =SUMIFS(p_Value,p_Status,"Lost")-SUM(E6:E11) | F12: =IFERROR(D12/(D12+E12),"") | G12: =SUMIFS(p_Still,p_Status,"Won",p_Still,">0")-SUM(G6:G11) | H12: =SUMIFS(p_Value,p_Status,"Open")-SUM(H6:H11) | I12: =SUMIFS(p_Weighted,p_Status,"Open")-SUM(I6:I11) | J12: =G12+I12
A13: TOTAL | B13: =SUM(B6:B12) | C13: =SUM(C6:C12) | D13: =SUM(D6:D12) | E13: =SUM(E6:E12) | F13: =IFERROR(D13/(D13+E13),"") | G13: =SUM(G6:G12) | H13: =SUM(H6:H12) | I13: =SUM(I6:I12) | J13: =SUM(J6:J12)
A16: 2. OPEN PIPELINE BY STAGE
A17: Stage | B17: Deals | C17: Full value | D17: Weighted value | E17: Probability | F17: Share of pipeline
A18: Building Value Proposition | B18: =COUNTIFS(p_Status,"Open",p_Stage,$A18) | C18: =SUMIFS(p_Value,p_Status,"Open",p_Stage,$A18) | D18: =SUMIFS(p_Weighted,p_Status,"Open",p_Stage,$A18) | E18: =IFERROR(D18/C18,0) | F18: =IFERROR(C18/$C$22,0)
A19: Proposal Sent | B19: =COUNTIFS(p_Status,"Open",p_Stage,$A19) | C19: =SUMIFS(p_Value,p_Status,"Open",p_Stage,$A19) | D19: =SUMIFS(p_Weighted,p_Status,"Open",p_Stage,$A19) | E19: =IFERROR(D19/C19,0) | F19: =IFERROR(C19/$C$22,0)
A20: Negotiation/Review | B20: =COUNTIFS(p_Status,"Open",p_Stage,$A20) | C20: =SUMIFS(p_Value,p_Status,"Open",p_Stage,$A20) | D20: =SUMIFS(p_Weighted,p_Status,"Open",p_Stage,$A20) | E20: =IFERROR(D20/C20,0) | F20: =IFERROR(C20/$C$22,0)
A21: Verbal Approval | B21: =COUNTIFS(p_Status,"Open",p_Stage,$A21) | C21: =SUMIFS(p_Value,p_Status,"Open",p_Stage,$A21) | D21: =SUMIFS(p_Weighted,p_Status,"Open",p_Stage,$A21) | E21: =IFERROR(D21/C21,0) | F21: =IFERROR(C21/$C$22,0)
A22: TOTAL OPEN | B22: =SUM(B18:B21) | C22: =SUM(C18:C21) | D22: =SUM(D18:D21) | E22: =IFERROR(D22/C22,0) | F22: =SUM(F18:F21)

Sheet Client Concentration
A1: Client Concentration
A2: How dependent FYTD invoiced revenue is on a few clients. Client names are grouped as typed on the tracker (upper case, trimmed).
A4: 1. TOP CLIENTS - invoiced financial year to date
A5: Rank | B5: Client | C5: Invoiced FYTD | D5: Share | E5: Cumulative share | F5: Invoices | L5: Client (all) | M5: No. | N5: Sort key | O5: Share | P5: Share squared
A6: 1 | B6: =IFERROR(INDEX($L$6:$L$305,MATCH(LARGE($N$6:$N$305,1),$N$6:$N$305,0)),"") | C6: =IF(B6="","",SUMIFS(rev_Amt,rev_FY,1,rev_Client,B6)) | D6: =IF(B6="","",IFERROR(C6/$C$28,0)) | E6: =IF(B6="","",SUM($D$6:D6)) | F6: =IF(B6="","",COUNTIFS(rev_FY,1,rev_Client,B6)) | L6: =IFERROR(INDEX(rev_Client,MATCH(1,rev_New,0)),"") | M6: =IF(L6="","",1) | N6: =IF(L6="","",SUMIFS(rev_Amt,rev_FY,1,rev_Client,L6)+1/1E+6) | O6: =IF(L6="","",IFERROR(SUMIFS(rev_Amt,rev_FY,1,rev_Client,L6)/$C$28,0)) | P6: =IF(O6="",0,O6^2)
A7: 2 | B7: =IFERROR(INDEX($L$6:$L$305,MATCH(LARGE($N$6:$N$305,2),$N$6:$N$305,0)),"") | C7: =IF(B7="","",SUMIFS(rev_Amt,rev_FY,1,rev_Client,B7)) | D7: =IF(B7="","",IFERROR(C7/$C$28,0)) | E7: =IF(B7="","",SUM($D$6:D7)) | F7: =IF(B7="","",COUNTIFS(rev_FY,1,rev_Client,B7)) | L7: =IFERROR(INDEX(rev_Client,MATCH(2,rev_New,0)),"") | M7: =IF(L7="","",2) | N7: =IF(L7="","",SUMIFS(rev_Amt,rev_FY,1,rev_Client,L7)+2/1E+6) | O7: =IF(L7="","",IFERROR(SUMIFS(rev_Amt,rev_FY,1,rev_Client,L7)/$C$28,0)) | P7: =IF(O7="",0,O7^2)
A8: 3 | B8: =IFERROR(INDEX($L$6:$L$305,MATCH(LARGE($N$6:$N$305,3),$N$6:$N$305,0)),"") | C8: =IF(B8="","",SUMIFS(rev_Amt,rev_FY,1,rev_Client,B8)) | D8: =IF(B8="","",IFERROR(C8/$C$28,0)) | E8: =IF(B8="","",SUM($D$6:D8)) | F8: =IF(B8="","",COUNTIFS(rev_FY,1,rev_Client,B8)) | L8: =IFERROR(INDEX(rev_Client,MATCH(3,rev_New,0)),"") | M8: =IF(L8="","",3) | N8: =IF(L8="","",SUMIFS(rev_Amt,rev_FY,1,rev_Client,L8)+3/1E+6) | O8: =IF(L8="","",IFERROR(SUMIFS(rev_Amt,rev_FY,1,rev_Client,L8)/$C$28,0)) | P8: =IF(O8="",0,O8^2)
A9: 4 | B9: =IFERROR(INDEX($L$6:$L$305,MATCH(LARGE($N$6:$N$305,4),$N$6:$N$305,0)),"") | C9: =IF(B9="","",SUMIFS(rev_Amt,rev_FY,1,rev_Client,B9)) | D9: =IF(B9="","",IFERROR(C9/$C$28,0)) | E9: =IF(B9="","",SUM($D$6:D9)) | F9: =IF(B9="","",COUNTIFS(rev_FY,1,rev_Client,B9)) | L9: =IFERROR(INDEX(rev_Client,MATCH(4,rev_New,0)),"") | M9: =IF(L9="","",4) | N9: =IF(L9="","",SUMIFS(rev_Amt,rev_FY,1,rev_Client,L9)+4/1E+6) | O9: =IF(L9="","",IFERROR(SUMIFS(rev_Amt,rev_FY,1,rev_Client,L9)/$C$28,0)) | P9: =IF(O9="",0,O9^2)
A10: 5 | B10: =IFERROR(INDEX($L$6:$L$305,MATCH(LARGE($N$6:$N$305,5),$N$6:$N$305,0)),"") | C10: =IF(B10="","",SUMIFS(rev_Amt,rev_FY,1,rev_Client,B10)) | D10: =IF(B10="","",IFERROR(C10/$C$28,0)) | E10: =IF(B10="","",SUM($D$6:D10)) | F10: =IF(B10="","",COUNTIFS(rev_FY,1,rev_Client,B10)) | L10: =IFERROR(INDEX(rev_Client,MATCH(5,rev_New,0)),"") | M10: =IF(L10="","",5) | N10: =IF(L10="","",SUMIFS(rev_Amt,rev_FY,1,rev_Client,L10)+5/1E+6) | O10: =IF(L10="","",IFERROR(SUMIFS(rev_Amt,rev_FY,1,rev_Client,L10)/$C$28,0)) | P10: =IF(O10="",0,O10^2)
A11: 6 | B11: =IFERROR(INDEX($L$6:$L$305,MATCH(LARGE($N$6:$N$305,6),$N$6:$N$305,0)),"") | C11: =IF(B11="","",SUMIFS(rev_Amt,rev_FY,1,rev_Client,B11)) | D11: =IF(B11="","",IFERROR(C11/$C$28,0)) | E11: =IF(B11="","",SUM($D$6:D11)) | F11: =IF(B11="","",COUNTIFS(rev_FY,1,rev_Client,B11)) | L11: =IFERROR(INDEX(rev_Client,MATCH(6,rev_New,0)),"") | M11: =IF(L11="","",6) | N11: =IF(L11="","",SUMIFS(rev_Amt,rev_FY,1,rev_Client,L11)+6/1E+6) | O11: =IF(L11="","",IFERROR(SUMIFS(rev_Amt,rev_FY,1,rev_Client,L11)/$C$28,0)) | P11: =IF(O11="",0,O11^2)
A12: 7 | B12: =IFERROR(INDEX($L$6:$L$305,MATCH(LARGE($N$6:$N$305,7),$N$6:$N$305,0)),"") | C12: =IF(B12="","",SUMIFS(rev_Amt,rev_FY,1,rev_Client,B12)) | D12: =IF(B12="","",IFERROR(C12/$C$28,0)) | E12: =IF(B12="","",SUM($D$6:D12)) | F12: =IF(B12="","",COUNTIFS(rev_FY,1,rev_Client,B12)) | L12: =IFERROR(INDEX(rev_Client,MATCH(7,rev_New,0)),"") | M12: =IF(L12="","",7) | N12: =IF(L12="","",SUMIFS(rev_Amt,rev_FY,1,rev_Client,L12)+7/1E+6) | O12: =IF(L12="","",IFERROR(SUMIFS(rev_Amt,rev_FY,1,rev_Client,L12)/$C$28,0)) | P12: =IF(O12="",0,O12^2)
A13: 8 | B13: =IFERROR(INDEX($L$6:$L$305,MATCH(LARGE($N$6:$N$305,8),$N$6:$N$305,0)),"") | C13: =IF(B13="","",SUMIFS(rev_Amt,rev_FY,1,rev_Client,B13)) | D13: =IF(B13="","",IFERROR(C13/$C$28,0)) | E13: =IF(B13="","",SUM($D$6:D13)) | F13: =IF(B13="","",COUNTIFS(rev_FY,1,rev_Client,B13)) | L13: =IFERROR(INDEX(rev_Client,MATCH(8,rev_New,0)),"") | M13: =IF(L13="","",8) | N13: =IF(L13="","",SUMIFS(rev_Amt,rev_FY,1,rev_Client,L13)+8/1E+6) | O13: =IF(L13="","",IFERROR(SUMIFS(rev_Amt,rev_FY,1,rev_Client,L13)/$C$28,0)) | P13: =IF(O13="",0,O13^2)
A14: 9 | B14: =IFERROR(INDEX($L$6:$L$305,MATCH(LARGE($N$6:$N$305,9),$N$6:$N$305,0)),"") | C14: =IF(B14="","",SUMIFS(rev_Amt,rev_FY,1,rev_Client,B14)) | D14: =IF(B14="","",IFERROR(C14/$C$28,0)) | E14: =IF(B14="","",SUM($D$6:D14)) | F14: =IF(B14="","",COUNTIFS(rev_FY,1,rev_Client,B14)) | L14: =IFERROR(INDEX(rev_Client,MATCH(9,rev_New,0)),"") | M14: =IF(L14="","",9) | N14: =IF(L14="","",SUMIFS(rev_Amt,rev_FY,1,rev_Client,L14)+9/1E+6) | O14: =IF(L14="","",IFERROR(SUMIFS(rev_Amt,rev_FY,1,rev_Client,L14)/$C$28,0)) | P14: =IF(O14="",0,O14^2)
A15: 10 | B15: =IFERROR(INDEX($L$6:$L$305,MATCH(LARGE($N$6:$N$305,10),$N$6:$N$305,0)),"") | C15: =IF(B15="","",SUMIFS(rev_Amt,rev_FY,1,rev_Client,B15)) | D15: =IF(B15="","",IFERROR(C15/$C$28,0)) | E15: =IF(B15="","",SUM($D$6:D15)) | F15: =IF(B15="","",COUNTIFS(rev_FY,1,rev_Client,B15)) | L15: =IFERROR(INDEX(rev_Client,MATCH(10,rev_New,0)),"") | M15: =IF(L15="","",10) | N15: =IF(L15="","",SUMIFS(rev_Amt,rev_FY,1,rev_Client,L15)+10/1E+6) | O15: =IF(L15="","",IFERROR(SUMIFS(rev_Amt,rev_FY,1,rev_Client,L15)/$C$28,0)) | P15: =IF(O15="",0,O15^2)
A16: 11 | B16: =IFERROR(INDEX($L$6:$L$305,MATCH(LARGE($N$6:$N$305,11),$N$6:$N$305,0)),"") | C16: =IF(B16="","",SUMIFS(rev_Amt,rev_FY,1,rev_Client,B16)) | D16: =IF(B16="","",IFERROR(C16/$C$28,0)) | E16: =IF(B16="","",SUM($D$6:D16)) | F16: =IF(B16="","",COUNTIFS(rev_FY,1,rev_Client,B16)) | L16: =IFERROR(INDEX(rev_Client,MATCH(11,rev_New,0)),"") | M16: =IF(L16="","",11) | N16: =IF(L16="","",SUMIFS(rev_Amt,rev_FY,1,rev_Client,L16)+11/1E+6) | O16: =IF(L16="","",IFERROR(SUMIFS(rev_Amt,rev_FY,1,rev_Client,L16)/$C$28,0)) | P16: =IF(O16="",0,O16^2)
A17: 12 | B17: =IFERROR(INDEX($L$6:$L$305,MATCH(LARGE($N$6:$N$305,12),$N$6:$N$305,0)),"") | C17: =IF(B17="","",SUMIFS(rev_Amt,rev_FY,1,rev_Client,B17)) | D17: =IF(B17="","",IFERROR(C17/$C$28,0)) | E17: =IF(B17="","",SUM($D$6:D17)) | F17: =IF(B17="","",COUNTIFS(rev_FY,1,rev_Client,B17)) | L17: =IFERROR(INDEX(rev_Client,MATCH(12,rev_New,0)),"") | M17: =IF(L17="","",12) | N17: =IF(L17="","",SUMIFS(rev_Amt,rev_FY,1,rev_Client,L17)+12/1E+6) | O17: =IF(L17="","",IFERROR(SUMIFS(rev_Amt,rev_FY,1,rev_Client,L17)/$C$28,0)) | P17: =IF(O17="",0,O17^2)
A18: 13 | B18: =IFERROR(INDEX($L$6:$L$305,MATCH(LARGE($N$6:$N$305,13),$N$6:$N$305,0)),"") | C18: =IF(B18="","",SUMIFS(rev_Amt,rev_FY,1,rev_Client,B18)) | D18: =IF(B18="","",IFERROR(C18/$C$28,0)) | E18: =IF(B18="","",SUM($D$6:D18)) | F18: =IF(B18="","",COUNTIFS(rev_FY,1,rev_Client,B18)) | L18: =IFERROR(INDEX(rev_Client,MATCH(13,rev_New,0)),"") | M18: =IF(L18="","",13) | N18: =IF(L18="","",SUMIFS(rev_Amt,rev_FY,1,rev_Client,L18)+13/1E+6) | O18: =IF(L18="","",IFERROR(SUMIFS(rev_Amt,rev_FY,1,rev_Client,L18)/$C$28,0)) | P18: =IF(O18="",0,O18^2)
A19: 14 | B19: =IFERROR(INDEX($L$6:$L$305,MATCH(LARGE($N$6:$N$305,14),$N$6:$N$305,0)),"") | C19: =IF(B19="","",SUMIFS(rev_Amt,rev_FY,1,rev_Client,B19)) | D19: =IF(B19="","",IFERROR(C19/$C$28,0)) | E19: =IF(B19="","",SUM($D$6:D19)) | F19: =IF(B19="","",COUNTIFS(rev_FY,1,rev_Client,B19)) | L19: =IFERROR(INDEX(rev_Client,MATCH(14,rev_New,0)),"") | M19: =IF(L19="","",14) | N19: =IF(L19="","",SUMIFS(rev_Amt,rev_FY,1,rev_Client,L19)+14/1E+6) | O19: =IF(L19="","",IFERROR(SUMIFS(rev_Amt,rev_FY,1,rev_Client,L19)/$C$28,0)) | P19: =IF(O19="",0,O19^2)
A20: 15 | B20: =IFERROR(INDEX($L$6:$L$305,MATCH(LARGE($N$6:$N$305,15),$N$6:$N$305,0)),"") | C20: =IF(B20="","",SUMIFS(rev_Amt,rev_FY,1,rev_Client,B20)) | D20: =IF(B20="","",IFERROR(C20/$C$28,0)) | E20: =IF(B20="","",SUM($D$6:D20)) | F20: =IF(B20="","",COUNTIFS(rev_FY,1,rev_Client,B20)) | L20: =IFERROR(INDEX(rev_Client,MATCH(15,rev_New,0)),"") | M20: =IF(L20="","",15) | N20: =IF(L20="","",SUMIFS(rev_Amt,rev_FY,1,rev_Client,L20)+15/1E+6) | O20: =IF(L20="","",IFERROR(SUMIFS(rev_Amt,rev_FY,1,rev_Client,L20)/$C$28,0)) | P20: =IF(O20="",0,O20^2)
A21: 16 | B21: =IFERROR(INDEX($L$6:$L$305,MATCH(LARGE($N$6:$N$305,16),$N$6:$N$305,0)),"") | C21: =IF(B21="","",SUMIFS(rev_Amt,rev_FY,1,rev_Client,B21)) | D21: =IF(B21="","",IFERROR(C21/$C$28,0)) | E21: =IF(B21="","",SUM($D$6:D21)) | F21: =IF(B21="","",COUNTIFS(rev_FY,1,rev_Client,B21)) | L21: =IFERROR(INDEX(rev_Client,MATCH(16,rev_New,0)),"") | M21: =IF(L21="","",16) | N21: =IF(L21="","",SUMIFS(rev_Amt,rev_FY,1,rev_Client,L21)+16/1E+6) | O21: =IF(L21="","",IFERROR(SUMIFS(rev_Amt,rev_FY,1,rev_Client,L21)/$C$28,0)) | P21: =IF(O21="",0,O21^2)
A22: 17 | B22: =IFERROR(INDEX($L$6:$L$305,MATCH(LARGE($N$6:$N$305,17),$N$6:$N$305,0)),"") | C22: =IF(B22="","",SUMIFS(rev_Amt,rev_FY,1,rev_Client,B22)) | D22: =IF(B22="","",IFERROR(C22/$C$28,0)) | E22: =IF(B22="","",SUM($D$6:D22)) | F22: =IF(B22="","",COUNTIFS(rev_FY,1,rev_Client,B22)) | L22: =IFERROR(INDEX(rev_Client,MATCH(17,rev_New,0)),"") | M22: =IF(L22="","",17) | N22: =IF(L22="","",SUMIFS(rev_Amt,rev_FY,1,rev_Client,L22)+17/1E+6) | O22: =IF(L22="","",IFERROR(SUMIFS(rev_Amt,rev_FY,1,rev_Client,L22)/$C$28,0)) | P22: =IF(O22="",0,O22^2)
A23: 18 | B23: =IFERROR(INDEX($L$6:$L$305,MATCH(LARGE($N$6:$N$305,18),$N$6:$N$305,0)),"") | C23: =IF(B23="","",SUMIFS(rev_Amt,rev_FY,1,rev_Client,B23)) | D23: =IF(B23="","",IFERROR(C23/$C$28,0)) | E23: =IF(B23="","",SUM($D$6:D23)) | F23: =IF(B23="","",COUNTIFS(rev_FY,1,rev_Client,B23)) | L23: =IFERROR(INDEX(rev_Client,MATCH(18,rev_New,0)),"") | M23: =IF(L23="","",18) | N23: =IF(L23="","",SUMIFS(rev_Amt,rev_FY,1,rev_Client,L23)+18/1E+6) | O23: =IF(L23="","",IFERROR(SUMIFS(rev_Amt,rev_FY,1,rev_Client,L23)/$C$28,0)) | P23: =IF(O23="",0,O23^2)
A24: 19 | B24: =IFERROR(INDEX($L$6:$L$305,MATCH(LARGE($N$6:$N$305,19),$N$6:$N$305,0)),"") | C24: =IF(B24="","",SUMIFS(rev_Amt,rev_FY,1,rev_Client,B24)) | D24: =IF(B24="","",IFERROR(C24/$C$28,0)) | E24: =IF(B24="","",SUM($D$6:D24)) | F24: =IF(B24="","",COUNTIFS(rev_FY,1,rev_Client,B24)) | L24: =IFERROR(INDEX(rev_Client,MATCH(19,rev_New,0)),"") | M24: =IF(L24="","",19) | N24: =IF(L24="","",SUMIFS(rev_Amt,rev_FY,1,rev_Client,L24)+19/1E+6) | O24: =IF(L24="","",IFERROR(SUMIFS(rev_Amt,rev_FY,1,rev_Client,L24)/$C$28,0)) | P24: =IF(O24="",0,O24^2)
A25: 20 | B25: =IFERROR(INDEX($L$6:$L$305,MATCH(LARGE($N$6:$N$305,20),$N$6:$N$305,0)),"") | C25: =IF(B25="","",SUMIFS(rev_Amt,rev_FY,1,rev_Client,B25)) | D25: =IF(B25="","",IFERROR(C25/$C$28,0)) | E25: =IF(B25="","",SUM($D$6:D25)) | F25: =IF(B25="","",COUNTIFS(rev_FY,1,rev_Client,B25)) | L25: =IFERROR(INDEX(rev_Client,MATCH(20,rev_New,0)),"") | M25: =IF(L25="","",20) | N25: =IF(L25="","",SUMIFS(rev_Amt,rev_FY,1,rev_Client,L25)+20/1E+6) | O25: =IF(L25="","",IFERROR(SUMIFS(rev_Amt,rev_FY,1,rev_Client,L25)/$C$28,0)) | P25: =IF(O25="",0,O25^2)
L26: =IFERROR(INDEX(rev_Client,MATCH(21,rev_New,0)),"") | M26: =IF(L26="","",21) | N26: =IF(L26="","",SUMIFS(rev_Amt,rev_FY,1,rev_Client,L26)+21/1E+6) | O26: =IF(L26="","",IFERROR(SUMIFS(rev_Amt,rev_FY,1,rev_Client,L26)/$C$28,0)) | P26: =IF(O26="",0,O26^2)
B27: All other clients | C27: =C28-SUM(C6:C25) | D27: =IFERROR(C27/C28,0) | L27: =IFERROR(INDEX(rev_Client,MATCH(22,rev_New,0)),"") | M27: =IF(L27="","",22) | N27: =IF(L27="","",SUMIFS(rev_Amt,rev_FY,1,rev_Client,L27)+22/1E+6) | O27: =IF(L27="","",IFERROR(SUMIFS(rev_Amt,rev_FY,1,rev_Client,L27)/$C$28,0)) | P27: =IF(O27="",0,O27^2)
B28: TOTAL INVOICED FYTD | C28: =SUMIFS(rev_Amt,rev_FY,1) | L28: =IFERROR(INDEX(rev_Client,MATCH(23,rev_New,0)),"") | M28: =IF(L28="","",23) | N28: =IF(L28="","",SUMIFS(rev_Amt,rev_FY,1,rev_Client,L28)+23/1E+6) | O28: =IF(L28="","",IFERROR(SUMIFS(rev_Amt,rev_FY,1,rev_Client,L28)/$C$28,0)) | P28: =IF(O28="",0,O28^2)
L29: =IFERROR(INDEX(rev_Client,MATCH(24,rev_New,0)),"") | M29: =IF(L29="","",24) | N29: =IF(L29="","",SUMIFS(rev_Amt,rev_FY,1,rev_Client,L29)+24/1E+6) | O29: =IF(L29="","",IFERROR(SUMIFS(rev_Amt,rev_FY,1,rev_Client,L29)/$C$28,0)) | P29: =IF(O29="",0,O29^2)
A30: 2. CONCENTRATION MEASURES | L30: =IFERROR(INDEX(rev_Client,MATCH(25,rev_New,0)),"") | M30: =IF(L30="","",25) | N30: =IF(L30="","",SUMIFS(rev_Amt,rev_FY,1,rev_Client,L30)+25/1E+6) | O30: =IF(L30="","",IFERROR(SUMIFS(rev_Amt,rev_FY,1,rev_Client,L30)/$C$28,0)) | P30: =IF(O30="",0,O30^2)
B31: Clients invoiced FYTD | C31: =MAX($M$6:$M$305) | L31: =IFERROR(INDEX(rev_Client,MATCH(26,rev_New,0)),"") | M31: =IF(L31="","",26) | N31: =IF(L31="","",SUMIFS(rev_Amt,rev_FY,1,rev_Client,L31)+26/1E+6) | O31: =IF(L31="","",IFERROR(SUMIFS(rev_Amt,rev_FY,1,rev_Client,L31)/$C$28,0)) | P31: =IF(O31="",0,O31^2)
B32: Largest client share | C32: =D6 | D32: =IF(D6>=set_ClientHigh,"High",IF(D6>=set_ClientHigh*0.6,"Medium","Low")) | L32: =IFERROR(INDEX(rev_Client,MATCH(27,rev_New,0)),"") | M32: =IF(L32="","",27) | N32: =IF(L32="","",SUMIFS(rev_Amt,rev_FY,1,rev_Client,L32)+27/1E+6) | O32: =IF(L32="","",IFERROR(SUMIFS(rev_Amt,rev_FY,1,rev_Client,L32)/$C$28,0)) | P32: =IF(O32="",0,O32^2)
B33: Top 5 clients share | C33: =IFERROR(SUM(C6:C10)/C28,0) | D33: =IF(C33>=set_Top5High,"High",IF(C33>=set_Top5High*0.75,"Medium","Low")) | L33: =IFERROR(INDEX(rev_Client,MATCH(28,rev_New,0)),"") | M33: =IF(L33="","",28) | N33: =IF(L33="","",SUMIFS(rev_Amt,rev_FY,1,rev_Client,L33)+28/1E+6) | O33: =IF(L33="","",IFERROR(SUMIFS(rev_Amt,rev_FY,1,rev_Client,L33)/$C$28,0)) | P33: =IF(O33="",0,O33^2)
B34: Top 10 clients share | C34: =IFERROR(SUM(C6:C15)/C28,0) | L34: =IFERROR(INDEX(rev_Client,MATCH(29,rev_New,0)),"") | M34: =IF(L34="","",29) | N34: =IF(L34="","",SUMIFS(rev_Amt,rev_FY,1,rev_Client,L34)+29/1E+6) | O34: =IF(L34="","",IFERROR(SUMIFS(rev_Amt,rev_FY,1,rev_Client,L34)/$C$28,0)) | P34: =IF(O34="",0,O34^2)
B35: Herfindahl index (0-10,000) | C35: =ROUND(SUM($P$6:$P$305)*10000,0) | D35: =IF(C35>=2500,"High",IF(C35>=1500,"Medium","Low")) | L35: =IFERROR(INDEX(rev_Client,MATCH(30,rev_New,0)),"") | M35: =IF(L35="","",30) | N35: =IF(L35="","",SUMIFS(rev_Amt,rev_FY,1,rev_Client,L35)+30/1E+6) | O35: =IF(L35="","",IFERROR(SUMIFS(rev_Amt,rev_FY,1,rev_Client,L35)/$C$28,0)) | P35: =IF(O35="",0,O35^2)
L36: =IFERROR(INDEX(rev_Client,MATCH(31,rev_New,0)),"") | M36: =IF(L36="","",31) | N36: =IF(L36="","",SUMIFS(rev_Amt,rev_FY,1,rev_Client,L36)+31/1E+6) | O36: =IF(L36="","",IFERROR(SUMIFS(rev_Amt,rev_FY,1,rev_Client,L36)/$C$28,0)) | P36: =IF(O36="",0,O36^2)
B37: Herfindahl index = sum of each client's squared share x 10,000. Under 1,500 is spread out, 1,500-2,500 moderate, over 2,500 concentrated (the usual market-concentration bands). Thresholds for the other two lines are on Settings. | L37: =IFERROR(INDEX(rev_Client,MATCH(32,rev_New,0)),"") | M37: =IF(L37="","",32) | N37: =IF(L37="","",SUMIFS(rev_Amt,rev_FY,1,rev_Client,L37)+32/1E+6) | O37: =IF(L37="","",IFERROR(SUMIFS(rev_Amt,rev_FY,1,rev_Client,L37)/$C$28,0)) | P37: =IF(O37="",0,O37^2)
L38: =IFERROR(INDEX(rev_Client,MATCH(33,rev_New,0)),"") | M38: =IF(L38="","",33) | N38: =IF(L38="","",SUMIFS(rev_Amt,rev_FY,1,rev_Client,L38)+33/1E+6) | O38: =IF(L38="","",IFERROR(SUMIFS(rev_Amt,rev_FY,1,rev_Client,L38)/$C$28,0)) | P38: =IF(O38="",0,O38^2)
L39: =IFERROR(INDEX(rev_Client,MATCH(34,rev_New,0)),"") | M39: =IF(L39="","",34) | N39: =IF(L39="","",SUMIFS(rev_Amt,rev_FY,1,rev_Client,L39)+34/1E+6) | O39: =IF(L39="","",IFERROR(SUMIFS(rev_Amt,rev_FY,1,rev_Client,L39)/$C$28,0)) | P39: =IF(O39="",0,O39^2)
L40: =IFERROR(INDEX(rev_Client,MATCH(35,rev_New,0)),"") | M40: =IF(L40="","",35) | N40: =IF(L40="","",SUMIFS(rev_Amt,rev_FY,1,rev_Client,L40)+35/1E+6) | O40: =IF(L40="","",IFERROR(SUMIFS(rev_Amt,rev_FY,1,rev_Client,L40)/$C$28,0)) | P40: =IF(O40="",0,O40^2)
L41: =IFERROR(INDEX(rev_Client,MATCH(36,rev_New,0)),"") | M41: =IF(L41="","",36) | N41: =IF(L41="","",SUMIFS(rev_Amt,rev_FY,1,rev_Client,L41)+36/1E+6) | O41: =IF(L41="","",IFERROR(SUMIFS(rev_Amt,rev_FY,1,rev_Client,L41)/$C$28,0)) | P41: =IF(O41="",0,O41^2)
L42: =IFERROR(INDEX(rev_Client,MATCH(37,rev_New,0)),"") | M42: =IF(L42="","",37) | N42: =IF(L42="","",SUMIFS(rev_Amt,rev_FY,1,rev_Client,L42)+37/1E+6) | O42: =IF(L42="","",IFERROR(SUMIFS(rev_Amt,rev_FY,1,rev_Client,L42)/$C$28,0)) | P42: =IF(O42="",0,O42^2)
L43: =IFERROR(INDEX(rev_Client,MATCH(38,rev_New,0)),"") | M43: =IF(L43="","",38) | N43: =IF(L43="","",SUMIFS(rev_Amt,rev_FY,1,rev_Client,L43)+38/1E+6) | O43: =IF(L43="","",IFERROR(SUMIFS(rev_Amt,rev_FY,1,rev_Client,L43)/$C$28,0)) | P43: =IF(O43="",0,O43^2)
L44: =IFERROR(INDEX(rev_Client,MATCH(39,rev_New,0)),"") | M44: =IF(L44="","",39) | N44: =IF(L44="","",SUMIFS(rev_Amt,rev_FY,1,rev_Client,L44)+39/1E+6) | O44: =IF(L44="","",IFERROR(SUMIFS(rev_Amt,rev_FY,1,rev_Client,L44)/$C$28,0)) | P44: =IF(O44="",0,O44^2)
L45: =IFERROR(INDEX(rev_Client,MATCH(40,rev_New,0)),"") | M45: =IF(L45="","",40) | N45: =IF(L45="","",SUMIFS(rev_Amt,rev_FY,1,rev_Client,L45)+40/1E+6) | O45: =IF(L45="","",IFERROR(SUMIFS(rev_Amt,rev_FY,1,rev_Client,L45)/$C$28,0)) | P45: =IF(O45="",0,O45^2)
L46: =IFERROR(INDEX(rev_Client,MATCH(41,rev_New,0)),"") | M46: =IF(L46="","",41) | N46: =IF(L46="","",SUMIFS(rev_Amt,rev_FY,1,rev_Client,L46)+41/1E+6) | O46: =IF(L46="","",IFERROR(SUMIFS(rev_Amt,rev_FY,1,rev_Client,L46)/$C$28,0)) | P46: =IF(O46="",0,O46^2)
L47: =IFERROR(INDEX(rev_Client,MATCH(42,rev_New,0)),"") | M47: =IF(L47="","",42) | N47: =IF(L47="","",SUMIFS(rev_Amt,rev_FY,1,rev_Client,L47)+42/1E+6) | O47: =IF(L47="","",IFERROR(SUMIFS(rev_Amt,rev_FY,1,rev_Client,L47)/$C$28,0)) | P47: =IF(O47="",0,O47^2)
L48: =IFERROR(INDEX(rev_Client,MATCH(43,rev_New,0)),"") | M48: =IF(L48="","",43) | N48: =IF(L48="","",SUMIFS(rev_Amt,rev_FY,1,rev_Client,L48)+43/1E+6) | O48: =IF(L48="","",IFERROR(SUMIFS(rev_Amt,rev_FY,1,rev_Client,L48)/$C$28,0)) | P48: =IF(O48="",0,O48^2)
L49: =IFERROR(INDEX(rev_Client,MATCH(44,rev_New,0)),"") | M49: =IF(L49="","",44) | N49: =IF(L49="","",SUMIFS(rev_Amt,rev_FY,1,rev_Client,L49)+44/1E+6) | O49: =IF(L49="","",IFERROR(SUMIFS(rev_Amt,rev_FY,1,rev_Client,L49)/$C$28,0)) | P49: =IF(O49="",0,O49^2)
L50: =IFERROR(INDEX(rev_Client,MATCH(45,rev_New,0)),"") | M50: =IF(L50="","",45) | N50: =IF(L50="","",SUMIFS(rev_Amt,rev_FY,1,rev_Client,L50)+45/1E+6) | O50: =IF(L50="","",IFERROR(SUMIFS(rev_Amt,rev_FY,1,rev_Client,L50)/$C$28,0)) | P50: =IF(O50="",0,O50^2)
L51: =IFERROR(INDEX(rev_Client,MATCH(46,rev_New,0)),"") | M51: =IF(L51="","",46) | N51: =IF(L51="","",SUMIFS(rev_Amt,rev_FY,1,rev_Client,L51)+46/1E+6) | O51: =IF(L51="","",IFERROR(SUMIFS(rev_Amt,rev_FY,1,rev_Client,L51)/$C$28,0)) | P51: =IF(O51="",0,O51^2)
L52: =IFERROR(INDEX(rev_Client,MATCH(47,rev_New,0)),"") | M52: =IF(L52="","",47) | N52: =IF(L52="","",SUMIFS(rev_Amt,rev_FY,1,rev_Client,L52)+47/1E+6) | O52: =IF(L52="","",IFERROR(SUMIFS(rev_Amt,rev_FY,1,rev_Client,L52)/$C$28,0)) | P52: =IF(O52="",0,O52^2)
L53: =IFERROR(INDEX(rev_Client,MATCH(48,rev_New,0)),"") | M53: =IF(L53="","",48) | N53: =IF(L53="","",SUMIFS(rev_Amt,rev_FY,1,rev_Client,L53)+48/1E+6) | O53: =IF(L53="","",IFERROR(SUMIFS(rev_Amt,rev_FY,1,rev_Client,L53)/$C$28,0)) | P53: =IF(O53="",0,O53^2)
L54: =IFERROR(INDEX(rev_Client,MATCH(49,rev_New,0)),"") | M54: =IF(L54="","",49) | N54: =IF(L54="","",SUMIFS(rev_Amt,rev_FY,1,rev_Client,L54)+49/1E+6) | O54: =IF(L54="","",IFERROR(SUMIFS(rev_Amt,rev_FY,1,rev_Client,L54)/$C$28,0)) | P54: =IF(O54="",0,O54^2)
L55: =IFERROR(INDEX(rev_Client,MATCH(50,rev_New,0)),"") | M55: =IF(L55="","",50) | N55: =IF(L55="","",SUMIFS(rev_Amt,rev_FY,1,rev_Client,L55)+50/1E+6) | O55: =IF(L55="","",IFERROR(SUMIFS(rev_Amt,rev_FY,1,rev_Client,L55)/$C$28,0)) | P55: =IF(O55="",0,O55^2)
L56: =IFERROR(INDEX(rev_Client,MATCH(51,rev_New,0)),"") | M56: =IF(L56="","",51) | N56: =IF(L56="","",SUMIFS(rev_Amt,rev_FY,1,rev_Client,L56)+51/1E+6) | O56: =IF(L56="","",IFERROR(SUMIFS(rev_Amt,rev_FY,1,rev_Client,L56)/$C$28,0)) | P56: =IF(O56="",0,O56^2)
L57: =IFERROR(INDEX(rev_Client,MATCH(52,rev_New,0)),"") | M57: =IF(L57="","",52) | N57: =IF(L57="","",SUMIFS(rev_Amt,rev_FY,1,rev_Client,L57)+52/1E+6) | O57: =IF(L57="","",IFERROR(SUMIFS(rev_Amt,rev_FY,1,rev_Client,L57)/$C$28,0)) | P57: =IF(O57="",0,O57^2)
L58: =IFERROR(INDEX(rev_Client,MATCH(53,rev_New,0)),"") | M58: =IF(L58="","",53) | N58: =IF(L58="","",SUMIFS(rev_Amt,rev_FY,1,rev_Client,L58)+53/1E+6) | O58: =IF(L58="","",IFERROR(SUMIFS(rev_Amt,rev_FY,1,rev_Client,L58)/$C$28,0)) | P58: =IF(O58="",0,O58^2)
L59: =IFERROR(INDEX(rev_Client,MATCH(54,rev_New,0)),"") | M59: =IF(L59="","",54) | N59: =IF(L59="","",SUMIFS(rev_Amt,rev_FY,1,rev_Client,L59)+54/1E+6) | O59: =IF(L59="","",IFERROR(SUMIFS(rev_Amt,rev_FY,1,rev_Client,L59)/$C$28,0)) | P59: =IF(O59="",0,O59^2)
L60: =IFERROR(INDEX(rev_Client,MATCH(55,rev_New,0)),"") | M60: =IF(L60="","",55) | N60: =IF(L60="","",SUMIFS(rev_Amt,rev_FY,1,rev_Client,L60)+55/1E+6) | O60: =IF(L60="","",IFERROR(SUMIFS(rev_Amt,rev_FY,1,rev_Client,L60)/$C$28,0)) | P60: =IF(O60="",0,O60^2)
L61: =IFERROR(INDEX(rev_Client,MATCH(56,rev_New,0)),"") | M61: =IF(L61="","",56) | N61: =IF(L61="","",SUMIFS(rev_Amt,rev_FY,1,rev_Client,L61)+56/1E+6) | O61: =IF(L61="","",IFERROR(SUMIFS(rev_Amt,rev_FY,1,rev_Client,L61)/$C$28,0)) | P61: =IF(O61="",0,O61^2)
L62: =IFERROR(INDEX(rev_Client,MATCH(57,rev_New,0)),"") | M62: =IF(L62="","",57) | N62: =IF(L62="","",SUMIFS(rev_Amt,rev_FY,1,rev_Client,L62)+57/1E+6) | O62: =IF(L62="","",IFERROR(SUMIFS(rev_Amt,rev_FY,1,rev_Client,L62)/$C$28,0)) | P62: =IF(O62="",0,O62^2)
L63: =IFERROR(INDEX(rev_Client,MATCH(58,rev_New,0)),"") | M63: =IF(L63="","",58) | N63: =IF(L63="","",SUMIFS(rev_Amt,rev_FY,1,rev_Client,L63)+58/1E+6) | O63: =IF(L63="","",IFERROR(SUMIFS(rev_Amt,rev_FY,1,rev_Client,L63)/$C$28,0)) | P63: =IF(O63="",0,O63^2)
L64: =IFERROR(INDEX(rev_Client,MATCH(59,rev_New,0)),"") | M64: =IF(L64="","",59) | N64: =IF(L64="","",SUMIFS(rev_Amt,rev_FY,1,rev_Client,L64)+59/1E+6) | O64: =IF(L64="","",IFERROR(SUMIFS(rev_Amt,rev_FY,1,rev_Client,L64)/$C$28,0)) | P64: =IF(O64="",0,O64^2)
L65: =IFERROR(INDEX(rev_Client,MATCH(60,rev_New,0)),"") | M65: =IF(L65="","",60) | N65: =IF(L65="","",SUMIFS(rev_Amt,rev_FY,1,rev_Client,L65)+60/1E+6) | O65: =IF(L65="","",IFERROR(SUMIFS(rev_Amt,rev_FY,1,rev_Client,L65)/$C$28,0)) | P65: =IF(O65="",0,O65^2)
L66: =IFERROR(INDEX(rev_Client,MATCH(61,rev_New,0)),"") | M66: =IF(L66="","",61) | N66: =IF(L66="","",SUMIFS(rev_Amt,rev_FY,1,rev_Client,L66)+61/1E+6) | O66: =IF(L66="","",IFERROR(SUMIFS(rev_Amt,rev_FY,1,rev_Client,L66)/$C$28,0)) | P66: =IF(O66="",0,O66^2)
L67: =IFERROR(INDEX(rev_Client,MATCH(62,rev_New,0)),"") | M67: =IF(L67="","",62) | N67: =IF(L67="","",SUMIFS(rev_Amt,rev_FY,1,rev_Client,L67)+62/1E+6) | O67: =IF(L67="","",IFERROR(SUMIFS(rev_Amt,rev_FY,1,rev_Client,L67)/$C$28,0)) | P67: =IF(O67="",0,O67^2)
L68: =IFERROR(INDEX(rev_Client,MATCH(63,rev_New,0)),"") | M68: =IF(L68="","",63) | N68: =IF(L68="","",SUMIFS(rev_Amt,rev_FY,1,rev_Client,L68)+63/1E+6) | O68: =IF(L68="","",IFERROR(SUMIFS(rev_Amt,rev_FY,1,rev_Client,L68)/$C$28,0)) | P68: =IF(O68="",0,O68^2)
L69: =IFERROR(INDEX(rev_Client,MATCH(64,rev_New,0)),"") | M69: =IF(L69="","",64) | N69: =IF(L69="","",SUMIFS(rev_Amt,rev_FY,1,rev_Client,L69)+64/1E+6) | O69: =IF(L69="","",IFERROR(SUMIFS(rev_Amt,rev_FY,1,rev_Client,L69)/$C$28,0)) | P69: =IF(O69="",0,O69^2)
L70: =IFERROR(INDEX(rev_Client,MATCH(65,rev_New,0)),"") | M70: =IF(L70="","",65) | N70: =IF(L70="","",SUMIFS(rev_Amt,rev_FY,1,rev_Client,L70)+65/1E+6) | O70: =IF(L70="","",IFERROR(SUMIFS(rev_Amt,rev_FY,1,rev_Client,L70)/$C$28,0)) | P70: =IF(O70="",0,O70^2)
L71: =IFERROR(INDEX(rev_Client,MATCH(66,rev_New,0)),"") | M71: =IF(L71="","",66) | N71: =IF(L71="","",SUMIFS(rev_Amt,rev_FY,1,rev_Client,L71)+66/1E+6) | O71: =IF(L71="","",IFERROR(SUMIFS(rev_Amt,rev_FY,1,rev_Client,L71)/$C$28,0)) | P71: =IF(O71="",0,O71^2)
L72: =IFERROR(INDEX(rev_Client,MATCH(67,rev_New,0)),"") | M72: =IF(L72="","",67) | N72: =IF(L72="","",SUMIFS(rev_Amt,rev_FY,1,rev_Client,L72)+67/1E+6) | O72: =IF(L72="","",IFERROR(SUMIFS(rev_Amt,rev_FY,1,rev_Client,L72)/$C$28,0)) | P72: =IF(O72="",0,O72^2)
L73: =IFERROR(INDEX(rev_Client,MATCH(68,rev_New,0)),"") | M73: =IF(L73="","",68) | N73: =IF(L73="","",SUMIFS(rev_Amt,rev_FY,1,rev_Client,L73)+68/1E+6) | O73: =IF(L73="","",IFERROR(SUMIFS(rev_Amt,rev_FY,1,rev_Client,L73)/$C$28,0)) | P73: =IF(O73="",0,O73^2)
L74: =IFERROR(INDEX(rev_Client,MATCH(69,rev_New,0)),"") | M74: =IF(L74="","",69) | N74: =IF(L74="","",SUMIFS(rev_Amt,rev_FY,1,rev_Client,L74)+69/1E+6) | O74: =IF(L74="","",IFERROR(SUMIFS(rev_Amt,rev_FY,1,rev_Client,L74)/$C$28,0)) | P74: =IF(O74="",0,O74^2)
L75: =IFERROR(INDEX(rev_Client,MATCH(70,rev_New,0)),"") | M75: =IF(L75="","",70) | N75: =IF(L75="","",SUMIFS(rev_Amt,rev_FY,1,rev_Client,L75)+70/1E+6) | O75: =IF(L75="","",IFERROR(SUMIFS(rev_Amt,rev_FY,1,rev_Client,L75)/$C$28,0)) | P75: =IF(O75="",0,O75^2)
L76: =IFERROR(INDEX(rev_Client,MATCH(71,rev_New,0)),"") | M76: =IF(L76="","",71) | N76: =IF(L76="","",SUMIFS(rev_Amt,rev_FY,1,rev_Client,L76)+71/1E+6) | O76: =IF(L76="","",IFERROR(SUMIFS(rev_Amt,rev_FY,1,rev_Client,L76)/$C$28,0)) | P76: =IF(O76="",0,O76^2)
L77: =IFERROR(INDEX(rev_Client,MATCH(72,rev_New,0)),"") | M77: =IF(L77="","",72) | N77: =IF(L77="","",SUMIFS(rev_Amt,rev_FY,1,rev_Client,L77)+72/1E+6) | O77: =IF(L77="","",IFERROR(SUMIFS(rev_Amt,rev_FY,1,rev_Client,L77)/$C$28,0)) | P77: =IF(O77="",0,O77^2)
L78: =IFERROR(INDEX(rev_Client,MATCH(73,rev_New,0)),"") | M78: =IF(L78="","",73) | N78: =IF(L78="","",SUMIFS(rev_Amt,rev_FY,1,rev_Client,L78)+73/1E+6) | O78: =IF(L78="","",IFERROR(SUMIFS(rev_Amt,rev_FY,1,rev_Client,L78)/$C$28,0)) | P78: =IF(O78="",0,O78^2)
L79: =IFERROR(INDEX(rev_Client,MATCH(74,rev_New,0)),"") | M79: =IF(L79="","",74) | N79: =IF(L79="","",SUMIFS(rev_Amt,rev_FY,1,rev_Client,L79)+74/1E+6) | O79: =IF(L79="","",IFERROR(SUMIFS(rev_Amt,rev_FY,1,rev_Client,L79)/$C$28,0)) | P79: =IF(O79="",0,O79^2)
L80: =IFERROR(INDEX(rev_Client,MATCH(75,rev_New,0)),"") | M80: =IF(L80="","",75) | N80: =IF(L80="","",SUMIFS(rev_Amt,rev_FY,1,rev_Client,L80)+75/1E+6) | O80: =IF(L80="","",IFERROR(SUMIFS(rev_Amt,rev_FY,1,rev_Client,L80)/$C$28,0)) | P80: =IF(O80="",0,O80^2)
L81: =IFERROR(INDEX(rev_Client,MATCH(76,rev_New,0)),"") | M81: =IF(L81="","",76) | N81: =IF(L81="","",SUMIFS(rev_Amt,rev_FY,1,rev_Client,L81)+76/1E+6) | O81: =IF(L81="","",IFERROR(SUMIFS(rev_Amt,rev_FY,1,rev_Client,L81)/$C$28,0)) | P81: =IF(O81="",0,O81^2)
L82: =IFERROR(INDEX(rev_Client,MATCH(77,rev_New,0)),"") | M82: =IF(L82="","",77) | N82: =IF(L82="","",SUMIFS(rev_Amt,rev_FY,1,rev_Client,L82)+77/1E+6) | O82: =IF(L82="","",IFERROR(SUMIFS(rev_Amt,rev_FY,1,rev_Client,L82)/$C$28,0)) | P82: =IF(O82="",0,O82^2)
L83: =IFERROR(INDEX(rev_Client,MATCH(78,rev_New,0)),"") | M83: =IF(L83="","",78) | N83: =IF(L83="","",SUMIFS(rev_Amt,rev_FY,1,rev_Client,L83)+78/1E+6) | O83: =IF(L83="","",IFERROR(SUMIFS(rev_Amt,rev_FY,1,rev_Client,L83)/$C$28,0)) | P83: =IF(O83="",0,O83^2)
L84: =IFERROR(INDEX(rev_Client,MATCH(79,rev_New,0)),"") | M84: =IF(L84="","",79) | N84: =IF(L84="","",SUMIFS(rev_Amt,rev_FY,1,rev_Client,L84)+79/1E+6) | O84: =IF(L84="","",IFERROR(SUMIFS(rev_Amt,rev_FY,1,rev_Client,L84)/$C$28,0)) | P84: =IF(O84="",0,O84^2)
L85: =IFERROR(INDEX(rev_Client,MATCH(80,rev_New,0)),"") | M85: =IF(L85="","",80) | N85: =IF(L85="","",SUMIFS(rev_Amt,rev_FY,1,rev_Client,L85)+80/1E+6) | O85: =IF(L85="","",IFERROR(SUMIFS(rev_Amt,rev_FY,1,rev_Client,L85)/$C$28,0)) | P85: =IF(O85="",0,O85^2)
L86: =IFERROR(INDEX(rev_Client,MATCH(81,rev_New,0)),"") | M86: =IF(L86="","",81) | N86: =IF(L86="","",SUMIFS(rev_Amt,rev_FY,1,rev_Client,L86)+81/1E+6) | O86: =IF(L86="","",IFERROR(SUMIFS(rev_Amt,rev_FY,1,rev_Client,L86)/$C$28,0)) | P86: =IF(O86="",0,O86^2)
L87: =IFERROR(INDEX(rev_Client,MATCH(82,rev_New,0)),"") | M87: =IF(L87="","",82) | N87: =IF(L87="","",SUMIFS(rev_Amt,rev_FY,1,rev_Client,L87)+82/1E+6) | O87: =IF(L87="","",IFERROR(SUMIFS(rev_Amt,rev_FY,1,rev_Client,L87)/$C$28,0)) | P87: =IF(O87="",0,O87^2)
L88: =IFERROR(INDEX(rev_Client,MATCH(83,rev_New,0)),"") | M88: =IF(L88="","",83) | N88: =IF(L88="","",SUMIFS(rev_Amt,rev_FY,1,rev_Client,L88)+83/1E+6) | O88: =IF(L88="","",IFERROR(SUMIFS(rev_Amt,rev_FY,1,rev_Client,L88)/$C$28,0)) | P88: =IF(O88="",0,O88^2)
L89: =IFERROR(INDEX(rev_Client,MATCH(84,rev_New,0)),"") | M89: =IF(L89="","",84) | N89: =IF(L89="","",SUMIFS(rev_Amt,rev_FY,1,rev_Client,L89)+84/1E+6) | O89: =IF(L89="","",IFERROR(SUMIFS(rev_Amt,rev_FY,1,rev_Client,L89)/$C$28,0)) | P89: =IF(O89="",0,O89^2)
L90: =IFERROR(INDEX(rev_Client,MATCH(85,rev_New,0)),"") | M90: =IF(L90="","",85) | N90: =IF(L90="","",SUMIFS(rev_Amt,rev_FY,1,rev_Client,L90)+85/1E+6) | O90: =IF(L90="","",IFERROR(SUMIFS(rev_Amt,rev_FY,1,rev_Client,L90)/$C$28,0)) | P90: =IF(O90="",0,O90^2)
L91: =IFERROR(INDEX(rev_Client,MATCH(86,rev_New,0)),"") | M91: =IF(L91="","",86) | N91: =IF(L91="","",SUMIFS(rev_Amt,rev_FY,1,rev_Client,L91)+86/1E+6) | O91: =IF(L91="","",IFERROR(SUMIFS(rev_Amt,rev_FY,1,rev_Client,L91)/$C$28,0)) | P91: =IF(O91="",0,O91^2)
L92: =IFERROR(INDEX(rev_Client,MATCH(87,rev_New,0)),"") | M92: =IF(L92="","",87) | N92: =IF(L92="","",SUMIFS(rev_Amt,rev_FY,1,rev_Client,L92)+87/1E+6) | O92: =IF(L92="","",IFERROR(SUMIFS(rev_Amt,rev_FY,1,rev_Client,L92)/$C$28,0)) | P92: =IF(O92="",0,O92^2)
L93: =IFERROR(INDEX(rev_Client,MATCH(88,rev_New,0)),"") | M93: =IF(L93="","",88) | N93: =IF(L93="","",SUMIFS(rev_Amt,rev_FY,1,rev_Client,L93)+88/1E+6) | O93: =IF(L93="","",IFERROR(SUMIFS(rev_Amt,rev_FY,1,rev_Client,L93)/$C$28,0)) | P93: =IF(O93="",0,O93^2)
L94: =IFERROR(INDEX(rev_Client,MATCH(89,rev_New,0)),"") | M94: =IF(L94="","",89) | N94: =IF(L94="","",SUMIFS(rev_Amt,rev_FY,1,rev_Client,L94)+89/1E+6) | O94: =IF(L94="","",IFERROR(SUMIFS(rev_Amt,rev_FY,1,rev_Client,L94)/$C$28,0)) | P94: =IF(O94="",0,O94^2)
L95: =IFERROR(INDEX(rev_Client,MATCH(90,rev_New,0)),"") | M95: =IF(L95="","",90) | N95: =IF(L95="","",SUMIFS(rev_Amt,rev_FY,1,rev_Client,L95)+90/1E+6) | O95: =IF(L95="","",IFERROR(SUMIFS(rev_Amt,rev_FY,1,rev_Client,L95)/$C$28,0)) | P95: =IF(O95="",0,O95^2)
L96: =IFERROR(INDEX(rev_Client,MATCH(91,rev_New,0)),"") | M96: =IF(L96="","",91) | N96: =IF(L96="","",SUMIFS(rev_Amt,rev_FY,1,rev_Client,L96)+91/1E+6) | O96: =IF(L96="","",IFERROR(SUMIFS(rev_Amt,rev_FY,1,rev_Client,L96)/$C$28,0)) | P96: =IF(O96="",0,O96^2)
L97: =IFERROR(INDEX(rev_Client,MATCH(92,rev_New,0)),"") | M97: =IF(L97="","",92) | N97: =IF(L97="","",SUMIFS(rev_Amt,rev_FY,1,rev_Client,L97)+92/1E+6) | O97: =IF(L97="","",IFERROR(SUMIFS(rev_Amt,rev_FY,1,rev_Client,L97)/$C$28,0)) | P97: =IF(O97="",0,O97^2)
L98: =IFERROR(INDEX(rev_Client,MATCH(93,rev_New,0)),"") | M98: =IF(L98="","",93) | N98: =IF(L98="","",SUMIFS(rev_Amt,rev_FY,1,rev_Client,L98)+93/1E+6) | O98: =IF(L98="","",IFERROR(SUMIFS(rev_Amt,rev_FY,1,rev_Client,L98)/$C$28,0)) | P98: =IF(O98="",0,O98^2)
L99: =IFERROR(INDEX(rev_Client,MATCH(94,rev_New,0)),"") | M99: =IF(L99="","",94) | N99: =IF(L99="","",SUMIFS(rev_Amt,rev_FY,1,rev_Client,L99)+94/1E+6) | O99: =IF(L99="","",IFERROR(SUMIFS(rev_Amt,rev_FY,1,rev_Client,L99)/$C$28,0)) | P99: =IF(O99="",0,O99^2)
L100: =IFERROR(INDEX(rev_Client,MATCH(95,rev_New,0)),"") | M100: =IF(L100="","",95) | N100: =IF(L100="","",SUMIFS(rev_Amt,rev_FY,1,rev_Client,L100)+95/1E+6) | O100: =IF(L100="","",IFERROR(SUMIFS(rev_Amt,rev_FY,1,rev_Client,L100)/$C$28,0)) | P100: =IF(O100="",0,O100^2)
L101: =IFERROR(INDEX(rev_Client,MATCH(96,rev_New,0)),"") | M101: =IF(L101="","",96) | N101: =IF(L101="","",SUMIFS(rev_Amt,rev_FY,1,rev_Client,L101)+96/1E+6) | O101: =IF(L101="","",IFERROR(SUMIFS(rev_Amt,rev_FY,1,rev_Client,L101)/$C$28,0)) | P101: =IF(O101="",0,O101^2)
...

Sheet Risk Register
A1: Risk Register
A2: Every open deal and every won deal not yet fully invoiced, worst first. Flags and scores are explained at the bottom; thresholds are on Settings.
A4: # | B4: Rating | C4: Score | D4: Job / Opp No | E4: Client | F4: Deal | G4: Cost Centre | H4: Status | I4: Stage | J4: Value | K4: Probability | L4: Revenue at risk | M4: Expected Month | N4: Why
A5: =IF(D5="","",1) | B5: =IFERROR(INDEX(p_Rating,MATCH(LARGE(p_Key,1),p_Key,0)),"") | C5: =IFERROR(INDEX(p_Score,MATCH(LARGE(p_Key,1),p_Key,0)),"") | D5: =IFERROR(INDEX(p_Job,MATCH(LARGE(p_Key,1),p_Key,0)),"") | E5: =IFERROR(INDEX(p_Client,MATCH(LARGE(p_Key,1),p_Key,0)),"") | F5: =IFERROR(INDEX(p_Deal,MATCH(LARGE(p_Key,1),p_Key,0)),"") | G5: =IFERROR(INDEX(p_CC,MATCH(LARGE(p_Key,1),p_Key,0)),"") | H5: =IFERROR(INDEX(p_Status,MATCH(LARGE(p_Key,1),p_Key,0)),"") | I5: =IFERROR(INDEX(p_Stage,MATCH(LARGE(p_Key,1),p_Key,0)),"") | J5: =IFERROR(INDEX(p_Value,MATCH(LARGE(p_Key,1),p_Key,0)),"") | K5: =IFERROR(IF(H5="Open",INDEX(p_Prob,MATCH(LARGE(p_Key,1),p_Key,0)),""),"") | L5: =IFERROR(INDEX(p_Risk,MATCH(LARGE(p_Key,1),p_Key,0)),"") | M5: =IFERROR(INDEX(p_Month,MATCH(LARGE(p_Key,1),p_Key,0)),"") | N5: =IFERROR(INDEX(p_Flags,MATCH(LARGE(p_Key,1),p_Key,0)),"")
A6: =IF(D6="","",2) | B6: =IFERROR(INDEX(p_Rating,MATCH(LARGE(p_Key,2),p_Key,0)),"") | C6: =IFERROR(INDEX(p_Score,MATCH(LARGE(p_Key,2),p_Key,0)),"") | D6: =IFERROR(INDEX(p_Job,MATCH(LARGE(p_Key,2),p_Key,0)),"") | E6: =IFERROR(INDEX(p_Client,MATCH(LARGE(p_Key,2),p_Key,0)),"") | F6: =IFERROR(INDEX(p_Deal,MATCH(LARGE(p_Key,2),p_Key,0)),"") | G6: =IFERROR(INDEX(p_CC,MATCH(LARGE(p_Key,2),p_Key,0)),"") | H6: =IFERROR(INDEX(p_Status,MATCH(LARGE(p_Key,2),p_Key,0)),"") | I6: =IFERROR(INDEX(p_Stage,MATCH(LARGE(p_Key,2),p_Key,0)),"") | J6: =IFERROR(INDEX(p_Value,MATCH(LARGE(p_Key,2),p_Key,0)),"") | K6: =IFERROR(IF(H6="Open",INDEX(p_Prob,MATCH(LARGE(p_Key,2),p_Key,0)),""),"") | L6: =IFERROR(INDEX(p_Risk,MATCH(LARGE(p_Key,2),p_Key,0)),"") | M6: =IFERROR(INDEX(p_Month,MATCH(LARGE(p_Key,2),p_Key,0)),"") | N6: =IFERROR(INDEX(p_Flags,MATCH(LARGE(p_Key,2),p_Key,0)),"")
A7: =IF(D7="","",3) | B7: =IFERROR(INDEX(p_Rating,MATCH(LARGE(p_Key,3),p_Key,0)),"") | C7: =IFERROR(INDEX(p_Score,MATCH(LARGE(p_Key,3),p_Key,0)),"") | D7: =IFERROR(INDEX(p_Job,MATCH(LARGE(p_Key,3),p_Key,0)),"") | E7: =IFERROR(INDEX(p_Client,MATCH(LARGE(p_Key,3),p_Key,0)),"") | F7: =IFERROR(INDEX(p_Deal,MATCH(LARGE(p_Key,3),p_Key,0)),"") | G7: =IFERROR(INDEX(p_CC,MATCH(LARGE(p_Key,3),p_Key,0)),"") | H7: =IFERROR(INDEX(p_Status,MATCH(LARGE(p_Key,3),p_Key,0)),"") | I7: =IFERROR(INDEX(p_Stage,MATCH(LARGE(p_Key,3),p_Key,0)),"") | J7: =IFERROR(INDEX(p_Value,MATCH(LARGE(p_Key,3),p_Key,0)),"") | K7: =IFERROR(IF(H7="Open",INDEX(p_Prob,MATCH(LARGE(p_Key,3),p_Key,0)),""),"") | L7: =IFERROR(INDEX(p_Risk,MATCH(LARGE(p_Key,3),p_Key,0)),"") | M7: =IFERROR(INDEX(p_Month,MATCH(LARGE(p_Key,3),p_Key,0)),"") | N7: =IFERROR(INDEX(p_Flags,MATCH(LARGE(p_Key,3),p_Key,0)),"")
A8: =IF(D8="","",4) | B8: =IFERROR(INDEX(p_Rating,MATCH(LARGE(p_Key,4),p_Key,0)),"") | C8: =IFERROR(INDEX(p_Score,MATCH(LARGE(p_Key,4),p_Key,0)),"") | D8: =IFERROR(INDEX(p_Job,MATCH(LARGE(p_Key,4),p_Key,0)),"") | E8: =IFERROR(INDEX(p_Client,MATCH(LARGE(p_Key,4),p_Key,0)),"") | F8: =IFERROR(INDEX(p_Deal,MATCH(LARGE(p_Key,4),p_Key,0)),"") | G8: =IFERROR(INDEX(p_CC,MATCH(LARGE(p_Key,4),p_Key,0)),"") | H8: =IFERROR(INDEX(p_Status,MATCH(LARGE(p_Key,4),p_Key,0)),"") | I8: =IFERROR(INDEX(p_Stage,MATCH(LARGE(p_Key,4),p_Key,0)),"") | J8: =IFERROR(INDEX(p_Value,MATCH(LARGE(p_Key,4),p_Key,0)),"") | K8: =IFERROR(IF(H8="Open",INDEX(p_Prob,MATCH(LARGE(p_Key,4),p_Key,0)),""),"") | L8: =IFERROR(INDEX(p_Risk,MATCH(LARGE(p_Key,4),p_Key,0)),"") | M8: =IFERROR(INDEX(p_Month,MATCH(LARGE(p_Key,4),p_Key,0)),"") | N8: =IFERROR(INDEX(p_Flags,MATCH(LARGE(p_Key,4),p_Key,0)),"")
A9: =IF(D9="","",5) | B9: =IFERROR(INDEX(p_Rating,MATCH(LARGE(p_Key,5),p_Key,0)),"") | C9: =IFERROR(INDEX(p_Score,MATCH(LARGE(p_Key,5),p_Key,0)),"") | D9: =IFERROR(INDEX(p_Job,MATCH(LARGE(p_Key,5),p_Key,0)),"") | E9: =IFERROR(INDEX(p_Client,MATCH(LARGE(p_Key,5),p_Key,0)),"") | F9: =IFERROR(INDEX(p_Deal,MATCH(LARGE(p_Key,5),p_Key,0)),"") | G9: =IFERROR(INDEX(p_CC,MATCH(LARGE(p_Key,5),p_Key,0)),"") | H9: =IFERROR(INDEX(p_Status,MATCH(LARGE(p_Key,5),p_Key,0)),"") | I9: =IFERROR(INDEX(p_Stage,MATCH(LARGE(p_Key,5),p_Key,0)),"") | J9: =IFERROR(INDEX(p_Value,MATCH(LARGE(p_Key,5),p_Key,0)),"") | K9: =IFERROR(IF(H9="Open",INDEX(p_Prob,MATCH(LARGE(p_Key,5),p_Key,0)),""),"") | L9: =IFERROR(INDEX(p_Risk,MATCH(LARGE(p_Key,5),p_Key,0)),"") | M9: =IFERROR(INDEX(p_Month,MATCH(LARGE(p_Key,5),p_Key,0)),"") | N9: =IFERROR(INDEX(p_Flags,MATCH(LARGE(p_Key,5),p_Key,0)),"")
A10: =IF(D10="","",6) | B10: =IFERROR(INDEX(p_Rating,MATCH(LARGE(p_Key,6),p_Key,0)),"") | C10: =IFERROR(INDEX(p_Score,MATCH(LARGE(p_Key,6),p_Key,0)),"") | D10: =IFERROR(INDEX(p_Job,MATCH(LARGE(p_Key,6),p_Key,0)),"") | E10: =IFERROR(INDEX(p_Client,MATCH(LARGE(p_Key,6),p_Key,0)),"") | F10: =IFERROR(INDEX(p_Deal,MATCH(LARGE(p_Key,6),p_Key,0)),"") | G10: =IFERROR(INDEX(p_CC,MATCH(LARGE(p_Key,6),p_Key,0)),"") | H10: =IFERROR(INDEX(p_Status,MATCH(LARGE(p_Key,6),p_Key,0)),"") | I10: =IFERROR(INDEX(p_Stage,MATCH(LARGE(p_Key,6),p_Key,0)),"") | J10: =IFERROR(INDEX(p_Value,MATCH(LARGE(p_Key,6),p_Key,0)),"") | K10: =IFERROR(IF(H10="Open",INDEX(p_Prob,MATCH(LARGE(p_Key,6),p_Key,0)),""),"") | L10: =IFERROR(INDEX(p_Risk,MATCH(LARGE(p_Key,6),p_Key,0)),"") | M10: =IFERROR(INDEX(p_Month,MATCH(LARGE(p_Key,6),p_Key,0)),"") | N10: =IFERROR(INDEX(p_Flags,MATCH(LARGE(p_Key,6),p_Key,0)),"")
A11: =IF(D11="","",7) | B11: =IFERROR(INDEX(p_Rating,MATCH(LARGE(p_Key,7),p_Key,0)),"") | C11: =IFERROR(INDEX(p_Score,MATCH(LARGE(p_Key,7),p_Key,0)),"") | D11: =IFERROR(INDEX(p_Job,MATCH(LARGE(p_Key,7),p_Key,0)),"") | E11: =IFERROR(INDEX(p_Client,MATCH(LARGE(p_Key,7),p_Key,0)),"") | F11: =IFERROR(INDEX(p_Deal,MATCH(LARGE(p_Key,7),p_Key,0)),"") | G11: =IFERROR(INDEX(p_CC,MATCH(LARGE(p_Key,7),p_Key,0)),"") | H11: =IFERROR(INDEX(p_Status,MATCH(LARGE(p_Key,7),p_Key,0)),"") | I11: =IFERROR(INDEX(p_Stage,MATCH(LARGE(p_Key,7),p_Key,0)),"") | J11: =IFERROR(INDEX(p_Value,MATCH(LARGE(p_Key,7),p_Key,0)),"") | K11: =IFERROR(IF(H11="Open",INDEX(p_Prob,MATCH(LARGE(p_Key,7),p_Key,0)),""),"") | L11: =IFERROR(INDEX(p_Risk,MATCH(LARGE(p_Key,7),p_Key,0)),"") | M11: =IFERROR(INDEX(p_Month,MATCH(LARGE(p_Key,7),p_Key,0)),"") | N11: =IFERROR(INDEX(p_Flags,MATCH(LARGE(p_Key,7),p_Key,0)),"")
A12: =IF(D12="","",8) | B12: =IFERROR(INDEX(p_Rating,MATCH(LARGE(p_Key,8),p_Key,0)),"") | C12: =IFERROR(INDEX(p_Score,MATCH(LARGE(p_Key,8),p_Key,0)),"") | D12: =IFERROR(INDEX(p_Job,MATCH(LARGE(p_Key,8),p_Key,0)),"") | E12: =IFERROR(INDEX(p_Client,MATCH(LARGE(p_Key,8),p_Key,0)),"") | F12: =IFERROR(INDEX(p_Deal,MATCH(LARGE(p_Key,8),p_Key,0)),"") | G12: =IFERROR(INDEX(p_CC,MATCH(LARGE(p_Key,8),p_Key,0)),"") | H12: =IFERROR(INDEX(p_Status,MATCH(LARGE(p_Key,8),p_Key,0)),"") | I12: =IFERROR(INDEX(p_Stage,MATCH(LARGE(p_Key,8),p_Key,0)),"") | J12: =IFERROR(INDEX(p_Value,MATCH(LARGE(p_Key,8),p_Key,0)),"") | K12: =IFERROR(IF(H12="Open",INDEX(p_Prob,MATCH(LARGE(p_Key,8),p_Key,0)),""),"") | L12: =IFERROR(INDEX(p_Risk,MATCH(LARGE(p_Key,8),p_Key,0)),"") | M12: =IFERROR(INDEX(p_Month,MATCH(LARGE(p_Key,8),p_Key,0)),"") | N12: =IFERROR(INDEX(p_Flags,MATCH(LARGE(p_Key,8),p_Key,0)),"")
A13: =IF(D13="","",9) | B13: =IFERROR(INDEX(p_Rating,MATCH(LARGE(p_Key,9),p_Key,0)),"") | C13: =IFERROR(INDEX(p_Score,MATCH(LARGE(p_Key,9),p_Key,0)),"") | D13: =IFERROR(INDEX(p_Job,MATCH(LARGE(p_Key,9),p_Key,0)),"") | E13: =IFERROR(INDEX(p_Client,MATCH(LARGE(p_Key,9),p_Key,0)),"") | F13: =IFERROR(INDEX(p_Deal,MATCH(LARGE(p_Key,9),p_Key,0)),"") | G13: =IFERROR(INDEX(p_CC,MATCH(LARGE(p_Key,9),p_Key,0)),"") | H13: =IFERROR(INDEX(p_Status,MATCH(LARGE(p_Key,9),p_Key,0)),"") | I13: =IFERROR(INDEX(p_Stage,MATCH(LARGE(p_Key,9),p_Key,0)),"") | J13: =IFERROR(INDEX(p_Value,MATCH(LARGE(p_Key,9),p_Key,0)),"") | K13: =IFERROR(IF(H13="Open",INDEX(p_Prob,MATCH(LARGE(p_Key,9),p_Key,0)),""),"") | L13: =IFERROR(INDEX(p_Risk,MATCH(LARGE(p_Key,9),p_Key,0)),"") | M13: =IFERROR(INDEX(p_Month,MATCH(LARGE(p_Key,9),p_Key,0)),"") | N13: =IFERROR(INDEX(p_Flags,MATCH(LARGE(p_Key,9),p_Key,0)),"")
A14: =IF(D14="","",10) | B14: =IFERROR(INDEX(p_Rating,MATCH(LARGE(p_Key,10),p_Key,0)),"") | C14: =IFERROR(INDEX(p_Score,MATCH(LARGE(p_Key,10),p_Key,0)),"") | D14: =IFERROR(INDEX(p_Job,MATCH(LARGE(p_Key,10),p_Key,0)),"") | E14: =IFERROR(INDEX(p_Client,MATCH(LARGE(p_Key,10),p_Key,0)),"") | F14: =IFERROR(INDEX(p_Deal,MATCH(LARGE(p_Key,10),p_Key,0)),"") | G14: =IFERROR(INDEX(p_CC,MATCH(LARGE(p_Key,10),p_Key,0)),"") | H14: =IFERROR(INDEX(p_Status,MATCH(LARGE(p_Key,10),p_Key,0)),"") | I14: =IFERROR(INDEX(p_Stage,MATCH(LARGE(p_Key,10),p_Key,0)),"") | J14: =IFERROR(INDEX(p_Value,MATCH(LARGE(p_Key,10),p_Key,0)),"") | K14: =IFERROR(IF(H14="Open",INDEX(p_Prob,MATCH(LARGE(p_Key,10),p_Key,0)),""),"") | L14: =IFERROR(INDEX(p_Risk,MATCH(LARGE(p_Key,10),p_Key,0)),"") | M14: =IFERROR(INDEX(p_Month,MATCH(LARGE(p_Key,10),p_Key,0)),"") | N14: =IFERROR(INDEX(p_Flags,MATCH(LARGE(p_Key,10),p_Key,0)),"")
A15: =IF(D15="","",11) | B15: =IFERROR(INDEX(p_Rating,MATCH(LARGE(p_Key,11),p_Key,0)),"") | C15: =IFERROR(INDEX(p_Score,MATCH(LARGE(p_Key,11),p_Key,0)),"") | D15: =IFERROR(INDEX(p_Job,MATCH(LARGE(p_Key,11),p_Key,0)),"") | E15: =IFERROR(INDEX(p_Client,MATCH(LARGE(p_Key,11),p_Key,0)),"") | F15: =IFERROR(INDEX(p_Deal,MATCH(LARGE(p_Key,11),p_Key,0)),"") | G15: =IFERROR(INDEX(p_CC,MATCH(LARGE(p_Key,11),p_Key,0)),"") | H15: =IFERROR(INDEX(p_Status,MATCH(LARGE(p_Key,11),p_Key,0)),"") | I15: =IFERROR(INDEX(p_Stage,MATCH(LARGE(p_Key,11),p_Key,0)),"") | J15: =IFERROR(INDEX(p_Value,MATCH(LARGE(p_Key,11),p_Key,0)),"") | K15: =IFERROR(IF(H15="Open",INDEX(p_Prob,MATCH(LARGE(p_Key,11),p_Key,0)),""),"") | L15: =IFERROR(INDEX(p_Risk,MATCH(LARGE(p_Key,11),p_Key,0)),"") | M15: =IFERROR(INDEX(p_Month,MATCH(LARGE(p_Key,11),p_Key,0)),"") | N15: =IFERROR(INDEX(p_Flags,MATCH(LARGE(p_Key,11),p_Key,0)),"")
A16: =IF(D16="","",12) | B16: =IFERROR(INDEX(p_Rating,MATCH(LARGE(p_Key,12),p_Key,0)),"") | C16: =IFERROR(INDEX(p_Score,MATCH(LARGE(p_Key,12),p_Key,0)),"") | D16: =IFERROR(INDEX(p_Job,MATCH(LARGE(p_Key,12),p_Key,0)),"") | E16: =IFERROR(INDEX(p_Client,MATCH(LARGE(p_Key,12),p_Key,0)),"") | F16: =IFERROR(INDEX(p_Deal,MATCH(LARGE(p_Key,12),p_Key,0)),"") | G16: =IFERROR(INDEX(p_CC,MATCH(LARGE(p_Key,12),p_Key,0)),"") | H16: =IFERROR(INDEX(p_Status,MATCH(LARGE(p_Key,12),p_Key,0)),"") | I16: =IFERROR(INDEX(p_Stage,MATCH(LARGE(p_Key,12),p_Key,0)),"") | J16: =IFERROR(INDEX(p_Value,MATCH(LARGE(p_Key,12),p_Key,0)),"") | K16: =IFERROR(IF(H16="Open",INDEX(p_Prob,MATCH(LARGE(p_Key,12),p_Key,0)),""),"") | L16: =IFERROR(INDEX(p_Risk,MATCH(LARGE(p_Key,12),p_Key,0)),"") | M16: =IFERROR(INDEX(p_Month,MATCH(LARGE(p_Key,12),p_Key,0)),"") | N16: =IFERROR(INDEX(p_Flags,MATCH(LARGE(p_Key,12),p_Key,0)),"")
A17: =IF(D17="","",13) | B17: =IFERROR(INDEX(p_Rating,MATCH(LARGE(p_Key,13),p_Key,0)),"") | C17: =IFERROR(INDEX(p_Score,MATCH(LARGE(p_Key,13),p_Key,0)),"") | D17: =IFERROR(INDEX(p_Job,MATCH(LARGE(p_Key,13),p_Key,0)),"") | E17: =IFERROR(INDEX(p_Client,MATCH(LARGE(p_Key,13),p_Key,0)),"") | F17: =IFERROR(INDEX(p_Deal,MATCH(LARGE(p_Key,13),p_Key,0)),"") | G17: =IFERROR(INDEX(p_CC,MATCH(LARGE(p_Key,13),p_Key,0)),"") | H17: =IFERROR(INDEX(p_Status,MATCH(LARGE(p_Key,13),p_Key,0)),"") | I17: =IFERROR(INDEX(p_Stage,MATCH(LARGE(p_Key,13),p_Key,0)),"") | J17: =IFERROR(INDEX(p_Value,MATCH(LARGE(p_Key,13),p_Key,0)),"") | K17: =IFERROR(IF(H17="Open",INDEX(p_Prob,MATCH(LARGE(p_Key,13),p_Key,0)),""),"") | L17: =IFERROR(INDEX(p_Risk,MATCH(LARGE(p_Key,13),p_Key,0)),"") | M17: =IFERROR(INDEX(p_Month,MATCH(LARGE(p_Key,13),p_Key,0)),"") | N17: =IFERROR(INDEX(p_Flags,MATCH(LARGE(p_Key,13),p_Key,0)),"")
A18: =IF(D18="","",14) | B18: =IFERROR(INDEX(p_Rating,MATCH(LARGE(p_Key,14),p_Key,0)),"") | C18: =IFERROR(INDEX(p_Score,MATCH(LARGE(p_Key,14),p_Key,0)),"") | D18: =IFERROR(INDEX(p_Job,MATCH(LARGE(p_Key,14),p_Key,0)),"") | E18: =IFERROR(INDEX(p_Client,MATCH(LARGE(p_Key,14),p_Key,0)),"") | F18: =IFERROR(INDEX(p_Deal,MATCH(LARGE(p_Key,14),p_Key,0)),"") | G18: =IFERROR(INDEX(p_CC,MATCH(LARGE(p_Key,14),p_Key,0)),"") | H18: =IFERROR(INDEX(p_Status,MATCH(LARGE(p_Key,14),p_Key,0)),"") | I18: =IFERROR(INDEX(p_Stage,MATCH(LARGE(p_Key,14),p_Key,0)),"") | J18: =IFERROR(INDEX(p_Value,MATCH(LARGE(p_Key,14),p_Key,0)),"") | K18: =IFERROR(IF(H18="Open",INDEX(p_Prob,MATCH(LARGE(p_Key,14),p_Key,0)),""),"") | L18: =IFERROR(INDEX(p_Risk,MATCH(LARGE(p_Key,14),p_Key,0)),"") | M18: =IFERROR(INDEX(p_Month,MATCH(LARGE(p_Key,14),p_Key,0)),"") | N18: =IFERROR(INDEX(p_Flags,MATCH(LARGE(p_Key,14),p_Key,0)),"")
A19: =IF(D19="","",15) | B19: =IFERROR(INDEX(p_Rating,MATCH(LARGE(p_Key,15),p_Key,0)),"") | C19: =IFERROR(INDEX(p_Score,MATCH(LARGE(p_Key,15),p_Key,0)),"") | D19: =IFERROR(INDEX(p_Job,MATCH(LARGE(p_Key,15),p_Key,0)),"") | E19: =IFERROR(INDEX(p_Client,MATCH(LARGE(p_Key,15),p_Key,0)),"") | F19: =IFERROR(INDEX(p_Deal,MATCH(LARGE(p_Key,15),p_Key,0)),"") | G19: =IFERROR(INDEX(p_CC,MATCH(LARGE(p_Key,15),p_Key,0)),"") | H19: =IFERROR(INDEX(p_Status,MATCH(LARGE(p_Key,15),p_Key,0)),"") | I19: =IFERROR(INDEX(p_Stage,MATCH(LARGE(p_Key,15),p_Key,0)),"") | J19: =IFERROR(INDEX(p_Value,MATCH(LARGE(p_Key,15),p_Key,0)),"") | K19: =IFERROR(IF(H19="Open",INDEX(p_Prob,MATCH(LARGE(p_Key,15),p_Key,0)),""),"") | L19: =IFERROR(INDEX(p_Risk,MATCH(LARGE(p_Key,15),p_Key,0)),"") | M19: =IFERROR(INDEX(p_Month,MATCH(LARGE(p_Key,15),p_Key,0)),"") | N19: =IFERROR(INDEX(p_Flags,MATCH(LARGE(p_Key,15),p_Key,0)),"")
A20: =IF(D20="","",16) | B20: =IFERROR(INDEX(p_Rating,MATCH(LARGE(p_Key,16),p_Key,0)),"") | C20: =IFERROR(INDEX(p_Score,MATCH(LARGE(p_Key,16),p_Key,0)),"") | D20: =IFERROR(INDEX(p_Job,MATCH(LARGE(p_Key,16),p_Key,0)),"") | E20: =IFERROR(INDEX(p_Client,MATCH(LARGE(p_Key,16),p_Key,0)),"") | F20: =IFERROR(INDEX(p_Deal,MATCH(LARGE(p_Key,16),p_Key,0)),"") | G20: =IFERROR(INDEX(p_CC,MATCH(LARGE(p_Key,16),p_Key,0)),"") | H20: =IFERROR(INDEX(p_Status,MATCH(LARGE(p_Key,16),p_Key,0)),"") | I20: =IFERROR(INDEX(p_Stage,MATCH(LARGE(p_Key,16),p_Key,0)),"") | J20: =IFERROR(INDEX(p_Value,MATCH(LARGE(p_Key,16),p_Key,0)),"") | K20: =IFERROR(IF(H20="Open",INDEX(p_Prob,MATCH(LARGE(p_Key,16),p_Key,0)),""),"") | L20: =IFERROR(INDEX(p_Risk,MATCH(LARGE(p_Key,16),p_Key,0)),"") | M20: =IFERROR(INDEX(p_Month,MATCH(LARGE(p_Key,16),p_Key,0)),"") | N20: =IFERROR(INDEX(p_Flags,MATCH(LARGE(p_Key,16),p_Key,0)),"")
A21: =IF(D21="","",17) | B21: =IFERROR(INDEX(p_Rating,MATCH(LARGE(p_Key,17),p_Key,0)),"") | C21: =IFERROR(INDEX(p_Score,MATCH(LARGE(p_Key,17),p_Key,0)),"") | D21: =IFERROR(INDEX(p_Job,MATCH(LARGE(p_Key,17),p_Key,0)),"") | E21: =IFERROR(INDEX(p_Client,MATCH(LARGE(p_Key,17),p_Key,0)),"") | F21: =IFERROR(INDEX(p_Deal,MATCH(LARGE(p_Key,17),p_Key,0)),"") | G21: =IFERROR(INDEX(p_CC,MATCH(LARGE(p_Key,17),p_Key,0)),"") | H21: =IFERROR(INDEX(p_Status,MATCH(LARGE(p_Key,17),p_Key,0)),"") | I21: =IFERROR(INDEX(p_Stage,MATCH(LARGE(p_Key,17),p_Key,0)),"") | J21: =IFERROR(INDEX(p_Value,MATCH(LARGE(p_Key,17),p_Key,0)),"") | K21: =IFERROR(IF(H21="Open",INDEX(p_Prob,MATCH(LARGE(p_Key,17),p_Key,0)),""),"") | L21: =IFERROR(INDEX(p_Risk,MATCH(LARGE(p_Key,17),p_Key,0)),"") | M21: =IFERROR(INDEX(p_Month,MATCH(LARGE(p_Key,17),p_Key,0)),"") | N21: =IFERROR(INDEX(p_Flags,MATCH(LARGE(p_Key,17),p_Key,0)),"")
A22: =IF(D22="","",18) | B22: =IFERROR(INDEX(p_Rating,MATCH(LARGE(p_Key,18),p_Key,0)),"") | C22: =IFERROR(INDEX(p_Score,MATCH(LARGE(p_Key,18),p_Key,0)),"") | D22: =IFERROR(INDEX(p_Job,MATCH(LARGE(p_Key,18),p_Key,0)),"") | E22: =IFERROR(INDEX(p_Client,MATCH(LARGE(p_Key,18),p_Key,0)),"") | F22: =IFERROR(INDEX(p_Deal,MATCH(LARGE(p_Key,18),p_Key,0)),"") | G22: =IFERROR(INDEX(p_CC,MATCH(LARGE(p_Key,18),p_Key,0)),"") | H22: =IFERROR(INDEX(p_Status,MATCH(LARGE(p_Key,18),p_Key,0)),"") | I22: =IFERROR(INDEX(p_Stage,MATCH(LARGE(p_Key,18),p_Key,0)),"") | J22: =IFERROR(INDEX(p_Value,MATCH(LARGE(p_Key,18),p_Key,0)),"") | K22: =IFERROR(IF(H22="Open",INDEX(p_Prob,MATCH(LARGE(p_Key,18),p_Key,0)),""),"") | L22: =IFERROR(INDEX(p_Risk,MATCH(LARGE(p_Key,18),p_Key,0)),"") | M22: =IFERROR(INDEX(p_Month,MATCH(LARGE(p_Key,18),p_Key,0)),"") | N22: =IFERROR(INDEX(p_Flags,MATCH(LARGE(p_Key,18),p_Key,0)),"")
A23: =IF(D23="","",19) | B23: =IFERROR(INDEX(p_Rating,MATCH(LARGE(p_Key,19),p_Key,0)),"") | C23: =IFERROR(INDEX(p_Score,MATCH(LARGE(p_Key,19),p_Key,0)),"") | D23: =IFERROR(INDEX(p_Job,MATCH(LARGE(p_Key,19),p_Key,0)),"") | E23: =IFERROR(INDEX(p_Client,MATCH(LARGE(p_Key,19),p_Key,0)),"") | F23: =IFERROR(INDEX(p_Deal,MATCH(LARGE(p_Key,19),p_Key,0)),"") | G23: =IFERROR(INDEX(p_CC,MATCH(LARGE(p_Key,19),p_Key,0)),"") | H23: =IFERROR(INDEX(p_Status,MATCH(LARGE(p_Key,19),p_Key,0)),"") | I23: =IFERROR(INDEX(p_Stage,MATCH(LARGE(p_Key,19),p_Key,0)),"") | J23: =IFERROR(INDEX(p_Value,MATCH(LARGE(p_Key,19),p_Key,0)),"") | K23: =IFERROR(IF(H23="Open",INDEX(p_Prob,MATCH(LARGE(p_Key,19),p_Key,0)),""),"") | L23: =IFERROR(INDEX(p_Risk,MATCH(LARGE(p_Key,19),p_Key,0)),"") | M23: =IFERROR(INDEX(p_Month,MATCH(LARGE(p_Key,19),p_Key,0)),"") | N23: =IFERROR(INDEX(p_Flags,MATCH(LARGE(p_Key,19),p_Key,0)),"")
A24: =IF(D24="","",20) | B24: =IFERROR(INDEX(p_Rating,MATCH(LARGE(p_Key,20),p_Key,0)),"") | C24: =IFERROR(INDEX(p_Score,MATCH(LARGE(p_Key,20),p_Key,0)),"") | D24: =IFERROR(INDEX(p_Job,MATCH(LARGE(p_Key,20),p_Key,0)),"") | E24: =IFERROR(INDEX(p_Client,MATCH(LARGE(p_Key,20),p_Key,0)),"") | F24: =IFERROR(INDEX(p_Deal,MATCH(LARGE(p_Key,20),p_Key,0)),"") | G24: =IFERROR(INDEX(p_CC,MATCH(LARGE(p_Key,20),p_Key,0)),"") | H24: =IFERROR(INDEX(p_Status,MATCH(LARGE(p_Key,20),p_Key,0)),"") | I24: =IFERROR(INDEX(p_Stage,MATCH(LARGE(p_Key,20),p_Key,0)),"") | J24: =IFERROR(INDEX(p_Value,MATCH(LARGE(p_Key,20),p_Key,0)),"") | K24: =IFERROR(IF(H24="Open",INDEX(p_Prob,MATCH(LARGE(p_Key,20),p_Key,0)),""),"") | L24: =IFERROR(INDEX(p_Risk,MATCH(LARGE(p_Key,20),p_Key,0)),"") | M24: =IFERROR(INDEX(p_Month,MATCH(LARGE(p_Key,20),p_Key,0)),"") | N24: =IFERROR(INDEX(p_Flags,MATCH(LARGE(p_Key,20),p_Key,0)),"")
A25: =IF(D25="","",21) | B25: =IFERROR(INDEX(p_Rating,MATCH(LARGE(p_Key,21),p_Key,0)),"") | C25: =IFERROR(INDEX(p_Score,MATCH(LARGE(p_Key,21),p_Key,0)),"") | D25: =IFERROR(INDEX(p_Job,MATCH(LARGE(p_Key,21),p_Key,0)),"") | E25: =IFERROR(INDEX(p_Client,MATCH(LARGE(p_Key,21),p_Key,0)),"") | F25: =IFERROR(INDEX(p_Deal,MATCH(LARGE(p_Key,21),p_Key,0)),"") | G25: =IFERROR(INDEX(p_CC,MATCH(LARGE(p_Key,21),p_Key,0)),"") | H25: =IFERROR(INDEX(p_Status,MATCH(LARGE(p_Key,21),p_Key,0)),"") | I25: =IFERROR(INDEX(p_Stage,MATCH(LARGE(p_Key,21),p_Key,0)),"") | J25: =IFERROR(INDEX(p_Value,MATCH(LARGE(p_Key,21),p_Key,0)),"") | K25: =IFERROR(IF(H25="Open",INDEX(p_Prob,MATCH(LARGE(p_Key,21),p_Key,0)),""),"") | L25: =IFERROR(INDEX(p_Risk,MATCH(LARGE(p_Key,21),p_Key,0)),"") | M25: =IFERROR(INDEX(p_Month,MATCH(LARGE(p_Key,21),p_Key,0)),"") | N25: =IFERROR(INDEX(p_Flags,MATCH(LARGE(p_Key,21),p_Key,0)),"")
A26: =IF(D26="","",22) | B26: =IFERROR(INDEX(p_Rating,MATCH(LARGE(p_Key,22),p_Key,0)),"") | C26: =IFERROR(INDEX(p_Score,MATCH(LARGE(p_Key,22),p_Key,0)),"") | D26: =IFERROR(INDEX(p_Job,MATCH(LARGE(p_Key,22),p_Key,0)),"") | E26: =IFERROR(INDEX(p_Client,MATCH(LARGE(p_Key,22),p_Key,0)),"") | F26: =IFERROR(INDEX(p_Deal,MATCH(LARGE(p_Key,22),p_Key,0)),"") | G26: =IFERROR(INDEX(p_CC,MATCH(LARGE(p_Key,22),p_Key,0)),"") | H26: =IFERROR(INDEX(p_Status,MATCH(LARGE(p_Key,22),p_Key,0)),"") | I26: =IFERROR(INDEX(p_Stage,MATCH(LARGE(p_Key,22),p_Key,0)),"") | J26: =IFERROR(INDEX(p_Value,MATCH(LARGE(p_Key,22),p_Key,0)),"") | K26: =IFERROR(IF(H26="Open",INDEX(p_Prob,MATCH(LARGE(p_Key,22),p_Key,0)),""),"") | L26: =IFERROR(INDEX(p_Risk,MATCH(LARGE(p_Key,22),p_Key,0)),"") | M26: =IFERROR(INDEX(p_Month,MATCH(LARGE(p_Key,22),p_Key,0)),"") | N26: =IFERROR(INDEX(p_Flags,MATCH(LARGE(p_Key,22),p_Key,0)),"")
A27: =IF(D27="","",23) | B27: =IFERROR(INDEX(p_Rating,MATCH(LARGE(p_Key,23),p_Key,0)),"") | C27: =IFERROR(INDEX(p_Score,MATCH(LARGE(p_Key,23),p_Key,0)),"") | D27: =IFERROR(INDEX(p_Job,MATCH(LARGE(p_Key,23),p_Key,0)),"") | E27: =IFERROR(INDEX(p_Client,MATCH(LARGE(p_Key,23),p_Key,0)),"") | F27: =IFERROR(INDEX(p_Deal,MATCH(LARGE(p_Key,23),p_Key,0)),"") | G27: =IFERROR(INDEX(p_CC,MATCH(LARGE(p_Key,23),p_Key,0)),"") | H27: =IFERROR(INDEX(p_Status,MATCH(LARGE(p_Key,23),p_Key,0)),"") | I27: =IFERROR(INDEX(p_Stage,MATCH(LARGE(p_Key,23),p_Key,0)),"") | J27: =IFERROR(INDEX(p_Value,MATCH(LARGE(p_Key,23),p_Key,0)),"") | K27: =IFERROR(IF(H27="Open",INDEX(p_Prob,MATCH(LARGE(p_Key,23),p_Key,0)),""),"") | L27: =IFERROR(INDEX(p_Risk,MATCH(LARGE(p_Key,23),p_Key,0)),"") | M27: =IFERROR(INDEX(p_Month,MATCH(LARGE(p_Key,23),p_Key,0)),"") | N27: =IFERROR(INDEX(p_Flags,MATCH(LARGE(p_Key,23),p_Key,0)),"")
A28: =IF(D28="","",24) | B28: =IFERROR(INDEX(p_Rating,MATCH(LARGE(p_Key,24),p_Key,0)),"") | C28: =IFERROR(INDEX(p_Score,MATCH(LARGE(p_Key,24),p_Key,0)),"") | D28: =IFERROR(INDEX(p_Job,MATCH(LARGE(p_Key,24),p_Key,0)),"") | E28: =IFERROR(INDEX(p_Client,MATCH(LARGE(p_Key,24),p_Key,0)),"") | F28: =IFERROR(INDEX(p_Deal,MATCH(LARGE(p_Key,24),p_Key,0)),"") | G28: =IFERROR(INDEX(p_CC,MATCH(LARGE(p_Key,24),p_Key,0)),"") | H28: =IFERROR(INDEX(p_Status,MATCH(LARGE(p_Key,24),p_Key,0)),"") | I28: =IFERROR(INDEX(p_Stage,MATCH(LARGE(p_Key,24),p_Key,0)),"") | J28: =IFERROR(INDEX(p_Value,MATCH(LARGE(p_Key,24),p_Key,0)),"") | K28: =IFERROR(IF(H28="Open",INDEX(p_Prob,MATCH(LARGE(p_Key,24),p_Key,0)),""),"") | L28: =IFERROR(INDEX(p_Risk,MATCH(LARGE(p_Key,24),p_Key,0)),"") | M28: =IFERROR(INDEX(p_Month,MATCH(LARGE(p_Key,24),p_Key,0)),"") | N28: =IFERROR(INDEX(p_Flags,MATCH(LARGE(p_Key,24),p_Key,0)),"")
A29: =IF(D29="","",25) | B29: =IFERROR(INDEX(p_Rating,MATCH(LARGE(p_Key,25),p_Key,0)),"") | C29: =IFERROR(INDEX(p_Score,MATCH(LARGE(p_Key,25),p_Key,0)),"") | D29: =IFERROR(INDEX(p_Job,MATCH(LARGE(p_Key,25),p_Key,0)),"") | E29: =IFERROR(INDEX(p_Client,MATCH(LARGE(p_Key,25),p_Key,0)),"") | F29: =IFERROR(INDEX(p_Deal,MATCH(LARGE(p_Key,25),p_Key,0)),"") | G29: =IFERROR(INDEX(p_CC,MATCH(LARGE(p_Key,25),p_Key,0)),"") | H29: =IFERROR(INDEX(p_Status,MATCH(LARGE(p_Key,25),p_Key,0)),"") | I29: =IFERROR(INDEX(p_Stage,MATCH(LARGE(p_Key,25),p_Key,0)),"") | J29: =IFERROR(INDEX(p_Value,MATCH(LARGE(p_Key,25),p_Key,0)),"") | K29: =IFERROR(IF(H29="Open",INDEX(p_Prob,MATCH(LARGE(p_Key,25),p_Key,0)),""),"") | L29: =IFERROR(INDEX(p_Risk,MATCH(LARGE(p_Key,25),p_Key,0)),"") | M29: =IFERROR(INDEX(p_Month,MATCH(LARGE(p_Key,25),p_Key,0)),"") | N29: =IFERROR(INDEX(p_Flags,MATCH(LARGE(p_Key,25),p_Key,0)),"")
A30: =IF(D30="","",26) | B30: =IFERROR(INDEX(p_Rating,MATCH(LARGE(p_Key,26),p_Key,0)),"") | C30: =IFERROR(INDEX(p_Score,MATCH(LARGE(p_Key,26),p_Key,0)),"") | D30: =IFERROR(INDEX(p_Job,MATCH(LARGE(p_Key,26),p_Key,0)),"") | E30: =IFERROR(INDEX(p_Client,MATCH(LARGE(p_Key,26),p_Key,0)),"") | F30: =IFERROR(INDEX(p_Deal,MATCH(LARGE(p_Key,26),p_Key,0)),"") | G30: =IFERROR(INDEX(p_CC,MATCH(LARGE(p_Key,26),p_Key,0)),"") | H30: =IFERROR(INDEX(p_Status,MATCH(LARGE(p_Key,26),p_Key,0)),"") | I30: =IFERROR(INDEX(p_Stage,MATCH(LARGE(p_Key,26),p_Key,0)),"") | J30: =IFERROR(INDEX(p_Value,MATCH(LARGE(p_Key,26),p_Key,0)),"") | K30: =IFERROR(IF(H30="Open",INDEX(p_Prob,MATCH(LARGE(p_Key,26),p_Key,0)),""),"") | L30: =IFERROR(INDEX(p_Risk,MATCH(LARGE(p_Key,26),p_Key,0)),"") | M30: =IFERROR(INDEX(p_Month,MATCH(LARGE(p_Key,26),p_Key,0)),"") | N30: =IFERROR(INDEX(p_Flags,MATCH(LARGE(p_Key,26),p_Key,0)),"")
A31: =IF(D31="","",27) | B31: =IFERROR(INDEX(p_Rating,MATCH(LARGE(p_Key,27),p_Key,0)),"") | C31: =IFERROR(INDEX(p_Score,MATCH(LARGE(p_Key,27),p_Key,0)),"") | D31: =IFERROR(INDEX(p_Job,MATCH(LARGE(p_Key,27),p_Key,0)),"") | E31: =IFERROR(INDEX(p_Client,MATCH(LARGE(p_Key,27),p_Key,0)),"") | F31: =IFERROR(INDEX(p_Deal,MATCH(LARGE(p_Key,27),p_Key,0)),"") | G31: =IFERROR(INDEX(p_CC,MATCH(LARGE(p_Key,27),p_Key,0)),"") | H31: =IFERROR(INDEX(p_Status,MATCH(LARGE(p_Key,27),p_Key,0)),"") | I31: =IFERROR(INDEX(p_Stage,MATCH(LARGE(p_Key,27),p_Key,0)),"") | J31: =IFERROR(INDEX(p_Value,MATCH(LARGE(p_Key,27),p_Key,0)),"") | K31: =IFERROR(IF(H31="Open",INDEX(p_Prob,MATCH(LARGE(p_Key,27),p_Key,0)),""),"") | L31: =IFERROR(INDEX(p_Risk,MATCH(LARGE(p_Key,27),p_Key,0)),"") | M31: =IFERROR(INDEX(p_Month,MATCH(LARGE(p_Key,27),p_Key,0)),"") | N31: =IFERROR(INDEX(p_Flags,MATCH(LARGE(p_Key,27),p_Key,0)),"")
A32: =IF(D32="","",28) | B32: =IFERROR(INDEX(p_Rating,MATCH(LARGE(p_Key,28),p_Key,0)),"") | C32: =IFERROR(INDEX(p_Score,MATCH(LARGE(p_Key,28),p_Key,0)),"") | D32: =IFERROR(INDEX(p_Job,MATCH(LARGE(p_Key,28),p_Key,0)),"") | E32: =IFERROR(INDEX(p_Client,MATCH(LARGE(p_Key,28),p_Key,0)),"") | F32: =IFERROR(INDEX(p_Deal,MATCH(LARGE(p_Key,28),p_Key,0)),"") | G32: =IFERROR(INDEX(p_CC,MATCH(LARGE(p_Key,28),p_Key,0)),"") | H32: =IFERROR(INDEX(p_Status,MATCH(LARGE(p_Key,28),p_Key,0)),"") | I32: =IFERROR(INDEX(p_Stage,MATCH(LARGE(p_Key,28),p_Key,0)),"") | J32: =IFERROR(INDEX(p_Value,MATCH(LARGE(p_Key,28),p_Key,0)),"") | K32: =IFERROR(IF(H32="Open",INDEX(p_Prob,MATCH(LARGE(p_Key,28),p_Key,0)),""),"") | L32: =IFERROR(INDEX(p_Risk,MATCH(LARGE(p_Key,28),p_Key,0)),"") | M32: =IFERROR(INDEX(p_Month,MATCH(LARGE(p_Key,28),p_Key,0)),"") | N32: =IFERROR(INDEX(p_Flags,MATCH(LARGE(p_Key,28),p_Key,0)),"")
A33: =IF(D33="","",29) | B33: =IFERROR(INDEX(p_Rating,MATCH(LARGE(p_Key,29),p_Key,0)),"") | C33: =IFERROR(INDEX(p_Score,MATCH(LARGE(p_Key,29),p_Key,0)),"") | D33: =IFERROR(INDEX(p_Job,MATCH(LARGE(p_Key,29),p_Key,0)),"") | E33: =IFERROR(INDEX(p_Client,MATCH(LARGE(p_Key,29),p_Key,0)),"") | F33: =IFERROR(INDEX(p_Deal,MATCH(LARGE(p_Key,29),p_Key,0)),"") | G33: =IFERROR(INDEX(p_CC,MATCH(LARGE(p_Key,29),p_Key,0)),"") | H33: =IFERROR(INDEX(p_Status,MATCH(LARGE(p_Key,29),p_Key,0)),"") | I33: =IFERROR(INDEX(p_Stage,MATCH(LARGE(p_Key,29),p_Key,0)),"") | J33: =IFERROR(INDEX(p_Value,MATCH(LARGE(p_Key,29),p_Key,0)),"") | K33: =IFERROR(IF(H33="Open",INDEX(p_Prob,MATCH(LARGE(p_Key,29),p_Key,0)),""),"") | L33: =IFERROR(INDEX(p_Risk,MATCH(LARGE(p_Key,29),p_Key,0)),"") | M33: =IFERROR(INDEX(p_Month,MATCH(LARGE(p_Key,29),p_Key,0)),"") | N33: =IFERROR(INDEX(p_Flags,MATCH(LARGE(p_Key,29),p_Key,0)),"")
A34: =IF(D34="","",30) | B34: =IFERROR(INDEX(p_Rating,MATCH(LARGE(p_Key,30),p_Key,0)),"") | C34: =IFERROR(INDEX(p_Score,MATCH(LARGE(p_Key,30),p_Key,0)),"") | D34: =IFERROR(INDEX(p_Job,MATCH(LARGE(p_Key,30),p_Key,0)),"") | E34: =IFERROR(INDEX(p_Client,MATCH(LARGE(p_Key,30),p_Key,0)),"") | F34: =IFERROR(INDEX(p_Deal,MATCH(LARGE(p_Key,30),p_Key,0)),"") | G34: =IFERROR(INDEX(p_CC,MATCH(LARGE(p_Key,30),p_Key,0)),"") | H34: =IFERROR(INDEX(p_Status,MATCH(LARGE(p_Key,30),p_Key,0)),"") | I34: =IFERROR(INDEX(p_Stage,MATCH(LARGE(p_Key,30),p_Key,0)),"") | J34: =IFERROR(INDEX(p_Value,MATCH(LARGE(p_Key,30),p_Key,0)),"") | K34: =IFERROR(IF(H34="Open",INDEX(p_Prob,MATCH(LARGE(p_Key,30),p_Key,0)),""),"") | L34: =IFERROR(INDEX(p_Risk,MATCH(LARGE(p_Key,30),p_Key,0)),"") | M34: =IFERROR(INDEX(p_Month,MATCH(LARGE(p_Key,30),p_Key,0)),"") | N34: =IFERROR(INDEX(p_Flags,MATCH(LARGE(p_Key,30),p_Key,0)),"")
A35: =IF(D35="","",31) | B35: =IFERROR(INDEX(p_Rating,MATCH(LARGE(p_Key,31),p_Key,0)),"") | C35: =IFERROR(INDEX(p_Score,MATCH(LARGE(p_Key,31),p_Key,0)),"") | D35: =IFERROR(INDEX(p_Job,MATCH(LARGE(p_Key,31),p_Key,0)),"") | E35: =IFERROR(INDEX(p_Client,MATCH(LARGE(p_Key,31),p_Key,0)),"") | F35: =IFERROR(INDEX(p_Deal,MATCH(LARGE(p_Key,31),p_Key,0)),"") | G35: =IFERROR(INDEX(p_CC,MATCH(LARGE(p_Key,31),p_Key,0)),"") | H35: =IFERROR(INDEX(p_Status,MATCH(LARGE(p_Key,31),p_Key,0)),"") | I35: =IFERROR(INDEX(p_Stage,MATCH(LARGE(p_Key,31),p_Key,0)),"") | J35: =IFERROR(INDEX(p_Value,MATCH(LARGE(p_Key,31),p_Key,0)),"") | K35: =IFERROR(IF(H35="Open",INDEX(p_Prob,MATCH(LARGE(p_Key,31),p_Key,0)),""),"") | L35: =IFERROR(INDEX(p_Risk,MATCH(LARGE(p_Key,31),p_Key,0)),"") | M35: =IFERROR(INDEX(p_Month,MATCH(LARGE(p_Key,31),p_Key,0)),"") | N35: =IFERROR(INDEX(p_Flags,MATCH(LARGE(p_Key,31),p_Key,0)),"")
A36: =IF(D36="","",32) | B36: =IFERROR(INDEX(p_Rating,MATCH(LARGE(p_Key,32),p_Key,0)),"") | C36: =IFERROR(INDEX(p_Score,MATCH(LARGE(p_Key,32),p_Key,0)),"") | D36: =IFERROR(INDEX(p_Job,MATCH(LARGE(p_Key,32),p_Key,0)),"") | E36: =IFERROR(INDEX(p_Client,MATCH(LARGE(p_Key,32),p_Key,0)),"") | F36: =IFERROR(INDEX(p_Deal,MATCH(LARGE(p_Key,32),p_Key,0)),"") | G36: =IFERROR(INDEX(p_CC,MATCH(LARGE(p_Key,32),p_Key,0)),"") | H36: =IFERROR(INDEX(p_Status,MATCH(LARGE(p_Key,32),p_Key,0)),"") | I36: =IFERROR(INDEX(p_Stage,MATCH(LARGE(p_Key,32),p_Key,0)),"") | J36: =IFERROR(INDEX(p_Value,MATCH(LARGE(p_Key,32),p_Key,0)),"") | K36: =IFERROR(IF(H36="Open",INDEX(p_Prob,MATCH(LARGE(p_Key,32),p_Key,0)),""),"") | L36: =IFERROR(INDEX(p_Risk,MATCH(LARGE(p_Key,32),p_Key,0)),"") | M36: =IFERROR(INDEX(p_Month,MATCH(LARGE(p_Key,32),p_Key,0)),"") | N36: =IFERROR(INDEX(p_Flags,MATCH(LARGE(p_Key,32),p_Key,0)),"")
A37: =IF(D37="","",33) | B37: =IFERROR(INDEX(p_Rating,MATCH(LARGE(p_Key,33),p_Key,0)),"") | C37: =IFERROR(INDEX(p_Score,MATCH(LARGE(p_Key,33),p_Key,0)),"") | D37: =IFERROR(INDEX(p_Job,MATCH(LARGE(p_Key,33),p_Key,0)),"") | E37: =IFERROR(INDEX(p_Client,MATCH(LARGE(p_Key,33),p_Key,0)),"") | F37: =IFERROR(INDEX(p_Deal,MATCH(LARGE(p_Key,33),p_Key,0)),"") | G37: =IFERROR(INDEX(p_CC,MATCH(LARGE(p_Key,33),p_Key,0)),"") | H37: =IFERROR(INDEX(p_Status,MATCH(LARGE(p_Key,33),p_Key,0)),"") | I37: =IFERROR(INDEX(p_Stage,MATCH(LARGE(p_Key,33),p_Key,0)),"") | J37: =IFERROR(INDEX(p_Value,MATCH(LARGE(p_Key,33),p_Key,0)),"") | K37: =IFERROR(IF(H37="Open",INDEX(p_Prob,MATCH(LARGE(p_Key,33),p_Key,0)),""),"") | L37: =IFERROR(INDEX(p_Risk,MATCH(LARGE(p_Key,33),p_Key,0)),"") | M37: =IFERROR(INDEX(p_Month,MATCH(LARGE(p_Key,33),p_Key,0)),"") | N37: =IFERROR(INDEX(p_Flags,MATCH(LARGE(p_Key,33),p_Key,0)),"")
A38: =IF(D38="","",34) | B38: =IFERROR(INDEX(p_Rating,MATCH(LARGE(p_Key,34),p_Key,0)),"") | C38: =IFERROR(INDEX(p_Score,MATCH(LARGE(p_Key,34),p_Key,0)),"") | D38: =IFERROR(INDEX(p_Job,MATCH(LARGE(p_Key,34),p_Key,0)),"") | E38: =IFERROR(INDEX(p_Client,MATCH(LARGE(p_Key,34),p_Key,0)),"") | F38: =IFERROR(INDEX(p_Deal,MATCH(LARGE(p_Key,34),p_Key,0)),"") | G38: =IFERROR(INDEX(p_CC,MATCH(LARGE(p_Key,34),p_Key,0)),"") | H38: =IFERROR(INDEX(p_Status,MATCH(LARGE(p_Key,34),p_Key,0)),"") | I38: =IFERROR(INDEX(p_Stage,MATCH(LARGE(p_Key,34),p_Key,0)),"") | J38: =IFERROR(INDEX(p_Value,MATCH(LARGE(p_Key,34),p_Key,0)),"") | K38: =IFERROR(IF(H38="Open",INDEX(p_Prob,MATCH(LARGE(p_Key,34),p_Key,0)),""),"") | L38: =IFERROR(INDEX(p_Risk,MATCH(LARGE(p_Key,34),p_Key,0)),"") | M38: =IFERROR(INDEX(p_Month,MATCH(LARGE(p_Key,34),p_Key,0)),"") | N38: =IFERROR(INDEX(p_Flags,MATCH(LARGE(p_Key,34),p_Key,0)),"")
A39: =IF(D39="","",35) | B39: =IFERROR(INDEX(p_Rating,MATCH(LARGE(p_Key,35),p_Key,0)),"") | C39: =IFERROR(INDEX(p_Score,MATCH(LARGE(p_Key,35),p_Key,0)),"") | D39: =IFERROR(INDEX(p_Job,MATCH(LARGE(p_Key,35),p_Key,0)),"") | E39: =IFERROR(INDEX(p_Client,MATCH(LARGE(p_Key,35),p_Key,0)),"") | F39: =IFERROR(INDEX(p_Deal,MATCH(LARGE(p_Key,35),p_Key,0)),"") | G39: =IFERROR(INDEX(p_CC,MATCH(LARGE(p_Key,35),p_Key,0)),"") | H39: =IFERROR(INDEX(p_Status,MATCH(LARGE(p_Key,35),p_Key,0)),"") | I39: =IFERROR(INDEX(p_Stage,MATCH(LARGE(p_Key,35),p_Key,0)),"") | J39: =IFERROR(INDEX(p_Value,MATCH(LARGE(p_Key,35),p_Key,0)),"") | K39: =IFERROR(IF(H39="Open",INDEX(p_Prob,MATCH(LARGE(p_Key,35),p_Key,0)),""),"") | L39: =IFERROR(INDEX(p_Risk,MATCH(LARGE(p_Key,35),p_Key,0)),"") | M39: =IFERROR(INDEX(p_Month,MATCH(LARGE(p_Key,35),p_Key,0)),"") | N39: =IFERROR(INDEX(p_Flags,MATCH(LARGE(p_Key,35),p_Key,0)),"")
A40: =IF(D40="","",36) | B40: =IFERROR(INDEX(p_Rating,MATCH(LARGE(p_Key,36),p_Key,0)),"") | C40: =IFERROR(INDEX(p_Score,MATCH(LARGE(p_Key,36),p_Key,0)),"") | D40: =IFERROR(INDEX(p_Job,MATCH(LARGE(p_Key,36),p_Key,0)),"") | E40: =IFERROR(INDEX(p_Client,MATCH(LARGE(p_Key,36),p_Key,0)),"") | F40: =IFERROR(INDEX(p_Deal,MATCH(LARGE(p_Key,36),p_Key,0)),"") | G40: =IFERROR(INDEX(p_CC,MATCH(LARGE(p_Key,36),p_Key,0)),"") | H40: =IFERROR(INDEX(p_Status,MATCH(LARGE(p_Key,36),p_Key,0)),"") | I40: =IFERROR(INDEX(p_Stage,MATCH(LARGE(p_Key,36),p_Key,0)),"") | J40: =IFERROR(INDEX(p_Value,MATCH(LARGE(p_Key,36),p_Key,0)),"") | K40: =IFERROR(IF(H40="Open",INDEX(p_Prob,MATCH(LARGE(p_Key,36),p_Key,0)),""),"") | L40: =IFERROR(INDEX(p_Risk,MATCH(LARGE(p_Key,36),p_Key,0)),"") | M40: =IFERROR(INDEX(p_Month,MATCH(LARGE(p_Key,36),p_Key,0)),"") | N40: =IFERROR(INDEX(p_Flags,MATCH(LARGE(p_Key,36),p_Key,0)),"")
A41: =IF(D41="","",37) | B41: =IFERROR(INDEX(p_Rating,MATCH(LARGE(p_Key,37),p_Key,0)),"") | C41: =IFERROR(INDEX(p_Score,MATCH(LARGE(p_Key,37),p_Key,0)),"") | D41: =IFERROR(INDEX(p_Job,MATCH(LARGE(p_Key,37),p_Key,0)),"") | E41: =IFERROR(INDEX(p_Client,MATCH(LARGE(p_Key,37),p_Key,0)),"") | F41: =IFERROR(INDEX(p_Deal,MATCH(LARGE(p_Key,37),p_Key,0)),"") | G41: =IFERROR(INDEX(p_CC,MATCH(LARGE(p_Key,37),p_Key,0)),"") | H41: =IFERROR(INDEX(p_Status,MATCH(LARGE(p_Key,37),p_Key,0)),"") | I41: =IFERROR(INDEX(p_Stage,MATCH(LARGE(p_Key,37),p_Key,0)),"") | J41: =IFERROR(INDEX(p_Value,MATCH(LARGE(p_Key,37),p_Key,0)),"") | K41: =IFERROR(IF(H41="Open",INDEX(p_Prob,MATCH(LARGE(p_Key,37),p_Key,0)),""),"") | L41: =IFERROR(INDEX(p_Risk,MATCH(LARGE(p_Key,37),p_Key,0)),"") | M41: =IFERROR(INDEX(p_Month,MATCH(LARGE(p_Key,37),p_Key,0)),"") | N41: =IFERROR(INDEX(p_Flags,MATCH(LARGE(p_Key,37),p_Key,0)),"")
A42: =IF(D42="","",38) | B42: =IFERROR(INDEX(p_Rating,MATCH(LARGE(p_Key,38),p_Key,0)),"") | C42: =IFERROR(INDEX(p_Score,MATCH(LARGE(p_Key,38),p_Key,0)),"") | D42: =IFERROR(INDEX(p_Job,MATCH(LARGE(p_Key,38),p_Key,0)),"") | E42: =IFERROR(INDEX(p_Client,MATCH(LARGE(p_Key,38),p_Key,0)),"") | F42: =IFERROR(INDEX(p_Deal,MATCH(LARGE(p_Key,38),p_Key,0)),"") | G42: =IFERROR(INDEX(p_CC,MATCH(LARGE(p_Key,38),p_Key,0)),"") | H42: =IFERROR(INDEX(p_Status,MATCH(LARGE(p_Key,38),p_Key,0)),"") | I42: =IFERROR(INDEX(p_Stage,MATCH(LARGE(p_Key,38),p_Key,0)),"") | J42: =IFERROR(INDEX(p_Value,MATCH(LARGE(p_Key,38),p_Key,0)),"") | K42: =IFERROR(IF(H42="Open",INDEX(p_Prob,MATCH(LARGE(p_Key,38),p_Key,0)),""),"") | L42: =IFERROR(INDEX(p_Risk,MATCH(LARGE(p_Key,38),p_Key,0)),"") | M42: =IFERROR(INDEX(p_Month,MATCH(LARGE(p_Key,38),p_Key,0)),"") | N42: =IFERROR(INDEX(p_Flags,MATCH(LARGE(p_Key,38),p_Key,0)),"")
A43: =IF(D43="","",39) | B43: =IFERROR(INDEX(p_Rating,MATCH(LARGE(p_Key,39),p_Key,0)),"") | C43: =IFERROR(INDEX(p_Score,MATCH(LARGE(p_Key,39),p_Key,0)),"") | D43: =IFERROR(INDEX(p_Job,MATCH(LARGE(p_Key,39),p_Key,0)),"") | E43: =IFERROR(INDEX(p_Client,MATCH(LARGE(p_Key,39),p_Key,0)),"") | F43: =IFERROR(INDEX(p_Deal,MATCH(LARGE(p_Key,39),p_Key,0)),"") | G43: =IFERROR(INDEX(p_CC,MATCH(LARGE(p_Key,39),p_Key,0)),"") | H43: =IFERROR(INDEX(p_Status,MATCH(LARGE(p_Key,39),p_Key,0)),"") | I43: =IFERROR(INDEX(p_Stage,MATCH(LARGE(p_Key,39),p_Key,0)),"") | J43: =IFERROR(INDEX(p_Value,MATCH(LARGE(p_Key,39),p_Key,0)),"") | K43: =IFERROR(IF(H43="Open",INDEX(p_Prob,MATCH(LARGE(p_Key,39),p_Key,0)),""),"") | L43: =IFERROR(INDEX(p_Risk,MATCH(LARGE(p_Key,39),p_Key,0)),"") | M43: =IFERROR(INDEX(p_Month,MATCH(LARGE(p_Key,39),p_Key,0)),"") | N43: =IFERROR(INDEX(p_Flags,MATCH(LARGE(p_Key,39),p_Key,0)),"")
A44: =IF(D44="","",40) | B44: =IFERROR(INDEX(p_Rating,MATCH(LARGE(p_Key,40),p_Key,0)),"") | C44: =IFERROR(INDEX(p_Score,MATCH(LARGE(p_Key,40),p_Key,0)),"") | D44: =IFERROR(INDEX(p_Job,MATCH(LARGE(p_Key,40),p_Key,0)),"") | E44: =IFERROR(INDEX(p_Client,MATCH(LARGE(p_Key,40),p_Key,0)),"") | F44: =IFERROR(INDEX(p_Deal,MATCH(LARGE(p_Key,40),p_Key,0)),"") | G44: =IFERROR(INDEX(p_CC,MATCH(LARGE(p_Key,40),p_Key,0)),"") | H44: =IFERROR(INDEX(p_Status,MATCH(LARGE(p_Key,40),p_Key,0)),"") | I44: =IFERROR(INDEX(p_Stage,MATCH(LARGE(p_Key,40),p_Key,0)),"") | J44: =IFERROR(INDEX(p_Value,MATCH(LARGE(p_Key,40),p_Key,0)),"") | K44: =IFERROR(IF(H44="Open",INDEX(p_Prob,MATCH(LARGE(p_Key,40),p_Key,0)),""),"") | L44: =IFERROR(INDEX(p_Risk,MATCH(LARGE(p_Key,40),p_Key,0)),"") | M44: =IFERROR(INDEX(p_Month,MATCH(LARGE(p_Key,40),p_Key,0)),"") | N44: =IFERROR(INDEX(p_Flags,MATCH(LARGE(p_Key,40),p_Key,0)),"")
A45: =IF(D45="","",41) | B45: =IFERROR(INDEX(p_Rating,MATCH(LARGE(p_Key,41),p_Key,0)),"") | C45: =IFERROR(INDEX(p_Score,MATCH(LARGE(p_Key,41),p_Key,0)),"") | D45: =IFERROR(INDEX(p_Job,MATCH(LARGE(p_Key,41),p_Key,0)),"") | E45: =IFERROR(INDEX(p_Client,MATCH(LARGE(p_Key,41),p_Key,0)),"") | F45: =IFERROR(INDEX(p_Deal,MATCH(LARGE(p_Key,41),p_Key,0)),"") | G45: =IFERROR(INDEX(p_CC,MATCH(LARGE(p_Key,41),p_Key,0)),"") | H45: =IFERROR(INDEX(p_Status,MATCH(LARGE(p_Key,41),p_Key,0)),"") | I45: =IFERROR(INDEX(p_Stage,MATCH(LARGE(p_Key,41),p_Key,0)),"") | J45: =IFERROR(INDEX(p_Value,MATCH(LARGE(p_Key,41),p_Key,0)),"") | K45: =IFERROR(IF(H45="Open",INDEX(p_Prob,MATCH(LARGE(p_Key,41),p_Key,0)),""),"") | L45: =IFERROR(INDEX(p_Risk,MATCH(LARGE(p_Key,41),p_Key,0)),"") | M45: =IFERROR(INDEX(p_Month,MATCH(LARGE(p_Key,41),p_Key,0)),"") | N45: =IFERROR(INDEX(p_Flags,MATCH(LARGE(p_Key,41),p_Key,0)),"")
A46: =IF(D46="","",42) | B46: =IFERROR(INDEX(p_Rating,MATCH(LARGE(p_Key,42),p_Key,0)),"") | C46: =IFERROR(INDEX(p_Score,MATCH(LARGE(p_Key,42),p_Key,0)),"") | D46: =IFERROR(INDEX(p_Job,MATCH(LARGE(p_Key,42),p_Key,0)),"") | E46: =IFERROR(INDEX(p_Client,MATCH(LARGE(p_Key,42),p_Key,0)),"") | F46: =IFERROR(INDEX(p_Deal,MATCH(LARGE(p_Key,42),p_Key,0)),"") | G46: =IFERROR(INDEX(p_CC,MATCH(LARGE(p_Key,42),p_Key,0)),"") | H46: =IFERROR(INDEX(p_Status,MATCH(LARGE(p_Key,42),p_Key,0)),"") | I46: =IFERROR(INDEX(p_Stage,MATCH(LARGE(p_Key,42),p_Key,0)),"") | J46: =IFERROR(INDEX(p_Value,MATCH(LARGE(p_Key,42),p_Key,0)),"") | K46: =IFERROR(IF(H46="Open",INDEX(p_Prob,MATCH(LARGE(p_Key,42),p_Key,0)),""),"") | L46: =IFERROR(INDEX(p_Risk,MATCH(LARGE(p_Key,42),p_Key,0)),"") | M46: =IFERROR(INDEX(p_Month,MATCH(LARGE(p_Key,42),p_Key,0)),"") | N46: =IFERROR(INDEX(p_Flags,MATCH(LARGE(p_Key,42),p_Key,0)),"")
A47: =IF(D47="","",43) | B47: =IFERROR(INDEX(p_Rating,MATCH(LARGE(p_Key,43),p_Key,0)),"") | C47: =IFERROR(INDEX(p_Score,MATCH(LARGE(p_Key,43),p_Key,0)),"") | D47: =IFERROR(INDEX(p_Job,MATCH(LARGE(p_Key,43),p_Key,0)),"") | E47: =IFERROR(INDEX(p_Client,MATCH(LARGE(p_Key,43),p_Key,0)),"") | F47: =IFERROR(INDEX(p_Deal,MATCH(LARGE(p_Key,43),p_Key,0)),"") | G47: =IFERROR(INDEX(p_CC,MATCH(LARGE(p_Key,43),p_Key,0)),"") | H47: =IFERROR(INDEX(p_Status,MATCH(LARGE(p_Key,43),p_Key,0)),"") | I47: =IFERROR(INDEX(p_Stage,MATCH(LARGE(p_Key,43),p_Key,0)),"") | J47: =IFERROR(INDEX(p_Value,MATCH(LARGE(p_Key,43),p_Key,0)),"") | K47: =IFERROR(IF(H47="Open",INDEX(p_Prob,MATCH(LARGE(p_Key,43),p_Key,0)),""),"") | L47: =IFERROR(INDEX(p_Risk,MATCH(LARGE(p_Key,43),p_Key,0)),"") | M47: =IFERROR(INDEX(p_Month,MATCH(LARGE(p_Key,43),p_Key,0)),"") | N47: =IFERROR(INDEX(p_Flags,MATCH(LARGE(p_Key,43),p_Key,0)),"")
A48: =IF(D48="","",44) | B48: =IFERROR(INDEX(p_Rating,MATCH(LARGE(p_Key,44),p_Key,0)),"") | C48: =IFERROR(INDEX(p_Score,MATCH(LARGE(p_Key,44),p_Key,0)),"") | D48: =IFERROR(INDEX(p_Job,MATCH(LARGE(p_Key,44),p_Key,0)),"") | E48: =IFERROR(INDEX(p_Client,MATCH(LARGE(p_Key,44),p_Key,0)),"") | F48: =IFERROR(INDEX(p_Deal,MATCH(LARGE(p_Key,44),p_Key,0)),"") | G48: =IFERROR(INDEX(p_CC,MATCH(LARGE(p_Key,44),p_Key,0)),"") | H48: =IFERROR(INDEX(p_Status,MATCH(LARGE(p_Key,44),p_Key,0)),"") | I48: =IFERROR(INDEX(p_Stage,MATCH(LARGE(p_Key,44),p_Key,0)),"") | J48: =IFERROR(INDEX(p_Value,MATCH(LARGE(p_Key,44),p_Key,0)),"") | K48: =IFERROR(IF(H48="Open",INDEX(p_Prob,MATCH(LARGE(p_Key,44),p_Key,0)),""),"") | L48: =IFERROR(INDEX(p_Risk,MATCH(LARGE(p_Key,44),p_Key,0)),"") | M48: =IFERROR(INDEX(p_Month,MATCH(LARGE(p_Key,44),p_Key,0)),"") | N48: =IFERROR(INDEX(p_Flags,MATCH(LARGE(p_Key,44),p_Key,0)),"")
A49: =IF(D49="","",45) | B49: =IFERROR(INDEX(p_Rating,MATCH(LARGE(p_Key,45),p_Key,0)),"") | C49: =IFERROR(INDEX(p_Score,MATCH(LARGE(p_Key,45),p_Key,0)),"") | D49: =IFERROR(INDEX(p_Job,MATCH(LARGE(p_Key,45),p_Key,0)),"") | E49: =IFERROR(INDEX(p_Client,MATCH(LARGE(p_Key,45),p_Key,0)),"") | F49: =IFERROR(INDEX(p_Deal,MATCH(LARGE(p_Key,45),p_Key,0)),"") | G49: =IFERROR(INDEX(p_CC,MATCH(LARGE(p_Key,45),p_Key,0)),"") | H49: =IFERROR(INDEX(p_Status,MATCH(LARGE(p_Key,45),p_Key,0)),"") | I49: =IFERROR(INDEX(p_Stage,MATCH(LARGE(p_Key,45),p_Key,0)),"") | J49: =IFERROR(INDEX(p_Value,MATCH(LARGE(p_Key,45),p_Key,0)),"") | K49: =IFERROR(IF(H49="Open",INDEX(p_Prob,MATCH(LARGE(p_Key,45),p_Key,0)),""),"") | L49: =IFERROR(INDEX(p_Risk,MATCH(LARGE(p_Key,45),p_Key,0)),"") | M49: =IFERROR(INDEX(p_Month,MATCH(LARGE(p_Key,45),p_Key,0)),"") | N49: =IFERROR(INDEX(p_Flags,MATCH(LARGE(p_Key,45),p_Key,0)),"")
A50: =IF(D50="","",46) | B50: =IFERROR(INDEX(p_Rating,MATCH(LARGE(p_Key,46),p_Key,0)),"") | C50: =IFERROR(INDEX(p_Score,MATCH(LARGE(p_Key,46),p_Key,0)),"") | D50: =IFERROR(INDEX(p_Job,MATCH(LARGE(p_Key,46),p_Key,0)),"") | E50: =IFERROR(INDEX(p_Client,MATCH(LARGE(p_Key,46),p_Key,0)),"") | F50: =IFERROR(INDEX(p_Deal,MATCH(LARGE(p_Key,46),p_Key,0)),"") | G50: =IFERROR(INDEX(p_CC,MATCH(LARGE(p_Key,46),p_Key,0)),"") | H50: =IFERROR(INDEX(p_Status,MATCH(LARGE(p_Key,46),p_Key,0)),"") | I50: =IFERROR(INDEX(p_Stage,MATCH(LARGE(p_Key,46),p_Key,0)),"") | J50: =IFERROR(INDEX(p_Value,MATCH(LARGE(p_Key,46),p_Key,0)),"") | K50: =IFERROR(IF(H50="Open",INDEX(p_Prob,MATCH(LARGE(p_Key,46),p_Key,0)),""),"") | L50: =IFERROR(INDEX(p_Risk,MATCH(LARGE(p_Key,46),p_Key,0)),"") | M50: =IFERROR(INDEX(p_Month,MATCH(LARGE(p_Key,46),p_Key,0)),"") | N50: =IFERROR(INDEX(p_Flags,MATCH(LARGE(p_Key,46),p_Key,0)),"")
A51: =IF(D51="","",47) | B51: =IFERROR(INDEX(p_Rating,MATCH(LARGE(p_Key,47),p_Key,0)),"") | C51: =IFERROR(INDEX(p_Score,MATCH(LARGE(p_Key,47),p_Key,0)),"") | D51: =IFERROR(INDEX(p_Job,MATCH(LARGE(p_Key,47),p_Key,0)),"") | E51: =IFERROR(INDEX(p_Client,MATCH(LARGE(p_Key,47),p_Key,0)),"") | F51: =IFERROR(INDEX(p_Deal,MATCH(LARGE(p_Key,47),p_Key,0)),"") | G51: =IFERROR(INDEX(p_CC,MATCH(LARGE(p_Key,47),p_Key,0)),"") | H51: =IFERROR(INDEX(p_Status,MATCH(LARGE(p_Key,47),p_Key,0)),"") | I51: =IFERROR(INDEX(p_Stage,MATCH(LARGE(p_Key,47),p_Key,0)),"") | J51: =IFERROR(INDEX(p_Value,MATCH(LARGE(p_Key,47),p_Key,0)),"") | K51: =IFERROR(IF(H51="Open",INDEX(p_Prob,MATCH(LARGE(p_Key,47),p_Key,0)),""),"") | L51: =IFERROR(INDEX(p_Risk,MATCH(LARGE(p_Key,47),p_Key,0)),"") | M51: =IFERROR(INDEX(p_Month,MATCH(LARGE(p_Key,47),p_Key,0)),"") | N51: =IFERROR(INDEX(p_Flags,MATCH(LARGE(p_Key,47),p_Key,0)),"")
A52: =IF(D52="","",48) | B52: =IFERROR(INDEX(p_Rating,MATCH(LARGE(p_Key,48),p_Key,0)),"") | C52: =IFERROR(INDEX(p_Score,MATCH(LARGE(p_Key,48),p_Key,0)),"") | D52: =IFERROR(INDEX(p_Job,MATCH(LARGE(p_Key,48),p_Key,0)),"") | E52: =IFERROR(INDEX(p_Client,MATCH(LARGE(p_Key,48),p_Key,0)),"") | F52: =IFERROR(INDEX(p_Deal,MATCH(LARGE(p_Key,48),p_Key,0)),"") | G52: =IFERROR(INDEX(p_CC,MATCH(LARGE(p_Key,48),p_Key,0)),"") | H52: =IFERROR(INDEX(p_Status,MATCH(LARGE(p_Key,48),p_Key,0)),"") | I52: =IFERROR(INDEX(p_Stage,MATCH(LARGE(p_Key,48),p_Key,0)),"") | J52: =IFERROR(INDEX(p_Value,MATCH(LARGE(p_Key,48),p_Key,0)),"") | K52: =IFERROR(IF(H52="Open",INDEX(p_Prob,MATCH(LARGE(p_Key,48),p_Key,0)),""),"") | L52: =IFERROR(INDEX(p_Risk,MATCH(LARGE(p_Key,48),p_Key,0)),"") | M52: =IFERROR(INDEX(p_Month,MATCH(LARGE(p_Key,48),p_Key,0)),"") | N52: =IFERROR(INDEX(p_Flags,MATCH(LARGE(p_Key,48),p_Key,0)),"")
A53: =IF(D53="","",49) | B53: =IFERROR(INDEX(p_Rating,MATCH(LARGE(p_Key,49),p_Key,0)),"") | C53: =IFERROR(INDEX(p_Score,MATCH(LARGE(p_Key,49),p_Key,0)),"") | D53: =IFERROR(INDEX(p_Job,MATCH(LARGE(p_Key,49),p_Key,0)),"") | E53: =IFERROR(INDEX(p_Client,MATCH(LARGE(p_Key,49),p_Key,0)),"") | F53: =IFERROR(INDEX(p_Deal,MATCH(LARGE(p_Key,49),p_Key,0)),"") | G53: =IFERROR(INDEX(p_CC,MATCH(LARGE(p_Key,49),p_Key,0)),"") | H53: =IFERROR(INDEX(p_Status,MATCH(LARGE(p_Key,49),p_Key,0)),"") | I53: =IFERROR(INDEX(p_Stage,MATCH(LARGE(p_Key,49),p_Key,0)),"") | J53: =IFERROR(INDEX(p_Value,MATCH(LARGE(p_Key,49),p_Key,0)),"") | K53: =IFERROR(IF(H53="Open",INDEX(p_Prob,MATCH(LARGE(p_Key,49),p_Key,0)),""),"") | L53: =IFERROR(INDEX(p_Risk,MATCH(LARGE(p_Key,49),p_Key,0)),"") | M53: =IFERROR(INDEX(p_Month,MATCH(LARGE(p_Key,49),p_Key,0)),"") | N53: =IFERROR(INDEX(p_Flags,MATCH(LARGE(p_Key,49),p_Key,0)),"")
A54: =IF(D54="","",50) | B54: =IFERROR(INDEX(p_Rating,MATCH(LARGE(p_Key,50),p_Key,0)),"") | C54: =IFERROR(INDEX(p_Score,MATCH(LARGE(p_Key,50),p_Key,0)),"") | D54: =IFERROR(INDEX(p_Job,MATCH(LARGE(p_Key,50),p_Key,0)),"") | E54: =IFERROR(INDEX(p_Client,MATCH(LARGE(p_Key,50),p_Key,0)),"") | F54: =IFERROR(INDEX(p_Deal,MATCH(LARGE(p_Key,50),p_Key,0)),"") | G54: =IFERROR(INDEX(p_CC,MATCH(LARGE(p_Key,50),p_Key,0)),"") | H54: =IFERROR(INDEX(p_Status,MATCH(LARGE(p_Key,50),p_Key,0)),"") | I54: =IFERROR(INDEX(p_Stage,MATCH(LARGE(p_Key,50),p_Key,0)),"") | J54: =IFERROR(INDEX(p_Value,MATCH(LARGE(p_Key,50),p_Key,0)),"") | K54: =IFERROR(IF(H54="Open",INDEX(p_Prob,MATCH(LARGE(p_Key,50),p_Key,0)),""),"") | L54: =IFERROR(INDEX(p_Risk,MATCH(LARGE(p_Key,50),p_Key,0)),"") | M54: =IFERROR(INDEX(p_Month,MATCH(LARGE(p_Key,50),p_Key,0)),"") | N54: =IFERROR(INDEX(p_Flags,MATCH(LARGE(p_Key,50),p_Key,0)),"")
A55: =IF(D55="","",51) | B55: =IFERROR(INDEX(p_Rating,MATCH(LARGE(p_Key,51),p_Key,0)),"") | C55: =IFERROR(INDEX(p_Score,MATCH(LARGE(p_Key,51),p_Key,0)),"") | D55: =IFERROR(INDEX(p_Job,MATCH(LARGE(p_Key,51),p_Key,0)),"") | E55: =IFERROR(INDEX(p_Client,MATCH(LARGE(p_Key,51),p_Key,0)),"") | F55: =IFERROR(INDEX(p_Deal,MATCH(LARGE(p_Key,51),p_Key,0)),"") | G55: =IFERROR(INDEX(p_CC,MATCH(LARGE(p_Key,51),p_Key,0)),"") | H55: =IFERROR(INDEX(p_Status,MATCH(LARGE(p_Key,51),p_Key,0)),"") | I55: =IFERROR(INDEX(p_Stage,MATCH(LARGE(p_Key,51),p_Key,0)),"") | J55: =IFERROR(INDEX(p_Value,MATCH(LARGE(p_Key,51),p_Key,0)),"") | K55: =IFERROR(IF(H55="Open",INDEX(p_Prob,MATCH(LARGE(p_Key,51),p_Key,0)),""),"") | L55: =IFERROR(INDEX(p_Risk,MATCH(LARGE(p_Key,51),p_Key,0)),"") | M55: =IFERROR(INDEX(p_Month,MATCH(LARGE(p_Key,51),p_Key,0)),"") | N55: =IFERROR(INDEX(p_Flags,MATCH(LARGE(p_Key,51),p_Key,0)),"")
A56: =IF(D56="","",52) | B56: =IFERROR(INDEX(p_Rating,MATCH(LARGE(p_Key,52),p_Key,0)),"") | C56: =IFERROR(INDEX(p_Score,MATCH(LARGE(p_Key,52),p_Key,0)),"") | D56: =IFERROR(INDEX(p_Job,MATCH(LARGE(p_Key,52),p_Key,0)),"") | E56: =IFERROR(INDEX(p_Client,MATCH(LARGE(p_Key,52),p_Key,0)),"") | F56: =IFERROR(INDEX(p_Deal,MATCH(LARGE(p_Key,52),p_Key,0)),"") | G56: =IFERROR(INDEX(p_CC,MATCH(LARGE(p_Key,52),p_Key,0)),"") | H56: =IFERROR(INDEX(p_Status,MATCH(LARGE(p_Key,52),p_Key,0)),"") | I56: =IFERROR(INDEX(p_Stage,MATCH(LARGE(p_Key,52),p_Key,0)),"") | J56: =IFERROR(INDEX(p_Value,MATCH(LARGE(p_Key,52),p_Key,0)),"") | K56: =IFERROR(IF(H56="Open",INDEX(p_Prob,MATCH(LARGE(p_Key,52),p_Key,0)),""),"") | L56: =IFERROR(INDEX(p_Risk,MATCH(LARGE(p_Key,52),p_Key,0)),"") | M56: =IFERROR(INDEX(p_Month,MATCH(LARGE(p_Key,52),p_Key,0)),"") | N56: =IFERROR(INDEX(p_Flags,MATCH(LARGE(p_Key,52),p_Key,0)),"")
A57: =IF(D57="","",53) | B57: =IFERROR(INDEX(p_Rating,MATCH(LARGE(p_Key,53),p_Key,0)),"") | C57: =IFERROR(INDEX(p_Score,MATCH(LARGE(p_Key,53),p_Key,0)),"") | D57: =IFERROR(INDEX(p_Job,MATCH(LARGE(p_Key,53),p_Key,0)),"") | E57: =IFERROR(INDEX(p_Client,MATCH(LARGE(p_Key,53),p_Key,0)),"") | F57: =IFERROR(INDEX(p_Deal,MATCH(LARGE(p_Key,53),p_Key,0)),"") | G57: =IFERROR(INDEX(p_CC,MATCH(LARGE(p_Key,53),p_Key,0)),"") | H57: =IFERROR(INDEX(p_Status,MATCH(LARGE(p_Key,53),p_Key,0)),"") | I57: =IFERROR(INDEX(p_Stage,MATCH(LARGE(p_Key,53),p_Key,0)),"") | J57: =IFERROR(INDEX(p_Value,MATCH(LARGE(p_Key,53),p_Key,0)),"") | K57: =IFERROR(IF(H57="Open",INDEX(p_Prob,MATCH(LARGE(p_Key,53),p_Key,0)),""),"") | L57: =IFERROR(INDEX(p_Risk,MATCH(LARGE(p_Key,53),p_Key,0)),"") | M57: =IFERROR(INDEX(p_Month,MATCH(LARGE(p_Key,53),p_Key,0)),"") | N57: =IFERROR(INDEX(p_Flags,MATCH(LARGE(p_Key,53),p_Key,0)),"")
A58: =IF(D58="","",54) | B58: =IFERROR(INDEX(p_Rating,MATCH(LARGE(p_Key,54),p_Key,0)),"") | C58: =IFERROR(INDEX(p_Score,MATCH(LARGE(p_Key,54),p_Key,0)),"") | D58: =IFERROR(INDEX(p_Job,MATCH(LARGE(p_Key,54),p_Key,0)),"") | E58: =IFERROR(INDEX(p_Client,MATCH(LARGE(p_Key,54),p_Key,0)),"") | F58: =IFERROR(INDEX(p_Deal,MATCH(LARGE(p_Key,54),p_Key,0)),"") | G58: =IFERROR(INDEX(p_CC,MATCH(LARGE(p_Key,54),p_Key,0)),"") | H58: =IFERROR(INDEX(p_Status,MATCH(LARGE(p_Key,54),p_Key,0)),"") | I58: =IFERROR(INDEX(p_Stage,MATCH(LARGE(p_Key,54),p_Key,0)),"") | J58: =IFERROR(INDEX(p_Value,MATCH(LARGE(p_Key,54),p_Key,0)),"") | K58: =IFERROR(IF(H58="Open",INDEX(p_Prob,MATCH(LARGE(p_Key,54),p_Key,0)),""),"") | L58: =IFERROR(INDEX(p_Risk,MATCH(LARGE(p_Key,54),p_Key,0)),"") | M58: =IFERROR(INDEX(p_Month,MATCH(LARGE(p_Key,54),p_Key,0)),"") | N58: =IFERROR(INDEX(p_Flags,MATCH(LARGE(p_Key,54),p_Key,0)),"")
A59: =IF(D59="","",55) | B59: =IFERROR(INDEX(p_Rating,MATCH(LARGE(p_Key,55),p_Key,0)),"") | C59: =IFERROR(INDEX(p_Score,MATCH(LARGE(p_Key,55),p_Key,0)),"") | D59: =IFERROR(INDEX(p_Job,MATCH(LARGE(p_Key,55),p_Key,0)),"") | E59: =IFERROR(INDEX(p_Client,MATCH(LARGE(p_Key,55),p_Key,0)),"") | F59: =IFERROR(INDEX(p_Deal,MATCH(LARGE(p_Key,55),p_Key,0)),"") | G59: =IFERROR(INDEX(p_CC,MATCH(LARGE(p_Key,55),p_Key,0)),"") | H59: =IFERROR(INDEX(p_Status,MATCH(LARGE(p_Key,55),p_Key,0)),"") | I59: =IFERROR(INDEX(p_Stage,MATCH(LARGE(p_Key,55),p_Key,0)),"") | J59: =IFERROR(INDEX(p_Value,MATCH(LARGE(p_Key,55),p_Key,0)),"") | K59: =IFERROR(IF(H59="Open",INDEX(p_Prob,MATCH(LARGE(p_Key,55),p_Key,0)),""),"") | L59: =IFERROR(INDEX(p_Risk,MATCH(LARGE(p_Key,55),p_Key,0)),"") | M59: =IFERROR(INDEX(p_Month,MATCH(LARGE(p_Key,55),p_Key,0)),"") | N59: =IFERROR(INDEX(p_Flags,MATCH(LARGE(p_Key,55),p_Key,0)),"")
A60: =IF(D60="","",56) | B60: =IFERROR(INDEX(p_Rating,MATCH(LARGE(p_Key,56),p_Key,0)),"") | C60: =IFERROR(INDEX(p_Score,MATCH(LARGE(p_Key,56),p_Key,0)),"") | D60: =IFERROR(INDEX(p_Job,MATCH(LARGE(p_Key,56),p_Key,0)),"") | E60: =IFERROR(INDEX(p_Client,MATCH(LARGE(p_Key,56),p_Key,0)),"") | F60: =IFERROR(INDEX(p_Deal,MATCH(LARGE(p_Key,56),p_Key,0)),"") | G60: =IFERROR(INDEX(p_CC,MATCH(LARGE(p_Key,56),p_Key,0)),"") | H60: =IFERROR(INDEX(p_Status,MATCH(LARGE(p_Key,56),p_Key,0)),"") | I60: =IFERROR(INDEX(p_Stage,MATCH(LARGE(p_Key,56),p_Key,0)),"") | J60: =IFERROR(INDEX(p_Value,MATCH(LARGE(p_Key,56),p_Key,0)),"") | K60: =IFERROR(IF(H60="Open",INDEX(p_Prob,MATCH(LARGE(p_Key,56),p_Key,0)),""),"") | L60: =IFERROR(INDEX(p_Risk,MATCH(LARGE(p_Key,56),p_Key,0)),"") | M60: =IFERROR(INDEX(p_Month,MATCH(LARGE(p_Key,56),p_Key,0)),"") | N60: =IFERROR(INDEX(p_Flags,MATCH(LARGE(p_Key,56),p_Key,0)),"")
A61: =IF(D61="","",57) | B61: =IFERROR(INDEX(p_Rating,MATCH(LARGE(p_Key,57),p_Key,0)),"") | C61: =IFERROR(INDEX(p_Score,MATCH(LARGE(p_Key,57),p_Key,0)),"") | D61: =IFERROR(INDEX(p_Job,MATCH(LARGE(p_Key,57),p_Key,0)),"") | E61: =IFERROR(INDEX(p_Client,MATCH(LARGE(p_Key,57),p_Key,0)),"") | F61: =IFERROR(INDEX(p_Deal,MATCH(LARGE(p_Key,57),p_Key,0)),"") | G61: =IFERROR(INDEX(p_CC,MATCH(LARGE(p_Key,57),p_Key,0)),"") | H61: =IFERROR(INDEX(p_Status,MATCH(LARGE(p_Key,57),p_Key,0)),"") | I61: =IFERROR(INDEX(p_Stage,MATCH(LARGE(p_Key,57),p_Key,0)),"") | J61: =IFERROR(INDEX(p_Value,MATCH(LARGE(p_Key,57),p_Key,0)),"") | K61: =IFERROR(IF(H61="Open",INDEX(p_Prob,MATCH(LARGE(p_Key,57),p_Key,0)),""),"") | L61: =IFERROR(INDEX(p_Risk,MATCH(LARGE(p_Key,57),p_Key,0)),"") | M61: =IFERROR(INDEX(p_Month,MATCH(LARGE(p_Key,57),p_Key,0)),"") | N61: =IFERROR(INDEX(p_Flags,MATCH(LARGE(p_Key,57),p_Key,0)),"")
A62: =IF(D62="","",58) | B62: =IFERROR(INDEX(p_Rating,MATCH(LARGE(p_Key,58),p_Key,0)),"") | C62: =IFERROR(INDEX(p_Score,MATCH(LARGE(p_Key,58),p_Key,0)),"") | D62: =IFERROR(INDEX(p_Job,MATCH(LARGE(p_Key,58),p_Key,0)),"") | E62: =IFERROR(INDEX(p_Client,MATCH(LARGE(p_Key,58),p_Key,0)),"") | F62: =IFERROR(INDEX(p_Deal,MATCH(LARGE(p_Key,58),p_Key,0)),"") | G62: =IFERROR(INDEX(p_CC,MATCH(LARGE(p_Key,58),p_Key,0)),"") | H62: =IFERROR(INDEX(p_Status,MATCH(LARGE(p_Key,58),p_Key,0)),"") | I62: =IFERROR(INDEX(p_Stage,MATCH(LARGE(p_Key,58),p_Key,0)),"") | J62: =IFERROR(INDEX(p_Value,MATCH(LARGE(p_Key,58),p_Key,0)),"") | K62: =IFERROR(IF(H62="Open",INDEX(p_Prob,MATCH(LARGE(p_Key,58),p_Key,0)),""),"") | L62: =IFERROR(INDEX(p_Risk,MATCH(LARGE(p_Key,58),p_Key,0)),"") | M62: =IFERROR(INDEX(p_Month,MATCH(LARGE(p_Key,58),p_Key,0)),"") | N62: =IFERROR(INDEX(p_Flags,MATCH(LARGE(p_Key,58),p_Key,0)),"")
A63: =IF(D63="","",59) | B63: =IFERROR(INDEX(p_Rating,MATCH(LARGE(p_Key,59),p_Key,0)),"") | C63: =IFERROR(INDEX(p_Score,MATCH(LARGE(p_Key,59),p_Key,0)),"") | D63: =IFERROR(INDEX(p_Job,MATCH(LARGE(p_Key,59),p_Key,0)),"") | E63: =IFERROR(INDEX(p_Client,MATCH(LARGE(p_Key,59),p_Key,0)),"") | F63: =IFERROR(INDEX(p_Deal,MATCH(LARGE(p_Key,59),p_Key,0)),"") | G63: =IFERROR(INDEX(p_CC,MATCH(LARGE(p_Key,59),p_Key,0)),"") | H63: =IFERROR(INDEX(p_Status,MATCH(LARGE(p_Key,59),p_Key,0)),"") | I63: =IFERROR(INDEX(p_Stage,MATCH(LARGE(p_Key,59),p_Key,0)),"") | J63: =IFERROR(INDEX(p_Value,MATCH(LARGE(p_Key,59),p_Key,0)),"") | K63: =IFERROR(IF(H63="Open",INDEX(p_Prob,MATCH(LARGE(p_Key,59),p_Key,0)),""),"") | L63: =IFERROR(INDEX(p_Risk,MATCH(LARGE(p_Key,59),p_Key,0)),"") | M63: =IFERROR(INDEX(p_Month,MATCH(LARGE(p_Key,59),p_Key,0)),"") | N63: =IFERROR(INDEX(p_Flags,MATCH(LARGE(p_Key,59),p_Key,0)),"")
A64: =IF(D64="","",60) | B64: =IFERROR(INDEX(p_Rating,MATCH(LARGE(p_Key,60),p_Key,0)),"") | C64: =IFERROR(INDEX(p_Score,MATCH(LARGE(p_Key,60),p_Key,0)),"") | D64: =IFERROR(INDEX(p_Job,MATCH(LARGE(p_Key,60),p_Key,0)),"") | E64: =IFERROR(INDEX(p_Client,MATCH(LARGE(p_Key,60),p_Key,0)),"") | F64: =IFERROR(INDEX(p_Deal,MATCH(LARGE(p_Key,60),p_Key,0)),"") | G64: =IFERROR(INDEX(p_CC,MATCH(LARGE(p_Key,60),p_Key,0)),"") | H64: =IFERROR(INDEX(p_Status,MATCH(LARGE(p_Key,60),p_Key,0)),"") | I64: =IFERROR(INDEX(p_Stage,MATCH(LARGE(p_Key,60),p_Key,0)),"") | J64: =IFERROR(INDEX(p_Value,MATCH(LARGE(p_Key,60),p_Key,0)),"") | K64: =IFERROR(IF(H64="Open",INDEX(p_Prob,MATCH(LARGE(p_Key,60),p_Key,0)),""),"") | L64: =IFERROR(INDEX(p_Risk,MATCH(LARGE(p_Key,60),p_Key,0)),"") | M64: =IFERROR(INDEX(p_Month,MATCH(LARGE(p_Key,60),p_Key,0)),"") | N64: =IFERROR(INDEX(p_Flags,MATCH(LARGE(p_Key,60),p_Key,0)),"")
A65: =IF(D65="","",61) | B65: =IFERROR(INDEX(p_Rating,MATCH(LARGE(p_Key,61),p_Key,0)),"") | C65: =IFERROR(INDEX(p_Score,MATCH(LARGE(p_Key,61),p_Key,0)),"") | D65: =IFERROR(INDEX(p_Job,MATCH(LARGE(p_Key,61),p_Key,0)),"") | E65: =IFERROR(INDEX(p_Client,MATCH(LARGE(p_Key,61),p_Key,0)),"") | F65: =IFERROR(INDEX(p_Deal,MATCH(LARGE(p_Key,61),p_Key,0)),"") | G65: =IFERROR(INDEX(p_CC,MATCH(LARGE(p_Key,61),p_Key,0)),"") | H65: =IFERROR(INDEX(p_Status,MATCH(LARGE(p_Key,61),p_Key,0)),"") | I65: =IFERROR(INDEX(p_Stage,MATCH(LARGE(p_Key,61),p_Key,0)),"") | J65: =IFERROR(INDEX(p_Value,MATCH(LARGE(p_Key,61),p_Key,0)),"") | K65: =IFERROR(IF(H65="Open",INDEX(p_Prob,MATCH(LARGE(p_Key,61),p_Key,0)),""),"") | L65: =IFERROR(INDEX(p_Risk,MATCH(LARGE(p_Key,61),p_Key,0)),"") | M65: =IFERROR(INDEX(p_Month,MATCH(LARGE(p_Key,61),p_Key,0)),"") | N65: =IFERROR(INDEX(p_Flags,MATCH(LARGE(p_Key,61),p_Key,0)),"")
A66: =IF(D66="","",62) | B66: =IFERROR(INDEX(p_Rating,MATCH(LARGE(p_Key,62),p_Key,0)),"") | C66: =IFERROR(INDEX(p_Score,MATCH(LARGE(p_Key,62),p_Key,0)),"") | D66: =IFERROR(INDEX(p_Job,MATCH(LARGE(p_Key,62),p_Key,0)),"") | E66: =IFERROR(INDEX(p_Client,MATCH(LARGE(p_Key,62),p_Key,0)),"") | F66: =IFERROR(INDEX(p_Deal,MATCH(LARGE(p_Key,62),p_Key,0)),"") | G66: =IFERROR(INDEX(p_CC,MATCH(LARGE(p_Key,62),p_Key,0)),"") | H66: =IFERROR(INDEX(p_Status,MATCH(LARGE(p_Key,62),p_Key,0)),"") | I66: =IFERROR(INDEX(p_Stage,MATCH(LARGE(p_Key,62),p_Key,0)),"") | J66: =IFERROR(INDEX(p_Value,MATCH(LARGE(p_Key,62),p_Key,0)),"") | K66: =IFERROR(IF(H66="Open",INDEX(p_Prob,MATCH(LARGE(p_Key,62),p_Key,0)),""),"") | L66: =IFERROR(INDEX(p_Risk,MATCH(LARGE(p_Key,62),p_Key,0)),"") | M66: =IFERROR(INDEX(p_Month,MATCH(LARGE(p_Key,62),p_Key,0)),"") | N66: =IFERROR(INDEX(p_Flags,MATCH(LARGE(p_Key,62),p_Key,0)),"")
A67: =IF(D67="","",63) | B67: =IFERROR(INDEX(p_Rating,MATCH(LARGE(p_Key,63),p_Key,0)),"") | C67: =IFERROR(INDEX(p_Score,MATCH(LARGE(p_Key,63),p_Key,0)),"") | D67: =IFERROR(INDEX(p_Job,MATCH(LARGE(p_Key,63),p_Key,0)),"") | E67: =IFERROR(INDEX(p_Client,MATCH(LARGE(p_Key,63),p_Key,0)),"") | F67: =IFERROR(INDEX(p_Deal,MATCH(LARGE(p_Key,63),p_Key,0)),"") | G67: =IFERROR(INDEX(p_CC,MATCH(LARGE(p_Key,63),p_Key,0)),"") | H67: =IFERROR(INDEX(p_Status,MATCH(LARGE(p_Key,63),p_Key,0)),"") | I67: =IFERROR(INDEX(p_Stage,MATCH(LARGE(p_Key,63),p_Key,0)),"") | J67: =IFERROR(INDEX(p_Value,MATCH(LARGE(p_Key,63),p_Key,0)),"") | K67: =IFERROR(IF(H67="Open",INDEX(p_Prob,MATCH(LARGE(p_Key,63),p_Key,0)),""),"") | L67: =IFERROR(INDEX(p_Risk,MATCH(LARGE(p_Key,63),p_Key,0)),"") | M67: =IFERROR(INDEX(p_Month,MATCH(LARGE(p_Key,63),p_Key,0)),"") | N67: =IFERROR(INDEX(p_Flags,MATCH(LARGE(p_Key,63),p_Key,0)),"")
A68: =IF(D68="","",64) | B68: =IFERROR(INDEX(p_Rating,MATCH(LARGE(p_Key,64),p_Key,0)),"") | C68: =IFERROR(INDEX(p_Score,MATCH(LARGE(p_Key,64),p_Key,0)),"") | D68: =IFERROR(INDEX(p_Job,MATCH(LARGE(p_Key,64),p_Key,0)),"") | E68: =IFERROR(INDEX(p_Client,MATCH(LARGE(p_Key,64),p_Key,0)),"") | F68: =IFERROR(INDEX(p_Deal,MATCH(LARGE(p_Key,64),p_Key,0)),"") | G68: =IFERROR(INDEX(p_CC,MATCH(LARGE(p_Key,64),p_Key,0)),"") | H68: =IFERROR(INDEX(p_Status,MATCH(LARGE(p_Key,64),p_Key,0)),"") | I68: =IFERROR(INDEX(p_Stage,MATCH(LARGE(p_Key,64),p_Key,0)),"") | J68: =IFERROR(INDEX(p_Value,MATCH(LARGE(p_Key,64),p_Key,0)),"") | K68: =IFERROR(IF(H68="Open",INDEX(p_Prob,MATCH(LARGE(p_Key,64),p_Key,0)),""),"") | L68: =IFERROR(INDEX(p_Risk,MATCH(LARGE(p_Key,64),p_Key,0)),"") | M68: =IFERROR(INDEX(p_Month,MATCH(LARGE(p_Key,64),p_Key,0)),"") | N68: =IFERROR(INDEX(p_Flags,MATCH(LARGE(p_Key,64),p_Key,0)),"")
A69: =IF(D69="","",65) | B69: =IFERROR(INDEX(p_Rating,MATCH(LARGE(p_Key,65),p_Key,0)),"") | C69: =IFERROR(INDEX(p_Score,MATCH(LARGE(p_Key,65),p_Key,0)),"") | D69: =IFERROR(INDEX(p_Job,MATCH(LARGE(p_Key,65),p_Key,0)),"") | E69: =IFERROR(INDEX(p_Client,MATCH(LARGE(p_Key,65),p_Key,0)),"") | F69: =IFERROR(INDEX(p_Deal,MATCH(LARGE(p_Key,65),p_Key,0)),"") | G69: =IFERROR(INDEX(p_CC,MATCH(LARGE(p_Key,65),p_Key,0)),"") | H69: =IFERROR(INDEX(p_Status,MATCH(LARGE(p_Key,65),p_Key,0)),"") | I69: =IFERROR(INDEX(p_Stage,MATCH(LARGE(p_Key,65),p_Key,0)),"") | J69: =IFERROR(INDEX(p_Value,MATCH(LARGE(p_Key,65),p_Key,0)),"") | K69: =IFERROR(IF(H69="Open",INDEX(p_Prob,MATCH(LARGE(p_Key,65),p_Key,0)),""),"") | L69: =IFERROR(INDEX(p_Risk,MATCH(LARGE(p_Key,65),p_Key,0)),"") | M69: =IFERROR(INDEX(p_Month,MATCH(LARGE(p_Key,65),p_Key,0)),"") | N69: =IFERROR(INDEX(p_Flags,MATCH(LARGE(p_Key,65),p_Key,0)),"")
A70: =IF(D70="","",66) | B70: =IFERROR(INDEX(p_Rating,MATCH(LARGE(p_Key,66),p_Key,0)),"") | C70: =IFERROR(INDEX(p_Score,MATCH(LARGE(p_Key,66),p_Key,0)),"") | D70: =IFERROR(INDEX(p_Job,MATCH(LARGE(p_Key,66),p_Key,0)),"") | E70: =IFERROR(INDEX(p_Client,MATCH(LARGE(p_Key,66),p_Key,0)),"") | F70: =IFERROR(INDEX(p_Deal,MATCH(LARGE(p_Key,66),p_Key,0)),"") | G70: =IFERROR(INDEX(p_CC,MATCH(LARGE(p_Key,66),p_Key,0)),"") | H70: =IFERROR(INDEX(p_Status,MATCH(LARGE(p_Key,66),p_Key,0)),"") | I70: =IFERROR(INDEX(p_Stage,MATCH(LARGE(p_Key,66),p_Key,0)),"") | J70: =IFERROR(INDEX(p_Value,MATCH(LARGE(p_Key,66),p_Key,0)),"") | K70: =IFERROR(IF(H70="Open",INDEX(p_Prob,MATCH(LARGE(p_Key,66),p_Key,0)),""),"") | L70: =IFERROR(INDEX(p_Risk,MATCH(LARGE(p_Key,66),p_Key,0)),"") | M70: =IFERROR(INDEX(p_Month,MATCH(LARGE(p_Key,66),p_Key,0)),"") | N70: =IFERROR(INDEX(p_Flags,MATCH(LARGE(p_Key,66),p_Key,0)),"")
A71: =IF(D71="","",67) | B71: =IFERROR(INDEX(p_Rating,MATCH(LARGE(p_Key,67),p_Key,0)),"") | C71: =IFERROR(INDEX(p_Score,MATCH(LARGE(p_Key,67),p_Key,0)),"") | D71: =IFERROR(INDEX(p_Job,MATCH(LARGE(p_Key,67),p_Key,0)),"") | E71: =IFERROR(INDEX(p_Client,MATCH(LARGE(p_Key,67),p_Key,0)),"") | F71: =IFERROR(INDEX(p_Deal,MATCH(LARGE(p_Key,67),p_Key,0)),"") | G71: =IFERROR(INDEX(p_CC,MATCH(LARGE(p_Key,67),p_Key,0)),"") | H71: =IFERROR(INDEX(p_Status,MATCH(LARGE(p_Key,67),p_Key,0)),"") | I71: =IFERROR(INDEX(p_Stage,MATCH(LARGE(p_Key,67),p_Key,0)),"") | J71: =IFERROR(INDEX(p_Value,MATCH(LARGE(p_Key,67),p_Key,0)),"") | K71: =IFERROR(IF(H71="Open",INDEX(p_Prob,MATCH(LARGE(p_Key,67),p_Key,0)),""),"") | L71: =IFERROR(INDEX(p_Risk,MATCH(LARGE(p_Key,67),p_Key,0)),"") | M71: =IFERROR(INDEX(p_Month,MATCH(LARGE(p_Key,67),p_Key,0)),"") | N71: =IFERROR(INDEX(p_Flags,MATCH(LARGE(p_Key,67),p_Key,0)),"")
A72: =IF(D72="","",68) | B72: =IFERROR(INDEX(p_Rating,MATCH(LARGE(p_Key,68),p_Key,0)),"") | C72: =IFERROR(INDEX(p_Score,MATCH(LARGE(p_Key,68),p_Key,0)),"") | D72: =IFERROR(INDEX(p_Job,MATCH(LARGE(p_Key,68),p_Key,0)),"") | E72: =IFERROR(INDEX(p_Client,MATCH(LARGE(p_Key,68),p_Key,0)),"") | F72: =IFERROR(INDEX(p_Deal,MATCH(LARGE(p_Key,68),p_Key,0)),"") | G72: =IFERROR(INDEX(p_CC,MATCH(LARGE(p_Key,68),p_Key,0)),"") | H72: =IFERROR(INDEX(p_Status,MATCH(LARGE(p_Key,68),p_Key,0)),"") | I72: =IFERROR(INDEX(p_Stage,MATCH(LARGE(p_Key,68),p_Key,0)),"") | J72: =IFERROR(INDEX(p_Value,MATCH(LARGE(p_Key,68),p_Key,0)),"") | K72: =IFERROR(IF(H72="Open",INDEX(p_Prob,MATCH(LARGE(p_Key,68),p_Key,0)),""),"") | L72: =IFERROR(INDEX(p_Risk,MATCH(LARGE(p_Key,68),p_Key,0)),"") | M72: =IFERROR(INDEX(p_Month,MATCH(LARGE(p_Key,68),p_Key,0)),"") | N72: =IFERROR(INDEX(p_Flags,MATCH(LARGE(p_Key,68),p_Key,0)),"")
A73: =IF(D73="","",69) | B73: =IFERROR(INDEX(p_Rating,MATCH(LARGE(p_Key,69),p_Key,0)),"") | C73: =IFERROR(INDEX(p_Score,MATCH(LARGE(p_Key,69),p_Key,0)),"") | D73: =IFERROR(INDEX(p_Job,MATCH(LARGE(p_Key,69),p_Key,0)),"") | E73: =IFERROR(INDEX(p_Client,MATCH(LARGE(p_Key,69),p_Key,0)),"") | F73: =IFERROR(INDEX(p_Deal,MATCH(LARGE(p_Key,69),p_Key,0)),"") | G73: =IFERROR(INDEX(p_CC,MATCH(LARGE(p_Key,69),p_Key,0)),"") | H73: =IFERROR(INDEX(p_Status,MATCH(LARGE(p_Key,69),p_Key,0)),"") | I73: =IFERROR(INDEX(p_Stage,MATCH(LARGE(p_Key,69),p_Key,0)),"") | J73: =IFERROR(INDEX(p_Value,MATCH(LARGE(p_Key,69),p_Key,0)),"") | K73: =IFERROR(IF(H73="Open",INDEX(p_Prob,MATCH(LARGE(p_Key,69),p_Key,0)),""),"") | L73: =IFERROR(INDEX(p_Risk,MATCH(LARGE(p_Key,69),p_Key,0)),"") | M73: =IFERROR(INDEX(p_Month,MATCH(LARGE(p_Key,69),p_Key,0)),"") | N73: =IFERROR(INDEX(p_Flags,MATCH(LARGE(p_Key,69),p_Key,0)),"")
A74: =IF(D74="","",70) | B74: =IFERROR(INDEX(p_Rating,MATCH(LARGE(p_Key,70),p_Key,0)),"") | C74: =IFERROR(INDEX(p_Score,MATCH(LARGE(p_Key,70),p_Key,0)),"") | D74: =IFERROR(INDEX(p_Job,MATCH(LARGE(p_Key,70),p_Key,0)),"") | E74: =IFERROR(INDEX(p_Client,MATCH(LARGE(p_Key,70),p_Key,0)),"") | F74: =IFERROR(INDEX(p_Deal,MATCH(LARGE(p_Key,70),p_Key,0)),"") | G74: =IFERROR(INDEX(p_CC,MATCH(LARGE(p_Key,70),p_Key,0)),"") | H74: =IFERROR(INDEX(p_Status,MATCH(LARGE(p_Key,70),p_Key,0)),"") | I74: =IFERROR(INDEX(p_Stage,MATCH(LARGE(p_Key,70),p_Key,0)),"") | J74: =IFERROR(INDEX(p_Value,MATCH(LARGE(p_Key,70),p_Key,0)),"") | K74: =IFERROR(IF(H74="Open",INDEX(p_Prob,MATCH(LARGE(p_Key,70),p_Key,0)),""),"") | L74: =IFERROR(INDEX(p_Risk,MATCH(LARGE(p_Key,70),p_Key,0)),"") | M74: =IFERROR(INDEX(p_Month,MATCH(LARGE(p_Key,70),p_Key,0)),"") | N74: =IFERROR(INDEX(p_Flags,MATCH(LARGE(p_Key,70),p_Key,0)),"")
A75: =IF(D75="","",71) | B75: =IFERROR(INDEX(p_Rating,MATCH(LARGE(p_Key,71),p_Key,0)),"") | C75: =IFERROR(INDEX(p_Score,MATCH(LARGE(p_Key,71),p_Key,0)),"") | D75: =IFERROR(INDEX(p_Job,MATCH(LARGE(p_Key,71),p_Key,0)),"") | E75: =IFERROR(INDEX(p_Client,MATCH(LARGE(p_Key,71),p_Key,0)),"") | F75: =IFERROR(INDEX(p_Deal,MATCH(LARGE(p_Key,71),p_Key,0)),"") | G75: =IFERROR(INDEX(p_CC,MATCH(LARGE(p_Key,71),p_Key,0)),"") | H75: =IFERROR(INDEX(p_Status,MATCH(LARGE(p_Key,71),p_Key,0)),"") | I75: =IFERROR(INDEX(p_Stage,MATCH(LARGE(p_Key,71),p_Key,0)),"") | J75: =IFERROR(INDEX(p_Value,MATCH(LARGE(p_Key,71),p_Key,0)),"") | K75: =IFERROR(IF(H75="Open",INDEX(p_Prob,MATCH(LARGE(p_Key,71),p_Key,0)),""),"") | L75: =IFERROR(INDEX(p_Risk,MATCH(LARGE(p_Key,71),p_Key,0)),"") | M75: =IFERROR(INDEX(p_Month,MATCH(LARGE(p_Key,71),p_Key,0)),"") | N75: =IFERROR(INDEX(p_Flags,MATCH(LARGE(p_Key,71),p_Key,0)),"")
A76: =IF(D76="","",72) | B76: =IFERROR(INDEX(p_Rating,MATCH(LARGE(p_Key,72),p_Key,0)),"") | C76: =IFERROR(INDEX(p_Score,MATCH(LARGE(p_Key,72),p_Key,0)),"") | D76: =IFERROR(INDEX(p_Job,MATCH(LARGE(p_Key,72),p_Key,0)),"") | E76: =IFERROR(INDEX(p_Client,MATCH(LARGE(p_Key,72),p_Key,0)),"") | F76: =IFERROR(INDEX(p_Deal,MATCH(LARGE(p_Key,72),p_Key,0)),"") | G76: =IFERROR(INDEX(p_CC,MATCH(LARGE(p_Key,72),p_Key,0)),"") | H76: =IFERROR(INDEX(p_Status,MATCH(LARGE(p_Key,72),p_Key,0)),"") | I76: =IFERROR(INDEX(p_Stage,MATCH(LARGE(p_Key,72),p_Key,0)),"") | J76: =IFERROR(INDEX(p_Value,MATCH(LARGE(p_Key,72),p_Key,0)),"") | K76: =IFERROR(IF(H76="Open",INDEX(p_Prob,MATCH(LARGE(p_Key,72),p_Key,0)),""),"") | L76: =IFERROR(INDEX(p_Risk,MATCH(LARGE(p_Key,72),p_Key,0)),"") | M76: =IFERROR(INDEX(p_Month,MATCH(LARGE(p_Key,72),p_Key,0)),"") | N76: =IFERROR(INDEX(p_Flags,MATCH(LARGE(p_Key,72),p_Key,0)),"")
A77: =IF(D77="","",73) | B77: =IFERROR(INDEX(p_Rating,MATCH(LARGE(p_Key,73),p_Key,0)),"") | C77: =IFERROR(INDEX(p_Score,MATCH(LARGE(p_Key,73),p_Key,0)),"") | D77: =IFERROR(INDEX(p_Job,MATCH(LARGE(p_Key,73),p_Key,0)),"") | E77: =IFERROR(INDEX(p_Client,MATCH(LARGE(p_Key,73),p_Key,0)),"") | F77: =IFERROR(INDEX(p_Deal,MATCH(LARGE(p_Key,73),p_Key,0)),"") | G77: =IFERROR(INDEX(p_CC,MATCH(LARGE(p_Key,73),p_Key,0)),"") | H77: =IFERROR(INDEX(p_Status,MATCH(LARGE(p_Key,73),p_Key,0)),"") | I77: =IFERROR(INDEX(p_Stage,MATCH(LARGE(p_Key,73),p_Key,0)),"") | J77: =IFERROR(INDEX(p_Value,MATCH(LARGE(p_Key,73),p_Key,0)),"") | K77: =IFERROR(IF(H77="Open",INDEX(p_Prob,MATCH(LARGE(p_Key,73),p_Key,0)),""),"") | L77: =IFERROR(INDEX(p_Risk,MATCH(LARGE(p_Key,73),p_Key,0)),"") | M77: =IFERROR(INDEX(p_Month,MATCH(LARGE(p_Key,73),p_Key,0)),"") | N77: =IFERROR(INDEX(p_Flags,MATCH(LARGE(p_Key,73),p_Key,0)),"")
A78: =IF(D78="","",74) | B78: =IFERROR(INDEX(p_Rating,MATCH(LARGE(p_Key,74),p_Key,0)),"") | C78: =IFERROR(INDEX(p_Score,MATCH(LARGE(p_Key,74),p_Key,0)),"") | D78: =IFERROR(INDEX(p_Job,MATCH(LARGE(p_Key,74),p_Key,0)),"") | E78: =IFERROR(INDEX(p_Client,MATCH(LARGE(p_Key,74),p_Key,0)),"") | F78: =IFERROR(INDEX(p_Deal,MATCH(LARGE(p_Key,74),p_Key,0)),"") | G78: =IFERROR(INDEX(p_CC,MATCH(LARGE(p_Key,74),p_Key,0)),"") | H78: =IFERROR(INDEX(p_Status,MATCH(LARGE(p_Key,74),p_Key,0)),"") | I78: =IFERROR(INDEX(p_Stage,MATCH(LARGE(p_Key,74),p_Key,0)),"") | J78: =IFERROR(INDEX(p_Value,MATCH(LARGE(p_Key,74),p_Key,0)),"") | K78: =IFERROR(IF(H78="Open",INDEX(p_Prob,MATCH(LARGE(p_Key,74),p_Key,0)),""),"") | L78: =IFERROR(INDEX(p_Risk,MATCH(LARGE(p_Key,74),p_Key,0)),"") | M78: =IFERROR(INDEX(p_Month,MATCH(LARGE(p_Key,74),p_Key,0)),"") | N78: =IFERROR(INDEX(p_Flags,MATCH(LARGE(p_Key,74),p_Key,0)),"")
A79: =IF(D79="","",75) | B79: =IFERROR(INDEX(p_Rating,MATCH(LARGE(p_Key,75),p_Key,0)),"") | C79: =IFERROR(INDEX(p_Score,MATCH(LARGE(p_Key,75),p_Key,0)),"") | D79: =IFERROR(INDEX(p_Job,MATCH(LARGE(p_Key,75),p_Key,0)),"") | E79: =IFERROR(INDEX(p_Client,MATCH(LARGE(p_Key,75),p_Key,0)),"") | F79: =IFERROR(INDEX(p_Deal,MATCH(LARGE(p_Key,75),p_Key,0)),"") | G79: =IFERROR(INDEX(p_CC,MATCH(LARGE(p_Key,75),p_Key,0)),"") | H79: =IFERROR(INDEX(p_Status,MATCH(LARGE(p_Key,75),p_Key,0)),"") | I79: =IFERROR(INDEX(p_Stage,MATCH(LARGE(p_Key,75),p_Key,0)),"") | J79: =IFERROR(INDEX(p_Value,MATCH(LARGE(p_Key,75),p_Key,0)),"") | K79: =IFERROR(IF(H79="Open",INDEX(p_Prob,MATCH(LARGE(p_Key,75),p_Key,0)),""),"") | L79: =IFERROR(INDEX(p_Risk,MATCH(LARGE(p_Key,75),p_Key,0)),"") | M79: =IFERROR(INDEX(p_Month,MATCH(LARGE(p_Key,75),p_Key,0)),"") | N79: =IFERROR(INDEX(p_Flags,MATCH(LARGE(p_Key,75),p_Key,0)),"")
A80: =IF(D80="","",76) | B80: =IFERROR(INDEX(p_Rating,MATCH(LARGE(p_Key,76),p_Key,0)),"") | C80: =IFERROR(INDEX(p_Score,MATCH(LARGE(p_Key,76),p_Key,0)),"") | D80: =IFERROR(INDEX(p_Job,MATCH(LARGE(p_Key,76),p_Key,0)),"") | E80: =IFERROR(INDEX(p_Client,MATCH(LARGE(p_Key,76),p_Key,0)),"") | F80: =IFERROR(INDEX(p_Deal,MATCH(LARGE(p_Key,76),p_Key,0)),"") | G80: =IFERROR(INDEX(p_CC,MATCH(LARGE(p_Key,76),p_Key,0)),"") | H80: =IFERROR(INDEX(p_Status,MATCH(LARGE(p_Key,76),p_Key,0)),"") | I80: =IFERROR(INDEX(p_Stage,MATCH(LARGE(p_Key,76),p_Key,0)),"") | J80: =IFERROR(INDEX(p_Value,MATCH(LARGE(p_Key,76),p_Key,0)),"") | K80: =IFERROR(IF(H80="Open",INDEX(p_Prob,MATCH(LARGE(p_Key,76),p_Key,0)),""),"") | L80: =IFERROR(INDEX(p_Risk,MATCH(LARGE(p_Key,76),p_Key,0)),"") | M80: =IFERROR(INDEX(p_Month,MATCH(LARGE(p_Key,76),p_Key,0)),"") | N80: =IFERROR(INDEX(p_Flags,MATCH(LARGE(p_Key,76),p_Key,0)),"")
A81: =IF(D81="","",77) | B81: =IFERROR(INDEX(p_Rating,MATCH(LARGE(p_Key,77),p_Key,0)),"") | C81: =IFERROR(INDEX(p_Score,MATCH(LARGE(p_Key,77),p_Key,0)),"") | D81: =IFERROR(INDEX(p_Job,MATCH(LARGE(p_Key,77),p_Key,0)),"") | E81: =IFERROR(INDEX(p_Client,MATCH(LARGE(p_Key,77),p_Key,0)),"") | F81: =IFERROR(INDEX(p_Deal,MATCH(LARGE(p_Key,77),p_Key,0)),"") | G81: =IFERROR(INDEX(p_CC,MATCH(LARGE(p_Key,77),p_Key,0)),"") | H81: =IFERROR(INDEX(p_Status,MATCH(LARGE(p_Key,77),p_Key,0)),"") | I81: =IFERROR(INDEX(p_Stage,MATCH(LARGE(p_Key,77),p_Key,0)),"") | J81: =IFERROR(INDEX(p_Value,MATCH(LARGE(p_Key,77),p_Key,0)),"") | K81: =IFERROR(IF(H81="Open",INDEX(p_Prob,MATCH(LARGE(p_Key,77),p_Key,0)),""),"") | L81: =IFERROR(INDEX(p_Risk,MATCH(LARGE(p_Key,77),p_Key,0)),"") | M81: =IFERROR(INDEX(p_Month,MATCH(LARGE(p_Key,77),p_Key,0)),"") | N81: =IFERROR(INDEX(p_Flags,MATCH(LARGE(p_Key,77),p_Key,0)),"")
A82: =IF(D82="","",78) | B82: =IFERROR(INDEX(p_Rating,MATCH(LARGE(p_Key,78),p_Key,0)),"") | C82: =IFERROR(INDEX(p_Score,MATCH(LARGE(p_Key,78),p_Key,0)),"") | D82: =IFERROR(INDEX(p_Job,MATCH(LARGE(p_Key,78),p_Key,0)),"") | E82: =IFERROR(INDEX(p_Client,MATCH(LARGE(p_Key,78),p_Key,0)),"") | F82: =IFERROR(INDEX(p_Deal,MATCH(LARGE(p_Key,78),p_Key,0)),"") | G82: =IFERROR(INDEX(p_CC,MATCH(LARGE(p_Key,78),p_Key,0)),"") | H82: =IFERROR(INDEX(p_Status,MATCH(LARGE(p_Key,78),p_Key,0)),"") | I82: =IFERROR(INDEX(p_Stage,MATCH(LARGE(p_Key,78),p_Key,0)),"") | J82: =IFERROR(INDEX(p_Value,MATCH(LARGE(p_Key,78),p_Key,0)),"") | K82: =IFERROR(IF(H82="Open",INDEX(p_Prob,MATCH(LARGE(p_Key,78),p_Key,0)),""),"") | L82: =IFERROR(INDEX(p_Risk,MATCH(LARGE(p_Key,78),p_Key,0)),"") | M82: =IFERROR(INDEX(p_Month,MATCH(LARGE(p_Key,78),p_Key,0)),"") | N82: =IFERROR(INDEX(p_Flags,MATCH(LARGE(p_Key,78),p_Key,0)),"")
A83: =IF(D83="","",79) | B83: =IFERROR(INDEX(p_Rating,MATCH(LARGE(p_Key,79),p_Key,0)),"") | C83: =IFERROR(INDEX(p_Score,MATCH(LARGE(p_Key,79),p_Key,0)),"") | D83: =IFERROR(INDEX(p_Job,MATCH(LARGE(p_Key,79),p_Key,0)),"") | E83: =IFERROR(INDEX(p_Client,MATCH(LARGE(p_Key,79),p_Key,0)),"") | F83: =IFERROR(INDEX(p_Deal,MATCH(LARGE(p_Key,79),p_Key,0)),"") | G83: =IFERROR(INDEX(p_CC,MATCH(LARGE(p_Key,79),p_Key,0)),"") | H83: =IFERROR(INDEX(p_Status,MATCH(LARGE(p_Key,79),p_Key,0)),"") | I83: =IFERROR(INDEX(p_Stage,MATCH(LARGE(p_Key,79),p_Key,0)),"") | J83: =IFERROR(INDEX(p_Value,MATCH(LARGE(p_Key,79),p_Key,0)),"") | K83: =IFERROR(IF(H83="Open",INDEX(p_Prob,MATCH(LARGE(p_Key,79),p_Key,0)),""),"") | L83: =IFERROR(INDEX(p_Risk,MATCH(LARGE(p_Key,79),p_Key,0)),"") | M83: =IFERROR(INDEX(p_Month,MATCH(LARGE(p_Key,79),p_Key,0)),"") | N83: =IFERROR(INDEX(p_Flags,MATCH(LARGE(p_Key,79),p_Key,0)),"")
A84: =IF(D84="","",80) | B84: =IFERROR(INDEX(p_Rating,MATCH(LARGE(p_Key,80),p_Key,0)),"") | C84: =IFERROR(INDEX(p_Score,MATCH(LARGE(p_Key,80),p_Key,0)),"") | D84: =IFERROR(INDEX(p_Job,MATCH(LARGE(p_Key,80),p_Key,0)),"") | E84: =IFERROR(INDEX(p_Client,MATCH(LARGE(p_Key,80),p_Key,0)),"") | F84: =IFERROR(INDEX(p_Deal,MATCH(LARGE(p_Key,80),p_Key,0)),"") | G84: =IFERROR(INDEX(p_CC,MATCH(LARGE(p_Key,80),p_Key,0)),"") | H84: =IFERROR(INDEX(p_Status,MATCH(LARGE(p_Key,80),p_Key,0)),"") | I84: =IFERROR(INDEX(p_Stage,MATCH(LARGE(p_Key,80),p_Key,0)),"") | J84: =IFERROR(INDEX(p_Value,MATCH(LARGE(p_Key,80),p_Key,0)),"") | K84: =IFERROR(IF(H84="Open",INDEX(p_Prob,MATCH(LARGE(p_Key,80),p_Key,0)),""),"") | L84: =IFERROR(INDEX(p_Risk,MATCH(LARGE(p_Key,80),p_Key,0)),"") | M84: =IFERROR(INDEX(p_Month,MATCH(LARGE(p_Key,80),p_Key,0)),"") | N84: =IFERROR(INDEX(p_Flags,MATCH(LARGE(p_Key,80),p_Key,0)),"")
A85: =IF(D85="","",81) | B85: =IFERROR(INDEX(p_Rating,MATCH(LARGE(p_Key,81),p_Key,0)),"") | C85: =IFERROR(INDEX(p_Score,MATCH(LARGE(p_Key,81),p_Key,0)),"") | D85: =IFERROR(INDEX(p_Job,MATCH(LARGE(p_Key,81),p_Key,0)),"") | E85: =IFERROR(INDEX(p_Client,MATCH(LARGE(p_Key,81),p_Key,0)),"") | F85: =IFERROR(INDEX(p_Deal,MATCH(LARGE(p_Key,81),p_Key,0)),"") | G85: =IFERROR(INDEX(p_CC,MATCH(LARGE(p_Key,81),p_Key,0)),"") | H85: =IFERROR(INDEX(p_Status,MATCH(LARGE(p_Key,81),p_Key,0)),"") | I85: =IFERROR(INDEX(p_Stage,MATCH(LARGE(p_Key,81),p_Key,0)),"") | J85: =IFERROR(INDEX(p_Value,MATCH(LARGE(p_Key,81),p_Key,0)),"") | K85: =IFERROR(IF(H85="Open",INDEX(p_Prob,MATCH(LARGE(p_Key,81),p_Key,0)),""),"") | L85: =IFERROR(INDEX(p_Risk,MATCH(LARGE(p_Key,81),p_Key,0)),"") | M85: =IFERROR(INDEX(p_Month,MATCH(LARGE(p_Key,81),p_Key,0)),"") | N85: =IFERROR(INDEX(p_Flags,MATCH(LARGE(p_Key,81),p_Key,0)),"")
A86: =IF(D86="","",82) | B86: =IFERROR(INDEX(p_Rating,MATCH(LARGE(p_Key,82),p_Key,0)),"") | C86: =IFERROR(INDEX(p_Score,MATCH(LARGE(p_Key,82),p_Key,0)),"") | D86: =IFERROR(INDEX(p_Job,MATCH(LARGE(p_Key,82),p_Key,0)),"") | E86: =IFERROR(INDEX(p_Client,MATCH(LARGE(p_Key,82),p_Key,0)),"") | F86: =IFERROR(INDEX(p_Deal,MATCH(LARGE(p_Key,82),p_Key,0)),"") | G86: =IFERROR(INDEX(p_CC,MATCH(LARGE(p_Key,82),p_Key,0)),"") | H86: =IFERROR(INDEX(p_Status,MATCH(LARGE(p_Key,82),p_Key,0)),"") | I86: =IFERROR(INDEX(p_Stage,MATCH(LARGE(p_Key,82),p_Key,0)),"") | J86: =IFERROR(INDEX(p_Value,MATCH(LARGE(p_Key,82),p_Key,0)),"") | K86: =IFERROR(IF(H86="Open",INDEX(p_Prob,MATCH(LARGE(p_Key,82),p_Key,0)),""),"") | L86: =IFERROR(INDEX(p_Risk,MATCH(LARGE(p_Key,82),p_Key,0)),"") | M86: =IFERROR(INDEX(p_Month,MATCH(LARGE(p_Key,82),p_Key,0)),"") | N86: =IFERROR(INDEX(p_Flags,MATCH(LARGE(p_Key,82),p_Key,0)),"")
A87: =IF(D87="","",83) | B87: =IFERROR(INDEX(p_Rating,MATCH(LARGE(p_Key,83),p_Key,0)),"") | C87: =IFERROR(INDEX(p_Score,MATCH(LARGE(p_Key,83),p_Key,0)),"") | D87: =IFERROR(INDEX(p_Job,MATCH(LARGE(p_Key,83),p_Key,0)),"") | E87: =IFERROR(INDEX(p_Client,MATCH(LARGE(p_Key,83),p_Key,0)),"") | F87: =IFERROR(INDEX(p_Deal,MATCH(LARGE(p_Key,83),p_Key,0)),"") | G87: =IFERROR(INDEX(p_CC,MATCH(LARGE(p_Key,83),p_Key,0)),"") | H87: =IFERROR(INDEX(p_Status,MATCH(LARGE(p_Key,83),p_Key,0)),"") | I87: =IFERROR(INDEX(p_Stage,MATCH(LARGE(p_Key,83),p_Key,0)),"") | J87: =IFERROR(INDEX(p_Value,MATCH(LARGE(p_Key,83),p_Key,0)),"") | K87: =IFERROR(IF(H87="Open",INDEX(p_Prob,MATCH(LARGE(p_Key,83),p_Key,0)),""),"") | L87: =IFERROR(INDEX(p_Risk,MATCH(LARGE(p_Key,83),p_Key,0)),"") | M87: =IFERROR(INDEX(p_Month,MATCH(LARGE(p_Key,83),p_Key,0)),"") | N87: =IFERROR(INDEX(p_Flags,MATCH(LARGE(p_Key,83),p_Key,0)),"")
A88: =IF(D88="","",84) | B88: =IFERROR(INDEX(p_Rating,MATCH(LARGE(p_Key,84),p_Key,0)),"") | C88: =IFERROR(INDEX(p_Score,MATCH(LARGE(p_Key,84),p_Key,0)),"") | D88: =IFERROR(INDEX(p_Job,MATCH(LARGE(p_Key,84),p_Key,0)),"") | E88: =IFERROR(INDEX(p_Client,MATCH(LARGE(p_Key,84),p_Key,0)),"") | F88: =IFERROR(INDEX(p_Deal,MATCH(LARGE(p_Key,84),p_Key,0)),"") | G88: =IFERROR(INDEX(p_CC,MATCH(LARGE(p_Key,84),p_Key,0)),"") | H88: =IFERROR(INDEX(p_Status,MATCH(LARGE(p_Key,84),p_Key,0)),"") | I88: =IFERROR(INDEX(p_Stage,MATCH(LARGE(p_Key,84),p_Key,0)),"") | J88: =IFERROR(INDEX(p_Value,MATCH(LARGE(p_Key,84),p_Key,0)),"") | K88: =IFERROR(IF(H88="Open",INDEX(p_Prob,MATCH(LARGE(p_Key,84),p_Key,0)),""),"") | L88: =IFERROR(INDEX(p_Risk,MATCH(LARGE(p_Key,84),p_Key,0)),"") | M88: =IFERROR(INDEX(p_Month,MATCH(LARGE(p_Key,84),p_Key,0)),"") | N88: =IFERROR(INDEX(p_Flags,MATCH(LARGE(p_Key,84),p_Key,0)),"")
A89: =IF(D89="","",85) | B89: =IFERROR(INDEX(p_Rating,MATCH(LARGE(p_Key,85),p_Key,0)),"") | C89: =IFERROR(INDEX(p_Score,MATCH(LARGE(p_Key,85),p_Key,0)),"") | D89: =IFERROR(INDEX(p_Job,MATCH(LARGE(p_Key,85),p_Key,0)),"") | E89: =IFERROR(INDEX(p_Client,MATCH(LARGE(p_Key,85),p_Key,0)),"") | F89: =IFERROR(INDEX(p_Deal,MATCH(LARGE(p_Key,85),p_Key,0)),"") | G89: =IFERROR(INDEX(p_CC,MATCH(LARGE(p_Key,85),p_Key,0)),"") | H89: =IFERROR(INDEX(p_Status,MATCH(LARGE(p_Key,85),p_Key,0)),"") | I89: =IFERROR(INDEX(p_Stage,MATCH(LARGE(p_Key,85),p_Key,0)),"") | J89: =IFERROR(INDEX(p_Value,MATCH(LARGE(p_Key,85),p_Key,0)),"") | K89: =IFERROR(IF(H89="Open",INDEX(p_Prob,MATCH(LARGE(p_Key,85),p_Key,0)),""),"") | L89: =IFERROR(INDEX(p_Risk,MATCH(LARGE(p_Key,85),p_Key,0)),"") | M89: =IFERROR(INDEX(p_Month,MATCH(LARGE(p_Key,85),p_Key,0)),"") | N89: =IFERROR(INDEX(p_Flags,MATCH(LARGE(p_Key,85),p_Key,0)),"")
A90: =IF(D90="","",86) | B90: =IFERROR(INDEX(p_Rating,MATCH(LARGE(p_Key,86),p_Key,0)),"") | C90: =IFERROR(INDEX(p_Score,MATCH(LARGE(p_Key,86),p_Key,0)),"") | D90: =IFERROR(INDEX(p_Job,MATCH(LARGE(p_Key,86),p_Key,0)),"") | E90: =IFERROR(INDEX(p_Client,MATCH(LARGE(p_Key,86),p_Key,0)),"") | F90: =IFERROR(INDEX(p_Deal,MATCH(LARGE(p_Key,86),p_Key,0)),"") | G90: =IFERROR(INDEX(p_CC,MATCH(LARGE(p_Key,86),p_Key,0)),"") | H90: =IFERROR(INDEX(p_Status,MATCH(LARGE(p_Key,86),p_Key,0)),"") | I90: =IFERROR(INDEX(p_Stage,MATCH(LARGE(p_Key,86),p_Key,0)),"") | J90: =IFERROR(INDEX(p_Value,MATCH(LARGE(p_Key,86),p_Key,0)),"") | K90: =IFERROR(IF(H90="Open",INDEX(p_Prob,MATCH(LARGE(p_Key,86),p_Key,0)),""),"") | L90: =IFERROR(INDEX(p_Risk,MATCH(LARGE(p_Key,86),p_Key,0)),"") | M90: =IFERROR(INDEX(p_Month,MATCH(LARGE(p_Key,86),p_Key,0)),"") | N90: =IFERROR(INDEX(p_Flags,MATCH(LARGE(p_Key,86),p_Key,0)),"")
A91: =IF(D91="","",87) | B91: =IFERROR(INDEX(p_Rating,MATCH(LARGE(p_Key,87),p_Key,0)),"") | C91: =IFERROR(INDEX(p_Score,MATCH(LARGE(p_Key,87),p_Key,0)),"") | D91: =IFERROR(INDEX(p_Job,MATCH(LARGE(p_Key,87),p_Key,0)),"") | E91: =IFERROR(INDEX(p_Client,MATCH(LARGE(p_Key,87),p_Key,0)),"") | F91: =IFERROR(INDEX(p_Deal,MATCH(LARGE(p_Key,87),p_Key,0)),"") | G91: =IFERROR(INDEX(p_CC,MATCH(LARGE(p_Key,87),p_Key,0)),"") | H91: =IFERROR(INDEX(p_Status,MATCH(LARGE(p_Key,87),p_Key,0)),"") | I91: =IFERROR(INDEX(p_Stage,MATCH(LARGE(p_Key,87),p_Key,0)),"") | J91: =IFERROR(INDEX(p_Value,MATCH(LARGE(p_Key,87),p_Key,0)),"") | K91: =IFERROR(IF(H91="Open",INDEX(p_Prob,MATCH(LARGE(p_Key,87),p_Key,0)),""),"") | L91: =IFERROR(INDEX(p_Risk,MATCH(LARGE(p_Key,87),p_Key,0)),"") | M91: =IFERROR(INDEX(p_Month,MATCH(LARGE(p_Key,87),p_Key,0)),"") | N91: =IFERROR(INDEX(p_Flags,MATCH(LARGE(p_Key,87),p_Key,0)),"")
A92: =IF(D92="","",88) | B92: =IFERROR(INDEX(p_Rating,MATCH(LARGE(p_Key,88),p_Key,0)),"") | C92: =IFERROR(INDEX(p_Score,MATCH(LARGE(p_Key,88),p_Key,0)),"") | D92: =IFERROR(INDEX(p_Job,MATCH(LARGE(p_Key,88),p_Key,0)),"") | E92: =IFERROR(INDEX(p_Client,MATCH(LARGE(p_Key,88),p_Key,0)),"") | F92: =IFERROR(INDEX(p_Deal,MATCH(LARGE(p_Key,88),p_Key,0)),"") | G92: =IFERROR(INDEX(p_CC,MATCH(LARGE(p_Key,88),p_Key,0)),"") | H92: =IFERROR(INDEX(p_Status,MATCH(LARGE(p_Key,88),p_Key,0)),"") | I92: =IFERROR(INDEX(p_Stage,MATCH(LARGE(p_Key,88),p_Key,0)),"") | J92: =IFERROR(INDEX(p_Value,MATCH(LARGE(p_Key,88),p_Key,0)),"") | K92: =IFERROR(IF(H92="Open",INDEX(p_Prob,MATCH(LARGE(p_Key,88),p_Key,0)),""),"") | L92: =IFERROR(INDEX(p_Risk,MATCH(LARGE(p_Key,88),p_Key,0)),"") | M92: =IFERROR(INDEX(p_Month,MATCH(LARGE(p_Key,88),p_Key,0)),"") | N92: =IFERROR(INDEX(p_Flags,MATCH(LARGE(p_Key,88),p_Key,0)),"")
A93: =IF(D93="","",89) | B93: =IFERROR(INDEX(p_Rating,MATCH(LARGE(p_Key,89),p_Key,0)),"") | C93: =IFERROR(INDEX(p_Score,MATCH(LARGE(p_Key,89),p_Key,0)),"") | D93: =IFERROR(INDEX(p_Job,MATCH(LARGE(p_Key,89),p_Key,0)),"") | E93: =IFERROR(INDEX(p_Client,MATCH(LARGE(p_Key,89),p_Key,0)),"") | F93: =IFERROR(INDEX(p_Deal,MATCH(LARGE(p_Key,89),p_Key,0)),"") | G93: =IFERROR(INDEX(p_CC,MATCH(LARGE(p_Key,89),p_Key,0)),"") | H93: =IFERROR(INDEX(p_Status,MATCH(LARGE(p_Key,89),p_Key,0)),"") | I93: =IFERROR(INDEX(p_Stage,MATCH(LARGE(p_Key,89),p_Key,0)),"") | J93: =IFERROR(INDEX(p_Value,MATCH(LARGE(p_Key,89),p_Key,0)),"") | K93: =IFERROR(IF(H93="Open",INDEX(p_Prob,MATCH(LARGE(p_Key,89),p_Key,0)),""),"") | L93: =IFERROR(INDEX(p_Risk,MATCH(LARGE(p_Key,89),p_Key,0)),"") | M93: =IFERROR(INDEX(p_Month,MATCH(LARGE(p_Key,89),p_Key,0)),"") | N93: =IFERROR(INDEX(p_Flags,MATCH(LARGE(p_Key,89),p_Key,0)),"")
A94: =IF(D94="","",90) | B94: =IFERROR(INDEX(p_Rating,MATCH(LARGE(p_Key,90),p_Key,0)),"") | C94: =IFERROR(INDEX(p_Score,MATCH(LARGE(p_Key,90),p_Key,0)),"") | D94: =IFERROR(INDEX(p_Job,MATCH(LARGE(p_Key,90),p_Key,0)),"") | E94: =IFERROR(INDEX(p_Client,MATCH(LARGE(p_Key,90),p_Key,0)),"") | F94: =IFERROR(INDEX(p_Deal,MATCH(LARGE(p_Key,90),p_Key,0)),"") | G94: =IFERROR(INDEX(p_CC,MATCH(LARGE(p_Key,90),p_Key,0)),"") | H94: =IFERROR(INDEX(p_Status,MATCH(LARGE(p_Key,90),p_Key,0)),"") | I94: =IFERROR(INDEX(p_Stage,MATCH(LARGE(p_Key,90),p_Key,0)),"") | J94: =IFERROR(INDEX(p_Value,MATCH(LARGE(p_Key,90),p_Key,0)),"") | K94: =IFERROR(IF(H94="Open",INDEX(p_Prob,MATCH(LARGE(p_Key,90),p_Key,0)),""),"") | L94: =IFERROR(INDEX(p_Risk,MATCH(LARGE(p_Key,90),p_Key,0)),"") | M94: =IFERROR(INDEX(p_Month,MATCH(LARGE(p_Key,90),p_Key,0)),"") | N94: =IFERROR(INDEX(p_Flags,MATCH(LARGE(p_Key,90),p_Key,0)),"")
A95: =IF(D95="","",91) | B95: =IFERROR(INDEX(p_Rating,MATCH(LARGE(p_Key,91),p_Key,0)),"") | C95: =IFERROR(INDEX(p_Score,MATCH(LARGE(p_Key,91),p_Key,0)),"") | D95: =IFERROR(INDEX(p_Job,MATCH(LARGE(p_Key,91),p_Key,0)),"") | E95: =IFERROR(INDEX(p_Client,MATCH(LARGE(p_Key,91),p_Key,0)),"") | F95: =IFERROR(INDEX(p_Deal,MATCH(LARGE(p_Key,91),p_Key,0)),"") | G95: =IFERROR(INDEX(p_CC,MATCH(LARGE(p_Key,91),p_Key,0)),"") | H95: =IFERROR(INDEX(p_Status,MATCH(LARGE(p_Key,91),p_Key,0)),"") | I95: =IFERROR(INDEX(p_Stage,MATCH(LARGE(p_Key,91),p_Key,0)),"") | J95: =IFERROR(INDEX(p_Value,MATCH(LARGE(p_Key,91),p_Key,0)),"") | K95: =IFERROR(IF(H95="Open",INDEX(p_Prob,MATCH(LARGE(p_Key,91),p_Key,0)),""),"") | L95: =IFERROR(INDEX(p_Risk,MATCH(LARGE(p_Key,91),p_Key,0)),"") | M95: =IFERROR(INDEX(p_Month,MATCH(LARGE(p_Key,91),p_Key,0)),"") | N95: =IFERROR(INDEX(p_Flags,MATCH(LARGE(p_Key,91),p_Key,0)),"")
A96: =IF(D96="","",92) | B96: =IFERROR(INDEX(p_Rating,MATCH(LARGE(p_Key,92),p_Key,0)),"") | C96: =IFERROR(INDEX(p_Score,MATCH(LARGE(p_Key,92),p_Key,0)),"") | D96: =IFERROR(INDEX(p_Job,MATCH(LARGE(p_Key,92),p_Key,0)),"") | E96: =IFERROR(INDEX(p_Client,MATCH(LARGE(p_Key,92),p_Key,0)),"") | F96: =IFERROR(INDEX(p_Deal,MATCH(LARGE(p_Key,92),p_Key,0)),"") | G96: =IFERROR(INDEX(p_CC,MATCH(LARGE(p_Key,92),p_Key,0)),"") | H96: =IFERROR(INDEX(p_Status,MATCH(LARGE(p_Key,92),p_Key,0)),"") | I96: =IFERROR(INDEX(p_Stage,MATCH(LARGE(p_Key,92),p_Key,0)),"") | J96: =IFERROR(INDEX(p_Value,MATCH(LARGE(p_Key,92),p_Key,0)),"") | K96: =IFERROR(IF(H96="Open",INDEX(p_Prob,MATCH(LARGE(p_Key,92),p_Key,0)),""),"") | L96: =IFERROR(INDEX(p_Risk,MATCH(LARGE(p_Key,92),p_Key,0)),"") | M96: =IFERROR(INDEX(p_Month,MATCH(LARGE(p_Key,92),p_Key,0)),"") | N96: =IFERROR(INDEX(p_Flags,MATCH(LARGE(p_Key,92),p_Key,0)),"")
A97: =IF(D97="","",93) | B97: =IFERROR(INDEX(p_Rating,MATCH(LARGE(p_Key,93),p_Key,0)),"") | C97: =IFERROR(INDEX(p_Score,MATCH(LARGE(p_Key,93),p_Key,0)),"") | D97: =IFERROR(INDEX(p_Job,MATCH(LARGE(p_Key,93),p_Key,0)),"") | E97: =IFERROR(INDEX(p_Client,MATCH(LARGE(p_Key,93),p_Key,0)),"") | F97: =IFERROR(INDEX(p_Deal,MATCH(LARGE(p_Key,93),p_Key,0)),"") | G97: =IFERROR(INDEX(p_CC,MATCH(LARGE(p_Key,93),p_Key,0)),"") | H97: =IFERROR(INDEX(p_Status,MATCH(LARGE(p_Key,93),p_Key,0)),"") | I97: =IFERROR(INDEX(p_Stage,MATCH(LARGE(p_Key,93),p_Key,0)),"") | J97: =IFERROR(INDEX(p_Value,MATCH(LARGE(p_Key,93),p_Key,0)),"") | K97: =IFERROR(IF(H97="Open",INDEX(p_Prob,MATCH(LARGE(p_Key,93),p_Key,0)),""),"") | L97: =IFERROR(INDEX(p_Risk,MATCH(LARGE(p_Key,93),p_Key,0)),"") | M97: =IFERROR(INDEX(p_Month,MATCH(LARGE(p_Key,93),p_Key,0)),"") | N97: =IFERROR(INDEX(p_Flags,MATCH(LARGE(p_Key,93),p_Key,0)),"")
A98: =IF(D98="","",94) | B98: =IFERROR(INDEX(p_Rating,MATCH(LARGE(p_Key,94),p_Key,0)),"") | C98: =IFERROR(INDEX(p_Score,MATCH(LARGE(p_Key,94),p_Key,0)),"") | D98: =IFERROR(INDEX(p_Job,MATCH(LARGE(p_Key,94),p_Key,0)),"") | E98: =IFERROR(INDEX(p_Client,MATCH(LARGE(p_Key,94),p_Key,0)),"") | F98: =IFERROR(INDEX(p_Deal,MATCH(LARGE(p_Key,94),p_Key,0)),"") | G98: =IFERROR(INDEX(p_CC,MATCH(LARGE(p_Key,94),p_Key,0)),"") | H98: =IFERROR(INDEX(p_Status,MATCH(LARGE(p_Key,94),p_Key,0)),"") | I98: =IFERROR(INDEX(p_Stage,MATCH(LARGE(p_Key,94),p_Key,0)),"") | J98: =IFERROR(INDEX(p_Value,MATCH(LARGE(p_Key,94),p_Key,0)),"") | K98: =IFERROR(IF(H98="Open",INDEX(p_Prob,MATCH(LARGE(p_Key,94),p_Key,0)),""),"") | L98: =IFERROR(INDEX(p_Risk,MATCH(LARGE(p_Key,94),p_Key,0)),"") | M98: =IFERROR(INDEX(p_Month,MATCH(LARGE(p_Key,94),p_Key,0)),"") | N98: =IFERROR(INDEX(p_Flags,MATCH(LARGE(p_Key,94),p_Key,0)),"")
A99: =IF(D99="","",95) | B99: =IFERROR(INDEX(p_Rating,MATCH(LARGE(p_Key,95),p_Key,0)),"") | C99: =IFERROR(INDEX(p_Score,MATCH(LARGE(p_Key,95),p_Key,0)),"") | D99: =IFERROR(INDEX(p_Job,MATCH(LARGE(p_Key,95),p_Key,0)),"") | E99: =IFERROR(INDEX(p_Client,MATCH(LARGE(p_Key,95),p_Key,0)),"") | F99: =IFERROR(INDEX(p_Deal,MATCH(LARGE(p_Key,95),p_Key,0)),"") | G99: =IFERROR(INDEX(p_CC,MATCH(LARGE(p_Key,95),p_Key,0)),"") | H99: =IFERROR(INDEX(p_Status,MATCH(LARGE(p_Key,95),p_Key,0)),"") | I99: =IFERROR(INDEX(p_Stage,MATCH(LARGE(p_Key,95),p_Key,0)),"") | J99: =IFERROR(INDEX(p_Value,MATCH(LARGE(p_Key,95),p_Key,0)),"") | K99: =IFERROR(IF(H99="Open",INDEX(p_Prob,MATCH(LARGE(p_Key,95),p_Key,0)),""),"") | L99: =IFERROR(INDEX(p_Risk,MATCH(LARGE(p_Key,95),p_Key,0)),"") | M99: =IFERROR(INDEX(p_Month,MATCH(LARGE(p_Key,95),p_Key,0)),"") | N99: =IFERROR(INDEX(p_Flags,MATCH(LARGE(p_Key,95),p_Key,0)),"")
A100: =IF(D100="","",96) | B100: =IFERROR(INDEX(p_Rating,MATCH(LARGE(p_Key,96),p_Key,0)),"") | C100: =IFERROR(INDEX(p_Score,MATCH(LARGE(p_Key,96),p_Key,0)),"") | D100: =IFERROR(INDEX(p_Job,MATCH(LARGE(p_Key,96),p_Key,0)),"") | E100: =IFERROR(INDEX(p_Client,MATCH(LARGE(p_Key,96),p_Key,0)),"") | F100: =IFERROR(INDEX(p_Deal,MATCH(LARGE(p_Key,96),p_Key,0)),"") | G100: =IFERROR(INDEX(p_CC,MATCH(LARGE(p_Key,96),p_Key,0)),"") | H100: =IFERROR(INDEX(p_Status,MATCH(LARGE(p_Key,96),p_Key,0)),"") | I100: =IFERROR(INDEX(p_Stage,MATCH(LARGE(p_Key,96),p_Key,0)),"") | J100: =IFERROR(INDEX(p_Value,MATCH(LARGE(p_Key,96),p_Key,0)),"") | K100: =IFERROR(IF(H100="Open",INDEX(p_Prob,MATCH(LARGE(p_Key,96),p_Key,0)),""),"") | L100: =IFERROR(INDEX(p_Risk,MATCH(LARGE(p_Key,96),p_Key,0)),"") | M100: =IFERROR(INDEX(p_Month,MATCH(LARGE(p_Key,96),p_Key,0)),"") | N100: =IFERROR(INDEX(p_Flags,MATCH(LARGE(p_Key,96),p_Key,0)),"")
A101: =IF(D101="","",97) | B101: =IFERROR(INDEX(p_Rating,MATCH(LARGE(p_Key,97),p_Key,0)),"") | C101: =IFERROR(INDEX(p_Score,MATCH(LARGE(p_Key,97),p_Key,0)),"") | D101: =IFERROR(INDEX(p_Job,MATCH(LARGE(p_Key,97),p_Key,0)),"") | E101: =IFERROR(INDEX(p_Client,MATCH(LARGE(p_Key,97),p_Key,0)),"") | F101: =IFERROR(INDEX(p_Deal,MATCH(LARGE(p_Key,97),p_Key,0)),"") | G101: =IFERROR(INDEX(p_CC,MATCH(LARGE(p_Key,97),p_Key,0)),"") | H101: =IFERROR(INDEX(p_Status,MATCH(LARGE(p_Key,97),p_Key,0)),"") | I101: =IFERROR(INDEX(p_Stage,MATCH(LARGE(p_Key,97),p_Key,0)),"") | J101: =IFERROR(INDEX(p_Value,MATCH(LARGE(p_Key,97),p_Key,0)),"") | K101: =IFERROR(IF(H101="Open",INDEX(p_Prob,MATCH(LARGE(p_Key,97),p_Key,0)),""),"") | L101: =IFERROR(INDEX(p_Risk,MATCH(LARGE(p_Key,97),p_Key,0)),"") | M101: =IFERROR(INDEX(p_Month,MATCH(LARGE(p_Key,97),p_Key,0)),"") | N101: =IFERROR(INDEX(p_Flags,MATCH(LARGE(p_Key,97),p_Key,0)),"")
...

Sheet Settings
A1: Settings
A2: Thresholds the risk ratings use. Change the cream cells - every sheet follows.
A4: Setting | B4: Value | C4: What it does
A5: Data as at | B5: 46290 | C5: The date the tracker data was taken. Used to decide what is overdue or stale.
A6: Financial year starts | B6: 46204 | C6: First day of the financial year (1 July).
A7: Single deal - share of open pipeline | B7: 0.1 | C7: An open deal worth this share of all open pipeline or more is a concentration risk.
A8: Large deal value | B8: 50000 | C8: Deals at or above this value count as large.
A9: Early stage - probability at or below | B9: 0.25 | C9: A large deal this early is a forecast risk.
A10: Top client share of revenue - High | B10: 0.2 | C10: One client above this share of FYTD revenue = High concentration.
A11: Top 5 clients share - High | B11: 0.6 | C11: Top five clients above this share of FYTD revenue = High concentration.
A12: Risk score for High | B12: 5 | C12: Risk Register: score at or above this = High.
A13: Risk score for Medium | B13: 3 | C13: Score at or above this (and below High) = Medium. Anything above 0 = Low.
A15: Probabilities by pipeline stage come from the tracker (Lists AA:AB) and arrive already applied in the Work Won data. They are assumptions, not Zoho data.

Sheet Data - Revenue
A1: Row ID | B1: Department | C1: Job Number | D1: Client | E1: Job Description | F1: Dept Expected Ex GST | G1: Xero Invoice No | H1: Xero Invoice Date | I1: Xero Invoiced Ex GST | J1: Variance Dept vs Xero | K1: Compare | L1: Issue | M1: Finance Notes | N1: Job in Xero? | O1: Job Name (Xero) | P1: Cost Centre | Q1: Invoice Type | R1: Tax Code | S1: Revenue GL | T1: PO or Quote Ref | U1: Dept Notes | V1: GST | W1: Inc GST | X1: Invoice Month | Y1: Lines on Job | Z1: Job Total Expected | AA1: Job Total Invoiced | AB1: Dept Row | AD1: Amount | AE1: Invoice Date | AF1: Counted | AG1: Month | AH1: Client | AI1: Cost Centre | AJ1: In this FY to date | AK1: New client no. | AL1: Running
A2: ONS-0001 | B2: Onsite | C2: 1350 | D2: CBA | E2: CBA BNE July 2026 | F2: 8588.45 | G2: INV-10525 | H2: 46234 | I2: 8588.45 | J2: 0 | K2: Agrees | N2: OK | O2: CBA Brisbane ONS | P2: ONSITE | Q2: Contract | R2: GST 10% | S2: 41100 | U2: 174.05 hours | V2: 858.85 | W2: 9447.3 | X2: 46234 | Y2: 3 | Z2: 22550.95 | AA2: 22550.95 | AB2: 1 | AD2: =IFERROR(N(IFERROR(INDEX($A2:$AB2,MATCH("Xero Invoiced Ex GST",$A$1:$AB$1,0)),"")),0) | AE2: =IFERROR(INDEX($A2:$AB2,MATCH("Xero Invoice Date",$A$1:$AB$1,0)),"") | AF2: =IF(AND(IFERROR(INDEX($A2:$AB2,MATCH("Xero Invoice No",$A$1:$AB$1,0)),"")&""<>"",ISNUMBER(AE2),AD2<>0),1,0) | AG2: =IF(AF2=1,EOMONTH(AE2,0),"") | AH2: =IF(AF2=1,UPPER(TRIM(IFERROR(INDEX($A2:$AB2,MATCH("Client",$A$1:$AB$1,0)),"")&"")),"") | AI2: =IF(AF2=1,IFERROR(INDEX($A2:$AB2,MATCH("Cost Centre",$A$1:$AB$1,0)),"")&"","") | AJ2: =IF(AND(AF2=1,AE2>=set_FYStart,AE2<=set_AsAt),1,0) | AK2: =IF(AND(AJ2=1,AH2<>"",COUNTIFS($AH$2:AH2,AH2,$AJ$2:AJ2,1)=1),N(AL1)+1,"") | AL2: =IF(AK2<>"",AK2,N(AL1))
A3: PRD-0001 | B3: Production | C3: 2602309 | D3: Elkiem | E3: Studio Support | 1.7.26 | F3: 380 | G3: INV-10513 | H3: 46204 | I3: 380 | J3: 0 | K3: Agrees | L3: Job number not in the Xero job list | N3: CHECK | P3: PRODUCTION | Q3: Project | R3: GST 10% | S3: 42100 | T3: 5879 | V3: 38 | W3: 418 | X3: 46234 | Y3: 1 | Z3: 380 | AA3: 380 | AB3: 1 | AD3: =IFERROR(N(IFERROR(INDEX($A3:$AB3,MATCH("Xero Invoiced Ex GST",$A$1:$AB$1,0)),"")),0) | AE3: =IFERROR(INDEX($A3:$AB3,MATCH("Xero Invoice Date",$A$1:$AB$1,0)),"") | AF3: =IF(AND(IFERROR(INDEX($A3:$AB3,MATCH("Xero Invoice No",$A$1:$AB$1,0)),"")&""<>"",ISNUMBER(AE3),AD3<>0),1,0) | AG3: =IF(AF3=1,EOMONTH(AE3,0),"") | AH3: =IF(AF3=1,UPPER(TRIM(IFERROR(INDEX($A3:$AB3,MATCH("Client",$A$1:$AB$1,0)),"")&"")),"") | AI3: =IF(AF3=1,IFERROR(INDEX($A3:$AB3,MATCH("Cost Centre",$A$1:$AB$1,0)),"")&"","") | AJ3: =IF(AND(AF3=1,AE3>=set_FYStart,AE3<=set_AsAt),1,0) | AK3: =IF(AND(AJ3=1,AH3<>"",COUNTIFS($AH$2:AH3,AH3,$AJ$2:AJ3,1)=1),N(AL2)+1,"") | AL3: =IF(AK3<>"",AK3,N(AL2))
A4: CON-0001 | B4: Consulting | C4: 25021901 | D4: DAFF | E4: Technology Standards Evaluation | F4: 9875 | G4: INV-9860 | H4: 45805 | I4: 9875 | J4: 0 | K4: Agrees | N4: OK | O4: DAFF Technology Standard | P4: CONSULTING | Q4: Project | R4: GST 10% | S4: 42800 | T4: https://cts.qwilr.com/25021901-DAFF-Technology-Standards-Evaluation-A7PRmNNwQ5Wn | U4: Status: Completed | Revenue still in WIP | V4: 987.5 | W4: 10862.5 | X4: 45808 | Y4: 1 | Z4: 9875 | AA4: 9875 | AB4: 1 | AD4: =IFERROR(N(IFERROR(INDEX($A4:$AB4,MATCH("Xero Invoiced Ex GST",$A$1:$AB$1,0)),"")),0) | AE4: =IFERROR(INDEX($A4:$AB4,MATCH("Xero Invoice Date",$A$1:$AB$1,0)),"") | AF4: =IF(AND(IFERROR(INDEX($A4:$AB4,MATCH("Xero Invoice No",$A$1:$AB$1,0)),"")&""<>"",ISNUMBER(AE4),AD4<>0),1,0) | AG4: =IF(AF4=1,EOMONTH(AE4,0),"") | AH4: =IF(AF4=1,UPPER(TRIM(IFERROR(INDEX($A4:$AB4,MATCH("Client",$A$1:$AB$1,0)),"")&"")),"") | AI4: =IF(AF4=1,IFERROR(INDEX($A4:$AB4,MATCH("Cost Centre",$A$1:$AB$1,0)),"")&"","") | AJ4: =IF(AND(AF4=1,AE4>=set_FYStart,AE4<=set_AsAt),1,0) | AK4: =IF(AND(AJ4=1,AH4<>"",COUNTIFS($AH$2:AH4,AH4,$AJ$2:AJ4,1)=1),N(AL3)+1,"") | AL4: =IF(AK4<>"",AK4,N(AL3))
A5: ONS-0002 | B5: Onsite | C5: 585/586/1755 | D5: CBA | E5: CBP July 2026 | F5: 22120.57 | G5: INV-10526 | H5: 46234 | I5: 22120.57 | J5: 0 | K5: Agrees | L5: Job number not in the Xero job list | N5: CHECK | P5: ONSITE | Q5: Contract | R5: GST 10% | S5: 41100 | U5: Deduct 3hrs for TN 01/07 & 6hrs for NP 14/07 | V5: 2212.06 | W5: 24332.63 | X5: 46234 | Y5: 2 | Z5: 22120.57 | AA5: 22120.57 | AB5: 2 | AD5: =IFERROR(N(IFERROR(INDEX($A5:$AB5,MATCH("Xero Invoiced Ex GST",$A$1:$AB$1,0)),"")),0) | AE5: =IFERROR(INDEX($A5:$AB5,MATCH("Xero Invoice Date",$A$1:$AB$1,0)),"") | AF5: =IF(AND(IFERROR(INDEX($A5:$AB5,MATCH("Xero Invoice No",$A$1:$AB$1,0)),"")&""<>"",ISNUMBER(AE5),AD5<>0),1,0) | AG5: =IF(AF5=1,EOMONTH(AE5,0),"") | AH5: =IF(AF5=1,UPPER(TRIM(IFERROR(INDEX($A5:$AB5,MATCH("Client",$A$1:$AB$1,0)),"")&"")),"") | AI5: =IF(AF5=1,IFERROR(INDEX($A5:$AB5,MATCH("Cost Centre",$A$1:$AB$1,0)),"")&"","") | AJ5: =IF(AND(AF5=1,AE5>=set_FYStart,AE5<=set_AsAt),1,0) | AK5: =IF(AND(AJ5=1,AH5<>"",COUNTIFS($AH$2:AH5,AH5,$AJ$2:AJ5,1)=1),N(AL4)+1,"") | AL5: =IF(AK5<>"",AK5,N(AL4))
A6: PRD-0002 | B6: Production | C6: 26032301 | D6: RSNSW | E6: Ordinary General Meeting | 1.7.26 | F6: 2042 | G6: INV-10519 | H6: 46210 | I6: 2042 | J6: 0 | K6: Agrees | N6: OK | O6: RSNSW - OGM - 1.7.2026 | P6: PRODUCTION | Q6: Project | R6: GST 10% | S6: 42100 | T6: 5924 | V6: 204.2 | W6: 2246.2 | X6: 46234 | Y6: 1 | Z6: 2042 | AA6: 2042 | AB6: 2 | AD6: =IFERROR(N(IFERROR(INDEX($A6:$AB6,MATCH("Xero Invoiced Ex GST",$A$1:$AB$1,0)),"")),0) | AE6: =IFERROR(INDEX($A6:$AB6,MATCH("Xero Invoice Date",$A$1:$AB$1,0)),"") | AF6: =IF(AND(IFERROR(INDEX($A6:$AB6,MATCH("Xero Invoice No",$A$1:$AB$1,0)),"")&""<>"",ISNUMBER(AE6),AD6<>0),1,0) | AG6: =IF(AF6=1,EOMONTH(AE6,0),"") | AH6: =IF(AF6=1,UPPER(TRIM(IFERROR(INDEX($A6:$AB6,MATCH("Client",$A$1:$AB$1,0)),"")&"")),"") | AI6: =IF(AF6=1,IFERROR(INDEX($A6:$AB6,MATCH("Cost Centre",$A$1:$AB$1,0)),"")&"","") | AJ6: =IF(AND(AF6=1,AE6>=set_FYStart,AE6<=set_AsAt),1,0) | AK6: =IF(AND(AJ6=1,AH6<>"",COUNTIFS($AH$2:AH6,AH6,$AJ$2:AJ6,1)=1),N(AL5)+1,"") | AL6: =IF(AK6<>"",AK6,N(AL5))
A7: CON-0002 | B7: Consulting | C7: 25102701 | D7: DEWR | E7: DEWR Studio Upgrade | F7: 23050 | G7: INV-10319 | H7: 46101 | I7: 23050 | J7: 0 | K7: Agrees | N7: OK | O7: DEWR - Studio Upgrade - Consulting, Design | P7: CONSULTING | Q7: Progress Claim | R7: GST 10% | S7: 42800 | T7: https://cts.qwilr.com/25102701-DEWR-Studio-Upgrade-ESE25-143997-Rev-4-KTqWXx2QQz6f | U7: Status: In Progress | Progress Claim 01 | V7: 2305 | W7: 25355 | X7: 46112 | Y7: 4 | Z7: 68273 | AA7: 68273 | AB7: 2 | AD7: =IFERROR(N(IFERROR(INDEX($A7:$AB7,MATCH("Xero Invoiced Ex GST",$A$1:$AB$1,0)),"")),0) | AE7: =IFERROR(INDEX($A7:$AB7,MATCH("Xero Invoice Date",$A$1:$AB$1,0)),"") | AF7: =IF(AND(IFERROR(INDEX($A7:$AB7,MATCH("Xero Invoice No",$A$1:$AB$1,0)),"")&""<>"",ISNUMBER(AE7),AD7<>0),1,0) | AG7: =IF(AF7=1,EOMONTH(AE7,0),"") | AH7: =IF(AF7=1,UPPER(TRIM(IFERROR(INDEX($A7:$AB7,MATCH("Client",$A$1:$AB$1,0)),"")&"")),"") | AI7: =IF(AF7=1,IFERROR(INDEX($A7:$AB7,MATCH("Cost Centre",$A$1:$AB$1,0)),"")&"","") | AJ7: =IF(AND(AF7=1,AE7>=set_FYStart,AE7<=set_AsAt),1,0) | AK7: =IF(AND(AJ7=1,AH7<>"",COUNTIFS($AH$2:AH7,AH7,$AJ$2:AJ7,1)=1),N(AL6)+1,"") | AL7: =IF(AK7<>"",AK7,N(AL6))
A8: ONS-0003 | B8: Onsite | C8: 587 | D8: CBA | E8: CBS July 2026 | F8: 10720 | G8: INV-10527 | H8: 46234 | I8: 10720 | J8: 0 | K8: Agrees | N8: OK | O8: CBA Tech TN | P8: ONSITE | Q8: Contract | R8: GST 10% | S8: 41100 | V8: 1072 | W8: 11792 | X8: 46234 | Y8: 4 | Z8: 31637.88 | AA8: 31637.88 | AB8: 3 | AD8: =IFERROR(N(IFERROR(INDEX($A8:$AB8,MATCH("Xero Invoiced Ex GST",$A$1:$AB$1,0)),"")),0) | AE8: =IFERROR(INDEX($A8:$AB8,MATCH("Xero Invoice Date",$A$1:$AB$1,0)),"") | AF8: =IF(AND(IFERROR(INDEX($A8:$AB8,MATCH("Xero Invoice No",$A$1:$AB$1,0)),"")&""<>"",ISNUMBER(AE8),AD8<>0),1,0) | AG8: =IF(AF8=1,EOMONTH(AE8,0),"") | AH8: =IF(AF8=1,UPPER(TRIM(IFERROR(INDEX($A8:$AB8,MATCH("Client",$A$1:$AB$1,0)),"")&"")),"") | AI8: =IF(AF8=1,IFERROR(INDEX($A8:$AB8,MATCH("Cost Centre",$A$1:$AB$1,0)),"")&"","") | AJ8: =IF(AND(AF8=1,AE8>=set_FYStart,AE8<=set_AsAt),1,0) | AK8: =IF(AND(AJ8=1,AH8<>"",COUNTIFS($AH$2:AH8,AH8,$AJ$2:AJ8,1)=1),N(AL7)+1,"") | AL8: =IF(AK8<>"",AK8,N(AL7))
A9: PRD-0003 | B9: Production | C9: 26062201 | D9: PWC | E9: Tax and Legal Webcast 2.7.26 | F9: 955 | G9: INV-10515 | H9: 46210 | I9: 955 | J9: 0 | K9: Agrees | N9: OK | O9: PWC - Tax & Legal Webcast 02.07.26 | P9: PRODUCTION | Q9: Project | R9: GST 10% | S9: 42100 | T9: 6076 | V9: 95.5 | W9: 1050.5 | X9: 46234 | Y9: 1 | Z9: 955 | AA9: 955 | AB9: 3 | AD9: =IFERROR(N(IFERROR(INDEX($A9:$AB9,MATCH("Xero Invoiced Ex GST",$A$1:$AB$1,0)),"")),0) | AE9: =IFERROR(INDEX($A9:$AB9,MATCH("Xero Invoice Date",$A$1:$AB$1,0)),"") | AF9: =IF(AND(IFERROR(INDEX($A9:$AB9,MATCH("Xero Invoice No",$A$1:$AB$1,0)),"")&""<>"",ISNUMBER(AE9),AD9<>0),1,0) | AG9: =IF(AF9=1,EOMONTH(AE9,0),"") | AH9: =IF(AF9=1,UPPER(TRIM(IFERROR(INDEX($A9:$AB9,MATCH("Client",$A$1:$AB$1,0)),"")&"")),"") | AI9: =IF(AF9=1,IFERROR(INDEX($A9:$AB9,MATCH("Cost Centre",$A$1:$AB$1,0)),"")&"","") | AJ9: =IF(AND(AF9=1,AE9>=set_FYStart,AE9<=set_AsAt),1,0) | AK9: =IF(AND(AJ9=1,AH9<>"",COUNTIFS($AH$2:AH9,AH9,$AJ$2:AJ9,1)=1),N(AL8)+1,"") | AL9: =IF(AK9<>"",AK9,N(AL8))
A10: CON-0003 | B10: Consulting | C10: 25102701 | D10: DEWR | E10: DEWR Studio Upgrade | F10: 13250 | G10: INV-10320 | H10: 46104 | I10: 13250 | J10: 0 | K10: Agrees | N10: OK | O10: DEWR - Studio Upgrade - Consulting, Design | P10: CONSULTING | Q10: Progress Claim | R10: GST 10% | S10: 42800 | T10: https://cts.qwilr.com/25102701-DEWR-Studio-Upgrade-ESE25-143997-Rev-4-KTqWXx2QQz6f | U10: Status: In Progress | Progress Claim 02 | V10: 1325 | W10: 14575 | X10: 46112 | Y10: 4 | Z10: 68273 | AA10: 68273 | AB10: 3 | AD10: =IFERROR(N(IFERROR(INDEX($A10:$AB10,MATCH("Xero Invoiced Ex GST",$A$1:$AB$1,0)),"")),0) | AE10: =IFERROR(INDEX($A10:$AB10,MATCH("Xero Invoice Date",$A$1:$AB$1,0)),"") | AF10: =IF(AND(IFERROR(INDEX($A10:$AB10,MATCH("Xero Invoice No",$A$1:$AB$1,0)),"")&""<>"",ISNUMBER(AE10),AD10<>0),1,0) | AG10: =IF(AF10=1,EOMONTH(AE10,0),"") | AH10: =IF(AF10=1,UPPER(TRIM(IFERROR(INDEX($A10:$AB10,MATCH("Client",$A$1:$AB$1,0)),"")&"")),"") | AI10: =IF(AF10=1,IFERROR(INDEX($A10:$AB10,MATCH("Cost Centre",$A$1:$AB$1,0)),"")&"","") | AJ10: =IF(AND(AF10=1,AE10>=set_FYStart,AE10<=set_AsAt),1,0) | AK10: =IF(AND(AJ10=1,AH10<>"",COUNTIFS($AH$2:AH10,AH10,$AJ$2:AJ10,1)=1),N(AL9)+1,"") | AL10: =IF(AK10<>"",AK10,N(AL9))
A11: ONS-0004 | B11: Onsite | C11: 2846/1401/725/1400/1530/1862/2402/2849/974 | D11: DTTL | E11: DTTL Contract July 2026 | F11: 103625.44 | G11: INV-10528 | H11: 46234 | I11: 103625.44 | J11: 0 | K11: Agrees | L11: Job number not in the Xero job list | N11: CHECK | P11: ONSITE | Q11: Contract | R11: GST 10% | S11: 41100 | V11: 10362.54 | W11: 113987.98 | X11: 46234 | Y11: 3 | Z11: 310876.32 | AA11: 310876.32 | AB11: 4 | AD11: =IFERROR(N(IFERROR(INDEX($A11:$AB11,MATCH("Xero Invoiced Ex GST",$A$1:$AB$1,0)),"")),0) | AE11: =IFERROR(INDEX($A11:$AB11,MATCH("Xero Invoice Date",$A$1:$AB$1,0)),"") | AF11: =IF(AND(IFERROR(INDEX($A11:$AB11,MATCH("Xero Invoice No",$A$1:$AB$1,0)),"")&""<>"",ISNUMBER(AE11),AD11<>0),1,0) | AG11: =IF(AF11=1,EOMONTH(AE11,0),"") | AH11: =IF(AF11=1,UPPER(TRIM(IFERROR(INDEX($A11:$AB11,MATCH("Client",$A$1:$AB$1,0)),"")&"")),"") | AI11: =IF(AF11=1,IFERROR(INDEX($A11:$AB11,MATCH("Cost Centre",$A$1:$AB$1,0)),"")&"","") | AJ11: =IF(AND(AF11=1,AE11>=set_FYStart,AE11<=set_AsAt),1,0) | AK11: =IF(AND(AJ11=1,AH11<>"",COUNTIFS($AH$2:AH11,AH11,$AJ$2:AJ11,1)=1),N(AL10)+1,"") | AL11: =IF(AK11<>"",AK11,N(AL10))
A12: PRD-0004 | B12: Production | C12: 2605802 | D12: Elkiem - PM** Cancelled | E12: Elkiem Studio Support | 15.7.26 | F12: 261.25 | G12: INV-10524 | H12: 46219 | I12: 261.25 | J12: 0 | K12: Agrees | L12: Job number not in the Xero job list | N12: CHECK | P12: PRODUCTION | Q12: Project | R12: GST 10% | S12: 42100 | T12: 6013 | V12: 26.13 | W12: 287.38 | X12: 46234 | Y12: 1 | Z12: 261.25 | AA12: 261.25 | AB12: 4 | AD12: =IFERROR(N(IFERROR(INDEX($A12:$AB12,MATCH("Xero Invoiced Ex GST",$A$1:$AB$1,0)),"")),0) | AE12: =IFERROR(INDEX($A12:$AB12,MATCH("Xero Invoice Date",$A$1:$AB$1,0)),"") | AF12: =IF(AND(IFERROR(INDEX($A12:$AB12,MATCH("Xero Invoice No",$A$1:$AB$1,0)),"")&""<>"",ISNUMBER(AE12),AD12<>0),1,0) | AG12: =IF(AF12=1,EOMONTH(AE12,0),"") | AH12: =IF(AF12=1,UPPER(TRIM(IFERROR(INDEX($A12:$AB12,MATCH("Client",$A$1:$AB$1,0)),"")&"")),"") | AI12: =IF(AF12=1,IFERROR(INDEX($A12:$AB12,MATCH("Cost Centre",$A$1:$AB$1,0)),"")&"","") | AJ12: =IF(AND(AF12=1,AE12>=set_FYStart,AE12<=set_AsAt),1,0) | AK12: =IF(AND(AJ12=1,AH12<>"",COUNTIFS($AH$2:AH12,AH12,$AJ$2:AJ12,1)=1),N(AL11)+1,"") | AL12: =IF(AK12<>"",AK12,N(AL11))
A13: CON-0004 | B13: Consulting | C13: 25102701 | D13: DEWR | E13: DEWR Studio Upgrade | F13: 24410 | G13: INV-10353 | H13: 46128 | I13: 24410 | J13: 0 | K13: Agrees | N13: OK | O13: DEWR - Studio Upgrade - Consulting, Design | P13: CONSULTING | Q13: Progress Claim | R13: GST 10% | S13: 42800 | T13: https://cts.qwilr.com/25102701-DEWR-Studio-Upgrade-ESE25-143997-Rev-4-KTqWXx2QQz6f | U13: Status: In Progress | Progress Claim 03 | V13: 2441 | W13: 26851 | X13: 46142 | Y13: 4 | Z13: 68273 | AA13: 68273 | AB13: 4 | AD13: =IFERROR(N(IFERROR(INDEX($A13:$AB13,MATCH("Xero Invoiced Ex GST",$A$1:$AB$1,0)),"")),0) | AE13: =IFERROR(INDEX($A13:$AB13,MATCH("Xero Invoice Date",$A$1:$AB$1,0)),"") | AF13: =IF(AND(IFERROR(INDEX($A13:$AB13,MATCH("Xero Invoice No",$A$1:$AB$1,0)),"")&""<>"",ISNUMBER(AE13),AD13<>0),1,0) | AG13: =IF(AF13=1,EOMONTH(AE13,0),"") | AH13: =IF(AF13=1,UPPER(TRIM(IFERROR(INDEX($A13:$AB13,MATCH("Client",$A$1:$AB$1,0)),"")&"")),"") | AI13: =IF(AF13=1,IFERROR(INDEX($A13:$AB13,MATCH("Cost Centre",$A$1:$AB$1,0)),"")&"","") | AJ13: =IF(AND(AF13=1,AE13>=set_FYStart,AE13<=set_AsAt),1,0) | AK13: =IF(AND(AJ13=1,AH13<>"",COUNTIFS($AH$2:AH13,AH13,$AJ$2:AJ13,1)=1),N(AL12)+1,"") | AL13: =IF(AK13<>"",AK13,N(AL12))
A14: ONS-0005 | B14: Onsite | C14: 732/1144 | D14: BW | E14: BW Contract July 2026 | F14: 19427.5 | G14: INV-10529 | H14: 46234 | I14: 19427.5 | J14: 0 | K14: Agrees | L14: Job number not in the Xero job list | N14: CHECK | P14: ONSITE | Q14: Contract | R14: GST 10% | S14: 41100 | V14: 1942.75 | W14: 21370.25 | X14: 46234 | Y14: 3 | Z14: 53823.75 | AA14: 53823.75 | AB14: 5 | AD14: =IFERROR(N(IFERROR(INDEX($A14:$AB14,MATCH("Xero Invoiced Ex GST",$A$1:$AB$1,0)),"")),0) | AE14: =IFERROR(INDEX($A14:$AB14,MATCH("Xero Invoice Date",$A$1:$AB$1,0)),"") | AF14: =IF(AND(IFERROR(INDEX($A14:$AB14,MATCH("Xero Invoice No",$A$1:$AB$1,0)),"")&""<>"",ISNUMBER(AE14),AD14<>0),1,0) | AG14: =IF(AF14=1,EOMONTH(AE14,0),"") | AH14: =IF(AF14=1,UPPER(TRIM(IFERROR(INDEX($A14:$AB14,MATCH("Client",$A$1:$AB$1,0)),"")&"")),"") | AI14: =IF(AF14=1,IFERROR(INDEX($A14:$AB14,MATCH("Cost Centre",$A$1:$AB$1,0)),"")&"","") | AJ14: =IF(AND(AF14=1,AE14>=set_FYStart,AE14<=set_AsAt),1,0) | AK14: =IF(AND(AJ14=1,AH14<>"",COUNTIFS($AH$2:AH14,AH14,$AJ$2:AJ14,1)=1),N(AL13)+1,"") | AL14: =IF(AK14<>"",AK14,N(AL13))
A15: PRD-0005 | B15: Production | C15: 2607701 | D15: Litecard | E15: Screen & Mic Hire 16.7.26 | F15: 500 | G15: INV-10518 | H15: 46210 | I15: 500 | J15: 0 | K15: Agrees | L15: Job number not in the Xero job list | N15: CHECK | P15: PRODUCTION | Q15: Project | R15: GST 10% | S15: 42100 | T15: 6089 | V15: 50 | W15: 550 | X15: 46234 | Y15: 2 | Z15: 500 | AA15: 500 | AB15: 5 | AD15: =IFERROR(N(IFERROR(INDEX($A15:$AB15,MATCH("Xero Invoiced Ex GST",$A$1:$AB$1,0)),"")),0) | AE15: =IFERROR(INDEX($A15:$AB15,MATCH("Xero Invoice Date",$A$1:$AB$1,0)),"") | AF15: =IF(AND(IFERROR(INDEX($A15:$AB15,MATCH("Xero Invoice No",$A$1:$AB$1,0)),"")&""<>"",ISNUMBER(AE15),AD15<>0),1,0) | AG15: =IF(AF15=1,EOMONTH(AE15,0),"") | AH15: =IF(AF15=1,UPPER(TRIM(IFERROR(INDEX($A15:$AB15,MATCH("Client",$A$1:$AB$1,0)),"")&"")),"") | AI15: =IF(AF15=1,IFERROR(INDEX($A15:$AB15,MATCH("Cost Centre",$A$1:$AB$1,0)),"")&"","") | AJ15: =IF(AND(AF15=1,AE15>=set_FYStart,AE15<=set_AsAt),1,0) | AK15: =IF(AND(AJ15=1,AH15<>"",COUNTIFS($AH$2:AH15,AH15,$AJ$2:AJ15,1)=1),N(AL14)+1,"") | AL15: =IF(AK15<>"",AK15,N(AL14))
A16: CON-0005 | B16: Consulting | C16: 26052002 | D16: DTTL | E16: BNE ​L23 Training Rooms Upgrade | F16: 57706 | G16: INV-10425 | H16: 46162 | I16: 57706 | J16: 0 | K16: Agrees | N16: OK | O16: DTTL BNE L23 Training Rooms Upgrade | P16: INTEGRATION | Q16: Project | R16: GST 10% | S16: 42300 | T16: https://cts.qwilr.com/26052002-DeloitteBNE-Proposal-v1-0-Agx8wV5qTcax | U16: Status: In Progress | V16: 5770.6 | W16: 63476.6 | X16: 46173 | Y16: 1 | Z16: 57706 | AA16: 57706 | AB16: 5 | AD16: =IFERROR(N(IFERROR(INDEX($A16:$AB16,MATCH("Xero Invoiced Ex GST",$A$1:$AB$1,0)),"")),0) | AE16: =IFERROR(INDEX($A16:$AB16,MATCH("Xero Invoice Date",$A$1:$AB$1,0)),"") | AF16: =IF(AND(IFERROR(INDEX($A16:$AB16,MATCH("Xero Invoice No",$A$1:$AB$1,0)),"")&""<>"",ISNUMBER(AE16),AD16<>0),1,0) | AG16: =IF(AF16=1,EOMONTH(AE16,0),"") | AH16: =IF(AF16=1,UPPER(TRIM(IFERROR(INDEX($A16:$AB16,MATCH("Client",$A$1:$AB$1,0)),"")&"")),"") | AI16: =IF(AF16=1,IFERROR(INDEX($A16:$AB16,MATCH("Cost Centre",$A$1:$AB$1,0)),"")&"","") | AJ16: =IF(AND(AF16=1,AE16>=set_FYStart,AE16<=set_AsAt),1,0) | AK16: =IF(AND(AJ16=1,AH16<>"",COUNTIFS($AH$2:AH16,AH16,$AJ$2:AJ16,1)=1),N(AL15)+1,"") | AL16: =IF(AK16<>"",AK16,N(AL15))
A17: ONS-0006 | B17: Onsite | C17: 2192 | D17: BW | E17: BW Additionals July 2026 | F17: 1120 | G17: INV-10530 | H17: 46234 | I17: 1120 | J17: 0 | K17: Agrees | N17: OK | O17: Bankwest Additional Tech | P17: ONSITE | Q17: Ad-hoc | R17: GST 10% | S17: 41100 | V17: 112 | W17: 1232 | X17: 46234 | Y17: 2 | Z17: 3200 | AA17: 3200 | AB17: 6 | AD17: =IFERROR(N(IFERROR(INDEX($A17:$AB17,MATCH("Xero Invoiced Ex GST",$A$1:$AB$1,0)),"")),0) | AE17: =IFERROR(INDEX($A17:$AB17,MATCH("Xero Invoice Date",$A$1:$AB$1,0)),"") | AF17: =IF(AND(IFERROR(INDEX($A17:$AB17,MATCH("Xero Invoice No",$A$1:$AB$1,0)),"")&""<>"",ISNUMBER(AE17),AD17<>0),1,0) | AG17: =IF(AF17=1,EOMONTH(AE17,0),"") | AH17: =IF(AF17=1,UPPER(TRIM(IFERROR(INDEX($A17:$AB17,MATCH("Client",$A$1:$AB$1,0)),"")&"")),"") | AI17: =IF(AF17=1,IFERROR(INDEX($A17:$AB17,MATCH("Cost Centre",$A$1:$AB$1,0)),"")&"","") | AJ17: =IF(AND(AF17=1,AE17>=set_FYStart,AE17<=set_AsAt),1,0) | AK17: =IF(AND(AJ17=1,AH17<>"",COUNTIFS($AH$2:AH17,AH17,$AJ$2:AJ17,1)=1),N(AL16)+1,"") | AL17: =IF(AK17<>"",AK17,N(AL16))
A18: PRD-0006 | B18: Production | C18: 2607701 | D18: Litecard | E18: Litecard - Event Photographer - 16.7.26 | F18: 0 | G18: INV-10522 | H18: 46216 | I18: 0 | J18: 0 | K18: Agrees | L18: Job number not in the Xero job list | N18: CHECK | P18: PRODUCTION | Q18: Project | R18: GST 10% | S18: 42100 | T18: 6102 | V18: 0 | W18: 0 | X18: 46234 | Y18: 2 | Z18: 500 | AA18: 500 | AB18: 6 | AD18: =IFERROR(N(IFERROR(INDEX($A18:$AB18,MATCH("Xero Invoiced Ex GST",$A$1:$AB$1,0)),"")),0) | AE18: =IFERROR(INDEX($A18:$AB18,MATCH("Xero Invoice Date",$A$1:$AB$1,0)),"") | AF18: =IF(AND(IFERROR(INDEX($A18:$AB18,MATCH("Xero Invoice No",$A$1:$AB$1,0)),"")&""<>"",ISNUMBER(AE18),AD18<>0),1,0) | AG18: =IF(AF18=1,EOMONTH(AE18,0),"") | AH18: =IF(AF18=1,UPPER(TRIM(IFERROR(INDEX($A18:$AB18,MATCH("Client",$A$1:$AB$1,0)),"")&"")),"") | AI18: =IF(AF18=1,IFERROR(INDEX($A18:$AB18,MATCH("Cost Centre",$A$1:$AB$1,0)),"")&"","") | AJ18: =IF(AND(AF18=1,AE18>=set_FYStart,AE18<=set_AsAt),1,0) | AK18: =IF(AND(AJ18=1,AH18<>"",COUNTIFS($AH$2:AH18,AH18,$AJ$2:AJ18,1)=1),N(AL17)+1,"") | AL18: =IF(AK18<>"",AK18,N(AL17))
A19: CON-0006 | B19: Consulting | C19: 26052003 | D19: DTTL | E19: SYD Mobile Display Supply | F19: 26234 | G19: INV-10426 | H19: 46163 | I19: 26234 | J19: 0 | K19: Agrees | N19: OK | O19: DTTL Mobile Commbox Displays | P19: INTEGRATION | Q19: Project | R19: GST 10% | S19: 42300 | T19: https://cts.qwilr.com/26052003-DTTL-Costing-v1-0-0mJlWQroQJWo | U19: Status: Closed | V19: 2623.4 | W19: 28857.4 | X19: 46173 | Y19: 2 | Z19: 33939 | AA19: 33939 | AB19: 6 | AD19: =IFERROR(N(IFERROR(INDEX($A19:$AB19,MATCH("Xero Invoiced Ex GST",$A$1:$AB$1,0)),"")),0) | AE19: =IFERROR(INDEX($A19:$AB19,MATCH("Xero Invoice Date",$A$1:$AB$1,0)),"") | AF19: =IF(AND(IFERROR(INDEX($A19:$AB19,MATCH("Xero Invoice No",$A$1:$AB$1,0)),"")&""<>"",ISNUMBER(AE19),AD19<>0),1,0) | AG19: =IF(AF19=1,EOMONTH(AE19,0),"") | AH19: =IF(AF19=1,UPPER(TRIM(IFERROR(INDEX($A19:$AB19,MATCH("Client",$A$1:$AB$1,0)),"")&"")),"") | AI19: =IF(AF19=1,IFERROR(INDEX($A19:$AB19,MATCH("Cost Centre",$A$1:$AB$1,0)),"")&"","") | AJ19: =IF(AND(AF19=1,AE19>=set_FYStart,AE19<=set_AsAt),1,0) | AK19: =IF(AND(AJ19=1,AH19<>"",COUNTIFS($AH$2:AH19,AH19,$AJ$2:AJ19,1)=1),N(AL18)+1,"") | AL19: =IF(AK19<>"",AK19,N(AL18))
A20: ONS-0007 | B20: Onsite | C20: 2488 | D20: PWC | E20: PWC Brisbane July 2026 | F20: 7150 | G20: INV-10531 | H20: 46234 | I20: 7150 | J20: 0 | K20: Agrees | N20: OK | O20: PWC IT P/T BNE | P20: ONSITE | Q20: Contract | R20: GST 10% | S20: 41100 | V20: 715 | W20: 7865 | X20: 46234 | Y20: 2 | Z20: 14300 | AA20: 14300 | AB20: 7 | AD20: =IFERROR(N(IFERROR(INDEX($A20:$AB20,MATCH("Xero Invoiced Ex GST",$A$1:$AB$1,0)),"")),0) | AE20: =IFERROR(INDEX($A20:$AB20,MATCH("Xero Invoice Date",$A$1:$AB$1,0)),"") | AF20: =IF(AND(IFERROR(INDEX($A20:$AB20,MATCH("Xero Invoice No",$A$1:$AB$1,0)),"")&""<>"",ISNUMBER(AE20),AD20<>0),1,0) | AG20: =IF(AF20=1,EOMONTH(AE20,0),"") | AH20: =IF(AF20=1,UPPER(TRIM(IFERROR(INDEX($A20:$AB20,MATCH("Client",$A$1:$AB$1,0)),"")&"")),"") | AI20: =IF(AF20=1,IFERROR(INDEX($A20:$AB20,MATCH("Cost Centre",$A$1:$AB$1,0)),"")&"","") | AJ20: =IF(AND(AF20=1,AE20>=set_FYStart,AE20<=set_AsAt),1,0) | AK20: =IF(AND(AJ20=1,AH20<>"",COUNTIFS($AH$2:AH20,AH20,$AJ$2:AJ20,1)=1),N(AL19)+1,"") | AL20: =IF(AK20<>"",AK20,N(AL19))
A21: PRD-0007 | B21: Production | C21: 26052703 | D21: Microsoft | E21: Microsoft Town Hall 21.7.26 | F21: 10885 | G21: INV-10554 | H21: 46234 | I21: 10885 | J21: 0 | K21: Agrees | N21: OK | O21: Microsoft Town Hall - 21.7.26 | P21: PRODUCTION | Q21: Project | R21: GST 10% | S21: 42100 | T21: 6034 | V21: 1088.5 | W21: 11973.5 | X21: 46234 | Y21: 1 | Z21: 10885 | AA21: 10885 | AB21: 7 | AD21: =IFERROR(N(IFERROR(INDEX($A21:$AB21,MATCH("Xero Invoiced Ex GST",$A$1:$AB$1,0)),"")),0) | AE21: =IFERROR(INDEX($A21:$AB21,MATCH("Xero Invoice Date",$A$1:$AB$1,0)),"") | AF21: =IF(AND(IFERROR(INDEX($A21:$AB21,MATCH("Xero Invoice No",$A$1:$AB$1,0)),"")&""<>"",ISNUMBER(AE21),AD21<>0),1,0) | AG21: =IF(AF21=1,EOMONTH(AE21,0),"") | AH21: =IF(AF21=1,UPPER(TRIM(IFERROR(INDEX($A21:$AB21,MATCH("Client",$A$1:$AB$1,0)),"")&"")),"") | AI21: =IF(AF21=1,IFERROR(INDEX($A21:$AB21,MATCH("Cost Centre",$A$1:$AB$1,0)),"")&"","") | AJ21: =IF(AND(AF21=1,AE21>=set_FYStart,AE21<=set_AsAt),1,0) | AK21: =IF(AND(AJ21=1,AH21<>"",COUNTIFS($AH$2:AH21,AH21,$AJ$2:AJ21,1)=1),N(AL20)+1,"") | AL21: =IF(AK21<>"",AK21,N(AL20))
A22: CON-0007 | B22: Consulting | C22: 25102701 | D22: DEWR | E22: DEWR Studio Upgrade | F22: 7563 | G22: INV-10442 | H22: 46171 | I22: 7563 | J22: 0 | K22: Agrees | N22: OK | O22: DEWR - Studio Upgrade - Consulting, Design | P22: CONSULTING | Q22: Progress Claim | R22: GST 10% | S22: 42800 | T22: https://cts.qwilr.com/25102701-DEWR-Studio-Upgrade-ESE25-143997-Rev-4-KTqWXx2QQz6f | U22: Status: In Progress | Progress Claim 04 | V22: 756.3 | W22: 8319.3 | X22: 46173 | Y22: 4 | Z22: 68273 | AA22: 68273 | AB22: 7 | AD22: =IFERROR(N(IFERROR(INDEX($A22:$AB22,MATCH("Xero Invoiced Ex GST",$A$1:$AB$1,0)),"")),0) | AE22: =IFERROR(INDEX($A22:$AB22,MATCH("Xero Invoice Date",$A$1:$AB$1,0)),"") | AF22: =IF(AND(IFERROR(INDEX($A22:$AB22,MATCH("Xero Invoice No",$A$1:$AB$1,0)),"")&""<>"",ISNUMBER(AE22),AD22<>0),1,0) | AG22: =IF(AF22=1,EOMONTH(AE22,0),"") | AH22: =IF(AF22=1,UPPER(TRIM(IFERROR(INDEX($A22:$AB22,MATCH("Client",$A$1:$AB$1,0)),"")&"")),"") | AI22: =IF(AF22=1,IFERROR(INDEX($A22:$AB22,MATCH("Cost Centre",$A$1:$AB$1,0)),"")&"","") | AJ22: =IF(AND(AF22=1,AE22>=set_FYStart,AE22<=set_AsAt),1,0) | AK22: =IF(AND(AJ22=1,AH22<>"",COUNTIFS($AH$2:AH22,AH22,$AJ$2:AJ22,1)=1),N(AL21)+1,"") | AL22: =IF(AK22<>"",AK22,N(AL21))
A23: ONS-0008 | B23: Onsite | C23: 26021602 | D23: Gen-E | E23: Gen-E ABS July 2026 | F23: 12388.8 | G23: INV-10532 | H23: 46234 | I23: 12388.8 | J23: 0 | K23: Agrees | N23: OK | O23: Gen E ABS AV Support (Canberra) | P23: ONSITE | Q23: Contract | R23: GST 10% | S23: 41100 | V23: 1238.88 | W23: 13627.68 | X23: 46234 | Y23: 3 | Z23: 37166.4 | AA23: 37166.4 | AB23: 8 | AD23: =IFERROR(N(IFERROR(INDEX($A23:$AB23,MATCH("Xero Invoiced Ex GST",$A$1:$AB$1,0)),"")),0) | AE23: =IFERROR(INDEX($A23:$AB23,MATCH("Xero Invoice Date",$A$1:$AB$1,0)),"") | AF23: =IF(AND(IFERROR(INDEX($A23:$AB23,MATCH("Xero Invoice No",$A$1:$AB$1,0)),"")&""<>"",ISNUMBER(AE23),AD23<>0),1,0) | AG23: =IF(AF23=1,EOMONTH(AE23,0),"") | AH23: =IF(AF23=1,UPPER(TRIM(IFERROR(INDEX($A23:$AB23,MATCH("Client",$A$1:$AB$1,0)),"")&"")),"") | AI23: =IF(AF23=1,IFERROR(INDEX($A23:$AB23,MATCH("Cost Centre",$A$1:$AB$1,0)),"")&"","") | AJ23: =IF(AND(AF23=1,AE23>=set_FYStart,AE23<=set_AsAt),1,0) | AK23: =IF(AND(AJ23=1,AH23<>"",COUNTIFS($AH$2:AH23,AH23,$AJ$2:AJ23,1)=1),N(AL22)+1,"") | AL23: =IF(AK23<>"",AK23,N(AL22))
A24: PRD-0008 | B24: Production | C24: 26041603 | D24: Optiver | E24: Mid-Year Town Hall 23.7.26 | F24: 745 | G24: INV-10538 | H24: 46232 | I24: 745 | J24: 0 | K24: Agrees | N24: OK | O24: Optiver - Town Hall - 23.7.26 | P24: PRODUCTION | Q24: Project | R24: GST 10% | S24: 42100 | T24: 6085 | V24: 74.5 | W24: 819.5 | X24: 46234 | Y24: 1 | Z24: 745 | AA24: 745 | AB24: 8 | AD24: =IFERROR(N(IFERROR(INDEX($A24:$AB24,MATCH("Xero Invoiced Ex GST",$A$1:$AB$1,0)),"")),0) | AE24: =IFERROR(INDEX($A24:$AB24,MATCH("Xero Invoice Date",$A$1:$AB$1,0)),"") | AF24: =IF(AND(IFERROR(INDEX($A24:$AB24,MATCH("Xero Invoice No",$A$1:$AB$1,0)),"")&""<>"",ISNUMBER(AE24),AD24<>0),1,0) | AG24: =IF(AF24=1,EOMONTH(AE24,0),"") | AH24: =IF(AF24=1,UPPER(TRIM(IFERROR(INDEX($A24:$AB24,MATCH("Client",$A$1:$AB$1,0)),"")&"")),"") | AI24: =IF(AF24=1,IFERROR(INDEX($A24:$AB24,MATCH("Cost Centre",$A$1:$AB$1,0)),"")&"","") | AJ24: =IF(AND(AF24=1,AE24>=set_FYStart,AE24<=set_AsAt),1,0) | AK24: =IF(AND(AJ24=1,AH24<>"",COUNTIFS($AH$2:AH24,AH24,$AJ$2:AJ24,1)=1),N(AL23)+1,"") | AL24: =IF(AK24<>"",AK24,N(AL23))
A25: CON-0008 | B25: Consulting | C25: 26051801 | D25: PwC | E25: Mel Studio Equipment | F25: 12039 | G25: INV-10462 | H25: 46190 | I25: 12039 | J25: 0 | K25: Agrees | N25: OK | O25: PwC | Mel Studio Equipment | P25: INTEGRATION | Q25: Project | R25: GST 10% | S25: 42300 | T25: https://cts.qwilr.com/26051801-PwC-Costing-v3-0-HUL2JaYQCO39 | U25: Status: Completed | V25: 1203.9 | W25: 13242.9 | X25: 46203 | Y25: 1 | Z25: 12039 | AA25: 12039 | AB25: 8 | AD25: =IFERROR(N(IFERROR(INDEX($A25:$AB25,MATCH("Xero Invoiced Ex GST",$A$1:$AB$1,0)),"")),0) | AE25: =IFERROR(INDEX($A25:$AB25,MATCH("Xero Invoice Date",$A$1:$AB$1,0)),"") | AF25: =IF(AND(IFERROR(INDEX($A25:$AB25,MATCH("Xero Invoice No",$A$1:$AB$1,0)),"")&""<>"",ISNUMBER(AE25),AD25<>0),1,0) | AG25: =IF(AF25=1,EOMONTH(AE25,0),"") | AH25: =IF(AF25=1,UPPER(TRIM(IFERROR(INDEX($A25:$AB25,MATCH("Client",$A$1:$AB$1,0)),"")&"")),"") | AI25: =IF(AF25=1,IFERROR(INDEX($A25:$AB25,MATCH("Cost Centre",$A$1:$AB$1,0)),"")&"","") | AJ25: =IF(AND(AF25=1,AE25>=set_FYStart,AE25<=set_AsAt),1,0) | AK25: =IF(AND(AJ25=1,AH25<>"",COUNTIFS($AH$2:AH25,AH25,$AJ$2:AJ25,1)=1),N(AL24)+1,"") | AL25: =IF(AK25<>"",AK25,N(AL24))
A26: ONS-0009 | B26: Onsite | C26: 26043001 | D26: CBA | E26: CBA Mel July 2026 | F26: 11377.12 | G26: INV-10534 | H26: 46234 | I26: 11377.12 | J26: 0 | K26: Agrees | N26: OK | O26: CBA FT Tech MEL - 12 months | P26: ONSITE | Q26: Contract | R26: GST 10% | S26: 41100 | U26: Deduct 8hrs CN for 03/07 | V26: 1137.71 | W26: 12514.83 | X26: 46234 | Y26: 3 | Z26: 35297.12 | AA26: 35297.12 | AB26: 9 | AD26: =IFERROR(N(IFERROR(INDEX($A26:$AB26,MATCH("Xero Invoiced Ex GST",$A$1:$AB$1,0)),"")),0) | AE26: =IFERROR(INDEX($A26:$AB26,MATCH("Xero Invoice Date",$A$1:$AB$1,0)),"") | AF26: =IF(AND(IFERROR(INDEX($A26:$AB26,MATCH("Xero Invoice No",$A$1:$AB$1,0)),"")&""<>"",ISNUMBER(AE26),AD26<>0),1,0) | AG26: =IF(AF26=1,EOMONTH(AE26,0),"") | AH26: =IF(AF26=1,UPPER(TRIM(IFERROR(INDEX($A26:$AB26,MATCH("Client",$A$1:$AB$1,0)),"")&"")),"") | AI26: =IF(AF26=1,IFERROR(INDEX($A26:$AB26,MATCH("Cost Centre",$A$1:$AB$1,0)),"")&"","") | AJ26: =IF(AND(AF26=1,AE26>=set_FYStart,AE26<=set_AsAt),1,0) | AK26: =IF(AND(AJ26=1,AH26<>"",COUNTIFS($AH$2:AH26,AH26,$AJ$2:AJ26,1)=1),N(AL25)+1,"") | AL26: =IF(AK26<>"",AK26,N(AL25))
A27: PRD-0009 | B27: Production | C27: 2605403 | D27: Arup | E27: Oves Awards Night 23.7.26 | F27: 5460 | G27: INV-10540 | H27: 46233 | I27: 5460 | J27: 0 | K27: Agrees | N27: OK | O27: ARUP - Oves Awards - 23.7.26 | P27: PRODUCTION | Q27: Project | R27: GST 10% | S27: 42100 | T27: 5956 | V27: 546 | W27: 6006 | X27: 46234 | Y27: 1 | Z27: 5460 | AA27: 5460 | AB27: 9 | AD27: =IFERROR(N(IFERROR(INDEX($A27:$AB27,MATCH("Xero Invoiced Ex GST",$A$1:$AB$1,0)),"")),0) | AE27: =IFERROR(INDEX($A27:$AB27,MATCH("Xero Invoice Date",$A$1:$AB$1,0)),"") | AF27: =IF(AND(IFERROR(INDEX($A27:$AB27,MATCH("Xero Invoice No",$A$1:$AB$1,0)),"")&""<>"",ISNUMBER(AE27),AD27<>0),1,0) | AG27: =IF(AF27=1,EOMONTH(AE27,0),"") | AH27: =IF(AF27=1,UPPER(TRIM(IFERROR(INDEX($A27:$AB27,MATCH("Client",$A$1:$AB$1,0)),"")&"")),"") | AI27: =IF(AF27=1,IFERROR(INDEX($A27:$AB27,MATCH("Cost Centre",$A$1:$AB$1,0)),"")&"","") | AJ27: =IF(AND(AF27=1,AE27>=set_FYStart,AE27<=set_AsAt),1,0) | AK27: =IF(AND(AJ27=1,AH27<>"",COUNTIFS($AH$2:AH27,AH27,$AJ$2:AJ27,1)=1),N(AL26)+1,"") | AL27: =IF(AK27<>"",AK27,N(AL26))
A28: CON-0009 | B28: Consulting | C28: 26043003 | D28: PwC | E28: Screen Replacements (SYD/MEL) | F28: 96068 | G28: INV-10461 | H28: 46190 | I28: 96068 | J28: 0 | K28: Agrees | N28: OK | O28: PwC Screen Replacements SYD+MEL | P28: INTEGRATION | Q28: Project | R28: GST 10% | S28: 42300 | T28: https://cts.qwilr.com/26043003-PwC-Costing-v1-0-LoPgcYilSIWh | U28: Status: Closed | V28: 9606.8 | W28: 105674.8 | X28: 46203 | Y28: 1 | Z28: 96068 | AA28: 96068 | AB28: 9 | AD28: =IFERROR(N(IFERROR(INDEX($A28:$AB28,MATCH("Xero Invoiced Ex GST",$A$1:$AB$1,0)),"")),0) | AE28: =IFERROR(INDEX($A28:$AB28,MATCH("Xero Invoice Date",$A$1:$AB$1,0)),"") | AF28: =IF(AND(IFERROR(INDEX($A28:$AB28,MATCH("Xero Invoice No",$A$1:$AB$1,0)),"")&""<>"",ISNUMBER(AE28),AD28<>0),1,0) | AG28: =IF(AF28=1,EOMONTH(AE28,0),"") | AH28: =IF(AF28=1,UPPER(TRIM(IFERROR(INDEX($A28:$AB28,MATCH("Client",$A$1:$AB$1,0)),"")&"")),"") | AI28: =IF(AF28=1,IFERROR(INDEX($A28:$AB28,MATCH("Cost Centre",$A$1:$AB$1,0)),"")&"","") | AJ28: =IF(AND(AF28=1,AE28>=set_FYStart,AE28<=set_AsAt),1,0) | AK28: =IF(AND(AJ28=1,AH28<>"",COUNTIFS($AH$2:AH28,AH28,$AJ$2:AJ28,1)=1),N(AL27)+1,"") | AL28: =IF(AK28<>"",AK28,N(AL27))
A29: ONS-0010 | B29: Onsite | C29: 25101301B | D29: PWC | E29: PWC Sydney IT July 2026 | F29: 11907 | G29: INV-10535 | H29: 46234 | I29: 11907 | J29: 0 | K29: Agrees | N29: OK | O29: PWC IT Support – Sydney | P29: ONSITE | Q29: Contract | R29: GST 10% | S29: 41100 | V29: 1190.7 | W29: 13097.7 | X29: 46234 | Y29: 2 | Z29: 23814 | AA29: 23814 | AB29: 10 | AD29: =IFERROR(N(IFERROR(INDEX($A29:$AB29,MATCH("Xero Invoiced Ex GST",$A$1:$AB$1,0)),"")),0) | AE29: =IFERROR(INDEX($A29:$AB29,MATCH("Xero Invoice Date",$A$1:$AB$1,0)),"") | AF29: =IF(AND(IFERROR(INDEX($A29:$AB29,MATCH("Xero Invoice No",$A$1:$AB$1,0)),"")&""<>"",ISNUMBER(AE29),AD29<>0),1,0) | AG29: =IF(AF29=1,EOMONTH(AE29,0),"") | AH29: =IF(AF29=1,UPPER(TRIM(IFERROR(INDEX($A29:$AB29,MATCH("Client",$A$1:$AB$1,0)),"")&"")),"") | AI29: =IF(AF29=1,IFERROR(INDEX($A29:$AB29,MATCH("Cost Centre",$A$1:$AB$1,0)),"")&"","") | AJ29: =IF(AND(AF29=1,AE29>=set_FYStart,AE29<=set_AsAt),1,0) | AK29: =IF(AND(AJ29=1,AH29<>"",COUNTIFS($AH$2:AH29,AH29,$AJ$2:AJ29,1)=1),N(AL28)+1,"") | AL29: =IF(AK29<>"",AK29,N(AL28))
A30: PRD-0010 | B30: Production | C30: 2607901 | D30: On24 | E30: KWM Event 23.7.26 (PO #25962) | F30: 2575 | G30: INV-10552 | H30: 46234 | I30: 2575 | J30: 0 | K30: Agrees | L30: Job number not in the Xero job list | N30: CHECK | P30: PRODUCTION | Q30: Project | R30: GST 10% | S30: 42100 | T30: 6097 | V30: 257.5 | W30: 2832.5 | X30: 46234 | Y30: 1 | Z30: 2575 | AA30: 2575 | AB30: 10 | AD30: =IFERROR(N(IFERROR(INDEX($A30:$AB30,MATCH("Xero Invoiced Ex GST",$A$1:$AB$1,0)),"")),0) | AE30: =IFERROR(INDEX($A30:$AB30,MATCH("Xero Invoice Date",$A$1:$AB$1,0)),"") | AF30: =IF(AND(IFERROR(INDEX($A30:$AB30,MATCH("Xero Invoice No",$A$1:$AB$1,0)),"")&""<>"",ISNUMBER(AE30),AD30<>0),1,0) | AG30: =IF(AF30=1,EOMONTH(AE30,0),"") | AH30: =IF(AF30=1,UPPER(TRIM(IFERROR(INDEX($A30:$AB30,MATCH("Client",$A$1:$AB$1,0)),"")&"")),"") | AI30: =IF(AF30=1,IFERROR(INDEX($A30:$AB30,MATCH("Cost Centre",$A$1:$AB$1,0)),"")&"","") | AJ30: =IF(AND(AF30=1,AE30>=set_FYStart,AE30<=set_AsAt),1,0) | AK30: =IF(AND(AJ30=1,AH30<>"",COUNTIFS($AH$2:AH30,AH30,$AJ$2:AJ30,1)=1),N(AL29)+1,"") | AL30: =IF(AK30<>"",AK30,N(AL29))
A31: CON-0010 | B31: Consulting | C31: 2606901 | D31: PwC | E31: Sydney Office box drop | F31: 561 | G31: INV-10500 | H31: 46198 | I31: 561 | J31: 0 | K31: Agrees | N31: OK | O31: PwC | Syd Studio Equipment | P31: INTEGRATION | Q31: Project | R31: GST 10% | S31: 42300 | T31: https://app.qwilr.com/#/page-view/6a336995d5bfec1e1c7a08ed | U31: Status: Closed | V31: 56.1 | W31: 617.1 | X31: 46203 | Y31: 1 | Z31: 561 | AA31: 561 | AB31: 10 | AD31: =IFERROR(N(IFERROR(INDEX($A31:$AB31,MATCH("Xero Invoiced Ex GST",$A$1:$AB$1,0)),"")),0) | AE31: =IFERROR(INDEX($A31:$AB31,MATCH("Xero Invoice Date",$A$1:$AB$1,0)),"") | AF31: =IF(AND(IFERROR(INDEX($A31:$AB31,MATCH("Xero Invoice No",$A$1:$AB$1,0)),"")&""<>"",ISNUMBER(AE31),AD31<>0),1,0) | AG31: =IF(AF31=1,EOMONTH(AE31,0),"") | AH31: =IF(AF31=1,UPPER(TRIM(IFERROR(INDEX($A31:$AB31,MATCH("Client",$A$1:$AB$1,0)),"")&"")),"") | AI31: =IF(AF31=1,IFERROR(INDEX($A31:$AB31,MATCH("Cost Centre",$A$1:$AB$1,0)),"")&"","") | AJ31: =IF(AND(AF31=1,AE31>=set_FYStart,AE31<=set_AsAt),1,0) | AK31: =IF(AND(AJ31=1,AH31<>"",COUNTIFS($AH$2:AH31,AH31,$AJ$2:AJ31,1)=1),N(AL30)+1,"") | AL31: =IF(AK31<>"",AK31,N(AL30))
A32: ONS-0011 | B32: Onsite | C32: 2880 | D32: RICOH | E32: Ricoh Contract July 2026 | F32: 11860.5 | G32: INV-10536 | H32: 46234 | I32: 11860.56 | J32: -0.06 | K32: Xero higher - check dept | M32: Xero check 28-Sep-26: Xero INV-10536 is $11,860.56 ex GST | N32: OK | O32: Ricoh - QANTAS | P32: ONSITE | Q32: Contract | R32: GST 10% | S32: 41100 | U32: 2 months extension | V32: 1186.06 | W32: 13046.62 | X32: 46234 | Y32: 2 | Z32: 23721.06 | AA32: 23721.12 | AB32: 11 | AD32: =IFERROR(N(IFERROR(INDEX($A32:$AB32,MATCH("Xero Invoiced Ex GST",$A$1:$AB$1,0)),"")),0) | AE32: =IFERROR(INDEX($A32:$AB32,MATCH("Xero Invoice Date",$A$1:$AB$1,0)),"") | AF32: =IF(AND(IFERROR(INDEX($A32:$AB32,MATCH("Xero Invoice No",$A$1:$AB$1,0)),"")&""<>"",ISNUMBER(AE32),AD32<>0),1,0) | AG32: =IF(AF32=1,EOMONTH(AE32,0),"") | AH32: =IF(AF32=1,UPPER(TRIM(IFERROR(INDEX($A32:$AB32,MATCH("Client",$A$1:$AB$1,0)),"")&"")),"") | AI32: =IF(AF32=1,IFERROR(INDEX($A32:$AB32,MATCH("Cost Centre",$A$1:$AB$1,0)),"")&"","") | AJ32: =IF(AND(AF32=1,AE32>=set_FYStart,AE32<=set_AsAt),1,0) | AK32: =IF(AND(AJ32=1,AH32<>"",COUNTIFS($AH$2:AH32,AH32,$AJ$2:AJ32,1)=1),N(AL31)+1,"") | AL32: =IF(AK32<>"",AK32,N(AL31))
A33: PRD-0011 | B33: Production | C33: 26063001 | D33: Skykick Ranger | E33: Sydney Performance Dry Hire 26.7.26 | F33: 975 | G33: INV-10533 | H33: 46223 | I33: 975 | J33: 0 | K33: Agrees | L33: Job number not in the Xero job list | N33: CHECK | P33: PRODUCTION | Q33: Project | R33: GST 10% | S33: 42100 | T33: 6114 | V33: 97.5 | W33: 1072.5 | X33: 46234 | Y33: 1 | Z33: 975 | AA33: 975 | AB33: 11 | AD33: =IFERROR(N(IFERROR(INDEX($A33:$AB33,MATCH("Xero Invoiced Ex GST",$A$1:$AB$1,0)),"")),0) | AE33: =IFERROR(INDEX($A33:$AB33,MATCH("Xero Invoice Date",$A$1:$AB$1,0)),"") | AF33: =IF(AND(IFERROR(INDEX($A33:$AB33,MATCH("Xero Invoice No",$A$1:$AB$1,0)),"")&""<>"",ISNUMBER(AE33),AD33<>0),1,0) | AG33: =IF(AF33=1,EOMONTH(AE33,0),"") | AH33: =IF(AF33=1,UPPER(TRIM(IFERROR(INDEX($A33:$AB33,MATCH("Client",$A$1:$AB$1,0)),"")&"")),"") | AI33: =IF(AF33=1,IFERROR(INDEX($A33:$AB33,MATCH("Cost Centre",$A$1:$AB$1,0)),"")&"","") | AJ33: =IF(AND(AF33=1,AE33>=set_FYStart,AE33<=set_AsAt),1,0) | AK33: =IF(AND(AJ33=1,AH33<>"",COUNTIFS($AH$2:AH33,AH33,$AJ$2:AJ33,1)=1),N(AL32)+1,"") | AL33: =IF(AK33<>"",AK33,N(AL32))
A34: CON-0011 | B34: Consulting | C34: 2602203 | D34: YSG Studio | E34: Orange Room Upgrade CONS | F34: 2247.5 | G34: INV-10499 | H34: 46198 | I34: 2247.5 | J34: 0 | K34: Agrees | N34: OK | O34: YSG Studio Orange Room Upgrade | P34: CONSULTING | Q34: Progress Claim | R34: GST 10% | S34: 42800 | T34: https://cts.qwilr.com/2602203-YSGStudio-Proposal-A-Yw8447MlTUK7 | U34: Status: In Progress | Progress Claim 03 | V34: 224.75 | W34: 2472.25 | X34: 46203 | Y34: 2 | Z34: 3262.5 | AA34: 3262.5 | AB34: 11 | AD34: =IFERROR(N(IFERROR(INDEX($A34:$AB34,MATCH("Xero Invoiced Ex GST",$A$1:$AB$1,0)),"")),0) | AE34: =IFERROR(INDEX($A34:$AB34,MATCH("Xero Invoice Date",$A$1:$AB$1,0)),"") | AF34: =IF(AND(IFERROR(INDEX($A34:$AB34,MATCH("Xero Invoice No",$A$1:$AB$1,0)),"")&""<>"",ISNUMBER(AE34),AD34<>0),1,0) | AG34: =IF(AF34=1,EOMONTH(AE34,0),"") | AH34: =IF(AF34=1,UPPER(TRIM(IFERROR(INDEX($A34:$AB34,MATCH("Client",$A$1:$AB$1,0)),"")&"")),"") | AI34: =IF(AF34=1,IFERROR(INDEX($A34:$AB34,MATCH("Cost Centre",$A$1:$AB$1,0)),"")&"","") | AJ34: =IF(AND(AF34=1,AE34>=set_FYStart,AE34<=set_AsAt),1,0) | AK34: =IF(AND(AJ34=1,AH34<>"",COUNTIFS($AH$2:AH34,AH34,$AJ$2:AJ34,1)=1),N(AL33)+1,"") | AL34: =IF(AK34<>"",AK34,N(AL33))
A35: ONS-0012 | B35: Onsite | D35: PWC | E35: PWC Dedicated Tech 29/07/2026 | F35: 340 | G35: INV-10537 | H35: 46233 | I35: 340 | J35: 0 | K35: Invoice on empty job row | L35: Invoice entered but the department row has no job number | P35: ONSITE | Q35: Ad-hoc | R35: GST 10% | S35: 41100 | U35: 29/07/2026 4hours | V35: 34 | W35: 374 | X35: 46234 | AB35: 12 | AD35: =IFERROR(N(IFERROR(INDEX($A35:$AB35,MATCH("Xero Invoiced Ex GST",$A$1:$AB$1,0)),"")),0) | AE35: =IFERROR(INDEX($A35:$AB35,MATCH("Xero Invoice Date",$A$1:$AB$1,0)),"") | AF35: =IF(AND(IFERROR(INDEX($A35:$AB35,MATCH("Xero Invoice No",$A$1:$AB$1,0)),"")&""<>"",ISNUMBER(AE35),AD35<>0),1,0) | AG35: =IF(AF35=1,EOMONTH(AE35,0),"") | AH35: =IF(AF35=1,UPPER(TRIM(IFERROR(INDEX($A35:$AB35,MATCH("Client",$A$1:$AB$1,0)),"")&"")),"") | AI35: =IF(AF35=1,IFERROR(INDEX($A35:$AB35,MATCH("Cost Centre",$A$1:$AB$1,0)),"")&"","") | AJ35: =IF(AND(AF35=1,AE35>=set_FYStart,AE35<=set_AsAt),1,0) | AK35: =IF(AND(AJ35=1,AH35<>"",COUNTIFS($AH$2:AH35,AH35,$AJ$2:AJ35,1)=1),N(AL34)+1,"") | AL35: =IF(AK35<>"",AK35,N(AL34))
A36: PRD-0012 | B36: Production | C36: 2604202 | D36: Ventia | E36: Ventia Awards 28 & 30.7.26 (PO 4701355678) | F36: 52749.78 | G36: INV-10557 | H36: 46234 | I36: 52749.78 | J36: 0 | K36: Agrees | N36: OK | O36: Ventia - Ventia Awards - 30.7.26 | P36: PRODUCTION | Q36: Project | R36: GST 10% | S36: 42100 | T36: 6099 | V36: 5274.98 | W36: 58024.76 | X36: 46234 | Y36: 1 | Z36: 52749.78 | AA36: 52749.78 | AB36: 12 | AD36: =IFERROR(N(IFERROR(INDEX($A36:$AB36,MATCH("Xero Invoiced Ex GST",$A$1:$AB$1,0)),"")),0) | AE36: =IFERROR(INDEX($A36:$AB36,MATCH("Xero Invoice Date",$A$1:$AB$1,0)),"") | AF36: =IF(AND(IFERROR(INDEX($A36:$AB36,MATCH("Xero Invoice No",$A$1:$AB$1,0)),"")&""<>"",ISNUMBER(AE36),AD36<>0),1,0) | AG36: =IF(AF36=1,EOMONTH(AE36,0),"") | AH36: =IF(AF36=1,UPPER(TRIM(IFERROR(INDEX($A36:$AB36,MATCH("Client",$A$1:$AB$1,0)),"")&"")),"") | AI36: =IF(AF36=1,IFERROR(INDEX($A36:$AB36,MATCH("Cost Centre",$A$1:$AB$1,0)),"")&"","") | AJ36: =IF(AND(AF36=1,AE36>=set_FYStart,AE36<=set_AsAt),1,0) | AK36: =IF(AND(AJ36=1,AH36<>"",COUNTIFS($AH$2:AH36,AH36,$AJ$2:AJ36,1)=1),N(AL35)+1,"") | AL36: =IF(AK36<>"",AK36,N(AL35))
A37: CON-0012 | B37: Consulting | C37: 25111203 | D37: CoS | E37: Barco E3 Sale | F37: 159150 | G37: INV-10510 | H37: 46203 | I37: 159150 | J37: 0 | K37: Agrees | N37: OK | O37: CoS | Barco E3 Sale | P37: INTEGRATION | Q37: Project | R37: GST 10% | S37: 42300 | T37: https://cts.qwilr.com/25111203-CoS-Proposal-v3-0-SyP1MwQ2TcKi | U37: Status: Closed | V37: 15915 | W37: 175065 | X37: 46203 | Y37: 1 | Z37: 159150 | AA37: 159150 | AB37: 12 | AD37: =IFERROR(N(IFERROR(INDEX($A37:$AB37,MATCH("Xero Invoiced Ex GST",$A$1:$AB$1,0)),"")),0) | AE37: =IFERROR(INDEX($A37:$AB37,MATCH("Xero Invoice Date",$A$1:$AB$1,0)),"") | AF37: =IF(AND(IFERROR(INDEX($A37:$AB37,MATCH("Xero Invoice No",$A$1:$AB$1,0)),"")&""<>"",ISNUMBER(AE37),AD37<>0),1,0) | AG37: =IF(AF37=1,EOMONTH(AE37,0),"") | AH37: =IF(AF37=1,UPPER(TRIM(IFERROR(INDEX($A37:$AB37,MATCH("Client",$A$1:$AB$1,0)),"")&"")),"") | AI37: =IF(AF37=1,IFERROR(INDEX($A37:$AB37,MATCH("Cost Centre",$A$1:$AB$1,0)),"")&"","") | AJ37: =IF(AND(AF37=1,AE37>=set_FYStart,AE37<=set_AsAt),1,0) | AK37: =IF(AND(AJ37=1,AH37<>"",COUNTIFS($AH$2:AH37,AH37,$AJ$2:AJ37,1)=1),N(AL36)+1,"") | AL37: =IF(AK37<>"",AK37,N(AL36))
A38: ONS-0013 | B38: Onsite | C38: 3056 | D38: APN | E38: APN Tech Support July 22 & 24 | F38: 680 | G38: INV-10541 | H38: 46233 | I38: 680 | J38: 0 | K38: Agrees | N38: OK | O38: AusPayNet Onsite [Chargeable] | P38: ONSITE | Q38: Ad-hoc | R38: GST 10% | S38: 41100 | V38: 68 | W38: 748 | X38: 46234 | Y38: 1 | Z38: 680 | AA38: 680 | AB38: 13 | AD38: =IFERROR(N(IFERROR(INDEX($A38:$AB38,MATCH("Xero Invoiced Ex GST",$A$1:$AB$1,0)),"")),0) | AE38: =IFERROR(INDEX($A38:$AB38,MATCH("Xero Invoice Date",$A$1:$AB$1,0)),"") | AF38: =IF(AND(IFERROR(INDEX($A38:$AB38,MATCH("Xero Invoice No",$A$1:$AB$1,0)),"")&""<>"",ISNUMBER(AE38),AD38<>0),1,0) | AG38: =IF(AF38=1,EOMONTH(AE38,0),"") | AH38: =IF(AF38=1,UPPER(TRIM(IFERROR(INDEX($A38:$AB38,MATCH("Client",$A$1:$AB$1,0)),"")&"")),"") | AI38: =IF(AF38=1,IFERROR(INDEX($A38:$AB38,MATCH("Cost Centre",$A$1:$AB$1,0)),"")&"","") | AJ38: =IF(AND(AF38=1,AE38>=set_FYStart,AE38<=set_AsAt),1,0) | AK38: =IF(AND(AJ38=1,AH38<>"",COUNTIFS($AH$2:AH38,AH38,$AJ$2:AJ38,1)=1),N(AL37)+1,"") | AL38: =IF(AK38<>"",AK38,N(AL37))
A39: PRD-0013 | B39: Production | C39: 26062202 | D39: PWC | E39: Early Careers Webcast 29.7.26 | F39: 1925 | G39: INV-10555 | H39: 46234 | I39: 1925 | J39: 0 | K39: Agrees | N39: OK | O39: PWC - Early Careers Webcast - 29.7.26 | P39: PRODUCTION | Q39: Project | R39: GST 10% | S39: 42100 | T39: 6075 | V39: 192.5 | W39: 2117.5 | X39: 46234 | Y39: 1 | Z39: 1925 | AA39: 1925 | AB39: 13 | AD39: =IFERROR(N(IFERROR(INDEX($A39:$AB39,MATCH("Xero Invoiced Ex GST",$A$1:$AB$1,0)),"")),0) | AE39: =IFERROR(INDEX($A39:$AB39,MATCH("Xero Invoice Date",$A$1:$AB$1,0)),"") | AF39: =IF(AND(IFERROR(INDEX($A39:$AB39,MATCH("Xero Invoice No",$A$1:$AB$1,0)),"")&""<>"",ISNUMBER(AE39),AD39<>0),1,0) | AG39: =IF(AF39=1,EOMONTH(AE39,0),"") | AH39: =IF(AF39=1,UPPER(TRIM(IFERROR(INDEX($A39:$AB39,MATCH("Client",$A$1:$AB$1,0)),"")&"")),"") | AI39: =IF(AF39=1,IFERROR(INDEX($A39:$AB39,MATCH("Cost Centre",$A$1:$AB$1,0)),"")&"","") | AJ39: =IF(AND(AF39=1,AE39>=set_FYStart,AE39<=set_AsAt),1,0) | AK39: =IF(AND(AJ39=1,AH39<>"",COUNTIFS($AH$2:AH39,AH39,$AJ$2:AJ39,1)=1),N(AL38)+1,"") | AL39: =IF(AK39<>"",AK39,N(AL38))
A40: CON-0013 | B40: Consulting | C40: 26033003 | D40: DTTL | E40: 8PSQ-Dream-Big-Microphones | F40: 27408 | G40: INV-10355 | H40: 46203 | I40: 27408 | J40: 0 | K40: Agrees | N40: OK | O40: DTTL 8PSQ Dream Big Microphones | P40: INTEGRATION | Q40: Project | R40: GST 10% | S40: 42300 | T40: 26033003-Deloitte-8PSQ-Dream-Big-Microphones-v1-0-E9jd4w9T62Y1 | U40: Status: Closed | Invoiced in DTTL Additionals | V40: 2740.8 | W40: 30148.8 | X40: 46203 | Y40: 1 | Z40: 27408 | AA40: 27408 | AB40: 13 | AD40: =IFERROR(N(IFERROR(INDEX($A40:$AB40,MATCH("Xero Invoiced Ex GST",$A$1:$AB$1,0)),"")),0) | AE40: =IFERROR(INDEX($A40:$AB40,MATCH("Xero Invoice Date",$A$1:$AB$1,0)),"") | AF40: =IF(AND(IFERROR(INDEX($A40:$AB40,MATCH("Xero Invoice No",$A$1:$AB$1,0)),"")&""<>"",ISNUMBER(AE40),AD40<>0),1,0) | AG40: =IF(AF40=1,EOMONTH(AE40,0),"") | AH40: =IF(AF40=1,UPPER(TRIM(IFERROR(INDEX($A40:$AB40,MATCH("Client",$A$1:$AB$1,0)),"")&"")),"") | AI40: =IF(AF40=1,IFERROR(INDEX($A40:$AB40,MATCH("Cost Centre",$A$1:$AB$1,0)),"")&"","") | AJ40: =IF(AND(AF40=1,AE40>=set_FYStart,AE40<=set_AsAt),1,0) | AK40: =IF(AND(AJ40=1,AH40<>"",COUNTIFS($AH$2:AH40,AH40,$AJ$2:AJ40,1)=1),N(AL39)+1,"") | AL40: =IF(AK40<>"",AK40,N(AL39))
A41: ONS-0014 | B41: Onsite | C41: 20250731 | D41: PWC | E41: PWC Pool of Hours (50 hours) | F41: 4250 | G41: INV-10539 | H41: 46233 | I41: 4250 | J41: 0 | K41: Agrees | N41: OK | O41: PWC National Pool of Hours | P41: ONSITE | Q41: Ad-hoc | R41: GST 10% | S41: 41100 | U41: PO2601703215 | V41: 425 | W41: 4675 | X41: 46234 | Y41: 1 | Z41: 4250 | AA41: 4250 | AB41: 14 | AD41: =IFERROR(N(IFERROR(INDEX($A41:$AB41,MATCH("Xero Invoiced Ex GST",$A$1:$AB$1,0)),"")),0) | AE41: =IFERROR(INDEX($A41:$AB41,MATCH("Xero Invoice Date",$A$1:$AB$1,0)),"") | AF41: =IF(AND(IFERROR(INDEX($A41:$AB41,MATCH("Xero Invoice No",$A$1:$AB$1,0)),"")&""<>"",ISNUMBER(AE41),AD41<>0),1,0) | AG41: =IF(AF41=1,EOMONTH(AE41,0),"") | AH41: =IF(AF41=1,UPPER(TRIM(IFERROR(INDEX($A41:$AB41,MATCH("Client",$A$1:$AB$1,0)),"")&"")),"") | AI41: =IF(AF41=1,IFERROR(INDEX($A41:$AB41,MATCH("Cost Centre",$A$1:$AB$1,0)),"")&"","") | AJ41: =IF(AND(AF41=1,AE41>=set_FYStart,AE41<=set_AsAt),1,0) | AK41: =IF(AND(AJ41=1,AH41<>"",COUNTIFS($AH$2:AH41,AH41,$AJ$2:AJ41,1)=1),N(AL40)+1,"") | AL41: =IF(AK41<>"",AK41,N(AL40))
A42: PRD-0014 | B42: Production | C42: 26071303 | D42: Ventia (Melbourne) | E42: Melbourne Office Event 30&31.7.26 | F42: 11570 | G42: INV-10558 | H42: 46234 | I42: 11570 | J42: 0 | K42: Agrees | N42: OK | O42: Ventia - Melbourne Office Event - 30.7.26 | P42: PRODUCTION | Q42: Project | R42: GST 10% | S42: 42100 | T42: 6125 | V42: 1157 | W42: 12727 | X42: 46234 | Y42: 1 | Z42: 11570 | AA42: 11570 | AB42: 14 | AD42: =IFERROR(N(IFERROR(INDEX($A42:$AB42,MATCH("Xero Invoiced Ex GST",$A$1:$AB$1,0)),"")),0) | AE42: =IFERROR(INDEX($A42:$AB42,MATCH("Xero Invoice Date",$A$1:$AB$1,0)),"") | AF42: =IF(AND(IFERROR(INDEX($A42:$AB42,MATCH("Xero Invoice No",$A$1:$AB$1,0)),"")&""<>"",ISNUMBER(AE42),AD42<>0),1,0) | AG42: =IF(AF42=1,EOMONTH(AE42,0),"") | AH42: =IF(AF42=1,UPPER(TRIM(IFERROR(INDEX($A42:$AB42,MATCH("Client",$A$1:$AB$1,0)),"")&"")),"") | AI42: =IF(AF42=1,IFERROR(INDEX($A42:$AB42,MATCH("Cost Centre",$A$1:$AB$1,0)),"")&"","") | AJ42: =IF(AND(AF42=1,AE42>=set_FYStart,AE42<=set_AsAt),1,0) | AK42: =IF(AND(AJ42=1,AH42<>"",COUNTIFS($AH$2:AH42,AH42,$AJ$2:AJ42,1)=1),N(AL41)+1,"") | AL42: =IF(AK42<>"",AK42,N(AL41))
A43: CON-0014 | B43: Consulting | C43: 26033005 | D43: DTTL | E43: QQT & 8PSQ_Crestron Connect Adaptor | F43: 20128 | G43: INV-10355 | H43: 46203 | I43: 20128 | J43: 0 | K43: Agrees | N43: OK | O43: DTTL QQT & 8PSQ Crestron Connect Adaptor | P43: INTEGRATION | Q43: Project | R43: GST 10% | S43: 42300 | T43: 26033005_Deloitte QQT & 8PSQ_Crestron Connect Adaptor_v1.0 | U43: Status: In Progress | V43: 2012.8 | W43: 22140.8 | X43: 46203 | Y43: 1 | Z43: 20128 | AA43: 20128 | AB43: 14 | AD43: =IFERROR(N(IFERROR(INDEX($A43:$AB43,MATCH("Xero Invoiced Ex GST",$A$1:$AB$1,0)),"")),0) | AE43: =IFERROR(INDEX($A43:$AB43,MATCH("Xero Invoice Date",$A$1:$AB$1,0)),"") | AF43: =IF(AND(IFERROR(INDEX($A43:$AB43,MATCH("Xero Invoice No",$A$1:$AB$1,0)),"")&""<>"",ISNUMBER(AE43),AD43<>0),1,0) | AG43: =IF(AF43=1,EOMONTH(AE43,0),"") | AH43: =IF(AF43=1,UPPER(TRIM(IFERROR(INDEX($A43:$AB43,MATCH("Client",$A$1:$AB$1,0)),"")&"")),"") | AI43: =IF(AF43=1,IFERROR(INDEX($A43:$AB43,MATCH("Cost Centre",$A$1:$AB$1,0)),"")&"","") | AJ43: =IF(AND(AF43=1,AE43>=set_FYStart,AE43<=set_AsAt),1,0) | AK43: =IF(AND(AJ43=1,AH43<>"",COUNTIFS($AH$2:AH43,AH43,$AJ$2:AJ43,1)=1),N(AL42)+1,"") | AL43: =IF(AK43<>"",AK43,N(AL42))
A44: ONS-0015 | B44: Onsite | C44: 1668 | D44: CBA | E44: AH Support 02/07/2026 | F44: 180 | G44: INV-10542 | H44: 46234 | I44: 180 | J44: 0 | K44: Agrees | N44: OK | O44: CBA Dedicated Tech | P44: ONSITE | Q44: Ad-hoc | R44: GST 10% | S44: 41100 | V44: 18 | W44: 198 | X44: 46234 | Y44: 12 | Z44: 5290 | AA44: 5290 | AB44: 15 | AD44: =IFERROR(N(IFERROR(INDEX($A44:$AB44,MATCH("Xero Invoiced Ex GST",$A$1:$AB$1,0)),"")),0) | AE44: =IFERROR(INDEX($A44:$AB44,MATCH("Xero Invoice Date",$A$1:$AB$1,0)),"") | AF44: =IF(AND(IFERROR(INDEX($A44:$AB44,MATCH("Xero Invoice No",$A$1:$AB$1,0)),"")&""<>"",ISNUMBER(AE44),AD44<>0),1,0) | AG44: =IF(AF44=1,EOMONTH(AE44,0),"") | AH44: =IF(AF44=1,UPPER(TRIM(IFERROR(INDEX($A44:$AB44,MATCH("Client",$A$1:$AB$1,0)),"")&"")),"") | AI44: =IF(AF44=1,IFERROR(INDEX($A44:$AB44,MATCH("Cost Centre",$A$1:$AB$1,0)),"")&"","") | AJ44: =IF(AND(AF44=1,AE44>=set_FYStart,AE44<=set_AsAt),1,0) | AK44: =IF(AND(AJ44=1,AH44<>"",COUNTIFS($AH$2:AH44,AH44,$AJ$2:AJ44,1)=1),N(AL43)+1,"") | AL44: =IF(AK44<>"",AK44,N(AL43))
A45: PRD-0015 | B45: Production | C45: 26061702 | D45: Garvan | E45: Morning Tea Event 31.7.26 (PO-58817) | F45: 1120 | G45: INV-10556 | H45: 46234 | I45: 1120 | J45: 0 | K45: Agrees | N45: OK | O45: Garvan - Morning Tea Event - 31.7.26 | P45: PRODUCTION | Q45: Project | R45: GST 10% | S45: 42100 | T45: 6066 | V45: 112 | W45: 1232 | X45: 46234 | Y45: 1 | Z45: 1120 | AA45: 1120 | AB45: 15 | AD45: =IFERROR(N(IFERROR(INDEX($A45:$AB45,MATCH("Xero Invoiced Ex GST",$A$1:$AB$1,0)),"")),0) | AE45: =IFERROR(INDEX($A45:$AB45,MATCH("Xero Invoice Date",$A$1:$AB$1,0)),"") | AF45: =IF(AND(IFERROR(INDEX($A45:$AB45,MATCH("Xero Invoice No",$A$1:$AB$1,0)),"")&""<>"",ISNUMBER(AE45),AD45<>0),1,0) | AG45: =IF(AF45=1,EOMONTH(AE45,0),"") | AH45: =IF(AF45=1,UPPER(TRIM(IFERROR(INDEX($A45:$AB45,MATCH("Client",$A$1:$AB$1,0)),"")&"")),"") | AI45: =IF(AF45=1,IFERROR(INDEX($A45:$AB45,MATCH("Cost Centre",$A$1:$AB$1,0)),"")&"","") | AJ45: =IF(AND(AF45=1,AE45>=set_FYStart,AE45<=set_AsAt),1,0) | AK45: =IF(AND(AJ45=1,AH45<>"",COUNTIFS($AH$2:AH45,AH45,$AJ$2:AJ45,1)=1),N(AL44)+1,"") | AL45: =IF(AK45<>"",AK45,N(AL44))
A46: CON-0015 | B46: Consulting | C46: 26033006 | D46: DTTL | E46: 8PSQ_Bluetooth Audio | F46: 5065 | G46: INV-10355 | H46: 46203 | I46: 5065 | J46: 0 | K46: Agrees | N46: OK | O46: DTTL 8PSQ Bluetooth Audio | P46: INTEGRATION | Q46: Project | R46: GST 10% | S46: 42300 | T46: 26033006_Deloitte 8PSQ_Bluetooth Audio_v1.0 | U46: Status: In Progress | V46: 506.5 | W46: 5571.5 | X46: 46203 | Y46: 1 | Z46: 5065 | AA46: 5065 | AB46: 15 | AD46: =IFERROR(N(IFERROR(INDEX($A46:$AB46,MATCH("Xero Invoiced Ex GST",$A$1:$AB$1,0)),"")),0) | AE46: =IFERROR(INDEX($A46:$AB46,MATCH("Xero Invoice Date",$A$1:$AB$1,0)),"") | AF46: =IF(AND(IFERROR(INDEX($A46:$AB46,MATCH("Xero Invoice No",$A$1:$AB$1,0)),"")&""<>"",ISNUMBER(AE46),AD46<>0),1,0) | AG46: =IF(AF46=1,EOMONTH(AE46,0),"") | AH46: =IF(AF46=1,UPPER(TRIM(IFERROR(INDEX($A46:$AB46,MATCH("Client",$A$1:$AB$1,0)),"")&"")),"") | AI46: =IF(AF46=1,IFERROR(INDEX($A46:$AB46,MATCH("Cost Centre",$A$1:$AB$1,0)),"")&"","") | AJ46: =IF(AND(AF46=1,AE46>=set_FYStart,AE46<=set_AsAt),1,0) | AK46: =IF(AND(AJ46=1,AH46<>"",COUNTIFS($AH$2:AH46,AH46,$AJ$2:AJ46,1)=1),N(AL45)+1,"") | AL46: =IF(AK46<>"",AK46,N(AL45))
A47: ONS-0016 | B47: Onsite | C47: 1668 | D47: CBA | E47: DT Support 02/07/2026 | F47: 425 | G47: INV-10543 | H47: 46234 | I47: 425 | J47: 0 | K47: Agrees | N47: OK | O47: CBA Dedicated Tech | P47: ONSITE | Q47: Ad-hoc | R47: GST 10% | S47: 41100 | V47: 42.5 | W47: 467.5 | X47: 46234 | Y47: 12 | Z47: 5290 | AA47: 5290 | AB47: 16 | AD47: =IFERROR(N(IFERROR(INDEX($A47:$AB47,MATCH("Xero Invoiced Ex GST",$A$1:$AB$1,0)),"")),0) | AE47: =IFERROR(INDEX($A47:$AB47,MATCH("Xero Invoice Date",$A$1:$AB$1,0)),"") | AF47: =IF(AND(IFERROR(INDEX($A47:$AB47,MATCH("Xero Invoice No",$A$1:$AB$1,0)),"")&""<>"",ISNUMBER(AE47),AD47<>0),1,0) | AG47: =IF(AF47=1,EOMONTH(AE47,0),"") | AH47: =IF(AF47=1,UPPER(TRIM(IFERROR(INDEX($A47:$AB47,MATCH("Client",$A$1:$AB$1,0)),"")&"")),"") | AI47: =IF(AF47=1,IFERROR(INDEX($A47:$AB47,MATCH("Cost Centre",$A$1:$AB$1,0)),"")&"","") | AJ47: =IF(AND(AF47=1,AE47>=set_FYStart,AE47<=set_AsAt),1,0) | AK47: =IF(AND(AJ47=1,AH47<>"",COUNTIFS($AH$2:AH47,AH47,$AJ$2:AJ47,1)=1),N(AL46)+1,"") | AL47: =IF(AK47<>"",AK47,N(AL46))
A48: PRD-0016 | B48: Production | C48: 26061701 | D48: CBA | E48: CBA LES July 2026 | F48: 8550 | G48: INV-10559 | H48: 46234 | I48: 8882.5 | J48: -332.5 | K48: Xero higher - check dept | M48: Xero check 28-Sep-26: Xero INV-10559 is $8,882.50 ex GST; the $332.50 loading reversal is the separate credit note row PRD-0017, so $8,550 here counted the credit twice | N48: OK | O48: CBA - LES - July 2026 | P48: PRODUCTION | Q48: Project | R48: GST 10% | S48: 42100 | T48: 6145 | V48: 888.25 | W48: 9770.75 | X48: 46234 | Y48: 2 | Z48: 8217.5 | AA48: 8550 | AB48: 16 | AD48: =IFERROR(N(IFERROR(INDEX($A48:$AB48,MATCH("Xero Invoiced Ex GST",$A$1:$AB$1,0)),"")),0) | AE48: =IFERROR(INDEX($A48:$AB48,MATCH("Xero Invoice Date",$A$1:$AB$1,0)),"") | AF48: =IF(AND(IFERROR(INDEX($A48:$AB48,MATCH("Xero Invoice No",$A$1:$AB$1,0)),"")&""<>"",ISNUMBER(AE48),AD48<>0),1,0) | AG48: =IF(AF48=1,EOMONTH(AE48,0),"") | AH48: =IF(AF48=1,UPPER(TRIM(IFERROR(INDEX($A48:$AB48,MATCH("Client",$A$1:$AB$1,0)),"")&"")),"") | AI48: =IF(AF48=1,IFERROR(INDEX($A48:$AB48,MATCH("Cost Centre",$A$1:$AB$1,0)),"")&"","") | AJ48: =IF(AND(AF48=1,AE48>=set_FYStart,AE48<=set_AsAt),1,0) | AK48: =IF(AND(AJ48=1,AH48<>"",COUNTIFS($AH$2:AH48,AH48,$AJ$2:AJ48,1)=1),N(AL47)+1,"") | AL48: =IF(AK48<>"",AK48,N(AL47))
A49: CON-0016 | B49: Consulting | C49: 26033007 | D49: DTTL | E49: QQT_Lv45 Seminar-Wheels repair | F49: 354 | G49: INV-10355 | H49: 46203 | I49: 354 | J49: 0 | K49: Agrees | N49: OK | O49: DTTL QQT Lv45 Seminar Wheels repair | P49: INTEGRATION | Q49: Project | R49: GST 10% | S49: 42300 | T49: 26033007_Deloitte QQT_Lv45 Seminar-Wheels repair_v1.0 | U49: Status: In Progress | V49: 35.4 | W49: 389.4 | X49: 46203 | Y49: 1 | Z49: 354 | AA49: 354 | AB49: 16 | AD49: =IFERROR(N(IFERROR(INDEX($A49:$AB49,MATCH("Xero Invoiced Ex GST",$A$1:$AB$1,0)),"")),0) | AE49: =IFERROR(INDEX($A49:$AB49,MATCH("Xero Invoice Date",$A$1:$AB$1,0)),"") | AF49: =IF(AND(IFERROR(INDEX($A49:$AB49,MATCH("Xero Invoice No",$A$1:$AB$1,0)),"")&""<>"",ISNUMBER(AE49),AD49<>0),1,0) | AG49: =IF(AF49=1,EOMONTH(AE49,0),"") | AH49: =IF(AF49=1,UPPER(TRIM(IFERROR(INDEX($A49:$AB49,MATCH("Client",$A$1:$AB$1,0)),"")&"")),"") | AI49: =IF(AF49=1,IFERROR(INDEX($A49:$AB49,MATCH("Cost Centre",$A$1:$AB$1,0)),"")&"","") | AJ49: =IF(AND(AF49=1,AE49>=set_FYStart,AE49<=set_AsAt),1,0) | AK49: =IF(AND(AJ49=1,AH49<>"",COUNTIFS($AH$2:AH49,AH49,$AJ$2:AJ49,1)=1),N(AL48)+1,"") | AL49: =IF(AK49<>"",AK49,N(AL48))
A50: ONS-0017 | B50: Onsite | C50: 1668 | D50: CBA | E50: DT Support 23/07/2026 | F50: 510 | G50: INV-10544 | H50: 46234 | I50: 510 | J50: 0 | K50: Agrees | N50: OK | O50: CBA Dedicated Tech | P50: ONSITE | Q50: Ad-hoc | R50: GST 10% | S50: 41100 | V50: 51 | W50: 561 | X50: 46234 | Y50: 12 | Z50: 5290 | AA50: 5290 | AB50: 17 | AD50: =IFERROR(N(IFERROR(INDEX($A50:$AB50,MATCH("Xero Invoiced Ex GST",$A$1:$AB$1,0)),"")),0) | AE50: =IFERROR(INDEX($A50:$AB50,MATCH("Xero Invoice Date",$A$1:$AB$1,0)),"") | AF50: =IF(AND(IFERROR(INDEX($A50:$AB50,MATCH("Xero Invoice No",$A$1:$AB$1,0)),"")&""<>"",ISNUMBER(AE50),AD50<>0),1,0) | AG50: =IF(AF50=1,EOMONTH(AE50,0),"") | AH50: =IF(AF50=1,UPPER(TRIM(IFERROR(INDEX($A50:$AB50,MATCH("Client",$A$1:$AB$1,0)),"")&"")),"") | AI50: =IF(AF50=1,IFERROR(INDEX($A50:$AB50,MATCH("Cost Centre",$A$1:$AB$1,0)),"")&"","") | AJ50: =IF(AND(AF50=1,AE50>=set_FYStart,AE50<=set_AsAt),1,0) | AK50: =IF(AND(AJ50=1,AH50<>"",COUNTIFS($AH$2:AH50,AH50,$AJ$2:AJ50,1)=1),N(AL49)+1,"") | AL50: =IF(AK50<>"",AK50,N(AL49))
A51: PRD-0017 | B51: Production | C51: 26061701 | D51: CBA | E51: CBA LES July 2026 Loading Reversal | F51: -332.5 | G51: CN-10563 | H51: 46247 | I51: -332.5 | J51: 0 | K51: Agrees | M51: Xero check 28-Sep-26: CN-10563 dated 13-Aug-26 in Xero - moved from July to August | N51: OK | O51: CBA - LES - July 2026 | P51: PRODUCTION | Q51: Credit Note | R51: GST 10% | S51: 42100 | T51: 6145 | V51: -33.25 | W51: -365.75 | X51: 46265 | Y51: 2 | Z51: 8217.5 | AA51: 8550 | AB51: 17 | AD51: =IFERROR(N(IFERROR(INDEX($A51:$AB51,MATCH("Xero Invoiced Ex GST",$A$1:$AB$1,0)),"")),0) | AE51: =IFERROR(INDEX($A51:$AB51,MATCH("Xero Invoice Date",$A$1:$AB$1,0)),"") | AF51: =IF(AND(IFERROR(INDEX($A51:$AB51,MATCH("Xero Invoice No",$A$1:$AB$1,0)),"")&""<>"",ISNUMBER(AE51),AD51<>0),1,0) | AG51: =IF(AF51=1,EOMONTH(AE51,0),"") | AH51: =IF(AF51=1,UPPER(TRIM(IFERROR(INDEX($A51:$AB51,MATCH("Client",$A$1:$AB$1,0)),"")&"")),"") | AI51: =IF(AF51=1,IFERROR(INDEX($A51:$AB51,MATCH("Cost Centre",$A$1:$AB$1,0)),"")&"","") | AJ51: =IF(AND(AF51=1,AE51>=set_FYStart,AE51<=set_AsAt),1,0) | AK51: =IF(AND(AJ51=1,AH51<>"",COUNTIFS($AH$2:AH51,AH51,$AJ$2:AJ51,1)=1),N(AL50)+1,"") | AL51: =IF(AK51<>"",AK51,N(AL50))
A52: CON-0017 | B52: Consulting | C52: 26051301 | D52: HP Poly - BAE | E52: Phone Mod | F52: 1161 | G52: INV-10516 | H52: 46209 | I52: 1161 | J52: 0 | K52: Agrees | N52: OK | O52: HP-BAE | Phone Mod | P52: INTEGRATION | Q52: Project | R52: GST 10% | S52: 42300 | T52: https://cts.qwilr.com/26051301-HP-BAE-PhoneMod-v1-0-nL48O1eQt25h | U52: Status: Closed | V52: 116.1 | W52: 1277.1 | X52: 46234 | Y52: 1 | Z52: 1161 | AA52: 1161 | AB52: 17 | AD52: =IFERROR(N(IFERROR(INDEX($A52:$AB52,MATCH("Xero Invoiced Ex GST",$A$1:$AB$1,0)),"")),0) | AE52: =IFERROR(INDEX($A52:$AB52,MATCH("Xero Invoice Date",$A$1:$AB$1,0)),"") | AF52: =IF(AND(IFERROR(INDEX($A52:$AB52,MATCH("Xero Invoice No",$A$1:$AB$1,0)),"")&""<>"",ISNUMBER(AE52),AD52<>0),1,0) | AG52: =IF(AF52=1,EOMONTH(AE52,0),"") | AH52: =IF(AF52=1,UPPER(TRIM(IFERROR(INDEX($A52:$AB52,MATCH("Client",$A$1:$AB$1,0)),"")&"")),"") | AI52: =IF(AF52=1,IFERROR(INDEX($A52:$AB52,MATCH("Cost Centre",$A$1:$AB$1,0)),"")&"","") | AJ52: =IF(AND(AF52=1,AE52>=set_FYStart,AE52<=set_AsAt),1,0) | AK52: =IF(AND(AJ52=1,AH52<>"",COUNTIFS($AH$2:AH52,AH52,$AJ$2:AJ52,1)=1),N(AL51)+1,"") | AL52: =IF(AK52<>"",AK52,N(AL51))
A53: ONS-0018 | B53: Onsite | C53: 2540 | D53: PWC | E53: PWC Dedicated Tech 30/07/2026 | F53: 340 | G53: INV-10545 | H53: 46233 | I53: 340 | J53: 0 | K53: Agrees | N53: OK | O53: PWC - SYD Tech | P53: ONSITE | Q53: Ad-hoc | R53: GST 10% | S53: 41100 | U53: PO2601703274 | V53: 34 | W53: 374 | X53: 46234 | Y53: 1 | Z53: 340 | AA53: 340 | AB53: 18 | AD53: =IFERROR(N(IFERROR(INDEX($A53:$AB53,MATCH("Xero Invoiced Ex GST",$A$1:$AB$1,0)),"")),0) | AE53: =IFERROR(INDEX($A53:$AB53,MATCH("Xero Invoice Date",$A$1:$AB$1,0)),"") | AF53: =IF(AND(IFERROR(INDEX($A53:$AB53,MATCH("Xero Invoice No",$A$1:$AB$1,0)),"")&""<>"",ISNUMBER(AE53),AD53<>0),1,0) | AG53: =IF(AF53=1,EOMONTH(AE53,0),"") | AH53: =IF(AF53=1,UPPER(TRIM(IFERROR(INDEX($A53:$AB53,MATCH("Client",$A$1:$AB$1,0)),"")&"")),"") | AI53: =IF(AF53=1,IFERROR(INDEX($A53:$AB53,MATCH("Cost Centre",$A$1:$AB$1,0)),"")&"","") | AJ53: =IF(AND(AF53=1,AE53>=set_FYStart,AE53<=set_AsAt),1,0) | AK53: =IF(AND(AJ53=1,AH53<>"",COUNTIFS($AH$2:AH53,AH53,$AJ$2:AJ53,1)=1),N(AL52)+1,"") | AL53: =IF(AK53<>"",AK53,N(AL52))
A54: PRD-0018 | B54: Production | C54: 2512804 | D54: RSNSW | E54: Ordinary General Meeting 5.8.26 | F54: 2232 | G54: INV-10561 | H54: 46247 | I54: 2232 | J54: 0 | K54: Agrees | N54: OK | O54: RSNSW Ordinary General Meeting 5.8.26 | P54: PRODUCTION | Q54: Project | R54: GST 10% | S54: 42100 | T54: 5826 | V54: 223.2 | W54: 2455.2 | X54: 46265 | Y54: 1 | Z54: 2232 | AA54: 2232 | AB54: 18 | AD54: =IFERROR(N(IFERROR(INDEX($A54:$AB54,MATCH("Xero Invoiced Ex GST",$A$1:$AB$1,0)),"")),0) | AE54: =IFERROR(INDEX($A54:$AB54,MATCH("Xero Invoice Date",$A$1:$AB$1,0)),"") | AF54: =IF(AND(IFERROR(INDEX($A54:$AB54,MATCH("Xero Invoice No",$A$1:$AB$1,0)),"")&""<>"",ISNUMBER(AE54),AD54<>0),1,0) | AG54: =IF(AF54=1,EOMONTH(AE54,0),"") | AH54: =IF(AF54=1,UPPER(TRIM(IFERROR(INDEX($A54:$AB54,MATCH("Client",$A$1:$AB$1,0)),"")&"")),"") | AI54: =IF(AF54=1,IFERROR(INDEX($A54:$AB54,MATCH("Cost Centre",$A$1:$AB$1,0)),"")&"","") | AJ54: =IF(AND(AF54=1,AE54>=set_FYStart,AE54<=set_AsAt),1,0) | AK54: =IF(AND(AJ54=1,AH54<>"",COUNTIFS($AH$2:AH54,AH54,$AJ$2:AJ54,1)=1),N(AL53)+1,"") | AL54: =IF(AK54<>"",AK54,N(AL53))
A55: CON-0018 | B55: Consulting | C55: 26061501 | D55: DTTL | E55: MEL Lv29 Display Supply | F55: 3890 | G55: INV-10546 | H55: 46233 | I55: 3890 | J55: 0 | K55: Agrees | N55: OK | O55: DTTL MEL Lv29 Display Supply | P55: INTEGRATION | Q55: Project | R55: GST 10% | S55: 42300 | T55: https://cts.qwilr.com/26061501-DTTL-Costing-v1-0-3HdQMOES9eDo | U55: Status: Closed | V55: 389 | W55: 4279 | X55: 46234 | Y55: 1 | Z55: 3890 | AA55: 3890 | AB55: 18 | AD55: =IFERROR(N(IFERROR(INDEX($A55:$AB55,MATCH("Xero Invoiced Ex GST",$A$1:$AB$1,0)),"")),0) | AE55: =IFERROR(INDEX($A55:$AB55,MATCH("Xero Invoice Date",$A$1:$AB$1,0)),"") | AF55: =IF(AND(IFERROR(INDEX($A55:$AB55,MATCH("Xero Invoice No",$A$1:$AB$1,0)),"")&""<>"",ISNUMBER(AE55),AD55<>0),1,0) | AG55: =IF(AF55=1,EOMONTH(AE55,0),"") | AH55: =IF(AF55=1,UPPER(TRIM(IFERROR(INDEX($A55:$AB55,MATCH("Client",$A$1:$AB$1,0)),"")&"")),"") | AI55: =IF(AF55=1,IFERROR(INDEX($A55:$AB55,MATCH("Cost Centre",$A$1:$AB$1,0)),"")&"","") | AJ55: =IF(AND(AF55=1,AE55>=set_FYStart,AE55<=set_AsAt),1,0) | AK55: =IF(AND(AJ55=1,AH55<>"",COUNTIFS($AH$2:AH55,AH55,$AJ$2:AJ55,1)=1),N(AL54)+1,"") | AL55: =IF(AK55<>"",AK55,N(AL54))
A56: ONS-0019 | B56: Onsite | C56: 26062501/2347 | D56: DTTL | E56: DH Travel 06-07/07 & Ad-hoc Tech Support 30/07 & Market Shapers | F56: 1672.5 | G56: INV-10546 | H56: 46233 | I56: 1672.5 | J56: 0 | K56: Agrees | L56: Job number not in the Xero job list | N56: CHECK | P56: ONSITE | Q56: Ad-hoc | R56: GST 10% | S56: 41100 | V56: 167.25 | W56: 1839.75 | X56: 46234 | Y56: 1 | Z56: 1672.5 | AA56: 1672.5 | AB56: 19 | AD56: =IFERROR(N(IFERROR(INDEX($A56:$AB56,MATCH("Xero Invoiced Ex GST",$A$1:$AB$1,0)),"")),0) | AE56: =IFERROR(INDEX($A56:$AB56,MATCH("Xero Invoice Date",$A$1:$AB$1,0)),"") | AF56: =IF(AND(IFERROR(INDEX($A56:$AB56,MATCH("Xero Invoice No",$A$1:$AB$1,0)),"")&""<>"",ISNUMBER(AE56),AD56<>0),1,0) | AG56: =IF(AF56=1,EOMONTH(AE56,0),"") | AH56: =IF(AF56=1,UPPER(TRIM(IFERROR(INDEX($A56:$AB56,MATCH("Client",$A$1:$AB$1,0)),"")&"")),"") | AI56: =IF(AF56=1,IFERROR(INDEX($A56:$AB56,MATCH("Cost Centre",$A$1:$AB$1,0)),"")&"","") | AJ56: =IF(AND(AF56=1,AE56>=set_FYStart,AE56<=set_AsAt),1,0) | AK56: =IF(AND(AJ56=1,AH56<>"",COUNTIFS($AH$2:AH56,AH56,$AJ$2:AJ56,1)=1),N(AL55)+1,"") | AL56: =IF(AK56<>"",AK56,N(AL55))
A57: PRD-0019 | B57: Production | C57: 2607703 | D57: Garvan | E57: YPO Event 6.8.26 (PO-58493) | F57: 2152.5 | G57: INV-10560 | H57: 46247 | I57: 2152.5 | J57: 0 | K57: Agrees | N57: OK | O57: Garvan - YPO Event - 6.8.2026 | P57: PRODUCTION | Q57: Project | R57: GST 10% | S57: 42100 | T57: 6088 | V57: 215.25 | W57: 2367.75 | X57: 46265 | Y57: 1 | Z57: 2152.5 | AA57: 2152.5 | AB57: 19 | AD57: =IFERROR(N(IFERROR(INDEX($A57:$AB57,MATCH("Xero Invoiced Ex GST",$A$1:$AB$1,0)),"")),0) | AE57: =IFERROR(INDEX($A57:$AB57,MATCH("Xero Invoice Date",$A$1:$AB$1,0)),"") | AF57: =IF(AND(IFERROR(INDEX($A57:$AB57,MATCH("Xero Invoice No",$A$1:$AB$1,0)),"")&""<>"",ISNUMBER(AE57),AD57<>0),1,0) | AG57: =IF(AF57=1,EOMONTH(AE57,0),"") | AH57: =IF(AF57=1,UPPER(TRIM(IFERROR(INDEX($A57:$AB57,MATCH("Client",$A$1:$AB$1,0)),"")&"")),"") | AI57: =IF(AF57=1,IFERROR(INDEX($A57:$AB57,MATCH("Cost Centre",$A$1:$AB$1,0)),"")&"","") | AJ57: =IF(AND(AF57=1,AE57>=set_FYStart,AE57<=set_AsAt),1,0) | AK57: =IF(AND(AJ57=1,AH57<>"",COUNTIFS($AH$2:AH57,AH57,$AJ$2:AJ57,1)=1),N(AL56)+1,"") | AL57: =IF(AK57<>"",AK57,N(AL56))
A58: CON-0019 | B58: Consulting | C58: 2605605 | D58: DTTL | E58: HBA AV Fitout | F58: 60348 | G58: INV-10546 | H58: 46233 | I58: 60348 | J58: 0 | K58: Agrees | N58: OK | O58: DTTL Hobart AV Fitout | P58: INTEGRATION | Q58: Project | R58: GST 10% | S58: 42300 | T58: https://cts.qwilr.com/2605605-DTTL-Hobart-v3-2-6eP2dgISRMec | U58: Status: In Progress | V58: 6034.8 | W58: 66382.8 | X58: 46234 | Y58: 1 | Z58: 60348 | AA58: 60348 | AB58: 19 | AD58: =IFERROR(N(IFERROR(INDEX($A58:$AB58,MATCH("Xero Invoiced Ex GST",$A$1:$AB$1,0)),"")),0) | AE58: =IFERROR(INDEX($A58:$AB58,MATCH("Xero Invoice Date",$A$1:$AB$1,0)),"") | AF58: =IF(AND(IFERROR(INDEX($A58:$AB58,MATCH("Xero Invoice No",$A$1:$AB$1,0)),"")&""<>"",ISNUMBER(AE58),AD58<>0),1,0) | AG58: =IF(AF58=1,EOMONTH(AE58,0),"") | AH58: =IF(AF58=1,UPPER(TRIM(IFERROR(INDEX($A58:$AB58,MATCH("Client",$A$1:$AB$1,0)),"")&"")),"") | AI58: =IF(AF58=1,IFERROR(INDEX($A58:$AB58,MATCH("Cost Centre",$A$1:$AB$1,0)),"")&"","") | AJ58: =IF(AND(AF58=1,AE58>=set_FYStart,AE58<=set_AsAt),1,0) | AK58: =IF(AND(AJ58=1,AH58<>"",COUNTIFS($AH$2:AH58,AH58,$AJ$2:AJ58,1)=1),N(AL57)+1,"") | AL58: =IF(AK58<>"",AK58,N(AL57))
A59: ONS-0020 | B59: Onsite | C59: 2026021101 | D59: APN | E59: APN Quarterly AV Support | F59: 1670 | G59: INV-10550 | H59: 46233 | I59: 1670 | J59: 0 | K59: Agrees | N59: OK | O59: AusPayNet Quarterly AV Support & Maintenance 2026 | P59: ONSITE | Q59: Ad-hoc | R59: GST 10% | S59: 41100 | U59: Invoice 1/2 | V59: 167 | W59: 1837 | X59: 46234 | Y59: 1 | Z59: 1670 | AA59: 1670 | AB59: 20 | AD59: =IFERROR(N(IFERROR(INDEX($A59:$AB59,MATCH("Xero Invoiced Ex GST",$A$1:$AB$1,0)),"")),0) | AE59: =IFERROR(INDEX($A59:$AB59,MATCH("Xero Invoice Date",$A$1:$AB$1,0)),"") | AF59: =IF(AND(IFERROR(INDEX($A59:$AB59,MATCH("Xero Invoice No",$A$1:$AB$1,0)),"")&""<>"",ISNUMBER(AE59),AD59<>0),1,0) | AG59: =IF(AF59=1,EOMONTH(AE59,0),"") | AH59: =IF(AF59=1,UPPER(TRIM(IFERROR(INDEX($A59:$AB59,MATCH("Client",$A$1:$AB$1,0)),"")&"")),"") | AI59: =IF(AF59=1,IFERROR(INDEX($A59:$AB59,MATCH("Cost Centre",$A$1:$AB$1,0)),"")&"","") | AJ59: =IF(AND(AF59=1,AE59>=set_FYStart,AE59<=set_AsAt),1,0) | AK59: =IF(AND(AJ59=1,AH59<>"",COUNTIFS($AH$2:AH59,AH59,$AJ$2:AJ59,1)=1),N(AL58)+1,"") | AL59: =IF(AK59<>"",AK59,N(AL58))
