Workbook
Name AcctName: #REF!
Name AcctName: #REF!
Name AcctName: #REF!
Name AcctName: #REF!
Name AcctSubCate: #REF!
Name AcctSubCate: #REF!
Name AcctSubCate: #REF!
Name AcctSubCate: #REF!

Sheet FY25 Forecast summary - Main
B1: ACTUAL | C1: ACTUAL | D1: FORECAST | E1: FORECAST | F1: FORECAST | G1: FORECAST | H1: FORECAST | I1: FORECAST | J1: FORECAST | K1: FORECAST | L1: FORECAST | M1: FORECAST | N1: FORECAST | O1: FORECAST | P1: FORECAST
B2: FY24 | C2: FY25 | D2: 45474 | E2: 45505 | F2: 45536 | G2: 45566 | H2: 45597 | I2: 45627 | J2: 45658 | K2: 45689 | L2: 45717 | M2: 45748 | N2: 45778 | O2: 45809 | P2: Total (Oct-Jun) | Q2: Forecast vs Actual
A3: Consulting | B3: ='FY27 Budget - detailed'!#REF! -> #REF! | C3: =#REF!+#REF!+#REF! -> #REF! | D3: ='FY27 Budget - detailed'!H3 -> 297416.49 | E3: ='FY27 Budget - detailed'!I3 -> 465645.39 | F3: ='FY27 Budget - detailed'!J3 -> 82321.892 | G3: ='FY27 Budget - detailed'!K3 -> 100061.89 | H3: ='FY27 Budget - detailed'!L3 -> 36337.392 | I3: ='FY27 Budget - detailed'!M3 -> 31337.392 | J3: ='FY27 Budget - detailed'!N3 -> 27340.652 | K3: ='FY27 Budget - detailed'!O3 -> 32340.652 | ... O3: ='FY27 Budget - detailed'!S3 -> 8035.0717 | P3: =D3+E3+F3+G3+H3+I3+J3+K3+L3+M3+N3+O3 -> 1153553.2 | Q3: =(C3-P3)/P3 -> #REF! | R3: =+P3-C3 -> #REF!
A4: Production | B4: ='FY27 Budget - detailed'!#REF! -> #REF! | C4: =#REF!+#REF!+#REF! -> #REF! | D4: ='FY27 Budget - detailed'!H4 -> 73000.02 | E4: ='FY27 Budget - detailed'!I4 -> 251215.02 | F4: ='FY27 Budget - detailed'!J4 -> 83326.02 | G4: ='FY27 Budget - detailed'!K4 -> 587307.02 | H4: ='FY27 Budget - detailed'!L4 -> 241601.02 | I4: ='FY27 Budget - detailed'!M4 -> 62316.02 | J4: ='FY27 Budget - detailed'!N4 -> 64261.937 | K4: ='FY27 Budget - detailed'!O4 -> 281912.02 | ... O4: ='FY27 Budget - detailed'!S4 -> 82637.02 | P4: =D4+E4+F4+G4+H4+I4+J4+K4+L4+M4+N4+O4 -> 2090722.1 | Q4: =(C4-P4)/P4 -> #REF! | R4: =+P4-C4 -> #REF!
A5: Onsite | B5: ='FY27 Budget - detailed'!#REF! -> #REF! | C5: =#REF!+#REF!+#REF! -> #REF! | D5: ='FY27 Budget - detailed'!H5 -> 238860.67 | E5: ='FY27 Budget - detailed'!I5 -> 256307.33 | F5: ='FY27 Budget - detailed'!J5 -> 248016.77 | G5: ='FY27 Budget - detailed'!K5 -> 263046.77 | H5: ='FY27 Budget - detailed'!L5 -> 262366.77 | I5: ='FY27 Budget - detailed'!M5 -> 251316.77 | J5: ='FY27 Budget - detailed'!N5 -> 262366.77 | K5: ='FY27 Budget - detailed'!O5 -> 262366.77 | ... O5: ='FY27 Budget - detailed'!S5 -> 242443.11 | P5: =D5+E5+F5+G5+H5+I5+J5+K5+L5+M5+N5+O5 -> 3060325.4 | Q5: =(C5-P5)/P5 -> #REF! | R5: =+P5-C5 -> #REF!
A6: Total Income | B6: =SUM(B3:B5) -> #REF! | C6: =SUM(C3:C5) -> #REF! | D6: =SUM(D3:D5) -> 609277.18 | E6: =SUM(E3:E5) -> 973167.74 | F6: =SUM(F3:F5) -> 413664.68 | G6: =SUM(G3:G5) -> 950415.68 | H6: =SUM(H3:H5) -> 540305.18 | I6: =SUM(I3:I5) -> 344970.18 | ... O6: =SUM(O3:O5) -> 333115.2 | P6: =D6+E6+F6+G6+H6+I6+J6+K6+L6+M6+N6+O6 -> 6304600.7 | Q6: =(C6-P6)/P6 -> #REF! | R6: =+P6-C6 -> #REF!
A7: Consulting Direct Costs | B7: ='FY27 Budget - detailed'!#REF! -> #REF! | C7: =#REF!+#REF!+#REF! -> #REF! | D7: ='FY27 Budget - detailed'!H7 -> 156894.91 | E7: ='FY27 Budget - detailed'!I7 -> 239607.17 | F7: ='FY27 Budget - detailed'!J7 -> 50130.112 | G7: ='FY27 Budget - detailed'!K7 -> 58336.599 | H7: ='FY27 Budget - detailed'!L7 -> 27394.352 | I7: ='FY27 Budget - detailed'!M7 -> 23963.88 | J7: ='FY27 Budget - detailed'!N7 -> 21263.504 | K7: ='FY27 Budget - detailed'!O7 -> 24080.807 | ... O7: ='FY27 Budget - detailed'!S7 -> 17919.298 | P7: =D7+E7+F7+G7+H7+I7+J7+K7+L7+M7+N7+O7 -> 681494.01 | Q7: =(C7-P7)/P7 -> #REF! | R7: =+P7-C7 -> #REF!
A8: Production Direct Costs | B8: ='FY27 Budget - detailed'!#REF! -> #REF! | C8: =#REF!+#REF!+#REF! -> #REF! | D8: ='FY27 Budget - detailed'!H11 -> 52683.663 | E8: ='FY27 Budget - detailed'!I11 -> 100269.81 | F8: ='FY27 Budget - detailed'!J11 -> 103519.69 | G8: ='FY27 Budget - detailed'!K11 -> 285683.94 | H8: ='FY27 Budget - detailed'!L11 -> 104223.85 | I8: ='FY27 Budget - detailed'!M11 -> 83048.46 | J8: ='FY27 Budget - detailed'!N11 -> 45343.173 | K8: ='FY27 Budget - detailed'!O11 -> 109744.55 | ... O8: ='FY27 Budget - detailed'!S11 -> 85630.235 | P8: =D8+E8+F8+G8+H8+I8+J8+K8+L8+M8+N8+O8 -> 1138130.7 | Q8: =(C8-P8)/P8 -> #REF! | R8: =+P8-C8 -> #REF!
A9: Onsite Direct Costs | B9: ='FY27 Budget - detailed'!#REF! -> #REF! | C9: =#REF!+#REF!+#REF! -> #REF! | D9: ='FY27 Budget - detailed'!H15 -> 129391.68 | E9: ='FY27 Budget - detailed'!I15 -> 115678.57 | F9: ='FY27 Budget - detailed'!J15 -> 135541.85 | G9: ='FY27 Budget - detailed'!K15 -> 130158.68 | H9: ='FY27 Budget - detailed'!L15 -> 127598.94 | I9: ='FY27 Budget - detailed'!M15 -> 134912.18 | J9: ='FY27 Budget - detailed'!N15 -> 112466.56 | K9: ='FY27 Budget - detailed'!O15 -> 116012.62 | ... O9: ='FY27 Budget - detailed'!S15 -> 139270 | P9: =D9+E9+F9+G9+H9+I9+J9+K9+L9+M9+N9+O9 -> 1559522.1 | Q9: =(C9-P9)/P9 -> #REF! | R9: =+P9-C9 -> #REF!
A10: Total Cost of Sales | B10: =SUM(B7:B9) -> #REF! | C10: =SUM(C7:C9) -> #REF! | D10: =SUM(D7:D9) -> 338970.25 | E10: =SUM(E7:E9) -> 455555.55 | F10: =SUM(F7:F9) -> 289191.66 | G10: =SUM(G7:G9) -> 474179.22 | H10: =SUM(H7:H9) -> 259217.14 | I10: =SUM(I7:I9) -> 241924.52 | ... O10: =SUM(O7:O9) -> 242819.53 | P10: =D10+E10+F10+G10+H10+I10+J10+K10+L10+M10+N10+O10 -> 3379146.7 | Q10: =(C10-P10)/P10 -> #REF! | R10: =+P10-C10 -> #REF!
A11: Gross Profit | B11: =+B6-B10 -> #REF! | C11: =+C6-C10 -> #REF! | D11: =+D6-D10 -> 270306.93 | E11: =+E6-E10 -> 517612.19 | F11: =+F6-F10 -> 124473.02 | G11: =+G6-G10 -> 476236.46 | H11: =+H6-H10 -> 281088.04 | I11: =+I6-I10 -> 103045.66 | ... P11: =+P6-P10 -> 2925453.9 | Q11: =(C11-P11)/P11 -> #REF! | R11: =+P11-C11 -> #REF!
A12: Gross Profit Margin | B12: =+B11/B6 -> #REF! | C12: =+C11/C6 -> #REF! | D12: =+D11/D6 -> 0.44365182 | E12: =+E11/E6 -> 0.53188383 | F12: =+F11/F6 -> 0.30090319 | G12: =+G11/G6 -> 0.50108228 | H12: =+H11/H6 -> 0.52023939 | I12: =+I11/I6 -> 0.2987089 | ... P12: =+P11/P6 -> 0.46401891
A13: CTS Overheads | B13: 2434714.2 | C13: =#REF!+#REF!+#REF! -> #REF! | D13: ='FY27 Budget - detailed'!H$73 -> 218401.7 | E13: ='FY27 Budget - detailed'!I$73 -> 239717.06 | F13: ='FY27 Budget - detailed'!J$73 -> 231573.15 | G13: ='FY27 Budget - detailed'!K$73 -> 209130.75 | H13: ='FY27 Budget - detailed'!L$73 -> 202345.83 | I13: ='FY27 Budget - detailed'!M$73 -> 201077.04 | J13: ='FY27 Budget - detailed'!N$73 -> 201203.71 | K13: ='FY27 Budget - detailed'!O$73 -> 197422.84 | ... O13: ='FY27 Budget - detailed'!S$73 -> 208102.17 | P13: =D13+E13+F13+G13+H13+I13+J13+K13+L13+M13+N13+O13 -> 2528203.2 | Q13: =(C13-P13)/P13 -> #REF! | R13: =+P13-C13 -> #REF!
A14: Total Expenses | B14: =SUM(B13:B13) -> 2434714.2 | C14: =SUM(C13:C13) -> #REF! | D14: =SUM(D13:D13) -> 218401.7 | E14: =SUM(E13:E13) -> 239717.06 | F14: =SUM(F13:F13) -> 231573.15 | G14: =SUM(G13:G13) -> 209130.75 | H14: =SUM(H13:H13) -> 202345.83 | I14: =SUM(I13:I13) -> 201077.04 | ... O14: =SUM(O13:O13) -> 208102.17 | P14: =D14+E14+F14+G14+H14+I14+J14+K14+L14+M14+N14+O14 -> 2528203.2 | Q14: =(C14-P14)/P14 -> #REF! | R14: =+P14-C14 -> #REF!
A15: Operating Profit | B15: =+B11-B14 -> #REF! | C15: =+C11-C14 -> #REF! | D15: =+D11-D14 -> 51905.235 | E15: =+E11-E14 -> 277895.13 | F15: =+F11-F14 -> -107100.12 | G15: =+G11-G14 -> 267105.71 | H15: =+H11-H14 -> 78742.202 | I15: =+I11-I14 -> -98031.373 | ... P15: =+P11-P14 -> 397250.75 | Q15: =(C15-P15)/P15 -> #REF! | R15: =+P15-C15 -> #REF!
A16: Profit Margin | B16: =+B15/B6 -> #REF! | C16: =+C15/C6 -> #REF! | D16: =+D15/D6 -> 0.085191497 | E16: =+E15/E6 -> 0.28555727 | F16: =+F15/F6 -> -0.25890565 | G16: =+G15/G6 -> 0.28104093 | H16: =+H15/H6 -> 0.14573653 | I16: =+I15/I6 -> -0.28417347 | ... P16: =+P15/P6 -> 0.063009662
A18: Commentary
A19: Respective Revenue Targets were "sense-checked" by DL | E19: =CONS!H33+ONS!G40+PRD!I38 -> 239717.06 | F19: =CONS!I33+ONS!H40+PRD!J38 -> 247510.84 | G19: =CONS!J33+ONS!I40+PRD!K38 -> 247510.84
A20: Total New Business $292K across all departments ($24K/month)
A21: In comparison to a 45k per month forecasted in the previous FY
A22: 12% Increase in CTS Overheads:
A23: - a standard 3.8% was forecasted for wages across the board
A24: - 16K for additional new office expenses
A25: Approved by DL on 19/07/2024

Sheet Sheet1
P3: Notes:
P4: Red tabs are temporary - should be deleted in new FY
A5: Support | B5: 45839 | C5: 45870 | D5: 45901 | E5: 45931 | F5: 45962 | G5: 45992 | H5: 46023 | I5: 46054 | J5: 46082 | K5: 46113 | L5: 46143 | M5: 46174
A6: Budget | B6: 250360.46 | C6: 249340.46 | D6: 241360.46 | E6: 242840.46 | F6: 243860.46 | G6: 243520.46 | H6: 248860.46 | I6: 248520.46 | J6: 249540.46 | K6: 249200.46 | L6: 249540.46 | M6: 237720.46
A7: Forecast | B7: 230051.49 | C7: 222701.08 | D7: 231234.35 | E7: 226930.46 | F7: 225020.46 | G7: 225700.46 | H7: 219590.46 | I7: 218360.46 | J7: 219380.46 | K7: 221290.46 | L7: 233420.46 | M7: 221600.46
A9: Production | B9: 45839 | C9: 45870 | D9: 45901 | E9: 45931 | F9: 45962 | G9: 45992 | H9: 46023 | I9: 46054 | J9: 46082 | K9: 46113 | L9: 46143 | M9: 46174
A10: Budget | B10: 46825 | C10: 298950 | D10: 170580 | E10: 749300 | F10: 316250 | G10: 106490 | H10: 31860 | I10: 303900 | J10: 156100 | K10: 78400 | L10: 134375 | M10: 167050
A11: Forecast | B11: 49635.14 | C11: 302897.09 | D11: 95379.458 | E11: 694120 | F11: 370750 | G11: 103890 | H11: 31860 | I11: 305300 | J11: 156100 | K11: 79800 | L11: 134375 | M11: 168450
A13: Consulting | B13: 45839 | C13: 45870 | D13: 45901 | E13: 45931 | F13: 45962 | G13: 45992 | H13: 46023 | I13: 46054 | J13: 46082 | K13: 46113 | L13: 46143 | M13: 46174
A14: Budget | B14: 69527 | C14: 80527 | D14: 52027 | E14: 79027 | F14: 69027 | G14: 38527 | H14: 37027 | I14: 80027 | J14: 72027 | K14: 61527 | L14: 51500 | M14: 65500
A15: Forecast | B15: 41121.43 | C15: 25871.288 | D15: 29771.061 | E15: 76880 | F15: 69861.5 | G15: 183880 | H15: 39380 | I15: 80380 | J15: 63380 | K15: 62880 | L15: 42853 | M15: 66853
A18: Budget | F18: Forecast
B19: Support Budget | C19: Production Budget | D19: Consulting Budget | E19: Support Forecast | F19: Production Forecast | G19: Consulting Forecast
A20: 45839 | B20: 250360.46 | C20: 46825 | D20: 69527 | E20: 230051.49 | F20: 49635.14 | G20: 41121.43
A21: 45870 | B21: 249340.46 | C21: 298950 | D21: 80527 | E21: 222694.95 | F21: 302890.78 | G21: 25865.16
A22: 45901 | B22: 241360.46 | C22: 170580 | D22: 52027 | E22: 231214.01 | F22: 95358.5 | G22: 29750.72
A23: 45931 | B23: 242840.46 | C23: 749300 | D23: 79027 | E23: 221948.09 | F23: 776911.15 | G23: 36702.62
A24: 45962 | B24: 243860.46 | C24: 316250 | D24: 69027 | E24: 229035.14 | F24: 253388.39 | G24: 24123.65
A25: 45992 | B25: 243520.46 | C25: 106490 | D25: 38527 | E25: 233853.71 | F25: 96218.49 | G25: 22816.11
A26: 46023 | B26: 248860.46 | C26: 31860 | D26: 37027 | E26: 193910.46 | F26: 26360 | G26: 52896.785
A27: 46054 | B27: 248520.46 | C27: 303900 | D27: 80027 | E27: 197600.46 | F27: 294500 | G27: 105726.79
A28: 46082 | B28: 249540.46 | C28: 156100 | D28: 72027 | E28: 223304.56 | F28: 148700 | G28: 272880
A29: 46113 | B29: 249200.46 | C29: 78400 | D29: 61527 | E29: 221162.62 | F29: 103400 | G29: 81380
A30: 46143 | B30: 249540.46 | C30: 134375 | D30: 51500 | E30: 233092.62 | F30: 151300 | G30: 68353
A31: 46174 | B31: 237720.46 | C31: 167050 | D31: 65500 | E31: 221272.62 | F31: 147550 | G31: 1122853

Sheet TO DO
A2: FALSE | B2: Casual Pays needs to be updated for June
A3: TRUE | B3: Em to check overhead bills
A4: TRUE | B4: Check Ptax calcs and input actual pay for the FY on 29/06
A5: TRUE | B5: AL expense update
A6: TRUE | B6: ONS Sales Budget
A7: TRUE | B7: PRD Sales Budget
A8: TRUE | B8: CONS Sales Budget
A9: FALSE | B9: Re-visit CONS Sales budget based on probability
I12: STAFF
I13: Admin | J13: 7
I14: Consulting | J14: 0 | K14: =(J14/67)*$J$13 -> 0 | L14: =K14/$J$13 -> 0
I15: Integration | J15: 1 | K15: =(J15/67)*$J$13 -> 0.10447761 | L15: =K15/$J$13 -> 0.014925373
I16: Onsite | J16: 39 | K16: =(J16/67)*$J$13 -> 4.0746269 | L16: =K16/$J$13 -> 0.58208955
I17: Prouduction | J17: 24 | K17: =(J17/67)*$J$13 -> 2.5074627 | L17: =K17/$J$13 -> 0.35820896
I18: Video | J18: 3 | K18: =(J18/67)*$J$13 -> 0.31343284 | L18: =K18/$J$13 -> 0.044776119
J19: =SUM(J13:J18) -> 74
I22: OFFICE DEPT
I23: Support | J23: 0.0179
I24: Production | J24: 0.875
I25: Video | J25: 0.0713
I26: Consulting | J26: 0.0179
I27: Integration | J27: 0.0179

Sheet FY27 Budget - Actuals
B1: ACTUAL | C1: ACTUAL | D1: ACTUAL | E1: BUDGET | F1: ACTUAL | G1: BUDGET | H1: BUDGET | I1: BUDGET | J1: BUDGET | K1: BUDGET | L1: BUDGET | M1: BUDGET | N1: BUDGET | O1: BUDGET | P1: BUDGET | Q1: BUDGET | R1: BUDGET
B2: FY26 (YTD) | C2: FY27 (YTD) | D2: 46204 | E2: 46204 | F2: 46235 | G2: 46235 | H2: 46266 | I2: 46296 | J2: 46327 | K2: 46357 | L2: 46388 | M2: 46419 | N2: 46447 | O2: 46478 | P2: 46508 | Q2: 46539 | R2: Total | S2: Budget vs Actual | U2: Budget vs LY
A3: Consulting | B3: 944789.64 | C3: =D3+F3 -> 207091.24 | D3: 112803.24 | E3: =CONS!G2 -> 297416.49 | F3: 94288 | G3: =CONS!H2 -> 465645.39 | H3: =CONS!I2 -> 82321.892 | I3: =CONS!J2 -> 100061.89 | J3: =CONS!K2 -> 36337.392 | K3: =CONS!L2 -> 31337.392 | L3: =CONS!M2 -> 27340.652 | M3: =CONS!N2 -> 32340.652 | N3: =CONS!O2 -> 32340.652 | ... Q3: =CONS!R2 -> 8035.0717 | R3: =E3+G3+H3+I3+J3+K3+L3+M3+N3+O3+P3+Q3 -> 1153553.2 | S3: =(C3-R3)/R3 -> -0.82047535 | T3: =+R3-C3 -> 946461.96 | U3: =(R3-B3)/B3 -> 0.22096301 | V3: =+R3-B3 -> 208763.56 | X3: =R3/$R$6 -> 0.18297007
A4: Production | B4: 2444121.4 | C4: =D4+F4 -> 379542.03 | D4: 110900.03 | E4: ='PRD Sales Forecast'!CN64 -> 73000.02 | F4: 268642 | G4: ='PRD Sales Forecast'!CO64 -> 251215.02 | H4: ='PRD Sales Forecast'!CP64 -> 83326.02 | I4: ='PRD Sales Forecast'!CQ64 -> 587307.02 | J4: ='PRD Sales Forecast'!CR64 -> 241601.02 | K4: ='PRD Sales Forecast'!CS64 -> 62316.02 | L4: ='PRD Sales Forecast'!CT64 -> 64261.937 | M4: ='PRD Sales Forecast'!CU64 -> 281912.02 | N4: ='PRD Sales Forecast'!CV64 -> 128882.02 | ... Q4: ='PRD Sales Forecast'!CY64 -> 82637.02 | R4: =E4+G4+H4+I4+J4+K4+L4+M4+N4+O4+P4+Q4 -> 2090722.1 | S4: =(C4-R4)/R4 -> -0.81846366 | T4: =+R4-C4 -> 1711180 | U4: =(R4-B4)/B4 -> -0.14459156 | V4: =+R4-B4 -> -353399.33 | X4: =R4/$R$6 -> 0.33161848
A5: Support | B5: 2724275 | C5: =D5+F5 -> 475638.94 | D5: 235402.94 | E5: =ONS!F6 -> 238860.67 | F5: 240236 | G5: =ONS!G6 -> 256307.33 | H5: =ONS!H6 -> 248016.77 | I5: =ONS!I6 -> 263046.77 | J5: =ONS!J6 -> 262366.77 | K5: =ONS!K6 -> 251316.77 | L5: =ONS!L6 -> 262366.77 | M5: =ONS!M6 -> 262366.77 | N5: =ONS!N6 -> 253016.77 | ... Q5: =ONS!Q6 -> 242443.11 | R5: =E5+G5+H5+I5+J5+K5+L5+M5+N5+O5+P5+Q5 -> 3060325.4 | S5: =(C5-R5)/R5 -> -0.84457896 | T5: =+R5-C5 -> 2584686.4 | U5: =(R5-B5)/B5 -> 0.12335406 | V5: =+R5-B5 -> 336050.39 | X5: =R5/$R$6 -> 0.48541146
A6: Total Income | B6: =SUM(B3:B5) -> 6113186 | C6: =SUM(C3:C5) -> 1062272.2 | D6: =SUM(D3:D5) -> 459106.21 | E6: =SUM(E3:E5) -> 609277.18 | F6: =SUM(F3:F5) -> 603166 | G6: =SUM(G3:G5) -> 973167.74 | H6: =SUM(H3:H5) -> 413664.68 | I6: =SUM(I3:I5) -> 950415.68 | ... Q6: =SUM(Q3:Q5) -> 333115.2 | R6: =E6+G6+H6+I6+J6+K6+L6+M6+N6+O6+P6+Q6 -> 6304600.7 | S6: =(C6-R6)/R6 -> -0.83150841 | T6: =+R6-C6 -> 5242328.4 | U6: =(R6-B6)/B6 -> 0.031311762 | V6: =+R6-B6 -> 191414.62
A7: Consulting Direct Costs | B7: 744807.04 | C7: =D7+F7 -> 182140.37 | D7: 106364.37 | E7: ='FY27 Budget - detailed'!H7 -> 156894.91 | F7: =73229+2547 -> 75776 | G7: ='FY27 Budget - detailed'!I7 -> 239607.17 | H7: ='FY27 Budget - detailed'!J7 -> 50130.112 | I7: ='FY27 Budget - detailed'!K7 -> 58336.599 | J7: ='FY27 Budget - detailed'!L7 -> 27394.352 | K7: ='FY27 Budget - detailed'!M7 -> 23963.88 | L7: ='FY27 Budget - detailed'!N7 -> 21263.504 | M7: ='FY27 Budget - detailed'!O7 -> 24080.807 | N7: ='FY27 Budget - detailed'!P7 -> 25062.909 | ... Q7: ='FY27 Budget - detailed'!S7 -> 17919.298 | R7: =E7+G7+H7+I7+J7+K7+L7+M7+N7+O7+P7+Q7 -> 681494.01 | S7: =(C7-R7)/R7 -> -0.73273372 | T7: =+R7-C7 -> 499353.64 | U7: =(R7-B7)/B7 -> -0.085005949 | V7: =+R7-B7 -> -63313.029
A8: Production Direct Costs | B8: 1172927.9 | C8: =D8+F8 -> 169851.09 | D8: 44738.09 | E8: ='FY27 Budget - detailed'!H11 -> 52683.663 | F8: =120188+4925 -> 125113 | G8: ='FY27 Budget - detailed'!I11 -> 100269.81 | H8: ='FY27 Budget - detailed'!J11 -> 103519.69 | I8: ='FY27 Budget - detailed'!K11 -> 285683.94 | J8: ='FY27 Budget - detailed'!L11 -> 104223.85 | K8: ='FY27 Budget - detailed'!M11 -> 83048.46 | L8: ='FY27 Budget - detailed'!N11 -> 45343.173 | M8: ='FY27 Budget - detailed'!O11 -> 109744.55 | N8: ='FY27 Budget - detailed'!P11 -> 59313.374 | ... Q8: ='FY27 Budget - detailed'!S11 -> 85630.235 | R8: =E8+G8+H8+I8+J8+K8+L8+M8+N8+O8+P8+Q8 -> 1138130.7 | S8: =(C8-R8)/R8 -> -0.8507631 | T8: =+R8-C8 -> 968279.57 | U8: =(R8-B8)/B8 -> -0.029667025 | V8: =+R8-B8 -> -34797.283
A9: Support Direct Costs | B9: 1579333.4 | C9: =D9+F9 -> 266009.69 | D9: 131411.69 | E9: ='FY27 Budget - detailed'!H15 -> 129391.68 | F9: 134598 | G9: ='FY27 Budget - detailed'!I15 -> 115678.57 | H9: ='FY27 Budget - detailed'!J15 -> 135541.85 | I9: ='FY27 Budget - detailed'!K15 -> 130158.68 | J9: ='FY27 Budget - detailed'!L15 -> 127598.94 | K9: ='FY27 Budget - detailed'!M15 -> 134912.18 | L9: ='FY27 Budget - detailed'!N15 -> 112466.56 | M9: ='FY27 Budget - detailed'!O15 -> 116012.62 | N9: ='FY27 Budget - detailed'!P15 -> 142206.77 | ... Q9: ='FY27 Budget - detailed'!S15 -> 139270 | R9: =E9+G9+H9+I9+J9+K9+L9+M9+N9+O9+P9+Q9 -> 1559522.1 | S9: =(C9-R9)/R9 -> -0.82942871 | T9: =+R9-C9 -> 1293512.4 | U9: =(R9-B9)/B9 -> -0.012544084 | V9: =+R9-B9 -> -19811.289
A10: Total Cost of Sales | B10: =SUM(B7:B9) -> 3497068.3 | C10: =SUM(C7:C9) -> 618001.15 | D10: =SUM(D7:D9) -> 282514.15 | E10: =SUM(E7:E9) -> 338970.25 | F10: =SUM(F7:F9) -> 335487 | G10: =SUM(G7:G9) -> 455555.55 | H10: =SUM(H7:H9) -> 289191.66 | I10: =SUM(I7:I9) -> 474179.22 | ... Q10: =SUM(Q7:Q9) -> 242819.53 | R10: =E10+G10+H10+I10+J10+K10+L10+M10+N10+O10+P10+Q10 -> 3379146.7 | S10: =(C10-R10)/R10 -> -0.81711325 | T10: =+R10-C10 -> 2761145.6 | U10: =(R10-B10)/B10 -> -0.033720131 | V10: =+R10-B10 -> -117921.6
A11: Gross Profit | B11: =+B6-B10 -> 2616117.7 | C11: =+C6-C10 -> 444271.06 | D11: =+D6-D10 -> 176592.06 | E11: =+E6-E10 -> 270306.93 | F11: =+F6-F10 -> 267679 | G11: =+G6-G10 -> 517612.19 | H11: =+H6-H10 -> 124473.02 | I11: =+I6-I10 -> 476236.46 | ... Q11: =+Q6-Q10 -> 90295.668 | R11: =E11+G11+H11+I11+J11+K11+L11+M11+N11+O11+P11+Q11 -> 2925453.9 | S11: =(C11-R11)/R11 -> -0.84813603 | T11: =+R11-C11 -> 2481182.9 | U11: =(R11-B11)/B11 -> 0.11824247 | V11: =+R11-B11 -> 309336.22
A12: Gross Profit Margin | B12: =+B11/B6 -> 0.42794669 | C12: =+C11/C6 -> 0.41822713 | D12: =+D11/D6 -> 0.38464315 | E12: =+E11/E6 -> 0.44365182 | F12: =+F11/F6 -> 0.44378994 | G12: =+G11/G6 -> 0.53188383 | H12: =+H11/H6 -> 0.30090319 | I12: =+I11/I6 -> 0.50108228 | ... R12: =+R11/R6 -> 0.46401891
A13: CTS Overheads | B13: 2380904.7 | C13: =D13+F13 -> 411287.76 | D13: 202397.94 | E13: 202397.94 | F13: 208889.82 | G13: ='FY27 Budget - detailed'!I73 -> 239717.06 | H13: ='FY27 Budget - detailed'!J73 -> 231573.15 | I13: ='FY27 Budget - detailed'!K73 -> 209130.75 | J13: ='FY27 Budget - detailed'!L73 -> 202345.83 | K13: ='FY27 Budget - detailed'!M73 -> 201077.04 | L13: ='FY27 Budget - detailed'!N73 -> 201203.71 | M13: ='FY27 Budget - detailed'!O73 -> 197422.84 | N13: ='FY27 Budget - detailed'!P73 -> 211706.91 | ... Q13: ='FY27 Budget - detailed'!S73 -> 208102.17 | R13: =+E13+G13+H13+I13+J13+K13+L13+M13+N13+O13+P13+Q13 -> 2512199.4 | S13: =(C13-R13)/R13 -> -0.83628379 | T13: =+R13-C13 -> 2100911.7 | U13: =(R13-B13)/B13 -> 0.055144903 | V13: =+R13-B13 -> 131294.76
A14: Total Expenses | B14: =SUM(B13:B13) -> 2380904.7 | C14: =SUM(C13:C13) -> 411287.76 | D14: =SUM(D13:D13) -> 202397.94 | E14: =SUM(E13:E13) -> 202397.94 | F14: =SUM(F13:F13) -> 208889.82 | G14: =SUM(G13:G13) -> 239717.06 | H14: =SUM(H13:H13) -> 231573.15 | I14: =SUM(I13:I13) -> 209130.75 | ... Q14: =SUM(Q13:Q13) -> 208102.17 | R14: =+E14+G14+H14+I14+J14+K14+L14+M14+N14+O14+P14+Q14 -> 2512199.4 | S14: =(C14-R14)/R14 -> -0.83628379 | T14: =+R14-C14 -> 2100911.7 | U14: =(R14-B14)/B14 -> 0.055144903 | V14: =+R14-B14 -> 131294.76
A15: Operating Profit | B15: =+B11-B14 -> 235213.04 | C15: =+C11-C14 -> 32983.3 | D15: =+D11-D14 -> -25805.88 | E15: =+E11-E14 -> 67908.991 | F15: =+F11-F14 -> 58789.18 | G15: =+G11-G14 -> 277895.13 | H15: =+H11-H14 -> -107100.12 | I15: =+I11-I14 -> 267105.71 | ... R15: =+R11-R14 -> 413254.51 | S15: =(C15-R15)/R15 -> -0.92018647 | T15: =+R15-C15 -> 380271.21 | U15: =(R15-B15)/B15 -> 0.75693707 | V15: =+R15-B15 -> 178041.47
A16: Profit Margin | B16: =+B15/B6 -> 0.038476343 | C16: =+C15/C6 -> 0.031049763 | D16: =+D15/D6 -> -0.056208954 | E16: =+E15/E6 -> 0.11145829 | F16: =+F15/F6 -> 0.097467662 | G16: =+G15/G6 -> 0.28555727 | H16: =+H15/H6 -> -0.25890565 | I16: =+I15/I6 -> 0.28104093 | ... R16: =+R15/R6 -> 0.065548087
E18: =E13-E20 -> -16003.755 | G18: =G13-G20 -> 0 | H18: =H13-H20 -> -15937.691 | I18: =I13-I20 -> -38380.086 | J18: =J13-J20 -> -43331.854 | K18: =K13-K20 -> -41895.079 | L18: =L13-L20 -> -39345.275 | M18: =M13-M20 -> -43126.143 | N18: =N13-N20 -> -33688.333 | ... Q18: =Q13-Q20 -> -34869.946
E20: =CONS!G33+ONS!F40+PRD!H38 -> 218401.7 | G20: =CONS!H33+ONS!G40+PRD!I38 -> 239717.06 | H20: =CONS!I33+ONS!H40+PRD!J38 -> 247510.84 | I20: =CONS!J33+ONS!I40+PRD!K38 -> 247510.84 | J20: =CONS!K33+ONS!J40+PRD!L38 -> 245677.69 | K20: =CONS!L33+ONS!K40+PRD!M38 -> 242972.12 | L20: =CONS!M33+ONS!L40+PRD!N38 -> 240548.99 | M20: =CONS!N33+ONS!M40+PRD!O38 -> 240548.99 | N20: =CONS!O33+ONS!N40+PRD!P38 -> 245395.25 | ... R20: =CONS!S33+ONS!R40+PRD!T38 -> 1376440.8
E32: Budget Expense commentaries: | M32: Budget Sales commentaries:
E33: ESG Budget reduced to $500 per month | M33: Production: $2.09M (34% of revenue)Support: $3M (47% of revenue)Consulting: $1.10M (18% of revenue)
E34: Instant Asset reduced to $5k per month | M34: Revenue is forecast to be strongest during: October ($921K for AGM Season) August ($951K where $400k worth of consulting work becomes realised)
E35: IT Support increased by $36k | M35: Support services remain the largest contributor to revenue, followed by Production, indicating the business continues to rely on recurring operational work rather than project-based consulting.
E36: CTS 20-year anniversary budgeted at $8.5k in Aug
E37: Headcount: Budget removed for Office Admin, Head of HR, 2 Prod technicians, 1 Cons intern
E38: Website update cost in Aug $12k
E39: CTS Logo Update $9.3k
E40: Salary increases factored in 3%
N42: CONS | O42: ONS | P42: PRD
M43: N/E | N43: ='CONS Sales Forecast'!EE16+'CONS Sales Forecast'!EE17 -> 31392 | O43: ='ONS Sales Forecast'!DI38 -> 45000 | P43: ='PRD Sales Forecast'!CZ4+'PRD Sales Forecast'!DP4 -> 120000 | Q43: =SUM(N43:P43) -> 196392 | R43: =Q43/$Q$47 -> 0.031150585
M44: N/N | O44: ='ONS Sales Forecast'!DI8 -> 131483.3 | P44: ='PRD Sales Forecast'!CZ5+'PRD Sales Forecast'!DP5 -> 90000 | Q44: =SUM(N44:P44) -> 221483.3 | R44: =Q44/$Q$47 -> 0.035130425
M45: E/E | N45: ='CONS Sales Forecast'!EE67-'FY27 Budget - Actuals'!N43 -> 1122161.2 | O45: ='ONS Sales Forecast'!DI61-'FY27 Budget - Actuals'!O43-'FY27 Budget - Actuals'!O44 -> 2883842.1 | P45: ='PRD Sales Forecast'!CZ51+'PRD Sales Forecast'!DP51-'FY27 Budget - Actuals'!P43-'FY27 Budget - Actuals'!P44 -> 1880722.1 | Q45: =SUM(N45:P45) -> 5886725.4 | R45: =Q45/$Q$47 -> 0.93371899
N47: =SUM(N43:N46) -> 1153553.2 | O47: =SUM(O43:O46) -> 3060325.4 | P47: =SUM(P43:P46) -> 2090722.1 | Q47: =SUM(Q43:Q46) -> 6304600.7
M49: Business Services | N49: =SUMIF('CONS Sales Forecast'!$DO$4:$DO$30,M49,'CONS Sales Forecast'!$EE$4:$EE$30) -> 0 | O49: =SUMIF('ONS Sales Forecast'!$CU$4:$CU$52,M49,'ONS Sales Forecast'!$DI$4:$DI$52) -> 1743442.4 | P49: =SUMIF('PRD Sales Forecast'!$CL$4:$CL$49,M49,'PRD Sales Forecast'!$CZ$4:$CZ$49)+SUMIF('PRD Sales Forecast'!$DB$4:$DB$49,M49,'PRD Sales Forecast'!$DP$4:$DP$49) -> 84352 | Q49: =SUM(N49:P49) -> 1827794.4 | R49: =Q49/$R$6 -> 0.28991438
M50: Finance | N50: =SUMIF('CONS Sales Forecast'!$DO$4:$DO$30,M50,'CONS Sales Forecast'!$EE$4:$EE$30) -> 802388 | O50: =SUMIF('ONS Sales Forecast'!$CU$4:$CU$52,M50,'ONS Sales Forecast'!$DI$4:$DI$52) -> 1147695.3 | P50: =SUMIF('PRD Sales Forecast'!$CL$4:$CL$49,M50,'PRD Sales Forecast'!$CZ$4:$CZ$49)+SUMIF('PRD Sales Forecast'!$DB$4:$DB$49,M50,'PRD Sales Forecast'!$DP$4:$DP$49) -> 877754.63 | Q50: =SUM(N50:P50) -> 2827837.9 | R50: =Q50/$R$6 -> 0.44853561
M51: IT & Media | N51: =SUMIF('CONS Sales Forecast'!$DO$4:$DO$30,M51,'CONS Sales Forecast'!$EE$4:$EE$30) -> 65575 | O51: =SUMIF('ONS Sales Forecast'!$CU$4:$CU$52,M51,'ONS Sales Forecast'!$DI$4:$DI$52) -> 169187.76 | P51: =SUMIF('PRD Sales Forecast'!$CL$4:$CL$49,M51,'PRD Sales Forecast'!$CZ$4:$CZ$49)+SUMIF('PRD Sales Forecast'!$DB$4:$DB$49,M51,'PRD Sales Forecast'!$DP$4:$DP$49) -> 235215.2 | Q51: =SUM(N51:P51) -> 469977.96 | R51: =Q51/$R$6 -> 0.074545239
M52: Energy, Utilities, Infrastructure | N52: =SUMIF('CONS Sales Forecast'!$DO$4:$DO$30,M52,'CONS Sales Forecast'!$EE$4:$EE$30) -> 37402.4 | O52: =SUMIF('ONS Sales Forecast'!$CU$4:$CU$52,M52,'ONS Sales Forecast'!$DI$4:$DI$52) -> 0 | P52: =SUMIF('PRD Sales Forecast'!$CL$4:$CL$49,M52,'PRD Sales Forecast'!$CZ$4:$CZ$49)+SUMIF('PRD Sales Forecast'!$DB$4:$DB$49,M52,'PRD Sales Forecast'!$DP$4:$DP$49) -> 465848.24 | Q52: =SUM(N52:P52) -> 503250.64 | R52: =Q52/$R$6 -> 0.079822762
M53: Other Sectors (Schools, Hospitals, etc) | N53: =SUMIF('CONS Sales Forecast'!$DO$4:$DO$30,M53,'CONS Sales Forecast'!$EE$4:$EE$30) -> 31392 | O53: =SUMIF('ONS Sales Forecast'!$CU$4:$CU$52,M53,'ONS Sales Forecast'!$DI$4:$DI$52) -> 0 | P53: =SUMIF('PRD Sales Forecast'!$CL$4:$CL$49,M53,'PRD Sales Forecast'!$CZ$4:$CZ$49)+SUMIF('PRD Sales Forecast'!$DB$4:$DB$49,M53,'PRD Sales Forecast'!$DP$4:$DP$49) -> 107132 | Q53: =SUM(N53:P53) -> 138524 | R53: =Q53/$R$6 -> 0.021971891
M54: Government | N54: =SUMIF('CONS Sales Forecast'!$DO$4:$DO$30,M54,'CONS Sales Forecast'!$EE$4:$EE$30) -> 207795.8 | O54: =SUMIF('ONS Sales Forecast'!$CU$4:$CU$52,M54,'ONS Sales Forecast'!$DI$4:$DI$52) -> 0 | P54: =SUMIF('PRD Sales Forecast'!$CL$4:$CL$49,M54,'PRD Sales Forecast'!$CZ$4:$CZ$49)+SUMIF('PRD Sales Forecast'!$DB$4:$DB$49,M54,'PRD Sales Forecast'!$DP$4:$DP$49) -> 0 | Q54: =SUM(N54:P54) -> 207795.8 | R54: =Q54/$R$6 -> 0.032959391
M55: Health | N55: =SUMIF('CONS Sales Forecast'!$DO$4:$DO$30,M55,'CONS Sales Forecast'!$EE$4:$EE$30) -> 0 | O55: =SUMIF('ONS Sales Forecast'!$CU$4:$CU$52,M55,'ONS Sales Forecast'!$DI$4:$DI$52) -> 0 | P55: =SUMIF('PRD Sales Forecast'!$CL$4:$CL$49,M55,'PRD Sales Forecast'!$CZ$4:$CZ$49)+SUMIF('PRD Sales Forecast'!$DB$4:$DB$49,M55,'PRD Sales Forecast'!$DP$4:$DP$49) -> 105420 | Q55: =SUM(N55:P55) -> 105420 | R55: =Q55/$R$6 -> 0.016721123
M56: Education | N56: =SUMIF('CONS Sales Forecast'!$DO$4:$DO$30,M56,'CONS Sales Forecast'!$EE$4:$EE$30) -> 0 | O56: =SUMIF('ONS Sales Forecast'!$CU$4:$CU$52,M56,'ONS Sales Forecast'!$DI$4:$DI$52) -> 0 | P56: =SUMIF('PRD Sales Forecast'!$CL$4:$CL$49,M56,'PRD Sales Forecast'!$CZ$4:$CZ$49)+SUMIF('PRD Sales Forecast'!$DB$4:$DB$49,M56,'PRD Sales Forecast'!$DP$4:$DP$49) -> 5000 | Q56: =SUM(N56:P56) -> 5000 | R56: =Q56/$R$6 -> 0.00079307164
N57: =SUM(N49:N56) -> 1144553.2 | O57: =SUM(O49:O56) -> 3060325.4 | P57: =SUM(P49:P56) -> 1880722.1

Sheet FY27 Budget
B1: ACTUAL | C1: ACTUAL | D1: BUDGET | E1: BUDGET | F1: BUDGET | G1: BUDGET | H1: BUDGET | I1: BUDGET | J1: BUDGET | K1: BUDGET | L1: BUDGET | M1: BUDGET | N1: BUDGET | O1: BUDGET | P1: BUDGET
B2: FY26 (YTD) | C2: FY27 (YTD) | D2: 46204 | E2: 46235 | F2: 46266 | G2: 46296 | H2: 46327 | I2: 46357 | J2: 46388 | K2: 46419 | L2: 46447 | M2: 46478 | N2: 46508 | O2: 46539 | P2: Total | Q2: Budget vs Actual | S2: Budget vs LY
A3: Consulting | B3: 944789.64 | C3: 0 | D3: =CONS!G2 -> 297416.49 | E3: =CONS!H2 -> 465645.39 | F3: =CONS!I2 -> 82321.892 | G3: =CONS!J2 -> 100061.89 | H3: =CONS!K2 -> 36337.392 | I3: =CONS!L2 -> 31337.392 | J3: =CONS!M2 -> 27340.652 | K3: =CONS!N2 -> 32340.652 | ... O3: =CONS!R2 -> 8035.0717 | P3: =D3+E3+F3+G3+H3+I3+J3+K3+L3+M3+N3+O3 -> 1153553.2 | Q3: =(C3-P3)/P3 -> -1 | R3: =+P3-C3 -> 1153553.2 | S3: =(P3-B3)/B3 -> 0.22096301 | T3: =+P3-B3 -> 208763.56 | V3: =P3/$P$6 -> 0.18297007
A4: Production | B4: 2444121.4 | C4: 0 | D4: ='PRD Sales Forecast'!CN64 -> 73000.02 | E4: ='PRD Sales Forecast'!CO64 -> 251215.02 | F4: ='PRD Sales Forecast'!CP64 -> 83326.02 | G4: ='PRD Sales Forecast'!CQ64 -> 587307.02 | H4: ='PRD Sales Forecast'!CR64 -> 241601.02 | I4: ='PRD Sales Forecast'!CS64 -> 62316.02 | J4: ='PRD Sales Forecast'!CT64 -> 64261.937 | K4: ='PRD Sales Forecast'!CU64 -> 281912.02 | ... O4: ='PRD Sales Forecast'!CY64 -> 82637.02 | P4: =D4+E4+F4+G4+H4+I4+J4+K4+L4+M4+N4+O4 -> 2090722.1 | Q4: =(C4-P4)/P4 -> -1 | R4: =+P4-C4 -> 2090722.1 | S4: =(P4-B4)/B4 -> -0.14459156 | T4: =+P4-B4 -> -353399.33 | V4: =P4/$P$6 -> 0.33161848
A5: Support | B5: 2724275 | C5: 0 | D5: =ONS!F6 -> 238860.67 | E5: =ONS!G6 -> 256307.33 | F5: =ONS!H6 -> 248016.77 | G5: =ONS!I6 -> 263046.77 | H5: =ONS!J6 -> 262366.77 | I5: =ONS!K6 -> 251316.77 | J5: =ONS!L6 -> 262366.77 | K5: =ONS!M6 -> 262366.77 | ... O5: =ONS!Q6 -> 242443.11 | P5: =D5+E5+F5+G5+H5+I5+J5+K5+L5+M5+N5+O5 -> 3060325.4 | Q5: =(C5-P5)/P5 -> -1 | R5: =+P5-C5 -> 3060325.4 | S5: =(P5-B5)/B5 -> 0.12335406 | T5: =+P5-B5 -> 336050.39 | V5: =P5/$P$6 -> 0.48541146
A6: Total Income | B6: =SUM(B3:B5) -> 6113186 | C6: =SUM(C3:C5) -> 0 | D6: =SUM(D3:D5) -> 609277.18 | E6: =SUM(E3:E5) -> 973167.74 | F6: =SUM(F3:F5) -> 413664.68 | G6: =SUM(G3:G5) -> 950415.68 | H6: =SUM(H3:H5) -> 540305.18 | I6: =SUM(I3:I5) -> 344970.18 | ... O6: =SUM(O3:O5) -> 333115.2 | P6: =D6+E6+F6+G6+H6+I6+J6+K6+L6+M6+N6+O6 -> 6304600.7 | Q6: =(C6-P6)/P6 -> -1 | R6: =+P6-C6 -> 6304600.7 | S6: =(P6-B6)/B6 -> 0.031311762 | T6: =+P6-B6 -> 191414.62
A7: Consulting Direct Costs | B7: 744807.04 | C7: 0 | D7: ='FY27 Budget - detailed'!H7 -> 156894.91 | E7: ='FY27 Budget - detailed'!I7 -> 239607.17 | F7: ='FY27 Budget - detailed'!J7 -> 50130.112 | G7: ='FY27 Budget - detailed'!K7 -> 58336.599 | H7: ='FY27 Budget - detailed'!L7 -> 27394.352 | I7: ='FY27 Budget - detailed'!M7 -> 23963.88 | J7: ='FY27 Budget - detailed'!N7 -> 21263.504 | K7: ='FY27 Budget - detailed'!O7 -> 24080.807 | ... O7: ='FY27 Budget - detailed'!S7 -> 17919.298 | P7: =D7+E7+F7+G7+H7+I7+J7+K7+L7+M7+N7+O7 -> 681494.01 | Q7: =(C7-P7)/P7 -> -1 | R7: =+P7-C7 -> 681494.01 | S7: =(P7-B7)/B7 -> -0.085005949 | T7: =+P7-B7 -> -63313.029
A8: Production Direct Costs | B8: 1172927.9 | C8: 0 | D8: ='FY27 Budget - detailed'!H11 -> 52683.663 | E8: ='FY27 Budget - detailed'!I11 -> 100269.81 | F8: ='FY27 Budget - detailed'!J11 -> 103519.69 | G8: ='FY27 Budget - detailed'!K11 -> 285683.94 | H8: ='FY27 Budget - detailed'!L11 -> 104223.85 | I8: ='FY27 Budget - detailed'!M11 -> 83048.46 | J8: ='FY27 Budget - detailed'!N11 -> 45343.173 | K8: ='FY27 Budget - detailed'!O11 -> 109744.55 | ... O8: ='FY27 Budget - detailed'!S11 -> 85630.235 | P8: =D8+E8+F8+G8+H8+I8+J8+K8+L8+M8+N8+O8 -> 1138130.7 | Q8: =(C8-P8)/P8 -> -1 | R8: =+P8-C8 -> 1138130.7 | S8: =(P8-B8)/B8 -> -0.029667025 | T8: =+P8-B8 -> -34797.283
A9: Support Direct Costs | B9: 1579333.4 | C9: 0 | D9: ='FY27 Budget - detailed'!H15 -> 129391.68 | E9: ='FY27 Budget - detailed'!I15 -> 115678.57 | F9: ='FY27 Budget - detailed'!J15 -> 135541.85 | G9: ='FY27 Budget - detailed'!K15 -> 130158.68 | H9: ='FY27 Budget - detailed'!L15 -> 127598.94 | I9: ='FY27 Budget - detailed'!M15 -> 134912.18 | J9: ='FY27 Budget - detailed'!N15 -> 112466.56 | K9: ='FY27 Budget - detailed'!O15 -> 116012.62 | ... O9: ='FY27 Budget - detailed'!S15 -> 139270 | P9: =D9+E9+F9+G9+H9+I9+J9+K9+L9+M9+N9+O9 -> 1559522.1 | Q9: =(C9-P9)/P9 -> -1 | R9: =+P9-C9 -> 1559522.1 | S9: =(P9-B9)/B9 -> -0.012544084 | T9: =+P9-B9 -> -19811.289
A10: Total Cost of Sales | B10: =SUM(B7:B9) -> 3497068.3 | C10: =SUM(C7:C9) -> 0 | D10: =SUM(D7:D9) -> 338970.25 | E10: =SUM(E7:E9) -> 455555.55 | F10: =SUM(F7:F9) -> 289191.66 | G10: =SUM(G7:G9) -> 474179.22 | H10: =SUM(H7:H9) -> 259217.14 | I10: =SUM(I7:I9) -> 241924.52 | ... O10: =SUM(O7:O9) -> 242819.53 | P10: =D10+E10+F10+G10+H10+I10+J10+K10+L10+M10+N10+O10 -> 3379146.7 | Q10: =(C10-P10)/P10 -> -1 | R10: =+P10-C10 -> 3379146.7 | S10: =(P10-B10)/B10 -> -0.033720131 | T10: =+P10-B10 -> -117921.6
A11: Gross Profit | B11: =+B6-B10 -> 2616117.7 | C11: =+C6-C10 -> 0 | D11: =+D6-D10 -> 270306.93 | E11: =+E6-E10 -> 517612.19 | F11: =+F6-F10 -> 124473.02 | G11: =+G6-G10 -> 476236.46 | H11: =+H6-H10 -> 281088.04 | I11: =+I6-I10 -> 103045.66 | ... O11: =+O6-O10 -> 90295.668 | P11: =D11+E11+F11+G11+H11+I11+J11+K11+L11+M11+N11+O11 -> 2925453.9 | Q11: =(C11-P11)/P11 -> -1 | R11: =+P11-C11 -> 2925453.9 | S11: =(P11-B11)/B11 -> 0.11824247 | T11: =+P11-B11 -> 309336.22
A12: Gross Profit Margin | B12: =+B11/B6 -> 0.42794669 | C12: =+C11/C6 -> #DIV/0! | D12: =+D11/D6 -> 0.44365182 | E12: =+E11/E6 -> 0.53188383 | F12: =+F11/F6 -> 0.30090319 | G12: =+G11/G6 -> 0.50108228 | H12: =+H11/H6 -> 0.52023939 | I12: =+I11/I6 -> 0.2987089 | ... P12: =+P11/P6 -> 0.46401891
A13: CTS Overheads | B13: 2380904.7 | C13: 0 | D13: ='FY27 Budget - detailed'!H73 -> 218401.7 | E13: ='FY27 Budget - detailed'!I73 -> 239717.06 | F13: ='FY27 Budget - detailed'!J73 -> 231573.15 | G13: ='FY27 Budget - detailed'!K73 -> 209130.75 | H13: ='FY27 Budget - detailed'!L73 -> 202345.83 | I13: ='FY27 Budget - detailed'!M73 -> 201077.04 | J13: ='FY27 Budget - detailed'!N73 -> 201203.71 | K13: ='FY27 Budget - detailed'!O73 -> 197422.84 | ... O13: ='FY27 Budget - detailed'!S73 -> 208102.17 | P13: =+D13+E13+F13+G13+H13+I13+J13+K13+L13+M13+N13+O13 -> 2528203.2 | Q13: =(C13-P13)/P13 -> -1 | R13: =+P13-C13 -> 2528203.2 | S13: =(P13-B13)/B13 -> 0.061866615 | T13: =+P13-B13 -> 147298.51
A14: Total Expenses | B14: =SUM(B13:B13) -> 2380904.7 | C14: =SUM(C13:C13) -> 0 | D14: =SUM(D13:D13) -> 218401.7 | E14: =SUM(E13:E13) -> 239717.06 | F14: =SUM(F13:F13) -> 231573.15 | G14: =SUM(G13:G13) -> 209130.75 | H14: =SUM(H13:H13) -> 202345.83 | I14: =SUM(I13:I13) -> 201077.04 | ... O14: =SUM(O13:O13) -> 208102.17 | P14: =+D14+E14+F14+G14+H14+I14+J14+K14+L14+M14+N14+O14 -> 2528203.2 | Q14: =(C14-P14)/P14 -> -1 | R14: =+P14-C14 -> 2528203.2 | S14: =(P14-B14)/B14 -> 0.061866615 | T14: =+P14-B14 -> 147298.51
A15: Operating Profit | B15: =+B11-B14 -> 235213.04 | C15: =+C11-C14 -> 0 | D15: =+D11-D14 -> 51905.235 | E15: =+E11-E14 -> 277895.13 | F15: =+F11-F14 -> -107100.12 | G15: =+G11-G14 -> 267105.71 | H15: =+H11-H14 -> 78742.202 | I15: =+I11-I14 -> -98031.373 | ... P15: =+P11-P14 -> 397250.75 | Q15: =(C15-P15)/P15 -> -1 | R15: =+P15-C15 -> 397250.75 | S15: =(P15-B15)/B15 -> 0.68889766 | T15: =+P15-B15 -> 162037.71
A16: Profit Margin | B16: =+B15/B6 -> 0.038476343 | C16: =+C15/C6 -> #DIV/0! | D16: =+D15/D6 -> 0.085191497 | E16: =+E15/E6 -> 0.28555727 | F16: =+F15/F6 -> -0.25890565 | G16: =+G15/G6 -> 0.28104093 | H16: =+H15/H6 -> 0.14573653 | I16: =+I15/I6 -> -0.28417347 | ... P16: =+P15/P6 -> 0.063009662
D18: =D13-D20 -> 0 | E18: =E13-E20 -> 0 | F18: =F13-F20 -> -15937.691 | G18: =G13-G20 -> -38380.086 | H18: =H13-H20 -> -43331.854 | I18: =I13-I20 -> -41895.079 | J18: =J13-J20 -> -39345.275 | K18: =K13-K20 -> -43126.143 | ... O18: =O13-O20 -> -34869.946
D20: =CONS!G33+ONS!F40+PRD!H38 -> 218401.7 | E20: =CONS!H33+ONS!G40+PRD!I38 -> 239717.06 | F20: =CONS!I33+ONS!H40+PRD!J38 -> 247510.84 | G20: =CONS!J33+ONS!I40+PRD!K38 -> 247510.84 | H20: =CONS!K33+ONS!J40+PRD!L38 -> 245677.69 | I20: =CONS!L33+ONS!K40+PRD!M38 -> 242972.12 | J20: =CONS!M33+ONS!L40+PRD!N38 -> 240548.99 | K20: =CONS!N33+ONS!M40+PRD!O38 -> 240548.99 | ... P20: =CONS!S33+ONS!R40+PRD!T38 -> 1376440.8
D32: Budget Expense commentaries: | K32: Budget Sales commentaries:
D33: ESG Budget reduced to $500 per month | K33: Production: $2.09M (34% of revenue)Support: $3M (47% of revenue)Consulting: $1.10M (18% of revenue)
D34: Instant Asset reduced to $5k per month | K34: Revenue is forecast to be strongest during: October ($921K for AGM Season) August ($951K where $400k worth of consulting work becomes realised)
D35: IT Support increased by $36k | K35: Support services remain the largest contributor to revenue, followed by Production, indicating the business continues to rely on recurring operational work rather than project-based consulting.
D36: CTS 20-year anniversary budgeted at $8.5k in Aug
D37: Headcount: Budget removed for Office Admin, Head of HR, 2 Prod technicians, 1 Cons intern
D38: Website update cost in Aug $12k
D39: CTS Logo Update $9.3k
D40: Salary increases factored in 3%
L42: CONS | M42: ONS | N42: PRD
K43: N/E | L43: ='CONS Sales Forecast'!EE16+'CONS Sales Forecast'!EE17 -> 31392 | M43: ='ONS Sales Forecast'!DI38 -> 45000 | N43: ='PRD Sales Forecast'!CZ4+'PRD Sales Forecast'!DP4 -> 120000 | O43: =SUM(L43:N43) -> 196392 | P43: =O43/$O$47 -> 0.031150585
K44: N/N | M44: ='ONS Sales Forecast'!DI8 -> 131483.3 | N44: ='PRD Sales Forecast'!CZ5+'PRD Sales Forecast'!DP5 -> 90000 | O44: =SUM(L44:N44) -> 221483.3 | P44: =O44/$O$47 -> 0.035130425
K45: E/E | L45: ='CONS Sales Forecast'!EE67-'FY27 Budget'!L43 -> 1122161.2 | M45: ='ONS Sales Forecast'!DI61-'FY27 Budget'!M43-'FY27 Budget'!M44 -> 2883842.1 | N45: ='PRD Sales Forecast'!CZ51+'PRD Sales Forecast'!DP51-'FY27 Budget'!N43-'FY27 Budget'!N44 -> 1880722.1 | O45: =SUM(L45:N45) -> 5886725.4 | P45: =O45/$O$47 -> 0.93371899
L47: =SUM(L43:L46) -> 1153553.2 | M47: =SUM(M43:M46) -> 3060325.4 | N47: =SUM(N43:N46) -> 2090722.1 | O47: =SUM(O43:O46) -> 6304600.7
K49: Business Services | L49: =SUMIF('CONS Sales Forecast'!$DO$4:$DO$30,K49,'CONS Sales Forecast'!$EE$4:$EE$30) -> 0 | M49: =SUMIF('ONS Sales Forecast'!$CU$4:$CU$52,K49,'ONS Sales Forecast'!$DI$4:$DI$52) -> 1743442.4 | N49: =SUMIF('PRD Sales Forecast'!$CL$4:$CL$49,K49,'PRD Sales Forecast'!$CZ$4:$CZ$49)+SUMIF('PRD Sales Forecast'!$DB$4:$DB$49,K49,'PRD Sales Forecast'!$DP$4:$DP$49) -> 84352 | O49: =SUM(L49:N49) -> 1827794.4 | P49: =O49/$P$6 -> 0.28991438
K50: Finance | L50: =SUMIF('CONS Sales Forecast'!$DO$4:$DO$30,K50,'CONS Sales Forecast'!$EE$4:$EE$30) -> 802388 | M50: =SUMIF('ONS Sales Forecast'!$CU$4:$CU$52,K50,'ONS Sales Forecast'!$DI$4:$DI$52) -> 1147695.3 | N50: =SUMIF('PRD Sales Forecast'!$CL$4:$CL$49,K50,'PRD Sales Forecast'!$CZ$4:$CZ$49)+SUMIF('PRD Sales Forecast'!$DB$4:$DB$49,K50,'PRD Sales Forecast'!$DP$4:$DP$49) -> 877754.63 | O50: =SUM(L50:N50) -> 2827837.9 | P50: =O50/$P$6 -> 0.44853561
K51: IT & Media | L51: =SUMIF('CONS Sales Forecast'!$DO$4:$DO$30,K51,'CONS Sales Forecast'!$EE$4:$EE$30) -> 65575 | M51: =SUMIF('ONS Sales Forecast'!$CU$4:$CU$52,K51,'ONS Sales Forecast'!$DI$4:$DI$52) -> 169187.76 | N51: =SUMIF('PRD Sales Forecast'!$CL$4:$CL$49,K51,'PRD Sales Forecast'!$CZ$4:$CZ$49)+SUMIF('PRD Sales Forecast'!$DB$4:$DB$49,K51,'PRD Sales Forecast'!$DP$4:$DP$49) -> 235215.2 | O51: =SUM(L51:N51) -> 469977.96 | P51: =O51/$P$6 -> 0.074545239
K52: Energy, Utilities, Infrastructure | L52: =SUMIF('CONS Sales Forecast'!$DO$4:$DO$30,K52,'CONS Sales Forecast'!$EE$4:$EE$30) -> 37402.4 | M52: =SUMIF('ONS Sales Forecast'!$CU$4:$CU$52,K52,'ONS Sales Forecast'!$DI$4:$DI$52) -> 0 | N52: =SUMIF('PRD Sales Forecast'!$CL$4:$CL$49,K52,'PRD Sales Forecast'!$CZ$4:$CZ$49)+SUMIF('PRD Sales Forecast'!$DB$4:$DB$49,K52,'PRD Sales Forecast'!$DP$4:$DP$49) -> 465848.24 | O52: =SUM(L52:N52) -> 503250.64 | P52: =O52/$P$6 -> 0.079822762
K53: Other Sectors (Schools, Hospitals, etc) | L53: =SUMIF('CONS Sales Forecast'!$DO$4:$DO$30,K53,'CONS Sales Forecast'!$EE$4:$EE$30) -> 31392 | M53: =SUMIF('ONS Sales Forecast'!$CU$4:$CU$52,K53,'ONS Sales Forecast'!$DI$4:$DI$52) -> 0 | N53: =SUMIF('PRD Sales Forecast'!$CL$4:$CL$49,K53,'PRD Sales Forecast'!$CZ$4:$CZ$49)+SUMIF('PRD Sales Forecast'!$DB$4:$DB$49,K53,'PRD Sales Forecast'!$DP$4:$DP$49) -> 107132 | O53: =SUM(L53:N53) -> 138524 | P53: =O53/$P$6 -> 0.021971891
K54: Government | L54: =SUMIF('CONS Sales Forecast'!$DO$4:$DO$30,K54,'CONS Sales Forecast'!$EE$4:$EE$30) -> 207795.8 | M54: =SUMIF('ONS Sales Forecast'!$CU$4:$CU$52,K54,'ONS Sales Forecast'!$DI$4:$DI$52) -> 0 | N54: =SUMIF('PRD Sales Forecast'!$CL$4:$CL$49,K54,'PRD Sales Forecast'!$CZ$4:$CZ$49)+SUMIF('PRD Sales Forecast'!$DB$4:$DB$49,K54,'PRD Sales Forecast'!$DP$4:$DP$49) -> 0 | O54: =SUM(L54:N54) -> 207795.8 | P54: =O54/$P$6 -> 0.032959391
K55: Health | L55: =SUMIF('CONS Sales Forecast'!$DO$4:$DO$30,K55,'CONS Sales Forecast'!$EE$4:$EE$30) -> 0 | M55: =SUMIF('ONS Sales Forecast'!$CU$4:$CU$52,K55,'ONS Sales Forecast'!$DI$4:$DI$52) -> 0 | N55: =SUMIF('PRD Sales Forecast'!$CL$4:$CL$49,K55,'PRD Sales Forecast'!$CZ$4:$CZ$49)+SUMIF('PRD Sales Forecast'!$DB$4:$DB$49,K55,'PRD Sales Forecast'!$DP$4:$DP$49) -> 105420 | O55: =SUM(L55:N55) -> 105420 | P55: =O55/$P$6 -> 0.016721123
K56: Education | L56: =SUMIF('CONS Sales Forecast'!$DO$4:$DO$30,K56,'CONS Sales Forecast'!$EE$4:$EE$30) -> 0 | M56: =SUMIF('ONS Sales Forecast'!$CU$4:$CU$52,K56,'ONS Sales Forecast'!$DI$4:$DI$52) -> 0 | N56: =SUMIF('PRD Sales Forecast'!$CL$4:$CL$49,K56,'PRD Sales Forecast'!$CZ$4:$CZ$49)+SUMIF('PRD Sales Forecast'!$DB$4:$DB$49,K56,'PRD Sales Forecast'!$DP$4:$DP$49) -> 5000 | O56: =SUM(L56:N56) -> 5000 | P56: =O56/$P$6 -> 0.00079307164
L57: =SUM(L49:L56) -> 1144553.2 | M57: =SUM(M49:M56) -> 3060325.4 | N57: =SUM(N49:N56) -> 1880722.1

Sheet FY27 Budget - detailed
A1: 46235 | H1: FORECAST | I1: FORECAST | J1: FORECAST | K1: FORECAST | L1: FORECAST | M1: FORECAST | N1: FORECAST | O1: FORECAST | P1: FORECAST | Q1: FORECAST | R1: FORECAST | S1: FORECAST | T1: FORECAST
H2: 46204 | I2: 46235 | J2: 46266 | K2: 46296 | L2: 46327 | M2: 46357 | N2: 46388 | O2: 46419 | P2: 46447 | Q2: 46478 | R2: 46508 | S2: 46539 | T2: Total | U2: Variance
G3: Consulting | H3: =CONS!G2 -> 297416.49 | I3: =CONS!H2 -> 465645.39 | J3: =CONS!I2 -> 82321.892 | K3: =CONS!J2 -> 100061.89 | L3: =CONS!K2 -> 36337.392 | M3: =CONS!L2 -> 31337.392 | N3: =CONS!M2 -> 27340.652 | O3: =CONS!N2 -> 32340.652 | ... S3: =CONS!R2 -> 8035.0717 | T3: =SUM(H3:S3) -> 1153553.2 | V3: =T3=CONS!S2 -> TRUE
G4: Production | H4: =PRD!H3 -> 73000.02 | I4: =PRD!I3 -> 251215.02 | J4: =PRD!J3 -> 83326.02 | K4: =PRD!K3 -> 587307.02 | L4: =PRD!L3 -> 241601.02 | M4: =PRD!M3 -> 62316.02 | N4: =PRD!N3 -> 64261.937 | O4: =PRD!O3 -> 281912.02 | ... S4: =PRD!S3 -> 82637.02 | T4: =SUM(H4:S4) -> 2090722.1 | V4: =T4=PRD!T2 -> TRUE
G5: Onsite | H5: =ONS!F6 -> 238860.67 | I5: =ONS!G6 -> 256307.33 | J5: =ONS!H6 -> 248016.77 | K5: =ONS!I6 -> 263046.77 | L5: =ONS!J6 -> 262366.77 | M5: =ONS!K6 -> 251316.77 | N5: =ONS!L6 -> 262366.77 | O5: =ONS!M6 -> 262366.77 | ... S5: =ONS!Q6 -> 242443.11 | T5: =SUM(H5:S5) -> 3060325.4 | V5: =T5=ONS!R6 -> TRUE
G6: Total Income | H6: =SUM(H3:H5) -> 609277.18 | I6: =SUM(I3:I5) -> 973167.74 | J6: =SUM(J3:J5) -> 413664.68 | K6: =SUM(K3:K5) -> 950415.68 | L6: =SUM(L3:L5) -> 540305.18 | M6: =SUM(M3:M5) -> 344970.18 | N6: =SUM(N3:N5) -> 353969.36 | O6: =SUM(O3:O5) -> 576619.44 | ... S6: =SUM(S3:S5) -> 333115.2 | T6: =SUM(H6:S6) -> 6304600.7
G7: Consulting COS | H7: =-CONS!G10 -> 156894.91 | I7: =-CONS!H10 -> 239607.17 | J7: =-CONS!I10 -> 50130.112 | K7: =-CONS!J10 -> 58336.599 | L7: =-CONS!K10 -> 27394.352 | M7: =-CONS!L10 -> 23963.88 | N7: =-CONS!M10 -> 21263.504 | O7: =-CONS!N10 -> 24080.807 | ... S7: =-CONS!R10 -> 17919.298 | T7: =SUM(H7:S7) -> 681494.01 | U7: =T7=-CONS!S10 -> TRUE | V7: =CONS!S10 -> -681494.01
G8: Labour | H8: =-CONS!G5-CONS!G6 -> 7209.615 | I8: =-CONS!H5-CONS!H6 -> 6457.3073 | J8: =-CONS!I5-CONS!I6 -> 8018.1534 | K8: =-CONS!J5-CONS!J6 -> 8018.1534 | L8: =-CONS!K5-CONS!K6 -> 7289.2304 | M8: =-CONS!L5-CONS!L6 -> 7653.6919 | N8: =-CONS!M5-CONS!M6 -> 7289.2304 | O8: =-CONS!N5-CONS!N6 -> 7289.2304 | ... S8: =-CONS!R5-CONS!R6 -> 7653.6919
G9: Equipment & Services | H9: =-CONS!G7 -> 148708.25 | I9: =-CONS!H7 -> 232822.7 | J9: =-CONS!I7 -> 41160.946 | K9: =-CONS!J7 -> 50030.946 | L9: =-CONS!K7 -> 18168.696 | M9: =-CONS!L7 -> 15668.696 | N9: =-CONS!M7 -> 13670.326 | O9: =-CONS!N7 -> 16170.326 | ... S9: =-CONS!R7 -> 4017.5358
G10: Transportation | H10: =-CONS!G9 -> 689.55156 | I10: =-CONS!H9 -> 39.67052 | J10: =-CONS!I9 -> 663.51226 | K10: =-CONS!J9 -> 0 | L10: =-CONS!K9 -> 1648.9256 | M10: =-CONS!L9 -> 353.9918 | N10: =-CONS!M9 -> 16.448 | O10: =-CONS!N9 -> 333.75048 | ... S10: =-CONS!R9 -> 5960.5702
G11: Production COS | H11: =-PRD!H15 -> 52683.663 | I11: =-PRD!I15 -> 100269.81 | J11: =-PRD!J15 -> 103519.69 | K11: =-PRD!K15 -> 285683.94 | L11: =-PRD!L15 -> 104223.85 | M11: =-PRD!M15 -> 83048.46 | N11: =-PRD!N15 -> 45343.173 | O11: =-PRD!O15 -> 109744.55 | ... S11: =-PRD!S15 -> 85630.235 | T11: =SUM(H11:S11) -> 1138130.7 | U11: =T11=-PRD!T15 -> TRUE | V11: =PRD!T15 -> -1138130.7
G12: Labour | H12: =-PRD!H4-PRD!H5-PRD!H6-PRD!H7-PRD!H9-PRD!H10-PRD!H8 -> 34963.677 | I12: =-PRD!I4-PRD!I5-PRD!I6-PRD!I7-PRD!I9-PRD!I10-PRD!I8 -> 43309.26 | J12: =-PRD!J4-PRD!J5-PRD!J6-PRD!J7-PRD!J9-PRD!J10-PRD!J8 -> 39454.055 | K12: =-PRD!K4-PRD!K5-PRD!K6-PRD!K7-PRD!K9-PRD!K10-PRD!K8 -> 43781.571 | L12: =-PRD!L4-PRD!L5-PRD!L6-PRD!L7-PRD!L9-PRD!L10-PRD!L8 -> 51301.026 | M12: =-PRD!M4-PRD!M5-PRD!M6-PRD!M7-PRD!M9-PRD!M10-PRD!M8 -> 49723.145 | N12: =-PRD!N4-PRD!N5-PRD!N6-PRD!N7-PRD!N9-PRD!N10-PRD!N8 -> 27041.554 | O12: =-PRD!O4-PRD!O5-PRD!O6-PRD!O7-PRD!O9-PRD!O10-PRD!O8 -> 43046.736 | ... R12: =-PRD!R4-PRD!R5-PRD!R6-PRD!R7-PRD!R9-PRD!R10-PRD!R8 -> 37174.461 | S12: =-PRD!S4-PRD!S5-PRD!S6-PRD!S7-PRD!S9-PRD!S10 -> 48755.36
G13: Equipment & Services | H13: =-PRD!H11-PRD!H12 -> 16456.235 | I13: =-PRD!I11-PRD!I12 -> 53025.213 | J13: =-PRD!J11-PRD!J12 -> 55901.12 | K13: =-PRD!K11-PRD!K12 -> 223518.3 | L13: =-PRD!L11-PRD!L12 -> 47833.787 | M13: =-PRD!M11-PRD!M12 -> 30380.64 | N13: =-PRD!N11-PRD!N12 -> 17774.774 | O13: =-PRD!O11-PRD!O12 -> 60051.722 | ... S13: =-PRD!S11-PRD!S12 -> 32960.714
G14: Transportation | H14: =-PRD!H13-PRD!H14 -> 1263.7512 | I14: =-PRD!I13-PRD!I14 -> 3935.3382 | J14: =-PRD!J13-PRD!J14 -> 8164.5194 | K14: =-PRD!K13-PRD!K14 -> 18384.074 | L14: =-PRD!L13-PRD!L14 -> 5089.038 | M14: =-PRD!M13-PRD!M14 -> 2944.6752 | N14: =-PRD!N13-PRD!N14 -> 526.84486 | O14: =-PRD!O13-PRD!O14 -> 6646.092 | ... S14: =-PRD!S13-PRD!S14 -> 3914.1614
G15: Onsite COS | H15: =-ONS!F14 -> 129391.68 | I15: =-ONS!G14 -> 115678.57 | J15: =-ONS!H14 -> 135541.85 | K15: =-ONS!I14 -> 130158.68 | L15: =-ONS!J14 -> 127598.94 | M15: =-ONS!K14 -> 134912.18 | N15: =-ONS!L14 -> 112466.56 | O15: =-ONS!M14 -> 116012.62 | ... S15: =-ONS!Q14 -> 139270 | T15: =SUM(H15:S15) -> 1559522.1 | U15: =T15=-ONS!R14 -> TRUE | V15: =ONS!R14 -> -1559522.1
A16: 3Way | G16: Labour | H16: =-ONS!F7-ONS!F8-ONS!F10 -> 127977.2 | I16: =-ONS!G7-ONS!G8-ONS!G10 -> 109984.29 | J16: =-ONS!H7-ONS!H8-ONS!H10 -> 128812.69 | K16: =-ONS!I7-ONS!I8-ONS!I10 -> 123051.54 | L16: =-ONS!J7-ONS!J8-ONS!J10 -> 121978.42 | M16: =-ONS!K7-ONS!K8-ONS!K10 -> 133541.68 | N16: =-ONS!L7-ONS!L8-ONS!L10 -> 106761.75 | O16: =-ONS!M7-ONS!M8-ONS!M10 -> 110392.11 | ... S16: =-ONS!Q7-ONS!Q8-ONS!Q10 -> 133831.91
A17: 0.34 | B17: 0.33 | C17: 0.33 | G17: Equipment & Services | H17: =-ONS!F12 -> 1188.723 | I17: =-ONS!G12 -> 991.066 | J17: =-ONS!H12 -> 2214.4794 | K17: =-ONS!I12 -> 1026.6731 | L17: =-ONS!J12 -> 1170.5178 | M17: =-ONS!K12 -> 1170.4972 | N17: =-ONS!L12 -> 1254.813 | O17: =-ONS!M12 -> 1170.5126 | ... S17: =-ONS!Q12 -> 988.0893
A18: Staff | G18: Transportation | H18: =-ONS!F13 -> 25.75 | I18: =-ONS!G13 -> 253.2152 | J18: =-ONS!H13 -> 64.684 | K18: =-ONS!I13 -> 1630.4642 | L18: =-ONS!J13 -> 0 | M18: =-ONS!K13 -> 0 | N18: =-ONS!L13 -> 0 | O18: =-ONS!M13 -> 0 | ... S18: =-ONS!Q13 -> 0
A19: ='TO DO'!L17+'TO DO'!L18 -> 0.40298507 | B19: ='TO DO'!L16 -> 0.58208955 | C19: ='TO DO'!L14+'TO DO'!L15 -> 0.014925373 | G19: Total Cost of Sales | H19: =H7+H11+H15 -> 338970.25 | I19: =I7+I11+I15 -> 455555.55 | J19: =J7+J11+J15 -> 289191.66 | K19: =K7+K11+K15 -> 474179.22 | L19: =L7+L11+L15 -> 259217.14 | M19: =M7+M11+M15 -> 241924.52 | N19: =N7+N11+N15 -> 179073.24 | O19: =O7+O11+O15 -> 249837.98 | ... S19: =S7+S11+S15 -> 242819.53 | T19: =SUM(H19:S19) -> 3379146.7 | Y19: =48+12+41 -> 101
A20: Office Dept | G20: Gross Profit | H20: =+H6-H19 -> 270306.93 | I20: =+I6-I19 -> 517612.19 | J20: =+J6-J19 -> 124473.02 | K20: =+K6-K19 -> 476236.46 | L20: =+L6-L19 -> 281088.04 | M20: =+M6-M19 -> 103045.66 | N20: =+N6-N19 -> 174896.12 | O20: =+O6-O19 -> 326781.46 | ... T20: =+T6-T19 -> 2925453.9
A21: 0.9463 | B21: 0.0179 | C21: 0.0358 | G21: Gross Profit Margin | H21: =+H20/H6 -> 0.44365182 | I21: =+I20/I6 -> 0.53188383 | J21: =+J20/J6 -> 0.30090319 | K21: =+K20/K6 -> 0.50108228 | L21: =+L20/L6 -> 0.52023939 | M21: =+M20/M6 -> 0.2987089 | N21: =+N20/N6 -> 0.49409961 | O21: =+O20/O6 -> 0.56671947 | ... T21: =+T20/T6 -> 0.46401891
A22: PRD/VID | B22: ONS | C22: CONS/INT | G22: General & Admin
A23: =$I$23*A17 -> 1161.6667 | B23: =$I$23*B17 -> 1127.5 | C23: =$I$23*C17 -> 1127.5 | E23: 3 Way | G23: Accounting Fees | H23: ='CTS Overheads'!D3 -> 3416.6667 | I23: ='CTS Overheads'!E3 -> 3416.6667 | J23: ='CTS Overheads'!F3 -> 4166.6667 | K23: ='CTS Overheads'!G3 -> 4166.6667 | L23: ='CTS Overheads'!H3 -> 4166.6667 | M23: ='CTS Overheads'!I3 -> 4166.6667 | N23: ='CTS Overheads'!J3 -> 4166.6667 | O23: ='CTS Overheads'!K3 -> 4166.6667 | ... S23: ='CTS Overheads'!O3 -> 5716.6667 | T23: =SUM(H23:S23) -> 54700 | U23: =T23='CTS Overheads'!P3 -> TRUE
A24: =$I$24*A17 -> 612 | B24: =$I$24*B17 -> 594 | C24: =$I$24*C17 -> 594 | E24: 3 Way | G24: Legal Fees | H24: ='CTS Overheads'!D4+'CTS Overheads'!D5 -> 1800 | I24: ='CTS Overheads'!E4+'CTS Overheads'!E5 -> 1800 | J24: ='CTS Overheads'!F4+'CTS Overheads'!F5 -> 1800 | K24: ='CTS Overheads'!G4+'CTS Overheads'!G5 -> 1800 | L24: ='CTS Overheads'!H4+'CTS Overheads'!H5 -> 1800 | M24: ='CTS Overheads'!I4+'CTS Overheads'!I5 -> 1800 | N24: ='CTS Overheads'!J4+'CTS Overheads'!J5 -> 1800 | O24: ='CTS Overheads'!K4+'CTS Overheads'!K5 -> 1800 | ... S24: ='CTS Overheads'!O4+'CTS Overheads'!O5 -> 1800 | T24: =SUM(H24:S24) -> 21600 | U24: =T24='CTS Overheads'!P4+'CTS Overheads'!P5 -> TRUE | V24: *$42K/12
A25: =$I$25*A19 -> 866.41791 | B25: =$I$25*B19 -> 1251.4925 | C25: =$I$25*C19 -> 32.089552 | E25: Staff | G25: Payroll Processing Fee | H25: ='CTS Overheads'!D6 -> 2150 | I25: ='CTS Overheads'!E6 -> 2150 | J25: ='CTS Overheads'!F6 -> 2150 | K25: ='CTS Overheads'!G6 -> 2150 | L25: ='CTS Overheads'!H6 -> 2150 | M25: ='CTS Overheads'!I6 -> 2150 | N25: ='CTS Overheads'!J6 -> 2150 | O25: ='CTS Overheads'!K6 -> 2150 | ... S25: ='CTS Overheads'!O6 -> 2150 | T25: =SUM(H25:S25) -> 25800 | U25: =T25='CTS Overheads'!P6 -> TRUE
A26: =$I$26*A17 -> 170 | B26: =$I$26*B17 -> 165 | C26: =$I$26*C17 -> 165 | E26: 3 Way | G26: Bank Charges | H26: ='CTS Overheads'!D7 -> 500 | I26: ='CTS Overheads'!E7 -> 500 | J26: ='CTS Overheads'!F7 -> 500 | K26: ='CTS Overheads'!G7 -> 500 | L26: ='CTS Overheads'!H7 -> 500 | M26: ='CTS Overheads'!I7 -> 500 | N26: ='CTS Overheads'!J7 -> 500 | O26: ='CTS Overheads'!K7 -> 500 | ... S26: ='CTS Overheads'!O7 -> 500 | T26: =SUM(H26:S26) -> 10516 | U26: =T26='CTS Overheads'!P7 -> TRUE | V26: *4K
A27: =$I$27*A17 -> 2273.5758 | B27: =$I$27*B17 -> 2206.706 | C27: =$I$27*C17 -> 2206.706 | E27: 3 Way | G27: Dues & Subscriptions (Admin CC) | H27: =SUM('CTS Overheads'!D8:D25) -> 6686.9877 | I27: =SUM('CTS Overheads'!E8:E25) -> 6686.9877 | J27: =SUM('CTS Overheads'!F8:F25) -> 6686.9877 | K27: =SUM('CTS Overheads'!G8:G25) -> 7386.9877 | L27: =SUM('CTS Overheads'!H8:H25) -> 7386.9877 | M27: =SUM('CTS Overheads'!I8:I25) -> 7386.9877 | N27: =SUM('CTS Overheads'!J8:J25) -> 7386.9877 | O27: =SUM('CTS Overheads'!K8:K25) -> 7386.9877 | ... S27: =SUM('CTS Overheads'!O8:O25) -> 7386.9877 | T27: =SUM(H27:S27) -> 86543.853 | U27: =T27=SUM('CTS Overheads'!P8:P25) -> TRUE
A28: =$I$28*A17 -> 0 | B28: =$I$28*B17 -> 0 | C28: =$I$28*C17 -> 0 | E28: 3 Way | G28: Donations / Charity | H28: ='CTS Overheads'!D26 -> 0 | I28: ='CTS Overheads'!E26 -> 0 | J28: ='CTS Overheads'!F26 -> 0 | K28: ='CTS Overheads'!G26 -> 0 | L28: ='CTS Overheads'!H26 -> 0 | M28: ='CTS Overheads'!I26 -> 0 | N28: ='CTS Overheads'!J26 -> 0 | O28: ='CTS Overheads'!K26 -> 200 | ... S28: ='CTS Overheads'!O26 -> 5000 | T28: =SUM(H28:S28) -> 5200 | U28: =T28='CTS Overheads'!P26 -> TRUE
A29: =$I$29*A17 -> 10.2 | B29: =$I$29*B17 -> 9.9 | C29: =$I$29*C17 -> 9.9 | E29: 3 Way | G29: Freight Paid | H29: ='CTS Overheads'!D27 -> 30 | I29: ='CTS Overheads'!E27 -> 30 | J29: ='CTS Overheads'!F27 -> 30 | K29: ='CTS Overheads'!G27 -> 30 | L29: ='CTS Overheads'!H27 -> 30 | M29: ='CTS Overheads'!I27 -> 150 | N29: ='CTS Overheads'!J27 -> 30 | O29: ='CTS Overheads'!K27 -> 30 | ... S29: ='CTS Overheads'!O27 -> 30 | T29: =SUM(H29:S29) -> 480 | U29: =T29='CTS Overheads'!P27 -> TRUE
A30: =$I$30*A17 -> 0 | B30: =$I$30*B17 -> 0 | C30: =$I$30*C17 -> 0 | E30: 3 Way | G30: Filing Fee | H30: ='CTS Overheads'!D28 -> 0 | I30: ='CTS Overheads'!E28 -> 0 | J30: ='CTS Overheads'!F28 -> 825 | K30: ='CTS Overheads'!G28 -> 0 | L30: ='CTS Overheads'!H28 -> 0 | M30: ='CTS Overheads'!I28 -> 0 | N30: ='CTS Overheads'!J28 -> 0 | O30: ='CTS Overheads'!K28 -> 0 | ... S30: ='CTS Overheads'!O28 -> 0 | T30: =SUM(H30:S30) -> 825 | U30: =T30='CTS Overheads'!P28 -> TRUE
A31: =$I$31*A21 -> 4731.5 | B31: =$I$31*B21 -> 89.5 | C31: =$I$31*C21 -> 179 | E31: Office Dept | G31: Instant Asset Write Off | H31: ='CTS Overheads'!D29 -> 5000 | I31: ='CTS Overheads'!E29 -> 5000 | J31: ='CTS Overheads'!F29 -> 5000 | K31: ='CTS Overheads'!G29 -> 5000 | L31: ='CTS Overheads'!H29 -> 5000 | M31: ='CTS Overheads'!I29 -> 5000 | N31: ='CTS Overheads'!J29 -> 5000 | O31: ='CTS Overheads'!K29 -> 5000 | ... S31: ='CTS Overheads'!O29 -> 5000 | T31: =SUM(H31:S31) -> 60000 | U31: =T31='CTS Overheads'!P29 -> TRUE
A32: =$I$32*A17 -> 6.8 | B32: =$I$32*B17 -> 6.6 | C32: =$I$32*C17 -> 6.6 | E32: 3 Way | G32: Credit Card Fees Paid | H32: ='CTS Overheads'!D30 -> 20 | I32: ='CTS Overheads'!E30 -> 20 | J32: ='CTS Overheads'!F30 -> 20 | K32: ='CTS Overheads'!G30 -> 20 | L32: ='CTS Overheads'!H30 -> 20 | M32: ='CTS Overheads'!I30 -> 20 | N32: ='CTS Overheads'!J30 -> 20 | O32: ='CTS Overheads'!K30 -> 20 | ... S32: ='CTS Overheads'!O30 -> 20 | T32: =SUM(H32:S32) -> 240 | U32: =T32='CTS Overheads'!P30 -> TRUE
A33: =$I$33*A17 -> 408 | B33: =$I$33*B17 -> 396 | C33: =$I$33*C17 -> 396 | E33: 3 Way | G33: Business Advisory | H33: ='CTS Overheads'!D31 -> 1200 | I33: ='CTS Overheads'!E31 -> 1200 | J33: ='CTS Overheads'!F31 -> 1200 | K33: ='CTS Overheads'!G31 -> 1200 | L33: ='CTS Overheads'!H31 -> 1200 | M33: ='CTS Overheads'!I31 -> 1200 | N33: ='CTS Overheads'!J31 -> 1200 | O33: ='CTS Overheads'!K31 -> 1200 | ... S33: ='CTS Overheads'!O31 -> 1200 | T33: =SUM(H33:S33) -> 14400 | U33: =T33='CTS Overheads'!P31 -> TRUE
A34: =$I$34*A17 -> 76.474217 | B34: =$I$34*B17 -> 74.224975 | C34: =$I$34*C17 -> 74.224975 | E34: 3 Way | G34: Custodian Vaults | H34: ='CTS Overheads'!D32 -> 224.92417 | I34: ='CTS Overheads'!E32 -> 224.92417 | J34: ='CTS Overheads'!F32 -> 224.92417 | K34: ='CTS Overheads'!G32 -> 224.92417 | L34: ='CTS Overheads'!H32 -> 224.92417 | M34: ='CTS Overheads'!I32 -> 224.92417 | N34: ='CTS Overheads'!J32 -> 224.92417 | O34: ='CTS Overheads'!K32 -> 224.92417 | ... S34: ='CTS Overheads'!O32 -> 224.92417 | T34: =SUM(H34:S34) -> 2699.09 | U34: =T34='CTS Overheads'!P32 -> TRUE
A35: =$I$35*A17 -> 187 | B35: =$I$35*B17 -> 181.5 | C35: =$I$35*C17 -> 181.5 | E35: 3 Way | G35: Taxis/Parking | H35: ='CTS Overheads'!D33 -> 300 | I35: ='CTS Overheads'!E33 -> 550 | J35: ='CTS Overheads'!F33 -> 300 | K35: ='CTS Overheads'!G33 -> 150 | L35: ='CTS Overheads'!H33 -> 150 | M35: ='CTS Overheads'!I33 -> 100 | N35: ='CTS Overheads'!J33 -> 50 | O35: ='CTS Overheads'!K33 -> 150 | ... S35: ='CTS Overheads'!O33 -> 100 | T35: =SUM(H35:S35) -> 2250 | U35: =T35='CTS Overheads'!P33 -> TRUE
A36: =$I$36*A17 -> 0 | B36: =$I$36*B17 -> 0 | C36: =$I$36*C17 -> 0 | E36: 3 Way | G36: Stamp Duty (Indirect) | H36: ='CTS Overheads'!D34 -> 0 | I36: ='CTS Overheads'!E34 -> 0 | J36: ='CTS Overheads'!F34 -> 2741.81 | K36: ='CTS Overheads'!G34 -> 0 | L36: ='CTS Overheads'!H34 -> 0 | M36: ='CTS Overheads'!I34 -> 0 | N36: ='CTS Overheads'!J34 -> 0 | O36: ='CTS Overheads'!K34 -> 0 | ... S36: ='CTS Overheads'!O34 -> 0 | T36: =SUM(H36:S36) -> 2741.81 | U36: =T36='CTS Overheads'!P34 -> TRUE
A37: =SUM(A23:A36) -> 10535.127 | B37: =SUM(B23:B36) -> 6228.4682 | C37: =SUM(C23:C36) -> 4814.9832 | G37: Business Insurances
A38: =$I$38*A17 -> 1160.9847 | B38: =$I$38*B17 -> 1126.8381 | C38: =$I$38*C17 -> 1126.8381 | E38: 3 Way | G38: Other Insurance | H38: ='CTS Overheads'!$A$40 -> 3414.6608 | I38: ='CTS Overheads'!$A$40 -> 3414.6608 | J38: ='CTS Overheads'!$A$40 -> 3414.6608 | K38: ='CTS Overheads'!$A$40 -> 3414.6608 | L38: ='CTS Overheads'!$A$40 -> 3414.6608 | M38: ='CTS Overheads'!$A$40 -> 3414.6608 | N38: ='CTS Overheads'!$A$40 -> 3414.6608 | O38: ='CTS Overheads'!$A$40 -> 3414.6608 | ... S38: ='CTS Overheads'!$A$40 -> 3414.6608 | T38: =SUM(H38:S38) -> 40975.93 | U38: =T38=SUM('CTS Overheads'!P36:P40) -> TRUE
A39: =$I$39*A17 -> 35.785 | B39: =$I$39*B17 -> 34.7325 | C39: =$I$39*C17 -> 34.7325 | E39: 3 Way | G39: Travel Insurance | H39: ='CTS Overheads'!D41 -> 105.25 | I39: ='CTS Overheads'!E41 -> 105.25 | J39: ='CTS Overheads'!F41 -> 105.25 | K39: ='CTS Overheads'!G41 -> 105.25 | L39: ='CTS Overheads'!H41 -> 105.25 | M39: ='CTS Overheads'!I41 -> 105.25 | N39: ='CTS Overheads'!J41 -> 105.25 | O39: ='CTS Overheads'!K41 -> 105.25 | ... S39: ='CTS Overheads'!O41 -> 105.25 | T39: =SUM(H39:S39) -> 1263 | U39: =T39='CTS Overheads'!P41 -> TRUE
A40: =SUM(A38:A39) -> 1196.7697 | B40: =SUM(B38:B39) -> 1161.5706 | C40: =SUM(C38:C39) -> 1161.5706
A41: =$I$41*A17 -> 8718.909 | B41: =$I$41*B17 -> 8462.4705 | C41: =$I$41*C17 -> 8462.4705 | E41: 3 Way | G41: Advertising | H41: =SUM('CTS Overheads'!D44:D48) -> 4643.85 | I41: =SUM('CTS Overheads'!E44:E48) -> 25643.85 | J41: =SUM('CTS Overheads'!F44:F48) -> 4643.85 | K41: =SUM('CTS Overheads'!G44:G48) -> 4643.85 | L41: =SUM('CTS Overheads'!H44:H48) -> 4643.85 | M41: =SUM('CTS Overheads'!I44:I48) -> 4643.85 | N41: =SUM('CTS Overheads'!J44:J48) -> 4643.85 | O41: =SUM('CTS Overheads'!K44:K48) -> 4643.85 | ... S41: =SUM('CTS Overheads'!O44:O48) -> 4643.85 | T41: =SUM(H41:S41) -> 76726.2 | U41: =T41=SUM('CTS Overheads'!P44:P48) -> TRUE
A42: =SUM(A41) -> 8718.909 | B42: =SUM(B41) -> 8462.4705 | C42: =SUM(C41) -> 8462.4705 | G42: Operating Expense
A43: =$I$43*A21 -> 189.26 | B43: =$I$43*B21 -> 3.58 | C43: =$I$43*C21 -> 7.16 | E43: Office Dept | G43: Office Supplies | H43: ='CTS Overheads'!D50 -> 200 | I43: ='CTS Overheads'!E50 -> 200 | J43: ='CTS Overheads'!F50 -> 200 | K43: ='CTS Overheads'!G50 -> 200 | L43: ='CTS Overheads'!H50 -> 200 | M43: ='CTS Overheads'!I50 -> 200 | N43: ='CTS Overheads'!J50 -> 200 | O43: ='CTS Overheads'!K50 -> 200 | ... S43: ='CTS Overheads'!O50 -> 200 | T43: =SUM(H43:S43) -> 2400 | U43: =T43='CTS Overheads'!P50 -> TRUE
A44: =$I$44*A17 -> 15.98 | B44: =$I$44*B17 -> 15.51 | C44: =$I$44*C17 -> 15.51 | E44: 3 Way | G44: Postage | H44: ='CTS Overheads'!D51+'CTS Overheads'!D52 -> 47 | I44: ='CTS Overheads'!E51+'CTS Overheads'!E52 -> 47 | J44: ='CTS Overheads'!F51+'CTS Overheads'!F52 -> 47 | K44: ='CTS Overheads'!G51+'CTS Overheads'!G52 -> 47 | L44: ='CTS Overheads'!H51+'CTS Overheads'!H52 -> 47 | M44: ='CTS Overheads'!I51+'CTS Overheads'!I52 -> 297 | N44: ='CTS Overheads'!J51+'CTS Overheads'!J52 -> 147 | O44: ='CTS Overheads'!K51+'CTS Overheads'!K52 -> 47 | ... S44: ='CTS Overheads'!O51+'CTS Overheads'!O52 -> 47 | T44: =SUM(H44:S44) -> 914 | U44: =T44='CTS Overheads'!P52+'CTS Overheads'!P51 -> TRUE
A45: =$I$45*A21 -> 189.26 | B45: =$I$45*B21 -> 3.58 | C45: =$I$45*C21 -> 7.16 | E45: Office Dept | G45: Printing | H45: ='CTS Overheads'!D53 -> 200 | I45: ='CTS Overheads'!E53 -> 200 | J45: ='CTS Overheads'!F53 -> 200 | K45: ='CTS Overheads'!G53 -> 200 | L45: ='CTS Overheads'!H53 -> 200 | M45: ='CTS Overheads'!I53 -> 200 | N45: ='CTS Overheads'!J53 -> 200 | O45: ='CTS Overheads'!K53 -> 200 | ... S45: ='CTS Overheads'!O53 -> 200 | T45: =SUM(H45:S45) -> 2400 | U45: =T45='CTS Overheads'!P53 -> TRUE
A46: =$I$46*A21 -> 283.89 | B46: =$I$46*B21 -> 5.37 | C46: =$I$46*C21 -> 10.74 | E46: Office Dept | G46: Electricity | H46: ='CTS Overheads'!D54 -> 300 | I46: ='CTS Overheads'!E54 -> 300 | J46: ='CTS Overheads'!F54 -> 300 | K46: ='CTS Overheads'!G54 -> 300 | L46: ='CTS Overheads'!H54 -> 300 | M46: ='CTS Overheads'!I54 -> 300 | N46: ='CTS Overheads'!J54 -> 300 | O46: ='CTS Overheads'!K54 -> 300 | ... S46: ='CTS Overheads'!O54 -> 300 | T46: =SUM(H46:S46) -> 3600 | U46: =T46='CTS Overheads'!P54 -> TRUE
A47: =$I$47*A21 -> 189.26 | B47: =$I$47*B21 -> 3.58 | C47: =$I$47*C21 -> 7.16 | E47: Office Dept | G47: Repairs & Maintenance | H47: ='CTS Overheads'!D55 -> 200 | I47: ='CTS Overheads'!E55 -> 200 | J47: ='CTS Overheads'!F55 -> 200 | K47: ='CTS Overheads'!G55 -> 200 | L47: ='CTS Overheads'!H55 -> 200 | M47: ='CTS Overheads'!I55 -> 200 | N47: ='CTS Overheads'!J55 -> 200 | O47: ='CTS Overheads'!K55 -> 200 | ... S47: ='CTS Overheads'!O55 -> 200 | T47: =SUM(H47:S47) -> 2400 | U47: =T47='CTS Overheads'!P55 -> TRUE
A48: =$I$48*A17 -> 22.1 | B48: =$I$48*B17 -> 21.45 | C48: =$I$48*C17 -> 21.45 | E48: 3 Way | G48: 1300 Number | H48: ='CTS Overheads'!D56 -> 65 | I48: ='CTS Overheads'!E56 -> 65 | J48: ='CTS Overheads'!F56 -> 65 | K48: ='CTS Overheads'!G56 -> 65 | L48: ='CTS Overheads'!H56 -> 65 | M48: ='CTS Overheads'!I56 -> 65 | N48: ='CTS Overheads'!J56 -> 65 | O48: ='CTS Overheads'!K56 -> 65 | ... S48: ='CTS Overheads'!O56 -> 65 | T48: =SUM(H48:S48) -> 780 | U48: =T48='CTS Overheads'!P56 -> TRUE
A49: =$I$49*A17 -> 68 | B49: =$I$49*B17 -> 66 | C49: =$I$49*C17 -> 66 | E49: 3 Way | G49: Office Phones | H49: ='CTS Overheads'!D57 -> 200 | I49: ='CTS Overheads'!E57 -> 200 | J49: ='CTS Overheads'!F57 -> 200 | K49: ='CTS Overheads'!G57 -> 200 | L49: ='CTS Overheads'!H57 -> 200 | M49: ='CTS Overheads'!I57 -> 200 | N49: ='CTS Overheads'!J57 -> 200 | O49: ='CTS Overheads'!K57 -> 200 | ... S49: ='CTS Overheads'!O57 -> 200 | T49: =SUM(H49:S49) -> 2400 | U49: =T49='CTS Overheads'!P57 -> TRUE
A50: =$I$50*A17 -> 93.5 | B50: =$I$50*B17 -> 90.75 | C50: =$I$50*C17 -> 90.75 | E50: 3 Way | G50: Mobile Phones | H50: ='CTS Overheads'!D58 -> 275 | I50: ='CTS Overheads'!E58 -> 275 | J50: ='CTS Overheads'!F58 -> 275 | K50: ='CTS Overheads'!G58 -> 275 | L50: ='CTS Overheads'!H58 -> 275 | M50: ='CTS Overheads'!I58 -> 275 | N50: ='CTS Overheads'!J58 -> 275 | O50: ='CTS Overheads'!K58 -> 275 | ... S50: ='CTS Overheads'!O58 -> 275 | T50: =SUM(H50:S50) -> 3300 | U50: =T50='CTS Overheads'!P58 -> TRUE
A51: =$I$51*A21 -> 379.65556 | B51: =$I$51*B21 -> 7.18148 | C51: =$I$51*C21 -> 14.36296 | E51: Office Dept | G51: Internet | H51: ='CTS Overheads'!D59 -> 401.2 | I51: ='CTS Overheads'!E59 -> 401.2 | J51: ='CTS Overheads'!F59 -> 401.2 | K51: ='CTS Overheads'!G59 -> 401.2 | L51: ='CTS Overheads'!H59 -> 401.2 | M51: ='CTS Overheads'!I59 -> 401.2 | N51: ='CTS Overheads'!J59 -> 401.2 | O51: ='CTS Overheads'!K59 -> 401.2 | ... S51: ='CTS Overheads'!O59 -> 401.2 | T51: =SUM(H51:S51) -> 4814.4 | U51: =T51='CTS Overheads'!P59 -> TRUE
A52: =$I$52*A21 -> 321.60006 | B52: =$I$52*B21 -> 6.083315 | C52: =$I$52*C21 -> 12.16663 | E52: Office Dept | G52: Office Cleaning | H52: ='CTS Overheads'!D60 -> 339.85 | I52: ='CTS Overheads'!E60 -> 339.85 | J52: ='CTS Overheads'!F60 -> 339.85 | K52: ='CTS Overheads'!G60 -> 339.85 | L52: ='CTS Overheads'!H60 -> 339.85 | M52: ='CTS Overheads'!I60 -> 339.85 | N52: ='CTS Overheads'!J60 -> 339.85 | O52: ='CTS Overheads'!K60 -> 339.85 | ... S52: ='CTS Overheads'!O60 -> 339.85 | T52: =SUM(H52:S52) -> 4078.2 | U52: =T52='CTS Overheads'!P60 -> TRUE
A53: =$I$53*A17 -> 4226.2 | B53: =$I$53*B17 -> 4101.9 | C53: =$I$53*C17 -> 4101.9 | E53: 3 Way | G53: IT Network Service & Support | H53: ='CTS Overheads'!D61 -> 12430 | I53: ='CTS Overheads'!E61 -> 12430 | J53: ='CTS Overheads'!F61 -> 12430 | K53: ='CTS Overheads'!G61 -> 12430 | L53: ='CTS Overheads'!H61 -> 12430 | M53: ='CTS Overheads'!I61 -> 12430 | N53: ='CTS Overheads'!J61 -> 12430 | O53: ='CTS Overheads'!K61 -> 12430 | ... S53: ='CTS Overheads'!O61 -> 12430 | T53: =SUM(H53:S53) -> 149160 | U53: =T53='CTS Overheads'!P61 -> TRUE
A54: =$I$54*A19 -> 3707.4627 | B54: =$I$54*B19 -> 5355.2239 | C54: =$I$54*C19 -> 137.31343 | E54: Staff | G54: Travel & Per Diems | H54: ='CTS Overheads'!D62 -> 200 | I54: ='CTS Overheads'!E62 -> 9200 | J54: ='CTS Overheads'!F62 -> 200 | K54: ='CTS Overheads'!G62 -> 200 | L54: ='CTS Overheads'!H62 -> 200 | M54: ='CTS Overheads'!I62 -> 3000 | N54: ='CTS Overheads'!J62 -> 200 | O54: ='CTS Overheads'!K62 -> 200 | ... S54: ='CTS Overheads'!O62 -> 200 | T54: =SUM(H54:S54) -> 14200 | U54: =T54='CTS Overheads'!P62 -> TRUE
A55: =$I$55*A17 -> 170 | B55: =$I$55*B17 -> 165 | C55: =$I$55*C17 -> 165 | E55: 3 Way | G55: Client Entertainment | H55: ='CTS Overheads'!D63 -> 500 | I55: ='CTS Overheads'!E63 -> 500 | J55: ='CTS Overheads'!F63 -> 8500 | K55: ='CTS Overheads'!G63 -> 500 | L55: ='CTS Overheads'!H63 -> 500 | M55: ='CTS Overheads'!I63 -> 5000 | N55: ='CTS Overheads'!J63 -> 500 | O55: ='CTS Overheads'!K63 -> 500 | ... S55: ='CTS Overheads'!O63 -> 500 | T55: =SUM(H55:S55) -> 18500 | U55: =T55='CTS Overheads'!P63 -> TRUE
A56: =SUM(A43:A55) -> 10777.654 | B56: =SUM(B43:B55) -> 12985.586 | C56: =SUM(C43:C55) -> 594.80989 | G56: Employment Expnses
A57: =$I$57*A19 -> 458.2665 | B57: =$I$57*B19 -> 661.9405 | C57: =$I$57*C19 -> 16.972833 | E57: Staff | G57: Leave expense (Long Service) | H57: ='CTS Overheads'!D64+'CTS Overheads'!D67 -> 797.48984 | I57: ='CTS Overheads'!E64+'CTS Overheads'!E67 -> 1137.1798 | J57: ='CTS Overheads'!F64+'CTS Overheads'!F67 -> 1137.1798 | K57: ='CTS Overheads'!G64+'CTS Overheads'!G67 -> 1137.1798 | L57: ='CTS Overheads'!H64+'CTS Overheads'!H67 -> 1137.1798 | M57: ='CTS Overheads'!I64+'CTS Overheads'!I67 -> 1137.1798 | N57: ='CTS Overheads'!J64+'CTS Overheads'!J67 -> 1137.1798 | O57: ='CTS Overheads'!K64+'CTS Overheads'!K67 -> 1137.1798 | ... S57: ='CTS Overheads'!O64+'CTS Overheads'!O67 -> 1137.1798 | T57: =SUM(H57:S57) -> 13306.468 | U57: =T57='CTS Overheads'!P64+'CTS Overheads'!P67 -> TRUE
A58: =$I$58*A19 -> 2341.6708 | B58: =$I$58*B19 -> 3382.4134 | C58: =$I$58*C19 -> 86.728548 | E58: Staff | G58: Leave expense (Annual) | H58: ='CTS Overheads'!D65+'CTS Overheads'!D66 -> 5810.8127 | I58: ='CTS Overheads'!E65+'CTS Overheads'!E66 -> 5810.8127 | J58: ='CTS Overheads'!F65+'CTS Overheads'!F66 -> 5810.8127 | K58: ='CTS Overheads'!G65+'CTS Overheads'!G66 -> 5810.8127 | L58: ='CTS Overheads'!H65+'CTS Overheads'!H66 -> 5810.8127 | M58: ='CTS Overheads'!I65+'CTS Overheads'!I66 -> 5810.8127 | N58: ='CTS Overheads'!J65+'CTS Overheads'!J66 -> 5810.8127 | O58: ='CTS Overheads'!K65+'CTS Overheads'!K66 -> 5810.8127 | ... S58: ='CTS Overheads'!O65+'CTS Overheads'!O66 -> 5810.8127 | T58: =ROUND(SUM(H58:S58),2) -> 69729.75 | U58: =T58=ROUND('CTS Overheads'!P65+'CTS Overheads'!P66,2) -> TRUE
A59: =$I$59*A19 -> 2919.9033 | B59: =$I$59*B19 -> 4217.6381 | C59: =$I$59*C19 -> 108.14457 | E59: Staff | G59: Payroll Tax | H59: ='CTS Overheads'!D68+'CTS Overheads'!D69 -> 7875.2584 | I59: ='CTS Overheads'!E68+'CTS Overheads'!E69 -> 7245.6859 | J59: ='CTS Overheads'!F68+'CTS Overheads'!F69 -> 7758.8505 | K59: ='CTS Overheads'!G68+'CTS Overheads'!G69 -> 7431.0352 | L59: ='CTS Overheads'!H68+'CTS Overheads'!H69 -> 7029.9861 | M59: ='CTS Overheads'!I68+'CTS Overheads'!I69 -> 7633.9184 | N59: ='CTS Overheads'!J68+'CTS Overheads'!J69 -> 6565.8467 | O59: ='CTS Overheads'!K68+'CTS Overheads'!K69 -> 7035.6973 | ... S59: ='CTS Overheads'!O68+'CTS Overheads'!O69 -> 6766.5353 | T59: =SUM(H59:S59) -> 88158.471 | U59: =T59='CTS Overheads'!P68+'CTS Overheads'!P69 -> TRUE
A60: =$I$60*A21 -> 94.63 | B60: =$I$60*B21 -> 1.79 | C60: =$I$60*C21 -> 3.58 | E60: Office Dept | G60: Staff Amenities | H60: ='CTS Overheads'!D70+'CTS Overheads'!D71 -> 100 | I60: ='CTS Overheads'!E70+'CTS Overheads'!E71 -> 100 | J60: ='CTS Overheads'!F70+'CTS Overheads'!F71 -> 665 | K60: ='CTS Overheads'!G70+'CTS Overheads'!G71 -> 200 | L60: ='CTS Overheads'!H70+'CTS Overheads'!H71 -> 100 | M60: ='CTS Overheads'!I70+'CTS Overheads'!I71 -> 665 | N60: ='CTS Overheads'!J70+'CTS Overheads'!J71 -> 100 | O60: ='CTS Overheads'!K70+'CTS Overheads'!K71 -> 100 | ... S60: ='CTS Overheads'!O70+'CTS Overheads'!O71 -> 100 | T60: =SUM(H60:S60) -> 2995 | U60: =T60='CTS Overheads'!P70+'CTS Overheads'!P71 -> TRUE
A61: =$I$61*A19 -> 2014.9254 | B61: =$I$61*B19 -> 2910.4478 | C61: =$I$61*C19 -> 74.626866 | E61: Staff | G61: Staff Entertainment | H61: ='CTS Overheads'!D72 -> 500 | I61: ='CTS Overheads'!E72 -> 5000 | J61: ='CTS Overheads'!F72 -> 500 | K61: ='CTS Overheads'!G72 -> 500 | L61: ='CTS Overheads'!H72 -> 500 | M61: ='CTS Overheads'!I72 -> 6500 | N61: ='CTS Overheads'!J72 -> 500 | O61: ='CTS Overheads'!K72 -> 500 | ... S61: ='CTS Overheads'!O72 -> 500 | T61: =SUM(H61:S61) -> 16500 | U61: =T61='CTS Overheads'!P72 -> TRUE
A62: =I62*$A$19 -> 3242.6101 | B62: =I62*$B$19 -> 4683.7701 | C62: =I62*$C$19 -> 120.09667 | E62: Staff | G62: Superannuation - Admin | H62: ='CTS Overheads'!D73 -> 8826.3442 | I62: ='CTS Overheads'!E73 -> 8046.4769 | J62: ='CTS Overheads'!F73 -> 8626.9056 | K62: ='CTS Overheads'!G73 -> 7487.6802 | L62: ='CTS Overheads'!H73 -> 7010.8175 | M62: ='CTS Overheads'!I73 -> 5580.2292 | N62: ='CTS Overheads'!J73 -> 7487.6802 | O62: ='CTS Overheads'!K73 -> 7010.8175 | ... S62: ='CTS Overheads'!O73 -> 7249.2488 | T62: =SUM(H62:S62) -> 89312.378 | U62: =T62='CTS Overheads'!P73 -> TRUE
A63: =I63*$A$19 -> 19741.859 | B63: =I63*$B$19 -> 28516.019 | C63: =I63*$C$19 -> 731.17996 | E63: Staff | G63: Indirect Salaries/Wages - Admin | H63: ='CTS Overheads'!D74 -> 55487.952 | I63: ='CTS Overheads'!E74 -> 48989.058 | J63: ='CTS Overheads'!F74 -> 53825.963 | K63: ='CTS Overheads'!G74 -> 44332.418 | L63: ='CTS Overheads'!H74 -> 40358.562 | M63: ='CTS Overheads'!I74 -> 28436.994 | N63: ='CTS Overheads'!J74 -> 44332.418 | O63: ='CTS Overheads'!K74 -> 40358.562 | ... S63: ='CTS Overheads'!O74 -> 42345.49 | T63: =SUM(H63:S63) -> 527490.82 | U63: =T63='CTS Overheads'!P74 -> TRUE
A64: =I64*$A$19 -> 13.057362 | B64: =I64*$B$19 -> 18.860634 | C64: =I64*$C$19 -> 0.48360601 | E64: Staff | G64: Workers' Compensation | H64: ='CTS Overheads'!D75 -> 32.401603 | I64: ='CTS Overheads'!E75 -> 32.401603 | J64: ='CTS Overheads'!F75 -> 32.401603 | K64: ='CTS Overheads'!G75 -> 32.401603 | L64: ='CTS Overheads'!H75 -> 32.401603 | M64: ='CTS Overheads'!I75 -> 32.401603 | N64: ='CTS Overheads'!J75 -> 32.401603 | O64: ='CTS Overheads'!K75 -> 32.401603 | ... S64: ='CTS Overheads'!O75 -> 32.401603 | T64: =SUM(H64:S64) -> 388.81923 | U64: =T64='CTS Overheads'!P75 -> TRUE
A65: =I65*$A$19 -> 429.57907 | B65: =I65*$B$19 -> 620.5031 | C65: =I65*$C$19 -> 15.910336 | E65: Staff | G65: Training Material & Courses | H65: =SUM('CTS Overheads'!D76:D79) -> 1065.9925 | I65: =SUM('CTS Overheads'!E76:E79) -> 1065.9925 | J65: =SUM('CTS Overheads'!F76:F79) -> 1065.9925 | K65: =SUM('CTS Overheads'!G76:G79) -> 1065.9925 | L65: =SUM('CTS Overheads'!H76:H79) -> 1065.9925 | M65: =SUM('CTS Overheads'!I76:I79) -> 1065.9925 | N65: =SUM('CTS Overheads'!J76:J79) -> 1065.9925 | O65: =SUM('CTS Overheads'!K76:K79) -> 1065.9925 | ... S65: =SUM('CTS Overheads'!O76:O79) -> 1065.9925 | T65: =SUM(H65:S65) -> 12791.91 | U65: =T65=(SUM('CTS Overheads'!P76:P79)) -> TRUE
A66: =I66*$A$19 -> 302.23881 | B66: =I66*$B$19 -> 436.56716 | C66: =I66*$C$19 -> 11.19403 | E66: Staff | G66: Recruitment | H66: =SUM('CTS Overheads'!D81:D84) -> 750 | I66: =SUM('CTS Overheads'!E81:E84) -> 750 | J66: =SUM('CTS Overheads'!F81:F84) -> 750 | K66: =SUM('CTS Overheads'!G81:G84) -> 750 | L66: =SUM('CTS Overheads'!H81:H84) -> 750 | M66: =SUM('CTS Overheads'!I81:I84) -> 750 | N66: =SUM('CTS Overheads'!J81:J84) -> 750 | O66: =SUM('CTS Overheads'!K81:K84) -> 750 | ... S66: =SUM('CTS Overheads'!O81:O84) -> 750 | T66: =SUM(H66:S66) -> 9000 | U66: =T66=SUM('CTS Overheads'!P81:P84) -> TRUE
A67: =I67*$A$19 -> 161.19403 | B67: =I67*$B$19 -> 232.83582 | C67: =I67*$C$19 -> 5.9701493 | E67: Staff | G67: Other Expenses | H67: ='CTS Overheads'!D85 -> 400 | I67: ='CTS Overheads'!E85 -> 400 | J67: ='CTS Overheads'!F85 -> 400 | K67: ='CTS Overheads'!G85 -> 400 | L67: ='CTS Overheads'!H85 -> 400 | M67: ='CTS Overheads'!I85 -> 400 | N67: ='CTS Overheads'!J85 -> 400 | O67: ='CTS Overheads'!K85 -> 400 | ... S67: ='CTS Overheads'!O85 -> 400 | T67: =SUM(H67:S67) -> 4800 | U67: =T67='CTS Overheads'!P85 -> TRUE
A68: =SUM(A57:A67) -> 31719.934 | B68: =SUM(B57:B67) -> 45682.785 | C68: =SUM(C57:C67) -> 1174.8876 | G68: Subtotal | H68: =ROUND(SUM(H23:H67),2) -> 126496.64 | I68: =ROUND(SUM(I23:I67),2) -> 153678 | J68: =ROUND(SUM(J23:J67),2) -> 137740.31 | K68: =ROUND(SUM(K23:K67),2) -> 115297.91 | L68: =ROUND(SUM(L23:L67),2) -> 110346.14 | M68: =ROUND(SUM(M23:M67),2) -> 111782.92 | N68: =ROUND(SUM(N23:N67),2) -> 114332.72 | O68: =ROUND(SUM(O23:O67),2) -> 110551.85 | ... T68: =ROUND(SUM(T23:T67),2) -> 1450381.1 | U68: =T68='CTS Overheads'!P86 -> TRUE
H69: =H68='CTS Overheads'!D86 -> TRUE | I69: =I68='CTS Overheads'!E86 -> TRUE | J69: =J68='CTS Overheads'!F86 -> TRUE | K69: =K68='CTS Overheads'!G86 -> TRUE | L69: =L68='CTS Overheads'!H86 -> TRUE | M69: =M68='CTS Overheads'!I86 -> TRUE | N69: =N68='CTS Overheads'!J86 -> TRUE | O69: =O68='CTS Overheads'!K86 -> TRUE | ... S69: =S68='CTS Overheads'!O86 -> TRUE
G70: CONS Overhead | H70: =-CONS!G20 -> 9396.6785 | I70: =-CONS!H20 -> 8644.3708 | J70: =-CONS!I20 -> 10205.217 | K70: =-CONS!J20 -> 10205.217 | L70: =-CONS!K20 -> 9476.2939 | M70: =-CONS!L20 -> 9840.7554 | N70: =-CONS!M20 -> 9476.2939 | O70: =-CONS!N20 -> 9476.2939 | ... S70: =-CONS!R20 -> 9840.7554 | T70: =SUM(H70:S70) -> 116084.14
G71: ONS Overhead | H71: =-ONS!F23 -> 29319.965 | I71: =-ONS!G23 -> 26580.438 | J71: =-ONS!H23 -> 28659.961 | K71: =-ONS!I23 -> 28659.961 | L71: =-ONS!J23 -> 26580.438 | M71: =-ONS!K23 -> 27620.2 | N71: =-ONS!L23 -> 26580.438 | O71: =-ONS!M23 -> 26580.438 | ... S71: =-ONS!Q23 -> 27620.2 | T71: =SUM(H71:S71) -> 331062.64
G72: PRD Overhead | H72: =-PRD!H24 -> 53188.411 | I72: =-PRD!I24 -> 50814.257 | J72: =-PRD!J24 -> 54967.663 | K72: =-PRD!K24 -> 54967.663 | L72: =-PRD!L24 -> 55942.961 | M72: =-PRD!M24 -> 51833.165 | N72: =-PRD!N24 -> 50814.257 | O72: =-PRD!O24 -> 50814.257 | ... S72: =-PRD!S24 -> 51833.165 | T72: =SUM(H72:S72) -> 630675.29
G73: Total Expenses | H73: =SUM(H23:H67)+SUM(H70:H72) -> 218401.7 | I73: =SUM(I23:I67)+SUM(I70:I72) -> 239717.06 | J73: =SUM(J23:J67)+SUM(J70:J72) -> 231573.15 | K73: =SUM(K23:K67)+SUM(K70:K72) -> 209130.75 | L73: =SUM(L23:L67)+SUM(L70:L72) -> 202345.83 | M73: =SUM(M23:M67)+SUM(M70:M72) -> 201077.04 | N73: =SUM(N23:N67)+SUM(N70:N72) -> 201203.71 | O73: =SUM(O23:O67)+SUM(O70:O72) -> 197422.84 | ... S73: =SUM(S23:S67)+SUM(S70:S72) -> 208102.17 | T73: =SUM(H73:S73) -> 2528203.2
G74: Operating Profit | H74: =+H20-H73 -> 51905.235 | I74: =+I20-I73 -> 277895.13 | J74: =+J20-J73 -> -107100.12 | K74: =+K20-K73 -> 267105.71 | L74: =+L20-L73 -> 78742.202 | M74: =+M20-M73 -> -98031.373 | N74: =+N20-N73 -> -26307.59 | O74: =+O20-O73 -> 129358.62 | ... S74: =+S20-S73 -> -117806.5 | T74: =SUM(H74:S74) -> 397250.75
G75: Profit Margin | H75: =+H74/H6 -> 0.085191497 | I75: =+I74/I6 -> 0.28555727 | J75: =+J74/J6 -> -0.25890565 | K75: =+K74/K6 -> 0.28104093 | L75: =+L74/L6 -> 0.14573653 | M75: =+M74/M6 -> -0.28417347 | N75: =+N74/N6 -> -0.074321659 | O75: =+O74/O6 -> 0.22433968 | ... T75: =+T74/T6 -> 0.063009662
H77: =H68 -> 126496.64 | I77: =I68 -> 153678 | J77: =J68 -> 137740.31 | K77: =K68 -> 115297.91 | L77: =L68 -> 110346.14 | M77: =M68 -> 111782.92 | N77: =N68 -> 114332.72 | O77: =O68 -> 110551.85 | ... R77: =R68 -> 119379.69 | S77: Check | T77: =SUM(T23:T67)-'CTS Overheads'!P86 -> -0.0039672309
H79: =H68-H77 -> 0 | I79: =I68-I77 -> 0 | J79: =J68-J77 -> 0 | K79: =K68-K77 -> 0 | L79: =L68-L77 -> 0 | M79: =M68-M77 -> 0 | N79: =N68-N77 -> 0 | O79: =O68-O77 -> 0 | ... R79: =R68-R77 -> 0
H82: =-(CONS!G20+ONS!F23+PRD!H24) -> 91905.055

Sheet CTS Overheads
D1: FORECAST | E1: FORECAST | F1: FORECAST | G1: FORECAST | H1: FORECAST | I1: FORECAST | J1: FORECAST | K1: FORECAST | L1: FORECAST | M1: FORECAST | N1: FORECAST | O1: FORECAST | P1: FORECAST
A2: CTS Overheads | D2: 46204 | E2: 46235 | F2: 46266 | G2: 46296 | H2: 46327 | I2: 46357 | J2: 46388 | K2: 46419 | L2: 46447 | M2: 46478 | N2: 46508 | O2: 46539 | P2: Total
A3: Accounting Fees | B3: KPMG FY2027 | D3: =(25000/12)+(16000/12) -> 3416.6667 | E3: =D3 -> 3416.6667 | F3: =E3+750 -> 4166.6667 | G3: =F3 -> 4166.6667 | H3: =G3 -> 4166.6667 | I3: =H3 -> 4166.6667 | J3: =I3 -> 4166.6667 | K3: =J3 -> 4166.6667 | L3: =K3+1550 -> 5716.6667 | M3: =L3 -> 5716.6667 | N3: =M3 -> 5716.6667 | O3: =N3 -> 5716.6667 | P3: =SUM(D3:O3) -> 54700
A4: Legal Fees | B4: Employsure (WHS & FW) until 2028 | D4: 800 | E4: 800 | F4: 800 | G4: 800 | H4: 800 | I4: 800 | J4: 800 | K4: 800 | L4: 800 | M4: 800 | N4: 800 | O4: 800 | P4: =SUM(D4:O4) -> 9600 | Q4: Employsure $800 p/m
A5: Legal Fees | B5: Easton Belle & Meyer West | D5: 1000 | E5: =D5 -> 1000 | F5: =E5 -> 1000 | G5: =F5 -> 1000 | H5: =G5 -> 1000 | I5: =H5 -> 1000 | J5: =I5 -> 1000 | K5: =J5 -> 1000 | L5: =K5 -> 1000 | ... O5: =N5 -> 1000 | P5: =SUM(D5:O5) -> 12000
A6: Payroll Processing Fee | B6: Employment Hero | D6: 2150 | E6: =D6 -> 2150 | F6: =E6 -> 2150 | G6: =F6 -> 2150 | H6: =G6 -> 2150 | I6: =H6 -> 2150 | J6: =I6 -> 2150 | K6: =J6 -> 2150 | L6: =K6 -> 2150 | ... O6: =N6 -> 2150 | P6: =SUM(D6:O6) -> 25800
A7: Bank Charges | B7: CBA/CCs | D7: 500 | E7: =D7 -> 500 | F7: =E7 -> 500 | G7: =F7 -> 500 | H7: =G7 -> 500 | I7: =H7 -> 500 | J7: =I7 -> 500 | K7: =J7 -> 500 | L7: =2258+500 -> 2758 | M7: =K7 -> 500 | N7: =L7 -> 2758 | O7: =M7 -> 500 | P7: =SUM(D7:O7) -> 10516
A8: Dues & Subscriptions | B8: MYOB/Xero | D8: =90.91+2 -> 92.91 | E8: =D8 -> 92.91 | F8: =E8 -> 92.91 | G8: =F8 -> 92.91 | H8: =G8 -> 92.91 | I8: =H8 -> 92.91 | J8: =I8 -> 92.91 | K8: =J8 -> 92.91 | L8: =K8 -> 92.91 | ... O8: =N8 -> 92.91 | P8: =SUM(D8:O8) -> 1114.92
B9: ESG (SBTi) | D9: 500 | E9: =D9 -> 500 | F9: =E9 -> 500 | G9: =F9 -> 500 | H9: =G9 -> 500 | I9: =H9 -> 500 | J9: =I9 -> 500 | K9: =J9 -> 500 | L9: =K9 -> 500 | ... O9: =N9 -> 500 | P9: =SUM(D9:O9) -> 6000
B10: First Focus (Managed Services Azure) | D10: 595 | E10: =D10 -> 595 | F10: =E10 -> 595 | G10: =F10 -> 595 | H10: =G10 -> 595 | I10: =H10 -> 595 | J10: =I10 -> 595 | K10: =J10 -> 595 | L10: =K10 -> 595 | ... O10: =N10 -> 595 | P10: =SUM(D10:O10) -> 7140 | Q10: MS Licences | S10: IT Costs:
B11: First Focus (MSA, Office, Planner, Visio, Business) | D11: 2897.09 | E11: =D11 -> 2897.09 | F11: =E11 -> 2897.09 | G11: =F11 -> 2897.09 | H11: =G11 -> 2897.09 | I11: =H11 -> 2897.09 | J11: =I11 -> 2897.09 | K11: =J11 -> 2897.09 | L11: =K11 -> 2897.09 | ... O11: =N11 -> 2897.09 | P11: =SUM(D11:O11) -> 34765.08 | Q11: Inclusive if MS increases as per FF
B12: The CEO Institute (DL & JS) | D12: 700 | E12: =D12 -> 700 | F12: =E12 -> 700 | G12: =F12*2 -> 1400 | H12: =G12 -> 1400 | I12: =H12 -> 1400 | J12: =I12 -> 1400 | K12: =J12 -> 1400 | L12: =K12 -> 1400 | M12: =L12 -> 1400 | N12: =M12 -> 1400 | O12: =N12 -> 1400 | P12: =SUM(D12:O12) -> 14700 | S12: Microsoft Azure | T12: 597 | U12: =T12+T13 -> 2097
B13: Dashlane | D13: =2790/12 -> 232.5 | E13: =D13 -> 232.5 | F13: =E13 -> 232.5 | G13: =F13 -> 232.5 | H13: =G13 -> 232.5 | I13: =H13 -> 232.5 | J13: =I13 -> 232.5 | K13: =J13 -> 232.5 | L13: =K13 -> 232.5 | ... O13: =N13 -> 232.5 | P13: =SUM(D13:O13) -> 2790 | S13: MSA and Office | T13: 1500
B14: Linkedin (Jordan&Graham) | D14: =37+60 -> 97 | E14: =D14 -> 97 | F14: =E14 -> 97 | G14: =F14 -> 97 | H14: =G14 -> 97 | I14: =H14 -> 97 | J14: =I14 -> 97 | K14: =J14 -> 97 | L14: =K14 -> 97 | ... O14: =N14 -> 97 | P14: =SUM(D14:O14) -> 1164 | Q14: **Linkedin (Jordan) - monthly
B15: Lucidchart (USD) | D15: =505/12 -> 42.083333 | E15: =D15 -> 42.083333 | F15: =E15 -> 42.083333 | G15: =F15 -> 42.083333 | H15: =G15 -> 42.083333 | I15: =H15 -> 42.083333 | J15: =I15 -> 42.083333 | K15: =J15 -> 42.083333 | L15: =K15 -> 42.083333 | ... O15: =N15 -> 42.083333 | P15: =SUM(D15:O15) -> 505
B16: AVIXA Annual Silver Membership | D16: =2850/12 -> 237.5 | E16: =D16 -> 237.5 | F16: =E16 -> 237.5 | G16: =F16 -> 237.5 | H16: =G16 -> 237.5 | I16: =H16 -> 237.5 | J16: =I16 -> 237.5 | K16: =J16 -> 237.5 | L16: =K16 -> 237.5 | ... O16: =N16 -> 237.5 | P16: =SUM(D16:O16) -> 2850
B17: Apple (icloud) | D17: 14 | E17: =D17 -> 14 | F17: =E17 -> 14 | G17: =F17 -> 14 | H17: =G17 -> 14 | I17: =H17 -> 14 | J17: =I17 -> 14 | K17: =J17 -> 14 | L17: =K17 -> 14 | ... O17: =N17 -> 14 | P17: =SUM(D17:O17) -> 168
B18: Zoho | D18: =2640/12 -> 220 | E18: =D18 -> 220 | F18: =E18 -> 220 | G18: =F18 -> 220 | H18: =G18 -> 220 | I18: =H18 -> 220 | J18: =I18 -> 220 | K18: =J18 -> 220 | L18: =K18 -> 220 | ... O18: =N18 -> 220 | P18: =SUM(D18:O18) -> 2640
B19: Dicker Data (subscription&support for neat pulse pro until 2027) | D19: 38.75 | E19: =D19 -> 38.75 | F19: 38.75 | G19: 38.75 | H19: 38.75 | I19: 38.75 | J19: 38.75 | K19: 38.75 | L19: 38.75 | M19: 38.75 | N19: 38.75 | O19: 38.75 | P19: =SUM(D19:O19) -> 465 | Q19: *neat pulse pro
B20: Amazon | D20: =71.82/12 -> 5.985 | E20: =D20 -> 5.985 | F20: =71.82/12 -> 5.985 | G20: =71.82/12 -> 5.985 | H20: =71.82/12 -> 5.985 | I20: =71.82/12 -> 5.985 | J20: =71.82/12 -> 5.985 | K20: =71.82/12 -> 5.985 | L20: =71.82/12 -> 5.985 | M20: =71.82/12 -> 5.985 | ... O20: =71.82/12 -> 5.985 | P20: =SUM(D20:O20) -> 71.82 | Q20: *swapped to annual fee from 05/12/2024
B21: Adobe (Marketing) | D21: =113.49/1.1 -> 103.17273 | E21: =D21 -> 103.17273 | F21: =E21 -> 103.17273 | G21: =F21 -> 103.17273 | H21: =G21 -> 103.17273 | I21: =H21 -> 103.17273 | J21: =I21 -> 103.17273 | K21: =J21 -> 103.17273 | L21: =K21 -> 103.17273 | ... O21: =N21 -> 103.17273 | P21: =SUM(D21:O21) -> 1238.0727
B22: Youtube (DL) | D22: 16 | E22: =D22 -> 16 | F22: =E22 -> 16 | G22: =F22 -> 16 | H22: =G22 -> 16 | I22: =H22 -> 16 | J22: =I22 -> 16 | K22: =J22 -> 16 | L22: =K22 -> 16 | ... O22: =N22 -> 16 | P22: =SUM(D22:O22) -> 192
B23: Trends Journal | D23: =140/12 -> 11.666667 | E23: =D23 -> 11.666667 | F23: =E23 -> 11.666667 | G23: =F23 -> 11.666667 | H23: =G23 -> 11.666667 | I23: =H23 -> 11.666667 | J23: =I23 -> 11.666667 | K23: =J23 -> 11.666667 | L23: =K23 -> 11.666667 | ... O23: =N23 -> 11.666667 | P23: =SUM(D23:O23) -> 140
B24: GPTW | D24: =383.33 -> 383.33 | E24: =D24 -> 383.33 | F24: =E24 -> 383.33 | G24: =F24 -> 383.33 | H24: =G24 -> 383.33 | I24: =H24 -> 383.33 | J24: =I24 -> 383.33 | K24: =J24 -> 383.33 | L24: =K24 -> 383.33 | ... O24: =N24 -> 383.33 | P24: =SUM(D24:O24) -> 4599.96
A25: =SUM(D8:D25) -> 6686.9877 | B25: Buffer | D25: 500 | E25: =D25 -> 500 | F25: =E25 -> 500 | G25: =F25 -> 500 | H25: =G25 -> 500 | I25: =H25 -> 500 | J25: =I25 -> 500 | K25: =J25 -> 500 | L25: =K25 -> 500 | ... O25: =N25 -> 500 | P25: =SUM(D25:O25) -> 6000
A26: Donations & Charity | B26: Donations | D26: 0 | E26: 0 | F26: 0 | G26: 0 | H26: 0 | I26: 0 | J26: 0 | K26: 200 | L26: 0 | M26: 0 | N26: 0 | O26: 5000 | P26: =SUM(D26:O26) -> 5200
A27: Freight Paid | B27: Freight | D27: 30 | E27: 30 | F27: 30 | G27: 30 | H27: 30 | I27: 150 | J27: 30 | K27: 30 | L27: 30 | M27: 30 | N27: 30 | O27: 30 | P27: =SUM(D27:O27) -> 480
A28: Filing Fee | B28: Filing Fee - Meyer West | F28: 825 | P28: =SUM(D28:O28) -> 825 | Q28: *ASIC filing fee $300 ~~
A29: Instant Asset Write Off | B29: Instant Asset Write-Off (up to $20k per asset) | D29: 5000 | E29: =D29 -> 5000 | F29: =E29 -> 5000 | G29: =F29 -> 5000 | H29: =G29 -> 5000 | I29: =H29 -> 5000 | J29: =I29 -> 5000 | K29: =J29 -> 5000 | L29: =K29 -> 5000 | ... O29: =N29 -> 5000 | P29: =SUM(D29:O29) -> 60000 | Q29: (office assets) - includes 14k extra from FY2025
A30: Credit Card Fees Paid | B30: CC fees | D30: 20 | E30: =D30 -> 20 | F30: =E30 -> 20 | G30: =F30 -> 20 | H30: =G30 -> 20 | I30: =H30 -> 20 | J30: =I30 -> 20 | K30: =J30 -> 20 | L30: =K30 -> 20 | ... O30: =N30 -> 20 | P30: =SUM(D30:O30) -> 240
A31: Business Advisory | B31: 80/20 Advisors | D31: 1200 | E31: =D31 -> 1200 | F31: =E31 -> 1200 | G31: =F31 -> 1200 | H31: =G31 -> 1200 | I31: =H31 -> 1200 | J31: =I31 -> 1200 | K31: =J31 -> 1200 | L31: =K31 -> 1200 | ... O31: =N31 -> 1200 | P31: =SUM(D31:O31) -> 14400
A32: Custodian Vaults | B32: Custodian Vaults | D32: =2699.09/12 -> 224.92417 | E32: =D32 -> 224.92417 | F32: =E32 -> 224.92417 | G32: =F32 -> 224.92417 | H32: =G32 -> 224.92417 | I32: =H32 -> 224.92417 | J32: =I32 -> 224.92417 | K32: =J32 -> 224.92417 | L32: =K32 -> 224.92417 | ... O32: =N32 -> 224.92417 | P32: =SUM(D32:O32) -> 2699.09 | Q32: =2897-263.36 -> 2633.64
A33: Taxis/Parking | B33: Taxis/Parking | D33: 300 | E33: 550 | F33: 300 | G33: 150 | H33: 150 | I33: 100 | J33: 50 | K33: 150 | L33: 150 | M33: 100 | N33: 150 | O33: 100 | P33: =SUM(D33:O33) -> 2250
A34: Stamp Duty (Indirect) | B34: Stamp Duty (indirect) | D34: 0 | E34: 0 | F34: =SUM(V37:V44) -> 2741.81 | G34: 0 | H34: 0 | I34: 0 | J34: 0 | K34: 0 | L34: 0 | M34: 0 | N34: 0 | O34: 0 | P34: =SUM(D34:O34) -> 2741.81
A35: Other Insurance | P35: =SUM(D35:O35) -> 0
B36: Key Man (Asteron) | D36: =9000/12 -> 750 | E36: =D36 -> 750 | F36: =E36 -> 750 | G36: =F36 -> 750 | H36: =G36 -> 750 | I36: =H36 -> 750 | J36: =I36 -> 750 | K36: =J36 -> 750 | L36: =K36 -> 750 | ... O36: =N36 -> 750 | P36: =SUM(D36:O36) -> 9000 | R36: Insurances FY26 | S36: Insurer | T36: Invoice Number | U36: Amount (Premium + FSL) | V36: Stamp Duty | W36: Period Covered | X36: GL Code | Z36: Cost Centre
B37: Bus. Com (Brookvale) | D37: =U37/12 -> 232.51167 | E37: =D37 -> 232.51167 | F37: =E37 -> 232.51167 | G37: =F37 -> 232.51167 | H37: =G37 -> 232.51167 | I37: =H37 -> 232.51167 | J37: =I37 -> 232.51167 | K37: =J37 -> 232.51167 | L37: =K37 -> 232.51167 | ... O37: =N37 -> 232.51167 | P37: =SUM(D37:O37) -> 2790.14 | R37: 1. Business Communication | S37: CGU | T37: 1847146 | U37: =1771.34+328.8+690 -> 2790.14 | V37: 207.9 | W37: 30/09/2025 to 30/09/2026 | X37: 6-2300 Other Insurance | Z37: 9000
B38: Business Interruption (Brookvale) | D38: =U38/12 -> 0 | E38: =D38 -> 0 | F38: =E38 -> 0 | G38: =F38 -> 0 | H38: =G38 -> 0 | I38: =H38 -> 0 | J38: =I38 -> 0 | K38: =J38 -> 0 | L38: =K38 -> 0 | ... O38: =N38 -> 0 | P38: =SUM(D38:O38) -> 0 | R38: 2. Business Interruption | S38: IUA | U38: 0 | V38: 0 | X38: 6-2300 Other Insurance | Z38: 9000
B39: IT (Brookvale) | D39: =U43/12 -> 1946.6767 | E39: =D39 -> 1946.6767 | F39: =E39 -> 1946.6767 | G39: =F39 -> 1946.6767 | H39: =G39 -> 1946.6767 | I39: =H39 -> 1946.6767 | J39: =I39 -> 1946.6767 | K39: =J39 -> 1946.6767 | L39: =K39 -> 1946.6767 | ... O39: =N39 -> 1946.6767 | P39: =SUM(D39:O39) -> 23360.12 | R39: 3. Removable equipment | S39: AIG | T39: 1847147 | U39: =5621.05+716.67+1200 -> 7537.72 | V39: 349.19 | W39: 30/09/2026 to 30/09/2026 | X39: 6-2300 Other Insurance | Z39: 9100
A40: =SUM(D36:D40) -> 3414.6608 | B40: Management Liability (Brookvale) | D40: =U44/12 -> 485.4725 | E40: =D40 -> 485.4725 | F40: =E40 -> 485.4725 | G40: =F40 -> 485.4725 | H40: =G40 -> 485.4725 | I40: =H40 -> 485.4725 | J40: =I40 -> 485.4725 | K40: =J40 -> 485.4725 | L40: =K40 -> 485.4725 | ... O40: =N40 -> 485.4725 | P40: =SUM(D40:O40) -> 5825.67 | R40: 4. Mecon Annual Contract Works | S40: Mecon | T40: 1847148 | U40: =3593+306.46+220+770 -> 4889.46 | V40: 378.89 | W40: 30/09/2026 to 30/09/2026 | X40: 6-2300 Other Insurance | Z40: 9200
A41: Travel Insurance | B41: Corp Travel Policy&Group Journey (Brookvale) | D41: =SUM(U41+U42)/12 -> 105.25 | E41: =D41 -> 105.25 | F41: =E41 -> 105.25 | G41: =F41 -> 105.25 | H41: =G41 -> 105.25 | I41: =H41 -> 105.25 | J41: =I41 -> 105.25 | K41: =J41 -> 105.25 | L41: =K41 -> 105.25 | ... O41: =N41 -> 105.25 | P41: =SUM(D41:O41) -> 1263 | R41: 5. Corporate Travel | S41: Chubb | T41: 1847169 | U41: =300+663+300 -> 1263 | V41: 35.37 | W41: 30/09/2026 to 30/09/2026 | X41: 6-2400 Travel Insurance | Z41: 9000
A42: Advertising | R42: 6. Group Journey Cover | S42: Chubb | U42: 0 | V42: 0 | X42: 6-2300 Other Insurance | Z42: 9000
R43: 7. IT Liability | S43: Chubb | T43: 1846354 | U43: =20000+3360.12 -> 23360.12 | V43: 1384 | W43: 30/09/2026 to 30/09/2026 | X43: 6-2300 Other Insurance | Z43: 9000
B44: Blinq Technologies | D44: 0 | E44: =D44 -> 0 | F44: =E44 -> 0 | G44: =F44 -> 0 | H44: =G44 -> 0 | I44: =H44 -> 0 | J44: =I44 -> 0 | K44: =J44 -> 0 | L44: =K44 -> 0 | ... O44: =N44 -> 0 | P44: =SUM(D44:O44) -> 0 | R44: 8. Management Liability | S44: Chubb | T44: 1846314 | U44: =4500.67+1325 -> 5825.67 | V44: 386.46 | W44: 30/09/2026 to 30/09/2026 | X44: 6-2300 Other Insurance | Z44: 9000
B45: Webflow (CMS) (USD) | D45: =(714)/12 -> 59.5 | E45: =D45 -> 59.5 | F45: =E45 -> 59.5 | G45: =F45 -> 59.5 | H45: =G45 -> 59.5 | I45: =H45 -> 59.5 | J45: =I45 -> 59.5 | K45: =J45 -> 59.5 | L45: =K45 -> 59.5 | ... O45: =N45 -> 59.5 | P45: =SUM(D45:O45) -> 714
B46: MailChimp | D46: 34.35 | E46: =D46 -> 34.35 | F46: =E46 -> 34.35 | G46: =F46 -> 34.35 | H46: =G46 -> 34.35 | I46: =H46 -> 34.35 | J46: =I46 -> 34.35 | K46: =J46 -> 34.35 | L46: =K46 -> 34.35 | ... O46: =N46 -> 34.35 | P46: =SUM(D46:O46) -> 412.2
B47: RJW Digital | D47: 4250 | E47: =4250+12000 -> 16250 | F47: 4250 | G47: 4250 | H47: 4250 | I47: 4250 | J47: 4250 | K47: 4250 | L47: 4250 | M47: 4250 | N47: 4250 | O47: 4250 | P47: =SUM(D47:O47) -> 63000
B48: Discretionary | D48: 300 | E48: 9300 | F48: 300 | G48: 300 | H48: 300 | I48: 300 | J48: 300 | K48: 300 | L48: 300 | M48: 300 | N48: 300 | O48: 300 | P48: =SUM(D48:O48) -> 12600
A49: =SUM(D42:D48) -> 4643.85 | B49: Total | P49: =SUM(D49:O49) -> 0
A50: Office Supplies | D50: 200 | E50: 200 | F50: 200 | G50: 200 | H50: 200 | I50: 200 | J50: 200 | K50: 200 | L50: 200 | M50: 200 | N50: 200 | O50: 200 | P50: =SUM(D50:O50) -> 2400
A51: Postage | B51: Postage | D51: 0 | E51: 0 | F51: 0 | G51: 0 | H51: 0 | I51: 250 | J51: 100 | K51: 0 | L51: 0 | M51: 0 | N51: 0 | O51: 0 | P51: =SUM(D51:O51) -> 350
A52: =D51+D52 -> 47 | B52: PO Box (AusPost) | D52: 47 | E52: 47 | F52: 47 | G52: 47 | H52: 47 | I52: 47 | J52: 47 | K52: 47 | L52: 47 | M52: 47 | N52: 47 | O52: 47 | P52: =SUM(D52:O52) -> 564
A53: Printing | B53: Ricoh | D53: 200 | E53: =D53 -> 200 | F53: =E53 -> 200 | G53: =F53 -> 200 | H53: =G53 -> 200 | I53: =H53 -> 200 | J53: =I53 -> 200 | K53: =J53 -> 200 | L53: =K53 -> 200 | ... O53: =N53 -> 200 | P53: =SUM(D53:O53) -> 2400
A54: Electricity | B54: Energy Australia | D54: 300 | E54: =D54 -> 300 | F54: =E54 -> 300 | G54: =F54 -> 300 | H54: =G54 -> 300 | I54: =H54 -> 300 | J54: =I54 -> 300 | K54: =J54 -> 300 | L54: =K54 -> 300 | ... O54: =N54 -> 300 | P54: =SUM(D54:O54) -> 3600
A55: Repairs & Maintenance | B55: Miscellaneous | D55: 200 | E55: 200 | F55: 200 | G55: 200 | H55: 200 | I55: 200 | J55: 200 | K55: 200 | L55: 200 | M55: 200 | N55: 200 | O55: 200 | P55: =SUM(D55:O55) -> 2400 | Q55: *3.75% increase on rent & outgoing
A56: 1300 & 1800 Number | B56: Optus | D56: 65 | E56: =D56 -> 65 | F56: =E56 -> 65 | G56: =F56 -> 65 | H56: =G56 -> 65 | I56: =H56 -> 65 | J56: =I56 -> 65 | K56: =J56 -> 65 | L56: =K56 -> 65 | ... O56: =N56 -> 65 | P56: =SUM(D56:O56) -> 780
A57: Office Phones | B57: Optus (Evolve Voice) | D57: 200 | E57: =D57 -> 200 | F57: =E57 -> 200 | G57: =F57 -> 200 | H57: =G57 -> 200 | I57: =H57 -> 200 | J57: =I57 -> 200 | K57: =J57 -> 200 | L57: =K57 -> 200 | ... O57: =N57 -> 200 | P57: =SUM(D57:O57) -> 2400
A58: Mobile Phones | B58: Optus (All coded to 9000) | D58: =275 -> 275 | E58: =D58 -> 275 | F58: =E58 -> 275 | G58: =F58 -> 275 | H58: =G58 -> 275 | I58: =H58 -> 275 | J58: =I58 -> 275 | K58: =J58 -> 275 | L58: =K58 -> 275 | ... O58: =N58 -> 275 | P58: =SUM(D58:O58) -> 3300
A59: Internet | B59: Optus (Evolve Internet + Lugstein Home wifi) | D59: =300+101.2 -> 401.2 | E59: =D59 -> 401.2 | F59: =E59 -> 401.2 | G59: =F59 -> 401.2 | H59: =G59 -> 401.2 | I59: =H59 -> 401.2 | J59: =I59 -> 401.2 | K59: =J59 -> 401.2 | L59: =K59 -> 401.2 | ... O59: =N59 -> 401.2 | P59: =SUM(D59:O59) -> 4814.4
A60: Office Cleaning | B60: Posh Services (Plant maintenance) | D60: =124.85+215 -> 339.85 | E60: =D60 -> 339.85 | F60: =E60 -> 339.85 | G60: =F60 -> 339.85 | H60: =G60 -> 339.85 | I60: =H60 -> 339.85 | J60: =I60 -> 339.85 | K60: =J60 -> 339.85 | L60: =K60 -> 339.85 | ... O60: =N60 -> 339.85 | P60: =SUM(D60:O60) -> 4078.2 | Q60: 625.75
A61: IT Network Service & Support | B61: First Focus Total Support Fee (incl DMARC, Storage, Firewall + Projects+CORE Managed) | D61: =8530+3750+150 -> 12430 | E61: =D61 -> 12430 | F61: =E61 -> 12430 | G61: =F61 -> 12430 | H61: =G61 -> 12430 | I61: =H61 -> 12430 | J61: =I61 -> 12430 | K61: =J61 -> 12430 | L61: =K61 -> 12430 | ... O61: =N61 -> 12430 | P61: =SUM(D61:O61) -> 149160 | Q61: IT Support (monthly) 6-4700
A62: Travel & Per Diems | B62: Travel & PD | D62: 200 | E62: 9200 | F62: 200 | G62: 200 | H62: 200 | I62: 3000 | J62: 200 | K62: 200 | L62: 200 | M62: 200 | N62: 200 | O62: 200 | P62: =SUM(D62:O62) -> 14200 | Q62: *reduced from $400. Does this include travel for Interstate xmas parties?
A63: Client Entertainment | B63: Client Entertainment | D63: 500 | E63: 500 | F63: =500+8000 -> 8500 | G63: 500 | H63: 500 | I63: 5000 | J63: 500 | K63: 500 | L63: 500 | M63: 500 | N63: 500 | O63: 500 | P63: =SUM(D63:O63) -> 18500
A64: Leave expense (Long Service Admin) | B64: LSL | D64: =J117 -> 188.65 | E64: 528.34 | F64: 528.34 | G64: 528.34 | H64: 528.34 | I64: 528.34 | J64: 528.34 | K64: 528.34 | L64: 528.34 | M64: 528.34 | N64: 528.34 | O64: 528.34 | P64: =SUM(D64:O64) -> 6000.39
A65: Leave expense (Annual Leave - Admin) | B65: AL | D65: =$I$117 -> 947.96153 | E65: =$I$117 -> 947.96153 | F65: =$I$117 -> 947.96153 | G65: =$I$117 -> 947.96153 | H65: =$I$117 -> 947.96153 | I65: =$I$117 -> 947.96153 | J65: =$I$117 -> 947.96153 | K65: =$I$117 -> 947.96153 | ... O65: =$I$117 -> 947.96153 | P65: =SUM(D65:O65) -> 11375.538
A66: Leave expense Annual Leave (ONS, CONS, PRD) | D66: ='CONS Fixed Costs'!C35+'ONS Fixed Costs'!C52+'PRD Fixed Costs'!B75 -> 4862.8512 | E66: ='CONS Fixed Costs'!D35+'ONS Fixed Costs'!D52+'PRD Fixed Costs'!C75 -> 4862.8512 | F66: ='CONS Fixed Costs'!E35+'ONS Fixed Costs'!E52+'PRD Fixed Costs'!D75 -> 4862.8512 | G66: ='CONS Fixed Costs'!F35+'ONS Fixed Costs'!F52+'PRD Fixed Costs'!E75 -> 4862.8512 | H66: ='CONS Fixed Costs'!G35+'ONS Fixed Costs'!G52+'PRD Fixed Costs'!F75 -> 4862.8512 | I66: ='CONS Fixed Costs'!H35+'ONS Fixed Costs'!H52+'PRD Fixed Costs'!G75 -> 4862.8512 | J66: ='CONS Fixed Costs'!I35+'ONS Fixed Costs'!I52+'PRD Fixed Costs'!H75 -> 4862.8512 | K66: ='CONS Fixed Costs'!J35+'ONS Fixed Costs'!J52+'PRD Fixed Costs'!I75 -> 4862.8512 | ... O66: ='CONS Fixed Costs'!N35+'ONS Fixed Costs'!N52+'PRD Fixed Costs'!M75 -> 4862.8512 | P66: =SUM(D66:O66) -> 58354.214
A67: Leave expense LSL (ONS, CONS, PRD) | D67: ='CONS Fixed Costs'!C36+'ONS Fixed Costs'!C53+'PRD Fixed Costs'!B76 -> 608.83984 | E67: ='CONS Fixed Costs'!D36+'ONS Fixed Costs'!D53+'PRD Fixed Costs'!C76 -> 608.83984 | F67: ='CONS Fixed Costs'!E36+'ONS Fixed Costs'!E53+'PRD Fixed Costs'!D76 -> 608.83984 | G67: ='CONS Fixed Costs'!F36+'ONS Fixed Costs'!F53+'PRD Fixed Costs'!E76 -> 608.83984 | H67: ='CONS Fixed Costs'!G36+'ONS Fixed Costs'!G53+'PRD Fixed Costs'!F76 -> 608.83984 | I67: ='CONS Fixed Costs'!H36+'ONS Fixed Costs'!H53+'PRD Fixed Costs'!G76 -> 608.83984 | J67: ='CONS Fixed Costs'!I36+'ONS Fixed Costs'!I53+'PRD Fixed Costs'!H76 -> 608.83984 | K67: ='CONS Fixed Costs'!J36+'ONS Fixed Costs'!J53+'PRD Fixed Costs'!I76 -> 608.83984 | ... O67: ='CONS Fixed Costs'!N36+'ONS Fixed Costs'!N53+'PRD Fixed Costs'!M76 -> 608.83984 | P67: =SUM(D67:O67) -> 7306.0781
A68: Payroll Tax (Admin) | B68: Ptax | D68: =B103 -> 1664.6386 | E68: =C103 -> 1469.6717 | F68: =D103 -> 1614.7789 | G68: =E103 -> 1329.9726 | H68: =F103 -> 1210.7569 | I68: =G103 -> 853.10981 | J68: =H103 -> 1329.9726 | K68: =I103 -> 1210.7569 | ... O68: =M103 -> 1270.3647 | P68: =SUM(D68:O68) -> 15824.725 | Q68: *average of ptax 9000 CC
A69: Payroll Tax (ONS, CONS, PRD) | D69: ='CONS Fixed Costs'!C33+'ONS Fixed Costs'!C50+'PRD Fixed Costs'!B74 -> 6210.6198 | E69: ='CONS Fixed Costs'!D33+'ONS Fixed Costs'!D50+'PRD Fixed Costs'!C74 -> 5776.0142 | F69: ='CONS Fixed Costs'!E33+'ONS Fixed Costs'!E50+'PRD Fixed Costs'!D74 -> 6144.0716 | G69: ='CONS Fixed Costs'!F33+'ONS Fixed Costs'!F50+'PRD Fixed Costs'!E74 -> 6101.0627 | H69: ='CONS Fixed Costs'!G33+'ONS Fixed Costs'!G50+'PRD Fixed Costs'!F74 -> 5819.2293 | I69: ='CONS Fixed Costs'!H33+'ONS Fixed Costs'!H50+'PRD Fixed Costs'!G74 -> 6780.8086 | J69: ='CONS Fixed Costs'!I33+'ONS Fixed Costs'!I50+'PRD Fixed Costs'!H74 -> 5235.8741 | K69: ='CONS Fixed Costs'!J33+'ONS Fixed Costs'!J50+'PRD Fixed Costs'!I74 -> 5824.9404 | ... O69: ='CONS Fixed Costs'!N33+'ONS Fixed Costs'!N50+'PRD Fixed Costs'!M74 -> 5496.1706 | P69: =SUM(D69:O69) -> 72333.746
A70: Staff Amenities | B70: Miscellaneous | D70: 100 | E70: 100 | F70: 100 | G70: =100+100 -> 200 | H70: 100 | I70: 100 | J70: 100 | K70: 100 | L70: 100 | M70: 100 | N70: 100 | O70: 100 | P70: =SUM(D70:O70) -> 1300
B71: Zip water filter | E71: 0 | F71: 565 | G71: 0 | H71: 0 | I71: 565 | J71: 0 | K71: 0 | L71: 565 | M71: 0 | N71: 0 | O71: 0 | P71: =SUM(D71:O71) -> 1695 | Q71: *filter only excl. labour
A72: Staff Entertainment | B72: Staff Ent | D72: 500 | E72: 5000 | F72: 500 | G72: 500 | H72: 500 | I72: =2500+1500+2500 -> 6500 | J72: 500 | K72: 500 | L72: 500 | M72: 500 | N72: 500 | O72: 500 | P72: =SUM(D72:O72) -> 16500 | Q72: **includes xmas gifts
A73: Superannuation (Admin) | B73: Based on calc below | D73: =B102+B104 -> 8826.3442 | E73: =C102+C104 -> 8046.4769 | F73: =D102+D104 -> 8626.9056 | G73: =E102+E104 -> 7487.6802 | H73: =F102+F104 -> 7010.8175 | I73: =G102+G104 -> 5580.2292 | J73: =H102+H104 -> 7487.6802 | K73: =I102+I104 -> 7010.8175 | ... O73: =M102+M104 -> 7249.2488 | P73: =SUM(D73:O73) -> 89312.378 | Q73: **Interstate parties allocated to ONS
A74: Indirect Wages/Salaries - Admin | B74: Based on calc below | D74: =+B$101 -> 55487.952 | E74: =+C$101 -> 48989.058 | F74: =+D$101 -> 53825.963 | G74: =+E$101 -> 44332.418 | H74: =+F$101 -> 40358.562 | I74: =+G$101 -> 28436.994 | J74: =+H$101 -> 44332.418 | K74: =+I$101 -> 40358.562 | ... O74: =+M$101 -> 42345.49 | P74: =SUM(D74:O74) -> 527490.82
A75: Workers' Compensation | B75: NSW Worker's Comp (Admin only) | D75: =((5054.65/65)*5)/12 -> 32.401603 | E75: =D75 -> 32.401603 | F75: =E75 -> 32.401603 | G75: =F75 -> 32.401603 | H75: =G75 -> 32.401603 | I75: =H75 -> 32.401603 | J75: =I75 -> 32.401603 | K75: =J75 -> 32.401603 | L75: =K75 -> 32.401603 | ... O75: =N75 -> 32.401603 | P75: =SUM(D75:O75) -> 388.81923 | Q75: *monthly payment / total employed staff * number of admin staff' | U75: =412/77 -> 5.3506494 | X75: 7960 | Y75: IT
A76: Training Material & Courses | B76: AVIXA Annual Silver Membership | D76: =2591.91/12 -> 215.9925 | E76: =D76 -> 215.9925 | F76: =E76 -> 215.9925 | G76: =F76 -> 215.9925 | H76: =G76 -> 215.9925 | I76: =H76 -> 215.9925 | J76: =I76 -> 215.9925 | K76: =J76 -> 215.9925 | L76: =K76 -> 215.9925 | ... O76: =N76 -> 215.9925 | P76: =SUM(D76:O76) -> 2591.91 | X76: 1231.74 | Y76: MSA Managed
B77: Ispring | D77: 0 | E77: =D77 -> 0 | F77: =E77 -> 0 | G77: =F77 -> 0 | H77: =G77 -> 0 | I77: =H77 -> 0 | J77: =I77 -> 0 | K77: =J77 -> 0 | L77: =K77 -> 0 | ... O77: =N77 -> 0 | P77: =SUM(D77:O77) -> 0
B78: Buffer | D78: 350 | E78: 350 | F78: 350 | G78: 350 | H78: 350 | I78: 350 | J78: 350 | K78: 350 | L78: 350 | M78: 350 | N78: 350 | O78: 350 | P78: =SUM(D78:O78) -> 4200 | X78: 600 | Y78: Azure
B79: Training | D79: 500 | E79: =D79 -> 500 | F79: =E79 -> 500 | G79: =F79 -> 500 | H79: =G79 -> 500 | I79: =H79 -> 500 | J79: =I79 -> 500 | K79: =J79 -> 500 | L79: =K79 -> 500 | ... O79: =N79 -> 500 | P79: =SUM(D79:O79) -> 6000 | X79: 300 | Y79: Tickets
A80: =SUM(D76:D80) -> 1065.9925 | P80: =SUM(D80:O80) -> 0
A81: Recruitment | B81: Seek Ads, etc (Flatworld) | D81: =76 -> 76 | E81: =D81 -> 76 | F81: =E81 -> 76 | G81: =F81 -> 76 | H81: =G81 -> 76 | I81: =H81 -> 76 | J81: =I81 -> 76 | K81: =J81 -> 76 | L81: =K81 -> 76 | ... O81: =N81 -> 76 | P81: =SUM(D81:O81) -> 912
B82: Linkedin Job Post | D82: =6360/12 -> 530 | E82: 530 | F82: 530 | G82: 530 | H82: 530 | I82: 530 | J82: 530 | K82: 530 | L82: 530 | M82: 530 | N82: 530 | O82: 530 | P82: =SUM(D82:O82) -> 6360
E83: =D83 -> 0 | F83: =E83 -> 0 | G83: =F83 -> 0 | H83: =G83 -> 0 | I83: =H83 -> 0 | J83: =I83 -> 0 | K83: =J83 -> 0 | L83: =K83 -> 0 | ... O83: =N83 -> 0 | P83: =SUM(D83:O83) -> 0
A84: =SUM(D81:D84) -> 750 | B84: Police Check | D84: =72*2 -> 144 | E84: 144 | F84: 144 | G84: 144 | H84: 144 | I84: 144 | J84: 144 | K84: 144 | L84: 144 | M84: 144 | N84: 144 | O84: 144 | P84: =SUM(D84:O84) -> 1728
A85: Other Expenses | B85: Other Expense | D85: 400 | E85: 400 | F85: 400 | G85: 400 | H85: 400 | I85: 400 | J85: 400 | K85: 400 | L85: 400 | M85: 400 | N85: 400 | O85: 400 | P85: =SUM(D85:O85) -> 4800
A86: Total Expenses | D86: =ROUND(SUM(D3:D85),2) -> 126496.64 | E86: =ROUND(SUM(E3:E85),2) -> 153678 | F86: =ROUND(SUM(F3:F85),2) -> 137740.31 | G86: =ROUND(SUM(G3:G85),2) -> 115297.91 | H86: =ROUND(SUM(H3:H85),2) -> 110346.14 | I86: =ROUND(SUM(I3:I85),2) -> 111782.92 | J86: =ROUND(SUM(J3:J85),2) -> 114332.72 | K86: =ROUND(SUM(K3:K85),2) -> 110551.85 | ... P86: =ROUND(SUM(P3:P85),2) -> 1450381.1
A89: Public Holidays | B89: 0 | C89: 1 | D89: 0 | E89: 0 | F89: 0 | G89: 2 | H89: 2 | I89: 0 | J89: 0 | K89: 5 | L89: 0 | M89: 1
A90: Working Days | B90: 23 | C90: 20 | D90: 22 | E90: 22 | F90: 20 | G90: 14 | H90: 20 | I90: 20 | J90: 22 | K90: 20 | L90: 21 | M90: 21 | P90: =(P86-P88)/P88 -> #DIV/0!
B91: Jul | C91: Aug | D91: Sep | E91: Oct | F91: Nov | G91: Dec | H91: Jan | I91: Feb | J91: Mar | K91: Apr | L91: May | M91: Jun
A92: LUGSTEIN, Duncan | B92: =B107*$B$90*8 -> 4781.7626 | C92: =D107*$C$90*8 -> 4158.0544 | D92: =D107*$D$90*8 -> 4573.8598 | E92: =D107*$E$90*8 -> 4573.8598 | F92: =D107*$F$90*8 -> 4158.0544 | G92: =D107*$G$90*8 -> 2910.6381 | H92: =D107*$D$90*8 -> 4573.8598 | I92: =D107*$I$90*8 -> 4158.0544 | J92: =D107*$D$90*8 -> 4573.8598 | K92: =D107*$K$90*8 -> 4158.0544 | L92: =D107*$D$90*8 -> 4573.8598 | M92: =D107*$M$90*8 -> 4365.9571
A93: LUGSTEIN, Premila | B93: =B108*$B$90*8 -> 5801.8144 | C93: =D108*$C$90*8 -> 5045.056 | D93: =D108*$D$90*8 -> 5549.5616 | E93: =D108*$E$90*8 -> 5549.5616 | F93: =D108*$F$90*8 -> 5045.056 | G93: =D108*$G$90*8 -> 3531.5392 | H93: =D108*$D$90*8 -> 5549.5616 | I93: =D108*$I$90*8 -> 5045.056 | J93: =D108*$D$90*8 -> 5549.5616 | K93: =D108*$K$90*8 -> 5045.056 | L93: =D108*$D$90*8 -> 5549.5616 | M93: =D108*$M$90*8 -> 5297.3088
A94: CHERRY, Graham | B94: =B109*$B$90*8 -> 19068.895 | C94: =D109*$C$90*8 -> 16581.648 | D94: =D109*$D$90*8 -> 18239.813 | E94: =D109*$E$90*8 -> 18239.813 | F94: =D109*$F$90*8 -> 16581.648 | G94: =D109*$G$90*8 -> 11607.154 | H94: =D109*$D$90*8 -> 18239.813 | I94: =D109*$I$90*8 -> 16581.648 | J94: =D109*$D$90*8 -> 18239.813 | K94: =D109*$K$90*8 -> 16581.648 | L94: =D109*$D$90*8 -> 18239.813 | M94: =D109*$M$90*8 -> 17410.73
A95: SEXTY, Jordan | B95: =B110*$B$90*8 -> 11847.528 | C95: =D110*$C$90*8 -> 10611.264 | D95: =D110*$D$90*8 -> 11672.391 | E95: =D110*$E$90*8 -> 11672.391 | F95: =D110*$F$90*8 -> 10611.264 | G95: =D110*$G$90*8 -> 7427.885 | H95: =D110*$D$90*8 -> 11672.391 | I95: =D110*$I$90*8 -> 10611.264 | J95: =D110*$D$90*8 -> 11672.391 | K95: =D110*$K$90*8 -> 10611.264 | L95: =D110*$D$90*8 -> 11672.391 | M95: =D110*$M$90*8 -> 11141.828
A96: YAO, Gianmaria-Gonzales | B96: =B111*$B$90*8 -> 9635.9898 | C96: =D111*$C$90*8 -> 8630.4952 | D96: =D111*$D$90*8 -> 9493.5448 | E96: 0 | F96: 0 | G96: 0 | H96: 0 | I96: 0 | J96: 0 | K96: 0 | L96: 0 | M96: 0 | N96: *Maternity Leave
A97: WAIYA, Emelda | B97: =B112*$B$90*4.8 -> 3731.9616 | C97: =D112*$C$90*4.8 -> 3342.5395 | D97: =D112*$D$90*4.8 -> 3676.7935 | E97: =D112*$E$90*4.8 -> 3676.7935 | F97: =D112*$F$90*4.8 -> 3342.5395 | G97: =D112*$G$90*4.8 -> 2339.7777 | H97: =D112*$D$90*4.8 -> 3676.7935 | I97: =D112*$I$90*4.8 -> 3342.5395 | J97: =D112*$D$90*4.8 -> 3676.7935 | K97: =D112*$K$90*4.8 -> 3342.5395 | L97: =D112*$D$90*4.8 -> 3676.7935 | M97: =D112*$M$90*4.8 -> 3509.6665
A98: Office Admin | B98: =B113*$B$90*6 -> 0 | C98: =D113*$C$90*6 -> 0 | D98: =D113*$D$90*6 -> 0 | E98: =D113*$E$90*6 -> 0 | F98: =D113*$F$90*6 -> 0 | G98: =D113*$G$90*6 -> 0 | H98: =D113*$D$90*6 -> 0 | I98: =D113*$I$90*6 -> 0 | J98: =D113*$D$90*6 -> 0 | K98: =D113*$K$90*6 -> 0 | L98: =D113*$D$90*6 -> 0 | M98: =D113*$M$90*6 -> 0
A99: Head of HR | B99: =B114*$B$90*8 -> 0 | C99: =D114*$C$90*8 -> 0 | D99: =D114*$D$90*8 -> 0 | E99: =D114*$E$90*8 -> 0 | F99: =D114*$F$90*8 -> 0 | G99: =D114*$G$90*8 -> 0 | H99: =D114*$D$90*8 -> 0 | I99: =D114*$I$90*8 -> 0 | J99: =D114*$D$90*8 -> 0 | K99: =D114*$K$90*8 -> 0 | L99: =D114*$D$90*8 -> 0 | M99: =D114*$M$90*8 -> 0
A100: NIKODINOVSKI, Isabella (casual) | B100: =($B$115*4)*4 -> 620 | C100: =($D$115*4)*4 -> 620 | D100: =($D$115*4)*4 -> 620 | E100: =($D$115*4)*4 -> 620 | F100: =($D$115*4)*4 -> 620 | G100: =($D$115*4)*4 -> 620 | H100: =($D$115*4)*4 -> 620 | I100: =($D$115*4)*4 -> 620 | J100: =($D$115*4)*4 -> 620 | ... M100: =($D$115*4)*4 -> 620
B101: =SUM(B92:B100) -> 55487.952 | C101: =SUM(C92:C100) -> 48989.058 | D101: =SUM(D92:D100) -> 53825.963 | E101: =SUM(E92:E100) -> 44332.418 | F101: =SUM(F92:F100) -> 40358.562 | G101: =SUM(G92:G100) -> 28436.994 | H101: =SUM(H92:H100) -> 44332.418 | I101: =SUM(I92:I100) -> 40358.562 | ... M101: =SUM(M92:M100) -> 42345.49
A102: Superannuation | B102: =B101*0.12 -> 6658.5542 | C102: =C101*0.12 -> 5878.6869 | D102: =D101*0.12 -> 6459.1156 | E102: =E101*0.12 -> 5319.8902 | F102: =F101*0.12 -> 4843.0275 | G102: =G101*0.12 -> 3412.4392 | H102: =H101*0.12 -> 5319.8902 | I102: =I101*0.12 -> 4843.0275 | ... M102: =M101*0.12 -> 5081.4588
...

Sheet Sheet2
A1: 45839 | B1: Support | C1: Production | D1: Video | E1: Integration | F1: Consulting
A2: Forecast/Actual | B2: Actual
A3: Revenue | B3: {=SUM(IF('ONS Sales Forecast'!BS3:BS60="Actual", VLOOKUP(B2,'ONS Sales Forecast'!BS3:BS60,1,FALSE),'ONS Sales Forecast'!BS3:BS60))} -> 250364.46
A4: Cost of Sales | B4: {=SUM(IF('ONS Sales Forecast'!BS62:BS68="Actual", VLOOKUP(B2,'ONS Sales Forecast'!BS62:BS68,1,FALSE),'ONS Sales Forecast'!BS62:BS68))} -> -129391.68
A5: Gross Profit | B5: =B3-B4 -> 379756.14

Sheet CONS
A1: ACTUAL FY23 | F1: BUDGET | G1: July | H1: August | I1: September | J1: October | K1: November | L1: December | M1: January | N1: February | O1: March | P1: April | Q1: May | R1: June | S1: Total
B2: Integration | C2: Consulting | D2: Total | E2: Revenue | F2: As per Forecast | G2: ='CONS Sales Forecast'!DR67 -> 297416.49 | H2: ='CONS Sales Forecast'!DS67 -> 465645.39 | I2: ='CONS Sales Forecast'!DT67 -> 82321.892 | J2: ='CONS Sales Forecast'!DU67 -> 100061.89 | K2: ='CONS Sales Forecast'!DV67 -> 36337.392 | L2: ='CONS Sales Forecast'!DW67 -> 31337.392 | M2: ='CONS Sales Forecast'!DX67 -> 27340.652 | N2: ='CONS Sales Forecast'!DY67 -> 32340.652 | ... R2: ='CONS Sales Forecast'!EC67 -> 8035.0717 | S2: =SUM(G2:R2) -> 1153553.2 | T2: =S2='CONS Sales Forecast'!EE67 -> TRUE
A3: Contract Support Staff | B3: 0 | C3: 2699 | D3: =B3+C3 -> 2699 | F3: ADDITIONAL - Breakeven | S3: =SUM(G3:R3) -> 0
A4: Subscriptions & Licences - Income | B4: 106533.74 | C4: 3500 | D4: =B4+C4 -> 110033.74 | F4: Total Revenue | G4: =SUM(G2:G3) -> 297416.49 | H4: =SUM(H2:H3) -> 465645.39 | I4: =SUM(I2:I3) -> 82321.892 | J4: =SUM(J2:J3) -> 100061.89 | K4: =SUM(K2:K3) -> 36337.392 | L4: =SUM(L2:L3) -> 31337.392 | M4: =SUM(M2:M3) -> 27340.652 | N4: =SUM(N2:N3) -> 32340.652 | ... S4: =SUM(S2:S3) -> 1153553.2
A5: Freight &Travel - WORKTECH | B5: 710.53 | C5: 0 | D5: =B5+C5 -> 710.53 | F5: Direct Salaries | G5: =-'CONS Fixed Costs'!C29 -> -6437.1562 | H5: =-'CONS Fixed Costs'!D29 -> -5765.453 | I5: =-'CONS Fixed Costs'!E29 -> -7159.0656 | J5: =-'CONS Fixed Costs'!F29 -> -7159.0656 | K5: =-'CONS Fixed Costs'!G29 -> -6508.2414 | L5: =-'CONS Fixed Costs'!H29 -> -6833.6535 | M5: =-'CONS Fixed Costs'!I29 -> -6508.2414 | N5: =-'CONS Fixed Costs'!J29 -> -6508.2414 | ... R5: =-'CONS Fixed Costs'!N29 -> -6833.6535 | S5: =SUM(G5:R5) -> -80213.732
F6: Direct Superannuation | G6: =-'CONS Fixed Costs'!C30 -> -772.45875 | H6: =-'CONS Fixed Costs'!D30 -> -691.85435 | I6: =-'CONS Fixed Costs'!E30 -> -859.08787 | J6: =-'CONS Fixed Costs'!F30 -> -859.08787 | K6: =-'CONS Fixed Costs'!G30 -> -780.98897 | L6: =-'CONS Fixed Costs'!H30 -> -820.03842 | M6: =-'CONS Fixed Costs'!I30 -> -780.98897 | N6: =-'CONS Fixed Costs'!J30 -> -780.98897 | ... R6: =-'CONS Fixed Costs'!N30 -> -820.03842 | S6: =SUM(G6:R6) -> -9625.6478
A7: Production Labour | B7: 375 | C7: 0 | D7: =B7+C7 -> 375 | E7: COGs | F7: INT- Equip/Sub-Contract/Licenses (50% of revenue) | G7: =-G2*0.5 -> -148708.25 | H7: =-H2*0.5 -> -232822.7 | I7: =-I2*0.5 -> -41160.946 | J7: =-J2*0.5 -> -50030.946 | K7: =-K2*0.5 -> -18168.696 | L7: =-L2*0.5 -> -15668.696 | M7: =-M2*0.5 -> -13670.326 | N7: =-N2*0.5 -> -16170.326 | ... R7: =-R2*0.5 -> -4017.5358 | S7: =SUM(G7:R7) -> -576776.6
F8: Aware Super (COS) | G8: -287.5 | H8: =-287.5 -> -287.5 | I8: =-287.5 -> -287.5 | J8: =-287.5 -> -287.5 | K8: =-287.5 -> -287.5 | L8: =-287.5 -> -287.5 | M8: =-287.5 -> -287.5 | N8: =-287.5 -> -287.5 | O8: =-287.5 -> -287.5 | ... R8: =-287.5 -> -287.5 | S8: =SUM(G8:R8) -> -3450
F9: Transport (INT & CONS) | G9: -689.55156 | H9: -39.67052 | I9: -663.51226 | J9: 0 | K9: -1648.9256 | L9: -353.9918 | M9: -16.448 | N9: -333.75048 | O9: -586.92952 | P9: -576.26147 | Q9: -558.41988 | R9: -5960.5702 | S9: =SUM(G9:R9) -> -11428.031
A10: Ad Hoc Service Labour | B10: 11089.8 | C10: 998 | D10: =B10+C10 -> 12087.8 | F10: Total COGs | G10: =+SUM(G5:G9) -> -156894.91 | H10: =+SUM(H5:H9) -> -239607.17 | I10: =+SUM(I5:I9) -> -50130.112 | J10: =+SUM(J5:J9) -> -58336.599 | K10: =+SUM(K5:K9) -> -27394.352 | L10: =+SUM(L5:L9) -> -23963.88 | M10: =+SUM(M5:M9) -> -21263.504 | N10: =+SUM(N5:N9) -> -24080.807 | ... R10: =+SUM(R5:R9) -> -17919.298 | S10: =SUM(G10:R10) -> -681494.01 | T10: =S10='CONS Sales Forecast'!CY75 -> FALSE
A11: Installation Labour | B11: 22594 | C11: 400 | D11: =B11+C11 -> 22994 | E11: Gen Ad | F11: Dues & Subscriptions | G11: =-SUM('CONS Fixed Costs'!D14:D19) -> -339.38833 | H11: =G11 -> -339.38833 | I11: =H11 -> -339.38833 | J11: =I11 -> -339.38833 | K11: =J11 -> -339.38833 | L11: =K11 -> -339.38833 | M11: =L11 -> -339.38833 | N11: =M11 -> -339.38833 | O11: =N11 -> -339.38833 | ... R11: =Q11 -> -339.38833 | S11: =SUM(G11:R11) -> -4072.66
A12: Equipment Sales | B12: 86019.07 | C12: 0 | D12: =B12+C12 -> 86019.07 | E12: Bus Ins | F12: Insurance | G12: =-'CONS Fixed Costs'!D13 -> -407.455 | H12: =G12 -> -407.455 | I12: =H12 -> -407.455 | J12: =I12 -> -407.455 | K12: =J12 -> -407.455 | L12: =K12 -> -407.455 | M12: =L12 -> -407.455 | N12: =M12 -> -407.455 | O12: =N12 -> -407.455 | ... R12: =Q12 -> -407.455 | S12: =SUM(G12:R12) -> -4889.46
A13: Tech Consulting/Project Manage | B13: 32579.72 | C13: 89929 | D13: =B13+C13 -> 122508.72 | E13: OpEx | F13: Rent/Rental Outgoings/Cleaning | G13: =-'CONS Fixed Costs'!$F$9 -> -913.73986 | H13: =-'CONS Fixed Costs'!$F$9 -> -913.73986 | I13: =-'CONS Fixed Costs'!$F$9 -> -913.73986 | J13: =-'CONS Fixed Costs'!$F$9 -> -913.73986 | K13: =-'CONS Fixed Costs'!$F$9 -> -913.73986 | L13: =-'CONS Fixed Costs'!$F$9 -> -913.73986 | M13: =-'CONS Fixed Costs'!$F$9 -> -913.73986 | N13: =-'CONS Fixed Costs'!$F$9 -> -913.73986 | ... R13: =-'CONS Fixed Costs'!$F$9 -> -913.73986 | S13: =SUM(G13:R13) -> -10964.878
A14: Tech Event Management | B14: 0 | C14: 2702.32 | D14: =B14+C14 -> 2702.32 | E14: OpEx | F14: Mobile Phones | G14: =-'CONS Fixed Costs'!C34 -> -70 | H14: =-'CONS Fixed Costs'!D34 -> -70 | I14: =-'CONS Fixed Costs'!E34 -> -70 | J14: =-'CONS Fixed Costs'!F34 -> -70 | K14: =-'CONS Fixed Costs'!G34 -> -70 | L14: =-'CONS Fixed Costs'!H34 -> -70 | M14: =-'CONS Fixed Costs'!I34 -> -70 | N14: =-'CONS Fixed Costs'!J34 -> -70 | ... R14: =-'CONS Fixed Costs'!N34 -> -70 | S14: =SUM(G14:R14) -> -840
D15: =B15+C15 -> 0 | E15: Emp | F15: Discretionary Bonuses | G15: -200 | H15: -200 | I15: -200 | J15: -200 | K15: -200 | L15: -200 | M15: -200 | N15: -200 | O15: -200 | P15: -200 | Q15: -200 | R15: -200 | S15: =SUM(G15:R15) -> -2400
E16: Emp | F16: Indirect Salaries | G16: =-'CONS Fixed Costs'!C31 -> -6437.1562 | H16: =-'CONS Fixed Costs'!D31 -> -5765.453 | I16: =-'CONS Fixed Costs'!E31 -> -7159.0656 | J16: =-'CONS Fixed Costs'!F31 -> -7159.0656 | K16: =-'CONS Fixed Costs'!G31 -> -6508.2414 | L16: =-'CONS Fixed Costs'!H31 -> -6833.6535 | M16: =-'CONS Fixed Costs'!I31 -> -6508.2414 | N16: =-'CONS Fixed Costs'!J31 -> -6508.2414 | ... R16: =-'CONS Fixed Costs'!N31 -> -6833.6535 | S16: =SUM(G16:R16) -> -80213.732
E17: Emp | F17: Indirect Superannuation | G17: =-'CONS Fixed Costs'!C32 -> -772.45875 | H17: =-'CONS Fixed Costs'!D32 -> -691.85435 | I17: =-'CONS Fixed Costs'!E32 -> -859.08787 | J17: =-'CONS Fixed Costs'!F32 -> -859.08787 | K17: =-'CONS Fixed Costs'!G32 -> -780.98897 | L17: =-'CONS Fixed Costs'!H32 -> -820.03842 | M17: =-'CONS Fixed Costs'!I32 -> -780.98897 | N17: =-'CONS Fixed Costs'!J32 -> -780.98897 | ... R17: =-'CONS Fixed Costs'!N32 -> -820.03842 | S17: =SUM(G17:R17) -> -9625.6478
E18: OpEx | F18: Workers Comp | G18: =-((5054.65/65)*1)/12 -> -6.4803205 | H18: =G18 -> -6.4803205 | I18: =H18 -> -6.4803205 | J18: =I18 -> -6.4803205 | K18: =J18 -> -6.4803205 | L18: =K18 -> -6.4803205 | M18: =L18 -> -6.4803205 | N18: =M18 -> -6.4803205 | O18: =N18 -> -6.4803205 | ... R18: =Q18 -> -6.4803205 | S18: =SUM(G18:R18) -> -77.763846
A19: Equipment - Purchase | B19: -81167.06 | C19: 0 | D19: =B19+C19 -> -81167.06 | E19: OpEx | F19: Miscellaneous Expenses | G19: -250 | H19: -250 | I19: -250 | J19: -250 | K19: -250 | L19: -250 | M19: -250 | N19: -250 | O19: -250 | P19: -250 | Q19: -250 | R19: -250 | S19: =SUM(G19:R19) -> -3000
A20: Sub-Contract Labour - WORKTECH | B20: -25305.04 | C20: -17540 | D20: =B20+C20 -> -42845.04 | F20: Total OpEx | G20: =SUM(G11:G19) -> -9396.6785 | H20: =SUM(H11:H19) -> -8644.3708 | I20: =SUM(I11:I19) -> -10205.217 | J20: =SUM(J11:J19) -> -10205.217 | K20: =SUM(K11:K19) -> -9476.2939 | L20: =SUM(L11:L19) -> -9840.7554 | M20: =SUM(M11:M19) -> -9476.2939 | N20: =SUM(N11:N19) -> -9476.2939 | ... R20: =SUM(R11:R19) -> -9840.7554 | S20: =SUM(G20:R20) -> -116084.14
A21: Sub-Contract Labour - CONS | B21: -4495 | C21: 0 | D21: =B21+C21 -> -4495 | F21: Gross Profit | G21: =+G4+G10 -> 140521.58 | H21: =+H4+H10 -> 226038.22 | I21: =+I4+I10 -> 32191.78 | J21: =+J4+J10 -> 41725.292 | K21: =+K4+K10 -> 8943.0398 | L21: =+L4+L10 -> 7373.5121 | M21: =+M4+M10 -> 6077.1474 | N21: =+N4+N10 -> 8259.845 | ... R21: =+R4+R10 -> -9884.2262 | S21: =SUM(G21:R21) -> 472059.19
A22: Service - hires | B22: -150 | C22: 0 | D22: =B22+C22 -> -150 | F22: Gross Profit Margin | G22: =+G21/G4 -> 0.47247407 | H22: =+H21/H4 -> 0.48542995 | I22: =+I21/I4 -> 0.39104762 | J22: =+J21/J4 -> 0.41699484 | K22: =+K21/K4 -> 0.24611122 | L22: =+L21/L4 -> 0.23529438 | M22: =+M21/M4 -> 0.22227515 | N22: =+N21/N4 -> 0.25540132 | ... S22: =+S21/S4 -> 0.40922186
A23: Damage Waiver | B23: -43.41 | C23: 0 | D23: =B23+C23 -> -43.41 | F23: Net Profit | G23: =G21-G33 -> 122017.21 | H23: =H21-H33 -> 201185.13 | I23: =I21-I33 -> 5777.8415 | J23: =J21-J33 -> 15311.354 | K23: =K21-K33 -> -16741.976 | L23: =L21-L33 -> -18675.965 | M23: =M21-M33 -> -19607.868 | N23: =N21-N33 -> -17425.171 | ... R23: =R21-R33 -> -35933.703 | S23: =SUM(G23:R23) -> 168571.41
A24: Direct Salaries - WORKTECH | B24: -5451.8 | C24: -2974.51 | D24: =B24+C24 -> -8426.31 | F24: NetProfit Margin | G24: =+G23/G4 -> 0.41025703 | H24: =+H23/H4 -> 0.43205652 | I24: =+I23/I4 -> 0.070185966 | J24: =+J23/J4 -> 0.15301883 | K24: =K23/K2 -> -0.46073686 | L24: =+L23/L4 -> -0.59596425 | M24: =+M23/M4 -> -0.71716901 | N24: =+N23/N4 -> -0.53880085 | O24: =+O23/O4 -> -0.59170718 | P24: =+P23/P4 -> -0.54629949 | Q24: =+Q23/Q4 -> -3.799786 | R24: =+R23/R4 -> -4.4721074 | S24: =+S23/S4 -> 0.14613233
A25: Direct Salaries - CONS | B25: -728.11 | C25: -31205.26 | D25: =B25+C25 -> -31933.37
A26: Direct Wages - CONS | B26: 0 | C26: -115.84 | D26: =B26+C26 -> -115.84 | F26: Total Direct Costs | G26: =+G7+G20 -> -158104.92 | H26: =+H7+H20 -> -241467.07 | I26: =+I7+I20 -> -51366.163 | J26: =+J7+J20 -> -60236.163 | K26: =+K7+K20 -> -27644.99 | L26: =+L7+L20 -> -25509.451 | M26: =+M7+M20 -> -23146.62 | N26: =+N7+N20 -> -25646.62 | ... S26: =+S7+S20 -> -692860.74
A27: Direct Superannuation-WORKTECH | B27: -572.46 | C27: -312.34 | D27: =B27+C27 -> -884.8
A28: Direct Superannuation - CONS | B28: -76.46 | C28: -3244.7 | D28: =B28+C28 -> -3321.16 | F28: Business Insurances | G28: 1569.0256 | H28: ='FY27 Budget - detailed'!$C$40-H12 -> 1569.0256 | I28: ='FY27 Budget - detailed'!$C$40-I12 -> 1569.0256 | J28: ='FY27 Budget - detailed'!$C$40-J12 -> 1569.0256 | K28: ='FY27 Budget - detailed'!$C$40-K12 -> 1569.0256 | L28: ='FY27 Budget - detailed'!$C$40-L12 -> 1569.0256 | M28: ='FY27 Budget - detailed'!$C$40-M12 -> 1569.0256 | N28: ='FY27 Budget - detailed'!$C$40-N12 -> 1569.0256 | O28: ='FY27 Budget - detailed'!$C$40-O12 -> 1569.0256 | ... R28: ='FY27 Budget - detailed'!$C$40-R12 -> 1569.0256
A29: Direct Travel - PRD | B29: -51.27 | C29: 0 | D29: =B29+C29 -> -51.27 | F29: Employment Expenses | G29: 8636.7835 | H29: ='FY27 Budget - detailed'!$C$68-SUM(H15:H18) -> 7838.6752 | I29: ='FY27 Budget - detailed'!$C$68-SUM(I15:I18) -> 9399.5213 | J29: ='FY27 Budget - detailed'!$C$68-SUM(J15:J18) -> 9399.5213 | K29: ='FY27 Budget - detailed'!$C$68-SUM(K15:K18) -> 8670.5983 | L29: ='FY27 Budget - detailed'!$C$68-SUM(L15:L18) -> 9035.0598 | M29: ='FY27 Budget - detailed'!$C$68-SUM(M15:M18) -> 8670.5983 | N29: ='FY27 Budget - detailed'!$C$68-SUM(N15:N18) -> 8670.5983 | O29: ='FY27 Budget - detailed'!$C$68-SUM(O15:O18) -> 9399.5213 | ... R29: ='FY27 Budget - detailed'!$C$68-SUM(R15:R18) -> 9035.0598
A30: Direct Travel - CONS | B30: 0 | C30: -26.83 | D30: =B30+C30 -> -26.83 | F30: General & Administrative Exp | G30: 5071.8715 | H30: ='FY27 Budget - detailed'!$C$37-SUM(H11) -> 5154.3715 | I30: ='FY27 Budget - detailed'!$C$37-SUM(I11) -> 5154.3715 | J30: ='FY27 Budget - detailed'!$C$37-SUM(J11) -> 5154.3715 | K30: ='FY27 Budget - detailed'!$C$37-SUM(K11) -> 5154.3715 | L30: ='FY27 Budget - detailed'!$C$37-SUM(L11) -> 5154.3715 | M30: ='FY27 Budget - detailed'!$C$37-SUM(M11) -> 5154.3715 | N30: ='FY27 Budget - detailed'!$C$37-SUM(N11) -> 5154.3715 | O30: ='FY27 Budget - detailed'!$C$37-SUM(O11) -> 5154.3715 | ... R30: ='FY27 Budget - detailed'!$C$37-SUM(R11) -> 5154.3715
A31: Direct Freight - ONS | B31: -144 | C31: 0 | D31: =B31+C31 -> -144 | F31: Operating Expenses | G31: 3226.6919 | H31: =('FY27 Budget - detailed'!$C$42+'FY27 Budget - detailed'!$C$56)-SUM(H13:H14,H19) -> 10291.02 | I31: =('FY27 Budget - detailed'!$C$42+'FY27 Budget - detailed'!$C$56)-SUM(I13:I14,I19) -> 10291.02 | J31: =('FY27 Budget - detailed'!$C$42+'FY27 Budget - detailed'!$C$56)-SUM(J13:J14,J19) -> 10291.02 | K31: =('FY27 Budget - detailed'!$C$42+'FY27 Budget - detailed'!$C$56)-SUM(K13:K14,K19) -> 10291.02 | L31: =('FY27 Budget - detailed'!$C$42+'FY27 Budget - detailed'!$C$56)-SUM(L13:L14,L19) -> 10291.02 | M31: =('FY27 Budget - detailed'!$C$42+'FY27 Budget - detailed'!$C$56)-SUM(M13:M14,M19) -> 10291.02 | N31: =('FY27 Budget - detailed'!$C$42+'FY27 Budget - detailed'!$C$56)-SUM(N13:N14,N19) -> 10291.02 | O31: =('FY27 Budget - detailed'!$C$42+'FY27 Budget - detailed'!$C$56)-SUM(O13:O14,O19) -> 10291.02 | ... R31: =('FY27 Budget - detailed'!$C$42+'FY27 Budget - detailed'!$C$56)-SUM(R13:R14,R19) -> 10291.02
A32: Direct Freight - WORKTECH | B32: -2203.14 | C32: 0 | D32: =B32+C32 -> -2203.14
A33: Total COGS | B33: =SUM(B19:B32) -> -120387.75 | C33: =SUM(C19:C32) -> -55419.48 | D33: =SUM(D19:D32) -> -175807.23 | G33: 18504.372 | H33: =SUM(H28:H32) -> 24853.093 | I33: =SUM(I28:I32) -> 26413.939 | J33: =SUM(J28:J32) -> 26413.939 | K33: =SUM(K28:K32) -> 25685.016 | L33: =SUM(L28:L32) -> 26049.477 | M33: =SUM(M28:M32) -> 25685.016 | N33: =SUM(N28:N32) -> 25685.016 | O33: =SUM(O28:O32) -> 26413.939 | ... R33: =SUM(R28:R32) -> 26049.477
A34: Bank Charges | B34: -2.61 | C34: 0 | D34: =B34+C34 -> -2.61
A35: Dues & Subscriptions | B35: -6468.86 | C35: -89.69 | D35: =B35+C35 -> -6558.55
A36: Freight Paid | B36: -9.1 | C36: -13.57 | D36: =B36+C36 -> -22.67
A37: Credit Card Fees Paid | B37: -2.48 | C37: -11.84 | D37: =B37+C37 -> -14.32 | F37: Notes:
A38: Taxis/Parking | B38: -20.91 | C38: -287.23 | D38: =B38+C38 -> -308.14 | F38: Do we keep 15% for COGS
A39: Other Insurance | B39: -4324.27 | C39: 0 | D39: =B39+C39 -> -4324.27 | F39: Do we keep 20% for overhead calc or perhaps 5% based on 'staff' category in opex split
A40: Postage | B40: 0 | C40: -14.08 | D40: =B40+C40 -> -14.08
A41: Rent | B41: -18258.7 | C41: -44442.41 | D41: =B41+C41 -> -62701.11
A42: Rental Outgoings | B42: -3221.87 | C42: -7280.51 | D42: =B42+C42 -> -10502.38 | G42: =G33-G20 -> 27901.051 | H42: =H33-H20 -> 33497.463 | I42: =I33-I20 -> 36619.156 | J42: =J33-J20 -> 36619.156 | K42: =K33-K20 -> 35161.309 | L42: =L33-L20 -> 35890.233 | M42: =M33-M20 -> 35161.309 | N42: =N33-N20 -> 35161.309 | ... S42: =S33-S20 -> 116084.14
A43: Mobile Phones | B43: -631.69 | C43: -631.68 | D43: =B43+C43 -> -1263.37 | G43: =G21-G42 -> 112620.53 | H43: =H21-H42 -> 192540.75 | I43: =I21-I42 -> -4427.3754 | J43: =J21-J42 -> 5106.1368 | K43: =K21-K42 -> -26218.27 | L43: =L21-L42 -> -28516.72 | M43: =M21-M42 -> -29084.162 | N43: =N21-N42 -> -26901.465 | ... S43: =S21-S42 -> 355975.05
A44: Travel & Per Diems | B44: -73.37 | C44: -39.72 | D44: =B44+C44 -> -113.09
A45: Client Entertainment | B45: -47.62 | C45: -2340.6 | D45: =B45+C45 -> -2388.22
A46: Payroll Tax | B46: -1724.37 | C46: -7997.88 | D46: =B46+C46 -> -9722.25
A47: Staff Amenities | B47: 0 | C47: -27.97 | D47: =B47+C47 -> -27.97
A48: Staff Entertainment | B48: 0 | C48: -376.07 | D48: =B48+C48 -> -376.07
A49: Superannuation | B49: -5726.58 | C49: -22921.38 | D49: =B49+C49 -> -28647.96
A50: Indirect Salaries - WORKTECH | B50: -24830.24 | C50: 0 | D50: =B50+C50 -> -24830.24
A51: Indirect Salaries - CONS | B51: 0 | C51: -207234.94 | D51: =B51+C51 -> -207234.94
A52: Workers' Compensation | B52: -42.84 | C52: -42.84 | D52: =B52+C52 -> -85.68
A53: Training Material & Courses | B53: -95 | C53: -1955.66 | D53: =B53+C53 -> -2050.66
A54: Recruitment | B54: 0 | C54: -365 | D54: =B54+C54 -> -365
A55: Indirect Wages - CONS | B55: 0 | C55: -570.13 | D55: =B55+C55 -> -570.13
... A57: Leave expense (Long Service) | B57: -1120.31 | C57: 0 | D57: =B57+C57 -> -1120.31
D58: =B58+C58 -> 0
D59: =B59+C59 -> 0
D60: =B60+C60 -> 0
D61: =B61+C61 -> 0
D62: =B62+C62 -> 0
D63: =B63+C63 -> 0
A64: Total OpEx | B64: =SUM(B34:B63) -> -64632.11 | C64: =SUM(C34:C63) -> -294993.06 | D64: =SUM(D34:D63) -> -359625.17
A65: Total Gross Profit | B65: =+#REF!+B33+B64 -> #REF! | C65: =+#REF!+C33+C64 -> #REF! | D65: =+#REF!+D33+D64 -> #REF!

Sheet CONS Fixed Costs
G1: Fixed Expenses per Employee
A2: Old rate | B2: Full-time Staff | D2: New hourly rate 4% | E2: Salary at 27 pay runs | F2: Super at 12% | G2: Total - Annual (Annual + Super) | H2: LSL Expense
A3: 48.076923 | B3: Sub-contracted lead consultants | C3: 0.5 | D3: =A3*1.03 -> 49.519231 | E3: =D3*8*5*52 -> 103000 | F3: =+E3*0.12 -> 12360 | G3: =+E3+F3 -> 115360
A4: 42.92582 | B4: Daniel SOBKOWSKI | C4: 0.5 | D4: =A4*1.03 -> 44.213595 | E4: =D4*8*5*52 -> 91964.277 | F4: =+E4*0.12 -> 11035.713 | G4: =+E4+F4 -> 102999.99 | H4: 114.49
E6: =SUM(E3:E4) -> 194964.28 | F6: =SUM(F3:F4) -> 23395.713 | G6: =SUM(G3:G4) -> 218359.99
B8: RENT - Monthly | D8: INT | E8: CONS
B9: Rent/Rental Outgoings (+3.75% increase per year) | D9: ='Rental Breakdown'!U22 -> 444.46684 | E9: ='Rental Breakdown'!U23 -> 444.46684 | F9: =+D9+E9+D10+E10 -> 913.73986
B10: Cleaning | D10: ='Rental Breakdown'!S22 -> 12.403089 | E10: ='Rental Breakdown'!S23 -> 12.403089
B12: Dues/Subscriptions | D12: Monthly Fees | E12: Department
B13: Brookvale (Mecon) | D13: ='CTS Overheads'!U40/12 -> 407.455 | E13: INT | F13: Contract Insurances | G13: 5035.02
B14: ASt Store Advanced Spatial technologies | D14: 0 | E14: INT
B15: Zoho | D15: =1452/12 -> 121 | E15: CONS
B16: Qwillr | D16: =478.51/12 -> 39.875833 | E16: INT
B17: Qwillr | D17: =478.51/12 -> 39.875833 | E17: CONS
B18: Smartsheets | D18: =283.64/12 -> 23.636667 | E18: CONS
B19: AutoCad | D19: =1380/12 -> 115 | E19: INT
B20: Total | D20: =SUM(D13:D19) -> 746.84333
B23: Working Days | C23: ='CTS Overheads'!B90 -> 23 | D23: ='CTS Overheads'!C90 -> 20 | E23: ='CTS Overheads'!D90 -> 22 | F23: ='CTS Overheads'!E90 -> 22 | G23: ='CTS Overheads'!F90 -> 20 | H23: 21 | I23: ='CTS Overheads'!H90 -> 20 | J23: ='CTS Overheads'!I90 -> 20 | K23: ='CTS Overheads'!J90 -> 22 | L23: ='CTS Overheads'!K90 -> 20 | M23: ='CTS Overheads'!L90 -> 21 | N23: ='CTS Overheads'!M90 -> 21
C24: Jul | D24: Aug | E24: Sep | F24: Oct | G24: Nov | H24: Dec | I24: Jan | J24: Feb | K24: Mar | L24: Apr | M24: May | N24: Jun
B25: =B3 -> Sub-contracted lead consultants | C25: =C23*$A$3*4.5 -> 4975.9615 | D25: =D23*$D$3*4.5 -> 4456.7308 | E25: =E23*$D$3*6 -> 6536.5385 | F25: =F23*$D$3*6 -> 6536.5385 | G25: =G23*$D$3*6 -> 5942.3077 | H25: =H23*$D$3*6 -> 6239.4231 | I25: =I23*$D$3*6 -> 5942.3077 | J25: =J23*$D$3*6 -> 5942.3077 | K25: =K23*$D$3*6 -> 6536.5385 | L25: =L23*$D$3*6 -> 5942.3077 | ... N25: =N23*$D$3*6 -> 6239.4231
B26: =B4 -> Daniel SOBKOWSKI | C26: =C23*$A$4*8 -> 7898.3509 | D26: =D23*$D$4*8 -> 7074.1751 | E26: =E23*$D$4*8 -> 7781.5926 | F26: =F23*$D$4*8 -> 7781.5926 | G26: =G23*$D$4*8 -> 7074.1751 | H26: =H23*$D$4*8 -> 7427.8839 | I26: =I23*$D$4*8 -> 7074.1751 | J26: =J23*$D$4*8 -> 7074.1751 | K26: =K23*$D$4*8 -> 7781.5926 | ... N26: =N23*$D$4*8 -> 7427.8839
B27: =B5 -> 0 | H27: =4*$A$5*8 -> 0 | I27: =4*$A$5*8 -> 0 | J27: =4*$A$5*8 -> 0 | K27: =4*$A$5*8 -> 0 | L27: =4*$A$5*8 -> 0 | M27: =4*$A$5*8 -> 0 | N27: =4*$A$5*8 -> 0
C28: =SUM(C25:C27) -> 12874.312 | D28: =SUM(D25:D27) -> 11530.906 | E28: =SUM(E25:E27) -> 14318.131 | F28: =SUM(F25:F27) -> 14318.131 | G28: =SUM(G25:G27) -> 13016.483 | H28: =SUM(H25:H27) -> 13667.307 | I28: =SUM(I25:I27) -> 13016.483 | J28: =SUM(J25:J27) -> 13016.483 | ... N28: =SUM(N25:N27) -> 13667.307
B29: Direct Salaries | C29: =C28*0.5 -> 6437.1562 | D29: =D28*0.5 -> 5765.453 | E29: =E28*0.5 -> 7159.0656 | F29: =F28*0.5 -> 7159.0656 | G29: =G28*0.5 -> 6508.2414 | H29: =H28*0.5 -> 6833.6535 | I29: =I28*0.5 -> 6508.2414 | J29: =J28*0.5 -> 6508.2414 | ... N29: =N28*0.5 -> 6833.6535
B30: Direct Superannuation | C30: =C29*0.12 -> 772.45875 | D30: =D29*0.12 -> 691.85435 | E30: =E29*0.12 -> 859.08787 | F30: =F29*0.12 -> 859.08787 | G30: =G29*0.12 -> 780.98897 | H30: =H29*0.12 -> 820.03842 | I30: =I29*0.12 -> 780.98897 | J30: =J29*0.12 -> 780.98897 | ... N30: =N29*0.12 -> 820.03842
B31: Indirect Salaries | C31: =C28*0.5 -> 6437.1562 | D31: =D28*0.5 -> 5765.453 | E31: =E28*0.5 -> 7159.0656 | F31: =F28*0.5 -> 7159.0656 | G31: =G28*0.5 -> 6508.2414 | H31: =H28*0.5 -> 6833.6535 | I31: =I28*0.5 -> 6508.2414 | J31: =J28*0.5 -> 6508.2414 | ... N31: =N28*0.5 -> 6833.6535
B32: Indirect Superannuation | C32: =C31*0.12 -> 772.45875 | D32: =D31*0.12 -> 691.85435 | E32: =E31*0.12 -> 859.08787 | F32: =F31*0.12 -> 859.08787 | G32: =G31*0.12 -> 780.98897 | H32: =H31*0.12 -> 820.03842 | I32: =I31*0.12 -> 780.98897 | J32: =J31*0.12 -> 780.98897 | ... N32: =N31*0.12 -> 820.03842
B33: Ptax | C33: =C28*0.03 -> 386.22937 | D33: =D28*0.03 -> 345.92718 | E33: =E28*0.03 -> 429.54393 | F33: =F28*0.03 -> 429.54393 | G33: =G28*0.03 -> 390.49448 | H33: =H28*0.03 -> 410.01921 | I33: =I28*0.03 -> 390.49448 | J33: =J28*0.03 -> 390.49448 | ... N33: =N28*0.03 -> 410.01921
B34: Mobile Phones | C34: =35*2 -> 70 | D34: =35*2 -> 70 | E34: =35*2 -> 70 | F34: =35*2 -> 70 | G34: =35*2 -> 70 | H34: =35*2 -> 70 | I34: =35*2 -> 70 | J34: =35*2 -> 70 | ... N34: =35*2 -> 70
B35: AL Expense | C35: 286.17213 | D35: =C35 -> 286.17213 | E35: =D35 -> 286.17213 | F35: =E35 -> 286.17213 | G35: =F35 -> 286.17213 | H35: =G35 -> 286.17213 | I35: =H35 -> 286.17213 | J35: =I35 -> 286.17213 | K35: =J35 -> 286.17213 | ... N35: =M35 -> 286.17213
B36: LSL Expense | C36: =$H$4 -> 114.49 | D36: =$H$4 -> 114.49 | E36: =$H$4 -> 114.49 | F36: =$H$4 -> 114.49 | G36: =$H$4 -> 114.49 | H36: =$H$4 -> 114.49 | I36: =$H$4 -> 114.49 | J36: =$H$4 -> 114.49 | ... N36: =$H$4 -> 114.49
B40: Add to main detailed tab
C42: AL Expense Calculation Logic
C43: 20 days AL allowed / 250 working days in a year
C44: =20/250 -> 0.08
B47: Working Days | C47: 23 | D47: 20 | E47: 22 | F47: 22 | G47: 20 | H47: 11 | I47: 20 | J47: 20 | K47: 22 | L47: 20 | M47: 21 | N47: 21
B48: Salary | C48: 7969.6306 | D48: 7276.6193 | E48: 8004.2812 | F48: 8004.2812 | G48: 7276.6193 | H48: 4002.1406 | I48: 7276.6193 | J48: 7276.6193 | K48: 8004.2812 | L48: 7276.6193 | M48: 7640.4502 | N48: 7640.4502
B49: AL Expense | C49: =(C48*0.08) -> 637.57045 | D49: =(D48*0.08) -> 582.12954 | E49: =(E48*0.08) -> 640.3425 | F49: =(F48*0.08) -> 640.3425 | G49: =(G48*0.08) -> 582.12954 | H49: =(H48*0.08) -> 320.17125 | I49: =(I48*0.08) -> 582.12954 | J49: =(J48*0.08) -> 582.12954 | ... N49: =(N48*0.08) -> 611.23602

Sheet CONS Sales Forecast
CJ1: 46054 | CL1: < Manually update to highlight current month | DO1: 46235 | DQ1: < Manually update to highlight current month
D2: 45108 | G2: 45139 | J2: 45170 | M2: 45200 | P2: 45231 | S2: 45261 | V2: 45292 | Y2: 45323 | AB2: 45352 | AE2: 45383 | AH2: 45413 | AK2: 45444 | AT2: FY25 | AX2: 45474 | BA2: 45505 | BD2: 45536 | BG2: 45566 | BJ2: 45597 | BM2: 45627 | BP2: 45658 | BS2: 45689 | BV2: 45717 | BY2: 45748 | CB2: 45778 | CE2: 45809 | CJ2: Revenue | CM2: 45839 | CN2: 45870 | CO2: 45901 | CP2: 45931 | CQ2: 45962 | CR2: 45992 | CS2: 46023 | CT2: 46054 | CU2: 46082 | CV2: 46113 | CW2: 46143 | CX2: 46174 | CY2: FY26 CONS | DA2: 45839 | DB2: 45870 | DC2: 45901 | DD2: 45931 | DE2: 45962 | DF2: 45992 | DG2: 46023 | DH2: 46054 | DI2: 46082 | DJ2: 46113 | DK2: 46143 | DL2: 46174 | DM2: FY26 CONS | DO2: Revenue | DR2: 46204 | DS2: 46235 | DT2: 46266 | DU2: 46296 | DV2: 46327 | DW2: 46357 | DX2: 46388 | DY2: 46419 | DZ2: 46447 | EA2: 46478 | EB2: 46508 | EC2: 46539 | ED2: Average Weighting (Approx) | EE2: FY27 CONS | EG2: =DR2 -> 46204 | EH2: =DS2 -> 46235 | EI2: =DT2 -> 46266 | EJ2: =DU2 -> 46296 | EK2: =DV2 -> 46327 | EL2: =DW2 -> 46357 | EM2: =DX2 -> 46388 | EN2: =DY2 -> 46419 | ... ER2: =EC2 -> 46539 | ES2: FY27 CONS
A3: Department | B3: Client / Account | C3: Job Description | D3: Forecast | E3: Actual | F3: Variance | G3: Forecast | H3: Actual | I3: Variance | J3: Forecast | K3: Actual | L3: Variance | M3: Forecast | N3: Actual | O3: Variance | P3: Forecast | Q3: Actual | R3: Variance | S3: Forecast | T3: Actual | U3: Variance | V3: Forecast | W3: Actual | X3: Variance | Y3: Forecast | Z3: Actual | AA3: Variance | AB3: Forecast | AC3: Actual | AD3: Variance | AE3: Forecast | AF3: Actual | AG3: Variance | AH3: Forecast | AI3: Actual | AJ3: Variance | AK3: Forecast | AL3: Actual | AM3: Variance | AN3: Jul-Dec 2023 Actual $ Total | AO3: Jan-Jun 2024 Actual $ Total | AP3: Running Total FY2024 | AQ3: Forecasted Total FY2024 | AR3: Variance | AT3: Department | AU3: Client / Account | AV3: Client / Account | AW3: Project / ID | AX3: Forecast | AY3: Actual | AZ3: Variance | BA3: Forecast | BB3: Actual | BC3: Variance | BD3: Forecast | BE3: Actual | BF3: Variance | BG3: Forecast | BH3: Actual | BI3: Variance | BJ3: Forecast | BK3: Actual | BL3: Variance | BM3: Forecast | BN3: Actual | BO3: Variance | BP3: Forecast | BQ3: Actual | BR3: Variance | BS3: Forecast | BT3: Actual | BU3: Variance | BV3: Forecast | BW3: Actual | BX3: Variance | BY3: Forecast | BZ3: Actual | CA3: Variance | CB3: Forecast | CC3: Actual | CD3: Variance | CE3: Forecast | CF3: Actual | CG3: Variance | CH3: TOTAL | CJ3: Industry | CK3: Department | CL3: Client/Job Name | CM3: Budget | CN3: Budget | CO3: Budget | CP3: Budget | CQ3: Budget | CR3: Budget | CS3: Budget | CT3: Budget | CU3: Budget | CV3: Budget | CW3: Budget | CX3: Budget | CY3: Budget | DA3: Actual | DB3: Actual | DC3: Actual | DD3: Actual | DE3: Actual | DF3: Actual | DG3: Actual | DH3: Actual | DI3: Actual | DJ3: Actual | DK3: Forecast | DL3: Forecast | DM3: Forecast | DN3: < Toggle between Forecast vs Actual | DO3: Industry | DP3: Department | DQ3: Client/Job Name | DR3: Budget | DS3: Budget | DT3: Budget | DU3: Budget | DV3: Budget | DW3: Budget | DX3: Budget | DY3: Budget | DZ3: Budget | EA3: Budget | EB3: Budget | EC3: Budget | ED3: Budget | EE3: Budget | EG3: Actual | EH3: Forecast | EI3: Forecast | EJ3: Forecast | EK3: Forecast | EL3: Forecast | EM3: Forecast | EN3: Forecast | EO3: Forecast | EP3: Forecast | EQ3: Forecast | ER3: Forecast | ES3: Forecast
A4: CONS | B4: Beetroot Music | C4: The Art Wall Bar - LED Video Wall Design (AKA) | D4: 4000 | X4: =+W4-V4 -> 0 | AA4: =+Z4-Y4 -> 0 | AD4: =+AC4-AB4 -> 0 | AE4: 3000 | AG4: =+AF4-AE4 -> -3000 | AJ4: =+AI4-AH4 -> 0 | AM4: =+AL4-AK4 -> 0 | AN4: =SUMIF($D$3:$U$3,"Actual",$D4:$U4) -> 0 | AO4: =SUMIF($V$3:$AM$3,"Actual",$V4:$AM4) -> 0 | AP4: =SUMIF($D$3:$AM$3,"Actual",$D4:$AM4) -> 0 | AQ4: =SUMIF($D$3:$AM$3,"Forecast",$D4:$AM4) -> 7000 | AR4: =AP4-AQ4 -> -7000 | CI4: CODE | CY4: =SUM(CM4:CX4) -> 0 | DA4: =CM4 -> 0 | DB4: =CN4 -> 0 | DC4: =CO4 -> 0 | DD4: =CP4 -> 0 | DE4: =CQ4 -> 0 | DF4: =CR4 -> 0 | DG4: 0 | DH4: 0 | DI4: 0 | DJ4: 0 | DK4: 0 | DL4: 0 | DM4: =SUM(DA4:DL4) -> 0 | DO4: Energy, Utilities, Infrastructure | DP4: INT | DQ4: APA (Sydney, Melbourne, Adelaide, Kidman) | DR4: =(16288+16288+7417+996.74)/12 -> 3415.8117 | DS4: =DR4 -> 3415.8117 | DT4: =DS4 -> 3415.8117 | DU4: =DT4 -> 3415.8117 | DV4: =DU4 -> 3415.8117 | DW4: =DV4 -> 3415.8117 | DX4: =DW4-996.74 -> 2419.0717 | DY4: =DX4 -> 2419.0717 | DZ4: =DY4 -> 2419.0717 | EA4: =DZ4 -> 2419.0717 | EB4: =EA4 -> 2419.0717 | EC4: =EB4 -> 2419.0717 | ED4: 1 | EE4: =SUM(DR4:EC4) -> 35009.3 | EG4: 5983.63 | EH4: =DS4 -> 3415.8117 | EI4: =DT4 -> 3415.8117 | EJ4: =DU4 -> 3415.8117 | EK4: =DV4 -> 3415.8117 | EL4: =DW4 -> 3415.8117 | EM4: 0 | EN4: 0 | EO4: 0 | EP4: 0 | EQ4: 0 | ER4: 0 | ES4: =SUM(EG4:ER4) -> 23062.688
A5: CONS | B5: Blacktown Council | C5: Showground Memorial Stage | F5: =+E5-D5 -> 0 | G5: 2000 | I5: =+H5-G5 -> -2000 | J5: 2000 | L5: =+K5-J5 -> -2000 | O5: =+N5-M5 -> 0 | R5: =+Q5-P5 -> 0 | U5: =+T5-S5 -> 0 | X5: =+W5-V5 -> 0 | AA5: =+Z5-Y5 -> 0 | AD5: =+AC5-AB5 -> 0 | AG5: =+AF5-AE5 -> 0 | AH5: 4000 | AJ5: =+AI5-AH5 -> -4000 | AM5: =+AL5-AK5 -> 0 | AN5: =SUMIF($D$3:$U$3,"Actual",$D5:$U5) -> 0 | AO5: =SUMIF($V$3:$AM$3,"Actual",$V5:$AM5) -> 0 | AP5: =SUMIF($D$3:$AM$3,"Actual",$D5:$AM5) -> 0 | AQ5: =SUMIF($D$3:$AM$3,"Forecast",$D5:$AM5) -> 8000 | AR5: =AP5-AQ5 -> -8000 | AV5: Blacktown Council | AX5: 0 | BA5: 0 | BD5: 0 | BG5: 0 | BJ5: 0 | BM5: 0 | BP5: 0 | BS5: 0 | BV5: 0 | BY5: 0 | CB5: 0 | CE5: 0 | CH5: =SUM(AX5:CE5) -> 0 | CI5: Likely/Confirmed | CJ5: Other Sectors (Schools, Hospitals, etc) | CK5: INT | CL5: APA | CN5: 20000 | CT5: 10000 | CX5: 10000 | CY5: =SUM(CM5:CX5) -> 40000 | DA5: =939.14+276+276+919.15+483.88+1035.15+1035.15 -> 4964.47 | DB5: =939.14+276+276+919.15+483.88+1035.15+1035.15+824.26 -> 5788.73 | DC5: =939.14+276+919.15+483.88+1035.15+1035.15+308.16 -> 4996.63 | DD5: 4996.63 | DE5: 4996.63 | DF5: =937.5+4996.63 -> 5934.13 | DG5: =3718.86+5090.55 -> 8809.41 | DH5: 5090.55 | DI5: 0 | DJ5: 0 | DK5: 0 | DL5: 2000 | DM5: =SUM(DA5:DL5) -> 47577.18 | DO5: Finance | DP5: CONS | DQ5: ASX | DR5: 0 | DS5: 0 | DT5: 0 | DU5: 0 | DV5: 0 | DW5: 0 | DX5: 0 | DY5: 0 | DZ5: 0 | EA5: 0 | EB5: 0 | EC5: 0 | ED5: 0.1 | EE5: =SUM(DR5:EC5) -> 0 | EG5: =DR5 -> 0 | EH5: =DS5 -> 0 | EI5: =DT5 -> 0 | EJ5: =DU5 -> 0 | EK5: =DV5 -> 0 | EL5: =DW5 -> 0 | EM5: =DX5 -> 0 | EN5: =DY5 -> 0 | ... ER5: =EC5 -> 0 | ES5: =SUM(EG5:ER5) -> 0
A6: CONS | B6: DAWE | C6: Bunker Theatrette | F6: =+E6-D6 -> 0 | G6: 3000 | I6: =+H6-G6 -> -3000 | L6: =+K6-J6 -> 0 | O6: =+N6-M6 -> 0 | R6: =+Q6-P6 -> 0 | S6: 5000 | U6: =+T6-S6 -> -5000 | X6: =+W6-V6 -> 0 | AA6: =+Z6-Y6 -> 0 | AD6: =+AC6-AB6 -> 0 | AG6: =+AF6-AE6 -> 0 | AJ6: =+AI6-AH6 -> 0 | AK6: 5000 | AM6: =+AL6-AK6 -> -5000 | AN6: =SUMIF($D$3:$U$3,"Actual",$D6:$U6) -> 0 | AO6: =SUMIF($V$3:$AM$3,"Actual",$V6:$AM6) -> 0 | AP6: =SUMIF($D$3:$AM$3,"Actual",$D6:$AM6) -> 0 | AQ6: =SUMIF($D$3:$AM$3,"Forecast",$D6:$AM6) -> 13000 | AR6: =AP6-AQ6 -> -13000 | AV6: DAWE | AZ6: x12 | CH6: =SUM(AX6:CE6) -> 0 | CI6: Tentative | CK6: CONS | CL6: Artefact | CM6: 500 | CY6: =SUM(CM6:CX6) -> 500 | DA6: 0 | DB6: =CN6 -> 0 | DC6: =CO6 -> 0 | DD6: =CP6 -> 0 | DE6: 0 | DF6: =CR6 -> 0 | DG6: 0 | DH6: 0 | DI6: 0 | DJ6: 0 | DK6: 0 | DL6: 0 | DM6: =SUM(DA6:DL6) -> 0 | DO6: Government | DP6: CONS | DQ6: Australian Museum | DR6: 0 | DS6: 0 | DT6: 0 | DU6: 0 | DV6: 0 | DW6: 0 | DX6: 0 | DY6: 0 | DZ6: 0 | EA6: 0 | EB6: 0 | EC6: 0 | ED6: 0.1 | EE6: =SUM(DR6:EC6) -> 0 | EG6: =DR6 -> 0 | EH6: =DS6 -> 0 | EI6: =DT6 -> 0 | EJ6: =DU6 -> 0 | EK6: =DV6 -> 0 | EL6: =DW6 -> 0 | EM6: =DX6 -> 0 | EN6: =DY6 -> 0 | ... ER6: =EC6 -> 0 | ES6: =SUM(EG6:ER6) -> 0
A7: CONS | B7: DAWE | C7: Regional Upgrades to meet standards | F7: =+E7-D7 -> 0 | I7: =+H7-G7 -> 0 | L7: =+K7-J7 -> 0 | O7: =+N7-M7 -> 0 | R7: =+Q7-P7 -> 0 | U7: =+T7-S7 -> 0 | X7: =+W7-V7 -> 0 | Y7: 2000 | AA7: =+Z7-Y7 -> -2000 | AD7: =+AC7-AB7 -> 0 | AE7: 2000 | AG7: =+AF7-AE7 -> -2000 | AJ7: =+AI7-AH7 -> 0 | AK7: 2000 | AM7: =+AL7-AK7 -> -2000 | AN7: =SUMIF($D$3:$U$3,"Actual",$D7:$U7) -> 0 | AO7: =SUMIF($V$3:$AM$3,"Actual",$V7:$AM7) -> 0 | AP7: =SUMIF($D$3:$AM$3,"Actual",$D7:$AM7) -> 0 | AQ7: =SUMIF($D$3:$AM$3,"Forecast",$D7:$AM7) -> 6000 | AR7: =AP7-AQ7 -> -6000 | AV7: DAWE | CH7: =SUM(AX7:CE7) -> 0 | CI7: Unlikely | CK7: INT | CL7: ASI | CO7: 500 | CR7: 500 | CU7: 500 | CX7: 500 | CY7: =SUM(CM7:CX7) -> 2000 | DA7: =CM7 -> 0 | DB7: =CN7 -> 0 | DC7: 0 | DD7: =CP7 -> 0 | DE7: =CQ7 -> 0 | DF7: 0 | DG7: 0 | DH7: 0 | DI7: 0 | DJ7: 0 | DK7: 0 | DL7: 0 | DM7: =SUM(DA7:DL7) -> 0 | DO7: Finance | DP7: CONS | DQ7: Australian Retirement Trust | DR7: $- | DT7: $- | DU7: $- | DV7: $- | DW7: $- | DX7: $- | DY7: $- | DZ7: $- | EA7: $- | EB7: $- | EC7: $- | ED7: 0.3 | EE7: =SUM(DR7:EC7) -> 0 | EG7: =DR7 -> $- | EH7: =DS7 -> 0 | EI7: =DT7 -> $- | EJ7: =DU7 -> $- | EK7: =DV7 -> $- | EL7: =DW7 -> $- | EM7: =DX7 -> $- | EN7: =DY7 -> $- | ... ER7: =EC7 -> $- | ES7: =SUM(EG7:ER7) -> 0
A8: CONS | B8: DAWE | C8: Sound Masking | F8: =+E8-D8 -> 0 | I8: =+H8-G8 -> 0 | J8: 2500 | L8: =+K8-J8 -> -2500 | M8: 2500 | O8: =+N8-M8 -> -2500 | R8: =+Q8-P8 -> 0 | U8: =+T8-S8 -> 0 | X8: =+W8-V8 -> 0 | AA8: =+Z8-Y8 -> 0 | AD8: =+AC8-AB8 -> 0 | AG8: =+AF8-AE8 -> 0 | AH8: 2000 | AJ8: =+AI8-AH8 -> -2000 | AM8: =+AL8-AK8 -> 0 | AN8: =SUMIF($D$3:$U$3,"Actual",$D8:$U8) -> 0 | AO8: =SUMIF($V$3:$AM$3,"Actual",$V8:$AM8) -> 0 | AP8: =SUMIF($D$3:$AM$3,"Actual",$D8:$AM8) -> 0 | AQ8: =SUMIF($D$3:$AM$3,"Forecast",$D8:$AM8) -> 7000 | AR8: =AP8-AQ8 -> -7000 | AV8: DAFF | AW8: Consulting | AX8: 1000 | BA8: 1000 | BD8: 1000 | BG8: 1000 | BJ8: 1000 | BM8: 0 | BN8: 0 | BO8: 0 | BP8: 0 | BS8: 1000 | BV8: 1000 | BY8: 1000 | CB8: 1000 | CE8: 1000 | CH8: =SUM(AX8:CE8) -> 10000 | CK8: CONS | CL8: ASX | CQ8: 1000 | CR8: 1000 | CY8: =SUM(CM8:CX8) -> 2000 | DA8: =CM8 -> 0 | DB8: =CN8 -> 0 | DC8: =CO8 -> 0 | DD8: =CP8 -> 0 | DE8: 0 | DF8: 0 | DG8: 0 | DI8: 5090.55 | DJ8: 5090.55 | DK8: 0 | DL8: 1000 | DM8: =SUM(DA8:DL8) -> 11181.1 | DO8: Finance | DP8: CONS | DQ8: Aware Super | DR8: =202647/2 -> 101323.5 | DS8: 101323.5 | DT8: 5000 | DU8: 5000 | DV8: 5000 | DW8: $- | DX8: $- | DY8: 5000 | DZ8: 5000 | EA8: 5000 | EB8: $- | EC8: $- | ED8: 1 | EE8: =SUM(DR8:EC8) -> 232647 | EG8: =6137+1821.25 -> 7958.25 | EH8: =DS8 -> 101323.5 | EI8: =DT8 -> 5000 | EJ8: =DU8 -> 5000 | EK8: =DV8 -> 5000 | EL8: =DW8 -> $- | EM8: =DX8 -> $- | EN8: =DY8 -> 5000 | EO8: =DZ8 -> 5000 | ... ER8: =EC8 -> $- | ES8: =SUM(EG8:ER8) -> 139281.75
A9: INT | B9: DESE | C9: Maintenance Extension | D9: =41980/4 -> 10495 | F9: =+E9-D9 -> -10495 | I9: =+H9-G9 -> 0 | L9: =+K9-J9 -> 0 | M9: =41980/4 -> 10495 | O9: =+N9-M9 -> -10495 | R9: =+Q9-P9 -> 0 | S9: 2500 | U9: =+T9-S9 -> -2500 | V9: =41980/4 -> 10495 | X9: =+W9-V9 -> -10495 | AA9: =+Z9-Y9 -> 0 | AD9: =+AC9-AB9 -> 0 | AE9: =41980/4 -> 10495 | AG9: =+AF9-AE9 -> -10495 | AJ9: =+AI9-AH9 -> 0 | AM9: =+AL9-AK9 -> 0 | AN9: =SUMIF($D$3:$U$3,"Actual",$D9:$U9) -> 0 | AO9: =SUMIF($V$3:$AM$3,"Actual",$V9:$AM9) -> 0 | AP9: =SUMIF($D$3:$AM$3,"Actual",$D9:$AM9) -> 0 | AQ9: =SUMIF($D$3:$AM$3,"Forecast",$D9:$AM9) -> 44480 | AR9: =AP9-AQ9 -> -44480 | AV9: DESE | AW9: CRM | AX9: 0 | AY9: 0 | AZ9: 0 | BA9: 0 | BB9: 0 | BC9: 0 | BD9: 0 | BE9: 0 | BF9: 0 | BG9: 0 | BH9: 0 | BI9: 0 | BJ9: 0 | BK9: 0 | BL9: 0 | BM9: 0 | BN9: 0 | BO9: 0 | BP9: 0 | BQ9: 0 | BR9: 0 | BS9: 0 | BT9: 0 | BU9: 0 | BV9: 0 | BW9: 0 | BX9: 0 | BY9: 0 | BZ9: 0 | CA9: 0 | CB9: 0 | CC9: 0 | CD9: 0 | CE9: 0 | CH9: =SUM(AX9:CE9) -> 0 | CK9: CONS | CL9: Australian Museum | CM9: 10000 | CP9: 10000 | CS9: 10000 | CV9: 10000 | CY9: =SUM(CM9:CX9) -> 40000 | DA9: 0 | DB9: =CN9 -> 0 | DC9: =CO9 -> 0 | DD9: 0 | DE9: =CQ9 -> 0 | DF9: =CR9 -> 0 | DG9: 0 | DH9: 0 | DI9: 0 | DJ9: 0 | DK9: 5000 | DL9: 10000 | DM9: =SUM(DA9:DL9) -> 15000 | DO9: Finance | DP9: CONS | DQ9: Bankwest | DR9: $- | DS9: $- | DT9: =DU9 -> 48984.5 | DU9: =(195938*ED9)/2 -> 48984.5 | DV9: $- | DW9: $- | DX9: $- | DY9: $- | DZ9: $- | EA9: $- | EB9: $- | EC9: $- | ED9: 0.5 | EE9: =SUM(DR9:EC9) -> 97969 | EG9: =DR9 -> $- | EH9: =DS9 -> $- | EI9: =DT9 -> 48984.5 | EJ9: =DU9 -> 48984.5 | EK9: =DV9 -> $- | EL9: =DW9 -> $- | EM9: =DX9 -> $- | EN9: =DY9 -> $- | ... ER9: =EC9 -> $- | ES9: =SUM(EG9:ER9) -> 97969
A10: CONS | B10: DFA | C10: Meeting Room Upgrades Consulting Services | F10: =+E10-D10 -> 0 | G10: 5000 | I10: =+H10-G10 -> -5000 | J10: 10000 | L10: =+K10-J10 -> -10000 | M10: 10000 | O10: =+N10-M10 -> -10000 | P10: 8000 | R10: =+Q10-P10 -> -8000 | U10: =+T10-S10 -> 0 | X10: =+W10-V10 -> 0 | AA10: =+Z10-Y10 -> 0 | AD10: =+AC10-AB10 -> 0 | AG10: =+AF10-AE10 -> 0 | AJ10: =+AI10-AH10 -> 0 | AK10: 2000 | AM10: =+AL10-AK10 -> -2000 | AN10: =SUMIF($D$3:$U$3,"Actual",$D10:$U10) -> 0 | AO10: =SUMIF($V$3:$AM$3,"Actual",$V10:$AM10) -> 0 | AP10: =SUMIF($D$3:$AM$3,"Actual",$D10:$AM10) -> 0 | AQ10: =SUMIF($D$3:$AM$3,"Forecast",$D10:$AM10) -> 35000 | AR10: =AP10-AQ10 -> -35000 | AV10: DFA | AX10: 0 | AY10: 0 | AZ10: 0 | BA10: 0 | BB10: 0 | BC10: 0 | BD10: 0 | BE10: 0 | BF10: 0 | BG10: 0 | BH10: 0 | BI10: 0 | BJ10: 0 | BK10: 0 | BL10: 0 | BM10: 0 | BN10: 0 | BO10: 0 | BP10: 0 | BQ10: 0 | BR10: 0 | BS10: 0 | BT10: 0 | BU10: 0 | BV10: 0 | BW10: 0 | BX10: 0 | BY10: 0 | BZ10: 0 | CA10: 0 | CB10: 0 | CC10: 0 | CD10: 0 | CE10: 0 | CH10: =SUM(AX10:CE10) -> 0 | CK10: INT | CL10: AusPayNet | CY10: =SUM(CM10:CX10) -> 0 | DA10: =CM10 -> 0 | DB10: =CN10 -> 0 | DC10: =CO10 -> 0 | DD10: =CP10 -> 0 | DE10: =CQ10 -> 0 | DF10: =CR10 -> 0 | DG10: 0 | DH10: 0 | DI10: 0 | DJ10: 0 | DK10: 0 | DL10: 0 | DM10: =SUM(DA10:DL10) -> 0 | DO10: Finance | DP10: CONS | DQ10: CBA | DR10: =74335*ED10 -> 22300.5 | DS10: $- | DT10: $- | DU10: $- | DV10: $- | DW10: $- | DX10: $- | DY10: $- | DZ10: $- | EA10: $- | EB10: $- | EC10: $- | ED10: 0.3 | EE10: =SUM(DR10:EC10) -> 22300.5 | EG10: 0 | EH10: =DS10 -> $- | EI10: =DT10 -> $- | EJ10: =DU10 -> $- | EK10: =DV10 -> $- | EL10: =DW10 -> $- | EM10: =DX10 -> $- | EN10: =DY10 -> $- | EO10: =DZ10 -> $- | ... ER10: =EC10 -> $- | ES10: =SUM(EG10:ER10) -> 0
A11: CONS | B11: DFA | C11: Forum | J11: 5000 | L11: =+K11-J11 -> -5000 | AV11: DFA | AX11: 2125 | BA11: 2125 | BD11: 0 | BE11: 0 | BF11: 0 | BG11: 0 | BH11: 0 | BI11: 0 | BJ11: 0 | BK11: 0 | BL11: 0 | BM11: 0 | BN11: 0 | BO11: 0 | BP11: 0 | BQ11: 0 | BR11: 0 | BS11: 0 | BT11: 0 | BU11: 0 | BV11: 0 | BW11: 0 | BX11: 0 | BY11: 0 | BZ11: 0 | CA11: 0 | CB11: 0 | CC11: 0 | CD11: 0 | CE11: 0 | CH11: =SUM(AX11:CE11) -> 4250 | CK11: CONS | CL11: Bankwest | CX11: 5000 | CY11: =SUM(CM11:CX11) -> 5000 | DA11: =CM11 -> 0 | DB11: =CN11 -> 0 | DC11: =CO11 -> 0 | DD11: =CP11 -> 0 | DE11: =CQ11 -> 0 | DF11: 0 | DG11: 0 | DH11: 0 | DI11: 0 | DJ11: 0 | DK11: 0 | DL11: 5000 | DM11: =SUM(DA11:DL11) -> 5000 | DO11: Government | DP11: INT | DQ11: City of Sydney | DR11: 0 | ED11: 0.3 | EE11: =SUM(DR11:EC11) -> 0 | EG11: =DR11 -> 0 | EH11: =DS11 -> 0 | EI11: =DT11 -> 0 | EJ11: =DU11 -> 0 | EK11: =DV11 -> 0 | EL11: =DW11 -> 0 | EM11: =DX11 -> 0 | EN11: =DY11 -> 0 | ... ER11: =EC11 -> 0 | ES11: =SUM(EG11:ER11) -> 0
A12: CONS | B12: DTTL | C12: Adhoc Consulting Hours | D12: 2000 | F12: =+E12-D12 -> -2000 | G12: 2000 | I12: =+H12-G12 -> -2000 | J12: 2000 | L12: =+K12-J12 -> -2000 | M12: 2000 | O12: =+N12-M12 -> -2000 | P12: 2000 | R12: =+Q12-P12 -> -2000 | S12: 2000 | U12: =+T12-S12 -> -2000 | V12: 2000 | X12: =+W12-V12 -> -2000 | Y12: 2000 | AA12: =+Z12-Y12 -> -2000 | AB12: 2000 | AD12: =+AC12-AB12 -> -2000 | AE12: 2000 | AG12: =+AF12-AE12 -> -2000 | AH12: 2000 | AJ12: =+AI12-AH12 -> -2000 | AK12: 2000 | AM12: =+AL12-AK12 -> -2000 | AN12: =SUMIF($D$3:$U$3,"Actual",$D12:$U12) -> 0 | AO12: =SUMIF($V$3:$AM$3,"Actual",$V12:$AM12) -> 0 | AP12: =SUMIF($D$3:$AM$3,"Actual",$D12:$AM12) -> 0 | AQ12: =SUMIF($D$3:$AM$3,"Forecast",$D12:$AM12) -> 24000 | AR12: =AP12-AQ12 -> -24000 | AV12: DTTL | AX12: 0 | BA12: 0 | BD12: 0 | BG12: 0 | BJ12: 0 | BS12: 2000 | BV12: 2000 | BY12: 2000 | CB12: 2000 | CE12: 2000 | CH12: =SUM(AX12:CE12) -> 10000 | CK12: CONS | CL12: Corrs Chambers Westgarth | CP12: 5000 | CQ12: 5000 | CR12: 5000 | CU12: 10000 | CW12: 10000 | CY12: =SUM(CM12:CX12) -> 35000 | DA12: 0 | DB12: =CN12 -> 0 | DC12: 0 | DD12: 5801.5 | DE12: 0 | DF12: 0 | DG12: 0 | DH12: 0 | DI12: 0 | DJ12: 0 | DK12: 10000 | DL12: 10000 | DM12: =SUM(DA12:DL12) -> 25801.5 | DO12: Other Sectors (Schools, Hospitals, etc) | DP12: CONS | DQ12: Corrs Chambers Westgarth | DR12: $- | DS12: $- | DT12: $- | DU12: =10000*$ED$12 -> 3000 | DV12: =10000*$ED$12 -> 3000 | DW12: =10000*$ED$12 -> 3000 | DX12: $- | DY12: $- | DZ12: $- | EA12: $- | EB12: $- | EC12: $- | ED12: 0.3 | EE12: =SUM(DR12:EC12) -> 9000 | EG12: =DR12 -> $- | EH12: =DS12 -> $- | EI12: =DT12 -> $- | EJ12: =DU12 -> 3000 | EK12: =DV12 -> 3000 | EL12: =DW12 -> 3000 | EM12: =DX12 -> $- | EN12: =DY12 -> $- | ... ER12: =EC12 -> $- | ES12: =SUM(EG12:ER12) -> 9000
A13: INT | B13: DTTL | C13: XiO Cloud Licensing | D13: =91749/12 -> 7645.75 | F13: =+E13-D13 -> -7645.75 | G13: =91749/12 -> 7645.75 | I13: =+H13-G13 -> -7645.75 | J13: =91749/12 -> 7645.75 | L13: =+K13-J13 -> -7645.75 | M13: =91749/12 -> 7645.75 | O13: =+N13-M13 -> -7645.75 | P13: =91749/12 -> 7645.75 | R13: =+Q13-P13 -> -7645.75 | S13: =91749/12 -> 7645.75 | U13: =+T13-S13 -> -7645.75 | V13: =91749/12 -> 7645.75 | X13: =+W13-V13 -> -7645.75 | Y13: =91749/12 -> 7645.75 | AA13: =+Z13-Y13 -> -7645.75 | AB13: =91749/12 -> 7645.75 | AD13: =+AC13-AB13 -> -7645.75 | AE13: =91749/12 -> 7645.75 | AG13: =+AF13-AE13 -> -7645.75 | AH13: =91749/12 -> 7645.75 | AJ13: =+AI13-AH13 -> -7645.75 | AK13: =91749/12 -> 7645.75 | AM13: =+AL13-AK13 -> -7645.75 | AN13: =SUMIF($D$3:$U$3,"Actual",$D13:$U13) -> 0 | AO13: =SUMIF($V$3:$AM$3,"Actual",$V13:$AM13) -> 0 | AP13: =SUMIF($D$3:$AM$3,"Actual",$D13:$AM13) -> 0 | AQ13: =SUMIF($D$3:$AM$3,"Forecast",$D13:$AM13) -> 91749 | AR13: =AP13-AQ13 -> -91749 | AV13: DTTL | AW13: Per Quote | AX13: =102000/12 -> 8500 | BA13: =102000/12 -> 8500 | BD13: =102000/12 -> 8500 | BG13: =102000/12 -> 8500 | BJ13: =102000/12 -> 8500 | BM13: =102000/12 -> 8500 | BP13: =102000/12 -> 8500 | BS13: =102000/12 -> 8500 | BV13: =102000/12 -> 8500 | BY13: =102000/12 -> 8500 | CB13: =102000/12 -> 8500 | CE13: =102000/12 -> 8500 | CH13: =SUM(AX13:CE13) -> 102000 | CK13: CONS | CL13: DAFF | CN13: 5000 | CQ13: 5000 | CT13: 5000 | CW13: 5000 | CY13: =SUM(CM13:CX13) -> 20000 | DA13: =CM13 -> 0 | DB13: 0 | DC13: =CO13 -> 0 | DD13: =CP13 -> 0 | DE13: 0 | DF13: =CR13 -> 0 | DG13: 0 | DH13: 0 | DI13: 0 | DJ13: 0 | DK13: 5000 | DL13: 0 | DM13: =SUM(DA13:DL13) -> 5000 | DO13: Finance | DP13: INT | DQ13: Deloitte | DR13: =6000*$ED$13 -> 3000 | DS13: =6000*$ED$13 -> 3000 | DT13: =6000*$ED$13 -> 3000 | DU13: =6000*$ED$13 -> 3000 | DV13: =6000*$ED$13 -> 3000 | DW13: =6000*$ED$13 -> 3000 | DX13: =6000*$ED$13 -> 3000 | DY13: =6000*$ED$13 -> 3000 | ... EC13: =6000*$ED$13 -> 3000 | ED13: 0.5 | EE13: =SUM(DR13:EC13) -> 36000 | EG13: 71943 | EH13: =DS13 -> 3000 | EI13: =DT13 -> 3000 | EJ13: =DU13 -> 3000 | EK13: =DV13 -> 3000 | EL13: =DW13 -> 3000 | EM13: =DX13 -> 3000 | EN13: =DY13 -> 3000 | EO13: =DZ13 -> 3000 | ... ER13: =EC13 -> 3000 | ES13: =SUM(EG13:ER13) -> 104943
A14: CONS | B14: DTTL | C14: XiO Cloud / Service Now Integration | G14: 5655 | AV14: DTTL | AW14: Per Quote | AX14: 0 | AY14: 0 | AZ14: 0 | BA14: 0 | BB14: 0 | BC14: 0 | BD14: 0 | BE14: 0 | BF14: 0 | BG14: 0 | BH14: 0 | BI14: 0 | BJ14: 0 | BK14: 0 | BL14: 0 | BM14: 0 | BN14: 0 | BO14: 0 | BP14: 0 | BQ14: 0 | BR14: 0 | BS14: 0 | BT14: 0 | BU14: 0 | BV14: 0 | BW14: 0 | BX14: 0 | BY14: 0 | BZ14: 0 | CA14: 0 | CB14: 0 | CC14: 0 | CD14: 0 | CE14: 0 | CH14: =SUM(AX14:CE14) -> 0 | CK14: INT | CL14: Deloitte | CM14: 15000 | CN14: 15000 | CO14: 15000 | CP14: 15000 | CQ14: 15000 | CT14: 30000 | CU14: 15000 | CV14: 15000 | CW14: 15000 | CX14: 15000 | CY14: =SUM(CM14:CX14) -> 165000 | DA14: 0 | DB14: 0 | DC14: 0 | DD14: 0 | DE14: 0 | DF14: =CR14 -> 0 | DG14: 16313.7 | DH14: 0 | DI14: 0 | DJ14: 0 | DK14: 15000 | DL14: 15000 | DM14: =SUM(DA14:DL14) -> 46313.7 | DO14: Government | DP14: INT | DQ14: DEWR | DS14: $- | DT14: $- | DU14: 14740 | DV14: $- | DW14: $- | DX14: $- | DY14: $- | DZ14: $- | EA14: $- | EB14: $- | EC14: $- | ED14: 1 | EE14: =SUM(DR14:EC14) -> 14740 | EG14: =DR14 -> 0 | EH14: =DS14 -> $- | EI14: =DT14 -> $- | EJ14: =DU14 -> 14740 | EK14: =DV14 -> $- | EL14: =DW14 -> $- | EM14: =DX14 -> $- | EN14: =DY14 -> $- | ... ER14: =EC14 -> $- | ES14: =SUM(EG14:ER14) -> 14740
A15: INT | B15: DTTL | C15: Service Calls | D15: 1500 | F15: =+E15-D15 -> -1500 | G15: 1500 | I15: =+H15-G15 -> -1500 | J15: 1500 | L15: =+K15-J15 -> -1500 | M15: 1500 | O15: =+N15-M15 -> -1500 | P15: 1500 | R15: =+Q15-P15 -> -1500 | S15: 1500 | U15: =+T15-S15 -> -1500 | V15: 1500 | X15: =+W15-V15 -> -1500 | Y15: 1500 | AA15: =+Z15-Y15 -> -1500 | AD15: =+AC15-AB15 -> 0 | AE15: 1500 | AG15: =+AF15-AE15 -> -1500 | AH15: 1500 | AJ15: =+AI15-AH15 -> -1500 | AK15: 1500 | AM15: =+AL15-AK15 -> -1500 | AN15: =SUMIF($D$3:$U$3,"Actual",$D15:$U15) -> 0 | AO15: =SUMIF($V$3:$AM$3,"Actual",$V15:$AM15) -> 0 | AP15: =SUMIF($D$3:$AM$3,"Actual",$D15:$AM15) -> 0 | AQ15: =SUMIF($D$3:$AM$3,"Forecast",$D15:$AM15) -> 16500 | AR15: =AP15-AQ15 -> -16500 | AV15: DTTL | AX15: 0 | AY15: 0 | AZ15: 0 | BA15: 0 | BB15: 0 | BC15: 0 | BD15: 0 | BE15: 0 | BF15: 0 | BG15: 0 | BH15: 0 | BI15: 0 | BJ15: 0 | BK15: 0 | BL15: 0 | BM15: 0 | BN15: 0 | BO15: 0 | BP15: 0 | BQ15: 0 | BR15: 0 | BS15: 0 | BT15: 0 | BU15: 0 | BV15: 0 | BW15: 0 | BX15: 0 | BY15: 0 | BZ15: 0 | CA15: 0 | CB15: 0 | CC15: 0 | CD15: 0 | CE15: 0 | CH15: =SUM(AX15:CE15) -> 0 | CK15: INT | CL15: DEWR | CM15: 8000 | CN15: 8000 | CO15: 8000 | CP15: 8000 | CQ15: 8000 | CR15: 8000 | CS15: 8000 | CT15: 8000 | CU15: 8000 | CV15: 8000 | CW15: 8000 | CX15: 8000 | CY15: =SUM(CM15:CX15) -> 96000 | DA15: 10495 | DB15: 0 | DC15: 0 | DD15: 0 | DE15: 0 | DF15: 0 | DG15: 5105 | DH15: 14270 | DI15: 0 | DJ15: 0 | DK15: 18000 | DL15: 0 | DM15: =SUM(DA15:DL15) -> 47870 | DO15: IT & Media | DP15: INT | DQ15: HP Poly | DR15: =160250*ED15 -> 48075 | ED15: 0.3 | EE15: =SUM(DR15:EC15) -> 48075 | EG15: 1161 | EH15: =DS15 -> 0 | EI15: =DT15 -> 0 | EJ15: =DU15 -> 0 | EK15: =DV15 -> 0 | EL15: =DW15 -> 0 | EM15: =DX15 -> 0 | EN15: =DY15 -> 0 | EO15: =DZ15 -> 0 | ... ER15: =EC15 -> 0 | ES15: =SUM(EG15:ER15) -> 1161
A16: INT | B16: DTTL | C16: Box Sales | F16: =+E16-D16 -> 0 | G16: 2000 | I16: =+H16-G16 -> -2000 | J16: 600 | L16: =+K16-J16 -> -600 | M16: 2000 | O16: =+N16-M16 -> -2000 | R16: =+Q16-P16 -> 0 | S16: 2000 | U16: =+T16-S16 -> -2000 | X16: =+W16-V16 -> 0 | Y16: 2000 | AA16: =+Z16-Y16 -> -2000 | AD16: =+AC16-AB16 -> 0 | AE16: 4000 | AG16: =+AF16-AE16 -> -4000 | AH16: 8000 | AJ16: =+AI16-AH16 -> -8000 | AM16: =+AL16-AK16 -> 0 | AN16: =SUMIF($D$3:$U$3,"Actual",$D16:$U16) -> 0 | AO16: =SUMIF($V$3:$AM$3,"Actual",$V16:$AM16) -> 0 | AP16: =SUMIF($D$3:$AM$3,"Actual",$D16:$AM16) -> 0 | AQ16: =SUMIF($D$3:$AM$3,"Forecast",$D16:$AM16) -> 20600 | AR16: =AP16-AQ16 -> -20600 | AV16: DTTL | AX16: 2000 | BA16: 2000 | BD16: 2000 | BG16: 2000 | BJ16: 2000 | BM16: 0 | BN16: 0 | BO16: 0 | BP16: 0 | BS16: 2000 | BV16: 2000 | BY16: 10000 | CB16: 10000 | CE16: 2000 | CH16: =SUM(AX16:CE16) -> 36000 | CK16: CONS | CL16: DFA | CP16: 2500 | CY16: =SUM(CM16:CX16) -> 2500 | DA16: =1000-298.75 -> 701.25 | DB16: =CN16 -> 0 | DC16: =CO16 -> 0 | DD16: 41.25 | DE16: =-938.75+1000 -> 61.25 | DF16: =CR16 -> 0 | DG16: 0 | DH16: 0 | DI16: 0 | DJ16: 0 | DK16: 0 | DL16: 0 | DM16: =SUM(DA16:DL16) -> 803.75 | DO16: Other Sectors (Schools, Hospitals, etc) | DP16: CONS | DQ16: New business N/E | DR16: =2000*$ED$16+(833) -> 1033 | DS16: =2000*$ED$16+(833) -> 1033 | DT16: =2000*$ED$16+(833) -> 1033 | DU16: =2000*$ED$16+(833) -> 1033 | DV16: =2000*$ED$16+(833) -> 1033 | DW16: =2000*$ED$16+(833) -> 1033 | DX16: =2000*$ED$16+(833) -> 1033 | DY16: =2000*$ED$16+(833) -> 1033 | ... EC16: =2000*$ED$16+(833) -> 1033 | ED16: 0.1 | EE16: =SUM(DR16:EC16) -> 12396 | EG16: 0 | EH16: =DS16 -> 1033 | EI16: =DT16 -> 1033 | EJ16: =DU16 -> 1033 | EK16: =DV16 -> 1033 | EL16: =DW16 -> 1033 | EM16: =DX16 -> 1033 | EN16: =DY16 -> 1033 | EO16: =DZ16 -> 1033 | ... ER16: =EC16 -> 1033 | ES16: =SUM(EG16:ER16) -> 11363
A17: CONS / INT | B17: DTTL | C17: National Rollout | F17: =+E17-D17 -> 0 | I17: =+H17-G17 -> 0 | L17: =+K17-J17 -> 0 | O17: =+N17-M17 -> 0 | R17: =+Q17-P17 -> 0 | U17: =+T17-S17 -> 0 | X17: =+W17-V17 -> 0 | AA17: =+Z17-Y17 -> 0 | AD17: =+AC17-AB17 -> 0 | AE17: 5000 | AG17: =+AF17-AE17 -> -5000 | AJ17: =+AI17-AH17 -> 0 | AK17: 5000 | AM17: =+AL17-AK17 -> -5000 | AN17: =SUMIF($D$3:$U$3,"Actual",$D17:$U17) -> 0 | AO17: =SUMIF($V$3:$AM$3,"Actual",$V17:$AM17) -> 0 | AP17: =SUMIF($D$3:$AM$3,"Actual",$D17:$AM17) -> 0 | AQ17: =SUMIF($D$3:$AM$3,"Forecast",$D17:$AM17) -> 10000 | AR17: =AP17-AQ17 -> -10000 | AV17: DTTL | AX17: 0 | AY17: 0 | AZ17: 0 | BA17: 0 | BB17: 0 | BC17: 0 | BD17: 0 | BE17: 0 | BF17: 0 | BG17: 0 | BH17: 0 | BI17: 0 | BJ17: 0 | BK17: 0 | BL17: 0 | BM17: 0 | BN17: 0 | BO17: 0 | BP17: 0 | BQ17: 0 | BR17: 0 | BS17: 0 | BT17: 0 | BU17: 0 | BV17: 0 | BW17: 0 | BX17: 0 | BY17: 0 | BZ17: 0 | CA17: 0 | CB17: 0 | CC17: 0 | CD17: 0 | CE17: 0 | CH17: =SUM(AX17:CE17) -> 0 | CK17: CONS | CL17: Hills Grammar School | CM17: 2500 | CQ17: 2500 | CU17: 2500 | CY17: =SUM(CM17:CX17) -> 7500 | DA17: 0 | DB17: 5131.47 | DC17: =CO17 -> 0 | DD17: =CP17 -> 0 | DE17: 2982.53 | DF17: =CR17 -> 0 | DG17: 0 | DH17: 0 | DI17: 0 | DJ17: 63705 | DK17: 0 | DL17: 0 | DM17: =SUM(DA17:DL17) -> 71819 | DO17: Other Sectors (Schools, Hospitals, etc) | DP17: INT | DQ17: New business N/E | DR17: =7500*$ED$17+(833) -> 1583 | DS17: =7500*$ED$17+(833) -> 1583 | DT17: =7500*$ED$17+(833) -> 1583 | DU17: =7500*$ED$17+(833) -> 1583 | DV17: =7500*$ED$17+(833) -> 1583 | DW17: =7500*$ED$17+(833) -> 1583 | DX17: =7500*$ED$17+(833) -> 1583 | DY17: =7500*$ED$17+(833) -> 1583 | ... EC17: =7500*$ED$17+(833) -> 1583 | ED17: 0.1 | EE17: =SUM(DR17:EC17) -> 18996 | EG17: 4702 | EH17: =DS17 -> 1583 | EI17: =DT17 -> 1583 | EJ17: =DU17 -> 1583 | EK17: =DV17 -> 1583 | EL17: =DW17 -> 1583 | EM17: =DX17 -> 1583 | EN17: =DY17 -> 1583 | EO17: =DZ17 -> 1583 | ... ER17: =EC17 -> 1583 | ES17: =SUM(EG17:ER17) -> 22115
A18: INT | B18: FY22-23 | C18: Service Calls | D18: 3000 | F18: =+E18-D18 -> -3000 | I18: =+H18-G18 -> 0 | J18: 1000 | L18: =+K18-J18 -> -1000 | O18: =+N18-M18 -> 0 | P18: 1000 | R18: =+Q18-P18 -> -1000 | U18: =+T18-S18 -> 0 | V18: 1000 | X18: =+W18-V18 -> -1000 | AA18: =+Z18-Y18 -> 0 | AB18: 1000 | AD18: =+AC18-AB18 -> -1000 | AG18: =+AF18-AE18 -> 0 | AH18: 1000 | AJ18: =+AI18-AH18 -> -1000 | AM18: =+AL18-AK18 -> 0 | AN18: =SUMIF($D$3:$U$3,"Actual",$D18:$U18) -> 0 | AO18: =SUMIF($V$3:$AM$3,"Actual",$V18:$AM18) -> 0 | AP18: =SUMIF($D$3:$AM$3,"Actual",$D18:$AM18) -> 0 | AQ18: =SUMIF($D$3:$AM$3,"Forecast",$D18:$AM18) -> 8000 | AR18: =AP18-AQ18 -> -8000 | AV18: FY24-25 | AX18: 500 | BA18: 500 | BD18: 500 | BG18: 500 | BJ18: 500 | BM18: 500 | BP18: 500 | BS18: 500 | BV18: 500 | BY18: 500 | CB18: 500 | CE18: 500 | CH18: =SUM(AX18:CE18) -> 6000 | CK18: INT | CL18: HP Poly | CM18: 2000 | CN18: 2000 | CO18: 2000 | CP18: 2000 | CQ18: 2000 | CT18: 2000 | CU18: 2000 | CV18: 2000 | CW18: 2000 | CX18: 2000 | CY18: =SUM(CM18:CX18) -> 20000 | DA18: 0 | DB18: 0 | DC18: 0 | DD18: 680 | DE18: 0 | DF18: =CR18 -> 0 | DG18: 2342.39 | DH18: 3117.5 | DI18: 16925 | DJ18: 24410 | DK18: 2000 | DL18: 200000 | DM18: =SUM(DA18:DL18) -> 249474.89 | DO18: Government | DP18: INT | DQ18: Property NSW | DR18: 19305.58 | DS18: 19305.58 | DT18: 19305.58 | DU18: 19305.58 | DV18: 19305.58 | DW18: 19305.58 | DX18: 19305.58 | DY18: 19305.58 | DZ18: 19305.58 | EA18: 19305.58 | ED18: 1 | EE18: =SUM(DR18:EC18) -> 193055.8 | EG18: 21055.39 | EH18: =DS18 -> 19305.58 | EI18: =DT18 -> 19305.58 | EJ18: =DU18 -> 19305.58 | EK18: =DV18 -> 19305.58 | EL18: =DW18 -> 19305.58 | EM18: =DX18 -> 19305.58 | EN18: =DY18 -> 19305.58 | EO18: =DZ18 -> 19305.58 | ... ER18: =EC18 -> 0 | ES18: =SUM(EG18:ER18) -> 194805.61
A19: INT | B19: FY22-23 | C19: Box Sales | F19: =+E19-D19 -> 0 | G19: 2000 | I19: =+H19-G19 -> -2000 | L19: =+K19-J19 -> 0 | M19: 2000 | O19: =+N19-M19 -> -2000 | R19: =+Q19-P19 -> 0 | S19: 2000 | U19: =+T19-S19 -> -2000 | X19: =+W19-V19 -> 0 | Y19: 2000 | AA19: =+Z19-Y19 -> -2000 | AD19: =+AC19-AB19 -> 0 | AE19: 2000 | AG19: =+AF19-AE19 -> -2000 | AH19: 5000 | AJ19: =+AI19-AH19 -> -5000 | AK19: 5000 | AM19: =+AL19-AK19 -> -5000 | AN19: =SUMIF($D$3:$U$3,"Actual",$D19:$U19) -> 0 | AO19: =SUMIF($V$3:$AM$3,"Actual",$V19:$AM19) -> 0 | AP19: =SUMIF($D$3:$AM$3,"Actual",$D19:$AM19) -> 0 | AQ19: =SUMIF($D$3:$AM$3,"Forecast",$D19:$AM19) -> 20000 | AR19: =AP19-AQ19 -> -20000 | AV19: FY24-25 | AX19: 2000 | BA19: 2000 | BD19: 2000 | BG19: 2000 | BJ19: 2000 | BM19: 2000 | BP19: 2000 | BS19: 2000 | BV19: 2000 | BY19: 2000 | CB19: 2000 | CE19: 2000 | CH19: =SUM(AX19:CE19) -> 24000 | CK19: CONS | CL19: Metcash | CN19: 10000 | CQ19: 10000 | CU19: 10000 | CX19: 10000 | CY19: =SUM(CM19:CX19) -> 40000 | DA19: =CM19 -> 0 | DB19: 0 | DC19: =CO19 -> 0 | DD19: =CP19 -> 0 | DE19: 0 | DF19: =CR19 -> 0 | DG19: 0 | DH19: 0 | DI19: 0 | DJ19: 0 | DK19: 0 | DL19: 2000 | DM19: =SUM(DA19:DL19) -> 2000 | DO19: Business Services | DP19: CONS | DQ19: PTS | DR19: $- | DS19: $- | DT19: $- | DU19: $- | DV19: $- | DW19: $- | DX19: $- | DY19: $- | DZ19: $- | EA19: $- | EB19: $- | EC19: 0 | ED19: 0.5 | EE19: =SUM(DR19:EC19) -> 0 | EG19: =DR19 -> $- | EH19: =DS19 -> $- | EI19: =DT19 -> $- | EJ19: =DU19 -> $- | EK19: =DV19 -> $- | EL19: =DW19 -> $- | EM19: =DX19 -> $- | EN19: =DY19 -> $- | ... ER19: =EC19 -> 0 | ES19: =SUM(EG19:ER19) -> 0
A20: INT | B20: KPMG | C20: Box Sales | D20: 2000 | F20: =+E20-D20 -> -2000 | I20: =+H20-G20 -> 0 | J20: 2000 | L20: =+K20-J20 -> -2000 | O20: =+N20-M20 -> 0 | P20: 1000 | R20: =+Q20-P20 -> -1000 | U20: =+T20-S20 -> 0 | V20: 1000 | X20: =+W20-V20 -> -1000 | AA20: =+Z20-Y20 -> 0 | AB20: 1000 | AD20: =+AC20-AB20 -> -1000 | AG20: =+AF20-AE20 -> 0 | AH20: 2000 | AJ20: =+AI20-AH20 -> -2000 | AK20: 2000 | AM20: =+AL20-AK20 -> -2000 | AN20: =SUMIF($D$3:$U$3,"Actual",$D20:$U20) -> 0 | AO20: =SUMIF($V$3:$AM$3,"Actual",$V20:$AM20) -> 0 | AP20: =SUMIF($D$3:$AM$3,"Actual",$D20:$AM20) -> 0 | AQ20: =SUMIF($D$3:$AM$3,"Forecast",$D20:$AM20) -> 11000 | AR20: =AP20-AQ20 -> -11000 | AV20: KPMG | AX20: 0 | BA20: 0 | BD20: 0 | BG20: 0 | BJ20: 0 | BM20: 0 | BP20: 0 | BS20: 1000 | BV20: 1000 | BY20: 1000 | CB20: 1000 | CE20: 1000 | CH20: =SUM(AX20:CE20) -> 5000 | CK20: INT | CL20: Property NSW | CM20: 9027 | CN20: 9027 | CO20: 9027 | CP20: 9027 | CQ20: 9027 | CR20: 9027 | CS20: 9027 | CT20: 9027 | CU20: 9027 | CV20: 9027 | CW20: 0 | CX20: 0 | CY20: =SUM(CM20:CX20) -> 90270 | DA20: 10133.96 | DB20: 10133.96 | DC20: =10133.96+1415.89+6704.24 -> 18254.09 | DD20: =20705.01+1870.73 -> 22575.74 | DE20: =13699.58-929.33+2873.66 -> 15643.91 | DF20: =9027+519.56+1887.85+439.33+245.13+1726.34+929.33+381.15 -> 15155.69 | DG20: 15155.69 | DH20: 15155.69 | DI20: 0 | DJ20: 0 | DK20: 1353 | DL20: 1353 | DM20: =SUM(DA20:DL20) -> 124914.73 | DO20: Finance | DP20: INT | DQ20: PwC | DR20: =116355*$ED$20 -> 58177.5 | DS20: =671969*$ED$20 -> 335984.5 | ED20: 0.5 | EE20: =SUM(DR20:EC20) -> 394162 | EG20: 0 | EH20: =DS20 -> 335984.5 | EI20: =DT20 -> 0 | EJ20: =DU20 -> 0 | EK20: =DV20 -> 0 | EL20: =DW20 -> 0 | EM20: =DX20 -> 0 | EN20: =DY20 -> 0 | EO20: =DZ20 -> 0 | ... ER20: =EC20 -> 0 | ES20: =SUM(EG20:ER20) -> 335984.5
A21: CONS | B21: Law Society | C21: AV Upgrade | F21: =+E21-D21 -> 0 | G21: 4000 | I21: =+H21-G21 -> -4000 | J21: 4000 | L21: =+K21-J21 -> -4000 | M21: 4000 | O21: =+N21-M21 -> -4000 | P21: 4000 | R21: =+Q21-P21 -> -4000 | U21: =+T21-S21 -> 0 | X21: =+W21-V21 -> 0 | AA21: =+Z21-Y21 -> 0 | AD21: =+AC21-AB21 -> 0 | AG21: =+AF21-AE21 -> 0 | AJ21: =+AI21-AH21 -> 0 | AM21: =+AL21-AK21 -> 0 | AN21: =SUMIF($D$3:$U$3,"Actual",$D21:$U21) -> 0 | AO21: =SUMIF($V$3:$AM$3,"Actual",$V21:$AM21) -> 0 | AP21: =SUMIF($D$3:$AM$3,"Actual",$D21:$AM21) -> 0 | AQ21: =SUMIF($D$3:$AM$3,"Forecast",$D21:$AM21) -> 16000 | AR21: =AP21-AQ21 -> -16000 | AV21: Law Society | CH21: =SUM(AX21:CE21) -> 0 | CL21: PwC | CM21: 5000 | CN21: 5000 | CO21: 5000 | CP21: 5000 | CQ21: 5000 | CR21: 5000 | CS21: 5000 | CT21: 5000 | CU21: 5000 | CV21: 5000 | CW21: 5000 | CX21: 5000 | CY21: =SUM(CM21:CX21) -> 60000 | DA21: 0 | DB21: 0 | DC21: 0 | DD21: 0 | DE21: 0 | DF21: 0 | DG21: 0 | DH21: 0 | DI21: 14055 | DJ21: 0 | DK21: 5000 | DL21: 5000 | DM21: =SUM(DA21:DL21) -> 24055 | DO21: Energy, Utilities, Infrastructure | DP21: INT | DQ21: Ventia | DR21: =7977*ED21 -> 2393.1 | DS21: $- | DT21: $- | DU21: $- | DV21: $- | DW21: $- | DX21: $- | DY21: $- | DZ21: $- | EA21: $- | EB21: $- | EC21: $- | ED21: 0.3 | EE21: =SUM(DR21:EC21) -> 2393.1 | EG21: 0 | EH21: =DS21 -> $- | EI21: =DT21 -> $- | EJ21: =DU21 -> $- | EK21: =DV21 -> $- | EL21: =DW21 -> $- | EM21: =DX21 -> $- | EN21: =DY21 -> $- | EO21: =DZ21 -> $- | ... ER21: =EC21 -> $- | ES21: =SUM(EG21:ER21) -> 0
A22: INT | B22: NSW Property | C22: 6PSQ Condeco | AN22: =SUMIF($D$3:$U$3,"Actual",$D22:$U22) -> 0 | AO22: =SUMIF($V$3:$AM$3,"Actual",$V22:$AM22) -> 0 | AP22: =SUMIF($D$3:$AM$3,"Actual",$D22:$AM22) -> 0 | AQ22: =SUMIF($D$3:$AM$3,"Forecast",$D22:$AM22) -> 0 | AR22: =AP22-AQ22 -> 0 | AV22: NSW Property | AX22: 0 | AY22: 0 | AZ22: 0 | BA22: 0 | BB22: 0 | BC22: 0 | BD22: 0 | BE22: 0 | BF22: 0 | BG22: 0 | BH22: 0 | BI22: 0 | BJ22: 0 | BK22: 0 | BL22: 0 | BM22: 0 | BN22: 0 | BO22: 0 | BP22: 0 | BQ22: 0 | BR22: 0 | BS22: 0 | BT22: 0 | BU22: 0 | BV22: 0 | BW22: 0 | BX22: 0 | BY22: 0 | BZ22: 0 | CA22: 0 | CB22: 0 | CC22: 0 | CD22: 0 | CE22: 0 | CH22: =SUM(AX22:CE22) -> 0 | CK22: CONS | CL22: Spacera | CM22: 0 | CN22: 0 | CO22: 5000 | CP22: 0 | CQ22: 0 | CR22: 5000 | CS22: 0 | CT22: 0 | CU22: 5000 | CV22: 0 | CW22: 0 | CX22: 5000 | CY22: =SUM(CM22:CX22) -> 20000 | DA22: =CM22 -> 0 | DB22: =CN22 -> 0 | DC22: 0 | DD22: =CP22 -> 0 | DE22: =CQ22 -> 0 | DF22: 0 | DG22: 0 | DH22: 0 | DI22: 0 | DJ22: 0 | DK22: 0 | DL22: 5000 | DM22: =SUM(DA22:DL22) -> 5000 | DO22: IT & Media | DP22: CONS | DQ22: Visagio | DR22: =35000*ED22 -> 17500 | DS22: $- | DT22: $- | DU22: $- | DV22: $- | DW22: $- | DX22: $- | DY22: $- | DZ22: $- | EA22: $- | EB22: $- | EC22: $- | ED22: 0.5 | EE22: =SUM(DR22:EC22) -> 17500 | EG22: 0 | EH22: =DS22 -> $- | EI22: =DT22 -> $- | EJ22: =DU22 -> $- | EK22: =DV22 -> $- | EL22: =DW22 -> $- | EM22: =DX22 -> $- | EN22: =DY22 -> $- | EO22: =DZ22 -> $- | ... ER22: =EC22 -> $- | ES22: =SUM(EG22:ER22) -> 0
A23: INT | B23: NSW Property | C23: 231 Elizabeth St Proxyclick | F23: =+E23-D23 -> 0 | I23: =+H23-G23 -> 0 | L23: =+K23-J23 -> 0 | M23: 25000 | O23: =+N23-M23 -> -25000 | P23: 25000 | R23: =+Q23-P23 -> -25000 | U23: =+T23-S23 -> 0 | X23: =+W23-V23 -> 0 | AA23: =+Z23-Y23 -> 0 | AD23: =+AC23-AB23 -> 0 | AG23: =+AF23-AE23 -> 0 | AJ23: =+AI23-AH23 -> 0 | AM23: =+AL23-AK23 -> 0 | AN23: =SUMIF($D$3:$U$3,"Actual",$D23:$U23) -> 0 | AO23: =SUMIF($V$3:$AM$3,"Actual",$V23:$AM23) -> 0 | AP23: =SUMIF($D$3:$AM$3,"Actual",$D23:$AM23) -> 0 | AQ23: =SUMIF($D$3:$AM$3,"Forecast",$D23:$AM23) -> 50000 | AR23: =AP23-AQ23 -> -50000 | AV23: NSW Property | AX23: 0 | BA23: 30000 | BD23: 0 | BE23: 0 | BF23: 0 | BG23: 0 | BH23: 0 | BI23: 0 | BJ23: 0 | BK23: 0 | BL23: 0 | BM23: 0 | BN23: 0 | BO23: 0 | BP23: 0 | BQ23: 0 | BR23: 0 | BS23: 0 | BT23: 0 | BU23: 0 | BV23: 0 | BW23: 0 | BX23: 0 | BY23: 0 | BZ23: 0 | CA23: 0 | CB23: 0 | CC23: 0 | CD23: 0 | CE23: 0 | CH23: =SUM(AX23:CE23) -> 30000 | CK23: CONS | CL23: St Catherines School | CP23: 5000 | CV23: 5000 | CY23: =SUM(CM23:CX23) -> 10000 | DA23: =CM23 -> 0 | DB23: =CN23 -> 0 | DC23: =CO23 -> 0 | DD23: 0 | DE23: =CQ23 -> 0 | DF23: =CR23 -> 0 | DG23: 0 | DH23: 0 | DI23: 15155.69 | DJ23: 15155.69 | DK23: 0 | DL23: 0 | DM23: =SUM(DA23:DL23) -> 30311.38 | DO23: Finance | DP23: CONS | DQ23: Wayflyer | DR23: =64365*ED23 -> 19309.5 | DS23: $- | DT23: $- | DU23: $- | DV23: $- | DW23: $- | DX23: $- | DY23: $- | DZ23: $- | EA23: $- | EB23: $- | EC23: $- | ED23: 0.3 | EE23: =SUM(DR23:EC23) -> 19309.5 | EG23: 0 | EH23: =DS23 -> $- | EI23: =DT23 -> $- | EJ23: =DU23 -> $- | EK23: =DV23 -> $- | EL23: =DW23 -> $- | EM23: =DX23 -> $- | EN23: =DY23 -> $- | EO23: =DZ23 -> $- | ... ER23: =EC23 -> $- | ES23: =SUM(EG23:ER23) -> 0
A24: CONS | B24: INVESTA | C24: 420 George Signage | O24: =+N24-M24 -> 0 | AN24: =SUMIF($D$3:$U$3,"Actual",$D24:$U24) -> 0 | AO24: =SUMIF($V$3:$AM$3,"Actual",$V24:$AM24) -> 0 | AP24: =SUMIF($D$3:$AM$3,"Actual",$D24:$AM24) -> 0 | AQ24: =SUMIF($D$3:$AM$3,"Forecast",$D24:$AM24) -> 0 | AR24: =AP24-AQ24 -> 0 | AV24: INVESTA | AX24: 0 | BA24: 0 | BD24: 0 | BG24: 0 | BJ24: 0 | BM24: 0 | BP24: 0 | BS24: 0 | BV24: 0 | BY24: 0 | CB24: 0 | CE24: 0 | CH24: =SUM(AX24:CE24) -> 0 | CK24: CONS | CL24: Stone & Chalk | CN24: 1500 | CQ24: 1500 | CT24: 1500 | CW24: 1500 | CY24: =SUM(CM24:CX24) -> 6000 | DA24: =CM24 -> 0 | DB24: 0 | DC24: =CO24 -> 0 | DD24: =CP24 -> 0 | DE24: 0 | DF24: =CR24 -> 0 | DG24: 0 | DH24: 0 | DI24: 0 | DJ24: 0 | DK24: 500 | DL24: 0 | DM24: =SUM(DA24:DL24) -> 500 | EE24: =SUM(DR24:EC24) -> 0 | EG24: =DR24 -> 0 | EH24: =DS24 -> 0 | EI24: =DT24 -> 0 | EJ24: =DU24 -> 0 | EK24: =DV24 -> 0 | EL24: =DW24 -> 0 | EM24: =DX24 -> 0 | EN24: =DY24 -> 0 | ... ER24: =EC24 -> 0 | ES24: =SUM(EG24:ER24) -> 0
A25: INT / CONS | B25: NSW Property | C25: Proxyclick / Condeco Licenses | D25: =30000/12 -> 2500 | F25: =+E25-D25 -> -2500 | G25: =30000/12 -> 2500 | I25: =+H25-G25 -> -2500 | J25: =30000/12 -> 2500 | L25: =+K25-J25 -> -2500 | M25: =30000/12 -> 2500 | O25: =+N25-M25 -> -2500 | P25: =30000/12 -> 2500 | R25: =+Q25-P25 -> -2500 | S25: =30000/12 -> 2500 | U25: =+T25-S25 -> -2500 | V25: =30000/12 -> 2500 | X25: =+W25-V25 -> -2500 | Y25: =30000/12 -> 2500 | AA25: =+Z25-Y25 -> -2500 | AB25: =30000/12 -> 2500 | AD25: =+AC25-AB25 -> -2500 | AE25: =30000/12 -> 2500 | AG25: =+AF25-AE25 -> -2500 | AH25: =30000/12 -> 2500 | AJ25: =+AI25-AH25 -> -2500 | AK25: =30000/12 -> 2500 | AM25: =+AL25-AK25 -> -2500 | AN25: =SUMIF($D$3:$U$3,"Actual",$D25:$U25) -> 0 | AO25: =SUMIF($V$3:$AM$3,"Actual",$V25:$AM25) -> 0 | AP25: =SUMIF($D$3:$AM$3,"Actual",$D25:$AM25) -> 0 | AQ25: =SUMIF($D$3:$AM$3,"Forecast",$D25:$AM25) -> 30000 | AR25: =AP25-AQ25 -> -30000 | AV25: NSW Property | AX25: 5000 | BA25: 5000 | BD25: 5000 | BG25: 5000 | BJ25: 5000 | BM25: 5000 | BP25: 5000 | BS25: 5000 | BV25: 5000 | BY25: 5000 | CB25: 5000 | CE25: 5000 | CH25: =SUM(AX25:CE25) -> 60000 | CK25: CONS | CL25: Stryker | CM25: 10000 | CP25: 10000 | CY25: =SUM(CM25:CX25) -> 20000 | DA25: 0 | DB25: =CN25 -> 0 | DC25: =CO25 -> 0 | DD25: 0 | DE25: =CQ25 -> 0 | DF25: =CR25 -> 0 | DG25: 0 | DH25: 0 | DI25: 0 | DJ25: 0 | DK25: 0 | DL25: 0 | DM25: =SUM(DA25:DL25) -> 0 | EE25: =SUM(DR25:EC25) -> 0 | EG25: =DR25 -> 0 | EH25: =DS25 -> 0 | EI25: =DT25 -> 0 | EJ25: =DU25 -> 0 | EK25: =DV25 -> 0 | EL25: =DW25 -> 0 | EM25: =DX25 -> 0 | EN25: =DY25 -> 0 | ... ER25: =EC25 -> 0 | ES25: =SUM(EG25:ER25) -> 0
A26: CONS | B26: PMG | C26: Consulting Opportunity | F26: =+E26-D26 -> 0 | G26: 5000 | I26: =+H26-G26 -> -5000 | J26: 5000 | L26: =+K26-J26 -> -5000 | O26: =+N26-M26 -> 0 | R26: =+Q26-P26 -> 0 | U26: =+T26-S26 -> 0 | X26: =+W26-V26 -> 0 | AA26: =+Z26-Y26 -> 0 | AD26: =+AC26-AB26 -> 0 | AG26: =+AF26-AE26 -> 0 | AJ26: =+AI26-AH26 -> 0 | AM26: =+AL26-AK26 -> 0 | AN26: =SUMIF($D$3:$U$3,"Actual",$D26:$U26) -> 0 | AO26: =SUMIF($V$3:$AM$3,"Actual",$V26:$AM26) -> 0 | AP26: =SUMIF($D$3:$AM$3,"Actual",$D26:$AM26) -> 0 | AQ26: =SUMIF($D$3:$AM$3,"Forecast",$D26:$AM26) -> 10000 | AR26: =AP26-AQ26 -> -10000 | AV26: PMG | AX26: 0 | BA26: 0 | BD26: 0 | BG26: 0 | BJ26: 0 | BM26: 0 | BP26: 0 | BV26: 1000 | BY26: 1000 | CB26: 1000 | CE26: 1000 | CH26: =SUM(AX26:CE26) -> 4000 | CK26: CONS | CL26: University of Wollongong | CM26: 2500 | CO26: 2500 | CP26: 2500 | CT26: 2500 | CV26: 2500 | CY26: =SUM(CM26:CX26) -> 12500 | DA26: 8233.75 | DB26: 4811 | DC26: 0 | DD26: 577.5 | DE26: =CQ26 -> 0 | DF26: 0 | DG26: 0 | DI26: 0 | DJ26: 0 | DK26: 0 | DL26: 0 | DM26: =SUM(DA26:DL26) -> 13622.25 | EE26: =SUM(DR26:EC26) -> 0 | EG26: =DR26 -> 0 | EH26: =DS26 -> 0 | EI26: =DT26 -> 0 | EJ26: =DU26 -> 0 | EK26: =DV26 -> 0 | EL26: =DW26 -> 0 | EM26: =DX26 -> 0 | EN26: =DY26 -> 0 | ... ER26: =EC26 -> 0 | ES26: =SUM(EG26:ER26) -> 0
A27: CONS | B27: PwC | C27: Sydney Mobile Kit Relocation | F27: =+E27-D27 -> 0 | I27: =+H27-G27 -> 0 | J27: 5000 | L27: =+K27-J27 -> -5000 | M27: 5000 | O27: =+N27-M27 -> -5000 | P27: 5000 | R27: =+Q27-P27 -> -5000 | S27: 7000 | U27: =+T27-S27 -> -7000 | X27: =+W27-V27 -> 0 | AA27: =+Z27-Y27 -> 0 | AD27: =+AC27-AB27 -> 0 | AE27: 5000 | AG27: =+AF27-AE27 -> -5000 | AH27: 3000 | AJ27: =+AI27-AH27 -> -3000 | AM27: =+AL27-AK27 -> 0 | AN27: =SUMIF($D$3:$U$3,"Actual",$D27:$U27) -> 0 | AO27: =SUMIF($V$3:$AM$3,"Actual",$V27:$AM27) -> 0 | AP27: =SUMIF($D$3:$AM$3,"Actual",$D27:$AM27) -> 0 | AQ27: =SUMIF($D$3:$AM$3,"Forecast",$D27:$AM27) -> 30000 | AR27: =AP27-AQ27 -> -30000 | AV27: PwC | CH27: =SUM(AX27:CE27) -> 0 | CL27: VinoMofo | CT27: 2000 | CY27: =SUM(CM27:CX27) -> 2000 | DA27: =CM27 -> 0 | DB27: =CN27 -> 0 | DC27: =CO27 -> 0 | DD27: =CP27 -> 0 | DE27: =CQ27 -> 0 | DF27: =CR27 -> 0 | DG27: 0 | DH27: 0 | DI27: 0 | DJ27: 0 | DK27: 0 | DL27: 0 | DM27: =SUM(DA27:DL27) -> 0 | EE27: =SUM(DR27:EC27) -> 0 | EG27: =DR27 -> 0 | EH27: =DS27 -> 0 | EI27: =DT27 -> 0 | EJ27: =DU27 -> 0 | EK27: =DV27 -> 0 | EL27: =DW27 -> 0 | EM27: =DX27 -> 0 | EN27: =DY27 -> 0 | ... ER27: =EC27 -> 0 | ES27: =SUM(EG27:ER27) -> 0
A28: INT | B28: PwC | C28: SYD & Melb Additional Lapels | R28: =+Q28-P28 -> 0 | U28: =+T28-S28 -> 0 | X28: =+W28-V28 -> 0 | AA28: =+Z28-Y28 -> 0 | AD28: =+AC28-AB28 -> 0 | AG28: =+AF28-AE28 -> 0 | AJ28: =+AI28-AH28 -> 0 | AM28: =+AL28-AK28 -> 0 | AN28: =SUMIF($D$3:$U$3,"Actual",$D28:$U28) -> 0 | AO28: =SUMIF($V$3:$AM$3,"Actual",$V28:$AM28) -> 0 | AP28: =SUMIF($D$3:$AM$3,"Actual",$D28:$AM28) -> 0 | AQ28: =SUMIF($D$3:$AM$3,"Forecast",$D28:$AM28) -> 0 | AR28: =AP28-AQ28 -> 0 | AV28: PwC | AW28: Project Works | AX28: 1000 | BA28: 1000 | BD28: 1000 | BG28: 1000 | BJ28: 1000 | BM28: 1000 | BP28: 1000 | BS28: 1000 | BV28: 1000 | BY28: 1000 | CB28: 1000 | CE28: 1000 | CH28: =SUM(AX28:CE28) -> 12000 | CY28: =SUM(CM28:CX28) -> 0 | DA28: =CM28 -> 0 | DB28: =CN28 -> 0 | DC28: =CO28 -> 0 | DD28: =CP28 -> 0 | DE28: =CQ28 -> 0 | DF28: =CR28 -> 0 | DG28: 0 | DH28: 0 | DI28: 0 | DJ28: 0 | DK28: 0 | DL28: 0 | DM28: =SUM(DA28:DL28) -> 0 | EE28: =SUM(DR28:EC28) -> 0 | EG28: =DR28 -> 0 | EH28: =DS28 -> 0 | EI28: =DT28 -> 0 | EJ28: =DU28 -> 0 | EK28: =DV28 -> 0 | EL28: =DW28 -> 0 | EM28: =DX28 -> 0 | EN28: =DY28 -> 0 | ... ER28: =EC28 -> 0 | ES28: =SUM(EG28:ER28) -> 0
A29: CONS | B29: RWC | C29: Whitlam Room Refurbishment | F29: =+E29-D29 -> 0 | I29: =+H29-G29 -> 0 | L29: =+K29-J29 -> 0 | M29: 15000 | O29: =+N29-M29 -> -15000 | P29: 10000 | R29: =+Q29-P29 -> -10000 | U29: =+T29-S29 -> 0 | X29: =+W29-V29 -> 0 | AA29: =+Z29-Y29 -> 0 | AD29: =+AC29-AB29 -> 0 | AG29: =+AF29-AE29 -> 0 | AJ29: =+AI29-AH29 -> 0 | AK29: 10000 | AM29: =+AL29-AK29 -> -10000 | AN29: =SUMIF($D$3:$U$3,"Actual",$D29:$U29) -> 0 | AO29: =SUMIF($V$3:$AM$3,"Actual",$V29:$AM29) -> 0 | AP29: =SUMIF($D$3:$AM$3,"Actual",$D29:$AM29) -> 0 | AQ29: =SUMIF($D$3:$AM$3,"Forecast",$D29:$AM29) -> 35000 | AR29: =AP29-AQ29 -> -35000 | AV29: RWC | CH29: =SUM(AX29:CE29) -> 0 | DA29: =CM29 -> 0 | DB29: =CN29 -> 0 | DC29: =CO29 -> 0 | DD29: =CP29 -> 0 | DE29: =CQ29 -> 0 | DF29: =CR29 -> 0 | DG29: 0 | DH29: 0 | DI29: 2342.39 | DJ29: 0 | DK29: 0 | DL29: 0 | DM29: =SUM(DA29:DL29) -> 2342.39 | EE29: =SUM(DR29:EC29) -> 0 | EG29: =DR29 -> 0 | EH29: =DS29 -> 0 | EI29: =DT29 -> 0 | EJ29: =DU29 -> 0 | EK29: =DV29 -> 0 | EL29: =DW29 -> 0 | EM29: =DX29 -> 0 | EN29: =DY29 -> 0 | ... ER29: =EC29 -> 0 | ES29: =SUM(EG29:ER29) -> 0
A30: CONS | B30: SOH | C30: Recording and Broadcast Studios Tender | X30: =+W30-V30 -> 0 | AN30: =SUMIF($D$3:$U$3,"Actual",$D30:$U30) -> 0 | AO30: =SUMIF($V$3:$AM$3,"Actual",$V30:$AM30) -> 0 | AP30: =SUMIF($D$3:$AM$3,"Actual",$D30:$AM30) -> 0 | AQ30: =SUMIF($D$3:$AM$3,"Forecast",$D30:$AM30) -> 0 | AR30: =AP30-AQ30 -> 0 | AV30: SOH | CH30: =SUM(AX30:CE30) -> 0 | DA30: =CM30 -> 0 | DB30: =CN30 -> 0 | DC30: =CO30 -> 0 | DD30: =CP30 -> 0 | DE30: =CQ30 -> 0 | DF30: =CR30 -> 0 | DG30: 0 | DH30: 0 | DI30: 0 | DJ30: 0 | DK30: 0 | DL30: 0 | DM30: =SUM(DA30:DL30) -> 0 | EE30: =SUM(DR30:EC30) -> 0 | EG30: =DR30 -> 0 | EH30: =DS30 -> 0 | EI30: =DT30 -> 0 | EJ30: =DU30 -> 0 | EK30: =DV30 -> 0 | EL30: =DW30 -> 0 | EM30: =DX30 -> 0 | EN30: =DY30 -> 0 | ... ER30: =EC30 -> 0 | ES30: =SUM(EG30:ER30) -> 0
A31: INT | B31: St Lukes | C31: Cartwright Room | F31: =+E31-D31 -> 0 | I31: =+H31-G31 -> 0 | L31: =+K31-J31 -> 0 | X31: =+W31-V31 -> 0 | AA31: =+Z31-Y31 -> 0 | AD31: =+AC31-AB31 -> 0 | AG31: =+AF31-AE31 -> 0 | AJ31: =+AI31-AH31 -> 0 | AM31: =+AL31-AK31 -> 0 | AN31: =SUMIF($D$3:$U$3,"Actual",$D31:$U31) -> 0 | AO31: =SUMIF($V$3:$AM$3,"Actual",$V31:$AM31) -> 0 | AP31: =SUMIF($D$3:$AM$3,"Actual",$D31:$AM31) -> 0 | AQ31: =SUMIF($D$3:$AM$3,"Forecast",$D31:$AM31) -> 0 | AR31: =AP31-AQ31 -> 0 | AV31: St Lukes | AW31: ? | AX31: 0 | AY31: 0 | AZ31: 0 | BA31: 0 | BB31: 0 | BC31: 0 | BD31: 0 | BE31: 0 | BF31: 0 | BG31: 0 | BH31: 0 | BI31: 0 | BJ31: 0 | BK31: 0 | BL31: 0 | BM31: 0 | BN31: 0 | BO31: 0 | BP31: 0 | BQ31: 0 | BR31: 0 | BS31: 0 | BT31: 0 | BU31: 0 | BV31: 0 | BW31: 0 | BX31: 0 | BY31: 0 | BZ31: 0 | CA31: 0 | CB31: 0 | CC31: 0 | CD31: 0 | CE31: 0 | CH31: =SUM(AX31:CE31) -> 0 | CY31: =SUM(CM31:CX31) -> 0 | DA31: =CM31 -> 0 | DB31: =CN31 -> 0 | DC31: =CO31 -> 0 | DD31: =CP31 -> 0 | DE31: =CQ31 -> 0 | DF31: =CR31 -> 0 | DG31: 0 | DH31: 0 | DI31: 0 | DJ31: 0 | DK31: 0 | DL31: 0 | DM31: =SUM(DA31:DL31) -> 0 | EE31: =SUM(DR31:EC31) -> 0 | EG31: =DR31 -> 0 | EH31: =DS31 -> 0 | EI31: =DT31 -> 0 | EJ31: =DU31 -> 0 | EK31: =DV31 -> 0 | EL31: =DW31 -> 0 | EM31: =DX31 -> 0 | EN31: =DY31 -> 0 | ... ER31: =EC31 -> 0 | ES31: =SUM(EG31:ER31) -> 0
A32: CONS | B32: Tank Stream Labs | C32: Live Event Space | O32: =+N32-M32 -> 0 | R32: =+Q32-P32 -> 0 | U32: =+T32-S32 -> 0 | X32: =+W32-V32 -> 0 | AA32: =+Z32-Y32 -> 0 | AD32: =+AC32-AB32 -> 0 | AG32: =+AF32-AE32 -> 0 | AJ32: =+AI32-AH32 -> 0 | AM32: =+AL32-AK32 -> 0 | AN32: =SUMIF($D$3:$U$3,"Actual",$D32:$U32) -> 0 | AO32: =SUMIF($V$3:$AM$3,"Actual",$V32:$AM32) -> 0 | AP32: =SUMIF($D$3:$AM$3,"Actual",$D32:$AM32) -> 0 | AQ32: =SUMIF($D$3:$AM$3,"Forecast",$D32:$AM32) -> 0 | AR32: =AP32-AQ32 -> 0 | AV32: Tank Stream Labs | AW32: ? | AX32: 0 | AY32: 0 | AZ32: 0 | BA32: 0 | BB32: 0 | BC32: 0 | BD32: 0 | BE32: 0 | BF32: 0 | BG32: 0 | BH32: 0 | BI32: 0 | BJ32: 0 | BK32: 0 | BL32: 0 | BM32: 0 | BN32: 0 | BO32: 0 | BP32: 0 | BQ32: 0 | BR32: 0 | BS32: 0 | BT32: 0 | BU32: 0 | BV32: 0 | BW32: 0 | BX32: 0 | BY32: 0 | BZ32: 0 | CA32: 0 | CB32: 0 | CC32: 0 | CD32: 0 | CE32: 0 | CH32: =SUM(AX32:CE32) -> 0 | CY32: =SUM(CM32:CX32) -> 0 | DA32: =CM32 -> 0 | DB32: =CN32 -> 0 | DC32: =CO32 -> 0 | DD32: =CP32 -> 0 | DE32: =CQ32 -> 0 | DF32: =CR32 -> 0 | DG32: 0 | DH32: 0 | DI32: 0 | DJ32: 0 | DK32: 0 | DL32: 0 | DM32: =SUM(DA32:DL32) -> 0 | EE32: =SUM(DR32:EC32) -> 0 | EG32: =DR32 -> 0 | EH32: =DS32 -> 0 | EI32: =DT32 -> 0 | EJ32: =DU32 -> 0 | EK32: =DV32 -> 0 | EL32: =DW32 -> 0 | EM32: =DX32 -> 0 | EN32: =DY32 -> 0 | ... ER32: =EC32 -> 0 | ES32: =SUM(EG32:ER32) -> 0
A33: CONS | B33: TBC | C33: North Head Quarantine Station (AKA) | X33: =+W33-V33 -> 0 | AA33: =+Z33-Y33 -> 0 | AB33: 2000 | AD33: =+AC33-AB33 -> -2000 | AE33: 2000 | AG33: =+AF33-AE33 -> -2000 | AH33: 2000 | AJ33: =+AI33-AH33 -> -2000 | AM33: =+AL33-AK33 -> 0 | AN33: =SUMIF($D$3:$U$3,"Actual",$D33:$U33) -> 0 | AO33: =SUMIF($V$3:$AM$3,"Actual",$V33:$AM33) -> 0 | AP33: =SUMIF($D$3:$AM$3,"Actual",$D33:$AM33) -> 0 | AQ33: =SUMIF($D$3:$AM$3,"Forecast",$D33:$AM33) -> 6000 | AR33: =AP33-AQ33 -> -6000 | AV33: TBC | CH33: =SUM(AX33:CE33) -> 0 | CY33: =SUM(CM33:CX33) -> 0 | DA33: =CM33 -> 0 | DB33: =CN33 -> 0 | DC33: =CO33 -> 0 | DD33: =CP33 -> 0 | DE33: =CQ33 -> 0 | DF33: =CR33 -> 0 | DG33: 0 | DH33: 0 | DI33: 0 | DJ33: 0 | DK33: 0 | DL33: 0 | DM33: =SUM(DA33:DL33) -> 0 | EE33: =SUM(DR33:EC33) -> 0 | EG33: =DR33 -> 0 | EH33: =DS33 -> 0 | EI33: =DT33 -> 0 | EJ33: =DU33 -> 0 | EK33: =DV33 -> 0 | EL33: =DW33 -> 0 | EM33: =DX33 -> 0 | EN33: =DY33 -> 0 | ... ER33: =EC33 -> 0 | ES33: =SUM(EG33:ER33) -> 0
A34: CONS | B34: UNSW | C34: GUI Design Development | F34: =+E34-D34 -> 0 | G34: 1500 | I34: =+H34-G34 -> -1500 | J34: 1500 | L34: =+K34-J34 -> -1500 | O34: =+N34-M34 -> 0 | R34: =+Q34-P34 -> 0 | U34: =+T34-S34 -> 0 | X34: =+W34-V34 -> 0 | AA34: =+Z34-Y34 -> 0 | AD34: =+AC34-AB34 -> 0 | AE34: 2000 | AG34: =+AF34-AE34 -> -2000 | AJ34: =+AI34-AH34 -> 0 | AM34: =+AL34-AK34 -> 0 | AN34: =SUMIF($D$3:$U$3,"Actual",$D34:$U34) -> 0 | AO34: =SUMIF($V$3:$AM$3,"Actual",$V34:$AM34) -> 0 | AP34: =SUMIF($D$3:$AM$3,"Actual",$D34:$AM34) -> 0 | AQ34: =SUMIF($D$3:$AM$3,"Forecast",$D34:$AM34) -> 5000 | AR34: =AP34-AQ34 -> -5000 | AV34: UNSW | CH34: =SUM(AX34:CE34) -> 0 | CY34: =SUM(CM34:CX34) -> 0 | DA34: =CM34 -> 0 | DB34: =CN34 -> 0 | DC34: =CO34 -> 0 | DD34: =CP34 -> 0 | DE34: =CQ34 -> 0 | DF34: =CR34 -> 0 | DG34: 0 | DH34: 0 | DI34: 0 | DJ34: 0 | DK34: 0 | DL34: 0 | DM34: =SUM(DA34:DL34) -> 0 | EE34: =SUM(DR34:EC34) -> 0 | EG34: =DR34 -> 0 | EH34: =DS34 -> 0 | EI34: =DT34 -> 0 | EJ34: =DU34 -> 0 | EK34: =DV34 -> 0 | EL34: =DW34 -> 0 | EM34: =DX34 -> 0 | EN34: =DY34 -> 0 | ... ER34: =EC34 -> 0 | ES34: =SUM(EG34:ER34) -> 0
A35: CONS | B35: UNSW | C35: Consulting Services | D35: =20000/12 -> 1666.6667 | F35: =+E35-D35 -> -1666.6667 | G35: =20000/12 -> 1666.6667 | J35: =20000/12 -> 1666.6667 | L35: =+K35-J35 -> -1666.6667 | M35: =20000/12 -> 1666.6667 | O35: =+N35-M35 -> -1666.6667 | P35: =20000/12 -> 1666.6667 | R35: =+Q35-P35 -> -1666.6667 | S35: =20000/12 -> 1666.6667 | U35: =+T35-S35 -> -1666.6667 | V35: =20000/12 -> 1666.6667 | X35: =+W35-V35 -> -1666.6667 | Y35: =20000/12 -> 1666.6667 | AA35: =+Z35-Y35 -> -1666.6667 | AB35: =20000/12 -> 1666.6667 | AD35: =+AC35-AB35 -> -1666.6667 | AE35: =20000/12 -> 1666.6667 | AG35: =+AF35-AE35 -> -1666.6667 | AH35: =20000/12 -> 1666.6667 | AJ35: =+AI35-AH35 -> -1666.6667 | AK35: =20000/12 -> 1666.6667 | AM35: =+AL35-AK35 -> -1666.6667 | AN35: =SUMIF($D$3:$U$3,"Actual",$D35:$U35) -> 0 | AO35: =SUMIF($V$3:$AM$3,"Actual",$V35:$AM35) -> 0 | AP35: =SUMIF($D$3:$AM$3,"Actual",$D35:$AM35) -> 0 | AQ35: =SUMIF($D$3:$AM$3,"Forecast",$D35:$AM35) -> 20000 | AR35: =AP35-AQ35 -> -20000 | AV35: UNSW | AX35: 0 | BA35: 0 | BD35: 0 | BG35: 0 | BJ35: 0 | BM35: 0 | BP35: 0 | BS35: 0 | BV35: 1000 | BY35: 1000 | CB35: 1000 | CE35: 1000 | CH35: =SUM(AX35:CE35) -> 4000 | CY35: =SUM(CM35:CX35) -> 0 | DA35: =CM35 -> 0 | DB35: =CN35 -> 0 | DC35: =CO35 -> 0 | DD35: =CP35 -> 0 | DE35: =CQ35 -> 0 | DF35: =CR35 -> 0 | DG35: 0 | DH35: 0 | DI35: 0 | DJ35: 0 | DK35: 0 | DL35: 0 | DM35: =SUM(DA35:DL35) -> 0 | EE35: =SUM(DR35:EC35) -> 0 | EG35: =DR35 -> 0 | EH35: =DS35 -> 0 | EI35: =DT35 -> 0 | EJ35: =DU35 -> 0 | EK35: =DV35 -> 0 | EL35: =DW35 -> 0 | EM35: =DX35 -> 0 | EN35: =DY35 -> 0 | ... ER35: =EC35 -> 0 | ES35: =SUM(EG35:ER35) -> 0
A36: INT | B36: Westpac | C36: Box Sales | F36: =+E36-D36 -> 0 | I36: =+H36-G36 -> 0 | L36: =+K36-J36 -> 0 | O36: =+N36-M36 -> 0 | R36: =+Q36-P36 -> 0 | U36: =+T36-S36 -> 0 | X36: =+W36-V36 -> 0 | AA36: =+Z36-Y36 -> 0 | AD36: =+AC36-AB36 -> 0 | AG36: =+AF36-AE36 -> 0 | AJ36: =+AI36-AH36 -> 0 | AM36: =+AL36-AK36 -> 0 | AN36: =SUMIF($D$3:$U$3,"Actual",$D36:$U36) -> 0 | AO36: =SUMIF($V$3:$AM$3,"Actual",$V36:$AM36) -> 0 | AP36: =SUMIF($D$3:$AM$3,"Actual",$D36:$AM36) -> 0 | AQ36: =SUMIF($D$3:$AM$3,"Forecast",$D36:$AM36) -> 0 | AR36: =AP36-AQ36 -> 0 | AV36: Westpac | CH36: =SUM(AX36:CE36) -> 0 | CY36: =SUM(CM36:CX36) -> 0 | DA36: =CM36 -> 0 | DB36: =CN36 -> 0 | DC36: =CO36 -> 0 | DD36: =CP36 -> 0 | DE36: =CQ36 -> 0 | DF36: =CR36 -> 0 | DG36: 0 | DH36: 0 | DI36: 0 | DJ36: 0 | DK36: 0 | DL36: 0 | DM36: =SUM(DA36:DL36) -> 0 | EE36: =SUM(DR36:EC36) -> 0 | EG36: =DR36 -> 0 | EH36: =DS36 -> 0 | EI36: =DT36 -> 0 | EJ36: =DU36 -> 0 | EK36: =DV36 -> 0 | EL36: =DW36 -> 0 | EM36: =DX36 -> 0 | EN36: =DY36 -> 0 | ... ER36: =EC36 -> 0 | ES36: =SUM(EG36:ER36) -> 0
A37: CONS | B37: Westpac | C37: Unique Space Consulting | F37: =+E37-D37 -> 0 | I37: =+H37-G37 -> 0 | R37: =+Q37-P37 -> 0 | U37: =+T37-S37 -> 0 | X37: =+W37-V37 -> 0 | AA37: =+Z37-Y37 -> 0 | AD37: =+AC37-AB37 -> 0 | AG37: =+AF37-AE37 -> 0 | AJ37: =+AI37-AH37 -> 0 | AM37: =+AL37-AK37 -> 0 | AN37: =SUMIF($D$3:$U$3,"Actual",$D37:$U37) -> 0 | AO37: =SUMIF($V$3:$AM$3,"Actual",$V37:$AM37) -> 0 | AP37: =SUMIF($D$3:$AM$3,"Actual",$D37:$AM37) -> 0 | AQ37: =SUMIF($D$3:$AM$3,"Forecast",$D37:$AM37) -> 0 | AR37: =AP37-AQ37 -> 0 | AV37: Westpac | AW37: Consulting | AX37: 500 | BA37: 500 | BD37: 500 | BG37: 500 | BJ37: 500 | BM37: 500 | BP37: 500 | BS37: 500 | BV37: 500 | BY37: 500 | CB37: 500 | CE37: 500 | CH37: =SUM(AX37:CE37) -> 6000 | CY37: =SUM(CM37:CX37) -> 0 | DA37: =CM37 -> 0 | DB37: =CN37 -> 0 | DC37: =CO37 -> 0 | DD37: =CP37 -> 0 | DE37: =CQ37 -> 0 | DF37: =CR37 -> 0 | DG37: 0 | DH37: 0 | DI37: 0 | DJ37: 0 | DK37: 0 | DL37: 0 | DM37: =SUM(DA37:DL37) -> 0 | EE37: =SUM(DR37:EC37) -> 0 | EG37: =DR37 -> 0 | EH37: =DS37 -> 0 | EI37: =DT37 -> 0 | EJ37: =DU37 -> 0 | EK37: =DV37 -> 0 | EL37: =DW37 -> 0 | EM37: =DX37 -> 0 | EN37: =DY37 -> 0 | ... ER37: =EC37 -> 0 | ES37: =SUM(EG37:ER37) -> 0
C38: New Business MISC | D38: 12000 | F38: =+E38-D38 -> -12000 | G38: 12000 | I38: =+H38-G38 -> -12000 | J38: 12000 | L38: =+K38-J38 -> -12000 | M38: 12000 | O38: =+N38-M38 -> -12000 | P38: 12000 | R38: =+Q38-P38 -> -12000 | S38: 12000 | U38: =+T38-S38 -> -12000 | X38: =+W38-V38 -> 0 | Y38: 10000 | AA38: =+Z38-Y38 -> -10000 | AB38: 10000 | AD38: =+AC38-AB38 -> -10000 | AE38: 10000 | AG38: =+AF38-AE38 -> -10000 | AH38: 10000 | AJ38: =+AI38-AH38 -> -10000 | AK38: 10000 | AM38: =+AL38-AK38 -> -10000 | AN38: =SUMIF($D$3:$U$3,"Actual",$D38:$U38) -> 0 | AO38: =SUMIF($V$3:$AM$3,"Actual",$V38:$AM38) -> 0 | AP38: =SUMIF($D$3:$AM$3,"Actual",$D38:$AM38) -> 0 | AQ38: =SUMIF($D$3:$AM$3,"Forecast",$D38:$AM38) -> 122000 | AR38: =AP38-AQ38 -> -122000 | CH38: =SUM(AX38:CE38) -> 0 | CY38: =SUM(CM38:CX38) -> 0 | DA38: =CM38 -> 0 | DB38: =CN38 -> 0 | DC38: =CO38 -> 0 | DD38: =CP38 -> 0 | DE38: =CQ38 -> 0 | DF38: =CR38 -> 0 | DG38: 0 | DH38: 0 | DI38: 0 | DJ38: 0 | DK38: 0 | DL38: 0 | DM38: =SUM(DA38:DL38) -> 0 | EE38: =SUM(DR38:EC38) -> 0 | EG38: =DR38 -> 0 | EH38: =DS38 -> 0 | EI38: =DT38 -> 0 | EJ38: =DU38 -> 0 | EK38: =DV38 -> 0 | EL38: =DW38 -> 0 | EM38: =DX38 -> 0 | EN38: =DY38 -> 0 | ... ER38: =EC38 -> 0 | ES38: =SUM(EG38:ER38) -> 0
B39: Lendlease | C39: TBD | AH39: 5000 | AK39: 5000 | AN39: =SUMIF($D$3:$U$3,"Actual",$D39:$U39) -> 0 | AO39: =SUMIF($V$3:$AM$3,"Actual",$V39:$AM39) -> 0 | AP39: =SUMIF($D$3:$AM$3,"Actual",$D39:$AM39) -> 0 | AQ39: =SUMIF($D$3:$AM$3,"Forecast",$D39:$AM39) -> 10000 | AR39: =AP39-AQ39 -> -10000 | AV39: Lendlease | CH39: =SUM(AX39:CE39) -> 0 | CY39: =SUM(CM39:CX39) -> 0 | DA39: =CM39 -> 0 | DB39: =CN39 -> 0 | DC39: =CO39 -> 0 | DD39: =CP39 -> 0 | DE39: =CQ39 -> 0 | DF39: =CR39 -> 0 | DG39: 0 | DH39: 0 | DI39: 0 | DJ39: 0 | DK39: 0 | DL39: 0 | DM39: =SUM(DA39:DL39) -> 0 | EE39: =SUM(DR39:EC39) -> 0 | EG39: =DR39 -> 0 | EH39: =DS39 -> 0 | EI39: =DT39 -> 0 | EJ39: =DU39 -> 0 | EK39: =DV39 -> 0 | EL39: =DW39 -> 0 | EM39: =DX39 -> 0 | EN39: =DY39 -> 0 | ... ER39: =EC39 -> 0 | ES39: =SUM(EG39:ER39) -> 0
B40: Deutsche Bank | C40: TBD | AV40: Deutsche Bank | AW40: ? | AX40: 0 | AY40: 0 | AZ40: 0 | BA40: 0 | BB40: 0 | BC40: 0 | BD40: 0 | BE40: 0 | BF40: 0 | BG40: 0 | BH40: 0 | BI40: 0 | BJ40: 0 | BK40: 0 | BL40: 0 | BM40: 0 | BN40: 0 | BO40: 0 | BP40: 0 | BQ40: 0 | BR40: 0 | BS40: 0 | BT40: 0 | BU40: 0 | BV40: 0 | BW40: 0 | BX40: 0 | BY40: 0 | BZ40: 0 | CA40: 0 | CB40: 0 | CC40: 0 | CD40: 0 | CE40: 0 | CH40: =SUM(AX40:CE40) -> 0 | CY40: =SUM(CM40:CX40) -> 0 | DA40: =CM40 -> 0 | DB40: =CN40 -> 0 | DC40: =CO40 -> 0 | DD40: =CP40 -> 0 | DE40: =CQ40 -> 0 | DF40: =CR40 -> 0 | DG40: 0 | DH40: 0 | DI40: 0 | DJ40: 0 | DK40: 0 | DL40: 0 | DM40: =SUM(DA40:DL40) -> 0 | EE40: =SUM(DR40:EC40) -> 0 | EG40: =DR40 -> 0 | EH40: =DS40 -> 0 | EI40: =DT40 -> 0 | EJ40: =DU40 -> 0 | EK40: =DV40 -> 0 | EL40: =DW40 -> 0 | EM40: =DX40 -> 0 | EN40: =DY40 -> 0 | ... ER40: =EC40 -> 0 | ES40: =SUM(EG40:ER40) -> 0
B41: Macquarie | C41: TBD | AV41: Macquarie | AW41: ? | AX41: 0 | AY41: 0 | AZ41: 0 | BA41: 0 | BB41: 0 | BC41: 0 | BD41: 0 | BE41: 0 | BF41: 0 | BG41: 0 | BH41: 0 | BI41: 0 | BJ41: 0 | BK41: 0 | BL41: 0 | BM41: 0 | BN41: 0 | BO41: 0 | BP41: 0 | BQ41: 0 | BR41: 0 | BS41: 0 | BT41: 0 | BU41: 0 | BV41: 0 | BW41: 0 | BX41: 0 | BY41: 0 | BZ41: 0 | CA41: 0 | CB41: 0 | CC41: 0 | CD41: 0 | CE41: 0 | CH41: =SUM(AX41:CE41) -> 0 | CY41: =SUM(CM41:CX41) -> 0 | DA41: =CM41 -> 0 | DB41: =CN41 -> 0 | DC41: =CO41 -> 0 | DD41: =CP41 -> 0 | DE41: =CQ41 -> 0 | DF41: =CR41 -> 0 | DG41: 0 | DH41: 0 | DI41: 0 | DJ41: 0 | DK41: 0 | DL41: 0 | DM41: =SUM(DA41:DL41) -> 0 | EE41: =SUM(DR41:EC41) -> 0 | EG41: =DR41 -> 0 | EH41: =DS41 -> 0 | EI41: =DT41 -> 0 | EJ41: =DU41 -> 0 | EK41: =DV41 -> 0 | EL41: =DW41 -> 0 | EM41: =DX41 -> 0 | EN41: =DY41 -> 0 | ... ER41: =EC41 -> 0 | ES41: =SUM(EG41:ER41) -> 0
A42: INT | B42: NSW Property | C42: 4PSQ Proxyclick Visitor Management System | M42: 34585.14 | AV42: NSW Property | CH42: =SUM(AX42:CE42) -> 0 | CY42: =SUM(CM42:CX42) -> 0 | DA42: =CM42 -> 0 | DB42: =CN42 -> 0 | DC42: =CO42 -> 0 | DD42: =CP42 -> 0 | DE42: =CQ42 -> 0 | DF42: =CR42 -> 0 | DG42: 0 | DH42: 0 | DI42: 0 | DJ42: 0 | DK42: 0 | DL42: 0 | DM42: =SUM(DA42:DL42) -> 0 | EE42: =SUM(DR42:EC42) -> 0 | EG42: =DR42 -> 0 | EH42: =DS42 -> 0 | EI42: =DT42 -> 0 | EJ42: =DU42 -> 0 | EK42: =DV42 -> 0 | EL42: =DW42 -> 0 | EM42: =DX42 -> 0 | EN42: =DY42 -> 0 | ... ER42: =EC42 -> 0 | ES42: =SUM(EG42:ER42) -> 0
A43: INT | B43: NSW Gov | C43: NSW Gov Newcastle Visitor Management Solution | M43: 42324.2 | AV43: NSW Gov | CH43: =SUM(AX43:CE43) -> 0 | CY43: =SUM(CM43:CX43) -> 0 | DA43: =CM43 -> 0 | DB43: =CN43 -> 0 | DC43: =CO43 -> 0 | DD43: =CP43 -> 0 | DE43: =CQ43 -> 0 | DF43: =CR43 -> 0 | DG43: 0 | DH43: 0 | DI43: 0 | DJ43: 0 | DK43: 0 | DL43: 0 | DM43: =SUM(DA43:DL43) -> 0 | EE43: =SUM(DR43:EC43) -> 0 | EG43: =DR43 -> 0 | EH43: =DS43 -> 0 | EI43: =DT43 -> 0 | EJ43: =DU43 -> 0 | EK43: =DV43 -> 0 | EL43: =DW43 -> 0 | EM43: =DX43 -> 0 | EN43: =DY43 -> 0 | ... ER43: =EC43 -> 0 | ES43: =SUM(EG43:ER43) -> 0
A44: INT | B44: PWC | C44: PwC Sydney Shure ULXD - Mobile Studio | D44: 28795.33 | AV44: PWC | CH44: =SUM(AX44:CE44) -> 0 | CY44: =SUM(CM44:CX44) -> 0 | DA44: =CM44 -> 0 | DB44: =CN44 -> 0 | DC44: =CO44 -> 0 | DD44: =CP44 -> 0 | DE44: =CQ44 -> 0 | DF44: =CR44 -> 0 | DG44: 0 | DH44: 0 | DI44: 0 | DJ44: 0 | DK44: 0 | DL44: 0 | DM44: =SUM(DA44:DL44) -> 0 | EE44: =SUM(DR44:EC44) -> 0 | EG44: =DR44 -> 0 | EH44: =DS44 -> 0 | EI44: =DT44 -> 0 | EJ44: =DU44 -> 0 | EK44: =DV44 -> 0 | EL44: =DW44 -> 0 | EM44: =DX44 -> 0 | EN44: =DY44 -> 0 | ... ER44: =EC44 -> 0 | ES44: =SUM(EG44:ER44) -> 0
A45: CON | B45: WIN | C45: WIN TV Broadcast | J45: 33750 | AV45: WIN | CH45: =SUM(AX45:CE45) -> 0 | CY45: =SUM(CM45:CX45) -> 0 | DA45: =CM45 -> 0 | DB45: =CN45 -> 0 | DC45: =CO45 -> 0 | DD45: =CP45 -> 0 | DE45: =CQ45 -> 0 | DF45: =CR45 -> 0 | DG45: 0 | DH45: 0 | DI45: 0 | DJ45: 0 | DK45: 0 | DL45: 0 | DM45: =SUM(DA45:DL45) -> 0 | EE45: =SUM(DR45:EC45) -> 0 | EG45: =DR45 -> 0 | EH45: =DS45 -> 0 | EI45: =DT45 -> 0 | EJ45: =DU45 -> 0 | EK45: =DV45 -> 0 | EL45: =DW45 -> 0 | EM45: =DX45 -> 0 | EN45: =DY45 -> 0 | ... ER45: =EC45 -> 0 | ES45: =SUM(EG45:ER45) -> 0
A46: CON | B46: WIN | C46: C91 Radio project | M46: 11250 | AV46: WIN | CH46: =SUM(AX46:CE46) -> 0 | CY46: =SUM(CM46:CX46) -> 0 | DA46: =CM46 -> 0 | DB46: =CN46 -> 0 | DC46: =CO46 -> 0 | DD46: =CP46 -> 0 | DE46: =CQ46 -> 0 | DF46: =CR46 -> 0 | DG46: 0 | DH46: 0 | DI46: 0 | DJ46: 0 | DK46: 0 | DL46: 0 | DM46: =SUM(DA46:DL46) -> 0 | EE46: =SUM(DR46:EC46) -> 0 | EG46: =DR46 -> 0 | EH46: =DS46 -> 0 | EI46: =DT46 -> 0 | EJ46: =DU46 -> 0 | EK46: =DV46 -> 0 | EL46: =DW46 -> 0 | EM46: =DX46 -> 0 | EN46: =DY46 -> 0 | ... ER46: =EC46 -> 0 | ES46: =SUM(EG46:ER46) -> 0
A47: INT | B47: HP | C47: HP Melb 21 rooms | D47: 38125 | G47: 38125 | J47: 38125 | AV47: HP | AW47: Installs | AX47: 3000 | BA47: 3000 | BD47: 3000 | BG47: 3000 | BJ47: 3000 | BM47: 3000 | BP47: 3000 | BS47: 3000 | BV47: 3000 | BY47: 3000 | CB47: 3000 | CE47: 3000 | CH47: =SUM(AX47:CE47) -> 36000 | CY47: =SUM(CM47:CX47) -> 0 | DA47: =CM47 -> 0 | DB47: =CN47 -> 0 | DC47: =CO47 -> 0 | DD47: =CP47 -> 0 | DE47: =CQ47 -> 0 | DF47: =CR47 -> 0 | DG47: 0 | DH47: 0 | DI47: 0 | DJ47: 0 | DK47: 0 | DL47: 0 | DM47: =SUM(DA47:DL47) -> 0 | EE47: =SUM(DR47:EC47) -> 0 | EG47: =DR47 -> 0 | EH47: =DS47 -> 0 | EI47: =DT47 -> 0 | EJ47: =DU47 -> 0 | EK47: =DV47 -> 0 | EL47: =DW47 -> 0 | EM47: =DX47 -> 0 | EN47: =DY47 -> 0 | ... ER47: =EC47 -> 0 | ES47: =SUM(EG47:ER47) -> 0
A48: INT | B48: HP | C48: HP SYD 10 rooms | D48: 15000 | AV48: HP | AW48: Other | AX48: 5000 | BA48: 5000 | BD48: 5000 | BG48: 5000 | BJ48: 5000 | BM48: 5000 | BP48: 5000 | BS48: 5000 | BV48: 5000 | BY48: 5000 | CB48: 5000 | CE48: 5000 | CH48: =SUM(AX48:CE48) -> 60000 | CY48: =SUM(CM48:CX48) -> 0 | DA48: =CM48 -> 0 | DB48: =CN48 -> 0 | DC48: =CO48 -> 0 | DD48: =CP48 -> 0 | DE48: =CQ48 -> 0 | DF48: =CR48 -> 0 | DG48: 0 | DH48: 0 | DI48: 0 | DJ48: 0 | DK48: 0 | DL48: 0 | DM48: =SUM(DA48:DL48) -> 0 | EE48: =SUM(DR48:EC48) -> 0 | EG48: =DR48 -> 0 | EH48: =DS48 -> 0 | EI48: =DT48 -> 0 | EJ48: =DU48 -> 0 | EK48: =DV48 -> 0 | EL48: =DW48 -> 0 | EM48: =DX48 -> 0 | EN48: =DY48 -> 0 | ... ER48: =EC48 -> 0 | ES48: =SUM(EG48:ER48) -> 0
A49: INT | B49: HP | C49: HP TAS 6 rooms | D49: 15000 | AV49: HP | CH49: =SUM(AX49:CE49) -> 0 | CY49: =SUM(CM49:CX49) -> 0 | DA49: =CM49 -> 0 | DB49: =CN49 -> 0 | DC49: =CO49 -> 0 | DD49: =CP49 -> 0 | DE49: =CQ49 -> 0 | DF49: =CR49 -> 0 | DG49: 0 | DH49: 0 | DI49: 0 | DJ49: 0 | DK49: 0 | DL49: 0 | DM49: =SUM(DA49:DL49) -> 0 | EE49: =SUM(DR49:EC49) -> 0 | EG49: =DR49 -> 0 | EH49: =DS49 -> 0 | EI49: =DT49 -> 0 | EJ49: =DU49 -> 0 | EK49: =DV49 -> 0 | EL49: =DW49 -> 0 | EM49: =DX49 -> 0 | EN49: =DY49 -> 0 | ... ER49: =EC49 -> 0 | ES49: =SUM(EG49:ER49) -> 0
B50: APA | C50: Proxyclick Visitor Management Implementation | M50: 20000 | P50: 20000 | S50: 20000 | V50: 20000 | AV50: APA | AW50: Proxyclick | AX50: 5000 | BA50: 5000 | BD50: 5000 | BG50: 5000 | BJ50: 5000 | BM50: 5000 | BP50: 5000 | BS50: 5000 | BV50: 5000 | BY50: 5000 | CB50: 5000 | CE50: 5000 | CH50: =SUM(AX50:CE50) -> 60000 | CY50: =SUM(CM50:CX50) -> 0 | DA50: =CM50 -> 0 | DB50: =CN50 -> 0 | DC50: =CO50 -> 0 | DD50: =CP50 -> 0 | DE50: =CQ50 -> 0 | DF50: =CR50 -> 0 | DG50: 0 | DH50: 0 | DI50: 0 | DJ50: 0 | DK50: 0 | DL50: 0 | DM50: =SUM(DA50:DL50) -> 0 | EE50: =SUM(DR50:EC50) -> 0 | EG50: =DR50 -> 0 | EH50: =DS50 -> 0 | EI50: =DT50 -> 0 | EJ50: =DU50 -> 0 | EK50: =DV50 -> 0 | EL50: =DW50 -> 0 | EM50: =DX50 -> 0 | EN50: =DY50 -> 0 | ... ER50: =EC50 -> 0 | ES50: =SUM(EG50:ER50) -> 0
AV51: Stone & Chalk | AW51: Consulting | AX51: 2600 | BA51: 5000 | BD51: 0 | BG51: 1000 | BJ51: 1000 | BM51: 0 | BN51: 0 | BO51: 0 | BP51: 0 | BS51: 1000 | BV51: 1000 | BY51: 1000 | CB51: 1000 | CE51: 1000 | CH51: =SUM(AX51:CE51) -> 14600 | CY51: =SUM(CM51:CX51) -> 0 | DA51: =CM51 -> 0 | DB51: =CN51 -> 0 | DC51: =CO51 -> 0 | DD51: =CP51 -> 0 | DE51: =CQ51 -> 0 | DF51: =CR51 -> 0 | DG51: 0 | DH51: 0 | DI51: 0 | DJ51: 0 | DK51: 0 | DL51: 0 | DM51: =SUM(DA51:DL51) -> 0 | EE51: =SUM(DR51:EC51) -> 0 | EG51: =DR51 -> 0 | EH51: =DS51 -> 0 | EI51: =DT51 -> 0 | EJ51: =DU51 -> 0 | EK51: =DV51 -> 0 | EL51: =DW51 -> 0 | EM51: =DX51 -> 0 | EN51: =DY51 -> 0 | ... ER51: =EC51 -> 0 | ES51: =SUM(EG51:ER51) -> 0
AV52: Irwin Solutions | AW52: Consulting | AX52: 0 | BA52: 18000 | BD52: 0 | BE52: 0 | BF52: 0 | BG52: 0 | BH52: 0 | BI52: 0 | BJ52: 0 | BK52: 0 | BL52: 0 | BM52: 0 | BN52: 0 | BO52: 0 | BP52: 0 | BQ52: 0 | BR52: 0 | BS52: 0 | BT52: 0 | BU52: 0 | BV52: 0 | BW52: 0 | BX52: 0 | BY52: 0 | BZ52: 0 | CA52: 0 | CB52: 0 | CC52: 0 | CD52: 0 | CE52: 0 | CH52: =SUM(AX52:CE52) -> 18000 | CY52: =SUM(CM52:CX52) -> 0 | DA52: =CM52 -> 0 | DB52: =CN52 -> 0 | DC52: =CO52 -> 0 | DD52: =CP52 -> 0 | DE52: =CQ52 -> 0 | DF52: =CR52 -> 0 | DG52: 0 | DH52: 0 | DI52: 0 | DJ52: 0 | DK52: 0 | DL52: 0 | DM52: =SUM(DA52:DL52) -> 0 | EE52: =SUM(DR52:EC52) -> 0 | EG52: =DR52 -> 0 | EH52: =DS52 -> 0 | EI52: =DT52 -> 0 | EJ52: =DU52 -> 0 | EK52: =DV52 -> 0 | EL52: =DW52 -> 0 | EM52: =DX52 -> 0 | EN52: =DY52 -> 0 | ... ER52: =EC52 -> 0 | ES52: =SUM(EG52:ER52) -> 0
AV53: Corrs | AW53: Melbourne | AX53: 3000 | BA53: 3000 | BD53: 3000 | BG53: 3000 | BJ53: 3000 | BM53: 3000 | BP53: 3000 | BS53: 3000 | BV53: 3000 | BY53: 3000 | CB53: 3000 | CE53: 3000 | CH53: =SUM(AX53:CE53) -> 36000 | CY53: =SUM(CM53:CX53) -> 0 | DA53: =CM53 -> 0 | DB53: =CN53 -> 0 | DC53: =CO53 -> 0 | DD53: =CP53 -> 0 | DE53: =CQ53 -> 0 | DF53: =CR53 -> 0 | DG53: 0 | DH53: 0 | DI53: 0 | DJ53: 0 | DK53: 0 | DL53: 0 | DM53: =SUM(DA53:DL53) -> 0 | EE53: =SUM(DR53:EC53) -> 0 | EG53: =DR53 -> 0 | EH53: =DS53 -> 0 | EI53: =DT53 -> 0 | EJ53: =DU53 -> 0 | EK53: =DV53 -> 0 | EL53: =DW53 -> 0 | EM53: =DX53 -> 0 | EN53: =DY53 -> 0 | ... ER53: =EC53 -> 0 | ES53: =SUM(EG53:ER53) -> 0
AV54: Corrs | AW54: Perth | AX54: 1000 | BA54: 1000 | BD54: 1000 | BG54: 1000 | BJ54: 1000 | BM54: 1000 | BP54: 1000 | BS54: 1000 | BV54: 1000 | BY54: 1000 | CB54: 1000 | CE54: 1000 | CH54: =SUM(AX54:CE54) -> 12000 | CY54: =SUM(CM54:CX54) -> 0 | DA54: =CM54 -> 0 | DB54: =CN54 -> 0 | DC54: =CO54 -> 0 | DD54: =CP54 -> 0 | DE54: =CQ54 -> 0 | DF54: =CR54 -> 0 | DG54: 0 | DH54: 0 | DI54: 0 | DJ54: 0 | DK54: 0 | DL54: 0 | DM54: =SUM(DA54:DL54) -> 0 | EE54: =SUM(DR54:EC54) -> 0 | EG54: =DR54 -> 0 | EH54: =DS54 -> 0 | EI54: =DT54 -> 0 | EJ54: =DU54 -> 0 | EK54: =DV54 -> 0 | EL54: =DW54 -> 0 | EM54: =DX54 -> 0 | EN54: =DY54 -> 0 | ... ER54: =EC54 -> 0 | ES54: =SUM(EG54:ER54) -> 0
AV55: BTC Investment Group | AW55: Robyn's Nest | AX55: 0 | BA55: 0 | BD55: 0 | BG55: 7000 | BJ55: 0 | BM55: 0 | BP55: 0 | BS55: 0 | BV55: 0 | BY55: 0 | CB55: 0 | CE55: 0 | CH55: =SUM(AX55:CE55) -> 7000 | CY55: =SUM(CM55:CX55) -> 0 | DA55: =CM55 -> 0 | DB55: =CN55 -> 0 | DC55: =CO55 -> 0 | DD55: =CP55 -> 0 | DE55: =CQ55 -> 0 | DF55: =CR55 -> 0 | DG55: 0 | DH55: 0 | DI55: 0 | DJ55: 0 | DK55: 0 | DL55: 0 | DM55: =SUM(DA55:DL55) -> 0 | EE55: =SUM(DR55:EC55) -> 0 | EG55: =DR55 -> 0 | EH55: =DS55 -> 0 | EI55: =DT55 -> 0 | EJ55: =DU55 -> 0 | EK55: =DV55 -> 0 | EL55: =DW55 -> 0 | EM55: =DX55 -> 0 | EN55: =DY55 -> 0 | ... ER55: =EC55 -> 0 | ES55: =SUM(EG55:ER55) -> 0
CL56: Scentre Group | DC56: 6500 | DG56: 8700 | DH56: 0 | DI56: 0 | DJ56: 0 | DK56: 0 | DL56: 0 | EE56: =SUM(DR56:EC56) -> 0 | EG56: =DR56 -> 0 | EH56: =DS56 -> 0 | EI56: =DT56 -> 0 | EJ56: =DU56 -> 0 | EK56: =DV56 -> 0 | EL56: =DW56 -> 0 | EM56: =DX56 -> 0 | EN56: =DY56 -> 0 | ... ER56: =EC56 -> 0
CK57: CONS | CL57: New business N/E | CM57: 2500 | CN57: 2500 | CO57: 2500 | CP57: 2500 | CQ57: 2500 | CR57: 2500 | CS57: 2500 | CT57: 2500 | CU57: 2500 | CV57: 2500 | CW57: 2500 | CX57: 2500 | CY57: =SUM(CM57:CX57) -> 30000 | DA57: 6358.7 | DB57: 0 | DC57: 0 | DD57: 2030 | DF57: 568.79 | DG57: 0 | DH57: 0 | DI57: 0 | DJ57: 0 | DK57: 2500 | DL57: 2500 | DM57: =SUM(DA57:DL57) -> 13957.49 | EE57: =SUM(DR57:EC57) -> 0 | EG57: =DR57 -> 0 | EH57: =DS57 -> 0 | EI57: =DT57 -> 0 | EJ57: =DU57 -> 0 | EK57: =DV57 -> 0 | EL57: =DW57 -> 0 | EM57: =DX57 -> 0 | EN57: =DY57 -> 0 | ... ER57: =EC57 -> 0 | ES57: =SUM(EG57:ER57) -> 0
AV58: Sri Venkateswara Temple Function Hall | AW58: Sri Venkateswara Temple Function Hall | AX58: 0 | BA58: 0 | BD58: 5000 | BG58: 5000 | BJ58: 0 | BM58: 0 | BP58: 0 | BS58: 0 | BV58: 5000 | BY58: 5000 | CB58: 0 | CE58: 0 | CH58: =SUM(AX58:CE58) -> 20000 | CK58: INT | CL58: New business N/E | CM58: 2500 | CN58: 2500 | CO58: 2500 | CP58: 2500 | CQ58: 2500 | CR58: 2500 | CS58: 2500 | CT58: 2500 | CU58: 2500 | CV58: 2500 | CW58: 2500 | CX58: 2500 | CY58: =SUM(CM58:CX58) -> 30000 | DA58: 0 | DB58: 0 | DC58: 0 | DD58: 0 | DE58: 439.33 | DG58: 0 | DH58: 0 | DI58: 0 | DJ58: 0 | DK58: 2500 | DL58: 2500 | DM58: =SUM(DA58:DL58) -> 5439.33 | EE58: =SUM(DR58:EC58) -> 0 | EG58: =DR58 -> 0 | EH58: =DS58 -> 0 | EI58: =DT58 -> 0 | EJ58: =DU58 -> 0 | EK58: =DV58 -> 0 | EL58: =DW58 -> 0 | EM58: =DX58 -> 0 | EN58: =DY58 -> 0 | ... ER58: =EC58 -> 0 | ES58: =SUM(EG58:ER58) -> 0
CL59: Novigi | DE59: 652.5 | DF59: =1810-652.5 -> 1157.5 | DG59: 761.25 | DH59: 0 | DI59: 0 | DJ59: 0 | DK59: 0 | DL59: 0 | DM59: =SUM(DA59:DL59) -> 2571.25 | EE59: =SUM(DR59:EC59) -> 0 | EG59: =DR59 -> 0 | EH59: =DS59 -> 0 | EI59: =DT59 -> 0 | EJ59: =DU59 -> 0 | EK59: =DV59 -> 0 | EL59: =DW59 -> 0 | EM59: =DX59 -> 0 | EN59: =DY59 -> 0 | ... ER59: =EC59 -> 0 | ES59: =SUM(EG59:ER59) -> 0
CL60: National Pharmacies | DG60: 0 | DH60: 42348.57 | DI60: 0 | DJ60: 0 | DK60: 0 | DL60: 0 | DM60: =SUM(DA60:DL60) -> 42348.57 | EE60: =SUM(DR60:EC60) -> 0 | EG60: =DR60 -> 0 | EH60: =DS60 -> 0 | EI60: =DT60 -> 0 | EJ60: =DU60 -> 0 | EK60: =DV60 -> 0 | EL60: =DW60 -> 0 | EM60: =DX60 -> 0 | EN60: =DY60 -> 0 | ... ER60: =EC60 -> 0 | ES60: =SUM(EG60:ER60) -> 0
CL61: City of Sydney | DG61: 0 | DH61: 0 | DI61: 0 | DJ61: 0 | DK61: 0 | DL61: 125000 | DM61: =SUM(DA61:DL61) -> 125000 | EE61: =SUM(DR61:EC61) -> 0 | EG61: =DR61 -> 0 | EH61: =DS61 -> 0 | EI61: =DT61 -> 0 | EJ61: =DU61 -> 0 | EK61: =DV61 -> 0 | EL61: =DW61 -> 0 | EM61: =DX61 -> 0 | EN61: =DY61 -> 0 | ... ER61: =EC61 -> 0 | ES61: =SUM(EG61:ER61) -> 0
CL62: Conservatorium of Music | DG62: 0 | DH62: 0 | DI62: 0 | DJ62: 227.5 | DK62: 0 | DL62: 500000 | DM62: =SUM(DA62:DL62) -> 500227.5 | EE62: =SUM(DR62:EC62) -> 0 | EG62: =DR62 -> 0 | EH62: =DS62 -> 0 | EI62: =DT62 -> 0 | EJ62: =DU62 -> 0 | EK62: =DV62 -> 0 | EL62: =DW62 -> 0 | EM62: =DX62 -> 0 | EN62: =DY62 -> 0 | ... ER62: =EC62 -> 0 | ES62: =SUM(EG62:ER62) -> 0
CL63: Kirra | DG63: 0 | DH63: 0 | DI63: 0 | DJ63: 0 | DK63: 1500 | DL63: 1500 | DM63: =SUM(DA63:DL63) -> 3000 | EE63: =SUM(DR63:EC63) -> 0 | EG63: =DR63 -> 0 | EH63: =DS63 -> 0 | EI63: =DT63 -> 0 | EJ63: =DU63 -> 0 | EK63: =DV63 -> 0 | EL63: =DW63 -> 0 | EM63: =DX63 -> 0 | EN63: =DY63 -> 0 | ... ER63: =EC63 -> 0 | ES63: =SUM(EG63:ER63) -> 0
CL64: Woolworths | DG64: 0 | DH64: 0 | DI64: 0 | DJ64: 0 | DK64: 0 | DL64: 5000 | DM64: =SUM(DA64:DL64) -> 5000 | EE64: =SUM(DR64:EC64) -> 0 | EG64: =DR64 -> 0 | EH64: =DS64 -> 0 | EI64: =DT64 -> 0 | EJ64: =DU64 -> 0 | EK64: =DV64 -> 0 | EL64: =DW64 -> 0 | EM64: =DX64 -> 0 | EN64: =DY64 -> 0 | ... ER64: =EC64 -> 0 | ES64: =SUM(EG64:ER64) -> 0
CL65: Automic | DG65: 0 | DH65: 0 | DI65: 0 | DJ65: 0 | DK65: 0 | DL65: 200000 | DM65: =SUM(DA65:DL65) -> 200000 | EE65: =SUM(DR65:EC65) -> 0 | EG65: =DR65 -> 0 | EH65: =DS65 -> 0 | EI65: =DT65 -> 0 | EJ65: =DU65 -> 0 | EK65: =DV65 -> 0 | EL65: =DW65 -> 0 | EM65: =DX65 -> 0 | EN65: =DY65 -> 0 | ... ER65: =EC65 -> 0 | ES65: =SUM(EG65:ER65) -> 0
