Workbook

Sheet Read Me
A1: How to use the Revenue Risk Profile
A3: What it shows
A4: How much of this year's revenue is already earned, how much is signed, and how much still depends on pipeline. It shows what happens if pipeline does not come through, or if certain customers walk away. It does this for each department.
A6: Each month
A7: 1. Settings: change the last month of P&L actuals to the new month end.
A8: 2. P&L Dump: clear A7 to Z1006. Paste the Xero Profit and Loss from cell A7, account names in column A, months across. In row 5, pick the month for each pasted column.
A9: 3. Zoho Dump: clear columns A to J. Run the Zoho report All Deals by Stage and paste the whole export into cell A1, exactly as it comes out.
A10: 4. Adjustments: add signed or likely revenue that is not in Zoho, such as recurring support contracts.
A11: 5. Dashboard: check the Data checks box at the bottom. Every line should say OK.
A12: 6. Dashboard: pick customers to withdraw and set the stress case to show management the risk.
A14: Colours
A15: Yellow cells with blue text are inputs. Everything else is a formula. Do not type over formulas.
... A31: Revenue that is never entered in Zoho, like recurring contracts, only shows if it is added on Adjustments.

Sheet Dashboard
A1: Revenue Risk Profile
A2: ="Financial year "&TEXT(Settings!$B$4,"dd/mm/yyyy")&" to "&TEXT(Settings!$B$6,"dd/mm/yyyy")&". P&L actuals to "&TEXT(Settings!$B$5,"dd/mm/yyyy")&". Zoho export: "&MID('Zoho Dump'!$A$3,FIND(" on ",'Zoho Dump'!$A$3)+4,40) -> Financial year 01/07/2026 to 30/06/2027. P&L actuals to 30/09/2026. Zoho export: 12/10/2026 11:49 AM
A4: ="Base forecast for the year is "&TEXT(F33,"$#,##0")&". Signed so far (actuals plus backlog) is "&TEXT(B33+C33,"$#,##0")&"." -> Base forecast for the year is $853,202. Signed so far (actuals plus backlog) is $85,402.
A5: ="If no more pipeline comes through than the stress case below, revenue falls by "&TEXT(L33,"$#,##0")&"." -> If no more pipeline comes through than the stress case below, revenue falls by $767,800.
A6: ="The selected customers withdrawing would cost "&TEXT(M33,"$#,##0")&" of forward revenue. Both together leave "&TEXT(O33,"$#,##0")&" for the year." -> The selected customers withdrawing would cost $0 of forward revenue. Both together leave $85,402 for the year.
A7: ="Largest single customer: "&B37&", "&TEXT(F37,"0.0%")&" of all forward revenue. Top 10 customers: "&TEXT(G46,"0.0%")&"." -> Largest single customer: Commonwealth Bank Australia (CBA), 50.3% of all forward revenue. Top 10 customers: 85.2%.
A9: Scenario levers (yellow cells)
A10: Stress case: share of pipeline that still comes through | C10: 0
A11: 0% means no open deal lands. Backlog is kept in full.
A12: Customers who withdraw (pick from the list)
B13: 1
B14: 2
B15: 3
B16: 4
B17: 5
B18: 6
B19: 7
B20: 8
B21: 9
B22: 10
A23: A withdrawal removes that customer's backlog and pipeline for the rest of the year. It does not touch actuals already earned, or revenue that is not in Zoho or Adjustments.
A25: Department | B25: Actual to date (P&L) | C25: Backlog, signed | D25: Pipeline, full value | E25: Pipeline, weighted | F25: Base forecast for FY | G25: Budget for FY | H25: Forecast less budget | I25: Signed as % of budget | J25: Pipeline share of forward revenue | K25: If pipeline falls through | L25: Revenue at risk from pipeline | M25: Lost if selected customers withdraw | N25: Forecast after withdrawals | O25: Worst case: both | P25: Largest customer | Q25: Largest customer share | R25: Overdue Zoho deals, full value | S25: Won to date in Zoho (reference) | T25: Risk rating | V25: Budget score | W25: Concentration score | X25: Pipeline score
A26: =Settings!$A$12 -> Onsite | B26: =SUMIFS('Monthly Outlook'!$C$8:$N$8,'Monthly Outlook'!$C$5:$N$5,"Actual") -> 0 | C26: ='Monthly Outlook'!$O$18 -> 17000 | D26: =SUMIFS('Zoho Dump'!$Y$8:$Y$3007,'Zoho Dump'!$P$8:$P$3007,$A26,'Zoho Dump'!$T$8:$T$3007,"Pipeline")+SUMIFS(Adjustments!$L$8:$L$207,Adjustments!$A$8:$A$207,$A26,Adjustments!$H$8:$H$207,"Pipeline")+SUMIFS('Zoho Dump'!$Y$8:$Y$3007,'Zoho Dump'!$P$8:$P$3007,$A26,'Zoho Dump'!$T$8:$T$3007,"Overdue")+SUMIFS(Adjustments!$L$8:$L$207,Adjustments!$A$8:$A$207,$A26,Adjustments!$H$8:$H$207,"Overdue") -> 75000 | E26: ='Monthly Outlook'!$O$28 -> 52500 | F26: ='Monthly Outlook'!$O$38 -> 69500 | G26: ='Monthly Outlook'!$O$58 -> 0 | H26: =IF(G26=0,"No budget",F26-G26) -> No budget | I26: =IF(G26=0,"No budget",(B26+C26)/G26) -> No budget | J26: =IF(C26+E26=0,0,E26/(C26+E26)) -> 0.75539568 | K26: ='Monthly Outlook'!$O$48 -> 17000 | L26: =F26-K26 -> 52500 | M26: =SUMIFS('Zoho Dump'!$X$8:$X$3007,'Zoho Dump'!$P$8:$P$3007,$A26,'Zoho Dump'!$AA$8:$AA$3007,1)+SUMIFS(Adjustments!$K$8:$K$207,Adjustments!$A$8:$A$207,$A26,Adjustments!$N$8:$N$207,1) -> 0 | N26: =F26-M26 -> 69500 | O26: =K26-(SUMIFS('Zoho Dump'!$Z$8:$Z$3007,'Zoho Dump'!$P$8:$P$3007,$A26,'Zoho Dump'!$AA$8:$AA$3007,1)+SUMIFS(Adjustments!$M$8:$M$207,Adjustments!$A$8:$A$207,$A26,Adjustments!$N$8:$N$207,1)) -> 17000 | P26: =IF(MAX('Customer Risk'!$K$5:$K$404)=0,"-",INDEX('Customer Risk'!$B$5:$B$404,MATCH(MAX('Customer Risk'!$K$5:$K$404),'Customer Risk'!$K$5:$K$404,0))) -> Deloitte Australia | Q26: =IF(SUM('Customer Risk'!$K$5:$K$404)=0,0,MAX('Customer Risk'!$K$5:$K$404)/SUM('Customer Risk'!$K$5:$K$404)) -> 0.75539568 | R26: =SUMIFS('Zoho Dump'!$Q$8:$Q$3007,'Zoho Dump'!$P$8:$P$3007,$A26,'Zoho Dump'!$T$8:$T$3007,"Overdue")+SUMIFS(Adjustments!$G$8:$G$207,Adjustments!$A$8:$A$207,$A26,Adjustments!$H$8:$H$207,"Overdue") -> 137200 | S26: =SUMIFS('Zoho Dump'!$Q$8:$Q$3007,'Zoho Dump'!$P$8:$P$3007,$A26,'Zoho Dump'!$T$8:$T$3007,"Delivered",'Zoho Dump'!$R$8:$R$3007,">="&Settings!$B$4) -> 159259 | T26: =IF(AND(B26=0,F26=0),"-",CHOOSE(MAX(V26:X26)+1,"Low","Medium","High")) -> High | V26: =IF(G26=0,0,IF(F26<G26*(1-Settings!$C$54),2,IF(F26<G26*(1-Settings!$B$54),1,0))) -> 0 | W26: =IF(Q26>=Settings!$C$55,2,IF(Q26>=Settings!$B$55,1,0)) -> 2 | X26: =IF(J26>=Settings!$C$56,2,IF(J26>=Settings!$B$56,1,0)) -> 2
A27: =Settings!$A$13 -> Production | B27: =SUMIFS('Monthly Outlook'!$C$9:$N$9,'Monthly Outlook'!$C$5:$N$5,"Actual") -> 0 | C27: ='Monthly Outlook'!$O$19 -> 57060 | D27: =SUMIFS('Zoho Dump'!$Y$8:$Y$3007,'Zoho Dump'!$P$8:$P$3007,$A27,'Zoho Dump'!$T$8:$T$3007,"Pipeline")+SUMIFS(Adjustments!$L$8:$L$207,Adjustments!$A$8:$A$207,$A27,Adjustments!$H$8:$H$207,"Pipeline")+SUMIFS('Zoho Dump'!$Y$8:$Y$3007,'Zoho Dump'!$P$8:$P$3007,$A27,'Zoho Dump'!$T$8:$T$3007,"Overdue")+SUMIFS(Adjustments!$L$8:$L$207,Adjustments!$A$8:$A$207,$A27,Adjustments!$H$8:$H$207,"Overdue") -> 874626 | E27: ='Monthly Outlook'!$O$29 -> 645044.5 | F27: ='Monthly Outlook'!$O$39 -> 702104.5 | G27: ='Monthly Outlook'!$O$59 -> 0 | H27: =IF(G27=0,"No budget",F27-G27) -> No budget | I27: =IF(G27=0,"No budget",(B27+C27)/G27) -> No budget | J27: =IF(C27+E27=0,0,E27/(C27+E27)) -> 0.91873005 | K27: ='Monthly Outlook'!$O$49 -> 57060 | L27: =F27-K27 -> 645044.5 | M27: =SUMIFS('Zoho Dump'!$X$8:$X$3007,'Zoho Dump'!$P$8:$P$3007,$A27,'Zoho Dump'!$AA$8:$AA$3007,1)+SUMIFS(Adjustments!$K$8:$K$207,Adjustments!$A$8:$A$207,$A27,Adjustments!$N$8:$N$207,1) -> 0 | N27: =F27-M27 -> 702104.5 | O27: =K27-(SUMIFS('Zoho Dump'!$Z$8:$Z$3007,'Zoho Dump'!$P$8:$P$3007,$A27,'Zoho Dump'!$AA$8:$AA$3007,1)+SUMIFS(Adjustments!$M$8:$M$207,Adjustments!$A$8:$A$207,$A27,Adjustments!$N$8:$N$207,1)) -> 57060 | P27: =IF(MAX('Customer Risk'!$L$5:$L$404)=0,"-",INDEX('Customer Risk'!$B$5:$B$404,MATCH(MAX('Customer Risk'!$L$5:$L$404),'Customer Risk'!$L$5:$L$404,0))) -> Commonwealth Bank Australia (CBA) | Q27: =IF(SUM('Customer Risk'!$L$5:$L$404)=0,0,MAX('Customer Risk'!$L$5:$L$404)/SUM('Customer Risk'!$L$5:$L$404)) -> 0.61155569 | R27: =SUMIFS('Zoho Dump'!$Q$8:$Q$3007,'Zoho Dump'!$P$8:$P$3007,$A27,'Zoho Dump'!$T$8:$T$3007,"Overdue")+SUMIFS(Adjustments!$G$8:$G$207,Adjustments!$A$8:$A$207,$A27,Adjustments!$H$8:$H$207,"Overdue") -> 60795 | S27: =SUMIFS('Zoho Dump'!$Q$8:$Q$3007,'Zoho Dump'!$P$8:$P$3007,$A27,'Zoho Dump'!$T$8:$T$3007,"Delivered",'Zoho Dump'!$R$8:$R$3007,">="&Settings!$B$4) -> 478946 | T27: =IF(AND(B27=0,F27=0),"-",CHOOSE(MAX(V27:X27)+1,"Low","Medium","High")) -> High | V27: =IF(G27=0,0,IF(F27<G27*(1-Settings!$C$54),2,IF(F27<G27*(1-Settings!$B$54),1,0))) -> 0 | W27: =IF(Q27>=Settings!$C$55,2,IF(Q27>=Settings!$B$55,1,0)) -> 2 | X27: =IF(J27>=Settings!$C$56,2,IF(J27>=Settings!$B$56,1,0)) -> 2
A28: =Settings!$A$14 -> Video | B28: =SUMIFS('Monthly Outlook'!$C$10:$N$10,'Monthly Outlook'!$C$5:$N$5,"Actual") -> 0 | C28: ='Monthly Outlook'!$O$20 -> 11342 | D28: =SUMIFS('Zoho Dump'!$Y$8:$Y$3007,'Zoho Dump'!$P$8:$P$3007,$A28,'Zoho Dump'!$T$8:$T$3007,"Pipeline")+SUMIFS(Adjustments!$L$8:$L$207,Adjustments!$A$8:$A$207,$A28,Adjustments!$H$8:$H$207,"Pipeline")+SUMIFS('Zoho Dump'!$Y$8:$Y$3007,'Zoho Dump'!$P$8:$P$3007,$A28,'Zoho Dump'!$T$8:$T$3007,"Overdue")+SUMIFS(Adjustments!$L$8:$L$207,Adjustments!$A$8:$A$207,$A28,Adjustments!$H$8:$H$207,"Overdue") -> 1395 | E28: ='Monthly Outlook'!$O$30 -> 1255.5 | F28: ='Monthly Outlook'!$O$40 -> 12597.5 | G28: ='Monthly Outlook'!$O$60 -> 0 | H28: =IF(G28=0,"No budget",F28-G28) -> No budget | I28: =IF(G28=0,"No budget",(B28+C28)/G28) -> No budget | J28: =IF(C28+E28=0,0,E28/(C28+E28)) -> 0.099662631 | K28: ='Monthly Outlook'!$O$50 -> 11342 | L28: =F28-K28 -> 1255.5 | M28: =SUMIFS('Zoho Dump'!$X$8:$X$3007,'Zoho Dump'!$P$8:$P$3007,$A28,'Zoho Dump'!$AA$8:$AA$3007,1)+SUMIFS(Adjustments!$K$8:$K$207,Adjustments!$A$8:$A$207,$A28,Adjustments!$N$8:$N$207,1) -> 0 | N28: =F28-M28 -> 12597.5 | O28: =K28-(SUMIFS('Zoho Dump'!$Z$8:$Z$3007,'Zoho Dump'!$P$8:$P$3007,$A28,'Zoho Dump'!$AA$8:$AA$3007,1)+SUMIFS(Adjustments!$M$8:$M$207,Adjustments!$A$8:$A$207,$A28,Adjustments!$N$8:$N$207,1)) -> 11342 | P28: =IF(MAX('Customer Risk'!$M$5:$M$404)=0,"-",INDEX('Customer Risk'!$B$5:$B$404,MATCH(MAX('Customer Risk'!$M$5:$M$404),'Customer Risk'!$M$5:$M$404,0))) -> ASX Refinitiv Charity Foundation Ltd | Q28: =IF(SUM('Customer Risk'!$M$5:$M$404)=0,0,MAX('Customer Risk'!$M$5:$M$404)/SUM('Customer Risk'!$M$5:$M$404)) -> 0.70101211 | R28: =SUMIFS('Zoho Dump'!$Q$8:$Q$3007,'Zoho Dump'!$P$8:$P$3007,$A28,'Zoho Dump'!$T$8:$T$3007,"Overdue")+SUMIFS(Adjustments!$G$8:$G$207,Adjustments!$A$8:$A$207,$A28,Adjustments!$H$8:$H$207,"Overdue") -> 0 | S28: =SUMIFS('Zoho Dump'!$Q$8:$Q$3007,'Zoho Dump'!$P$8:$P$3007,$A28,'Zoho Dump'!$T$8:$T$3007,"Delivered",'Zoho Dump'!$R$8:$R$3007,">="&Settings!$B$4) -> 6401 | T28: =IF(AND(B28=0,F28=0),"-",CHOOSE(MAX(V28:X28)+1,"Low","Medium","High")) -> High | V28: =IF(G28=0,0,IF(F28<G28*(1-Settings!$C$54),2,IF(F28<G28*(1-Settings!$B$54),1,0))) -> 0 | W28: =IF(Q28>=Settings!$C$55,2,IF(Q28>=Settings!$B$55,1,0)) -> 2 | X28: =IF(J28>=Settings!$C$56,2,IF(J28>=Settings!$B$56,1,0)) -> 0
A29: =Settings!$A$15 -> Consulting | B29: =SUMIFS('Monthly Outlook'!$C$11:$N$11,'Monthly Outlook'!$C$5:$N$5,"Actual") -> 0 | C29: ='Monthly Outlook'!$O$21 -> 0 | D29: =SUMIFS('Zoho Dump'!$Y$8:$Y$3007,'Zoho Dump'!$P$8:$P$3007,$A29,'Zoho Dump'!$T$8:$T$3007,"Pipeline")+SUMIFS(Adjustments!$L$8:$L$207,Adjustments!$A$8:$A$207,$A29,Adjustments!$H$8:$H$207,"Pipeline")+SUMIFS('Zoho Dump'!$Y$8:$Y$3007,'Zoho Dump'!$P$8:$P$3007,$A29,'Zoho Dump'!$T$8:$T$3007,"Overdue")+SUMIFS(Adjustments!$L$8:$L$207,Adjustments!$A$8:$A$207,$A29,Adjustments!$H$8:$H$207,"Overdue") -> 75000 | E29: ='Monthly Outlook'!$O$31 -> 15000 | F29: ='Monthly Outlook'!$O$41 -> 15000 | G29: ='Monthly Outlook'!$O$61 -> 0 | H29: =IF(G29=0,"No budget",F29-G29) -> No budget | I29: =IF(G29=0,"No budget",(B29+C29)/G29) -> No budget | J29: =IF(C29+E29=0,0,E29/(C29+E29)) -> 1 | K29: ='Monthly Outlook'!$O$51 -> 0 | L29: =F29-K29 -> 15000 | M29: =SUMIFS('Zoho Dump'!$X$8:$X$3007,'Zoho Dump'!$P$8:$P$3007,$A29,'Zoho Dump'!$AA$8:$AA$3007,1)+SUMIFS(Adjustments!$K$8:$K$207,Adjustments!$A$8:$A$207,$A29,Adjustments!$N$8:$N$207,1) -> 0 | N29: =F29-M29 -> 15000 | O29: =K29-(SUMIFS('Zoho Dump'!$Z$8:$Z$3007,'Zoho Dump'!$P$8:$P$3007,$A29,'Zoho Dump'!$AA$8:$AA$3007,1)+SUMIFS(Adjustments!$M$8:$M$207,Adjustments!$A$8:$A$207,$A29,Adjustments!$N$8:$N$207,1)) -> 0 | P29: =IF(MAX('Customer Risk'!$N$5:$N$404)=0,"-",INDEX('Customer Risk'!$B$5:$B$404,MATCH(MAX('Customer Risk'!$N$5:$N$404),'Customer Risk'!$N$5:$N$404,0))) -> Hills Grammar | Q29: =IF(SUM('Customer Risk'!$N$5:$N$404)=0,0,MAX('Customer Risk'!$N$5:$N$404)/SUM('Customer Risk'!$N$5:$N$404)) -> 1 | R29: =SUMIFS('Zoho Dump'!$Q$8:$Q$3007,'Zoho Dump'!$P$8:$P$3007,$A29,'Zoho Dump'!$T$8:$T$3007,"Overdue")+SUMIFS(Adjustments!$G$8:$G$207,Adjustments!$A$8:$A$207,$A29,Adjustments!$H$8:$H$207,"Overdue") -> 3000 | S29: =SUMIFS('Zoho Dump'!$Q$8:$Q$3007,'Zoho Dump'!$P$8:$P$3007,$A29,'Zoho Dump'!$T$8:$T$3007,"Delivered",'Zoho Dump'!$R$8:$R$3007,">="&Settings!$B$4) -> 53469 | T29: =IF(AND(B29=0,F29=0),"-",CHOOSE(MAX(V29:X29)+1,"Low","Medium","High")) -> High | V29: =IF(G29=0,0,IF(F29<G29*(1-Settings!$C$54),2,IF(F29<G29*(1-Settings!$B$54),1,0))) -> 0 | W29: =IF(Q29>=Settings!$C$55,2,IF(Q29>=Settings!$B$55,1,0)) -> 2 | X29: =IF(J29>=Settings!$C$56,2,IF(J29>=Settings!$B$56,1,0)) -> 2
A30: =Settings!$A$16 -> Integration | B30: =SUMIFS('Monthly Outlook'!$C$12:$N$12,'Monthly Outlook'!$C$5:$N$5,"Actual") -> 0 | C30: ='Monthly Outlook'!$O$22 -> 0 | D30: =SUMIFS('Zoho Dump'!$Y$8:$Y$3007,'Zoho Dump'!$P$8:$P$3007,$A30,'Zoho Dump'!$T$8:$T$3007,"Pipeline")+SUMIFS(Adjustments!$L$8:$L$207,Adjustments!$A$8:$A$207,$A30,Adjustments!$H$8:$H$207,"Pipeline")+SUMIFS('Zoho Dump'!$Y$8:$Y$3007,'Zoho Dump'!$P$8:$P$3007,$A30,'Zoho Dump'!$T$8:$T$3007,"Overdue")+SUMIFS(Adjustments!$L$8:$L$207,Adjustments!$A$8:$A$207,$A30,Adjustments!$H$8:$H$207,"Overdue") -> 98456 | E30: ='Monthly Outlook'!$O$32 -> 53999.7 | F30: ='Monthly Outlook'!$O$42 -> 53999.7 | G30: ='Monthly Outlook'!$O$62 -> 0 | H30: =IF(G30=0,"No budget",F30-G30) -> No budget | I30: =IF(G30=0,"No budget",(B30+C30)/G30) -> No budget | J30: =IF(C30+E30=0,0,E30/(C30+E30)) -> 1 | K30: ='Monthly Outlook'!$O$52 -> 0 | L30: =F30-K30 -> 53999.7 | M30: =SUMIFS('Zoho Dump'!$X$8:$X$3007,'Zoho Dump'!$P$8:$P$3007,$A30,'Zoho Dump'!$AA$8:$AA$3007,1)+SUMIFS(Adjustments!$K$8:$K$207,Adjustments!$A$8:$A$207,$A30,Adjustments!$N$8:$N$207,1) -> 0 | N30: =F30-M30 -> 53999.7 | O30: =K30-(SUMIFS('Zoho Dump'!$Z$8:$Z$3007,'Zoho Dump'!$P$8:$P$3007,$A30,'Zoho Dump'!$AA$8:$AA$3007,1)+SUMIFS(Adjustments!$M$8:$M$207,Adjustments!$A$8:$A$207,$A30,Adjustments!$N$8:$N$207,1)) -> 0 | P30: =IF(MAX('Customer Risk'!$O$5:$O$404)=0,"-",INDEX('Customer Risk'!$B$5:$B$404,MATCH(MAX('Customer Risk'!$O$5:$O$404),'Customer Risk'!$O$5:$O$404,0))) -> Aware Super | Q30: =IF(SUM('Customer Risk'!$O$5:$O$404)=0,0,MAX('Customer Risk'!$O$5:$O$404)/SUM('Customer Risk'!$O$5:$O$404)) -> 0.3823762 | R30: =SUMIFS('Zoho Dump'!$Q$8:$Q$3007,'Zoho Dump'!$P$8:$P$3007,$A30,'Zoho Dump'!$T$8:$T$3007,"Overdue")+SUMIFS(Adjustments!$G$8:$G$207,Adjustments!$A$8:$A$207,$A30,Adjustments!$H$8:$H$207,"Overdue") -> 0 | S30: =SUMIFS('Zoho Dump'!$Q$8:$Q$3007,'Zoho Dump'!$P$8:$P$3007,$A30,'Zoho Dump'!$T$8:$T$3007,"Delivered",'Zoho Dump'!$R$8:$R$3007,">="&Settings!$B$4) -> 181846 | T30: =IF(AND(B30=0,F30=0),"-",CHOOSE(MAX(V30:X30)+1,"Low","Medium","High")) -> High | V30: =IF(G30=0,0,IF(F30<G30*(1-Settings!$C$54),2,IF(F30<G30*(1-Settings!$B$54),1,0))) -> 0 | W30: =IF(Q30>=Settings!$C$55,2,IF(Q30>=Settings!$B$55,1,0)) -> 1 | X30: =IF(J30>=Settings!$C$56,2,IF(J30>=Settings!$B$56,1,0)) -> 2
A31: =Settings!$A$17 -> Admin | B31: =SUMIFS('Monthly Outlook'!$C$13:$N$13,'Monthly Outlook'!$C$5:$N$5,"Actual") -> 0 | C31: ='Monthly Outlook'!$O$23 -> 0 | D31: =SUMIFS('Zoho Dump'!$Y$8:$Y$3007,'Zoho Dump'!$P$8:$P$3007,$A31,'Zoho Dump'!$T$8:$T$3007,"Pipeline")+SUMIFS(Adjustments!$L$8:$L$207,Adjustments!$A$8:$A$207,$A31,Adjustments!$H$8:$H$207,"Pipeline")+SUMIFS('Zoho Dump'!$Y$8:$Y$3007,'Zoho Dump'!$P$8:$P$3007,$A31,'Zoho Dump'!$T$8:$T$3007,"Overdue")+SUMIFS(Adjustments!$L$8:$L$207,Adjustments!$A$8:$A$207,$A31,Adjustments!$H$8:$H$207,"Overdue") -> 0 | E31: ='Monthly Outlook'!$O$33 -> 0 | F31: ='Monthly Outlook'!$O$43 -> 0 | G31: ='Monthly Outlook'!$O$63 -> 0 | H31: =IF(G31=0,"No budget",F31-G31) -> No budget | I31: =IF(G31=0,"No budget",(B31+C31)/G31) -> No budget | J31: =IF(C31+E31=0,0,E31/(C31+E31)) -> 0 | K31: ='Monthly Outlook'!$O$53 -> 0 | L31: =F31-K31 -> 0 | M31: =SUMIFS('Zoho Dump'!$X$8:$X$3007,'Zoho Dump'!$P$8:$P$3007,$A31,'Zoho Dump'!$AA$8:$AA$3007,1)+SUMIFS(Adjustments!$K$8:$K$207,Adjustments!$A$8:$A$207,$A31,Adjustments!$N$8:$N$207,1) -> 0 | N31: =F31-M31 -> 0 | O31: =K31-(SUMIFS('Zoho Dump'!$Z$8:$Z$3007,'Zoho Dump'!$P$8:$P$3007,$A31,'Zoho Dump'!$AA$8:$AA$3007,1)+SUMIFS(Adjustments!$M$8:$M$207,Adjustments!$A$8:$A$207,$A31,Adjustments!$N$8:$N$207,1)) -> 0 | P31: =IF(MAX('Customer Risk'!$P$5:$P$404)=0,"-",INDEX('Customer Risk'!$B$5:$B$404,MATCH(MAX('Customer Risk'!$P$5:$P$404),'Customer Risk'!$P$5:$P$404,0))) -> - | Q31: =IF(SUM('Customer Risk'!$P$5:$P$404)=0,0,MAX('Customer Risk'!$P$5:$P$404)/SUM('Customer Risk'!$P$5:$P$404)) -> 0 | R31: =SUMIFS('Zoho Dump'!$Q$8:$Q$3007,'Zoho Dump'!$P$8:$P$3007,$A31,'Zoho Dump'!$T$8:$T$3007,"Overdue")+SUMIFS(Adjustments!$G$8:$G$207,Adjustments!$A$8:$A$207,$A31,Adjustments!$H$8:$H$207,"Overdue") -> 0 | S31: =SUMIFS('Zoho Dump'!$Q$8:$Q$3007,'Zoho Dump'!$P$8:$P$3007,$A31,'Zoho Dump'!$T$8:$T$3007,"Delivered",'Zoho Dump'!$R$8:$R$3007,">="&Settings!$B$4) -> 0 | T31: =IF(AND(B31=0,F31=0),"-",CHOOSE(MAX(V31:X31)+1,"Low","Medium","High")) -> - | V31: =IF(G31=0,0,IF(F31<G31*(1-Settings!$C$54),2,IF(F31<G31*(1-Settings!$B$54),1,0))) -> 0 | W31: =IF(Q31>=Settings!$C$55,2,IF(Q31>=Settings!$B$55,1,0)) -> 0 | X31: =IF(J31>=Settings!$C$56,2,IF(J31>=Settings!$B$56,1,0)) -> 0
A32: =Settings!$A$18 -> Unallocated | B32: =SUMIFS('Monthly Outlook'!$C$14:$N$14,'Monthly Outlook'!$C$5:$N$5,"Actual") -> 0 | C32: ='Monthly Outlook'!$O$24 -> 0 | D32: =SUMIFS('Zoho Dump'!$Y$8:$Y$3007,'Zoho Dump'!$P$8:$P$3007,$A32,'Zoho Dump'!$T$8:$T$3007,"Pipeline")+SUMIFS(Adjustments!$L$8:$L$207,Adjustments!$A$8:$A$207,$A32,Adjustments!$H$8:$H$207,"Pipeline")+SUMIFS('Zoho Dump'!$Y$8:$Y$3007,'Zoho Dump'!$P$8:$P$3007,$A32,'Zoho Dump'!$T$8:$T$3007,"Overdue")+SUMIFS(Adjustments!$L$8:$L$207,Adjustments!$A$8:$A$207,$A32,Adjustments!$H$8:$H$207,"Overdue") -> 0 | E32: ='Monthly Outlook'!$O$34 -> 0 | F32: ='Monthly Outlook'!$O$44 -> 0 | G32: ='Monthly Outlook'!$O$64 -> 0 | H32: =IF(G32=0,"No budget",F32-G32) -> No budget | I32: =IF(G32=0,"No budget",(B32+C32)/G32) -> No budget | J32: =IF(C32+E32=0,0,E32/(C32+E32)) -> 0 | K32: ='Monthly Outlook'!$O$54 -> 0 | L32: =F32-K32 -> 0 | M32: =SUMIFS('Zoho Dump'!$X$8:$X$3007,'Zoho Dump'!$P$8:$P$3007,$A32,'Zoho Dump'!$AA$8:$AA$3007,1)+SUMIFS(Adjustments!$K$8:$K$207,Adjustments!$A$8:$A$207,$A32,Adjustments!$N$8:$N$207,1) -> 0 | N32: =F32-M32 -> 0 | O32: =K32-(SUMIFS('Zoho Dump'!$Z$8:$Z$3007,'Zoho Dump'!$P$8:$P$3007,$A32,'Zoho Dump'!$AA$8:$AA$3007,1)+SUMIFS(Adjustments!$M$8:$M$207,Adjustments!$A$8:$A$207,$A32,Adjustments!$N$8:$N$207,1)) -> 0 | P32: =IF(MAX('Customer Risk'!$Q$5:$Q$404)=0,"-",INDEX('Customer Risk'!$B$5:$B$404,MATCH(MAX('Customer Risk'!$Q$5:$Q$404),'Customer Risk'!$Q$5:$Q$404,0))) -> - | Q32: =IF(SUM('Customer Risk'!$Q$5:$Q$404)=0,0,MAX('Customer Risk'!$Q$5:$Q$404)/SUM('Customer Risk'!$Q$5:$Q$404)) -> 0 | R32: =SUMIFS('Zoho Dump'!$Q$8:$Q$3007,'Zoho Dump'!$P$8:$P$3007,$A32,'Zoho Dump'!$T$8:$T$3007,"Overdue")+SUMIFS(Adjustments!$G$8:$G$207,Adjustments!$A$8:$A$207,$A32,Adjustments!$H$8:$H$207,"Overdue") -> 0 | S32: =SUMIFS('Zoho Dump'!$Q$8:$Q$3007,'Zoho Dump'!$P$8:$P$3007,$A32,'Zoho Dump'!$T$8:$T$3007,"Delivered",'Zoho Dump'!$R$8:$R$3007,">="&Settings!$B$4) -> 0 | T32: =IF(AND(B32=0,F32=0),"-",CHOOSE(MAX(V32:X32)+1,"Low","Medium","High")) -> - | V32: =IF(G32=0,0,IF(F32<G32*(1-Settings!$C$54),2,IF(F32<G32*(1-Settings!$B$54),1,0))) -> 0 | W32: =IF(Q32>=Settings!$C$55,2,IF(Q32>=Settings!$B$55,1,0)) -> 0 | X32: =IF(J32>=Settings!$C$56,2,IF(J32>=Settings!$B$56,1,0)) -> 0
A33: Total | B33: =SUM(B26:B32) -> 0 | C33: =SUM(C26:C32) -> 85402 | D33: =SUM(D26:D32) -> 1124477 | E33: =SUM(E26:E32) -> 767799.7 | F33: =SUM(F26:F32) -> 853201.7 | G33: =SUM(G26:G32) -> 0 | H33: =IF(G33=0,"No budget",F33-G33) -> No budget | I33: =IF(G33=0,"No budget",(B33+C33)/G33) -> No budget | J33: =IF(C33+E33=0,0,E33/(C33+E33)) -> 0.89990409 | K33: =SUM(K26:K32) -> 85402 | L33: =SUM(L26:L32) -> 767799.7 | M33: =SUM(M26:M32) -> 0 | N33: =SUM(N26:N32) -> 853201.7 | O33: =SUM(O26:O32) -> 85402 | P33: =B37 -> Commonwealth Bank Australia (CBA) | Q33: =F37 -> 0.50325263 | R33: =SUM(R26:R32) -> 200995 | S33: =SUM(S26:S32) -> 879921
A35: Top 10 customers by forward revenue
A36: Rank | B36: Customer | C36: Backlog, signed | D36: Pipeline, weighted | E36: Forward revenue | F36: Share of all forward revenue | G36: Cumulative share | H36: Withdrawn in scenario
A37: 1 | B37: =IFERROR(INDEX('Customer Risk'!$B$5:$B$404,MATCH(LARGE('Customer Risk'!$R$5:$R$404,1),'Customer Risk'!$R$5:$R$404,0)),"") -> Commonwealth Bank Australia (CBA) | C37: =IFERROR(INDEX('Customer Risk'!$D$5:$D$404,MATCH(LARGE('Customer Risk'!$R$5:$R$404,1),'Customer Risk'!$R$5:$R$404,0)),0) -> 0 | D37: =IFERROR(INDEX('Customer Risk'!$F$5:$F$404,MATCH(LARGE('Customer Risk'!$R$5:$R$404,1),'Customer Risk'!$R$5:$R$404,0)),0) -> 429376 | E37: =IFERROR(INDEX('Customer Risk'!$G$5:$G$404,MATCH(LARGE('Customer Risk'!$R$5:$R$404,1),'Customer Risk'!$R$5:$R$404,0)),0) -> 429376 | F37: =IFERROR(INDEX('Customer Risk'!$H$5:$H$404,MATCH(LARGE('Customer Risk'!$R$5:$R$404,1),'Customer Risk'!$R$5:$R$404,0)),0) -> 0.50325263 | G37: =SUM($F$37:F37) -> 0.50325263 | H37: =IFERROR(INDEX('Customer Risk'!$J$5:$J$404,MATCH(LARGE('Customer Risk'!$R$5:$R$404,1),'Customer Risk'!$R$5:$R$404,0)),"")
A38: 2 | B38: =IFERROR(INDEX('Customer Risk'!$B$5:$B$404,MATCH(LARGE('Customer Risk'!$R$5:$R$404,2),'Customer Risk'!$R$5:$R$404,0)),"") -> MUFG IR / Orient Capital | C38: =IFERROR(INDEX('Customer Risk'!$D$5:$D$404,MATCH(LARGE('Customer Risk'!$R$5:$R$404,2),'Customer Risk'!$R$5:$R$404,0)),0) -> 0 | D38: =IFERROR(INDEX('Customer Risk'!$F$5:$F$404,MATCH(LARGE('Customer Risk'!$R$5:$R$404,2),'Customer Risk'!$R$5:$R$404,0)),0) -> 74751.4 | E38: =IFERROR(INDEX('Customer Risk'!$G$5:$G$404,MATCH(LARGE('Customer Risk'!$R$5:$R$404,2),'Customer Risk'!$R$5:$R$404,0)),0) -> 74751.4 | F38: =IFERROR(INDEX('Customer Risk'!$H$5:$H$404,MATCH(LARGE('Customer Risk'!$R$5:$R$404,2),'Customer Risk'!$R$5:$R$404,0)),0) -> 0.087612812 | G38: =SUM($F$37:F38) -> 0.59086544 | H38: =IFERROR(INDEX('Customer Risk'!$J$5:$J$404,MATCH(LARGE('Customer Risk'!$R$5:$R$404,2),'Customer Risk'!$R$5:$R$404,0)),"")
A39: 3 | B39: =IFERROR(INDEX('Customer Risk'!$B$5:$B$404,MATCH(LARGE('Customer Risk'!$R$5:$R$404,3),'Customer Risk'!$R$5:$R$404,0)),"") -> Deloitte Australia | C39: =IFERROR(INDEX('Customer Risk'!$D$5:$D$404,MATCH(LARGE('Customer Risk'!$R$5:$R$404,3),'Customer Risk'!$R$5:$R$404,0)),0) -> 0 | D39: =IFERROR(INDEX('Customer Risk'!$F$5:$F$404,MATCH(LARGE('Customer Risk'!$R$5:$R$404,3),'Customer Risk'!$R$5:$R$404,0)),0) -> 53012.5 | E39: =IFERROR(INDEX('Customer Risk'!$G$5:$G$404,MATCH(LARGE('Customer Risk'!$R$5:$R$404,3),'Customer Risk'!$R$5:$R$404,0)),0) -> 53012.5 | F39: =IFERROR(INDEX('Customer Risk'!$H$5:$H$404,MATCH(LARGE('Customer Risk'!$R$5:$R$404,3),'Customer Risk'!$R$5:$R$404,0)),0) -> 0.062133608 | G39: =SUM($F$37:F39) -> 0.65299905 | H39: =IFERROR(INDEX('Customer Risk'!$J$5:$J$404,MATCH(LARGE('Customer Risk'!$R$5:$R$404,3),'Customer Risk'!$R$5:$R$404,0)),"")
A40: 4 | B40: =IFERROR(INDEX('Customer Risk'!$B$5:$B$404,MATCH(LARGE('Customer Risk'!$R$5:$R$404,4),'Customer Risk'!$R$5:$R$404,0)),"") -> Automic Group | C40: =IFERROR(INDEX('Customer Risk'!$D$5:$D$404,MATCH(LARGE('Customer Risk'!$R$5:$R$404,4),'Customer Risk'!$R$5:$R$404,0)),0) -> 0 | D40: =IFERROR(INDEX('Customer Risk'!$F$5:$F$404,MATCH(LARGE('Customer Risk'!$R$5:$R$404,4),'Customer Risk'!$R$5:$R$404,0)),0) -> 40654.7 | E40: =IFERROR(INDEX('Customer Risk'!$G$5:$G$404,MATCH(LARGE('Customer Risk'!$R$5:$R$404,4),'Customer Risk'!$R$5:$R$404,0)),0) -> 40654.7 | F40: =IFERROR(INDEX('Customer Risk'!$H$5:$H$404,MATCH(LARGE('Customer Risk'!$R$5:$R$404,4),'Customer Risk'!$R$5:$R$404,0)),0) -> 0.047649577 | G40: =SUM($F$37:F40) -> 0.70064863 | H40: =IFERROR(INDEX('Customer Risk'!$J$5:$J$404,MATCH(LARGE('Customer Risk'!$R$5:$R$404,4),'Customer Risk'!$R$5:$R$404,0)),"")
A41: 5 | B41: =IFERROR(INDEX('Customer Risk'!$B$5:$B$404,MATCH(LARGE('Customer Risk'!$R$5:$R$404,5),'Customer Risk'!$R$5:$R$404,0)),"") -> Microsoft | C41: =IFERROR(INDEX('Customer Risk'!$D$5:$D$404,MATCH(LARGE('Customer Risk'!$R$5:$R$404,5),'Customer Risk'!$R$5:$R$404,0)),0) -> 27122 | D41: =IFERROR(INDEX('Customer Risk'!$F$5:$F$404,MATCH(LARGE('Customer Risk'!$R$5:$R$404,5),'Customer Risk'!$R$5:$R$404,0)),0) -> 0 | E41: =IFERROR(INDEX('Customer Risk'!$G$5:$G$404,MATCH(LARGE('Customer Risk'!$R$5:$R$404,5),'Customer Risk'!$R$5:$R$404,0)),0) -> 27122 | F41: =IFERROR(INDEX('Customer Risk'!$H$5:$H$404,MATCH(LARGE('Customer Risk'!$R$5:$R$404,5),'Customer Risk'!$R$5:$R$404,0)),0) -> 0.031788497 | G41: =SUM($F$37:F41) -> 0.73243712 | H41: =IFERROR(INDEX('Customer Risk'!$J$5:$J$404,MATCH(LARGE('Customer Risk'!$R$5:$R$404,5),'Customer Risk'!$R$5:$R$404,0)),"")
A42: 6 | B42: =IFERROR(INDEX('Customer Risk'!$B$5:$B$404,MATCH(LARGE('Customer Risk'!$R$5:$R$404,6),'Customer Risk'!$R$5:$R$404,0)),"") -> The Lottery Corporation | C42: =IFERROR(INDEX('Customer Risk'!$D$5:$D$404,MATCH(LARGE('Customer Risk'!$R$5:$R$404,6),'Customer Risk'!$R$5:$R$404,0)),0) -> 0 | D42: =IFERROR(INDEX('Customer Risk'!$F$5:$F$404,MATCH(LARGE('Customer Risk'!$R$5:$R$404,6),'Customer Risk'!$R$5:$R$404,0)),0) -> 25543.8 | E42: =IFERROR(INDEX('Customer Risk'!$G$5:$G$404,MATCH(LARGE('Customer Risk'!$R$5:$R$404,6),'Customer Risk'!$R$5:$R$404,0)),0) -> 25543.8 | F42: =IFERROR(INDEX('Customer Risk'!$H$5:$H$404,MATCH(LARGE('Customer Risk'!$R$5:$R$404,6),'Customer Risk'!$R$5:$R$404,0)),0) -> 0.029938759 | G42: =SUM($F$37:F42) -> 0.76237588 | H42: =IFERROR(INDEX('Customer Risk'!$J$5:$J$404,MATCH(LARGE('Customer Risk'!$R$5:$R$404,6),'Customer Risk'!$R$5:$R$404,0)),"")
A43: 7 | B43: =IFERROR(INDEX('Customer Risk'!$B$5:$B$404,MATCH(LARGE('Customer Risk'!$R$5:$R$404,7),'Customer Risk'!$R$5:$R$404,0)),"") -> Aware Super | C43: =IFERROR(INDEX('Customer Risk'!$D$5:$D$404,MATCH(LARGE('Customer Risk'!$R$5:$R$404,7),'Customer Risk'!$R$5:$R$404,0)),0) -> 0 | D43: =IFERROR(INDEX('Customer Risk'!$F$5:$F$404,MATCH(LARGE('Customer Risk'!$R$5:$R$404,7),'Customer Risk'!$R$5:$R$404,0)),0) -> 22648.2 | E43: =IFERROR(INDEX('Customer Risk'!$G$5:$G$404,MATCH(LARGE('Customer Risk'!$R$5:$R$404,7),'Customer Risk'!$R$5:$R$404,0)),0) -> 22648.2 | F43: =IFERROR(INDEX('Customer Risk'!$H$5:$H$404,MATCH(LARGE('Customer Risk'!$R$5:$R$404,7),'Customer Risk'!$R$5:$R$404,0)),0) -> 0.026544954 | G43: =SUM($F$37:F43) -> 0.78892084 | H43: =IFERROR(INDEX('Customer Risk'!$J$5:$J$404,MATCH(LARGE('Customer Risk'!$R$5:$R$404,7),'Customer Risk'!$R$5:$R$404,0)),"")
A44: 8 | B44: =IFERROR(INDEX('Customer Risk'!$B$5:$B$404,MATCH(LARGE('Customer Risk'!$R$5:$R$404,8),'Customer Risk'!$R$5:$R$404,0)),"") -> PWC | C44: =IFERROR(INDEX('Customer Risk'!$D$5:$D$404,MATCH(LARGE('Customer Risk'!$R$5:$R$404,8),'Customer Risk'!$R$5:$R$404,0)),0) -> 17000 | D44: =IFERROR(INDEX('Customer Risk'!$F$5:$F$404,MATCH(LARGE('Customer Risk'!$R$5:$R$404,8),'Customer Risk'!$R$5:$R$404,0)),0) -> 4428 | E44: =IFERROR(INDEX('Customer Risk'!$G$5:$G$404,MATCH(LARGE('Customer Risk'!$R$5:$R$404,8),'Customer Risk'!$R$5:$R$404,0)),0) -> 21428 | F44: =IFERROR(INDEX('Customer Risk'!$H$5:$H$404,MATCH(LARGE('Customer Risk'!$R$5:$R$404,8),'Customer Risk'!$R$5:$R$404,0)),0) -> 0.025114812 | G44: =SUM($F$37:F44) -> 0.81403565 | H44: =IFERROR(INDEX('Customer Risk'!$J$5:$J$404,MATCH(LARGE('Customer Risk'!$R$5:$R$404,8),'Customer Risk'!$R$5:$R$404,0)),"")
A45: 9 | B45: =IFERROR(INDEX('Customer Risk'!$B$5:$B$404,MATCH(LARGE('Customer Risk'!$R$5:$R$404,9),'Customer Risk'!$R$5:$R$404,0)),"") -> Stryker | C45: =IFERROR(INDEX('Customer Risk'!$D$5:$D$404,MATCH(LARGE('Customer Risk'!$R$5:$R$404,9),'Customer Risk'!$R$5:$R$404,0)),0) -> 0 | D45: =IFERROR(INDEX('Customer Risk'!$F$5:$F$404,MATCH(LARGE('Customer Risk'!$R$5:$R$404,9),'Customer Risk'!$R$5:$R$404,0)),0) -> 17034 | E45: =IFERROR(INDEX('Customer Risk'!$G$5:$G$404,MATCH(LARGE('Customer Risk'!$R$5:$R$404,9),'Customer Risk'!$R$5:$R$404,0)),0) -> 17034 | F45: =IFERROR(INDEX('Customer Risk'!$H$5:$H$404,MATCH(LARGE('Customer Risk'!$R$5:$R$404,9),'Customer Risk'!$R$5:$R$404,0)),0) -> 0.019964798 | G45: =SUM($F$37:F45) -> 0.83400045 | H45: =IFERROR(INDEX('Customer Risk'!$J$5:$J$404,MATCH(LARGE('Customer Risk'!$R$5:$R$404,9),'Customer Risk'!$R$5:$R$404,0)),"")
A46: 10 | B46: =IFERROR(INDEX('Customer Risk'!$B$5:$B$404,MATCH(LARGE('Customer Risk'!$R$5:$R$404,10),'Customer Risk'!$R$5:$R$404,0)),"") -> APA | C46: =IFERROR(INDEX('Customer Risk'!$D$5:$D$404,MATCH(LARGE('Customer Risk'!$R$5:$R$404,10),'Customer Risk'!$R$5:$R$404,0)),0) -> 1825 | D46: =IFERROR(INDEX('Customer Risk'!$F$5:$F$404,MATCH(LARGE('Customer Risk'!$R$5:$R$404,10),'Customer Risk'!$R$5:$R$404,0)),0) -> 13383 | E46: =IFERROR(INDEX('Customer Risk'!$G$5:$G$404,MATCH(LARGE('Customer Risk'!$R$5:$R$404,10),'Customer Risk'!$R$5:$R$404,0)),0) -> 15208 | F46: =IFERROR(INDEX('Customer Risk'!$H$5:$H$404,MATCH(LARGE('Customer Risk'!$R$5:$R$404,10),'Customer Risk'!$R$5:$R$404,0)),0) -> 0.017824625 | G46: =SUM($F$37:F46) -> 0.85182507 | H46: =IFERROR(INDEX('Customer Risk'!$J$5:$J$404,MATCH(LARGE('Customer Risk'!$R$5:$R$404,10),'Customer Risk'!$R$5:$R$404,0)),"")
A49: Data checks
A50: Check | B50: Result | C50: Status
A51: Zoho column headings found | B51: =COUNTIF('Zoho Dump'!$L$6:$R$6,">0") -> 6 | C51: =IF(B51=6,"OK","A Zoho heading has changed") -> OK
A52: Zoho deals read | B52: =COUNTIF('Zoho Dump'!$M$8:$M$3007,"?*") -> 663 | C52: =IFERROR(IF(B52=VALUE(TRIM(MID('Zoho Dump'!$A$5,FIND(":",'Zoho Dump'!$A$5)+1,20))),"OK, matches Zoho record count","Does not match Zoho record count"),"Check") -> OK, matches Zoho record count
A53: Deals whose Zoho department is not mapped | B53: =COUNTIF('Zoho Dump'!$P$8:$P$3007,"UNMAPPED") -> 0 | C53: =IF(B53=0,"OK","Add it on Settings") -> OK
A54: Deals whose stage is not in Settings | B54: =COUNTIF('Zoho Dump'!$S$8:$S$3007,"UNMAPPED") -> 0 | C54: =IF(B54=0,"OK","Add it on Settings") -> OK
A55: Deals with no closing date | B55: =COUNTIF('Zoho Dump'!$T$8:$T$3007,"NO DATE") -> 0 | C55: =IF(B55=0,"OK","Ask sales to fix in Zoho") -> OK
A56: Open deals with zero or blank amount | B56: =COUNTIFS('Zoho Dump'!$S$8:$S$3007,"Open",'Zoho Dump'!$Q$8:$Q$3007,0) -> 14 | C56: =IF(B56=0,"OK","Pipeline is understated") -> Pipeline is understated
A57: Open deals past their closing date | B57: =COUNTIF('Zoho Dump'!$T$8:$T$3007,"Overdue") -> 6 | C57: =IF(B57=0,"OK",IF(Settings!$B$8="Yes","Counted in forecast","Not counted. Ask sales to update")) -> Not counted. Ask sales to update
A58: P&L months picked in row 5 | B58: =COUNT('P&L Dump'!$B$5:$Z$5) -> 0 | C58: =IF(B58>0,"OK","No P&L pasted yet") -> No P&L pasted yet
A59: Actual months with no P&L column | B59: =SUMPRODUCT((Settings!$D$12:$D$23<=Settings!$B$5)*(COUNTIF('P&L Dump'!$B$5:$Z$5,Settings!$D$12:$D$23)=0)) -> 3 | C59: =IF(B59=0,"OK","Paste or pick the missing months") -> Paste or pick the missing months
A60: P&L rows not in the Account Map | B60: =SUM('P&L Dump'!$AE$7:$AE$1006) -> 0 | C60: =IF(B60=0,"OK","Add the account to Account Map") -> OK
A61: Customers in the Zoho export | B61: =MAX('Zoho Dump'!$AB$8:$AB$3007) -> 133 | C61: =IF(B61<=400,"OK","More than 400. Extend Customer Risk") -> OK

Sheet Monthly Outlook
A1: Monthly Outlook by department
A2: Months up to the last P&L month show actuals. Later months show Zoho backlog plus weighted pipeline, plus Adjustments.
A4: Month | C4: =Settings!$D$12 -> 46204 | D4: =Settings!$D$13 -> 46235 | E4: =Settings!$D$14 -> 46266 | F4: =Settings!$D$15 -> 46296 | G4: =Settings!$D$16 -> 46327 | H4: =Settings!$D$17 -> 46357 | I4: =Settings!$D$18 -> 46388 | J4: =Settings!$D$19 -> 46419 | K4: =Settings!$D$20 -> 46447 | L4: =Settings!$D$21 -> 46478 | M4: =Settings!$D$22 -> 46508 | N4: =Settings!$D$23 -> 46539 | O4: FY total
A5: Actual or forecast | C5: =IF(C$4<=Settings!$B$5,"Actual","Forecast") -> Actual | D5: =IF(D$4<=Settings!$B$5,"Actual","Forecast") -> Actual | E5: =IF(E$4<=Settings!$B$5,"Actual","Forecast") -> Actual | F5: =IF(F$4<=Settings!$B$5,"Actual","Forecast") -> Forecast | G5: =IF(G$4<=Settings!$B$5,"Actual","Forecast") -> Forecast | H5: =IF(H$4<=Settings!$B$5,"Actual","Forecast") -> Forecast | I5: =IF(I$4<=Settings!$B$5,"Actual","Forecast") -> Forecast | J5: =IF(J$4<=Settings!$B$5,"Actual","Forecast") -> Forecast | ... N5: =IF(N$4<=Settings!$B$5,"Actual","Forecast") -> Forecast
A7: Actual revenue | B7: From P&L Dump, Income accounts
A8: =Settings!$A$12 -> Onsite | C8: =IFERROR(SUMIFS(INDEX('P&L Dump'!$B$7:$Z$1006,0,MATCH(C$4,'P&L Dump'!$B$5:$Z$5,0)),'P&L Dump'!$AC$7:$AC$1006,"Income",'P&L Dump'!$AD$7:$AD$1006,$A8),0) -> 0 | D8: =IFERROR(SUMIFS(INDEX('P&L Dump'!$B$7:$Z$1006,0,MATCH(D$4,'P&L Dump'!$B$5:$Z$5,0)),'P&L Dump'!$AC$7:$AC$1006,"Income",'P&L Dump'!$AD$7:$AD$1006,$A8),0) -> 0 | E8: =IFERROR(SUMIFS(INDEX('P&L Dump'!$B$7:$Z$1006,0,MATCH(E$4,'P&L Dump'!$B$5:$Z$5,0)),'P&L Dump'!$AC$7:$AC$1006,"Income",'P&L Dump'!$AD$7:$AD$1006,$A8),0) -> 0 | F8: =IFERROR(SUMIFS(INDEX('P&L Dump'!$B$7:$Z$1006,0,MATCH(F$4,'P&L Dump'!$B$5:$Z$5,0)),'P&L Dump'!$AC$7:$AC$1006,"Income",'P&L Dump'!$AD$7:$AD$1006,$A8),0) -> 0 | G8: =IFERROR(SUMIFS(INDEX('P&L Dump'!$B$7:$Z$1006,0,MATCH(G$4,'P&L Dump'!$B$5:$Z$5,0)),'P&L Dump'!$AC$7:$AC$1006,"Income",'P&L Dump'!$AD$7:$AD$1006,$A8),0) -> 0 | H8: =IFERROR(SUMIFS(INDEX('P&L Dump'!$B$7:$Z$1006,0,MATCH(H$4,'P&L Dump'!$B$5:$Z$5,0)),'P&L Dump'!$AC$7:$AC$1006,"Income",'P&L Dump'!$AD$7:$AD$1006,$A8),0) -> 0 | I8: =IFERROR(SUMIFS(INDEX('P&L Dump'!$B$7:$Z$1006,0,MATCH(I$4,'P&L Dump'!$B$5:$Z$5,0)),'P&L Dump'!$AC$7:$AC$1006,"Income",'P&L Dump'!$AD$7:$AD$1006,$A8),0) -> 0 | J8: =IFERROR(SUMIFS(INDEX('P&L Dump'!$B$7:$Z$1006,0,MATCH(J$4,'P&L Dump'!$B$5:$Z$5,0)),'P&L Dump'!$AC$7:$AC$1006,"Income",'P&L Dump'!$AD$7:$AD$1006,$A8),0) -> 0 | ... N8: =IFERROR(SUMIFS(INDEX('P&L Dump'!$B$7:$Z$1006,0,MATCH(N$4,'P&L Dump'!$B$5:$Z$5,0)),'P&L Dump'!$AC$7:$AC$1006,"Income",'P&L Dump'!$AD$7:$AD$1006,$A8),0) -> 0 | O8: =SUM(C8:N8) -> 0
A9: =Settings!$A$13 -> Production | C9: =IFERROR(SUMIFS(INDEX('P&L Dump'!$B$7:$Z$1006,0,MATCH(C$4,'P&L Dump'!$B$5:$Z$5,0)),'P&L Dump'!$AC$7:$AC$1006,"Income",'P&L Dump'!$AD$7:$AD$1006,$A9),0) -> 0 | D9: =IFERROR(SUMIFS(INDEX('P&L Dump'!$B$7:$Z$1006,0,MATCH(D$4,'P&L Dump'!$B$5:$Z$5,0)),'P&L Dump'!$AC$7:$AC$1006,"Income",'P&L Dump'!$AD$7:$AD$1006,$A9),0) -> 0 | E9: =IFERROR(SUMIFS(INDEX('P&L Dump'!$B$7:$Z$1006,0,MATCH(E$4,'P&L Dump'!$B$5:$Z$5,0)),'P&L Dump'!$AC$7:$AC$1006,"Income",'P&L Dump'!$AD$7:$AD$1006,$A9),0) -> 0 | F9: =IFERROR(SUMIFS(INDEX('P&L Dump'!$B$7:$Z$1006,0,MATCH(F$4,'P&L Dump'!$B$5:$Z$5,0)),'P&L Dump'!$AC$7:$AC$1006,"Income",'P&L Dump'!$AD$7:$AD$1006,$A9),0) -> 0 | G9: =IFERROR(SUMIFS(INDEX('P&L Dump'!$B$7:$Z$1006,0,MATCH(G$4,'P&L Dump'!$B$5:$Z$5,0)),'P&L Dump'!$AC$7:$AC$1006,"Income",'P&L Dump'!$AD$7:$AD$1006,$A9),0) -> 0 | H9: =IFERROR(SUMIFS(INDEX('P&L Dump'!$B$7:$Z$1006,0,MATCH(H$4,'P&L Dump'!$B$5:$Z$5,0)),'P&L Dump'!$AC$7:$AC$1006,"Income",'P&L Dump'!$AD$7:$AD$1006,$A9),0) -> 0 | I9: =IFERROR(SUMIFS(INDEX('P&L Dump'!$B$7:$Z$1006,0,MATCH(I$4,'P&L Dump'!$B$5:$Z$5,0)),'P&L Dump'!$AC$7:$AC$1006,"Income",'P&L Dump'!$AD$7:$AD$1006,$A9),0) -> 0 | J9: =IFERROR(SUMIFS(INDEX('P&L Dump'!$B$7:$Z$1006,0,MATCH(J$4,'P&L Dump'!$B$5:$Z$5,0)),'P&L Dump'!$AC$7:$AC$1006,"Income",'P&L Dump'!$AD$7:$AD$1006,$A9),0) -> 0 | ... N9: =IFERROR(SUMIFS(INDEX('P&L Dump'!$B$7:$Z$1006,0,MATCH(N$4,'P&L Dump'!$B$5:$Z$5,0)),'P&L Dump'!$AC$7:$AC$1006,"Income",'P&L Dump'!$AD$7:$AD$1006,$A9),0) -> 0 | O9: =SUM(C9:N9) -> 0
A10: =Settings!$A$14 -> Video | C10: =IFERROR(SUMIFS(INDEX('P&L Dump'!$B$7:$Z$1006,0,MATCH(C$4,'P&L Dump'!$B$5:$Z$5,0)),'P&L Dump'!$AC$7:$AC$1006,"Income",'P&L Dump'!$AD$7:$AD$1006,$A10),0) -> 0 | D10: =IFERROR(SUMIFS(INDEX('P&L Dump'!$B$7:$Z$1006,0,MATCH(D$4,'P&L Dump'!$B$5:$Z$5,0)),'P&L Dump'!$AC$7:$AC$1006,"Income",'P&L Dump'!$AD$7:$AD$1006,$A10),0) -> 0 | E10: =IFERROR(SUMIFS(INDEX('P&L Dump'!$B$7:$Z$1006,0,MATCH(E$4,'P&L Dump'!$B$5:$Z$5,0)),'P&L Dump'!$AC$7:$AC$1006,"Income",'P&L Dump'!$AD$7:$AD$1006,$A10),0) -> 0 | F10: =IFERROR(SUMIFS(INDEX('P&L Dump'!$B$7:$Z$1006,0,MATCH(F$4,'P&L Dump'!$B$5:$Z$5,0)),'P&L Dump'!$AC$7:$AC$1006,"Income",'P&L Dump'!$AD$7:$AD$1006,$A10),0) -> 0 | G10: =IFERROR(SUMIFS(INDEX('P&L Dump'!$B$7:$Z$1006,0,MATCH(G$4,'P&L Dump'!$B$5:$Z$5,0)),'P&L Dump'!$AC$7:$AC$1006,"Income",'P&L Dump'!$AD$7:$AD$1006,$A10),0) -> 0 | H10: =IFERROR(SUMIFS(INDEX('P&L Dump'!$B$7:$Z$1006,0,MATCH(H$4,'P&L Dump'!$B$5:$Z$5,0)),'P&L Dump'!$AC$7:$AC$1006,"Income",'P&L Dump'!$AD$7:$AD$1006,$A10),0) -> 0 | I10: =IFERROR(SUMIFS(INDEX('P&L Dump'!$B$7:$Z$1006,0,MATCH(I$4,'P&L Dump'!$B$5:$Z$5,0)),'P&L Dump'!$AC$7:$AC$1006,"Income",'P&L Dump'!$AD$7:$AD$1006,$A10),0) -> 0 | J10: =IFERROR(SUMIFS(INDEX('P&L Dump'!$B$7:$Z$1006,0,MATCH(J$4,'P&L Dump'!$B$5:$Z$5,0)),'P&L Dump'!$AC$7:$AC$1006,"Income",'P&L Dump'!$AD$7:$AD$1006,$A10),0) -> 0 | ... N10: =IFERROR(SUMIFS(INDEX('P&L Dump'!$B$7:$Z$1006,0,MATCH(N$4,'P&L Dump'!$B$5:$Z$5,0)),'P&L Dump'!$AC$7:$AC$1006,"Income",'P&L Dump'!$AD$7:$AD$1006,$A10),0) -> 0 | O10: =SUM(C10:N10) -> 0
A11: =Settings!$A$15 -> Consulting | C11: =IFERROR(SUMIFS(INDEX('P&L Dump'!$B$7:$Z$1006,0,MATCH(C$4,'P&L Dump'!$B$5:$Z$5,0)),'P&L Dump'!$AC$7:$AC$1006,"Income",'P&L Dump'!$AD$7:$AD$1006,$A11),0) -> 0 | D11: =IFERROR(SUMIFS(INDEX('P&L Dump'!$B$7:$Z$1006,0,MATCH(D$4,'P&L Dump'!$B$5:$Z$5,0)),'P&L Dump'!$AC$7:$AC$1006,"Income",'P&L Dump'!$AD$7:$AD$1006,$A11),0) -> 0 | E11: =IFERROR(SUMIFS(INDEX('P&L Dump'!$B$7:$Z$1006,0,MATCH(E$4,'P&L Dump'!$B$5:$Z$5,0)),'P&L Dump'!$AC$7:$AC$1006,"Income",'P&L Dump'!$AD$7:$AD$1006,$A11),0) -> 0 | F11: =IFERROR(SUMIFS(INDEX('P&L Dump'!$B$7:$Z$1006,0,MATCH(F$4,'P&L Dump'!$B$5:$Z$5,0)),'P&L Dump'!$AC$7:$AC$1006,"Income",'P&L Dump'!$AD$7:$AD$1006,$A11),0) -> 0 | G11: =IFERROR(SUMIFS(INDEX('P&L Dump'!$B$7:$Z$1006,0,MATCH(G$4,'P&L Dump'!$B$5:$Z$5,0)),'P&L Dump'!$AC$7:$AC$1006,"Income",'P&L Dump'!$AD$7:$AD$1006,$A11),0) -> 0 | H11: =IFERROR(SUMIFS(INDEX('P&L Dump'!$B$7:$Z$1006,0,MATCH(H$4,'P&L Dump'!$B$5:$Z$5,0)),'P&L Dump'!$AC$7:$AC$1006,"Income",'P&L Dump'!$AD$7:$AD$1006,$A11),0) -> 0 | I11: =IFERROR(SUMIFS(INDEX('P&L Dump'!$B$7:$Z$1006,0,MATCH(I$4,'P&L Dump'!$B$5:$Z$5,0)),'P&L Dump'!$AC$7:$AC$1006,"Income",'P&L Dump'!$AD$7:$AD$1006,$A11),0) -> 0 | J11: =IFERROR(SUMIFS(INDEX('P&L Dump'!$B$7:$Z$1006,0,MATCH(J$4,'P&L Dump'!$B$5:$Z$5,0)),'P&L Dump'!$AC$7:$AC$1006,"Income",'P&L Dump'!$AD$7:$AD$1006,$A11),0) -> 0 | ... N11: =IFERROR(SUMIFS(INDEX('P&L Dump'!$B$7:$Z$1006,0,MATCH(N$4,'P&L Dump'!$B$5:$Z$5,0)),'P&L Dump'!$AC$7:$AC$1006,"Income",'P&L Dump'!$AD$7:$AD$1006,$A11),0) -> 0 | O11: =SUM(C11:N11) -> 0
A12: =Settings!$A$16 -> Integration | C12: =IFERROR(SUMIFS(INDEX('P&L Dump'!$B$7:$Z$1006,0,MATCH(C$4,'P&L Dump'!$B$5:$Z$5,0)),'P&L Dump'!$AC$7:$AC$1006,"Income",'P&L Dump'!$AD$7:$AD$1006,$A12),0) -> 0 | D12: =IFERROR(SUMIFS(INDEX('P&L Dump'!$B$7:$Z$1006,0,MATCH(D$4,'P&L Dump'!$B$5:$Z$5,0)),'P&L Dump'!$AC$7:$AC$1006,"Income",'P&L Dump'!$AD$7:$AD$1006,$A12),0) -> 0 | E12: =IFERROR(SUMIFS(INDEX('P&L Dump'!$B$7:$Z$1006,0,MATCH(E$4,'P&L Dump'!$B$5:$Z$5,0)),'P&L Dump'!$AC$7:$AC$1006,"Income",'P&L Dump'!$AD$7:$AD$1006,$A12),0) -> 0 | F12: =IFERROR(SUMIFS(INDEX('P&L Dump'!$B$7:$Z$1006,0,MATCH(F$4,'P&L Dump'!$B$5:$Z$5,0)),'P&L Dump'!$AC$7:$AC$1006,"Income",'P&L Dump'!$AD$7:$AD$1006,$A12),0) -> 0 | G12: =IFERROR(SUMIFS(INDEX('P&L Dump'!$B$7:$Z$1006,0,MATCH(G$4,'P&L Dump'!$B$5:$Z$5,0)),'P&L Dump'!$AC$7:$AC$1006,"Income",'P&L Dump'!$AD$7:$AD$1006,$A12),0) -> 0 | H12: =IFERROR(SUMIFS(INDEX('P&L Dump'!$B$7:$Z$1006,0,MATCH(H$4,'P&L Dump'!$B$5:$Z$5,0)),'P&L Dump'!$AC$7:$AC$1006,"Income",'P&L Dump'!$AD$7:$AD$1006,$A12),0) -> 0 | I12: =IFERROR(SUMIFS(INDEX('P&L Dump'!$B$7:$Z$1006,0,MATCH(I$4,'P&L Dump'!$B$5:$Z$5,0)),'P&L Dump'!$AC$7:$AC$1006,"Income",'P&L Dump'!$AD$7:$AD$1006,$A12),0) -> 0 | J12: =IFERROR(SUMIFS(INDEX('P&L Dump'!$B$7:$Z$1006,0,MATCH(J$4,'P&L Dump'!$B$5:$Z$5,0)),'P&L Dump'!$AC$7:$AC$1006,"Income",'P&L Dump'!$AD$7:$AD$1006,$A12),0) -> 0 | ... N12: =IFERROR(SUMIFS(INDEX('P&L Dump'!$B$7:$Z$1006,0,MATCH(N$4,'P&L Dump'!$B$5:$Z$5,0)),'P&L Dump'!$AC$7:$AC$1006,"Income",'P&L Dump'!$AD$7:$AD$1006,$A12),0) -> 0 | O12: =SUM(C12:N12) -> 0
A13: =Settings!$A$17 -> Admin | C13: =IFERROR(SUMIFS(INDEX('P&L Dump'!$B$7:$Z$1006,0,MATCH(C$4,'P&L Dump'!$B$5:$Z$5,0)),'P&L Dump'!$AC$7:$AC$1006,"Income",'P&L Dump'!$AD$7:$AD$1006,$A13),0) -> 0 | D13: =IFERROR(SUMIFS(INDEX('P&L Dump'!$B$7:$Z$1006,0,MATCH(D$4,'P&L Dump'!$B$5:$Z$5,0)),'P&L Dump'!$AC$7:$AC$1006,"Income",'P&L Dump'!$AD$7:$AD$1006,$A13),0) -> 0 | E13: =IFERROR(SUMIFS(INDEX('P&L Dump'!$B$7:$Z$1006,0,MATCH(E$4,'P&L Dump'!$B$5:$Z$5,0)),'P&L Dump'!$AC$7:$AC$1006,"Income",'P&L Dump'!$AD$7:$AD$1006,$A13),0) -> 0 | F13: =IFERROR(SUMIFS(INDEX('P&L Dump'!$B$7:$Z$1006,0,MATCH(F$4,'P&L Dump'!$B$5:$Z$5,0)),'P&L Dump'!$AC$7:$AC$1006,"Income",'P&L Dump'!$AD$7:$AD$1006,$A13),0) -> 0 | G13: =IFERROR(SUMIFS(INDEX('P&L Dump'!$B$7:$Z$1006,0,MATCH(G$4,'P&L Dump'!$B$5:$Z$5,0)),'P&L Dump'!$AC$7:$AC$1006,"Income",'P&L Dump'!$AD$7:$AD$1006,$A13),0) -> 0 | H13: =IFERROR(SUMIFS(INDEX('P&L Dump'!$B$7:$Z$1006,0,MATCH(H$4,'P&L Dump'!$B$5:$Z$5,0)),'P&L Dump'!$AC$7:$AC$1006,"Income",'P&L Dump'!$AD$7:$AD$1006,$A13),0) -> 0 | I13: =IFERROR(SUMIFS(INDEX('P&L Dump'!$B$7:$Z$1006,0,MATCH(I$4,'P&L Dump'!$B$5:$Z$5,0)),'P&L Dump'!$AC$7:$AC$1006,"Income",'P&L Dump'!$AD$7:$AD$1006,$A13),0) -> 0 | J13: =IFERROR(SUMIFS(INDEX('P&L Dump'!$B$7:$Z$1006,0,MATCH(J$4,'P&L Dump'!$B$5:$Z$5,0)),'P&L Dump'!$AC$7:$AC$1006,"Income",'P&L Dump'!$AD$7:$AD$1006,$A13),0) -> 0 | ... N13: =IFERROR(SUMIFS(INDEX('P&L Dump'!$B$7:$Z$1006,0,MATCH(N$4,'P&L Dump'!$B$5:$Z$5,0)),'P&L Dump'!$AC$7:$AC$1006,"Income",'P&L Dump'!$AD$7:$AD$1006,$A13),0) -> 0 | O13: =SUM(C13:N13) -> 0
A14: =Settings!$A$18 -> Unallocated | C14: =IFERROR(SUMIFS(INDEX('P&L Dump'!$B$7:$Z$1006,0,MATCH(C$4,'P&L Dump'!$B$5:$Z$5,0)),'P&L Dump'!$AC$7:$AC$1006,"Income",'P&L Dump'!$AD$7:$AD$1006,$A14),0) -> 0 | D14: =IFERROR(SUMIFS(INDEX('P&L Dump'!$B$7:$Z$1006,0,MATCH(D$4,'P&L Dump'!$B$5:$Z$5,0)),'P&L Dump'!$AC$7:$AC$1006,"Income",'P&L Dump'!$AD$7:$AD$1006,$A14),0) -> 0 | E14: =IFERROR(SUMIFS(INDEX('P&L Dump'!$B$7:$Z$1006,0,MATCH(E$4,'P&L Dump'!$B$5:$Z$5,0)),'P&L Dump'!$AC$7:$AC$1006,"Income",'P&L Dump'!$AD$7:$AD$1006,$A14),0) -> 0 | F14: =IFERROR(SUMIFS(INDEX('P&L Dump'!$B$7:$Z$1006,0,MATCH(F$4,'P&L Dump'!$B$5:$Z$5,0)),'P&L Dump'!$AC$7:$AC$1006,"Income",'P&L Dump'!$AD$7:$AD$1006,$A14),0) -> 0 | G14: =IFERROR(SUMIFS(INDEX('P&L Dump'!$B$7:$Z$1006,0,MATCH(G$4,'P&L Dump'!$B$5:$Z$5,0)),'P&L Dump'!$AC$7:$AC$1006,"Income",'P&L Dump'!$AD$7:$AD$1006,$A14),0) -> 0 | H14: =IFERROR(SUMIFS(INDEX('P&L Dump'!$B$7:$Z$1006,0,MATCH(H$4,'P&L Dump'!$B$5:$Z$5,0)),'P&L Dump'!$AC$7:$AC$1006,"Income",'P&L Dump'!$AD$7:$AD$1006,$A14),0) -> 0 | I14: =IFERROR(SUMIFS(INDEX('P&L Dump'!$B$7:$Z$1006,0,MATCH(I$4,'P&L Dump'!$B$5:$Z$5,0)),'P&L Dump'!$AC$7:$AC$1006,"Income",'P&L Dump'!$AD$7:$AD$1006,$A14),0) -> 0 | J14: =IFERROR(SUMIFS(INDEX('P&L Dump'!$B$7:$Z$1006,0,MATCH(J$4,'P&L Dump'!$B$5:$Z$5,0)),'P&L Dump'!$AC$7:$AC$1006,"Income",'P&L Dump'!$AD$7:$AD$1006,$A14),0) -> 0 | ... N14: =IFERROR(SUMIFS(INDEX('P&L Dump'!$B$7:$Z$1006,0,MATCH(N$4,'P&L Dump'!$B$5:$Z$5,0)),'P&L Dump'!$AC$7:$AC$1006,"Income",'P&L Dump'!$AD$7:$AD$1006,$A14),0) -> 0 | O14: =SUM(C14:N14) -> 0
A15: Total | C15: =SUM(C8:C14) -> 0 | D15: =SUM(D8:D14) -> 0 | E15: =SUM(E8:E14) -> 0 | F15: =SUM(F8:F14) -> 0 | G15: =SUM(G8:G14) -> 0 | H15: =SUM(H8:H14) -> 0 | I15: =SUM(I8:I14) -> 0 | J15: =SUM(J8:J14) -> 0 | ... O15: =SUM(O8:O14) -> 0
A17: Backlog | B17: Signed. Zoho Closed Won after the last P&L month, plus Adjustments
A18: =Settings!$A$12 -> Onsite | C18: =SUMIFS('Zoho Dump'!$X$8:$X$3007,'Zoho Dump'!$P$8:$P$3007,$A18,'Zoho Dump'!$W$8:$W$3007,C$4,'Zoho Dump'!$T$8:$T$3007,"Backlog")+SUMIFS(Adjustments!$K$8:$K$207,Adjustments!$A$8:$A$207,$A18,Adjustments!$J$8:$J$207,C$4,Adjustments!$H$8:$H$207,"Backlog") -> 0 | D18: =SUMIFS('Zoho Dump'!$X$8:$X$3007,'Zoho Dump'!$P$8:$P$3007,$A18,'Zoho Dump'!$W$8:$W$3007,D$4,'Zoho Dump'!$T$8:$T$3007,"Backlog")+SUMIFS(Adjustments!$K$8:$K$207,Adjustments!$A$8:$A$207,$A18,Adjustments!$J$8:$J$207,D$4,Adjustments!$H$8:$H$207,"Backlog") -> 0 | E18: =SUMIFS('Zoho Dump'!$X$8:$X$3007,'Zoho Dump'!$P$8:$P$3007,$A18,'Zoho Dump'!$W$8:$W$3007,E$4,'Zoho Dump'!$T$8:$T$3007,"Backlog")+SUMIFS(Adjustments!$K$8:$K$207,Adjustments!$A$8:$A$207,$A18,Adjustments!$J$8:$J$207,E$4,Adjustments!$H$8:$H$207,"Backlog") -> 0 | F18: =SUMIFS('Zoho Dump'!$X$8:$X$3007,'Zoho Dump'!$P$8:$P$3007,$A18,'Zoho Dump'!$W$8:$W$3007,F$4,'Zoho Dump'!$T$8:$T$3007,"Backlog")+SUMIFS(Adjustments!$K$8:$K$207,Adjustments!$A$8:$A$207,$A18,Adjustments!$J$8:$J$207,F$4,Adjustments!$H$8:$H$207,"Backlog") -> 17000 | G18: =SUMIFS('Zoho Dump'!$X$8:$X$3007,'Zoho Dump'!$P$8:$P$3007,$A18,'Zoho Dump'!$W$8:$W$3007,G$4,'Zoho Dump'!$T$8:$T$3007,"Backlog")+SUMIFS(Adjustments!$K$8:$K$207,Adjustments!$A$8:$A$207,$A18,Adjustments!$J$8:$J$207,G$4,Adjustments!$H$8:$H$207,"Backlog") -> 0 | H18: =SUMIFS('Zoho Dump'!$X$8:$X$3007,'Zoho Dump'!$P$8:$P$3007,$A18,'Zoho Dump'!$W$8:$W$3007,H$4,'Zoho Dump'!$T$8:$T$3007,"Backlog")+SUMIFS(Adjustments!$K$8:$K$207,Adjustments!$A$8:$A$207,$A18,Adjustments!$J$8:$J$207,H$4,Adjustments!$H$8:$H$207,"Backlog") -> 0 | I18: =SUMIFS('Zoho Dump'!$X$8:$X$3007,'Zoho Dump'!$P$8:$P$3007,$A18,'Zoho Dump'!$W$8:$W$3007,I$4,'Zoho Dump'!$T$8:$T$3007,"Backlog")+SUMIFS(Adjustments!$K$8:$K$207,Adjustments!$A$8:$A$207,$A18,Adjustments!$J$8:$J$207,I$4,Adjustments!$H$8:$H$207,"Backlog") -> 0 | J18: =SUMIFS('Zoho Dump'!$X$8:$X$3007,'Zoho Dump'!$P$8:$P$3007,$A18,'Zoho Dump'!$W$8:$W$3007,J$4,'Zoho Dump'!$T$8:$T$3007,"Backlog")+SUMIFS(Adjustments!$K$8:$K$207,Adjustments!$A$8:$A$207,$A18,Adjustments!$J$8:$J$207,J$4,Adjustments!$H$8:$H$207,"Backlog") -> 0 | ... N18: =SUMIFS('Zoho Dump'!$X$8:$X$3007,'Zoho Dump'!$P$8:$P$3007,$A18,'Zoho Dump'!$W$8:$W$3007,N$4,'Zoho Dump'!$T$8:$T$3007,"Backlog")+SUMIFS(Adjustments!$K$8:$K$207,Adjustments!$A$8:$A$207,$A18,Adjustments!$J$8:$J$207,N$4,Adjustments!$H$8:$H$207,"Backlog") -> 0 | O18: =SUM(C18:N18) -> 17000
A19: =Settings!$A$13 -> Production | C19: =SUMIFS('Zoho Dump'!$X$8:$X$3007,'Zoho Dump'!$P$8:$P$3007,$A19,'Zoho Dump'!$W$8:$W$3007,C$4,'Zoho Dump'!$T$8:$T$3007,"Backlog")+SUMIFS(Adjustments!$K$8:$K$207,Adjustments!$A$8:$A$207,$A19,Adjustments!$J$8:$J$207,C$4,Adjustments!$H$8:$H$207,"Backlog") -> 0 | D19: =SUMIFS('Zoho Dump'!$X$8:$X$3007,'Zoho Dump'!$P$8:$P$3007,$A19,'Zoho Dump'!$W$8:$W$3007,D$4,'Zoho Dump'!$T$8:$T$3007,"Backlog")+SUMIFS(Adjustments!$K$8:$K$207,Adjustments!$A$8:$A$207,$A19,Adjustments!$J$8:$J$207,D$4,Adjustments!$H$8:$H$207,"Backlog") -> 0 | E19: =SUMIFS('Zoho Dump'!$X$8:$X$3007,'Zoho Dump'!$P$8:$P$3007,$A19,'Zoho Dump'!$W$8:$W$3007,E$4,'Zoho Dump'!$T$8:$T$3007,"Backlog")+SUMIFS(Adjustments!$K$8:$K$207,Adjustments!$A$8:$A$207,$A19,Adjustments!$J$8:$J$207,E$4,Adjustments!$H$8:$H$207,"Backlog") -> 0 | F19: =SUMIFS('Zoho Dump'!$X$8:$X$3007,'Zoho Dump'!$P$8:$P$3007,$A19,'Zoho Dump'!$W$8:$W$3007,F$4,'Zoho Dump'!$T$8:$T$3007,"Backlog")+SUMIFS(Adjustments!$K$8:$K$207,Adjustments!$A$8:$A$207,$A19,Adjustments!$J$8:$J$207,F$4,Adjustments!$H$8:$H$207,"Backlog") -> 40626 | G19: =SUMIFS('Zoho Dump'!$X$8:$X$3007,'Zoho Dump'!$P$8:$P$3007,$A19,'Zoho Dump'!$W$8:$W$3007,G$4,'Zoho Dump'!$T$8:$T$3007,"Backlog")+SUMIFS(Adjustments!$K$8:$K$207,Adjustments!$A$8:$A$207,$A19,Adjustments!$J$8:$J$207,G$4,Adjustments!$H$8:$H$207,"Backlog") -> 13553 | H19: =SUMIFS('Zoho Dump'!$X$8:$X$3007,'Zoho Dump'!$P$8:$P$3007,$A19,'Zoho Dump'!$W$8:$W$3007,H$4,'Zoho Dump'!$T$8:$T$3007,"Backlog")+SUMIFS(Adjustments!$K$8:$K$207,Adjustments!$A$8:$A$207,$A19,Adjustments!$J$8:$J$207,H$4,Adjustments!$H$8:$H$207,"Backlog") -> 2881 | I19: =SUMIFS('Zoho Dump'!$X$8:$X$3007,'Zoho Dump'!$P$8:$P$3007,$A19,'Zoho Dump'!$W$8:$W$3007,I$4,'Zoho Dump'!$T$8:$T$3007,"Backlog")+SUMIFS(Adjustments!$K$8:$K$207,Adjustments!$A$8:$A$207,$A19,Adjustments!$J$8:$J$207,I$4,Adjustments!$H$8:$H$207,"Backlog") -> 0 | J19: =SUMIFS('Zoho Dump'!$X$8:$X$3007,'Zoho Dump'!$P$8:$P$3007,$A19,'Zoho Dump'!$W$8:$W$3007,J$4,'Zoho Dump'!$T$8:$T$3007,"Backlog")+SUMIFS(Adjustments!$K$8:$K$207,Adjustments!$A$8:$A$207,$A19,Adjustments!$J$8:$J$207,J$4,Adjustments!$H$8:$H$207,"Backlog") -> 0 | ... N19: =SUMIFS('Zoho Dump'!$X$8:$X$3007,'Zoho Dump'!$P$8:$P$3007,$A19,'Zoho Dump'!$W$8:$W$3007,N$4,'Zoho Dump'!$T$8:$T$3007,"Backlog")+SUMIFS(Adjustments!$K$8:$K$207,Adjustments!$A$8:$A$207,$A19,Adjustments!$J$8:$J$207,N$4,Adjustments!$H$8:$H$207,"Backlog") -> 0 | O19: =SUM(C19:N19) -> 57060
A20: =Settings!$A$14 -> Video | C20: =SUMIFS('Zoho Dump'!$X$8:$X$3007,'Zoho Dump'!$P$8:$P$3007,$A20,'Zoho Dump'!$W$8:$W$3007,C$4,'Zoho Dump'!$T$8:$T$3007,"Backlog")+SUMIFS(Adjustments!$K$8:$K$207,Adjustments!$A$8:$A$207,$A20,Adjustments!$J$8:$J$207,C$4,Adjustments!$H$8:$H$207,"Backlog") -> 0 | D20: =SUMIFS('Zoho Dump'!$X$8:$X$3007,'Zoho Dump'!$P$8:$P$3007,$A20,'Zoho Dump'!$W$8:$W$3007,D$4,'Zoho Dump'!$T$8:$T$3007,"Backlog")+SUMIFS(Adjustments!$K$8:$K$207,Adjustments!$A$8:$A$207,$A20,Adjustments!$J$8:$J$207,D$4,Adjustments!$H$8:$H$207,"Backlog") -> 0 | E20: =SUMIFS('Zoho Dump'!$X$8:$X$3007,'Zoho Dump'!$P$8:$P$3007,$A20,'Zoho Dump'!$W$8:$W$3007,E$4,'Zoho Dump'!$T$8:$T$3007,"Backlog")+SUMIFS(Adjustments!$K$8:$K$207,Adjustments!$A$8:$A$207,$A20,Adjustments!$J$8:$J$207,E$4,Adjustments!$H$8:$H$207,"Backlog") -> 0 | F20: =SUMIFS('Zoho Dump'!$X$8:$X$3007,'Zoho Dump'!$P$8:$P$3007,$A20,'Zoho Dump'!$W$8:$W$3007,F$4,'Zoho Dump'!$T$8:$T$3007,"Backlog")+SUMIFS(Adjustments!$K$8:$K$207,Adjustments!$A$8:$A$207,$A20,Adjustments!$J$8:$J$207,F$4,Adjustments!$H$8:$H$207,"Backlog") -> 0 | G20: =SUMIFS('Zoho Dump'!$X$8:$X$3007,'Zoho Dump'!$P$8:$P$3007,$A20,'Zoho Dump'!$W$8:$W$3007,G$4,'Zoho Dump'!$T$8:$T$3007,"Backlog")+SUMIFS(Adjustments!$K$8:$K$207,Adjustments!$A$8:$A$207,$A20,Adjustments!$J$8:$J$207,G$4,Adjustments!$H$8:$H$207,"Backlog") -> 11342 | H20: =SUMIFS('Zoho Dump'!$X$8:$X$3007,'Zoho Dump'!$P$8:$P$3007,$A20,'Zoho Dump'!$W$8:$W$3007,H$4,'Zoho Dump'!$T$8:$T$3007,"Backlog")+SUMIFS(Adjustments!$K$8:$K$207,Adjustments!$A$8:$A$207,$A20,Adjustments!$J$8:$J$207,H$4,Adjustments!$H$8:$H$207,"Backlog") -> 0 | I20: =SUMIFS('Zoho Dump'!$X$8:$X$3007,'Zoho Dump'!$P$8:$P$3007,$A20,'Zoho Dump'!$W$8:$W$3007,I$4,'Zoho Dump'!$T$8:$T$3007,"Backlog")+SUMIFS(Adjustments!$K$8:$K$207,Adjustments!$A$8:$A$207,$A20,Adjustments!$J$8:$J$207,I$4,Adjustments!$H$8:$H$207,"Backlog") -> 0 | J20: =SUMIFS('Zoho Dump'!$X$8:$X$3007,'Zoho Dump'!$P$8:$P$3007,$A20,'Zoho Dump'!$W$8:$W$3007,J$4,'Zoho Dump'!$T$8:$T$3007,"Backlog")+SUMIFS(Adjustments!$K$8:$K$207,Adjustments!$A$8:$A$207,$A20,Adjustments!$J$8:$J$207,J$4,Adjustments!$H$8:$H$207,"Backlog") -> 0 | ... N20: =SUMIFS('Zoho Dump'!$X$8:$X$3007,'Zoho Dump'!$P$8:$P$3007,$A20,'Zoho Dump'!$W$8:$W$3007,N$4,'Zoho Dump'!$T$8:$T$3007,"Backlog")+SUMIFS(Adjustments!$K$8:$K$207,Adjustments!$A$8:$A$207,$A20,Adjustments!$J$8:$J$207,N$4,Adjustments!$H$8:$H$207,"Backlog") -> 0 | O20: =SUM(C20:N20) -> 11342
A21: =Settings!$A$15 -> Consulting | C21: =SUMIFS('Zoho Dump'!$X$8:$X$3007,'Zoho Dump'!$P$8:$P$3007,$A21,'Zoho Dump'!$W$8:$W$3007,C$4,'Zoho Dump'!$T$8:$T$3007,"Backlog")+SUMIFS(Adjustments!$K$8:$K$207,Adjustments!$A$8:$A$207,$A21,Adjustments!$J$8:$J$207,C$4,Adjustments!$H$8:$H$207,"Backlog") -> 0 | D21: =SUMIFS('Zoho Dump'!$X$8:$X$3007,'Zoho Dump'!$P$8:$P$3007,$A21,'Zoho Dump'!$W$8:$W$3007,D$4,'Zoho Dump'!$T$8:$T$3007,"Backlog")+SUMIFS(Adjustments!$K$8:$K$207,Adjustments!$A$8:$A$207,$A21,Adjustments!$J$8:$J$207,D$4,Adjustments!$H$8:$H$207,"Backlog") -> 0 | E21: =SUMIFS('Zoho Dump'!$X$8:$X$3007,'Zoho Dump'!$P$8:$P$3007,$A21,'Zoho Dump'!$W$8:$W$3007,E$4,'Zoho Dump'!$T$8:$T$3007,"Backlog")+SUMIFS(Adjustments!$K$8:$K$207,Adjustments!$A$8:$A$207,$A21,Adjustments!$J$8:$J$207,E$4,Adjustments!$H$8:$H$207,"Backlog") -> 0 | F21: =SUMIFS('Zoho Dump'!$X$8:$X$3007,'Zoho Dump'!$P$8:$P$3007,$A21,'Zoho Dump'!$W$8:$W$3007,F$4,'Zoho Dump'!$T$8:$T$3007,"Backlog")+SUMIFS(Adjustments!$K$8:$K$207,Adjustments!$A$8:$A$207,$A21,Adjustments!$J$8:$J$207,F$4,Adjustments!$H$8:$H$207,"Backlog") -> 0 | G21: =SUMIFS('Zoho Dump'!$X$8:$X$3007,'Zoho Dump'!$P$8:$P$3007,$A21,'Zoho Dump'!$W$8:$W$3007,G$4,'Zoho Dump'!$T$8:$T$3007,"Backlog")+SUMIFS(Adjustments!$K$8:$K$207,Adjustments!$A$8:$A$207,$A21,Adjustments!$J$8:$J$207,G$4,Adjustments!$H$8:$H$207,"Backlog") -> 0 | H21: =SUMIFS('Zoho Dump'!$X$8:$X$3007,'Zoho Dump'!$P$8:$P$3007,$A21,'Zoho Dump'!$W$8:$W$3007,H$4,'Zoho Dump'!$T$8:$T$3007,"Backlog")+SUMIFS(Adjustments!$K$8:$K$207,Adjustments!$A$8:$A$207,$A21,Adjustments!$J$8:$J$207,H$4,Adjustments!$H$8:$H$207,"Backlog") -> 0 | I21: =SUMIFS('Zoho Dump'!$X$8:$X$3007,'Zoho Dump'!$P$8:$P$3007,$A21,'Zoho Dump'!$W$8:$W$3007,I$4,'Zoho Dump'!$T$8:$T$3007,"Backlog")+SUMIFS(Adjustments!$K$8:$K$207,Adjustments!$A$8:$A$207,$A21,Adjustments!$J$8:$J$207,I$4,Adjustments!$H$8:$H$207,"Backlog") -> 0 | J21: =SUMIFS('Zoho Dump'!$X$8:$X$3007,'Zoho Dump'!$P$8:$P$3007,$A21,'Zoho Dump'!$W$8:$W$3007,J$4,'Zoho Dump'!$T$8:$T$3007,"Backlog")+SUMIFS(Adjustments!$K$8:$K$207,Adjustments!$A$8:$A$207,$A21,Adjustments!$J$8:$J$207,J$4,Adjustments!$H$8:$H$207,"Backlog") -> 0 | ... N21: =SUMIFS('Zoho Dump'!$X$8:$X$3007,'Zoho Dump'!$P$8:$P$3007,$A21,'Zoho Dump'!$W$8:$W$3007,N$4,'Zoho Dump'!$T$8:$T$3007,"Backlog")+SUMIFS(Adjustments!$K$8:$K$207,Adjustments!$A$8:$A$207,$A21,Adjustments!$J$8:$J$207,N$4,Adjustments!$H$8:$H$207,"Backlog") -> 0 | O21: =SUM(C21:N21) -> 0
A22: =Settings!$A$16 -> Integration | C22: =SUMIFS('Zoho Dump'!$X$8:$X$3007,'Zoho Dump'!$P$8:$P$3007,$A22,'Zoho Dump'!$W$8:$W$3007,C$4,'Zoho Dump'!$T$8:$T$3007,"Backlog")+SUMIFS(Adjustments!$K$8:$K$207,Adjustments!$A$8:$A$207,$A22,Adjustments!$J$8:$J$207,C$4,Adjustments!$H$8:$H$207,"Backlog") -> 0 | D22: =SUMIFS('Zoho Dump'!$X$8:$X$3007,'Zoho Dump'!$P$8:$P$3007,$A22,'Zoho Dump'!$W$8:$W$3007,D$4,'Zoho Dump'!$T$8:$T$3007,"Backlog")+SUMIFS(Adjustments!$K$8:$K$207,Adjustments!$A$8:$A$207,$A22,Adjustments!$J$8:$J$207,D$4,Adjustments!$H$8:$H$207,"Backlog") -> 0 | E22: =SUMIFS('Zoho Dump'!$X$8:$X$3007,'Zoho Dump'!$P$8:$P$3007,$A22,'Zoho Dump'!$W$8:$W$3007,E$4,'Zoho Dump'!$T$8:$T$3007,"Backlog")+SUMIFS(Adjustments!$K$8:$K$207,Adjustments!$A$8:$A$207,$A22,Adjustments!$J$8:$J$207,E$4,Adjustments!$H$8:$H$207,"Backlog") -> 0 | F22: =SUMIFS('Zoho Dump'!$X$8:$X$3007,'Zoho Dump'!$P$8:$P$3007,$A22,'Zoho Dump'!$W$8:$W$3007,F$4,'Zoho Dump'!$T$8:$T$3007,"Backlog")+SUMIFS(Adjustments!$K$8:$K$207,Adjustments!$A$8:$A$207,$A22,Adjustments!$J$8:$J$207,F$4,Adjustments!$H$8:$H$207,"Backlog") -> 0 | G22: =SUMIFS('Zoho Dump'!$X$8:$X$3007,'Zoho Dump'!$P$8:$P$3007,$A22,'Zoho Dump'!$W$8:$W$3007,G$4,'Zoho Dump'!$T$8:$T$3007,"Backlog")+SUMIFS(Adjustments!$K$8:$K$207,Adjustments!$A$8:$A$207,$A22,Adjustments!$J$8:$J$207,G$4,Adjustments!$H$8:$H$207,"Backlog") -> 0 | H22: =SUMIFS('Zoho Dump'!$X$8:$X$3007,'Zoho Dump'!$P$8:$P$3007,$A22,'Zoho Dump'!$W$8:$W$3007,H$4,'Zoho Dump'!$T$8:$T$3007,"Backlog")+SUMIFS(Adjustments!$K$8:$K$207,Adjustments!$A$8:$A$207,$A22,Adjustments!$J$8:$J$207,H$4,Adjustments!$H$8:$H$207,"Backlog") -> 0 | I22: =SUMIFS('Zoho Dump'!$X$8:$X$3007,'Zoho Dump'!$P$8:$P$3007,$A22,'Zoho Dump'!$W$8:$W$3007,I$4,'Zoho Dump'!$T$8:$T$3007,"Backlog")+SUMIFS(Adjustments!$K$8:$K$207,Adjustments!$A$8:$A$207,$A22,Adjustments!$J$8:$J$207,I$4,Adjustments!$H$8:$H$207,"Backlog") -> 0 | J22: =SUMIFS('Zoho Dump'!$X$8:$X$3007,'Zoho Dump'!$P$8:$P$3007,$A22,'Zoho Dump'!$W$8:$W$3007,J$4,'Zoho Dump'!$T$8:$T$3007,"Backlog")+SUMIFS(Adjustments!$K$8:$K$207,Adjustments!$A$8:$A$207,$A22,Adjustments!$J$8:$J$207,J$4,Adjustments!$H$8:$H$207,"Backlog") -> 0 | ... N22: =SUMIFS('Zoho Dump'!$X$8:$X$3007,'Zoho Dump'!$P$8:$P$3007,$A22,'Zoho Dump'!$W$8:$W$3007,N$4,'Zoho Dump'!$T$8:$T$3007,"Backlog")+SUMIFS(Adjustments!$K$8:$K$207,Adjustments!$A$8:$A$207,$A22,Adjustments!$J$8:$J$207,N$4,Adjustments!$H$8:$H$207,"Backlog") -> 0 | O22: =SUM(C22:N22) -> 0
A23: =Settings!$A$17 -> Admin | C23: =SUMIFS('Zoho Dump'!$X$8:$X$3007,'Zoho Dump'!$P$8:$P$3007,$A23,'Zoho Dump'!$W$8:$W$3007,C$4,'Zoho Dump'!$T$8:$T$3007,"Backlog")+SUMIFS(Adjustments!$K$8:$K$207,Adjustments!$A$8:$A$207,$A23,Adjustments!$J$8:$J$207,C$4,Adjustments!$H$8:$H$207,"Backlog") -> 0 | D23: =SUMIFS('Zoho Dump'!$X$8:$X$3007,'Zoho Dump'!$P$8:$P$3007,$A23,'Zoho Dump'!$W$8:$W$3007,D$4,'Zoho Dump'!$T$8:$T$3007,"Backlog")+SUMIFS(Adjustments!$K$8:$K$207,Adjustments!$A$8:$A$207,$A23,Adjustments!$J$8:$J$207,D$4,Adjustments!$H$8:$H$207,"Backlog") -> 0 | E23: =SUMIFS('Zoho Dump'!$X$8:$X$3007,'Zoho Dump'!$P$8:$P$3007,$A23,'Zoho Dump'!$W$8:$W$3007,E$4,'Zoho Dump'!$T$8:$T$3007,"Backlog")+SUMIFS(Adjustments!$K$8:$K$207,Adjustments!$A$8:$A$207,$A23,Adjustments!$J$8:$J$207,E$4,Adjustments!$H$8:$H$207,"Backlog") -> 0 | F23: =SUMIFS('Zoho Dump'!$X$8:$X$3007,'Zoho Dump'!$P$8:$P$3007,$A23,'Zoho Dump'!$W$8:$W$3007,F$4,'Zoho Dump'!$T$8:$T$3007,"Backlog")+SUMIFS(Adjustments!$K$8:$K$207,Adjustments!$A$8:$A$207,$A23,Adjustments!$J$8:$J$207,F$4,Adjustments!$H$8:$H$207,"Backlog") -> 0 | G23: =SUMIFS('Zoho Dump'!$X$8:$X$3007,'Zoho Dump'!$P$8:$P$3007,$A23,'Zoho Dump'!$W$8:$W$3007,G$4,'Zoho Dump'!$T$8:$T$3007,"Backlog")+SUMIFS(Adjustments!$K$8:$K$207,Adjustments!$A$8:$A$207,$A23,Adjustments!$J$8:$J$207,G$4,Adjustments!$H$8:$H$207,"Backlog") -> 0 | H23: =SUMIFS('Zoho Dump'!$X$8:$X$3007,'Zoho Dump'!$P$8:$P$3007,$A23,'Zoho Dump'!$W$8:$W$3007,H$4,'Zoho Dump'!$T$8:$T$3007,"Backlog")+SUMIFS(Adjustments!$K$8:$K$207,Adjustments!$A$8:$A$207,$A23,Adjustments!$J$8:$J$207,H$4,Adjustments!$H$8:$H$207,"Backlog") -> 0 | I23: =SUMIFS('Zoho Dump'!$X$8:$X$3007,'Zoho Dump'!$P$8:$P$3007,$A23,'Zoho Dump'!$W$8:$W$3007,I$4,'Zoho Dump'!$T$8:$T$3007,"Backlog")+SUMIFS(Adjustments!$K$8:$K$207,Adjustments!$A$8:$A$207,$A23,Adjustments!$J$8:$J$207,I$4,Adjustments!$H$8:$H$207,"Backlog") -> 0 | J23: =SUMIFS('Zoho Dump'!$X$8:$X$3007,'Zoho Dump'!$P$8:$P$3007,$A23,'Zoho Dump'!$W$8:$W$3007,J$4,'Zoho Dump'!$T$8:$T$3007,"Backlog")+SUMIFS(Adjustments!$K$8:$K$207,Adjustments!$A$8:$A$207,$A23,Adjustments!$J$8:$J$207,J$4,Adjustments!$H$8:$H$207,"Backlog") -> 0 | ... N23: =SUMIFS('Zoho Dump'!$X$8:$X$3007,'Zoho Dump'!$P$8:$P$3007,$A23,'Zoho Dump'!$W$8:$W$3007,N$4,'Zoho Dump'!$T$8:$T$3007,"Backlog")+SUMIFS(Adjustments!$K$8:$K$207,Adjustments!$A$8:$A$207,$A23,Adjustments!$J$8:$J$207,N$4,Adjustments!$H$8:$H$207,"Backlog") -> 0 | O23: =SUM(C23:N23) -> 0
A24: =Settings!$A$18 -> Unallocated | C24: =SUMIFS('Zoho Dump'!$X$8:$X$3007,'Zoho Dump'!$P$8:$P$3007,$A24,'Zoho Dump'!$W$8:$W$3007,C$4,'Zoho Dump'!$T$8:$T$3007,"Backlog")+SUMIFS(Adjustments!$K$8:$K$207,Adjustments!$A$8:$A$207,$A24,Adjustments!$J$8:$J$207,C$4,Adjustments!$H$8:$H$207,"Backlog") -> 0 | D24: =SUMIFS('Zoho Dump'!$X$8:$X$3007,'Zoho Dump'!$P$8:$P$3007,$A24,'Zoho Dump'!$W$8:$W$3007,D$4,'Zoho Dump'!$T$8:$T$3007,"Backlog")+SUMIFS(Adjustments!$K$8:$K$207,Adjustments!$A$8:$A$207,$A24,Adjustments!$J$8:$J$207,D$4,Adjustments!$H$8:$H$207,"Backlog") -> 0 | E24: =SUMIFS('Zoho Dump'!$X$8:$X$3007,'Zoho Dump'!$P$8:$P$3007,$A24,'Zoho Dump'!$W$8:$W$3007,E$4,'Zoho Dump'!$T$8:$T$3007,"Backlog")+SUMIFS(Adjustments!$K$8:$K$207,Adjustments!$A$8:$A$207,$A24,Adjustments!$J$8:$J$207,E$4,Adjustments!$H$8:$H$207,"Backlog") -> 0 | F24: =SUMIFS('Zoho Dump'!$X$8:$X$3007,'Zoho Dump'!$P$8:$P$3007,$A24,'Zoho Dump'!$W$8:$W$3007,F$4,'Zoho Dump'!$T$8:$T$3007,"Backlog")+SUMIFS(Adjustments!$K$8:$K$207,Adjustments!$A$8:$A$207,$A24,Adjustments!$J$8:$J$207,F$4,Adjustments!$H$8:$H$207,"Backlog") -> 0 | G24: =SUMIFS('Zoho Dump'!$X$8:$X$3007,'Zoho Dump'!$P$8:$P$3007,$A24,'Zoho Dump'!$W$8:$W$3007,G$4,'Zoho Dump'!$T$8:$T$3007,"Backlog")+SUMIFS(Adjustments!$K$8:$K$207,Adjustments!$A$8:$A$207,$A24,Adjustments!$J$8:$J$207,G$4,Adjustments!$H$8:$H$207,"Backlog") -> 0 | H24: =SUMIFS('Zoho Dump'!$X$8:$X$3007,'Zoho Dump'!$P$8:$P$3007,$A24,'Zoho Dump'!$W$8:$W$3007,H$4,'Zoho Dump'!$T$8:$T$3007,"Backlog")+SUMIFS(Adjustments!$K$8:$K$207,Adjustments!$A$8:$A$207,$A24,Adjustments!$J$8:$J$207,H$4,Adjustments!$H$8:$H$207,"Backlog") -> 0 | I24: =SUMIFS('Zoho Dump'!$X$8:$X$3007,'Zoho Dump'!$P$8:$P$3007,$A24,'Zoho Dump'!$W$8:$W$3007,I$4,'Zoho Dump'!$T$8:$T$3007,"Backlog")+SUMIFS(Adjustments!$K$8:$K$207,Adjustments!$A$8:$A$207,$A24,Adjustments!$J$8:$J$207,I$4,Adjustments!$H$8:$H$207,"Backlog") -> 0 | J24: =SUMIFS('Zoho Dump'!$X$8:$X$3007,'Zoho Dump'!$P$8:$P$3007,$A24,'Zoho Dump'!$W$8:$W$3007,J$4,'Zoho Dump'!$T$8:$T$3007,"Backlog")+SUMIFS(Adjustments!$K$8:$K$207,Adjustments!$A$8:$A$207,$A24,Adjustments!$J$8:$J$207,J$4,Adjustments!$H$8:$H$207,"Backlog") -> 0 | ... N24: =SUMIFS('Zoho Dump'!$X$8:$X$3007,'Zoho Dump'!$P$8:$P$3007,$A24,'Zoho Dump'!$W$8:$W$3007,N$4,'Zoho Dump'!$T$8:$T$3007,"Backlog")+SUMIFS(Adjustments!$K$8:$K$207,Adjustments!$A$8:$A$207,$A24,Adjustments!$J$8:$J$207,N$4,Adjustments!$H$8:$H$207,"Backlog") -> 0 | O24: =SUM(C24:N24) -> 0
A25: Total | C25: =SUM(C18:C24) -> 0 | D25: =SUM(D18:D24) -> 0 | E25: =SUM(E18:E24) -> 0 | F25: =SUM(F18:F24) -> 57626 | G25: =SUM(G18:G24) -> 24895 | H25: =SUM(H18:H24) -> 2881 | I25: =SUM(I18:I24) -> 0 | J25: =SUM(J18:J24) -> 0 | ... O25: =SUM(O18:O24) -> 85402
A27: Pipeline (weighted) | B27: Open Zoho deals times stage probability, plus Adjustments
A28: =Settings!$A$12 -> Onsite | C28: =SUMIFS('Zoho Dump'!$X$8:$X$3007,'Zoho Dump'!$P$8:$P$3007,$A28,'Zoho Dump'!$W$8:$W$3007,C$4,'Zoho Dump'!$T$8:$T$3007,"Pipeline")+SUMIFS(Adjustments!$K$8:$K$207,Adjustments!$A$8:$A$207,$A28,Adjustments!$J$8:$J$207,C$4,Adjustments!$H$8:$H$207,"Pipeline")+SUMIFS('Zoho Dump'!$X$8:$X$3007,'Zoho Dump'!$P$8:$P$3007,$A28,'Zoho Dump'!$W$8:$W$3007,C$4,'Zoho Dump'!$T$8:$T$3007,"Overdue")+SUMIFS(Adjustments!$K$8:$K$207,Adjustments!$A$8:$A$207,$A28,Adjustments!$J$8:$J$207,C$4,Adjustments!$H$8:$H$207,"Overdue") -> 0 | D28: =SUMIFS('Zoho Dump'!$X$8:$X$3007,'Zoho Dump'!$P$8:$P$3007,$A28,'Zoho Dump'!$W$8:$W$3007,D$4,'Zoho Dump'!$T$8:$T$3007,"Pipeline")+SUMIFS(Adjustments!$K$8:$K$207,Adjustments!$A$8:$A$207,$A28,Adjustments!$J$8:$J$207,D$4,Adjustments!$H$8:$H$207,"Pipeline")+SUMIFS('Zoho Dump'!$X$8:$X$3007,'Zoho Dump'!$P$8:$P$3007,$A28,'Zoho Dump'!$W$8:$W$3007,D$4,'Zoho Dump'!$T$8:$T$3007,"Overdue")+SUMIFS(Adjustments!$K$8:$K$207,Adjustments!$A$8:$A$207,$A28,Adjustments!$J$8:$J$207,D$4,Adjustments!$H$8:$H$207,"Overdue") -> 0 | E28: =SUMIFS('Zoho Dump'!$X$8:$X$3007,'Zoho Dump'!$P$8:$P$3007,$A28,'Zoho Dump'!$W$8:$W$3007,E$4,'Zoho Dump'!$T$8:$T$3007,"Pipeline")+SUMIFS(Adjustments!$K$8:$K$207,Adjustments!$A$8:$A$207,$A28,Adjustments!$J$8:$J$207,E$4,Adjustments!$H$8:$H$207,"Pipeline")+SUMIFS('Zoho Dump'!$X$8:$X$3007,'Zoho Dump'!$P$8:$P$3007,$A28,'Zoho Dump'!$W$8:$W$3007,E$4,'Zoho Dump'!$T$8:$T$3007,"Overdue")+SUMIFS(Adjustments!$K$8:$K$207,Adjustments!$A$8:$A$207,$A28,Adjustments!$J$8:$J$207,E$4,Adjustments!$H$8:$H$207,"Overdue") -> 0 | F28: =SUMIFS('Zoho Dump'!$X$8:$X$3007,'Zoho Dump'!$P$8:$P$3007,$A28,'Zoho Dump'!$W$8:$W$3007,F$4,'Zoho Dump'!$T$8:$T$3007,"Pipeline")+SUMIFS(Adjustments!$K$8:$K$207,Adjustments!$A$8:$A$207,$A28,Adjustments!$J$8:$J$207,F$4,Adjustments!$H$8:$H$207,"Pipeline")+SUMIFS('Zoho Dump'!$X$8:$X$3007,'Zoho Dump'!$P$8:$P$3007,$A28,'Zoho Dump'!$W$8:$W$3007,F$4,'Zoho Dump'!$T$8:$T$3007,"Overdue")+SUMIFS(Adjustments!$K$8:$K$207,Adjustments!$A$8:$A$207,$A28,Adjustments!$J$8:$J$207,F$4,Adjustments!$H$8:$H$207,"Overdue") -> 0 | G28: =SUMIFS('Zoho Dump'!$X$8:$X$3007,'Zoho Dump'!$P$8:$P$3007,$A28,'Zoho Dump'!$W$8:$W$3007,G$4,'Zoho Dump'!$T$8:$T$3007,"Pipeline")+SUMIFS(Adjustments!$K$8:$K$207,Adjustments!$A$8:$A$207,$A28,Adjustments!$J$8:$J$207,G$4,Adjustments!$H$8:$H$207,"Pipeline")+SUMIFS('Zoho Dump'!$X$8:$X$3007,'Zoho Dump'!$P$8:$P$3007,$A28,'Zoho Dump'!$W$8:$W$3007,G$4,'Zoho Dump'!$T$8:$T$3007,"Overdue")+SUMIFS(Adjustments!$K$8:$K$207,Adjustments!$A$8:$A$207,$A28,Adjustments!$J$8:$J$207,G$4,Adjustments!$H$8:$H$207,"Overdue") -> 0 | H28: =SUMIFS('Zoho Dump'!$X$8:$X$3007,'Zoho Dump'!$P$8:$P$3007,$A28,'Zoho Dump'!$W$8:$W$3007,H$4,'Zoho Dump'!$T$8:$T$3007,"Pipeline")+SUMIFS(Adjustments!$K$8:$K$207,Adjustments!$A$8:$A$207,$A28,Adjustments!$J$8:$J$207,H$4,Adjustments!$H$8:$H$207,"Pipeline")+SUMIFS('Zoho Dump'!$X$8:$X$3007,'Zoho Dump'!$P$8:$P$3007,$A28,'Zoho Dump'!$W$8:$W$3007,H$4,'Zoho Dump'!$T$8:$T$3007,"Overdue")+SUMIFS(Adjustments!$K$8:$K$207,Adjustments!$A$8:$A$207,$A28,Adjustments!$J$8:$J$207,H$4,Adjustments!$H$8:$H$207,"Overdue") -> 0 | I28: =SUMIFS('Zoho Dump'!$X$8:$X$3007,'Zoho Dump'!$P$8:$P$3007,$A28,'Zoho Dump'!$W$8:$W$3007,I$4,'Zoho Dump'!$T$8:$T$3007,"Pipeline")+SUMIFS(Adjustments!$K$8:$K$207,Adjustments!$A$8:$A$207,$A28,Adjustments!$J$8:$J$207,I$4,Adjustments!$H$8:$H$207,"Pipeline")+SUMIFS('Zoho Dump'!$X$8:$X$3007,'Zoho Dump'!$P$8:$P$3007,$A28,'Zoho Dump'!$W$8:$W$3007,I$4,'Zoho Dump'!$T$8:$T$3007,"Overdue")+SUMIFS(Adjustments!$K$8:$K$207,Adjustments!$A$8:$A$207,$A28,Adjustments!$J$8:$J$207,I$4,Adjustments!$H$8:$H$207,"Overdue") -> 0 | J28: =SUMIFS('Zoho Dump'!$X$8:$X$3007,'Zoho Dump'!$P$8:$P$3007,$A28,'Zoho Dump'!$W$8:$W$3007,J$4,'Zoho Dump'!$T$8:$T$3007,"Pipeline")+SUMIFS(Adjustments!$K$8:$K$207,Adjustments!$A$8:$A$207,$A28,Adjustments!$J$8:$J$207,J$4,Adjustments!$H$8:$H$207,"Pipeline")+SUMIFS('Zoho Dump'!$X$8:$X$3007,'Zoho Dump'!$P$8:$P$3007,$A28,'Zoho Dump'!$W$8:$W$3007,J$4,'Zoho Dump'!$T$8:$T$3007,"Overdue")+SUMIFS(Adjustments!$K$8:$K$207,Adjustments!$A$8:$A$207,$A28,Adjustments!$J$8:$J$207,J$4,Adjustments!$H$8:$H$207,"Overdue") -> 52500 | ... N28: =SUMIFS('Zoho Dump'!$X$8:$X$3007,'Zoho Dump'!$P$8:$P$3007,$A28,'Zoho Dump'!$W$8:$W$3007,N$4,'Zoho Dump'!$T$8:$T$3007,"Pipeline")+SUMIFS(Adjustments!$K$8:$K$207,Adjustments!$A$8:$A$207,$A28,Adjustments!$J$8:$J$207,N$4,Adjustments!$H$8:$H$207,"Pipeline")+SUMIFS('Zoho Dump'!$X$8:$X$3007,'Zoho Dump'!$P$8:$P$3007,$A28,'Zoho Dump'!$W$8:$W$3007,N$4,'Zoho Dump'!$T$8:$T$3007,"Overdue")+SUMIFS(Adjustments!$K$8:$K$207,Adjustments!$A$8:$A$207,$A28,Adjustments!$J$8:$J$207,N$4,Adjustments!$H$8:$H$207,"Overdue") -> 0 | O28: =SUM(C28:N28) -> 52500
A29: =Settings!$A$13 -> Production | C29: =SUMIFS('Zoho Dump'!$X$8:$X$3007,'Zoho Dump'!$P$8:$P$3007,$A29,'Zoho Dump'!$W$8:$W$3007,C$4,'Zoho Dump'!$T$8:$T$3007,"Pipeline")+SUMIFS(Adjustments!$K$8:$K$207,Adjustments!$A$8:$A$207,$A29,Adjustments!$J$8:$J$207,C$4,Adjustments!$H$8:$H$207,"Pipeline")+SUMIFS('Zoho Dump'!$X$8:$X$3007,'Zoho Dump'!$P$8:$P$3007,$A29,'Zoho Dump'!$W$8:$W$3007,C$4,'Zoho Dump'!$T$8:$T$3007,"Overdue")+SUMIFS(Adjustments!$K$8:$K$207,Adjustments!$A$8:$A$207,$A29,Adjustments!$J$8:$J$207,C$4,Adjustments!$H$8:$H$207,"Overdue") -> 0 | D29: =SUMIFS('Zoho Dump'!$X$8:$X$3007,'Zoho Dump'!$P$8:$P$3007,$A29,'Zoho Dump'!$W$8:$W$3007,D$4,'Zoho Dump'!$T$8:$T$3007,"Pipeline")+SUMIFS(Adjustments!$K$8:$K$207,Adjustments!$A$8:$A$207,$A29,Adjustments!$J$8:$J$207,D$4,Adjustments!$H$8:$H$207,"Pipeline")+SUMIFS('Zoho Dump'!$X$8:$X$3007,'Zoho Dump'!$P$8:$P$3007,$A29,'Zoho Dump'!$W$8:$W$3007,D$4,'Zoho Dump'!$T$8:$T$3007,"Overdue")+SUMIFS(Adjustments!$K$8:$K$207,Adjustments!$A$8:$A$207,$A29,Adjustments!$J$8:$J$207,D$4,Adjustments!$H$8:$H$207,"Overdue") -> 0 | E29: =SUMIFS('Zoho Dump'!$X$8:$X$3007,'Zoho Dump'!$P$8:$P$3007,$A29,'Zoho Dump'!$W$8:$W$3007,E$4,'Zoho Dump'!$T$8:$T$3007,"Pipeline")+SUMIFS(Adjustments!$K$8:$K$207,Adjustments!$A$8:$A$207,$A29,Adjustments!$J$8:$J$207,E$4,Adjustments!$H$8:$H$207,"Pipeline")+SUMIFS('Zoho Dump'!$X$8:$X$3007,'Zoho Dump'!$P$8:$P$3007,$A29,'Zoho Dump'!$W$8:$W$3007,E$4,'Zoho Dump'!$T$8:$T$3007,"Overdue")+SUMIFS(Adjustments!$K$8:$K$207,Adjustments!$A$8:$A$207,$A29,Adjustments!$J$8:$J$207,E$4,Adjustments!$H$8:$H$207,"Overdue") -> 0 | F29: =SUMIFS('Zoho Dump'!$X$8:$X$3007,'Zoho Dump'!$P$8:$P$3007,$A29,'Zoho Dump'!$W$8:$W$3007,F$4,'Zoho Dump'!$T$8:$T$3007,"Pipeline")+SUMIFS(Adjustments!$K$8:$K$207,Adjustments!$A$8:$A$207,$A29,Adjustments!$J$8:$J$207,F$4,Adjustments!$H$8:$H$207,"Pipeline")+SUMIFS('Zoho Dump'!$X$8:$X$3007,'Zoho Dump'!$P$8:$P$3007,$A29,'Zoho Dump'!$W$8:$W$3007,F$4,'Zoho Dump'!$T$8:$T$3007,"Overdue")+SUMIFS(Adjustments!$K$8:$K$207,Adjustments!$A$8:$A$207,$A29,Adjustments!$J$8:$J$207,F$4,Adjustments!$H$8:$H$207,"Overdue") -> 132772.2 | G29: =SUMIFS('Zoho Dump'!$X$8:$X$3007,'Zoho Dump'!$P$8:$P$3007,$A29,'Zoho Dump'!$W$8:$W$3007,G$4,'Zoho Dump'!$T$8:$T$3007,"Pipeline")+SUMIFS(Adjustments!$K$8:$K$207,Adjustments!$A$8:$A$207,$A29,Adjustments!$J$8:$J$207,G$4,Adjustments!$H$8:$H$207,"Pipeline")+SUMIFS('Zoho Dump'!$X$8:$X$3007,'Zoho Dump'!$P$8:$P$3007,$A29,'Zoho Dump'!$W$8:$W$3007,G$4,'Zoho Dump'!$T$8:$T$3007,"Overdue")+SUMIFS(Adjustments!$K$8:$K$207,Adjustments!$A$8:$A$207,$A29,Adjustments!$J$8:$J$207,G$4,Adjustments!$H$8:$H$207,"Overdue") -> 61320.6 | H29: =SUMIFS('Zoho Dump'!$X$8:$X$3007,'Zoho Dump'!$P$8:$P$3007,$A29,'Zoho Dump'!$W$8:$W$3007,H$4,'Zoho Dump'!$T$8:$T$3007,"Pipeline")+SUMIFS(Adjustments!$K$8:$K$207,Adjustments!$A$8:$A$207,$A29,Adjustments!$J$8:$J$207,H$4,Adjustments!$H$8:$H$207,"Pipeline")+SUMIFS('Zoho Dump'!$X$8:$X$3007,'Zoho Dump'!$P$8:$P$3007,$A29,'Zoho Dump'!$W$8:$W$3007,H$4,'Zoho Dump'!$T$8:$T$3007,"Overdue")+SUMIFS(Adjustments!$K$8:$K$207,Adjustments!$A$8:$A$207,$A29,Adjustments!$J$8:$J$207,H$4,Adjustments!$H$8:$H$207,"Overdue") -> 21270.7 | I29: =SUMIFS('Zoho Dump'!$X$8:$X$3007,'Zoho Dump'!$P$8:$P$3007,$A29,'Zoho Dump'!$W$8:$W$3007,I$4,'Zoho Dump'!$T$8:$T$3007,"Pipeline")+SUMIFS(Adjustments!$K$8:$K$207,Adjustments!$A$8:$A$207,$A29,Adjustments!$J$8:$J$207,I$4,Adjustments!$H$8:$H$207,"Pipeline")+SUMIFS('Zoho Dump'!$X$8:$X$3007,'Zoho Dump'!$P$8:$P$3007,$A29,'Zoho Dump'!$W$8:$W$3007,I$4,'Zoho Dump'!$T$8:$T$3007,"Overdue")+SUMIFS(Adjustments!$K$8:$K$207,Adjustments!$A$8:$A$207,$A29,Adjustments!$J$8:$J$207,I$4,Adjustments!$H$8:$H$207,"Overdue") -> 224 | J29: =SUMIFS('Zoho Dump'!$X$8:$X$3007,'Zoho Dump'!$P$8:$P$3007,$A29,'Zoho Dump'!$W$8:$W$3007,J$4,'Zoho Dump'!$T$8:$T$3007,"Pipeline")+SUMIFS(Adjustments!$K$8:$K$207,Adjustments!$A$8:$A$207,$A29,Adjustments!$J$8:$J$207,J$4,Adjustments!$H$8:$H$207,"Pipeline")+SUMIFS('Zoho Dump'!$X$8:$X$3007,'Zoho Dump'!$P$8:$P$3007,$A29,'Zoho Dump'!$W$8:$W$3007,J$4,'Zoho Dump'!$T$8:$T$3007,"Overdue")+SUMIFS(Adjustments!$K$8:$K$207,Adjustments!$A$8:$A$207,$A29,Adjustments!$J$8:$J$207,J$4,Adjustments!$H$8:$H$207,"Overdue") -> 1600 | ... N29: =SUMIFS('Zoho Dump'!$X$8:$X$3007,'Zoho Dump'!$P$8:$P$3007,$A29,'Zoho Dump'!$W$8:$W$3007,N$4,'Zoho Dump'!$T$8:$T$3007,"Pipeline")+SUMIFS(Adjustments!$K$8:$K$207,Adjustments!$A$8:$A$207,$A29,Adjustments!$J$8:$J$207,N$4,Adjustments!$H$8:$H$207,"Pipeline")+SUMIFS('Zoho Dump'!$X$8:$X$3007,'Zoho Dump'!$P$8:$P$3007,$A29,'Zoho Dump'!$W$8:$W$3007,N$4,'Zoho Dump'!$T$8:$T$3007,"Overdue")+SUMIFS(Adjustments!$K$8:$K$207,Adjustments!$A$8:$A$207,$A29,Adjustments!$J$8:$J$207,N$4,Adjustments!$H$8:$H$207,"Overdue") -> 0 | O29: =SUM(C29:N29) -> 645044.5
A30: =Settings!$A$14 -> Video | C30: =SUMIFS('Zoho Dump'!$X$8:$X$3007,'Zoho Dump'!$P$8:$P$3007,$A30,'Zoho Dump'!$W$8:$W$3007,C$4,'Zoho Dump'!$T$8:$T$3007,"Pipeline")+SUMIFS(Adjustments!$K$8:$K$207,Adjustments!$A$8:$A$207,$A30,Adjustments!$J$8:$J$207,C$4,Adjustments!$H$8:$H$207,"Pipeline")+SUMIFS('Zoho Dump'!$X$8:$X$3007,'Zoho Dump'!$P$8:$P$3007,$A30,'Zoho Dump'!$W$8:$W$3007,C$4,'Zoho Dump'!$T$8:$T$3007,"Overdue")+SUMIFS(Adjustments!$K$8:$K$207,Adjustments!$A$8:$A$207,$A30,Adjustments!$J$8:$J$207,C$4,Adjustments!$H$8:$H$207,"Overdue") -> 0 | D30: =SUMIFS('Zoho Dump'!$X$8:$X$3007,'Zoho Dump'!$P$8:$P$3007,$A30,'Zoho Dump'!$W$8:$W$3007,D$4,'Zoho Dump'!$T$8:$T$3007,"Pipeline")+SUMIFS(Adjustments!$K$8:$K$207,Adjustments!$A$8:$A$207,$A30,Adjustments!$J$8:$J$207,D$4,Adjustments!$H$8:$H$207,"Pipeline")+SUMIFS('Zoho Dump'!$X$8:$X$3007,'Zoho Dump'!$P$8:$P$3007,$A30,'Zoho Dump'!$W$8:$W$3007,D$4,'Zoho Dump'!$T$8:$T$3007,"Overdue")+SUMIFS(Adjustments!$K$8:$K$207,Adjustments!$A$8:$A$207,$A30,Adjustments!$J$8:$J$207,D$4,Adjustments!$H$8:$H$207,"Overdue") -> 0 | E30: =SUMIFS('Zoho Dump'!$X$8:$X$3007,'Zoho Dump'!$P$8:$P$3007,$A30,'Zoho Dump'!$W$8:$W$3007,E$4,'Zoho Dump'!$T$8:$T$3007,"Pipeline")+SUMIFS(Adjustments!$K$8:$K$207,Adjustments!$A$8:$A$207,$A30,Adjustments!$J$8:$J$207,E$4,Adjustments!$H$8:$H$207,"Pipeline")+SUMIFS('Zoho Dump'!$X$8:$X$3007,'Zoho Dump'!$P$8:$P$3007,$A30,'Zoho Dump'!$W$8:$W$3007,E$4,'Zoho Dump'!$T$8:$T$3007,"Overdue")+SUMIFS(Adjustments!$K$8:$K$207,Adjustments!$A$8:$A$207,$A30,Adjustments!$J$8:$J$207,E$4,Adjustments!$H$8:$H$207,"Overdue") -> 0 | F30: =SUMIFS('Zoho Dump'!$X$8:$X$3007,'Zoho Dump'!$P$8:$P$3007,$A30,'Zoho Dump'!$W$8:$W$3007,F$4,'Zoho Dump'!$T$8:$T$3007,"Pipeline")+SUMIFS(Adjustments!$K$8:$K$207,Adjustments!$A$8:$A$207,$A30,Adjustments!$J$8:$J$207,F$4,Adjustments!$H$8:$H$207,"Pipeline")+SUMIFS('Zoho Dump'!$X$8:$X$3007,'Zoho Dump'!$P$8:$P$3007,$A30,'Zoho Dump'!$W$8:$W$3007,F$4,'Zoho Dump'!$T$8:$T$3007,"Overdue")+SUMIFS(Adjustments!$K$8:$K$207,Adjustments!$A$8:$A$207,$A30,Adjustments!$J$8:$J$207,F$4,Adjustments!$H$8:$H$207,"Overdue") -> 1255.5 | G30: =SUMIFS('Zoho Dump'!$X$8:$X$3007,'Zoho Dump'!$P$8:$P$3007,$A30,'Zoho Dump'!$W$8:$W$3007,G$4,'Zoho Dump'!$T$8:$T$3007,"Pipeline")+SUMIFS(Adjustments!$K$8:$K$207,Adjustments!$A$8:$A$207,$A30,Adjustments!$J$8:$J$207,G$4,Adjustments!$H$8:$H$207,"Pipeline")+SUMIFS('Zoho Dump'!$X$8:$X$3007,'Zoho Dump'!$P$8:$P$3007,$A30,'Zoho Dump'!$W$8:$W$3007,G$4,'Zoho Dump'!$T$8:$T$3007,"Overdue")+SUMIFS(Adjustments!$K$8:$K$207,Adjustments!$A$8:$A$207,$A30,Adjustments!$J$8:$J$207,G$4,Adjustments!$H$8:$H$207,"Overdue") -> 0 | H30: =SUMIFS('Zoho Dump'!$X$8:$X$3007,'Zoho Dump'!$P$8:$P$3007,$A30,'Zoho Dump'!$W$8:$W$3007,H$4,'Zoho Dump'!$T$8:$T$3007,"Pipeline")+SUMIFS(Adjustments!$K$8:$K$207,Adjustments!$A$8:$A$207,$A30,Adjustments!$J$8:$J$207,H$4,Adjustments!$H$8:$H$207,"Pipeline")+SUMIFS('Zoho Dump'!$X$8:$X$3007,'Zoho Dump'!$P$8:$P$3007,$A30,'Zoho Dump'!$W$8:$W$3007,H$4,'Zoho Dump'!$T$8:$T$3007,"Overdue")+SUMIFS(Adjustments!$K$8:$K$207,Adjustments!$A$8:$A$207,$A30,Adjustments!$J$8:$J$207,H$4,Adjustments!$H$8:$H$207,"Overdue") -> 0 | I30: =SUMIFS('Zoho Dump'!$X$8:$X$3007,'Zoho Dump'!$P$8:$P$3007,$A30,'Zoho Dump'!$W$8:$W$3007,I$4,'Zoho Dump'!$T$8:$T$3007,"Pipeline")+SUMIFS(Adjustments!$K$8:$K$207,Adjustments!$A$8:$A$207,$A30,Adjustments!$J$8:$J$207,I$4,Adjustments!$H$8:$H$207,"Pipeline")+SUMIFS('Zoho Dump'!$X$8:$X$3007,'Zoho Dump'!$P$8:$P$3007,$A30,'Zoho Dump'!$W$8:$W$3007,I$4,'Zoho Dump'!$T$8:$T$3007,"Overdue")+SUMIFS(Adjustments!$K$8:$K$207,Adjustments!$A$8:$A$207,$A30,Adjustments!$J$8:$J$207,I$4,Adjustments!$H$8:$H$207,"Overdue") -> 0 | J30: =SUMIFS('Zoho Dump'!$X$8:$X$3007,'Zoho Dump'!$P$8:$P$3007,$A30,'Zoho Dump'!$W$8:$W$3007,J$4,'Zoho Dump'!$T$8:$T$3007,"Pipeline")+SUMIFS(Adjustments!$K$8:$K$207,Adjustments!$A$8:$A$207,$A30,Adjustments!$J$8:$J$207,J$4,Adjustments!$H$8:$H$207,"Pipeline")+SUMIFS('Zoho Dump'!$X$8:$X$3007,'Zoho Dump'!$P$8:$P$3007,$A30,'Zoho Dump'!$W$8:$W$3007,J$4,'Zoho Dump'!$T$8:$T$3007,"Overdue")+SUMIFS(Adjustments!$K$8:$K$207,Adjustments!$A$8:$A$207,$A30,Adjustments!$J$8:$J$207,J$4,Adjustments!$H$8:$H$207,"Overdue") -> 0 | ... N30: =SUMIFS('Zoho Dump'!$X$8:$X$3007,'Zoho Dump'!$P$8:$P$3007,$A30,'Zoho Dump'!$W$8:$W$3007,N$4,'Zoho Dump'!$T$8:$T$3007,"Pipeline")+SUMIFS(Adjustments!$K$8:$K$207,Adjustments!$A$8:$A$207,$A30,Adjustments!$J$8:$J$207,N$4,Adjustments!$H$8:$H$207,"Pipeline")+SUMIFS('Zoho Dump'!$X$8:$X$3007,'Zoho Dump'!$P$8:$P$3007,$A30,'Zoho Dump'!$W$8:$W$3007,N$4,'Zoho Dump'!$T$8:$T$3007,"Overdue")+SUMIFS(Adjustments!$K$8:$K$207,Adjustments!$A$8:$A$207,$A30,Adjustments!$J$8:$J$207,N$4,Adjustments!$H$8:$H$207,"Overdue") -> 0 | O30: =SUM(C30:N30) -> 1255.5
A31: =Settings!$A$15 -> Consulting | C31: =SUMIFS('Zoho Dump'!$X$8:$X$3007,'Zoho Dump'!$P$8:$P$3007,$A31,'Zoho Dump'!$W$8:$W$3007,C$4,'Zoho Dump'!$T$8:$T$3007,"Pipeline")+SUMIFS(Adjustments!$K$8:$K$207,Adjustments!$A$8:$A$207,$A31,Adjustments!$J$8:$J$207,C$4,Adjustments!$H$8:$H$207,"Pipeline")+SUMIFS('Zoho Dump'!$X$8:$X$3007,'Zoho Dump'!$P$8:$P$3007,$A31,'Zoho Dump'!$W$8:$W$3007,C$4,'Zoho Dump'!$T$8:$T$3007,"Overdue")+SUMIFS(Adjustments!$K$8:$K$207,Adjustments!$A$8:$A$207,$A31,Adjustments!$J$8:$J$207,C$4,Adjustments!$H$8:$H$207,"Overdue") -> 0 | D31: =SUMIFS('Zoho Dump'!$X$8:$X$3007,'Zoho Dump'!$P$8:$P$3007,$A31,'Zoho Dump'!$W$8:$W$3007,D$4,'Zoho Dump'!$T$8:$T$3007,"Pipeline")+SUMIFS(Adjustments!$K$8:$K$207,Adjustments!$A$8:$A$207,$A31,Adjustments!$J$8:$J$207,D$4,Adjustments!$H$8:$H$207,"Pipeline")+SUMIFS('Zoho Dump'!$X$8:$X$3007,'Zoho Dump'!$P$8:$P$3007,$A31,'Zoho Dump'!$W$8:$W$3007,D$4,'Zoho Dump'!$T$8:$T$3007,"Overdue")+SUMIFS(Adjustments!$K$8:$K$207,Adjustments!$A$8:$A$207,$A31,Adjustments!$J$8:$J$207,D$4,Adjustments!$H$8:$H$207,"Overdue") -> 0 | E31: =SUMIFS('Zoho Dump'!$X$8:$X$3007,'Zoho Dump'!$P$8:$P$3007,$A31,'Zoho Dump'!$W$8:$W$3007,E$4,'Zoho Dump'!$T$8:$T$3007,"Pipeline")+SUMIFS(Adjustments!$K$8:$K$207,Adjustments!$A$8:$A$207,$A31,Adjustments!$J$8:$J$207,E$4,Adjustments!$H$8:$H$207,"Pipeline")+SUMIFS('Zoho Dump'!$X$8:$X$3007,'Zoho Dump'!$P$8:$P$3007,$A31,'Zoho Dump'!$W$8:$W$3007,E$4,'Zoho Dump'!$T$8:$T$3007,"Overdue")+SUMIFS(Adjustments!$K$8:$K$207,Adjustments!$A$8:$A$207,$A31,Adjustments!$J$8:$J$207,E$4,Adjustments!$H$8:$H$207,"Overdue") -> 0 | F31: =SUMIFS('Zoho Dump'!$X$8:$X$3007,'Zoho Dump'!$P$8:$P$3007,$A31,'Zoho Dump'!$W$8:$W$3007,F$4,'Zoho Dump'!$T$8:$T$3007,"Pipeline")+SUMIFS(Adjustments!$K$8:$K$207,Adjustments!$A$8:$A$207,$A31,Adjustments!$J$8:$J$207,F$4,Adjustments!$H$8:$H$207,"Pipeline")+SUMIFS('Zoho Dump'!$X$8:$X$3007,'Zoho Dump'!$P$8:$P$3007,$A31,'Zoho Dump'!$W$8:$W$3007,F$4,'Zoho Dump'!$T$8:$T$3007,"Overdue")+SUMIFS(Adjustments!$K$8:$K$207,Adjustments!$A$8:$A$207,$A31,Adjustments!$J$8:$J$207,F$4,Adjustments!$H$8:$H$207,"Overdue") -> 0 | G31: =SUMIFS('Zoho Dump'!$X$8:$X$3007,'Zoho Dump'!$P$8:$P$3007,$A31,'Zoho Dump'!$W$8:$W$3007,G$4,'Zoho Dump'!$T$8:$T$3007,"Pipeline")+SUMIFS(Adjustments!$K$8:$K$207,Adjustments!$A$8:$A$207,$A31,Adjustments!$J$8:$J$207,G$4,Adjustments!$H$8:$H$207,"Pipeline")+SUMIFS('Zoho Dump'!$X$8:$X$3007,'Zoho Dump'!$P$8:$P$3007,$A31,'Zoho Dump'!$W$8:$W$3007,G$4,'Zoho Dump'!$T$8:$T$3007,"Overdue")+SUMIFS(Adjustments!$K$8:$K$207,Adjustments!$A$8:$A$207,$A31,Adjustments!$J$8:$J$207,G$4,Adjustments!$H$8:$H$207,"Overdue") -> 15000 | H31: =SUMIFS('Zoho Dump'!$X$8:$X$3007,'Zoho Dump'!$P$8:$P$3007,$A31,'Zoho Dump'!$W$8:$W$3007,H$4,'Zoho Dump'!$T$8:$T$3007,"Pipeline")+SUMIFS(Adjustments!$K$8:$K$207,Adjustments!$A$8:$A$207,$A31,Adjustments!$J$8:$J$207,H$4,Adjustments!$H$8:$H$207,"Pipeline")+SUMIFS('Zoho Dump'!$X$8:$X$3007,'Zoho Dump'!$P$8:$P$3007,$A31,'Zoho Dump'!$W$8:$W$3007,H$4,'Zoho Dump'!$T$8:$T$3007,"Overdue")+SUMIFS(Adjustments!$K$8:$K$207,Adjustments!$A$8:$A$207,$A31,Adjustments!$J$8:$J$207,H$4,Adjustments!$H$8:$H$207,"Overdue") -> 0 | I31: =SUMIFS('Zoho Dump'!$X$8:$X$3007,'Zoho Dump'!$P$8:$P$3007,$A31,'Zoho Dump'!$W$8:$W$3007,I$4,'Zoho Dump'!$T$8:$T$3007,"Pipeline")+SUMIFS(Adjustments!$K$8:$K$207,Adjustments!$A$8:$A$207,$A31,Adjustments!$J$8:$J$207,I$4,Adjustments!$H$8:$H$207,"Pipeline")+SUMIFS('Zoho Dump'!$X$8:$X$3007,'Zoho Dump'!$P$8:$P$3007,$A31,'Zoho Dump'!$W$8:$W$3007,I$4,'Zoho Dump'!$T$8:$T$3007,"Overdue")+SUMIFS(Adjustments!$K$8:$K$207,Adjustments!$A$8:$A$207,$A31,Adjustments!$J$8:$J$207,I$4,Adjustments!$H$8:$H$207,"Overdue") -> 0 | J31: =SUMIFS('Zoho Dump'!$X$8:$X$3007,'Zoho Dump'!$P$8:$P$3007,$A31,'Zoho Dump'!$W$8:$W$3007,J$4,'Zoho Dump'!$T$8:$T$3007,"Pipeline")+SUMIFS(Adjustments!$K$8:$K$207,Adjustments!$A$8:$A$207,$A31,Adjustments!$J$8:$J$207,J$4,Adjustments!$H$8:$H$207,"Pipeline")+SUMIFS('Zoho Dump'!$X$8:$X$3007,'Zoho Dump'!$P$8:$P$3007,$A31,'Zoho Dump'!$W$8:$W$3007,J$4,'Zoho Dump'!$T$8:$T$3007,"Overdue")+SUMIFS(Adjustments!$K$8:$K$207,Adjustments!$A$8:$A$207,$A31,Adjustments!$J$8:$J$207,J$4,Adjustments!$H$8:$H$207,"Overdue") -> 0 | ... N31: =SUMIFS('Zoho Dump'!$X$8:$X$3007,'Zoho Dump'!$P$8:$P$3007,$A31,'Zoho Dump'!$W$8:$W$3007,N$4,'Zoho Dump'!$T$8:$T$3007,"Pipeline")+SUMIFS(Adjustments!$K$8:$K$207,Adjustments!$A$8:$A$207,$A31,Adjustments!$J$8:$J$207,N$4,Adjustments!$H$8:$H$207,"Pipeline")+SUMIFS('Zoho Dump'!$X$8:$X$3007,'Zoho Dump'!$P$8:$P$3007,$A31,'Zoho Dump'!$W$8:$W$3007,N$4,'Zoho Dump'!$T$8:$T$3007,"Overdue")+SUMIFS(Adjustments!$K$8:$K$207,Adjustments!$A$8:$A$207,$A31,Adjustments!$J$8:$J$207,N$4,Adjustments!$H$8:$H$207,"Overdue") -> 0 | O31: =SUM(C31:N31) -> 15000
A32: =Settings!$A$16 -> Integration | C32: =SUMIFS('Zoho Dump'!$X$8:$X$3007,'Zoho Dump'!$P$8:$P$3007,$A32,'Zoho Dump'!$W$8:$W$3007,C$4,'Zoho Dump'!$T$8:$T$3007,"Pipeline")+SUMIFS(Adjustments!$K$8:$K$207,Adjustments!$A$8:$A$207,$A32,Adjustments!$J$8:$J$207,C$4,Adjustments!$H$8:$H$207,"Pipeline")+SUMIFS('Zoho Dump'!$X$8:$X$3007,'Zoho Dump'!$P$8:$P$3007,$A32,'Zoho Dump'!$W$8:$W$3007,C$4,'Zoho Dump'!$T$8:$T$3007,"Overdue")+SUMIFS(Adjustments!$K$8:$K$207,Adjustments!$A$8:$A$207,$A32,Adjustments!$J$8:$J$207,C$4,Adjustments!$H$8:$H$207,"Overdue") -> 0 | D32: =SUMIFS('Zoho Dump'!$X$8:$X$3007,'Zoho Dump'!$P$8:$P$3007,$A32,'Zoho Dump'!$W$8:$W$3007,D$4,'Zoho Dump'!$T$8:$T$3007,"Pipeline")+SUMIFS(Adjustments!$K$8:$K$207,Adjustments!$A$8:$A$207,$A32,Adjustments!$J$8:$J$207,D$4,Adjustments!$H$8:$H$207,"Pipeline")+SUMIFS('Zoho Dump'!$X$8:$X$3007,'Zoho Dump'!$P$8:$P$3007,$A32,'Zoho Dump'!$W$8:$W$3007,D$4,'Zoho Dump'!$T$8:$T$3007,"Overdue")+SUMIFS(Adjustments!$K$8:$K$207,Adjustments!$A$8:$A$207,$A32,Adjustments!$J$8:$J$207,D$4,Adjustments!$H$8:$H$207,"Overdue") -> 0 | E32: =SUMIFS('Zoho Dump'!$X$8:$X$3007,'Zoho Dump'!$P$8:$P$3007,$A32,'Zoho Dump'!$W$8:$W$3007,E$4,'Zoho Dump'!$T$8:$T$3007,"Pipeline")+SUMIFS(Adjustments!$K$8:$K$207,Adjustments!$A$8:$A$207,$A32,Adjustments!$J$8:$J$207,E$4,Adjustments!$H$8:$H$207,"Pipeline")+SUMIFS('Zoho Dump'!$X$8:$X$3007,'Zoho Dump'!$P$8:$P$3007,$A32,'Zoho Dump'!$W$8:$W$3007,E$4,'Zoho Dump'!$T$8:$T$3007,"Overdue")+SUMIFS(Adjustments!$K$8:$K$207,Adjustments!$A$8:$A$207,$A32,Adjustments!$J$8:$J$207,E$4,Adjustments!$H$8:$H$207,"Overdue") -> 0 | F32: =SUMIFS('Zoho Dump'!$X$8:$X$3007,'Zoho Dump'!$P$8:$P$3007,$A32,'Zoho Dump'!$W$8:$W$3007,F$4,'Zoho Dump'!$T$8:$T$3007,"Pipeline")+SUMIFS(Adjustments!$K$8:$K$207,Adjustments!$A$8:$A$207,$A32,Adjustments!$J$8:$J$207,F$4,Adjustments!$H$8:$H$207,"Pipeline")+SUMIFS('Zoho Dump'!$X$8:$X$3007,'Zoho Dump'!$P$8:$P$3007,$A32,'Zoho Dump'!$W$8:$W$3007,F$4,'Zoho Dump'!$T$8:$T$3007,"Overdue")+SUMIFS(Adjustments!$K$8:$K$207,Adjustments!$A$8:$A$207,$A32,Adjustments!$J$8:$J$207,F$4,Adjustments!$H$8:$H$207,"Overdue") -> 52346.7 | G32: =SUMIFS('Zoho Dump'!$X$8:$X$3007,'Zoho Dump'!$P$8:$P$3007,$A32,'Zoho Dump'!$W$8:$W$3007,G$4,'Zoho Dump'!$T$8:$T$3007,"Pipeline")+SUMIFS(Adjustments!$K$8:$K$207,Adjustments!$A$8:$A$207,$A32,Adjustments!$J$8:$J$207,G$4,Adjustments!$H$8:$H$207,"Pipeline")+SUMIFS('Zoho Dump'!$X$8:$X$3007,'Zoho Dump'!$P$8:$P$3007,$A32,'Zoho Dump'!$W$8:$W$3007,G$4,'Zoho Dump'!$T$8:$T$3007,"Overdue")+SUMIFS(Adjustments!$K$8:$K$207,Adjustments!$A$8:$A$207,$A32,Adjustments!$J$8:$J$207,G$4,Adjustments!$H$8:$H$207,"Overdue") -> 1653 | H32: =SUMIFS('Zoho Dump'!$X$8:$X$3007,'Zoho Dump'!$P$8:$P$3007,$A32,'Zoho Dump'!$W$8:$W$3007,H$4,'Zoho Dump'!$T$8:$T$3007,"Pipeline")+SUMIFS(Adjustments!$K$8:$K$207,Adjustments!$A$8:$A$207,$A32,Adjustments!$J$8:$J$207,H$4,Adjustments!$H$8:$H$207,"Pipeline")+SUMIFS('Zoho Dump'!$X$8:$X$3007,'Zoho Dump'!$P$8:$P$3007,$A32,'Zoho Dump'!$W$8:$W$3007,H$4,'Zoho Dump'!$T$8:$T$3007,"Overdue")+SUMIFS(Adjustments!$K$8:$K$207,Adjustments!$A$8:$A$207,$A32,Adjustments!$J$8:$J$207,H$4,Adjustments!$H$8:$H$207,"Overdue") -> 0 | I32: =SUMIFS('Zoho Dump'!$X$8:$X$3007,'Zoho Dump'!$P$8:$P$3007,$A32,'Zoho Dump'!$W$8:$W$3007,I$4,'Zoho Dump'!$T$8:$T$3007,"Pipeline")+SUMIFS(Adjustments!$K$8:$K$207,Adjustments!$A$8:$A$207,$A32,Adjustments!$J$8:$J$207,I$4,Adjustments!$H$8:$H$207,"Pipeline")+SUMIFS('Zoho Dump'!$X$8:$X$3007,'Zoho Dump'!$P$8:$P$3007,$A32,'Zoho Dump'!$W$8:$W$3007,I$4,'Zoho Dump'!$T$8:$T$3007,"Overdue")+SUMIFS(Adjustments!$K$8:$K$207,Adjustments!$A$8:$A$207,$A32,Adjustments!$J$8:$J$207,I$4,Adjustments!$H$8:$H$207,"Overdue") -> 0 | J32: =SUMIFS('Zoho Dump'!$X$8:$X$3007,'Zoho Dump'!$P$8:$P$3007,$A32,'Zoho Dump'!$W$8:$W$3007,J$4,'Zoho Dump'!$T$8:$T$3007,"Pipeline")+SUMIFS(Adjustments!$K$8:$K$207,Adjustments!$A$8:$A$207,$A32,Adjustments!$J$8:$J$207,J$4,Adjustments!$H$8:$H$207,"Pipeline")+SUMIFS('Zoho Dump'!$X$8:$X$3007,'Zoho Dump'!$P$8:$P$3007,$A32,'Zoho Dump'!$W$8:$W$3007,J$4,'Zoho Dump'!$T$8:$T$3007,"Overdue")+SUMIFS(Adjustments!$K$8:$K$207,Adjustments!$A$8:$A$207,$A32,Adjustments!$J$8:$J$207,J$4,Adjustments!$H$8:$H$207,"Overdue") -> 0 | ... N32: =SUMIFS('Zoho Dump'!$X$8:$X$3007,'Zoho Dump'!$P$8:$P$3007,$A32,'Zoho Dump'!$W$8:$W$3007,N$4,'Zoho Dump'!$T$8:$T$3007,"Pipeline")+SUMIFS(Adjustments!$K$8:$K$207,Adjustments!$A$8:$A$207,$A32,Adjustments!$J$8:$J$207,N$4,Adjustments!$H$8:$H$207,"Pipeline")+SUMIFS('Zoho Dump'!$X$8:$X$3007,'Zoho Dump'!$P$8:$P$3007,$A32,'Zoho Dump'!$W$8:$W$3007,N$4,'Zoho Dump'!$T$8:$T$3007,"Overdue")+SUMIFS(Adjustments!$K$8:$K$207,Adjustments!$A$8:$A$207,$A32,Adjustments!$J$8:$J$207,N$4,Adjustments!$H$8:$H$207,"Overdue") -> 0 | O32: =SUM(C32:N32) -> 53999.7
A33: =Settings!$A$17 -> Admin | C33: =SUMIFS('Zoho Dump'!$X$8:$X$3007,'Zoho Dump'!$P$8:$P$3007,$A33,'Zoho Dump'!$W$8:$W$3007,C$4,'Zoho Dump'!$T$8:$T$3007,"Pipeline")+SUMIFS(Adjustments!$K$8:$K$207,Adjustments!$A$8:$A$207,$A33,Adjustments!$J$8:$J$207,C$4,Adjustments!$H$8:$H$207,"Pipeline")+SUMIFS('Zoho Dump'!$X$8:$X$3007,'Zoho Dump'!$P$8:$P$3007,$A33,'Zoho Dump'!$W$8:$W$3007,C$4,'Zoho Dump'!$T$8:$T$3007,"Overdue")+SUMIFS(Adjustments!$K$8:$K$207,Adjustments!$A$8:$A$207,$A33,Adjustments!$J$8:$J$207,C$4,Adjustments!$H$8:$H$207,"Overdue") -> 0 | D33: =SUMIFS('Zoho Dump'!$X$8:$X$3007,'Zoho Dump'!$P$8:$P$3007,$A33,'Zoho Dump'!$W$8:$W$3007,D$4,'Zoho Dump'!$T$8:$T$3007,"Pipeline")+SUMIFS(Adjustments!$K$8:$K$207,Adjustments!$A$8:$A$207,$A33,Adjustments!$J$8:$J$207,D$4,Adjustments!$H$8:$H$207,"Pipeline")+SUMIFS('Zoho Dump'!$X$8:$X$3007,'Zoho Dump'!$P$8:$P$3007,$A33,'Zoho Dump'!$W$8:$W$3007,D$4,'Zoho Dump'!$T$8:$T$3007,"Overdue")+SUMIFS(Adjustments!$K$8:$K$207,Adjustments!$A$8:$A$207,$A33,Adjustments!$J$8:$J$207,D$4,Adjustments!$H$8:$H$207,"Overdue") -> 0 | E33: =SUMIFS('Zoho Dump'!$X$8:$X$3007,'Zoho Dump'!$P$8:$P$3007,$A33,'Zoho Dump'!$W$8:$W$3007,E$4,'Zoho Dump'!$T$8:$T$3007,"Pipeline")+SUMIFS(Adjustments!$K$8:$K$207,Adjustments!$A$8:$A$207,$A33,Adjustments!$J$8:$J$207,E$4,Adjustments!$H$8:$H$207,"Pipeline")+SUMIFS('Zoho Dump'!$X$8:$X$3007,'Zoho Dump'!$P$8:$P$3007,$A33,'Zoho Dump'!$W$8:$W$3007,E$4,'Zoho Dump'!$T$8:$T$3007,"Overdue")+SUMIFS(Adjustments!$K$8:$K$207,Adjustments!$A$8:$A$207,$A33,Adjustments!$J$8:$J$207,E$4,Adjustments!$H$8:$H$207,"Overdue") -> 0 | F33: =SUMIFS('Zoho Dump'!$X$8:$X$3007,'Zoho Dump'!$P$8:$P$3007,$A33,'Zoho Dump'!$W$8:$W$3007,F$4,'Zoho Dump'!$T$8:$T$3007,"Pipeline")+SUMIFS(Adjustments!$K$8:$K$207,Adjustments!$A$8:$A$207,$A33,Adjustments!$J$8:$J$207,F$4,Adjustments!$H$8:$H$207,"Pipeline")+SUMIFS('Zoho Dump'!$X$8:$X$3007,'Zoho Dump'!$P$8:$P$3007,$A33,'Zoho Dump'!$W$8:$W$3007,F$4,'Zoho Dump'!$T$8:$T$3007,"Overdue")+SUMIFS(Adjustments!$K$8:$K$207,Adjustments!$A$8:$A$207,$A33,Adjustments!$J$8:$J$207,F$4,Adjustments!$H$8:$H$207,"Overdue") -> 0 | G33: =SUMIFS('Zoho Dump'!$X$8:$X$3007,'Zoho Dump'!$P$8:$P$3007,$A33,'Zoho Dump'!$W$8:$W$3007,G$4,'Zoho Dump'!$T$8:$T$3007,"Pipeline")+SUMIFS(Adjustments!$K$8:$K$207,Adjustments!$A$8:$A$207,$A33,Adjustments!$J$8:$J$207,G$4,Adjustments!$H$8:$H$207,"Pipeline")+SUMIFS('Zoho Dump'!$X$8:$X$3007,'Zoho Dump'!$P$8:$P$3007,$A33,'Zoho Dump'!$W$8:$W$3007,G$4,'Zoho Dump'!$T$8:$T$3007,"Overdue")+SUMIFS(Adjustments!$K$8:$K$207,Adjustments!$A$8:$A$207,$A33,Adjustments!$J$8:$J$207,G$4,Adjustments!$H$8:$H$207,"Overdue") -> 0 | H33: =SUMIFS('Zoho Dump'!$X$8:$X$3007,'Zoho Dump'!$P$8:$P$3007,$A33,'Zoho Dump'!$W$8:$W$3007,H$4,'Zoho Dump'!$T$8:$T$3007,"Pipeline")+SUMIFS(Adjustments!$K$8:$K$207,Adjustments!$A$8:$A$207,$A33,Adjustments!$J$8:$J$207,H$4,Adjustments!$H$8:$H$207,"Pipeline")+SUMIFS('Zoho Dump'!$X$8:$X$3007,'Zoho Dump'!$P$8:$P$3007,$A33,'Zoho Dump'!$W$8:$W$3007,H$4,'Zoho Dump'!$T$8:$T$3007,"Overdue")+SUMIFS(Adjustments!$K$8:$K$207,Adjustments!$A$8:$A$207,$A33,Adjustments!$J$8:$J$207,H$4,Adjustments!$H$8:$H$207,"Overdue") -> 0 | I33: =SUMIFS('Zoho Dump'!$X$8:$X$3007,'Zoho Dump'!$P$8:$P$3007,$A33,'Zoho Dump'!$W$8:$W$3007,I$4,'Zoho Dump'!$T$8:$T$3007,"Pipeline")+SUMIFS(Adjustments!$K$8:$K$207,Adjustments!$A$8:$A$207,$A33,Adjustments!$J$8:$J$207,I$4,Adjustments!$H$8:$H$207,"Pipeline")+SUMIFS('Zoho Dump'!$X$8:$X$3007,'Zoho Dump'!$P$8:$P$3007,$A33,'Zoho Dump'!$W$8:$W$3007,I$4,'Zoho Dump'!$T$8:$T$3007,"Overdue")+SUMIFS(Adjustments!$K$8:$K$207,Adjustments!$A$8:$A$207,$A33,Adjustments!$J$8:$J$207,I$4,Adjustments!$H$8:$H$207,"Overdue") -> 0 | J33: =SUMIFS('Zoho Dump'!$X$8:$X$3007,'Zoho Dump'!$P$8:$P$3007,$A33,'Zoho Dump'!$W$8:$W$3007,J$4,'Zoho Dump'!$T$8:$T$3007,"Pipeline")+SUMIFS(Adjustments!$K$8:$K$207,Adjustments!$A$8:$A$207,$A33,Adjustments!$J$8:$J$207,J$4,Adjustments!$H$8:$H$207,"Pipeline")+SUMIFS('Zoho Dump'!$X$8:$X$3007,'Zoho Dump'!$P$8:$P$3007,$A33,'Zoho Dump'!$W$8:$W$3007,J$4,'Zoho Dump'!$T$8:$T$3007,"Overdue")+SUMIFS(Adjustments!$K$8:$K$207,Adjustments!$A$8:$A$207,$A33,Adjustments!$J$8:$J$207,J$4,Adjustments!$H$8:$H$207,"Overdue") -> 0 | ... N33: =SUMIFS('Zoho Dump'!$X$8:$X$3007,'Zoho Dump'!$P$8:$P$3007,$A33,'Zoho Dump'!$W$8:$W$3007,N$4,'Zoho Dump'!$T$8:$T$3007,"Pipeline")+SUMIFS(Adjustments!$K$8:$K$207,Adjustments!$A$8:$A$207,$A33,Adjustments!$J$8:$J$207,N$4,Adjustments!$H$8:$H$207,"Pipeline")+SUMIFS('Zoho Dump'!$X$8:$X$3007,'Zoho Dump'!$P$8:$P$3007,$A33,'Zoho Dump'!$W$8:$W$3007,N$4,'Zoho Dump'!$T$8:$T$3007,"Overdue")+SUMIFS(Adjustments!$K$8:$K$207,Adjustments!$A$8:$A$207,$A33,Adjustments!$J$8:$J$207,N$4,Adjustments!$H$8:$H$207,"Overdue") -> 0 | O33: =SUM(C33:N33) -> 0
A34: =Settings!$A$18 -> Unallocated | C34: =SUMIFS('Zoho Dump'!$X$8:$X$3007,'Zoho Dump'!$P$8:$P$3007,$A34,'Zoho Dump'!$W$8:$W$3007,C$4,'Zoho Dump'!$T$8:$T$3007,"Pipeline")+SUMIFS(Adjustments!$K$8:$K$207,Adjustments!$A$8:$A$207,$A34,Adjustments!$J$8:$J$207,C$4,Adjustments!$H$8:$H$207,"Pipeline")+SUMIFS('Zoho Dump'!$X$8:$X$3007,'Zoho Dump'!$P$8:$P$3007,$A34,'Zoho Dump'!$W$8:$W$3007,C$4,'Zoho Dump'!$T$8:$T$3007,"Overdue")+SUMIFS(Adjustments!$K$8:$K$207,Adjustments!$A$8:$A$207,$A34,Adjustments!$J$8:$J$207,C$4,Adjustments!$H$8:$H$207,"Overdue") -> 0 | D34: =SUMIFS('Zoho Dump'!$X$8:$X$3007,'Zoho Dump'!$P$8:$P$3007,$A34,'Zoho Dump'!$W$8:$W$3007,D$4,'Zoho Dump'!$T$8:$T$3007,"Pipeline")+SUMIFS(Adjustments!$K$8:$K$207,Adjustments!$A$8:$A$207,$A34,Adjustments!$J$8:$J$207,D$4,Adjustments!$H$8:$H$207,"Pipeline")+SUMIFS('Zoho Dump'!$X$8:$X$3007,'Zoho Dump'!$P$8:$P$3007,$A34,'Zoho Dump'!$W$8:$W$3007,D$4,'Zoho Dump'!$T$8:$T$3007,"Overdue")+SUMIFS(Adjustments!$K$8:$K$207,Adjustments!$A$8:$A$207,$A34,Adjustments!$J$8:$J$207,D$4,Adjustments!$H$8:$H$207,"Overdue") -> 0 | E34: =SUMIFS('Zoho Dump'!$X$8:$X$3007,'Zoho Dump'!$P$8:$P$3007,$A34,'Zoho Dump'!$W$8:$W$3007,E$4,'Zoho Dump'!$T$8:$T$3007,"Pipeline")+SUMIFS(Adjustments!$K$8:$K$207,Adjustments!$A$8:$A$207,$A34,Adjustments!$J$8:$J$207,E$4,Adjustments!$H$8:$H$207,"Pipeline")+SUMIFS('Zoho Dump'!$X$8:$X$3007,'Zoho Dump'!$P$8:$P$3007,$A34,'Zoho Dump'!$W$8:$W$3007,E$4,'Zoho Dump'!$T$8:$T$3007,"Overdue")+SUMIFS(Adjustments!$K$8:$K$207,Adjustments!$A$8:$A$207,$A34,Adjustments!$J$8:$J$207,E$4,Adjustments!$H$8:$H$207,"Overdue") -> 0 | F34: =SUMIFS('Zoho Dump'!$X$8:$X$3007,'Zoho Dump'!$P$8:$P$3007,$A34,'Zoho Dump'!$W$8:$W$3007,F$4,'Zoho Dump'!$T$8:$T$3007,"Pipeline")+SUMIFS(Adjustments!$K$8:$K$207,Adjustments!$A$8:$A$207,$A34,Adjustments!$J$8:$J$207,F$4,Adjustments!$H$8:$H$207,"Pipeline")+SUMIFS('Zoho Dump'!$X$8:$X$3007,'Zoho Dump'!$P$8:$P$3007,$A34,'Zoho Dump'!$W$8:$W$3007,F$4,'Zoho Dump'!$T$8:$T$3007,"Overdue")+SUMIFS(Adjustments!$K$8:$K$207,Adjustments!$A$8:$A$207,$A34,Adjustments!$J$8:$J$207,F$4,Adjustments!$H$8:$H$207,"Overdue") -> 0 | G34: =SUMIFS('Zoho Dump'!$X$8:$X$3007,'Zoho Dump'!$P$8:$P$3007,$A34,'Zoho Dump'!$W$8:$W$3007,G$4,'Zoho Dump'!$T$8:$T$3007,"Pipeline")+SUMIFS(Adjustments!$K$8:$K$207,Adjustments!$A$8:$A$207,$A34,Adjustments!$J$8:$J$207,G$4,Adjustments!$H$8:$H$207,"Pipeline")+SUMIFS('Zoho Dump'!$X$8:$X$3007,'Zoho Dump'!$P$8:$P$3007,$A34,'Zoho Dump'!$W$8:$W$3007,G$4,'Zoho Dump'!$T$8:$T$3007,"Overdue")+SUMIFS(Adjustments!$K$8:$K$207,Adjustments!$A$8:$A$207,$A34,Adjustments!$J$8:$J$207,G$4,Adjustments!$H$8:$H$207,"Overdue") -> 0 | H34: =SUMIFS('Zoho Dump'!$X$8:$X$3007,'Zoho Dump'!$P$8:$P$3007,$A34,'Zoho Dump'!$W$8:$W$3007,H$4,'Zoho Dump'!$T$8:$T$3007,"Pipeline")+SUMIFS(Adjustments!$K$8:$K$207,Adjustments!$A$8:$A$207,$A34,Adjustments!$J$8:$J$207,H$4,Adjustments!$H$8:$H$207,"Pipeline")+SUMIFS('Zoho Dump'!$X$8:$X$3007,'Zoho Dump'!$P$8:$P$3007,$A34,'Zoho Dump'!$W$8:$W$3007,H$4,'Zoho Dump'!$T$8:$T$3007,"Overdue")+SUMIFS(Adjustments!$K$8:$K$207,Adjustments!$A$8:$A$207,$A34,Adjustments!$J$8:$J$207,H$4,Adjustments!$H$8:$H$207,"Overdue") -> 0 | I34: =SUMIFS('Zoho Dump'!$X$8:$X$3007,'Zoho Dump'!$P$8:$P$3007,$A34,'Zoho Dump'!$W$8:$W$3007,I$4,'Zoho Dump'!$T$8:$T$3007,"Pipeline")+SUMIFS(Adjustments!$K$8:$K$207,Adjustments!$A$8:$A$207,$A34,Adjustments!$J$8:$J$207,I$4,Adjustments!$H$8:$H$207,"Pipeline")+SUMIFS('Zoho Dump'!$X$8:$X$3007,'Zoho Dump'!$P$8:$P$3007,$A34,'Zoho Dump'!$W$8:$W$3007,I$4,'Zoho Dump'!$T$8:$T$3007,"Overdue")+SUMIFS(Adjustments!$K$8:$K$207,Adjustments!$A$8:$A$207,$A34,Adjustments!$J$8:$J$207,I$4,Adjustments!$H$8:$H$207,"Overdue") -> 0 | J34: =SUMIFS('Zoho Dump'!$X$8:$X$3007,'Zoho Dump'!$P$8:$P$3007,$A34,'Zoho Dump'!$W$8:$W$3007,J$4,'Zoho Dump'!$T$8:$T$3007,"Pipeline")+SUMIFS(Adjustments!$K$8:$K$207,Adjustments!$A$8:$A$207,$A34,Adjustments!$J$8:$J$207,J$4,Adjustments!$H$8:$H$207,"Pipeline")+SUMIFS('Zoho Dump'!$X$8:$X$3007,'Zoho Dump'!$P$8:$P$3007,$A34,'Zoho Dump'!$W$8:$W$3007,J$4,'Zoho Dump'!$T$8:$T$3007,"Overdue")+SUMIFS(Adjustments!$K$8:$K$207,Adjustments!$A$8:$A$207,$A34,Adjustments!$J$8:$J$207,J$4,Adjustments!$H$8:$H$207,"Overdue") -> 0 | ... N34: =SUMIFS('Zoho Dump'!$X$8:$X$3007,'Zoho Dump'!$P$8:$P$3007,$A34,'Zoho Dump'!$W$8:$W$3007,N$4,'Zoho Dump'!$T$8:$T$3007,"Pipeline")+SUMIFS(Adjustments!$K$8:$K$207,Adjustments!$A$8:$A$207,$A34,Adjustments!$J$8:$J$207,N$4,Adjustments!$H$8:$H$207,"Pipeline")+SUMIFS('Zoho Dump'!$X$8:$X$3007,'Zoho Dump'!$P$8:$P$3007,$A34,'Zoho Dump'!$W$8:$W$3007,N$4,'Zoho Dump'!$T$8:$T$3007,"Overdue")+SUMIFS(Adjustments!$K$8:$K$207,Adjustments!$A$8:$A$207,$A34,Adjustments!$J$8:$J$207,N$4,Adjustments!$H$8:$H$207,"Overdue") -> 0 | O34: =SUM(C34:N34) -> 0
A35: Total | C35: =SUM(C28:C34) -> 0 | D35: =SUM(D28:D34) -> 0 | E35: =SUM(E28:E34) -> 0 | F35: =SUM(F28:F34) -> 186374.4 | G35: =SUM(G28:G34) -> 77973.6 | H35: =SUM(H28:H34) -> 21270.7 | I35: =SUM(I28:I34) -> 224 | J35: =SUM(J28:J34) -> 54100 | ... O35: =SUM(O28:O34) -> 767799.7
A37: Forecast | B37: Actuals to date, then backlog plus weighted pipeline
A38: =Settings!$A$12 -> Onsite | C38: =IF(C$4<=Settings!$B$5,C8,C18+C28) -> 0 | D38: =IF(D$4<=Settings!$B$5,D8,D18+D28) -> 0 | E38: =IF(E$4<=Settings!$B$5,E8,E18+E28) -> 0 | F38: =IF(F$4<=Settings!$B$5,F8,F18+F28) -> 17000 | G38: =IF(G$4<=Settings!$B$5,G8,G18+G28) -> 0 | H38: =IF(H$4<=Settings!$B$5,H8,H18+H28) -> 0 | I38: =IF(I$4<=Settings!$B$5,I8,I18+I28) -> 0 | J38: =IF(J$4<=Settings!$B$5,J8,J18+J28) -> 52500 | ... N38: =IF(N$4<=Settings!$B$5,N8,N18+N28) -> 0 | O38: =SUM(C38:N38) -> 69500
A39: =Settings!$A$13 -> Production | C39: =IF(C$4<=Settings!$B$5,C9,C19+C29) -> 0 | D39: =IF(D$4<=Settings!$B$5,D9,D19+D29) -> 0 | E39: =IF(E$4<=Settings!$B$5,E9,E19+E29) -> 0 | F39: =IF(F$4<=Settings!$B$5,F9,F19+F29) -> 173398.2 | G39: =IF(G$4<=Settings!$B$5,G9,G19+G29) -> 74873.6 | H39: =IF(H$4<=Settings!$B$5,H9,H19+H29) -> 24151.7 | I39: =IF(I$4<=Settings!$B$5,I9,I19+I29) -> 224 | J39: =IF(J$4<=Settings!$B$5,J9,J19+J29) -> 1600 | ... N39: =IF(N$4<=Settings!$B$5,N9,N19+N29) -> 0 | O39: =SUM(C39:N39) -> 702104.5
A40: =Settings!$A$14 -> Video | C40: =IF(C$4<=Settings!$B$5,C10,C20+C30) -> 0 | D40: =IF(D$4<=Settings!$B$5,D10,D20+D30) -> 0 | E40: =IF(E$4<=Settings!$B$5,E10,E20+E30) -> 0 | F40: =IF(F$4<=Settings!$B$5,F10,F20+F30) -> 1255.5 | G40: =IF(G$4<=Settings!$B$5,G10,G20+G30) -> 11342 | H40: =IF(H$4<=Settings!$B$5,H10,H20+H30) -> 0 | I40: =IF(I$4<=Settings!$B$5,I10,I20+I30) -> 0 | J40: =IF(J$4<=Settings!$B$5,J10,J20+J30) -> 0 | ... N40: =IF(N$4<=Settings!$B$5,N10,N20+N30) -> 0 | O40: =SUM(C40:N40) -> 12597.5
A41: =Settings!$A$15 -> Consulting | C41: =IF(C$4<=Settings!$B$5,C11,C21+C31) -> 0 | D41: =IF(D$4<=Settings!$B$5,D11,D21+D31) -> 0 | E41: =IF(E$4<=Settings!$B$5,E11,E21+E31) -> 0 | F41: =IF(F$4<=Settings!$B$5,F11,F21+F31) -> 0 | G41: =IF(G$4<=Settings!$B$5,G11,G21+G31) -> 15000 | H41: =IF(H$4<=Settings!$B$5,H11,H21+H31) -> 0 | I41: =IF(I$4<=Settings!$B$5,I11,I21+I31) -> 0 | J41: =IF(J$4<=Settings!$B$5,J11,J21+J31) -> 0 | ... N41: =IF(N$4<=Settings!$B$5,N11,N21+N31) -> 0 | O41: =SUM(C41:N41) -> 15000
A42: =Settings!$A$16 -> Integration | C42: =IF(C$4<=Settings!$B$5,C12,C22+C32) -> 0 | D42: =IF(D$4<=Settings!$B$5,D12,D22+D32) -> 0 | E42: =IF(E$4<=Settings!$B$5,E12,E22+E32) -> 0 | F42: =IF(F$4<=Settings!$B$5,F12,F22+F32) -> 52346.7 | G42: =IF(G$4<=Settings!$B$5,G12,G22+G32) -> 1653 | H42: =IF(H$4<=Settings!$B$5,H12,H22+H32) -> 0 | I42: =IF(I$4<=Settings!$B$5,I12,I22+I32) -> 0 | J42: =IF(J$4<=Settings!$B$5,J12,J22+J32) -> 0 | ... N42: =IF(N$4<=Settings!$B$5,N12,N22+N32) -> 0 | O42: =SUM(C42:N42) -> 53999.7
A43: =Settings!$A$17 -> Admin | C43: =IF(C$4<=Settings!$B$5,C13,C23+C33) -> 0 | D43: =IF(D$4<=Settings!$B$5,D13,D23+D33) -> 0 | E43: =IF(E$4<=Settings!$B$5,E13,E23+E33) -> 0 | F43: =IF(F$4<=Settings!$B$5,F13,F23+F33) -> 0 | G43: =IF(G$4<=Settings!$B$5,G13,G23+G33) -> 0 | H43: =IF(H$4<=Settings!$B$5,H13,H23+H33) -> 0 | I43: =IF(I$4<=Settings!$B$5,I13,I23+I33) -> 0 | J43: =IF(J$4<=Settings!$B$5,J13,J23+J33) -> 0 | ... N43: =IF(N$4<=Settings!$B$5,N13,N23+N33) -> 0 | O43: =SUM(C43:N43) -> 0
A44: =Settings!$A$18 -> Unallocated | C44: =IF(C$4<=Settings!$B$5,C14,C24+C34) -> 0 | D44: =IF(D$4<=Settings!$B$5,D14,D24+D34) -> 0 | E44: =IF(E$4<=Settings!$B$5,E14,E24+E34) -> 0 | F44: =IF(F$4<=Settings!$B$5,F14,F24+F34) -> 0 | G44: =IF(G$4<=Settings!$B$5,G14,G24+G34) -> 0 | H44: =IF(H$4<=Settings!$B$5,H14,H24+H34) -> 0 | I44: =IF(I$4<=Settings!$B$5,I14,I24+I34) -> 0 | J44: =IF(J$4<=Settings!$B$5,J14,J24+J34) -> 0 | ... N44: =IF(N$4<=Settings!$B$5,N14,N24+N34) -> 0 | O44: =SUM(C44:N44) -> 0
A45: Total | C45: =SUM(C38:C44) -> 0 | D45: =SUM(D38:D44) -> 0 | E45: =SUM(E38:E44) -> 0 | F45: =SUM(F38:F44) -> 244000.4 | G45: =SUM(G38:G44) -> 102868.6 | H45: =SUM(H38:H44) -> 24151.7 | I45: =SUM(I38:I44) -> 224 | J45: =SUM(J38:J44) -> 54100 | ... O45: =SUM(O38:O44) -> 853201.7
A47: If pipeline falls through | B47: Actuals, then backlog plus pipeline at the stress case rate on the Dashboard
A48: =Settings!$A$12 -> Onsite | C48: =IF(C$4<=Settings!$B$5,C8,SUMIFS('Zoho Dump'!$Z$8:$Z$3007,'Zoho Dump'!$P$8:$P$3007,$A48,'Zoho Dump'!$W$8:$W$3007,C$4)+SUMIFS(Adjustments!$M$8:$M$207,Adjustments!$A$8:$A$207,$A48,Adjustments!$J$8:$J$207,C$4)) -> 0 | D48: =IF(D$4<=Settings!$B$5,D8,SUMIFS('Zoho Dump'!$Z$8:$Z$3007,'Zoho Dump'!$P$8:$P$3007,$A48,'Zoho Dump'!$W$8:$W$3007,D$4)+SUMIFS(Adjustments!$M$8:$M$207,Adjustments!$A$8:$A$207,$A48,Adjustments!$J$8:$J$207,D$4)) -> 0 | E48: =IF(E$4<=Settings!$B$5,E8,SUMIFS('Zoho Dump'!$Z$8:$Z$3007,'Zoho Dump'!$P$8:$P$3007,$A48,'Zoho Dump'!$W$8:$W$3007,E$4)+SUMIFS(Adjustments!$M$8:$M$207,Adjustments!$A$8:$A$207,$A48,Adjustments!$J$8:$J$207,E$4)) -> 0 | F48: =IF(F$4<=Settings!$B$5,F8,SUMIFS('Zoho Dump'!$Z$8:$Z$3007,'Zoho Dump'!$P$8:$P$3007,$A48,'Zoho Dump'!$W$8:$W$3007,F$4)+SUMIFS(Adjustments!$M$8:$M$207,Adjustments!$A$8:$A$207,$A48,Adjustments!$J$8:$J$207,F$4)) -> 17000 | G48: =IF(G$4<=Settings!$B$5,G8,SUMIFS('Zoho Dump'!$Z$8:$Z$3007,'Zoho Dump'!$P$8:$P$3007,$A48,'Zoho Dump'!$W$8:$W$3007,G$4)+SUMIFS(Adjustments!$M$8:$M$207,Adjustments!$A$8:$A$207,$A48,Adjustments!$J$8:$J$207,G$4)) -> 0 | H48: =IF(H$4<=Settings!$B$5,H8,SUMIFS('Zoho Dump'!$Z$8:$Z$3007,'Zoho Dump'!$P$8:$P$3007,$A48,'Zoho Dump'!$W$8:$W$3007,H$4)+SUMIFS(Adjustments!$M$8:$M$207,Adjustments!$A$8:$A$207,$A48,Adjustments!$J$8:$J$207,H$4)) -> 0 | I48: =IF(I$4<=Settings!$B$5,I8,SUMIFS('Zoho Dump'!$Z$8:$Z$3007,'Zoho Dump'!$P$8:$P$3007,$A48,'Zoho Dump'!$W$8:$W$3007,I$4)+SUMIFS(Adjustments!$M$8:$M$207,Adjustments!$A$8:$A$207,$A48,Adjustments!$J$8:$J$207,I$4)) -> 0 | J48: =IF(J$4<=Settings!$B$5,J8,SUMIFS('Zoho Dump'!$Z$8:$Z$3007,'Zoho Dump'!$P$8:$P$3007,$A48,'Zoho Dump'!$W$8:$W$3007,J$4)+SUMIFS(Adjustments!$M$8:$M$207,Adjustments!$A$8:$A$207,$A48,Adjustments!$J$8:$J$207,J$4)) -> 0 | ... N48: =IF(N$4<=Settings!$B$5,N8,SUMIFS('Zoho Dump'!$Z$8:$Z$3007,'Zoho Dump'!$P$8:$P$3007,$A48,'Zoho Dump'!$W$8:$W$3007,N$4)+SUMIFS(Adjustments!$M$8:$M$207,Adjustments!$A$8:$A$207,$A48,Adjustments!$J$8:$J$207,N$4)) -> 0 | O48: =SUM(C48:N48) -> 17000
A49: =Settings!$A$13 -> Production | C49: =IF(C$4<=Settings!$B$5,C9,SUMIFS('Zoho Dump'!$Z$8:$Z$3007,'Zoho Dump'!$P$8:$P$3007,$A49,'Zoho Dump'!$W$8:$W$3007,C$4)+SUMIFS(Adjustments!$M$8:$M$207,Adjustments!$A$8:$A$207,$A49,Adjustments!$J$8:$J$207,C$4)) -> 0 | D49: =IF(D$4<=Settings!$B$5,D9,SUMIFS('Zoho Dump'!$Z$8:$Z$3007,'Zoho Dump'!$P$8:$P$3007,$A49,'Zoho Dump'!$W$8:$W$3007,D$4)+SUMIFS(Adjustments!$M$8:$M$207,Adjustments!$A$8:$A$207,$A49,Adjustments!$J$8:$J$207,D$4)) -> 0 | E49: =IF(E$4<=Settings!$B$5,E9,SUMIFS('Zoho Dump'!$Z$8:$Z$3007,'Zoho Dump'!$P$8:$P$3007,$A49,'Zoho Dump'!$W$8:$W$3007,E$4)+SUMIFS(Adjustments!$M$8:$M$207,Adjustments!$A$8:$A$207,$A49,Adjustments!$J$8:$J$207,E$4)) -> 0 | F49: =IF(F$4<=Settings!$B$5,F9,SUMIFS('Zoho Dump'!$Z$8:$Z$3007,'Zoho Dump'!$P$8:$P$3007,$A49,'Zoho Dump'!$W$8:$W$3007,F$4)+SUMIFS(Adjustments!$M$8:$M$207,Adjustments!$A$8:$A$207,$A49,Adjustments!$J$8:$J$207,F$4)) -> 40626 | G49: =IF(G$4<=Settings!$B$5,G9,SUMIFS('Zoho Dump'!$Z$8:$Z$3007,'Zoho Dump'!$P$8:$P$3007,$A49,'Zoho Dump'!$W$8:$W$3007,G$4)+SUMIFS(Adjustments!$M$8:$M$207,Adjustments!$A$8:$A$207,$A49,Adjustments!$J$8:$J$207,G$4)) -> 13553 | H49: =IF(H$4<=Settings!$B$5,H9,SUMIFS('Zoho Dump'!$Z$8:$Z$3007,'Zoho Dump'!$P$8:$P$3007,$A49,'Zoho Dump'!$W$8:$W$3007,H$4)+SUMIFS(Adjustments!$M$8:$M$207,Adjustments!$A$8:$A$207,$A49,Adjustments!$J$8:$J$207,H$4)) -> 2881 | I49: =IF(I$4<=Settings!$B$5,I9,SUMIFS('Zoho Dump'!$Z$8:$Z$3007,'Zoho Dump'!$P$8:$P$3007,$A49,'Zoho Dump'!$W$8:$W$3007,I$4)+SUMIFS(Adjustments!$M$8:$M$207,Adjustments!$A$8:$A$207,$A49,Adjustments!$J$8:$J$207,I$4)) -> 0 | J49: =IF(J$4<=Settings!$B$5,J9,SUMIFS('Zoho Dump'!$Z$8:$Z$3007,'Zoho Dump'!$P$8:$P$3007,$A49,'Zoho Dump'!$W$8:$W$3007,J$4)+SUMIFS(Adjustments!$M$8:$M$207,Adjustments!$A$8:$A$207,$A49,Adjustments!$J$8:$J$207,J$4)) -> 0 | ... N49: =IF(N$4<=Settings!$B$5,N9,SUMIFS('Zoho Dump'!$Z$8:$Z$3007,'Zoho Dump'!$P$8:$P$3007,$A49,'Zoho Dump'!$W$8:$W$3007,N$4)+SUMIFS(Adjustments!$M$8:$M$207,Adjustments!$A$8:$A$207,$A49,Adjustments!$J$8:$J$207,N$4)) -> 0 | O49: =SUM(C49:N49) -> 57060
A50: =Settings!$A$14 -> Video | C50: =IF(C$4<=Settings!$B$5,C10,SUMIFS('Zoho Dump'!$Z$8:$Z$3007,'Zoho Dump'!$P$8:$P$3007,$A50,'Zoho Dump'!$W$8:$W$3007,C$4)+SUMIFS(Adjustments!$M$8:$M$207,Adjustments!$A$8:$A$207,$A50,Adjustments!$J$8:$J$207,C$4)) -> 0 | D50: =IF(D$4<=Settings!$B$5,D10,SUMIFS('Zoho Dump'!$Z$8:$Z$3007,'Zoho Dump'!$P$8:$P$3007,$A50,'Zoho Dump'!$W$8:$W$3007,D$4)+SUMIFS(Adjustments!$M$8:$M$207,Adjustments!$A$8:$A$207,$A50,Adjustments!$J$8:$J$207,D$4)) -> 0 | E50: =IF(E$4<=Settings!$B$5,E10,SUMIFS('Zoho Dump'!$Z$8:$Z$3007,'Zoho Dump'!$P$8:$P$3007,$A50,'Zoho Dump'!$W$8:$W$3007,E$4)+SUMIFS(Adjustments!$M$8:$M$207,Adjustments!$A$8:$A$207,$A50,Adjustments!$J$8:$J$207,E$4)) -> 0 | F50: =IF(F$4<=Settings!$B$5,F10,SUMIFS('Zoho Dump'!$Z$8:$Z$3007,'Zoho Dump'!$P$8:$P$3007,$A50,'Zoho Dump'!$W$8:$W$3007,F$4)+SUMIFS(Adjustments!$M$8:$M$207,Adjustments!$A$8:$A$207,$A50,Adjustments!$J$8:$J$207,F$4)) -> 0 | G50: =IF(G$4<=Settings!$B$5,G10,SUMIFS('Zoho Dump'!$Z$8:$Z$3007,'Zoho Dump'!$P$8:$P$3007,$A50,'Zoho Dump'!$W$8:$W$3007,G$4)+SUMIFS(Adjustments!$M$8:$M$207,Adjustments!$A$8:$A$207,$A50,Adjustments!$J$8:$J$207,G$4)) -> 11342 | H50: =IF(H$4<=Settings!$B$5,H10,SUMIFS('Zoho Dump'!$Z$8:$Z$3007,'Zoho Dump'!$P$8:$P$3007,$A50,'Zoho Dump'!$W$8:$W$3007,H$4)+SUMIFS(Adjustments!$M$8:$M$207,Adjustments!$A$8:$A$207,$A50,Adjustments!$J$8:$J$207,H$4)) -> 0 | I50: =IF(I$4<=Settings!$B$5,I10,SUMIFS('Zoho Dump'!$Z$8:$Z$3007,'Zoho Dump'!$P$8:$P$3007,$A50,'Zoho Dump'!$W$8:$W$3007,I$4)+SUMIFS(Adjustments!$M$8:$M$207,Adjustments!$A$8:$A$207,$A50,Adjustments!$J$8:$J$207,I$4)) -> 0 | J50: =IF(J$4<=Settings!$B$5,J10,SUMIFS('Zoho Dump'!$Z$8:$Z$3007,'Zoho Dump'!$P$8:$P$3007,$A50,'Zoho Dump'!$W$8:$W$3007,J$4)+SUMIFS(Adjustments!$M$8:$M$207,Adjustments!$A$8:$A$207,$A50,Adjustments!$J$8:$J$207,J$4)) -> 0 | ... N50: =IF(N$4<=Settings!$B$5,N10,SUMIFS('Zoho Dump'!$Z$8:$Z$3007,'Zoho Dump'!$P$8:$P$3007,$A50,'Zoho Dump'!$W$8:$W$3007,N$4)+SUMIFS(Adjustments!$M$8:$M$207,Adjustments!$A$8:$A$207,$A50,Adjustments!$J$8:$J$207,N$4)) -> 0 | O50: =SUM(C50:N50) -> 11342
A51: =Settings!$A$15 -> Consulting | C51: =IF(C$4<=Settings!$B$5,C11,SUMIFS('Zoho Dump'!$Z$8:$Z$3007,'Zoho Dump'!$P$8:$P$3007,$A51,'Zoho Dump'!$W$8:$W$3007,C$4)+SUMIFS(Adjustments!$M$8:$M$207,Adjustments!$A$8:$A$207,$A51,Adjustments!$J$8:$J$207,C$4)) -> 0 | D51: =IF(D$4<=Settings!$B$5,D11,SUMIFS('Zoho Dump'!$Z$8:$Z$3007,'Zoho Dump'!$P$8:$P$3007,$A51,'Zoho Dump'!$W$8:$W$3007,D$4)+SUMIFS(Adjustments!$M$8:$M$207,Adjustments!$A$8:$A$207,$A51,Adjustments!$J$8:$J$207,D$4)) -> 0 | E51: =IF(E$4<=Settings!$B$5,E11,SUMIFS('Zoho Dump'!$Z$8:$Z$3007,'Zoho Dump'!$P$8:$P$3007,$A51,'Zoho Dump'!$W$8:$W$3007,E$4)+SUMIFS(Adjustments!$M$8:$M$207,Adjustments!$A$8:$A$207,$A51,Adjustments!$J$8:$J$207,E$4)) -> 0 | F51: =IF(F$4<=Settings!$B$5,F11,SUMIFS('Zoho Dump'!$Z$8:$Z$3007,'Zoho Dump'!$P$8:$P$3007,$A51,'Zoho Dump'!$W$8:$W$3007,F$4)+SUMIFS(Adjustments!$M$8:$M$207,Adjustments!$A$8:$A$207,$A51,Adjustments!$J$8:$J$207,F$4)) -> 0 | G51: =IF(G$4<=Settings!$B$5,G11,SUMIFS('Zoho Dump'!$Z$8:$Z$3007,'Zoho Dump'!$P$8:$P$3007,$A51,'Zoho Dump'!$W$8:$W$3007,G$4)+SUMIFS(Adjustments!$M$8:$M$207,Adjustments!$A$8:$A$207,$A51,Adjustments!$J$8:$J$207,G$4)) -> 0 | H51: =IF(H$4<=Settings!$B$5,H11,SUMIFS('Zoho Dump'!$Z$8:$Z$3007,'Zoho Dump'!$P$8:$P$3007,$A51,'Zoho Dump'!$W$8:$W$3007,H$4)+SUMIFS(Adjustments!$M$8:$M$207,Adjustments!$A$8:$A$207,$A51,Adjustments!$J$8:$J$207,H$4)) -> 0 | I51: =IF(I$4<=Settings!$B$5,I11,SUMIFS('Zoho Dump'!$Z$8:$Z$3007,'Zoho Dump'!$P$8:$P$3007,$A51,'Zoho Dump'!$W$8:$W$3007,I$4)+SUMIFS(Adjustments!$M$8:$M$207,Adjustments!$A$8:$A$207,$A51,Adjustments!$J$8:$J$207,I$4)) -> 0 | J51: =IF(J$4<=Settings!$B$5,J11,SUMIFS('Zoho Dump'!$Z$8:$Z$3007,'Zoho Dump'!$P$8:$P$3007,$A51,'Zoho Dump'!$W$8:$W$3007,J$4)+SUMIFS(Adjustments!$M$8:$M$207,Adjustments!$A$8:$A$207,$A51,Adjustments!$J$8:$J$207,J$4)) -> 0 | ... N51: =IF(N$4<=Settings!$B$5,N11,SUMIFS('Zoho Dump'!$Z$8:$Z$3007,'Zoho Dump'!$P$8:$P$3007,$A51,'Zoho Dump'!$W$8:$W$3007,N$4)+SUMIFS(Adjustments!$M$8:$M$207,Adjustments!$A$8:$A$207,$A51,Adjustments!$J$8:$J$207,N$4)) -> 0 | O51: =SUM(C51:N51) -> 0
A52: =Settings!$A$16 -> Integration | C52: =IF(C$4<=Settings!$B$5,C12,SUMIFS('Zoho Dump'!$Z$8:$Z$3007,'Zoho Dump'!$P$8:$P$3007,$A52,'Zoho Dump'!$W$8:$W$3007,C$4)+SUMIFS(Adjustments!$M$8:$M$207,Adjustments!$A$8:$A$207,$A52,Adjustments!$J$8:$J$207,C$4)) -> 0 | D52: =IF(D$4<=Settings!$B$5,D12,SUMIFS('Zoho Dump'!$Z$8:$Z$3007,'Zoho Dump'!$P$8:$P$3007,$A52,'Zoho Dump'!$W$8:$W$3007,D$4)+SUMIFS(Adjustments!$M$8:$M$207,Adjustments!$A$8:$A$207,$A52,Adjustments!$J$8:$J$207,D$4)) -> 0 | E52: =IF(E$4<=Settings!$B$5,E12,SUMIFS('Zoho Dump'!$Z$8:$Z$3007,'Zoho Dump'!$P$8:$P$3007,$A52,'Zoho Dump'!$W$8:$W$3007,E$4)+SUMIFS(Adjustments!$M$8:$M$207,Adjustments!$A$8:$A$207,$A52,Adjustments!$J$8:$J$207,E$4)) -> 0 | F52: =IF(F$4<=Settings!$B$5,F12,SUMIFS('Zoho Dump'!$Z$8:$Z$3007,'Zoho Dump'!$P$8:$P$3007,$A52,'Zoho Dump'!$W$8:$W$3007,F$4)+SUMIFS(Adjustments!$M$8:$M$207,Adjustments!$A$8:$A$207,$A52,Adjustments!$J$8:$J$207,F$4)) -> 0 | G52: =IF(G$4<=Settings!$B$5,G12,SUMIFS('Zoho Dump'!$Z$8:$Z$3007,'Zoho Dump'!$P$8:$P$3007,$A52,'Zoho Dump'!$W$8:$W$3007,G$4)+SUMIFS(Adjustments!$M$8:$M$207,Adjustments!$A$8:$A$207,$A52,Adjustments!$J$8:$J$207,G$4)) -> 0 | H52: =IF(H$4<=Settings!$B$5,H12,SUMIFS('Zoho Dump'!$Z$8:$Z$3007,'Zoho Dump'!$P$8:$P$3007,$A52,'Zoho Dump'!$W$8:$W$3007,H$4)+SUMIFS(Adjustments!$M$8:$M$207,Adjustments!$A$8:$A$207,$A52,Adjustments!$J$8:$J$207,H$4)) -> 0 | I52: =IF(I$4<=Settings!$B$5,I12,SUMIFS('Zoho Dump'!$Z$8:$Z$3007,'Zoho Dump'!$P$8:$P$3007,$A52,'Zoho Dump'!$W$8:$W$3007,I$4)+SUMIFS(Adjustments!$M$8:$M$207,Adjustments!$A$8:$A$207,$A52,Adjustments!$J$8:$J$207,I$4)) -> 0 | J52: =IF(J$4<=Settings!$B$5,J12,SUMIFS('Zoho Dump'!$Z$8:$Z$3007,'Zoho Dump'!$P$8:$P$3007,$A52,'Zoho Dump'!$W$8:$W$3007,J$4)+SUMIFS(Adjustments!$M$8:$M$207,Adjustments!$A$8:$A$207,$A52,Adjustments!$J$8:$J$207,J$4)) -> 0 | ... N52: =IF(N$4<=Settings!$B$5,N12,SUMIFS('Zoho Dump'!$Z$8:$Z$3007,'Zoho Dump'!$P$8:$P$3007,$A52,'Zoho Dump'!$W$8:$W$3007,N$4)+SUMIFS(Adjustments!$M$8:$M$207,Adjustments!$A$8:$A$207,$A52,Adjustments!$J$8:$J$207,N$4)) -> 0 | O52: =SUM(C52:N52) -> 0
A53: =Settings!$A$17 -> Admin | C53: =IF(C$4<=Settings!$B$5,C13,SUMIFS('Zoho Dump'!$Z$8:$Z$3007,'Zoho Dump'!$P$8:$P$3007,$A53,'Zoho Dump'!$W$8:$W$3007,C$4)+SUMIFS(Adjustments!$M$8:$M$207,Adjustments!$A$8:$A$207,$A53,Adjustments!$J$8:$J$207,C$4)) -> 0 | D53: =IF(D$4<=Settings!$B$5,D13,SUMIFS('Zoho Dump'!$Z$8:$Z$3007,'Zoho Dump'!$P$8:$P$3007,$A53,'Zoho Dump'!$W$8:$W$3007,D$4)+SUMIFS(Adjustments!$M$8:$M$207,Adjustments!$A$8:$A$207,$A53,Adjustments!$J$8:$J$207,D$4)) -> 0 | E53: =IF(E$4<=Settings!$B$5,E13,SUMIFS('Zoho Dump'!$Z$8:$Z$3007,'Zoho Dump'!$P$8:$P$3007,$A53,'Zoho Dump'!$W$8:$W$3007,E$4)+SUMIFS(Adjustments!$M$8:$M$207,Adjustments!$A$8:$A$207,$A53,Adjustments!$J$8:$J$207,E$4)) -> 0 | F53: =IF(F$4<=Settings!$B$5,F13,SUMIFS('Zoho Dump'!$Z$8:$Z$3007,'Zoho Dump'!$P$8:$P$3007,$A53,'Zoho Dump'!$W$8:$W$3007,F$4)+SUMIFS(Adjustments!$M$8:$M$207,Adjustments!$A$8:$A$207,$A53,Adjustments!$J$8:$J$207,F$4)) -> 0 | G53: =IF(G$4<=Settings!$B$5,G13,SUMIFS('Zoho Dump'!$Z$8:$Z$3007,'Zoho Dump'!$P$8:$P$3007,$A53,'Zoho Dump'!$W$8:$W$3007,G$4)+SUMIFS(Adjustments!$M$8:$M$207,Adjustments!$A$8:$A$207,$A53,Adjustments!$J$8:$J$207,G$4)) -> 0 | H53: =IF(H$4<=Settings!$B$5,H13,SUMIFS('Zoho Dump'!$Z$8:$Z$3007,'Zoho Dump'!$P$8:$P$3007,$A53,'Zoho Dump'!$W$8:$W$3007,H$4)+SUMIFS(Adjustments!$M$8:$M$207,Adjustments!$A$8:$A$207,$A53,Adjustments!$J$8:$J$207,H$4)) -> 0 | I53: =IF(I$4<=Settings!$B$5,I13,SUMIFS('Zoho Dump'!$Z$8:$Z$3007,'Zoho Dump'!$P$8:$P$3007,$A53,'Zoho Dump'!$W$8:$W$3007,I$4)+SUMIFS(Adjustments!$M$8:$M$207,Adjustments!$A$8:$A$207,$A53,Adjustments!$J$8:$J$207,I$4)) -> 0 | J53: =IF(J$4<=Settings!$B$5,J13,SUMIFS('Zoho Dump'!$Z$8:$Z$3007,'Zoho Dump'!$P$8:$P$3007,$A53,'Zoho Dump'!$W$8:$W$3007,J$4)+SUMIFS(Adjustments!$M$8:$M$207,Adjustments!$A$8:$A$207,$A53,Adjustments!$J$8:$J$207,J$4)) -> 0 | ... N53: =IF(N$4<=Settings!$B$5,N13,SUMIFS('Zoho Dump'!$Z$8:$Z$3007,'Zoho Dump'!$P$8:$P$3007,$A53,'Zoho Dump'!$W$8:$W$3007,N$4)+SUMIFS(Adjustments!$M$8:$M$207,Adjustments!$A$8:$A$207,$A53,Adjustments!$J$8:$J$207,N$4)) -> 0 | O53: =SUM(C53:N53) -> 0
A54: =Settings!$A$18 -> Unallocated | C54: =IF(C$4<=Settings!$B$5,C14,SUMIFS('Zoho Dump'!$Z$8:$Z$3007,'Zoho Dump'!$P$8:$P$3007,$A54,'Zoho Dump'!$W$8:$W$3007,C$4)+SUMIFS(Adjustments!$M$8:$M$207,Adjustments!$A$8:$A$207,$A54,Adjustments!$J$8:$J$207,C$4)) -> 0 | D54: =IF(D$4<=Settings!$B$5,D14,SUMIFS('Zoho Dump'!$Z$8:$Z$3007,'Zoho Dump'!$P$8:$P$3007,$A54,'Zoho Dump'!$W$8:$W$3007,D$4)+SUMIFS(Adjustments!$M$8:$M$207,Adjustments!$A$8:$A$207,$A54,Adjustments!$J$8:$J$207,D$4)) -> 0 | E54: =IF(E$4<=Settings!$B$5,E14,SUMIFS('Zoho Dump'!$Z$8:$Z$3007,'Zoho Dump'!$P$8:$P$3007,$A54,'Zoho Dump'!$W$8:$W$3007,E$4)+SUMIFS(Adjustments!$M$8:$M$207,Adjustments!$A$8:$A$207,$A54,Adjustments!$J$8:$J$207,E$4)) -> 0 | F54: =IF(F$4<=Settings!$B$5,F14,SUMIFS('Zoho Dump'!$Z$8:$Z$3007,'Zoho Dump'!$P$8:$P$3007,$A54,'Zoho Dump'!$W$8:$W$3007,F$4)+SUMIFS(Adjustments!$M$8:$M$207,Adjustments!$A$8:$A$207,$A54,Adjustments!$J$8:$J$207,F$4)) -> 0 | G54: =IF(G$4<=Settings!$B$5,G14,SUMIFS('Zoho Dump'!$Z$8:$Z$3007,'Zoho Dump'!$P$8:$P$3007,$A54,'Zoho Dump'!$W$8:$W$3007,G$4)+SUMIFS(Adjustments!$M$8:$M$207,Adjustments!$A$8:$A$207,$A54,Adjustments!$J$8:$J$207,G$4)) -> 0 | H54: =IF(H$4<=Settings!$B$5,H14,SUMIFS('Zoho Dump'!$Z$8:$Z$3007,'Zoho Dump'!$P$8:$P$3007,$A54,'Zoho Dump'!$W$8:$W$3007,H$4)+SUMIFS(Adjustments!$M$8:$M$207,Adjustments!$A$8:$A$207,$A54,Adjustments!$J$8:$J$207,H$4)) -> 0 | I54: =IF(I$4<=Settings!$B$5,I14,SUMIFS('Zoho Dump'!$Z$8:$Z$3007,'Zoho Dump'!$P$8:$P$3007,$A54,'Zoho Dump'!$W$8:$W$3007,I$4)+SUMIFS(Adjustments!$M$8:$M$207,Adjustments!$A$8:$A$207,$A54,Adjustments!$J$8:$J$207,I$4)) -> 0 | J54: =IF(J$4<=Settings!$B$5,J14,SUMIFS('Zoho Dump'!$Z$8:$Z$3007,'Zoho Dump'!$P$8:$P$3007,$A54,'Zoho Dump'!$W$8:$W$3007,J$4)+SUMIFS(Adjustments!$M$8:$M$207,Adjustments!$A$8:$A$207,$A54,Adjustments!$J$8:$J$207,J$4)) -> 0 | ... N54: =IF(N$4<=Settings!$B$5,N14,SUMIFS('Zoho Dump'!$Z$8:$Z$3007,'Zoho Dump'!$P$8:$P$3007,$A54,'Zoho Dump'!$W$8:$W$3007,N$4)+SUMIFS(Adjustments!$M$8:$M$207,Adjustments!$A$8:$A$207,$A54,Adjustments!$J$8:$J$207,N$4)) -> 0 | O54: =SUM(C54:N54) -> 0
A55: Total | C55: =SUM(C48:C54) -> 0 | D55: =SUM(D48:D54) -> 0 | E55: =SUM(E48:E54) -> 0 | F55: =SUM(F48:F54) -> 57626 | G55: =SUM(G48:G54) -> 24895 | H55: =SUM(H48:H54) -> 2881 | I55: =SUM(I48:I54) -> 0 | J55: =SUM(J48:J54) -> 0 | ... O55: =SUM(O48:O54) -> 85402
A57: Budget | B57: From the Budget sheet
A58: =Settings!$A$12 -> Onsite | C58: =Budget!B5 -> 0 | D58: =Budget!C5 -> 0 | E58: =Budget!D5 -> 0 | F58: =Budget!E5 -> 0 | G58: =Budget!F5 -> 0 | H58: =Budget!G5 -> 0 | I58: =Budget!H5 -> 0 | J58: =Budget!I5 -> 0 | ... N58: =Budget!M5 -> 0 | O58: =SUM(C58:N58) -> 0
A59: =Settings!$A$13 -> Production | C59: =Budget!B6 -> 0 | D59: =Budget!C6 -> 0 | E59: =Budget!D6 -> 0 | F59: =Budget!E6 -> 0 | G59: =Budget!F6 -> 0 | H59: =Budget!G6 -> 0 | I59: =Budget!H6 -> 0 | J59: =Budget!I6 -> 0 | ... N59: =Budget!M6 -> 0 | O59: =SUM(C59:N59) -> 0
A60: =Settings!$A$14 -> Video | C60: =Budget!B7 -> 0 | D60: =Budget!C7 -> 0 | E60: =Budget!D7 -> 0 | F60: =Budget!E7 -> 0 | G60: =Budget!F7 -> 0 | H60: =Budget!G7 -> 0 | I60: =Budget!H7 -> 0 | J60: =Budget!I7 -> 0 | ... N60: =Budget!M7 -> 0 | O60: =SUM(C60:N60) -> 0
A61: =Settings!$A$15 -> Consulting | C61: =Budget!B8 -> 0 | D61: =Budget!C8 -> 0 | E61: =Budget!D8 -> 0 | F61: =Budget!E8 -> 0 | G61: =Budget!F8 -> 0 | H61: =Budget!G8 -> 0 | I61: =Budget!H8 -> 0 | J61: =Budget!I8 -> 0 | ... N61: =Budget!M8 -> 0 | O61: =SUM(C61:N61) -> 0
A62: =Settings!$A$16 -> Integration | C62: =Budget!B9 -> 0 | D62: =Budget!C9 -> 0 | E62: =Budget!D9 -> 0 | F62: =Budget!E9 -> 0 | G62: =Budget!F9 -> 0 | H62: =Budget!G9 -> 0 | I62: =Budget!H9 -> 0 | J62: =Budget!I9 -> 0 | ... N62: =Budget!M9 -> 0 | O62: =SUM(C62:N62) -> 0
A63: =Settings!$A$17 -> Admin | C63: =Budget!B10 -> 0 | D63: =Budget!C10 -> 0 | E63: =Budget!D10 -> 0 | F63: =Budget!E10 -> 0 | G63: =Budget!F10 -> 0 | H63: =Budget!G10 -> 0 | I63: =Budget!H10 -> 0 | J63: =Budget!I10 -> 0 | ... N63: =Budget!M10 -> 0 | O63: =SUM(C63:N63) -> 0
A64: =Settings!$A$18 -> Unallocated | C64: =Budget!B11 -> 0 | D64: =Budget!C11 -> 0 | E64: =Budget!D11 -> 0 | F64: =Budget!E11 -> 0 | G64: =Budget!F11 -> 0 | H64: =Budget!G11 -> 0 | I64: =Budget!H11 -> 0 | J64: =Budget!I11 -> 0 | ... N64: =Budget!M11 -> 0 | O64: =SUM(C64:N64) -> 0
A65: Total | C65: =SUM(C58:C64) -> 0 | D65: =SUM(D58:D64) -> 0 | E65: =SUM(E58:E64) -> 0 | F65: =SUM(F58:F64) -> 0 | G65: =SUM(G58:G64) -> 0 | H65: =SUM(H58:H64) -> 0 | I65: =SUM(I58:I64) -> 0 | J65: =SUM(J58:J64) -> 0 | ... O65: =SUM(O58:O64) -> 0
A67: Forecast less budget | B67: Negative means short of budget
A68: =Settings!$A$12 -> Onsite | C68: =C38-C58 -> 0 | D68: =D38-D58 -> 0 | E68: =E38-E58 -> 0 | F68: =F38-F58 -> 17000 | G68: =G38-G58 -> 0 | H68: =H38-H58 -> 0 | I68: =I38-I58 -> 0 | J68: =J38-J58 -> 52500 | ... N68: =N38-N58 -> 0 | O68: =SUM(C68:N68) -> 69500
A69: =Settings!$A$13 -> Production | C69: =C39-C59 -> 0 | D69: =D39-D59 -> 0 | E69: =E39-E59 -> 0 | F69: =F39-F59 -> 173398.2 | G69: =G39-G59 -> 74873.6 | H69: =H39-H59 -> 24151.7 | I69: =I39-I59 -> 224 | J69: =J39-J59 -> 1600 | ... N69: =N39-N59 -> 0 | O69: =SUM(C69:N69) -> 702104.5
A70: =Settings!$A$14 -> Video | C70: =C40-C60 -> 0 | D70: =D40-D60 -> 0 | E70: =E40-E60 -> 0 | F70: =F40-F60 -> 1255.5 | G70: =G40-G60 -> 11342 | H70: =H40-H60 -> 0 | I70: =I40-I60 -> 0 | J70: =J40-J60 -> 0 | ... N70: =N40-N60 -> 0 | O70: =SUM(C70:N70) -> 12597.5
A71: =Settings!$A$15 -> Consulting | C71: =C41-C61 -> 0 | D71: =D41-D61 -> 0 | E71: =E41-E61 -> 0 | F71: =F41-F61 -> 0 | G71: =G41-G61 -> 15000 | H71: =H41-H61 -> 0 | I71: =I41-I61 -> 0 | J71: =J41-J61 -> 0 | ... N71: =N41-N61 -> 0 | O71: =SUM(C71:N71) -> 15000
A72: =Settings!$A$16 -> Integration | C72: =C42-C62 -> 0 | D72: =D42-D62 -> 0 | E72: =E42-E62 -> 0 | F72: =F42-F62 -> 52346.7 | G72: =G42-G62 -> 1653 | H72: =H42-H62 -> 0 | I72: =I42-I62 -> 0 | J72: =J42-J62 -> 0 | ... N72: =N42-N62 -> 0 | O72: =SUM(C72:N72) -> 53999.7
A73: =Settings!$A$17 -> Admin | C73: =C43-C63 -> 0 | D73: =D43-D63 -> 0 | E73: =E43-E63 -> 0 | F73: =F43-F63 -> 0 | G73: =G43-G63 -> 0 | H73: =H43-H63 -> 0 | I73: =I43-I63 -> 0 | J73: =J43-J63 -> 0 | ... N73: =N43-N63 -> 0 | O73: =SUM(C73:N73) -> 0
A74: =Settings!$A$18 -> Unallocated | C74: =C44-C64 -> 0 | D74: =D44-D64 -> 0 | E74: =E44-E64 -> 0 | F74: =F44-F64 -> 0 | G74: =G44-G64 -> 0 | H74: =H44-H64 -> 0 | I74: =I44-I64 -> 0 | J74: =J44-J64 -> 0 | ... N74: =N44-N64 -> 0 | O74: =SUM(C74:N74) -> 0
A75: Total | C75: =SUM(C68:C74) -> 0 | D75: =SUM(D68:D74) -> 0 | E75: =SUM(E68:E74) -> 0 | F75: =SUM(F68:F74) -> 244000.4 | G75: =SUM(G68:G74) -> 102868.6 | H75: =SUM(H68:H74) -> 24151.7 | I75: =SUM(I68:I74) -> 224 | J75: =SUM(J68:J74) -> 54100 | ... O75: =SUM(O68:O74) -> 853201.7

Sheet Customer Risk
A1: Customer Risk
A2: Every customer in the Zoho export. Forward revenue means backlog plus weighted pipeline for the rest of this FY.
A4: # | B4: Customer | C4: Won this FY to date (Zoho) | D4: Backlog this FY | E4: Pipeline full value | F4: Pipeline weighted | G4: Forward revenue | H4: Share of all forward revenue | I4: Lost this FY (Zoho) | J4: Withdrawn in scenario | K4: Forward: Onsite | L4: Forward: Production | M4: Forward: Video | N4: Forward: Consulting | O4: Forward: Integration | P4: Forward: Admin | Q4: Forward: Unallocated | R4: Sort key
A5: 1 | B5: =IFERROR(INDEX('Zoho Dump'!$N$8:$N$3007,MATCH(A5,'Zoho Dump'!$AB$8:$AB$3007,0)),"") -> Deloitte Australia | C5: =IF($B5="",0,SUMIFS('Zoho Dump'!$Q$8:$Q$3007,'Zoho Dump'!$N$8:$N$3007,$B5,'Zoho Dump'!$T$8:$T$3007,"Delivered",'Zoho Dump'!$R$8:$R$3007,">="&Settings!$B$4)) -> 164246 | D5: =IF($B5="",0,SUMIFS('Zoho Dump'!$X$8:$X$3007,'Zoho Dump'!$N$8:$N$3007,$B5,'Zoho Dump'!$T$8:$T$3007,"Backlog")+SUMIFS(Adjustments!$K$8:$K$207,Adjustments!$B$8:$B$207,$B5,Adjustments!$H$8:$H$207,"Backlog")) -> 0 | E5: =IF($B5="",0,SUMIFS('Zoho Dump'!$Y$8:$Y$3007,'Zoho Dump'!$N$8:$N$3007,$B5,'Zoho Dump'!$T$8:$T$3007,"Pipeline")+SUMIFS(Adjustments!$L$8:$L$207,Adjustments!$B$8:$B$207,$B5,Adjustments!$H$8:$H$207,"Pipeline")+SUMIFS('Zoho Dump'!$Y$8:$Y$3007,'Zoho Dump'!$N$8:$N$3007,$B5,'Zoho Dump'!$T$8:$T$3007,"Overdue")+SUMIFS(Adjustments!$L$8:$L$207,Adjustments!$B$8:$B$207,$B5,Adjustments!$H$8:$H$207,"Overdue")) -> 76025 | F5: =IF($B5="",0,SUMIFS('Zoho Dump'!$X$8:$X$3007,'Zoho Dump'!$N$8:$N$3007,$B5,'Zoho Dump'!$T$8:$T$3007,"Pipeline")+SUMIFS(Adjustments!$K$8:$K$207,Adjustments!$B$8:$B$207,$B5,Adjustments!$H$8:$H$207,"Pipeline")+SUMIFS('Zoho Dump'!$X$8:$X$3007,'Zoho Dump'!$N$8:$N$3007,$B5,'Zoho Dump'!$T$8:$T$3007,"Overdue")+SUMIFS(Adjustments!$K$8:$K$207,Adjustments!$B$8:$B$207,$B5,Adjustments!$H$8:$H$207,"Overdue")) -> 53012.5 | G5: =D5+F5 -> 53012.5 | H5: =IF(SUM($G$5:$G$404)=0,0,G5/SUM($G$5:$G$404)) -> 0.062133608 | I5: =IF($B5="",0,SUMIFS('Zoho Dump'!$Q$8:$Q$3007,'Zoho Dump'!$N$8:$N$3007,$B5,'Zoho Dump'!$T$8:$T$3007,"Lost",'Zoho Dump'!$R$8:$R$3007,">="&Settings!$B$4)) -> 1426 | J5: =IF($B5="","",IF(COUNTIF(Dashboard!$C$13:$C$22,$B5)>0,"Yes","")) | K5: =IF($B5="",0,SUMIFS('Zoho Dump'!$X$8:$X$3007,'Zoho Dump'!$N$8:$N$3007,$B5,'Zoho Dump'!$P$8:$P$3007,Settings!$A$12)+SUMIFS(Adjustments!$K$8:$K$207,Adjustments!$B$8:$B$207,$B5,Adjustments!$A$8:$A$207,Settings!$A$12)) -> 52500 | L5: =IF($B5="",0,SUMIFS('Zoho Dump'!$X$8:$X$3007,'Zoho Dump'!$N$8:$N$3007,$B5,'Zoho Dump'!$P$8:$P$3007,Settings!$A$13)+SUMIFS(Adjustments!$K$8:$K$207,Adjustments!$B$8:$B$207,$B5,Adjustments!$A$8:$A$207,Settings!$A$13)) -> 0 | M5: =IF($B5="",0,SUMIFS('Zoho Dump'!$X$8:$X$3007,'Zoho Dump'!$N$8:$N$3007,$B5,'Zoho Dump'!$P$8:$P$3007,Settings!$A$14)+SUMIFS(Adjustments!$K$8:$K$207,Adjustments!$B$8:$B$207,$B5,Adjustments!$A$8:$A$207,Settings!$A$14)) -> 0 | N5: =IF($B5="",0,SUMIFS('Zoho Dump'!$X$8:$X$3007,'Zoho Dump'!$N$8:$N$3007,$B5,'Zoho Dump'!$P$8:$P$3007,Settings!$A$15)+SUMIFS(Adjustments!$K$8:$K$207,Adjustments!$B$8:$B$207,$B5,Adjustments!$A$8:$A$207,Settings!$A$15)) -> 0 | O5: =IF($B5="",0,SUMIFS('Zoho Dump'!$X$8:$X$3007,'Zoho Dump'!$N$8:$N$3007,$B5,'Zoho Dump'!$P$8:$P$3007,Settings!$A$16)+SUMIFS(Adjustments!$K$8:$K$207,Adjustments!$B$8:$B$207,$B5,Adjustments!$A$8:$A$207,Settings!$A$16)) -> 512.5 | P5: =IF($B5="",0,SUMIFS('Zoho Dump'!$X$8:$X$3007,'Zoho Dump'!$N$8:$N$3007,$B5,'Zoho Dump'!$P$8:$P$3007,Settings!$A$17)+SUMIFS(Adjustments!$K$8:$K$207,Adjustments!$B$8:$B$207,$B5,Adjustments!$A$8:$A$207,Settings!$A$17)) -> 0 | Q5: =IF($B5="",0,SUMIFS('Zoho Dump'!$X$8:$X$3007,'Zoho Dump'!$N$8:$N$3007,$B5,'Zoho Dump'!$P$8:$P$3007,Settings!$A$18)+SUMIFS(Adjustments!$K$8:$K$207,Adjustments!$B$8:$B$207,$B5,Adjustments!$A$8:$A$207,Settings!$A$18)) -> 0 | R5: =IF(G5>0,G5+A5/10000000,"") -> 53012.5
A6: 2 | B6: =IFERROR(INDEX('Zoho Dump'!$N$8:$N$3007,MATCH(A6,'Zoho Dump'!$AB$8:$AB$3007,0)),"") -> Investa | C6: =IF($B6="",0,SUMIFS('Zoho Dump'!$Q$8:$Q$3007,'Zoho Dump'!$N$8:$N$3007,$B6,'Zoho Dump'!$T$8:$T$3007,"Delivered",'Zoho Dump'!$R$8:$R$3007,">="&Settings!$B$4)) -> 0 | D6: =IF($B6="",0,SUMIFS('Zoho Dump'!$X$8:$X$3007,'Zoho Dump'!$N$8:$N$3007,$B6,'Zoho Dump'!$T$8:$T$3007,"Backlog")+SUMIFS(Adjustments!$K$8:$K$207,Adjustments!$B$8:$B$207,$B6,Adjustments!$H$8:$H$207,"Backlog")) -> 0 | E6: =IF($B6="",0,SUMIFS('Zoho Dump'!$Y$8:$Y$3007,'Zoho Dump'!$N$8:$N$3007,$B6,'Zoho Dump'!$T$8:$T$3007,"Pipeline")+SUMIFS(Adjustments!$L$8:$L$207,Adjustments!$B$8:$B$207,$B6,Adjustments!$H$8:$H$207,"Pipeline")+SUMIFS('Zoho Dump'!$Y$8:$Y$3007,'Zoho Dump'!$N$8:$N$3007,$B6,'Zoho Dump'!$T$8:$T$3007,"Overdue")+SUMIFS(Adjustments!$L$8:$L$207,Adjustments!$B$8:$B$207,$B6,Adjustments!$H$8:$H$207,"Overdue")) -> 2400 | F6: =IF($B6="",0,SUMIFS('Zoho Dump'!$X$8:$X$3007,'Zoho Dump'!$N$8:$N$3007,$B6,'Zoho Dump'!$T$8:$T$3007,"Pipeline")+SUMIFS(Adjustments!$K$8:$K$207,Adjustments!$B$8:$B$207,$B6,Adjustments!$H$8:$H$207,"Pipeline")+SUMIFS('Zoho Dump'!$X$8:$X$3007,'Zoho Dump'!$N$8:$N$3007,$B6,'Zoho Dump'!$T$8:$T$3007,"Overdue")+SUMIFS(Adjustments!$K$8:$K$207,Adjustments!$B$8:$B$207,$B6,Adjustments!$H$8:$H$207,"Overdue")) -> 1200 | G6: =D6+F6 -> 1200 | H6: =IF(SUM($G$5:$G$404)=0,0,G6/SUM($G$5:$G$404)) -> 0.001406467 | I6: =IF($B6="",0,SUMIFS('Zoho Dump'!$Q$8:$Q$3007,'Zoho Dump'!$N$8:$N$3007,$B6,'Zoho Dump'!$T$8:$T$3007,"Lost",'Zoho Dump'!$R$8:$R$3007,">="&Settings!$B$4)) -> 0 | J6: =IF($B6="","",IF(COUNTIF(Dashboard!$C$13:$C$22,$B6)>0,"Yes","")) | K6: =IF($B6="",0,SUMIFS('Zoho Dump'!$X$8:$X$3007,'Zoho Dump'!$N$8:$N$3007,$B6,'Zoho Dump'!$P$8:$P$3007,Settings!$A$12)+SUMIFS(Adjustments!$K$8:$K$207,Adjustments!$B$8:$B$207,$B6,Adjustments!$A$8:$A$207,Settings!$A$12)) -> 0 | L6: =IF($B6="",0,SUMIFS('Zoho Dump'!$X$8:$X$3007,'Zoho Dump'!$N$8:$N$3007,$B6,'Zoho Dump'!$P$8:$P$3007,Settings!$A$13)+SUMIFS(Adjustments!$K$8:$K$207,Adjustments!$B$8:$B$207,$B6,Adjustments!$A$8:$A$207,Settings!$A$13)) -> 1200 | M6: =IF($B6="",0,SUMIFS('Zoho Dump'!$X$8:$X$3007,'Zoho Dump'!$N$8:$N$3007,$B6,'Zoho Dump'!$P$8:$P$3007,Settings!$A$14)+SUMIFS(Adjustments!$K$8:$K$207,Adjustments!$B$8:$B$207,$B6,Adjustments!$A$8:$A$207,Settings!$A$14)) -> 0 | N6: =IF($B6="",0,SUMIFS('Zoho Dump'!$X$8:$X$3007,'Zoho Dump'!$N$8:$N$3007,$B6,'Zoho Dump'!$P$8:$P$3007,Settings!$A$15)+SUMIFS(Adjustments!$K$8:$K$207,Adjustments!$B$8:$B$207,$B6,Adjustments!$A$8:$A$207,Settings!$A$15)) -> 0 | O6: =IF($B6="",0,SUMIFS('Zoho Dump'!$X$8:$X$3007,'Zoho Dump'!$N$8:$N$3007,$B6,'Zoho Dump'!$P$8:$P$3007,Settings!$A$16)+SUMIFS(Adjustments!$K$8:$K$207,Adjustments!$B$8:$B$207,$B6,Adjustments!$A$8:$A$207,Settings!$A$16)) -> 0 | P6: =IF($B6="",0,SUMIFS('Zoho Dump'!$X$8:$X$3007,'Zoho Dump'!$N$8:$N$3007,$B6,'Zoho Dump'!$P$8:$P$3007,Settings!$A$17)+SUMIFS(Adjustments!$K$8:$K$207,Adjustments!$B$8:$B$207,$B6,Adjustments!$A$8:$A$207,Settings!$A$17)) -> 0 | Q6: =IF($B6="",0,SUMIFS('Zoho Dump'!$X$8:$X$3007,'Zoho Dump'!$N$8:$N$3007,$B6,'Zoho Dump'!$P$8:$P$3007,Settings!$A$18)+SUMIFS(Adjustments!$K$8:$K$207,Adjustments!$B$8:$B$207,$B6,Adjustments!$A$8:$A$207,Settings!$A$18)) -> 0 | R6: =IF(G6>0,G6+A6/10000000,"") -> 1200
A7: 3 | B7: =IFERROR(INDEX('Zoho Dump'!$N$8:$N$3007,MATCH(A7,'Zoho Dump'!$AB$8:$AB$3007,0)),"") -> Stryker | C7: =IF($B7="",0,SUMIFS('Zoho Dump'!$Q$8:$Q$3007,'Zoho Dump'!$N$8:$N$3007,$B7,'Zoho Dump'!$T$8:$T$3007,"Delivered",'Zoho Dump'!$R$8:$R$3007,">="&Settings!$B$4)) -> 0 | D7: =IF($B7="",0,SUMIFS('Zoho Dump'!$X$8:$X$3007,'Zoho Dump'!$N$8:$N$3007,$B7,'Zoho Dump'!$T$8:$T$3007,"Backlog")+SUMIFS(Adjustments!$K$8:$K$207,Adjustments!$B$8:$B$207,$B7,Adjustments!$H$8:$H$207,"Backlog")) -> 0 | E7: =IF($B7="",0,SUMIFS('Zoho Dump'!$Y$8:$Y$3007,'Zoho Dump'!$N$8:$N$3007,$B7,'Zoho Dump'!$T$8:$T$3007,"Pipeline")+SUMIFS(Adjustments!$L$8:$L$207,Adjustments!$B$8:$B$207,$B7,Adjustments!$H$8:$H$207,"Pipeline")+SUMIFS('Zoho Dump'!$Y$8:$Y$3007,'Zoho Dump'!$N$8:$N$3007,$B7,'Zoho Dump'!$T$8:$T$3007,"Overdue")+SUMIFS(Adjustments!$L$8:$L$207,Adjustments!$B$8:$B$207,$B7,Adjustments!$H$8:$H$207,"Overdue")) -> 34068 | F7: =IF($B7="",0,SUMIFS('Zoho Dump'!$X$8:$X$3007,'Zoho Dump'!$N$8:$N$3007,$B7,'Zoho Dump'!$T$8:$T$3007,"Pipeline")+SUMIFS(Adjustments!$K$8:$K$207,Adjustments!$B$8:$B$207,$B7,Adjustments!$H$8:$H$207,"Pipeline")+SUMIFS('Zoho Dump'!$X$8:$X$3007,'Zoho Dump'!$N$8:$N$3007,$B7,'Zoho Dump'!$T$8:$T$3007,"Overdue")+SUMIFS(Adjustments!$K$8:$K$207,Adjustments!$B$8:$B$207,$B7,Adjustments!$H$8:$H$207,"Overdue")) -> 17034 | G7: =D7+F7 -> 17034 | H7: =IF(SUM($G$5:$G$404)=0,0,G7/SUM($G$5:$G$404)) -> 0.019964798 | I7: =IF($B7="",0,SUMIFS('Zoho Dump'!$Q$8:$Q$3007,'Zoho Dump'!$N$8:$N$3007,$B7,'Zoho Dump'!$T$8:$T$3007,"Lost",'Zoho Dump'!$R$8:$R$3007,">="&Settings!$B$4)) -> 0 | J7: =IF($B7="","",IF(COUNTIF(Dashboard!$C$13:$C$22,$B7)>0,"Yes","")) | K7: =IF($B7="",0,SUMIFS('Zoho Dump'!$X$8:$X$3007,'Zoho Dump'!$N$8:$N$3007,$B7,'Zoho Dump'!$P$8:$P$3007,Settings!$A$12)+SUMIFS(Adjustments!$K$8:$K$207,Adjustments!$B$8:$B$207,$B7,Adjustments!$A$8:$A$207,Settings!$A$12)) -> 0 | L7: =IF($B7="",0,SUMIFS('Zoho Dump'!$X$8:$X$3007,'Zoho Dump'!$N$8:$N$3007,$B7,'Zoho Dump'!$P$8:$P$3007,Settings!$A$13)+SUMIFS(Adjustments!$K$8:$K$207,Adjustments!$B$8:$B$207,$B7,Adjustments!$A$8:$A$207,Settings!$A$13)) -> 0 | M7: =IF($B7="",0,SUMIFS('Zoho Dump'!$X$8:$X$3007,'Zoho Dump'!$N$8:$N$3007,$B7,'Zoho Dump'!$P$8:$P$3007,Settings!$A$14)+SUMIFS(Adjustments!$K$8:$K$207,Adjustments!$B$8:$B$207,$B7,Adjustments!$A$8:$A$207,Settings!$A$14)) -> 0 | N7: =IF($B7="",0,SUMIFS('Zoho Dump'!$X$8:$X$3007,'Zoho Dump'!$N$8:$N$3007,$B7,'Zoho Dump'!$P$8:$P$3007,Settings!$A$15)+SUMIFS(Adjustments!$K$8:$K$207,Adjustments!$B$8:$B$207,$B7,Adjustments!$A$8:$A$207,Settings!$A$15)) -> 0 | O7: =IF($B7="",0,SUMIFS('Zoho Dump'!$X$8:$X$3007,'Zoho Dump'!$N$8:$N$3007,$B7,'Zoho Dump'!$P$8:$P$3007,Settings!$A$16)+SUMIFS(Adjustments!$K$8:$K$207,Adjustments!$B$8:$B$207,$B7,Adjustments!$A$8:$A$207,Settings!$A$16)) -> 17034 | P7: =IF($B7="",0,SUMIFS('Zoho Dump'!$X$8:$X$3007,'Zoho Dump'!$N$8:$N$3007,$B7,'Zoho Dump'!$P$8:$P$3007,Settings!$A$17)+SUMIFS(Adjustments!$K$8:$K$207,Adjustments!$B$8:$B$207,$B7,Adjustments!$A$8:$A$207,Settings!$A$17)) -> 0 | Q7: =IF($B7="",0,SUMIFS('Zoho Dump'!$X$8:$X$3007,'Zoho Dump'!$N$8:$N$3007,$B7,'Zoho Dump'!$P$8:$P$3007,Settings!$A$18)+SUMIFS(Adjustments!$K$8:$K$207,Adjustments!$B$8:$B$207,$B7,Adjustments!$A$8:$A$207,Settings!$A$18)) -> 0 | R7: =IF(G7>0,G7+A7/10000000,"") -> 17034
A8: 4 | B8: =IFERROR(INDEX('Zoho Dump'!$N$8:$N$3007,MATCH(A8,'Zoho Dump'!$AB$8:$AB$3007,0)),"") -> Datacom | C8: =IF($B8="",0,SUMIFS('Zoho Dump'!$Q$8:$Q$3007,'Zoho Dump'!$N$8:$N$3007,$B8,'Zoho Dump'!$T$8:$T$3007,"Delivered",'Zoho Dump'!$R$8:$R$3007,">="&Settings!$B$4)) -> 0 | D8: =IF($B8="",0,SUMIFS('Zoho Dump'!$X$8:$X$3007,'Zoho Dump'!$N$8:$N$3007,$B8,'Zoho Dump'!$T$8:$T$3007,"Backlog")+SUMIFS(Adjustments!$K$8:$K$207,Adjustments!$B$8:$B$207,$B8,Adjustments!$H$8:$H$207,"Backlog")) -> 0 | E8: =IF($B8="",0,SUMIFS('Zoho Dump'!$Y$8:$Y$3007,'Zoho Dump'!$N$8:$N$3007,$B8,'Zoho Dump'!$T$8:$T$3007,"Pipeline")+SUMIFS(Adjustments!$L$8:$L$207,Adjustments!$B$8:$B$207,$B8,Adjustments!$H$8:$H$207,"Pipeline")+SUMIFS('Zoho Dump'!$Y$8:$Y$3007,'Zoho Dump'!$N$8:$N$3007,$B8,'Zoho Dump'!$T$8:$T$3007,"Overdue")+SUMIFS(Adjustments!$L$8:$L$207,Adjustments!$B$8:$B$207,$B8,Adjustments!$H$8:$H$207,"Overdue")) -> 1175 | F8: =IF($B8="",0,SUMIFS('Zoho Dump'!$X$8:$X$3007,'Zoho Dump'!$N$8:$N$3007,$B8,'Zoho Dump'!$T$8:$T$3007,"Pipeline")+SUMIFS(Adjustments!$K$8:$K$207,Adjustments!$B$8:$B$207,$B8,Adjustments!$H$8:$H$207,"Pipeline")+SUMIFS('Zoho Dump'!$X$8:$X$3007,'Zoho Dump'!$N$8:$N$3007,$B8,'Zoho Dump'!$T$8:$T$3007,"Overdue")+SUMIFS(Adjustments!$K$8:$K$207,Adjustments!$B$8:$B$207,$B8,Adjustments!$H$8:$H$207,"Overdue")) -> 587.5 | G8: =D8+F8 -> 587.5 | H8: =IF(SUM($G$5:$G$404)=0,0,G8/SUM($G$5:$G$404)) -> 0.00068858278 | I8: =IF($B8="",0,SUMIFS('Zoho Dump'!$Q$8:$Q$3007,'Zoho Dump'!$N$8:$N$3007,$B8,'Zoho Dump'!$T$8:$T$3007,"Lost",'Zoho Dump'!$R$8:$R$3007,">="&Settings!$B$4)) -> 0 | J8: =IF($B8="","",IF(COUNTIF(Dashboard!$C$13:$C$22,$B8)>0,"Yes","")) | K8: =IF($B8="",0,SUMIFS('Zoho Dump'!$X$8:$X$3007,'Zoho Dump'!$N$8:$N$3007,$B8,'Zoho Dump'!$P$8:$P$3007,Settings!$A$12)+SUMIFS(Adjustments!$K$8:$K$207,Adjustments!$B$8:$B$207,$B8,Adjustments!$A$8:$A$207,Settings!$A$12)) -> 0 | L8: =IF($B8="",0,SUMIFS('Zoho Dump'!$X$8:$X$3007,'Zoho Dump'!$N$8:$N$3007,$B8,'Zoho Dump'!$P$8:$P$3007,Settings!$A$13)+SUMIFS(Adjustments!$K$8:$K$207,Adjustments!$B$8:$B$207,$B8,Adjustments!$A$8:$A$207,Settings!$A$13)) -> 0 | M8: =IF($B8="",0,SUMIFS('Zoho Dump'!$X$8:$X$3007,'Zoho Dump'!$N$8:$N$3007,$B8,'Zoho Dump'!$P$8:$P$3007,Settings!$A$14)+SUMIFS(Adjustments!$K$8:$K$207,Adjustments!$B$8:$B$207,$B8,Adjustments!$A$8:$A$207,Settings!$A$14)) -> 0 | N8: =IF($B8="",0,SUMIFS('Zoho Dump'!$X$8:$X$3007,'Zoho Dump'!$N$8:$N$3007,$B8,'Zoho Dump'!$P$8:$P$3007,Settings!$A$15)+SUMIFS(Adjustments!$K$8:$K$207,Adjustments!$B$8:$B$207,$B8,Adjustments!$A$8:$A$207,Settings!$A$15)) -> 0 | O8: =IF($B8="",0,SUMIFS('Zoho Dump'!$X$8:$X$3007,'Zoho Dump'!$N$8:$N$3007,$B8,'Zoho Dump'!$P$8:$P$3007,Settings!$A$16)+SUMIFS(Adjustments!$K$8:$K$207,Adjustments!$B$8:$B$207,$B8,Adjustments!$A$8:$A$207,Settings!$A$16)) -> 587.5 | P8: =IF($B8="",0,SUMIFS('Zoho Dump'!$X$8:$X$3007,'Zoho Dump'!$N$8:$N$3007,$B8,'Zoho Dump'!$P$8:$P$3007,Settings!$A$17)+SUMIFS(Adjustments!$K$8:$K$207,Adjustments!$B$8:$B$207,$B8,Adjustments!$A$8:$A$207,Settings!$A$17)) -> 0 | Q8: =IF($B8="",0,SUMIFS('Zoho Dump'!$X$8:$X$3007,'Zoho Dump'!$N$8:$N$3007,$B8,'Zoho Dump'!$P$8:$P$3007,Settings!$A$18)+SUMIFS(Adjustments!$K$8:$K$207,Adjustments!$B$8:$B$207,$B8,Adjustments!$A$8:$A$207,Settings!$A$18)) -> 0 | R8: =IF(G8>0,G8+A8/10000000,"") -> 587.5
A9: 5 | B9: =IFERROR(INDEX('Zoho Dump'!$N$8:$N$3007,MATCH(A9,'Zoho Dump'!$AB$8:$AB$3007,0)),"") -> PWC | C9: =IF($B9="",0,SUMIFS('Zoho Dump'!$Q$8:$Q$3007,'Zoho Dump'!$N$8:$N$3007,$B9,'Zoho Dump'!$T$8:$T$3007,"Delivered",'Zoho Dump'!$R$8:$R$3007,">="&Settings!$B$4)) -> 36380 | D9: =IF($B9="",0,SUMIFS('Zoho Dump'!$X$8:$X$3007,'Zoho Dump'!$N$8:$N$3007,$B9,'Zoho Dump'!$T$8:$T$3007,"Backlog")+SUMIFS(Adjustments!$K$8:$K$207,Adjustments!$B$8:$B$207,$B9,Adjustments!$H$8:$H$207,"Backlog")) -> 17000 | E9: =IF($B9="",0,SUMIFS('Zoho Dump'!$Y$8:$Y$3007,'Zoho Dump'!$N$8:$N$3007,$B9,'Zoho Dump'!$T$8:$T$3007,"Pipeline")+SUMIFS(Adjustments!$L$8:$L$207,Adjustments!$B$8:$B$207,$B9,Adjustments!$H$8:$H$207,"Pipeline")+SUMIFS('Zoho Dump'!$Y$8:$Y$3007,'Zoho Dump'!$N$8:$N$3007,$B9,'Zoho Dump'!$T$8:$T$3007,"Overdue")+SUMIFS(Adjustments!$L$8:$L$207,Adjustments!$B$8:$B$207,$B9,Adjustments!$H$8:$H$207,"Overdue")) -> 8856 | F9: =IF($B9="",0,SUMIFS('Zoho Dump'!$X$8:$X$3007,'Zoho Dump'!$N$8:$N$3007,$B9,'Zoho Dump'!$T$8:$T$3007,"Pipeline")+SUMIFS(Adjustments!$K$8:$K$207,Adjustments!$B$8:$B$207,$B9,Adjustments!$H$8:$H$207,"Pipeline")+SUMIFS('Zoho Dump'!$X$8:$X$3007,'Zoho Dump'!$N$8:$N$3007,$B9,'Zoho Dump'!$T$8:$T$3007,"Overdue")+SUMIFS(Adjustments!$K$8:$K$207,Adjustments!$B$8:$B$207,$B9,Adjustments!$H$8:$H$207,"Overdue")) -> 4428 | G9: =D9+F9 -> 21428 | H9: =IF(SUM($G$5:$G$404)=0,0,G9/SUM($G$5:$G$404)) -> 0.025114812 | I9: =IF($B9="",0,SUMIFS('Zoho Dump'!$Q$8:$Q$3007,'Zoho Dump'!$N$8:$N$3007,$B9,'Zoho Dump'!$T$8:$T$3007,"Lost",'Zoho Dump'!$R$8:$R$3007,">="&Settings!$B$4)) -> 682119 | J9: =IF($B9="","",IF(COUNTIF(Dashboard!$C$13:$C$22,$B9)>0,"Yes","")) | K9: =IF($B9="",0,SUMIFS('Zoho Dump'!$X$8:$X$3007,'Zoho Dump'!$N$8:$N$3007,$B9,'Zoho Dump'!$P$8:$P$3007,Settings!$A$12)+SUMIFS(Adjustments!$K$8:$K$207,Adjustments!$B$8:$B$207,$B9,Adjustments!$A$8:$A$207,Settings!$A$12)) -> 17000 | L9: =IF($B9="",0,SUMIFS('Zoho Dump'!$X$8:$X$3007,'Zoho Dump'!$N$8:$N$3007,$B9,'Zoho Dump'!$P$8:$P$3007,Settings!$A$13)+SUMIFS(Adjustments!$K$8:$K$207,Adjustments!$B$8:$B$207,$B9,Adjustments!$A$8:$A$207,Settings!$A$13)) -> 0 | M9: =IF($B9="",0,SUMIFS('Zoho Dump'!$X$8:$X$3007,'Zoho Dump'!$N$8:$N$3007,$B9,'Zoho Dump'!$P$8:$P$3007,Settings!$A$14)+SUMIFS(Adjustments!$K$8:$K$207,Adjustments!$B$8:$B$207,$B9,Adjustments!$A$8:$A$207,Settings!$A$14)) -> 0 | N9: =IF($B9="",0,SUMIFS('Zoho Dump'!$X$8:$X$3007,'Zoho Dump'!$N$8:$N$3007,$B9,'Zoho Dump'!$P$8:$P$3007,Settings!$A$15)+SUMIFS(Adjustments!$K$8:$K$207,Adjustments!$B$8:$B$207,$B9,Adjustments!$A$8:$A$207,Settings!$A$15)) -> 0 | O9: =IF($B9="",0,SUMIFS('Zoho Dump'!$X$8:$X$3007,'Zoho Dump'!$N$8:$N$3007,$B9,'Zoho Dump'!$P$8:$P$3007,Settings!$A$16)+SUMIFS(Adjustments!$K$8:$K$207,Adjustments!$B$8:$B$207,$B9,Adjustments!$A$8:$A$207,Settings!$A$16)) -> 4428 | P9: =IF($B9="",0,SUMIFS('Zoho Dump'!$X$8:$X$3007,'Zoho Dump'!$N$8:$N$3007,$B9,'Zoho Dump'!$P$8:$P$3007,Settings!$A$17)+SUMIFS(Adjustments!$K$8:$K$207,Adjustments!$B$8:$B$207,$B9,Adjustments!$A$8:$A$207,Settings!$A$17)) -> 0 | Q9: =IF($B9="",0,SUMIFS('Zoho Dump'!$X$8:$X$3007,'Zoho Dump'!$N$8:$N$3007,$B9,'Zoho Dump'!$P$8:$P$3007,Settings!$A$18)+SUMIFS(Adjustments!$K$8:$K$207,Adjustments!$B$8:$B$207,$B9,Adjustments!$A$8:$A$207,Settings!$A$18)) -> 0 | R9: =IF(G9>0,G9+A9/10000000,"") -> 21428
A10: 6 | B10: =IFERROR(INDEX('Zoho Dump'!$N$8:$N$3007,MATCH(A10,'Zoho Dump'!$AB$8:$AB$3007,0)),"") -> AICD | C10: =IF($B10="",0,SUMIFS('Zoho Dump'!$Q$8:$Q$3007,'Zoho Dump'!$N$8:$N$3007,$B10,'Zoho Dump'!$T$8:$T$3007,"Delivered",'Zoho Dump'!$R$8:$R$3007,">="&Settings!$B$4)) -> 0 | D10: =IF($B10="",0,SUMIFS('Zoho Dump'!$X$8:$X$3007,'Zoho Dump'!$N$8:$N$3007,$B10,'Zoho Dump'!$T$8:$T$3007,"Backlog")+SUMIFS(Adjustments!$K$8:$K$207,Adjustments!$B$8:$B$207,$B10,Adjustments!$H$8:$H$207,"Backlog")) -> 0 | E10: =IF($B10="",0,SUMIFS('Zoho Dump'!$Y$8:$Y$3007,'Zoho Dump'!$N$8:$N$3007,$B10,'Zoho Dump'!$T$8:$T$3007,"Pipeline")+SUMIFS(Adjustments!$L$8:$L$207,Adjustments!$B$8:$B$207,$B10,Adjustments!$H$8:$H$207,"Pipeline")+SUMIFS('Zoho Dump'!$Y$8:$Y$3007,'Zoho Dump'!$N$8:$N$3007,$B10,'Zoho Dump'!$T$8:$T$3007,"Overdue")+SUMIFS(Adjustments!$L$8:$L$207,Adjustments!$B$8:$B$207,$B10,Adjustments!$H$8:$H$207,"Overdue")) -> 0 | F10: =IF($B10="",0,SUMIFS('Zoho Dump'!$X$8:$X$3007,'Zoho Dump'!$N$8:$N$3007,$B10,'Zoho Dump'!$T$8:$T$3007,"Pipeline")+SUMIFS(Adjustments!$K$8:$K$207,Adjustments!$B$8:$B$207,$B10,Adjustments!$H$8:$H$207,"Pipeline")+SUMIFS('Zoho Dump'!$X$8:$X$3007,'Zoho Dump'!$N$8:$N$3007,$B10,'Zoho Dump'!$T$8:$T$3007,"Overdue")+SUMIFS(Adjustments!$K$8:$K$207,Adjustments!$B$8:$B$207,$B10,Adjustments!$H$8:$H$207,"Overdue")) -> 0 | G10: =D10+F10 -> 0 | H10: =IF(SUM($G$5:$G$404)=0,0,G10/SUM($G$5:$G$404)) -> 0 | I10: =IF($B10="",0,SUMIFS('Zoho Dump'!$Q$8:$Q$3007,'Zoho Dump'!$N$8:$N$3007,$B10,'Zoho Dump'!$T$8:$T$3007,"Lost",'Zoho Dump'!$R$8:$R$3007,">="&Settings!$B$4)) -> 0 | J10: =IF($B10="","",IF(COUNTIF(Dashboard!$C$13:$C$22,$B10)>0,"Yes","")) | K10: =IF($B10="",0,SUMIFS('Zoho Dump'!$X$8:$X$3007,'Zoho Dump'!$N$8:$N$3007,$B10,'Zoho Dump'!$P$8:$P$3007,Settings!$A$12)+SUMIFS(Adjustments!$K$8:$K$207,Adjustments!$B$8:$B$207,$B10,Adjustments!$A$8:$A$207,Settings!$A$12)) -> 0 | L10: =IF($B10="",0,SUMIFS('Zoho Dump'!$X$8:$X$3007,'Zoho Dump'!$N$8:$N$3007,$B10,'Zoho Dump'!$P$8:$P$3007,Settings!$A$13)+SUMIFS(Adjustments!$K$8:$K$207,Adjustments!$B$8:$B$207,$B10,Adjustments!$A$8:$A$207,Settings!$A$13)) -> 0 | M10: =IF($B10="",0,SUMIFS('Zoho Dump'!$X$8:$X$3007,'Zoho Dump'!$N$8:$N$3007,$B10,'Zoho Dump'!$P$8:$P$3007,Settings!$A$14)+SUMIFS(Adjustments!$K$8:$K$207,Adjustments!$B$8:$B$207,$B10,Adjustments!$A$8:$A$207,Settings!$A$14)) -> 0 | N10: =IF($B10="",0,SUMIFS('Zoho Dump'!$X$8:$X$3007,'Zoho Dump'!$N$8:$N$3007,$B10,'Zoho Dump'!$P$8:$P$3007,Settings!$A$15)+SUMIFS(Adjustments!$K$8:$K$207,Adjustments!$B$8:$B$207,$B10,Adjustments!$A$8:$A$207,Settings!$A$15)) -> 0 | O10: =IF($B10="",0,SUMIFS('Zoho Dump'!$X$8:$X$3007,'Zoho Dump'!$N$8:$N$3007,$B10,'Zoho Dump'!$P$8:$P$3007,Settings!$A$16)+SUMIFS(Adjustments!$K$8:$K$207,Adjustments!$B$8:$B$207,$B10,Adjustments!$A$8:$A$207,Settings!$A$16)) -> 0 | P10: =IF($B10="",0,SUMIFS('Zoho Dump'!$X$8:$X$3007,'Zoho Dump'!$N$8:$N$3007,$B10,'Zoho Dump'!$P$8:$P$3007,Settings!$A$17)+SUMIFS(Adjustments!$K$8:$K$207,Adjustments!$B$8:$B$207,$B10,Adjustments!$A$8:$A$207,Settings!$A$17)) -> 0 | Q10: =IF($B10="",0,SUMIFS('Zoho Dump'!$X$8:$X$3007,'Zoho Dump'!$N$8:$N$3007,$B10,'Zoho Dump'!$P$8:$P$3007,Settings!$A$18)+SUMIFS(Adjustments!$K$8:$K$207,Adjustments!$B$8:$B$207,$B10,Adjustments!$A$8:$A$207,Settings!$A$18)) -> 0 | R10: =IF(G10>0,G10+A10/10000000,"")
A11: 7 | B11: =IFERROR(INDEX('Zoho Dump'!$N$8:$N$3007,MATCH(A11,'Zoho Dump'!$AB$8:$AB$3007,0)),"") -> Elkiem | C11: =IF($B11="",0,SUMIFS('Zoho Dump'!$Q$8:$Q$3007,'Zoho Dump'!$N$8:$N$3007,$B11,'Zoho Dump'!$T$8:$T$3007,"Delivered",'Zoho Dump'!$R$8:$R$3007,">="&Settings!$B$4)) -> 2280 | D11: =IF($B11="",0,SUMIFS('Zoho Dump'!$X$8:$X$3007,'Zoho Dump'!$N$8:$N$3007,$B11,'Zoho Dump'!$T$8:$T$3007,"Backlog")+SUMIFS(Adjustments!$K$8:$K$207,Adjustments!$B$8:$B$207,$B11,Adjustments!$H$8:$H$207,"Backlog")) -> 0 | E11: =IF($B11="",0,SUMIFS('Zoho Dump'!$Y$8:$Y$3007,'Zoho Dump'!$N$8:$N$3007,$B11,'Zoho Dump'!$T$8:$T$3007,"Pipeline")+SUMIFS(Adjustments!$L$8:$L$207,Adjustments!$B$8:$B$207,$B11,Adjustments!$H$8:$H$207,"Pipeline")+SUMIFS('Zoho Dump'!$Y$8:$Y$3007,'Zoho Dump'!$N$8:$N$3007,$B11,'Zoho Dump'!$T$8:$T$3007,"Overdue")+SUMIFS(Adjustments!$L$8:$L$207,Adjustments!$B$8:$B$207,$B11,Adjustments!$H$8:$H$207,"Overdue")) -> 380 | F11: =IF($B11="",0,SUMIFS('Zoho Dump'!$X$8:$X$3007,'Zoho Dump'!$N$8:$N$3007,$B11,'Zoho Dump'!$T$8:$T$3007,"Pipeline")+SUMIFS(Adjustments!$K$8:$K$207,Adjustments!$B$8:$B$207,$B11,Adjustments!$H$8:$H$207,"Pipeline")+SUMIFS('Zoho Dump'!$X$8:$X$3007,'Zoho Dump'!$N$8:$N$3007,$B11,'Zoho Dump'!$T$8:$T$3007,"Overdue")+SUMIFS(Adjustments!$K$8:$K$207,Adjustments!$B$8:$B$207,$B11,Adjustments!$H$8:$H$207,"Overdue")) -> 190 | G11: =D11+F11 -> 190 | H11: =IF(SUM($G$5:$G$404)=0,0,G11/SUM($G$5:$G$404)) -> 0.0002226906 | I11: =IF($B11="",0,SUMIFS('Zoho Dump'!$Q$8:$Q$3007,'Zoho Dump'!$N$8:$N$3007,$B11,'Zoho Dump'!$T$8:$T$3007,"Lost",'Zoho Dump'!$R$8:$R$3007,">="&Settings!$B$4)) -> 2280 | J11: =IF($B11="","",IF(COUNTIF(Dashboard!$C$13:$C$22,$B11)>0,"Yes","")) | K11: =IF($B11="",0,SUMIFS('Zoho Dump'!$X$8:$X$3007,'Zoho Dump'!$N$8:$N$3007,$B11,'Zoho Dump'!$P$8:$P$3007,Settings!$A$12)+SUMIFS(Adjustments!$K$8:$K$207,Adjustments!$B$8:$B$207,$B11,Adjustments!$A$8:$A$207,Settings!$A$12)) -> 0 | L11: =IF($B11="",0,SUMIFS('Zoho Dump'!$X$8:$X$3007,'Zoho Dump'!$N$8:$N$3007,$B11,'Zoho Dump'!$P$8:$P$3007,Settings!$A$13)+SUMIFS(Adjustments!$K$8:$K$207,Adjustments!$B$8:$B$207,$B11,Adjustments!$A$8:$A$207,Settings!$A$13)) -> 190 | M11: =IF($B11="",0,SUMIFS('Zoho Dump'!$X$8:$X$3007,'Zoho Dump'!$N$8:$N$3007,$B11,'Zoho Dump'!$P$8:$P$3007,Settings!$A$14)+SUMIFS(Adjustments!$K$8:$K$207,Adjustments!$B$8:$B$207,$B11,Adjustments!$A$8:$A$207,Settings!$A$14)) -> 0 | N11: =IF($B11="",0,SUMIFS('Zoho Dump'!$X$8:$X$3007,'Zoho Dump'!$N$8:$N$3007,$B11,'Zoho Dump'!$P$8:$P$3007,Settings!$A$15)+SUMIFS(Adjustments!$K$8:$K$207,Adjustments!$B$8:$B$207,$B11,Adjustments!$A$8:$A$207,Settings!$A$15)) -> 0 | O11: =IF($B11="",0,SUMIFS('Zoho Dump'!$X$8:$X$3007,'Zoho Dump'!$N$8:$N$3007,$B11,'Zoho Dump'!$P$8:$P$3007,Settings!$A$16)+SUMIFS(Adjustments!$K$8:$K$207,Adjustments!$B$8:$B$207,$B11,Adjustments!$A$8:$A$207,Settings!$A$16)) -> 0 | P11: =IF($B11="",0,SUMIFS('Zoho Dump'!$X$8:$X$3007,'Zoho Dump'!$N$8:$N$3007,$B11,'Zoho Dump'!$P$8:$P$3007,Settings!$A$17)+SUMIFS(Adjustments!$K$8:$K$207,Adjustments!$B$8:$B$207,$B11,Adjustments!$A$8:$A$207,Settings!$A$17)) -> 0 | Q11: =IF($B11="",0,SUMIFS('Zoho Dump'!$X$8:$X$3007,'Zoho Dump'!$N$8:$N$3007,$B11,'Zoho Dump'!$P$8:$P$3007,Settings!$A$18)+SUMIFS(Adjustments!$K$8:$K$207,Adjustments!$B$8:$B$207,$B11,Adjustments!$A$8:$A$207,Settings!$A$18)) -> 0 | R11: =IF(G11>0,G11+A11/10000000,"") -> 190
A12: 8 | B12: =IFERROR(INDEX('Zoho Dump'!$N$8:$N$3007,MATCH(A12,'Zoho Dump'!$AB$8:$AB$3007,0)),"") -> Automic Group | C12: =IF($B12="",0,SUMIFS('Zoho Dump'!$Q$8:$Q$3007,'Zoho Dump'!$N$8:$N$3007,$B12,'Zoho Dump'!$T$8:$T$3007,"Delivered",'Zoho Dump'!$R$8:$R$3007,">="&Settings!$B$4)) -> 7978 | D12: =IF($B12="",0,SUMIFS('Zoho Dump'!$X$8:$X$3007,'Zoho Dump'!$N$8:$N$3007,$B12,'Zoho Dump'!$T$8:$T$3007,"Backlog")+SUMIFS(Adjustments!$K$8:$K$207,Adjustments!$B$8:$B$207,$B12,Adjustments!$H$8:$H$207,"Backlog")) -> 0 | E12: =IF($B12="",0,SUMIFS('Zoho Dump'!$Y$8:$Y$3007,'Zoho Dump'!$N$8:$N$3007,$B12,'Zoho Dump'!$T$8:$T$3007,"Pipeline")+SUMIFS(Adjustments!$L$8:$L$207,Adjustments!$B$8:$B$207,$B12,Adjustments!$H$8:$H$207,"Pipeline")+SUMIFS('Zoho Dump'!$Y$8:$Y$3007,'Zoho Dump'!$N$8:$N$3007,$B12,'Zoho Dump'!$T$8:$T$3007,"Overdue")+SUMIFS(Adjustments!$L$8:$L$207,Adjustments!$B$8:$B$207,$B12,Adjustments!$H$8:$H$207,"Overdue")) -> 71283 | F12: =IF($B12="",0,SUMIFS('Zoho Dump'!$X$8:$X$3007,'Zoho Dump'!$N$8:$N$3007,$B12,'Zoho Dump'!$T$8:$T$3007,"Pipeline")+SUMIFS(Adjustments!$K$8:$K$207,Adjustments!$B$8:$B$207,$B12,Adjustments!$H$8:$H$207,"Pipeline")+SUMIFS('Zoho Dump'!$X$8:$X$3007,'Zoho Dump'!$N$8:$N$3007,$B12,'Zoho Dump'!$T$8:$T$3007,"Overdue")+SUMIFS(Adjustments!$K$8:$K$207,Adjustments!$B$8:$B$207,$B12,Adjustments!$H$8:$H$207,"Overdue")) -> 40654.7 | G12: =D12+F12 -> 40654.7 | H12: =IF(SUM($G$5:$G$404)=0,0,G12/SUM($G$5:$G$404)) -> 0.047649577 | I12: =IF($B12="",0,SUMIFS('Zoho Dump'!$Q$8:$Q$3007,'Zoho Dump'!$N$8:$N$3007,$B12,'Zoho Dump'!$T$8:$T$3007,"Lost",'Zoho Dump'!$R$8:$R$3007,">="&Settings!$B$4)) -> 0 | J12: =IF($B12="","",IF(COUNTIF(Dashboard!$C$13:$C$22,$B12)>0,"Yes","")) | K12: =IF($B12="",0,SUMIFS('Zoho Dump'!$X$8:$X$3007,'Zoho Dump'!$N$8:$N$3007,$B12,'Zoho Dump'!$P$8:$P$3007,Settings!$A$12)+SUMIFS(Adjustments!$K$8:$K$207,Adjustments!$B$8:$B$207,$B12,Adjustments!$A$8:$A$207,Settings!$A$12)) -> 0 | L12: =IF($B12="",0,SUMIFS('Zoho Dump'!$X$8:$X$3007,'Zoho Dump'!$N$8:$N$3007,$B12,'Zoho Dump'!$P$8:$P$3007,Settings!$A$13)+SUMIFS(Adjustments!$K$8:$K$207,Adjustments!$B$8:$B$207,$B12,Adjustments!$A$8:$A$207,Settings!$A$13)) -> 40654.7 | M12: =IF($B12="",0,SUMIFS('Zoho Dump'!$X$8:$X$3007,'Zoho Dump'!$N$8:$N$3007,$B12,'Zoho Dump'!$P$8:$P$3007,Settings!$A$14)+SUMIFS(Adjustments!$K$8:$K$207,Adjustments!$B$8:$B$207,$B12,Adjustments!$A$8:$A$207,Settings!$A$14)) -> 0 | N12: =IF($B12="",0,SUMIFS('Zoho Dump'!$X$8:$X$3007,'Zoho Dump'!$N$8:$N$3007,$B12,'Zoho Dump'!$P$8:$P$3007,Settings!$A$15)+SUMIFS(Adjustments!$K$8:$K$207,Adjustments!$B$8:$B$207,$B12,Adjustments!$A$8:$A$207,Settings!$A$15)) -> 0 | O12: =IF($B12="",0,SUMIFS('Zoho Dump'!$X$8:$X$3007,'Zoho Dump'!$N$8:$N$3007,$B12,'Zoho Dump'!$P$8:$P$3007,Settings!$A$16)+SUMIFS(Adjustments!$K$8:$K$207,Adjustments!$B$8:$B$207,$B12,Adjustments!$A$8:$A$207,Settings!$A$16)) -> 0 | P12: =IF($B12="",0,SUMIFS('Zoho Dump'!$X$8:$X$3007,'Zoho Dump'!$N$8:$N$3007,$B12,'Zoho Dump'!$P$8:$P$3007,Settings!$A$17)+SUMIFS(Adjustments!$K$8:$K$207,Adjustments!$B$8:$B$207,$B12,Adjustments!$A$8:$A$207,Settings!$A$17)) -> 0 | Q12: =IF($B12="",0,SUMIFS('Zoho Dump'!$X$8:$X$3007,'Zoho Dump'!$N$8:$N$3007,$B12,'Zoho Dump'!$P$8:$P$3007,Settings!$A$18)+SUMIFS(Adjustments!$K$8:$K$207,Adjustments!$B$8:$B$207,$B12,Adjustments!$A$8:$A$207,Settings!$A$18)) -> 0 | R12: =IF(G12>0,G12+A12/10000000,"") -> 40654.7
A13: 9 | B13: =IFERROR(INDEX('Zoho Dump'!$N$8:$N$3007,MATCH(A13,'Zoho Dump'!$AB$8:$AB$3007,0)),"") -> Property and Development NSW | C13: =IF($B13="",0,SUMIFS('Zoho Dump'!$Q$8:$Q$3007,'Zoho Dump'!$N$8:$N$3007,$B13,'Zoho Dump'!$T$8:$T$3007,"Delivered",'Zoho Dump'!$R$8:$R$3007,">="&Settings!$B$4)) -> 0 | D13: =IF($B13="",0,SUMIFS('Zoho Dump'!$X$8:$X$3007,'Zoho Dump'!$N$8:$N$3007,$B13,'Zoho Dump'!$T$8:$T$3007,"Backlog")+SUMIFS(Adjustments!$K$8:$K$207,Adjustments!$B$8:$B$207,$B13,Adjustments!$H$8:$H$207,"Backlog")) -> 0 | E13: =IF($B13="",0,SUMIFS('Zoho Dump'!$Y$8:$Y$3007,'Zoho Dump'!$N$8:$N$3007,$B13,'Zoho Dump'!$T$8:$T$3007,"Pipeline")+SUMIFS(Adjustments!$L$8:$L$207,Adjustments!$B$8:$B$207,$B13,Adjustments!$H$8:$H$207,"Pipeline")+SUMIFS('Zoho Dump'!$Y$8:$Y$3007,'Zoho Dump'!$N$8:$N$3007,$B13,'Zoho Dump'!$T$8:$T$3007,"Overdue")+SUMIFS(Adjustments!$L$8:$L$207,Adjustments!$B$8:$B$207,$B13,Adjustments!$H$8:$H$207,"Overdue")) -> 0 | F13: =IF($B13="",0,SUMIFS('Zoho Dump'!$X$8:$X$3007,'Zoho Dump'!$N$8:$N$3007,$B13,'Zoho Dump'!$T$8:$T$3007,"Pipeline")+SUMIFS(Adjustments!$K$8:$K$207,Adjustments!$B$8:$B$207,$B13,Adjustments!$H$8:$H$207,"Pipeline")+SUMIFS('Zoho Dump'!$X$8:$X$3007,'Zoho Dump'!$N$8:$N$3007,$B13,'Zoho Dump'!$T$8:$T$3007,"Overdue")+SUMIFS(Adjustments!$K$8:$K$207,Adjustments!$B$8:$B$207,$B13,Adjustments!$H$8:$H$207,"Overdue")) -> 0 | G13: =D13+F13 -> 0 | H13: =IF(SUM($G$5:$G$404)=0,0,G13/SUM($G$5:$G$404)) -> 0 | I13: =IF($B13="",0,SUMIFS('Zoho Dump'!$Q$8:$Q$3007,'Zoho Dump'!$N$8:$N$3007,$B13,'Zoho Dump'!$T$8:$T$3007,"Lost",'Zoho Dump'!$R$8:$R$3007,">="&Settings!$B$4)) -> 0 | J13: =IF($B13="","",IF(COUNTIF(Dashboard!$C$13:$C$22,$B13)>0,"Yes","")) | K13: =IF($B13="",0,SUMIFS('Zoho Dump'!$X$8:$X$3007,'Zoho Dump'!$N$8:$N$3007,$B13,'Zoho Dump'!$P$8:$P$3007,Settings!$A$12)+SUMIFS(Adjustments!$K$8:$K$207,Adjustments!$B$8:$B$207,$B13,Adjustments!$A$8:$A$207,Settings!$A$12)) -> 0 | L13: =IF($B13="",0,SUMIFS('Zoho Dump'!$X$8:$X$3007,'Zoho Dump'!$N$8:$N$3007,$B13,'Zoho Dump'!$P$8:$P$3007,Settings!$A$13)+SUMIFS(Adjustments!$K$8:$K$207,Adjustments!$B$8:$B$207,$B13,Adjustments!$A$8:$A$207,Settings!$A$13)) -> 0 | M13: =IF($B13="",0,SUMIFS('Zoho Dump'!$X$8:$X$3007,'Zoho Dump'!$N$8:$N$3007,$B13,'Zoho Dump'!$P$8:$P$3007,Settings!$A$14)+SUMIFS(Adjustments!$K$8:$K$207,Adjustments!$B$8:$B$207,$B13,Adjustments!$A$8:$A$207,Settings!$A$14)) -> 0 | N13: =IF($B13="",0,SUMIFS('Zoho Dump'!$X$8:$X$3007,'Zoho Dump'!$N$8:$N$3007,$B13,'Zoho Dump'!$P$8:$P$3007,Settings!$A$15)+SUMIFS(Adjustments!$K$8:$K$207,Adjustments!$B$8:$B$207,$B13,Adjustments!$A$8:$A$207,Settings!$A$15)) -> 0 | O13: =IF($B13="",0,SUMIFS('Zoho Dump'!$X$8:$X$3007,'Zoho Dump'!$N$8:$N$3007,$B13,'Zoho Dump'!$P$8:$P$3007,Settings!$A$16)+SUMIFS(Adjustments!$K$8:$K$207,Adjustments!$B$8:$B$207,$B13,Adjustments!$A$8:$A$207,Settings!$A$16)) -> 0 | P13: =IF($B13="",0,SUMIFS('Zoho Dump'!$X$8:$X$3007,'Zoho Dump'!$N$8:$N$3007,$B13,'Zoho Dump'!$P$8:$P$3007,Settings!$A$17)+SUMIFS(Adjustments!$K$8:$K$207,Adjustments!$B$8:$B$207,$B13,Adjustments!$A$8:$A$207,Settings!$A$17)) -> 0 | Q13: =IF($B13="",0,SUMIFS('Zoho Dump'!$X$8:$X$3007,'Zoho Dump'!$N$8:$N$3007,$B13,'Zoho Dump'!$P$8:$P$3007,Settings!$A$18)+SUMIFS(Adjustments!$K$8:$K$207,Adjustments!$B$8:$B$207,$B13,Adjustments!$A$8:$A$207,Settings!$A$18)) -> 0 | R13: =IF(G13>0,G13+A13/10000000,"")
A14: 10 | B14: =IFERROR(INDEX('Zoho Dump'!$N$8:$N$3007,MATCH(A14,'Zoho Dump'!$AB$8:$AB$3007,0)),"") -> MUFG IR / Orient Capital | C14: =IF($B14="",0,SUMIFS('Zoho Dump'!$Q$8:$Q$3007,'Zoho Dump'!$N$8:$N$3007,$B14,'Zoho Dump'!$T$8:$T$3007,"Delivered",'Zoho Dump'!$R$8:$R$3007,">="&Settings!$B$4)) -> 28652 | D14: =IF($B14="",0,SUMIFS('Zoho Dump'!$X$8:$X$3007,'Zoho Dump'!$N$8:$N$3007,$B14,'Zoho Dump'!$T$8:$T$3007,"Backlog")+SUMIFS(Adjustments!$K$8:$K$207,Adjustments!$B$8:$B$207,$B14,Adjustments!$H$8:$H$207,"Backlog")) -> 0 | E14: =IF($B14="",0,SUMIFS('Zoho Dump'!$Y$8:$Y$3007,'Zoho Dump'!$N$8:$N$3007,$B14,'Zoho Dump'!$T$8:$T$3007,"Pipeline")+SUMIFS(Adjustments!$L$8:$L$207,Adjustments!$B$8:$B$207,$B14,Adjustments!$H$8:$H$207,"Pipeline")+SUMIFS('Zoho Dump'!$Y$8:$Y$3007,'Zoho Dump'!$N$8:$N$3007,$B14,'Zoho Dump'!$T$8:$T$3007,"Overdue")+SUMIFS(Adjustments!$L$8:$L$207,Adjustments!$B$8:$B$207,$B14,Adjustments!$H$8:$H$207,"Overdue")) -> 110686 | F14: =IF($B14="",0,SUMIFS('Zoho Dump'!$X$8:$X$3007,'Zoho Dump'!$N$8:$N$3007,$B14,'Zoho Dump'!$T$8:$T$3007,"Pipeline")+SUMIFS(Adjustments!$K$8:$K$207,Adjustments!$B$8:$B$207,$B14,Adjustments!$H$8:$H$207,"Pipeline")+SUMIFS('Zoho Dump'!$X$8:$X$3007,'Zoho Dump'!$N$8:$N$3007,$B14,'Zoho Dump'!$T$8:$T$3007,"Overdue")+SUMIFS(Adjustments!$K$8:$K$207,Adjustments!$B$8:$B$207,$B14,Adjustments!$H$8:$H$207,"Overdue")) -> 74751.4 | G14: =D14+F14 -> 74751.4 | H14: =IF(SUM($G$5:$G$404)=0,0,G14/SUM($G$5:$G$404)) -> 0.087612812 | I14: =IF($B14="",0,SUMIFS('Zoho Dump'!$Q$8:$Q$3007,'Zoho Dump'!$N$8:$N$3007,$B14,'Zoho Dump'!$T$8:$T$3007,"Lost",'Zoho Dump'!$R$8:$R$3007,">="&Settings!$B$4)) -> 0 | J14: =IF($B14="","",IF(COUNTIF(Dashboard!$C$13:$C$22,$B14)>0,"Yes","")) | K14: =IF($B14="",0,SUMIFS('Zoho Dump'!$X$8:$X$3007,'Zoho Dump'!$N$8:$N$3007,$B14,'Zoho Dump'!$P$8:$P$3007,Settings!$A$12)+SUMIFS(Adjustments!$K$8:$K$207,Adjustments!$B$8:$B$207,$B14,Adjustments!$A$8:$A$207,Settings!$A$12)) -> 0 | L14: =IF($B14="",0,SUMIFS('Zoho Dump'!$X$8:$X$3007,'Zoho Dump'!$N$8:$N$3007,$B14,'Zoho Dump'!$P$8:$P$3007,Settings!$A$13)+SUMIFS(Adjustments!$K$8:$K$207,Adjustments!$B$8:$B$207,$B14,Adjustments!$A$8:$A$207,Settings!$A$13)) -> 74751.4 | M14: =IF($B14="",0,SUMIFS('Zoho Dump'!$X$8:$X$3007,'Zoho Dump'!$N$8:$N$3007,$B14,'Zoho Dump'!$P$8:$P$3007,Settings!$A$14)+SUMIFS(Adjustments!$K$8:$K$207,Adjustments!$B$8:$B$207,$B14,Adjustments!$A$8:$A$207,Settings!$A$14)) -> 0 | N14: =IF($B14="",0,SUMIFS('Zoho Dump'!$X$8:$X$3007,'Zoho Dump'!$N$8:$N$3007,$B14,'Zoho Dump'!$P$8:$P$3007,Settings!$A$15)+SUMIFS(Adjustments!$K$8:$K$207,Adjustments!$B$8:$B$207,$B14,Adjustments!$A$8:$A$207,Settings!$A$15)) -> 0 | O14: =IF($B14="",0,SUMIFS('Zoho Dump'!$X$8:$X$3007,'Zoho Dump'!$N$8:$N$3007,$B14,'Zoho Dump'!$P$8:$P$3007,Settings!$A$16)+SUMIFS(Adjustments!$K$8:$K$207,Adjustments!$B$8:$B$207,$B14,Adjustments!$A$8:$A$207,Settings!$A$16)) -> 0 | P14: =IF($B14="",0,SUMIFS('Zoho Dump'!$X$8:$X$3007,'Zoho Dump'!$N$8:$N$3007,$B14,'Zoho Dump'!$P$8:$P$3007,Settings!$A$17)+SUMIFS(Adjustments!$K$8:$K$207,Adjustments!$B$8:$B$207,$B14,Adjustments!$A$8:$A$207,Settings!$A$17)) -> 0 | Q14: =IF($B14="",0,SUMIFS('Zoho Dump'!$X$8:$X$3007,'Zoho Dump'!$N$8:$N$3007,$B14,'Zoho Dump'!$P$8:$P$3007,Settings!$A$18)+SUMIFS(Adjustments!$K$8:$K$207,Adjustments!$B$8:$B$207,$B14,Adjustments!$A$8:$A$207,Settings!$A$18)) -> 0 | R14: =IF(G14>0,G14+A14/10000000,"") -> 74751.4
A15: 11 | B15: =IFERROR(INDEX('Zoho Dump'!$N$8:$N$3007,MATCH(A15,'Zoho Dump'!$AB$8:$AB$3007,0)),"") -> Kirra Services | C15: =IF($B15="",0,SUMIFS('Zoho Dump'!$Q$8:$Q$3007,'Zoho Dump'!$N$8:$N$3007,$B15,'Zoho Dump'!$T$8:$T$3007,"Delivered",'Zoho Dump'!$R$8:$R$3007,">="&Settings!$B$4)) -> 0 | D15: =IF($B15="",0,SUMIFS('Zoho Dump'!$X$8:$X$3007,'Zoho Dump'!$N$8:$N$3007,$B15,'Zoho Dump'!$T$8:$T$3007,"Backlog")+SUMIFS(Adjustments!$K$8:$K$207,Adjustments!$B$8:$B$207,$B15,Adjustments!$H$8:$H$207,"Backlog")) -> 0 | E15: =IF($B15="",0,SUMIFS('Zoho Dump'!$Y$8:$Y$3007,'Zoho Dump'!$N$8:$N$3007,$B15,'Zoho Dump'!$T$8:$T$3007,"Pipeline")+SUMIFS(Adjustments!$L$8:$L$207,Adjustments!$B$8:$B$207,$B15,Adjustments!$H$8:$H$207,"Pipeline")+SUMIFS('Zoho Dump'!$Y$8:$Y$3007,'Zoho Dump'!$N$8:$N$3007,$B15,'Zoho Dump'!$T$8:$T$3007,"Overdue")+SUMIFS(Adjustments!$L$8:$L$207,Adjustments!$B$8:$B$207,$B15,Adjustments!$H$8:$H$207,"Overdue")) -> 0 | F15: =IF($B15="",0,SUMIFS('Zoho Dump'!$X$8:$X$3007,'Zoho Dump'!$N$8:$N$3007,$B15,'Zoho Dump'!$T$8:$T$3007,"Pipeline")+SUMIFS(Adjustments!$K$8:$K$207,Adjustments!$B$8:$B$207,$B15,Adjustments!$H$8:$H$207,"Pipeline")+SUMIFS('Zoho Dump'!$X$8:$X$3007,'Zoho Dump'!$N$8:$N$3007,$B15,'Zoho Dump'!$T$8:$T$3007,"Overdue")+SUMIFS(Adjustments!$K$8:$K$207,Adjustments!$B$8:$B$207,$B15,Adjustments!$H$8:$H$207,"Overdue")) -> 0 | G15: =D15+F15 -> 0 | H15: =IF(SUM($G$5:$G$404)=0,0,G15/SUM($G$5:$G$404)) -> 0 | I15: =IF($B15="",0,SUMIFS('Zoho Dump'!$Q$8:$Q$3007,'Zoho Dump'!$N$8:$N$3007,$B15,'Zoho Dump'!$T$8:$T$3007,"Lost",'Zoho Dump'!$R$8:$R$3007,">="&Settings!$B$4)) -> 58850 | J15: =IF($B15="","",IF(COUNTIF(Dashboard!$C$13:$C$22,$B15)>0,"Yes","")) | K15: =IF($B15="",0,SUMIFS('Zoho Dump'!$X$8:$X$3007,'Zoho Dump'!$N$8:$N$3007,$B15,'Zoho Dump'!$P$8:$P$3007,Settings!$A$12)+SUMIFS(Adjustments!$K$8:$K$207,Adjustments!$B$8:$B$207,$B15,Adjustments!$A$8:$A$207,Settings!$A$12)) -> 0 | L15: =IF($B15="",0,SUMIFS('Zoho Dump'!$X$8:$X$3007,'Zoho Dump'!$N$8:$N$3007,$B15,'Zoho Dump'!$P$8:$P$3007,Settings!$A$13)+SUMIFS(Adjustments!$K$8:$K$207,Adjustments!$B$8:$B$207,$B15,Adjustments!$A$8:$A$207,Settings!$A$13)) -> 0 | M15: =IF($B15="",0,SUMIFS('Zoho Dump'!$X$8:$X$3007,'Zoho Dump'!$N$8:$N$3007,$B15,'Zoho Dump'!$P$8:$P$3007,Settings!$A$14)+SUMIFS(Adjustments!$K$8:$K$207,Adjustments!$B$8:$B$207,$B15,Adjustments!$A$8:$A$207,Settings!$A$14)) -> 0 | N15: =IF($B15="",0,SUMIFS('Zoho Dump'!$X$8:$X$3007,'Zoho Dump'!$N$8:$N$3007,$B15,'Zoho Dump'!$P$8:$P$3007,Settings!$A$15)+SUMIFS(Adjustments!$K$8:$K$207,Adjustments!$B$8:$B$207,$B15,Adjustments!$A$8:$A$207,Settings!$A$15)) -> 0 | O15: =IF($B15="",0,SUMIFS('Zoho Dump'!$X$8:$X$3007,'Zoho Dump'!$N$8:$N$3007,$B15,'Zoho Dump'!$P$8:$P$3007,Settings!$A$16)+SUMIFS(Adjustments!$K$8:$K$207,Adjustments!$B$8:$B$207,$B15,Adjustments!$A$8:$A$207,Settings!$A$16)) -> 0 | P15: =IF($B15="",0,SUMIFS('Zoho Dump'!$X$8:$X$3007,'Zoho Dump'!$N$8:$N$3007,$B15,'Zoho Dump'!$P$8:$P$3007,Settings!$A$17)+SUMIFS(Adjustments!$K$8:$K$207,Adjustments!$B$8:$B$207,$B15,Adjustments!$A$8:$A$207,Settings!$A$17)) -> 0 | Q15: =IF($B15="",0,SUMIFS('Zoho Dump'!$X$8:$X$3007,'Zoho Dump'!$N$8:$N$3007,$B15,'Zoho Dump'!$P$8:$P$3007,Settings!$A$18)+SUMIFS(Adjustments!$K$8:$K$207,Adjustments!$B$8:$B$207,$B15,Adjustments!$A$8:$A$207,Settings!$A$18)) -> 0 | R15: =IF(G15>0,G15+A15/10000000,"")
A16: 12 | B16: =IFERROR(INDEX('Zoho Dump'!$N$8:$N$3007,MATCH(A16,'Zoho Dump'!$AB$8:$AB$3007,0)),"") -> Amnesium | C16: =IF($B16="",0,SUMIFS('Zoho Dump'!$Q$8:$Q$3007,'Zoho Dump'!$N$8:$N$3007,$B16,'Zoho Dump'!$T$8:$T$3007,"Delivered",'Zoho Dump'!$R$8:$R$3007,">="&Settings!$B$4)) -> 0 | D16: =IF($B16="",0,SUMIFS('Zoho Dump'!$X$8:$X$3007,'Zoho Dump'!$N$8:$N$3007,$B16,'Zoho Dump'!$T$8:$T$3007,"Backlog")+SUMIFS(Adjustments!$K$8:$K$207,Adjustments!$B$8:$B$207,$B16,Adjustments!$H$8:$H$207,"Backlog")) -> 0 | E16: =IF($B16="",0,SUMIFS('Zoho Dump'!$Y$8:$Y$3007,'Zoho Dump'!$N$8:$N$3007,$B16,'Zoho Dump'!$T$8:$T$3007,"Pipeline")+SUMIFS(Adjustments!$L$8:$L$207,Adjustments!$B$8:$B$207,$B16,Adjustments!$H$8:$H$207,"Pipeline")+SUMIFS('Zoho Dump'!$Y$8:$Y$3007,'Zoho Dump'!$N$8:$N$3007,$B16,'Zoho Dump'!$T$8:$T$3007,"Overdue")+SUMIFS(Adjustments!$L$8:$L$207,Adjustments!$B$8:$B$207,$B16,Adjustments!$H$8:$H$207,"Overdue")) -> 8811 | F16: =IF($B16="",0,SUMIFS('Zoho Dump'!$X$8:$X$3007,'Zoho Dump'!$N$8:$N$3007,$B16,'Zoho Dump'!$T$8:$T$3007,"Pipeline")+SUMIFS(Adjustments!$K$8:$K$207,Adjustments!$B$8:$B$207,$B16,Adjustments!$H$8:$H$207,"Pipeline")+SUMIFS('Zoho Dump'!$X$8:$X$3007,'Zoho Dump'!$N$8:$N$3007,$B16,'Zoho Dump'!$T$8:$T$3007,"Overdue")+SUMIFS(Adjustments!$K$8:$K$207,Adjustments!$B$8:$B$207,$B16,Adjustments!$H$8:$H$207,"Overdue")) -> 4405.5 | G16: =D16+F16 -> 4405.5 | H16: =IF(SUM($G$5:$G$404)=0,0,G16/SUM($G$5:$G$404)) -> 0.0051634918 | I16: =IF($B16="",0,SUMIFS('Zoho Dump'!$Q$8:$Q$3007,'Zoho Dump'!$N$8:$N$3007,$B16,'Zoho Dump'!$T$8:$T$3007,"Lost",'Zoho Dump'!$R$8:$R$3007,">="&Settings!$B$4)) -> 0 | J16: =IF($B16="","",IF(COUNTIF(Dashboard!$C$13:$C$22,$B16)>0,"Yes","")) | K16: =IF($B16="",0,SUMIFS('Zoho Dump'!$X$8:$X$3007,'Zoho Dump'!$N$8:$N$3007,$B16,'Zoho Dump'!$P$8:$P$3007,Settings!$A$12)+SUMIFS(Adjustments!$K$8:$K$207,Adjustments!$B$8:$B$207,$B16,Adjustments!$A$8:$A$207,Settings!$A$12)) -> 0 | L16: =IF($B16="",0,SUMIFS('Zoho Dump'!$X$8:$X$3007,'Zoho Dump'!$N$8:$N$3007,$B16,'Zoho Dump'!$P$8:$P$3007,Settings!$A$13)+SUMIFS(Adjustments!$K$8:$K$207,Adjustments!$B$8:$B$207,$B16,Adjustments!$A$8:$A$207,Settings!$A$13)) -> 0 | M16: =IF($B16="",0,SUMIFS('Zoho Dump'!$X$8:$X$3007,'Zoho Dump'!$N$8:$N$3007,$B16,'Zoho Dump'!$P$8:$P$3007,Settings!$A$14)+SUMIFS(Adjustments!$K$8:$K$207,Adjustments!$B$8:$B$207,$B16,Adjustments!$A$8:$A$207,Settings!$A$14)) -> 0 | N16: =IF($B16="",0,SUMIFS('Zoho Dump'!$X$8:$X$3007,'Zoho Dump'!$N$8:$N$3007,$B16,'Zoho Dump'!$P$8:$P$3007,Settings!$A$15)+SUMIFS(Adjustments!$K$8:$K$207,Adjustments!$B$8:$B$207,$B16,Adjustments!$A$8:$A$207,Settings!$A$15)) -> 0 | O16: =IF($B16="",0,SUMIFS('Zoho Dump'!$X$8:$X$3007,'Zoho Dump'!$N$8:$N$3007,$B16,'Zoho Dump'!$P$8:$P$3007,Settings!$A$16)+SUMIFS(Adjustments!$K$8:$K$207,Adjustments!$B$8:$B$207,$B16,Adjustments!$A$8:$A$207,Settings!$A$16)) -> 4405.5 | P16: =IF($B16="",0,SUMIFS('Zoho Dump'!$X$8:$X$3007,'Zoho Dump'!$N$8:$N$3007,$B16,'Zoho Dump'!$P$8:$P$3007,Settings!$A$17)+SUMIFS(Adjustments!$K$8:$K$207,Adjustments!$B$8:$B$207,$B16,Adjustments!$A$8:$A$207,Settings!$A$17)) -> 0 | Q16: =IF($B16="",0,SUMIFS('Zoho Dump'!$X$8:$X$3007,'Zoho Dump'!$N$8:$N$3007,$B16,'Zoho Dump'!$P$8:$P$3007,Settings!$A$18)+SUMIFS(Adjustments!$K$8:$K$207,Adjustments!$B$8:$B$207,$B16,Adjustments!$A$8:$A$207,Settings!$A$18)) -> 0 | R16: =IF(G16>0,G16+A16/10000000,"") -> 4405.5
... A404: 400 | B404: =IFERROR(INDEX('Zoho Dump'!$N$8:$N$3007,MATCH(A404,'Zoho Dump'!$AB$8:$AB$3007,0)),"") | C404: =IF($B404="",0,SUMIFS('Zoho Dump'!$Q$8:$Q$3007,'Zoho Dump'!$N$8:$N$3007,$B404,'Zoho Dump'!$T$8:$T$3007,"Delivered",'Zoho Dump'!$R$8:$R$3007,">="&Settings!$B$4)) -> 0 | D404: =IF($B404="",0,SUMIFS('Zoho Dump'!$X$8:$X$3007,'Zoho Dump'!$N$8:$N$3007,$B404,'Zoho Dump'!$T$8:$T$3007,"Backlog")+SUMIFS(Adjustments!$K$8:$K$207,Adjustments!$B$8:$B$207,$B404,Adjustments!$H$8:$H$207,"Backlog")) -> 0 | E404: =IF($B404="",0,SUMIFS('Zoho Dump'!$Y$8:$Y$3007,'Zoho Dump'!$N$8:$N$3007,$B404,'Zoho Dump'!$T$8:$T$3007,"Pipeline")+SUMIFS(Adjustments!$L$8:$L$207,Adjustments!$B$8:$B$207,$B404,Adjustments!$H$8:$H$207,"Pipeline")+SUMIFS('Zoho Dump'!$Y$8:$Y$3007,'Zoho Dump'!$N$8:$N$3007,$B404,'Zoho Dump'!$T$8:$T$3007,"Overdue")+SUMIFS(Adjustments!$L$8:$L$207,Adjustments!$B$8:$B$207,$B404,Adjustments!$H$8:$H$207,"Overdue")) -> 0 | F404: =IF($B404="",0,SUMIFS('Zoho Dump'!$X$8:$X$3007,'Zoho Dump'!$N$8:$N$3007,$B404,'Zoho Dump'!$T$8:$T$3007,"Pipeline")+SUMIFS(Adjustments!$K$8:$K$207,Adjustments!$B$8:$B$207,$B404,Adjustments!$H$8:$H$207,"Pipeline")+SUMIFS('Zoho Dump'!$X$8:$X$3007,'Zoho Dump'!$N$8:$N$3007,$B404,'Zoho Dump'!$T$8:$T$3007,"Overdue")+SUMIFS(Adjustments!$K$8:$K$207,Adjustments!$B$8:$B$207,$B404,Adjustments!$H$8:$H$207,"Overdue")) -> 0 | G404: =D404+F404 -> 0 | H404: =IF(SUM($G$5:$G$404)=0,0,G404/SUM($G$5:$G$404)) -> 0 | I404: =IF($B404="",0,SUMIFS('Zoho Dump'!$Q$8:$Q$3007,'Zoho Dump'!$N$8:$N$3007,$B404,'Zoho Dump'!$T$8:$T$3007,"Lost",'Zoho Dump'!$R$8:$R$3007,">="&Settings!$B$4)) -> 0 | J404: =IF($B404="","",IF(COUNTIF(Dashboard!$C$13:$C$22,$B404)>0,"Yes","")) | K404: =IF($B404="",0,SUMIFS('Zoho Dump'!$X$8:$X$3007,'Zoho Dump'!$N$8:$N$3007,$B404,'Zoho Dump'!$P$8:$P$3007,Settings!$A$12)+SUMIFS(Adjustments!$K$8:$K$207,Adjustments!$B$8:$B$207,$B404,Adjustments!$A$8:$A$207,Settings!$A$12)) -> 0 | L404: =IF($B404="",0,SUMIFS('Zoho Dump'!$X$8:$X$3007,'Zoho Dump'!$N$8:$N$3007,$B404,'Zoho Dump'!$P$8:$P$3007,Settings!$A$13)+SUMIFS(Adjustments!$K$8:$K$207,Adjustments!$B$8:$B$207,$B404,Adjustments!$A$8:$A$207,Settings!$A$13)) -> 0 | M404: =IF($B404="",0,SUMIFS('Zoho Dump'!$X$8:$X$3007,'Zoho Dump'!$N$8:$N$3007,$B404,'Zoho Dump'!$P$8:$P$3007,Settings!$A$14)+SUMIFS(Adjustments!$K$8:$K$207,Adjustments!$B$8:$B$207,$B404,Adjustments!$A$8:$A$207,Settings!$A$14)) -> 0 | N404: =IF($B404="",0,SUMIFS('Zoho Dump'!$X$8:$X$3007,'Zoho Dump'!$N$8:$N$3007,$B404,'Zoho Dump'!$P$8:$P$3007,Settings!$A$15)+SUMIFS(Adjustments!$K$8:$K$207,Adjustments!$B$8:$B$207,$B404,Adjustments!$A$8:$A$207,Settings!$A$15)) -> 0 | O404: =IF($B404="",0,SUMIFS('Zoho Dump'!$X$8:$X$3007,'Zoho Dump'!$N$8:$N$3007,$B404,'Zoho Dump'!$P$8:$P$3007,Settings!$A$16)+SUMIFS(Adjustments!$K$8:$K$207,Adjustments!$B$8:$B$207,$B404,Adjustments!$A$8:$A$207,Settings!$A$16)) -> 0 | P404: =IF($B404="",0,SUMIFS('Zoho Dump'!$X$8:$X$3007,'Zoho Dump'!$N$8:$N$3007,$B404,'Zoho Dump'!$P$8:$P$3007,Settings!$A$17)+SUMIFS(Adjustments!$K$8:$K$207,Adjustments!$B$8:$B$207,$B404,Adjustments!$A$8:$A$207,Settings!$A$17)) -> 0 | Q404: =IF($B404="",0,SUMIFS('Zoho Dump'!$X$8:$X$3007,'Zoho Dump'!$N$8:$N$3007,$B404,'Zoho Dump'!$P$8:$P$3007,Settings!$A$18)+SUMIFS(Adjustments!$K$8:$K$207,Adjustments!$B$8:$B$207,$B404,Adjustments!$A$8:$A$207,Settings!$A$18)) -> 0 | R404: =IF(G404>0,G404+A404/10000000,"")
B405: Total | C405: =SUM(C5:C404) -> 879921 | D405: =SUM(D5:D404) -> 85402 | E405: =SUM(E5:E404) -> 1124477 | F405: =SUM(F5:F404) -> 767799.7 | G405: =SUM(G5:G404) -> 853201.7 | H405: =SUM(H5:H404) -> 1 | I405: =SUM(I5:I404) -> 1140606 | K405: =SUM(K5:K404) -> 69500 | L405: =SUM(L5:L404) -> 702104.5 | M405: =SUM(M5:M404) -> 12597.5 | N405: =SUM(N5:N404) -> 15000 | O405: =SUM(O5:O404) -> 53999.7 | P405: =SUM(P5:P404) -> 0 | Q405: =SUM(Q5:Q404) -> 0

Sheet Zoho Dump
L1: Helper columns. Formulas only. Do not type here.
A2: All Deals by Stage (FY26-FY27)
A3: Generated by Jordan Sexty on 12/10/2026 11:49 AM | L3: Column found at:
A5: Record Count : 663 | L5: Stage | M5: Deal Name | N5: Account Name | O5: CTS DEPARTMENT | Q5: Amount | R5: Closing Date
L6: =IFERROR(MATCH("Stage",$A$7:$J$7,0),0) -> 1 | M6: =IFERROR(MATCH("Deal Name",$A$7:$J$7,0),0) -> 2 | N6: =IFERROR(MATCH("Account Name",$A$7:$J$7,0),0) -> 3 | O6: =IFERROR(MATCH("CTS DEPARTMENT",$A$7:$J$7,0),0) -> 5 | Q6: =IFERROR(MATCH("Amount*",$A$7:$J$7,0),0) -> 4 | R6: =IFERROR(MATCH("Closing Date",$A$7:$J$7,0),0) -> 6
A7: Stage | B7: Deal Name | C7: Account Name | D7: Amount (Record Currency) | E7: CTS DEPARTMENT | F7: Closing Date | G7: Opportunity Number | L7: Stage | M7: Deal | N7: Customer | O7: Zoho dept | P7: P&L dept | Q7: Amount | R7: Closing date | S7: Stage type | T7: Category | U7: Probability | V7: Weighted | W7: Lands in month | X7: Forward (weighted, this FY) | Y7: Forward (full value, this FY) | Z7: Stress case value | AA7: Withdrawn customer | AB7: Customer #
A8: Proposal Sent ( 12 ) | B8: DTTL | SYD Good Rooms programming - 2609601 | C8: Deloitte Australia | D8: 1025 | E8: Integration | F8: 46325 | G8: 2609601 | L8: =IF(INDEX($A8:$J8,$L$6)<>"",TRIM(LEFT(INDEX($A8:$J8,$L$6),FIND("(",INDEX($A8:$J8,$L$6)&"(")-1)),L7) -> Proposal Sent | M8: =IF(INDEX($A8:$J8,$M$6)="","",INDEX($A8:$J8,$M$6)&"") -> DTTL | SYD Good Rooms programming - 2609601 | N8: =IF($M8="","",TRIM(INDEX($A8:$J8,$N$6)&"")) -> Deloitte Australia | O8: =IF($M8="","",TRIM(INDEX($A8:$J8,$O$6)&"")) -> Integration | P8: =IF($M8="","",IFERROR(IF(INDEX(Settings!$B$41:$B$50,MATCH(O8,Settings!$A$41:$A$50,0))&""="","UNMAPPED",INDEX(Settings!$B$41:$B$50,MATCH(O8,Settings!$A$41:$A$50,0))&""),"UNMAPPED")) -> Integration | Q8: =IF($M8="",0,N(INDEX($A8:$J8,$Q$6))) -> 1025 | R8: =IF($M8="","",INDEX($A8:$J8,$R$6)) -> 46325 | S8: =IF($M8="","",IFERROR(INDEX(Settings!$B$27:$B$36,MATCH(L8,Settings!$A$27:$A$36,0))&"","UNMAPPED")) -> Open | T8: =IF($M8="","",IF(NOT(ISNUMBER(R8)),"NO DATE",IF(S8="Won",IF(R8>Settings!$B$5,"Backlog","Delivered"),IF(S8="Open",IF(R8>Settings!$B$5,"Pipeline","Overdue"),IF(S8="Lost","Lost","UNMAPPED"))))) -> Pipeline | U8: =IF(T8="Backlog",1,IF(OR(T8="Pipeline",T8="Overdue"),N(INDEX(Settings!$C$27:$C$36,MATCH(L8,Settings!$A$27:$A$36,0))),0)) -> 0.5 | V8: =Q8*U8 -> 512.5 | W8: =IF($M8="","",IF(T8="Overdue",IF(Settings!$B$8="Yes",Settings!$B$7,""),IF(ISNUMBER(R8),DATE(YEAR(R8),MONTH(R8),1),""))) -> 46296 | X8: =IF(AND(OR(T8="Backlog",T8="Pipeline",T8="Overdue"),ISNUMBER(W8)),IF(W8<=Settings!$B$6,V8,0),0) -> 512.5 | Y8: =IF(AND(OR(T8="Backlog",T8="Pipeline",T8="Overdue"),ISNUMBER(W8)),IF(W8<=Settings!$B$6,Q8,0),0) -> 1025 | Z8: =IF(Y8=0,0,IF(T8="Backlog",Q8,Q8*Dashboard!$C$10)) -> 0 | AA8: =IF($N8="",0,IF(COUNTIF(Dashboard!$C$13:$C$22,$N8)>0,1,0)) -> 0 | AB8: =IF($N8="","",IF(COUNTIF($N$8:$N8,$N8)=1,MAX($AB$7:$AB7)+1,"")) -> 1
B9: Investa - Barrack Place Bingo - Feb 27' | C9: Investa | D9: 2400 | E9: Event Production | F9: 46429 | G9: 26021901 | L9: =IF(INDEX($A9:$J9,$L$6)<>"",TRIM(LEFT(INDEX($A9:$J9,$L$6),FIND("(",INDEX($A9:$J9,$L$6)&"(")-1)),L8) -> Proposal Sent | M9: =IF(INDEX($A9:$J9,$M$6)="","",INDEX($A9:$J9,$M$6)&"") -> Investa - Barrack Place Bingo - Feb 27' | N9: =IF($M9="","",TRIM(INDEX($A9:$J9,$N$6)&"")) -> Investa | O9: =IF($M9="","",TRIM(INDEX($A9:$J9,$O$6)&"")) -> Event Production | P9: =IF($M9="","",IFERROR(IF(INDEX(Settings!$B$41:$B$50,MATCH(O9,Settings!$A$41:$A$50,0))&""="","UNMAPPED",INDEX(Settings!$B$41:$B$50,MATCH(O9,Settings!$A$41:$A$50,0))&""),"UNMAPPED")) -> Production | Q9: =IF($M9="",0,N(INDEX($A9:$J9,$Q$6))) -> 2400 | R9: =IF($M9="","",INDEX($A9:$J9,$R$6)) -> 46429 | S9: =IF($M9="","",IFERROR(INDEX(Settings!$B$27:$B$36,MATCH(L9,Settings!$A$27:$A$36,0))&"","UNMAPPED")) -> Open | T9: =IF($M9="","",IF(NOT(ISNUMBER(R9)),"NO DATE",IF(S9="Won",IF(R9>Settings!$B$5,"Backlog","Delivered"),IF(S9="Open",IF(R9>Settings!$B$5,"Pipeline","Overdue"),IF(S9="Lost","Lost","UNMAPPED"))))) -> Pipeline | U9: =IF(T9="Backlog",1,IF(OR(T9="Pipeline",T9="Overdue"),N(INDEX(Settings!$C$27:$C$36,MATCH(L9,Settings!$A$27:$A$36,0))),0)) -> 0.5 | V9: =Q9*U9 -> 1200 | W9: =IF($M9="","",IF(T9="Overdue",IF(Settings!$B$8="Yes",Settings!$B$7,""),IF(ISNUMBER(R9),DATE(YEAR(R9),MONTH(R9),1),""))) -> 46419 | X9: =IF(AND(OR(T9="Backlog",T9="Pipeline",T9="Overdue"),ISNUMBER(W9)),IF(W9<=Settings!$B$6,V9,0),0) -> 1200 | Y9: =IF(AND(OR(T9="Backlog",T9="Pipeline",T9="Overdue"),ISNUMBER(W9)),IF(W9<=Settings!$B$6,Q9,0),0) -> 2400 | Z9: =IF(Y9=0,0,IF(T9="Backlog",Q9,Q9*Dashboard!$C$10)) -> 0 | AA9: =IF($N9="",0,IF(COUNTIF(Dashboard!$C$13:$C$22,$N9)>0,1,0)) -> 0 | AB9: =IF($N9="","",IF(COUNTIF($N$8:$N9,$N9)=1,MAX($AB$7:$AB8)+1,"")) -> 2
B10: HP-Stryker | Multi-Site Device Replacement - 2606201 | C10: Stryker | D10: 34068 | E10: Integration | F10: 46325 | G10: 2606201 | L10: =IF(INDEX($A10:$J10,$L$6)<>"",TRIM(LEFT(INDEX($A10:$J10,$L$6),FIND("(",INDEX($A10:$J10,$L$6)&"(")-1)),L9) -> Proposal Sent | M10: =IF(INDEX($A10:$J10,$M$6)="","",INDEX($A10:$J10,$M$6)&"") -> HP-Stryker | Multi-Site Device Replacement - 2606201 | N10: =IF($M10="","",TRIM(INDEX($A10:$J10,$N$6)&"")) -> Stryker | O10: =IF($M10="","",TRIM(INDEX($A10:$J10,$O$6)&"")) -> Integration | P10: =IF($M10="","",IFERROR(IF(INDEX(Settings!$B$41:$B$50,MATCH(O10,Settings!$A$41:$A$50,0))&""="","UNMAPPED",INDEX(Settings!$B$41:$B$50,MATCH(O10,Settings!$A$41:$A$50,0))&""),"UNMAPPED")) -> Integration | Q10: =IF($M10="",0,N(INDEX($A10:$J10,$Q$6))) -> 34068 | R10: =IF($M10="","",INDEX($A10:$J10,$R$6)) -> 46325 | S10: =IF($M10="","",IFERROR(INDEX(Settings!$B$27:$B$36,MATCH(L10,Settings!$A$27:$A$36,0))&"","UNMAPPED")) -> Open | T10: =IF($M10="","",IF(NOT(ISNUMBER(R10)),"NO DATE",IF(S10="Won",IF(R10>Settings!$B$5,"Backlog","Delivered"),IF(S10="Open",IF(R10>Settings!$B$5,"Pipeline","Overdue"),IF(S10="Lost","Lost","UNMAPPED"))))) -> Pipeline | U10: =IF(T10="Backlog",1,IF(OR(T10="Pipeline",T10="Overdue"),N(INDEX(Settings!$C$27:$C$36,MATCH(L10,Settings!$A$27:$A$36,0))),0)) -> 0.5 | V10: =Q10*U10 -> 17034 | W10: =IF($M10="","",IF(T10="Overdue",IF(Settings!$B$8="Yes",Settings!$B$7,""),IF(ISNUMBER(R10),DATE(YEAR(R10),MONTH(R10),1),""))) -> 46296 | X10: =IF(AND(OR(T10="Backlog",T10="Pipeline",T10="Overdue"),ISNUMBER(W10)),IF(W10<=Settings!$B$6,V10,0),0) -> 17034 | Y10: =IF(AND(OR(T10="Backlog",T10="Pipeline",T10="Overdue"),ISNUMBER(W10)),IF(W10<=Settings!$B$6,Q10,0),0) -> 34068 | Z10: =IF(Y10=0,0,IF(T10="Backlog",Q10,Q10*Dashboard!$C$10)) -> 0 | AA10: =IF($N10="",0,IF(COUNTIF(Dashboard!$C$13:$C$22,$N10)>0,1,0)) -> 0 | AB10: =IF($N10="","",IF(COUNTIF($N$8:$N10,$N10)=1,MAX($AB$7:$AB9)+1,"")) -> 3
B11: HP-DFAT | Phone Mod x2 - 26091605 | C11: Datacom | D11: 1175 | E11: Integration | F11: 46325 | G11: 26091605 | L11: =IF(INDEX($A11:$J11,$L$6)<>"",TRIM(LEFT(INDEX($A11:$J11,$L$6),FIND("(",INDEX($A11:$J11,$L$6)&"(")-1)),L10) -> Proposal Sent | M11: =IF(INDEX($A11:$J11,$M$6)="","",INDEX($A11:$J11,$M$6)&"") -> HP-DFAT | Phone Mod x2 - 26091605 | N11: =IF($M11="","",TRIM(INDEX($A11:$J11,$N$6)&"")) -> Datacom | O11: =IF($M11="","",TRIM(INDEX($A11:$J11,$O$6)&"")) -> Integration | P11: =IF($M11="","",IFERROR(IF(INDEX(Settings!$B$41:$B$50,MATCH(O11,Settings!$A$41:$A$50,0))&""="","UNMAPPED",INDEX(Settings!$B$41:$B$50,MATCH(O11,Settings!$A$41:$A$50,0))&""),"UNMAPPED")) -> Integration | Q11: =IF($M11="",0,N(INDEX($A11:$J11,$Q$6))) -> 1175 | R11: =IF($M11="","",INDEX($A11:$J11,$R$6)) -> 46325 | S11: =IF($M11="","",IFERROR(INDEX(Settings!$B$27:$B$36,MATCH(L11,Settings!$A$27:$A$36,0))&"","UNMAPPED")) -> Open | T11: =IF($M11="","",IF(NOT(ISNUMBER(R11)),"NO DATE",IF(S11="Won",IF(R11>Settings!$B$5,"Backlog","Delivered"),IF(S11="Open",IF(R11>Settings!$B$5,"Pipeline","Overdue"),IF(S11="Lost","Lost","UNMAPPED"))))) -> Pipeline | U11: =IF(T11="Backlog",1,IF(OR(T11="Pipeline",T11="Overdue"),N(INDEX(Settings!$C$27:$C$36,MATCH(L11,Settings!$A$27:$A$36,0))),0)) -> 0.5 | V11: =Q11*U11 -> 587.5 | W11: =IF($M11="","",IF(T11="Overdue",IF(Settings!$B$8="Yes",Settings!$B$7,""),IF(ISNUMBER(R11),DATE(YEAR(R11),MONTH(R11),1),""))) -> 46296 | X11: =IF(AND(OR(T11="Backlog",T11="Pipeline",T11="Overdue"),ISNUMBER(W11)),IF(W11<=Settings!$B$6,V11,0),0) -> 587.5 | Y11: =IF(AND(OR(T11="Backlog",T11="Pipeline",T11="Overdue"),ISNUMBER(W11)),IF(W11<=Settings!$B$6,Q11,0),0) -> 1175 | Z11: =IF(Y11=0,0,IF(T11="Backlog",Q11,Q11*Dashboard!$C$10)) -> 0 | AA11: =IF($N11="",0,IF(COUNTIF(Dashboard!$C$13:$C$22,$N11)>0,1,0)) -> 0 | AB11: =IF($N11="","",IF(COUNTIF($N$8:$N11,$N11)=1,MAX($AB$7:$AB10)+1,"")) -> 4
B12: PwC | Parra Display Replacement - 26091701 | C12: PWC | D12: 8856 | E12: Integration | F12: 46325 | G12: 26091701 | L12: =IF(INDEX($A12:$J12,$L$6)<>"",TRIM(LEFT(INDEX($A12:$J12,$L$6),FIND("(",INDEX($A12:$J12,$L$6)&"(")-1)),L11) -> Proposal Sent | M12: =IF(INDEX($A12:$J12,$M$6)="","",INDEX($A12:$J12,$M$6)&"") -> PwC | Parra Display Replacement - 26091701 | N12: =IF($M12="","",TRIM(INDEX($A12:$J12,$N$6)&"")) -> PWC | O12: =IF($M12="","",TRIM(INDEX($A12:$J12,$O$6)&"")) -> Integration | P12: =IF($M12="","",IFERROR(IF(INDEX(Settings!$B$41:$B$50,MATCH(O12,Settings!$A$41:$A$50,0))&""="","UNMAPPED",INDEX(Settings!$B$41:$B$50,MATCH(O12,Settings!$A$41:$A$50,0))&""),"UNMAPPED")) -> Integration | Q12: =IF($M12="",0,N(INDEX($A12:$J12,$Q$6))) -> 8856 | R12: =IF($M12="","",INDEX($A12:$J12,$R$6)) -> 46325 | S12: =IF($M12="","",IFERROR(INDEX(Settings!$B$27:$B$36,MATCH(L12,Settings!$A$27:$A$36,0))&"","UNMAPPED")) -> Open | T12: =IF($M12="","",IF(NOT(ISNUMBER(R12)),"NO DATE",IF(S12="Won",IF(R12>Settings!$B$5,"Backlog","Delivered"),IF(S12="Open",IF(R12>Settings!$B$5,"Pipeline","Overdue"),IF(S12="Lost","Lost","UNMAPPED"))))) -> Pipeline | U12: =IF(T12="Backlog",1,IF(OR(T12="Pipeline",T12="Overdue"),N(INDEX(Settings!$C$27:$C$36,MATCH(L12,Settings!$A$27:$A$36,0))),0)) -> 0.5 | V12: =Q12*U12 -> 4428 | W12: =IF($M12="","",IF(T12="Overdue",IF(Settings!$B$8="Yes",Settings!$B$7,""),IF(ISNUMBER(R12),DATE(YEAR(R12),MONTH(R12),1),""))) -> 46296 | X12: =IF(AND(OR(T12="Backlog",T12="Pipeline",T12="Overdue"),ISNUMBER(W12)),IF(W12<=Settings!$B$6,V12,0),0) -> 4428 | Y12: =IF(AND(OR(T12="Backlog",T12="Pipeline",T12="Overdue"),ISNUMBER(W12)),IF(W12<=Settings!$B$6,Q12,0),0) -> 8856 | Z12: =IF(Y12=0,0,IF(T12="Backlog",Q12,Q12*Dashboard!$C$10)) -> 0 | AA12: =IF($N12="",0,IF(COUNTIF(Dashboard!$C$13:$C$22,$N12)>0,1,0)) -> 0 | AB12: =IF($N12="","",IF(COUNTIF($N$8:$N12,$N12)=1,MAX($AB$7:$AB11)+1,"")) -> 5
B13: AICD | Member Engagement & Sponsor Activation Concept - 2610801 | C13: AICD | E13: Event Production | F13: 46325 | G13: 2610801 | L13: =IF(INDEX($A13:$J13,$L$6)<>"",TRIM(LEFT(INDEX($A13:$J13,$L$6),FIND("(",INDEX($A13:$J13,$L$6)&"(")-1)),L12) -> Proposal Sent | M13: =IF(INDEX($A13:$J13,$M$6)="","",INDEX($A13:$J13,$M$6)&"") -> AICD | Member Engagement & Sponsor Activation Concept - 2610801 | N13: =IF($M13="","",TRIM(INDEX($A13:$J13,$N$6)&"")) -> AICD | O13: =IF($M13="","",TRIM(INDEX($A13:$J13,$O$6)&"")) -> Event Production | P13: =IF($M13="","",IFERROR(IF(INDEX(Settings!$B$41:$B$50,MATCH(O13,Settings!$A$41:$A$50,0))&""="","UNMAPPED",INDEX(Settings!$B$41:$B$50,MATCH(O13,Settings!$A$41:$A$50,0))&""),"UNMAPPED")) -> Production | Q13: =IF($M13="",0,N(INDEX($A13:$J13,$Q$6))) -> 0 | R13: =IF($M13="","",INDEX($A13:$J13,$R$6)) -> 46325 | S13: =IF($M13="","",IFERROR(INDEX(Settings!$B$27:$B$36,MATCH(L13,Settings!$A$27:$A$36,0))&"","UNMAPPED")) -> Open | T13: =IF($M13="","",IF(NOT(ISNUMBER(R13)),"NO DATE",IF(S13="Won",IF(R13>Settings!$B$5,"Backlog","Delivered"),IF(S13="Open",IF(R13>Settings!$B$5,"Pipeline","Overdue"),IF(S13="Lost","Lost","UNMAPPED"))))) -> Pipeline | U13: =IF(T13="Backlog",1,IF(OR(T13="Pipeline",T13="Overdue"),N(INDEX(Settings!$C$27:$C$36,MATCH(L13,Settings!$A$27:$A$36,0))),0)) -> 0.5 | V13: =Q13*U13 -> 0 | W13: =IF($M13="","",IF(T13="Overdue",IF(Settings!$B$8="Yes",Settings!$B$7,""),IF(ISNUMBER(R13),DATE(YEAR(R13),MONTH(R13),1),""))) -> 46296 | X13: =IF(AND(OR(T13="Backlog",T13="Pipeline",T13="Overdue"),ISNUMBER(W13)),IF(W13<=Settings!$B$6,V13,0),0) -> 0 | Y13: =IF(AND(OR(T13="Backlog",T13="Pipeline",T13="Overdue"),ISNUMBER(W13)),IF(W13<=Settings!$B$6,Q13,0),0) -> 0 | Z13: =IF(Y13=0,0,IF(T13="Backlog",Q13,Q13*Dashboard!$C$10)) -> 0 | AA13: =IF($N13="",0,IF(COUNTIF(Dashboard!$C$13:$C$22,$N13)>0,1,0)) -> 0 | AB13: =IF($N13="","",IF(COUNTIF($N$8:$N13,$N13)=1,MAX($AB$7:$AB12)+1,"")) -> 6
B14: Elkiem - Studio Support - 3.11.26 | C14: Elkiem | D14: 380 | E14: Event Production | F14: 46329 | G14: 26093001 | L14: =IF(INDEX($A14:$J14,$L$6)<>"",TRIM(LEFT(INDEX($A14:$J14,$L$6),FIND("(",INDEX($A14:$J14,$L$6)&"(")-1)),L13) -> Proposal Sent | M14: =IF(INDEX($A14:$J14,$M$6)="","",INDEX($A14:$J14,$M$6)&"") -> Elkiem - Studio Support - 3.11.26 | N14: =IF($M14="","",TRIM(INDEX($A14:$J14,$N$6)&"")) -> Elkiem | O14: =IF($M14="","",TRIM(INDEX($A14:$J14,$O$6)&"")) -> Event Production | P14: =IF($M14="","",IFERROR(IF(INDEX(Settings!$B$41:$B$50,MATCH(O14,Settings!$A$41:$A$50,0))&""="","UNMAPPED",INDEX(Settings!$B$41:$B$50,MATCH(O14,Settings!$A$41:$A$50,0))&""),"UNMAPPED")) -> Production | Q14: =IF($M14="",0,N(INDEX($A14:$J14,$Q$6))) -> 380 | R14: =IF($M14="","",INDEX($A14:$J14,$R$6)) -> 46329 | S14: =IF($M14="","",IFERROR(INDEX(Settings!$B$27:$B$36,MATCH(L14,Settings!$A$27:$A$36,0))&"","UNMAPPED")) -> Open | T14: =IF($M14="","",IF(NOT(ISNUMBER(R14)),"NO DATE",IF(S14="Won",IF(R14>Settings!$B$5,"Backlog","Delivered"),IF(S14="Open",IF(R14>Settings!$B$5,"Pipeline","Overdue"),IF(S14="Lost","Lost","UNMAPPED"))))) -> Pipeline | U14: =IF(T14="Backlog",1,IF(OR(T14="Pipeline",T14="Overdue"),N(INDEX(Settings!$C$27:$C$36,MATCH(L14,Settings!$A$27:$A$36,0))),0)) -> 0.5 | V14: =Q14*U14 -> 190 | W14: =IF($M14="","",IF(T14="Overdue",IF(Settings!$B$8="Yes",Settings!$B$7,""),IF(ISNUMBER(R14),DATE(YEAR(R14),MONTH(R14),1),""))) -> 46327 | X14: =IF(AND(OR(T14="Backlog",T14="Pipeline",T14="Overdue"),ISNUMBER(W14)),IF(W14<=Settings!$B$6,V14,0),0) -> 190 | Y14: =IF(AND(OR(T14="Backlog",T14="Pipeline",T14="Overdue"),ISNUMBER(W14)),IF(W14<=Settings!$B$6,Q14,0),0) -> 380 | Z14: =IF(Y14=0,0,IF(T14="Backlog",Q14,Q14*Dashboard!$C$10)) -> 0 | AA14: =IF($N14="",0,IF(COUNTIF(Dashboard!$C$13:$C$22,$N14)>0,1,0)) -> 0 | AB14: =IF($N14="","",IF(COUNTIF($N$8:$N14,$N14)=1,MAX($AB$7:$AB13)+1,"")) -> 7
B15: Automic - AGM RFQ - May 27' | C15: Automic Group | D15: 18500 | E15: Event Production | F15: 46535 | G15: 26071406 | L15: =IF(INDEX($A15:$J15,$L$6)<>"",TRIM(LEFT(INDEX($A15:$J15,$L$6),FIND("(",INDEX($A15:$J15,$L$6)&"(")-1)),L14) -> Proposal Sent | M15: =IF(INDEX($A15:$J15,$M$6)="","",INDEX($A15:$J15,$M$6)&"") -> Automic - AGM RFQ - May 27' | N15: =IF($M15="","",TRIM(INDEX($A15:$J15,$N$6)&"")) -> Automic Group | O15: =IF($M15="","",TRIM(INDEX($A15:$J15,$O$6)&"")) -> Event Production | P15: =IF($M15="","",IFERROR(IF(INDEX(Settings!$B$41:$B$50,MATCH(O15,Settings!$A$41:$A$50,0))&""="","UNMAPPED",INDEX(Settings!$B$41:$B$50,MATCH(O15,Settings!$A$41:$A$50,0))&""),"UNMAPPED")) -> Production | Q15: =IF($M15="",0,N(INDEX($A15:$J15,$Q$6))) -> 18500 | R15: =IF($M15="","",INDEX($A15:$J15,$R$6)) -> 46535 | S15: =IF($M15="","",IFERROR(INDEX(Settings!$B$27:$B$36,MATCH(L15,Settings!$A$27:$A$36,0))&"","UNMAPPED")) -> Open | T15: =IF($M15="","",IF(NOT(ISNUMBER(R15)),"NO DATE",IF(S15="Won",IF(R15>Settings!$B$5,"Backlog","Delivered"),IF(S15="Open",IF(R15>Settings!$B$5,"Pipeline","Overdue"),IF(S15="Lost","Lost","UNMAPPED"))))) -> Pipeline | U15: =IF(T15="Backlog",1,IF(OR(T15="Pipeline",T15="Overdue"),N(INDEX(Settings!$C$27:$C$36,MATCH(L15,Settings!$A$27:$A$36,0))),0)) -> 0.5 | V15: =Q15*U15 -> 9250 | W15: =IF($M15="","",IF(T15="Overdue",IF(Settings!$B$8="Yes",Settings!$B$7,""),IF(ISNUMBER(R15),DATE(YEAR(R15),MONTH(R15),1),""))) -> 46508 | X15: =IF(AND(OR(T15="Backlog",T15="Pipeline",T15="Overdue"),ISNUMBER(W15)),IF(W15<=Settings!$B$6,V15,0),0) -> 9250 | Y15: =IF(AND(OR(T15="Backlog",T15="Pipeline",T15="Overdue"),ISNUMBER(W15)),IF(W15<=Settings!$B$6,Q15,0),0) -> 18500 | Z15: =IF(Y15=0,0,IF(T15="Backlog",Q15,Q15*Dashboard!$C$10)) -> 0 | AA15: =IF($N15="",0,IF(COUNTIF(Dashboard!$C$13:$C$22,$N15)>0,1,0)) -> 0 | AB15: =IF($N15="","",IF(COUNTIF($N$8:$N15,$N15)=1,MAX($AB$7:$AB14)+1,"")) -> 8
B16: PDNSW | 6PSQ Eptura Visitor Subscription Renewal - 2610603 | C16: Property and Development NSW | E16: Integration | F16: 46325 | G16: 2610603 | L16: =IF(INDEX($A16:$J16,$L$6)<>"",TRIM(LEFT(INDEX($A16:$J16,$L$6),FIND("(",INDEX($A16:$J16,$L$6)&"(")-1)),L15) -> Proposal Sent | M16: =IF(INDEX($A16:$J16,$M$6)="","",INDEX($A16:$J16,$M$6)&"") -> PDNSW | 6PSQ Eptura Visitor Subscription Renewal - 2610603 | N16: =IF($M16="","",TRIM(INDEX($A16:$J16,$N$6)&"")) -> Property and Development NSW | O16: =IF($M16="","",TRIM(INDEX($A16:$J16,$O$6)&"")) -> Integration | P16: =IF($M16="","",IFERROR(IF(INDEX(Settings!$B$41:$B$50,MATCH(O16,Settings!$A$41:$A$50,0))&""="","UNMAPPED",INDEX(Settings!$B$41:$B$50,MATCH(O16,Settings!$A$41:$A$50,0))&""),"UNMAPPED")) -> Integration | Q16: =IF($M16="",0,N(INDEX($A16:$J16,$Q$6))) -> 0 | R16: =IF($M16="","",INDEX($A16:$J16,$R$6)) -> 46325 | S16: =IF($M16="","",IFERROR(INDEX(Settings!$B$27:$B$36,MATCH(L16,Settings!$A$27:$A$36,0))&"","UNMAPPED")) -> Open | T16: =IF($M16="","",IF(NOT(ISNUMBER(R16)),"NO DATE",IF(S16="Won",IF(R16>Settings!$B$5,"Backlog","Delivered"),IF(S16="Open",IF(R16>Settings!$B$5,"Pipeline","Overdue"),IF(S16="Lost","Lost","UNMAPPED"))))) -> Pipeline | U16: =IF(T16="Backlog",1,IF(OR(T16="Pipeline",T16="Overdue"),N(INDEX(Settings!$C$27:$C$36,MATCH(L16,Settings!$A$27:$A$36,0))),0)) -> 0.5 | V16: =Q16*U16 -> 0 | W16: =IF($M16="","",IF(T16="Overdue",IF(Settings!$B$8="Yes",Settings!$B$7,""),IF(ISNUMBER(R16),DATE(YEAR(R16),MONTH(R16),1),""))) -> 46296 | X16: =IF(AND(OR(T16="Backlog",T16="Pipeline",T16="Overdue"),ISNUMBER(W16)),IF(W16<=Settings!$B$6,V16,0),0) -> 0 | Y16: =IF(AND(OR(T16="Backlog",T16="Pipeline",T16="Overdue"),ISNUMBER(W16)),IF(W16<=Settings!$B$6,Q16,0),0) -> 0 | Z16: =IF(Y16=0,0,IF(T16="Backlog",Q16,Q16*Dashboard!$C$10)) -> 0 | AA16: =IF($N16="",0,IF(COUNTIF(Dashboard!$C$13:$C$22,$N16)>0,1,0)) -> 0 | AB16: =IF($N16="","",IF(COUNTIF($N$8:$N16,$N16)=1,MAX($AB$7:$AB15)+1,"")) -> 9
B17: MUFG - NXT DC AGM - 20.11.26 | C17: MUFG IR / Orient Capital | D17: 18415 | E17: Event Production | F17: 46346 | G17: 2608401 | L17: =IF(INDEX($A17:$J17,$L$6)<>"",TRIM(LEFT(INDEX($A17:$J17,$L$6),FIND("(",INDEX($A17:$J17,$L$6)&"(")-1)),L16) -> Proposal Sent | M17: =IF(INDEX($A17:$J17,$M$6)="","",INDEX($A17:$J17,$M$6)&"") -> MUFG - NXT DC AGM - 20.11.26 | N17: =IF($M17="","",TRIM(INDEX($A17:$J17,$N$6)&"")) -> MUFG IR / Orient Capital | O17: =IF($M17="","",TRIM(INDEX($A17:$J17,$O$6)&"")) -> Event Production | P17: =IF($M17="","",IFERROR(IF(INDEX(Settings!$B$41:$B$50,MATCH(O17,Settings!$A$41:$A$50,0))&""="","UNMAPPED",INDEX(Settings!$B$41:$B$50,MATCH(O17,Settings!$A$41:$A$50,0))&""),"UNMAPPED")) -> Production | Q17: =IF($M17="",0,N(INDEX($A17:$J17,$Q$6))) -> 18415 | R17: =IF($M17="","",INDEX($A17:$J17,$R$6)) -> 46346 | S17: =IF($M17="","",IFERROR(INDEX(Settings!$B$27:$B$36,MATCH(L17,Settings!$A$27:$A$36,0))&"","UNMAPPED")) -> Open | T17: =IF($M17="","",IF(NOT(ISNUMBER(R17)),"NO DATE",IF(S17="Won",IF(R17>Settings!$B$5,"Backlog","Delivered"),IF(S17="Open",IF(R17>Settings!$B$5,"Pipeline","Overdue"),IF(S17="Lost","Lost","UNMAPPED"))))) -> Pipeline | U17: =IF(T17="Backlog",1,IF(OR(T17="Pipeline",T17="Overdue"),N(INDEX(Settings!$C$27:$C$36,MATCH(L17,Settings!$A$27:$A$36,0))),0)) -> 0.5 | V17: =Q17*U17 -> 9207.5 | W17: =IF($M17="","",IF(T17="Overdue",IF(Settings!$B$8="Yes",Settings!$B$7,""),IF(ISNUMBER(R17),DATE(YEAR(R17),MONTH(R17),1),""))) -> 46327 | X17: =IF(AND(OR(T17="Backlog",T17="Pipeline",T17="Overdue"),ISNUMBER(W17)),IF(W17<=Settings!$B$6,V17,0),0) -> 9207.5 | Y17: =IF(AND(OR(T17="Backlog",T17="Pipeline",T17="Overdue"),ISNUMBER(W17)),IF(W17<=Settings!$B$6,Q17,0),0) -> 18415 | Z17: =IF(Y17=0,0,IF(T17="Backlog",Q17,Q17*Dashboard!$C$10)) -> 0 | AA17: =IF($N17="",0,IF(COUNTIF(Dashboard!$C$13:$C$22,$N17)>0,1,0)) -> 0 | AB17: =IF($N17="","",IF(COUNTIF($N$8:$N17,$N17)=1,MAX($AB$7:$AB16)+1,"")) -> 10
B18: Kirra | WACHS Tender Support - 26072104 | C18: Kirra Services | E18: Consulting | F18: 46325 | G18: 26072104 | L18: =IF(INDEX($A18:$J18,$L$6)<>"",TRIM(LEFT(INDEX($A18:$J18,$L$6),FIND("(",INDEX($A18:$J18,$L$6)&"(")-1)),L17) -> Proposal Sent | M18: =IF(INDEX($A18:$J18,$M$6)="","",INDEX($A18:$J18,$M$6)&"") -> Kirra | WACHS Tender Support - 26072104 | N18: =IF($M18="","",TRIM(INDEX($A18:$J18,$N$6)&"")) -> Kirra Services | O18: =IF($M18="","",TRIM(INDEX($A18:$J18,$O$6)&"")) -> Consulting | P18: =IF($M18="","",IFERROR(IF(INDEX(Settings!$B$41:$B$50,MATCH(O18,Settings!$A$41:$A$50,0))&""="","UNMAPPED",INDEX(Settings!$B$41:$B$50,MATCH(O18,Settings!$A$41:$A$50,0))&""),"UNMAPPED")) -> Consulting | Q18: =IF($M18="",0,N(INDEX($A18:$J18,$Q$6))) -> 0 | R18: =IF($M18="","",INDEX($A18:$J18,$R$6)) -> 46325 | S18: =IF($M18="","",IFERROR(INDEX(Settings!$B$27:$B$36,MATCH(L18,Settings!$A$27:$A$36,0))&"","UNMAPPED")) -> Open | T18: =IF($M18="","",IF(NOT(ISNUMBER(R18)),"NO DATE",IF(S18="Won",IF(R18>Settings!$B$5,"Backlog","Delivered"),IF(S18="Open",IF(R18>Settings!$B$5,"Pipeline","Overdue"),IF(S18="Lost","Lost","UNMAPPED"))))) -> Pipeline | U18: =IF(T18="Backlog",1,IF(OR(T18="Pipeline",T18="Overdue"),N(INDEX(Settings!$C$27:$C$36,MATCH(L18,Settings!$A$27:$A$36,0))),0)) -> 0.5 | V18: =Q18*U18 -> 0 | W18: =IF($M18="","",IF(T18="Overdue",IF(Settings!$B$8="Yes",Settings!$B$7,""),IF(ISNUMBER(R18),DATE(YEAR(R18),MONTH(R18),1),""))) -> 46296 | X18: =IF(AND(OR(T18="Backlog",T18="Pipeline",T18="Overdue"),ISNUMBER(W18)),IF(W18<=Settings!$B$6,V18,0),0) -> 0 | Y18: =IF(AND(OR(T18="Backlog",T18="Pipeline",T18="Overdue"),ISNUMBER(W18)),IF(W18<=Settings!$B$6,Q18,0),0) -> 0 | Z18: =IF(Y18=0,0,IF(T18="Backlog",Q18,Q18*Dashboard!$C$10)) -> 0 | AA18: =IF($N18="",0,IF(COUNTIF(Dashboard!$C$13:$C$22,$N18)>0,1,0)) -> 0 | AB18: =IF($N18="","",IF(COUNTIF($N$8:$N18,$N18)=1,MAX($AB$7:$AB17)+1,"")) -> 11
B19: HP-Amnesium | Austrade Phone Mod x12 - 26091603 | C19: Amnesium | D19: 8811 | E19: Integration | F19: 46325 | G19: 26091603 | L19: =IF(INDEX($A19:$J19,$L$6)<>"",TRIM(LEFT(INDEX($A19:$J19,$L$6),FIND("(",INDEX($A19:$J19,$L$6)&"(")-1)),L18) -> Proposal Sent | M19: =IF(INDEX($A19:$J19,$M$6)="","",INDEX($A19:$J19,$M$6)&"") -> HP-Amnesium | Austrade Phone Mod x12 - 26091603 | N19: =IF($M19="","",TRIM(INDEX($A19:$J19,$N$6)&"")) -> Amnesium | O19: =IF($M19="","",TRIM(INDEX($A19:$J19,$O$6)&"")) -> Integration | P19: =IF($M19="","",IFERROR(IF(INDEX(Settings!$B$41:$B$50,MATCH(O19,Settings!$A$41:$A$50,0))&""="","UNMAPPED",INDEX(Settings!$B$41:$B$50,MATCH(O19,Settings!$A$41:$A$50,0))&""),"UNMAPPED")) -> Integration | Q19: =IF($M19="",0,N(INDEX($A19:$J19,$Q$6))) -> 8811 | R19: =IF($M19="","",INDEX($A19:$J19,$R$6)) -> 46325 | S19: =IF($M19="","",IFERROR(INDEX(Settings!$B$27:$B$36,MATCH(L19,Settings!$A$27:$A$36,0))&"","UNMAPPED")) -> Open | T19: =IF($M19="","",IF(NOT(ISNUMBER(R19)),"NO DATE",IF(S19="Won",IF(R19>Settings!$B$5,"Backlog","Delivered"),IF(S19="Open",IF(R19>Settings!$B$5,"Pipeline","Overdue"),IF(S19="Lost","Lost","UNMAPPED"))))) -> Pipeline | U19: =IF(T19="Backlog",1,IF(OR(T19="Pipeline",T19="Overdue"),N(INDEX(Settings!$C$27:$C$36,MATCH(L19,Settings!$A$27:$A$36,0))),0)) -> 0.5 | V19: =Q19*U19 -> 4405.5 | W19: =IF($M19="","",IF(T19="Overdue",IF(Settings!$B$8="Yes",Settings!$B$7,""),IF(ISNUMBER(R19),DATE(YEAR(R19),MONTH(R19),1),""))) -> 46296 | X19: =IF(AND(OR(T19="Backlog",T19="Pipeline",T19="Overdue"),ISNUMBER(W19)),IF(W19<=Settings!$B$6,V19,0),0) -> 4405.5 | Y19: =IF(AND(OR(T19="Backlog",T19="Pipeline",T19="Overdue"),ISNUMBER(W19)),IF(W19<=Settings!$B$6,Q19,0),0) -> 8811 | Z19: =IF(Y19=0,0,IF(T19="Backlog",Q19,Q19*Dashboard!$C$10)) -> 0 | AA19: =IF($N19="",0,IF(COUNTIF(Dashboard!$C$13:$C$22,$N19)>0,1,0)) -> 0 | AB19: =IF($N19="","",IF(COUNTIF($N$8:$N19,$N19)=1,MAX($AB$7:$AB18)+1,"")) -> 12
A20: Negotiation/Review ( 9 ) | B20: Perth AV & Hospitality Technician (MAR27-AUG27) | C20: Deloitte Australia | D20: 75000 | E20: Support | F20: 46444 | G20: 26073104 | L20: =IF(INDEX($A20:$J20,$L$6)<>"",TRIM(LEFT(INDEX($A20:$J20,$L$6),FIND("(",INDEX($A20:$J20,$L$6)&"(")-1)),L19) -> Negotiation/Review | M20: =IF(INDEX($A20:$J20,$M$6)="","",INDEX($A20:$J20,$M$6)&"") -> Perth AV & Hospitality Technician (MAR27-AUG27) | N20: =IF($M20="","",TRIM(INDEX($A20:$J20,$N$6)&"")) -> Deloitte Australia | O20: =IF($M20="","",TRIM(INDEX($A20:$J20,$O$6)&"")) -> Support | P20: =IF($M20="","",IFERROR(IF(INDEX(Settings!$B$41:$B$50,MATCH(O20,Settings!$A$41:$A$50,0))&""="","UNMAPPED",INDEX(Settings!$B$41:$B$50,MATCH(O20,Settings!$A$41:$A$50,0))&""),"UNMAPPED")) -> Onsite | Q20: =IF($M20="",0,N(INDEX($A20:$J20,$Q$6))) -> 75000 | R20: =IF($M20="","",INDEX($A20:$J20,$R$6)) -> 46444 | S20: =IF($M20="","",IFERROR(INDEX(Settings!$B$27:$B$36,MATCH(L20,Settings!$A$27:$A$36,0))&"","UNMAPPED")) -> Open | T20: =IF($M20="","",IF(NOT(ISNUMBER(R20)),"NO DATE",IF(S20="Won",IF(R20>Settings!$B$5,"Backlog","Delivered"),IF(S20="Open",IF(R20>Settings!$B$5,"Pipeline","Overdue"),IF(S20="Lost","Lost","UNMAPPED"))))) -> Pipeline | U20: =IF(T20="Backlog",1,IF(OR(T20="Pipeline",T20="Overdue"),N(INDEX(Settings!$C$27:$C$36,MATCH(L20,Settings!$A$27:$A$36,0))),0)) -> 0.7 | V20: =Q20*U20 -> 52500 | W20: =IF($M20="","",IF(T20="Overdue",IF(Settings!$B$8="Yes",Settings!$B$7,""),IF(ISNUMBER(R20),DATE(YEAR(R20),MONTH(R20),1),""))) -> 46419 | X20: =IF(AND(OR(T20="Backlog",T20="Pipeline",T20="Overdue"),ISNUMBER(W20)),IF(W20<=Settings!$B$6,V20,0),0) -> 52500 | Y20: =IF(AND(OR(T20="Backlog",T20="Pipeline",T20="Overdue"),ISNUMBER(W20)),IF(W20<=Settings!$B$6,Q20,0),0) -> 75000 | Z20: =IF(Y20=0,0,IF(T20="Backlog",Q20,Q20*Dashboard!$C$10)) -> 0 | AA20: =IF($N20="",0,IF(COUNTIF(Dashboard!$C$13:$C$22,$N20)>0,1,0)) -> 0 | AB20: =IF($N20="","",IF(COUNTIF($N$8:$N20,$N20)=1,MAX($AB$7:$AB19)+1,""))
B21: Chorus Call - Nanosonics Investor Day - TBC.11.26 | C21: Chorus Call | D21: 4706 | E21: Event Production | F21: 46330 | G21: 2608103 | L21: =IF(INDEX($A21:$J21,$L$6)<>"",TRIM(LEFT(INDEX($A21:$J21,$L$6),FIND("(",INDEX($A21:$J21,$L$6)&"(")-1)),L20) -> Negotiation/Review | M21: =IF(INDEX($A21:$J21,$M$6)="","",INDEX($A21:$J21,$M$6)&"") -> Chorus Call - Nanosonics Investor Day - TBC.11.26 | N21: =IF($M21="","",TRIM(INDEX($A21:$J21,$N$6)&"")) -> Chorus Call | O21: =IF($M21="","",TRIM(INDEX($A21:$J21,$O$6)&"")) -> Event Production | P21: =IF($M21="","",IFERROR(IF(INDEX(Settings!$B$41:$B$50,MATCH(O21,Settings!$A$41:$A$50,0))&""="","UNMAPPED",INDEX(Settings!$B$41:$B$50,MATCH(O21,Settings!$A$41:$A$50,0))&""),"UNMAPPED")) -> Production | Q21: =IF($M21="",0,N(INDEX($A21:$J21,$Q$6))) -> 4706 | R21: =IF($M21="","",INDEX($A21:$J21,$R$6)) -> 46330 | S21: =IF($M21="","",IFERROR(INDEX(Settings!$B$27:$B$36,MATCH(L21,Settings!$A$27:$A$36,0))&"","UNMAPPED")) -> Open | T21: =IF($M21="","",IF(NOT(ISNUMBER(R21)),"NO DATE",IF(S21="Won",IF(R21>Settings!$B$5,"Backlog","Delivered"),IF(S21="Open",IF(R21>Settings!$B$5,"Pipeline","Overdue"),IF(S21="Lost","Lost","UNMAPPED"))))) -> Pipeline | U21: =IF(T21="Backlog",1,IF(OR(T21="Pipeline",T21="Overdue"),N(INDEX(Settings!$C$27:$C$36,MATCH(L21,Settings!$A$27:$A$36,0))),0)) -> 0.7 | V21: =Q21*U21 -> 3294.2 | W21: =IF($M21="","",IF(T21="Overdue",IF(Settings!$B$8="Yes",Settings!$B$7,""),IF(ISNUMBER(R21),DATE(YEAR(R21),MONTH(R21),1),""))) -> 46327 | X21: =IF(AND(OR(T21="Backlog",T21="Pipeline",T21="Overdue"),ISNUMBER(W21)),IF(W21<=Settings!$B$6,V21,0),0) -> 3294.2 | Y21: =IF(AND(OR(T21="Backlog",T21="Pipeline",T21="Overdue"),ISNUMBER(W21)),IF(W21<=Settings!$B$6,Q21,0),0) -> 4706 | Z21: =IF(Y21=0,0,IF(T21="Backlog",Q21,Q21*Dashboard!$C$10)) -> 0 | AA21: =IF($N21="",0,IF(COUNTIF(Dashboard!$C$13:$C$22,$N21)>0,1,0)) -> 0 | AB21: =IF($N21="","",IF(COUNTIF($N$8:$N21,$N21)=1,MAX($AB$7:$AB20)+1,"")) -> 13
B22: Automic - Capital Markets Forum - November 25-27 | C22: Automic Group | D22: 28000 | E22: Event Production | F22: 46328 | G22: 2603405 | L22: =IF(INDEX($A22:$J22,$L$6)<>"",TRIM(LEFT(INDEX($A22:$J22,$L$6),FIND("(",INDEX($A22:$J22,$L$6)&"(")-1)),L21) -> Negotiation/Review | M22: =IF(INDEX($A22:$J22,$M$6)="","",INDEX($A22:$J22,$M$6)&"") -> Automic - Capital Markets Forum - November 25-27 | N22: =IF($M22="","",TRIM(INDEX($A22:$J22,$N$6)&"")) -> Automic Group | O22: =IF($M22="","",TRIM(INDEX($A22:$J22,$O$6)&"")) -> Event Production | P22: =IF($M22="","",IFERROR(IF(INDEX(Settings!$B$41:$B$50,MATCH(O22,Settings!$A$41:$A$50,0))&""="","UNMAPPED",INDEX(Settings!$B$41:$B$50,MATCH(O22,Settings!$A$41:$A$50,0))&""),"UNMAPPED")) -> Production | Q22: =IF($M22="",0,N(INDEX($A22:$J22,$Q$6))) -> 28000 | R22: =IF($M22="","",INDEX($A22:$J22,$R$6)) -> 46328 | S22: =IF($M22="","",IFERROR(INDEX(Settings!$B$27:$B$36,MATCH(L22,Settings!$A$27:$A$36,0))&"","UNMAPPED")) -> Open | T22: =IF($M22="","",IF(NOT(ISNUMBER(R22)),"NO DATE",IF(S22="Won",IF(R22>Settings!$B$5,"Backlog","Delivered"),IF(S22="Open",IF(R22>Settings!$B$5,"Pipeline","Overdue"),IF(S22="Lost","Lost","UNMAPPED"))))) -> Pipeline | U22: =IF(T22="Backlog",1,IF(OR(T22="Pipeline",T22="Overdue"),N(INDEX(Settings!$C$27:$C$36,MATCH(L22,Settings!$A$27:$A$36,0))),0)) -> 0.7 | V22: =Q22*U22 -> 19600 | W22: =IF($M22="","",IF(T22="Overdue",IF(Settings!$B$8="Yes",Settings!$B$7,""),IF(ISNUMBER(R22),DATE(YEAR(R22),MONTH(R22),1),""))) -> 46327 | X22: =IF(AND(OR(T22="Backlog",T22="Pipeline",T22="Overdue"),ISNUMBER(W22)),IF(W22<=Settings!$B$6,V22,0),0) -> 19600 | Y22: =IF(AND(OR(T22="Backlog",T22="Pipeline",T22="Overdue"),ISNUMBER(W22)),IF(W22<=Settings!$B$6,Q22,0),0) -> 28000 | Z22: =IF(Y22=0,0,IF(T22="Backlog",Q22,Q22*Dashboard!$C$10)) -> 0 | AA22: =IF($N22="",0,IF(COUNTIF(Dashboard!$C$13:$C$22,$N22)>0,1,0)) -> 0 | AB22: =IF($N22="","",IF(COUNTIF($N$8:$N22,$N22)=1,MAX($AB$7:$AB21)+1,""))
B23: MEL Display Replacement | C23: Aware Super | D23: 27136 | E23: Integration | F23: 46325 | G23: 2610201 | L23: =IF(INDEX($A23:$J23,$L$6)<>"",TRIM(LEFT(INDEX($A23:$J23,$L$6),FIND("(",INDEX($A23:$J23,$L$6)&"(")-1)),L22) -> Negotiation/Review | M23: =IF(INDEX($A23:$J23,$M$6)="","",INDEX($A23:$J23,$M$6)&"") -> MEL Display Replacement | N23: =IF($M23="","",TRIM(INDEX($A23:$J23,$N$6)&"")) -> Aware Super | O23: =IF($M23="","",TRIM(INDEX($A23:$J23,$O$6)&"")) -> Integration | P23: =IF($M23="","",IFERROR(IF(INDEX(Settings!$B$41:$B$50,MATCH(O23,Settings!$A$41:$A$50,0))&""="","UNMAPPED",INDEX(Settings!$B$41:$B$50,MATCH(O23,Settings!$A$41:$A$50,0))&""),"UNMAPPED")) -> Integration | Q23: =IF($M23="",0,N(INDEX($A23:$J23,$Q$6))) -> 27136 | R23: =IF($M23="","",INDEX($A23:$J23,$R$6)) -> 46325 | S23: =IF($M23="","",IFERROR(INDEX(Settings!$B$27:$B$36,MATCH(L23,Settings!$A$27:$A$36,0))&"","UNMAPPED")) -> Open | T23: =IF($M23="","",IF(NOT(ISNUMBER(R23)),"NO DATE",IF(S23="Won",IF(R23>Settings!$B$5,"Backlog","Delivered"),IF(S23="Open",IF(R23>Settings!$B$5,"Pipeline","Overdue"),IF(S23="Lost","Lost","UNMAPPED"))))) -> Pipeline | U23: =IF(T23="Backlog",1,IF(OR(T23="Pipeline",T23="Overdue"),N(INDEX(Settings!$C$27:$C$36,MATCH(L23,Settings!$A$27:$A$36,0))),0)) -> 0.7 | V23: =Q23*U23 -> 18995.2 | W23: =IF($M23="","",IF(T23="Overdue",IF(Settings!$B$8="Yes",Settings!$B$7,""),IF(ISNUMBER(R23),DATE(YEAR(R23),MONTH(R23),1),""))) -> 46296 | X23: =IF(AND(OR(T23="Backlog",T23="Pipeline",T23="Overdue"),ISNUMBER(W23)),IF(W23<=Settings!$B$6,V23,0),0) -> 18995.2 | Y23: =IF(AND(OR(T23="Backlog",T23="Pipeline",T23="Overdue"),ISNUMBER(W23)),IF(W23<=Settings!$B$6,Q23,0),0) -> 27136 | Z23: =IF(Y23=0,0,IF(T23="Backlog",Q23,Q23*Dashboard!$C$10)) -> 0 | AA23: =IF($N23="",0,IF(COUNTIF(Dashboard!$C$13:$C$22,$N23)>0,1,0)) -> 0 | AB23: =IF($N23="","",IF(COUNTIF($N$8:$N23,$N23)=1,MAX($AB$7:$AB22)+1,"")) -> 14
B24: CBA - Private Hosting Payments Webinar - Postponed to October | C24: Commonwealth Bank Australia (CBA) | D24: 795 | E24: Event Production | F24: 46280 | G24: 26081903 | L24: =IF(INDEX($A24:$J24,$L$6)<>"",TRIM(LEFT(INDEX($A24:$J24,$L$6),FIND("(",INDEX($A24:$J24,$L$6)&"(")-1)),L23) -> Negotiation/Review | M24: =IF(INDEX($A24:$J24,$M$6)="","",INDEX($A24:$J24,$M$6)&"") -> CBA - Private Hosting Payments Webinar - Postponed to October | N24: =IF($M24="","",TRIM(INDEX($A24:$J24,$N$6)&"")) -> Commonwealth Bank Australia (CBA) | O24: =IF($M24="","",TRIM(INDEX($A24:$J24,$O$6)&"")) -> Event Production | P24: =IF($M24="","",IFERROR(IF(INDEX(Settings!$B$41:$B$50,MATCH(O24,Settings!$A$41:$A$50,0))&""="","UNMAPPED",INDEX(Settings!$B$41:$B$50,MATCH(O24,Settings!$A$41:$A$50,0))&""),"UNMAPPED")) -> Production | Q24: =IF($M24="",0,N(INDEX($A24:$J24,$Q$6))) -> 795 | R24: =IF($M24="","",INDEX($A24:$J24,$R$6)) -> 46280 | S24: =IF($M24="","",IFERROR(INDEX(Settings!$B$27:$B$36,MATCH(L24,Settings!$A$27:$A$36,0))&"","UNMAPPED")) -> Open | T24: =IF($M24="","",IF(NOT(ISNUMBER(R24)),"NO DATE",IF(S24="Won",IF(R24>Settings!$B$5,"Backlog","Delivered"),IF(S24="Open",IF(R24>Settings!$B$5,"Pipeline","Overdue"),IF(S24="Lost","Lost","UNMAPPED"))))) -> Overdue | U24: =IF(T24="Backlog",1,IF(OR(T24="Pipeline",T24="Overdue"),N(INDEX(Settings!$C$27:$C$36,MATCH(L24,Settings!$A$27:$A$36,0))),0)) -> 0.7 | V24: =Q24*U24 -> 556.5 | W24: =IF($M24="","",IF(T24="Overdue",IF(Settings!$B$8="Yes",Settings!$B$7,""),IF(ISNUMBER(R24),DATE(YEAR(R24),MONTH(R24),1),""))) | X24: =IF(AND(OR(T24="Backlog",T24="Pipeline",T24="Overdue"),ISNUMBER(W24)),IF(W24<=Settings!$B$6,V24,0),0) -> 0 | Y24: =IF(AND(OR(T24="Backlog",T24="Pipeline",T24="Overdue"),ISNUMBER(W24)),IF(W24<=Settings!$B$6,Q24,0),0) -> 0 | Z24: =IF(Y24=0,0,IF(T24="Backlog",Q24,Q24*Dashboard!$C$10)) -> 0 | AA24: =IF($N24="",0,IF(COUNTIF(Dashboard!$C$13:$C$22,$N24)>0,1,0)) -> 0 | AB24: =IF($N24="","",IF(COUNTIF($N$8:$N24,$N24)=1,MAX($AB$7:$AB23)+1,"")) -> 15
B25: Ventia | Mobile Displays x2 - 26042302 | C25: Ventia | D25: 9120 | E25: Integration | F25: 46325 | G25: 26042302 | L25: =IF(INDEX($A25:$J25,$L$6)<>"",TRIM(LEFT(INDEX($A25:$J25,$L$6),FIND("(",INDEX($A25:$J25,$L$6)&"(")-1)),L24) -> Negotiation/Review | M25: =IF(INDEX($A25:$J25,$M$6)="","",INDEX($A25:$J25,$M$6)&"") -> Ventia | Mobile Displays x2 - 26042302 | N25: =IF($M25="","",TRIM(INDEX($A25:$J25,$N$6)&"")) -> Ventia | O25: =IF($M25="","",TRIM(INDEX($A25:$J25,$O$6)&"")) -> Integration | P25: =IF($M25="","",IFERROR(IF(INDEX(Settings!$B$41:$B$50,MATCH(O25,Settings!$A$41:$A$50,0))&""="","UNMAPPED",INDEX(Settings!$B$41:$B$50,MATCH(O25,Settings!$A$41:$A$50,0))&""),"UNMAPPED")) -> Integration | Q25: =IF($M25="",0,N(INDEX($A25:$J25,$Q$6))) -> 9120 | R25: =IF($M25="","",INDEX($A25:$J25,$R$6)) -> 46325 | S25: =IF($M25="","",IFERROR(INDEX(Settings!$B$27:$B$36,MATCH(L25,Settings!$A$27:$A$36,0))&"","UNMAPPED")) -> Open | T25: =IF($M25="","",IF(NOT(ISNUMBER(R25)),"NO DATE",IF(S25="Won",IF(R25>Settings!$B$5,"Backlog","Delivered"),IF(S25="Open",IF(R25>Settings!$B$5,"Pipeline","Overdue"),IF(S25="Lost","Lost","UNMAPPED"))))) -> Pipeline | U25: =IF(T25="Backlog",1,IF(OR(T25="Pipeline",T25="Overdue"),N(INDEX(Settings!$C$27:$C$36,MATCH(L25,Settings!$A$27:$A$36,0))),0)) -> 0.7 | V25: =Q25*U25 -> 6384 | W25: =IF($M25="","",IF(T25="Overdue",IF(Settings!$B$8="Yes",Settings!$B$7,""),IF(ISNUMBER(R25),DATE(YEAR(R25),MONTH(R25),1),""))) -> 46296 | X25: =IF(AND(OR(T25="Backlog",T25="Pipeline",T25="Overdue"),ISNUMBER(W25)),IF(W25<=Settings!$B$6,V25,0),0) -> 6384 | Y25: =IF(AND(OR(T25="Backlog",T25="Pipeline",T25="Overdue"),ISNUMBER(W25)),IF(W25<=Settings!$B$6,Q25,0),0) -> 9120 | Z25: =IF(Y25=0,0,IF(T25="Backlog",Q25,Q25*Dashboard!$C$10)) -> 0 | AA25: =IF($N25="",0,IF(COUNTIF(Dashboard!$C$13:$C$22,$N25)>0,1,0)) -> 0 | AB25: =IF($N25="","",IF(COUNTIF($N$8:$N25,$N25)=1,MAX($AB$7:$AB24)+1,"")) -> 16
B26: Chorus Call - Nanosonics AGM - 4.11.26 | C26: Chorus Call | D26: 4516 | E26: Event Production | F26: 46330 | G26: 26073109 | L26: =IF(INDEX($A26:$J26,$L$6)<>"",TRIM(LEFT(INDEX($A26:$J26,$L$6),FIND("(",INDEX($A26:$J26,$L$6)&"(")-1)),L25) -> Negotiation/Review | M26: =IF(INDEX($A26:$J26,$M$6)="","",INDEX($A26:$J26,$M$6)&"") -> Chorus Call - Nanosonics AGM - 4.11.26 | N26: =IF($M26="","",TRIM(INDEX($A26:$J26,$N$6)&"")) -> Chorus Call | O26: =IF($M26="","",TRIM(INDEX($A26:$J26,$O$6)&"")) -> Event Production | P26: =IF($M26="","",IFERROR(IF(INDEX(Settings!$B$41:$B$50,MATCH(O26,Settings!$A$41:$A$50,0))&""="","UNMAPPED",INDEX(Settings!$B$41:$B$50,MATCH(O26,Settings!$A$41:$A$50,0))&""),"UNMAPPED")) -> Production | Q26: =IF($M26="",0,N(INDEX($A26:$J26,$Q$6))) -> 4516 | R26: =IF($M26="","",INDEX($A26:$J26,$R$6)) -> 46330 | S26: =IF($M26="","",IFERROR(INDEX(Settings!$B$27:$B$36,MATCH(L26,Settings!$A$27:$A$36,0))&"","UNMAPPED")) -> Open | T26: =IF($M26="","",IF(NOT(ISNUMBER(R26)),"NO DATE",IF(S26="Won",IF(R26>Settings!$B$5,"Backlog","Delivered"),IF(S26="Open",IF(R26>Settings!$B$5,"Pipeline","Overdue"),IF(S26="Lost","Lost","UNMAPPED"))))) -> Pipeline | U26: =IF(T26="Backlog",1,IF(OR(T26="Pipeline",T26="Overdue"),N(INDEX(Settings!$C$27:$C$36,MATCH(L26,Settings!$A$27:$A$36,0))),0)) -> 0.7 | V26: =Q26*U26 -> 3161.2 | W26: =IF($M26="","",IF(T26="Overdue",IF(Settings!$B$8="Yes",Settings!$B$7,""),IF(ISNUMBER(R26),DATE(YEAR(R26),MONTH(R26),1),""))) -> 46327 | X26: =IF(AND(OR(T26="Backlog",T26="Pipeline",T26="Overdue"),ISNUMBER(W26)),IF(W26<=Settings!$B$6,V26,0),0) -> 3161.2 | Y26: =IF(AND(OR(T26="Backlog",T26="Pipeline",T26="Overdue"),ISNUMBER(W26)),IF(W26<=Settings!$B$6,Q26,0),0) -> 4516 | Z26: =IF(Y26=0,0,IF(T26="Backlog",Q26,Q26*Dashboard!$C$10)) -> 0 | AA26: =IF($N26="",0,IF(COUNTIF(Dashboard!$C$13:$C$22,$N26)>0,1,0)) -> 0 | AB26: =IF($N26="","",IF(COUNTIF($N$8:$N26,$N26)=1,MAX($AB$7:$AB25)+1,""))
